{"id": "BTB__BTB_32", "text": "Title: Computer Science for Engineers\nModule Number: BTB 32\nCredits: 5.0 CP\nSemester: None\nOffered In: winter_semester\nLanguage: de\nExam Type: written_exam\nInstructor: None Helmut Hiller (helmut.hiller@hs-duesseldorf.de)\n--- Goals (EN) ---\nAfter successfully completing the module, students will be able to:\n- explain the basic structure of a computer and the principles of data processing\n- classify different programming paradigms and languages and apply the fundamentals of programming in C\n- design, write, and test simple programs in C independently\n- understand basic algorithms and data structures\n- formulate simple database queries and understand fundamental database concepts\n- understand and explain the typical phases and processes of software development\n- use common software development tools such as compilers and IDEs\n- explain fundamental aspects of IT security and data protection and their relevance to computer science\n--- Goals (DE) ---\nNach erfolgreichem Abschluss des Moduls können die Studierenden:\n- den grundlegenden Aufbau eines Computers sowie Prinzipien der Datenverarbeitung erklären\n- verschiedene Programmierparadigmen und -sprachen einordnen und die Grundzüge der Programmierung in C praktisch anwenden\n- einfache Programme in C eigenständig entwerfen, schreiben und testen \n- einfache Algorithmen und Datenstrukturen verstehen\n- einfache Datenbankabfragen formulieren und grundlegende Datenbankkonzepte kennen\n- die typischen Phasen und Prozesse der Softwareentwicklung verstehen und erklären\n- gängige Softwareentwicklungswerkzeuge wie Compiler und IDEs verwenden\n- grundlegende Aspekte der IT-Sicherheit und des Datenschutzes und deren Relevanz für die Informatik erklären\n--- Contents (EN) ---\nThis module provides fundamental knowledge in computer science and software development. It covers the structure and functionality of computers, offers an overview of programming languages, and introduces core programming concepts using the C language. Key topics include data types, control structures, functions, and basic algorithms and data structures. In addition, students are introduced to typical software development cycles and to tools such as operating systems, development environments, and compilers. Further topics include essential software engineering processes, an introduction to working with databases, and an overview of IT security and data protection.\n--- Contents (DE) ---\nDas Modul vermittelt grundlegende Kenntnisse der Informatik und Softwareentwicklung. Behandelt werden der Aufbau und die Funktionsweise von Computern, ein Überblick zu Programmiersprachen sowie zentrale Konzepte der Programmierung am Beispiel der Sprache C. Wichtige Themen sind dabei Datentypen, Kontrollstrukturen, Funktionen und einfache Algorithmen und Datenstrukturen. Ergänzend erfolgt eine Einführung in typische Entwicklungszyklen sowie in Werkzeuge wie Betriebssystem, Entwicklungsumgebung und Compiler. Weitere Themen sind grundlegende Prozesse im Softwareengineering, der Einstieg in die Arbeit mit Datenbanken sowie ein Überblick zu den Themen IT-Sicherheit und Datenschutz.\n--- Literature (EN) ---\n- Ernst, Hartmut, Jochen Schmidt, und Gerd Hinrich Beneken. 2023. Grundkurs Informatik: Grundlagen und Konzepte für die erfolgreiche IT-Praxis - eine umfassende Einführung. 8. Auflage. Wiesbaden: Springer Vieweg.\n- Goll, Joachim, und Tobias Stamm. 2024. C als erste Programmiersprache: Nach den Standards C11 und C23. Wiesbaden: Springer Fachmedien.\n- Knolle, Harm, Andreas Behrend, Birgit Bertelsmeier, Heide Faeskorn-Woyke, Thomas Rakow, Inga Saatz, und Johann Schaible. 2024. Datenbanksysteme: Eine praktische Einführung. 1. Auflage. München: Hanser, Carl.\n- Eckert, Claudia. 2023. IT-Sicherheit: Konzepte, Verfahren, Protokolle. 11. Auflage. De Gruyter Studium. München Boston: De Gruyter Oldenbourg.\n--- Literature (DE) ---\n- Ernst, Hartmut, Jochen Schmidt, und Gerd Hinrich Beneken. 2023. Grundkurs Informatik: Grundlagen und Konzepte für die erfolgreiche IT-Praxis - eine umfassende Einführung. 8. Auflage. Wiesbaden: Springer Vieweg.\n- Goll, Joachim, und Tobias Stamm. 2024. C als erste Programmiersprache: Nach den Standards C11 und C23. Wiesbaden: Springer Fachmedien.\n- Knolle, Harm, Andreas Behrend, Birgit Bertelsmeier, Heide Faeskorn-Woyke, Thomas Rakow, Inga Saatz, und Johann Schaible. 2024. Datenbanksysteme: Eine praktische Einführung. 1. Auflage. München: Hanser, Carl.\n- Eckert, Claudia. 2023. IT-Sicherheit: Konzepte, Verfahren, Protokolle. 11. Auflage. De Gruyter Studium. München Boston: De Gruyter Oldenbourg.", "metadata": {"moduleNumber": "BTB 32", "moduleName": "Computer Science for Engineers", "creditPoints": "5.0", "suggestedSemester": null, "offeredInSeason": "winter_semester", "examType": "written_exam", "heldInLanguage": "de", "reviserName": "None Helmut Hiller", "reviserEmail": "helmut.hiller@hs-duesseldorf.de", "studyProgramId": 10, "source_type": "json"}}
{"id": "BTB__BTB_30", "text": "Title: Network Engineering\nModule Number: BTB 30\nCredits: 5.0 CP\nSemester: None\nOffered In: winter_semester\nLanguage: de\nExam Type: written_exam\nInstructor: Prof. Dr.-Ing. Stefanie Dederichs (stefanie.dederichs@hs-duesseldorf.de)\n--- Goals (EN) ---\nStudents will be familiar with the most important protocols and components in computer networks and building, lighting and event technology networks. They know what tasks they perform and how they relate to each other. Students will be able to plan, set up and configure a local network with all the necessary components. They will be able to systematically analyse and solve connection and performance problems.\n--- Goals (DE) ---\nDie Studierenden kennen die wichtigsten Protokolle und Komponenten in Rechnernetzwerken und Netzwerken der Haus- , Beleuchtungs- und Veranstaltungstechnik. Sie wissen, welche Aufgaben diese übernehmen und in welchem Zusammenhang sie zueinanderstehen. Die Studierenden sind in der Lage, ein lokales Netz mit allen notwendigen Komponenten zu planen, aufzubauen und zu konfigurieren. Sie können Verbindungs- und Performanceprobleme systematisch analysieren und lösen.\n--- Contents (EN) ---\n- Basic concepts of computer networks\n- Basic concepts of networks in building, lighting and event technology\n- Transmission methods and media\n- Concepts and technologies for local networks\n- Network protocols\n--- Contents (DE) ---\n- Grundbegriffe zu Rechnernetzen\n- Grundbegriffe der Netzwerke der Haus-, Beleuchtungs- und Veranstaltungstechnik\n- Übertragungsverfahren und medien\n- Konzepte und Technologien für lokale Netze\n- Netzwerkprotokolle\n--- Literature (EN) ---\n- F. Kauffels: Lokale Netze Band 1 und 2, mitp- Verlag, 2003\n- Cisco CCNA Kursunterlagen (lokale Akademie HSD)\n- D. Comor: Computernetzwerke und Internets, Prentice Hall, 1998\n\nFurther various scripts of the RRZN Hannover on the mentioned topics are offered by the CampusIT of the HSD.\n--- Literature (DE) ---\n- F. Kauffels: Lokale Netze Band 1 und 2, mitp- Verlag, 2003\n- Cisco CCNA Kursunterlagen (lokale Akademie HSD)\n- D. Comor: Computernetzwerke und Internets, Prentice Hall, 1998\n\nWeitere diverse Skripte des RRZN Hannover zu den angeführten Themenbereichen werden im Vertrieb durch die CampusIT der HSD angeboten.", "metadata": {"moduleNumber": "BTB 30", "moduleName": "Network Engineering", "creditPoints": "5.0", "suggestedSemester": null, "offeredInSeason": "winter_semester", "examType": "written_exam", "heldInLanguage": "de", "reviserName": "Prof. Dr.-Ing. Stefanie Dederichs", "reviserEmail": "stefanie.dederichs@hs-duesseldorf.de", "studyProgramId": 10, "source_type": "json"}}
{"id": "BTB__BTB_31", "text": "Title: Technical Acoustics\nModule Number: BTB 31\nCredits: 5.0 CP\nSemester: 3\nOffered In: winter_semester\nLanguage: de\nExam Type: written_exam\nInstructor: Prof. Dr.-Ing. Jochen Steffens (jochen.steffens@hs-duesseldorf.de)\n--- Goals (EN) ---\nThe students are able to apply fundamentials of physics and engineering to calculate sound propagation.  They have basic knowledge on the determination of sound field quantities, acoustic properties of different materials an they can judge different spacial sound source configurations acoordung to their functions\n--- Goals (DE) ---\nDie Studierenden können die wesentlichen physikalischen, technischen Grundlagen zur akustischer Schallausbreitung anwenden. Sie beherrschen grundlegende Methoden zur Bestimmung von Schallfeldgrößen, akustische Materialgrößen und können räumliche Anordnung von Schallquellen in der Funktionsweise beurteilen.\n--- Contents (EN) ---\n- Definition and meaning of acoustics\n- Sound and vibrations (sound field quantities)\n- Perception of sound (Weber-Fechner law, loudness perception and decibels, hearing range)\n- Basic concepts of wave propagation (general gas equation, adiabatic equation of state, basic equations of acoustics, wave equation)\n- Propagating and standing waves (solutions of the wave equation, propagating waves, standing waves and resonance phenomena, total fields, three-dimensional wave equation)\n- Energy and power transport and intensity measurement methods\n- Wave propagation in a moving medium (Doppler effect)\n- Sound radiation (omnidirectional radiation from point and line sources, volume sources, sound field of two sources, dipole)\n- Loudspeaker arrays (one-dimensional piston cone, shaping of main and side lobes, electronic panning)\n- Sound absorption I / measurements in Kundt's tube (2dim. Sound propagation in the tube, Mini-Max method, wave separation, sound absorption quantities, in-situ measurement method)\n- Sound absorption II (wall impedance, porous absorbers, matching law, acoustic equations in a porous medium, special absorbing arrangements)\n- Room acoustics (sound propagation in a room, mirror sound sources, wave theory, diffuse sound field, Sabine's reverberation formula)\n- Electroacoustic transducers for airborne sound (general operating principles, condenser microphones, directional dependencies of microphones, electrodynamic microphones and loudspeakers)\n--- Contents (DE) ---\n- Definition und Bedeutung von Akustik\n- Schall und Schwingungen (Schallfeldgrößen)\n- Wahrnehmung von Schall (Weber-Fechner-Gesetz, Lautstärkeempfindung und Dezibel, Hörbereich)\n- Grundbegriffe der Wellenausbreitung (Allgemeine Gasgleichung, adiabatische Zustandsgleichung, Grundgleichungen der Akustik, Wellengleichung)\n- Fortschreitende und stehende Wellen (Lösungen der Wellengleichung, fortschreitende Wellen, stehende Wellen und Resonanzphänomen, Gesamtfelder, dreidimensionale Wellengleichung)\n- Energie- und Leistungstransport und Intensitätsmessverfahren\n- Wellenausbreitung im bewegten Medium (Dopplereffekt)\n- Schallabstrahlung (Ungerichtete Abstrahlung von Punkt- und Linienquellen, Volumenquellen, Schallfeld zweier Quellen, Dipol)\n- Lautsprecherzeilen (eindimensionale Kolbenmembran, Formung von Haupt- und Nebenkeulen, elektronisches Schwenken\n- Schallabsorption I / Messungen im Kundtschen Rohr (2dim. Schallausbreitung im Rohr, Mini-Max-Verfahren, Wellentrennung, Größen der Schallabsorption, In-Situ-Messverfahren)\n- Schallabsorption II (Wandimpedanz, poröse Absorber, Anpassungsgesetz, akustische Gleichungen im porösen Medium, spezielle absorbierende Anordnungen)\n- Raumakustik (Schallausbreitung im Raum, Spiegelschallquellen, wellentheoretische Betrachtung, diffuses Schallfeld, Sabinesche Nachhallformel)\n- Elektroakustische Wandler für Luftschall (Allgemeine Funktionsprinzipien, Kondensatormikrofone, Richtungsabhängigkeiten von Mikrofonen, Elektrodynamische Mikrofone und Lautsprecher)\n--- Literature (EN) ---\nMöser, M.: Technische Akustik 10.Aufl. Springer, 2015\nKuttruff, H.: Akustik - Eine Einführung, Hirzel, 2004\nCremer, L. & Müller, H. A.: Die wissenschaftlichen Grundlagen der Raumakustik, Bd. 1, Hirzel, 1978\nLerch, R.: Technische Akustik: Grundlagen und Anwendungen, Springer, 2009\n--- Literature (DE) ---\nMöser, M.: Technische Akustik 10.Aufl. Springer, 2015\nKuttruff, H.: Akustik - Eine Einführung, Hirzel, 2004\nCremer, L. & Müller, H. A.: Die wissenschaftlichen Grundlagen der Raumakustik, Bd. 1, Hirzel, 1978\nLerch, R.: Technische Akustik: Grundlagen und Anwendungen, Springer, 2009", "metadata": {"moduleNumber": "BTB 31", "moduleName": "Technical Acoustics", "creditPoints": "5.0", "suggestedSemester": 3, "offeredInSeason": "winter_semester", "examType": "written_exam", "heldInLanguage": "de", "reviserName": "Prof. Dr.-Ing. Jochen Steffens", "reviserEmail": "jochen.steffens@hs-duesseldorf.de", "studyProgramId": 10, "source_type": "json"}}
{"id": "BTB__BTB_41", "text": "Title: Advanced Acoustics (Psychoacoustics)\nModule Number: BTB 41\nCredits: 5.0 CP\nSemester: 4\nOffered In: winter_semester\nLanguage: de\nExam Type: oral_exam\nInstructor: Prof. Dr.-Ing. Jochen Steffens (jochen.steffens@hs-duesseldorf.de)\n--- Goals (EN) ---\nThe students are able to transfer the contents conveyed in the module Technical Acoustics (Acoustics 1) to the concrete application areas of psychoacoustics and to answer some of the central questions of psychoacoustics (including how our hearing works and what it processes, where its limits lie, how it can be fooled and what that means for the perception of music, language and our acoustic environment). In addition, they are able to correctly classify and explain perceptual phenomena by means of central concepts of psychoacoustics.\n--- Goals (DE) ---\nDie Studierenden sind in der Lage, die im Modul Technische Akustik (Akustik 1) vermittelten Inhalte auf die konkreten Anwendungsgebiete der Psychoakustik zu übertragen und einige zentrale Fragen der Psychoakustik zu beantworten (u. a wie unser Gehör arbeitet und was es verarbeitet, wo seine Grenzen liegen, wie es sich täuschen lässt und was dies für die Wahrnehmung von Musik, Sprache und unserer akustischen Umwelt bedeutet). Sie sind darüber hinaus in der Lage, Wahrnehmungsphänomene mittels zentraler Konzepte der Psychoakustik richtig einzuordnen und zu erklären.\n--- Contents (EN) ---\n- Anatomy of the auditory system (outer, middle and inner ear, afferent and efferent auditory pathway, auditory cortex)\n- Functions of the auditory system (tonotopy, signal transmission of neurons, tuning curves, coding of frequency and intensity, otoacoustic emissions)\n- Sound analysis of the auditory system I (pitch perception and periodicity recognition, frequency groups, masking)\n- Sound analysis of the auditory system II (temporal resolution, Weber-Fechner law, loudness perception, psychoacoustic metrics)\n- Pathology of the auditory system (sound conduction and perception disorders and their diagnosis)\n- Spatial hearing (HRTF, spatial hearing with one and more sound sources) Hearing with one and several sound sources, distance perception, binaural signal processing)\n- Auditory attention (bottom-up and top-down processes, theories of selective attention, Gestalt perception, auditory scene analysis)\n- Methods of psychoacoustics I (classical psychophysical methods, adaptive forced choice (AFC) methods, methods for evaluating audio quality)\n- Methods of psychoacoustics II - listening tests (variables, hypotheses, measurement theory, empirical methods and their quality criteria, questionnaire construction)\n- Statistical evaluation methods (descriptive and inferential statistics, correlation, regression, variance analysis, general and mixed linear models)\n- Noise - causes and effects (noise effects, noise measurement, noise protection)\n- Ecological psychoacoustics & soundscapes (perception of acoustic events in everyday life, soundscape approach, effects of sounds and noise)\n--- Contents (DE) ---\n- Aufbau des Gehörs (Außen, Mittel- und Innenohr, afferente und efferente Hörbahn, auditorischer Kortex)\n- Funktionen des Gehörs (Tonotopie, Signalübertragung von Neuronen, Tuning Curves, Kodierung von Frequenz und Intensität, otoakustische Emissionen\n- Schallanalyse des Gehörs I (Tonhöhenempfindung und Periodizitätserkennung, Frequenzgruppen, Maskierung)\n- Schallanalyse des Gehörs II (Zeitliches Auflösungsvermögen, Weber-Fechner-Gesetz, Lautheitswahrnehmung, psychoakustische Größen)\n- Pathologie des Gehörs (Schallleitungs- und empfindungsstörungen und deren Diagnostik)\n- Räumliches Hören (HRTF, räuml. Hören bei einer und mehreren Schallquellen, Entfernungshören, binaurale Signalverarbeitung)\n- Auditive Aufmerksamkeit (Bottom-up und Top-down-Prozesse, Theorien der selekt. Aufmerksamkeit, Gestaltwahrnehmung, auditive Szenenanalyse)\n- Methoden der Psychoakustik I (klass. psychophysische Methoden, Adaptive Forced-Choice (AFC)-Methoden, Verfahren zur Bewertung von Audioqualität)\n- Methoden der Psychoakustik II - Hörversuche (Variablen, Hypothesen, Messtheorie, empirische Methoden und deren Gütekriterien, Fragebogenkonstruktion)\n- Statistische Auswertungsmethoden (Deskriptive und Inferenzstatistik, Korrelation, Regression, Varianzanalyse, allgemeine und gemischte lineare Modelle)\n- Lärm - Ursachen und Wirkungen (Lärmwirkungen, Lärmmessung, Lärmschutz)\n- Ökologische Psychoakustik & Soundscapes (Wahrnehmung akustischer Ereignisse im Alltag, Soundscape-Ansatz, Effekte von Geräuschen und Musik)\n- Praktische Psychoakustik (Audio Branding und Produkt-Sound-Design)\n--- Literature (EN) ---\nH. Fastl, E. Zwicker: Psychoacoustics: Facts and models, Springer Science & Business Media., 2007. \nA. Gelfand: Hearing: An introduction to psychological and physiological acoustics, CRC Press, 2009.\nJ. Hellbrück, W. Ellermeier: Horen: Physiologie, Psychologie und Pathologie, Hogrefe Verlag, 2004.\n--- Literature (DE) ---\nH. Fastl, E. Zwicker: Psychoacoustics: Facts and models, Springer Science & Business Media., 2007. \nA. Gelfand: Hearing: An introduction to psychological and physiological acoustics, CRC Press, 2009.\nJ. Hellbrück, W. Ellermeier: Horen: Physiologie, Psychologie und Pathologie, Hogrefe Verlag, 2004.", "metadata": {"moduleNumber": "BTB 41", "moduleName": "Advanced Acoustics (Psychoacoustics)", "creditPoints": "5.0", "suggestedSemester": 4, "offeredInSeason": "winter_semester", "examType": "oral_exam", "heldInLanguage": "de", "reviserName": "Prof. Dr.-Ing. Jochen Steffens", "reviserEmail": "jochen.steffens@hs-duesseldorf.de", "studyProgramId": 10, "source_type": "json"}}
{"id": "BTB__BTB_W16", "text": "Title: Room and Building Acoustics\nModule Number: BTB W16\nCredits: 5.0 CP\nSemester: None\nOffered In: to_be_announced\nLanguage: de\nExam Type: written_exam\nInstructor: None Jörg Becker-Schweitzer (jbs@hs-duesseldorf.de)\n--- Goals (EN) ---\nAfter completing this event, the students have applied and market-related basic knowledge in the field of room and building acoustics. They are able to judge given space situations technically and to be able to estimate technical innovations in the field of room and building acoustics\n--- Goals (DE) ---\nDie Studierenden verfügen nach Abschluss dieser Veranstaltung über anwendungs- und marktbezogene Grundkenntnisse im Bereich der Raum- und Bauakustik. Sie sind im Stande, gegebene Raumsituationen fachtechnisch zu beurteilen und technische Innovationen im Bereich der Raum- und Bauakustik einschätzen zu können\n--- Contents (EN) ---\nThe lecture deals with basic methods and procedures of room acoustics analysis and project planning. The focus is on teaching basic principles of room acoustics models: Geometric room acoustics, Statistical room acoustics, Wave theoretical room acoustics. Application-oriented methods, methods and estimations used in room acoustics consulting are presented. At the impedance model of interfaces basic equations of building acoustics are derived.\n\nSound propagation in rooms, reflection, transmission, absorption, direct field, diffuse sound field, Hall radius, sound level in space, absorbers and their application (porous absorbers, plate vibrators, Helmholtz resonators, alternative absorbers), noise reduction, reflection, sound insulation, definition of reverberation time according to planned use, design criteria for rooms, examples of different rooms, DIN standards, fundamentals of studio acoustics\n--- Contents (DE) ---\nDie Vorlesung behandelt grundlegende Methoden und Verfahren der raumakustischen Analyse und Projektierung. Der Schwerpunkt liegt auf der Vermittlung von grundlegenden Prinzipien der Raumakustik Modelle: Geometrische Raumakustik, Statistische Raumakustik, Wellentheoretische Raumakustik. Es werden anwendungsorientierte Verfahren, Methoden und Abschätzungen, die in der raumakustischen Beratung zum Einsatz kommen, vorgestellt. Am Impedanzmodell von Grenzflächen werden grundlegende Gleichungen der Bauakustik abgeleitet.\n\nSchallausbreitung in Räumen, Reflexion, Transmission, Absorption, Direktfeld, Diffuses Schallfeld, Hallradius, Schallpegel im Raum, Absorber und ihre Anwendung (Poröse Absorber, Plattenschwinger, Helmholtz-Resonatoren, Alternative Absorber), Schallenkung, Reflexion, Schalldämmung, Festlegung der Nachhallzeit je nach geplanter Nutzung, Auslegungskriterien für Räume, Beispiele für verschiedene Räume, DIN Normen, Grundlagen der Studioakustik\n--- Literature (EN) ---\n--- Literature (DE) ---\n- H. Kuttruff: Room Acoustics, Applied Science Publishers London. 4th Edition 2000\n- J. Cowan: Architectural Acoustics Design Guide, MCGraw-Hill 2000\n- L.K. Irvine, R.L. Richards: Acoustics and Noise Control Handbook for Architects an Builders, Krieger Publishing 1998\n- H. Bobran, I. Bobran: Handbuch der Bauphysik, Vieweg Braunschweig 1995\n- C. Romer: Schall und Raum - Eine kleine Einführung in die Raumakustik, vde verlag Berlin 1994\n- L. Cremer, H.A. Müller: Die wissenschaftlichen Grundlagen der Raumakustik, Bd. 1 u. 2 Hirzel Verlag Stuttgart 1978", "metadata": {"moduleNumber": "BTB W16", "moduleName": "Room and Building Acoustics", "creditPoints": "5.0", "suggestedSemester": null, "offeredInSeason": "to_be_announced", "examType": "written_exam", "heldInLanguage": "de", "reviserName": "None Jörg Becker-Schweitzer", "reviserEmail": "jbs@hs-duesseldorf.de", "studyProgramId": 10, "source_type": "json"}}
{"id": "BTB__BTB_W29", "text": "Title: Virtual Studio\nModule Number: BTB W29\nCredits: 5.0 CP\nSemester: None\nOffered In: to_be_announced\nLanguage: de\nExam Type: oral_exam\nInstructor: Prof. Dr. Eng. Univ. of Tsukuba Jens Herder (jens.herder@hs-duesseldorf.de)\n--- Goals (EN) ---\nSuccessful participants will have a profound knowledge in building and developing virtual set environments for broadcasting applications and will be able to evaluate virtual studio (TV) technology. Composition of video and computer graphics under live conditions for media productions is an essential part.\n--- Goals (DE) ---\nStudierende können Video und Computergrafik unter Live-Bedingungen in Produktionen verbinden. Hierzu gehört die Erstellung fiktiver Umgebungen, in die Menschen und Gegenstände versetzt werden. Sie können Virtuelle Studios entwickeln, aufbauen und einsetzen.\n--- Contents (EN) ---\nTopics include virtual set design for artificial or real scenes, hard- and software for digital (TV) studio productions, light and light setting for TV studios, camera and actor tracking systems, motion capture, real-time computer graphics and effects, separation of image elements (e.g., chroma keying), inserting of animations and virtual characters, as well as studio production planning.\n--- Contents (DE) ---\nZu den Themen gehört die Wirkung künstlich erstellter Realitätsebenen, irrealer Szenenbilder und virtueller Kulissen. Bestandteile sind Hard- und Software für digitale Studioproduktionstechnik, Licht und Beleuchtung im Virtuellen Studio, Kameraverfolgungssysteme (Tracking), Bewegungsaufzeichnung, Echtzeitgenerierung dreidimensionaler Computergrafik, Herauslösen von Bildelementen (Chromakeying), Einbindung von Animationen und virtuellen Charakteren und Produktionsplanung.\n--- Literature (EN) ---\n- S. Gibbs. 1998. Virtual Studios. IEEE MultiMedia 5, 1 (January 1998, 17-17. DOI=10.1109/MMUL.1998.664739\n- A. R. Smith and J. F. Blinn. 1996. Blue screen matting. In Proceedings of the 23rd annual conference on Computer graphics and interactive techniques (SIGGRAPH '96). ACM, New York, NY, USA, 259-268. DOI=10.1145/237170.237263\n- R. Brinkmann: The Art and Science of Digital Compositing, Morgan Kaufman Verlag 2008\n- M. Moshkovitz: The Virtual Studio Technology & Techniques, Focal Press 2000\n- P. Tucker: Secrets of Screen Acting, Routlege Chapman & Hall 2003\n- D. Arijon: Grammar of the Film Language, Silman-James Press 1991\n- U. Schmidt: Professionelle Videotechnik: Analoge und Digitale Grundlagen, Filmtechnik, Fernsehtechnik, HDTV, Kameras, Displays, Videorecorder, Produktion und Studiotechnik, Springer Verlag 2009\n\nFurther current literature will be announced at the beginning of the course.\n--- Literature (DE) ---\n- S. Gibbs. 1998. Virtual Studios. IEEE MultiMedia 5, 1 (January 1998, 17-17. DOI=10.1109/MMUL.1998.664739\n- A. R. Smith and J. F. Blinn. 1996. Blue screen matting. In Proceedings of the 23rd annual conference on Computer graphics and interactive techniques (SIGGRAPH '96). ACM, New York, NY, USA, 259-268. DOI=10.1145/237170.237263\n-R. Brinkmann: The Art and Science of Digital Compositing, Morgan Kaufman Verlag 2008\n- M. Moshkovitz: The Virtual Studio Technology & Techniques, Focal Press 2000\n- P. Tucker: Secrets of Screen Acting, Routlege Chapman & Hall 2003\n- D. Arijon: Grammar of the Film Language, Silman-James Press 1991\n- U. Schmidt: Professionelle Videotechnik: Analoge und Digitale Grundlagen, Filmtechnik, Fernsehtechnik, HDTV, Kameras, Displays, Videorecorder, Produktion und Studiotechnik, Springer Verlag 2009\n\nWeitere aktuelle Literatur wird zu Beginn der LV bekannt gegeben.", "metadata": {"moduleNumber": "BTB W29", "moduleName": "Virtual Studio", "creditPoints": "5.0", "suggestedSemester": null, "offeredInSeason": "to_be_announced", "examType": "oral_exam", "heldInLanguage": "de", "reviserName": "Prof. Dr. Eng. Univ. of Tsukuba Jens Herder", "reviserEmail": "jens.herder@hs-duesseldorf.de", "studyProgramId": 10, "source_type": "json"}}
{"id": "BTB__BTB_W19", "text": "Title: Advanced Room and Building Acoustics\nModule Number: BTB W19\nCredits: 5.0 CP\nSemester: None\nOffered In: to_be_announced\nLanguage: de\nExam Type: oral_exam\nInstructor: None Jörg Becker-Schweitzer (jbs@hs-duesseldorf.de)\n--- Goals (EN) ---\nAfter completing this course, students have applied and market-related knowledge in the field of room and building acoustics, the contents and requirements of relevant standards and guidelines are familiar to them. They are able to carry out building acoustical measurements and to be able to evaluate rooms on the basis of characteristic values.\n--- Goals (DE) ---\nDie Studierenden verfügen nach Abschluss dieser Veranstaltung über anwendungs- und marktbezogene Kenntnisse im Bereich der Raum- und Bauakustik, die Inhalte und Anforderungen einschlägiger Normen und Richtlinien sind ihnen geläufig. Sie sind im Stande bau und raumakustische Messungen durchzuführen und Räume anhand von Kennwerten beurteilen zu können.\n--- Contents (EN) ---\nIn the event further contents and procedures of the measuring technique of the room acoustics and building acoustics as well as the noise measurement technology are presented. The focus is on communicating the content of relevant standards and guidelines. Different requirement profiles for music rooms, speech lecture, office use are explained. By way of example, measurements and calculations are carried out to determine the room and building acoustic characteristics. Detailed solutions for achieving the high acoustic requirements in studio areas are described.Keywords: metrology:FFT / RTA, LA, eq, airborne, impact and structure-borne sound insulation, derivation of single number characteristic, noise limits for sound reinforcement, room acoustics parameters in the concert hall and auditorium, acoustic requirements in studio zones, acoustics in office areas Components: absorber, reflector and diffuser\n--- Contents (DE) ---\nIn der Veranstaltung werden weiterführende Inhalte und Verfahren der Messtechnik der Raum- bzw. Bauakustik sowie der Lärmmesstechnik vorgestellt. Der Schwerpunkt liegt auf der Vermittlung der Inhalte einschlägiger Normen und Richtlinien. Unterschiedliche Anforderungsprofile für Musikräume, Sprachvortrag, Büronutzung werden erläutert. Beispielhaft werden Messungen und Berechnungen zur Ermittlung der Raum- und Bauakustik-Kennwerte durchgeführt. Detaillösungen zur Erreichung der hohen Akustikanforderungen in Studiobereichen werden beschrieben. Schlagworte: Messtechnik:FFT / RTA, LA,eq , Luftschall-, Trittschall- undKorperschalldammung, Ableitung von Einzahl-Kennwerten,Lärmgrenzwerte bei Beschallung, Raumakustik-Parameter imKonzertsaal und Hörsaal, Akustikanforderungen in Studiozonen,Akustik in Bürobereichen Bauelemente: Absorber, Reflektor undDiffusor\n--- Literature (EN) ---\n--- Literature (DE) ---\n- H. Kuttruff: Room Acoustics, Applied Science Publishers 2000\n- R. F. Barron: Industrial Noise Control and Acoustics, CRC Press 2002\n- P. Newell: Recording Studio Design, Focal Press 3 rd Ed. 2011\n- Th. Rossing: Handbook of Acoustics, Springer Verlag 2007\n- J. Meyer: Acoustics and Performance of Music, Springer Verlag 2009\n- L. Cremer, H.A. Müller: Die wissenschaftlichen Grundlagen der Raumakustik, Bd. 1 u. 2 Hirzel Verlag Stuttgart 1978\n- T. E. Vigran: Building Acoustics, Taylor & Francis 2007\n- H. Fuchs: Schallabsorber und Schalldampfer_3-2010\n- F. A. Everest, K. C. Pohlmann: Master Handbook of Acoustics, 6th Ed McGraw-Hill 2014\n- T. Cox, P. D'Antonio: Acoustic Absorbers and Diffusers, CRC Press 2nd Ed. 2009\n- M. Long: Architectural Acoustics, Academic Press 2006\n- BBC-Engineering: Guide to Acoustic Practice 2nd Ed. 1990\n- Div. Normen und Richtlinien der Fachliteratur", "metadata": {"moduleNumber": "BTB W19", "moduleName": "Advanced Room and Building Acoustics", "creditPoints": "5.0", "suggestedSemester": null, "offeredInSeason": "to_be_announced", "examType": "oral_exam", "heldInLanguage": "de", "reviserName": "None Jörg Becker-Schweitzer", "reviserEmail": "jbs@hs-duesseldorf.de", "studyProgramId": 10, "source_type": "json"}}
{"id": "BTB__BTB_W25", "text": "Title: Selected Topics in Image Engineering\nModule Number: BTB W25\nCredits: 5.0 CP\nSemester: 7\nOffered In: to_be_announced\nLanguage: de\nExam Type: portfolio\nInstructor: Prof. Dr.-Ing. Thomas Bonse (thomas.bonse@hs-duesseldorf.de)\n--- Goals (EN) ---\nStudents can apply advanced technologies, algorithms and applications of image technology. Students can derive important content from professional topic research, prepare it didactically and present it in a differentiated manner in the seminar. They evaluate the central results of the seminar-based treatment of an image engineeering topic in a short scientific documentation.\n--- Goals (DE) ---\nDie Studierenden können fortgeschrittene Technologien, Algorithmen und Anwendungen der Bildtechnik anwenden. Die Studierenden können in einer professionellen Themenrecherche wichtige Inhalte ableiten, didaktisch aufbereiten und differenziert im Seminar präsentieren. Sie evaluieren die zentralen Ergebnisse der seminaristischen Behandlung eines bildtechnischen Themas in einer kurzen wissenschaftlichen Dokumentation.\n--- Contents (EN) ---\nThis module covers selected topics in image and video engineering. These may vary from semester to semester. Examples:\n- Algorithms and applications of digital image processing, e.g. image manipulation, filters, feature extraction (object recognition, image processing in the automotive sector, medical image processing), image processing with machine learning and KI\n- Special image recording and playback processes (multi-camera recordings for virtual camera movements and 360-degree productions)\n- Technologies and applications for VR HMDs\n- Specialised areas in video post-production Video distribution (media, broadcast, IP infrastructures, etc.)\n- Camera movement and image stabilisation (action cam and drone), camera-side stabilisation and image stabilisation in post-production\n- Studio networking, studio automation and remote production\n- Video communication/video distribution (broadcast and streaming)\n- Image presentation in the cinema, culture and event sector\n--- Contents (DE) ---\nIn diesem Modul werden ausgewählte Themengebiete der Bild- und Videotechnik behandelt. Diese können von Semester zu Semester variieren. Beispiele:\n- Algorithmen und Anwendungen der digitalen Bildverarbeitung, z.B. Bildmanipulation, Filter, Feature Extraktion (Object Recognition, BV im Automobilbereich, medizinische BV), BV mit Maschine Learning und KI\n- Besondere Bildaufnahme- und Wiedergabeverfahren (Multikameraaufnahmen für virtuelle Kamerabewegungen und 360-Grad Produktionen)\n- Technologien und Anwendungen für VR-HMDs\n- Spezialgebiete in der Video-Postproduktion Videodistribution (Medien, Broadcast, IP-Infrastrukturen etc.)\n- Kamerabewegung und Bildstabilisierung (Actioncam und Drohne), kameraseitige Stabilisierung und Bildstabilisierung in der Postproduktion\n- Studiovernetzung, Studioautomatisation und Remote Produktion\n- VideokommunikationVideodistribution (Broadcast und Streaming)\n- Bilddarstellung im Kino-, Kultur- und Eventbereich\n--- Literature (EN) ---\nCurrent sources will be announced at the beginning of the course according to the seminar topics.\n--- Literature (DE) ---\nAktuelle Quellen werden den Seminarthemen entsprechend zu Beginn der LV bekannt gegeben.", "metadata": {"moduleNumber": "BTB W25", "moduleName": "Selected Topics in Image Engineering", "creditPoints": "5.0", "suggestedSemester": 7, "offeredInSeason": "to_be_announced", "examType": "portfolio", "heldInLanguage": "de", "reviserName": "Prof. Dr.-Ing. Thomas Bonse", "reviserEmail": "thomas.bonse@hs-duesseldorf.de", "studyProgramId": 10, "source_type": "json"}}
{"id": "BTB__BTB_W38", "text": "Title: External Semester\nModule Number: BTB W38\nCredits: 30.0 CP\nSemester: 7\nOffered In: to_be_announced\nLanguage: de\nExam Type: oral_exam\nInstructor: Prof. Dr.-Ing. Jochen Steffens (jochen.steffens@hs-duesseldorf.de)\n--- Goals (EN) ---\nsee individual modules BTB W42_1 / BTB W42_2 / BTB W42_3\n--- Goals (DE) ---\nsiehe Einzelmodule BTB W42_1 / BTB W42_2 / BTB W42_3\n--- Contents (EN) ---\nCompulsory elective module. It can be chosen between Module BTB W42_1 (practical semester), BTB W42_2 (semester abroad) or module BTB W42_3 (research semester)\n--- Contents (DE) ---\nWahlpflichtmodul. Es kann Modul BTB W42_1 (Praxissemester), BTB W42_2 (Auslandsstudiensemester) oder Modul BTB W42_3 (Forschungssemester) belegt werden.\n--- Literature (EN) ---\nLiterature depends on the topic/institution and is agreed with the supervising professor at the beginning of the external semester.\n--- Literature (DE) ---\nLiteratur ist themen-/institutionsabhängig und wird zu Beginn des Externen Semesters mit der betreuenden Professorin bzw. dem betreuenden Professor abgestimmt.", "metadata": {"moduleNumber": "BTB W38", "moduleName": "External Semester", "creditPoints": "30.0", "suggestedSemester": 7, "offeredInSeason": "to_be_announced", "examType": "oral_exam", "heldInLanguage": "de", "reviserName": "Prof. Dr.-Ing. Jochen Steffens", "reviserEmail": "jochen.steffens@hs-duesseldorf.de", "studyProgramId": 10, "source_type": "json"}}
{"id": "BTB__BTB_W", "text": "Title: Elective Modules / Specialization Modules\nModule Number: BTB W\nCredits: 75.0 CP\nSemester: None\nOffered In: every_semester\nLanguage: de\nExam Type: see_elective\nInstructor: Prof. Dr.-Ing. Jochen Steffens (jochen.steffens@hs-duesseldorf.de)\n--- Goals (EN) ---\nsee BTB 20.01 to BTB 20.20\n--- Goals (DE) ---\n​​siehe BTB 20.01 bis BTB 20.20\n--- Contents (EN) ---\nsee attached catalogue of elective courses\n--- Contents (DE) ---\nsiehe angehängter Wahlkatalog\n--- Literature (EN) ---\n--- Literature (DE) ---", "metadata": {"moduleNumber": "BTB W", "moduleName": "Elective Modules / Specialization Modules", "creditPoints": "75.0", "suggestedSemester": null, "offeredInSeason": "every_semester", "examType": "see_elective", "heldInLanguage": "de", "reviserName": "Prof. Dr.-Ing. Jochen Steffens", "reviserEmail": "jochen.steffens@hs-duesseldorf.de", "studyProgramId": 10, "source_type": "json"}}
{"id": "BTB__BTB_W37", "text": "Title: Special Modules from Other Degree Programs\nModule Number: BTB W37\nCredits: 5.0 CP\nSemester: None\nOffered In: to_be_announced\nLanguage: de\nExam Type: see_elective\nInstructor: Prof. Dr.-Ing. Jochen Steffens (jochen.steffens@hs-duesseldorf.de)\n--- Goals (EN) ---\nModule-dependent\n--- Goals (DE) ---\nModulabhängig\n--- Contents (EN) ---\nThis module enables the recognition of achievements acquired in degree programmes other than this one. The content ideally expands the degree programme to include interdisciplinary elements. However, no content requirements are made. Exemplary subject areas: Architecture, design, all humanities, engineering degree programmes, economics\n--- Contents (DE) ---\nDieses Modul ermöglicht die Anerkennung von Leistungen, die in anderen Studiengängen als dem vorliegenden erworben wurden. Die Inhalte erweitern idealerweise das Studium um interdisziplinäre Anteile. Es werden aber keine inhaltlichen Vorgaben gemacht. Beispielhafte Fachgebiete: Architektur, Design, alle Geisteswissenschaften, Ingenieurstudiengänge, Wirtschaftswissenschaften\n--- Literature (EN) ---\nModule-dependent\n--- Literature (DE) ---\nModulabhängig.", "metadata": {"moduleNumber": "BTB W37", "moduleName": "Special Modules from Other Degree Programs", "creditPoints": "5.0", "suggestedSemester": null, "offeredInSeason": "to_be_announced", "examType": "see_elective", "heldInLanguage": "de", "reviserName": "Prof. Dr.-Ing. Jochen Steffens", "reviserEmail": "jochen.steffens@hs-duesseldorf.de", "studyProgramId": 10, "source_type": "json"}}
{"id": "BTB__BTB_W33", "text": "Title: Scientific Deepening\nModule Number: BTB W33\nCredits: 10.0 CP\nSemester: None\nOffered In: to_be_announced\nLanguage: de\nExam Type: presentation\nInstructor: Prof. Dr.-Ing. Jochen Steffens (jochen.steffens@hs-duesseldorf.de)\n--- Goals (EN) ---\nStudents are proficient in dealing with scientific information sources (both in German and English), can cite them correctly and use them to determine the state of the art in research and technology as well as to analyse and plan their own tasks. Students are able to judge their own work in the context of the specialised environment and to communicate about it in an appropriate written and oral form.\n--- Goals (DE) ---\nDie Studierenden beherrschen den Umgang mit wissenschaftlichen Informationsquellen (sowohl deutsch- als auch englischsprachig), können diese korrekt zitieren und sie dazu nutzen, den Stand der Forschung und Technik zu ermitteln sowie eigene Aufgabenstellungen zu analysieren und zu planen. Die Studierenden sind in der Lage, eigene Arbeiten im Kontext des fachlichen Umfeldes zu beurteilen und in angemessener Form schriftlich und mündlich darüber zu kommunizieren.\n--- Contents (EN) ---\nThe students work on the following tasks under supervision for a special topic from audio and video engineering: familiarisation with the task, research for relevant sources of information (scientific publications, specialist books, standards, etc.), content analysis of the sources of information, compilation of the results in a term paper, presentation of the topic in a paper.\n--- Contents (DE) ---\nDie Studierenden bearbeiten unter Anleitung für ein spezielles Thema aus der Ton- oder Bildtechnik folgende Aufgaben: Einarbeitung in die Aufgabenstellung, Recherche nach relevanten Informationsquellen (wissenschaftliche Veröffentlichungen, Fachbücher, Standards, etc.), Inhaltliche Analyse der Informationsquellen, Zusammenstellung der Ergebnisse in einer Hausarbeit, Prasentation des Themas in einem Referat.\n--- Literature (EN) ---\nThe literature depends on the task and will be announced at the beginning of the course.\n--- Literature (DE) ---\nDie Literatur ist abhängig von der Aufgabenstellung und wird zu Beginn der Lehrveranstaltung bekannt gegeben.", "metadata": {"moduleNumber": "BTB W33", "moduleName": "Scientific Deepening", "creditPoints": "10.0", "suggestedSemester": null, "offeredInSeason": "to_be_announced", "examType": "presentation", "heldInLanguage": "de", "reviserName": "Prof. Dr.-Ing. Jochen Steffens", "reviserEmail": "jochen.steffens@hs-duesseldorf.de", "studyProgramId": 10, "source_type": "json"}}
{"id": "BTB__BTB_80", "text": "Title: Bachelor Thesis with Colloquium\nModule Number: BTB 80\nCredits: 15.0 CP\nSemester: 8\nOffered In: winter_semester\nLanguage: de\nExam Type: bachelor_thesis_and_colloquium\nInstructor: Prof. Dr.-Ing. Jochen Steffens (jochen.steffens@hs-duesseldorf.de)\n--- Goals (EN) ---\nThe Bachelor's thesis aims on demonstrating that the candidate is able to work independently on a theoretical or practical problem from the subject area of the Bachelor's degree programme Audio and Video engineering in a written form within a given period of time. The subsequent colloquium serves to determine whether the candidate is able to present the results of the final thesis, its technical foundations, its interdisciplinary connections and its extra-curricular references orally and to justify them independently and to assess their significance for practice. The colloquium serves to determine whether the candidate is able to orally present and independently justify the results of the thesis, its subject-specific principles, its interdisciplinary connections and its extracurricular references and to assess their significance for practice.\n--- Goals (DE) ---\nDie Bachelorarbeit soll zeigen, dass die Kandidatin oder der Kandidat in der Lage ist, innerhalb einer vorgegebenen Frist ein theoretisches oder praktisches Problem aus dem Fachgebiet des Bachelor-Studiengangs Ton- und Bildtechnik selbständig und schriftlich zu bearbeiten. Das anschließende Kolloquium dient\nder Feststellung, ob die Kandidatin oder der Kandidat befähigt ist, die Ergebnisse der Abschlussarbeit, ihre fachlichen Grundlagen, ihre fächerübergreifenden Zusammenhänge und ihre außerfachlichen Bezüge mündlich darzustellen und selbständig zu begründen und ihre Bedeutung für die Praxis einzuschätzen.\nDas Kolloquium dient der Feststellung, ob die Kandidatin oder der Kandidat befähigt ist, die Ergebnisse der Abschlussarbeit, ihre fachlichen Grundlagen, ihre fächerübergreifenden Zusammenhänge und ihre außerfachlichen Bezüge mündlich darzustellen und selbständig zu begründen und ihre Bedeutung für die\nPraxis einzuschätzen.\n--- Contents (EN) ---\nThe Bachelor's thesis consists of a final paper. The colloquium consists of a presentation summarising the completed Bachelor's thesis.\n--- Contents (DE) ---\nDie Bachelorarbeit besteht aus einer Abschlussarbeit. Das Kolloquium besteht aus einer Präsentation als Zusammenfassung der bestandenen Bachelorarbeit.\n--- Literature (EN) ---\nVaries depending on the topic\n--- Literature (DE) ---\nUnterschiedlich je nach Themenstellung", "metadata": {"moduleNumber": "BTB 80", "moduleName": "Bachelor Thesis with Colloquium", "creditPoints": "15.0", "suggestedSemester": 8, "offeredInSeason": "winter_semester", "examType": "bachelor_thesis_and_colloquium", "heldInLanguage": "de", "reviserName": "Prof. Dr.-Ing. Jochen Steffens", "reviserEmail": "jochen.steffens@hs-duesseldorf.de", "studyProgramId": 10, "source_type": "json"}}
{"id": "BTB__BTB_61", "text": "Title: Advanced Image Engineering\nModule Number: BTB 61\nCredits: 5.0 CP\nSemester: 6\nOffered In: summer_semester\nLanguage: de\nExam Type: written_exam\nInstructor: Prof. Dr.-Ing. Thomas Bonse (thomas.bonse@hs-duesseldorf.de)\n--- Goals (EN) ---\nStudents will be able to name the most important algorithms and concepts of video coding and apply them in practical examples. They also understand the basics of the Digital Video Broadcast Standard (DVB) and can name and apply the most important basics in the field of video streaming.\n--- Goals (DE) ---\nDie Studierenden können die wichtigsten Algorithmen und Konzepte der Videocodierung benennen und diese in praktischen Beispielen anwenden. Sie verstehen überdies auch die Grundlagen des Digital Video Broadcast Standards (DVB) und können im Bereich des Videostreamings die wichtigsten Grundlagen benennen und anwenden.\n--- Contents (EN) ---\nThe module deepens and extends the image and video engineering from the module Image Engineering Basics (BMT 114):\n- Intra-frame video coding and predictive image coding with motion estimation\n- Hybrid DCT, MPEG video standards\n- Improved video coding\n- Digital video distribution for broadcast and streaming applications\n- Fundamentals of digital image processing\n- Digital formats for recording media and the AV archive\n--- Contents (DE) ---\nDas Modul vertieft und erweitert die Bild- und Videotechnik aus Modul Bildtechnik Grundlagen (BMT 114):\n- Intra-Frame Bewegtbildcodierungen und prädiktive Bildcodierung mit Bewegungsschätzung\n- Hybride DCT, MPEG-VideostandardsV\n- Verbesserte Bewegtbildcodierung\n- Digitale Videoübertragung für Broadcast- und Streaming-Anwendungen\n- Grundlagen der digitalen Bildverarbeitung\n- Digitale Formate für Aufzeichnungsmedien und das AV-Archiv\n--- Literature (EN) ---\n--- Literature (DE) ---\n-Th. Bonse, F. Kaderali: Digitale Bildcodierung - Grundlagen der digitalen Bildtechnik, Hagen, 2007\n- U. Schmidt: Professionelle Videotechnik, Springer Verlag 2021\n- W. Fischer: Digitale Fernseh- und Hörfunktechnik in Theorie und Praxis, Springer 2016\n- I. E. G. Richardson: The H.264 Advanced Compression Standard, 2nd Ed., Wiley 2010\n- U. Reimers: DVB  digitale Fernsehtechnik: Datenkompression und Übertragung, Springer 2008\n- Akramullah, S.: Digital Video Concepts, Methods, and Metrics: Quality, Compression, Performance, and Power Trade-off Analysis, ApressOpen 2014", "metadata": {"moduleNumber": "BTB 61", "moduleName": "Advanced Image Engineering", "creditPoints": "5.0", "suggestedSemester": 6, "offeredInSeason": "summer_semester", "examType": "written_exam", "heldInLanguage": "de", "reviserName": "Prof. Dr.-Ing. Thomas Bonse", "reviserEmail": "thomas.bonse@hs-duesseldorf.de", "studyProgramId": 10, "source_type": "json"}}
{"id": "BTB__BTB_51", "text": "Title: IT-networked AV Media Production\nModule Number: BTB 51\nCredits: 5.0 CP\nSemester: 5\nOffered In: winter_semester\nLanguage: de\nExam Type: written_exam\nInstructor: Prof. Dr.-Ing. Thomas Bonse (thomas.bonse@hs-duesseldorf.de)\n--- Goals (EN) ---\nStudents achieve an understanding of the fundamentals of audiovisual media production in the context of IP networks.\nStudents will be able to demonstrate the integration of IP network technology into the entire production cycle.\nThey will be able to develop solutions to the challenges of audiovisual media production using IP networks.\nThey will be able to transfer their practical experience in the configuration and management of IP networks for media production to new scenarios.\n--- Goals (DE) ---\nStudierende erlangen Verständnis für die Grundlagen der audiovisuellen Medienproduktion im Kontext von IP-Netzwerken.\nStudierende erhalten die Fähigkeit, die Integration von IP-Netzwerktechnik in den gesamten Produktionszyklus aufzuzeigen.\nSie können Lösungen für die Herausforderungen der audiovisuellen Medienproduktion unter Verwendung von IP-Netzwerken entwickeln.\nSie können ihre praktische Erfahrung in der Konfiguration und Verwaltung von IP-Netzwerken für Medienproduktion auf neue Szenarien übertragen.\n--- Contents (EN) ---\nThis module covers the integration of IP network technology into the audiovisual media production process. It focuses on the design, implementation and optimisation of networked media production systems using IT infrastructures.\n1. information technology in media production: overview of IT infrastructures for media production, data management and storage, cloud-based media production tools\n2. media storage and transmission in IP networks: storage of media content in IP networks, streaming technologies and protocols\n3. networked media production: collaborative tools and platforms for collaboration, real-time communication and remote editing and production technologies\n4. IT infrastructure for audiovisual media production: design and implementation of networked production environments, virtualisation and cloud resources for media production\n5. interactive media production with IP technology: IP networks for the development of interactive media content, application of IP technology in virtual reality (VR) and augmented reality (AR)\n--- Contents (DE) ---\nDieses Modul vermittelt die Integration von IP-Netzwerktechnik in den Produktionsprozess audiovisueller Medien. Es konzentriert sich auf die Konzeption, Implementierung und Optimierung von vernetzten Medienproduktionssystemen unter Verwendung von IT-Infrastrukturen.\n1. Informationstechnologie in der Medienproduktion: Überblick über IT-Infrastrukturen für Medienproduktion, Datenmanagement und -speicherung, Cloud-basierte Medienproduktionswerkzeuge\n2. Medienspeicherung und -übertragung in IP-Netzwerken: Speicherung von Medieninhalten in IP-Netzwerken, Streaming-Technologien und -Protokolle\n3. Vernetzte Medienproduktion: Kollaborative Tools und Plattformen für die Zusammenarbeit, Echtzeit-Kommunikation und Remote-Editing- und Produktionstechnologien\n4. IT-Infrastruktur für audiovisuelle Medienproduktion: Konzeption und Implementierung von vernetzten Produktionsumgebungen, Virtualisierung und Cloud-Ressourcen für Medienproduktion\n5. Interaktive Medienproduktion mit IP-Technologie: IP-Netzwerke für die Entwicklung von interaktiven Medieninhalten, Anwendung von IP-Technologie in Virtual Reality (VR) und Augmented Reality (AR)\n--- Literature (EN) ---\nAppropriate teaching materials will be provided in the course.\n--- Literature (DE) ---\nGeeignete Lehrmaterialien werden in der Lehrveranstaltung bekannt gegeben.", "metadata": {"moduleNumber": "BTB 51", "moduleName": "IT-networked AV Media Production", "creditPoints": "5.0", "suggestedSemester": 5, "offeredInSeason": "winter_semester", "examType": "written_exam", "heldInLanguage": "de", "reviserName": "Prof. Dr.-Ing. Thomas Bonse", "reviserEmail": "thomas.bonse@hs-duesseldorf.de", "studyProgramId": 10, "source_type": "json"}}
{"id": "BTB__BTB_52", "text": "Title: Fundamentals of Image Engineering\nModule Number: BTB 52\nCredits: 5.0 CP\nSemester: 5\nOffered In: winter_semester\nLanguage: de\nExam Type: written_exam\nInstructor: Prof. Dr.-Ing. Thomas Bonse (thomas.bonse@hs-duesseldorf.de)\n--- Goals (EN) ---\nStudents understand the physical principles of light and lighting and can describe them formally. They know the most important properties of the human visual system. They will be able to describe how technical systems for image acquisition and reproduction work in image transmission systems (studio cameras, EB cameras, displays). They will be able to describe the necessary fundamentals of signal processing for digital video signals (image field decomposition, scanning, transmission). They are able to give examples of important interfaces between the system components of image engineering. They are able to interpret the coding transformation for still images (DCT) and calculate this themself in practical examples.\n--- Goals (DE) ---\nDie Studierenden verstehen die physikalischen Grundlagen von Licht und Beleuchtung und können diese formal beschreiben. Sie kennen die wichtigsten Eigenschaften des menschlichen visuellen Systems. Sie können in Bildübertragungssystemen beschreiben, wie technische Systeme zur Bildaufnahme und Bildwiedergabe funktionieren (Studiokameras, EB-Kameras, Displays). Dabei können sie die erforderlichen Grundlagen der Signaltheorie für digitale Bildsignale (Bildfeldzerlegung, Abtastung, Übertragung) darstellen. Für wichtige Schnittstellen zwischen den Systemkomponenten der Bildtechnik können Sie Beispiele angeben. Sie können die Transformationscodierung für Stillbilder (DCT) interpretieren und diese in praktischen Beispielen selbst errechnen.\n--- Contents (EN) ---\nThe module provides an introduction to image and video engineering:\n- Physical and psychophysical fundamentals of image engineering\n- Colourimetry, lighting technology\n- Fundamentals of signal processing in video technology\n- camera and display technologies\n- Fundamentals of digital image and video technology\n- Source coding for images\n--- Contents (DE) ---\nDas Modul führt in Bild- und Videotechnik ein:\n- Physikalische und psychophysische Grundlagen der Bildtechnik\n- Farbmetrik, Beleuchtungstechnik\n- Grundlagen der Signalverarbeitung in der Videotechnik\n- Bildaufnahme- und Bildwiedergabetechnik\n- Grundlagen der digitalen Bild- und Videotechnik\n- Quellencodierung für Stillbilder\nAnschlussmodul: Vertiefung Bildtechnik\n--- Literature (EN) ---\n--- Literature (DE) ---\n- U. Schmidt: Professionelle Videotechnik, Springer Verlag 2021\n- C. Poynton: Digital Video and HD, 2nd Edition, Algorithms and Interfaces, Morgan Kaufmann Publishers 2012\n- Th, Bonse, F. Kaderali: Digitale Bildcodierung - Grundlagen der Bildcodierung, Hagen, 2007", "metadata": {"moduleNumber": "BTB 52", "moduleName": "Fundamentals of Image Engineering", "creditPoints": "5.0", "suggestedSemester": 5, "offeredInSeason": "winter_semester", "examType": "written_exam", "heldInLanguage": "de", "reviserName": "Prof. Dr.-Ing. Thomas Bonse", "reviserEmail": "thomas.bonse@hs-duesseldorf.de", "studyProgramId": 10, "source_type": "json"}}
{"id": "BTB__BTB_10", "text": "Title: Mathematics 1\nModule Number: BTB 10\nCredits: 5.0 CP\nSemester: 1\nOffered In: winter_semester\nLanguage: de\nExam Type: written_exam\nInstructor: None Jörg Becker-Schweitzer (jbs@hs-duesseldorf.de)\n--- Goals (EN) ---\nStudents are able to apply mathematical methods to a wide range of problems. They have a solid understanding of basic concepts in the areas of propositional logic, set theory, relations and functions. In addition, they are proficient in dealing with elementary functions and complex numbers. Students are able to analyze problems in the field of differential and integral calculus and develop appropriate solutions.\n--- Goals (DE) ---\nDie Studierenden können die mathematische Arbeitsweise gezielt auf vielfältige Fragestellungen anwenden. Sie verfügen über ein solides Verständnis der Grundkonzepte in den Bereichen Aussagenlogik, Mengenlehre, sowie Relationen und Funktionen. Darüber hinaus beherrschen sie den Umgang mit elementaren Funktionen und komplexen Zahlen. Die Studierenden sind in der Lage, Problemstellungen im Bereich der Differential- und Integralrechnung zu analysieren und angemessene Lösungsansätze zu entwickeln.\n--- Contents (EN) ---\n- Repetition of basic mathematical knowledge\n- Propositional logic, sets and number spaces\n- Relations and functions\n- Elementary functions\n- Complex numbers\n- Differential calculus\n- Integral calculus\n--- Contents (DE) ---\n- Wiederholung mathematischen Grundwissens\n- Aussagenlogik, Mengen und Zahlenräume\n- Relationen und Funktionen\n- Elementare Funktionen\n- Komplexe Zahlen\n- Differenzialrechnung\n- Integralrechnung\n--- Literature (EN) ---\n- J. Koch, M. Stämpfle: Mathematik für das Ingenieurstudium,3. Auflage, Hanser Verlag, 2015\n- L. Papula: Mathematik für Ingenieure und Naturwissenschaftler, Vieweg Verlag 2004\n- M. Brill: Mathematik für Informatiker, Hanser Verlag 2005\n- K. Kiyek, F. Schwarz: Mathematik für Informatiker, Teubner Verlag 1999\n- P. Stingl: Mathematik für Fachhochschulen, Technik und Informatik, Hanser Verlag 1998\n- L. Papula: Mathematik für Ingenieure und Naturwissenschaftler, Vieweg Verlag 2004\n- T. Westermann: Mathematik für Ingenieure mit Maple, Springer Verlag 2004\n- Maple 9.5 Programming Guide 2005\n- G. Strang: Video-Lectures on Linear Algebra, MIT Boston, USA (Massachusetts Institute of Technology), Weblink: https://ocw.mit.edu/courses/18-06-linear-algebra-spring-2010/video_galleries/video-lectures/\n--- Literature (DE) ---\n- J. Koch, M. Stämpfle: Mathematik für das Ingenieurstudium,3. Auflage, Hanser Verlag, 2015\n- L. Papula: Mathematik für Ingenieure und Naturwissenschaftler, Vieweg Verlag 2004\n- M. Brill: Mathematik für Informatiker, Hanser Verlag 2005\n- K. Kiyek, F. Schwarz: Mathematik für Informatiker, Teubner Verlag 1999\n- P. Stingl: Mathematik für Fachhochschulen, Technik und Informatik, Hanser Verlag 1998\n- L. Papula: Mathematik für Ingenieure und Naturwissenschaftler, Vieweg Verlag 2004\n- T. Westermann: Mathematik für Ingenieure mit Maple, Springer Verlag 2004\n- Maple 9.5 Programming Guide 2005\n- G. Strang: Video-Lectures on Linear Algebra, MIT Boston, USA (Massachusetts Institute of Technology), Weblink: https://ocw.mit.edu/courses/18-06-linear-algebra-spring-2010/video_galleries/video-lectures/", "metadata": {"moduleNumber": "BTB 10", "moduleName": "Mathematics 1", "creditPoints": "5.0", "suggestedSemester": 1, "offeredInSeason": "winter_semester", "examType": "written_exam", "heldInLanguage": "de", "reviserName": "None Jörg Becker-Schweitzer", "reviserEmail": "jbs@hs-duesseldorf.de", "studyProgramId": 10, "source_type": "json"}}
{"id": "BTB__BTB_20", "text": "Title: Mathematics 2\nModule Number: BTB 20\nCredits: 5.0 CP\nSemester: 2\nOffered In: summer_semester\nLanguage: de\nExam Type: written_exam\nInstructor: None Jörg Becker-Schweitzer (jbs@hs-duesseldorf.de)\n--- Goals (EN) ---\nStudents are able to apply mathematical methods to a variety of problems. They have a solid understanding of the basic concepts in the areas of linear systems of equations, vector calculus, analytical geometry and linear algebra. In addition, they are proficient in dealing with sequences and power series. Students are able to understand the concept and application of the Fourier transformation and how to carry it out.\n--- Goals (DE) ---\nDie Studierenden können mathematische Methoden gezielt auf eine Vielzahl von Fragestellungen anwenden. Sie verfügen über ein solides Verständnis der Grundkonzepte in den Bereichen lineare Gleichungssysteme, Vektorrechnung, Analytische Geometrie und lineare Algebra. Darüber hinaus beherrschen sie den Umgang mit Folgen, sowie Potenzreihen. Die Studierenden sind in der Lage, das Konzept und die Anwendung der Fourier-Transformation zu verstehen und durchzuführen.\n--- Contents (EN) ---\n- Solving linear systems of equations\n- Vector calculus\n- Analytic geometry\n- Linear algebra\n- Sequences, limits and continuity\n- Power series\n- Generalized functions\n- Fourier transform\n- Laplace transformation\n--- Contents (DE) ---\n- Lösen linearer Gleichungssysteme\n- Vektorrechnung\n- Analytische Geometrie\n- Lineare Algebra\n- Folgen, Grenzwerte und Stetigkeit\n- Potenzreihen\n- Verallgemeinerte Funktionen\n- Fourier-Transformation\n- Laplace-Transformation\n--- Literature (EN) ---\n- J. Koch, M. Stämpfle: Mathematik für das Ingenieurstudium, 3. Auflage, Hanser Verlag, 2015\n- M. Brill: Mathematik für Informatiker, Hanser Verlag 2005\n- K. Kiyek, F. Schwarz: Mathematik für Informatiker, 2 Bände, Teubner Verlag 1999\n- P. Stingl: Mathematik für Fachhochschulen, Technik und Informatik, Hanser Verlag 1998\n- L. Papula: Mathematik für Ingenieure und Naturwissenschaftler, 3 Bände, Vieweg Verlag 2004\n- T. Westermann: Mathematik für Ingenieure mit Maple, 2 Bände, Springer Verlag 2004\n- Maple 9.5 Programming Guide 2005\n--- Literature (DE) ---\n- J. Koch, M. Stämpfle: Mathematik für das Ingenieurstudium, 3. Auflage, Hanser Verlag, 2015\n- M. Brill: Mathematik für Informatiker, Hanser Verlag 2005\n- K. Kiyek, F. Schwarz: Mathematik für Informatiker, 2 Bände, Teubner Verlag 1999\n- P. Stingl: Mathematik für Fachhochschulen, Technik und Informatik, Hanser Verlag 1998\n- L. Papula: Mathematik für Ingenieure und Naturwissenschaftler, 3 Bände, Vieweg Verlag 2004\n- T. Westermann: Mathematik für Ingenieure mit Maple, 2 Bände, Springer Verlag 2004\n- Maple 9.5 Programming Guide 2005", "metadata": {"moduleNumber": "BTB 20", "moduleName": "Mathematics 2", "creditPoints": "5.0", "suggestedSemester": 2, "offeredInSeason": "summer_semester", "examType": "written_exam", "heldInLanguage": "de", "reviserName": "None Jörg Becker-Schweitzer", "reviserEmail": "jbs@hs-duesseldorf.de", "studyProgramId": 10, "source_type": "json"}}
{"id": "BTB__BTB_11", "text": "Title: Fundamentals of Electrical Engineering and Physics\nModule Number: BTB 11\nCredits: 5.0 CP\nSemester: 1\nOffered In: winter_semester\nLanguage: de\nExam Type: written_exam\nInstructor: None Jörg Becker-Schweitzer (jbs@hs-duesseldorf.de)\n--- Goals (EN) ---\nStudents know and understand basic mathematical concepts that enable them to solve application-oriented problems \nsolve application-oriented problems from the natural sciences, electrical engineering and computer science. Students have knowledge of basic \nphysics. They are familiar with laws, the understanding of \nphysical or electrical engineering contexts, the independent \napply basic physical principles independently up to and including \nmathematical equations and the application of procedures up to the solution of differential equation systems.\n--- Goals (DE) ---\nDie Studierenden kennen und verstehen grundlegende mathematische Begriffe, die dazu befähigen, anwendungsorientierte Problemstellungen aus Naturwissenschaft, Elektrotechnik und Informatik zu lösen. Die Studierenden besitzen Kenntnis grundlegender Physik. Sie beherrschen Gesetzmäßigkeiten, das Erfassen von \nphysikalischen oder elektrotechnischen Zusammenhangen, das selbstständige Anwenden grundlegender physikalischer bis hin zur Umsetzung in mathematische Gleichungen und die Anwendung von Verfahren bis hin zur Lösung von Differentialgleichungssystemen.\n--- Contents (EN) ---\n- Fundamentals of physics (Physical Quantities, Measured Value, \nMeasurement Error, SI-Units, Derived Units\n Linear motion, Momentum, Force, Work, Energy\nPower)\n- Electrostatics (Electric Field in empty Space, Charge, Potential, Field Strength, Fields of several point Charges, \nCapacitance, Dielectrics, Polarisation)\nElectric current (Resistance, Ohm's law, \nSwitching processes at capacitances)\nTheory of common Current Networks (Node-mesh analysis, Substitute Sources, Superposition theorem)\nMagnetism (Magnetic Field in empty Space, \nLorenz force, Magnetic Flux, Matter in a Magnetic Field,\nInduction, Switching processes on Coils)\n--- Contents (DE) ---\n- Grundlagen der Physik (Physikalische Größen, Messwert, Messfehler, SI-Einheiten, Abgeleitete Einheiten\n Lineare Bewegung, Impuls, Kraft, Arbeit, Energie, Leistung)\n- Elektrostatik (Elektrisches Feld im leeren Raum, Ladung, Potential, Feldstärke, Felder mehrerer Punktladungen, Kapazitäten, Dielektrika, Polarisation)\n- Elektrischer Strom (Widerstand, Ohm'sches Gesetz, Schaltvorgänge an Kapazitäten)\n- Theorie der Gleichtstromnetze (Knoten- Maschenanalyse, Ersatzquellen, Überlagerungssatz)\n- Magnetismus (Magnetisches Feld im leeren Raum, Lorenzkraft, magnetischer Fluss, Materie im Magnetfeld, Induktion, Schaltvorgänge an Spulen)\n--- Literature (EN) ---\n--- Literature (DE) ---\n- R. Pregla: Grundlagen der Elektrotechnik, 9.Auflage. VDE-Verlag 2016\n- W. Nerreter: Grundlagen der Elektrotechnik, Hanser Verlag 2011", "metadata": {"moduleNumber": "BTB 11", "moduleName": "Fundamentals of Electrical Engineering and Physics", "creditPoints": "5.0", "suggestedSemester": 1, "offeredInSeason": "winter_semester", "examType": "written_exam", "heldInLanguage": "de", "reviserName": "None Jörg Becker-Schweitzer", "reviserEmail": "jbs@hs-duesseldorf.de", "studyProgramId": 10, "source_type": "json"}}
{"id": "BTB__BTB_21", "text": "Title: Fundamentals of Electrical Engineering\nModule Number: BTB 21\nCredits: 5.0 CP\nSemester: 2\nOffered In: winter_semester\nLanguage: de\nExam Type: portfolio\nInstructor: None Jörg Becker-Schweitzer (jbs@hs-duesseldorf.de)\n--- Goals (EN) ---\nStudents have knowledge of physics. They master \nlaws, the understanding of physical relationships, the independent application of basic physical principles, through to the implementation in mathematical equations, the application of methods for solving systems of equations. \nequations, application of methods for solving systems of equations.\nThey learn how to deal with the basic mathematical concepts of analysis, i.e. differential and integral calculus. In particular, students acquire the skills to implement and solve application-oriented problems in electrical engineering. They will be able to calculate and design simple basic electrical engineering circuits in direct and alternating current networks. They can design simple active and passive filters and simple amplifier circuits\n--- Goals (DE) ---\nDie Studierenden besitzen Kenntnis der Physik. Sie beherrschen Gesetzmäßigkeiten, das Erfassen von physikalischen Zusammenhängen, das selbständige Anwenden grundlegender physikalische Prinzipien, bis hin zur Umsetzung in mathematische Gleichungen, Anwendung von Verfahren zur Lösung der Gleichungssysteme.\nSie erwerben den Umgang mit den grundlegenden mathematischen Begriffen der Analysis, d.h. der Differenzial- und Integralrechnung. Insbesondere erhalten die Studierenden die Kompetenzen, anwendungsorientierte Probleme aus Elektrotechnik umzusetzen und zu lösen. Sie können einfache Grundschaltungen der Elektrotechnik im Gleich- und Wechselstromnetz berechnen und auslegen. Sie können einfache aktive und passive Filter sowie einfache Verstärkerschaltungen entwerfen\n--- Contents (EN) ---\nDirect current networks\nAlternating current networks\nThree-phase networks\nTransformer, resonant circuits, Maxwell's equations, \nElectromagnetic waves, waveguides\nComponents: Semiconductor physics, PN junction, diode, transistor, \noperational amplifier\n--- Contents (DE) ---\n- Gleichstromnetzwerke\n- Wechselstromnetzwerke\n- Drehstromnetzwerke\n- Transformator,  Schwingkreise, Maxwell'sche Gleichungen, Elektromagnetische Wellen, Wellenleiter\n- Bauteile: Halbleiterphysik, PN-Übergang, Diode, Transistor, Operationsverstärker\n--- Literature (EN) ---\n--- Literature (DE) ---\n- R. Pregla: Grundlagen der Elektrotechnik, 9.Auflage. VDE-Verlag 2016\n- W. Nerreter: Grundlagen der Elektrotechnik, Hanser Verlag 2011", "metadata": {"moduleNumber": "BTB 21", "moduleName": "Fundamentals of Electrical Engineering", "creditPoints": "5.0", "suggestedSemester": 2, "offeredInSeason": "winter_semester", "examType": "portfolio", "heldInLanguage": "de", "reviserName": "None Jörg Becker-Schweitzer", "reviserEmail": "jbs@hs-duesseldorf.de", "studyProgramId": 10, "source_type": "json"}}
{"id": "BTB__BTB_W32", "text": "Title: Embedded Systems\nModule Number: BTB W32\nCredits: 5.0 CP\nSemester: None\nOffered In: to_be_announced\nLanguage: de\nExam Type: written_exam\nInstructor: Dipl.-Ing. M.Sc. Christian Epe (christian.epe@hs-duesseldorf.de)\n--- Goals (EN) ---\nStudents can understand digital media technology devices in terms of their hardware function and assess the specifications. They can recognize the requirements for a microcontroller/microprocessor-based system including sensors and actuators and design, develop and program them accordingly.\n--- Goals (DE) ---\nStudierende können digitale Geräte der Medientechnik in ihrer Hardwarefunktion verstehen und die Spezifikationen beurteilen. Sie können die Anforderungen an ein mikrocontroller- /mikoprozessorbasiertes System inkl. Sensoren und Aktoren erkennen und entsprechend konzipieren, entwickeln und programmieren.\n--- Contents (EN) ---\n- Programming of common microcontroller systems\n- Introduction to semiconductor manufacturing and integrated circuit design (ASIC, FPGA, logic synthesis)\n- Processor types and their tasks in the media technology context\n- Parallel/serial interfaces and bus systems in media technology\n- Storage technologies (volatile & non-volatile memories)\n- Finite state machines\n- SoC\n- Sensor technology\n- Power-saving µC design\n- Real-time systems\n- Introduction to feedback control system technology\n- Wireless transmission in the area of IoT and smart home\n--- Contents (DE) ---\n- Programmierung gängiger Mikrocontroller-Systeme\n- Einführung in die Halbleiterherstellung und den Entwurf integrierter Schaltungen (ASIC, FPGA, Logic-Synthese)\n- Prozessortypen und ihre Aufgaben im medientechnologischen Kontext\n- Parallele/Serielle Schnittstellen und Bus-Systeme in der Medientechnik\n- Speichertechnologien (flüchtige & nicht flüchtige Speicher)\n- Finite-State-Machines\n- SoC \n- Sensorik\n- Stromsparendes µC-Design \n- Echtzeitsysteme\n- Einführung in die Regelungstechnik\n- Drahtlose Übertragung im Bereich IoT und Smarthome\n--- Literature (EN) ---\n- D. W. Hoffmann : Grundlagen der Technischen Informatik, Carl Hanser Verlag\n- H.Göbel: Einführung in die Halbleiter-Schaltungstechnik, Springer \n- Frank Kesel: FPGA Hardware-Entwurf, De Gruyter Oldenbourg\n- Jens Lienig: Layoutsynthese elektronischer Schaltungen, Springer\n- Klaus Wüst: Mikroprozessortechnik, Vieweg & Teubner\n- W.Plaßmann, D.Schulz : Handbuch Elektrotechnik - Grundlagen und Anwendungen für Elektrotechniker , Springer\n- L.Stiny: Grundwissen Elektrotechnik und Elektronik, Springer\n--- Literature (DE) ---\n- D. W. Hoffmann : Grundlagen der Technischen Informatik, Carl Hanser Verlag\n- H.Göbel: Einführung in die Halbleiter-Schaltungstechnik, Springer \n- Frank Kesel: FPGA Hardware-Entwurf, De Gruyter Oldenbourg\n- Jens Lienig: Layoutsynthese elektronischer Schaltungen, Springer\n- Klaus Wüst: Mikroprozessortechnik, Vieweg & Teubner\n- W.Plaßmann, D.Schulz : Handbuch Elektrotechnik - Grundlagen und Anwendungen für Elektrotechniker , Springer\n- L.Stiny: Grundwissen Elektrotechnik und Elektronik, Springer", "metadata": {"moduleNumber": "BTB W32", "moduleName": "Embedded Systems", "creditPoints": "5.0", "suggestedSemester": null, "offeredInSeason": "to_be_announced", "examType": "written_exam", "heldInLanguage": "de", "reviserName": "Dipl.-Ing. M.Sc. Christian Epe", "reviserEmail": "christian.epe@hs-duesseldorf.de", "studyProgramId": 10, "source_type": "json"}}
{"id": "BTB__BTB_42_1", "text": "Title: Fundamentals of Digital Engineering\nModule Number: BTB 42_1\nCredits: 5.0 CP\nSemester: 4\nOffered In: summer_semester\nLanguage: de\nExam Type: written_exam\nInstructor: None Jörg Becker-Schweitzer (jbs@hs-duesseldorf.de)\n--- Goals (EN) ---\nStudents understand the principles of converting analog to digital signals. They can perform simple digital processing, encoding and storage. They can convert the digital signals back to analog signals. They are able to simulate the processes.\n--- Goals (DE) ---\nDie Studierenden verstehen die Prinzipien der Umwandlung von analogen zu digitalen Signalen. Sie können einfache digitale Verarbeitung, Codierung und Speicherung durchführen und die digitalen Signale wieder in analoge Signale umwandeln. Sie sind in der Lage, die Vorgänge mittels Softwareunterstützung zu simulieren.\n--- Contents (EN) ---\nAnalog to digital conversion, Coding and numerical systems, Boolean algebrabasic logic modules, programmable logic building blocks, basic digital circuitsdigital to analog conversion, simulation of circuits\n--- Contents (DE) ---\nAnalog-Digitalwandlung, Kodierung und Zahlensysteme, boolesche Algebra, einfache Logikbausteine, programmierbare Logikbausteine, digitale Grundschaltungen, Digital-Analogwandlung, Simulation von Schaltungen\n--- Literature (EN) ---\n- K. Fricke: Digitaltechnik, Verlag Vieweg+Teubner 2009\n- C. Siemers, A. Sikora: Taschenbuch Digitaltechnik, HanserVerlag 2007\n\nFurther literature will be announced at the beginning of the course.\n--- Literature (DE) ---\n- K. Fricke: Digitaltechnik, Verlag Vieweg+Teubner 2009\n- C. Siemers, A. Sikora: Taschenbuch Digitaltechnik, HanserVerlag 2007\n\nWeitere Literatur wird zu Beginn der LV bekannt gegeben.", "metadata": {"moduleNumber": "BTB 42_1", "moduleName": "Fundamentals of Digital Engineering", "creditPoints": "5.0", "suggestedSemester": 4, "offeredInSeason": "summer_semester", "examType": "written_exam", "heldInLanguage": "de", "reviserName": "None Jörg Becker-Schweitzer", "reviserEmail": "jbs@hs-duesseldorf.de", "studyProgramId": 10, "source_type": "json"}}
{"id": "BTB__BTB_W15", "text": "Title: Rapid System Prototyping\nModule Number: BTB W15\nCredits: 5.0 CP\nSemester: 6\nOffered In: to_be_announced\nLanguage: de\nExam Type: oral_exam\nInstructor: Dipl.-Ing. M.Sc. Christian Epe (christian.epe@hs-duesseldorf.de)\n--- Goals (EN) ---\n- Understanding of the concepts and importance of rapid system prototyping in hardware and software development.\n- Mastering techniques for creating functional prototypes of hardware/software and information systems.\n- Ability to apply various prototyping tools and methods, including prototyping software, mockups and wireframes.\n--- Goals (DE) ---\n- Verständnis der Konzepte und Bedeutung des Rapid System Prototyping in der Hard- und Softwareentwicklung. \n- Beherrschung von Techniken zur Erstellung funktionsfähiger Prototypen von Hard-/Software- und Informationssystemen. \n- Fähigkeit zur Anwendung verschiedener Prototyping-Tools und -Methoden, einschließlich Prototyping-Software, Mockups und Wireframes.\n--- Contents (EN) ---\n- Conception and implementation of prototypical works in the field of media technology\n- Introduction to Rapid System Prototyping: Concepts, Goals and Applications.\n- Prototyping tools and methods: Available tools and selection of suitable methods for various applications, e.g. 3D modeling, implementation using CAM processes (3D printing, CNC milling, lasering)\n- Development of circuit diagrams and design of circuit boards\n- Prototyping: Practical exercises in creating prototypes using prototyping software, mockups and wireframes.\n- Iteration and Validation: Methods for quickly iterating prototypes based on feedback and validation of design ideas and requirements.\n--- Contents (DE) ---\n- Konzeption und Umsetzung von prototypischen Arbeiten aus dem Bereich der Medientechnik \n- Einführung in das Rapid System Prototyping: Konzepte, Ziele und Anwendungen. \n- Prototyping-Tools und -Methoden: Verfügbare Tools und Auswahl geeigneter Methoden für verschiedene Anwendungsfälle z.B. 3D-Modellierung, Umsetzung mittels CAM-Verfahren (3D-Druck, CNC Fräsen, Lasern) \n- Entwicklung von Schaltplänen und Design von Leiterplatten \n- Erstellung von Prototypen: Praktische Übungen zur Erstellung von Prototypen unter Verwendung von Prototyping-Software, Mockups und Wireframes. \n- Iteration und Validierung: Methoden zur schnellen Iteration von Prototypen basierend auf Feedback und Validierung von Designideen und Anforderungen.\n--- Literature (EN) ---\n- Alexander Pusch, Nils Haverkamp: \"3D-Druck für Schule und Hochschule\", Springer Spektrum\n- Jens Lienig, Juergen Scheible: \"Fundamentals of Layout Design for Electronic Circuits\", Springer Engineering\n- Ulrich Tietze, Christoph Schenk, Eberhard Gamm: \"Halbleiter-Schaltungstechnik\", Springer Vieweg\n--- Literature (DE) ---\n- Alexander Pusch, Nils Haverkamp: \"3D-Druck für Schule und Hochschule\", Springer Spektrum\n- Jens Lienig, Juergen Scheible: \"Fundamentals of Layout Design for Electronic Circuits\", Springer Engineering\n- Ulrich Tietze, Christoph Schenk, Eberhard Gamm: \"Halbleiter-Schaltungstechnik\", Springer Vieweg", "metadata": {"moduleNumber": "BTB W15", "moduleName": "Rapid System Prototyping", "creditPoints": "5.0", "suggestedSemester": 6, "offeredInSeason": "to_be_announced", "examType": "oral_exam", "heldInLanguage": "de", "reviserName": "Dipl.-Ing. M.Sc. Christian Epe", "reviserEmail": "christian.epe@hs-duesseldorf.de", "studyProgramId": 10, "source_type": "json"}}
{"id": "BTB__BTB_50", "text": "Title: Audio Engineering\nModule Number: BTB 50\nCredits: 5.0 CP\nSemester: None\nOffered In: winter_semester\nLanguage: de\nExam Type: written_exam\nInstructor: Prof. Dr.-Ing. Dieter Leckschat (dieter.leckschat@hs-duesseldorf.de)\n--- Goals (EN) ---\nAfter completing the course, students will be able to use audio technology equipment and relevant software in a professional manner and with the necessary background knowledge. From the practical exercises, students will have learned the basic methods of sound and music production. They can apply these in such a way that technically flawless and sonically appealing productions are created.\n--- Goals (DE) ---\nDie Studierenden sind nach Abschluss der Lehrveranstaltung in der Lage, mit Geräten der Audiotechnik und einschlägiger Software in professioneller Weise und mit dem nötigen Hintergrundwissen umzugehen. Aus den praktischen Übungen haben die Studierenden grundlegende Arbeitsweisen der Ton- und Musikproduktion erlernt. Sie können diese so anwenden, dass technisch einwandfreie und klanglich ansprechende Produktionen entstehen.\n--- Contents (EN) ---\nThe focus is on the basics and conventional sound technology: basics of audio technology, professional recording, processing, storage, transmission and analysis of analogue and digital sound signals and the technical implementation of equipment.\n--- Contents (DE) ---\nDer Schwerpunkt liegt auf den Grundlagen und der konventionellen Tontechnik: Grundlagen der Audiotechnik, Professionelle Aufnahme, Bearbeitung, Speicherung, Übertragung und Analyse von analogen und digitalen Tonsignalen und die gerätetechnische Realisierung.\n--- Literature (EN) ---\n- Th. Gorne: Tontechnik, Hanser Fachbuchverlag 2011S. \n- Weinzierl (Hrgb.): Handbuch der Audiotechnik, Springer Verlag 2008\n- J. Webers: Das Handbuch der Tonstudiotechnik, Franzis´ Verlag 7. Auflage 1999\n- M.Zollner, E. Zwicker: Elektroakustik, Springer Verlag 1998\n- Journal of the Audio Engineering Society (AES)\n--- Literature (DE) ---\n- Th. Gorne: Tontechnik, Hanser Fachbuchverlag 2011S. \n- Weinzierl (Hrgb.): Handbuch der Audiotechnik, Springer Verlag 2008\n- J. Webers: Das Handbuch der Tonstudiotechnik, Franzis´ Verlag 7. Auflage 1999\n- M.Zollner, E. Zwicker: Elektroakustik, Springer Verlag 1998\n- Journal of the Audio Engineering Society (AES)", "metadata": {"moduleNumber": "BTB 50", "moduleName": "Audio Engineering", "creditPoints": "5.0", "suggestedSemester": null, "offeredInSeason": "winter_semester", "examType": "written_exam", "heldInLanguage": "de", "reviserName": "Prof. Dr.-Ing. Dieter Leckschat", "reviserEmail": "dieter.leckschat@hs-duesseldorf.de", "studyProgramId": 10, "source_type": "json"}}
{"id": "BTB__BTB_60", "text": "Title: Advanced Audio Engineering\nModule Number: BTB 60\nCredits: 5.0 CP\nSemester: None\nOffered In: summer_semester\nLanguage: de\nExam Type: written_exam\nInstructor: Prof. Dr.-Ing. Dieter Leckschat (dieter.leckschat@hs-duesseldorf.de)\n--- Goals (EN) ---\nAfter completing the course, the students will be able to deal with sound equipment and relevant software in a professional manner and with well-founded background knowledge. From the practical exercises the students have learned ways of working with sound and music production. They can use them such that technically flawless and sonically pleasing productions arise.\n--- Goals (DE) ---\nDie Studierenden sind nach Abschluss der Lehrveranstaltung in der Lage, mit Geräten der Tontechnik und einschlägiger Software in professioneller Weise und mit einem fundierten Hintergrundwissen umzugehen. Aus den praktischen Übungen haben die Studierenden grundlegende Arbeitsweisen der Ton und Musikproduktion erlernt. Sie können diese so anwenden, dass technisch einwandfreie und klanglich ansprechende Produktionen entstehen.\n--- Contents (EN) ---\nA focus of this module is in digital audio technology: Professional recording, editing, storage, transmission and analysis of analog and digital audio signals and device implementationIntroduction to algorithms of digital audio signal processing and audio coding (data reduction).\n--- Contents (DE) ---\nDer Schwerpunkt dieses Moduls liegt in der Digitalen Audiotechnik: Professionelle Aufnahme, Bearbeitung, Speicherung, Übertragung und Analyse von analogen und digitalen Tonsignalen und die gerätetechnische Realisierung. Einführung in Algorithmen der Digitalen Audiosignalverarbeitung und Datenreduktionsverfahren.\n--- Literature (EN) ---\n- Th. Gorne: Tontechnik, Hanser Fachbuchverlag 2011S. \n- Weinzierl (Hrgb.): Handbuch der Audiotechnik Springer Verlag 2008\n- J. - Webers: Das Handbuch der Tonstudiotechnik Franzis´ Verlag 7. Auflage 1999\n- U. - Zolzer, M. Bossert, N. Fliege: Digitale Audiosignalverarbeitung, Vieweg+Teubner Verlag 2005\n- M. Zollner, E. Zwicker: Elektroakustik, Springer Verlag 1998\n- M. - Kahrs, K.-H. Brandenburg (Ed.): Applications of Digital Signal Processing to Audio and Acoustics, Kluwer Academic Press 1998\n- A. - Spanias, T. Painter: Perceptual Coding of Digital Audio, Proc. IEEE, Vol.88 No.4, 2000 \n- Journal of the Audio Engineering Sociey (AES)\n--- Literature (DE) ---\n- Th. Gorne: Tontechnik, Hanser Fachbuchverlag 2011S. \n- Weinzierl (Hrgb.): Handbuch der Audiotechnik Springer Verlag 2008\n- J. - Webers: Das Handbuch der Tonstudiotechnik Franzis´ Verlag 7. Auflage 1999\n- U. - Zolzer, M. Bossert, N. Fliege: Digitale Audiosignalverarbeitung, Vieweg+Teubner Verlag 2005\n- M. Zollner, E. Zwicker: Elektroakustik, Springer Verlag 1998\n- M. - Kahrs, K.-H. Brandenburg (Ed.): Applications of Digital Signal Processing to Audio and Acoustics, Kluwer Academic Press 1998\n- A. - Spanias, T. Painter: Perceptual Coding of Digital Audio, Proc. IEEE, Vol.88 No.4, 2000 \n- Journal of the Audio Engineering Sociey (AES)", "metadata": {"moduleNumber": "BTB 60", "moduleName": "Advanced Audio Engineering", "creditPoints": "5.0", "suggestedSemester": null, "offeredInSeason": "summer_semester", "examType": "written_exam", "heldInLanguage": "de", "reviserName": "Prof. Dr.-Ing. Dieter Leckschat", "reviserEmail": "dieter.leckschat@hs-duesseldorf.de", "studyProgramId": 10, "source_type": "json"}}
{"id": "BTB__BTB_W27", "text": "Title: Special fields of audio engineering\nModule Number: BTB W27\nCredits: 5.0 CP\nSemester: None\nOffered In: to_be_announced\nLanguage: de\nExam Type: oral_exam\nInstructor: Prof. Dr.-Ing. Dieter Leckschat (dieter.leckschat@hs-duesseldorf.de)\n--- Goals (EN) ---\nStudents master activities with selected, advanced techniques from the fields of recording studio technology, measurement technology, electroacoustics or digital audio signal processing. Skills to be acquired may include, for example, the ability to program audio algorithms. Learning objectives for other selected topics include technical understanding and the ability to analyze and synthesize sometimes complex sound engineering systems.\n--- Goals (DE) ---\nDie Studierenden beherrschen Tätigkeiten mit ausgewählten, fortgeschrittenen Techniken aus den Gebieten Tonstudiotechnik, Messtechnik, Elektroakustik oder Digitaler Audiosignalverarbeitung. Zu erwerbende Kompetenzen können beispielsweise die Fähigkeit zur Programmierung von Audioalgorithmen sein. Lernziele bei weiteren Auswahlthemen umfassen das technische Verständnis, die Analyse- und Synthesefähigkeit von teilweise komplexen Systemen des Sound Engineering.\n--- Contents (EN) ---\nFurther, selected topics from the field of recording studio technology: electroacoustics/electromechanical analogies, theory and practical aspects of sound transducers, binaural technology, electroacoustic measurement technology, sound reinforcement technology, spatial audio, digital audio signal processing, fast convolution, adaptive filters, filter banks, audio coding (data reduction), realization of digital audio effects, e.g: Room simulation, modulation effects, dynamic effects, signal processors: DSP technology.\n--- Contents (DE) ---\nWeiterführende, ausgewählte Themen aus dem Gebiet Tonstudiotechnik: Elektroakustik/Elektromechanische Analogien, Theorie und praktische Aspekte der Schallwandler, Binauraltechnik, Elektroakustische Messtechnik, Beschallungstechnik, Spatial Audio, Digitale Audiosignalverarbeitung, Schnelle Faltung, Adaptive Filter, Filterbanke, Audio Coding (Datenreduktion), Realisierung digitaler Audioeffekte, z.B.: Raumsimulation, Modulationseffekte, Dynamikeffekte, Signalprozessoren: DSP-Technik.\n--- Literature (EN) ---\n- M. Zollner, E. Zwicker: Elektroakustik, Springer Verlag 1998\n- I. Veit: Technische Akustik, Vogel Fachbuch Verlag 2005\n- S. Weinzierl (Hrsg.): Handbuch der Audiotechnik, Springer Verlag 2008\n- H. Kuttruff: Akustik  eine Einführung, Hirzel Verlag 2004\n- W. Ahnert, F. Steffen: Beschallungstechnik  Grundlagen und Praxis, Hirzel Verlag 1993\n- M. Gayford (Hrsg.): Microphone Engineering Handbook, Focal Press 1994\n- M. Colloms: High Performance Loudspeakers, John Wiley&Sons 1999\n- U. Zolzer: Digitale Audiosignalverarbeitung, Vieweg+Teubner Verlag 2005\n- J. Dattorro: Effect Design Part 1 - 3, AES Journal Vol. 45 Nr.9 ff\n- M. Kahrs, K.H. Brandenburg (Ed.): Applications of Digital Signal Processing to Audio and Acoustics, Kluwer Academic Press 1998\n--- Literature (DE) ---\n- M. Zollner, E. Zwicker: Elektroakustik, Springer Verlag 1998\n- I. Veit: Technische Akustik, Vogel Fachbuch Verlag 2005\n- S. Weinzierl (Hrsg.): Handbuch der Audiotechnik, Springer Verlag 2008\n- H. Kuttruff: Akustik  eine Einführung, Hirzel Verlag 2004\n- W. Ahnert, F. Steffen: Beschallungstechnik  Grundlagen und Praxis, Hirzel Verlag 1993\n- M. Gayford (Hrsg.): Microphone Engineering Handbook, Focal Press 1994\n- M. Colloms: High Performance Loudspeakers, John Wiley&Sons 1999\n- U. Zolzer: Digitale Audiosignalverarbeitung, Vieweg+Teubner Verlag 2005\n- J. Dattorro: Effect Design Part 1 - 3, AES Journal Vol. 45 Nr.9 ff\n- M. Kahrs, K.H. Brandenburg (Ed.): Applications of Digital Signal Processing to Audio and Acoustics, Kluwer Academic Press 1998", "metadata": {"moduleNumber": "BTB W27", "moduleName": "Special fields of audio engineering", "creditPoints": "5.0", "suggestedSemester": null, "offeredInSeason": "to_be_announced", "examType": "oral_exam", "heldInLanguage": "de", "reviserName": "Prof. Dr.-Ing. Dieter Leckschat", "reviserEmail": "dieter.leckschat@hs-duesseldorf.de", "studyProgramId": 10, "source_type": "json"}}
{"id": "BTB__BTB_W01", "text": "Title: Computer Animation\nModule Number: BTB W01\nCredits: 5.0 CP\nSemester: None\nOffered In: to_be_announced\nLanguage: de\nExam Type: oral_exam\nInstructor: Prof. Dr.-Ing. Sina Mostafawy (sina.mostafawy@hs-duesseldorf.de)\n--- Goals (EN) ---\nThe students master general and special procedures in the field of computer animation.Theoretical and mathematical basics of 3D animation.Various methods of data acquisition and data generation for animations.Real-time rendering vs. classic rendering methods. Additionally they will learn to prepare and give a presentation about a scientific topic of computeranimation.\n--- Goals (DE) ---\nDie Student:innen beherrschen allgemeine und spezielle Verfahren aus dem Bereich der Computeranimation. Theoretisch-mathematische Grundlagen der 3D-Animation, verschiedene Verfahren der Datenerzeugung für Animationen und Echtzeitrendering. Zusätzlich wird ein dem Kurs gelernt wie ein Vortrag recherchiert, vorbereitet und vor Publikum gehlaten wird.\n--- Contents (EN) ---\n- 12 Basic Principles of Animation \n- Rotation with Quaternions\n- Forward and Inverse Kinematics\n- Partikelanimation and Swarm Simulation\n- Deformation & Morphing Algorithms\n- Rigid- und Soft Bodies\n- Planing und Production of Animations\n--- Contents (DE) ---\n- 12 Basic Principles of Animation \n- Rotation with Quaternions\n- Forward and Inverse Kinematics\n- Partikelanimation and Swarm Simulation\n- Deformation & Morphing Algorithms\n- Rigid- und Soft Bodies\n- Planing und Production of Animations\n--- Literature (EN) ---\n- Computer Animation: Algorithms and Techniques, Rick Parent, 3rd 2012 \n- Advanced Animation and Renderning Techniques: Alan Watt, Mark Watt, Addision Wesley\n- Real-Time Rendering, Eric Haines, 4th 2020Computer Graphics with Open GL, Pearson Prentice Hall, 4th 2013\n--- Literature (DE) ---\n- Computer Animation: Algorithms and Techniques, Rick Parent, 3rd 2012 \n- Advanced Animation and Renderning Techniques: Alan Watt, Mark Watt, Addision Wesley\n- Real-Time Rendering, Eric Haines, 4th 2020Computer Graphics with Open GL, Pearson Prentice Hall, 4th 2013", "metadata": {"moduleNumber": "BTB W01", "moduleName": "Computer Animation", "creditPoints": "5.0", "suggestedSemester": null, "offeredInSeason": "to_be_announced", "examType": "oral_exam", "heldInLanguage": "de", "reviserName": "Prof. Dr.-Ing. Sina Mostafawy", "reviserEmail": "sina.mostafawy@hs-duesseldorf.de", "studyProgramId": 10, "source_type": "json"}}
{"id": "BTB__BTB_W02", "text": "Title: Digital Literacy & AI Literacy\nModule Number: BTB W02\nCredits: 5.0 CP\nSemester: None\nOffered In: to_be_announced\nLanguage: de\nExam Type: portfolio\nInstructor: Prof. Dr. rer. nat. Michael Marmann (marmann@hs-duesseldorf.de)\n--- Goals (EN) ---\nThe students\n\n- recognize the importance of digital literacy in today's information society.\n- understand the basic concepts and applications of artificial intelligence.\n- can critically evaluate digital tools and use them effectively for different purposes.\n- are able to identify and discuss the ethical and social implications of AI use.\n- develop the ability to analyze AI technologies in terms of data protection and data security.\n- can design and implement their own projects using AI elements.\n- can research and structure a current topic and present it at several levels of abstraction \n- are able to argue a topic in the seminar group \n- can prepare a current topic digitally and with interactive elements\n--- Goals (DE) ---\nDie Studierenden\n\n- erkennen die Bedeutung von Digital Literacy in der heutigen Informationsgesellschaft.\n- verstehen die grundlegenden Konzepte und Anwendungen künstlicher Intelligenz.\n- können digitale Werkzeuge kritisch bewerten und effektiv für verschiedene Zwecke einsetzen.\n- sind in der Lage, ethische und soziale Implikationen der KI-Nutzung zu identifizieren und zu diskutieren.\n- entwickeln die Fähigkeit, KI-Technologien in Bezug auf Datenschutz und Datensicherheit zu analysieren.\n- können eigene Projekte unter Einbeziehung von AI-Elementen konzipieren und umsetzen.\n- können ein aktuelles Thema recherchieren, strukturieren und auf mehreren Abstraktionslevels präsentieren \n- können ein bearbeitetes Thema in der Seminargruppe argumentativ vertreten \n- können ein aktuelles Thema digital und mit interaktiven Elementen aufbereiten\n--- Contents (EN) ---\nThe 'Digital Literacy & AI Literacy' seminar provides students with an in-depth understanding of the digital literacies necessary to navigate effectively in the modern world. It covers the skills needed to search, evaluate and create information digitally. The focus is on critically examining the reliability and credibility of digital content.\n\nIn parallel, there is a focus on AI Literacy, which covers the understanding and application of artificial intelligence in different areas of life and work. Students will learn the basic principles of AI systems, including machine learning and data processing. They deal with the latest developments in the field of AI and reflect on their impact on society and the individual.\n\nThe seminar also examines the ethical aspects of digital and AI technologies, such as data protection, algorithmic bias and the effects of automation on the labor market. Methods are developed to deal with these challenges and students are enabled to plan and implement their own digital and AI-related projects.\n--- Contents (DE) ---\nDas Seminar \"Digital Literacy & AI Literacy\" bietet den Studierenden ein tiefgreifendes Verständnis der digitalen Kompetenzen, die notwendig sind, um in der modernen Welt effektiv zu navigieren. Es behandelt die Fähigkeiten, die benötigt werden, um Informationen digital zu suchen, zu bewerten und zu erstellen. Im Zentrum steht die kritische Auseinandersetzung mit der Verlässlichkeit und Glaubwürdigkeit von digitalen Inhalten.\n\nParallel dazu wird ein Schwerpunkt auf AI Literacy gelegt, der das Verständnis und die Anwendung von künstlicher Intelligenz in verschiedenen Lebens- und Arbeitsbereichen umfasst. Die Studierenden lernen die Grundprinzipien von KI-Systemen kennen, einschließlich maschinellem Lernen und Datenverarbeitung. Sie setzen sich mit den neuesten Entwicklungen im Bereich der KI auseinander und reflektieren deren Auswirkungen auf Gesellschaft und Individuum.\n\nDas Seminar beleuchtet zudem die ethischen Aspekte der digitalen und KI-Technologien, wie Datenschutz, Bias in Algorithmen (algorithmic bias) und die Auswirkungen der Automatisierung auf den Arbeitsmarkt. Es werden Methoden erarbeitet, um mit diesen Herausforderungen umzugehen und die Studierenden dazu befähigt, eigene digitale und KI-bezogene Projekte zu planen und zu realisieren.\n--- Literature (EN) ---\nCurrent literature references and sources of information are provided at the beginning of the module or directly from the course context. In addition, digital media are increasingly used as a source of knowledge.\n--- Literature (DE) ---\nAktuelle Literaturhinweise und Informationsquellen werden zu Beginn des Moduls oder unmittelbar aus dem Veranstaltungskontext herausgegeben. Zusätzlich werden verstärkt digitale Medien als Wissensquelle eingesetzt.", "metadata": {"moduleNumber": "BTB W02", "moduleName": "Digital Literacy & AI Literacy", "creditPoints": "5.0", "suggestedSemester": null, "offeredInSeason": "to_be_announced", "examType": "portfolio", "heldInLanguage": "de", "reviserName": "Prof. Dr. rer. nat. Michael Marmann", "reviserEmail": "marmann@hs-duesseldorf.de", "studyProgramId": 10, "source_type": "json"}}
{"id": "BTB__BTB_W03", "text": "Title: E-Business\nModule Number: BTB W03\nCredits: 5.0 CP\nSemester: None\nOffered In: to_be_announced\nLanguage: de\nExam Type: portfolio\nInstructor: Prof. Dr.-Ing. Thomas Rakow (thomas.rakow@hs-duesseldorf.de)\n--- Goals (EN) ---\nThe students know the participants and processes of e-business and can apply their knowledge to their tasks. You can analyze, develop and present e-business tasks in a team.\n--- Goals (DE) ---\nDie Studierenden kennen die Beteiligten und Prozesse des E-Business und können ihre Kenntnisse in dessen Aufgabenstellungen anwenden. Sie können im Team Aufgabenstellungen des E-Business analysieren, entwickeln und präsentieren.\n--- Contents (EN) ---\nDevelopment of e-business and the Web\nData privacy and security\nProducts and services on the Web: business models, e-shops, e-marketplaces, online publications\nMarketplaces on the Web: e-marketplaces, procurement on the Web, Web services, REST/SOAP\nOnline marketing: development model for online customers, methods, key figures, cooperations, web analytics & control\nDigital supply chain: distribution, value chain, rights protection, online payment, mobile devices\nCustomer relationship: customer relationship management, customer evaluation, data management, data analysis, customer communication\n--- Contents (DE) ---\nEntwicklung des E-Business und des Web \nDatenschutz und -sicherheit\nProdukte und Dienstleistungen im Web: Geschäftsmodelle, E-Shops, E-Marktplätze, Online-Publikationen\nMarktplätze im Web: E-Marktplätze, Beschaffung im Web, Web-Services, REST/ SOAP \nOnline-Marketing: Entwicklungsmodell für Online-Kunden, Methoden, Kennzahlen, Kooperationen, Web Analytics & Control\nDigitale Lieferkette: Distribution, Wertekette, Rechteschutz, Online-Bezahlung, mobile Geräte\nKundenbeziehung: Customer-Relationship-Management, Kundenbewertung, Datenverwaltung, Datenanalyse, Kundenkommunikation\n--- Literature (EN) ---\n--- Literature (DE) ---\nKollmann, Tobias: E-Business - Grundlagen elektronischer Geschäftsprozesse in der Net Economy, 6. Auflage, Gabler, Wiesbaden 2016.\nMeier, Andreas, Stormer, Henrik: eBusiness & eCommerce - Management der digitalen Wertschöpfungskette, 3. Aufl., Springer, 2012.\nWirtz, Bernd: Electronic Business - Wertschöpfung im Online-Geschäft, 5. Auflage, Gabler, Wiesbaden, 2016", "metadata": {"moduleNumber": "BTB W03", "moduleName": "E-Business", "creditPoints": "5.0", "suggestedSemester": null, "offeredInSeason": "to_be_announced", "examType": "portfolio", "heldInLanguage": "de", "reviserName": "Prof. Dr.-Ing. Thomas Rakow", "reviserEmail": "thomas.rakow@hs-duesseldorf.de", "studyProgramId": 10, "source_type": "json"}}
{"id": "BTB__BTB_W04", "text": "Title: Introduction to 3D Modeling\nModule Number: BTB W04\nCredits: 5.0 CP\nSemester: None\nOffered In: to_be_announced\nLanguage: de\nExam Type: oral_exam\nInstructor: Prof. Dr.-Ing. Sina Mostafawy (sina.mostafawy@hs-duesseldorf.de)\n--- Goals (EN) ---\nThe participants will be able to construct complex objects in a 3D program after the course. They are still able to texture and illuminate them in order to represent them realistically. You are able to transfer from a given storyboard graphically implemented scenes in 3D and animate it there. You have a basic knowledge of different rendering methods and techniques. They have basic knowledge of what parts have to be rendered and what areas need to be created in post-production. Also, they can decide if a scene should be filmed in real or digitally generated.\n--- Goals (DE) ---\nDie Teilnehmer sind nach dem Kurs in der Lage komplexe Objekte in einem 3D Programm zu konstruieren. Sie sind weiterhin in der Lage diese zu texturieren und zu beleuchten, um sie realistisch abbilden zu können. Sie sind in der Lage aus einem vorgegebenen Storyboard zeichnerisch umgesetzte Sezen in 3D zu übertragen und diese dort nachzubilden. Sie haben ein grundsätzliches Wissen über verschieden Renderingmethoden und -techniken. Sie verfügen über grundsätzliches Wissen welche Bereiche gerendert und welche Bereiche in der Postproduktion entstehen müssen. Auch können sie entscheiden, ob eine Szene real gefilmt, oder beser digital erzeugt werden sollte.\n--- Contents (EN) ---\nIntroduction to 3D modeling\nIntroduction to 3D design with curves and freeform surfaces\nTexturing and mapping\n3D illumination and lighting\nCreation of simple path animations, rendering of individual images and animations.\nBasics of post-production with 3D and 2D elements.es\n--- Contents (DE) ---\nEinführung in 3D-Modellierung\nEinführung in 3D-Konstruktion mit Kurven und Freiformfläche\nTexturierung und Mapping\n3D Illumination und Beleuchtung\nErstellung einfacher Pfadanimationen, Rendering von Einzelbildern und Animationen.\nGrundlagen der Postproduktion mit 3D und 2D Elementen.\n--- Literature (EN) ---\n--- Literature (DE) ---\nWird in der Vorlesung bekannt gegeben", "metadata": {"moduleNumber": "BTB W04", "moduleName": "Introduction to 3D Modeling", "creditPoints": "5.0", "suggestedSemester": null, "offeredInSeason": "to_be_announced", "examType": "oral_exam", "heldInLanguage": "de", "reviserName": "Prof. Dr.-Ing. Sina Mostafawy", "reviserEmail": "sina.mostafawy@hs-duesseldorf.de", "studyProgramId": 10, "source_type": "json"}}
{"id": "BTB__BTB_W05", "text": "Title: Fundamentals of stochastics\nModule Number: BTB W05\nCredits: 5.0 CP\nSemester: None\nOffered In: to_be_announced\nLanguage: de\nExam Type: portfolio\nInstructor: None Jörg Becker-Schweitzer (jbs@hs-duesseldorf.de)\n--- Goals (EN) ---\nStudents acquire a basic understanding of the relationships and methods in probability theory and statistics, with a particular focus on their application in engineering and the natural sciences. They are able to use stochastic methods for further scientific work and have the necessary skills to work out relationships in specialist texts/publications on data analysis and statistical modeling.\n--- Goals (DE) ---\nDie Studierenden erwerben ein grundlegendes Verständnis der Zusammenhänge und Methoden in Wahrscheinlichkeitstheorie und Statistik, mit besonderem Blick auf deren Anwendung in den Ingenieur- und Naturwissenschaften. Sie können stochastische Methoden für weiterführende wissenschaftliche Arbeiten nutzen und besitzen die notwendigen Kompetenzen, um sich Zusammenhänge in Fachtexten/Veröffentlichungen zur Datenanalyse und statistischen Modellierung zu erarbeiten.\n--- Contents (EN) ---\n- Probability spaces and random variables\n- Probability distributions\n- Conditional probabilities and independence\n- Descriptive statistics\n- Estimation theory\n- Law of large numbers and central limit theorem\n- Confidence intervals and distributions\n- Regression and variance analysis\n- Hypothesis tests\n--- Contents (DE) ---\n- Wahrscheinlichkeitsräume und Zufallsvariablen\n- Wahrscheinlichkeitsverteilungen\n- Bedingte Wahrscheinlichkeiten und Unabhängigkeit\n- Deskriptive Statistik\n- Schätztheorie\n- Gesetz der großen Zahlen und zentraler Grenzwertsatz\n- Konfidenzintervalle und Verteilungen\n- Regressions- und Varianzanalyse\n- Hypothesen Tests\n--- Literature (EN) ---\n--- Literature (DE) ---\nL. Fahrmeir, C. Heumann, R. Künstler, I. Pigeot, G. Tutz: Statistik - Der Weg zur Datenanalyse, Springer, 2016.\nL. Papula: Mathematik für Ingenieure und Naturwissenschaftler 3, Vieweg, 2009.\nE. Behrends: Elementare Stochastik, Vieweg, 2012.", "metadata": {"moduleNumber": "BTB W05", "moduleName": "Fundamentals of stochastics", "creditPoints": "5.0", "suggestedSemester": null, "offeredInSeason": "to_be_announced", "examType": "portfolio", "heldInLanguage": "de", "reviserName": "None Jörg Becker-Schweitzer", "reviserEmail": "jbs@hs-duesseldorf.de", "studyProgramId": 10, "source_type": "json"}}
{"id": "BTB__BTB_W06", "text": "Title: Immersive Visualisation\nModule Number: BTB W06\nCredits: 5.0 CP\nSemester: None\nOffered In: to_be_announced\nLanguage: de\nExam Type: portfolio\nInstructor: Prof. Dr. rer. nat. Christian Geiger (geiger@hs-duesseldorf.de)\n--- Goals (EN) ---\nStudents will be familiar with the key concepts of visualization and typical design procedures. They also know typical examples of successful visualization projects and can explain and evaluate them. They are able to recognize typical problems in the design and development of immersive visualizations and to develop expressive and effective visual representation concepts based on established procedures for multivariate data and to implement and evaluate them using suitable immersive technologies (visualization systems, 3D game engines, frameworks).\n--- Goals (DE) ---\nDie Studierenden kennen die wesentlichen Begriffe der Visualisierung und typische Vorgehensweise beim Entwurf. Sie kennen darüber hinaus typische Beispiele erfolgreicher Visualisierungsprojekte und können diese erläutern und bewerten. Sie sind in der Lage typische Probleme der bei der Gestaltung und Entwicklung immersiver Visualisierungen zu erkennen und auf Basis etablierter Vorgehensweisen  für multivariate Daten expressive und effektive visuelle Darstellungskonzepte zu entwickeln, mittels geeigneter immersiver Technologien (Visualisierungssysteme, 3D gameEngines, Frameworks) zu realisieren und zu bewerten.\n--- Contents (EN) ---\nThe course Immersive Visualization deals with computer-aided methods for the graphical representation of information and data, which are given an immersive character through design and technology. This can be achieved through extensive interaction, XR technologies, projections or large-scale displays. This special visual representation is intended to help evaluate, present and inform data or gain new insights from it. The main contents are \n- Aspects of human visual perception and visualization models:\n- Visualization of multivariate data\n- Workflow and procedure models in the visualization process (visualization pipeline)\n- multimodal interaction concepts, design principles and storytelling \n- Overview of typical visualization systems for real-time applications \nThe course will choose a specific topic in each semester offered, which will then be worked on with the participants. External lectures and excursions round off the program.\n--- Contents (DE) ---\nDie Veranstaltung Immersive Visualisierung befasst sich mit computerunterstützten Methoden zur grafischen Repräsentation von Informationen und Daten, die durch Gestaltung und Technologie einen immersiven Charakter erhalten. Das kann durch umfangreiche Interaktion, XR -Technologien, Projektionen oder großflächige Displays erfolgen. Diese besondere bildliche Darstellung soll dabei helfen, Daten auszuwerten, zu präsentieren und informieren bzw. neue Erkenntnisse daraus zu gewinnen. Wesentliche Inhalte sind \n- Aspekte der menschlichen visuellen Wahrnehmung und Modell der Visualisierung:\n- Visualisierung multivariater Daten\n- Workflow und Vorgehensmodelle im Visualisierungsprozess (Visualisierungspipeline)\n- multimodale Interaktionskonzepte, Gestaltungsgrundlagen und Storytelling \n- Überblick typischer Visualisierungssysteme für Echtzeitanwendungen \nDie Veranstaltung wird sich in jedem angebotenen Semester ein spezielles Thema wählen, das mit den Teilnehmer:innen dann bearbeitet wird. Externe Vorträge und Exkursionen runden das Angebot ab.\n--- Literature (EN) ---\n--- Literature (DE) ---\n- Chaomei Chen: Information Visualization. Beyond the Horizon. 2. Auflage, Springer London, (2004)\n- Colin Ware: Information Visualization : Perception for Design Morgan Kaufmann Series in Interactive Technologies, San Francisco, (2000)\n- Natha Yau: Visualize This: The Flowing Data Guide to Design, Visualization and Statistics, Wiley, (2011)\n- Cole Nussbaumer Knaflic: Storytelling with Data: A Data Visualization Guide for Business Professionals, Wiley, (2015)", "metadata": {"moduleNumber": "BTB W06", "moduleName": "Immersive Visualisation", "creditPoints": "5.0", "suggestedSemester": null, "offeredInSeason": "to_be_announced", "examType": "portfolio", "heldInLanguage": "de", "reviserName": "Prof. Dr. rer. nat. Christian Geiger", "reviserEmail": "geiger@hs-duesseldorf.de", "studyProgramId": 10, "source_type": "json"}}
{"id": "BTB__BTB_W07", "text": "Title: Learning agency\nModule Number: BTB W07\nCredits: 5.0 CP\nSemester: None\nOffered In: to_be_announced\nLanguage: de\nExam Type: portfolio\nInstructor: Prof. Dr. rer. nat. Michael Marmann (marmann@hs-duesseldorf.de)\n--- Goals (EN) ---\nThe students \n\n- know the typical work processes of a digital agency and apply them under largely real conditions \n- take on a role within the project that corresponds to their competencies and a typical job profile in an agency \n- learn to organize themselves, act independently and participate in team development processes \n- know the tools required for the different project phases and can apply them in a phase-specific manner\n- are familiar with agile process models and supporting tools and apply these in the context of teamwork \n- design and develop a digital media product or a digitally supported service in a team on the basis of a specific project assignment \n- can present the results of individual project phases and the overall result to internal or external clients\n--- Goals (DE) ---\nDie Studierenden \n\n- kennen die typischen Arbeitsprozesse einer Digitalagentur und wenden diese unter weitgehend realen Bedingungen an \n- nehmen innerhalb des Projektes eine ihren Kompetenzen entsprechende Rolle ein, die einem typischen Tätigkeitsprofil in einer Agentur entspricht \n- lernen, sich selbst zu organisieren, eigenverantwortlich zu handeln und an Teamentwicklungsprozessen teilzunehmen \n- kennen die für die unterschiedlichen Projektphasen notwendigen Werkzeuge und können diese phasenspezifisch anwenden\n- kennen agile Vorgehensmodelle sowie unterstützende Tools und wenden diese im Rahmen der Teamarbeit an \n- konzipieren und entwickeln im Team auf der Basis eines konkreten Projektauftrages ein digitales Medienprodukt oder eine digital gestützte Dienstleistung \n- können Ergebnisse einzelner Projektphasen und das Gesamtergebnis vor internen oder externen Auftraggebern präsentieren\n--- Contents (EN) ---\nThe learning agency module is a special type of project that is highly relevant for later professional life. The special feature is that students work in a team on concrete and practical customer solutions, just like in a real digital agency, from the initial idea through to implementation. \n\nThe client can be internal or external. To this end, students take on specific roles that correspond to real job profiles in agencies. For example, there will be sales-oriented students as well as project managers, concept developers, developers or designers. If several teams are formed, they will be in competition with each other. The solution to be developed will go through all phases of digital product development or an online communication project. Special emphasis is placed on agile project management methods.\n--- Contents (DE) ---\nBeim Modul Lernagentur handelt es sich um eine spezielle Projektform mit hoher Relevanz für das spätere Berufsleben. Die Besonderheit besteht darin, dass Studierende wie in einer realen Digitalagentur im Team an konkreten und praxisnahen Kundenlösungen arbeiten, und zwar von der ersten Idee bis zur Umsetzung. \n\nDabei kann der Auftraggeber intern oder extern sein. Hierzu nehmen die Studierenden bestimmte Rollen ein, die realen Tätigkeitsprofilen in Agenturen entsprechen. So wird es vertrieblich orientierte Studierende genauso geben, wie z.B. Projektmanager, Konzepter, Entwickler oder Designer. Sollten sich mehrere Teams formieren, dann stehen sie im Wettbewerb zueinander. Die zu erarbeitende Lösung durchläuft alle Phasen einer digitalen Produktentwicklung oder eines Online-Kommunikations-Projektes. Dabei wird besonderer Wert auf agile Projektmanagementmethoden gelegt.\n--- Literature (EN) ---\nCurrent literature references and sources of information are provided at the beginning of the module or directly from the course context, if necessary. In addition, digital media are increasingly used as a source of knowledge.\n--- Literature (DE) ---\nAktuelle Literaturhinweise und Informationsquellen werden, so-fern notwendig, zu Beginn des Moduls oder unmittelbar aus dem Veranstaltungskontext herausgegeben. Zusätzlich werden verstärkt digitale Medien als Wissensquelle eingesetzt.", "metadata": {"moduleNumber": "BTB W07", "moduleName": "Learning agency", "creditPoints": "5.0", "suggestedSemester": null, "offeredInSeason": "to_be_announced", "examType": "portfolio", "heldInLanguage": "de", "reviserName": "Prof. Dr. rer. nat. Michael Marmann", "reviserEmail": "marmann@hs-duesseldorf.de", "studyProgramId": 10, "source_type": "json"}}
{"id": "BTB__BTB_W08", "text": "Title: Lighting Engineering\nModule Number: BTB W08\nCredits: 5.0 CP\nSemester: None\nOffered In: to_be_announced\nLanguage: de\nExam Type: project\nInstructor: None Jörg Becker-Schweitzer (jbs@hs-duesseldorf.de)\n--- Goals (EN) ---\nThe students have basic knowledge of the quality criteria and the most important physical parameters needed in lighting technology. On this basis, they are able to provide advice, design and planning with light and color as well as its effect on materials.They have knowledge of the devices of lighting technology and their use in event technology. They are able to dimension lighting systems, to position them and to estimate their effects on the interior.\n--- Goals (DE) ---\nDie Studierenden besitzen Grundkenntnisse über die Qualitätskriterien und die wichtigsten physikalischen Größen, die in der Lichttechnik benötigt werden. Auf dieser Basis sind sie in der Lage, Beratung, Gestaltung und Planung mit Licht und Farbe sowie dessen Wirkung auf Materialien durchzuführen. Sie besitzen Kenntnisse über die Geräte der Lichttechnik und deren Einsatz in der Veranstaltungstechnik. Sie sind in der Lage, Beleuchtungsanlagen zu dimensionieren, zu positionieren und deren Wirkungen auf den Innenraum abzuschätzen.\n--- Contents (EN) ---\nFundamentals of light: biological effects, visual perception, spectraFundamentals of lighting technology: Basic parameters such as luminance, daylight quotient, illuminance, glare, light colorFundamentals of light physics: Types of light generation, emergency lighting, measuring instruments of lighting technologyLighting control and dimming technologyLighting arrangements, lighting design, lighting effectsColor events as artistic impulsesCreate simple lighting plans\n--- Contents (DE) ---\nGrundlagen Licht: biologische Wirkungen, optische Wahrnehmung, Spektren\nGrundlagen Lichttechnik: Grundgrößen wie Leuchtdichte, Tageslichtquotient, Beleuchtungsstärke, Blendung, Lichtfarbe\nGrundlagen Lichtphysik: Arten der Lichterzeugung, Sicherheitsbeleuchtung, Messgeräte der Lichttechnik\nLichtsteuerung und Dimmertechnik\nLichtarrangements, Lichtplanung, Lichteffekte\nFarbereignisse als künstlerische Impulse\nErstellen einfacher Lichtplanungen\n--- Literature (EN) ---\n--- Literature (DE) ---\n- H. R. Ris: Beleuchtungstechnik für Praktiker, VDE Verlag 2008DIN EN 12464-1, z.B. in Leitfaden zur DIN EN 12464-1-Beleuchtung von Arbeitsstatten, Beuth Verlag 2006\n- C. Geissmar-Brandi: Lichtbuch. Die Praxis der Lichtplanung, Birkhäuser Verlag 2001\n- H. J. Hentschel: Licht und Beleuchtung, Hüthig Verlag 2001\n- N. Ackermann: Lichttechnik, Oldenbourg Wissenschaftsverlag 2006\n- J. Müller: Handbuch der Lichttechnik: Das Kompendium für den Praktiker. Know-How für Film. Fernsehen, Theater, Veranstaltungen und Events, PPV Medien Verlag 2008\n- M. Keller: Faszination Licht: Licht auf der Bühne, Prestel Verlag 2010 \nWeitere aktuelle Literatur wird zu Beginn der LV bekannt gegeben.", "metadata": {"moduleNumber": "BTB W08", "moduleName": "Lighting Engineering", "creditPoints": "5.0", "suggestedSemester": null, "offeredInSeason": "to_be_announced", "examType": "project", "heldInLanguage": "de", "reviserName": "None Jörg Becker-Schweitzer", "reviserEmail": "jbs@hs-duesseldorf.de", "studyProgramId": 10, "source_type": "json"}}
{"id": "BTB__BTB_W09", "text": "Title: Mathematics 3\nModule Number: BTB W09\nCredits: 5.0 CP\nSemester: None\nOffered In: to_be_announced\nLanguage: de\nExam Type: portfolio\nInstructor: None Jörg Becker-Schweitzer (jbs@hs-duesseldorf.de)\n--- Goals (EN) ---\nThe students acquire a deeper understanding of mathematical relationships and methods, with a particular focus on their application in the engineering and natural sciences. They can use mathematical methods for advanced scientific work and have the necessary skills to work on mathematical relationships in advanced technical texts / publications on media technology.\n--- Goals (DE) ---\nDie Studierenden erwerben ein vertieftes Verständnis mathematischer Zusammenhänge und Methoden, mit besonderem Blick auf deren Anwendung in den Ingenieur- und Naturwissenschaften. Sie können mathematische Methoden für weiterführende wissenschaftliche Arbeiten nutzen und besitzen die notwendigen Kompetenzen, um sich mathematische Zusammenhänge in fortgeschrittenen Fachtexten/Veröffentlichungen zur Medientechnik zu erarbeiten.\n--- Contents (EN) ---\n- Differential calculus in R^n (domain integral and volume integrals)\n- Vector Analysis\n- Partial differential equations\n- Numerical Methods in Mathematics\n--- Contents (DE) ---\n- Differentialrechnung im R^n (Gebietsintegrale und Volumenintegrale)\n- Vektoranalysis\n- Partielle Differentialgleichungen\n- Numerische Methoden in Mathematik\n--- Literature (EN) ---\n--- Literature (DE) ---\nL. Papula: Mathematik für Ingenieure und Naturwissenschaftler 3, Vieweg, 2009.O. Forster: Analysis 2, Vieweg, 2002.J. Stoer: Numerische Mathematik 1, Springer, 2004.J. Stoer, R. Bulirsch: Numerische Mathematik 2, Springer, 2000. A. Hoffmann, B. Max, W. Vogt: Mathematik für Ingenieure 1/2", "metadata": {"moduleNumber": "BTB W09", "moduleName": "Mathematics 3", "creditPoints": "5.0", "suggestedSemester": null, "offeredInSeason": "to_be_announced", "examType": "portfolio", "heldInLanguage": "de", "reviserName": "None Jörg Becker-Schweitzer", "reviserEmail": "jbs@hs-duesseldorf.de", "studyProgramId": 10, "source_type": "json"}}
{"id": "BTB__BTB_W10", "text": "Title: Human-Computer Interaction\nModule Number: BTB W10\nCredits: 5.0 CP\nSemester: None\nOffered In: to_be_announced\nLanguage: de\nExam Type: written_exam\nInstructor: Prof. Dr.-Ing. M.Sc. Markus Dahm (markus.dahm@hs-duesseldorf.de)\n--- Goals (EN) ---\nStudents can explain basic models and guidelines of HCI and their applicability. They can base technical and programatical properties on human physiology and psychology and can design interactive systems accordingly. Given tasks can be analysed, human computer actions can be appropriately designed for optimal usability comforming to HCI norms and models. Students can describe a user centered process for designing and implelmentation of interaktive applications. They can evaluate and optimize the usability of given interactive system, i.e. they can explain and assess their properties as well as give well founded advice for improvement.\n--- Goals (DE) ---\nStudierende können grundlegende Modelle und Richtlinien der MCI erklären und ihre Anwendbarkeit einordnen. Sie können technische und programmatische Eigenschaften von interaktiven Systemen auf physiologische und psychologische Merkmale des Menschen zurückführen und daraufhin optimieren. GegebeneAufgabenstellungen können analysiert, Mensch-ComputerInteraktionen entworfen und ihre Gestaltung anhand von MCINormen und Modellen begründet werden. Studierende können einenEntwicklungsprozess beschreiben, mit dem nutzerzentriert MCI-en entworfen werden. Sie können Interaktive Systeme bezüglich ihrer Usability anhand geeigneter Normen, Modelle und Richtlinien evaluieren und optimieren, d.h. sie können ihre Eigenschaften erklären und bewerten sowie fundierte Verbesserungsvorschläge machen.\n--- Contents (EN) ---\n- Basics, methods, models and concepts of the design of user interfaces for interactive applications\n- Physiological and psychological basics of human perception, memory, knowledge, experience plus action control; their application in HCI\n- Consequences of the design of hardware and software for the user\n- Models of communication and their application in HCI\n- Design of interactive systems, especially webbased and mobile systems: dialog, information architecture, navigation, orientation, interaction methods\n- Integration of usability engineering in software engineering, user centered design\n- Norms, legal requirements and guidelines\n- Basic concepts of UI programming\n--- Contents (DE) ---\n- Grundlagen, Methoden, Modelle und Konzepte zur Gestaltung von Benutzungsschnittstellen für interaktive Anwendungen.\n- Physiologische und Psychologische Grundlagen der Wahrnehmung, von Gedächtnis, Wissen, Erfahrung sowie der Handlungsregulation sowie Ihre Anwendung in der MCI\n- Konsequenzen der Gestaltung von Hardware und Software für Nutzer.\n- Modelle der Kommunikation und Anwendung auf die MCI\n- Gestaltung von interaktiven Systemen, insbesondere webbasierte Systeme: Dialoggestaltung, Informationsdarstellung, Navigation, Orientierung, Interaktionsformen\n- Integration von Software-Ergonomie in Software Engineering\n- Normen, gesetzliche Grundlagen und Richtlinien\n- Grundlagen der Programmierung von GUIs\n--- Literature (EN) ---\n- Markus Dahm: Grundlagen der Mensch-Computer-Interaktion, Pearson (2006)\n- Jens Jacobsen: Praxisbuch Usability und UX, Rheinwerk (2017)\n- Steve Krug: Don't make me think - revisited, New Riders (2013)\n- Bernhard Preim, Raimund Dachselt: Interaktive Systeme Band 1 und 2, eXamen.press\n- Don Norman: The Design of Everyday Things, Basic Books (2013)\n- Michael Richter, Markus D. Flückiger: Usability und UX kompakt: Produkte für Menschen (IT kompakt), Springer Vieweg (2016)\n--- Literature (DE) ---\n- Markus Dahm: Grundlagen der Mensch-Computer-Interaktion, Pearson (2006)\n- Jens Jacobsen: Praxisbuch Usability und UX, Rheinwerk (2017)\n- Steve Krug: Don't make me think - revisited, New Riders (2013)\n- Bernhard Preim, Raimund Dachselt: Interaktive Systeme Band 1 und 2, eXamen.press\n- Don Norman: The Design of Everyday Things, Basic Books (2013)\n- Michael Richter, Markus D. Flückiger: Usability und UX kompakt: Produkte für Menschen (IT kompakt), Springer Vieweg (2016)", "metadata": {"moduleNumber": "BTB W10", "moduleName": "Human-Computer Interaction", "creditPoints": "5.0", "suggestedSemester": null, "offeredInSeason": "to_be_announced", "examType": "written_exam", "heldInLanguage": "de", "reviserName": "Prof. Dr.-Ing. M.Sc. Markus Dahm", "reviserEmail": "markus.dahm@hs-duesseldorf.de", "studyProgramId": 10, "source_type": "json"}}
{"id": "BTB__BTB_W11", "text": "Title: Multicopter Technology\nModule Number: BTB W11\nCredits: 5.0 CP\nSemester: None\nOffered In: to_be_announced\nLanguage: de\nExam Type: written_exam\nInstructor: None Jörg Becker-Schweitzer (jbs@hs-duesseldorf.de)\n--- Goals (EN) ---\nThe students understand the technical structure and the components of a multicopter. They know the technical as well as the legal framework and can plan a multicopter flight on this basis. The students are able to put the aircraft into flight mode and operate it. They know the technical security systems of a multicopter and can react appropriately to dangerous situations. Students acquire the necessary flight experience and learn how to use a multicopter in professional film and video productions.\n--- Goals (DE) ---\nDie Studierenden verstehen den technischen Aufbau sowie die Komponenten eines Multikopters. Sie kennen technische als auch rechtliche Rahmenbedingungen und können auf dieser Grundlage einen Multikopterflug planen. Die Studierenden sind in der Lage, das Fluggerät in den Flugmodus zu bringen und zu bedienen. Sie kennen die technischen Sicherungssysteme eines Multikopters und können auf Gefahrensituationen geeignet reagieren. Die Studierenden erwerben die notwendige Flugpraxis und lernen den Einsatz eines Multikopters in professionellen Film- und Videoproduktionen kennen.\n--- Contents (EN) ---\nTechnical components of multicopters and comparable unmanned aerial vehicles, Basics of regulatory framework for usage in Germany, for example air traffic laws and media laws, Handling and controlling of multicopters / flight practice, Common safety systems and flight modes of multicopters, Usage of multicopters in video production environments\n--- Contents (DE) ---\nSchematischer Aufbau von Multikoptern sowie vergleichbaren Fluggeräten, Grundlagen rechtlicher Rahmenbedingungen in Deutschland, u. a. Luft-Verkehrsrecht und Medienrecht, Bedienung und Steuerung von Multikoptern / Flugpraxis, Gängige Sicherheitssysteme und Flugmodi von Multikoptern, Einsatz von Multikoptern in Videoproduktionen\n--- Literature (EN) ---\n--- Literature (DE) ---\n- R. Büchi: Faszination Multicopter, vth 2015\n- C. Kornmeier: Der Einsatz von Drohnen zur Bildaufnahme (Eine luftverkehrs- und datenschutzrechliche Betrachtung), LIT 2012\n- D. A. Knight: Überirdisch Die Schonheit der Welt in Drohnenfotografie, teNeues 2016\n- E. Cheng: Mit Drohnen fotografieren und filmen: Das Praxisbuch für Einsteiger, dpunkt.Verlag GmbH 2016\n- I. Marloh / M. J. Sanderson: Filmen und Fotografieren mit Drohnen: Technik, Kaufratgeber, Pilotenschule, Vierfarben 2016", "metadata": {"moduleNumber": "BTB W11", "moduleName": "Multicopter Technology", "creditPoints": "5.0", "suggestedSemester": null, "offeredInSeason": "to_be_announced", "examType": "written_exam", "heldInLanguage": "de", "reviserName": "None Jörg Becker-Schweitzer", "reviserEmail": "jbs@hs-duesseldorf.de", "studyProgramId": 10, "source_type": "json"}}
{"id": "BTB__BTB_W12", "text": "Title: Multimedia Storytelling\nModule Number: BTB W12\nCredits: 5.0 CP\nSemester: None\nOffered In: to_be_announced\nLanguage: de\nExam Type: portfolio\nInstructor: Prof. Gabriele Schwab-Trapp (gabi.schwab-trapp@hs-duesseldorf.de)\n--- Goals (EN) ---\nStudents acquire skills in the conceptual handling of free or applied topics and the ability to independently develop context-related content. The development and practical realisation of their own ideas is made possible with the help of design processes. Experience in interdisciplinary, creative and constructive collaboration is gained within the seminar and possible project groups as well as in dealing with various forms of presentation.\n--- Goals (DE) ---\nDie Studierenden erwerben Fähigkeiten im konzeptionellen Umgang mit freien oder angewandten Themen und die Befähigung zur selbstständigen Erarbeitung von kontextbezogenen Inhalten. Mithilfe von Gestaltungsprozessen werden die Entwicklung und die praktische Umsetzung eigener Ideen ermöglicht. Erfahrungen in interdisziplinärer, kreativer und konstruktiver Zusammenarbeit werden innerhalb der Seminar- und möglicher Projektgruppen sowie im Umgang mit verschiedenen Präsentationsformen gesammelt.\n--- Contents (EN) ---\nFree or applied topics are dealt with, which are presented at the beginning of the semester. The joint deepening, development and unfolding of the topic takes place in seminar form. This also includes philosophical, knowledge-orientated and opinion-forming discussions. The aim is the independent development and realisation of context-related, visual concepts in various media. Various forms of presentation are practised according to the topics and results. Excursions may be organised to support the topics, which will be announced at the beginning of the semester. Material and literature references will be provided for the respective topic in the seminar. Information in the form of text extracts, literature, image examples and research suggestions will be provided to support the respective learning, realisation and design steps. \nMultimedia storytelling is regularly offered as an open, collaborative and interdisciplinary module with students from other subject areas.\n--- Contents (DE) ---\nInhaltlich werden freie oder angewandte Themen behandelt, die zu Beginn des Semesters vorgestellt werden. Die gemeinsame Vertiefung, Entwicklung und Entfaltung des Themas findet in Seminarform statt. Dazu gehört auch die philosophische, erkenntnisorientierte und meinungsbildende Auseinandersetzung. Ziel ist die selbstständige Entwicklung und Umsetzung von kontextbezogenen, visuellen Konzepten in unterschiedlichen Medien. Den Themen und Ergebnissen entsprechend werden verschiedene Präsentationsformen eingeübt. Themenunterstützend können Exkursionen stattfinden, die zu Beginn des Semesters bekannt gegeben werden. Material- und Literaturangaben werden zu dem jeweiligen Thema im Seminar ausgegeben. Zur Unterstützung der jeweiligen Lern-, Erkenntnis- und Gestaltungsschritte werden Hinweise in Form von Textauszügen, Literatur, Bildbeispielen und Recherchevorschlägen gegeben. \nMultimediales Erzählen wird regelmäßig als offenes, kollaboratives und interdisziplinäres Modul mit Studierenden aus anderen Fachbereichen angeboten.\n--- Literature (EN) ---\nLists of materials and literature are issued each semester in the seminar. The respective learning, realisation and design steps are supported by references in the form of text excerpts, literature, image examples and research suggestions. There is also a detailed oral introduction.\n--- Literature (DE) ---\nMaterial- und Literaturlisten werden jedes Semester aktuell im Seminar ausgegeben. Die jeweiligen Lern-, Erkenntnis- und Gestaltungsschritte werden unterstützt durch Hinweise in Form von Textauszügen, Literatur, Bildbeispielen und Recherchevorschlägen. Zudem erfolgt eine ausführliche mündliche Einführung.", "metadata": {"moduleNumber": "BTB W12", "moduleName": "Multimedia Storytelling", "creditPoints": "5.0", "suggestedSemester": null, "offeredInSeason": "to_be_announced", "examType": "portfolio", "heldInLanguage": "de", "reviserName": "Prof. Gabriele Schwab-Trapp", "reviserEmail": "gabi.schwab-trapp@hs-duesseldorf.de", "studyProgramId": 10, "source_type": "json"}}
{"id": "BTB__BTB_W13", "text": "Title: New Work & New Learning\nModule Number: BTB W13\nCredits: 5.0 CP\nSemester: None\nOffered In: to_be_announced\nLanguage: de\nExam Type: portfolio\nInstructor: Prof. Dr. rer. nat. Michael Marmann (marmann@hs-duesseldorf.de)\n--- Goals (EN) ---\nThe students\n\n- understand the concepts and driving forces behind the New Work movement.\n- can identify the principles of New Learning and apply them to educational contexts.\n- are able to design modern working and learning environments that promote creativity and innovation.\n- can critically analyze the effects of new technologies on work and education.\n- develop skills to act as change agents in their organizations.\n- can implement interdisciplinary approaches for lifelong learning and agile work processes.\n- can research and structure a current topic and present it at several levels of abstraction.\n- can argue a topic in the seminar group.\n- can prepare a current topic digitally and with interactive elements.\n--- Goals (DE) ---\nDie Studierenden\n- verstehen die Konzepte und treibenden Kräfte hinter der New Work-Bewegung.\n- können die Prinzipien des New Learning identifizieren und auf Bildungskontexte anwenden.\n- sind in der Lage, moderne Arbeits- und Lernumgebungen zu gestalten, die Kreativität und Innovation fördern.\n- können kritisch die Auswirkungen neuer Technologien auf Arbeit und Bildung analysieren.\n- entwickeln Fähigkeiten, um als Change Agents in ihren Organisationen zu fungieren.\n- können interdisziplinäre Ansätze für lebenslanges Lernen und agile Arbeitsprozesse implementieren.\n- können ein aktuelles Thema recherchieren, strukturieren und auf mehreren Abstraktionslevels präsentieren.\n- können ein bearbeitetes Thema in der Seminargruppe argumentativ vertreten.\n- können ein aktuelles Thema digital und mit interaktiven Elementen aufbereiten.\n--- Contents (EN) ---\nThis seminar deals with the current changes in the world of work and their influence on learning processes. The basics of the New Work movement, which focuses on autonomy, flexibility and participation in the workplace, as well as the principles of New Learning, which emphasizes self-directed learning and the use of new technologies, are covered. Students learn about innovative approaches to the design of working and learning environments that take into account both the individual needs of learners and the requirements of modern organizations.\n\nAn essential part of the seminar is the examination of the challenges and opportunities that digital technologies bring for the world of work and education. Concepts such as lifelong learning, knowledge management and skills development in the context of New Work and New Learning will be discussed.\n\nThe seminar promotes the development of skills that enable participants to act as change agents and implement interdisciplinary approaches in their own professional contexts. This includes critical reflection on existing structures and the ability to design and manage agile and flexible learning and work processes.\n--- Contents (DE) ---\nDieses Seminar beschäftigt sich mit den aktuellen Veränderungen in der Arbeitswelt und deren Einfluss auf Lernprozesse. Es werden die Grundlagen der New Work-Bewegung, die auf Autonomie, Flexibilität und Partizipation am Arbeitsplatz abzielt, sowie die Prinzipien des New Learning, welches Selbstgesteuertes Lernen und den Einsatz neuer Technologien in den Vordergrund stellt, behandelt. Die Studierenden lernen innovative Ansätze zur Gestaltung von Arbeits- und Lernumgebungen kennen, die sowohl die individuellen Bedürfnisse der Lernenden als auch die Anforderungen moderner Organisationen berücksichtigen.\n\nEin wesentlicher Bestandteil des Seminars ist die Auseinandersetzung mit den Herausforderungen und Chancen, die digitale Technologien für die Arbeitswelt und das Bildungswesen mit sich bringen. Es werden Konzepte wie das lebenslange Lernen, Wissensmanagement und die Kompetenzentwicklung im Kontext von New Work und New Learning diskutiert.\n\nDas Seminar fördert die Entwicklung von Kompetenzen, die es den Teilnehmenden ermöglichen, als Change Agents zu agieren und interdisziplinäre Ansätze in ihren eigenen beruflichen Kontexten umzusetzen. Dies beinhaltet die kritische Reflexion über bestehende Strukturen und die Fähigkeit, agile und flexible Lern- und Arbeitsprozesse zu gestalten und zu steuern.\n--- Literature (EN) ---\nCurrent literature references and sources of information are provided at the beginning of the module or directly from the course context. In addition, digital media are increasingly used as a source of knowledge.\n--- Literature (DE) ---\nAktuelle Literaturhinweise und Informationsquellen werden zu Beginn des Moduls oder unmittelbar aus dem Veranstaltungskontext herausgegeben. Zusätzlich werden verstärkt digitale Medien als Wissensquelle eingesetzt.", "metadata": {"moduleNumber": "BTB W13", "moduleName": "New Work & New Learning", "creditPoints": "5.0", "suggestedSemester": null, "offeredInSeason": "to_be_announced", "examType": "portfolio", "heldInLanguage": "de", "reviserName": "Prof. Dr. rer. nat. Michael Marmann", "reviserEmail": "marmann@hs-duesseldorf.de", "studyProgramId": 10, "source_type": "json"}}
{"id": "BTB__BTB_W14", "text": "Title: Pencils and Polygons\nModule Number: BTB W14\nCredits: 5.0 CP\nSemester: None\nOffered In: to_be_announced\nLanguage: de\nExam Type: project\nInstructor: Prof. Dr.-Ing. Sina Mostafawy (sina.mostafawy@hs-duesseldorf.de)\n--- Goals (EN) ---\nThe students know the basics of drawing (picture composition, techniques, shading, perspective). They can transfer their knowledge from 2D to 3D modeling and rendering.\n--- Goals (DE) ---\nDie Studierenden erlernen die Grundlagen des Zeichnens. Sie können das Wissen aus dem 2D Zeichnen in die Erstellung von 3D Modelle übertragen (insbesondere Beleuchtung). Sie wissen, in welcher Form der Begriff des Formens sowie Licht und Schatten die Arbeit in der 3D Welt prägen.\n--- Contents (EN) ---\n- Basics of drawing\n- Dynamic and linear lines\n- Hatching techniques\n- Light and shadow\n- Image composition, image division and -perspective\n- Storyboard drawings\n--- Contents (DE) ---\n- Grundlagen des Zeichnens\n- Dynamische und lineare Linie\n- Schraffur Techniken\n- Licht und Schatten\n- Bildkomposition, Bildeinteilung und -perspektive\n- Storyboard Zeichnungen\n--- Literature (EN) ---\n--- Literature (DE) ---\n- F. A. Cerver: Zeichnen für Einsteiger, Konemann Verlag Koln 2002G. Bammes: Studien zur Gestalt des Menschen, 3. Aufl. Urania Verlag 2001", "metadata": {"moduleNumber": "BTB W14", "moduleName": "Pencils and Polygons", "creditPoints": "5.0", "suggestedSemester": null, "offeredInSeason": "to_be_announced", "examType": "project", "heldInLanguage": "de", "reviserName": "Prof. Dr.-Ing. Sina Mostafawy", "reviserEmail": "sina.mostafawy@hs-duesseldorf.de", "studyProgramId": 10, "source_type": "json"}}
{"id": "BTB__BTB_W17", "text": "Title: Technical Event Planning\nModule Number: BTB W17\nCredits: 5.0 CP\nSemester: None\nOffered In: to_be_announced\nLanguage: de\nExam Type: oral_exam\nInstructor: None Jörg Becker-Schweitzer (jbs@hs-duesseldorf.de)\n--- Goals (EN) ---\nThe students have the ability to carry out technical planning tasks. They can plan a booth and display it with CAD. They can perform simple analysis of the static structures and construction parts as well as the electrical connection performance.\n--- Goals (DE) ---\nDie Studierenden besitzen die Fähigkeit zur Durchführung von Aufgabenstellungen der technischen Messeplanung. Sie können einen Messestand planen, mit CAD darstellen und einfache statische Untersuchungen der Konstruktionen und Konstruktionsteile sowie der elektrischen Anschlussleistungen durchführen.\n--- Contents (EN) ---\nStatic equilibrium conditions, application examplesDetermination of internal forces and moments (normal force, lateral force, bending moment, torsional moment) and the stressesDealing with computer aided (structural) design toolsExamples, tasks and exercises for all teaching contentsRegulations and guidelines of the exhibition and event area\n--- Contents (DE) ---\nGleichgewichtsbedingungen, AnwendungsbeispieleErmittlung der inneren Kräfte und Momente (Normalkraft, Querkraft, Biegemoment, Torsionsmoment) und der Spannungen\nUmgang mit Computer Aided (Structural) Design-Werkzeugen\nBeispiele, Aufgaben und Übungen zu allen Lehrinhalten\nVorschriften und Richtlinien des Messe- und Veranstaltungsbereiches\n--- Literature (EN) ---\n--- Literature (DE) ---\n- J. Berger: Technische Mechanik für Ingenieure, Bande: Bd.1: Statik, Vieweg Verlag 1991 Bd.2: Festigkeitslehre, Vieweg Verlag 1994 Bd.3: Dynamik, Vieweg Verlag 1998\n- D. Gross, W. Hauger, J. Schroder, W. Wall: Technische Mechanik 1: Statik, Springer Verlag 2011\n- D. Gross, W. Hauger, J. Schroder, W. Wall: Technische Mechanik 2: Elastostatik, Springer Verlag 2011\n- D. Gross, W. Hauger, J. Schroder, W. Wall: Technische Mechanik 3: Kinetik, Springer Verlag 2010\n- D. Gross, W. Hauger, J. Schröder, W. Wall: Technische Mechanik 4: Hydromechanik, Springer Verlag 2009\n- H. Dankert, J. Dankert: Technische Mechanik computerunterstützt, Teubner B.G. Verlag 1995\n- G. Henning, A. Jahr, U. Mrowka: Technische Mechanik mit Mathcad, Matlab und Maple, Vieweg & Teubner Verlag 2004\nWeitere aktuelle Literatur wird zu Beginn der LV bekanntgegeben.", "metadata": {"moduleNumber": "BTB W17", "moduleName": "Technical Event Planning", "creditPoints": "5.0", "suggestedSemester": null, "offeredInSeason": "to_be_announced", "examType": "oral_exam", "heldInLanguage": "de", "reviserName": "None Jörg Becker-Schweitzer", "reviserEmail": "jbs@hs-duesseldorf.de", "studyProgramId": 10, "source_type": "json"}}
{"id": "BTB__BTB_W18", "text": "Title: Company Formation\nModule Number: BTB W18\nCredits: 5.0 CP\nSemester: None\nOffered In: to_be_announced\nLanguage: de\nExam Type: research_paper\nInstructor: Prof. Dr.-Ing. M.Sc. Markus Dahm (markus.dahm@hs-duesseldorf.de)\n--- Goals (EN) ---\nAfter successfully completing the module, students know and understand basic business terms and approaches that enable them to develop a business idea in the form of a business plan. They are able to analyse and evaluate the strengths and weaknesses of a business model in order to develop a target-oriented competitive strategy on this basis\n--- Goals (DE) ---\nNach erfolgreicher Teilnahme am Modul kennen und verstehen die Studierenden grundlegende betriebswirtschaftliche Begriffe und Ansätze, die sie dazu befähigen, eine Geschäftsidee in Form eines Business Plans zu entwickeln. Sie sind in der Lage Stärken und Schwächen eines Geschäftsmodells zu analysieren und zu bewerten, um auf dieser Grundlage eine zielführende Wettbewerbsstrategie entwickeln zu können\n--- Contents (EN) ---\n- Descriptive parameters of a business model\n- Competition analysis\n- Target group analysis\n- SWOT analysis\n- Turnover/sales planning\n- P&L planning\n- Calculation of cost of goods sold\n- Financial planning\n- Determination of capital requirements (balance sheet) and financing\n- Choice of legal form\n--- Contents (DE) ---\n- Deskriptive Parameter eines Geschäftsmodells\n- Wettbewerbsanalyse\n- Zielgruppenanalyse\n- SWOT-Analyse\n- Umsatz-/Absatzplanung\n- GuV-Planung\n- Kalkulation der Selbstkosten\n- Finanzplanung\n- Kapitalbedarfsermittlung (bilanziell) und Finanzierung\n- Rechtsformwahl\n--- Literature (EN) ---\n- Kollmann, T.: E-Entrepreneurship. Grundlagen der Unternehmensgründung in der digitalen Wirtschaft. München, 2016\n- neuesunternehmertum.de (Materialien zur Erstellung eines Business Plans)\n- Osterwalder, L. et al.: Value Proposition Design: Entwickeln Sie Produkte und Services, die Ihre Kunden wirklich wollen. Frankfurt a.M., 2015\n- Ries, E.: Lean-Startup. Schnell, risikolos und erfolgreich Unternehmengründen. München, 2014\n--- Literature (DE) ---\n- Kollmann, T.: E-Entrepreneurship. Grundlagen der Unternehmensgründung in der digitalen Wirtschaft. München, 2016\n- neuesunternehmertum.de (Materialien zur Erstellung eines Business Plans)\n- Osterwalder, L. et al.: Value Proposition Design: Entwickeln Sie Produkte und Services, die Ihre Kunden wirklich wollen. Frankfurt a.M., 2015\n- Ries, E.: Lean-Startup. Schnell, risikolos und erfolgreich Unternehmengründen. München, 2014", "metadata": {"moduleNumber": "BTB W18", "moduleName": "Company Formation", "creditPoints": "5.0", "suggestedSemester": null, "offeredInSeason": "to_be_announced", "examType": "research_paper", "heldInLanguage": "de", "reviserName": "Prof. Dr.-Ing. M.Sc. Markus Dahm", "reviserEmail": "markus.dahm@hs-duesseldorf.de", "studyProgramId": 10, "source_type": "json"}}
{"id": "BTB__BTB_W20", "text": "Title: Virtual Reality and Augmented Reality\nModule Number: BTB W20\nCredits: 5.0 CP\nSemester: None\nOffered In: to_be_announced\nLanguage: en_on_demand\nExam Type: portfolio\nInstructor: Prof. Dr. Eng. Univ. of Tsukuba Jens Herder (jens.herder@hs-duesseldorf.de)\n--- Goals (EN) ---\nSuccessful participants will have a profound knowledge in building and developing virtual environments and will be able to evaluate application based on vr technology.\n--- Goals (DE) ---\nDie Studierenden kennen die wichtigsten VR-Technologien und sind in der Lage, virtuelle Umgebungen zu konzipieren, aufzubauen und in der Anwendung zu bewerten.\n--- Contents (EN) ---\n- Motivation, definitions, Layout and design of virtual environment\n- Application fields\n- Human factors in virtual environments\n- Augmented Reality\n- Display systems (e.g., stereo projection)\n- Input and output devices\n- Scene modeling (scene graph based)\n- Data structures and algorithms\n- Simulation\n- Programming of virtual environments\n- Tracking for user interaction\n- Navigation and Interaction in VR\n- Real-time rendering and special effects\n- Haptics\n- Virtual acoustics\n--- Contents (DE) ---\n- Motivation / Begriffsdefinition / Aufbau virtueller Umgebungen\n- Aktuelle Anwendungsgebiet\n- Wahrnehmungsfaktoren für virtuellen Umgebungen\n- Augmented Reality\n- Darstellungstechniken (u.a. stereographische Projektion)\n- Ein- und Ausgabegeräte\n- 3D-Szenenmodellierung\n- Datenstrukturen und Algorithmen für Virtuelle Umgebungen\n- Simulation in virtuellen Umgebungen\n- Entwurf und Programmierung virtueller Umgebungen\n- Tracking von Benutzern und Objekten in VR-Umgebungen\n- Navigation und Interaktion in VR\n- Visuelle Effekte in Echtzeit (u.a. Schatten)\n- Haptik\n- Virtuelle Akustik\n- Nicht-visuelle Repräsentation in Virtuellen Umgebungen\n--- Literature (EN) ---\n- Ralf Dörner, Wolfgang Broll, Paul Grimm, Bernhard Jung, Virtual and Augmented Reality (VR/AR), Foundations and Methods of Extended Realities (XR), Springer, 2022, DOI 10.1007/978-3-030-79062-2\n- Jason Jerald. The VR Book: Human-Centered Design for Virtual Reality. Association for Computing Machinery and Morgan & Claypool, New York, NY, USA, 2015, DOI 10.1145/2792790\n- G. C. Burdea, P. Coiffet: Virtual Reality Technology, John Wiley & Sons, 3. Edition, 2024, ISBN 978-1-118-01480-6\n- M. Guiterrez, F. Vexo, D. Thalman: Stepping into Virtual Reality, Springer Nature Publisher, 2. Edition, 2023, DOI 10.1007/978-3-031-36487-7\n- W. Sherman, A. Craig: Understanding Virtual Reality - Interface, Application, and Design, Morgan Kaufman, 2. Edition 2018, DOI 10.1016/C2013-0-18583-2\n- J. Vince: Introduction to Virtual Reality, Springer 2004, DOI 10.1007/978-0-85729-386-2\n- J. Blauert: Spatial Hearing - The Psychophysics of Human Sound Localization, The MIT Press, Revised Edition, ISBN 0-262-02413-6, 1996\n\nFurther recent literature will be announced at the beginning of the course.\n--- Literature (DE) ---\n- R. Dörner, W. Broll, P. Grimm, B. Jung (Hrsg.), Virtual und Augmented Reality (VR/AR), Grundlagen und Methoden der Virtuellen und Augmentierten Realität, Springer, 2014, DOI 10.1007/978-3-642-28903-3\n- Jason Jerald. The VR Book: Human-Centered Design for Virtual Reality. Association for Computing Machinery and Morgan & Claypool, New York, NY, USA. 2015, DOI 10.1145/2792790\n- G. C. Burdea, P. Coiffet: Virtual Reality Technology, John Wiley & Sons, 3. Auflage, 2024, ISBN 978-1-118-01480-6\n- M. Guiterrez, F. Vexo, D. Thalman: Stepping into Virtual Reality, Springer Nature Verlag, 2. Ausgabe, 2023, DOI 10.1007/978-3-031-36487-7\n- W. Sherman, A. Craig: Understanding Virtual Reality - Interface, Application, and Design, Morgan Kaufman, 2. Auflage, 2018, DOI 10.1016/C2013-0-18583-2\n- J. Vince: Introduction to Virtual Reality, Springer 2004, DOI 10.1007/978-0-85729-386-2\n- J. Blauert: Spatial Hearing - The Psychophysics of Human Sound Localization, The MIT Press, Revised Edition, ISBN 0-262-02413-6, 1996\n\nWeitere aktuelle Literatur wird zu Beginn der LV bekannt gegeben.", "metadata": {"moduleNumber": "BTB W20", "moduleName": "Virtual Reality and Augmented Reality", "creditPoints": "5.0", "suggestedSemester": null, "offeredInSeason": "to_be_announced", "examType": "portfolio", "heldInLanguage": "en_on_demand", "reviserName": "Prof. Dr. Eng. Univ. of Tsukuba Jens Herder", "reviserEmail": "jens.herder@hs-duesseldorf.de", "studyProgramId": 10, "source_type": "json"}}
{"id": "BTB__BTB_W21", "text": "Title: Web Programming\nModule Number: BTB W21\nCredits: 5.0 CP\nSemester: None\nOffered In: to_be_announced\nLanguage: de\nExam Type: written_exam\nInstructor: Prof. Dr. Manfred Wojciechowski (manfred.wojciechowski@hs-duesseldorf.de)\n--- Goals (EN) ---\nThe student understands the technical foundations of web applications and the separation between structure, design and behavior of web sites. They can apply those technologies for the implementation of static websites. They can also apply advanced technologies for the clientside adaption of websites regarding the diverse presentation constraints of different end devices. They are able the evaluate existing static websites regarding the quality of implementation.\n--- Goals (DE) ---\nDie Studierenden verstehen die technischen Grundlagen von Webanwendungen und die Trennung zwischen Struktur, Design und Verhalten von Webseiten. Sie können Technologien zur Realisierung statischer Webseiten sowie Fortgeschrittene Techniken für die clientseitige Anpassung von Webseiten in Hinblick auf unterschiedliche Darstellungsanforderungen anwenden. Sie sind in der Lagebestehende statische Webseiten bezüglich einer sauberen Realisierung zu bewerten.\n--- Contents (EN) ---\nweb application fundamentals (www, client-server-architecture, http)\ntechnologies for the realization of static web sites: structure and content (XML, HTML5); design (CSS3); scripting (ECMAScript 6+, DOM)\nadvanced technologies for the adaption of representation requirements, e.g. responsive webdesign\n--- Contents (DE) ---\nVorlesung:\nGrundlagen von Webanwendungen (WWW, Client-Server, http-Protokoll)\nTechniken für die Realisierung von statischen Webseiten: Struktur und Inhalte (XML, HTML5); Design (CSS3); Verhalten (ECMAScript 6, DOM)\nFortgeschrittene Techniken zur Adaption an Darstellungsanforderungen, z.B. responsive Webdesign\nÜbung: Übungsaufgaben zur Anwendung der Lehrinhalte aus der Vorlesung\nUmsetzung einer eigenen Webseite auf Basis der gelernten Techniken.\n--- Literature (EN) ---\n--- Literature (DE) ---\n- M. Wojciechowski: Vorlesungsskript zur Webprogrammierung\n- E. Robson, E. Freeman: HTML und CSS von Kopf bis Fuß, O'Reilly 2013\n-E. Robson, E. Freeman: HTML5-Programmierung von Kopf bis Fuß: Webanwendungen mit HTML5 und JavaScript, 2012\n- C. Zillgens: Responsive Webdesign, Hanser-Verlag 2013\n- S. Münz, C. Gull: HTML5 Handbuch, Franzis Verlag 2013", "metadata": {"moduleNumber": "BTB W21", "moduleName": "Web Programming", "creditPoints": "5.0", "suggestedSemester": null, "offeredInSeason": "to_be_announced", "examType": "written_exam", "heldInLanguage": "de", "reviserName": "Prof. Dr. Manfred Wojciechowski", "reviserEmail": "manfred.wojciechowski@hs-duesseldorf.de", "studyProgramId": 10, "source_type": "json"}}
{"id": "BTB__BTB_W22", "text": "Title: Network Engineering 2\nModule Number: BTB W22\nCredits: 5.0 CP\nSemester: None\nOffered In: to_be_announced\nLanguage: de\nExam Type: portfolio\nInstructor: Prof. Dr.-Ing. Stefanie Dederichs (stefanie.dederichs@hs-duesseldorf.de)\n--- Goals (EN) ---\nStudents are aware of the need for routing when submitting packets over subnets. They are able to classify the routing according to the ISO / OSI layer model. They now the use cases, the advantages and disadvantages of static and dynamic routing. They are able to apply those concepts in the configuration of small and medium sized networks. The students know the reasons for the usage of VLANs. They are able to create VLANs on routers and switches. They know selected use cases for access control lists. They are able to limit access to subnets by creating appropriate access control lists. They are aware of the need for dynamic allocation of IPv4 and IPv6 addresses. They know mechanisms for the dynamic allocation of IPv6 addresses. They are able to configure network participants and routers for the dynamic allocation of IP addresses. The students know some use cases for the temporary assignment of public addresses. They are able to configure NAT on a router.\n--- Goals (DE) ---\nDie Studierenden kennen die Notwendigkeit des Routings bei der Übermittlung von Paketen über Subnetze und können dieses im ISO/OSI Kommunikationmodell einordnen. Sie kennen die Einsatzfälle, sowie die Vor- und Nachteile des statischen bzw. des dynamischen Routings. Sie sind in der Lage statische und dynamische Routen zu erstellen. Die Studierenden kennen Gründe für den Einsatz von VLANs. Sie sind in der Lage ein VLAN auf Routern und Switchen anzulegen. Sie kennen einige Einsatzfälle für Zugriffskontrolllisten. Sie sind in der Lage den Zugriff auf Subnetze durch das Anlegen von entsprechenden Zugriffskontrolllisten zu kontrollieren. Sie kennen die Notwendigkeit für die dynamische Zuordnung von IPv4 und IPv6-Adressen. Sie kennen Mechanismen zur dynamischen Zuordnung von IPv6-Adressen. Sie sind in der Lage Netzwerkteilnehmer und Router für die dynamische Vergabe von IP-Adressen zu konfigurieren. Die Studierenden kennen Einsatzfelder für die temporäre Zuordnung öffentlicher Adressen. Sie sind in der Lage auf einem Router das NAT zu konfigurieren.\n--- Contents (EN) ---\nStatic and dynamic routing, Flexible networks using VLAN, Access Control List, Dynamic assigment of IP adresses using DHCP, Temporary mapping of public addresses using NAT\n--- Contents (DE) ---\nStatisches und Dynamisches Routing, Flexible Netzwerke mit Hilfe von VLANs, Zugriffskontrolllisten, Dynamische Vergabe von IP-Adressen mittels DHCP, Temporare Zuordnung öffentlicher Adressen mittels NAT\n--- Literature (EN) ---\n--- Literature (DE) ---\nWebbasiertes Curriculum CCNA 2Computer-Netzwerke: Grundlagen, Funktionsweisen, Anwendung. Für Studium, Ausbildung und Beruf, Rheinwerk ComputingNetzwerktechnik, Band 2: Erweiterte Grundlagen, Airnet", "metadata": {"moduleNumber": "BTB W22", "moduleName": "Network Engineering 2", "creditPoints": "5.0", "suggestedSemester": null, "offeredInSeason": "to_be_announced", "examType": "portfolio", "heldInLanguage": "de", "reviserName": "Prof. Dr.-Ing. Stefanie Dederichs", "reviserEmail": "stefanie.dederichs@hs-duesseldorf.de", "studyProgramId": 10, "source_type": "json"}}
{"id": "BTB__BTB_W23", "text": "Title: Advanced Signal Processing\nModule Number: BTB W23\nCredits: 5.0 CP\nSemester: None\nOffered In: to_be_announced\nLanguage: de\nExam Type: portfolio\nInstructor: Prof. Dr.-Ing. Stefanie Dederichs (stefanie.dederichs@hs-duesseldorf.de)\n--- Goals (EN) ---\n--- Goals (DE) ---\nStudierende haben Erfahrung mit der Auswahl geeigneter Signalanalytischer Verfahren und deren Auswahl für vorliegende Anwendungen.\n--- Contents (EN) ---\n--- Contents (DE) ---\nVerständnis und Auswahl verschiedener Frequenz- und Zeitbereichs basierter Methoden zur Skalierung, Transformation, Analyse, Interpretation und Manipulation von Signalen. Anwendungen enthalten die Verbesserung der Qualität, Extraktion von nützlicher Information und Generation neuer Signale.\n--- Literature (EN) ---\n--- Literature (DE) ---\n- Alan V. Oppenheim, Alan S. Willsky, Signals & Systems, Prentice Hall\n- Alan V. Oppenheim, Ronald W. Schafer: Zeitdiskrete Signalverarbeitung. R. Oldenbourg, \n- Steven W. Smith: The Scientist and Engineer's Guide to digital Signal Processing. California Technical Publishing", "metadata": {"moduleNumber": "BTB W23", "moduleName": "Advanced Signal Processing", "creditPoints": "5.0", "suggestedSemester": null, "offeredInSeason": "to_be_announced", "examType": "portfolio", "heldInLanguage": "de", "reviserName": "Prof. Dr.-Ing. Stefanie Dederichs", "reviserEmail": "stefanie.dederichs@hs-duesseldorf.de", "studyProgramId": 10, "source_type": "json"}}
{"id": "BTB__BTB_W24", "text": "Title: Musical Acoustics\nModule Number: BTB W24\nCredits: 5.0 CP\nSemester: None\nOffered In: to_be_announced\nLanguage: de\nExam Type: oral_exam\nInstructor: Prof. Dr.-Ing. Jochen Steffens (jochen.steffens@hs-duesseldorf.de)\n--- Goals (EN) ---\nThe students are able to transfer the contents conveyed in the modules \"Technical Acoustics\" and \"Psychoacoustics\" to concrete applications of Musical Acoustics.In the field of musical instrument acoustics, they know the mode of operation of the individual instruments of different instrument groups and master their acoustic or sonic analysis. They are familiar with common analysis methods (e.g., vibration / modal analyzes, artificial lip / blower and stimulation devices) as well as the evaluation of quality features (e.g., intonation, response, style). This includes phenomena of the interaction between the musician and the instrument.They may explain the influence of instrumentation and performance parameters on perception and effect on the recipient (e.g., material or nature of mouthpiece, reed, valve and bow, as well as intonation or movement patterns of musicians). In addition, they are able to assess phenomena of musical acoustics from a perceptual-psychological or music-psychological perspective.\n--- Goals (DE) ---\nDie Studierenden sind in der Lage, die in den Modulen \"Technische Akustik\" und \"Psychoakustik\" vermittelten Inhalte auf konkrete Anwendungsgebiete der musikalischen Akustik zu übertragen. Im Bereich der Musikinstrumentenakustik kennen sie die Funktionsweise der einzelnen Instrumente unterschiedlicher Instrumentengruppen und beherrschen deren akustische bzw. klangliche Analyse. Sie sind vertraut mit gängigen Analysemethoden (z.B. Schwingungs-/ Modalanalysen, künstliche Lippen / Anblas- und Anregungsvorrichtungen) sowie der Bewertung von Qualitätsmerkmalen (z.B. Intonation, Ansprache, Spielart). Dazu gehören auch Phänomene der Interaktion zwischen Musiker und Instrument. Sie können den Einfluss von instrumentenakustischen und spieltechnischen Parametern hinsichtlich der Wahrnehmung und Wirkung auf den Rezipienten erklären (z.B. Material oder Beschaffenheit von Mundstück, Rohrblatt, Ventil und Bogen sowie Intonation oder Bewegungsmuster von Musikern).  Darüber hinaus sind sie in der Lage, Phänomene der musikalischen Akustik aus einer wahrnehmungspsychologischen bzw. musikpsychologischen Perspektive zu beurteilen.\n--- Contents (EN) ---\n- Introduction to musical acoustics and related disciplines\n- Acoustics of musical sound sources (sound power and dynamics, transient and decay processes, excitation and spectrum, radiation)\n- Stringed instruments (types of excitation, string vibration, properties of wood, bridge admittance)\n- Brass instruments (how they work, mouthpiece, airlock model, resonance and response, natural tone formation, summation principle, valves)\n- Woodwind instruments (flutes, single and double reed instruments, edge and reed tone, resonance conditions)\n- Percussion instruments (idiophones and membranophones, modes of vibration, coupled vibration systems, modal structures, presentation of relevant instruments)\n- The acoustics of the voice (source-filter model, sound formation, formants, vocal genres, vocal registers, singing styles)\n- The acoustics of the (pipe) organ (mechanics, stops, lip and reed pipes)\n- Tone systems (interval perception, harmonic series, Pythagorean music theory, pure, meantone and equal temperament, non-Western and modern systems)\n- Interplay of musical instruments (auditory scene analysis, arrangement of timbres, dissonance and consonance)\n- Room acoustics of musical performance spaces (basics of room acoustics, historical development of concert halls, room shapes, physical and perceptual evaluation measures)\n- Sound synthesis (additive and subtractive synthesis, amplitude and frequency modulation, waveshaping, granular synthesis, physical modelling, sampling, direct synthesis)\n- Electronic instruments and musical interfaces (history, MIDI and OSC protocol, types of controllers)\n- Music Information Retrieval (areas of application, audio features, methods of pitch and chord recognition, novelty function, tempo and beat recognition, toolboxes)\n-\tMusic psychology I (music listening behaviour, functions of music listening, musical taste, musicality, personal and situational influences)\n-\tMusic Psychology II - Music and Emotion (definition and classification of emotions, perception and induction of musical emotions, emotion measurement)\n--- Contents (DE) ---\n- Einführung in die musikalische Akustik und verwandete Disziplinen\n- Akustik musikalischer Schallquellen (Schallleistung und Dynamik, Ein- und Ausschwingvorgänge, Anregung und Spektrum, Abstrahlung)\n- Saiteninstrumente (Arten der Erregung, Saitenschwingung, Eigenschaften von Holz, Stegadmittanz)\n- Blechblasinstrumente (Funktionsweise, Mundstück, Schleusenmodell, Resonanz und Ansprache, Naturtonbildung, Summenprinzip, Ventile)\n- Holzblasinstrumente (Flöten, Einfach- und Doppelrohrblattinstrumente, Kanten- und Zungenton, Resonanzbedingungen)\n- Schlaginstrumente (Idio- und Membranophone, Schwingungsformen, gekoppelte Schwingungssysteme, modale Strukturen, Vorstellung relevanter Instrumente)\n- Die Akustik der Stimme (Quelle-Filter-Modell, Klangformung, Formanten, Stimmgattungen, Stimmregister, Singstile)\n- Die Akustik der (Pfeifen-)Orgel (Mechanik, Register, Lippen- und Zungenpfeifen)\n- Tonsysteme (Intervallwahrnehmung, harmonische Reihe, pythagoräische Musiklehre, reine, mitteltönige und gleichstufige Stimmung, nichtwestliche und moderne Systeme)\n- Zusammenklang von Musikinstrumenten (Auditorische Szenenanalyse, Anordnung von Klangfarben, Dissonanz und Konsonanz)\n- Raumakustik musikalischer Aufführungsräume (Grundlagen der Raumakustik, historische Entwicklung von Konzertsälen, Raumformen, physikalische und perzeptive Bewertungsmaße)\n- Klangsynthese (Additive und subtraktive S., Amplituden-  und Frequenzmodulation, Waveshaping, Granularsynthese, Physical Modeling, Sampling, Direkte Synthese)\n- Elektronische Instrumente und Musical Interfaces (Geschichte, MIDI- und OSC-Protokoll, Arten von Controllern)\n- Music Information Retrieval (Anwendungsgebiete, Audiodeskriptoren, Verfahren der Tonhöhen- und Akkorderkennung, Novelty-Function, Tempo- und Takterkennung, Toolboxen)\n- Musikpsychologie I (Musikhörverhalten, Funktionen des Musikhörens, Musikgeschmack, Musikalität, Einflussfaktoren von Person und Situation)\n- Musikpsychologie II - Musik und Emotion (Definition und Klassifikation von Emotionen, Wahrnehmung und Induktion musikalischer Emotionen, Emotionsmessung)\n--- Literature (EN) ---\nJ.W. Beauchamp: Analysis, synthesis, and perception of musical sounds: the sound of music. Springer, 2007\nN.H. Fletcher & T. D. Rossing: The Physics of Musical Instruments. Berlin: Springer, 1998\nD.E. Hall, Musikalische Akustik. Schott, 2008M.R. Jones; Music Perception. Springer, 2010·\nJ. Meyer: Akustik und musikalische Aufführungspraxis, 6. erweiterte Auflage, Edition Bochinsky, 2015\nS. Weinzierl, Akustische Grundlagen der Musik. Laaber, 2014\n--- Literature (DE) ---\nJ.W. Beauchamp: Analysis, synthesis, and perception of musical sounds: the sound of music. Springer, 2007\nN.H. Fletcher & T. D. Rossing: The Physics of Musical Instruments. Berlin: Springer, 1998\nD.E. Hall, Musikalische Akustik. Schott, 2008M.R. Jones; Music Perception. Springer, 2010·\nJ. Meyer: Akustik und musikalische Aufführungspraxis, 6. erweiterte Auflage, Edition Bochinsky, 2015\nS. Weinzierl, Akustische Grundlagen der Musik. Laaber, 2014", "metadata": {"moduleNumber": "BTB W24", "moduleName": "Musical Acoustics", "creditPoints": "5.0", "suggestedSemester": null, "offeredInSeason": "to_be_announced", "examType": "oral_exam", "heldInLanguage": "de", "reviserName": "Prof. Dr.-Ing. Jochen Steffens", "reviserEmail": "jochen.steffens@hs-duesseldorf.de", "studyProgramId": 10, "source_type": "json"}}
{"id": "BTB__BTB_W26", "text": "Title: Network Engineering 3\nModule Number: BTB W26\nCredits: 5.0 CP\nSemester: None\nOffered In: to_be_announced\nLanguage: de\nExam Type: portfolio\nInstructor: Prof. Dr.-Ing. Stefanie Dederichs (stefanie.dederichs@hs-duesseldorf.de)\n--- Goals (EN) ---\n--- Goals (DE) ---\nDie Studierenden erklären sich die Arbeitsweise und die Vorteile des Spanning Tree Protokolls. Sie sind in der Lage ein solches Protokoll im Netzwerk zu konfigurieren und Fehler zu beseitigen. Sie kennen die Eigenschaften des Inter-VLAN Routing und sind in der Lage das Netzwerk entsprechend einzurichten. Sie kennen die Möglichkeiten, die Bandbreiten zwischen verschiedenen Knoten mittels der Aggregation mehrerer physikalischer Leitungen zu erhöhen. Sie kennen die entsprechenden Protokolle dazu und können das Netzwerk entsprechend konfigurieren. Sie kennen unterschiedliche dynamische Routingprotokolle und setzen diese entsprechend ein.\n--- Contents (EN) ---\n--- Contents (DE) ---\nAusgewählte Gebiete der Netzwerktechnik werden vertieft: Technologien für große und komplexe Netzwerke, Spanning Tree Protocol, Inter-VLAN Routing, EtherChannel und HSRP, Routing Protokolle, z.B. OSPF und EIGRP\n--- Literature (EN) ---\n--- Literature (DE) ---\nTanenbaum: Computer Networks, Pearson;\nR. Schreiner: Computernetzwerke: Von den Grundlagen zur Funktion und Anwendung, Carl Hanser Verlag;\nWebbasiertes Curriculum;", "metadata": {"moduleNumber": "BTB W26", "moduleName": "Network Engineering 3", "creditPoints": "5.0", "suggestedSemester": null, "offeredInSeason": "to_be_announced", "examType": "portfolio", "heldInLanguage": "de", "reviserName": "Prof. Dr.-Ing. Stefanie Dederichs", "reviserEmail": "stefanie.dederichs@hs-duesseldorf.de", "studyProgramId": 10, "source_type": "json"}}
{"id": "BTB__BTB_W28", "text": "Title: Fundamentals of Computer Graphics\nModule Number: BTB W28\nCredits: 5.0 CP\nSemester: None\nOffered In: to_be_announced\nLanguage: de\nExam Type: written_exam\nInstructor: Prof. Dr.-Ing. Sina Mostafawy (sina.mostafawy@hs-duesseldorf.de)\n--- Goals (EN) ---\nThe students know the basics of 3D computer graphics, the functionality of the graphics pipeline, local illumoination algorithms and shading techniques and can apply them.\n--- Goals (DE) ---\nDie Student:innen kennen die Grundlagen der 3D Computergrafik, die Funktionsweise der Grafikpipeline, lokale Beleuchtungsmodelle und Shading-Verfahren und können diese anwenden.\n--- Contents (EN) ---\nFixed Graphics Pipeline\nRasterization techniques\nClipping and Culling Algorithms\nMatrix Transformations  (2D/ 3D)\nOrthogonal and Perspective Projektion\nIllumination and Shading Algorithms \nBasics of Beziér interpolation\n--- Contents (DE) ---\nFixed Graphics Pipeline\nRasterization techniques\nClipping and Culling Algorithms\nMatrix Transformations  (2D/ 3D)\nOrthogonal and Perspective Projektion\nIllumination and Shading Algorithms \nBasics of Beziér interpolation\n--- Literature (EN) ---\n--- Literature (DE) ---\nComputer Graphics with OpenGL, D. Hearn, M.P. Baker, Pearson Education I\nAdvanced Animation and Rendering Techniques, Watt, M. Watt, Addison Wesley\nComputergrafik,Xiang, Zhigang; Plastock, Roy mitp/bhv\nFundamentals of Computer Graphics, Shirley P. \nAdvanced Global Illumination, P. Dutré, AK Peters", "metadata": {"moduleNumber": "BTB W28", "moduleName": "Fundamentals of Computer Graphics", "creditPoints": "5.0", "suggestedSemester": null, "offeredInSeason": "to_be_announced", "examType": "written_exam", "heldInLanguage": "de", "reviserName": "Prof. Dr.-Ing. Sina Mostafawy", "reviserEmail": "sina.mostafawy@hs-duesseldorf.de", "studyProgramId": 10, "source_type": "json"}}
{"id": "BTB__BTB_W30", "text": "Title: Medial Productions\nModule Number: BTB W30\nCredits: 5.0 CP\nSemester: None\nOffered In: to_be_announced\nLanguage: de\nExam Type: project\nInstructor: Prof. Dr. rer. nat. Christian Geiger (geiger@hs-duesseldorf.de)\n--- Goals (EN) ---\nThe participants learn the procedures in the conception, design, development, construction and operation of media staging. Conceptual, design, technical and economic aspects are considered in equal parts. By critically discussing current or historically significant examples, participants can assess media staging and reflect critically on their work from different perspectives. The participants have practical experience in the pre-visualization and final implementation of simple installation concepts based on selected marketable or freely available tools.\n--- Goals (DE) ---\nDie Teilnehmer lernen die Vorgehensweisen bei der Konzeption, Gestaltung, Entwicklung, Aufbau und Betrieb medialer Inszenierungen. Dabei werden konzeptionelle, gestalterische, technische und wirtschaftliche Aspekte zu gleichen Teilen betrachtet. Durch die kritische Diskussion aktueller bzw. historisch bedeutsamer Beispiele können die Teilnehmer mediale Inszenierungen beurteilen und den Einsatz aus verschiedenen Blickwinkeln kritisch reflektieren. Die Teilnehmer besitzen praktische Erfahrung in der Prävisualisierung und finalen Umsetzung einfacher Installationskonzepte auf Basis ausgewählter marktgängiger bzw. frei verfügbarer Werkzeuge.\n--- Contents (EN) ---\n- Theoretical foundations of media staging (perception, artistic expression, media architectures)\n- Analysis of historically relevant examplesTransmedia spaces, video art and performances\n- Selected forms of media staging, \n- Attempt at typification\n- Selected technical aspects of digital and physical object and space design (projection mapping, multi-displays, VR/AR)\n-Tools for media productions\n-Workflow planning and operation of extensive installations\n- Audience development and user feedback\n- Critical reflection and impact from multiple perspectives (artistic, technical, economic, social)\n--- Contents (DE) ---\nTheoretische Grundlagen medialer Inszenierung (Wahrnehmung, künstlerischer Ausdruck, mediale Architekturen)\n- Analyse historisch relevanter BeispieleTransmediale Räume, Videokunst und Performances\n- Ausgewählte Formen medialer Inszenierung, \n- Versuch einer Typisierung\n- Ausgewählte technische Aspekte des digitale und physischen Objekt- und Raumdesigns (Projection Mapping, Multi-Displays, VR/AR)\n-Werkzeuge für mediale Inszenierungen\n-WorkflowPlanung und Betrieb umfangreicher Installationen\n- Audience Development und Nutzerfeedback\n- Kritische Reflektion und Impact aus multiplen Perspektiven (künstlerisch, technisch, wirtschaftlich, sozial)\n--- Literature (EN) ---\n--- Literature (DE) ---\n- Claire Bishop: Installation Art, Tate Publishing (2005)\n- New Installation Art, Ginko Press (2013)\n- The Complete Book of Mixed Media Art, Walter Foster Creative Team, 2018\n- Aktuelle Ausstellungskataloge erfolgreicher Inszenierungen", "metadata": {"moduleNumber": "BTB W30", "moduleName": "Medial Productions", "creditPoints": "5.0", "suggestedSemester": null, "offeredInSeason": "to_be_announced", "examType": "project", "heldInLanguage": "de", "reviserName": "Prof. Dr. rer. nat. Christian Geiger", "reviserEmail": "geiger@hs-duesseldorf.de", "studyProgramId": 10, "source_type": "json"}}
{"id": "BTB__BTB_W31", "text": "Title: Mixed Reality Art\nModule Number: BTB W31\nCredits: 5.0 CP\nSemester: None\nOffered In: to_be_announced\nLanguage: de\nExam Type: project\nInstructor: Prof. Dr. rer. nat. Christian Geiger (geiger@hs-duesseldorf.de)\n--- Goals (EN) ---\nParticipants will be given an overview of current works on mixed reality art.\nBased on a discussion of the concept of art, they will learn the procedures for the conception, design, development, construction and operation of mixed reality art projects,\ndesign, development, construction and operation of mixed reality art projects. Conceptual, creative, technical and economic aspects are considered in equal measure. Through\nthe critical discussion of current and historically significant examples\nexamples, participants will be able to assess this art form from a technical and conceptual perspective and critically reflect on its use from different angles.The participants have practical experience in pre-visualization and final implementation of simple installation concepts on the basis of selected marketable or freely available tools.\n--- Goals (DE) ---\nDie Teilnehmer erhalten einen Überblick aktueller Arbeiten zu Mixed Reality Art.\nAusgehend von einer Diskussion des Kunstbegriffs lernen sie die Vorgehensweisen bei der Konzeption,\nGestaltung, Entwicklung, Aufbau und Betrieb von Mixed Reality Art Projekten. Dabei werden konzeptionelle, gestalterische, technische und wirtschaftliche Aspekte zu gleichen Teilen betrachtet. Durch\ndie kritische Diskussion aktueller bzw. historisch bedeutsamer\nBeispiele können die Teilnehmer diese Kunstform aus technisch-konzeptioneller Sicht beurteilen und den Einsatz aus verschiedenen Blickwinkeln kritisch\nreflektieren. Die Teilnehmer besitzen praktische Erfahrung in der\nPrävisualisierung und finalen Umsetzung einfacher Installationskonzepte auf Basis ausgewählter marktgängiger bzw. frei verfügbarer Werkzeuge.\n--- Contents (EN) ---\nBasic concepts of mixed reality art (definition, artistic expression, XR technologies, experience)\n- Analysis of historically relevant examples and established artists\n- Critical reflection on selected examples\n- Selected technical aspects of digital and physical object and spatial design, (projection mapping,\n VR/AR, Generative AI)\n- Tools for mixed reality art\n- Workflow, planning and operation of extensive installations\n- Excursion and invited lectures by artists, curators and media experts\n- Seminar phase and project phase\n--- Contents (DE) ---\n- Grundlegende Begriffe Mixed Reality Art (Definition, künstlerischer Ausdruck,  XR-Technologien, Experience)\n- Analyse historisch relevanter Beispiele und etablierter Künstler:innen\n- Kritische Reflektion ausgewählter Beispiele\n- Ausgewählte technische Aspekte des digitale und physischen Objekt- und Raumdesigns (Projection Mapping,\n VR/AR, Generative KI)\n- Werkzeuge für Mixed Reality Art\n- Workflow, Planung und Betrieb umfangreicher Installationen\n- Exkursion und eingeladene Vorträge von Künstler:innen, Kurator:innen und Medienexperten\n- Seminarphase und Projektphase\n--- Literature (EN) ---\nVladimir Geroimenko: Augmented Reality Art: From an Emerging Technology to a Novel Creative Medium (3rd Ed), 2022\n--- Literature (DE) ---\nVladimir Geroimenko: Augmented Reality Art: From an Emerging Technology to a Novel Creative Medium (3rd Ed), 2022", "metadata": {"moduleNumber": "BTB W31", "moduleName": "Mixed Reality Art", "creditPoints": "5.0", "suggestedSemester": null, "offeredInSeason": "to_be_announced", "examType": "project", "heldInLanguage": "de", "reviserName": "Prof. Dr. rer. nat. Christian Geiger", "reviserEmail": "geiger@hs-duesseldorf.de", "studyProgramId": 10, "source_type": "json"}}
{"id": "BTB__BTB_40", "text": "Title: Signal Processing\nModule Number: BTB 40\nCredits: 5.0 CP\nSemester: None\nOffered In: winter_semester\nLanguage: de\nExam Type: written_exam\nInstructor: Prof. Dr.-Ing. Stefanie Dederichs (stefanie.dederichs@hs-duesseldorf.de)\n--- Goals (EN) ---\nStudents are able to apply appropriate transformations on signals and have basic knowledge of analysing signals in the frequency domain.\n--- Goals (DE) ---\nStudierende wenden geeignete Transformationen auf kontinuierliche und diskrete Zeitsignale an und erkennen wesentliche Merkmale im Frequenzbereich. Das Abtasttheorem wird in jedem Zusammenhang sicher beherrscht.\n--- Contents (EN) ---\nThe modul focuses on continuous and discrete time signals and thus on digital signal processing. The basics include sampling with respect to the Nyquist-Shannon-Theorem and properties of signals and systems, in particular linear and time-invariant systems, so-called LTI systems. The transformation to the frequency domain contains the continuous and discrete Fourier-Transformation, the Laplace-Transformationand the Z-Transformation.\n--- Contents (DE) ---\nElementare Grundlagen zeitdiskreter und zeitkontinuierlicher Signale sowie die Abtastung unter Berücksichtigung des Nyquist-Shannon-Theorem sind Gegenstand der Lehre. Die Grundlagen beinhalten Eigenschaften von Signalen und Systemen, insbesondere lineare und zeitinvariante Systeme, sogenannte LTI-Systeme, Fourier-Transformation zeitdiskreter und zeitkontinuierlicher Signale, Laplace-Transformation, Z-Transformation.\n--- Literature (EN) ---\nOppenheim, Willsky: Signals and Systems; \nMartin Werner: Nachrichtentechnik;\nMartin Meyer: Signalverarbeitung - Analoge und digitale Signale, Systeme und Filter;\nB. Boulet: Fundamentals of Signals and Systems;\nK. Kammeyer, K. Kroschel: Digitale Signalverarbeitung; etc.\n--- Literature (DE) ---\nOppenheim, Willsky: Signals and Systems; \nMartin Werner: Nachrichtentechnik;\nMartin Meyer: Signalverarbeitung - Analoge und digitale Signale, Systeme und Filter;\nB. Boulet: Fundamentals of Signals and Systems;\nK. Kammeyer, K. Kroschel: Digitale Signalverarbeitung; u.v.m.", "metadata": {"moduleNumber": "BTB 40", "moduleName": "Signal Processing", "creditPoints": "5.0", "suggestedSemester": null, "offeredInSeason": "winter_semester", "examType": "written_exam", "heldInLanguage": "de", "reviserName": "Prof. Dr.-Ing. Stefanie Dederichs", "reviserEmail": "stefanie.dederichs@hs-duesseldorf.de", "studyProgramId": 10, "source_type": "json"}}
{"id": "BTB__BTB_42_2", "text": "Title: Informatics for Engineers 2\nModule Number: BTB 42_2\nCredits: 5.0 CP\nSemester: 4\nOffered In: summer_semester\nLanguage: de\nExam Type: written_exam\nInstructor: None Helmut Hiller (helmut.hiller@hs-duesseldorf.de)\n--- Goals (EN) ---\nAfter successfully completing the module, students will be able to:\n- confidently apply object-oriented concepts such as classes, objects, inheritance, and interfaces\n- design, implement, and test simple applications in Java\n- implement state-based logic\n- design and develop graphical user interfaces (GUIs)\n- understand, select, and implement fundamental algorithms and data structures at an advanced level\n- demonstrate an overview of using version control tools (e.g., Git) in both team and individual projects\n- plan, structure, and organize small software projects in a team environment\n- integrate software testing into the development process to ensure software quality\n--- Goals (DE) ---\nNach erfolgreichem Abschluss des Moduls sind die Studierenden in der Lage:\n-\tobjektorientierte Konzepte wie Klassen, Objekte, Vererbung und Interfaces sicher anzuwenden\n-\teinfache Anwendungen in Java zu entwerfen, zu implementieren und zu testen\n-\tzustandsbasierte Logik umzusetzen\n-\tgrafische Benutzeroberflächen (GUIs) zu gestalten und umzusetzen\n-\tgrundlegende Algorithmen und Datenstrukturen vertiefend zu verstehen, auszuwählen und zu implementieren\n-\tÜberblick zur Nutzung von Werkzeugen zur Versionskontrolle (Git) in Team- und Einzelprojekten\n-\teinfache Softwareprojekte zu planen, zu strukturieren und im Team zu organisieren\n-\tSoftwaretests in den Entwicklungsprozess zu integrieren (Qualität von Software sichern)\n--- Contents (EN) ---\nThis module builds on the foundations of software development, with a focus on object-oriented programming and software development processes. It covers the principles of object-oriented and state-based programming using the Java programming language, including classes, objects, methods, inheritance, and interfaces. Additional topics include the development of graphical user interfaces (GUIs), software testing, and the design and implementation of small applications. Furthermore, important algorithms and data structures are explored in greater depth and applied. The module also introduces students to the organization and management of software projects, including the practical use of version control systems with Git.\n--- Contents (DE) ---\nDas Modul vertieft die Grundlagen der Softwareentwicklung mit Fokus auf objektorientierte Programmierung und Softwareentwicklungsprozessen. Behandelt werden Konzepte der objektorientierten und zustandsbasierten Programmierung anhand der Programmiersprache Java: Klassen, Objekte, Methoden, Vererbung und Interfaces. Weitere Inhalte sind die Entwicklung grafischer Benutzeroberflächen (GUIs), Testen von Software sowie der Entwurf und die Umsetzung kleiner Anwendungen. Darüber hinaus werden wichtige Algorithmen und Datenstrukturen weiterführend betrachtet und angewendet.  Ergänzend wird in die Organisation und das Management von Softwareprojekten eingeführt unter praktischer Nutzung der Versionsverwaltung mit Git.\n--- Literature (EN) ---\n- Sommerville, Ian. 2020. Modernes Software-Engineering: Entwurf und Entwicklung von Softwareprodukten. Studium IT. München: Pearson Deutschland.\n- Abts, Dietmar. 2024. Grundkurs JAVA: Von den Grundlagen bis zu Datenbank- und Netzanwendungen. Wiesbaden: Springer Fachmedien.\n- Kopec, David. 2021. Algorithmen in Java: 32 Klassiker vom Rucksackproblem bis zu Neuronalen Netzen. 1. Auflage. Bonn: Rheinwerk Verlag.\n- Ullenboom, Christian. 2024. Java ist auch eine Insel: Einführung, Ausbildung, Praxis. 17., aktualisierte und überarbeitete Auflage. Bonn: Rheinwerk Computing.\n--- Literature (DE) ---\n- Sommerville, Ian. 2020. Modernes Software-Engineering: Entwurf und Entwicklung von Softwareprodukten. Studium IT. München: Pearson Deutschland.\n- Abts, Dietmar. 2024. Grundkurs JAVA: Von den Grundlagen bis zu Datenbank- und Netzanwendungen. Wiesbaden: Springer Fachmedien.\n- Kopec, David. 2021. Algorithmen in Java: 32 Klassiker vom Rucksackproblem bis zu Neuronalen Netzen. 1. Auflage. Bonn: Rheinwerk Verlag.\n- Ullenboom, Christian. 2024. Java ist auch eine Insel: Einführung, Ausbildung, Praxis. 17., aktualisierte und überarbeitete Auflage. Bonn: Rheinwerk Computing.", "metadata": {"moduleNumber": "BTB 42_2", "moduleName": "Informatics for Engineers 2", "creditPoints": "5.0", "suggestedSemester": 4, "offeredInSeason": "summer_semester", "examType": "written_exam", "heldInLanguage": "de", "reviserName": "None Helmut Hiller", "reviserEmail": "helmut.hiller@hs-duesseldorf.de", "studyProgramId": 10, "source_type": "json"}}
{"id": "BTB__BTB_80_2", "text": "Title: Bachelor's Thesis\nModule Number: BTB 80_2\nCredits: 12.0 CP\nSemester: 8\nOffered In: every_semester\nLanguage: en_on_demand\nExam Type: none\nInstructor: Prof. Dr. Eng. Univ. of Tsukuba Jens Herder (jens.herder@hs-duesseldorf.de)\n--- Goals (EN) ---\nCompetence for the independent solution of complex tasks from the subject area of the study program\n--- Goals (DE) ---\nKompetenz zur selbständigen Lösung komplexer Aufgaben aus dem fachlichen Gebiet des Studiengangs\n--- Contents (EN) ---\nThe bachelor thesis should show that the candidate is capable of solving a theoretical or practical task in the subject area of the study program independently within a specified period of time and writing it down.\n--- Contents (DE) ---\nDie Bachelorarbeit soll zeigen, dass die Kandidatin / der Kandidat in der Lage ist, innerhalb einer vorgegebenen Frist eine theoretische oder praktische Aufgabe aus dem Fachgebiet des Studiengangs selbständig zu lösen und schriftlich niederzulegen.\n--- Literature (EN) ---\n--- Literature (DE) ---\nLiteratur / Quellen sind je nach Aufgabenstellung verschieden und werden durch den jeweiligen Betreuer / die jeweilige Betreuerin bekannt gegeben.", "metadata": {"moduleNumber": "BTB 80_2", "moduleName": "Bachelor's Thesis", "creditPoints": "12.0", "suggestedSemester": 8, "offeredInSeason": "every_semester", "examType": "none", "heldInLanguage": "en_on_demand", "reviserName": "Prof. Dr. Eng. Univ. of Tsukuba Jens Herder", "reviserEmail": "jens.herder@hs-duesseldorf.de", "studyProgramId": 10, "source_type": "json"}}
{"id": "BTB__BTB_80_1", "text": "Title: Colloquium\nModule Number: BTB 80_1\nCredits: 3.0 CP\nSemester: 8\nOffered In: every_semester\nLanguage: en_on_demand\nExam Type: none\nInstructor: Prof. Dr.-Ing. Thomas Bonse (thomas.bonse@hs-duesseldorf.de)\n--- Goals (EN) ---\nThe purpose of the colloquium is to determine whether the candidate is able to present and explain the results of the Bachelor Thesis, their subject matter, their interdisciplinary contexts and their extra-curricular interests, and to assess their significance for the practice.\n--- Goals (DE) ---\nDas Kolloquium dient der Feststellung, ob die Kandidatin / der Kandidat befähigt ist, die Ergebnisse der Bachelor-Abschlussarbeit, ihre fachlichen Grundlagen, ihre fächerübergreifenden Zusammenhänge und ihre außerfachlichen Bezüge mündlich darzustellen und selbstständig zu begründen und ihre Bedeutung für die Praxis einzuschätzen.\n--- Contents (EN) ---\nThe colloquium consists of a presentation as a summary of the completed bachelor thesis and a related expert discussion.\n--- Contents (DE) ---\nDas Kolloquium besteht aus einer Präsentation als Zusammenfassung der bestandenen Bachelorarbeit und einem dazugehörigen Fachgespräch.\n--- Literature (EN) ---\n--- Literature (DE) ---\nLiteratur / Quellen sind je nach Aufgabenstellung verschieden und werden durch den jeweiligen Betreuer / die jeweilige Betreuerin bekannt gegeben.", "metadata": {"moduleNumber": "BTB 80_1", "moduleName": "Colloquium", "creditPoints": "3.0", "suggestedSemester": 8, "offeredInSeason": "every_semester", "examType": "none", "heldInLanguage": "en_on_demand", "reviserName": "Prof. Dr.-Ing. Thomas Bonse", "reviserEmail": "thomas.bonse@hs-duesseldorf.de", "studyProgramId": 10, "source_type": "json"}}
{"id": "BTB__BTB_W36", "text": "Title: Project extension\nModule Number: BTB W36\nCredits: 5.0 CP\nSemester: None\nOffered In: to_be_announced\nLanguage: de\nExam Type: project\nInstructor: Prof. Dr.-Ing. Jochen Steffens (jochen.steffens@hs-duesseldorf.de)\n--- Goals (EN) ---\n--- Goals (DE) ---\n--- Contents (EN) ---\nExtension of project A or B with further supplementary and/or in-depth content, dependent on project\n--- Contents (DE) ---\nErweiterung des Projekt A oder B um weitere ergänzende und/oder vertiefende Inhalte, abhängig vom Projekt\n--- Literature (EN) ---\n--- Literature (DE) ---", "metadata": {"moduleNumber": "BTB W36", "moduleName": "Project extension", "creditPoints": "5.0", "suggestedSemester": null, "offeredInSeason": "to_be_announced", "examType": "project", "heldInLanguage": "de", "reviserName": "Prof. Dr.-Ing. Jochen Steffens", "reviserEmail": "jochen.steffens@hs-duesseldorf.de", "studyProgramId": 10, "source_type": "json"}}
{"id": "BTB__BTB_W34", "text": "Title: Project A\nModule Number: BTB W34\nCredits: 5.0 CP\nSemester: None\nOffered In: every_semester\nLanguage: de\nExam Type: project\nInstructor: Prof. Dr.-Ing. Jochen Steffens (jochen.steffens@hs-duesseldorf.de)\n--- Goals (EN) ---\nProject A provides students with specialist skills in audio and video technology and prepares them specifically for professional practice. By working on an industry-related project, students acquire skills in solving industrial problems using technical/scientific methods. In addition, they learn procedures for professional teamwork and project work in conjunction with presentation techniques.\n--- Goals (DE) ---\nDurch das Projekt A erhalten die Studierenden Fachkompetenzen der Ton- und Bildtechnik und werden gezielt auf die berufliche Praxis vorbereitet. Die Studierenden erlangen durch Arbeit an einem in­dustrienahen Projekt Kompetenzen bei der Lösung industrieller Problemstellungen mit fachlichen/wissenschaftlichen Methoden. Darüber hinaus werden Prozeduren beruflicher Teamarbeit und Projektarbeit in Verbindung mit Präsentationstechniken erlernt.\n--- Contents (EN) ---\nIn Project A, students work in a team to solve a complex task. From the initial idea to conception and realisation, they go through all the steps of a typical sound and image project. In order to optimally prepare students for future work situations, particular emphasis is placed on the organisation of team processes. The content of the project is based on the media-related lectures of the degree programme, such as acoustics, recording studio technology, image and video technology, multimedia authoring and vibration technology.  In addition, partial aspects of media design can also be covered.\n--- Contents (DE) ---\nIm Projekt A arbeiten die Studierenden im Team an der Lösung einer komplexen Aufgabenstellung. Von der ersten Idee über die Konzeption bis hin zur Um­setzung werden alle Schritte eines typischen Ton- und Bildprojektes durchlaufen. Um die Studierenden optimal auf zukünftige Arbeitssituationen vorzubereiten, wird insbe­sondere auf die Ausgestaltung von Teamprozessen Wert gelegt. Inhaltlich orientiert sich das Projekt an den mediennahen Vorlesungen des Studiengangs, wie z. B. Akustik, Tonstudiotechnik, Bild- und Videotechnik, Multimedia-Authoring, Schwingungstechnik. Darüber hinaus können auch Teilaspekte der Mediengestaltung behandelt werden.\n--- Literature (EN) ---\n--- Literature (DE) ---", "metadata": {"moduleNumber": "BTB W34", "moduleName": "Project A", "creditPoints": "5.0", "suggestedSemester": null, "offeredInSeason": "every_semester", "examType": "project", "heldInLanguage": "de", "reviserName": "Prof. Dr.-Ing. Jochen Steffens", "reviserEmail": "jochen.steffens@hs-duesseldorf.de", "studyProgramId": 10, "source_type": "json"}}
{"id": "BTB__BTB_W35", "text": "Title: Project B\nModule Number: BTB W35\nCredits: 5.0 CP\nSemester: None\nOffered In: every_semester\nLanguage: de\nExam Type: project\nInstructor: Prof. Dr.-Ing. Jochen Steffens (jochen.steffens@hs-duesseldorf.de)\n--- Goals (EN) ---\nProject B provides students with specialist skills in sound and image technology and prepares them specifically for professional practice. By working on an industry-related project, students acquire skills in solving industrial problems using technical/scientific methods.\n--- Goals (DE) ---\nDurch das Projekt B erhalten die Studierenden Fachkompetenzen der Ton- und Bildtechnik und werden gezielt auf die berufliche Praxis vorbereitet. Die Studierenden erlangen durch Arbeit an einem in­dustrienahen Projekt Kompetenzen bei der Lösung industrieller Problemstellungen mit fachlichen/wissenschaftlichen Methoden. Darüber hinaus werden Prozeduren beruflicher Teamarbeit und Projektarbeit in Verbindung mit Präsentationstechniken erlernt.\n--- Contents (EN) ---\nIn Project B, students work in a team to solve a complex task. From the initial idea to conception and realisation, they go through all the steps of a typical sound and image project. In order to optimally prepare students for future work situations, particular emphasis is placed on the organisation of team processes. The content of the project is based on the media-related lectures of the degree programme, such as acoustics, recording studio technology, image and video technology, multimedia authoring and vibration technology.  In addition, partial aspects of media design can also be covered.\n--- Contents (DE) ---\nIm Projekt B arbeiten die Studierenden im Team an der Lösung einer komplexen Aufgabenstellung. Von der ersten Idee über die Konzeption bis hin zur Um­setzung werden alle Schritte eines typischen Ton- und Bildprojektes durchlaufen. Um die Studierenden optimal auf zukünftige Arbeitssituationen vorzubereiten, wird insbe­sondere auf die Ausgestaltung von Teamprozessen Wert gelegt. Inhaltlich orientiert sich das Projekt an den mediennahen Vorlesungen des Studiengangs, wie z. B. Akustik, Tonstudiotechnik, Bild- und Videotechnik, Multimedia-Authoring, Schwingungstechnik.  Darüber hinaus können auch Teilaspekte der Mediengestaltung behandelt werden.\n--- Literature (EN) ---\n--- Literature (DE) ---", "metadata": {"moduleNumber": "BTB W35", "moduleName": "Project B", "creditPoints": "5.0", "suggestedSemester": null, "offeredInSeason": "every_semester", "examType": "project", "heldInLanguage": "de", "reviserName": "Prof. Dr.-Ing. Jochen Steffens", "reviserEmail": "jochen.steffens@hs-duesseldorf.de", "studyProgramId": 10, "source_type": "json"}}
