{"id": "MMI01", "text": "Title: Advanced Software Engineering\nModule Number: MMI 01\nCredits: 5.0 CP\nSemester: 2\nOffered In: summer_semester\nLanguage: de\nExam Type: written_exam\nInstructor: Prof. Dr. Thomas Franz (thomas.franz@hs-duesseldorf.de)\n--- Goals (EN) ---\nThe students know essential advanced methods, procedures and techniques of software engineering. They can distinguish, evaluate, select and apply them in a software development process.\n--- Goals (DE) ---\nDie Studierenden kennen wichtige fortgeschrittene Methoden, Vorgehensweisen und Techniken des Software Engineering. Sie können diese einordnen, bewerten und in einem Software-Entwicklungsprozess auswählen und einsetzen.\n--- Contents (EN) ---\nSelected advanced methods, procedures and techniques of software engineering, e.g. Impact Mapping und Domain Storytelling for Requirements Engineering, Domain-Driven Design for Software Architectures, Clean Code for Software Development, scaled agile Methodologies, Cloud-Native Infrastructure.\n--- Contents (DE) ---\nAusgewählte fortgeschrittene Methoden, Vorgehensweisen und Techniken des Software Engineerings, z.B. Impact Mapping und Domain Storytelling für das Requirements Engineering, Domain-Driven Design für Software Architekturen, Clean Code Prinzipien der Softwareentwicklung, agile Vorgehensweisen und deren Skalierung, Cloud-Native Infrastrukturen.\n--- Literature (EN) ---\nS. Hofer, H. Schwentner: Domain Storytelling: Gemeinschaftlich, visuell und agil zu fachlich wertvoller Software, dpunkt.verlag, 2023\nE. Evans: Domain driven design: tackling complexity in the heart of software, Addison-Wesley, 2011\nR. C. Martin: Clean Code - Refactoring, Patterns, Testen und Techniken für sauberen Code, mitp (2009)\nC. Mathis: SAFe  Das Scaled Agile Framework: Lean und Agile in großen Unternehmen skalieren, dpunkt.verlag, 2017\nC. Surianarayanan, P. R. Chelliah: Essentials of Cloud Computing: A Holistic, Cloud-Native Perspective, Springer, 2023\n\nAdditionally, selected articles for specific topics.\n--- Literature (DE) ---\nS. Hofer, H. Schwentner: Domain Storytelling: Gemeinschaftlich, visuell und agil zu fachlich wertvoller Software, dpunkt.verlag, 2023\nE. Evans: Domain driven design: tackling complexity in the heart of software, Addison-Wesley, 2011\nR. C. Martin: Clean Code - Refactoring, Patterns, Testen und Techniken für sauberen Code, mitp (2009)\nC. Mathis: SAFe  Das Scaled Agile Framework: Lean und Agile in großen Unternehmen skalieren, dpunkt.verlag, 2017\nC. Surianarayanan, P. R. Chelliah: Essentials of Cloud Computing: A Holistic, Cloud-Native Perspective, Springer, 2023\n\nAusgewählte Artikel und Fachliteratur zu den jeweiligen Themen\n\nMMI 01 - Advanced Software Engineering\nAdvanced Software Engineering\nModulbeauftragte*r\nResponsible\nThomas Franz\nDozent*in\nTeaching staff\nLehrende*r der Hochschule Düsseldorf\nStudiengang\nM.Sc. Medieninformatik 2025\nVerwendung in anderen\nStudiengängen: / Used in other\nstudy programmes\nM.Sc. Medieninformatik, PO 2018 /\nM.Sc. Media Informatics, PO 2018\n\n\nLehrformen (alle Angaben in SWS zu je 45 Minuten / all values in SWS of 45 minutes each)\n\nCredits/\nCredits\nWorkload /\nWorkload\nKontaktzeit/\nContact time\nSelbststudium/\nSelf study\nDauer/\nLength\nSemester/\nSemester\nSprache/\nLanguage\n5\n150 h\n\n60 h\n90 h\n1 Sem.\n2\nDeutsch\nVorlesung/\nLecture\nÜbung/\nPractice\nSeminar/\nSeminar\nPraktiku\nm/ Lab\nwork\nProjekt/\nProject\nTutorium/\nTutorial\nSeminarist.\nUnterricht/\nSeminaristic\nlesson\nStudien\narbeit/\nResearch\nproject\nBegleitetes\nSelbstlernen/\nAccompan‘d\nself study\n2\n1\n1\n\n\n\n\n\n\nModulkategorie / category\n\nPflichtmodul / Compulsory module\nWahlkatalog(e) /\n\n/\nelective catalogue(s)\n\n\nVoraussetzungen zur Teilnahme /\nrequirements for participation\n\n\nFormal /\nFormal\n\nKeine /\nnone\n\nInhaltlich /\ncontentwise\n\nKeine /\nnone\nVoraussetzungen zur Prüfung /\nprerequisites for the\nexamination\n\nKeine / None\nPrüfungsform /\nform of examination\n\nKlausurarbeit /\nWritten examination\nBenotet, Stellenwert der Note\nfür die Endnote /\ngraded, value of the grade for\nthe final grade\n\nBenotet: Ja / Is graded: Yes\n\n5/90 bzw. 5/120 / 5/90 resp. 5/120\nVoraussetzungen zur\nCreditvergabe/ requirements for\nawarding credit:\n\nBestandene Modulprüfung / Passed module examination\n\nLernergebnisse, Kompetenzen:\n\n\nDie Studierenden kennen wichtige fortgeschrittene Methoden,\nVorgehensweisen und Techniken des Software Engineering. Sie\nkönnen diese einordnen, bewerten und in einem Software-\nEntwicklungsprozess auswählen und einsetzen.\n\nLehrinhalte:\n\n\nAusgewählte fortgeschrittene Methoden, Vorgehensweisen und\nTechniken des Software Engineerings, z.B. Impact Mapping und\n\nHochschule Düsseldorf\nModulhandbuch M.Sc. Medieninformatik\nVersion 1.0\nPO 2025\n9\n\n\nEnglish descriptions\n\nDomain Storytelling für das Requirements Engineering, Domain-\nDriven Design für Software Architekturen, Clean Code Prinzipien\nder Softwareentwicklung, agile Vorgehensweisen und deren\nSkalierung, Cloud-Native Infrastrukturen.\n\nLiteratur:\n\n\nS. Hofer, H. Schwentner: Domain Storytelling: Gemeinschaftlich,\nvisuell und agil zu fachlich wertvoller Software, dpunkt.verlag,\n2023\nE. Evans: Domain driven design: tackling complexity in the heart\nof software, Addison-Wesley, 2011\nR. C. Martin: Clean Code - Refactoring, Patterns, Testen und\nTechniken für sauberen Code, mitp (2009)\nC. Mathis: SAFe  Das Scaled Agile Framework: Lean und Agile in\ngroßen Unternehmen skalieren, dpunkt.verlag, 2017\nC. Surianarayanan, P. R. Chelliah: Essentials of Cloud\nComputing: A Holistic, Cloud-Native Perspective, Springer, 2023\n\nAusgewählte Artikel und Fachliteratur zu den jeweiligen Themen\n\nLearning outcomes,\ncompetences\n\n\nThe students know essential advanced methods, procedures\nand techniques of software engineering. They can distinguish,\nevaluate, select and apply them in a software development\nprocess.\n\nContent\n\n\nSelected advanced methods, procedures and techniques of\nsoftware engineering, e.g. Impact Mapping und Domain\nStorytelling for Requirements Engineering, Domain-Driven\nDesign for Software Architectures, Clean Code for Software\nDevelopment, scaled agile Methodologies, Cloud-Native\nInfrastructure.\n\nHochschule Düsseldorf\nModulhandbuch M.Sc. Medieninformatik\nVersion 1.0\nPO 2025\n10", "metadata": {"moduleNumber": "MMI 01", "moduleName": "Advanced Software Engineering", "creditPoints": "5.0", "suggestedSemester": 2, "offeredInSeason": "summer_semester", "examType": "written_exam", "heldInLanguage": "de", "reviserName": "Prof. Dr. Thomas Franz", "reviserEmail": "thomas.franz@hs-duesseldorf.de", "studyProgramId": 11, "source_type": "json", "moduleNameDe": "Advanced Software Engineering", "source_file": "MMI_MHB_PO2025_V1.0.pdf", "pdf_page_start": 8, "pdf_page_end": 9, "studyProgramAbbrev": "MMI", "studyProgram_Url": "https://medien.hs-duesseldorf.de/mmi", "pdf_url": "https://medien.hs-duesseldorf.de/studium/studiengaenge/Documents/Modulhandb%C3%BCcher/MMI_MHB_PO2025_V1.0.pdf"}}
{"id": "MMI02", "text": "Title: Computational Thinking\nModule Number: MMI 02\nCredits: 5.0 CP\nSemester: 1\nOffered In: winter_semester\nLanguage: de\nExam Type: written_exam\nInstructor: Prof. Dr. rer. nat. Christian Geiger (geiger@hs-duesseldorf.de)\n--- Goals (EN) ---\nStudents know and understand the various automata models and formal languages as well as the essential properties of formal systems. Students know and understand calculation models and complexity measures suitable for these models. They understand the problem of algorithmic solvability/non-solvability of problems. Students are able to independently analyze problems and estimate complexity and are familiar with the basic relationships between computability, decidability and complexity. They know the typical proof methods of mathematics and can apply these to simple problems in computer science. They have gained an insight into problem solving (puzzle-based problem solving) and can develop solutions for new problems using suitable strategies.\n--- Goals (DE) ---\nDie Studierenden kennen und verstehen die verschiedenen Automatenmodelle und formale Sprachen sowie wesentliche Eigenschaften formaler Systeme. Die Studierenden kennen und verstehen Berechnungsmodelle und zu diesen Modellen passende Komplexitätsmaße. Sie verstehen die Problematik der algorithmischen Lösbarkeit/Nichtlösbarkeit von Problemen. Die Studierenden sind in der Lage, eigenständig Probleme zu analysieren und Komplexitätsabschätzungen vorzunehmen und beherrschen die grundlegenden Zusammenhänge zwichen Berechenbarkeit, Entscheidbarkeit und Komplexität. Sie kennen die typischen Beweisverfahren der Mathematik und können diese auf einfache Probleme der Informatik anwenden. Sie haben einen Einblick in das Problemlösen erhalten (Puzzle Based Problem Solving) und können durch geeignete Strategien Lösungen für neue Probleme entwickeln.\n--- Contents (EN) ---\nPuzzle-Based Problem Solving (PBPS) and mathematical thinking: \nPBPS as an exploratory approach to strategic problem solving\nStrategies and rules of PBPS\nWorkshop on various techniques and strategies for problem solving\nProof methods in computer science (direct, indirect, induction)\n\nFinite automata: Selected properties from\n- Equivalence to regular expressions and regular languages\n- Pumping lemma\n- Algorithms on automata (minimization, transformation of non-deterministic automata)\n\nContext-free and context-sensitive languages: Selected properties from\n- Pumping lemma\n- Conclusion properties and operational models (PDA, LBA)\n- Normalization of CFG (Chomsky normal form)\n- Algorithms on CFG (CYK, etc)\n\nTuring machines: Selected properties from\n- Formal description of Turing machines\n- Examples of Turing programs\n- Variants: Single-band TM, multi-band TM, multi-head TM\n- Chomsky hierarchy\n\nComplexity, computability, decidability\n- Computability models and complexity classes\n- Non-computable or undecidable problems\n- NP-completeness, P =NP hypothesis and reduction of problems\n--- Contents (DE) ---\nPuzzle-Based Problem Solving (PBPS) und Mathematisches Denken: \nPBPS als explorativer Ansatz zum strategischen Problemlösen\nStrategien und Regeln des PBPS\nWorkshop zu verschiedenen Techniken und Strategien der Problemlösung\nBeweisverfahren der Informatik (dirket, indirekt, Induktion)\n\nEndliche Automaten: Ausgewählte Eigenschaften aus\n-\tAquivalenz zu regulären Ausdrücke und regulären Sprachen\n-\tPumping Lemma\n-\tAlgorithmen auf Automaten (Minimierung, Umwandlung Nichtdeterministische Automaten)\n\nKontextfreie und kontextsenstive Sprachen: Ausgewählte Eigenschaften aus\n-\tPumpingLemma\n-\tAbschlusseigenschaften und operationale Modelle (PDA, LBA)\n-\tNormalisierung von CFG (Chomsky Normalform)\n-\tAlgorithmen auf CFG (CYK, etc)\n\nTuringmaschinen: Ausgewählte Eigenschaften aus\n-\tFormale Beschreibung Turingmaschine\n-\tBeispiele zu Turingprogrammen\n-\tVarianten: Einband-TM, Mehrband-TM, Mehrkopf-TM\n-\tChomsky-Hierarchie\n\nKomplexität, Berechenbarkeit, Entscheidbarkeit\n-\tBerechenbarkeitsmodelle und Komplexitätsklassen\n-\tNichtberechenbare bzw unentscheidbare Probleme\n-\tNP-Vollständigkeit, P =NP Hypothese und Reduktion von Problemen\n--- Literature (EN) ---\n--- Literature (DE) ---\nJ.E. Hopcroft, R. Motwani, und J.D. Ullman: Einführung in die Automatentheorie, formale Sprachen und Komplexitätstheorie, Pearson Studium (2011)\n\nU. Schöning: Theoretische Informatik  kurz gefasst, Spektrum Akademischer Verlag (2008)\n\nD. Hoffmann: Theoretische Informatik, Hanser Verlag, 2023\n\nZ. Michalewicz, M. Michalewicz: Puzzle-based Learning: Introduction to critical thinking, mathematics, and problem solving, Credibility CorporationPty Ltd, 2008\n\nE. F. F. Meyer, N. Falkner, R. Sooriamurthi, Z. Michalewicz. Guide to Puzzle-Based Learning, Springer 2014\n\nMMI 02 - Computational Thinking\nComputational Thinking\nModulbeauftragte*r\nResponsible\nChristian Geiger\nDozent*in\nTeaching staff\nLehrende*r der Hochschule Düsseldorf\nStudiengang\nM.Sc. Medieninformatik 2025\nVerwendung in anderen\nStudiengängen: / Used in other\nstudy programmes\nM.Sc. Medieninformatik, PO 2018 /\nM.Sc. Media Informatics, PO 2018\n\n\nLehrformen (alle Angaben in SWS zu je 45 Minuten / all values in SWS of 45 minutes each)\n\nCredits/\nCredits\nWorkload /\nWorkload\nKontaktzeit/\nContact time\nSelbststudium/\nSelf study\nDauer/\nLength\nSemester/\nSemester\nSprache/\nLanguage\n5\n150 h\n\n60 h\n90 h\n1 Sem.\n1\nDeutsch\nVorlesung/\nLecture\nÜbung/\nPractice\nSeminar/\nSeminar\nPraktiku\nm/ Lab\nwork\nProjekt/\nProject\nTutorium/\nTutorial\nSeminarist.\nUnterricht/\nSeminaristic\nlesson\nStudien\narbeit/\nResearch\nproject\nBegleitetes\nSelbstlernen/\nAccompan‘d\nself study\n2\n2\n\n\n\n\n\n\n\nModulkategorie / category\n\nPflichtmodul / Compulsory module\nWahlkatalog(e) /\n\n/\nelective catalogue(s)\n\n\nVoraussetzungen zur Teilnahme /\nrequirements for participation\n\n\nFormal /\nFormal\n\nKeine /\nnone\n\nInhaltlich /\ncontentwise\n\nKeine /\nnone\nVoraussetzungen zur Prüfung /\nprerequisites for the\nexamination\n\nKeine / None\nPrüfungsform /\nform of examination\n\nKlausurarbeit /\nWritten examination\nBenotet, Stellenwert der Note\nfür die Endnote /\ngraded, value of the grade for\nthe final grade\n\nBenotet: Ja / Is graded: Yes\n\n5/90 bzw. 5/120 / 5/90 resp. 5/120\nVoraussetzungen zur\nCreditvergabe/ requirements for\nawarding credit:\n\nBestandene Modulprüfung / Passed module examination\n\nLernergebnisse, Kompetenzen:\n\n\nDie Studierenden kennen und verstehen die verschiedenen\nAutomatenmodelle und formale Sprachen sowie wesentliche\nEigenschaften formaler Systeme. Die Studierenden kennen und\nverstehen Berechnungsmodelle und zu diesen Modellen\npassende Komplexitätsmaße. Sie verstehen die Problematik der\nalgorithmischen Lösbarkeit/Nichtlösbarkeit von Problemen. Die\nStudierenden sind in der Lage, eigenständig Probleme zu\nanalysieren und Komplexitätsabschätzungen vorzunehmen und\n\nHochschule Düsseldorf\nModulhandbuch M.Sc. Medieninformatik\nVersion 1.0\nPO 2025\n11\n\nbeherrschen die grundlegenden Zusammenhänge zwichen\nBerechenbarkeit, Entscheidbarkeit und Komplexität. Sie kennen\ndie typischen Beweisverfahren der Mathematik und können diese\nauf einfache Probleme der Informatik anwenden. Sie haben einen\nEinblick in das Problemlösen erhalten (Puzzle Based Problem\nSolving) und können durch geeignete Strategien Lösungen für\nneue Probleme entwickeln.\n\nLehrinhalte:\n\n\nPuzzle-Based Problem Solving (PBPS) und Mathematisches\nDenken:\nPBPS als explorativer Ansatz zum strategischen Problemlösen\nStrategien und Regeln des PBPS\nWorkshop zu verschiedenen Techniken und Strategien der\nProblemlösung\nBeweisverfahren der Informatik (dirket, indirekt, Induktion)\n\nEndliche Automaten: Ausgewählte Eigenschaften aus\n-\nAquivalenz zu regulären Ausdrücke und regulären\nSprachen\n-\nPumping Lemma\n-\nAlgorithmen auf Automaten (Minimierung, Umwandlung\nNichtdeterministische Automaten)\n\nKontextfreie und kontextsenstive Sprachen: Ausgewählte\nEigenschaften aus\n-\nPumpingLemma\n-\nAbschlusseigenschaften und operationale Modelle (PDA,\nLBA)\n-\nNormalisierung von CFG (Chomsky Normalform)\n-\nAlgorithmen auf CFG (CYK, etc)\n\nTuringmaschinen: Ausgewählte Eigenschaften aus\n-\nFormale Beschreibung Turingmaschine\n-\nBeispiele zu Turingprogrammen\n-\nVarianten: Einband-TM, Mehrband-TM, Mehrkopf-TM\n-\nChomsky-Hierarchie\n\nKomplexität, Berechenbarkeit, Entscheidbarkeit\n-\nBerechenbarkeitsmodelle und Komplexitätsklassen\n-\nNichtberechenbare bzw unentscheidbare Probleme\n-\nNP-Vollständigkeit, P =NP Hypothese und Reduktion von\nProblemen\n\nLiteratur:\n\n\nJ.E. Hopcroft, R. Motwani, und J.D. Ullman: Einführung in die\nAutomatentheorie, formale Sprachen und Komplexitätstheorie,\nPearson Studium (2011)\n\nU. Schöning: Theoretische Informatik  kurz gefasst, Spektrum\nAkademischer Verlag (2008)\n\nD. Hoffmann: Theoretische Informatik, Hanser Verlag, 2023\n\n\nHochschule Düsseldorf\nModulhandbuch M.Sc. Medieninformatik\nVersion 1.0\nPO 2025\n12\n\n\nEnglish descriptions\n\nZ. Michalewicz, M. Michalewicz: Puzzle-based Learning:\nIntroduction to critical thinking, mathematics, and problem solving,\nCredibility CorporationPty Ltd, 2008\n\nE. F. F. Meyer, N. Falkner, R. Sooriamurthi, Z. Michalewicz. Guide\nto Puzzle-Based Learning, Springer 2014\n\nLearning outcomes,\ncompetences\n\n\nStudents know and understand the various automata models\nand formal languages as well as the essential properties of\nformal systems. Students know and understand calculation\nmodels and complexity measures suitable for these models.\nThey understand the problem of algorithmic solvability/non-\nsolvability of problems. Students are able to independently\nanalyze problems and estimate complexity and are familiar with\nthe basic relationships between computability, decidability and\ncomplexity. They know the typical proof methods of mathematics\nand can apply these to simple problems in computer science.\nThey have gained an insight into problem solving (puzzle-based\nproblem solving) and can develop solutions for new problems\nusing suitable strategies.\n\nContent\n\n\nPuzzle-Based Problem Solving (PBPS) and mathematical\nthinking:\nPBPS as an exploratory approach to strategic problem solving\nStrategies and rules of PBPS\nWorkshop on various techniques and strategies for problem\nsolving\nProof methods in computer science (direct, indirect, induction)\n\nFinite automata: Selected properties from\n- Equivalence to regular expressions and regular languages\n- Pumping lemma\n- Algorithms on automata (minimization, transformation of non-\ndeterministic automata)\n\nContext-free and context-sensitive languages: Selected\nproperties from\n- Pumping lemma\n- Conclusion properties and operational models (PDA, LBA)\n- Normalization of CFG (Chomsky normal form)\n- Algorithms on CFG (CYK, etc)\n\nTuring machines: Selected properties from\n- Formal description of Turing machines\n- Examples of Turing programs\n- Variants: Single-band TM, multi-band TM, multi-head TM\n- Chomsky hierarchy\n\nComplexity, computability, decidability\n- Computability models and complexity classes\n- Non-computable or undecidable problems\n- NP-completeness, P =NP hypothesis and reduction of\nproblems\n\nHochschule Düsseldorf\nModulhandbuch M.Sc. Medieninformatik\nVersion 1.0\nPO 2025\n13", "metadata": {"moduleNumber": "MMI 02", "moduleName": "Computational Thinking", "creditPoints": "5.0", "suggestedSemester": 1, "offeredInSeason": "winter_semester", "examType": "written_exam", "heldInLanguage": "de", "reviserName": "Prof. Dr. rer. nat. Christian Geiger", "reviserEmail": "geiger@hs-duesseldorf.de", "studyProgramId": 11, "source_type": "json", "moduleNameDe": "Computational Thinking", "source_file": "MMI_MHB_PO2025_V1.0.pdf", "pdf_page_start": 10, "pdf_page_end": 12, "studyProgramAbbrev": "MMI", "studyProgram_Url": "https://medien.hs-duesseldorf.de/mmi", "pdf_url": "https://medien.hs-duesseldorf.de/studium/studiengaenge/Documents/Modulhandb%C3%BCcher/MMI_MHB_PO2025_V1.0.pdf"}}
{"id": "MMI03", "text": "Title: Master Project 1\nModule Number: MMI 03\nCredits: 10.0 CP\nSemester: 1\nOffered In: winter_semester\nLanguage: en_on_demand\nExam Type: project\nInstructor: Prof. Dr. Thomas Franz (thomas.franz@hs-duesseldorf.de)\n--- Goals (EN) ---\nThe students are able to work successfully on a complex application-oriented project in the field of- media informatics or, alternatively,- media engineering, event technology or media design with a focus on informatics.They can achieve results in the different project phases independently, analyse them critically and present the results.\n--- Goals (DE) ---\nTeilnehmer sind in der Lage, eine komplexe anwendungs-orientierte Aufgabenstellung aus dem Bereiche Medieninformatik bzw. Medientechnik / Veranstaltungstechnik / Mediengestaltung mit signifikanten Informatikanteilen erfolgreich zu bearbeiten und in den verschiedenen Projektphasen eigenständig Ergebnisse erzielen, diese kritisch zu analysieren und Resultate zu präsentieren.\n--- Contents (EN) ---\nThe students work alone or in teams on individual research questions within the area of media informatics or related disciplines with a focus on informatics. They discuss their progress regularly with the supervisor and present first results. The main focus is the research-oriented implementation of the concepts developed based on scientific methodology.\n--- Contents (DE) ---\nStudierende arbeiten alleine oder im Team an einer eigenständigen wissenschaftlichen Fragestellung der Medieninformatik bzw. verwandter Medienbereiche mit Informatikanteil. Der Fortschritt wird regelmäßig mit dem Betreuer besprochen und (Teil-) Ergebnisse entsprechend präsentiert. Der Schwerpunkt liegt auf der forschungsorientierten Umsetzung der entwickelten Konzepte auf Basis wissenschaftlicher Methoden.\n--- Literature (EN) ---\n--- Literature (DE) ---\nJe nach Dozent und Projektthema verschieden\n\nMMI 03 - Masterprojekt 1\nMaster Project 1\nModulbeauftragte*r\nResponsible\nThomas Franz\nDozent*in\nTeaching staff\nLehrende*r der Hochschule Düsseldorf\nStudiengang\nM.Sc. Medieninformatik 2025\nVerwendung in anderen\nStudiengängen: / Used in other\nstudy programmes\nM.Sc. Medieninformatik, PO 2018 /\nM.Sc. Media Informatics, PO 2018\n\n\nLehrformen (alle Angaben in SWS zu je 45 Minuten / all values in SWS of 45 minutes each)\n\nCredits/\nCredits\nWorkload /\nWorkload\nKontaktzeit/\nContact time\nSelbststudium/\nSelf study\nDauer/\nLength\nSemester/\nSemester\nSprache/\nLanguage\n5\n300 h\n\n120 h\n180 h\n1 Sem.\n\nEnglish on\ndemand\nVorlesung/\nLecture\nÜbung/\nPractice\nSeminar/\nSeminar\nPraktiku\nm/ Lab\nwork\nProjekt/\nProject\nTutorium/\nTutorial\nSeminarist.\nUnterricht/\nSeminaristic\nlesson\nStudien\narbeit/\nResearch\nproject\nBegleitetes\nSelbstlernen/\nAccompan‘d\nself study\n\n\n2\n\n6\n\n\n\n\nModulkategorie / category\n\nWahlpflichtmodul / Elective module\nWahlkatalog(e) /\n\n/\nelective catalogue(s)\n\n\nVoraussetzungen zur Teilnahme /\nrequirements for participation\n\n\nFormal /\nFormal\n\nKeine /\nnone\n\nInhaltlich /\ncontentwise\n\nKeine /\nnone\nVoraussetzungen zur Prüfung /\nprerequisites for the\nexamination\n\nErfolgreiche Teilnahme am Seminar und Projekt / Successful\nparticipation in seminar and project\nPrüfungsform /\nform of examination\n\nProjektprüfung /\nProject examination\nBenotet, Stellenwert der Note\nfür die Endnote /\ngraded, value of the grade for\nthe final grade\n\nBenotet: Ja / Is graded: Yes\n\n5/90 bzw. 5/120 / 5/90 resp. 5/120\nVoraussetzungen zur\nCreditvergabe/ requirements for\nawarding credit:\n\nBestandene Modulprüfung / Passed module examination\n\nLernergebnisse, Kompetenzen:\n\n\nTeilnehmer sind in der Lage, eine komplexe anwendungs-\norientierte Aufgabenstellung aus dem Bereiche Medieninformatik\nbzw. Medientechnik / Veranstaltungstechnik / Mediengestaltung\nmit signifikanten Informatikanteilen erfolgreich zu bearbeiten und\nin den verschiedenen Projektphasen eigenständig Ergebnisse\nerzielen, diese kritisch zu analysieren und Resultate zu\npräsentieren.\n\n\n\n\nHochschule Düsseldorf\nModulhandbuch M.Sc. Medieninformatik\nVersion 1.0\nPO 2025\n14\n\n\nEnglish descriptions\n\nLehrinhalte:\nStudierende arbeiten alleine oder im Team an einer\neigenständigen wissenschaftlichen Fragestellung der\nMedieninformatik bzw. verwandter Medienbereiche mit\nInformatikanteil. Der Fortschritt wird regelmäßig mit dem Betreuer\nbesprochen und (Teil-) Ergebnisse entsprechend präsentiert. Der\nSchwerpunkt liegt auf der forschungsorientierten Umsetzung der\nentwickelten Konzepte auf Basis wissenschaftlicher Methoden.\n\nLiteratur:\n\n\nJe nach Dozent und Projektthema verschieden\n\nLearning outcomes,\ncompetences\n\n\nThe students are able to work successfully on a complex\napplication-oriented project in the field of- media informatics or,\nalternatively,- media engineering, event technology or media\ndesign with a focus on informatics.They can achieve results in\nthe different project phases independently, analyse them\ncritically and present the results.\n\nContent\n\n\nThe students work alone or in teams on individual research\nquestions within the area of media informatics or related\ndisciplines with a focus on informatics. They discuss their\nprogress regularly with the supervisor and present first results.\nThe main focus is the research-oriented implementation of the\nconcepts developed based on scientific methodology.\n\nHochschule Düsseldorf\nModulhandbuch M.Sc. Medieninformatik\nVersion 1.0\nPO 2025\n15", "metadata": {"moduleNumber": "MMI 03", "moduleName": "Master Project 1", "creditPoints": "10.0", "suggestedSemester": 1, "offeredInSeason": "winter_semester", "examType": "project", "heldInLanguage": "en_on_demand", "reviserName": "Prof. Dr. Thomas Franz", "reviserEmail": "thomas.franz@hs-duesseldorf.de", "studyProgramId": 11, "source_type": "json", "moduleNameDe": "Masterprojekt 1", "source_file": "MMI_MHB_PO2025_V1.0.pdf", "pdf_page_start": 13, "pdf_page_end": 14, "studyProgramAbbrev": "MMI", "studyProgram_Url": "https://medien.hs-duesseldorf.de/mmi", "pdf_url": "https://medien.hs-duesseldorf.de/studium/studiengaenge/Documents/Modulhandb%C3%BCcher/MMI_MHB_PO2025_V1.0.pdf"}}
{"id": "MMI04", "text": "Title: Master Project 2\nModule Number: MMI 04\nCredits: 10.0 CP\nSemester: 2\nOffered In: summer_semester\nLanguage: en_on_demand\nExam Type: project\nInstructor: Prof. Dr. Thomas Franz (thomas.franz@hs-duesseldorf.de)\n--- Goals (EN) ---\nThe students are able to work successfully on a complex application-oriented project in the field ofmedia informatics or, alternatively,media engineering, event technology or media design with a focus on informatics.They can achieve results in the different project phases independently, analyse them critically and present the results.\n--- Goals (DE) ---\nTeilnehmer sind in der Lage, eine komplexe, forschungs-orientierte Aufgabenstellung aus dem Bereiche Medieninformatik bzw. Medientechnik / Veranstaltungstechnik / Mediengestaltung mit signifikanten Informatikanteilen erfolgreich zu bearbeiten und in den verschiedenen Projektphasen eigenständig Ergebnisse erzielen, diese kritisch zu analysieren und Resultate zu präsentieren.\n--- Contents (EN) ---\nThe students work alone or in teams on individual research questions within the area of media informatics or related disciplines with a focus on informatics. They discuss their progress regularly with the supervisor and present first results. The main focus is the research-oriented implementation of the concepts developed based on scientific methodology.\n--- Contents (DE) ---\nStudierende arbeiten alleine oder im Team an einer eigenständigen wissenschaftlichen Fragestellung der Medieninformatik bzw. verwandter Medienbereiche mit Informatikanteil. Der Fortschritt wird regelmäßig mit dem Betreuer besprochen und (Teil-) Ergebnisse entsprechend präsentiert. Der Schwerpunkt liegt auf der forschungsorientierten Umsetzung der entwickelten Konzepte auf Basis wissenschaftlicher Methoden.\n--- Literature (EN) ---\n--- Literature (DE) ---\nJe nach Dozent und Projektthema verschieden\n\nMMI 04 - Masterprojekt 2\nMaster Project 2\nModulbeauftragte*r\nResponsible\nThomas Franz\nDozent*in\nTeaching staff\nLehrende*r der Hochschule Düsseldorf\nStudiengang\nM.Sc. Medieninformatik 2025\nVerwendung in anderen\nStudiengängen: / Used in other\nstudy programmes\nM.Sc. Medieninformatik, PO 2018 /\nM.Sc. Media Informatics, PO 2018\n\n\nLehrformen (alle Angaben in SWS zu je 45 Minuten / all values in SWS of 45 minutes each)\n\nCredits/\nCredits\nWorkload /\nWorkload\nKontaktzeit/\nContact time\nSelbststudium/\nSelf study\nDauer/\nLength\nSemester/\nSemester\nSprache/\nLanguage\n5\n300 h\n\n120 h\n180 h\n1 Sem.\n\nEnglish on\ndemand\nVorlesung/\nLecture\nÜbung/\nPractice\nSeminar/\nSeminar\nPraktiku\nm/ Lab\nwork\nProjekt/\nProject\nTutorium/\nTutorial\nSeminarist.\nUnterricht/\nSeminaristic\nlesson\nStudien\narbeit/\nResearch\nproject\nBegleitetes\nSelbstlernen/\nAccompan‘d\nself study\n\n\n2\n\n6\n\n\n\n\nModulkategorie / category\n\nWahlpflichtmodul / Elective module\nWahlkatalog(e) /\n\n/\nelective catalogue(s)\n\n\nVoraussetzungen zur Teilnahme /\nrequirements for participation\n\n\nFormal /\nFormal\n\nKeine /\nnone\n\nInhaltlich /\ncontentwise\n\nKeine /\nnone\nVoraussetzungen zur Prüfung /\nprerequisites for the\nexamination\n\nErfolgreiche Teilnahme am Seminar und Projekt / Successful\nparticipation in seminar and project\nPrüfungsform /\nform of examination\n\nProjektprüfung /\nProject examination\nBenotet, Stellenwert der Note\nfür die Endnote /\ngraded, value of the grade for\nthe final grade\n\nBenotet: Ja / Is graded: Yes\n\n5/90 bzw. 5/120 / 5/90 resp. 5/120\nVoraussetzungen zur\nCreditvergabe/ requirements for\nawarding credit:\n\nBestandene Modulprüfung / Passed module examination\n\nLernergebnisse, Kompetenzen:\n\n\nTeilnehmer sind in der Lage, eine komplexe, forschungs-\norientierte Aufgabenstellung aus dem Bereiche Medieninformatik\nbzw. Medientechnik / Veranstaltungstechnik / Mediengestaltung\nmit signifikanten Informatikanteilen erfolgreich zu bearbeiten und\nin den verschiedenen Projektphasen eigenständig Ergebnisse\nerzielen, diese kritisch zu analysieren und Resultate zu\npräsentieren.\n\n\n\n\nHochschule Düsseldorf\nModulhandbuch M.Sc. Medieninformatik\nVersion 1.0\nPO 2025\n16\n\n\nEnglish descriptions\n\n\n\nLehrinhalte:\nStudierende arbeiten alleine oder im Team an einer\neigenständigen wissenschaftlichen Fragestellung der\nMedieninformatik bzw. verwandter Medienbereiche mit\nInformatikanteil. Der Fortschritt wird regelmäßig mit dem Betreuer\nbesprochen und (Teil-) Ergebnisse entsprechend präsentiert. Der\nSchwerpunkt liegt auf der forschungsorientierten Umsetzung der\nentwickelten Konzepte auf Basis wissenschaftlicher Methoden.\n\nLiteratur:\n\n\nJe nach Dozent und Projektthema verschieden\n\nLearning outcomes,\ncompetences\n\n\nThe students are able to work successfully on a complex\napplication-oriented project in the field ofmedia informatics or,\nalternatively,media engineering, event technology or media\ndesign with a focus on informatics.They can achieve results in\nthe different project phases independently, analyse them\ncritically and present the results.\n\nContent\n\n\nThe students work alone or in teams on individual research\nquestions within the area of media informatics or related\ndisciplines with a focus on informatics. They discuss their\nprogress regularly with the supervisor and present first results.\nThe main focus is the research-oriented implementation of the\nconcepts developed based on scientific methodology.\n\nHochschule Düsseldorf\nModulhandbuch M.Sc. Medieninformatik\nVersion 1.0\nPO 2025\n17", "metadata": {"moduleNumber": "MMI 04", "moduleName": "Master Project 2", "creditPoints": "10.0", "suggestedSemester": 2, "offeredInSeason": "summer_semester", "examType": "project", "heldInLanguage": "en_on_demand", "reviserName": "Prof. Dr. Thomas Franz", "reviserEmail": "thomas.franz@hs-duesseldorf.de", "studyProgramId": 11, "source_type": "json", "moduleNameDe": "Masterprojekt 2", "source_file": "MMI_MHB_PO2025_V1.0.pdf", "pdf_page_start": 15, "pdf_page_end": 16, "studyProgramAbbrev": "MMI", "studyProgram_Url": "https://medien.hs-duesseldorf.de/mmi", "pdf_url": "https://medien.hs-duesseldorf.de/studium/studiengaenge/Documents/Modulhandb%C3%BCcher/MMI_MHB_PO2025_V1.0.pdf"}}
{"id": "MMI05.02", "text": "Title: Usability Engineering and User Experience\nModule Number: MMI 05.02\nCredits: 5.0 CP\nSemester: 2\nOffered In: summer_semester\nLanguage: en_on_demand\nExam Type: project\nInstructor: Prof. Dr. Alina Huldtgren (alina.huldtgren@hs-duesseldorf.de)\n--- Goals (EN) ---\nThe students understand how technology can influence human experience and how to develop digital products according to users' needs and habits. They know the basic characteristics of human experiences according to Hassenzahl. They can select and apply common methods for needs analysis, prototyping and evaluation. The students understand fundamental differences between usability and UX. They can determine and communicate requirements for the technical development of a product in the context of usability and UX.\n--- Goals (DE) ---\nDie Studierenden verstehen in welcher Weise Technik die menschliche Erfahrung beeinflussen kann und wie man digitale Produkte mit Hinblick auf die Bedürfnisse und Erfahrungen der Nutzer hin entwickelt. Dabei kennen die Studierenden die grundlegenden Eigenschaften menschlicher Erfahrungen nach Hassenzahl und können gängige Methoden zur Bedürfnisanalyse, Prototyping und Evaluation auswählen und anwenden. Sie verstehen grundlegende Unterschiede zwischen Usability und UX und können Anforderungen für die technische Entwicklung eines Produktes im Hinblick auf Usability und UX formulieren und kommunizieren.\n--- Contents (EN) ---\nHistorical development of usability and UXBasic theoretical models on actions and human experiencesntroduction to design processes such as user-centred design, co-design and experience designPractical application of UX design methods (interviews, personas, scenarios, prototyping, evaluation) based on a design task\n--- Contents (DE) ---\nGeschichtliche Entwicklung der Usability und UXGrundlegende Theoretische Modelle zu Handlungen und menschlichen Erfahrungen/ErlebnissenEinführung in Designprozesse wie Nutzerzentrierter Gestaltung, Co-Design und Experience DesignPraktische Anwendung von UX Design Methoden (Interviews, Personas, Szenarien, Prototyping, Evaluation) anhand einer Designaufgabe\n--- Literature (EN) ---\n--- Literature (DE) ---\nMorgan Kaufmann: Observing the user experience: a practitioner's guide to user research, Goodman, Kuniavsky and Moed (2012)Hassenzahl, M: Experience design: Technology for all the right reasons. Synthesis Lectures on Human-Centered Informatics, 3(1), 1-95 (2010)Richter und Flückiger: Usability Engineering Kompakt, Spektrum Akademischer Verlag (2009)Aktuelle Publikationen aus der HCI-Forschung, z. B. von Konferenzen wie ACM CHI, ACM UIST, DIS, Mensch und Computer, etc.\n\nMMI 05.02 - Usability Engineering und User Experience\nUsability Engineering and User Experience\nModulbeauftragte*r\nResponsible\nProf. Dr.  Alina Huldtgren\nDozent*in\nTeaching staff\nLehrende*r der Hochschule Düsseldorf\nStudiengang\nM.Sc. Medieninformatik 2025\nVerwendung in anderen\nStudiengängen: / Used in other\nstudy programmes\nM.Sc. Medieninformatik, PO 2018 /\nM.Sc. Media Informatics, PO 2018\n\n\nLehrformen (alle Angaben in SWS zu je 45 Minuten / all values in SWS of 45 minutes each)\n\nCredits/\nCredits\nWorkload /\nWorkload\nKontaktzeit/\nContact time\nSelbststudium/\nSelf study\nDauer/\nLength\nSemester/\nSemester\nSprache/\nLanguage\n5\n150 h\n\n75 h\n75 h\n1 Sem.\n2\nEnglish on\ndemand\nVorlesung/\nLecture\nÜbung/\nPractice\nSeminar/\nSeminar\nPraktiku\nm/ Lab\nwork\nProjekt/\nProject\nTutorium/\nTutorial\nSeminarist.\nUnterricht/\nSeminaristic\nlesson\nStudien\narbeit/\nResearch\nproject\nBegleitetes\nSelbstlernen/\nAccompan‘d\nself study\n\n\n2\n\n3\n\n\n\n\nModulkategorie / category\n\nWahlangebot / Module offer\nWahlkatalog(e) /\n\n/\nelective catalogue(s)\n\n\nVoraussetzungen zur Teilnahme /\nrequirements for participation\n\n\nFormal /\nFormal\n\nKeine /\nnone\n\nInhaltlich /\ncontentwise\n\nKeine /\nnone\nVoraussetzungen zur Prüfung /\nprerequisites for the\nexamination\n\nKeine / None\nPrüfungsform /\nform of examination\n\nProjektprüfung /\nProject examination\nBenotet, Stellenwert der Note\nfür die Endnote /\ngraded, value of the grade for\nthe final grade\n\nBenotet: Ja / Is graded: Yes\n\n5/90 bzw. 5/120 / 5/90 resp. 5/120\nVoraussetzungen zur\nCreditvergabe/ requirements for\nawarding credit:\n\nBestandene Modulprüfung / Passed module examination\n\nLernergebnisse, Kompetenzen:\n\n\nDie Studierenden verstehen in welcher Weise Technik die\nmenschliche Erfahrung beeinflussen kann und wie man digitale\nProdukte mit Hinblick auf die Bedürfnisse und Erfahrungen der\nNutzer hin entwickelt. Dabei kennen die Studierenden die\ngrundlegenden Eigenschaften menschlicher Erfahrungen nach\nHassenzahl und können gängige Methoden zur Bedürfnisanalyse,\nPrototyping und Evaluation auswählen und anwenden. Sie\nverstehen grundlegende Unterschiede zwischen Usability und UX\n\nHochschule Düsseldorf\nModulhandbuch M.Sc. Medieninformatik\nVersion 1.0\nPO 2025\n40\n\n\nEnglish descriptions\n\nund können Anforderungen für die technische Entwicklung eines\nProduktes im Hinblick auf Usability und UX formulieren und\nkommunizieren.\n\nLehrinhalte:\n\n\nGeschichtliche Entwicklung der Usability und UXGrundlegende\nTheoretische Modelle zu Handlungen und menschlichen\nErfahrungen/ErlebnissenEinführung in Designprozesse wie\nNutzerzentrierter Gestaltung, Co-Design und Experience\nDesignPraktische Anwendung von UX Design Methoden\n(Interviews, Personas, Szenarien, Prototyping, Evaluation)\nanhand einer Designaufgabe\n\nLiteratur:\n\n\nMorgan Kaufmann: Observing the user experience: a\npractitioner's guide to user research, Goodman, Kuniavsky and\nMoed (2012)Hassenzahl, M: Experience design: Technology for\nall the right reasons. Synthesis Lectures on Human-Centered\nInformatics, 3(1), 1-95 (2010)Richter und Flückiger: Usability\nEngineering Kompakt, Spektrum Akademischer Verlag\n(2009)Aktuelle Publikationen aus der HCI-Forschung, z. B. von\nKonferenzen wie ACM CHI, ACM UIST, DIS, Mensch und\nComputer, etc.\n\nLearning outcomes,\ncompetences\n\n\nThe students understand how technology can influence human\nexperience and how to develop digital products according to\nusers' needs and habits. They know the basic characteristics of\nhuman experiences according to Hassenzahl. They can select\nand apply common methods for needs analysis, prototyping and\nevaluation. The students understand fundamental differences\nbetween usability and UX. They can determine and\ncommunicate requirements for the technical development of a\nproduct in the context of usability and UX.\n\nContent\n\n\nHistorical development of usability and UXBasic theoretical\nmodels on actions and human experiencesntroduction to design\nprocesses such as user-centred design, co-design and\nexperience designPractical application of UX design methods\n(interviews, personas, scenarios, prototyping, evaluation) based\non a design task\n\nHochschule Düsseldorf\nModulhandbuch M.Sc. Medieninformatik\nVersion 1.0\nPO 2025\n41", "metadata": {"moduleNumber": "MMI 05.02", "moduleName": "Usability Engineering and User Experience", "creditPoints": "5.0", "suggestedSemester": 2, "offeredInSeason": "summer_semester", "examType": "project", "heldInLanguage": "en_on_demand", "reviserName": "Prof. Dr. Alina Huldtgren", "reviserEmail": "alina.huldtgren@hs-duesseldorf.de", "studyProgramId": 11, "source_type": "json", "moduleNameDe": "Usability Engineering und User Experience", "source_file": "MMI_MHB_PO2025_V1.0.pdf", "pdf_page_start": 39, "pdf_page_end": 40, "studyProgramAbbrev": "MMI", "studyProgram_Url": "https://medien.hs-duesseldorf.de/mmi", "pdf_url": "https://medien.hs-duesseldorf.de/studium/studiengaenge/Documents/Modulhandb%C3%BCcher/MMI_MHB_PO2025_V1.0.pdf"}}
{"id": "MMI05.03", "text": "Title: Advanced User Interfaces\nModule Number: MMI 05.03\nCredits: 5.0 CP\nSemester: None\nOffered In: to_be_announced\nLanguage: de\nExam Type: project\nInstructor: Prof. Dr. rer. nat. Christian Geiger (geiger@hs-duesseldorf.de)\n--- Goals (EN) ---\nThe students know selected advanced approaches to advanced user interfaces (post-WIMP interfaces, such as tangible and embedded interaction, 3D user interfaces, mixed reality interaction). They are able to understand new ideas based on scientific publications or peers’ project results, critically reflect on them and implement or expand them in their own approaches. For specific selected problems, the students can develop new ideas and test their implementation. They can evaluate their results and present them (e.g. at trade fairs, workshops and conferences).\n--- Goals (DE) ---\nDie Studierenden kennen ausgewählte fortgeschrittene Ansätze zu fortgeschrittenen Benutzungsschnittstellen (Post-WIMP Interfaces, z. B. tangible and embedded Interaction, 3D User Interfaces, Mixed Reality Interaktion) und sind in der Lage, sich auf Grundlage wissenschaftlicher Publikationen bzw. fremder Projektergebnisse in neue Ideen einzuarbeiten, diese kritisch zu reflektieren und in eigenen Ansätzen umzusetzen bzw. zu erweitern. Für spezifische ausgewählte Probleme können Sie neue Ideen entwickeln und prototypisch realisieren sowie ihre Ergebnisse bewerten und öffentlich präsentieren (z. B. auf Messen, Workshops / Konferenzen).\n--- Contents (EN) ---\nIn this module, the students analyse current work from different fields depending on the focus chosen. They present results, critically discuss and apply them to an individual assignment or develop the results further into a new solution. Possible topics include:Tangible and embedded interactionMixed, augmented and virtual reality interfacesIntelligent user interfacesUbiquitous computingPhysical computing interfaces\n--- Contents (DE) ---\nJe nach gewähltem Schwerpunkt werden aktuelle Arbeiten unterschiedlicher Gebiete ausgewählt. Diese werden präsentiert, kritisch diskutiert und im Rahmen einer eigenen Aufgabenstellung umgesetzt bzw. zu einer neuen Lösung weiterentwickelt. Mögliche Bereiche sind dabei:Tangible and Embedded InteractionMixed, Augmented and Virtual Reality InterfacesIntelligent User InterfacesUbiquitous ComputingPhysical Computing Interfaces\n--- Literature (EN) ---\n--- Literature (DE) ---\nSears, Jacko: The Human-Computer Interaction Handbook, 2nd Edition, CRC Press (2008)Bowman, Kruijff, LaViola, Poupyrev: 3D User Interfaces: Theory and Practice, Addison-Wesley (2004)Jason Jerald: The VR Book: Human-Centered Design for Virtual Reality, Association for Computing Machinery and Morgan & Claypool, New York, NY, USA (2015)D. Schmalstieg and T. Höllerer: Augmented Reality: Principles and Practice. Addison-Wesley Professional, First Edition (June 2016)M. Haller, M. Billinghurst, B. Thomas: Emerging Technologies of Augmented Reality: Interfaces and Design, Idea Group Publishing (2006)Aktuelle Publikationen aus ACM / IEEE Konferenzen wie z.B. TEI, ISMAR, CHI, UIST, VR, VRST, IST, soweit verfügbar in den digitalen Bibliotheken www.acm.org, www.computer.org\n\nMMI 05.03 - Advanced User Interfaces\nAdvanced User Interfaces\nModulbeauftragte*r\nResponsible\nChristian Geiger\nDozent*in\nTeaching staff\nLehrende*r der Hochschule Düsseldorf\nStudiengang\nM.Sc. Medieninformatik 2025\nVerwendung in anderen\nStudiengängen: / Used in other\nstudy programmes\nM.Sc. Medieninformatik, PO 2018 /\nM.Sc. Media Informatics, PO 2018\n\n\nLehrformen (alle Angaben in SWS zu je 45 Minuten / all values in SWS of 45 minutes each)\n\nCredits/\nCredits\nWorkload /\nWorkload\nKontaktzeit/\nContact time\nSelbststudium/\nSelf study\nDauer/\nLength\nSemester/\nSemester\nSprache/\nLanguage\n5\n150 h\n\n45 h\n105 h\n1 Sem.\n\nDeutsch\nVorlesung/\nLecture\nÜbung/\nPractice\nSeminar/\nSeminar\nPraktiku\nm/ Lab\nwork\nProjekt/\nProject\nTutorium/\nTutorial\nSeminarist.\nUnterricht/\nSeminaristic\nlesson\nStudien\narbeit/\nResearch\nproject\nBegleitetes\nSelbstlernen/\nAccompan‘d\nself study\n\n\n3\n\n\n\n\n\n\nModulkategorie / category\n\nWahlangebot / Module offer\nWahlkatalog(e) /\n\n/\nelective catalogue(s)\n\n\nVoraussetzungen zur Teilnahme /\nrequirements for participation\n\n\nFormal /\nFormal\n\nKeine /\nnone\n\nInhaltlich /\ncontentwise\n\nKeine /\nnone\nVoraussetzungen zur Prüfung /\nprerequisites for the\nexamination\n\nKeine / None\nPrüfungsform /\nform of examination\n\nProjektprüfung /\nProject examination\nBenotet, Stellenwert der Note\nfür die Endnote /\ngraded, value of the grade for\nthe final grade\n\nBenotet: Ja / Is graded: Yes\n\n5/90 bzw. 5/120 / 5/90 resp. 5/120\nVoraussetzungen zur\nCreditvergabe/ requirements for\nawarding credit:\n\nBestandene Modulprüfung / Passed module examination\n\nLernergebnisse, Kompetenzen:\n\n\nDie Studierenden kennen ausgewählte fortgeschrittene Ansätze\nzu fortgeschrittenen Benutzungsschnittstellen (Post-WIMP\nInterfaces, z. B. tangible and embedded Interaction, 3D User\nInterfaces, Mixed Reality Interaktion) und sind in der Lage, sich\nauf Grundlage wissenschaftlicher Publikationen bzw. fremder\nProjektergebnisse in neue Ideen einzuarbeiten, diese kritisch zu\nreflektieren und in eigenen Ansätzen umzusetzen bzw. zu\nerweitern. Für spezifische ausgewählte Probleme können Sie\n\nHochschule Düsseldorf\nModulhandbuch M.Sc. Medieninformatik\nVersion 1.0\nPO 2025\n42\n\n\nEnglish descriptions\n\nneue Ideen entwickeln und prototypisch realisieren sowie ihre\nErgebnisse bewerten und öffentlich präsentieren (z. B. auf\nMessen, Workshops / Konferenzen).\n\nLehrinhalte:\n\n\nJe nach gewähltem Schwerpunkt werden aktuelle Arbeiten\nunterschiedlicher Gebiete ausgewählt. Diese werden präsentiert,\nkritisch diskutiert und im Rahmen einer eigenen Aufgabenstellung\numgesetzt bzw. zu einer neuen Lösung weiterentwickelt. Mögliche\nBereiche sind dabei:Tangible and Embedded InteractionMixed,\nAugmented and Virtual Reality InterfacesIntelligent User\nInterfacesUbiquitous ComputingPhysical Computing Interfaces\n\nLiteratur:\n\n\nSears, Jacko: The Human-Computer Interaction Handbook, 2nd\nEdition, CRC Press (2008)Bowman, Kruijff, LaViola, Poupyrev: 3D\nUser Interfaces: Theory and Practice, Addison-Wesley\n(2004)Jason Jerald: The VR Book: Human-Centered Design for\nVirtual Reality, Association for Computing Machinery and Morgan\n& Claypool, New York, NY, USA (2015)D. Schmalstieg and T.\nHöllerer: Augmented Reality: Principles and Practice. Addison-\nWesley Professional, First Edition (June 2016)M. Haller, M.\nBillinghurst, B. Thomas: Emerging Technologies of Augmented\nReality: Interfaces and Design, Idea Group Publishing\n(2006)Aktuelle Publikationen aus ACM / IEEE Konferenzen wie\nz.B. TEI, ISMAR, CHI, UIST, VR, VRST, IST, soweit verfügbar in\nden digitalen Bibliotheken www.acm.org, www.computer.org\n\nLearning outcomes,\ncompetences\n\n\nThe students know selected advanced approaches to advanced\nuser interfaces (post-WIMP interfaces, such as tangible and\nembedded interaction, 3D user interfaces, mixed reality\ninteraction). They are able to understand new ideas based on\nscientific publications or peers’ project results, critically reflect on\nthem and implement or expand them in their own approaches.\nFor specific selected problems, the students can develop new\nideas and test their implementation. They can evaluate their\nresults and present them (e.g. at trade fairs, workshops and\nconferences).\n\nContent\n\n\nIn this module, the students analyse current work from different\nfields depending on the focus chosen. They present results,\ncritically discuss and apply them to an individual assignment or\ndevelop the results further into a new solution. Possible topics\ninclude:Tangible and embedded interactionMixed, augmented\nand virtual reality interfacesIntelligent user interfacesUbiquitous\ncomputingPhysical computing interfaces\n\nHochschule Düsseldorf\nModulhandbuch M.Sc. Medieninformatik\nVersion 1.0\nPO 2025\n43", "metadata": {"moduleNumber": "MMI 05.03", "moduleName": "Advanced User Interfaces", "creditPoints": "5.0", "suggestedSemester": null, "offeredInSeason": "to_be_announced", "examType": "project", "heldInLanguage": "de", "reviserName": "Prof. Dr. rer. nat. Christian Geiger", "reviserEmail": "geiger@hs-duesseldorf.de", "studyProgramId": 11, "source_type": "json", "moduleNameDe": "Advanced User Interfaces", "source_file": "MMI_MHB_PO2025_V1.0.pdf", "pdf_page_start": 41, "pdf_page_end": 42, "studyProgramAbbrev": "MMI", "studyProgram_Url": "https://medien.hs-duesseldorf.de/mmi", "pdf_url": "https://medien.hs-duesseldorf.de/studium/studiengaenge/Documents/Modulhandb%C3%BCcher/MMI_MHB_PO2025_V1.0.pdf"}}
{"id": "MMI05.04", "text": "Title: Web Data Analytics\nModule Number: MMI 05.04\nCredits: 5.0 CP\nSemester: 2\nOffered In: summer_semester\nLanguage: de\nExam Type: portfolio\nInstructor: Prof. Dr.-Ing. Thomas Rakow (thomas.rakow@hs-duesseldorf.de)\n--- Goals (EN) ---\nThe students can analyse data which are unstructured, heterogenous, large or gathered from media content. They master techniques to analyse applications of the Web such as search engines, social networks and user access data. They are enabled to apply the results in typical environments and to visualise them appropriately. They understand the economic impact of data analysis.In order to meet the scientific as well as the application-oriented demands of the topic of data analysis, the competences are tested in two examinations.1) Student thesis: Presentation of scientific papers with presentation and elaboration (seminar)2) Project appraisal: Demonstration of a software prototype and creation of a handout (project)\n--- Goals (DE) ---\nDie Studierenden können unstrukturierte, heterogene, große und mediale Datenvolumina analysieren. Sie beherrschen die Techniken zur Analyse von Web-Anwendungen wie Suchmaschinen, Sozialen Netzwerken und Zugriffscontrolling. Sie können deren Ergebnisse praktisch anwenden und visualisieren. Die wirtschaftliche Bedeutung des Themas ist verstanden worden.\n--- Contents (EN) ---\nDesigning database systems for text, image, speech, music, video and animation content\nUnderstanding distributed systems for large data volumes in the context of the web\nVisualising large data volumes\nRetrieving content-based information\nDeveloping semantic networks based on heterogenous data sets\nAnalysing user access data \nGetting information from big data and open data\nSentiment Analysis\n--- Contents (DE) ---\nMediale Datenbanken, insbesondere für Text, Bild, Sprache, Musik, Video, Animation\nVerteilte Systeme zur Verarbeitung großer Datenvolumina aus dem Web\nVisualisierung großer Datenbestände\nInhaltsbasiertes Retrieval\nSemantische Netze aus heterogenen Datenbasen\nWeb-Analyse, insbesondere Zugriffsdaten\nBig Data und Open Data\nSentiment Analyse\n--- Literature (EN) ---\nSee the current notes in the course on the respective topic\n--- Literature (DE) ---\nSiehe die aktuellen Hinweise im Kurs zu dem jeweiligen Thema\n\nMMI 05.04 - Datenanalyse im Web\nWeb Data Analytics\nModulbeauftragte*r\nResponsible\nThomas Rakow\nDozent*in\nTeaching staff\nLehrende*r der Hochschule Düsseldorf\nStudiengang\nM.Sc. Medieninformatik 2025\nVerwendung in anderen\nStudiengängen: / Used in other\nstudy programmes\nM.Sc. Medieninformatik, PO 2018 /\nM.Sc. Media Informatics, PO 2018\n\n\nLehrformen (alle Angaben in SWS zu je 45 Minuten / all values in SWS of 45 minutes each)\n\nCredits/\nCredits\nWorkload /\nWorkload\nKontaktzeit/\nContact time\nSelbststudium/\nSelf study\nDauer/\nLength\nSemester/\nSemester\nSprache/\nLanguage\n5\n150 h\n\n45 h\n105 h\n1 Sem.\n2\nDeutsch\nVorlesung/\nLecture\nÜbung/\nPractice\nSeminar/\nSeminar\nPraktiku\nm/ Lab\nwork\nProjekt/\nProject\nTutorium/\nTutorial\nSeminarist.\nUnterricht/\nSeminaristic\nlesson\nStudien\narbeit/\nResearch\nproject\nBegleitetes\nSelbstlernen/\nAccompan‘d\nself study\n1\n1\n1\n\n3\n\n\n\n\nModulkategorie / category\n\nWahlangebot / Module offer\nWahlkatalog(e) /\n\n/\nelective catalogue(s)\n\n\nVoraussetzungen zur Teilnahme /\nrequirements for participation\n\n\nFormal /\nFormal\n\nKeine /\nnone\n\nInhaltlich /\ncontentwise\n\nKenntnisse in Analysis, Wahrscheinlichkeitsrechnung, Software\nEngineering, Datenbanksysteme, Verteilte Systeme,\nWebanwendungen /\nKnowledge in Analysis, Probability, Software Engineering,\nDatabase Systems, Distributed Systems, Web Applications\nVoraussetzungen zur Prüfung /\nprerequisites for the\nexamination\n\nErfolgreiche Teilnahme am Seminar und Projekt / Successful\nparticipation in seminar and project\nPrüfungsform /\nform of examination\n\nBearbeitung von Seminar-, Praktikums-, oder Übungsaufgaben\noder Laborversuchen (Portfolio) /\nPortfolio submittal or participation in laboratory experiments\nBenotet, Stellenwert der Note\nfür die Endnote /\ngraded, value of the grade for\nthe final grade\n\nBenotet: Ja / Is graded: Yes\n\n5/90 bzw. 5/120 / 5/90 resp. 5/120\nVoraussetzungen zur\nCreditvergabe/ requirements for\nawarding credit:\n\nBestandene Modulprüfung / Passed module examination\n\nLernergebnisse, Kompetenzen:\n\n\nDie Studierenden können unstrukturierte, heterogene, große und\nmediale Datenvolumina analysieren. Sie beherrschen die\nTechniken zur Analyse von Web-Anwendungen wie\nSuchmaschinen, Sozialen Netzwerken und Zugriffscontrolling. Sie\n\nHochschule Düsseldorf\nModulhandbuch M.Sc. Medieninformatik\nVersion 1.0\nPO 2025\n44\n\n\nEnglish descriptions\n\nkönnen deren Ergebnisse praktisch anwenden und visualisieren.\nDie wirtschaftliche Bedeutung des Themas ist verstanden worden.\n\nLehrinhalte:\n\n\nMediale Datenbanken, insbesondere für Text, Bild, Sprache,\nMusik, Video, Animation\nVerteilte Systeme zur Verarbeitung großer Datenvolumina aus\ndem Web\nVisualisierung großer Datenbestände\nInhaltsbasiertes Retrieval\nSemantische Netze aus heterogenen Datenbasen\nWeb-Analyse, insbesondere Zugriffsdaten\nBig Data und Open Data\nSentiment Analyse\n\nLiteratur:\n\n\nSiehe die aktuellen Hinweise im Kurs zu dem jeweiligen Thema\n\nLearning outcomes,\ncompetences\n\n\nThe students can analyse data which are unstructured,\nheterogenous, large or gathered from media content. They\nmaster techniques to analyse applications of the Web such as\nsearch engines, social networks and user access data. They are\nenabled to apply the results in typical environments and to\nvisualise them appropriately. They understand the economic\nimpact of data analysis.In order to meet the scientific as well as\nthe application-oriented demands of the topic of data analysis,\nthe competences are tested in two examinations.1) Student\nthesis: Presentation of scientific papers with presentation and\nelaboration (seminar)2) Project appraisal: Demonstration of a\nsoftware prototype and creation of a handout (project)\n\nContent\n\n\nDesigning database systems for text, image, speech, music,\nvideo and animation content\nUnderstanding distributed systems for large data volumes in the\ncontext of the web\nVisualising large data volumes\nRetrieving content-based information\nDeveloping semantic networks based on heterogenous data sets\nAnalysing user access data\nGetting information from big data and open data\nSentiment Analysis\n\nHochschule Düsseldorf\nModulhandbuch M.Sc. Medieninformatik\nVersion 1.0\nPO 2025\n45", "metadata": {"moduleNumber": "MMI 05.04", "moduleName": "Web Data Analytics", "creditPoints": "5.0", "suggestedSemester": 2, "offeredInSeason": "summer_semester", "examType": "portfolio", "heldInLanguage": "de", "reviserName": "Prof. Dr.-Ing. Thomas Rakow", "reviserEmail": "thomas.rakow@hs-duesseldorf.de", "studyProgramId": 11, "source_type": "json", "moduleNameDe": "Datenanalyse im Web", "source_file": "MMI_MHB_PO2025_V1.0.pdf", "pdf_page_start": 43, "pdf_page_end": 44, "studyProgramAbbrev": "MMI", "studyProgram_Url": "https://medien.hs-duesseldorf.de/mmi", "pdf_url": "https://medien.hs-duesseldorf.de/studium/studiengaenge/Documents/Modulhandb%C3%BCcher/MMI_MHB_PO2025_V1.0.pdf"}}
{"id": "MMI05.05", "text": "Title: Immersive Visualization\nModule Number: MMI 05.05\nCredits: 5.0 CP\nSemester: 2\nOffered In: summer_semester\nLanguage: de\nExam Type: none\nInstructor: Prof. Dr. rer. nat. Christian Geiger (geiger@hs-duesseldorf.de)\n--- Goals (EN) ---\nStudents will be familiar with the key concepts of visualization and typical design procedures. They also know typical examples of successful immersive visualization projects and can explain and evaluate them. They are able to recognize typical problems in the design and development of immersive visualizations and to develop expressive and effective visual representation concepts based on established procedures for multivariate data, to implement and evaluate them using suitable immersive technologies (visualization systems, 3D game engines, frameworks). They are able to design their own visualization projects and successfully implement them within a given time frame. They will be able to present and critically reflect on the scientific and artistic state of development.\n--- Goals (DE) ---\nDie Studierenden kennen die wesentlichen Begriffe der Visualisierung und typische Vorgehensweise beim Entwurf. Sie kennen darüber hinaus typische Beispiele erfolgreicher immersiver Visualisierungsprojekte und können diese erläutern und bewerten. Sie sind in der Lage, typische Probleme der bei der Gestaltung und Entwicklung immersiver Visualisierungen zu erkennen und auf Basis etablierter Vorgehensweisen  für multivariate Daten expressive und effektive visuelle Darstellungskonzepte zu entwickeln, mittels geeigneter immersiver Technologien (Visualisierungssysteme, 3D Game Engines, Frameworks) zu realisieren und zu bewerten. Sie sind in der Lage, eigene Visualisierungsprojekte zu konzipieren und in einem gegebenen Zeitrahmen erfolgreich umzusetzen. Sie können den wissenschaftlichen und künstlerischen Stand der Entwicklung darstellen und kritisch reflektieren.\n--- Contents (EN) ---\nThe course Immersive Visualization deals with computer-aided methods for the graphical representation of information and data, which are given an immersive character through design and technology. This can be achieved through extensive interaction, XR technologies, projections or large-scale displays. This special visual representation is intended to help evaluate, present and inform data or gain new insights from it. The main contents are \n- Aspects of human visual perception and visualization models:\n- Visualization of multivariate data\n- Workflow and procedure models in the visualization process (visualization pipeline)\n- multimodal interaction concepts, design principles and storytelling \n- Overview of typical visualization systems for real-time applications \n- VR/AR technologies for immersive visualization\n- scientific and artistic research in this field\n\nThe course will choose a specific topic in each semester offered, which will then be worked on with the participants. External lectures and excursions round off the program.\n--- Contents (DE) ---\nDie Veranstaltung Immersive Visualisierung befasst sich mit computerunterstützten Methoden zur grafischen Repräsentation von Informationen und Daten, die durch Gestaltung und Technologie einen immersiven Charakter erhalten. Das kann durch umfangreiche Interaktion, XR -Technologien, Projektionen oder großflächige Displays erfolgen. Diese besondere bildliche Darstellung soll dabei helfen, Daten auszuwerten, zu präsentieren und informieren bzw. neue Erkenntnisse daraus zu gewinnen. Wesentliche Inhalte sind \n- Aspekte der menschlichen visuellen Wahrnehmung und Modell der Visualisierung:\n- Visualisierung multivariater Daten\n- Workflow und Vorgehensmodelle im Visualisierungsprozess (Visualisierungspipeline)\n- multimodale Interaktionskonzepte, Gestaltungsgrundlagen und Storytelling \n- Überblick typischer Visualisierungssysteme für Echtzeitanwendungen \n- VR/AR Technologien für immersive Visualisierung\n- wissenschaftliche und künstlerische Forschung in diesem Bereich\n\nDie Veranstaltung wird sich in jedem angebotenen Semester ein spezielles Thema wählen, das mit den Teilnehmer:innen dann bearbeitet wird. Externe Vorträge und Exkursionen runden das Angebot ab.\n--- Literature (EN) ---\n--- Literature (DE) ---\n-Chaomei Chen: Information Visualization. Beyond the Horizon. 2. Auflage, Springer London, (2004)\n-Colin Ware: Information Visualization : Perception for Design Morgan Kaufmann Series in Interactive Technologies, San Francisco, (2000)\n-Natha Yau: Visualize This: The Flowing Data Guide to Design, Visualization and Statistics, Wiley, (2011)\n- Cole Nussbaumer Knaflic: Storytelling with Data: A Data Visualization Guide for Business Professionals, Wiley, (2015)\n- Cornel Hillmann: UX for XR: User Experience Design and Strategies for Immersive Technologies (Design Thinking), Apress 2021.\n\nMMI 05.05 - Immersive Visualisierung\nImmersive Visualization\nModulbeauftragte*r\nResponsible\nChristian Geiger\nDozent*in\nTeaching staff\nLehrende*r der Hochschule Düsseldorf\nStudiengang\nM.Sc. Medieninformatik 2025\nVerwendung in anderen\nStudiengängen: / Used in other\nstudy programmes\nM.Sc. Medieninformatik, PO 2018 /\nM.Sc. Media Informatics, PO 2018\n\n\nLehrformen (alle Angaben in SWS zu je 45 Minuten / all values in SWS of 45 minutes each)\n\nCredits/\nCredits\nWorkload /\nWorkload\nKontaktzeit/\nContact time\nSelbststudium/\nSelf study\nDauer/\nLength\nSemester/\nSemester\nSprache/\nLanguage\n5\n150 h\n\n60 h\n90 h\n1 Sem.\n2\nDeutsch\nVorlesung/\nLecture\nÜbung/\nPractice\nSeminar/\nSeminar\nPraktiku\nm/ Lab\nwork\nProjekt/\nProject\nTutorium/\nTutorial\nSeminarist.\nUnterricht/\nSeminaristic\nlesson\nStudien\narbeit/\nResearch\nproject\nBegleitetes\nSelbstlernen/\nAccompan‘d\nself study\n\n\n2\n\n2\n\n\n\n\nModulkategorie / category\n\nWahlangebot / Module offer\nWahlkatalog(e) /\n\n/\nelective catalogue(s)\n\n\nVoraussetzungen zur Teilnahme /\nrequirements for participation\n\n\nFormal /\nFormal\n\nKeine /\nnone\n\nInhaltlich /\ncontentwise\n\nKeine /\nnone\nVoraussetzungen zur Prüfung /\nprerequisites for the\nexamination\n\nKeine / None\nPrüfungsform /\nform of examination\n\nKeine Prüfung /\nNo exam\nBenotet, Stellenwert der Note\nfür die Endnote /\ngraded, value of the grade for\nthe final grade\n\nBenotet: Ja / Is graded: Yes\n\n5/90 bzw. 5/120 / 5/90 resp. 5/120\nVoraussetzungen zur\nCreditvergabe/ requirements for\nawarding credit:\n\nBestandene Modulprüfung / Passed module examination\n\nLernergebnisse, Kompetenzen:\n\n\nDie Studierenden kennen die wesentlichen Begriffe der\nVisualisierung und typische Vorgehensweise beim Entwurf. Sie\nkennen darüber hinaus typische Beispiele erfolgreicher\nimmersiver Visualisierungsprojekte und können diese erläutern\nund bewerten. Sie sind in der Lage, typische Probleme der bei der\nGestaltung und Entwicklung immersiver Visualisierungen zu\nerkennen und auf Basis etablierter Vorgehensweisen  für\nmultivariate Daten expressive und effektive visuelle\n\nHochschule Düsseldorf\nModulhandbuch M.Sc. Medieninformatik\nVersion 1.0\nPO 2025\n46\n\n\nEnglish descriptions\nDarstellungskonzepte zu entwickeln, mittels geeigneter\nimmersiver Technologien (Visualisierungssysteme, 3D Game\nEngines, Frameworks) zu realisieren und zu bewerten. Sie sind in\nder Lage, eigene Visualisierungsprojekte zu konzipieren und in\neinem gegebenen Zeitrahmen erfolgreich umzusetzen. Sie\nkönnen den wissenschaftlichen und künstlerischen Stand der\nEntwicklung darstellen und kritisch reflektieren.\n\nLehrinhalte:\n\n\nDie Veranstaltung Immersive Visualisierung befasst sich mit\ncomputerunterstützten Methoden zur grafischen Repräsentation\nvon Informationen und Daten, die durch Gestaltung und\nTechnologie einen immersiven Charakter erhalten. Das kann\ndurch umfangreiche Interaktion, XR -Technologien, Projektionen\noder großflächige Displays erfolgen. Diese besondere bildliche\nDarstellung soll dabei helfen, Daten auszuwerten, zu präsentieren\nund informieren bzw. neue Erkenntnisse daraus zu gewinnen.\nWesentliche Inhalte sind\n- Aspekte der menschlichen visuellen Wahrnehmung und Modell\nder Visualisierung:\n- Visualisierung multivariater Daten\n- Workflow und Vorgehensmodelle im Visualisierungsprozess\n(Visualisierungspipeline)\n- multimodale Interaktionskonzepte, Gestaltungsgrundlagen und\nStorytelling\n- Überblick typischer Visualisierungssysteme für\nEchtzeitanwendungen\n- VR/AR Technologien für immersive Visualisierung\n- wissenschaftliche und künstlerische Forschung in diesem\nBereich\n\nDie Veranstaltung wird sich in jedem angebotenen Semester ein\nspezielles Thema wählen, das mit den Teilnehmer:innen dann\nbearbeitet wird. Externe Vorträge und Exkursionen runden das\nAngebot ab.\n\nLiteratur:\n\n\n-Chaomei Chen: Information Visualization. Beyond the Horizon. 2.\nAuflage, Springer London, (2004)\n-Colin Ware: Information Visualization : Perception for Design\nMorgan Kaufmann Series in Interactive Technologies, San\nFrancisco, (2000)\n-Natha Yau: Visualize This: The Flowing Data Guide to Design,\nVisualization and Statistics, Wiley, (2011)\n- Cole Nussbaumer Knaflic: Storytelling with Data: A Data\nVisualization Guide for Business Professionals, Wiley, (2015)\n- Cornel Hillmann: UX for XR: User Experience Design and\nStrategies for Immersive Technologies (Design Thinking), Apress\n2021.\n\nLearning outcomes,\ncompetences\n\n\nStudents will be familiar with the key concepts of visualization\nand typical design procedures. They also know typical examples\n\nHochschule Düsseldorf\nModulhandbuch M.Sc. Medieninformatik\nVersion 1.0\nPO 2025\n47\n\n\nof successful immersive visualization projects and can explain\nand evaluate them. They are able to recognize typical problems\nin the design and development of immersive visualizations and\nto develop expressive and effective visual representation\nconcepts based on established procedures for multivariate data,\nto implement and evaluate them using suitable immersive\ntechnologies (visualization systems, 3D game engines,\nframeworks). They are able to design their own visualization\nprojects and successfully implement them within a given time\nframe. They will be able to present and critically reflect on the\nscientific and artistic state of development.\n\nContent\n\n\nThe course Immersive Visualization deals with computer-aided\nmethods for the graphical representation of information and\ndata, which are given an immersive character through design\nand technology. This can be achieved through extensive\ninteraction, XR technologies, projections or large-scale displays.\nThis special visual representation is intended to help evaluate,\npresent and inform data or gain new insights from it. The main\ncontents are\n- Aspects of human visual perception and visualization models:\n- Visualization of multivariate data\n- Workflow and procedure models in the visualization process\n(visualization pipeline)\n- multimodal interaction concepts, design principles and\nstorytelling\n- Overview of typical visualization systems for real-time\napplications\n- VR/AR technologies for immersive visualization\n- scientific and artistic research in this field\n\nThe course will choose a specific topic in each semester offered,\nwhich will then be worked on with the participants. External\nlectures and excursions round off the program.\n\nHochschule Düsseldorf\nModulhandbuch M.Sc. Medieninformatik\nVersion 1.0\nPO 2025\n48", "metadata": {"moduleNumber": "MMI 05.05", "moduleName": "Immersive Visualization", "creditPoints": "5.0", "suggestedSemester": 2, "offeredInSeason": "summer_semester", "examType": "none", "heldInLanguage": "de", "reviserName": "Prof. Dr. rer. nat. Christian Geiger", "reviserEmail": "geiger@hs-duesseldorf.de", "studyProgramId": 11, "source_type": "json", "moduleNameDe": "Immersive Visualisierung", "source_file": "MMI_MHB_PO2025_V1.0.pdf", "pdf_page_start": 45, "pdf_page_end": 47, "studyProgramAbbrev": "MMI", "studyProgram_Url": "https://medien.hs-duesseldorf.de/mmi", "pdf_url": "https://medien.hs-duesseldorf.de/studium/studiengaenge/Documents/Modulhandb%C3%BCcher/MMI_MHB_PO2025_V1.0.pdf"}}
{"id": "MMI05.07", "text": "Title: Intelligent Systems\nModule Number: MMI 05.07\nCredits: 5.0 CP\nSemester: 2\nOffered In: summer_semester\nLanguage: de\nExam Type: written_exam\nInstructor: Prof. Dr. Dennis Müller (dennis.mueller@hs-duesseldorf.de)\n--- Goals (EN) ---\nUpon successful completion of the module, students are able to\n\nDetermine regression and classification models using linear and logistic methods,\n\nFind linear separating hyperplanes in high-dimensional spaces using a kernelized support vector machine,\n\nSelect different loss functions for optimizing regression problems purposefully and solve the resulting optimization problem,\n\nIdentify and interpret important metrics and measures (e.g., accuracy, precision, recall) of classification models,\n\nIndependently train perceptrons and multilayer neural networks using appropriate methods,\n\nImplement and train simple neural networks in PyTorch using training data.\n\nMMI PO18 and MMI PO25 only:\nThe students independently work on a simple task from the field of \"Artificial Intelligence\" in consultation with the instructor and present the results in a short oral presentation during lecture or exercise time. The additional required work will be coordinated with the instructor at the beginning of the semester and independently developed during the semester.\n--- Goals (DE) ---\nMit dem erfolgreichen Absolvieren des Moduls sind Studierende in der Lage\n\nRegressions- und Klassifikationsmodelle mit Hilfe linearer sowie logistischer Methoden zu bestimmen,\n\nLineare Trennebenen in hochdimensionalen Räumen mit Hilfe einer kernelisierten Support-Vektor-Maschine zu finden,\n\nUnterschiedliche Loss-Funktionen zur Optimierung von Regressionsproblemen zielgerichtet auszuwählen und das sich daraus ergebende Optimierungsproblem zu lösen,\n\nWichtige Kenngrößen und Metriken (z.B. Accuracy, Precision, Recall) von Klassifikationsmodellen zu ermitteln und zu interpretieren,\n\nPerzeptronen- und mehrschichtige neuronale Netzwerke unter Einsatz geeigneter Verfahren selbstständig zu trainieren,\n\neinfache neuronale Netzwerke in PyTorch zu implementieren und anhand von Trainingsdaten zu trainieren.\n\nFür MMI PO18 und MMI PO25 zusätzlich:\nDie Studierenden bearbeiten selbstständig eine einfache Aufgabenstellung aus dem Bereich \"Künstliche Intelligenz\" in Absprache mit dem Dozierenden und stellen die Ergebnisse in einem kurzen mündlichen Vortrag während der Vorlesungs- oder Übungszeit vor. Die zu erbringende Zusatzleistung wird am Anfang des Semesters mit dem Dozenten abgestimmt und im laufenden Semester selbstständig erarbeitet.\n--- Contents (EN) ---\nHistory of artificial intelligence / knowledge-based systems\nLinear regression and linear classification\nKernel methods for regression and classification in high-dimensional spaces\nSupport vector machines\nLoss functions and metrics\nPerceptrons and neural networks\nBackpropagation and delta learning rule\nPractical application in Python and PyTorch\n--- Contents (DE) ---\nGeschichte der künstlichen Intelligenz / wissensbasierter Systeme\nLineare Regression und lineare Klassifikation\nKernelmethoden zur Regression und Klassifikation in hochdimensionalen Räumen\nSupport Vektor Maschinen\nLoss-Funktionen und Metriken\nPerzeptronen- und Neuronalenetzwerke\nBackpropagation und Delta-Lernregel\nPraktische Anwendung in Python und PyTorch\n--- Literature (EN) ---\nRussell, S. J., & Norvig, P. (2020). Artificial Intelligence: A Modern Approach (4th ed.). Pearson.\nDomingos, P. (2015). The Master Algorithm: How the Quest for the Ultimate Learning Machine Will Remake Our World. Basic Books.\nMitchell, T. M. (1997). Machine Learning. McGraw-Hill.\nGoodfellow, I., Bengio, Y., & Courville, A. (2016). Deep Learning. MIT Press.\nTegmark, M. (2017). Life 3.0: Being Human in the Age of Artificial Intelligence. Knopf.\n--- Literature (DE) ---\nRussell, S. J., & Norvig, P. (2020). Artificial Intelligence: A Modern Approach (4th ed.). Pearson.\nDomingos, P. (2015). The Master Algorithm: How the Quest for the Ultimate Learning Machine Will Remake Our World. Basic Books.\nMitchell, T. M. (1997). Machine Learning. McGraw-Hill.\nGoodfellow, I., Bengio, Y., & Courville, A. (2016). Deep Learning. MIT Press.\nTegmark, M. (2017). Life 3.0: Being Human in the Age of Artificial Intelligence. Knopf.\n\nMMI 05.07 - Intelligente Systeme\nIntelligent Systems\nModulbeauftragte*r\nResponsible\nDennis Müller\nDozent*in\nTeaching staff\nLehrende*r der Hochschule Düsseldorf\nStudiengang\nM.Sc. Medieninformatik 2025\nVerwendung in anderen\nStudiengängen: / Used in other\nstudy programmes\nB.Sc. Medieninformatik, PO 2018\nM.Sc. Medieninformatik, PO 2018 /\nB.Sc. Media Informatics, PO 2018\nM.Sc. Media Informatics, PO 2018\n\n\nLehrformen (alle Angaben in SWS zu je 45 Minuten / all values in SWS of 45 minutes each)\n\nCredits/\nCredits\nWorkload /\nWorkload\nKontaktzeit/\nContact time\nSelbststudium/\nSelf study\nDauer/\nLength\nSemester/\nSemester\nSprache/\nLanguage\n5\n150 h\n\n90 h\n60 h\n1 Sem.\n2\nDeutsch\nVorlesung/\nLecture\nÜbung/\nPractice\nSeminar/\nSeminar\nPraktiku\nm/ Lab\nwork\nProjekt/\nProject\nTutorium/\nTutorial\nSeminarist.\nUnterricht/\nSeminaristic\nlesson\nStudien\narbeit/\nResearch\nproject\nBegleitetes\nSelbstlernen/\nAccompan‘d\nself study\n2\n2\n\n2\n\n\n\n\n\nModulkategorie / category\n\nWahlangebot / Module offer\nWahlkatalog(e) /\n\n/\nelective catalogue(s)\n\n\nVoraussetzungen zur Teilnahme /\nrequirements for participation\n\n\nFormal /\nFormal\n\nKeine /\nnone\n\nInhaltlich /\ncontentwise\n\nMathematik 1/2/3 /\nMathematics 1/2/3\nVoraussetzungen zur Prüfung /\nprerequisites for the\nexamination\n\nKeine / None\nPrüfungsform /\nform of examination\n\nKlausurarbeit /\nWritten examination\nBenotet, Stellenwert der Note\nfür die Endnote /\ngraded, value of the grade for\nthe final grade\n\nBenotet: Ja / Is graded: Yes\n\n5/90 bzw. 5/120 / 5/90 resp. 5/120\nVoraussetzungen zur\nCreditvergabe/ requirements for\nawarding credit:\n\nBestandene Modulprüfung / Passed module examination\n\nLernergebnisse, Kompetenzen:\n\n\nMit dem erfolgreichen Absolvieren des Moduls sind Studierende in\nder Lage\n\nRegressions- und Klassifikationsmodelle mit Hilfe linearer sowie\nlogistischer Methoden zu bestimmen,\n\n\nHochschule Düsseldorf\nModulhandbuch M.Sc. Medieninformatik\nVersion 1.0\nPO 2025\n49\n\n\nEnglish descriptions\nLineare Trennebenen in hochdimensionalen Räumen mit Hilfe\neiner kernelisierten Support-Vektor-Maschine zu finden,\n\nUnterschiedliche Loss-Funktionen zur Optimierung von\nRegressionsproblemen zielgerichtet auszuwählen und das sich\ndaraus ergebende Optimierungsproblem zu lösen,\n\nWichtige Kenngrößen und Metriken (z.B. Accuracy, Precision,\nRecall) von Klassifikationsmodellen zu ermitteln und zu\ninterpretieren,\n\nPerzeptronen- und mehrschichtige neuronale Netzwerke unter\nEinsatz geeigneter Verfahren selbstständig zu trainieren,\n\neinfache neuronale Netzwerke in PyTorch zu implementieren und\nanhand von Trainingsdaten zu trainieren.\n\nFür MMI PO18 und MMI PO25 zusätzlich:\nDie Studierenden bearbeiten selbstständig eine einfache\nAufgabenstellung aus dem Bereich 'Künstliche Intelligenz' in\nAbsprache mit dem Dozierenden und stellen die Ergebnisse in\neinem kurzen mündlichen Vortrag während der Vorlesungs- oder\nÜbungszeit vor. Die zu erbringende Zusatzleistung wird am\nAnfang des Semesters mit dem Dozenten abgestimmt und im\nlaufenden Semester selbstständig erarbeitet.\n\nLehrinhalte:\n\n\nGeschichte der künstlichen Intelligenz / wissensbasierter Systeme\nLineare Regression und lineare Klassifikation\nKernelmethoden zur Regression und Klassifikation in\nhochdimensionalen Räumen\nSupport Vektor Maschinen\nLoss-Funktionen und Metriken\nPerzeptronen- und Neuronalenetzwerke\nBackpropagation und Delta-Lernregel\nPraktische Anwendung in Python und PyTorch\n\nLiteratur:\n\n\nRussell, S. J., & Norvig, P. (2020). Artificial Intelligence: A Modern\nApproach (4th ed.). Pearson.\nDomingos, P. (2015). The Master Algorithm: How the Quest for\nthe Ultimate Learning Machine Will Remake Our World. Basic\nBooks.\nMitchell, T. M. (1997). Machine Learning. McGraw-Hill.\nGoodfellow, I., Bengio, Y., & Courville, A. (2016). Deep Learning.\nMIT Press.\nTegmark, M. (2017). Life 3.0: Being Human in the Age of Artificial\nIntelligence. Knopf.\n\nLearning outcomes,\ncompetences\n\n\nUpon successful completion of the module, students are able to\n\n\nHochschule Düsseldorf\nModulhandbuch M.Sc. Medieninformatik\nVersion 1.0\nPO 2025\n50\n\n\nDetermine regression and classification models using linear and\nlogistic methods,\n\nFind linear separating hyperplanes in high-dimensional spaces\nusing a kernelized support vector machine,\n\nSelect different loss functions for optimizing regression problems\npurposefully and solve the resulting optimization problem,\n\nIdentify and interpret important metrics and measures (e.g.,\naccuracy, precision, recall) of classification models,\n\nIndependently train perceptrons and multilayer neural networks\nusing appropriate methods,\n\nImplement and train simple neural networks in PyTorch using\ntraining data.\n\nMMI PO18 and MMI PO25 only:\nThe students independently work on a simple task from the field\nof 'Artificial Intelligence' in consultation with the instructor and\npresent the results in a short oral presentation during lecture or\nexercise time. The additional required work will be coordinated\nwith the instructor at the beginning of the semester and\nindependently developed during the semester.\n\nContent\n\n\nHistory of artificial intelligence / knowledge-based systems\nLinear regression and linear classification\nKernel methods for regression and classification in high-\ndimensional spaces\nSupport vector machines\nLoss functions and metrics\nPerceptrons and neural networks\nBackpropagation and delta learning rule\nPractical application in Python and PyTorch\n\nHochschule Düsseldorf\nModulhandbuch M.Sc. Medieninformatik\nVersion 1.0\nPO 2025\n51", "metadata": {"moduleNumber": "MMI 05.07", "moduleName": "Intelligent Systems", "creditPoints": "5.0", "suggestedSemester": 2, "offeredInSeason": "summer_semester", "examType": "written_exam", "heldInLanguage": "de", "reviserName": "Prof. Dr. Dennis Müller", "reviserEmail": "dennis.mueller@hs-duesseldorf.de", "studyProgramId": 11, "source_type": "json", "moduleNameDe": "Intelligente Systeme", "source_file": "MMI_MHB_PO2025_V1.0.pdf", "pdf_page_start": 48, "pdf_page_end": 50, "studyProgramAbbrev": "MMI", "studyProgram_Url": "https://medien.hs-duesseldorf.de/mmi", "pdf_url": "https://medien.hs-duesseldorf.de/studium/studiengaenge/Documents/Modulhandb%C3%BCcher/MMI_MHB_PO2025_V1.0.pdf"}}
{"id": "MMI05.08", "text": "Title: Interactive Virtual Studio\nModule Number: MMI 05.08\nCredits: 5.0 CP\nSemester: 1\nOffered In: winter_semester\nLanguage: en_on_demand\nExam Type: project\nInstructor: Prof. Dr. Eng. Univ. of Tsukuba Jens Herder (jens.herder@hs-duesseldorf.de)\n--- Goals (EN) ---\nSuccessful participants will have a profound knowledge in building and developing virtual set environments for broadcasting applications and will be able to evaluate virtual studio (TV) technology. Tracking, composition of video and computer graphics under live conditions for media productions are essential part.\n--- Goals (DE) ---\nStudierende können Video und Computergrafik unter Live-Bedingungen in Produktionen verbinden. Hierzu gehört die Erstellung fiktiver Umgebungen, in die Menschen und Gegenstande versetzt werden. Sie können Virtuelle Studios entwickeln, aufbauen und einsetzen. Die grundlegenden Technologien wie z.B. Tracking, Computergrafik können angepasst und bewertet werden.\n--- Contents (EN) ---\nTopics include:\n- Application and use of virtual sets\n- Effect of artificially created levels of reality, unreal scenery and virtual backdrops\n- Hard- and software for digital (TV) studio productions\n- Light and light setting for TV studios\n- Camera and actor tracking systems\n- Virtual set design for artificial or real scenes\n- Motion capture\n- Real-time computer graphics and visual effects\n- Separation of image elements (e.g., chroma keying)\n- Integration of animations and virtual characters/avatars\n- Interaction within a virtual tv studio\n- Feedback methods for actors\n- Studio production planning and automation\n--- Contents (DE) ---\nZu den Themen gehören:\n- Anwendungen und Nutzung von virtuellen Sets\n- Wirkung künstlich erstellter Realitätsebenen, irrealer Szenenbilder und virtueller Kulissen\n- Hard- und Software für digitale Studioproduktionstechnik\n- Licht und Beleuchtung im Virtuellen Studio, Lichtschätzung\n- Kamera- und Darstellerverfolgungssysteme (Tracking)\n- Set Design\n- Bewegungsaufzeichnung (auch markerlos)\n- Echtzeitgenerierung dreidimensionaler Computergraphik, visuelle Effekte\n- Herauslösen von Bildelementen (z.B. Chromakeying)\n- Einbindung von Animationen und virtuellen Charakteren/Avataren\n- Interaktion im Virtuellen Studio\n- Feedbackmethoden für Darsteller\n- Produktionsplanung, Automatisierung und Produktionsdurchführung\n--- Literature (EN) ---\n- S. Gibbs: Virtual Studios, IEEE MultiMedia 5, 1 (January 1998), 17-17. DOI=http://dx.doi.org/10.1109/MMUL.1998.664739\n- A. R. Smith and J. F. Blinn: Blue screen matting. In Proceedings of the 23rd annual conference on Computer graphics and interactive techniques (SIGGRAPH '96), ACM, New York, NY, USA, 259-268. DOI=http://dx.doi.org/10.1145/237170.237263\n- R. Brinkmann: The Art and Science of Digital Compositing, Morgan Kaufman, lis Group (März 2000)\n- M. Moshkovitz: The Virtual Studio Technology & Techniques, Focal Press (2000)\n- P. Tucker: Secrets of Screen Acting, Routlege (1994)\n- D. Arijon: Grammar of the Film Language, Silman-James Press (1976)\n- U. Schmidt: Professionelle Videotechnik: Analoge und Digitale Grundlagen, Filmtechnik, Fernsehtechnik, HDTV, Kameras, Displays, Videorecorder, Produktion und Studiotechnik, Springer (2005)\n- Journal of Virtual Reality and Broadcasting, www.jvrb.org\n--- Literature (DE) ---\n- S. Gibbs: Virtual Studios, IEEE MultiMedia 5, 1 (January 1998), 17-17. DOI=http://dx.doi.org/10.1109/MMUL.1998.664739\n- A. R. Smith and J. F. Blinn: Blue screen matting. In Proceedings of the 23rd annual conference on Computer graphics and interactive techniques (SIGGRAPH '96), ACM, New York, NY, USA, 259-268. DOI=http://dx.doi.org/10.1145/237170.237263\n- R. Brinkmann: The Art and Science of Digital Compositing, Morgan Kaufman, lis Group (März 2000)\n- M. Moshkovitz: The Virtual Studio Technology & Techniques, Focal Press (2000)\n- P. Tucker: Secrets of Screen Acting, Routlege (1994)\n- D. Arijon: Grammar of the Film Language, Silman-James Press (1976)\n- U. Schmidt: Professionelle Videotechnik: Analoge und Digitale Grundlagen, Filmtechnik, Fernsehtechnik, HDTV, Kameras, Displays, Videorecorder, Produktion und Studiotechnik, Springer (2005)\n- Journal of Virtual Reality and Broadcasting, www.jvrb.org\n\nMMI 05.08 - Interaktives Virtuelles Studio\nInteractive Virtual Studio\nModulbeauftragte*r\nResponsible\nJens Herder\nDozent*in\nTeaching staff\nLehrende*r der Hochschule Düsseldorf\nStudiengang\nM.Sc. Medieninformatik 2025\nVerwendung in anderen\nStudiengängen: / Used in other\nstudy programmes\nM.Sc. Medieninformatik, PO 2018 /\nM.Sc. Media Informatics, PO 2018\n\n\nLehrformen (alle Angaben in SWS zu je 45 Minuten / all values in SWS of 45 minutes each)\n\nCredits/\nCredits\nWorkload /\nWorkload\nKontaktzeit/\nContact time\nSelbststudium/\nSelf study\nDauer/\nLength\nSemester/\nSemester\nSprache/\nLanguage\n5\n150 h\n\n60 h\n90 h\n1 Sem.\n1\nEnglish on\ndemand\nVorlesung/\nLecture\nÜbung/\nPractice\nSeminar/\nSeminar\nPraktiku\nm/ Lab\nwork\nProjekt/\nProject\nTutorium/\nTutorial\nSeminarist.\nUnterricht/\nSeminaristic\nlesson\nStudien\narbeit/\nResearch\nproject\nBegleitetes\nSelbstlernen/\nAccompan‘d\nself study\n1\n\n1\n\n2\n\n\n\n\nModulkategorie / category\n\nWahlangebot / Module offer\nWahlkatalog(e) /\n\n/\nelective catalogue(s)\n\n\nVoraussetzungen zur Teilnahme /\nrequirements for participation\n\n\nFormal /\nFormal\n\nKeine /\nnone\n\nInhaltlich /\ncontentwise\n\nKeine /\nnone\nVoraussetzungen zur Prüfung /\nprerequisites for the\nexamination\n\nErfolgreiche Teilnahme am Projekt / Successful participation in\nproject\nPrüfungsform /\nform of examination\n\nProjektprüfung /\nProject examination\nBenotet, Stellenwert der Note\nfür die Endnote /\ngraded, value of the grade for\nthe final grade\n\nBenotet: Ja / Is graded: Yes\n\n5/90 bzw. 5/120 / 5/90 resp. 5/120\nVoraussetzungen zur\nCreditvergabe/ requirements for\nawarding credit:\n\nBestandene Modulprüfung / Passed module examination\n\nLernergebnisse, Kompetenzen:\n\n\nStudierende können Video und Computergrafik unter Live-\nBedingungen in Produktionen verbinden. Hierzu gehört die\nErstellung fiktiver Umgebungen, in die Menschen und\nGegenstande versetzt werden. Sie können Virtuelle Studios\nentwickeln, aufbauen und einsetzen. Die grundlegenden\nTechnologien wie z.B. Tracking, Computergrafik können\nangepasst und bewertet werden.\n\n\n\n\nHochschule Düsseldorf\nModulhandbuch M.Sc. Medieninformatik\nVersion 1.0\nPO 2025\n52\n\n\nEnglish descriptions\nLehrinhalte:\nZu den Themen gehören:\nWirkung künstlich erstellter Realitätsebenen, irrealer Szenenbilder\nund virtueller Kulissen\nHard- und Software für digitale Studioproduktionstechnik\nLicht und Beleuchtung im Virtuellen Studio, Lichtschätzung\nKamera- und Darstellerverfolgungssysteme (Tracking)\nSet Design\nBewegungsaufzeichnung (auch markerlos)\nEchtzeitgenerierung dreidimensionaler Computergraphik, visuelle\nEffekte\nHerauslösen von Bildelementen (z.B. Chromakeying)\nEinbindung von Animationen und virtuellen Charakteren/Avataren\nInteraktion im Virtuellen Studio\nFeedbackmethoden für Darsteller\nProduktionsplanung, Automatisierung und\nProduktionsdurchführung\n\nLiteratur:\n\n\nS. Gibbs: Virtual Studios, IEEE MultiMedia 5, 1 (January 1998),\n17-17. DOI=http://dx.doi.org/10.1109/MMUL.1998.664739\nA. R. Smith and J. F. Blinn: Blue screen matting. In Proceedings\nof the 23rd annual conference on Computer graphics and\ninteractive techniques (SIGGRAPH '96), ACM, New York, NY,\nUSA, 259-268. DOI=http://dx.doi.org/10.1145/237170.237263\nR. Brinkmann: The Art and Science of Digital Compositing,\nMorgan Kaufman, lis Group (März 2000)\nM. Moshkovitz: The Virtual Studio Technology & Techniques,\nFocal Press (2000)\nP. Tucker: Secrets of Screen Acting, Routlege (1994)\nD. Arijon: Grammar of the Film Language, Silman-James Press\n(1976)\nU. Schmidt: Professionelle Videotechnik: Analoge und Digitale\nGrundlagen, Filmtechnik, Fernsehtechnik, HDTV, Kameras,\nDisplays, Videorecorder, Produktion und Studiotechnik, Springer\n(2005)\nJournal of Virtual Reality and Broadcasting, www.jvrb.org\n\nLearning outcomes,\ncompetences\n\n\nSuccessful participants will have a profound knowledge in\nbuilding and developing virtual set environments for\nbroadcasting applications and will be able to evaluate virtual\nstudio (TV) technology. Tracking, composition of video and\ncomputer graphics under live conditions for media productions\nare essential part.\n\nContent\n\n\nTopics include:\nApplication and use of virtual sets\nHard- and software for digital (TV) studio productions\nLight and light setting for TV studios\nCamera and actor tracking systems\nVirtual set design for artificial or real scenes\nMotion capture\nReal-time computer graphics and effects\nSeparation of image elements (e.g., chroma keying)\n\nHochschule Düsseldorf\nModulhandbuch M.Sc. Medieninformatik\nVersion 1.0\nPO 2025\n53\n\n\nIntegration of animations and virtual characters/avatars\nInteraction within a virtual tv studio\nFeedback methods for actors\nStudio production planning\n\nHochschule Düsseldorf\nModulhandbuch M.Sc. Medieninformatik\nVersion 1.0\nPO 2025\n54", "metadata": {"moduleNumber": "MMI 05.08", "moduleName": "Interactive Virtual Studio", "creditPoints": "5.0", "suggestedSemester": 1, "offeredInSeason": "winter_semester", "examType": "project", "heldInLanguage": "en_on_demand", "reviserName": "Prof. Dr. Eng. Univ. of Tsukuba Jens Herder", "reviserEmail": "jens.herder@hs-duesseldorf.de", "studyProgramId": 11, "source_type": "json", "moduleNameDe": "Interaktives Virtuelles Studio", "source_file": "MMI_MHB_PO2025_V1.0.pdf", "pdf_page_start": 51, "pdf_page_end": 53, "studyProgramAbbrev": "MMI", "studyProgram_Url": "https://medien.hs-duesseldorf.de/mmi", "pdf_url": "https://medien.hs-duesseldorf.de/studium/studiengaenge/Documents/Modulhandb%C3%BCcher/MMI_MHB_PO2025_V1.0.pdf"}}
{"id": "MMI05.09", "text": "Title: VR and AR Systems\nModule Number: MMI 05.09\nCredits: 5.0 CP\nSemester: 2\nOffered In: summer_semester\nLanguage: en_on_demand\nExam Type: oral_exam\nInstructor: Prof. Dr. Eng. Univ. of Tsukuba Jens Herder (jens.herder@hs-duesseldorf.de)\n--- Goals (EN) ---\nSuccessful participants will have a profound knowledge in building and developing VR and AR systems and will be able to evaluate application based on VR and AR technology. Specific base technology (e.g., tracking) can be further developed and new VR and AR concepts can be implemented.\n--- Goals (DE) ---\nStudierende beherrschen die wichtigsten VR / AR-Technologien (Virtual Reality / Augmented Reality) und sind in der Lage, virtuelle Umgebungen und Augmented Reality-Anwendungen zu konzipieren, aufzubauen und zu bewerten. Studierende können einzelne Basistechnologien (z.B. Tracking) weiterentwickeln und neue VR/AR-Konzepte umsetzten.\n--- Contents (EN) ---\n- Motivation, definitions, Layout and design of VR and AR systems\n- Applications in VR and AR\n- Multimodal cues\n- Augmented Reality\n- Advanced display technology for mixed reality\n- Advanded input and output devices\n- Hybrid tracking for users, objects and environments\n- Navigation and interaction in VR\n- Haptic\n- Virtual acoustics for realtime applications\n- Scene modeling (scene graph based ) and programming\n- Data structures and algorithmes für VR and AR\n- Rapid prototyping and tools for VR/AR systems\n--- Contents (DE) ---\n- Motivation / Begriffsdefinition / Aufbau von VR/AR-Systemen\n- Aktuelle Anwendungsgebiete\n- Multimodalen Wahrnehmungsfaktoren\n- Augmented Reality\n- Fortgeschrittenen Darstellungstechniken (u.a. Mixed Reality)\n- Fortgeschrittene Ein- und Ausgabegeräte für VR/AR\n- Hybrides Tracking von Benutzern, Objekten und Umgebungen\n- Navigation und Interaktionstechniken\n- Haptik\n- Virtuelle Akustik für Echtzeitanwendungen\n- VR/AR-Szenenmodellierung und Programmierung\n- Datenstrukturen und Algorithmen für VR/AR Umgebungen\n- Entwurf und Werkzeuge für VR/AR-Systemen\n--- Literature (EN) ---\n- R. Dörner, W. Broll, P. Grimm, B. Jung, Virtual and Augmented Reality (VR/AR), Foundations and Methods of Extended Realities (XR), Springer, 2022, DOI 10.1007/978-3-030-79062-2\n- Jason Jerald. The VR Book: Human-Centered Design for Virtual Reality. Association for Computing Machinery and Morgan & Claypool, New York, NY, USA. 2015, DOI 10.1145/2792790\n- G. C. Burdea, P. Coiffet: Virtual Reality Technology, John Wiley & Sons, 3. Auflage, 2024, ISBN 978-1-118-01480-6\n- M. Guiterrez, F. Vexo, D. Thalman: Stepping into Virtual Reality, Springer Nature Verlag, 2. Ausgabe, 2023, DOI 10.1007/978-3-031-36487-7\n- W. Sherman, A. Craig: Understanding Virtual Reality - Interface, Application, and Design, Morgan Kaufman, 2. Auflage, 2018, DOI 10.1016/C2013-0-18583-2\n- J. Vince: Introduction to Virtual Reality, Springer 2004, DOI 10.1007/978-0-85729-386-2\n- J. Blauert: Spatial Hearing - The Psychophysics of Human Sound Localization, The MIT Press, Revised Edition, 1996, ISBN 0-262-02413-6\n- T. Akenine-Möller, E. Haines und N. Hoffman: Real- Time Rendering, A.K. Peters Ltd., 2008, ISBN 978-1-56881-424-7\n- O. Bimber and R. Raskar: Spatial Augmented Reality - Merging Real and Virtual Worlds, A K Peters LTD, 2005, DOI 10.1201/b10624\n- C. Ericson, Real-Time Collision Detection, Morgan Kaufmann Series in Interactive 3D Technology, 2005, ISBN 1-55860-732-3\n- Thorsten A. Kern, Christian Hatzfeld, Alireza Abbasimoshaei (Editors): Engineering Haptic Devices, Springer (2023), DOI: 10.1007/978-3-031-04536-3\n\n\nFurther literature will be announced at the beginning of the lecture.\n--- Literature (DE) ---\n- R. Dörner, W. Broll, P. Grimm, B. Jung (Hrsg.): Virtual und Augmented Reality (VR/AR), Grundlagen und Methoden der Virtuellen und Augmentierten Realität, Springer, 2019, DOI 10.1007/978-3-662-58861-1\n- Jason Jerald. The VR Book: Human-Centered Design for Virtual Reality. Association for Computing Machinery and Morgan & Claypool, New York, NY, USA. 2015, DOI 10.1145/2792790\n- G. C. Burdea, P. Coiffet: Virtual Reality Technology, John Wiley & Sons, 3. Auflage, 2024, ISBN 978-1-118-01480-6\n- M. Guiterrez, F. Vexo, D. Thalman: Stepping into Virtual Reality, Springer Nature Verlag, 2. Ausgabe, 2023, DOI 10.1007/978-3-031-36487-7\n- W. Sherman, A. Craig: Understanding Virtual Reality - Interface, Application, and Design, Morgan Kaufman, 2. Auflage, 2018, DOI 10.1016/C2013-0-18583-2\n- J. Vince: Introduction to Virtual Reality, Springer 2004, DOI 10.1007/978-0-85729-386-2\n- J. Blauert: Spatial Hearing - The Psychophysics of Human Sound Localization, The MIT Press, Revised Edition, 1996, ISBN 0-262-02413-6\n- T. Akenine-Möller, E. Haines und N. Hoffman: Real- Time Rendering, A.K. Peters Ltd., 2008, ISBN 978-1-56881-424-7\n- O. Bimber und R. Raskar: Spatial Augmented Reality - Merging Real and Virtual Worlds, A K Peters LTD, 2005, DOI 10.1201/b10624\n- C. Ericson, Real-Time Collision Detection, Morgan Kaufmann Series in Interactive 3D Technology, 2005, ISBN 1-55860-732-3\n- T. A. Kern (Hrsg.): Entwicklung Haptischer Geräte - Ein Einstieg für Ingenieure, Springer, 2009, ISBN: 978-3-540-87643-4\n\nWeitere Literatur zu speziellen Gebieten wird in der Vorlesung bekannt gegeben.\n\nMMI 05.09 - VR und AR Systeme\nVR and AR Systems\nModulbeauftragte*r\nResponsible\nJens Herder\nDozent*in\nTeaching staff\nLehrende*r der Hochschule Düsseldorf\nStudiengang\nM.Sc. Medieninformatik 2025\nVerwendung in anderen\nStudiengängen: / Used in other\nstudy programmes\nM.Sc. Medieninformatik, PO 2018 /\nM.Sc. Media Informatics, PO 2018\n\n\nLehrformen (alle Angaben in SWS zu je 45 Minuten / all values in SWS of 45 minutes each)\n\nCredits/\nCredits\nWorkload /\nWorkload\nKontaktzeit/\nContact time\nSelbststudium/\nSelf study\nDauer/\nLength\nSemester/\nSemester\nSprache/\nLanguage\n5\n150 h\n\n60 h\n90 h\n1 Sem.\n2\nEnglish on\ndemand\nVorlesung/\nLecture\nÜbung/\nPractice\nSeminar/\nSeminar\nPraktiku\nm/ Lab\nwork\nProjekt/\nProject\nTutorium/\nTutorial\nSeminarist.\nUnterricht/\nSeminaristic\nlesson\nStudien\narbeit/\nResearch\nproject\nBegleitetes\nSelbstlernen/\nAccompan‘d\nself study\n1\n\n1\n1\n1\n\n\n\n\nModulkategorie / category\n\nWahlangebot / Module offer\nWahlkatalog(e) /\n\n/\nelective catalogue(s)\n\n\nVoraussetzungen zur Teilnahme /\nrequirements for participation\n\n\nFormal /\nFormal\n\nKeine /\nnone\n\nInhaltlich /\ncontentwise\n\nKeine /\nnone\nVoraussetzungen zur Prüfung /\nprerequisites for the\nexamination\n\nErfolgreiche Teilnahme am Seminar und Praktikum und Projekt /\nSuccessful participation in seminar and lab work and project\nPrüfungsform /\nform of examination\n\nMündliche Prüfung/Fachgespräch /\nOral examination\nBenotet, Stellenwert der Note\nfür die Endnote /\ngraded, value of the grade for\nthe final grade\n\nBenotet: Ja / Is graded: Yes\n\n5/90 bzw. 5/120 / 5/90 resp. 5/120\nVoraussetzungen zur\nCreditvergabe/ requirements for\nawarding credit:\n\nBestandene Modulprüfung / Passed module examination\n\nLernergebnisse, Kompetenzen:\n\n\nStudierende beherrschen die wichtigsten VR / AR-Technologien\n(Virtual Reality / Augmented Reality) und sind in der Lage,\nvirtuelle Umgebungen und Augmented Reality-Anwendungen zu\nkonzipieren, aufzubauen und zu bewerten. Studierende können\neinzelne Basistechnologien (z.B. Tracking) weiterentwickeln und\nneue VR/AR-Konzepte umsetzten.\n\nLehrinhalte:\n\n\n- Motivation / Begriffsdefinition / Aufbau von VR/AR-Systemen\n\nHochschule Düsseldorf\nModulhandbuch M.Sc. Medieninformatik\nVersion 1.0\nPO 2025\n55\n\n\nEnglish descriptions\n- Aktuelle Anwendungsgebiete\n- Multimodalen Wahrnehmungsfaktoren\n- Augmented Reality\n- Fortgeschrittenen Darstellungstechniken (u.a. Mixed Reality)\n- Fortgeschrittene Ein- und Ausgabegeräte für VR/AR\n- Hybrides Tracking von Benutzern, Objekten und Umgebungen\n- Navigation und Interaktionstechniken\n- Haptik\n- Virtuelle Akustik für Echtzeitanwendungen\n- VR/AR-Szenenmodellierung und Programmierung\n- Datenstrukturen und Algorithmen für VR/AR Umgebungen\n- Entwurf und Werkzeuge für VR/AR-Systemen\n\nLiteratur:\n\n\n- R. Dörner, W. Broll, P. Grimm, B. Jung (Hrsg.): Virtual und\nAugmented Reality (VR/AR), Grundlagen und Methoden der\nVirtuellen und Augmentierten Realität, Springer, 2019, DOI\n10.1007/978-3-662-58861-1\n- G. C. Burdea und P. Coiffet: Virtual Reality Technology, John\nWiley & Sons, 2. Auflage (2003)\n- M. Guiterrez, F. Vexo, D. Thalman: Stepping into Virtual Reality,\nSpringer (2008)\n- W. Sherman, A. Craig: Understanding Virtual Reality, Morgan\nKaufman (2002)\n- T. Akenine-Möller, E. Haines und N. Hoffman: Real- Time\nRendering, A.K. Peters Ltd. (2008), ISBN 978-1-56881-424-7\n- O. Bimber und R. Raskar: Spatial Augmented Reality - Merging\nReal and Virtual Worlds, A K Peters LTD\n- J. Vince: Introduction to Virtual Reality, Springer (2004)\n- C. Ericson, Real-Time Collision Detection, Morgan Kaufmann\nSeries in Interactive 3D Technology (2005)\n- T. A. Kern (Hrsg.): Entwicklung Haptischer Geräte - Ein Einstieg\nfür Ingenieure, Springer (2009), ISBN: 978-3-540-87643-4\n- J. Blauert: Räumliches Hören / Spatial Hearing, The MIT Press,\nRevised Edition (1996), ISBN 0-262-02413-6\n\nWeitere Literatur zu speziellen Gebieten wird in der Vorlesung\nbekannt gegeben.\n\nLearning outcomes,\ncompetences\n\n\nSuccessful participants will have a profound knowledge in\nbuilding and developing VR and AR systems and will be able to\nevaluate application based on VR and AR technology. Specific\nbase technology (e.g., tracking) can be further developed and\nnew VR and AR concepts can be implemented.\n\nContent\n\n\n- Motivation, definitions, Layout and design of VR and AR\nsystems\n- Applications in VR and AR\n- Multimodal cues\n- Augmented Reality\n- Advanced display technology for mixed reality\n- Advanded input and output devices\n- Hybrid tracking for users, objects and environments\n\nHochschule Düsseldorf\nModulhandbuch M.Sc. Medieninformatik\nVersion 1.0\nPO 2025\n56\n\n\n- Navigation and interaction in VR\n- Haptic\n- Virtual acoustics for realtime applications\n- Scene modeling (scene graph based ) and programming\n- Data structures and algorithmes für VR and AR\n- Rapid prototyping and tools for VR/AR systems\n\nHochschule Düsseldorf\nModulhandbuch M.Sc. Medieninformatik\nVersion 1.0\nPO 2025\n57", "metadata": {"moduleNumber": "MMI 05.09", "moduleName": "VR and AR Systems", "creditPoints": "5.0", "suggestedSemester": 2, "offeredInSeason": "summer_semester", "examType": "oral_exam", "heldInLanguage": "en_on_demand", "reviserName": "Prof. Dr. Eng. Univ. of Tsukuba Jens Herder", "reviserEmail": "jens.herder@hs-duesseldorf.de", "studyProgramId": 11, "source_type": "json", "moduleNameDe": "VR und AR Systeme", "source_file": "MMI_MHB_PO2025_V1.0.pdf", "pdf_page_start": 54, "pdf_page_end": 56, "studyProgramAbbrev": "MMI", "studyProgram_Url": "https://medien.hs-duesseldorf.de/mmi", "pdf_url": "https://medien.hs-duesseldorf.de/studium/studiengaenge/Documents/Modulhandb%C3%BCcher/MMI_MHB_PO2025_V1.0.pdf"}}
{"id": "MMI05.10", "text": "Title: Real-Time Rendering\nModule Number: MMI 05.10\nCredits: 5.0 CP\nSemester: 2\nOffered In: summer_semester\nLanguage: en_on_demand\nExam Type: project\nInstructor: Prof. Dr. Eng. Univ. of Tsukuba Jens Herder (jens.herder@hs-duesseldorf.de)\n--- Goals (EN) ---\nSuccessful participants will have developed skills for literature research, documentation and presentation as well as the ability to compare objectively different approaches to scientific problems. Participants gain profound insides to realtime rendering for virtual environments.\n--- Goals (DE) ---\nSpezielle Algorithmen und Verfahren zur Echtzeit-Computergrafik kennen, Methodische Entwicklung eigener Verfahren, Einsatz in relevanten Anwendungsfeldern beurteilen und umsetzen können, Anforderungen an Computerhardware erstellen und beurteilen können.\n--- Contents (EN) ---\n- Architecture of graphic hardware\n- Rendering pipeline and optimization\n- Shader (Pixel, Vertex, ...)\n- Image operations using shader\n- Shadow algorithms\n- Real-time raytracing\n- Selected topics for realtime graphics like advance collision detection, continouse level of detail, image based rendering, non photorealistic renderig, efficient modelling procedures\n--- Contents (DE) ---\n- Architektur von Grafikhardware\n- Render Pipeline und Optimierung\n- Shader (Pixel, Vertex, ...)\n- Bildoperatoren per Shader\n- Schattenalgorithmen\n- Realtime Raytracing\n- Ausgewählte Algorithmen zur 3D-Echtzeitgrafik, z. B. Fortgeschrittene Kollisionserkennung, Kontinuierlicher Level of Detail, Image-based Rendering, Nicht photorealistisches Rendering, Effiziente Modellierungsverfahren\n--- Literature (EN) ---\n- T. Akenine-Möller, E. Haines, N. Hoffman, A. Pesce, M. Iwanicki, und S. Hillaire: Real-Time Rendering, 4th Ed, A.K. Peters/CRC Press (2018).\n- E. Haines und T. Akenine-Möller: Ray Tracing Gems, Apress (2019).\n- R. Fernando: GPU Gems I+II, Addison-Wesley Professional (2004/05)\n- S. St. Laurent: Shaders for Game Programmers and Artists, Premier Press (2004)\n- T. Strothotte, S. Schlechtweg: Non-Photorealistic Computer Graphics, Morgan Kaufmann Publisher (2002)\n--- Literature (DE) ---\n- T. Akenine-Möller, E. Haines, N. Hoffman, A. Pesce, M. Iwanicki, und S. Hillaire: Real-Time Rendering, 4th Ed, A.K. Peters/CRC Press (2018).\n- E. Haines und T. Akenine-Möller: Ray Tracing Gems, Apress (2019).\n- R. Fernando: GPU Gems I+II, Addison-Wesley Professional (2004/05)\n- S. St. Laurent: Shaders for Game Programmers and Artists, Premier Press (2004)\n- T. Strothotte, S. Schlechtweg: Non-Photorealistic Computer Graphics, Morgan Kaufmann Publisher (2002)\n\nMMI 05.10 - Realtime Rendering\nReal-Time Rendering\nModulbeauftragte*r\nResponsible\nJens Herder\nDozent*in\nTeaching staff\nLehrende*r der Hochschule Düsseldorf\nStudiengang\nM.Sc. Medieninformatik 2025\nVerwendung in anderen\nStudiengängen: / Used in other\nstudy programmes\nM.Sc. Medieninformatik, PO 2018 /\nM.Sc. Media Informatics, PO 2018\n\n\nLehrformen (alle Angaben in SWS zu je 45 Minuten / all values in SWS of 45 minutes each)\n\nCredits/\nCredits\nWorkload /\nWorkload\nKontaktzeit/\nContact time\nSelbststudium/\nSelf study\nDauer/\nLength\nSemester/\nSemester\nSprache/\nLanguage\n5\n150 h\n\n60 h\n90 h\n1 Sem.\n2\nEnglish on\ndemand\nVorlesung/\nLecture\nÜbung/\nPractice\nSeminar/\nSeminar\nPraktiku\nm/ Lab\nwork\nProjekt/\nProject\nTutorium/\nTutorial\nSeminarist.\nUnterricht/\nSeminaristic\nlesson\nStudien\narbeit/\nResearch\nproject\nBegleitetes\nSelbstlernen/\nAccompan‘d\nself study\n1\n\n1\n1\n1\n\n\n\n\nModulkategorie / category\n\nWahlangebot / Module offer\nWahlkatalog(e) /\n\n/\nelective catalogue(s)\n\n\nVoraussetzungen zur Teilnahme /\nrequirements for participation\n\n\nFormal /\nFormal\n\nKeine /\nnone\n\nInhaltlich /\ncontentwise\n\nKeine /\nnone\nVoraussetzungen zur Prüfung /\nprerequisites for the\nexamination\n\nErfolgreiche Teilnahme am Seminar und Praktikum und Projekt /\nSuccessful participation in seminar and lab work and project\nPrüfungsform /\nform of examination\n\nProjektprüfung /\nProject examination\nBenotet, Stellenwert der Note\nfür die Endnote /\ngraded, value of the grade for\nthe final grade\n\nBenotet: Ja / Is graded: Yes\n\n5/90 bzw. 5/120 / 5/90 resp. 5/120\nVoraussetzungen zur\nCreditvergabe/ requirements for\nawarding credit:\n\nBestandene Modulprüfung / Passed module examination\n\nLernergebnisse, Kompetenzen:\n\n\nSpezielle Algorithmen und Verfahren zur Echtzeit-Computergrafik\nkennen, Methodische Entwicklung eigener Verfahren, Einsatz in\nrelevanten Anwendungsfeldern beurteilen und umsetzen können,\nAnforderungen an Computerhardware erstellen und beurteilen\nkönnen.\n\nLehrinhalte:\n\n\n- Architektur von Grafikhardware\n- Render Pipeline und Optimierung\n\nHochschule Düsseldorf\nModulhandbuch M.Sc. Medieninformatik\nVersion 1.0\nPO 2025\n58\n\n\nEnglish descriptions\n\n- Shader (Pixel, Vertex, ...)\n- Bildoperatoren per Shader\n- Schattenalgorithmen\n- Realtime Raytracing\n- Ausgewählte Algorithmen zur 3D-Echtzeitgrafik, z. B.\nFortgeschrittene Kollisionserkennung, Kontinuierlicher Level of\nDetail, Image-based Rendering, Nicht photorealistisches\nRendering, Effiziente Modellierungsverfahren\n\nLiteratur:\n\n\n- T. Akenine-Möller, E. Haines, N. Hoffman, A. Pesce, M. Iwanicki,\nund S. Hillaire: Real-Time Rendering, 4th Ed, A.K. Peters/CRC\nPress (2018).\n- E. Haines und T. Akenine-Möller: Ray Tracing Gems, Apress\n(2019).\n- R. Fernando: GPU Gems I+II, Addison-Wesley Professional\n(2004/05)\n- S. St. Laurent: Shaders for Game Programmers and Artists,\nPremier Press (2004)\n- T. Strothotte, S. Schlechtweg: Non-Photorealistic Computer\nGraphics, Morgan Kaufmann Publisher (2002)\n\nLearning outcomes,\ncompetences\n\n\nSuccessful participants will have developed skills for literature\nresearch, documentation and presentation as well as the ability\nto compare objectively different approaches to scientific\nproblems. Participants gain profound insides to realtime\nrendering for virtual environments.\n\nContent\n\n\n- Architecture of graphic hardware\n- Rendering pipeline and optimization\n- Shader (Pixel, Vertex, ...)\n- Image operations using shader\n- Shadow algorithms\n- Real-time raytracing\n- Selected topics for realtime graphics like advance collision\ndetection, continouse level of detail, image based rendering, non\nphotorealistic renderig, efficient modelling procedures\n\nHochschule Düsseldorf\nModulhandbuch M.Sc. Medieninformatik\nVersion 1.0\nPO 2025\n59", "metadata": {"moduleNumber": "MMI 05.10", "moduleName": "Real-Time Rendering", "creditPoints": "5.0", "suggestedSemester": 2, "offeredInSeason": "summer_semester", "examType": "project", "heldInLanguage": "en_on_demand", "reviserName": "Prof. Dr. Eng. Univ. of Tsukuba Jens Herder", "reviserEmail": "jens.herder@hs-duesseldorf.de", "studyProgramId": 11, "source_type": "json", "moduleNameDe": "Realtime Rendering", "source_file": "MMI_MHB_PO2025_V1.0.pdf", "pdf_page_start": 57, "pdf_page_end": 58, "studyProgramAbbrev": "MMI", "studyProgram_Url": "https://medien.hs-duesseldorf.de/mmi", "pdf_url": "https://medien.hs-duesseldorf.de/studium/studiengaenge/Documents/Modulhandb%C3%BCcher/MMI_MHB_PO2025_V1.0.pdf"}}
{"id": "MMI05.11", "text": "Title: Computer Animation\nModule Number: MMI 05.11\nCredits: 5.0 CP\nSemester: 1\nOffered In: to_be_announced\nLanguage: de\nExam Type: oral_exam\nInstructor: Prof. Dr.-Ing. Sina Mostafawy (sina.mostafawy@hs-duesseldorf.de)\n--- Goals (EN) ---\nThe students master general and special procedures in the field of computer animation.Theoretical and mathematical basics of 3D animation.Various methods of data acquisition and data generation for animations.Real-time rendering vs. classic rendering methods. Additionally they will learn to prepare and give a presentation about a scientific topic of computeranimation.\n--- Goals (DE) ---\nDie Student:innen beherrschen allgemeine und spezielle Verfahren aus dem Bereich der Computeranimation. Theoretisch-mathematische Grundlagen der 3D-Animation, verschiedene Verfahren der Datenerzeugung für Animationen und Echtzeitrendering. Zusätzlich wird ein dem Kurs gelernt wie ein Vortrag recherchiert, vorbereitet und vor Publikum gehlaten wird.\n--- Contents (EN) ---\n- 12 Basic Principles of Animation \n- Rotation with Quaternions\n- Forward and Inverse Kinematics\n- Partikelanimation and Swarm Simulation\n- Deformation & Morphing Algorithms\n- Rigid- und Soft Bodies\n- Planing und Production of Animations\n--- Contents (DE) ---\n- 12 Basic Principles of Animation \n- Rotation with Quaternions\n- Forward and Inverse Kinematics\n- Partikelanimation and Swarm Simulation\n- Deformation & Morphing Algorithms\n- Rigid- und Soft Bodies\n- Planing und Production of Animations\n--- Literature (EN) ---\n- Computer Animation: Algorithms and Techniques, Rick Parent, 3rd 2012 \n- Advanced Animation and Renderning Techniques: Alan Watt, Mark Watt, Addision Wesley\n- Real-Time Rendering, Eric Haines, 4th 2020Computer Graphics with Open GL, Pearson Prentice Hall, 4th 2013\n--- Literature (DE) ---\n- Computer Animation: Algorithms and Techniques, Rick Parent, 3rd 2012 \n- Advanced Animation and Renderning Techniques: Alan Watt, Mark Watt, Addision Wesley\n- Real-Time Rendering, Eric Haines, 4th 2020Computer Graphics with Open GL, Pearson Prentice Hall, 4th 2013\n\nMMI 05.11 - Computer Animation\nComputer Animation\nModulbeauftragte*r\nResponsible\nSina Mostafawy\nDozent*in\nTeaching staff\nLehrende*r der Hochschule Düsseldorf\nStudiengang\nM.Sc. Medieninformatik 2025\nVerwendung in anderen\nStudiengängen: / Used in other\nstudy programmes\nB.Sc. Medieninformatik, PO 2018\nB.Eng. Medientechnik, PO 2018\nM.Sc. Medieninformatik, PO 2018\nB.Sc. Medieninformatik, PO 2025\nB.Eng. Medientechnik, PO 2025\nB.A. Creative, Synthetic & Interactive Media, PO 2026\nB.Eng. Ton und Bild, PO 2025 /\nB.Sc. Media Informatics, PO 2018\nB.Eng. Media Engineering, PO 2018\nM.Sc. Media Informatics, PO 2018\nB.Sc. Media Informatics, PO 2025\nB.Eng. Media Engineering, PO 2025\nB.A. Creative, Synthetic & Interactive Media, PO 2026\nB.Eng. Audio and Video, PO 2025\n\n\nLehrformen (alle Angaben in SWS zu je 45 Minuten / all values in SWS of 45 minutes each)\n\nCredits/\nCredits\nWorkload /\nWorkload\nKontaktzeit/\nContact time\nSelbststudium/\nSelf study\nDauer/\nLength\nSemester/\nSemester\nSprache/\nLanguage\n5\n150 h\n\n60 h\n90 h\n1 Sem.\n1\nDeutsch\nVorlesung/\nLecture\nÜbung/\nPractice\nSeminar/\nSeminar\nPraktiku\nm/ Lab\nwork\nProjekt/\nProject\nTutorium/\nTutorial\nSeminarist.\nUnterricht/\nSeminaristic\nlesson\nStudien\narbeit/\nResearch\nproject\nBegleitetes\nSelbstlernen/\nAccompan‘d\nself study\n2\n2\n\n\n\n\n\n\n\nModulkategorie / category\n\nWahlangebot / Module offer\nWahlkatalog(e) /\n\n/\nelective catalogue(s)\n\n\nVoraussetzungen zur Teilnahme /\nrequirements for participation\n\n\nFormal /\nFormal\n\nKeine /\nnone\n\nInhaltlich /\ncontentwise\n\nKeine /\nnone\nVoraussetzungen zur Prüfung /\nprerequisites for the\nexamination\n\nErfolgreiche Teilnahme an der Übung und am Praktikum /\nSuccessful participation in exercise and lab work\nPrüfungsform /\nform of examination\n\nMündliche Prüfung/Fachgespräch /\nOral examination\nBenotet, Stellenwert der Note\nfür die Endnote /\ngraded, value of the grade for\nthe final grade\n\nBenotet: Ja / Is graded: Yes\n\n5/90 bzw. 5/120 / 5/90 resp. 5/120\n\nHochschule Düsseldorf\nModulhandbuch M.Sc. Medieninformatik\nVersion 1.0\nPO 2025\n60\n\n\nEnglish descriptions\n\nVoraussetzungen zur\nCreditvergabe/ requirements for\nawarding credit:\n\nBestandene Modulprüfung / Passed module examination\n\nLernergebnisse, Kompetenzen:\n\n\nDie Student:innen beherrschen allgemeine und spezielle\nVerfahren aus dem Bereich der Computeranimation. Theoretisch-\nmathematische Grundlagen der 3D-Animation, verschiedene\nVerfahren der Datenerzeugung für Animationen und\nEchtzeitrendering. Zusätzlich wird ein dem Kurs gelernt wie ein\nVortrag recherchiert, vorbereitet und vor Publikum gehlaten wird.\n\nLehrinhalte:\n\n\n12 Basic Principles of Animation\nRotation with Quaternions\nForward and Inverse Kinematics\nPartikelanimation and Swarm Simulation\nDeformation & Morphing Algorithms\nRigid- und Soft Bodies\nPlaning und Production of Animations\n\nLiteratur:\n\n\nComputer Animation: Algorithms and Techniques, Rick Parent,\n3rd 2012\nAdvanced Animation and Renderning Techniques: Alan Watt,\nMark Watt, Addision Wesley\nReal-Time Rendering, Eric Haines, 4th 2020Computer Graphics\nwith Open GL, Pearson Prentice Hall, 4th 2013\n\nLearning outcomes,\ncompetences\n\n\nThe students master general and special procedures in the field\nof computer animation.Theoretical and mathematical basics of\n3D animation.Various methods of data acquisition and data\ngeneration for animations.Real-time rendering vs. classic\nrendering methods. Additionally they will learn to prepare and\ngive a presentation about a scientific topic of\ncomputeranimation.\n\nContent\n\n\n12 Basic Principles of Animation\nRotation with Quaternions\nForward and Inverse Kinematics\nPartikelanimation and Swarm Simulation\nDeformation & Morphing Algorithms\nRigid- und Soft Bodies\nPlaning und Production of Animations\n\nHochschule Düsseldorf\nModulhandbuch M.Sc. Medieninformatik\nVersion 1.0\nPO 2025\n61", "metadata": {"moduleNumber": "MMI 05.11", "moduleName": "Computer Animation", "creditPoints": "5.0", "suggestedSemester": 1, "offeredInSeason": "to_be_announced", "examType": "oral_exam", "heldInLanguage": "de", "reviserName": "Prof. Dr.-Ing. Sina Mostafawy", "reviserEmail": "sina.mostafawy@hs-duesseldorf.de", "studyProgramId": 11, "source_type": "json", "moduleNameDe": "Computer Animation", "source_file": "MMI_MHB_PO2025_V1.0.pdf", "pdf_page_start": 59, "pdf_page_end": 60, "studyProgramAbbrev": "MMI", "studyProgram_Url": "https://medien.hs-duesseldorf.de/mmi", "pdf_url": "https://medien.hs-duesseldorf.de/studium/studiengaenge/Documents/Modulhandb%C3%BCcher/MMI_MHB_PO2025_V1.0.pdf"}}
{"id": "MMI05.12", "text": "Title: Character Production\nModule Number: MMI 05.12\nCredits: 5.0 CP\nSemester: 2\nOffered In: to_be_announced\nLanguage: de\nExam Type: project\nInstructor: Prof. Dr. rer. nat. Christian Geiger (geiger@hs-duesseldorf.de)\n--- Goals (EN) ---\nThe students know the fields of application of character production and can list and assess prominent examples. They know all steps in the process to produce virtual characters as well as basic techniques for selected steps. They can apply these techniques independently using relevant tools. The students can design a character independently, step by step, based on a concept. They can define criteria for a successful character production and assess both characters produced by themselves and others.\n--- Goals (DE) ---\nDie Studierenden kennen die Einsatzgebiete der Charakterproduktion und können prominente Beispiele nennen und diese bewerten. Sie kennen alle Arbeitsschritte des Produktionsprozesses bei der Erstellung virtueller Charaktere und die grundlegenden Techniken ausgewählter Arbeitsschritte. Diese können sie in auch selbständig mit relevanten Werkzeugen anwenden. Den Entwurf eines Charakters über alle Entwicklungsschritte ausgehend von einem Konzept können die Studierenden selbständig umsetzen und Kriterien einer gelungenen Charakterproduktion formulieren und existierende eigene und fremde Arbeiten bewerten.\n--- Contents (EN) ---\nHistory of character production and milestones of the genreOverview of current examplesProcess of and different steps in character production (workflow and pipeline)Tools and production environmentSelected techniques of character production (modelling, texturing, rigging, skinning, animation and simulation, rendering and output)Integration into larger projects (films, games, installations)Distribution formatsAnalysis and assessmentPrinciples of design and profitability analysis\n--- Contents (DE) ---\nHistorie der Charakterproduktion und Meilensteine des GenresÜbersicht aktueller BeispieleProduktionsprozess und Arbeitsschritte der Charakterproduktion (Workflow und Pipeline)Werkzeuge und ProduktionsumgebungenAusgewählte Techniken der Charakterproduktion (Modellierung, Texturierung, Rigging, Skinning, Animation / Simulation, Rendering / Output)Integration in größere Projekte (Film, Games, Installation)DistributionsformateAnalyse und BewertungGestaltungsprinzipien und Wirtschaftlichkeitsbetrachtungen\n--- Literature (EN) ---\n--- Literature (DE) ---\nRichard Willimas: The Animator's Survival Kit: A Manual of Methods, Principles and Formulas for Classical, Computer, Games, Stop Motion and Internet Animator, 4th ed, Farrar, Straus and Giroux (2012)Parag Chaudhuri, Prem Kalra, Subhashis Banerjee: View-Dependent Character Animation, Springer (2009)Eric Allen et al: Body Language: Advanced 3D Character Rigging, Sybex (2008)Jason Opira: Stop Staring - Facial Modeling and Animation Done Right, 3rd Edition, Sybex (2010)Chris Legaspi: Anatomy for 3D Artists: The Essential Guide for CG Professionals, 3DTotal Publishing (2015)\n\nMMI 05.12 - Charakter Produktion\nCharacter Production\nModulbeauftragte*r\nResponsible\nChristian Geiger\nDozent*in\nTeaching staff\nLehrende*r der Hochschule Düsseldorf\nStudiengang\nM.Sc. Medieninformatik 2025\nVerwendung in anderen\nStudiengängen: / Used in other\nstudy programmes\nM.Sc. Medieninformatik, PO 2018 /\nM.Sc. Media Informatics, PO 2018\n\n\nLehrformen (alle Angaben in SWS zu je 45 Minuten / all values in SWS of 45 minutes each)\n\nCredits/\nCredits\nWorkload /\nWorkload\nKontaktzeit/\nContact time\nSelbststudium/\nSelf study\nDauer/\nLength\nSemester/\nSemester\nSprache/\nLanguage\n5\n150 h\n\n60 h\n90 h\n1 Sem.\n2\nDeutsch\nVorlesung/\nLecture\nÜbung/\nPractice\nSeminar/\nSeminar\nPraktiku\nm/ Lab\nwork\nProjekt/\nProject\nTutorium/\nTutorial\nSeminarist.\nUnterricht/\nSeminaristic\nlesson\nStudien\narbeit/\nResearch\nproject\nBegleitetes\nSelbstlernen/\nAccompan‘d\nself study\n\n\n1\n\n3\n\n\n\n\nModulkategorie / category\n\nWahlangebot / Module offer\nWahlkatalog(e) /\n\n/\nelective catalogue(s)\n\n\nVoraussetzungen zur Teilnahme /\nrequirements for participation\n\n\nFormal /\nFormal\n\nKeine /\nnone\n\nInhaltlich /\ncontentwise\n\nKeine /\nnone\nVoraussetzungen zur Prüfung /\nprerequisites for the\nexamination\n\nKeine / None\nPrüfungsform /\nform of examination\n\nProjektprüfung /\nProject examination\nBenotet, Stellenwert der Note\nfür die Endnote /\ngraded, value of the grade for\nthe final grade\n\nBenotet: Ja / Is graded: Yes\n\n5/90 bzw. 5/120 / 5/90 resp. 5/120\nVoraussetzungen zur\nCreditvergabe/ requirements for\nawarding credit:\n\nBestandene Modulprüfung / Passed module examination\n\nLernergebnisse, Kompetenzen:\n\n\nDie Studierenden kennen die Einsatzgebiete der\nCharakterproduktion und können prominente Beispiele nennen\nund diese bewerten. Sie kennen alle Arbeitsschritte des\nProduktionsprozesses bei der Erstellung virtueller Charaktere und\ndie grundlegenden Techniken ausgewählter Arbeitsschritte. Diese\nkönnen sie in auch selbständig mit relevanten Werkzeugen\nanwenden. Den Entwurf eines Charakters über alle\nEntwicklungsschritte ausgehend von einem Konzept können die\n\nHochschule Düsseldorf\nModulhandbuch M.Sc. Medieninformatik\nVersion 1.0\nPO 2025\n62\n\n\nEnglish descriptions\n\nStudierenden selbständig umsetzen und Kriterien einer\ngelungenen Charakterproduktion formulieren und existierende\neigene und fremde Arbeiten bewerten.\n\nLehrinhalte:\n\n\nHistorie der Charakterproduktion und Meilensteine des\nGenresÜbersicht aktueller BeispieleProduktionsprozess und\nArbeitsschritte der Charakterproduktion (Workflow und\nPipeline)Werkzeuge und ProduktionsumgebungenAusgewählte\nTechniken der Charakterproduktion (Modellierung, Texturierung,\nRigging, Skinning, Animation / Simulation, Rendering /\nOutput)Integration in größere Projekte (Film, Games,\nInstallation)DistributionsformateAnalyse und\nBewertungGestaltungsprinzipien und\nWirtschaftlichkeitsbetrachtungen\n\nLiteratur:\n\n\nRichard Willimas: The Animator's Survival Kit: A Manual of\nMethods, Principles and Formulas for Classical, Computer,\nGames, Stop Motion and Internet Animator, 4th ed, Farrar, Straus\nand Giroux (2012)Parag Chaudhuri, Prem Kalra, Subhashis\nBanerjee: View-Dependent Character Animation, Springer\n(2009)Eric Allen et al: Body Language: Advanced 3D Character\nRigging, Sybex (2008)Jason Opira: Stop Staring - Facial Modeling\nand Animation Done Right, 3rd Edition, Sybex (2010)Chris\nLegaspi: Anatomy for 3D Artists: The Essential Guide for CG\nProfessionals, 3DTotal Publishing (2015)\n\nLearning outcomes,\ncompetences\n\n\nThe students know the fields of application of character\nproduction and can list and assess prominent examples. They\nknow all steps in the process to produce virtual characters as\nwell as basic techniques for selected steps. They can apply\nthese techniques independently using relevant tools. The\nstudents can design a character independently, step by step,\nbased on a concept. They can define criteria for a successful\ncharacter production and assess both characters produced by\nthemselves and others.\n\nContent\n\n\nHistory of character production and milestones of the\ngenreOverview of current examplesProcess of and different\nsteps in character production (workflow and pipeline)Tools and\nproduction environmentSelected techniques of character\nproduction (modelling, texturing, rigging, skinning, animation and\nsimulation, rendering and output)Integration into larger projects\n(films, games, installations)Distribution formatsAnalysis and\nassessmentPrinciples of design and profitability analysis\n\nHochschule Düsseldorf\nModulhandbuch M.Sc. Medieninformatik\nVersion 1.0\nPO 2025\n63", "metadata": {"moduleNumber": "MMI 05.12", "moduleName": "Character Production", "creditPoints": "5.0", "suggestedSemester": 2, "offeredInSeason": "to_be_announced", "examType": "project", "heldInLanguage": "de", "reviserName": "Prof. Dr. rer. nat. Christian Geiger", "reviserEmail": "geiger@hs-duesseldorf.de", "studyProgramId": 11, "source_type": "json", "moduleNameDe": "Charakter Produktion", "source_file": "MMI_MHB_PO2025_V1.0.pdf", "pdf_page_start": 61, "pdf_page_end": 62, "studyProgramAbbrev": "MMI", "studyProgram_Url": "https://medien.hs-duesseldorf.de/mmi", "pdf_url": "https://medien.hs-duesseldorf.de/studium/studiengaenge/Documents/Modulhandb%C3%BCcher/MMI_MHB_PO2025_V1.0.pdf"}}
{"id": "MMI05.13", "text": "Title: Ambient Assisted Living\nModule Number: MMI 05.13\nCredits: 5.0 CP\nSemester: None\nOffered In: to_be_announced\nLanguage: en_on_demand\nExam Type: written_exam\nInstructor: Prof. Dr. Manfred Wojciechowski (manfred.wojciechowski@hs-duesseldorf.de)\n--- Goals (EN) ---\nThe students know the basic concepts of ambient assisted living (AAL) solutions. They can describe the application domains, benefits and restrictions of AAL technology. They can develop sociotechnical concepts and implement prototypes. The students are able to read relevant scientific publications and put them into the right context of AAL.\n--- Goals (DE) ---\nThe student knows the basic concepts of AAL solutions. He/she can describe the application domains, benefits and restrictions of AAL technology. He/she can develop socio-technical concepts and implement prototypes. The student is able to read relevant scientific publications and place them into the right context of AAL.\n--- Contents (EN) ---\nLearning ObjectivesTheoryObjectives of AAL, demographic backgroundTechnology aspectsSmart EnvironmentsContext AwarenessKnowledge RepresentationInfrastructureInteroperabilityApplication domainsHome careRestrictionsPracticeDeveloping an AAL solution Scientific workReading and discussing scientific publicationsEnglishScientific community in AAL\n--- Contents (DE) ---\nLearning ObjectivesTheoryObjectives of AAL, demographic backgroundTechnology aspectsSmart EnvironmentsContext AwarenessKnowledge RepresentationInfrastructureInteroperabilityApplication domainsHome careRestrictionsPracticeDeveloping an AAL solution Scientific workReading and discussing scientific publicationsEnglishScientific community in AAL\n--- Literature (EN) ---\n--- Literature (DE) ---\nWill be given during the lectures\n\nMMI 05.13 - Ambient Assisted Living\nAmbient Assisted Living\nModulbeauftragte*r\nResponsible\nManfred Wojciechowski\nDozent*in\nTeaching staff\nLehrende*r der Hochschule Düsseldorf\nStudiengang\nM.Sc. Medieninformatik 2025\nVerwendung in anderen\nStudiengängen: / Used in other\nstudy programmes\nM.Sc. Medieninformatik, PO 2018 /\nM.Sc. Media Informatics, PO 2018\n\n\nLehrformen (alle Angaben in SWS zu je 45 Minuten / all values in SWS of 45 minutes each)\n\nCredits/\nCredits\nWorkload /\nWorkload\nKontaktzeit/\nContact time\nSelbststudium/\nSelf study\nDauer/\nLength\nSemester/\nSemester\nSprache/\nLanguage\n5\n150 h\n\n60 h\n90 h\n1 Sem.\n\nEnglish on\ndemand\nVorlesung/\nLecture\nÜbung/\nPractice\nSeminar/\nSeminar\nPraktiku\nm/ Lab\nwork\nProjekt/\nProject\nTutorium/\nTutorial\nSeminarist.\nUnterricht/\nSeminaristic\nlesson\nStudien\narbeit/\nResearch\nproject\nBegleitetes\nSelbstlernen/\nAccompan‘d\nself study\n2\n\n\n\n2\n\n\n\n\nModulkategorie / category\n\nWahlangebot / Module offer\nWahlkatalog(e) /\n\n/\nelective catalogue(s)\n\n\nVoraussetzungen zur Teilnahme /\nrequirements for participation\n\n\nFormal /\nFormal\n\nKeine /\nnone\n\nInhaltlich /\ncontentwise\n\nKeine /\nnone\nVoraussetzungen zur Prüfung /\nprerequisites for the\nexamination\n\nErfolgreiche Teilnahme am Projekt / Successful participation in\nproject\nPrüfungsform /\nform of examination\n\nKlausurarbeit /\nWritten examination\nBenotet, Stellenwert der Note\nfür die Endnote /\ngraded, value of the grade for\nthe final grade\n\nBenotet: Ja / Is graded: Yes\n\n5/90 bzw. 5/120 / 5/90 resp. 5/120\nVoraussetzungen zur\nCreditvergabe/ requirements for\nawarding credit:\n\nBestandene Modulprüfung / Passed module examination\n\nLernergebnisse, Kompetenzen:\n\n\nThe student knows the basic concepts of AAL solutions. He/she\ncan describe the application domains, benefits and restrictions of\nAAL technology. He/she can develop socio-technical concepts\nand implement prototypes. The student is able to read relevant\nscientific publications and place them into the right context of AAL.\n\nLehrinhalte:\n\n\nLearning ObjectivesTheoryObjectives of AAL, demographic\nbackgroundTechnology aspectsSmart EnvironmentsContext\n\nHochschule Düsseldorf\nModulhandbuch M.Sc. Medieninformatik\nVersion 1.0\nPO 2025\n64\n\n\nEnglish descriptions\n\nAwarenessKnowledge\nRepresentationInfrastructureInteroperabilityApplication\ndomainsHome careRestrictionsPracticeDeveloping an AAL\nsolution Scientific workReading and discussing scientific\npublicationsEnglishScientific community in AAL\n\nLiteratur:\n\n\nWill be given during the lectures\n\nLearning outcomes,\ncompetences\n\n\nThe students know the basic concepts of ambient assisted living\n(AAL) solutions. They can describe the application domains,\nbenefits and restrictions of AAL technology. They can develop\nsociotechnical concepts and implement prototypes. The students\nare able to read relevant scientific publications and put them into\nthe right context of AAL.\n\nContent\n\n\nLearning ObjectivesTheoryObjectives of AAL, demographic\nbackgroundTechnology aspectsSmart EnvironmentsContext\nAwarenessKnowledge\nRepresentationInfrastructureInteroperabilityApplication\ndomainsHome careRestrictionsPracticeDeveloping an AAL\nsolution Scientific workReading and discussing scientific\npublicationsEnglishScientific community in AAL\n\nHochschule Düsseldorf\nModulhandbuch M.Sc. Medieninformatik\nVersion 1.0\nPO 2025\n65", "metadata": {"moduleNumber": "MMI 05.13", "moduleName": "Ambient Assisted Living", "creditPoints": "5.0", "suggestedSemester": null, "offeredInSeason": "to_be_announced", "examType": "written_exam", "heldInLanguage": "en_on_demand", "reviserName": "Prof. Dr. Manfred Wojciechowski", "reviserEmail": "manfred.wojciechowski@hs-duesseldorf.de", "studyProgramId": 11, "source_type": "json", "moduleNameDe": "Ambient Assisted Living", "source_file": "MMI_MHB_PO2025_V1.0.pdf", "pdf_page_start": 63, "pdf_page_end": 64, "studyProgramAbbrev": "MMI", "studyProgram_Url": "https://medien.hs-duesseldorf.de/mmi", "pdf_url": "https://medien.hs-duesseldorf.de/studium/studiengaenge/Documents/Modulhandb%C3%BCcher/MMI_MHB_PO2025_V1.0.pdf"}}
{"id": "MMI05.14", "text": "Title: Music Informatics\nModule Number: MMI 05.14\nCredits: 5.0 CP\nSemester: 2\nOffered In: summer_semester\nLanguage: de\nExam Type: project\nInstructor: Prof. Dr.-Ing. Jochen Steffens (jochen.steffens@hs-duesseldorf.de)\n--- Goals (EN) ---\nThe students have an application-oriented overview of the field of music informatics. This includes particularly music information retrieval (MIR) as well as sound synthesis and musical interfaces. The students master basic concepts and methods of MIR. They know the fields of application and can apply standard tools (e.g. MIRtoolbox) to conduct analyses (e.g. feature extraction for audio signals, audio identification, audio matching).They also master the basic concepts of different kinds of sound synthesis and can apply these to environments for music and multimedia development (e.g. in MAX/MSP). A focus is on common technology to realise interactions between humans and (electrical) musical instruments using musical interfaces or sensors.\n--- Goals (DE) ---\nDie Studierenden erhalten einen anwendungsbezogenen Überblick über das Feld der Musikinformatik. Dabei stehen die Gebiete des Music Information Retrieval (MIR) sowie der Klangsynthese und musikalischen Interfaces im Mittelpunkt. Die Studierenden beherrschen die Grundbegriffe und Methoden des MIR. Sie kennen die Anwendungsgebiete und können mit Hilfe von Standardwerkzeugen (z.B. MIRtoolbox) selbst verschiedene Analysen durchführen (z.B. Merkmalsextraktion für Audiosignale, Audioidentifikation, Audio Matching). Des Weiteren beherrschen die Studierenden die grundlegenden Konzepte verschiedener Klangsynthesearten und können diese in Entwicklungsumgebungen für Musik und Multimedia anwenden (z.B. in Max/MSP). Ein Schwerpunkt liegt dabei auf den gängigen Technologien zur Realisierung der Interaktion zwischen Mensch und (elektronischem) Musikinstrument mittels musikalischer Interfaces bzw. Sensoren.\n--- Contents (EN) ---\nMusic information retrieval (MIR)Fundamentals of MIRStandard tools of MIR (e.g. MIRtoolbox, Auditory toolbox, SOM toolbox)Application of MIR (e.g. music recommendation systems, classification of sounds and music, automatic instrument and genre recognition, automatic transcription and notation systems)Computational auditory scene analysis (CASA), sound synthesis and musical interfacesElectrical and electronic musical instrumentsAnalogue and digital sound synthesisAudio programming (e.g. in Max/MSP, Csound, Pure Data, NI Reaktor), live electronicsMusical interfacesSensor and controller environmentsCommunication protocols for musical applications (e.g. Open Sound Control (OSC), MIDI, HD Protocol, mLAN)\n--- Contents (DE) ---\nMusic Information RetrievalGrundlagen des Music Information Retrieval (MIR)Standardwerkzeuge des MIR (z.B. MIRtoolbox, Auditory toolbox, SOM toolbox)Anwendungen des Music Information Retrieval (u.a. Musikalische Empfehlungsdienste, Klassifikation von Klängen/Musik, automatische Instrumenten- und Genreerkennung, automatische Transkriptions- und Notationssysteme)CASA - Computational Auditory Scene Analysis, Klangsynthese und musikalische InterfacesElektrische und elektronische MusikinstrumenteAnaloge und digitale KlangsyntheseAudio-Programmierung (z.B. mit Max/MSP, Csound, Pure Data, NI Reaktor) / Live-ElektronikMusikalische InterfacesSensor- und Controllerumgebungen Kommunikationsprotokolle für musikalische Anwendungen (z.B. Open Sound Control (OSC), MIDI, HD Protocol, mLAN)\n--- Literature (EN) ---\n--- Literature (DE) ---\nBeauchamp, J. W.: Analysis, synthesis, and perception of musical sounds : the sound of music, New York Springer (2007)Boulanger, R.: The Csound Book: Perspectives in Software Synthesis, Sound Design, Signal Processing, and Programming. Cambridge MIT Press (2000)Mazzola, G. B.: Elemente der Musikinformatik. Basel Birkhäuser (2006)Miranda, E. R.: Computer sound design: synthesis techniques and programming. Oxford Focal Press (2002)Müller, M.: Information Retrieval for Music and Motion. Berlin Springer (2007)Russ, M.: Sound Synthesis and Sampling. Oxford Focal Press (2009)Wang, D. L. Brown, G. J.: Computational auditory scene analysis: Principles, algorithms and applications. IEEE Press (2006)Aktuelle Publikationen aus folgenden Konferenzen: ICMC, ICMPC, IEEE, ISMIR, NIME\n\nMMI 05.14 - Musikinformatik\nMusic Informatics\nModulbeauftragte*r\nResponsible\nJochen Steffens\nDozent*in\nTeaching staff\nLehrende*r der Hochschule Düsseldorf\nStudiengang\nM.Sc. Medieninformatik 2025\nVerwendung in anderen\nStudiengängen: / Used in other\nstudy programmes\nM.Sc. Medieninformatik, PO 2018 /\nM.Sc. Media Informatics, PO 2018\n\n\nLehrformen (alle Angaben in SWS zu je 45 Minuten / all values in SWS of 45 minutes each)\n\nCredits/\nCredits\nWorkload /\nWorkload\nKontaktzeit/\nContact time\nSelbststudium/\nSelf study\nDauer/\nLength\nSemester/\nSemester\nSprache/\nLanguage\n5\n150 h\n\n60 h\n90 h\n1 Sem.\n2\nDeutsch\nVorlesung/\nLecture\nÜbung/\nPractice\nSeminar/\nSeminar\nPraktiku\nm/ Lab\nwork\nProjekt/\nProject\nTutorium/\nTutorial\nSeminarist.\nUnterricht/\nSeminaristic\nlesson\nStudien\narbeit/\nResearch\nproject\nBegleitetes\nSelbstlernen/\nAccompan‘d\nself study\n2\n\n\n\n2\n\n\n\n\nModulkategorie / category\n\nWahlangebot / Module offer\nWahlkatalog(e) /\n\n/\nelective catalogue(s)\n\n\nVoraussetzungen zur Teilnahme /\nrequirements for participation\n\n\nFormal /\nFormal\n\nKeine /\nnone\n\nInhaltlich /\ncontentwise\n\nKeine /\nnone\nVoraussetzungen zur Prüfung /\nprerequisites for the\nexamination\n\nKeine / None\nPrüfungsform /\nform of examination\n\nProjektprüfung /\nProject examination\nBenotet, Stellenwert der Note\nfür die Endnote /\ngraded, value of the grade for\nthe final grade\n\nBenotet: Ja / Is graded: Yes\n\n5/90 bzw. 5/120 / 5/90 resp. 5/120\nVoraussetzungen zur\nCreditvergabe/ requirements for\nawarding credit:\n\nBestandene Modulprüfung / Passed module examination\n\nLernergebnisse, Kompetenzen:\n\n\nDie Studierenden erhalten einen anwendungsbezogenen\nÜberblick über das Feld der Musikinformatik. Dabei stehen die\nGebiete des Music Information Retrieval (MIR) sowie der\nKlangsynthese und musikalischen Interfaces im Mittelpunkt. Die\nStudierenden beherrschen die Grundbegriffe und Methoden des\nMIR. Sie kennen die Anwendungsgebiete und können mit Hilfe\nvon Standardwerkzeugen (z.B. MIRtoolbox) selbst verschiedene\nAnalysen durchführen (z.B. Merkmalsextraktion für Audiosignale,\n\nHochschule Düsseldorf\nModulhandbuch M.Sc. Medieninformatik\nVersion 1.0\nPO 2025\n66\n\n\nEnglish descriptions\nAudioidentifikation, Audio Matching). Des Weiteren beherrschen\ndie Studierenden die grundlegenden Konzepte verschiedener\nKlangsynthesearten und können diese in\nEntwicklungsumgebungen für Musik und Multimedia anwenden\n(z.B. in Max/MSP). Ein Schwerpunkt liegt dabei auf den gängigen\nTechnologien zur Realisierung der Interaktion zwischen Mensch\nund (elektronischem) Musikinstrument mittels musikalischer\nInterfaces bzw. Sensoren.\n\nLehrinhalte:\n\n\nMusic Information RetrievalGrundlagen des Music Information\nRetrieval (MIR)Standardwerkzeuge des MIR (z.B. MIRtoolbox,\nAuditory toolbox, SOM toolbox)Anwendungen des Music\nInformation Retrieval (u.a. Musikalische Empfehlungsdienste,\nKlassifikation von Klängen/Musik, automatische Instrumenten-\nund Genreerkennung, automatische Transkriptions- und\nNotationssysteme)CASA - Computational Auditory Scene\nAnalysis, Klangsynthese und musikalische InterfacesElektrische\nund elektronische MusikinstrumenteAnaloge und digitale\nKlangsyntheseAudio-Programmierung (z.B. mit Max/MSP,\nCsound, Pure Data, NI Reaktor) / Live-ElektronikMusikalische\nInterfacesSensor- und Controllerumgebungen\nKommunikationsprotokolle für musikalische Anwendungen (z.B.\nOpen Sound Control (OSC), MIDI, HD Protocol, mLAN)\n\nLiteratur:\n\n\nBeauchamp, J. W.: Analysis, synthesis, and perception of musical\nsounds : the sound of music, New York Springer\n(2007)Boulanger, R.: The Csound Book: Perspectives in Software\nSynthesis, Sound Design, Signal Processing, and Programming.\nCambridge MIT Press (2000)Mazzola, G. B.: Elemente der\nMusikinformatik. Basel Birkhäuser (2006)Miranda, E. R.:\nComputer sound design: synthesis techniques and programming.\nOxford Focal Press (2002)Müller, M.: Information Retrieval for\nMusic and Motion. Berlin Springer (2007)Russ, M.: Sound\nSynthesis and Sampling. Oxford Focal Press (2009)Wang, D. L.\nBrown, G. J.: Computational auditory scene analysis: Principles,\nalgorithms and applications. IEEE Press (2006)Aktuelle\nPublikationen aus folgenden Konferenzen: ICMC, ICMPC, IEEE,\nISMIR, NIME\n\nLearning outcomes,\ncompetences\n\n\nThe students have an application-oriented overview of the field\nof music informatics. This includes particularly music information\nretrieval (MIR) as well as sound synthesis and musical\ninterfaces. The students master basic concepts and methods of\nMIR. They know the fields of application and can apply standard\ntools (e.g. MIRtoolbox) to conduct analyses (e.g. feature\nextraction for audio signals, audio identification, audio\nmatching).They also master the basic concepts of different kinds\nof sound synthesis and can apply these to environments for\nmusic and multimedia development (e.g. in MAX/MSP). A focus\nis on common technology to realise interactions between\nhumans and (electrical) musical instruments using musical\ninterfaces or sensors.\n\nHochschule Düsseldorf\nModulhandbuch M.Sc. Medieninformatik\nVersion 1.0\nPO 2025\n67\n\n\n\nContent\n\n\nMusic information retrieval (MIR)Fundamentals of MIRStandard\ntools of MIR (e.g. MIRtoolbox, Auditory toolbox, SOM\ntoolbox)Application of MIR (e.g. music recommendation\nsystems, classification of sounds and music, automatic\ninstrument and genre recognition, automatic transcription and\nnotation systems)Computational auditory scene analysis\n(CASA), sound synthesis and musical interfacesElectrical and\nelectronic musical instrumentsAnalogue and digital sound\nsynthesisAudio programming (e.g. in Max/MSP, Csound, Pure\nData, NI Reaktor), live electronicsMusical interfacesSensor and\ncontroller environmentsCommunication protocols for musical\napplications (e.g. Open Sound Control (OSC), MIDI, HD\nProtocol, mLAN)\n\nHochschule Düsseldorf\nModulhandbuch M.Sc. Medieninformatik\nVersion 1.0\nPO 2025\n68", "metadata": {"moduleNumber": "MMI 05.14", "moduleName": "Music Informatics", "creditPoints": "5.0", "suggestedSemester": 2, "offeredInSeason": "summer_semester", "examType": "project", "heldInLanguage": "de", "reviserName": "Prof. Dr.-Ing. Jochen Steffens", "reviserEmail": "jochen.steffens@hs-duesseldorf.de", "studyProgramId": 11, "source_type": "json", "moduleNameDe": "Musikinformatik", "source_file": "MMI_MHB_PO2025_V1.0.pdf", "pdf_page_start": 65, "pdf_page_end": 67, "studyProgramAbbrev": "MMI", "studyProgram_Url": "https://medien.hs-duesseldorf.de/mmi", "pdf_url": "https://medien.hs-duesseldorf.de/studium/studiengaenge/Documents/Modulhandb%C3%BCcher/MMI_MHB_PO2025_V1.0.pdf"}}
{"id": "MMI05.15", "text": "Title: Media Conception\nModule Number: MMI 05.15\nCredits: 5.0 CP\nSemester: 1\nOffered In: winter_semester\nLanguage: de\nExam Type: portfolio\nInstructor: Prof. Gabriele Schwab-Trapp (gabi.schwab-trapp@hs-duesseldorf.de)\n--- Goals (EN) ---\nThe students have acquired skills to apply a conceptual approach to individual or applied topics. They are able to independently develop contextual content. The students have learned to use design processes to develop and practically implement their own ideas. They have gained experience in creative and constructive cooperation within the seminar and potentially within project groups. They have also practised to deal with different presentation forms.\n--- Goals (DE) ---\nDie Studierenden erwerben Fähigkeiten im konzeptionellen Umgang mit freien oder angewandten Themen und die Befähigung zur selbstständigen Erarbeitung von kontextbezogenen Inhalten. Mithilfe von Gestaltungsprozessen werden die Entwicklung und die praktische Umsetzung eigener Ideen ermöglicht. Erfahrungen in interdisziplinärer, kreativer und konstruktiver Zusammenarbeit werden innerhalb der Seminar- und möglicher Projektgruppen sowie im Umgang mit verschiedenen Präsentationsformen gesammelt.\n--- Contents (EN) ---\nThe module focuses on individual or applied topics which will be communicated at the beginning of the semester. A seminar serves to go deeper into the topic and to develop it further, together with the lecturer and the other students. This includes philosophical, insight-oriented and opinion-forming debates. The goal is to develop contextual, visual concepts independently and realise them using different media. The students practise different forms of presentation depending on the topics and results. If excursions relevant to the topics are planned, they will be announced at the beginning of the semester. Media conception is regularly offered as an open, collaborative and interdisciplinary module with students from other departments.\n--- Contents (DE) ---\nInhaltlich werden freie oder angewandte Themen behandelt, die zu Beginn des Semesters vorgestellt werden. Die gemeinsame Vertiefung, Entwicklung und Entfaltung des Themas findet in Seminarform statt. Dazu gehört auch die philosophische, erkenntnisorientierte und meinungsbildende Auseinandersetzung. Ziel ist die selbstständige Entwicklung und Umsetzung von kontextbezogenen, visuellen Konzepten in unterschiedlichen Medien. Den Themen und Ergebnissen entsprechend werden verschiedene Präsentationsformen eingeübt. Themenunterstützend können Exkursionen stattfinden, die zu Beginn des Semesters bekannt gegeben werden. Medienkonzeption wird regelmäßig als offenes, kollaboratives und interdisziplinäres Modul mit Studierenden aus anderen Fachbereichen angeboten.\n--- Literature (EN) ---\nMaterial and literature references are provided for the respective topic in the seminar. Information in the form of text extracts, literature, image examples and research suggestions are provided to support the respective learning, realisation and design steps.\n--- Literature (DE) ---\nMaterial- und Literaturangaben werden zu dem jeweiligen Thema im Seminar ausgegeben. Zur Unterstützung der jeweiligen Lern-, Erkenntnis- und Gestaltungsschritte werden Hinweise in Form von Textauszügen, Literatur, Bildbeispielen und Recherchevorschlägen gegeben.\n\nMMI 05.15 - Medienkonzeption\nMedia Conception\nModulbeauftragte*r\nResponsible\nProf.  Gabriele Schwab-Trapp\nDozent*in\nTeaching staff\nLehrende*r der Hochschule Düsseldorf\nStudiengang\nM.Sc. Medieninformatik 2025\nVerwendung in anderen\nStudiengängen: / Used in other\nstudy programmes\nM.Sc. Medieninformatik, PO 2018 /\nM.Sc. Media Informatics, PO 2018\n\n\nLehrformen (alle Angaben in SWS zu je 45 Minuten / all values in SWS of 45 minutes each)\n\nCredits/\nCredits\nWorkload /\nWorkload\nKontaktzeit/\nContact time\nSelbststudium/\nSelf study\nDauer/\nLength\nSemester/\nSemester\nSprache/\nLanguage\n5\n150 h\n\n60 h\n90 h\n1 Sem.\n1\nDeutsch\nVorlesung/\nLecture\nÜbung/\nPractice\nSeminar/\nSeminar\nPraktiku\nm/ Lab\nwork\nProjekt/\nProject\nTutorium/\nTutorial\nSeminarist.\nUnterricht/\nSeminaristic\nlesson\nStudien\narbeit/\nResearch\nproject\nBegleitetes\nSelbstlernen/\nAccompan‘d\nself study\n\n\n4\n\n\n\n\n\n\nModulkategorie / category\n\nWahlangebot / Module offer\nWahlkatalog(e) /\n\n/\nelective catalogue(s)\n\n\nVoraussetzungen zur Teilnahme /\nrequirements for participation\n\n\nFormal /\nFormal\n\nKeine /\nnone\n\nInhaltlich /\ncontentwise\n\nKeine /\nnone\nVoraussetzungen zur Prüfung /\nprerequisites for the\nexamination\n\nErfolgreiche Teilnahme am Seminar / Successful participation in\nseminar\nPrüfungsform /\nform of examination\n\nPortfolio-Abgabe und mündliche Prüfung /\nPortfolio submittal and oral examination\nBenotet, Stellenwert der Note\nfür die Endnote /\ngraded, value of the grade for\nthe final grade\n\nBenotet: Ja / Is graded: Yes\n\n5/90 bzw. 5/120 / 5/90 resp. 5/120\nVoraussetzungen zur\nCreditvergabe/ requirements for\nawarding credit:\n\nBestandene Modulprüfung / Passed module examination\n\nLernergebnisse, Kompetenzen:\n\n\nDie Studierenden erwerben Fähigkeiten im konzeptionellen\nUmgang mit freien oder angewandten Themen und die\nBefähigung zur selbstständigen Erarbeitung von\nkontextbezogenen Inhalten. Mithilfe von Gestaltungsprozessen\nwerden die Entwicklung und die praktische Umsetzung eigener\nIdeen ermöglicht. Erfahrungen in interdisziplinärer, kreativer und\nkonstruktiver Zusammenarbeit werden innerhalb der Seminar-\n\nHochschule Düsseldorf\nModulhandbuch M.Sc. Medieninformatik\nVersion 1.0\nPO 2025\n69\n\n\nEnglish descriptions\n\nund möglicher Projektgruppen sowie im Umgang mit\nverschiedenen Präsentationsformen gesammelt.\n\nLehrinhalte:\n\n\nInhaltlich werden freie oder angewandte Themen behandelt, die\nzu Beginn des Semesters vorgestellt werden. Die gemeinsame\nVertiefung, Entwicklung und Entfaltung des Themas findet in\nSeminarform statt. Dazu gehört auch die philosophische,\nerkenntnisorientierte und meinungsbildende Auseinandersetzung.\nZiel ist die selbstständige Entwicklung und Umsetzung von\nkontextbezogenen, visuellen Konzepten in unterschiedlichen\nMedien. Den Themen und Ergebnissen entsprechend werden\nverschiedene Präsentationsformen eingeübt.\nThemenunterstützend können Exkursionen stattfinden, die zu\nBeginn des Semesters bekannt gegeben werden.\nMedienkonzeption wird regelmäßig als offenes, kollaboratives und\ninterdisziplinäres Modul mit Studierenden aus anderen\nFachbereichen angeboten.\n\nLiteratur:\n\n\nMaterial- und Literaturangaben werden zu dem jeweiligen Thema\nim Seminar ausgegeben. Zur Unterstützung der jeweiligen Lern-,\nErkenntnis- und Gestaltungsschritte werden Hinweise in Form von\nTextauszügen, Literatur, Bildbeispielen und\nRecherchevorschlägen gegeben.\n\nLearning outcomes,\ncompetences\n\n\nThe students have acquired skills to apply a conceptual\napproach to individual or applied topics. They are able to\nindependently develop contextual content. The students have\nlearned to use design processes to develop and practically\nimplement their own ideas. They have gained experience in\ncreative and constructive cooperation within the seminar and\npotentially within project groups. They have also practised to\ndeal with different presentation forms.\n\nContent\n\n\nThe module focuses on individual or applied topics which will be\ncommunicated at the beginning of the semester. A seminar\nserves to go deeper into the topic and to develop it further,\ntogether with the lecturer and the other students. This includes\nphilosophical, insight-oriented and opinion-forming debates. The\ngoal is to develop contextual, visual concepts independently and\nrealise them using different media. The students practise\ndifferent forms of presentation depending on the topics and\nresults. If excursions relevant to the topics are planned, they will\nbe announced at the beginning of the semester. Media\nconception is regularly offered as an open, collaborative and\ninterdisciplinary module with students from other departments.\n\nHochschule Düsseldorf\nModulhandbuch M.Sc. Medieninformatik\nVersion 1.0\nPO 2025\n70", "metadata": {"moduleNumber": "MMI 05.15", "moduleName": "Media Conception", "creditPoints": "5.0", "suggestedSemester": 1, "offeredInSeason": "winter_semester", "examType": "portfolio", "heldInLanguage": "de", "reviserName": "Prof. Gabriele Schwab-Trapp", "reviserEmail": "gabi.schwab-trapp@hs-duesseldorf.de", "studyProgramId": 11, "source_type": "json", "moduleNameDe": "Medienkonzeption", "source_file": "MMI_MHB_PO2025_V1.0.pdf", "pdf_page_start": 68, "pdf_page_end": 69, "studyProgramAbbrev": "MMI", "studyProgram_Url": "https://medien.hs-duesseldorf.de/mmi", "pdf_url": "https://medien.hs-duesseldorf.de/studium/studiengaenge/Documents/Modulhandb%C3%BCcher/MMI_MHB_PO2025_V1.0.pdf"}}
{"id": "MMI05.16", "text": "Title: Machine-Learning for Digital Health & Social Services\nModule Number: MMI 05.16\nCredits: 5.0 CP\nSemester: 2\nOffered In: summer_semester\nLanguage: en_on_demand\nExam Type: portfolio\nInstructor: Prof. Dr. Florian Huber (florian.huber@hs-duesseldorf.de)\n--- Goals (EN) ---\nStudents are able to weigh up and apply the use of previously considered methods for data science and artificial intelligence for the application area of digital health and social services.\n--- Goals (DE) ---\nDie Studierenden sind in der Lage, den Einsatz zuvor betrachteter Methoden für Data Science und Künstliche Intelligenz für den Anwendungsbereich Digitale Gesundheit und Soziale Dienste abzuwägen und anzuwenden.\n--- Contents (EN) ---\nTechniques from the field of artificial intelligence, especially machine learning, offer numerous promising applications in digital health and social services. This is particularly true for the analysis and use of very large and complex data sets. Examples include medical diagnostics and prognostics, or the large-scale evaluation and linking of text and process data with the aim of optimising or improving processes in healthcare or social services. This event provides an overview of current and future developments in the field. Key machine learning methods will be implemented with real data from the healthcare and social services sectors in live coding sessions.\n- Overview of application areas and common methods in the field of digital health and social services\n- Handling of key data types in the above-mentioned areas: tabular data, image data, time series, text data\n- Conventional linear models in medicine\n- Prediction models of classical machine learning (including linear models, random forest)\n- Evaluation of models and explainable AI\n- Deep learning models (e.g. CNNs) for the classification and segmentation of image data.\n- Deep learning models for the classification of time series (e.g. CNNs, LSTMs).\n- Consideration of related ethical issues regarding the use of AI for critical applications (e.g. biases, interpretability, or privacy).\n--- Contents (DE) ---\nTechniken aus dem Bereich Künstliche Intelligenz, insbesondere Machine-Learning, bieten zahlreiche vielversprechende Einsatzmöglichkeiten im Bereich Digital Health und Social Services. Das gilt besonders für die Analyse und Nutzung von sehr großen und komplexer Datensätzen. Beispiele dafür sind die medizinische Diagnostik oder Prognose, oder der großflächigen Auswertung und Verknüpfung von Text- und Prozessdaten mit dem Ziel Abläufe im Gesundheitsbereich oder bei sozialen Diensten zu optimieren oder zu verbessern. Dieser Veranstaltung gibt einen Überblick über aktuelle und zukünftige Entwicklungen in dem Gebiet, Zentrale Machine-Learning Verfahren werden dabei mit realen Daten aus dem Bereich Gesundheit oder Social Services in Live Coding Sessions umgesetzt.\n- Überblick über Einsatzgebiete und gängige Verfahren im Bereich Digital Health und Social Services\n- Behandlung zentraler Datentypen in den genannten Bereichen: Tabellarische Daten, Bilddaten, Zeitserien, Textdaten\n- Konventionelle linear Modelle in der Medizin\n- Vorhersagemodelle des klassischen Machine Learnings (u.a. lineare Modelle, Random Forest).\n- Evaluation von Modellen und Explainable AI\n- Deep Learning Modelle (z.B. CNNs) zur Klassifizierung und Segmentierung von Bilddaten.\n- Deep Learning Modele zur Klassifizierung von Zeitserien (z.B. CNNs, LSTMs).\n- Betrachtung angrenzender ethischer Fragen zum Einsatz von KI für kritische Anwendungen (z.B. Biases, Interpretierbarkeit, oder Privatshäre).\n--- Literature (EN) ---\nScientific articles are shared and discussed as part of a journal club. Further literature will be announced at the beginning of the lecture.\n--- Literature (DE) ---\nIm Rahmen eines Journal-Clubs werden wissenschaftliche Fachartikel geteilt und besprochen. Weitere Literatur wird bei Vorlesungsbeginn bekannt gegeben.\n\nMMI 05.16 - Intelligente Systeme für Smart Health\nIntelligent Systems for Smart Health\nModulbeauftragte*r\nResponsible\nFlorian Huber\nDozent*in\nTeaching staff\nLehrende*r der Hochschule Düsseldorf\nStudiengang\nM.Sc. Medieninformatik 2025\nVerwendung in anderen\nStudiengängen: / Used in other\nstudy programmes\nB.Sc. Data Science, AI und Intelligente Systeme, PO\n2021\nM.Sc. Medieninformatik, PO 2018 /\nB.Sc. Data Science, AI and Intelligent Systems, PO\n2021\nM.Sc. Media Informatics, PO 2018\n\n\nLehrformen (alle Angaben in SWS zu je 45 Minuten / all values in SWS of 45 minutes each)\n\nCredits/\nCredits\nWorkload /\nWorkload\nKontaktzeit/\nContact time\nSelbststudium/\nSelf study\nDauer/\nLength\nSemester/\nSemester\nSprache/\nLanguage\n5\n150 h\n\n60 h\n90 h\n1 Sem.\n2\nDeutsch\nVorlesung/\nLecture\nÜbung/\nPractice\nSeminar/\nSeminar\nPraktiku\nm/ Lab\nwork\nProjekt/\nProject\nTutorium/\nTutorial\nSeminarist.\nUnterricht/\nSeminaristic\nlesson\nStudien\narbeit/\nResearch\nproject\nBegleitetes\nSelbstlernen/\nAccompan‘d\nself study\n\n\n2\n2\n\n\n\n\n\nModulkategorie / category\n\nWahlangebot / Module offer\nWahlkatalog(e) /\n\n/\nelective catalogue(s)\n\n\nVoraussetzungen zur Teilnahme /\nrequirements for participation\n\n\nFormal /\nFormal\n\nKeine /\nnone\n\nInhaltlich /\ncontentwise\n\nKeine /\nnone\nVoraussetzungen zur Prüfung /\nprerequisites for the\nexamination\n\nKeine / None\nPrüfungsform /\nform of examination\n\nPortfolio-Abgabe und mündliche Prüfung /\nPortfolio submittal and oral examination\nBenotet, Stellenwert der Note\nfür die Endnote /\ngraded, value of the grade for\nthe final grade\n\nBenotet: Ja / Is graded: Yes\n\n5/90 bzw. 5/120 / 5/90 resp. 5/120\nVoraussetzungen zur\nCreditvergabe/ requirements for\nawarding credit:\n\nBestandene Modulprüfung / Passed module examination\n\nLernergebnisse, Kompetenzen:\n\n\nDie Studierenden sind in der Lage, den Einsatz zuvor betrachteter\nMethoden für Data Science und Künstliche Intelligenz für den\nAnwendungsbereich Digitale Gesundheit abzuwägen und\nanzuwenden.\n\n\n\n\nHochschule Düsseldorf\nModulhandbuch M.Sc. Medieninformatik\nVersion 1.0\nPO 2025\n71\n\n\nEnglish descriptions\nLehrinhalte:\nInnerhalb des Anwendungsbereichs digitalen Gesundheit\nbeziehen sich Smart Health auf den Einsatz\ndatenwissenschaftlicher Techniken zur Erfassung und Analyse\nriesiger und komplexer Datensätze, um die Ergebnisse der\nPatientenversorgung bzw. generell Methoden im Bereich Public\nHealth positiv zu beeinflussen und die Geschäftsprozesse im\nGesundheitswesen zu optimieren. Des Weiteren werden in-\ntelligente Verfahren betrachtet, um Informationen zu extrahieren,\nneues Wissen zu erschließen und nutzeradaptive Systeme zu\ngestalten.\n- Grundlagen medizinischer Statistik (Deskriptive Statistik,\nInferenzstatistik, Studiendesign)\n- Behandlung zentraler (und im Medizin/Health-Bereich\nrelevanter) Datentypen: Tabellarische Daten, Bilddaten, Zeitserien\n- Konventionelle linear Modelle in der Medizin\n- Vorhersagemodelle des klassischen Machine Learnings (u.a.\nlineare Modelle, Random Forest).\n- Evaluation von Modellen und Explainable AI\n- Deep Learning Modelle (z.B. CNNs) zur Klassifizierung und\nSegmentierung von Bilddaten.\n- Deep Learning Modele zur Klassifizierung von Zeitserien (z.B.\nCNNs, LSTMs).\n- Betrachtung angrenzender ethischer Fragen zum Einsatz von KI\nfür medizinische Anwendun-gen (z.B. Biases, Interpretierbarkeit,\noder Privatshäre).\n\nLiteratur:\n\n\nIm Rahmen eines Journal-Clubs werden wissenschaftliche\nFachartikel geteilt und besprochen. Weitere Literatur wird bei\nVorlesungsbeginn bekannt gegeben.\n\nLearning outcomes,\ncompetences\n\n\nStudents are able to weigh up and apply the use of previously\nconsidered methods for data science and artificial intelligence for\nthe application area of digital health.\n\nContent\n\n\nWithin the application area of digital health, smart health refers\nto the use of data science techniques to collect and analyze\nhuge and complex data sets in order to positively influence the\nresults of patient care and public health methods in general and\nto optimize business processes in the healthcare sector.\nFurthermore, intelligent methods are considered in order to\nextract information, develop new knowledge and design user-\nadaptive systems.\n- Fundamentals of medical statistics (descriptive statistics,\ninferential statistics, study design)\n- Treatment of central (and in the medical/health sector relevant)\ndata types: Tabular data, image data, time series\n- Conventional linear models in medicine\n- Prediction models of classical machine learning (e.g. linear\nmodels, random forest).\n- Evaluation of models and explainable AI\n- Deep learning models (e.g. CNNs) for the classification and\nsegmentation of image data.\n\nHochschule Düsseldorf\nModulhandbuch M.Sc. Medieninformatik\nVersion 1.0\nPO 2025\n72\n\n\n- Deep learning models for the classification of time series (e.g.\nCNNs, LSTMs).\n- Consideration of related ethical questions on the use of AI for\nmedical applications (e.g. biases, interpretability, or privacy).\n\nHochschule Düsseldorf\nModulhandbuch M.Sc. Medieninformatik\nVersion 1.0\nPO 2025\n73", "metadata": {"moduleNumber": "MMI 05.16", "moduleName": "Machine-Learning for Digital Health & Social Services", "creditPoints": "5.0", "suggestedSemester": 2, "offeredInSeason": "summer_semester", "examType": "portfolio", "heldInLanguage": "en_on_demand", "reviserName": "Prof. Dr. Florian Huber", "reviserEmail": "florian.huber@hs-duesseldorf.de", "studyProgramId": 11, "source_type": "json", "moduleNameDe": "Intelligente Systeme für Smart Health", "source_file": "MMI_MHB_PO2025_V1.0.pdf", "pdf_page_start": 70, "pdf_page_end": 72, "studyProgramAbbrev": "MMI", "studyProgram_Url": "https://medien.hs-duesseldorf.de/mmi", "pdf_url": "https://medien.hs-duesseldorf.de/studium/studiengaenge/Documents/Modulhandb%C3%BCcher/MMI_MHB_PO2025_V1.0.pdf"}}
{"id": "MMI05.20", "text": "Title: Distributed Collaborative Systems\nModule Number: MMI 05.20\nCredits: 5.0 CP\nSemester: 1\nOffered In: winter_semester\nLanguage: de\nExam Type: portfolio\nInstructor: Prof. Dr.-Ing. Thomas Rakow (thomas.rakow@hs-duesseldorf.de)\n--- Goals (EN) ---\nThe students have acquired knowledge of distributed systems, their architecture, processes and applications. They are particularly familiar with the requirements of collaborative applications. They are able to evaluate distributed algorithms.\n--- Goals (DE) ---\nDie Teilnehmer erwerben Kenntnisse über die Architektur und Funktionsweise verteilter Systeme und Anwendungen, unter besonderer Berücksichtigung der Anforderungen kollaborativer Anwendungen. Verteilte Algorithmen können bewertet werden.\n--- Contents (EN) ---\nArchitecture of distributed systems\nProcesses and communication\nNaming systems\nSynchronisation in distributed systems\nConsistency and replication\nFault tolerance and security\nParadigms of distributed systems: file, object, coordination, streaming\nCooperation and collaboration\nComputer supported cooperative work\n--- Contents (DE) ---\nArchitekturen verteilter Systeme\nProzesse und Kommunikation\nBenennungs- und Namenssysteme\nSynchronisierung in verteilten Systemen\nKonsistenz und Replikation\nFehlertoleranz und Sicherheit\nParadigmen verteilter Systeme: Datei, Objekt, Koordination, Streaming\nKooperation und Kollaboration\n--- Literature (EN) ---\n--- Literature (DE) ---\nMaarten van Steen, Andrew S. Tanenbaum: Distributed Systems, 3rd Ed. Self-publishing 2017\nM. Tamer Özsu, Patrick Valduriez: Principles of Distributed Database Systems, 4th Ed., Springer 2020\nFranz Lehner: Wissensmanagement, 6. Aufl. Hanser (2019)\n\nMMI 05.20 - Verteilte kollaborative Systeme\nDistributed Collaborative Systems\nModulbeauftragte*r\nResponsible\nThomas Rakow\nDozent*in\nTeaching staff\nLehrende*r der Hochschule Düsseldorf\nStudiengang\nM.Sc. Medieninformatik 2025\nVerwendung in anderen\nStudiengängen: / Used in other\nstudy programmes\nM.Sc. Medieninformatik, PO 2018 /\nM.Sc. Media Informatics, PO 2018\n\n\nLehrformen (alle Angaben in SWS zu je 45 Minuten / all values in SWS of 45 minutes each)\n\nCredits/\nCredits\nWorkload /\nWorkload\nKontaktzeit/\nContact time\nSelbststudium/\nSelf study\nDauer/\nLength\nSemester/\nSemester\nSprache/\nLanguage\n5\n150 h\n\n90 h\n60 h\n1 Sem.\n1\nDeutsch\nVorlesung/\nLecture\nÜbung/\nPractice\nSeminar/\nSeminar\nPraktiku\nm/ Lab\nwork\nProjekt/\nProject\nTutorium/\nTutorial\nSeminarist.\nUnterricht/\nSeminaristic\nlesson\nStudien\narbeit/\nResearch\nproject\nBegleitetes\nSelbstlernen/\nAccompan‘d\nself study\n2\n\n1\n\n3\n\n\n\n\nModulkategorie / category\n\nWahlangebot / Module offer\nWahlkatalog(e) /\n\n/\nelective catalogue(s)\n\n\nVoraussetzungen zur Teilnahme /\nrequirements for participation\n\n\nFormal /\nFormal\n\nKeine /\nnone\n\nInhaltlich /\ncontentwise\n\nKenntnisse in Software Engineering, Datenbanksysteme,\nRechnernetze, Webanwendungen /\nKnowledge in software engineering, database systems, computer\nnetworks, web applications\nVoraussetzungen zur Prüfung /\nprerequisites for the\nexamination\n\nErfolgreiche Teilnahme am Portfolio / Successful participation in\nportfolio\nPrüfungsform /\nform of examination\n\nBearbeitung von Seminar-, Praktikums-, oder Übungsaufgaben\noder Laborversuchen (Portfolio) /\nPortfolio submittal or participation in laboratory experiments\nBenotet, Stellenwert der Note\nfür die Endnote /\ngraded, value of the grade for\nthe final grade\n\nBenotet: Ja / Is graded: Yes\n\n5/90 bzw. 5/120 / 5/90 resp. 5/120\nVoraussetzungen zur\nCreditvergabe/ requirements for\nawarding credit:\n\nBestandene Modulprüfung / Passed module examination\n\nLernergebnisse, Kompetenzen:\n\n\nDie Teilnehmer erwerben Kenntnisse über die Architektur und\nFunktionsweise verteilter Systeme und Anwendungen, unter\nbesonderer Berücksichtigung der Anforderungen kollaborativer\nAnwendungen. Verteilte Algorithmen können bewertet werden.\n\nLehrinhalte:\n\n\nArchitekturen verteilter Systeme\n\nHochschule Düsseldorf\nModulhandbuch M.Sc. Medieninformatik\nVersion 1.0\nPO 2025\n74\n\n\nEnglish descriptions\n\nProzesse und Kommunikation\nBenennungs- und Namenssysteme\nSynchronisierung in verteilten Systemen\nKonsistenz und Replikation\nFehlertoleranz und Sicherheit\nParadigmen verteilter Systeme: Datei, Objekt, Koordination,\nStreaming\nKooperation und Kollaboration\n\nLiteratur:\n\n\nMaarten van Steen, Andrew S. Tanenbaum: Distributed Systems,\n3rd Ed. Self-publishing 2017\nM. Tamer Özsu, Patrick Valduriez: Principles of Distributed\nDatabase Systems, 4th Ed., Springer 2020\nFranz Lehner: Wissensmanagement, 6. Aufl. Hanser (2019)\n\nLearning outcomes,\ncompetences\n\n\nThe students have acquired knowledge of distributed systems,\ntheir architecture, processes and applications. They are\nparticularly familiar with the requirements of collaborative\napplications. They are able to evaluate distributed algorithms.\n\nContent\n\n\nArchitecture of distributed systems\nProcesses and communication\nNaming systems\nSynchronisation in distributed systems\nConsistency and replication\nFault tolerance and security\nParadigms of distributed systems: file, object, coordination,\nstreaming\nCooperation and collaboration\nComputer supported cooperative work\n\nHochschule Düsseldorf\nModulhandbuch M.Sc. Medieninformatik\nVersion 1.0\nPO 2025\n75", "metadata": {"moduleNumber": "MMI 05.20", "moduleName": "Distributed Collaborative Systems", "creditPoints": "5.0", "suggestedSemester": 1, "offeredInSeason": "winter_semester", "examType": "portfolio", "heldInLanguage": "de", "reviserName": "Prof. Dr.-Ing. Thomas Rakow", "reviserEmail": "thomas.rakow@hs-duesseldorf.de", "studyProgramId": 11, "source_type": "json", "moduleNameDe": "Verteilte kollaborative Systeme", "source_file": "MMI_MHB_PO2025_V1.0.pdf", "pdf_page_start": 73, "pdf_page_end": 74, "studyProgramAbbrev": "MMI", "studyProgram_Url": "https://medien.hs-duesseldorf.de/mmi", "pdf_url": "https://medien.hs-duesseldorf.de/studium/studiengaenge/Documents/Modulhandb%C3%BCcher/MMI_MHB_PO2025_V1.0.pdf"}}
{"id": "MMI05.21", "text": "Title: Scientific Work\nModule Number: MMI 05.21\nCredits: 5.0 CP\nSemester: 1\nOffered In: winter_semester\nLanguage: en_on_demand\nExam Type: academic_paper\nInstructor: Prof. Dr. Alina Huldtgren (alina.huldtgren@hs-duesseldorf.de)\n--- Goals (EN) ---\nThe students know and understand the basic aspects of scientific work with the essential methods and tools for the planning, production and documentation of scientific results. They acquire the skills to deal with scientific literature and comparable research documents and to be able to filter out the essentials. The clearly structured and formally correct production of scientific texts in the various variants (house and seminar papers, reports, scientific publications) as well as the presentation of the results, also in English, is known to the students.\n--- Goals (DE) ---\nDie Studierenden kennen und verstehen die grundlegenden Aspekte wissenschaftlichen Arbeitens mit den wesentlichen Methoden und Werkzeuge für die Planung, Produktion und Dokumentation wissenschaftlicher Ergebnisse. Sie erwerben die Fähigkeiten mit wissenschaftlicher Literatur und vergleichbaren Forschungsdokumenten umgehen und das Wesentliche herausfiltern zu können. Die klar strukturierte und formal korrekte Produktion wissenschaftlicher Texte in den verschiedenen Varianten (Haus- und Seminararbeiten, Berichte, wiss. Publikationen) sowie die Präsentationen der Ergebnisse, auch in englischer Sprache, ist den Studierenden bekannt.\n--- Contents (EN) ---\nQuality criteria in scienceScientific methods in adjacent relevant scientific fieldsIdentify, rate and cite relevant literatureWrite, evaluate and evaluate scientific textsPrepare, present and document presentationsLead and moderate expert discussions\n--- Contents (DE) ---\nQualitätskriterien in der WissenschaftWissenschaftliche Methoden in angrenzenden relevanten WissenschaftsfeldernEinschlägige Literatur ermitteln, bewerten und richtig zitierenWissenschaftliche Texte schreiben, evaluieren und bewertenPräsentationen vorbereiten, vortragen und dokumentierenFachdiskussionen führen und moderieren\n--- Literature (EN) ---\n--- Literature (DE) ---\nH. Balzert, C.Schäfer, M. Schröder, U.Kern: Wissenschaftliches Arbeiten, W3L GmbH (2008)Norbert Franck: Handbuch Wissenschaftliches Arbeiten, 3. Aufl. Paderborn: Schöningh (2017)Berit Sandberg: Wissenschaftlich Arbeiten von Abbildung bis Zitat. Ein Lehr- und Übungsbuch für Bachelor, Master und Promotion., Oldenbourg, München (2012)\n\nMMI 05.21 - Wissenschaftliches Arbeiten\nScientific Work\nModulbeauftragte*r\nResponsible\nProf. Dr.  Alina Huldtgren\nDozent*in\nTeaching staff\nLehrende*r der Hochschule Düsseldorf\nStudiengang\nM.Sc. Medieninformatik 2025\nVerwendung in anderen\nStudiengängen: / Used in other\nstudy programmes\nM.Sc. Medieninformatik, PO 2018 /\nM.Sc. Media Informatics, PO 2018\n\n\nLehrformen (alle Angaben in SWS zu je 45 Minuten / all values in SWS of 45 minutes each)\n\nCredits/\nCredits\nWorkload /\nWorkload\nKontaktzeit/\nContact time\nSelbststudium/\nSelf study\nDauer/\nLength\nSemester/\nSemester\nSprache/\nLanguage\n5\n150 h\n\n45 h\n105 h\n1 Sem.\n1\nEnglish on\ndemand\nVorlesung/\nLecture\nÜbung/\nPractice\nSeminar/\nSeminar\nPraktiku\nm/ Lab\nwork\nProjekt/\nProject\nTutorium/\nTutorial\nSeminarist.\nUnterricht/\nSeminaristic\nlesson\nStudien\narbeit/\nResearch\nproject\nBegleitetes\nSelbstlernen/\nAccompan‘d\nself study\n\n\n3\n\n\n\n\n\n\nModulkategorie / category\n\nWahlangebot / Module offer\nWahlkatalog(e) /\n\n/\nelective catalogue(s)\n\n\nVoraussetzungen zur Teilnahme /\nrequirements for participation\n\n\nFormal /\nFormal\n\nKeine /\nnone\n\nInhaltlich /\ncontentwise\n\nKeine /\nnone\nVoraussetzungen zur Prüfung /\nprerequisites for the\nexamination\n\nKeine / None\nPrüfungsform /\nform of examination\n\nWissenschaftliche Arbeit (nur MMI) /\nAcademic paper (only MMI)\nBenotet, Stellenwert der Note\nfür die Endnote /\ngraded, value of the grade for\nthe final grade\n\nBenotet: Ja / Is graded: Yes\n\n5/90 bzw. 5/120 / 5/90 resp. 5/120\nVoraussetzungen zur\nCreditvergabe/ requirements for\nawarding credit:\n\nBestandene Modulprüfung / Passed module examination\n\nLernergebnisse, Kompetenzen:\n\n\nDie Studierenden kennen und verstehen die grundlegenden\nAspekte wissenschaftlichen Arbeitens mit den wesentlichen\nMethoden und Werkzeuge für die Planung, Produktion und\nDokumentation wissenschaftlicher Ergebnisse. Sie erwerben die\nFähigkeiten mit wissenschaftlicher Literatur und vergleichbaren\nForschungsdokumenten umgehen und das Wesentliche\nherausfiltern zu können. Die klar strukturierte und formal korrekte\nProduktion wissenschaftlicher Texte in den verschiedenen\n\nHochschule Düsseldorf\nModulhandbuch M.Sc. Medieninformatik\nVersion 1.0\nPO 2025\n76\n\n\nEnglish descriptions\n\nVarianten (Haus- und Seminararbeiten, Berichte, wiss.\nPublikationen) sowie die Präsentationen der Ergebnisse, auch in\nenglischer Sprache, ist den Studierenden bekannt.\n\nLehrinhalte:\n\n\nQualitätskriterien in der WissenschaftWissenschaftliche Methoden\nin angrenzenden relevanten WissenschaftsfeldernEinschlägige\nLiteratur ermitteln, bewerten und richtig zitierenWissenschaftliche\nTexte schreiben, evaluieren und bewertenPräsentationen\nvorbereiten, vortragen und dokumentierenFachdiskussionen\nführen und moderieren\n\nLiteratur:\n\n\nH. Balzert, C.Schäfer, M. Schröder, U.Kern: Wissenschaftliches\nArbeiten, W3L GmbH (2008)Norbert Franck: Handbuch\nWissenschaftliches Arbeiten, 3. Aufl. Paderborn: Schöningh\n(2017)Berit Sandberg: Wissenschaftlich Arbeiten von Abbildung\nbis Zitat. Ein Lehr- und Übungsbuch für Bachelor, Master und\nPromotion., Oldenbourg, München (2012)\n\nLearning outcomes,\ncompetences\n\n\nThe students know and understand the basic aspects of\nscientific work with the essential methods and tools for the\nplanning, production and documentation of scientific results.\nThey acquire the skills to deal with scientific literature and\ncomparable research documents and to be able to filter out the\nessentials. The clearly structured and formally correct production\nof scientific texts in the various variants (house and seminar\npapers, reports, scientific publications) as well as the\npresentation of the results, also in English, is known to the\nstudents.\n\nContent\n\n\nQuality criteria in scienceScientific methods in adjacent relevant\nscientific fieldsIdentify, rate and cite relevant literatureWrite,\nevaluate and evaluate scientific textsPrepare, present and\ndocument presentationsLead and moderate expert discussions\n\nHochschule Düsseldorf\nModulhandbuch M.Sc. Medieninformatik\nVersion 1.0\nPO 2025\n77", "metadata": {"moduleNumber": "MMI 05.21", "moduleName": "Scientific Work", "creditPoints": "5.0", "suggestedSemester": 1, "offeredInSeason": "winter_semester", "examType": "academic_paper", "heldInLanguage": "en_on_demand", "reviserName": "Prof. Dr. Alina Huldtgren", "reviserEmail": "alina.huldtgren@hs-duesseldorf.de", "studyProgramId": 11, "source_type": "json", "moduleNameDe": "Wissenschaftliches Arbeiten", "source_file": "MMI_MHB_PO2025_V1.0.pdf", "pdf_page_start": 75, "pdf_page_end": 76, "studyProgramAbbrev": "MMI", "studyProgram_Url": "https://medien.hs-duesseldorf.de/mmi", "pdf_url": "https://medien.hs-duesseldorf.de/studium/studiengaenge/Documents/Modulhandb%C3%BCcher/MMI_MHB_PO2025_V1.0.pdf"}}
{"id": "MMI05.22", "text": "Title: Mobile Systemes\nModule Number: MMI 05.22\nCredits: 5.0 CP\nSemester: 1\nOffered In: winter_semester\nLanguage: de\nExam Type: oral_exam\nInstructor: Prof. Dr.-Ing. M.Sc. Markus Dahm (markus.dahm@hs-duesseldorf.de)\n--- Goals (EN) ---\n- Forms of mobility (device, service, user)\n- Mobile radio technologies (radio technology)\n- Mobile radio systems and protocols (e.g. GSM, UMTS, LTE, 5G)\n- Mobile devices (mobile phone, tablet, smartphone, VR/AR)\n- Mobile services (e.g. SMS, LBS, added value)\n- Mobile applications (e.g. Android, WebApps)\n- Mobile business (mCommerce, mPayment)\n- Mobile content (e.g. information, games)\n- Mobile usability / UX\n- Mobile social impact (technology assessment)\n--- Goals (DE) ---\n- Mobilitätsformen (Gerät, Dienst, Benutzer)\n- Mobilfunk-Technologien (Funktechnik)\n- Mobilfunk-Systeme und Protokolle (z.B. GSM, UMTS, LTE, 5G)\n- Mobile Geräte (Handy, Tablet, Smartphone, VR/AR)\n- Mobile Dienste (z.B. SMS, LBS, Mehrwert)\n- Mobile Anwendungen (z.B. Android, WebApps)\n- Mobile Business (mCommerce, mPayment)\n- Mobile Content (z.B. Information, Spiele)\n- Mobile Usability / UX\n- Mobile Soziale Auswirkungen (Technikfolgenabschätzung)\n--- Contents (EN) ---\nStudents understand the technical fundamentals of mobile systems - both mobile devices and the infrastructure - and their impact on the use and development of mobile applications. They are familiar with various mobile services and know how they can be linked to business models. Students will be familiar with typical mobile devices and some of the options for developing customised applications for them, taking into account the special characteristics of the mobile usage context.\n--- Contents (DE) ---\nStudierende verstehen die technischen Grundlagen mobiler Systeme - sowohl der mobilen Geräte als auch der Infrastruktur - und ihre Auswirkungen auf die Nutzung und die Entwicklung mobiler Anwendungen. Sie kennen verschiedene mobile Dienste und wissen, wie sie mit Geschäftsmodellen verknüpft werden können. \nDie Studierenden kennen typische mobile Geräte sowie einige Möglichkeiten, darauf angepasste Anwendungen zu entwickeln, wobei sie die besonderen Eigenschaften des mobilen Nutzungskontextes berücksichtigen können.\n--- Literature (EN) ---\n- Schiller: Mobilkommunikation, Pearson (2003)\n- Tanenbaum, van Steen: Verteilte Systeme, Pearson (2007)\n- http://www.wi-mobile.de/\n- http://www.eco.de/arbeitskreise/mobile.htm\n- http://www.heise.de/mobil/\n- http://developer.android.com\n--- Literature (DE) ---\n- Schiller: Mobilkommunikation, Pearson (2003)\n- Tanenbaum, van Steen: Verteilte Systeme, Pearson (2007)\n- http://www.wi-mobile.de/\n- http://www.eco.de/arbeitskreise/mobile.htm\n- http://www.heise.de/mobil/\n- http://developer.android.com\n\nMMI 05.22 - Mobile Systeme\nMobile Systemes\nModulbeauftragte*r\nResponsible\nMarkus Dahm\nDozent*in\nTeaching staff\nLehrende*r der Hochschule Düsseldorf\nStudiengang\nM.Sc. Medieninformatik 2025\nVerwendung in anderen\nStudiengängen: / Used in other\nstudy programmes\nM.Sc. Medieninformatik, PO 2018 /\nM.Sc. Media Informatics, PO 2018\n\n\nLehrformen (alle Angaben in SWS zu je 45 Minuten / all values in SWS of 45 minutes each)\n\nCredits/\nCredits\nWorkload /\nWorkload\nKontaktzeit/\nContact time\nSelbststudium/\nSelf study\nDauer/\nLength\nSemester/\nSemester\nSprache/\nLanguage\n5\n150 h\n\n60 h\n90 h\n1 Sem.\n1\nDeutsch\nVorlesung/\nLecture\nÜbung/\nPractice\nSeminar/\nSeminar\nPraktiku\nm/ Lab\nwork\nProjekt/\nProject\nTutorium/\nTutorial\nSeminarist.\nUnterricht/\nSeminaristic\nlesson\nStudien\narbeit/\nResearch\nproject\nBegleitetes\nSelbstlernen/\nAccompan‘d\nself study\n2\n\n2\n\n\n\n\n\n\nModulkategorie / category\n\nWahlangebot / Module offer\nWahlkatalog(e) /\n\n/\nelective catalogue(s)\n\n\nVoraussetzungen zur Teilnahme /\nrequirements for participation\n\n\nFormal /\nFormal\n\nKeine /\nnone\n\nInhaltlich /\ncontentwise\n\nKenntnisse der Informatik-Module und der Mediengestaltung /\nKnowledge of the informatics modules and media design\nVoraussetzungen zur Prüfung /\nprerequisites for the\nexamination\n\nErfolgreiche Teilnahme am Seminar / Successful participation in\nseminar\nPrüfungsform /\nform of examination\n\nMündliche Prüfung/Fachgespräch /\nOral examination\nBenotet, Stellenwert der Note\nfür die Endnote /\ngraded, value of the grade for\nthe final grade\n\nBenotet: Ja / Is graded: Yes\n\n5/90 bzw. 5/120 / 5/90 resp. 5/120\nVoraussetzungen zur\nCreditvergabe/ requirements for\nawarding credit:\n\nBestandene Modulprüfung / Passed module examination\n\nLernergebnisse, Kompetenzen:\n\n\n- Mobilitätsformen (Gerät, Dienst, Benutzer)\n- Mobilfunk-Technologien (Funktechnik)\n- Mobilfunk-Systeme und Protokolle (z.B. GSM, UMTS, LTE, 5G)\n- Mobile Geräte (Handy, Tablet, Smartphone, VR/AR)\n- Mobile Dienste (z.B. SMS, LBS, Mehrwert)\n- Mobile Anwendungen (z.B. Android, WebApps)\n- Mobile Business (mCommerce, mPayment)\n- Mobile Content (z.B. Information, Spiele)\n\nHochschule Düsseldorf\nModulhandbuch M.Sc. Medieninformatik\nVersion 1.0\nPO 2025\n78\n\n\nEnglish descriptions\n\n- Mobile Usability / UX\n- Mobile Soziale Auswirkungen (Technikfolgenabschätzung)\n\nLehrinhalte:\n\n\nStudierende verstehen die technischen Grundlagen mobiler\nSysteme - sowohl der mobilen Geräte als auch der Infrastruktur -\nund ihre Auswirkungen auf die Nutzung und die Entwicklung\nmobiler Anwendungen. Sie kennen verschiedene mobile Dienste\nund wissen, wie sie mit Geschäftsmodellen verknüpft werden\nkönnen.\nDie Studierenden kennen typische mobile Geräte sowie einige\nMöglichkeiten, darauf angepasste Anwendungen zu entwickeln,\nwobei sie die besonderen Eigenschaften des mobilen\nNutzungskontextes berücksichtigen können.\n\nLiteratur:\n\n\n- Schiller: Mobilkommunikation, Pearson (2003)\n- Tanenbaum, van Steen: Verteilte Systeme, Pearson (2007)\n- http://www.wi-mobile.de/\n- http://www.eco.de/arbeitskreise/mobile.htm\n- http://www.heise.de/mobil/\n- http://developer.android.com\n\nLearning outcomes,\ncompetences\n\n\n- Forms of mobility (device, service, user)\n- Mobile radio technologies (radio technology)\n- Mobile radio systems and protocols (e.g. GSM, UMTS, LTE,\n5G)\n- Mobile devices (mobile phone, tablet, smartphone, VR/AR)\n- Mobile services (e.g. SMS, LBS, added value)\n- Mobile applications (e.g. Android, WebApps)\n- Mobile business (mCommerce, mPayment)\n- Mobile content (e.g. information, games)\n- Mobile usability / UX\n- Mobile social impact (technology assessment)\n\nContent\n\n\nStudents understand the technical fundamentals of mobile\nsystems - both mobile devices and the infrastructure - and their\nimpact on the use and development of mobile applications. They\nare familiar with various mobile services and know how they can\nbe linked to business models. Students will be familiar with\ntypical mobile devices and some of the options for developing\ncustomised applications for them, taking into account the special\ncharacteristics of the mobile usage context.\n\nHochschule Düsseldorf\nModulhandbuch M.Sc. Medieninformatik\nVersion 1.0\nPO 2025\n79", "metadata": {"moduleNumber": "MMI 05.22", "moduleName": "Mobile Systemes", "creditPoints": "5.0", "suggestedSemester": 1, "offeredInSeason": "winter_semester", "examType": "oral_exam", "heldInLanguage": "de", "reviserName": "Prof. Dr.-Ing. M.Sc. Markus Dahm", "reviserEmail": "markus.dahm@hs-duesseldorf.de", "studyProgramId": 11, "source_type": "json", "moduleNameDe": "Mobile Systeme", "source_file": "MMI_MHB_PO2025_V1.0.pdf", "pdf_page_start": 77, "pdf_page_end": 78, "studyProgramAbbrev": "MMI", "studyProgram_Url": "https://medien.hs-duesseldorf.de/mmi", "pdf_url": "https://medien.hs-duesseldorf.de/studium/studiengaenge/Documents/Modulhandb%C3%BCcher/MMI_MHB_PO2025_V1.0.pdf"}}
{"id": "MMI05.23", "text": "Title: Medial Productions\nModule Number: MMI 05.23\nCredits: 5.0 CP\nSemester: 2\nOffered In: summer_semester\nLanguage: de\nExam Type: project\nInstructor: Prof. Dr. rer. nat. Christian Geiger (geiger@hs-duesseldorf.de)\n--- Goals (EN) ---\nThe participants learn the procedures in the conception, design, development, construction and operation of media staging. Conceptual, design, technical and economic aspects are considered in equal parts. By critically discussing current or historically significant examples, participants can assess media staging and reflect critically on their work from different perspectives. The participants have practical experience in the pre-visualization and final implementation of simple installation concepts based on selected marketable or freely available tools.\n--- Goals (DE) ---\nDie Teilnehmer lernen die Vorgehensweisen bei der Konzeption, Gestaltung, Entwicklung, Aufbau und Betrieb medialer Inszenierungen. Dabei werden konzeptionelle, gestalterische, technische und wirtschaftliche Aspekte zu gleichen Teilen betrachtet. Durch die kritische Diskussion aktueller bzw. historisch bedeutsamer Beispiele können die Teilnehmer mediale Inszenierungen beurteilen und den Einsatz aus verschiedenen Blickwinkeln kritisch reflektieren. Die Teilnehmer besitzen praktische Erfahrung in der Prävisualisierung und finalen Umsetzung einfacher Installationskonzepte auf Basis ausgewählter marktgängiger bzw. frei verfügbarer Werkzeuge.\n--- Contents (EN) ---\n- Theoretical foundations of media staging (perception, artistic expression, media architectures)\n- Analysis of historically relevant examplesTransmedia spaces, video art and performances\n- Selected forms of media staging, \n- Attempt at typification\n- Selected technical aspects of digital and physical object and space design (projection mapping, multi-displays, VR/AR)\n-Tools for media productions\n-Workflow planning and operation of extensive installations\n- Audience development and user feedback\n- Critical reflection and impact from multiple perspectives (artistic, technical, economic, social)\n--- Contents (DE) ---\nTheoretische Grundlagen medialer Inszenierung (Wahrnehmung, künstlerischer Ausdruck, mediale Architekturen)\n- Analyse historisch relevanter BeispieleTransmediale Räume, Videokunst und Performances\n- Ausgewählte Formen medialer Inszenierung, \n- Versuch einer Typisierung\n- Ausgewählte technische Aspekte des digitale und physischen Objekt- und Raumdesigns (Projection Mapping, Multi-Displays, VR/AR)\n-Werkzeuge für mediale Inszenierungen\n-WorkflowPlanung und Betrieb umfangreicher Installationen\n- Audience Development und Nutzerfeedback\n- Kritische Reflektion und Impact aus multiplen Perspektiven (künstlerisch, technisch, wirtschaftlich, sozial)\n--- Literature (EN) ---\n--- Literature (DE) ---\n- Claire Bishop: Installation Art, Tate Publishing (2005)\n- New Installation Art, Ginko Press (2013)\n- The Complete Book of Mixed Media Art, Walter Foster Creative Team, 2018\n- Aktuelle Ausstellungskataloge erfolgreicher Inszenierungen\n\nMMI 05.23 - Mediale Inszenierungen\nMedial Productions\nModulbeauftragte*r\nResponsible\nChristian Geiger\nDozent*in\nTeaching staff\nLehrende*r der Hochschule Düsseldorf\nStudiengang\nM.Sc. Medieninformatik 2025\nVerwendung in anderen\nStudiengängen: / Used in other\nstudy programmes\nM.Sc. Medieninformatik, PO 2018\nB.Eng. Ton und Bild, PO 2025 /\nM.Sc. Media Informatics, PO 2018\nB.Eng. Audio and Video, PO 2025\n\n\nLehrformen (alle Angaben in SWS zu je 45 Minuten / all values in SWS of 45 minutes each)\n\nCredits/\nCredits\nWorkload /\nWorkload\nKontaktzeit/\nContact time\nSelbststudium/\nSelf study\nDauer/\nLength\nSemester/\nSemester\nSprache/\nLanguage\n5\n150 h\n\n60 h\n90 h\n1 Sem.\n2\nDeutsch\nVorlesung/\nLecture\nÜbung/\nPractice\nSeminar/\nSeminar\nPraktiku\nm/ Lab\nwork\nProjekt/\nProject\nTutorium/\nTutorial\nSeminarist.\nUnterricht/\nSeminaristic\nlesson\nStudien\narbeit/\nResearch\nproject\nBegleitetes\nSelbstlernen/\nAccompan‘d\nself study\n\n\n2\n\n2\n\n\n\n\nModulkategorie / category\n\nWahlangebot / Module offer\nWahlkatalog(e) /\n\n/\nelective catalogue(s)\n\n\nVoraussetzungen zur Teilnahme /\nrequirements for participation\n\n\nFormal /\nFormal\n\nKeine /\nnone\n\nInhaltlich /\ncontentwise\n\nKeine /\nnone\nVoraussetzungen zur Prüfung /\nprerequisites for the\nexamination\n\nKeine / None\nPrüfungsform /\nform of examination\n\nProjektprüfung /\nProject examination\nBenotet, Stellenwert der Note\nfür die Endnote /\ngraded, value of the grade for\nthe final grade\n\nBenotet: Ja / Is graded: Yes\n\n5/90 bzw. 5/120 / 5/90 resp. 5/120\nVoraussetzungen zur\nCreditvergabe/ requirements for\nawarding credit:\n\nBestandene Modulprüfung / Passed module examination\n\nLernergebnisse, Kompetenzen:\n\n\nDie Teilnehmer lernen die Vorgehensweisen bei der Konzeption,\nGestaltung, Entwicklung, Aufbau und Betrieb medialer\nInszenierungen. Dabei werden konzeptionelle, gestalterische,\ntechnische und wirtschaftliche Aspekte zu gleichen Teilen\nbetrachtet. Durch die kritische Diskussion aktueller bzw. historisch\nbedeutsamer Beispiele können die Teilnehmer mediale\nInszenierungen beurteilen und den Einsatz aus verschiedenen\n\nHochschule Düsseldorf\nModulhandbuch M.Sc. Medieninformatik\nVersion 1.0\nPO 2025\n80\n\n\nEnglish descriptions\n\nBlickwinkeln kritisch reflektieren. Die Teilnehmer besitzen\npraktische Erfahrung in der Prävisualisierung und finalen\nUmsetzung einfacher Installationskonzepte auf Basis\nausgewählter marktgängiger bzw. frei verfügbarer Werkzeuge.\n\nLehrinhalte:\n\n\nTheoretische Grundlagen medialer Inszenierung (Wahrnehmung,\nkünstlerischer Ausdruck, mediale Architekturen)\n- Analyse historisch relevanter BeispieleTransmediale Räume,\nVideokunst und Performances\n- Ausgewählte Formen medialer Inszenierung,\n- Versuch einer Typisierung\n- Ausgewählte technische Aspekte des digitale und physischen\nObjekt- und Raumdesigns (Projection Mapping, Multi-Displays,\nVR/AR)\n-Werkzeuge für mediale Inszenierungen\n-WorkflowPlanung und Betrieb umfangreicher Installationen\n- Audience Development und Nutzerfeedback\n- Kritische Reflektion und Impact aus multiplen Perspektiven\n(künstlerisch, technisch, wirtschaftlich, sozial)\n\nLiteratur:\n\n\n- Claire Bishop: Installation Art, Tate Publishing (2005)\n- New Installation Art, Ginko Press (2013)\n- The Complete Book of Mixed Media Art, Walter Foster Creative\nTeam, 2018\n- Aktuelle Ausstellungskataloge erfolgreicher Inszenierungen\n\nLearning outcomes,\ncompetences\n\n\nThe participants learn the procedures in the conception, design,\ndevelopment, construction and operation of media staging.\nConceptual, design, technical and economic aspects are\nconsidered in equal parts. By critically discussing current or\nhistorically significant examples, participants can assess media\nstaging and reflect critically on their work from different\nperspectives. The participants have practical experience in the\npre-visualization and final implementation of simple installation\nconcepts based on selected marketable or freely available tools.\n\nContent\n\n\n- Theoretical foundations of media staging (perception, artistic\nexpression, media architectures)\n- Analysis of historically relevant examplesTransmedia spaces,\nvideo art and performances\n- Selected forms of media staging,\n- Attempt at typification\n- Selected technical aspects of digital and physical object and\nspace design (projection mapping, multi-displays, VR/AR)\n-Tools for media productions\n-Workflow planning and operation of extensive installations\n- Audience development and user feedback\n- Critical reflection and impact from multiple perspectives\n(artistic, technical, economic, social)\n\nHochschule Düsseldorf\nModulhandbuch M.Sc. Medieninformatik\nVersion 1.0\nPO 2025\n81", "metadata": {"moduleNumber": "MMI 05.23", "moduleName": "Medial Productions", "creditPoints": "5.0", "suggestedSemester": 2, "offeredInSeason": "summer_semester", "examType": "project", "heldInLanguage": "de", "reviserName": "Prof. Dr. rer. nat. Christian Geiger", "reviserEmail": "geiger@hs-duesseldorf.de", "studyProgramId": 11, "source_type": "json", "moduleNameDe": "Mediale Inszenierungen", "source_file": "MMI_MHB_PO2025_V1.0.pdf", "pdf_page_start": 79, "pdf_page_end": 80, "studyProgramAbbrev": "MMI", "studyProgram_Url": "https://medien.hs-duesseldorf.de/mmi", "pdf_url": "https://medien.hs-duesseldorf.de/studium/studiengaenge/Documents/Modulhandb%C3%BCcher/MMI_MHB_PO2025_V1.0.pdf"}}
{"id": "MMI05.24", "text": "Title: Qualitative and Quantitative Methods\nModule Number: MMI 05.24\nCredits: 5.0 CP\nSemester: 1\nOffered In: winter_semester\nLanguage: de\nExam Type: none\nInstructor: Prof. Dr. Thomas Franz (thomas.franz@hs-duesseldorf.de)\n--- Goals (EN) ---\nThe students understand that there are fundamentally different ways to gather and analyse data to evaluate concepts and prototypes of digital media. They also know the epistemological background of these different approaches respectively. The students are able to determine the most suitable method to work on a given research question. They can apply both quantitative and qualitative methods in practice and analyse data accordingly. In terms of quantitative methods, the students can design and implement methods and technologies for experiments, form hypotheses, plan experiments and perform statistical evaluations. In terms of qualitative methods, the students can prepare a suitable interview guide, record observation results, code data in different ways and prepare a thematic map.\n--- Goals (DE) ---\nDie Studierenden verstehen, dass es grundlegend unterschiedliche Arten der Datensammlung und Analyse zur Evaluation von Konzepten und Prototypen digitaler Medien gibt und welchen erkenntnistheoretischen Hintergrund diese haben. Sie können anhand einer Forschungsfrage analysieren, welche Methodik sich am besten zur Beantwortung der Frage eignet. Sie können sowohl quantitative als auch qualitative Methoden in der Praxis anwenden und die Daten dementsprechend analysieren. Im Bereich der quantitativen Methoden, können Studierende Konstrukte zur Messung operationalisieren, Hypothesen aufstellen, Experimente planen, und statistische Auswertungen vornehmen. Im Bereich der qualitativen Methoden können Studierende einen Interviewleitfaden erstellen, ein Beobachtungsprotokoll erstellen, verschiedene Kodierungen der Daten vornehmen und eine Thematic Map erstellen.\n--- Contents (EN) ---\nIntroduction to the differences between quantitative and qualitative research from an epistemological perspectiveDeveloping research questions and determining suitable methods to work on themIntroduction to scientific experiments, formation of hypotheses, operationalisation, testing of hypothesis, statistical data analysisIntroduction to qualitative, empirical data acquisition by means of observation, interviews, focus groups and diaries\n--- Contents (DE) ---\nEinführung in die Unterschiede quantitativer und qualitativer Forschung aus erkenntnistheoretischer SichtEntwicklung von Forschungsfragen und Auswahl geeigneter Methoden zur BeantwortungEinführung in wiss. Experimente, Hypothesenbildung, Operationalisierung, Hypothesentesten, statistische DatenanalyseEinführung in die Erhebung qualitativer, empirischer Daten durch Beobachtungen, Interviews, Fokusgruppen und Tagebücher.\n--- Literature (EN) ---\n--- Literature (DE) ---\nDöring, N. und Bortz, J.: Forschungsmethoden und Evaluation in den Sozial- und Humanwissenschaften, 3. Auflage Springer (2016)", "metadata": {"moduleNumber": "MMI 05.24", "moduleName": "Qualitative and Quantitative Methods", "creditPoints": "5.0", "suggestedSemester": 1, "offeredInSeason": "winter_semester", "examType": "none", "heldInLanguage": "de", "reviserName": "Prof. Dr. Thomas Franz", "reviserEmail": "thomas.franz@hs-duesseldorf.de", "studyProgramId": 11, "source_type": "json", "moduleNameDe": "Qualitative and Quantitative Methods", "source_file": "no data", "pdf_page_start": 0, "pdf_page_end": 0, "studyProgramAbbrev": "MMI", "studyProgram_Url": "https://medien.hs-duesseldorf.de/mmi", "pdf_url": "https://medien.hs-duesseldorf.de/studium/studiengaenge/Documents/Modulhandb%C3%BCcher/MMI_MHB_PO2025_V1.0.pdf"}}
{"id": "MMI05.25", "text": "Title: Image Processing\nModule Number: MMI 05.25\nCredits: 5.0 CP\nSemester: 2\nOffered In: to_be_announced\nLanguage: de\nExam Type: portfolio\nInstructor: Prof. Dr.-Ing. Thomas Bonse (thomas.bonse@hs-duesseldorf.de)\n--- Goals (EN) ---\nStudents develop a profound understanding of the fundamental concepts of digital image processing. Students are familiar with advanced image processing algorithms and are able to apply them.\nStudents are able to apply theoretical concepts of image processing to real-world problems.\nStudents acquire practical experience in the implementation of image processing algorithms. They deepen their programming skills and strengthen their handling of relevant software tools in order to evaluate their results.\n--- Goals (DE) ---\nDie Studierenden entwickeln ein fundiertes Verständnis der grundlegenden Konzepte in der digitalen Bildverarbeitung. Die Studierenden kennen fortgeschrittene Bildverarbeitungsalgorithmen und können diese anwenden.\nDie Studierenden sind in der Lage, theoretische Konzepte der Bildverarbeitung auf reale Probleme anzuwenden.\nDie Studierenden erwerben praktische Erfahrung in der Implementierung von Bildverarbeitungsalgorithmen. Sie vertiefen ihre Fähigkeiten in der Programmierung und stärken Ihren Umgang mit relevanten Softwaretools, um ihre Ergebnisse zu evaluieren.\n--- Contents (EN) ---\nThe module offers an in-depth examination of advanced concepts and techniques in the processing of digital images. The module focuses on theoretical foundations, algorithmic approaches and practical applications in order to provide students with a comprehensive understanding of digital image processing. Bachelor's and Master's students each receive customised subtasks. \n1. theoretical basics: image representation, colour models, image filtering and transformations.\n2. algorithms and techniques: Digital filters, image segmentation, pattern recognition, feature extraction and description, and algorithms from image coding\n3. applications in practice: feature extraction, image recognition and interpretation, machine vision. \n4. programming and implementation.\n--- Contents (DE) ---\nDas Modul bietet eine vertiefte Auseinandersetzung mit fortgeschrittenen Konzepten und Techniken in der Verarbeitung von digitalen Bildern. Das Modul legt den Fokus auf theoretische Grundlagen, algorithmische Ansätze und praktische Anwendungen, um den Studierenden ein umfassendes Verständnis für die digitale Bildverarbeitung zu vermitteln. Bachelor- und Masterstudierende erhalten jeweils angepasste Teilaufgaben. \n1. Theoretische Grundlagen: Bildrepräsentation, Farbmodelle, Bildfilterung und Transformationen.\n2. Algorithmen und Techniken: Digitale Filter, Bildsegmentierung, Mustererkennung, Merkmalsextraktion und -beschreibung sowie Algorithmen aus der Bildcodierung.\n3. Anwendungen in der Praxis: Feature Extraction, Bilderkennung und Interpretation, maschinelles Sehen. \n4. Programmierung und Implementierung.\n--- Literature (EN) ---\n- Gonzalez, R.C., Woods, R.E.: Digital Image Processing, Pearson 2008\n- Burger,  W., Burge, M.J.: Digital Image Processing, Springer 2022\n- Burger, W., Burge, M.J.: Digitale Bildverarbeitung - Eine algorithmische Einführung mit Java, Springer 2015\n- Russ, J.C.: The Image Processing Handbook, CRC Press 2018\n- Jähne, B.: Digitale Bildverarbeitung und Bildgewinnung, Springer 2012\n--- Literature (DE) ---\n- Gonzalez, R.C., Woods, R.E.: Digital Image Processing, Pearson 2008\n- Burger,  W., Burge, M.J.: Digital Image Processing, Springer 2022\n- Burger, W., Burge, M.J.: Digitale Bildverarbeitung - Eine algorithmische Einführung mit Java, Springer 2015\n- Russ, J.C.: The Image Processing Handbook, CRC Press 2018\n- Jähne, B.: Digitale Bildverarbeitung und Bildgewinnung, Springer 2012\n\nMMI 05.25 - Digitale Bildverarbeitung\nImage Processing\nModulbeauftragte*r\nResponsible\nThomas Bonse\nDozent*in\nTeaching staff\nLehrende*r der Hochschule Düsseldorf\nStudiengang\nM.Sc. Medieninformatik 2025\nVerwendung in anderen\nStudiengängen: / Used in other\nstudy programmes\nM.Sc. Medieninformatik, PO 2018 /\nM.Sc. Media Informatics, PO 2018\n\n\nLehrformen (alle Angaben in SWS zu je 45 Minuten / all values in SWS of 45 minutes each)\n\nCredits/\nCredits\nWorkload /\nWorkload\nKontaktzeit/\nContact time\nSelbststudium/\nSelf study\nDauer/\nLength\nSemester/\nSemester\nSprache/\nLanguage\n5\n150 h\n\n60 h\n90 h\n1 Sem.\n2\nDeutsch\nVorlesung/\nLecture\nÜbung/\nPractice\nSeminar/\nSeminar\nPraktiku\nm/ Lab\nwork\nProjekt/\nProject\nTutorium/\nTutorial\nSeminarist.\nUnterricht/\nSeminaristic\nlesson\nStudien\narbeit/\nResearch\nproject\nBegleitetes\nSelbstlernen/\nAccompan‘d\nself study\n0\n\n\n\n2\n\n1\n0\n1\nModulkategorie / category\n\nWahlangebot / Module offer\nWahlkatalog(e) /\n\n/\nelective catalogue(s)\n\n\nVoraussetzungen zur Teilnahme /\nrequirements for participation\n\n\nFormal /\nFormal\n\nKeine /\nnone\n\nInhaltlich /\ncontentwise\n\nKeine /\nnone\nVoraussetzungen zur Prüfung /\nprerequisites for the\nexamination\n\nErfolgreiche Teilnahme am Seminaristischen Unterricht und\nPraktikum / Successful participation in seminaristic lecture and lab\nwork\nPrüfungsform /\nform of examination\n\nBearbeitung von Seminar-, Praktikums-, oder Übungsaufgaben\noder Laborversuchen (Portfolio) /\nPortfolio submittal or participation in laboratory experiments\nBenotet, Stellenwert der Note\nfür die Endnote /\ngraded, value of the grade for\nthe final grade\n\nBenotet: Ja / Is graded: Yes\n\n5/90 bzw. 5/120 / 5/90 resp. 5/120\nVoraussetzungen zur\nCreditvergabe/ requirements for\nawarding credit:\n\nBestandene Modulprüfung / Passed module examination\n\nLernergebnisse, Kompetenzen:\n\n\nDie Studierenden entwickeln ein fundiertes Verständnis der\ngrundlegenden Konzepte in der digitalen Bildverarbeitung. Die\nStudierenden kennen fortgeschrittene\nBildverarbeitungsalgorithmen und können diese anwenden.\nDie Studierenden sind in der Lage, theoretische Konzepte der\nBildverarbeitung auf reale Probleme anzuwenden.\n\nHochschule Düsseldorf\nModulhandbuch M.Sc. Medieninformatik\nVersion 1.0\nPO 2025\n82\n\n\nEnglish descriptions\nDie Studierenden erwerben praktische Erfahrung in der\nImplementierung von Bildverarbeitungsalgorithmen. Sie vertiefen\nihre Fähigkeiten in der Programmierung und stärken Ihren\nUmgang mit relevanten Softwaretools, um ihre Ergebnisse zu\nevaluieren.\n\nLehrinhalte:\n\n\nDas Modul bietet eine vertiefte Auseinandersetzung mit\nfortgeschrittenen Konzepten und Techniken in der Verarbeitung\nvon digitalen Bildern. Das Modul legt den Fokus auf theoretische\nGrundlagen, algorithmische Ansätze und praktische\nAnwendungen, um den Studierenden ein umfassendes\nVerständnis für die digitale Bildverarbeitung zu vermitteln.\nBachelor- und Masterstudierende erhalten jeweils angepasste\nTeilaufgaben.\n1. Theoretische Grundlagen: Bildrepräsentation, Farbmodelle,\nBildfilterung und Transformationen.\n2. Algorithmen und Techniken: Digitale Filter, Bildsegmentierung,\nMustererkennung, Merkmalsextraktion und -beschreibung sowie\nAlgorithmen aus der Bildcodierung.\n3. Anwendungen in der Praxis: Feature Extraction, Bilderkennung\nund Interpretation, maschinelles Sehen.\n4. Programmierung und Implementierung.\n\nLiteratur:\n\n\n- Gonzalez, R.C., Woods, R.E.: Digital Image Processing,\nPearson 2008\n- Burger,  W., Burge, M.J.: Digital Image Processing, Springer\n2022\n- Burger, W., Burge, M.J.: Digitale Bildverarbeitung - Eine\nalgorithmische Einführung mit Java, Springer 2015\n- Russ, J.C.: The Image Processing Handbook, CRC Press 2018\n- Jähne, B.: Digitale Bildverarbeitung und Bildgewinnung, Springer\n2012\n\nLearning outcomes,\ncompetences\n\n\nStudents develop a profound understanding of the fundamental\nconcepts of digital image processing. Students are familiar with\nadvanced image processing algorithms and are able to apply\nthem.\nStudents are able to apply theoretical concepts of image\nprocessing to real-world problems.\nStudents acquire practical experience in the implementation of\nimage processing algorithms. They deepen their programming\nskills and strengthen their handling of relevant software tools in\norder to evaluate their results.\n\nContent\n\n\nThe module offers an in-depth examination of advanced\nconcepts and techniques in the processing of digital images. The\nmodule focuses on theoretical foundations, algorithmic\napproaches and practical applications in order to provide\nstudents with a comprehensive understanding of digital image\nprocessing. Bachelor's and Master's students each receive\ncustomised subtasks.\n1. theoretical basics: image representation, colour models,\nimage filtering and transformations.\n\nHochschule Düsseldorf\nModulhandbuch M.Sc. Medieninformatik\nVersion 1.0\nPO 2025\n83\n\n\n2. algorithms and techniques: Digital filters, image segmentation,\npattern recognition, feature extraction and description, and\nalgorithms from image coding\n3. applications in practice: feature extraction, image recognition\nand interpretation, machine vision.\n4. programming and implementation.\n\nHochschule Düsseldorf\nModulhandbuch M.Sc. Medieninformatik\nVersion 1.0\nPO 2025\n84", "metadata": {"moduleNumber": "MMI 05.25", "moduleName": "Image Processing", "creditPoints": "5.0", "suggestedSemester": 2, "offeredInSeason": "to_be_announced", "examType": "portfolio", "heldInLanguage": "de", "reviserName": "Prof. Dr.-Ing. Thomas Bonse", "reviserEmail": "thomas.bonse@hs-duesseldorf.de", "studyProgramId": 11, "source_type": "json", "moduleNameDe": "Digitale Bildverarbeitung", "source_file": "MMI_MHB_PO2025_V1.0.pdf", "pdf_page_start": 81, "pdf_page_end": 83, "studyProgramAbbrev": "MMI", "studyProgram_Url": "https://medien.hs-duesseldorf.de/mmi", "pdf_url": "https://medien.hs-duesseldorf.de/studium/studiengaenge/Documents/Modulhandb%C3%BCcher/MMI_MHB_PO2025_V1.0.pdf"}}
{"id": "MMI05.26", "text": "Title: Digital Storytelling\nModule Number: MMI 05.26\nCredits: 5.0 CP\nSemester: 1\nOffered In: to_be_announced\nLanguage: de\nExam Type: project\nInstructor: Prof. Dr. rer. nat. Christian Geiger (geiger@hs-duesseldorf.de)\n--- Goals (EN) ---\nThe students know the concepts of digital storytelling and narrative structures. They can use the necessary practical fundamentals in various fields of application (e.g. games, marketing, social media). They can describe the design process of digital storytelling and apply basic principles for the development of narrative structures to various formats. In addition, they can outline other current issues as well as solutions in the field of digital and non-linear storytelling.\n--- Goals (DE) ---\nDie Studierenden kennen das Konzept des „Digital Storytelling“ und narrativer Strukturen und beherrschen die notwendigen praktischen Grundlage in verschiedene Anwendungsbereiche (wie Games, Marketing, Social Media) transferieren. Sie können den Entwurfsprozess des Digital Storytellings beschreiben und grundsätzliche Prinzipien der Entwicklung narrativer Strukturen für verschiedene Formate anwenden. Außerdem können sie weitere aktuelle Fragestellungen sowie deren Lösungen aus dem Bereich digitales und nicht-lineares Storytelling skizzieren.\n--- Contents (EN) ---\nTelling stories: history and narrative fundamentalsStorytelling in filmsStorytelling in gamesScripts and storyboardsStorytelling as a marketing toolForms of digital storytellingStorytelling in virtual realityInteractive storytelling (non-linear)Multimodal storytellingTransmedia storytellingWeb 2.0 storytellingSocial media storytellingNew forms of storytelling for new media\n--- Contents (DE) ---\nGeschichten erzählen: Historie und narrative GrundlagenStorytelling im FilmStorytelling in GamesScripts and StoryboardsStorytelling als Marketing InstrumentFormen von Digital StorytellingStorytelling in der Virtuellen RealitätInteractive Storytelling (nonlinear)Multimodales StorytellingTransmedia Storytelling Web 2.0 StorytellingSocial Media StorytellingNeue Storytelling Formen für neue Medien\n--- Literature (EN) ---\n--- Literature (DE) ---\nBryan Alexander: The New Digital Storytelling: Creating Narratives with New Media, ABC-ClioDennis Eick: Digitales Erzählen. Die Dramaturgie der Neuen Medien, UVK VerlagsgesellschaftPia Kleine Wieskamp: Storytelling: Digital - Multimedial - Social: Formen und Praxis für PR, Marketing, TV, Game und Social Media, HanserMedienNetzwerk Bayern: Story Now: Ein Handbuch für digitales Erzählen, mixtvisionDavid Lochner: Storytelling in virtuellen Welten, UVK Verlagsgesellschaft\n\nMMI 05.26 - Digital Storytelling\nDigital Storytelling\nModulbeauftragte*r\nResponsible\nChristian Geiger\nDozent*in\nTeaching staff\nLehrende*r der Hochschule Düsseldorf\nStudiengang\nM.Sc. Medieninformatik 2025\nVerwendung in anderen\nStudiengängen: / Used in other\nstudy programmes\nM.Sc. Medieninformatik, PO 2018 /\nM.Sc. Media Informatics, PO 2018\n\n\nLehrformen (alle Angaben in SWS zu je 45 Minuten / all values in SWS of 45 minutes each)\n\nCredits/\nCredits\nWorkload /\nWorkload\nKontaktzeit/\nContact time\nSelbststudium/\nSelf study\nDauer/\nLength\nSemester/\nSemester\nSprache/\nLanguage\n5\n150 h\n\n60 h\n90 h\n1 Sem.\n1\nDeutsch\nVorlesung/\nLecture\nÜbung/\nPractice\nSeminar/\nSeminar\nPraktiku\nm/ Lab\nwork\nProjekt/\nProject\nTutorium/\nTutorial\nSeminarist.\nUnterricht/\nSeminaristic\nlesson\nStudien\narbeit/\nResearch\nproject\nBegleitetes\nSelbstlernen/\nAccompan‘d\nself study\n\n\n2\n\n2\n\n\n\n\nModulkategorie / category\n\nWahlangebot / Module offer\nWahlkatalog(e) /\n\n/\nelective catalogue(s)\n\n\nVoraussetzungen zur Teilnahme /\nrequirements for participation\n\n\nFormal /\nFormal\n\nKeine /\nnone\n\nInhaltlich /\ncontentwise\n\nKeine /\nnone\nVoraussetzungen zur Prüfung /\nprerequisites for the\nexamination\n\nKeine / None\nPrüfungsform /\nform of examination\n\nProjektprüfung /\nProject examination\nBenotet, Stellenwert der Note\nfür die Endnote /\ngraded, value of the grade for\nthe final grade\n\nBenotet: Ja / Is graded: Yes\n\n5/90 bzw. 5/120 / 5/90 resp. 5/120\nVoraussetzungen zur\nCreditvergabe/ requirements for\nawarding credit:\n\nBestandene Modulprüfung / Passed module examination\n\nLernergebnisse, Kompetenzen:\n\n\nDie Studierenden kennen das Konzept des 'Digital Storytelling'\nund narrativer Strukturen und beherrschen die notwendigen\npraktischen Grundlage in verschiedene Anwendungsbereiche (wie\nGames, Marketing, Social Media) transferieren. Sie können den\nEntwurfsprozess des Digital Storytellings beschreiben und\ngrundsätzliche Prinzipien der Entwicklung narrativer Strukturen für\nverschiedene Formate anwenden. Außerdem können sie weitere\n\nHochschule Düsseldorf\nModulhandbuch M.Sc. Medieninformatik\nVersion 1.0\nPO 2025\n85\n\n\nEnglish descriptions\n\naktuelle Fragestellungen sowie deren Lösungen aus dem Bereich\ndigitales und nicht-lineares Storytelling skizzieren.\n\nLehrinhalte:\n\n\nGeschichten erzählen: Historie und narrative\nGrundlagenStorytelling im FilmStorytelling in GamesScripts and\nStoryboardsStorytelling als Marketing InstrumentFormen von\nDigital StorytellingStorytelling in der Virtuellen RealitätInteractive\nStorytelling (nonlinear)Multimodales StorytellingTransmedia\nStorytelling Web 2.0 StorytellingSocial Media StorytellingNeue\nStorytelling Formen für neue Medien\n\nLiteratur:\n\n\nBryan Alexander: The New Digital Storytelling: Creating\nNarratives with New Media, ABC-ClioDennis Eick: Digitales\nErzählen. Die Dramaturgie der Neuen Medien, UVK\nVerlagsgesellschaftPia Kleine Wieskamp: Storytelling: Digital -\nMultimedial - Social: Formen und Praxis für PR, Marketing, TV,\nGame und Social Media, HanserMedienNetzwerk Bayern: Story\nNow: Ein Handbuch für digitales Erzählen, mixtvisionDavid\nLochner: Storytelling in virtuellen Welten, UVK\nVerlagsgesellschaft\n\nLearning outcomes,\ncompetences\n\n\nThe students know the concepts of digital storytelling and\nnarrative structures. They can use the necessary practical\nfundamentals in various fields of application (e.g. games,\nmarketing, social media). They can describe the design process\nof digital storytelling and apply basic principles for the\ndevelopment of narrative structures to various formats. In\naddition, they can outline other current issues as well as\nsolutions in the field of digital and non-linear storytelling.\n\nContent\n\n\nTelling stories: history and narrative fundamentalsStorytelling in\nfilmsStorytelling in gamesScripts and storyboardsStorytelling as\na marketing toolForms of digital storytellingStorytelling in virtual\nrealityInteractive storytelling (non-linear)Multimodal\nstorytellingTransmedia storytellingWeb 2.0 storytellingSocial\nmedia storytellingNew forms of storytelling for new media\n\nHochschule Düsseldorf\nModulhandbuch M.Sc. Medieninformatik\nVersion 1.0\nPO 2025\n86", "metadata": {"moduleNumber": "MMI 05.26", "moduleName": "Digital Storytelling", "creditPoints": "5.0", "suggestedSemester": 1, "offeredInSeason": "to_be_announced", "examType": "project", "heldInLanguage": "de", "reviserName": "Prof. Dr. rer. nat. Christian Geiger", "reviserEmail": "geiger@hs-duesseldorf.de", "studyProgramId": 11, "source_type": "json", "moduleNameDe": "Digital Storytelling", "source_file": "MMI_MHB_PO2025_V1.0.pdf", "pdf_page_start": 84, "pdf_page_end": 85, "studyProgramAbbrev": "MMI", "studyProgram_Url": "https://medien.hs-duesseldorf.de/mmi", "pdf_url": "https://medien.hs-duesseldorf.de/studium/studiengaenge/Documents/Modulhandb%C3%BCcher/MMI_MHB_PO2025_V1.0.pdf"}}
{"id": "MMI05.27", "text": "Title: Design Thinking\nModule Number: MMI 05.27\nCredits: 5.0 CP\nSemester: None\nOffered In: to_be_announced\nLanguage: en_on_demand\nExam Type: project\nInstructor: Prof. Dr. Alina Huldtgren (alina.huldtgren@hs-duesseldorf.de)\n--- Goals (EN) ---\nThe students understand why it is important to keep a balance between user focus, economical considerations and technical feasibility for the development of new digital media. In this context, they have learned about the wicked problems, which designers often face today. The students know the process of design thinking and its five phases: understanding, observing, point-of-view, brainstorming, prototyping and refinement. They have applied methods of the Stanford d.school to a design task.\n--- Goals (DE) ---\nDie Studierenden verstehen, warum eine Balance zwischen Nutzerfokus, ökonomischen Abwägungen und technischer Machbarkeit zur Entwicklung neuer digitaler Medien wichtig ist. In diesem Zusammenhang lernen sie das Konzept des Wicked Problems kennen, mit denen Designer sich heutzutage oft konfrontiert sehen. Die Studierenden lernen den Prozess des Design Thinkings mit den 5 Schritten: Verstehen, Beobachten, Point-of-View, Ideenfindung, Prototyping, und Verfeinerung kennen und wenden Methoden der Standford d.school in einer Designaufgabe an.\n--- Contents (EN) ---\nTeam building exercise (e.g. the Marshmallow Challenge)Introduction to wicked problems and changing requirements for the design of digital media in the digital ageOverview of design thinking: five phases, T-shaped people, principles of design thinking (e.g. ‘Show, don’t tell!’, radical collaboration etc.)Application of individual design thinking methods in the different phasesSelected approaches of iterative prototyping according to the topic of the courseProject work in groups on a previously selected problem area and a suitable research question\n--- Contents (DE) ---\nTeambuilding mittels Marshmallow Challenge oder vgl.Einführung Wicked Problems und Veränderungen der Anforderungen an das Design digitaler Medien im Zeitalter der DigitalisierungÜbersicht Design Thinking: 5 Phasen, T-Shaped People, Prinzipien des Design Thinkings (z.B. Show don't tell, Radical Collaboration, etc)Anwendung einzelner Design Thinking Methoden in den PhasenAusgewählte Ansätze des iterativen Prototypings je nach gewähltem Themenkomplex der VeranstaltungProjektarbeit in Gruppen bzgl eines zuvor ausgewählten Problembereichs und einer geeigneten Fragestellung\n--- Literature (EN) ---\n--- Literature (DE) ---\nJürgen Erbeldinger, Thomas Ramge, Erik Spiekermann: Durch die Decke denken: Design Thinking in der Praxis, Redline (2013)Martin J. Eppler: Creability: Gemeinsam kreativ - innovative Methoden für die Ideenentwicklung in Teams, Schäfer/Poeschel (2014)Sebastian Olma, Yulia Kryazheva: The Serendipity Machine, Verlag Stitching Society (2013)Thomas Brown: Change by design, Harper Business (2009)\n\nMMI 05.27 - Design Thinking\nDesign Thinking\nModulbeauftragte*r\nResponsible\nProf. Dr.  Alina Huldtgren\nDozent*in\nTeaching staff\nLehrende*r der Hochschule Düsseldorf\nStudiengang\nM.Sc. Medieninformatik 2025\nVerwendung in anderen\nStudiengängen: / Used in other\nstudy programmes\nM.Sc. Medieninformatik, PO 2018 /\nM.Sc. Media Informatics, PO 2018\n\n\nLehrformen (alle Angaben in SWS zu je 45 Minuten / all values in SWS of 45 minutes each)\n\nCredits/\nCredits\nWorkload /\nWorkload\nKontaktzeit/\nContact time\nSelbststudium/\nSelf study\nDauer/\nLength\nSemester/\nSemester\nSprache/\nLanguage\n5\n150 h\n\n60 h\n90 h\n1 Sem.\n\nEnglish on\ndemand\nVorlesung/\nLecture\nÜbung/\nPractice\nSeminar/\nSeminar\nPraktiku\nm/ Lab\nwork\nProjekt/\nProject\nTutorium/\nTutorial\nSeminarist.\nUnterricht/\nSeminaristic\nlesson\nStudien\narbeit/\nResearch\nproject\nBegleitetes\nSelbstlernen/\nAccompan‘d\nself study\n2\n\n\n\n2\n\n\n\n\nModulkategorie / category\n\nWahlangebot / Module offer\nWahlkatalog(e) /\n\n/\nelective catalogue(s)\n\n\nVoraussetzungen zur Teilnahme /\nrequirements for participation\n\n\nFormal /\nFormal\n\nKeine /\nnone\n\nInhaltlich /\ncontentwise\n\nKeine /\nnone\nVoraussetzungen zur Prüfung /\nprerequisites for the\nexamination\n\nKeine / None\nPrüfungsform /\nform of examination\n\nProjektprüfung /\nProject examination\nBenotet, Stellenwert der Note\nfür die Endnote /\ngraded, value of the grade for\nthe final grade\n\nBenotet: Ja / Is graded: Yes\n\n5/90 bzw. 5/120 / 5/90 resp. 5/120\nVoraussetzungen zur\nCreditvergabe/ requirements for\nawarding credit:\n\nBestandene Modulprüfung / Passed module examination\n\nLernergebnisse, Kompetenzen:\n\n\nDie Studierenden verstehen, warum eine Balance zwischen\nNutzerfokus, ökonomischen Abwägungen und technischer\nMachbarkeit zur Entwicklung neuer digitaler Medien wichtig ist. In\ndiesem Zusammenhang lernen sie das Konzept des Wicked\nProblems kennen, mit denen Designer sich heutzutage oft\nkonfrontiert sehen. Die Studierenden lernen den Prozess des\nDesign Thinkings mit den 5 Schritten: Verstehen, Beobachten,\nPoint-of-View, Ideenfindung, Prototyping, und Verfeinerung\n\nHochschule Düsseldorf\nModulhandbuch M.Sc. Medieninformatik\nVersion 1.0\nPO 2025\n87\n\n\nEnglish descriptions\n\nkennen und wenden Methoden der Standford d.school in einer\nDesignaufgabe an.\n\nLehrinhalte:\n\n\nTeambuilding mittels Marshmallow Challenge oder vgl.Einführung\nWicked Problems und Veränderungen der Anforderungen an das\nDesign digitaler Medien im Zeitalter der DigitalisierungÜbersicht\nDesign Thinking: 5 Phasen, T-Shaped People, Prinzipien des\nDesign Thinkings (z.B. Show don't tell, Radical Collaboration,\netc)Anwendung einzelner Design Thinking Methoden in den\nPhasenAusgewählte Ansätze des iterativen Prototypings je nach\ngewähltem Themenkomplex der VeranstaltungProjektarbeit in\nGruppen bzgl eines zuvor ausgewählten Problembereichs und\neiner geeigneten Fragestellung\n\nLiteratur:\n\n\nJürgen Erbeldinger, Thomas Ramge, Erik Spiekermann: Durch\ndie Decke denken: Design Thinking in der Praxis, Redline\n(2013)Martin J. Eppler: Creability: Gemeinsam kreativ - innovative\nMethoden für die Ideenentwicklung in Teams, Schäfer/Poeschel\n(2014)Sebastian Olma, Yulia Kryazheva: The Serendipity\nMachine, Verlag Stitching Society (2013)Thomas Brown: Change\nby design, Harper Business (2009)\n\nLearning outcomes,\ncompetences\n\n\nThe students understand why it is important to keep a balance\nbetween user focus, economical considerations and technical\nfeasibility for the development of new digital media. In this\ncontext, they have learned about the wicked problems, which\ndesigners often face today. The students know the process of\ndesign thinking and its five phases: understanding, observing,\npoint-of-view, brainstorming, prototyping and refinement. They\nhave applied methods of the Stanford d.school to a design task.\n\nContent\n\n\nTeam building exercise (e.g. the Marshmallow\nChallenge)Introduction to wicked problems and changing\nrequirements for the design of digital media in the digital\nageOverview of design thinking: five phases, T-shaped people,\nprinciples of design thinking (e.g. ‘Show, don’t tell!’, radical\ncollaboration etc.)Application of individual design thinking\nmethods in the different phasesSelected approaches of iterative\nprototyping according to the topic of the courseProject work in\ngroups on a previously selected problem area and a suitable\nresearch question\n\nHochschule Düsseldorf\nModulhandbuch M.Sc. Medieninformatik\nVersion 1.0\nPO 2025\n88", "metadata": {"moduleNumber": "MMI 05.27", "moduleName": "Design Thinking", "creditPoints": "5.0", "suggestedSemester": null, "offeredInSeason": "to_be_announced", "examType": "project", "heldInLanguage": "en_on_demand", "reviserName": "Prof. Dr. Alina Huldtgren", "reviserEmail": "alina.huldtgren@hs-duesseldorf.de", "studyProgramId": 11, "source_type": "json", "moduleNameDe": "Design Thinking", "source_file": "MMI_MHB_PO2025_V1.0.pdf", "pdf_page_start": 86, "pdf_page_end": 87, "studyProgramAbbrev": "MMI", "studyProgram_Url": "https://medien.hs-duesseldorf.de/mmi", "pdf_url": "https://medien.hs-duesseldorf.de/studium/studiengaenge/Documents/Modulhandb%C3%BCcher/MMI_MHB_PO2025_V1.0.pdf"}}
{"id": "MMI05.28", "text": "Title: Selected Aspects of Multimedia Systems\nModule Number: MMI 05.28\nCredits: 5.0 CP\nSemester: None\nOffered In: every_semester\nLanguage: de\nExam Type: none\nInstructor: Prof. Dr. Thomas Franz (thomas.franz@hs-duesseldorf.de)\n--- Goals (EN) ---\nThe students know relevant concepts, systems, technologies and fields of application of a selected area of media informatics. Having familiarised themselves with the topic, they are able to critically evaluate existing work or independently develop new approaches.\n--- Goals (DE) ---\nDer Studierende kennt für einen ausgewählten Bereich der\nMedieninformatik die zugrunde liegenden Konzepte, Systeme & Technologien bzw.\nAnwendungsgebiete. Nach der Einarbeitung in die Thematik ist er in der Lage\nexistierende Arbeiten kritisch zu beurteilen bzw. neue Ansätze eigenständig zu\nentwickeln.\n--- Contents (EN) ---\nEach semester, the lecturer determines the contents for the semester and the study programme director confirms them. This module serves as a placeholder to be able to react flexibly to new developments in media informatics or to include relevant topics from other study programmes. The topics mustbe closely related to media informatics andhave an orientation which is comparable to the orientation of the compulsory elective modules from the professional specialisation Multimedia Systems and Applications.\n--- Contents (DE) ---\nDieses Modul dient als Platzhalter um flexibel auf neue Entwick-lungen in der Medieninformatik / Vertiefungsrichtung „Digitalisie-rung in multimedialen Systemen“ zu reagieren bzw. auch um relevante Fächer aus anderen Studiengängen importieren zu können. Die Fächer müssen einen starken Bezug zur Medienin-formatik auf Masterniveau besitzen und in der Ausrichtung ver-gleichbar sein mit WPF-Modulen aus der Vertiefungsrichtung „Digitalisierung in multimedialen Systemen“. Die Inhalte werden von dem jeweiligen Dozenten festgelegt und durch den Studien-gangskoordinator bestätigt. Bereits früher importierte, externe Module:•\t\"E-Business“ aus BMI PO 2018 (Prüfungsumfang mit Mas-terniveau nach Absprache)•\t„Entwicklung sicherer Software“ aus BMI PO 2018 (Prü-fungsumfang mit Masterniveau nach Absprache)•\t„Musikalische Akustik“ aus BTB PO 2018 (Prüfungsumfang mit Masterniveau nach Absprache)\n--- Literature (EN) ---\n--- Literature (DE) ---\nLiteratur wird vom jeweiligen Dozenten bekannt gegeben. Verstärkt werden neben einschlägigen Lehrbüchern auch Beiträge aus Fachzeitschriften und Konferenzen als Literatur eingesetzt.\n\nMMI 05.28 - Spezielle Aspekte multimedialer Systeme\nSelected Aspects of Multimedia Systems\nModulbeauftragte*r\nResponsible\nThomas Franz\nDozent*in\nTeaching staff\nLehrende*r der Hochschule Düsseldorf\nStudiengang\nM.Sc. Medieninformatik 2025\nVerwendung in anderen\nStudiengängen: / Used in other\nstudy programmes\nM.Sc. Medieninformatik, PO 2018 /\nM.Sc. Media Informatics, PO 2018\n\n\nLehrformen (alle Angaben in SWS zu je 45 Minuten / all values in SWS of 45 minutes each)\n\nCredits/\nCredits\nWorkload /\nWorkload\nKontaktzeit/\nContact time\nSelbststudium/\nSelf study\nDauer/\nLength\nSemester/\nSemester\nSprache/\nLanguage\n5\n150 h\n\n60 h\n90 h\n1 Sem.\n\nDeutsch\nVorlesung/\nLecture\nÜbung/\nPractice\nSeminar/\nSeminar\nPraktiku\nm/ Lab\nwork\nProjekt/\nProject\nTutorium/\nTutorial\nSeminarist.\nUnterricht/\nSeminaristic\nlesson\nStudien\narbeit/\nResearch\nproject\nBegleitetes\nSelbstlernen/\nAccompan‘d\nself study\n\n\n2\n\n2\n\n\n\n\nModulkategorie / category\n\nWahlangebot / Module offer\nWahlkatalog(e) /\n\n/\nelective catalogue(s)\n\n\nVoraussetzungen zur Teilnahme /\nrequirements for participation\n\n\nFormal /\nFormal\n\nKeine /\nnone\n\nInhaltlich /\ncontentwise\n\nKeine /\nnone\nVoraussetzungen zur Prüfung /\nprerequisites for the\nexamination\n\nKeine / None\nPrüfungsform /\nform of examination\n\nKeine Prüfung /\nNo exam\nBenotet, Stellenwert der Note\nfür die Endnote /\ngraded, value of the grade for\nthe final grade\n\nBenotet: Ja / Is graded: Yes\n\n5/90 bzw. 5/120 / 5/90 resp. 5/120\nVoraussetzungen zur\nCreditvergabe/ requirements for\nawarding credit:\n\nBestandene Modulprüfung / Passed module examination\n\nLernergebnisse, Kompetenzen:\n\n\nDer Studierende kennt für einen ausgewählten Bereich der\nMedieninformatik die zugrunde liegenden Konzepte, Systeme &\nTechnologien bzw.\nAnwendungsgebiete. Nach der Einarbeitung in die Thematik ist er\nin der Lage\nexistierende Arbeiten kritisch zu beurteilen bzw. neue Ansätze\neigenständig zu\nentwickeln.\n\nHochschule Düsseldorf\nModulhandbuch M.Sc. Medieninformatik\nVersion 1.0\nPO 2025\n89\n\n\nEnglish descriptions\n\n\nLehrinhalte:\n\n\nDieses Modul dient als Platzhalter um flexibel auf neue Entwick-\nlungen in der Medieninformatik / Vertiefungsrichtung 'Digitalisie-\nrung in multimedialen Systemen' zu reagieren bzw. auch um\nrelevante Fächer aus anderen Studiengängen importieren zu\nkönnen. Die Fächer müssen einen starken Bezug zur Medienin-\nformatik auf Masterniveau besitzen und in der Ausrichtung ver-\ngleichbar sein mit WPF-Modulen aus der Vertiefungsrichtung\n'Digitalisierung in multimedialen Systemen'. Die Inhalte werden\nvon dem jeweiligen Dozenten festgelegt und durch den Studien-\ngangskoordinator bestätigt. Bereits früher importierte, externe\nModule:•\n'E-Business' aus BMI PO 2018 (Prüfungsumfang\nmit Mas-terniveau nach Absprache)•\n'Entwicklung sicherer\nSoftware' aus BMI PO 2018 (Prü-fungsumfang mit Masterniveau\nnach Absprache)•\n'Musikalische Akustik' aus BTB PO 2018\n(Prüfungsumfang mit Masterniveau nach Absprache)\n\nLiteratur:\n\n\nLiteratur wird vom jeweiligen Dozenten bekannt gegeben.\nVerstärkt werden neben einschlägigen Lehrbüchern auch Beiträge\naus Fachzeitschriften und Konferenzen als Literatur eingesetzt.\n\nLearning outcomes,\ncompetences\n\n\nThe students know relevant concepts, systems, technologies\nand fields of application of a selected area of media informatics.\nHaving familiarised themselves with the topic, they are able to\ncritically evaluate existing work or independently develop new\napproaches.\n\nContent\n\n\nEach semester, the lecturer determines the contents for the\nsemester and the study programme director confirms them. This\nmodule serves as a placeholder to be able to react flexibly to\nnew developments in media informatics or to include relevant\ntopics from other study programmes. The topics mustbe closely\nrelated to media informatics andhave an orientation which is\ncomparable to the orientation of the compulsory elective\nmodules from the professional specialisation Multimedia\nSystems and Applications.\n\nHochschule Düsseldorf\nModulhandbuch M.Sc. Medieninformatik\nVersion 1.0\nPO 2025\n90", "metadata": {"moduleNumber": "MMI 05.28", "moduleName": "Selected Aspects of Multimedia Systems", "creditPoints": "5.0", "suggestedSemester": null, "offeredInSeason": "every_semester", "examType": "none", "heldInLanguage": "de", "reviserName": "Prof. Dr. Thomas Franz", "reviserEmail": "thomas.franz@hs-duesseldorf.de", "studyProgramId": 11, "source_type": "json", "moduleNameDe": "Spezielle Aspekte multimedialer Systeme", "source_file": "MMI_MHB_PO2025_V1.0.pdf", "pdf_page_start": 88, "pdf_page_end": 89, "studyProgramAbbrev": "MMI", "studyProgram_Url": "https://medien.hs-duesseldorf.de/mmi", "pdf_url": "https://medien.hs-duesseldorf.de/studium/studiengaenge/Documents/Modulhandb%C3%BCcher/MMI_MHB_PO2025_V1.0.pdf"}}
{"id": "MMI05.29", "text": "Title: Selected Aspects of Virtual Environments\nModule Number: MMI 05.29\nCredits: 5.0 CP\nSemester: None\nOffered In: every_semester\nLanguage: en_on_demand\nExam Type: none\nInstructor: Prof. Dr. Eng. Univ. of Tsukuba Jens Herder (jens.herder@hs-duesseldorf.de)\n--- Goals (EN) ---\nThe student knows the underlying concepts, systems & technologies and areas of application for a selected area of Virtual Environments / Media Informatics. After familiarising themselves with the topic, they will be able to critically assess existing work and independently develop new approaches.\n--- Goals (DE) ---\nDer Studierende kennt für einen ausgewählten Bereich der Richtung\nVirtueller Umgebungen / Medieninformatik die zugrunde liegenden Konzepte, Systeme\n& Technologien bzw. Anwendungsgebiete. Nach der Einarbeitung in die\nThematik ist er in der Lage, existierende Arbeiten kritisch zu beurteilen bzw.\nneue Ansätze eigenständig zu entwickeln.\n--- Contents (EN) ---\nEach semester, the lecturer determines the contents for the semester and the study programme director confirms them. This module serves as a placeholder to be able to react flexibly to new developments in virtual systems and media informatics or to include relevant topics from other study programmes. The topics mustbe closely related to media informatics andhave an orientation which is comparable to the orientation of the compulsory elective modules from the professional specialisation Virtual Environments.\n--- Contents (DE) ---\nDieses Modul dient als Platzhalter um flexibel auf neue Entwicklungen in der Medieninformatik / Vertiefungsrichtung „Virtuelle Umgebungen“ zu reagieren bzw. auch relevante Fächer aus anderen Studiengängen importieren zu können. Die Fächer müssen einen starken Bezug zur Medieninformatik auf Masterniveau besitzen und in der Ausrichtung vergleichbar sein mit WPF-Modulen aus der Vertiefungsrichtung „Virtuelle Umgebungen“. Die Inhalte werden von dem jeweiligen Dozenten festgelegt und durch den Studiengangskoordinator bestätigt. Bereits früher importierte, externe Module:„Einführung in die 3D Modellierung“ aus BMI PO 2018 (Prüfungsumfang mit Masterniveau nach Absprache)„Pencils and Polygons“ aus BMT PO 2018 (Prüfungsumfang mit Masterniveau nach Absprache)\n--- Literature (EN) ---\nRecommended literature will be announced depending on the topic. In addition to relevant books, the recommendations may include articles from specialist journals and contributions from conferences.\n--- Literature (DE) ---\nWird vom jeweiligen Dozenten bekannt gegeben. Verstärkt werden neben einschlägigen Lehrbüchern auch Beiträge aus Fachzeitschriften und Konferenzen als Literatur eingesetzt.\n\nMMI 05.29 - Spezielle Aspekte virtueller Umgebungen\nSelected Aspects of Virtual Environments\nModulbeauftragte*r\nResponsible\nJens Herder\nDozent*in\nTeaching staff\nLehrende*r der Hochschule Düsseldorf\nStudiengang\nM.Sc. Medieninformatik 2025\nVerwendung in anderen\nStudiengängen: / Used in other\nstudy programmes\nM.Sc. Medieninformatik, PO 2018 /\nM.Sc. Media Informatics, PO 2018\n\n\nLehrformen (alle Angaben in SWS zu je 45 Minuten / all values in SWS of 45 minutes each)\n\nCredits/\nCredits\nWorkload /\nWorkload\nKontaktzeit/\nContact time\nSelbststudium/\nSelf study\nDauer/\nLength\nSemester/\nSemester\nSprache/\nLanguage\n5\n150 h\n\n60 h\n90 h\n1 Sem.\n\nEnglish on\ndemand\nVorlesung/\nLecture\nÜbung/\nPractice\nSeminar/\nSeminar\nPraktiku\nm/ Lab\nwork\nProjekt/\nProject\nTutorium/\nTutorial\nSeminarist.\nUnterricht/\nSeminaristic\nlesson\nStudien\narbeit/\nResearch\nproject\nBegleitetes\nSelbstlernen/\nAccompan‘d\nself study\n\n\n2\n\n2\n\n\n\n\nModulkategorie / category\n\nWahlangebot / Module offer\nWahlkatalog(e) /\n\n/\nelective catalogue(s)\n\n\nVoraussetzungen zur Teilnahme /\nrequirements for participation\n\n\nFormal /\nFormal\n\nKeine /\nnone\n\nInhaltlich /\ncontentwise\n\nKeine /\nnone\nVoraussetzungen zur Prüfung /\nprerequisites for the\nexamination\n\nKeine / None\nPrüfungsform /\nform of examination\n\nKeine Prüfung /\nNo exam\nBenotet, Stellenwert der Note\nfür die Endnote /\ngraded, value of the grade for\nthe final grade\n\nBenotet: Ja / Is graded: Yes\n\n5/90 bzw. 5/120 / 5/90 resp. 5/120\nVoraussetzungen zur\nCreditvergabe/ requirements for\nawarding credit:\n\nBestandene Modulprüfung / Passed module examination\n\nLernergebnisse, Kompetenzen:\n\n\nDer Studierende kennt für einen ausgewählten Bereich der\nRichtung\nVirtuelle Systeme / Medieninformatik die zugrunde liegenden\nKonzepte, Systeme\n& Technologien bzw. Anwendungsgebiete. Nach der Einarbeitung\nin die\nThematik ist er in der Lage, existierende Arbeiten kritisch zu\nbeurteilen bzw.\n\nHochschule Düsseldorf\nModulhandbuch M.Sc. Medieninformatik\nVersion 1.0\nPO 2025\n91\n\n\nEnglish descriptions\n\nneue Ansätze eigenständig zu entwickeln.\n\nLehrinhalte:\n\n\nDieses Modul dient als Platzhalter um flexibel auf neue\nEntwicklungen in der Medieninformatik / Vertiefungsrichtung\n'Virtuelle Umgebungen' zu reagieren bzw. auch relevante Fächer\naus anderen Studiengängen importieren zu können. Die Fächer\nmüssen einen starken Bezug zur Medieninformatik auf\nMasterniveau besitzen und in der Ausrichtung vergleichbar sein\nmit WPF-Modulen aus der Vertiefungsrichtung 'Virtuelle\nUmgebungen'. Die Inhalte werden von dem jeweiligen Dozenten\nfestgelegt und durch den Studiengangskoordinator bestätigt.\nBereits früher importierte, externe Module:'Einführung in die 3D\nModellierung' aus BMI PO 2018 (Prüfungsumfang mit\nMasterniveau nach Absprache)'Pencils and Polygons' aus BMT\nPO 2018 (Prüfungsumfang mit Masterniveau nach Absprache)\n\nLiteratur:\n\n\nWird vom jeweiligen Dozenten bekannt gegeben. Verstärkt\nwerden neben einschlägigen Lehrbüchern auch Beiträge aus\nFachzeitschriften und Konferenzen als Literatur eingesetzt.\n\nLearning outcomes,\ncompetences\n\n\nRecommended literature will be announced depending on the\ntopic. In addition to relevant books, the recommendations may\ninclude articles from specialist journals and contributions from\nconferences.\n\nContent\n\n\nEach semester, the lecturer determines the contents for the\nsemester and the study programme director confirms them. This\nmodule serves as a placeholder to be able to react flexibly to\nnew developments in virtual systems and media informatics or to\ninclude relevant topics from other study programmes. The topics\nmustbe closely related to media informatics andhave an\norientation which is comparable to the orientation of the\ncompulsory elective modules from the professional\nspecialisation Virtual Environments.\n\nHochschule Düsseldorf\nModulhandbuch M.Sc. Medieninformatik\nVersion 1.0\nPO 2025\n92", "metadata": {"moduleNumber": "MMI 05.29", "moduleName": "Selected Aspects of Virtual Environments", "creditPoints": "5.0", "suggestedSemester": null, "offeredInSeason": "every_semester", "examType": "none", "heldInLanguage": "en_on_demand", "reviserName": "Prof. Dr. Eng. Univ. of Tsukuba Jens Herder", "reviserEmail": "jens.herder@hs-duesseldorf.de", "studyProgramId": 11, "source_type": "json", "moduleNameDe": "Spezielle Aspekte virtueller Umgebungen", "source_file": "MMI_MHB_PO2025_V1.0.pdf", "pdf_page_start": 90, "pdf_page_end": 91, "studyProgramAbbrev": "MMI", "studyProgram_Url": "https://medien.hs-duesseldorf.de/mmi", "pdf_url": "https://medien.hs-duesseldorf.de/studium/studiengaenge/Documents/Modulhandb%C3%BCcher/MMI_MHB_PO2025_V1.0.pdf"}}
{"id": "MMI05.30", "text": "Title: Digital Literacy & AI Literacy\nModule Number: MMI 05.30\nCredits: 5.0 CP\nSemester: 1\nOffered In: winter_semester\nLanguage: de\nExam Type: portfolio\nInstructor: Prof. Dr. rer. nat. Michael Marmann (marmann@hs-duesseldorf.de)\n--- Goals (EN) ---\nThe students\n\n- recognize the importance of digital literacy in today's information society.\n- understand the basic concepts and applications of artificial intelligence.\n- can critically evaluate digital tools and use them effectively for different purposes.\n- are able to identify and discuss the ethical and social implications of AI use.\n- develop the ability to analyze AI technologies in terms of data protection and data security.\n- can design and implement their own projects using AI elements.\n- can research and structure a current topic and present it at several levels of abstraction \n- are able to argue a topic in the seminar group \n- can prepare a current topic digitally and with interactive elements\n--- Goals (DE) ---\nDie Studierenden\n\n- erkennen die Bedeutung von Digital Literacy in der heutigen Informationsgesellschaft.\n- verstehen die grundlegenden Konzepte und Anwendungen künstlicher Intelligenz.\n- können digitale Werkzeuge kritisch bewerten und effektiv für verschiedene Zwecke einsetzen.\n- sind in der Lage, ethische und soziale Implikationen der KI-Nutzung zu identifizieren und zu diskutieren.\n- entwickeln die Fähigkeit, KI-Technologien in Bezug auf Datenschutz und Datensicherheit zu analysieren.\n- können eigene Projekte unter Einbeziehung von AI-Elementen konzipieren und umsetzen.\n- können ein aktuelles Thema recherchieren, strukturieren und auf mehreren Abstraktionslevels präsentieren \n- können ein bearbeitetes Thema in der Seminargruppe argumentativ vertreten \n- können ein aktuelles Thema digital und mit interaktiven Elementen aufbereiten\n--- Contents (EN) ---\nThe 'Digital Literacy & AI Literacy' seminar provides students with an in-depth understanding of the digital literacies necessary to navigate effectively in the modern world. It covers the skills needed to search, evaluate and create information digitally. The focus is on critically examining the reliability and credibility of digital content.\n\nIn parallel, there is a focus on AI Literacy, which covers the understanding and application of artificial intelligence in different areas of life and work. Students will learn the basic principles of AI systems, including machine learning and data processing. They deal with the latest developments in the field of AI and reflect on their impact on society and the individual.\n\nThe seminar also examines the ethical aspects of digital and AI technologies, such as data protection, algorithmic bias and the effects of automation on the labor market. Methods are developed to deal with these challenges and students are enabled to plan and implement their own digital and AI-related projects.\n--- Contents (DE) ---\nDas Seminar \"Digital Literacy & AI Literacy\" bietet den Studierenden ein tiefgreifendes Verständnis der digitalen Kompetenzen, die notwendig sind, um in der modernen Welt effektiv zu navigieren. Es behandelt die Fähigkeiten, die benötigt werden, um Informationen digital zu suchen, zu bewerten und zu erstellen. Im Zentrum steht die kritische Auseinandersetzung mit der Verlässlichkeit und Glaubwürdigkeit von digitalen Inhalten.\n\nParallel dazu wird ein Schwerpunkt auf AI Literacy gelegt, der das Verständnis und die Anwendung von künstlicher Intelligenz in verschiedenen Lebens- und Arbeitsbereichen umfasst. Die Studierenden lernen die Grundprinzipien von KI-Systemen kennen, einschließlich maschinellem Lernen und Datenverarbeitung. Sie setzen sich mit den neuesten Entwicklungen im Bereich der KI auseinander und reflektieren deren Auswirkungen auf Gesellschaft und Individuum.\n\nDas Seminar beleuchtet zudem die ethischen Aspekte der digitalen und KI-Technologien, wie Datenschutz, Bias in Algorithmen (algorithmic bias) und die Auswirkungen der Automatisierung auf den Arbeitsmarkt. Es werden Methoden erarbeitet, um mit diesen Herausforderungen umzugehen und die Studierenden dazu befähigt, eigene digitale und KI-bezogene Projekte zu planen und zu realisieren.\n--- Literature (EN) ---\nCurrent literature references and sources of information are provided at the beginning of the module or directly from the course context. In addition, digital media are increasingly used as a source of knowledge.\n--- Literature (DE) ---\nAktuelle Literaturhinweise und Informationsquellen werden zu Beginn des Moduls oder unmittelbar aus dem Veranstaltungskontext herausgegeben. Zusätzlich werden verstärkt digitale Medien als Wissensquelle eingesetzt.\n\nMMI 05.30 - Digital Literacy & AI Literacy\nDigital Literacy & AI Literacy\nModulbeauftragte*r\nResponsible\nProf. Dr. rer. nat. Michael Marmann\nDozent*in\nTeaching staff\nLehrende*r der Hochschule Düsseldorf\nStudiengang\nM.Sc. Medieninformatik 2025\nVerwendung in anderen\nStudiengängen: / Used in other\nstudy programmes\nB.A. Creative, Synthetic & Interactive Media, PO 2026\nB.Sc. Medieninformatik, PO 2025\nB.Eng. Medientechnik, PO 2025\nB.Eng. Ton und Bild, PO 2025 /\nB.A. Creative, Synthetic & Interactive Media, PO 2026\nB.Sc. Media Informatics, PO 2025\nB.Eng. Media Engineering, PO 2025\nB.Eng. Audio and Video, PO 2025\n\n\nLehrformen (alle Angaben in SWS zu je 45 Minuten / all values in SWS of 45 minutes each)\n\nCredits/\nCredits\nWorkload /\nWorkload\nKontaktzeit/\nContact time\nSelbststudium/\nSelf study\nDauer/\nLength\nSemester/\nSemester\nSprache/\nLanguage\n5\n150 h\n\n60 h\n90 h\n1 Sem.\n1\nDeutsch\nVorlesung/\nLecture\nÜbung/\nPractice\nSeminar/\nSeminar\nPraktiku\nm/ Lab\nwork\nProjekt/\nProject\nTutorium/\nTutorial\nSeminarist.\nUnterricht/\nSeminaristic\nlesson\nStudien\narbeit/\nResearch\nproject\nBegleitetes\nSelbstlernen/\nAccompan‘d\nself study\n\n\n3\n1\n\n\n\n\n\nModulkategorie / category\n\nWahlangebot / Module offer\nWahlkatalog(e) /\n\n/\nelective catalogue(s)\n\n\nVoraussetzungen zur Teilnahme /\nrequirements for participation\n\n\nFormal /\nFormal\n\nKeine /\nnone\n\nInhaltlich /\ncontentwise\n\nKeine /\nnone\nVoraussetzungen zur Prüfung /\nprerequisites for the\nexamination\n\nErfolgreiche Teilnahme am Seminar und Praktikum / Successful\nparticipation in seminar and lab work\nPrüfungsform /\nform of examination\n\nBearbeitung von Seminar-, Praktikums-, oder Übungsaufgaben\noder Laborversuchen (Portfolio) /\nPortfolio submittal or participation in laboratory experiments\nBenotet, Stellenwert der Note\nfür die Endnote /\ngraded, value of the grade for\nthe final grade\n\nBenotet: Ja / Is graded: Yes\n\n5/90 bzw. 5/120 / 5/90 resp. 5/120\nVoraussetzungen zur\nCreditvergabe/ requirements for\nawarding credit:\n\nBestandene Modulprüfung / Passed module examination\n\nLernergebnisse, Kompetenzen:\n\n\nDie Studierenden\n\n\nHochschule Düsseldorf\nModulhandbuch M.Sc. Medieninformatik\nVersion 1.0\nPO 2025\n93\n\n- erkennen die Bedeutung von Digital Literacy in der heutigen\nInformationsgesellschaft.\n\n- verstehen die grundlegenden Konzepte und Anwendungen\nkünstlicher Intelligenz.\n\n- können digitale Werkzeuge kritisch bewerten und effektiv für\nverschiedene Zwecke einsetzen.\n\n- sind in der Lage, ethische und soziale Implikationen der KI-\nNutzung zu identifizieren und zu diskutieren.\n\n- entwickeln die Fähigkeit, KI-Technologien in Bezug auf\nDatenschutz und Datensicherheit zu analysieren.\n\n- können eigene Projekte unter Einbeziehung von AI-Elementen\nkonzipieren und umsetzen.\n\n- können ein aktuelles Thema recherchieren, strukturieren und auf\nmehreren Abstraktionslevels präsentieren\n\n- können ein bearbeitetes Thema in der Seminargruppe\nargumentativ vertreten\n\n- können ein aktuelles Thema digital und mit interaktiven\nElementen aufbereiten\n\nLehrinhalte:\n\n\nDas Seminar 'Digital Literacy & AI Literacy' bietet den\nStudierenden ein tiefgreifendes Verständnis der digitalen\nKompetenzen, die notwendig sind, um in der modernen Welt\neffektiv zu navigieren. Es behandelt die Fähigkeiten, die benötigt\nwerden, um Informationen digital zu suchen, zu bewerten und zu\nerstellen. Im Zentrum steht die kritische Auseinandersetzung mit\nder Verlässlichkeit und Glaubwürdigkeit von digitalen Inhalten.\n\nParallel dazu wird ein Schwerpunkt auf AI Literacy gelegt, der das\nVerständnis und die Anwendung von künstlicher Intelligenz in\nverschiedenen Lebens- und Arbeitsbereichen umfasst. Die\nStudierenden lernen die Grundprinzipien von KI-Systemen\nkennen, einschließlich maschinellem Lernen und\nDatenverarbeitung. Sie setzen sich mit den neuesten\nEntwicklungen im Bereich der KI auseinander und reflektieren\nderen Auswirkungen auf Gesellschaft und Individuum.\n\nDas Seminar beleuchtet zudem die ethischen Aspekte der\ndigitalen und KI-Technologien, wie Datenschutz, Bias in\nAlgorithmen (algorithmic bias) und die Auswirkungen der\nAutomatisierung auf den Arbeitsmarkt. Es werden Methoden\nerarbeitet, um mit diesen Herausforderungen umzugehen und die\nStudierenden dazu befähigt, eigene digitale und KI-bezogene\nProjekte zu planen und zu realisieren.\n\nLiteratur:\n\n\nAktuelle Literaturhinweise und Informationsquellen werden zu\n\nHochschule Düsseldorf\nModulhandbuch M.Sc. Medieninformatik\nVersion 1.0\nPO 2025\n94\n\n\nEnglish descriptions\n\nBeginn des Moduls oder unmittelbar aus dem\nVeranstaltungskontext herausgegeben. Zusätzlich werden\nverstärkt digitale Medien als Wissensquelle eingesetzt.\n\nLearning outcomes,\ncompetences\n\n\nThe students\n\n- recognize the importance of digital literacy in today's\ninformation society.\n\n- understand the basic concepts and applications of artificial\nintelligence.\n\n- can critically evaluate digital tools and use them effectively for\ndifferent purposes.\n\n- are able to identify and discuss the ethical and social\nimplications of AI use.\n\n- develop the ability to analyze AI technologies in terms of data\nprotection and data security.\n\n- can design and implement their own projects using AI\nelements.\n\n- can research and structure a current topic and present it at\nseveral levels of abstraction\n\n- are able to argue a topic in the seminar group\n\n- can prepare a current topic digitally and with interactive\nelements\n\nContent\n\n\nThe 'Digital Literacy & AI Literacy' seminar provides students\nwith an in-depth understanding of the digital literacies necessary\nto navigate effectively in the modern world. It covers the skills\nneeded to search, evaluate and create information digitally. The\nfocus is on critically examining the reliability and credibility of\ndigital content.\n\nIn parallel, there is a focus on AI Literacy, which covers the\nunderstanding and application of artificial intelligence in different\nareas of life and work. Students will learn the basic principles of\nAI systems, including machine learning and data processing.\nThey deal with the latest developments in the field of AI and\nreflect on their impact on society and the individual.\n\nThe seminar also examines the ethical aspects of digital and AI\ntechnologies, such as data protection, algorithmic bias and the\neffects of automation on the labor market. Methods are\ndeveloped to deal with these challenges and students are\nenabled to plan and implement their own digital and AI-related\nprojects.\n\nHochschule Düsseldorf\nModulhandbuch M.Sc. Medieninformatik\nVersion 1.0\nPO 2025\n95", "metadata": {"moduleNumber": "MMI 05.30", "moduleName": "Digital Literacy & AI Literacy", "creditPoints": "5.0", "suggestedSemester": 1, "offeredInSeason": "winter_semester", "examType": "portfolio", "heldInLanguage": "de", "reviserName": "Prof. Dr. rer. nat. Michael Marmann", "reviserEmail": "marmann@hs-duesseldorf.de", "studyProgramId": 11, "source_type": "json", "moduleNameDe": "Digital Literacy & AI Literacy", "source_file": "MMI_MHB_PO2025_V1.0.pdf", "pdf_page_start": 92, "pdf_page_end": 94, "studyProgramAbbrev": "MMI", "studyProgram_Url": "https://medien.hs-duesseldorf.de/mmi", "pdf_url": "https://medien.hs-duesseldorf.de/studium/studiengaenge/Documents/Modulhandb%C3%BCcher/MMI_MHB_PO2025_V1.0.pdf"}}
{"id": "MMI05.31", "text": "Title: New Work & New Learning\nModule Number: MMI 05.31\nCredits: 5.0 CP\nSemester: 2\nOffered In: summer_semester\nLanguage: de\nExam Type: portfolio\nInstructor: Prof. Dr. rer. nat. Michael Marmann (marmann@hs-duesseldorf.de)\n--- Goals (EN) ---\nThe students\n\n- understand the concepts and driving forces behind the New Work movement.\n- can identify the principles of New Learning and apply them to educational contexts.\n- are able to design modern working and learning environments that promote creativity and innovation.\n- can critically analyze the effects of new technologies on work and education.\n- develop skills to act as change agents in their organizations.\n- can implement interdisciplinary approaches for lifelong learning and agile work processes.\n- can research and structure a current topic and present it at several levels of abstraction.\n- can argue a topic in the seminar group.\n- can prepare a current topic digitally and with interactive elements.\n--- Goals (DE) ---\nDie Studierenden\n- verstehen die Konzepte und treibenden Kräfte hinter der New Work-Bewegung.\n- können die Prinzipien des New Learning identifizieren und auf Bildungskontexte anwenden.\n- sind in der Lage, moderne Arbeits- und Lernumgebungen zu gestalten, die Kreativität und Innovation fördern.\n- können kritisch die Auswirkungen neuer Technologien auf Arbeit und Bildung analysieren.\n- entwickeln Fähigkeiten, um als Change Agents in ihren Organisationen zu fungieren.\n- können interdisziplinäre Ansätze für lebenslanges Lernen und agile Arbeitsprozesse implementieren.\n- können ein aktuelles Thema recherchieren, strukturieren und auf mehreren Abstraktionslevels präsentieren.\n- können ein bearbeitetes Thema in der Seminargruppe argumentativ vertreten.\n- können ein aktuelles Thema digital und mit interaktiven Elementen aufbereiten.\n--- Contents (EN) ---\nThis seminar deals with the current changes in the world of work and their influence on learning processes. The basics of the New Work movement, which focuses on autonomy, flexibility and participation in the workplace, as well as the principles of New Learning, which emphasizes self-directed learning and the use of new technologies, are covered. Students learn about innovative approaches to the design of working and learning environments that take into account both the individual needs of learners and the requirements of modern organizations.\n\nAn essential part of the seminar is the examination of the challenges and opportunities that digital technologies bring for the world of work and education. Concepts such as lifelong learning, knowledge management and skills development in the context of New Work and New Learning will be discussed.\n\nThe seminar promotes the development of skills that enable participants to act as change agents and implement interdisciplinary approaches in their own professional contexts. This includes critical reflection on existing structures and the ability to design and manage agile and flexible learning and work processes.\n--- Contents (DE) ---\nDieses Seminar beschäftigt sich mit den aktuellen Veränderungen in der Arbeitswelt und deren Einfluss auf Lernprozesse. Es werden die Grundlagen der New Work-Bewegung, die auf Autonomie, Flexibilität und Partizipation am Arbeitsplatz abzielt, sowie die Prinzipien des New Learning, welches Selbstgesteuertes Lernen und den Einsatz neuer Technologien in den Vordergrund stellt, behandelt. Die Studierenden lernen innovative Ansätze zur Gestaltung von Arbeits- und Lernumgebungen kennen, die sowohl die individuellen Bedürfnisse der Lernenden als auch die Anforderungen moderner Organisationen berücksichtigen.\n\nEin wesentlicher Bestandteil des Seminars ist die Auseinandersetzung mit den Herausforderungen und Chancen, die digitale Technologien für die Arbeitswelt und das Bildungswesen mit sich bringen. Es werden Konzepte wie das lebenslange Lernen, Wissensmanagement und die Kompetenzentwicklung im Kontext von New Work und New Learning diskutiert.\n\nDas Seminar fördert die Entwicklung von Kompetenzen, die es den Teilnehmenden ermöglichen, als Change Agents zu agieren und interdisziplinäre Ansätze in ihren eigenen beruflichen Kontexten umzusetzen. Dies beinhaltet die kritische Reflexion über bestehende Strukturen und die Fähigkeit, agile und flexible Lern- und Arbeitsprozesse zu gestalten und zu steuern.\n--- Literature (EN) ---\nCurrent literature references and sources of information are provided at the beginning of the module or directly from the course context. In addition, digital media are increasingly used as a source of knowledge.\n--- Literature (DE) ---\nAktuelle Literaturhinweise und Informationsquellen werden zu Beginn des Moduls oder unmittelbar aus dem Veranstaltungskontext herausgegeben. Zusätzlich werden verstärkt digitale Medien als Wissensquelle eingesetzt.\n\nMMI 05.31 - New Work & New Learning\nNew Work & New Learning\nModulbeauftragte*r\nResponsible\nProf. Dr. rer. nat. Michael Marmann\nDozent*in\nTeaching staff\nLehrende*r der Hochschule Düsseldorf\nStudiengang\nM.Sc. Medieninformatik 2025\nVerwendung in anderen\nStudiengängen: / Used in other\nstudy programmes\nB.A. Creative, Synthetic & Interactive Media, PO 2026\nB.Sc. Medieninformatik, PO 2025\nB.Eng. Medientechnik, PO 2025\nB.Eng. Ton und Bild, PO 2025 /\nB.A. Creative, Synthetic & Interactive Media, PO 2026\nB.Sc. Media Informatics, PO 2025\nB.Eng. Media Engineering, PO 2025\nB.Eng. Audio and Video, PO 2025\n\n\nLehrformen (alle Angaben in SWS zu je 45 Minuten / all values in SWS of 45 minutes each)\n\nCredits/\nCredits\nWorkload /\nWorkload\nKontaktzeit/\nContact time\nSelbststudium/\nSelf study\nDauer/\nLength\nSemester/\nSemester\nSprache/\nLanguage\n5\n150 h\n\n60 h\n90 h\n1 Sem.\n2\nDeutsch\nVorlesung/\nLecture\nÜbung/\nPractice\nSeminar/\nSeminar\nPraktiku\nm/ Lab\nwork\nProjekt/\nProject\nTutorium/\nTutorial\nSeminarist.\nUnterricht/\nSeminaristic\nlesson\nStudien\narbeit/\nResearch\nproject\nBegleitetes\nSelbstlernen/\nAccompan‘d\nself study\n\n\n3\n1\n\n\n\n\n\nModulkategorie / category\n\nWahlangebot / Module offer\nWahlkatalog(e) /\n\n/\nelective catalogue(s)\n\n\nVoraussetzungen zur Teilnahme /\nrequirements for participation\n\n\nFormal /\nFormal\n\nKeine /\nnone\n\nInhaltlich /\ncontentwise\n\nKeine /\nnone\nVoraussetzungen zur Prüfung /\nprerequisites for the\nexamination\n\nErfolgreiche Teilnahme am Seminar und Praktikum / Successful\nparticipation in seminar and lab work\nPrüfungsform /\nform of examination\n\nBearbeitung von Seminar-, Praktikums-, oder Übungsaufgaben\noder Laborversuchen (Portfolio) /\nPortfolio submittal or participation in laboratory experiments\nBenotet, Stellenwert der Note\nfür die Endnote /\ngraded, value of the grade for\nthe final grade\n\nBenotet: Ja / Is graded: Yes\n\n5/90 bzw. 5/120 / 5/90 resp. 5/120\nVoraussetzungen zur\nCreditvergabe/ requirements for\nawarding credit:\n\nBestandene Modulprüfung / Passed module examination\n\nLernergebnisse, Kompetenzen:\n\n\nDie Studierenden\n\n\nHochschule Düsseldorf\nModulhandbuch M.Sc. Medieninformatik\nVersion 1.0\nPO 2025\n96\n\n\nEnglish descriptions\n- verstehen die Konzepte und treibenden Kräfte hinter der New\nWork-Bewegung.\n- können die Prinzipien des New Learning identifizieren und auf\nBildungskontexte anwenden.\n- sind in der Lage, moderne Arbeits- und Lernumgebungen zu\ngestalten, die Kreativität und Innovation fördern.\n- können kritisch die Auswirkungen neuer Technologien auf Arbeit\nund Bildung analysieren.\n- entwickeln Fähigkeiten, um als Change Agents in ihren\nOrganisationen zu fungieren.\n- können interdisziplinäre Ansätze für lebenslanges Lernen und\nagile Arbeitsprozesse implementieren.\n- können ein aktuelles Thema recherchieren, strukturieren und auf\nmehreren Abstraktionslevels präsentieren.\n- können ein bearbeitetes Thema in der Seminargruppe\nargumentativ vertreten.\n- können ein aktuelles Thema digital und mit interaktiven\nElementen aufbereiten.\n\nLehrinhalte:\n\n\nDieses Seminar beschäftigt sich mit den aktuellen Veränderungen\nin der Arbeitswelt und deren Einfluss auf Lernprozesse. Es\nwerden die Grundlagen der New Work-Bewegung, die auf\nAutonomie, Flexibilität und Partizipation am Arbeitsplatz abzielt,\nsowie die Prinzipien des New Learning, welches\nSelbstgesteuertes Lernen und den Einsatz neuer Technologien in\nden Vordergrund stellt, behandelt. Die Studierenden lernen\ninnovative Ansätze zur Gestaltung von Arbeits- und\nLernumgebungen kennen, die sowohl die individuellen\nBedürfnisse der Lernenden als auch die Anforderungen moderner\nOrganisationen berücksichtigen.\n\nEin wesentlicher Bestandteil des Seminars ist die\nAuseinandersetzung mit den Herausforderungen und Chancen,\ndie digitale Technologien für die Arbeitswelt und das\nBildungswesen mit sich bringen. Es werden Konzepte wie das\nlebenslange Lernen, Wissensmanagement und die\nKompetenzentwicklung im Kontext von New Work und New\nLearning diskutiert.\n\nDas Seminar fördert die Entwicklung von Kompetenzen, die es\nden Teilnehmenden ermöglichen, als Change Agents zu agieren\nund interdisziplinäre Ansätze in ihren eigenen beruflichen\nKontexten umzusetzen. Dies beinhaltet die kritische Reflexion\nüber bestehende Strukturen und die Fähigkeit, agile und flexible\nLern- und Arbeitsprozesse zu gestalten und zu steuern.\n\nLiteratur:\n\n\nAktuelle Literaturhinweise und Informationsquellen werden zu\nBeginn des Moduls oder unmittelbar aus dem\nVeranstaltungskontext herausgegeben. Zusätzlich werden\nverstärkt digitale Medien als Wissensquelle eingesetzt.\n\nHochschule Düsseldorf\nModulhandbuch M.Sc. Medieninformatik\nVersion 1.0\nPO 2025\n97\n\n\n\nLearning outcomes,\ncompetences\n\n\nThe students\n\n- understand the concepts and driving forces behind the New\nWork movement.\n- can identify the principles of New Learning and apply them to\neducational contexts.\n- are able to design modern working and learning environments\nthat promote creativity and innovation.\n- can critically analyze the effects of new technologies on work\nand education.\n- develop skills to act as change agents in their organizations.\n- can implement interdisciplinary approaches for lifelong learning\nand agile work processes.\n- can research and structure a current topic and present it at\nseveral levels of abstraction.\n- can argue a topic in the seminar group.\n- can prepare a current topic digitally and with interactive\nelements.\n\nContent\n\n\nThis seminar deals with the current changes in the world of work\nand their influence on learning processes. The basics of the New\nWork movement, which focuses on autonomy, flexibility and\nparticipation in the workplace, as well as the principles of New\nLearning, which emphasizes self-directed learning and the use\nof new technologies, are covered. Students learn about\ninnovative approaches to the design of working and learning\nenvironments that take into account both the individual needs of\nlearners and the requirements of modern organizations.\n\nAn essential part of the seminar is the examination of the\nchallenges and opportunities that digital technologies bring for\nthe world of work and education. Concepts such as lifelong\nlearning, knowledge management and skills development in the\ncontext of New Work and New Learning will be discussed.\n\nThe seminar promotes the development of skills that enable\nparticipants to act as change agents and implement\ninterdisciplinary approaches in their own professional contexts.\nThis includes critical reflection on existing structures and the\nability to design and manage agile and flexible learning and work\nprocesses.\n\nHochschule Düsseldorf\nModulhandbuch M.Sc. Medieninformatik\nVersion 1.0\nPO 2025\n98", "metadata": {"moduleNumber": "MMI 05.31", "moduleName": "New Work & New Learning", "creditPoints": "5.0", "suggestedSemester": 2, "offeredInSeason": "summer_semester", "examType": "portfolio", "heldInLanguage": "de", "reviserName": "Prof. Dr. rer. nat. Michael Marmann", "reviserEmail": "marmann@hs-duesseldorf.de", "studyProgramId": 11, "source_type": "json", "moduleNameDe": "New Work & New Learning", "source_file": "MMI_MHB_PO2025_V1.0.pdf", "pdf_page_start": 95, "pdf_page_end": 97, "studyProgramAbbrev": "MMI", "studyProgram_Url": "https://medien.hs-duesseldorf.de/mmi", "pdf_url": "https://medien.hs-duesseldorf.de/studium/studiengaenge/Documents/Modulhandb%C3%BCcher/MMI_MHB_PO2025_V1.0.pdf"}}
{"id": "MMI05.33", "text": "Title: 360deg Video\nModule Number: MMI 05.33\nCredits: 5.0 CP\nSemester: None\nOffered In: to_be_announced\nLanguage: de\nExam Type: project\nInstructor: Prof. Dr. rer. nat. Christian Geiger (geiger@hs-duesseldorf.de)\n--- Goals (EN) ---\nThe students have gained an overview of relevant technologies for immersive media productions. At the same time, they have experienced changed procedures in digital storytelling and media production as a holistic process. They have learned the essential steps in the process from conception to playout of immersive contents and applied the acquired knowledge to practical immersive media production. The students have also taken a closer look at relevant effects of this new media form on users and society.\n--- Goals (DE) ---\nDie Studierenden erhalten einen Überblick relevanter Technologien für die immersive Medienproduktion und betrachten gleichzeitig die geänderten Vorgehensweisen im Storytelling und der Medienproduktion als ganzheitlichen Prozess. Sie erlernen die wesentlichen Arbeitsschritte von der Konzeption bis zur Ausspielung immersiver Inhalte und wenden das erworbene Wissen praktisch in einer immersiven Medienproduktion an. Die Auswirkungen dieser neuen Vermittlungsform werden ebenfalls umfangreich betrachtet.\n--- Contents (EN) ---\nFundamentals of moving image production in the context of innovative technologiesHardware and software technologies for mixed reality storytellingNon-linear storytelling for mixed realityImmersive applications: theatre, performances, journalism, educationWorkflow of immersive media productionsReflection on immersive technologies and participatory approaches\n--- Contents (DE) ---\nDas Medium Video bzw. Bewegtbild wird in vielen Bereichen der Digitalisierung eingesetzt, insbesondere im Kontext Wissensvermittlung, Lehre und Ausbildung. Der Einsatz immersiver Technologien in der Medienproduktion erfordert neben der Beherrschung relevanter Technologien auch neue Ansätze der Kameraführung und Aufbereitung der inhaltlichen Darstellung. Die Veranstaltung betrachtet daher sowohl technische, gestalterische, inhaltliche und prozessorientierte Ansätze der Bewegtbildproduktion. Grundlagen Bewegtbildproduktion im Kontext innovativer Technologien Hardware / Softwaretechnologien für Mixed Reality Storytelling Nicht-lineares Storytelling für Mixed Reality Immersive Anwendungsgebiete: Theater, Performances, Journalismus, Ausbildung Workflow immersiver Medienproduktion Reflektion immersiver Technologien und partizipativer Ansätze\n--- Literature (EN) ---\n--- Literature (DE) ---\nJ. Bucher. Storytelling for Virtual Reality: Methods and Principles for Crafting Immersive Narratives, Focal Press, 2017C. Tricart. Virtual Reality Filmmaking: Techniques & Best Practices for VR Filmmakers, Routledge, 2017J. Jerald. The VR Book: Human Centred Design of Virtual Reality, ACM Books, 2015M. Wohl. The 360° Video Handbook: A step-by-step guide to creating video for virtual reality, WohlProductions, 2017K. Kulshreshth, J.J. LaViola Jr. Designing Immersive Video Games Using 3DUI Technologies, Springer, 2018\n\nMMI 05.33 - 360grad Video\n360deg Video\nModulbeauftragte*r\nResponsible\nChristian Geiger\nDozent*in\nTeaching staff\nLehrende*r der Hochschule Düsseldorf\nStudiengang\nM.Sc. Medieninformatik 2025\nVerwendung in anderen\nStudiengängen: / Used in other\nstudy programmes\nM.Sc. Medieninformatik, PO 2018 /\nM.Sc. Media Informatics, PO 2018\n\n\nLehrformen (alle Angaben in SWS zu je 45 Minuten / all values in SWS of 45 minutes each)\n\nCredits/\nCredits\nWorkload /\nWorkload\nKontaktzeit/\nContact time\nSelbststudium/\nSelf study\nDauer/\nLength\nSemester/\nSemester\nSprache/\nLanguage\n5\n150 h\n\n60 h\n90 h\n1 Sem.\n\nDeutsch\nVorlesung/\nLecture\nÜbung/\nPractice\nSeminar/\nSeminar\nPraktiku\nm/ Lab\nwork\nProjekt/\nProject\nTutorium/\nTutorial\nSeminarist.\nUnterricht/\nSeminaristic\nlesson\nStudien\narbeit/\nResearch\nproject\nBegleitetes\nSelbstlernen/\nAccompan‘d\nself study\n\n\n2\n\n2\n\n\n\n1\nModulkategorie / category\n\nWahlangebot / Module offer\nWahlkatalog(e) /\n\n/\nelective catalogue(s)\n\n\nVoraussetzungen zur Teilnahme /\nrequirements for participation\n\n\nFormal /\nFormal\n\nKeine /\nnone\n\nInhaltlich /\ncontentwise\n\nKeine /\nnone\nVoraussetzungen zur Prüfung /\nprerequisites for the\nexamination\n\nKeine / None\nPrüfungsform /\nform of examination\n\nProjektprüfung /\nProject examination\nBenotet, Stellenwert der Note\nfür die Endnote /\ngraded, value of the grade for\nthe final grade\n\nBenotet: Ja / Is graded: Yes\n\n5/90 bzw. 5/120 / 5/90 resp. 5/120\nVoraussetzungen zur\nCreditvergabe/ requirements for\nawarding credit:\n\nBestandene Modulprüfung / Passed module examination\n\nLernergebnisse, Kompetenzen:\n\n\nDie Studierenden erhalten einen Überblick relevanter\nTechnologien für die immersive Medienproduktion und betrachten\ngleichzeitig die geänderten Vorgehensweisen im Storytelling und\nder Medienproduktion als ganzheitlichen Prozess. Sie erlernen die\nwesentlichen Arbeitsschritte von der Konzeption bis zur\nAusspielung immersiver Inhalte und wenden das erworbene\nWissen praktisch in einer immersiven Medienproduktion an. Die\n\nHochschule Düsseldorf\nModulhandbuch M.Sc. Medieninformatik\nVersion 1.0\nPO 2025\n99\n\n\nEnglish descriptions\n\nAuswirkungen dieser neuen Vermittlungsform werden ebenfalls\numfangreich betrachtet.\n\nLehrinhalte:\n\n\nDas Medium Video bzw. Bewegtbild wird in vielen Bereichen der\nDigitalisierung eingesetzt, insbesondere im Kontext\nWissensvermittlung, Lehre und Ausbildung. Der Einsatz\nimmersiver Technologien in der Medienproduktion erfordert neben\nder Beherrschung relevanter Technologien auch neue Ansätze\nder Kameraführung und Aufbereitung der inhaltlichen Darstellung.\nDie Veranstaltung betrachtet daher sowohl technische,\ngestalterische, inhaltliche und prozessorientierte Ansätze der\nBewegtbildproduktion. Grundlagen Bewegtbildproduktion im\nKontext innovativer Technologien Hardware /\nSoftwaretechnologien für Mixed Reality Storytelling Nicht-lineares\nStorytelling für Mixed Reality Immersive Anwendungsgebiete:\nTheater, Performances, Journalismus, Ausbildung Workflow\nimmersiver Medienproduktion Reflektion immersiver Technologien\nund partizipativer Ansätze\n\nLiteratur:\n\n\nJ. Bucher. Storytelling for Virtual Reality: Methods and Principles\nfor Crafting Immersive Narratives, Focal Press, 2017C. Tricart.\nVirtual Reality Filmmaking: Techniques & Best Practices for VR\nFilmmakers, Routledge, 2017J. Jerald. The VR Book: Human\nCentred Design of Virtual Reality, ACM Books, 2015M. Wohl. The\n360° Video Handbook: A step-by-step guide to creating video for\nvirtual reality, WohlProductions, 2017K. Kulshreshth, J.J. LaViola\nJr. Designing Immersive Video Games Using 3DUI Technologies,\nSpringer, 2018\n\nLearning outcomes,\ncompetences\n\n\nThe students have gained an overview of relevant technologies\nfor immersive media productions. At the same time, they have\nexperienced changed procedures in digital storytelling and\nmedia production as a holistic process. They have learned the\nessential steps in the process from conception to playout of\nimmersive contents and applied the acquired knowledge to\npractical immersive media production. The students have also\ntaken a closer look at relevant effects of this new media form on\nusers and society.\n\nContent\n\n\nFundamentals of moving image production in the context of\ninnovative technologiesHardware and software technologies for\nmixed reality storytellingNon-linear storytelling for mixed\nrealityImmersive applications: theatre, performances, journalism,\neducationWorkflow of immersive media productionsReflection on\nimmersive technologies and participatory approaches\n\nHochschule Düsseldorf\nModulhandbuch M.Sc. Medieninformatik\nVersion 1.0\nPO 2025\n100", "metadata": {"moduleNumber": "MMI 05.33", "moduleName": "360deg Video", "creditPoints": "5.0", "suggestedSemester": null, "offeredInSeason": "to_be_announced", "examType": "project", "heldInLanguage": "de", "reviserName": "Prof. Dr. rer. nat. Christian Geiger", "reviserEmail": "geiger@hs-duesseldorf.de", "studyProgramId": 11, "source_type": "json", "moduleNameDe": "360grad Video", "source_file": "MMI_MHB_PO2025_V1.0.pdf", "pdf_page_start": 98, "pdf_page_end": 99, "studyProgramAbbrev": "MMI", "studyProgram_Url": "https://medien.hs-duesseldorf.de/mmi", "pdf_url": "https://medien.hs-duesseldorf.de/studium/studiengaenge/Documents/Modulhandb%C3%BCcher/MMI_MHB_PO2025_V1.0.pdf"}}
{"id": "MMI05.35", "text": "Title: Data Science\nModule Number: MMI 05.35\nCredits: 5.0 CP\nSemester: 2\nOffered In: summer_semester\nLanguage: en_on_demand\nExam Type: portfolio\nInstructor: Prof. Dr. Florian Huber (florian.huber@hs-duesseldorf.de)\n--- Goals (EN) ---\nStudents can use basic data science methods to gain insights from complex data and communicate them. This includes getting to know typical data science workflows that are implemented in a practical way using Python. Central techniques for cleaning, analyzing, interpreting and visualizing data are discussed and applied. Another core aspect is the critical examination of data (or its origin) and interpretations based on it. Insights gained from data are presented and discussed using data visualization\n--- Goals (DE) ---\nDie Studierenden können mit Hilfe grundlegender Data Science Methoden aus komplexen Daten Erkenntnisse zu gewinnen und zu kommunizieren. Dies beinhaltet das Kennenlernen typischer Data Science Workflows die praxisnah mit Python umgesetzt werden. Dabei werden zentrale Techniken zum Aufreinigen, Analysieren, Interpretieren und Visualisieren von Daten besprochen und eingesetzt. Ein weiterer Kernaspekt ist die kritische Auseinandersetzung mit Daten (bzw. deren Ursprung) und darauf beruhenden Interpretationen. Aus Daten gewonnene Erkenntnisse werden über Datenvisualisierungen dargestellt und diskutiert\n--- Contents (EN) ---\n- Use of Python in the field of data science (data import, data exploration, analysis, evaluation) \n- Dealing with common data types and formats. \n- Fundamentals of epistemology and scientific method (correlation, causality, logic, dealing with cognitive distortions)\n- Statistical and graphical analysis of data \n- Application of frequently used clustering algorithms (K-Means, DBSCAN)\n- Techniques for dimensionality reduction (PCA, t-SNE)\n- Fundamentals of network analysis, graph theory \n- Use of machine learning to analyze data as well as for prediction \n- Critical consideration of the possibilities and consequences / technology impact assessment\n--- Contents (DE) ---\n- Nutzung von Python im Bereich Data Science (Datenimport, Datenerkundung, Analyse, Auswertung)  \n- Umgang mit häufigen Datentypen und Formaten. \n- Grundlagen der Erkenntnistheorie und wissenschaftlichen Methode (Korrelation, Kausalität, Logik, Umgang mit kognitiven Verzerrungen)\n- Statistische und graphische Analyse der Daten  \n- Anwendung von häufig genutzten Clustering-Algorithmen (K-Means, DBSCAN)\n- Techniken zur Dimensionsreduktion (PCA, t-SNE)\n- Grundlagen der Netzwerkanalyse, Graphentheorie \n- Einsatz von Maschinellem Lernen zur Analyse von Daten sowie auch zur Vorhersage  \n- Kritische Betrachtung der Möglichkeiten und Konsequenzen / Technikfolgenabschätzung\n--- Literature (EN) ---\nFlorian Huber, \"Introduction to Data (for not-yet-scientists), https://florian-huber.github.io/data_science_course/\n--- Literature (DE) ---\nFlorian Huber, \"Introduction to Data (for not-yet-scientists), https://florian-huber.github.io/data_science_course/\n\nMMI 05.35 - Data Science\nData Science\nModulbeauftragte*r\nResponsible\nFlorian Huber\nDozent*in\nTeaching staff\nLehrende*r der Hochschule Düsseldorf\nStudiengang\nM.Sc. Medieninformatik 2025\nVerwendung in anderen\nStudiengängen: / Used in other\nstudy programmes\nM.Sc. Medieninformatik, PO 2018 /\nM.Sc. Media Informatics, PO 2018\n\n\nLehrformen (alle Angaben in SWS zu je 45 Minuten / all values in SWS of 45 minutes each)\n\nCredits/\nCredits\nWorkload /\nWorkload\nKontaktzeit/\nContact time\nSelbststudium/\nSelf study\nDauer/\nLength\nSemester/\nSemester\nSprache/\nLanguage\n5\n150 h\n\n60 h\n90 h\n1 Sem.\n2\nEnglish on\ndemand\nVorlesung/\nLecture\nÜbung/\nPractice\nSeminar/\nSeminar\nPraktiku\nm/ Lab\nwork\nProjekt/\nProject\nTutorium/\nTutorial\nSeminarist.\nUnterricht/\nSeminaristic\nlesson\nStudien\narbeit/\nResearch\nproject\nBegleitetes\nSelbstlernen/\nAccompan‘d\nself study\n2\n\n0\n2\n0\n\n\n\n\nModulkategorie / category\n\nWahlangebot / Module offer\nWahlkatalog(e) /\n\n/\nelective catalogue(s)\n\n\nVoraussetzungen zur Teilnahme /\nrequirements for participation\n\n\nFormal /\nFormal\n\nKeine /\nnone\n\nInhaltlich /\ncontentwise\n\nKeine /\nnone\nVoraussetzungen zur Prüfung /\nprerequisites for the\nexamination\n\nKeine / None\nPrüfungsform /\nform of examination\n\nPortfolio-Abgabe und mündliche Prüfung /\nPortfolio submittal and oral examination\nBenotet, Stellenwert der Note\nfür die Endnote /\ngraded, value of the grade for\nthe final grade\n\nBenotet: Ja / Is graded: Yes\n\n5/90 bzw. 5/120 / 5/90 resp. 5/120\nVoraussetzungen zur\nCreditvergabe/ requirements for\nawarding credit:\n\nBestandene Modulprüfung / Passed module examination\n\nLernergebnisse, Kompetenzen:\n\n\nDie Studierenden können mit Hilfe grundlegender Data Science\nMethoden aus komplexen Daten Erkenntnisse zu gewinnen und\nzu kommunizieren. Dies beinhaltet das Kennenlernen typischer\nData Science Workflows die praxisnah mit Python umgesetzt\nwerden. Dabei werden zentrale Techniken zum Aufreinigen,\nAnalysieren, Interpretieren und Visualisieren von Daten\nbesprochen und eingesetzt. Ein weiterer Kernaspekt ist die\nkritische Auseinandersetzung mit Daten (bzw. deren Ursprung)\n\nHochschule Düsseldorf\nModulhandbuch M.Sc. Medieninformatik\nVersion 1.0\nPO 2025\n101\n\n\nEnglish descriptions\n\nund darauf beruhenden Interpretationen. Aus Daten gewonnene\nErkenntnisse werden über Datenvisualisierungen dargestellt und\ndiskutiert\n\nLehrinhalte:\n\n\n- Nutzung von Python im Bereich Data Science (Datenimport,\nDatenerkundung, Analyse, Auswertung)\n- Umgang mit häufigen Datentypen und Formaten.\n- Grundlagen der Erkenntnistheorie und wissenschaftlichen\nMethode (Korrelation, Kausalität, Logik, Umgang mit kognitiven\nVerzerrungen)\n- Statistische und graphische Analyse der Daten\n- Anwendung von häufig genutzten Clustering-Algorithmen (K-\nMeans, DBSCAN)\n- Techniken zur Dimensionsreduktion (PCA, t-SNE)\n- Grundlagen der Netzwerkanalyse, Graphentheorie\n- Einsatz von Maschinellem Lernen zur Analyse von Daten sowie\nauch zur Vorhersage\n- Kritische Betrachtung der Möglichkeiten und Konsequenzen /\nTechnikfolgenabschätzung\n\nLiteratur:\n\n\nFlorian Huber, 'Introduction to Data (for not-yet-scientists),\nhttps://florian-huber.github.io/data_science_course/\n\nLearning outcomes,\ncompetences\n\n\nStudents can use basic data science methods to gain insights\nfrom complex data and communicate them. This includes getting\nto know typical data science workflows that are implemented in a\npractical way using Python. Central techniques for cleaning,\nanalyzing, interpreting and visualizing data are discussed and\napplied. Another core aspect is the critical examination of data\n(or its origin) and interpretations based on it. Insights gained\nfrom data are presented and discussed using data visualization\n\nContent\n\n\n- Use of Python in the field of data science (data import, data\nexploration, analysis, evaluation)\n- Dealing with common data types and formats.\n- Fundamentals of epistemology and scientific method\n(correlation, causality, logic, dealing with cognitive distortions)\n- Statistical and graphical analysis of data\n- Application of frequently used clustering algorithms (K-Means,\nDBSCAN)\n- Techniques for dimensionality reduction (PCA, t-SNE)\n- Fundamentals of network analysis, graph theory\n- Use of machine learning to analyze data as well as for\nprediction\n- Critical consideration of the possibilities and consequences /\ntechnology impact assessment\n\nHochschule Düsseldorf\nModulhandbuch M.Sc. Medieninformatik\nVersion 1.0\nPO 2025\n102", "metadata": {"moduleNumber": "MMI 05.35", "moduleName": "Data Science", "creditPoints": "5.0", "suggestedSemester": 2, "offeredInSeason": "summer_semester", "examType": "portfolio", "heldInLanguage": "en_on_demand", "reviserName": "Prof. Dr. Florian Huber", "reviserEmail": "florian.huber@hs-duesseldorf.de", "studyProgramId": 11, "source_type": "json", "moduleNameDe": "Data Science", "source_file": "MMI_MHB_PO2025_V1.0.pdf", "pdf_page_start": 100, "pdf_page_end": 101, "studyProgramAbbrev": "MMI", "studyProgram_Url": "https://medien.hs-duesseldorf.de/mmi", "pdf_url": "https://medien.hs-duesseldorf.de/studium/studiengaenge/Documents/Modulhandb%C3%BCcher/MMI_MHB_PO2025_V1.0.pdf"}}
{"id": "MMI05.36", "text": "Title: Pencils and Polygons\nModule Number: MMI 05.36\nCredits: 5.0 CP\nSemester: 2\nOffered In: summer_semester\nLanguage: de\nExam Type: project\nInstructor: Prof. Dr.-Ing. Sina Mostafawy (sina.mostafawy@hs-duesseldorf.de)\n--- Goals (EN) ---\nThe students know the basics of drawing (picture composition, techniques, shading, perspective). They can transfer their knowledge from 2D to 3D modeling and rendering.\n--- Goals (DE) ---\nDie Studierenden erlernen die Grundlagen des Zeichnens. Sie können das Wissen aus dem 2D Zeichnen in die Erstellung von 3D Modelle übertragen (insbesondere Beleuchtung). Sie wissen, in welcher Form der Begriff des Formens sowie Licht und Schatten die Arbeit in der 3D Welt prägen.\n--- Contents (EN) ---\n- Basics of drawing\n- Dynamic and linear lines\n- Hatching techniques\n- Light and shadow\n- Image composition, image division and -perspective\n- Storyboard drawings\n--- Contents (DE) ---\n- Grundlagen des Zeichnens\n- Dynamische und lineare Linie\n- Schraffur Techniken\n- Licht und Schatten\n- Bildkomposition, Bildeinteilung und -perspektive\n- Storyboard Zeichnungen\n--- Literature (EN) ---\n--- Literature (DE) ---\n- F. A. Cerver: Zeichnen für Einsteiger, Konemann Verlag Koln 2002G. Bammes: Studien zur Gestalt des Menschen, 3. Aufl. Urania Verlag 2001\n\nMMI 05.36 - Pencils and Polygons\nPencils and Polygons\nModulbeauftragte*r\nResponsible\nSina Mostafawy\nDozent*in\nTeaching staff\nLehrende*r der Hochschule Düsseldorf\nStudiengang\nM.Sc. Medieninformatik 2025\nVerwendung in anderen\nStudiengängen: / Used in other\nstudy programmes\nB.Eng. Medientechnik, PO 2018\nB.Sc. Medieninformatik, PO 2018\nB.Sc. Medieninformatik, PO 2025\nB.Eng. Medientechnik, PO 2025\nB.A. Creative, Synthetic & Interactive Media, PO 2026\nB.Eng. Ton und Bild, PO 2025 /\nB.Eng. Media Engineering, PO 2018\nB.Sc. Media Informatics, PO 2018\nB.Sc. Media Informatics, PO 2025\nB.Eng. Media Engineering, PO 2025\nB.A. Creative, Synthetic & Interactive Media, PO 2026\nB.Eng. Audio and Video, PO 2025\n\n\nLehrformen (alle Angaben in SWS zu je 45 Minuten / all values in SWS of 45 minutes each)\n\nCredits/\nCredits\nWorkload /\nWorkload\nKontaktzeit/\nContact time\nSelbststudium/\nSelf study\nDauer/\nLength\nSemester/\nSemester\nSprache/\nLanguage\n5\n150 h\n\n60 h\n90 h\n1 Sem.\n2\nDeutsch\nVorlesung/\nLecture\nÜbung/\nPractice\nSeminar/\nSeminar\nPraktiku\nm/ Lab\nwork\nProjekt/\nProject\nTutorium/\nTutorial\nSeminarist.\nUnterricht/\nSeminaristic\nlesson\nStudien\narbeit/\nResearch\nproject\nBegleitetes\nSelbstlernen/\nAccompan‘d\nself study\n\n\n2\n\n2\n\n\n\n\nModulkategorie / category\n\nWahlangebot / Module offer\nWahlkatalog(e) /\n\n/\nelective catalogue(s)\n\n\nVoraussetzungen zur Teilnahme /\nrequirements for participation\n\n\nFormal /\nFormal\n\nKeine /\nnone\n\nInhaltlich /\ncontentwise\n\nKeine /\nnone\nVoraussetzungen zur Prüfung /\nprerequisites for the\nexamination\n\nErfolgreiche Teilnahme am Seminar und Praktikum / Successful\nparticipation in seminar and lab work\nPrüfungsform /\nform of examination\n\nProjektprüfung /\nProject examination\nBenotet, Stellenwert der Note\nfür die Endnote /\ngraded, value of the grade for\nthe final grade\n\nBenotet: Ja / Is graded: Yes\n\n5/90 bzw. 5/120 / 5/90 resp. 5/120\n\nHochschule Düsseldorf\nModulhandbuch M.Sc. Medieninformatik\nVersion 1.0\nPO 2025\n103\n\n\nEnglish descriptions\n\nVoraussetzungen zur\nCreditvergabe/ requirements for\nawarding credit:\n\nBestandene Modulprüfung / Passed module examination\n\nLernergebnisse, Kompetenzen:\n\n\nDie Studierenden erlernen die Grundlagen des Zeichnens. Sie\nkönnen das Wissen aus dem 2D Zeichnen in die Erstellung von\n3D Modelle übertragen (insbesondere Beleuchtung). Sie wissen,\nin welcher Form der Begriff des Formens sowie Licht und\nSchatten die Arbeit in der 3D Welt prägen.\n\nLehrinhalte:\n\n\nGrundlagen des Zeichnens\nDynamische und lineare Linie\nSchraffur Techniken\nLicht und Schatten\nBildkomposition, Bildeinteilung und -perspektive\nStoryboard Zeichnungen\n\nLiteratur:\n\n\nF. A. Cerver: Zeichnen für Einsteiger, Könemann Verlag Köln\n2002G. Bammes: Studien zur Gestalt des Menschen, 3. Aufl.\nUrania Verlag 2001\n\nLearning outcomes,\ncompetences\n\n\nThe students know the basics of drawing (picture composition,\ntechniques, shading, perspective). They can transfer their\nknowledge from 2D to 3D modeling and rendering.\n\nContent\n\n\nBasics of drawing\nDynamic and linear lines\nHatching techniques\nLight and shadow\nImage composition, image division and -perspective\nStoryboard drawings\n\nHochschule Düsseldorf\nModulhandbuch M.Sc. Medieninformatik\nVersion 1.0\nPO 2025\n104", "metadata": {"moduleNumber": "MMI 05.36", "moduleName": "Pencils and Polygons", "creditPoints": "5.0", "suggestedSemester": 2, "offeredInSeason": "summer_semester", "examType": "project", "heldInLanguage": "de", "reviserName": "Prof. Dr.-Ing. Sina Mostafawy", "reviserEmail": "sina.mostafawy@hs-duesseldorf.de", "studyProgramId": 11, "source_type": "json", "moduleNameDe": "Pencils and Polygons", "source_file": "MMI_MHB_PO2025_V1.0.pdf", "pdf_page_start": 102, "pdf_page_end": 103, "studyProgramAbbrev": "MMI", "studyProgram_Url": "https://medien.hs-duesseldorf.de/mmi", "pdf_url": "https://medien.hs-duesseldorf.de/studium/studiengaenge/Documents/Modulhandb%C3%BCcher/MMI_MHB_PO2025_V1.0.pdf"}}
{"id": "MMI05.37", "text": "Title: Technology utilisation and technology appropriation\nModule Number: MMI 05.37\nCredits: 5.0 CP\nSemester: 1\nOffered In: to_be_announced\nLanguage: de\nExam Type: research_paper\nInstructor: None Martin Doll (martin.doll@hs-duesseldorf.de)\n--- Goals (EN) ---\nStudents have skills in the application of central concepts of media studies, media psychology and media sociology. They are familiar with the theoretical foundations of media usage research and can apply them to specific contexts of their studies and future professional activities. They can analyse the effects of different media and technology usage patterns in a theoretically sound manner and are able to understand their complex conditionality. They recognise the significance of heterogeneity and diversity in patterns of use and appropriation processes of new technologies, are aware of the importance of specific technical skills and have the skills to reflect on their own role, especially from the perspective of new developments in the context of data science and artificial intelligence. In addition to theoretical approaches, e.g. from the fields of media studies, sociology and psychology, students should be able to recognise various aspects of dealing with media and technology (e.g. aspects of activity and passivity, communitisation and isolation, addiction, emotionalisation and cognition) and be able to reflect on them contextually. They should be able to assess the relevance of specific media skills and reflect on their role as developers of digital technologies.\n--- Goals (DE) ---\nStudierende verfügen über Kompetenzen in der Anwendung zentraler Begriffe der Medienwissenschaft, der Medienpsychologie und der Mediensoziologie. Sie kennen theoretische Grundlagen der Mediennutzungsforschung und können sie auf konkrete Kontexte ihres Studiums und künftiger beruflicher Tätigkeit übertragen. Sie können die Auswirkungen verschiedener Medien- und Techniknutzungsmuster theoretisch fundiert analysieren und sind in der Lage, deren komplexe Bedingtheit zu verstehen. Sie erkennen die Bedeutsamkeit von Heterogenität und Diversität in Nutzungsmustern und Aneignungsprozessen neuer Technologien, sind sich der Bedeutung spezifischer Technikkompetenzen bewusst und verfügen über Fähigkeiten zur Reflexion der eigenen Rolle, insbesondere aus der Perspektive neuer Entwicklungen im Kontext von Data Science und künstlicher Intelligenz.Neben theoretischen Ansätzen, z. B. aus dem Feld der Medienwissenschaft, der Soziologie und der Psychologie sollen Studierende in der Lage sein, verschiedene Aspekte des Umgangs mit Medien bzw. Technik (z. B. Aspekte von Aktivität- und Passivität, Vergemeinschaftung und Isolation, Sucht, Emotionalisierung und Kognition) zu erkennen und sie kontextuell reflektieren können. Sie sollen die Relevanz spezifischer Medienkompetenzen beurteilen und ihre Rolle als Entwickler*innen digitaler Technologien reflektieren können.\n--- Contents (EN) ---\nThe module focuses on the human use and appropriation of technology, its conditions and consequences, with a particular focus on accelerated digital change. Students should become familiar with patterns of technology use and appropriation, acquire skills for the theoretically sound analysis of media and technology use, develop awareness of problematic and pathological media use and recognise social functions, e.g. of internet use Central concepts of media science, media psychology and media sociology Central principles of media use research, in particular theoretical approaches from the functional (e.g. uses and gratifications approach), procedural and structural perspectives Societal and social framework conditions and accompanying processes (e.g. basics of media socialisation) of media and technology use and appropriation. Fundamentals of media socialisation) of media and technology use and appropriation Fundamentals of the mediatisation of everyday life and society, mediatisation of social relationships, media and generations, media and cultural change Mediatisation and heterogeneity / diversity, e.g. from the perspective of gender media studies and cultural media studies Models, techniques and practices of data processing Fundamentals of media psychology for analysing the prerequisites and consequences of media use, including the possibilities of shaping mediaTheoretical and practical fundamentals of acquiring, teaching and applying media skills.\n--- Contents (DE) ---\nDer Fokus des Moduls liegt auf der menschlichen Techniknutzung und Technikaneignung, ihren Bedingungen und Folgen unter besonderer Betrachtung eines beschleunigten digitalen Wandels. Studierende sollen Muster der Techniknutzung und -aneignung kennenlernen, Kompetenzen zur theoretisch fundierten Analyse von Medien- und Techniknutzung erwerben, Bewusstsein für problematischen und pathologischen Mediengebrauch entwickeln sowie soziale Funktionen, z. B. des Internetgebrauchs, erkennen.Zentraler Begriffe der Medienwissenschaft, der Medienpsychologie und Mediensoziologie Zentrale Grundlagen der Mediennutzungsforschung, insbesondere theoretische Ansätze aus der funktionalen (z. B. Uses-and-Gratifications-Ansatz), prozessualen und strukturellen Perspektive Gesellschaftliche und soziale Rahmenbedingungen und Begleitprozesse (z. B. Grundlagen der Mediensozialisation) von Medien- bzw. Techniknutzung und -aneignung Grundlagen der Mediatisierung von Alltag und Gesellschaft, Mediatisierung sozialer Beziehungen, Medien und Generationen, Medien und kultureller Wandel Mediatisierung und Heterogenität / Diversität, z. B. aus Sicht der Gender Media Studies und Cultural Media Studies Modelle, Techniken und Praktiken der Verdatung Medienpsychologische Grundlagen zur Analyse der Voraussetzungen sowie der Folgen von Mediennutzung inkl. der Möglichkeiten der Gestaltung von MedienTheoretische und praktische Grundlagen des Erwerbs, der Vermittlung und Anwendung von Medienkompetenzen\n--- Literature (EN) ---\nBonfadelli, H. & Friemel, T.N. (2011). Medienwirkungsforschung. Konstanz, München: UVK; UTB\nKnoblauch, H. (2016). Die kommunikative Konstruktion der Wirklichkeit. Wiesbaden: Springer VS\nKrotz, F., Despotovic, C. & Kruse, M.-M. (Hrsg.) (2017). Mediatisierung als Metaprozess. Transformationen, Formen der Entwicklung und die Generierung von Neuem. Wiesbaden: Springer VS\nMämecke, T., Passoth, J.-H. & Wehner, J. (Hrsg.) (2018). Bedeutende Daten. Modelle, Verfahren und Praxis der Vermessung und Verdatung im Netz. Wiesbaden: Springer VS\nSchweiger, W. (2007). Theorien der Mediennutzung. Eine Einführung. Wiesbaden: Springer VS\nPfadenhauer, M. & Grenz, T. (Hrsg.) (2017). De-Mediatisierung. Diskontinuitäten, Non-Linearitäten und Ambivalenzen im Mediatisierungsprozess. Wiesbaden: Springer VS\nTrepte, S. & Reinecke, K. (2013). Medienpsychologie. Stuttgart: KohlhammerWeitere Literatur wird bei Vorlesungsbeginn bekannt gegeben.\n--- Literature (DE) ---\nBonfadelli, H. & Friemel, T.N. (2011). Medienwirkungsforschung. Konstanz, München: UVK; UTB\nKnoblauch, H. (2016). Die kommunikative Konstruktion der Wirklichkeit. Wiesbaden: Springer VS\nKrotz, F., Despotovic, C. & Kruse, M.-M. (Hrsg.) (2017). Mediatisierung als Metaprozess. Transformationen, Formen der Entwicklung und die Generierung von Neuem. Wiesbaden: Springer VS\nMämecke, T., Passoth, J.-H. & Wehner, J. (Hrsg.) (2018). Bedeutende Daten. Modelle, Verfahren und Praxis der Vermessung und Verdatung im Netz. Wiesbaden: Springer VS\nSchweiger, W. (2007). Theorien der Mediennutzung. Eine Einführung. Wiesbaden: Springer VS\nPfadenhauer, M. & Grenz, T. (Hrsg.) (2017). De-Mediatisierung. Diskontinuitäten, Non-Linearitäten und Ambivalenzen im Mediatisierungsprozess. Wiesbaden: Springer VS\nTrepte, S. & Reinecke, K. (2013). Medienpsychologie. Stuttgart: KohlhammerWeitere Literatur wird bei Vorlesungsbeginn bekannt gegeben.\n\nMMI 05.37 - Techniknutzung und Technikaneignung\nTechnology utilisation and technology appropriation\nModulbeauftragte*r\nResponsible\nMarkus Dahm\nDozent*in\nTeaching staff\nLehrende*r der Hochschule Düsseldorf\nStudiengang\nM.Sc. Medieninformatik 2025\nVerwendung in anderen\nStudiengängen: / Used in other\nstudy programmes\nB.Sc. Data Science, AI und Intelligente Systeme, PO\n2021 /\nB.Sc. Data Science, AI and Intelligent Systems, PO\n2021\n\n\nLehrformen (alle Angaben in SWS zu je 45 Minuten / all values in SWS of 45 minutes each)\n\nCredits/\nCredits\nWorkload /\nWorkload\nKontaktzeit/\nContact time\nSelbststudium/\nSelf study\nDauer/\nLength\nSemester/\nSemester\nSprache/\nLanguage\n5\n150 h\n\n60 h\n90 h\n1 Sem.\n1\nDeutsch\nVorlesung/\nLecture\nÜbung/\nPractice\nSeminar/\nSeminar\nPraktiku\nm/ Lab\nwork\nProjekt/\nProject\nTutorium/\nTutorial\nSeminarist.\nUnterricht/\nSeminaristic\nlesson\nStudien\narbeit/\nResearch\nproject\nBegleitetes\nSelbstlernen/\nAccompan‘d\nself study\n\n\n4\n\n\n\n\n\n\nModulkategorie / category\n\nWahlangebot / Module offer\nWahlkatalog(e) /\n\n/\nelective catalogue(s)\n\n\nVoraussetzungen zur Teilnahme /\nrequirements for participation\n\n\nFormal /\nFormal\n\nKeine /\nnone\n\nInhaltlich /\ncontentwise\n\nKeine /\nnone\nVoraussetzungen zur Prüfung /\nprerequisites for the\nexamination\n\nKeine / None\nPrüfungsform /\nform of examination\n\nStudienarbeitsprüfung /\nResearch paper examination\nBenotet, Stellenwert der Note\nfür die Endnote /\ngraded, value of the grade for\nthe final grade\n\nBenotet: Ja / Is graded: Yes\n\n5/90 bzw. 5/120 / 5/90 resp. 5/120\nVoraussetzungen zur\nCreditvergabe/ requirements for\nawarding credit:\n\nBestandene Modulprüfung / Passed module examination\n\nLernergebnisse, Kompetenzen:\n\n\nStudierende verfügen über Kompetenzen in der Anwendung\nzentraler Begriffe der Medienwissenschaft, der\nMedienpsychologie und der Mediensoziologie. Sie kennen\ntheoretische Grundlagen der Mediennutzungsforschung und\nkönnen sie auf konkrete Kontexte ihres Studiums und künftiger\nberuflicher Tätigkeit übertragen. Sie können die Auswirkungen\nverschiedener Medien- und Techniknutzungsmuster theoretisch\n\nHochschule Düsseldorf\nModulhandbuch M.Sc. Medieninformatik\nVersion 1.0\nPO 2025\n105\n\nfundiert analysieren und sind in der Lage, deren komplexe\nBedingtheit zu verstehen. Sie erkennen die Bedeutsamkeit von\nHeterogenität und Diversität in Nutzungsmustern und\nAneignungsprozessen neuer Technologien, sind sich der\nBedeutung spezifischer Technikkompetenzen bewusst und\nverfügen über Fähigkeiten zur Reflexion der eigenen Rolle,\ninsbesondere aus der Perspektive neuer Entwicklungen im\nKontext von Data Science und künstlicher Intelligenz.Neben\ntheoretischen Ansätzen, z. B. aus dem Feld der\nMedienwissenschaft, der Soziologie und der Psychologie sollen\nStudierende in der Lage sein, verschiedene Aspekte des\nUmgangs mit Medien bzw. Technik (z. B. Aspekte von Aktivität-\nund Passivität, Vergemeinschaftung und Isolation, Sucht,\nEmotionalisierung und Kognition) zu erkennen und sie kontextuell\nreflektieren können. Sie sollen die Relevanz spezifischer\nMedienkompetenzen beurteilen und ihre Rolle als\nEntwickler*innen digitaler Technologien reflektieren können.\n\nLehrinhalte:\n\n\nDer Fokus des Moduls liegt auf der menschlichen Techniknutzung\nund Technikaneignung, ihren Bedingungen und Folgen unter\nbesonderer Betrachtung eines beschleunigten digitalen Wandels.\nStudierende sollen Muster der Techniknutzung und -aneignung\nkennenlernen, Kompetenzen zur theoretisch fundierten Analyse\nvon Medien- und Techniknutzung erwerben, Bewusstsein für\nproblematischen und pathologischen Mediengebrauch entwickeln\nsowie soziale Funktionen, z. B. des Internetgebrauchs,\nerkennen.Zentraler Begriffe der Medienwissenschaft, der\nMedienpsychologie und Mediensoziologie Zentrale Grundlagen\nder Mediennutzungsforschung, insbesondere theoretische\nAnsätze aus der funktionalen (z. B. Uses-and-Gratifications-\nAnsatz), prozessualen und strukturellen Perspektive\nGesellschaftliche und soziale Rahmenbedingungen und\nBegleitprozesse (z. B. Grundlagen der Mediensozialisation) von\nMedien- bzw. Techniknutzung und -aneignung Grundlagen der\nMediatisierung von Alltag und Gesellschaft, Mediatisierung\nsozialer Beziehungen, Medien und Generationen, Medien und\nkultureller Wandel Mediatisierung und Heterogenität / Diversität, z.\nB. aus Sicht der Gender Media Studies und Cultural Media\nStudies Modelle, Techniken und Praktiken der Verdatung\nMedienpsychologische Grundlagen zur Analyse der\nVoraussetzungen sowie der Folgen von Mediennutzung inkl. der\nMöglichkeiten der Gestaltung von MedienTheoretische und\npraktische Grundlagen des Erwerbs, der Vermittlung und\nAnwendung von Medienkompetenzen\n\nLiteratur:\n\n\nBonfadelli, H. & Friemel, T.N. (2011). Medienwirkungsforschung.\nKonstanz, München: UVK; UTB\nKnoblauch, H. (2016). Die kommunikative Konstruktion der\nWirklichkeit. Wiesbaden: Springer VS\nKrotz, F., Despotovic, C. & Kruse, M.-M. (Hrsg.) (2017).\nMediatisierung als Metaprozess. Transformationen, Formen der\nEntwicklung und die Generierung von Neuem. Wiesbaden:\nSpringer VS\n\nHochschule Düsseldorf\nModulhandbuch M.Sc. Medieninformatik\nVersion 1.0\nPO 2025\n106\n\n\nEnglish descriptions\nMämecke, T., Passoth, J.-H. & Wehner, J. (Hrsg.) (2018).\nBedeutende Daten. Modelle, Verfahren und Praxis der\nVermessung und Verdatung im Netz. Wiesbaden: Springer VS\nSchweiger, W. (2007). Theorien der Mediennutzung. Eine\nEinführung. Wiesbaden: Springer VS\nPfadenhauer, M. & Grenz, T. (Hrsg.) (2017). De-Mediatisierung.\nDiskontinuitäten, Non-Linearitäten und Ambivalenzen im\nMediatisierungsprozess. Wiesbaden: Springer VS\nTrepte, S. & Reinecke, K. (2013). Medienpsychologie. Stuttgart:\nKohlhammerWeitere Literatur wird bei Vorlesungsbeginn bekannt\ngegeben.\n\nLearning outcomes,\ncompetences\n\n\nStudents have skills in the application of central concepts of\nmedia studies, media psychology and media sociology. They are\nfamiliar with the theoretical foundations of media usage research\nand can apply them to specific contexts of their studies and\nfuture professional activities. They can analyse the effects of\ndifferent media and technology usage patterns in a theoretically\nsound manner and are able to understand their complex\nconditionality. They recognise the significance of heterogeneity\nand diversity in patterns of use and appropriation processes of\nnew technologies, are aware of the importance of specific\ntechnical skills and have the skills to reflect on their own role,\nespecially from the perspective of new developments in the\ncontext of data science and artificial intelligence. In addition to\ntheoretical approaches, e.g. from the fields of media studies,\nsociology and psychology, students should be able to recognise\nvarious aspects of dealing with media and technology (e.g.\naspects of activity and passivity, communitisation and isolation,\naddiction, emotionalisation and cognition) and be able to reflect\non them contextually. They should be able to assess the\nrelevance of specific media skills and reflect on their role as\ndevelopers of digital technologies.\n\nContent\n\n\nThe module focuses on the human use and appropriation of\ntechnology, its conditions and consequences, with a particular\nfocus on accelerated digital change. Students should become\nfamiliar with patterns of technology use and appropriation,\nacquire skills for the theoretically sound analysis of media and\ntechnology use, develop awareness of problematic and\npathological media use and recognise social functions, e.g. of\ninternet use Central concepts of media science, media\npsychology and media sociology Central principles of media use\nresearch, in particular theoretical approaches from the functional\n(e.g. uses and gratifications approach), procedural and structural\nperspectives Societal and social framework conditions and\naccompanying processes (e.g. basics of media socialisation) of\nmedia and technology use and appropriation. Fundamentals of\nmedia socialisation) of media and technology use and\nappropriation Fundamentals of the mediatisation of everyday life\nand society, mediatisation of social relationships, media and\ngenerations, media and cultural change Mediatisation and\nheterogeneity / diversity, e.g. from the perspective of gender\nmedia studies and cultural media studies Models, techniques\nand practices of data processing Fundamentals of media\npsychology for analysing the prerequisites and consequences of\n\nHochschule Düsseldorf\nModulhandbuch M.Sc. Medieninformatik\nVersion 1.0\nPO 2025\n107\n\n\nmedia use, including the possibilities of shaping\nmediaTheoretical and practical fundamentals of acquiring,\nteaching and applying media skills.\n\nHochschule Düsseldorf\nModulhandbuch M.Sc. Medieninformatik\nVersion 1.0\nPO 2025\n108", "metadata": {"moduleNumber": "MMI 05.37", "moduleName": "Technology utilisation and technology appropriation", "creditPoints": "5.0", "suggestedSemester": 1, "offeredInSeason": "to_be_announced", "examType": "research_paper", "heldInLanguage": "de", "reviserName": "None Martin Doll", "reviserEmail": "martin.doll@hs-duesseldorf.de", "studyProgramId": 11, "source_type": "json", "moduleNameDe": "Techniknutzung und Technikaneignung", "source_file": "MMI_MHB_PO2025_V1.0.pdf", "pdf_page_start": 104, "pdf_page_end": 107, "studyProgramAbbrev": "MMI", "studyProgram_Url": "https://medien.hs-duesseldorf.de/mmi", "pdf_url": "https://medien.hs-duesseldorf.de/studium/studiengaenge/Documents/Modulhandb%C3%BCcher/MMI_MHB_PO2025_V1.0.pdf"}}
{"id": "MMI05.38", "text": "Title: Product Owner Seminar\nModule Number: MMI 05.38\nCredits: 5.0 CP\nSemester: 2\nOffered In: summer_semester\nLanguage: de\nExam Type: project\nInstructor: Prof. Dr. Thomas Franz (thomas.franz@hs-duesseldorf.de)\n--- Goals (EN) ---\n--- Goals (DE) ---\nDie Studierenden kennen ausgewählte Konzepte, Methoden und Praktiken der agilen Software-Produkt-Entwicklung und können diese für Weiterentwicklung konkreter Softwareprodukte anwenden. Sie sind in der Lage, die Entwicklung von Software-Produkten wertorientiert zu planen und in Zusammenarbeit mit agilen Software-Entwicklungsteams zu steuern. Sie können Wert- und Verschwendung identifizieren und beschreiben, sowie Experimente für die Produktinnovation konzipieren und durchführen.\n--- Contents (EN) ---\n--- Contents (DE) ---\nLehrinhalte sind Konzepte, Methoden und Praktiken der agilen Software-Produkt-Entwicklung, insbesondere die Rolle des Product Owners in der agilen Software-Produkt-Entwicklung, die Definition von Wert und Verschwendung, Innovation Accounting, Pivotierungsformen, Produkt-Experimente, agile Planung und Priorisierung.\n--- Literature (EN) ---\n--- Literature (DE) ---\nIn Abhängigkeit aktueller Entwicklungen: verschiedene wissenschaftliche Grundlagen-Artikel sowie (i.d.R. online verfügbare Artikel und Blog-Posts aus der Praxis).\n- RIES, Eric, 2017. The lean startup: how todays entrepreneurs use continuous innovation to create radically successful businesses. Currency international edition, first international edition. New York: Currency. ISBN 9781524762407\n- PICHLER, Roman und Stefan ZUMBRÄGEL, 2023. Strategisches Produktmanagement: Produktstrategien und Roadmaps für digitale Produkte und agile Teams. Übersetzung der 2. englischen Auflage von Stefan Zumbrägel. Heidelberg: dpunkt.verlag. ISBN 9783988900807\n\nMMI 05.38 - Agile Entwicklung von Software-Produkten\nAgile Development of Software Products\nModulbeauftragte*r\nResponsible\nThomas Franz\nDozent*in\nTeaching staff\nLehrende*r der Hochschule Düsseldorf\nStudiengang\nM.Sc. Medieninformatik 2025\nVerwendung in anderen\nStudiengängen: / Used in other\nstudy programmes\nM.Sc. Medieninformatik, PO 2018 /\nM.Sc. Media Informatics, PO 2018\n\n\nLehrformen (alle Angaben in SWS zu je 45 Minuten / all values in SWS of 45 minutes each)\n\nCredits/\nCredits\nWorkload /\nWorkload\nKontaktzeit/\nContact time\nSelbststudium/\nSelf study\nDauer/\nLength\nSemester/\nSemester\nSprache/\nLanguage\n5\n150 h\n\n30 h\n120 h\n1 Sem.\n2\nDeutsch\nVorlesung/\nLecture\nÜbung/\nPractice\nSeminar/\nSeminar\nPraktiku\nm/ Lab\nwork\nProjekt/\nProject\nTutorium/\nTutorial\nSeminarist.\nUnterricht/\nSeminaristic\nlesson\nStudien\narbeit/\nResearch\nproject\nBegleitetes\nSelbstlernen/\nAccompan‘d\nself study\n\n\n2\n\n3\n\n\n\n\nModulkategorie / category\n\nWahlangebot / Module offer\nWahlkatalog(e) /\n\n/\nelective catalogue(s)\n\n\nVoraussetzungen zur Teilnahme /\nrequirements for participation\n\n\nFormal /\nFormal\n\nKeine /\nnone\n\nInhaltlich /\ncontentwise\n\nKeine /\nnone\nVoraussetzungen zur Prüfung /\nprerequisites for the\nexamination\n\nKeine / None\nPrüfungsform /\nform of examination\n\nProjektprüfung /\nProject examination\nBenotet, Stellenwert der Note\nfür die Endnote /\ngraded, value of the grade for\nthe final grade\n\nBenotet: Ja / Is graded: Yes\n\n5/90 bzw. 5/120 / 5/90 resp. 5/120\nVoraussetzungen zur\nCreditvergabe/ requirements for\nawarding credit:\n\nBestandene Modulprüfung / Passed module examination\n\nLernergebnisse, Kompetenzen:\n\n\nDie Studierenden kennen ausgewählte Konzepte, Methoden und\nPraktiken der agilen Software-Produkt-Entwicklung und können\ndiese für Weiterentwicklung konkreter Softwareprodukte\nanwenden. Sie sind in der Lage, die Entwicklung von Software-\nProdukten wertorientiert zu planen und in Zusammenarbeit mit\nagilen Software-Entwicklungsteams zu steuern. Sie können Wert-\nund Verschwendung identifizieren und beschreiben, sowie\n\nHochschule Düsseldorf\nModulhandbuch M.Sc. Medieninformatik\nVersion 1.0\nPO 2025\n109\n\n\nEnglish descriptions\n\nExperimente für die Produktinnovation konzipieren und\ndurchführen.\n\nLehrinhalte:\n\n\nLehrinhalte sind Konzepte, Methoden und Praktiken der agilen\nSoftware-Produkt-Entwicklung, insbesondere die Rolle des\nProduct Owners in der agilen Software-Produkt-Entwicklung, die\nDefinition von Wert und Verschwendung, Innovation Accounting,\nPivotierungsformen, Produkt-Experimente, agile Planung und\nPriorisierung.\n\nLiteratur:\n\n\nIn Abhängigkeit aktueller Entwicklungen: verschiedene\nwissenschaftliche Grundlagen-Artikel sowie (i.d.R. online\nverfügbare Artikel und Blog-Posts aus der Praxis).\n- RIES, Eric, 2017. The lean startup: how todays entrepreneurs\nuse continuous innovation to create radically successful\nbusinesses. Currency international edition, first international\nedition. New York: Currency. ISBN 9781524762407\n- PICHLER, Roman und Stefan ZUMBRÄGEL, 2023.\nStrategisches Produktmanagement: Produktstrategien und\nRoadmaps für digitale Produkte und agile Teams. Übersetzung\nder 2. englischen Auflage von Stefan Zumbrägel. Heidelberg:\ndpunkt.verlag. ISBN 9783988900807\n\nLearning outcomes,\ncompetences\n\n\n\nContent\n\n\n\nHochschule Düsseldorf\nModulhandbuch M.Sc. Medieninformatik\nVersion 1.0\nPO 2025\n110", "metadata": {"moduleNumber": "MMI 05.38", "moduleName": "Product Owner Seminar", "creditPoints": "5.0", "suggestedSemester": 2, "offeredInSeason": "summer_semester", "examType": "project", "heldInLanguage": "de", "reviserName": "Prof. Dr. Thomas Franz", "reviserEmail": "thomas.franz@hs-duesseldorf.de", "studyProgramId": 11, "source_type": "json", "moduleNameDe": "Agile Entwicklung von Software-Produkten", "source_file": "MMI_MHB_PO2025_V1.0.pdf", "pdf_page_start": 108, "pdf_page_end": 109, "studyProgramAbbrev": "MMI", "studyProgram_Url": "https://medien.hs-duesseldorf.de/mmi", "pdf_url": "https://medien.hs-duesseldorf.de/studium/studiengaenge/Documents/Modulhandb%C3%BCcher/MMI_MHB_PO2025_V1.0.pdf"}}
{"id": "MMI05.39", "text": "Title: Entrepreneurship\nModule Number: MMI 05.39\nCredits: 5.0 CP\nSemester: 1\nOffered In: to_be_announced\nLanguage: de\nExam Type: portfolio\nInstructor: None Denise Heidenreich (denise.heidenreich@hs-duesseldorf.de)\n--- Goals (EN) ---\n--- Goals (DE) ---\nNach erfolgreicher Teilnahme an dem Modul sind die Studierenden in der Lage:\n- Entrepreneurship zu definieren \n- Grundungsideen im fachbereichsubergreifenden Zusammenspiel mit anderen Studierenden anhand erlernter Methoden zu entwickeln und fur eine Umsetzung weiter zu nutzen\n- Chancen und Risiken ihrer Geschäftsidee zu bewerten\n- die relevanten Schritte zur Gründung eines Startups/Unternehmens zu nennen, zu erklären und auszuüben\n- ihre eigene Gründungsidee zielgerichtet zu kommunizieren und sich vor einem interdisziplinären Plenum zu positionieren\n- die Weiterentwicklungschancen fur ihre Idee zu erkennen und für die Praxis zu nutzen\n- ihr Wissen über unternehmerisches Denken und Handeln in der Berufspraxis anzuwenden\n--- Contents (EN) ---\n--- Contents (DE) ---\nIn diesem Modul erhalten die Studierenden eine praxisorientierte Einfuhrung in das Thema Entrepreneurship und lernen grundlegende Kenntnisse des unternehmerischen Denkens und Handelns für eine Gründung und/oder ihre berufliche Entwicklung kennen. \n\nLerninhalte im Detail:\n\tEntrepreneurial Mindset und Gründer*innenpersönlichkeit\n\tEntrepreneurship vs. Intrapreneurship\n\tEntwicklung Geschäftsmodelle\n\tWettbewerbsanalyse und Marktforschung \n\tMarketing- und Vertriebsstrategien \n\tSWOT-Analyse\n\tBusiness Model Canvas\n\tFinanzen und Fördermöglichkeiten\n\tInterdisziplinäre Ideenwerkstatt: Wie entwickle ich eine tragfähige Gründungsidee?\n\tDer Wert der Idee und Ideenkommunikation \n\tPitch Deck: Aufbau, Struktur, Ziele\n\nKriterien eines guten Pitches: Zielgruppe, Rhetorik, Körpersprache\n\nArbeitsformen/Methodik\n\nDie Veranstaltung findet im 2-Wochen-Rhythmus statt, um in den einzelnen Einheiten die jeweiligen Bausteine theoretisch einzuführen und im Anschluss direkt in der Praxis zu erproben. Die Studierenden werden nach einer generellen Einführung in Teams arbeiten, um gemeinsam eine reale oder fiktive Idee zu entwickeln und die Gründung durchzuspielen. \n\n- Die Vermittlung der Lehrinhalte erfolgt durch Impulsvorträge, Lehrgespräche und Diskussionen im Rahmen der Lehrveranstaltung. Die einzelnen Aspekte der Lehrinhalte werden in moderierter und gezielt unterstützter Gruppenarbeit erarbeitet. Kreativmethoden und Elemente des Design Thinking werden eingesetzt. Die erlernten Inhalte werden an der eigens entwickelten Idee angewandt. \n- Die Präsentation der eigenen, entwickelten Geschäftsidee erfolgt anhand eines Kurzpitches vor den Lehrenden und den Teilnehmer*innen. Aus den Ideenpitches werden die Ideen für den Praxisteil ausgewählt, an denen die Teilnehmer*innen dann in kleinen Teams weiterarbeiten und die finalen Ideen in einem Abschlussfinale präsentieren.\n\nWeiterer Bestandteil der Prüfungsleistung ist zudem ein aussagekräftiger Kurzbericht für die Weiterentwicklung der Idee.\n--- Literature (EN) ---\n--- Literature (DE) ---\n\nMMI 05.39 - Entrepreneurship\nEntrepreneurship\nModulbeauftragte*r\nResponsible\nMarkus Dahm\nDozent*in\nTeaching staff\nLehrende*r der Hochschule Düsseldorf\nStudiengang\nM.Sc. Medieninformatik 2025\nVerwendung in anderen\nStudiengängen: / Used in other\nstudy programmes\n/\n\n\nLehrformen (alle Angaben in SWS zu je 45 Minuten / all values in SWS of 45 minutes each)\n\nCredits/\nCredits\nWorkload /\nWorkload\nKontaktzeit/\nContact time\nSelbststudium/\nSelf study\nDauer/\nLength\nSemester/\nSemester\nSprache/\nLanguage\n5\n150 h\n\n60 h\n90 h\n1 Sem.\n1\nDeutsch\nVorlesung/\nLecture\nÜbung/\nPractice\nSeminar/\nSeminar\nPraktiku\nm/ Lab\nwork\nProjekt/\nProject\nTutorium/\nTutorial\nSeminarist.\nUnterricht/\nSeminaristic\nlesson\nStudien\narbeit/\nResearch\nproject\nBegleitetes\nSelbstlernen/\nAccompan‘d\nself study\n\n\n2\n\n2\n\n\n\n\nModulkategorie / category\n\nWahlangebot / Module offer\nWahlkatalog(e) /\n\n/\nelective catalogue(s)\n\n\nVoraussetzungen zur Teilnahme /\nrequirements for participation\n\n\nFormal /\nFormal\n\nKeine /\nnone\n\nInhaltlich /\ncontentwise\n\nKeine /\nnone\nVoraussetzungen zur Prüfung /\nprerequisites for the\nexamination\n\nKeine / None\nPrüfungsform /\nform of examination\n\nPortfolio-Abgabe und mündliche Prüfung /\nPortfolio submittal and oral examination\nBenotet, Stellenwert der Note\nfür die Endnote /\ngraded, value of the grade for\nthe final grade\n\nBenotet: Ja / Is graded: Yes\n\n5/90 bzw. 5/120 / 5/90 resp. 5/120\nVoraussetzungen zur\nCreditvergabe/ requirements for\nawarding credit:\n\nBestandene Modulprüfung / Passed module examination\n\nLernergebnisse, Kompetenzen:\n\n\nNach erfolgreicher Teilnahme an dem Modul sind die\nStudierenden in der Lage:\n- Entrepreneurship zu definieren\n- Grundungsideen im fachbereichsubergreifenden Zusammenspiel\nmit anderen Studierenden anhand erlernter Methoden zu\nentwickeln und fur eine Umsetzung weiter zu nutzen\n- Chancen und Risiken ihrer Geschäftsidee zu bewerten\n\nHochschule Düsseldorf\nModulhandbuch M.Sc. Medieninformatik\nVersion 1.0\nPO 2025\n111\n\n- die relevanten Schritte zur Gründung eines\nStartups/Unternehmens zu nennen, zu erklären und auszuüben\n- ihre eigene Gründungsidee zielgerichtet zu kommunizieren und\nsich vor einem interdisziplinären Plenum zu positionieren\n- die Weiterentwicklungschancen fur ihre Idee zu erkennen und\nfür die Praxis zu nutzen\n- ihr Wissen über unternehmerisches Denken und Handeln in der\nBerufspraxis anzuwenden\n\nLehrinhalte:\n\n\nIn diesem Modul erhalten die Studierenden eine praxisorientierte\nEinfuhrung in das Thema Entrepreneurship und lernen\ngrundlegende Kenntnisse des unternehmerischen Denkens und\nHandelns für eine Gründung und/oder ihre berufliche Entwicklung\nkennen.\n\nLerninhalte im Detail:\n\nEntrepreneurial Mindset und Gründer*innenpersönlichkeit\n\nEntrepreneurship vs. Intrapreneurship\n\nEntwicklung Geschäftsmodelle\n\nWettbewerbsanalyse und Marktforschung\n\nMarketing- und Vertriebsstrategien\n\nSWOT-Analyse\n\nBusiness Model Canvas\n\nFinanzen und Fördermöglichkeiten\n\nInterdisziplinäre Ideenwerkstatt: Wie entwickle ich eine\ntragfähige Gründungsidee?\n\nDer Wert der Idee und Ideenkommunikation\n\nPitch Deck: Aufbau, Struktur, Ziele\n\nKriterien eines guten Pitches: Zielgruppe, Rhetorik,\nKörpersprache\n\nArbeitsformen/Methodik\n\nDie Veranstaltung findet im 2-Wochen-Rhythmus statt, um in den\neinzelnen Einheiten die jeweiligen Bausteine theoretisch\neinzuführen und im Anschluss direkt in der Praxis zu erproben.\nDie Studierenden werden nach einer generellen Einführung in\nTeams arbeiten, um gemeinsam eine reale oder fiktive Idee zu\nentwickeln und die Gründung durchzuspielen.\n\n- Die Vermittlung der Lehrinhalte erfolgt durch Impulsvorträge,\nLehrgespräche und Diskussionen im Rahmen der\nLehrveranstaltung. Die einzelnen Aspekte der Lehrinhalte werden\nin moderierter und gezielt unterstützter Gruppenarbeit erarbeitet.\nKreativmethoden und Elemente des Design Thinking werden\neingesetzt. Die erlernten Inhalte werden an der eigens\nentwickelten Idee angewandt.\n- Die Präsentation der eigenen, entwickelten Geschäftsidee erfolgt\nanhand eines Kurzpitches vor den Lehrenden und den\nTeilnehmer*innen. Aus den Ideenpitches werden die Ideen für den\nPraxisteil ausgewählt, an denen die Teilnehmer*innen dann in\n\nHochschule Düsseldorf\nModulhandbuch M.Sc. Medieninformatik\nVersion 1.0\nPO 2025\n112\n\n\nEnglish descriptions\n\nkleinen Teams weiterarbeiten und die finalen Ideen in einem\nAbschlussfinale präsentieren.\n\nWeiterer Bestandteil der Prüfungsleistung ist zudem ein\naussagekräftiger Kurzbericht für die Weiterentwicklung der Idee.\n\nLiteratur:\n\n\n\nLearning outcomes,\ncompetences\n\n\n\nContent\n\n\n\nHochschule Düsseldorf\nModulhandbuch M.Sc. Medieninformatik\nVersion 1.0\nPO 2025\n113", "metadata": {"moduleNumber": "MMI 05.39", "moduleName": "Entrepreneurship", "creditPoints": "5.0", "suggestedSemester": 1, "offeredInSeason": "to_be_announced", "examType": "portfolio", "heldInLanguage": "de", "reviserName": "None Denise Heidenreich", "reviserEmail": "denise.heidenreich@hs-duesseldorf.de", "studyProgramId": 11, "source_type": "json", "moduleNameDe": "Entrepreneurship", "source_file": "MMI_MHB_PO2025_V1.0.pdf", "pdf_page_start": 110, "pdf_page_end": 112, "studyProgramAbbrev": "MMI", "studyProgram_Url": "https://medien.hs-duesseldorf.de/mmi", "pdf_url": "https://medien.hs-duesseldorf.de/studium/studiengaenge/Documents/Modulhandb%C3%BCcher/MMI_MHB_PO2025_V1.0.pdf"}}
{"id": "MMI05.40", "text": "Title: Mixed Reality Art\nModule Number: MMI 05.40\nCredits: 5.0 CP\nSemester: 1\nOffered In: to_be_announced\nLanguage: de\nExam Type: project\nInstructor: Prof. Dr. rer. nat. Christian Geiger (geiger@hs-duesseldorf.de)\n--- Goals (EN) ---\nParticipants will be given an overview of current works on mixed reality art.\nBased on a discussion of the concept of art, they will learn the procedures for the conception, design, development, construction and operation of mixed reality art projects,\ndesign, development, construction and operation of mixed reality art projects. Conceptual, creative, technical and economic aspects are considered in equal measure. Through\nthe critical discussion of current and historically significant examples\nexamples, participants will be able to assess this art form from a technical and conceptual perspective and critically reflect on its use from different angles.The participants have practical experience in pre-visualization and final implementation of simple installation concepts on the basis of selected marketable or freely available tools.\n--- Goals (DE) ---\nDie Teilnehmer erhalten einen Überblick aktueller Arbeiten zu Mixed Reality Art.\nAusgehend von einer Diskussion des Kunstbegriffs lernen sie die Vorgehensweisen bei der Konzeption,\nGestaltung, Entwicklung, Aufbau und Betrieb von Mixed Reality Art Projekten. Dabei werden konzeptionelle, gestalterische, technische und wirtschaftliche Aspekte zu gleichen Teilen betrachtet. Durch\ndie kritische Diskussion aktueller bzw. historisch bedeutsamer\nBeispiele können die Teilnehmer diese Kunstform aus technisch-konzeptioneller Sicht beurteilen und den Einsatz aus verschiedenen Blickwinkeln kritisch\nreflektieren. Die Teilnehmer besitzen praktische Erfahrung in der\nPrävisualisierung und finalen Umsetzung einfacher Installationskonzepte auf Basis ausgewählter marktgängiger bzw. frei verfügbarer Werkzeuge.\n--- Contents (EN) ---\nBasic concepts of mixed reality art (definition, artistic expression, XR technologies, experience)\n- Analysis of historically relevant examples and established artists\n- Critical reflection on selected examples\n- Selected technical aspects of digital and physical object and spatial design, (projection mapping,\n VR/AR, Generative AI)\n- Tools for mixed reality art\n- Workflow, planning and operation of extensive installations\n- Excursion and invited lectures by artists, curators and media experts\n- Seminar phase and project phase\n--- Contents (DE) ---\n- Grundlegende Begriffe Mixed Reality Art (Definition, künstlerischer Ausdruck,  XR-Technologien, Experience)\n- Analyse historisch relevanter Beispiele und etablierter Künstler:innen\n- Kritische Reflektion ausgewählter Beispiele\n- Ausgewählte technische Aspekte des digitale und physischen Objekt- und Raumdesigns (Projection Mapping,\n VR/AR, Generative KI)\n- Werkzeuge für Mixed Reality Art\n- Workflow, Planung und Betrieb umfangreicher Installationen\n- Exkursion und eingeladene Vorträge von Künstler:innen, Kurator:innen und Medienexperten\n- Seminarphase und Projektphase\n--- Literature (EN) ---\nVladimir Geroimenko: Augmented Reality Art: From an Emerging Technology to a Novel Creative Medium (3rd Ed), 2022\n--- Literature (DE) ---\nVladimir Geroimenko: Augmented Reality Art: From an Emerging Technology to a Novel Creative Medium (3rd Ed), 2022\n\nMMI 05.40 - Mixed Reality Art\nMixed Reality Art\nModulbeauftragte*r\nResponsible\nChristian Geiger\nDozent*in\nTeaching staff\nLehrende*r der Hochschule Düsseldorf\nStudiengang\nM.Sc. Medieninformatik 2025\nVerwendung in anderen\nStudiengängen: / Used in other\nstudy programmes\nB.Eng. Ton und Bild, PO 2025 /\nB.Eng. Audio and Video, PO 2025\n\n\nLehrformen (alle Angaben in SWS zu je 45 Minuten / all values in SWS of 45 minutes each)\n\nCredits/\nCredits\nWorkload /\nWorkload\nKontaktzeit/\nContact time\nSelbststudium/\nSelf study\nDauer/\nLength\nSemester/\nSemester\nSprache/\nLanguage\n5\n150 h\n\n60 h\n90 h\n1 Sem.\n1\nDeutsch\nVorlesung/\nLecture\nÜbung/\nPractice\nSeminar/\nSeminar\nPraktiku\nm/ Lab\nwork\nProjekt/\nProject\nTutorium/\nTutorial\nSeminarist.\nUnterricht/\nSeminaristic\nlesson\nStudien\narbeit/\nResearch\nproject\nBegleitetes\nSelbstlernen/\nAccompan‘d\nself study\n\n\n2\n\n2\n\n\n\n\nModulkategorie / category\n\nWahlangebot / Module offer\nWahlkatalog(e) /\n\n/\nelective catalogue(s)\n\n\nVoraussetzungen zur Teilnahme /\nrequirements for participation\n\n\nFormal /\nFormal\n\nKeine /\nnone\n\nInhaltlich /\ncontentwise\n\nKeine /\nnone\nVoraussetzungen zur Prüfung /\nprerequisites for the\nexamination\n\nKeine / None\nPrüfungsform /\nform of examination\n\nProjektprüfung /\nProject examination\nBenotet, Stellenwert der Note\nfür die Endnote /\ngraded, value of the grade for\nthe final grade\n\nBenotet: Ja / Is graded: Yes\n\n5/90 bzw. 5/120 / 5/90 resp. 5/120\nVoraussetzungen zur\nCreditvergabe/ requirements for\nawarding credit:\n\nBestandene Modulprüfung / Passed module examination\n\nLernergebnisse, Kompetenzen:\n\n\nDie Teilnehmer erhalten einen Überblick aktueller Arbeiten zu\nMixed Reality Art.\nAusgehend von einer Diskussion des Kunstbegriffs lernen sie die\nVorgehensweisen bei der Konzeption,\nGestaltung, Entwicklung, Aufbau und Betrieb von Mixed Reality\nArt Projekten. Dabei werden konzeptionelle, gestalterische,\ntechnische und wirtschaftliche Aspekte zu gleichen Teilen\nbetrachtet. Durch\n\nHochschule Düsseldorf\nModulhandbuch M.Sc. Medieninformatik\nVersion 1.0\nPO 2025\n114\n\n\nEnglish descriptions\ndie kritische Diskussion aktueller bzw. historisch bedeutsamer\nBeispiele können die Teilnehmer diese Kunstform aus technisch-\nkonzeptioneller Sicht beurteilen und den Einsatz aus\nverschiedenen Blickwinkeln kritisch\nreflektieren. Die Teilnehmer besitzen praktische Erfahrung in der\nPrävisualisierung und finalen Umsetzung einfacher\nInstallationskonzepte auf Basis ausgewählter marktgängiger bzw.\nfrei verfügbarer Werkzeuge.\n\nLehrinhalte:\n\n\n- Grundlegende Begriffe Mixed Reality Art (Definition,\nkünstlerischer Ausdruck,  XR-Technologien, Experience)\n- Analyse historisch relevanter Beispiele und etablierter\nKünstler:innen\n- Kritische Reflektion ausgewählter Beispiele\n- Ausgewählte technische Aspekte des digitale und physischen\nObjekt- und Raumdesigns (Projection Mapping,\nVR/AR, Generative KI)\n- Werkzeuge für Mixed Reality Art\n- Workflow, Planung und Betrieb umfangreicher Installationen\n- Exkursion und eingeladene Vorträge von Künstler:innen,\nKurator:innen und Medienexperten\n- Seminarphase und Projektphase\n\nLiteratur:\n\n\nVladimir Geroimenko: Augmented Reality Art: From an Emerging\nTechnology to a Novel Creative Medium (3rd Ed), 2022\n\nLearning outcomes,\ncompetences\n\n\nParticipants will be given an overview of current works on mixed\nreality art.\nBased on a discussion of the concept of art, they will learn the\nprocedures for the conception, design, development,\nconstruction and operation of mixed reality art projects,\ndesign, development, construction and operation of mixed reality\nart projects. Conceptual, creative, technical and economic\naspects are considered in equal measure. Through\nthe critical discussion of current and historically significant\nexamples\nexamples, participants will be able to assess this art form from a\ntechnical and conceptual perspective and critically reflect on its\nuse from different angles.The participants have practical\nexperience in pre-visualization and final implementation of\nsimple installation concepts on the basis of selected marketable\nor freely available tools.\n\nContent\n\n\nBasic concepts of mixed reality art (definition, artistic expression,\nXR technologies, experience)\n- Analysis of historically relevant examples and established\nartists\n- Critical reflection on selected examples\n- Selected technical aspects of digital and physical object and\nspatial design, (projection mapping,\nVR/AR, Generative AI)\n- Tools for mixed reality art\n- Workflow, planning and operation of extensive installations\n\nHochschule Düsseldorf\nModulhandbuch M.Sc. Medieninformatik\nVersion 1.0\nPO 2025\n115\n\n\n- Excursion and invited lectures by artists, curators and media\nexperts\n- Seminar phase and project phase\n\nHochschule Düsseldorf\nModulhandbuch M.Sc. Medieninformatik\nVersion 1.0\nPO 2025\n116", "metadata": {"moduleNumber": "MMI 05.40", "moduleName": "Mixed Reality Art", "creditPoints": "5.0", "suggestedSemester": 1, "offeredInSeason": "to_be_announced", "examType": "project", "heldInLanguage": "de", "reviserName": "Prof. Dr. rer. nat. Christian Geiger", "reviserEmail": "geiger@hs-duesseldorf.de", "studyProgramId": 11, "source_type": "json", "moduleNameDe": "Mixed Reality Art", "source_file": "MMI_MHB_PO2025_V1.0.pdf", "pdf_page_start": 113, "pdf_page_end": 115, "studyProgramAbbrev": "MMI", "studyProgram_Url": "https://medien.hs-duesseldorf.de/mmi", "pdf_url": "https://medien.hs-duesseldorf.de/studium/studiengaenge/Documents/Modulhandb%C3%BCcher/MMI_MHB_PO2025_V1.0.pdf"}}
{"id": "MMI05.41", "text": "Title: Metathematisches Storytelling\nModule Number: MMI 05.41\nCredits: 5.0 CP\nSemester: 1\nOffered In: winter_semester\nLanguage: de\nExam Type: portfolio\nInstructor: Prof. Gabriele Schwab-Trapp (gabi.schwab-trapp@hs-duesseldorf.de)\n--- Goals (EN) ---\nStudents acquire skills in the conceptual handling of free or applied topics and the ability to independently develop context-related content. The development and practical realisation of their own ideas is made possible with the help of design processes. Experience in interdisciplinary, creative and constructive collaboration is gained within the seminar and possible project groups as well as in dealing with various forms of presentation.\n--- Goals (DE) ---\nDie Studierenden erwerben Fähigkeiten im konzeptionellen Umgang mit freien oder angewandten Themen und die Befähigung zur selbstständigen Erarbeitung von kontextbezogenen Inhalten. Mithilfe von Gestaltungsprozessen werden die Entwicklung und die praktische Umsetzung eigener Ideen ermöglicht. Erfahrungen in interdisziplinärer, kreativer und konstruktiver Zusammenarbeit werden innerhalb der Seminar- und möglicher Projektgruppen sowie im Umgang mit verschiedenen Präsentationsformen gesammelt.\n--- Contents (EN) ---\nFree or applied topics are dealt with, which are presented at the beginning of the semester. The joint deepening, development and unfolding of the topic takes place in seminar form. This also includes philosophical, knowledge-orientated and opinion-forming discussions. The aim is the independent development and realisation of context-related, visual concepts in various media. Various forms of presentation are practised according to the topics and results. Excursions may take place to support the topics, which will be announced at the beginning of the semester.\nThe module is regularly offered on an open, collaborative and interdisciplinary basis with students from other subject areas.\n\nSuitable advanced tasks are assigned for Master's students.\n--- Contents (DE) ---\nInhaltlich werden freie oder angewandte Themen behandelt, die zu Beginn des Semesters vorgestellt werden. Die gemeinsame Vertiefung, Entwicklung und Entfaltung des Themas findet in Seminarform statt. Dazu gehört auch die philosophische, erkenntnisorientierte und meinungsbildende Auseinandersetzung. Ziel ist die selbstständige Entwicklung und Umsetzung von kontextbezogenen, visuellen Konzepten in unterschiedlichen Medien. Den Themen und Ergebnissen entsprechend werden verschiedene Präsentationsformen eingeübt. Themenunterstützend können Exkursionen stattfinden, die zu Beginn des Semesters bekannt gegeben werden.\nDas Modul wird regelmäßig offen, kollaborativ und interdisziplinär mit Studierenden aus anderen Fachbereichen angeboten.\n\nFür Master-Studierende werden geeignete, fortgeschrittene Aufgaben vergeben.\n--- Literature (EN) ---\nMaterial and literature references are provided for the respective topic in the seminar. Information in the form of text extracts, literature, image examples and research suggestions are provided to support the respective learning, realisation and design steps.\n--- Literature (DE) ---\nMaterial- und Literaturangaben werden zu dem jeweiligen Thema im Seminar ausgegeben. Zur Unterstützung der jeweiligen Lern-, Erkenntnis- und Gestaltungsschritte werden Hinweise in Form von Textauszügen, Literatur, Bildbeispielen und Recherchevorschlägen gegeben.\n\nMMI 05.41 - Metathematisches Storytelling\nMetathematisches Storytelling\nModulbeauftragte*r\nResponsible\nProf.  Gabriele Schwab-Trapp\nDozent*in\nTeaching staff\nLehrende*r der Hochschule Düsseldorf\nStudiengang\nM.Sc. Medieninformatik 2025\nVerwendung in anderen\nStudiengängen: / Used in other\nstudy programmes\nB.A. Creative, Synthetic & Interactive Media, PO 2026\nB.Sc. Medieninformatik, PO 2025 /\nB.A. Creative, Synthetic & Interactive Media, PO 2026\nB.Sc. Media Informatics, PO 2025\n\n\nLehrformen (alle Angaben in SWS zu je 45 Minuten / all values in SWS of 45 minutes each)\n\nCredits/\nCredits\nWorkload /\nWorkload\nKontaktzeit/\nContact time\nSelbststudium/\nSelf study\nDauer/\nLength\nSemester/\nSemester\nSprache/\nLanguage\n5\n150 h\n\n60 h\n90 h\n1 Sem.\n1\nDeutsch\nVorlesung/\nLecture\nÜbung/\nPractice\nSeminar/\nSeminar\nPraktiku\nm/ Lab\nwork\nProjekt/\nProject\nTutorium/\nTutorial\nSeminarist.\nUnterricht/\nSeminaristic\nlesson\nStudien\narbeit/\nResearch\nproject\nBegleitetes\nSelbstlernen/\nAccompan‘d\nself study\n\n\n4\n\n\n\n\n\n\nModulkategorie / category\n\nWahlangebot / Module offer\nWahlkatalog(e) /\n\n/\nelective catalogue(s)\n\n\nVoraussetzungen zur Teilnahme /\nrequirements for participation\n\n\nFormal /\nFormal\n\nKeine /\nnone\n\nInhaltlich /\ncontentwise\n\nKeine /\nnone\nVoraussetzungen zur Prüfung /\nprerequisites for the\nexamination\n\nErfolgreiche Teilnahme am Seminar / Successful participation in\nseminar\nPrüfungsform /\nform of examination\n\nPortfolio-Abgabe und mündliche Prüfung /\nPortfolio submittal and oral examination\nBenotet, Stellenwert der Note\nfür die Endnote /\ngraded, value of the grade for\nthe final grade\n\nBenotet: Ja / Is graded: Yes\n\n5/90 bzw. 5/120 / 5/90 resp. 5/120\nVoraussetzungen zur\nCreditvergabe/ requirements for\nawarding credit:\n\nBestandene Modulprüfung / Passed module examination\n\nLernergebnisse, Kompetenzen:\n\n\nDie Studierenden erwerben Fähigkeiten im konzeptionellen\nUmgang mit freien oder angewandten Themen und die\nBefähigung zur selbstständigen Erarbeitung von\nkontextbezogenen Inhalten. Mithilfe von Gestaltungsprozessen\nwerden die Entwicklung und die praktische Umsetzung eigener\nIdeen ermöglicht. Erfahrungen in interdisziplinärer, kreativer und\nkonstruktiver Zusammenarbeit werden innerhalb der Seminar-\n\nHochschule Düsseldorf\nModulhandbuch M.Sc. Medieninformatik\nVersion 1.0\nPO 2025\n117\n\n\nEnglish descriptions\n\nund möglicher Projektgruppen sowie im Umgang mit\nverschiedenen Präsentationsformen gesammelt.\n\nLehrinhalte:\n\n\nInhaltlich werden freie oder angewandte Themen behandelt, die\nzu Beginn des Semesters vorgestellt werden. Die gemeinsame\nVertiefung, Entwicklung und Entfaltung des Themas findet in\nSeminarform statt. Dazu gehört auch die philosophische,\nerkenntnisorientierte und meinungsbildende Auseinandersetzung.\nZiel ist die selbstständige Entwicklung und Umsetzung von\nkontextbezogenen, visuellen Konzepten in unterschiedlichen\nMedien. Den Themen und Ergebnissen entsprechend werden\nverschiedene Präsentationsformen eingeübt.\nThemenunterstützend können Exkursionen stattfinden, die zu\nBeginn des Semesters bekannt gegeben werden.\nDas Modul wird regelmäßig offen, kollaborativ und interdisziplinär\nmit Studierenden aus anderen Fachbereichen angeboten.\n\nFür Master-Studierende werden geeignete, fortgeschrittene\nAufgaben vergeben.\n\nLiteratur:\n\n\nMaterial- und Literaturangaben werden zu dem jeweiligen Thema\nim Seminar ausgegeben. Zur Unterstützung der jeweiligen Lern-,\nErkenntnis- und Gestaltungsschritte werden Hinweise in Form von\nTextauszügen, Literatur, Bildbeispielen und\nRecherchevorschlägen gegeben.\n\nLearning outcomes,\ncompetences\n\n\nStudents acquire skills in the conceptual handling of free or\napplied topics and the ability to independently develop context-\nrelated content. The development and practical realisation of\ntheir own ideas is made possible with the help of design\nprocesses. Experience in interdisciplinary, creative and\nconstructive collaboration is gained within the seminar and\npossible project groups as well as in dealing with various forms\nof presentation.\n\nContent\n\n\nFree or applied topics are dealt with, which are presented at the\nbeginning of the semester. The joint deepening, development\nand unfolding of the topic takes place in seminar form. This also\nincludes philosophical, knowledge-orientated and opinion-\nforming discussions. The aim is the independent development\nand realisation of context-related, visual concepts in various\nmedia. Various forms of presentation are practised according to\nthe topics and results. Excursions may take place to support the\ntopics, which will be announced at the beginning of the\nsemester.\nThe module is regularly offered on an open, collaborative and\ninterdisciplinary basis with students from other subject areas.\n\nSuitable advanced tasks are assigned for Master's students.\n\nHochschule Düsseldorf\nModulhandbuch M.Sc. Medieninformatik\nVersion 1.0\nPO 2025\n118", "metadata": {"moduleNumber": "MMI 05.41", "moduleName": "Metathematisches Storytelling", "creditPoints": "5.0", "suggestedSemester": 1, "offeredInSeason": "winter_semester", "examType": "portfolio", "heldInLanguage": "de", "reviserName": "Prof. Gabriele Schwab-Trapp", "reviserEmail": "gabi.schwab-trapp@hs-duesseldorf.de", "studyProgramId": 11, "source_type": "json", "moduleNameDe": "Metathematisches Storytelling", "source_file": "MMI_MHB_PO2025_V1.0.pdf", "pdf_page_start": 116, "pdf_page_end": 117, "studyProgramAbbrev": "MMI", "studyProgram_Url": "https://medien.hs-duesseldorf.de/mmi", "pdf_url": "https://medien.hs-duesseldorf.de/studium/studiengaenge/Documents/Modulhandb%C3%BCcher/MMI_MHB_PO2025_V1.0.pdf"}}
{"id": "MMI05.42", "text": "Title: Discursive Design and Future Visions\nModule Number: MMI 05.42\nCredits: 5.0 CP\nSemester: 1\nOffered In: winter_semester\nLanguage: de\nExam Type: portfolio\nInstructor: Prof. Gabriele Schwab-Trapp (gabi.schwab-trapp@hs-duesseldorf.de)\n--- Goals (EN) ---\nStudents recognise the connection between design, technology, science and shaping the future. They are able to critically reflect on design concepts and their effects and can utilise speculative design strategies as a method for generating creative and sustainable ideas. They are able to apply and categorise the research potential of design.\n--- Goals (DE) ---\nDie Studierenden erkennen den Zusammenhang zwischen Design, Technik, Wissenschaft und Zukunftsgestaltung. Sie sind in der Lage Gestaltungskonzepte und deren Auswirkungen kritisch zu reflektieren und können den Einsatz spekulativer Designstrategien als Methode zur Erzeugung kreativer und nachhaltiger Ideen nutzen. Sie sind in der Lage das Forschungspotenzial durch Gestaltung anzuwenden und einzuordnen.\n--- Contents (EN) ---\nStudents are encouraged to engage analytically, theoretically and practically with concepts such as \"Design Fiction\", \"Critical Design\" and \"Speculative Design\". The focus is on the critical examination of current developments in science, technology, design and communication and their potential impact on society.\nOn this basis, possible future scenarios are to be developed and told in free narratives. Through the creative fusion of scientific knowledge and narrative elements, combined with practical applications, alternative realities can be explored and discussions stimulated that promote critical thinking. This integrative approach allows research through design to be trialled, using design as a tool to explore and deepen understanding of current issues and potential future scenarios. The aim is to identify the opportunities and challenges that designers and product developers face when dealing with increasingly complex and urgent social, political and environmental issues.\nThe theoretical discussion includes design and media history, design and media theory, as well as categorisation in the context of social developments.\n\nTranslated with DeepL.com (free version)\n--- Contents (DE) ---\nDie Studierenden werden dazu angeleitet, sich analytisch, theoretisch und praktisch mit Konzepten wie \"Design Fiction\", \"Critical Design\" und \"Speculative Design\" auseinanderzusetzen. Der Schwerpunkt liegt auf der kritischen Untersuchung aktueller Entwicklungen in Wissenschaft, Technik, Design und Kommunikation sowie deren potenziellen Auswirkungen auf die Gesellschaft. \n\nAuf dieser Basis sollen mögliche Zukunftsszenarien entwickelt werden, die in freien Narrativen erzählt werden. Durch die kreative Verschmelzung von wissenschaftlichem Wissen und erzählerischen Elementen, verknüpft mit praktischen Anwendungen, können alternative Realitäten erforscht und Diskussionen angeregt werden, die kritische Denkweisen fördern. Dieser integrative Ansatz ermöglicht es, Forschung durch Gestaltung zu erproben, bei dem Design als Instrument zur Erforschung und Vertiefung des Verständnisses aktueller Themen und potenzieller Zukunftsszenarien dient. Dabei sollen Möglichkeiten und Herausforderungen aufzeigt werden, denen sich GestalterInnen und ProduktentwicklerInnen stellen müssen, wenn sie sich mit immer komplexeren und dringlicheren sozialen, politischen und ökologischen Themen auseinandersetzen.\n\nZu der theoretischen Auseinandersetzung gehören Design- und Mediengeschichte, Design- und Medientheorie, sowie die Einordnung in gesellschaftliche Entwicklungen.\n--- Literature (EN) ---\nMaterial and literature references are provided for the respective topic in the seminar. Information in the form of text extracts, literature, image examples and research suggestions are provided to support the respective learning, realisation and design steps.\n--- Literature (DE) ---\nMaterial- und Literaturangaben werden zu dem jeweiligen Thema im Seminar ausgegeben. Zur Unterstützung der jeweiligen Lern-, Erkenntnis- und Gestaltungsschritte werden Hinweise in Form von Textauszügen, Literatur, Bildbeispielen und Recherchevorschlägen gegeben.\n\nMMI 05.42 - Diskursives Design und Zukunftsvisionen\nDiscursive Design and Future Visions\nModulbeauftragte*r\nResponsible\nProf.  Gabriele Schwab-Trapp\nDozent*in\nTeaching staff\nLehrende*r der Hochschule Düsseldorf\nStudiengang\nM.Sc. Medieninformatik 2025\nVerwendung in anderen\nStudiengängen: / Used in other\nstudy programmes\nB.A. Creative, Synthetic & Interactive Media, PO 2026\nB.Sc. Medieninformatik, PO 2025 /\nB.A. Creative, Synthetic & Interactive Media, PO 2026\nB.Sc. Media Informatics, PO 2025\n\n\nLehrformen (alle Angaben in SWS zu je 45 Minuten / all values in SWS of 45 minutes each)\n\nCredits/\nCredits\nWorkload /\nWorkload\nKontaktzeit/\nContact time\nSelbststudium/\nSelf study\nDauer/\nLength\nSemester/\nSemester\nSprache/\nLanguage\n5\n150 h\n\n60 h\n90 h\n1 Sem.\n1\nDeutsch\nVorlesung/\nLecture\nÜbung/\nPractice\nSeminar/\nSeminar\nPraktiku\nm/ Lab\nwork\nProjekt/\nProject\nTutorium/\nTutorial\nSeminarist.\nUnterricht/\nSeminaristic\nlesson\nStudien\narbeit/\nResearch\nproject\nBegleitetes\nSelbstlernen/\nAccompan‘d\nself study\n\n\n4\n\n\n\n\n\n\nModulkategorie / category\n\nWahlangebot / Module offer\nWahlkatalog(e) /\n\n/\nelective catalogue(s)\n\n\nVoraussetzungen zur Teilnahme /\nrequirements for participation\n\n\nFormal /\nFormal\n\nKeine /\nnone\n\nInhaltlich /\ncontentwise\n\nKeine /\nnone\nVoraussetzungen zur Prüfung /\nprerequisites for the\nexamination\n\nErfolgreiche Teilnahme am Seminar / Successful participation in\nseminar\nPrüfungsform /\nform of examination\n\nPortfolio-Abgabe und mündliche Prüfung /\nPortfolio submittal and oral examination\nBenotet, Stellenwert der Note\nfür die Endnote /\ngraded, value of the grade for\nthe final grade\n\nBenotet: Ja / Is graded: Yes\n\n5/90 bzw. 5/120 / 5/90 resp. 5/120\nVoraussetzungen zur\nCreditvergabe/ requirements for\nawarding credit:\n\nBestandene Modulprüfung / Passed module examination\n\nLernergebnisse, Kompetenzen:\n\n\nDie Studierenden erkennen den Zusammenhang zwischen\nDesign, Technik, Wissenschaft und Zukunftsgestaltung. Sie sind\nin der Lage Gestaltungskonzepte und deren Auswirkungen\nkritisch zu reflektieren und können den Einsatz spekulativer\nDesignstrategien als Methode zur Erzeugung kreativer und\nnachhaltiger Ideen nutzen. Sie sind in der Lage das\n\nHochschule Düsseldorf\nModulhandbuch M.Sc. Medieninformatik\nVersion 1.0\nPO 2025\n119\n\n\nEnglish descriptions\nForschungspotenzial durch Gestaltung anzuwenden und\neinzuordnen.\n\nLehrinhalte:\n\n\nDie Studierenden werden dazu angeleitet, sich analytisch,\ntheoretisch und praktisch mit Konzepten wie 'Design Fiction',\n'Critical Design' und 'Speculative Design' auseinanderzusetzen.\nDer Schwerpunkt liegt auf der kritischen Untersuchung aktueller\nEntwicklungen in Wissenschaft, Technik, Design und\nKommunikation sowie deren potenziellen Auswirkungen auf die\nGesellschaft.\n\nAuf dieser Basis sollen mögliche Zukunftsszenarien entwickelt\nwerden, die in freien Narrativen erzählt werden. Durch die kreative\nVerschmelzung von wissenschaftlichem Wissen und\nerzählerischen Elementen, verknüpft mit praktischen\nAnwendungen, können alternative Realitäten erforscht und\nDiskussionen angeregt werden, die kritische Denkweisen fördern.\nDieser integrative Ansatz ermöglicht es, Forschung durch\nGestaltung zu erproben, bei dem Design als Instrument zur\nErforschung und Vertiefung des Verständnisses aktueller Themen\nund potenzieller Zukunftsszenarien dient. Dabei sollen\nMöglichkeiten und Herausforderungen aufzeigt werden, denen\nsich GestalterInnen und ProduktentwicklerInnen stellen müssen,\nwenn sie sich mit immer komplexeren und dringlicheren sozialen,\npolitischen und ökologischen Themen auseinandersetzen.\n\nZu der theoretischen Auseinandersetzung gehören Design- und\nMediengeschichte, Design- und Medientheorie, sowie die\nEinordnung in gesellschaftliche Entwicklungen.\n\nLiteratur:\n\n\nMaterial- und Literaturangaben werden zu dem jeweiligen Thema\nim Seminar ausgegeben. Zur Unterstützung der jeweiligen Lern-,\nErkenntnis- und Gestaltungsschritte werden Hinweise in Form von\nTextauszügen, Literatur, Bildbeispielen und\nRecherchevorschlägen gegeben.\n\nLearning outcomes,\ncompetences\n\n\nStudents recognise the connection between design, technology,\nscience and shaping the future. They are able to critically reflect\non design concepts and their effects and can utilise speculative\ndesign strategies as a method for generating creative and\nsustainable ideas. They are able to apply and categorise the\nresearch potential of design.\n\nContent\n\n\nStudents are encouraged to engage analytically, theoretically\nand practically with concepts such as 'Design Fiction', 'Critical\nDesign' and 'Speculative Design'. The focus is on the critical\nexamination of current developments in science, technology,\ndesign and communication and their potential impact on society.\nOn this basis, possible future scenarios are to be developed and\ntold in free narratives. Through the creative fusion of scientific\nknowledge and narrative elements, combined with practical\napplications, alternative realities can be explored and\n\nHochschule Düsseldorf\nModulhandbuch M.Sc. Medieninformatik\nVersion 1.0\nPO 2025\n120\n\n\n\n\ndiscussions stimulated that promote critical thinking. This\nintegrative approach allows research through design to be\ntrialled, using design as a tool to explore and deepen\nunderstanding of current issues and potential future scenarios.\nThe aim is to identify the opportunities and challenges that\ndesigners and product developers face when dealing with\nincreasingly complex and urgent social, political and\nenvironmental issues.\nThe theoretical discussion includes design and media history,\ndesign and media theory, as well as categorisation in the context\nof social developments.\n\nTranslated with DeepL.com (free version)", "metadata": {"moduleNumber": "MMI 05.42", "moduleName": "Discursive Design and Future Visions", "creditPoints": "5.0", "suggestedSemester": 1, "offeredInSeason": "winter_semester", "examType": "portfolio", "heldInLanguage": "de", "reviserName": "Prof. Gabriele Schwab-Trapp", "reviserEmail": "gabi.schwab-trapp@hs-duesseldorf.de", "studyProgramId": 11, "source_type": "json", "moduleNameDe": "Diskursives Design und Zukunftsvisionen", "source_file": "MMI_MHB_PO2025_V1.0.pdf", "pdf_page_start": 118, "pdf_page_end": 120, "studyProgramAbbrev": "MMI", "studyProgram_Url": "https://medien.hs-duesseldorf.de/mmi", "pdf_url": "https://medien.hs-duesseldorf.de/studium/studiengaenge/Documents/Modulhandb%C3%BCcher/MMI_MHB_PO2025_V1.0.pdf"}}
{"id": "MMI07", "text": "Title: Masterproject 3\nModule Number: MMI 07\nCredits: 10.0 CP\nSemester: 3\nOffered In: winter_semester\nLanguage: en_on_demand\nExam Type: project\nInstructor: Prof. Dr. Thomas Franz (thomas.franz@hs-duesseldorf.de)\n--- Goals (EN) ---\nThe students are able to work successfully on a complex application-oriented project in the field ofmedia informatics or, alternatively,media engineering, event technology or media design with a focus on informatics.They can achieve results in the different project phases independently, analyse them critically and present the results.\n--- Goals (DE) ---\nTeilnehmer sind in der Lage, eine komplexe anwendungsorientierte Aufgabenstellung aus dem Bereiche Medieninformatik bzw. Medientechnik / Veranstaltungstechnik / Mediengestaltung mit signifikanten Informatikanteilen erfolgreich zu bearbeiten und in den verschiedenen Projektphasen eigenständig Ergebnisse erzielen, diese kritisch zu analysieren und Resultate zu präsentieren.\n--- Contents (EN) ---\nThe students work alone or in teams on individual research questions within the area of media informatics or related disciplines with a focus on informatics. They discuss their progress regularly with the supervisor and present first results. The main focus is the research-oriented implementation of the concepts developed based on scientific methodology.\n--- Contents (DE) ---\nStudierende arbeiten alleine oder im Team an einer eigenständigen wissenschaftlichen Fragestellung der Medieninformatik bzw. verwandter Medienbereiche mit Informatikanteil. Der Fortschritt wird regelmäßig mit dem Betreuer besprochen und (Teil-) Ergebnisse entsprechend präsentiert. Der Schwerpunkt liegt auf der forschungsorientierten Umsetzung der entwickelten Konzepte auf Basis wissenschaftlicher Methoden.\n--- Literature (EN) ---\n--- Literature (DE) ---\nJe nach Dozent und Projektthema verschieden\n\nMMI 07 - Masterprojekt 3\nMasterproject 3\nModulbeauftragte*r\nResponsible\nThomas Franz\nDozent*in\nTeaching staff\nLehrende*r der Hochschule Düsseldorf\nStudiengang\nM.Sc. Medieninformatik 2025\nVerwendung in anderen\nStudiengängen: / Used in other\nstudy programmes\nM.Sc. Medieninformatik, PO 2018 /\nM.Sc. Media Informatics, PO 2018\n\n\nLehrformen (alle Angaben in SWS zu je 45 Minuten / all values in SWS of 45 minutes each)\n\nCredits/\nCredits\nWorkload /\nWorkload\nKontaktzeit/\nContact time\nSelbststudium/\nSelf study\nDauer/\nLength\nSemester/\nSemester\nSprache/\nLanguage\n10\n300 h\n\n120 h\n180 h\n1 Sem.\n\nEnglish on\ndemand\nVorlesung/\nLecture\nÜbung/\nPractice\nSeminar/\nSeminar\nPraktiku\nm/ Lab\nwork\nProjekt/\nProject\nTutorium/\nTutorial\nSeminarist.\nUnterricht/\nSeminaristic\nlesson\nStudien\narbeit/\nResearch\nproject\nBegleitetes\nSelbstlernen/\nAccompan‘d\nself study\n\n\n2\n\n6\n\n\n\n\nModulkategorie / category\n\nWahlpflichtmodul / Elective module\nWahlkatalog(e) /\n\n/\nelective catalogue(s)\n\n\nVoraussetzungen zur Teilnahme /\nrequirements for participation\n\n\nFormal /\nFormal\n\nKeine /\nnone\n\nInhaltlich /\ncontentwise\n\nKeine /\nnone\nVoraussetzungen zur Prüfung /\nprerequisites for the\nexamination\n\nErfolgreiche Teilnahme am Seminar und Projekt / Successful\nparticipation in seminar and project\nPrüfungsform /\nform of examination\n\nProjektprüfung /\nProject examination\nBenotet, Stellenwert der Note\nfür die Endnote /\ngraded, value of the grade for\nthe final grade\n\nBenotet: Ja / Is graded: Yes\n\n10/90 bzw. 10/120 / 10/90 resp. 10/120\nVoraussetzungen zur\nCreditvergabe/ requirements for\nawarding credit:\n\nBestandene Modulprüfung / Passed module examination\n\nLernergebnisse, Kompetenzen:\n\n\nTeilnehmer sind in der Lage, eine komplexe\nanwendungsorientierte Aufgabenstellung aus dem Bereiche\nMedieninformatik bzw. Medientechnik / Veranstaltungstechnik /\nMediengestaltung mit signifikanten Informatikanteilen erfolgreich\nzu bearbeiten und in den verschiedenen Projektphasen\neigenständig Ergebnisse erzielen, diese kritisch zu analysieren\nund Resultate zu präsentieren.\n\n\n\n\nHochschule Düsseldorf\nModulhandbuch M.Sc. Medieninformatik\nVersion 1.0\nPO 2025\n18\n\n\nEnglish descriptions\n\nLehrinhalte:\nStudierende arbeiten alleine oder im Team an einer\neigenständigen wissenschaftlichen Fragestellung der\nMedieninformatik bzw. verwandter Medienbereiche mit\nInformatikanteil. Der Fortschritt wird regelmäßig mit dem Betreuer\nbesprochen und (Teil-) Ergebnisse entsprechend präsentiert. Der\nSchwerpunkt liegt auf der forschungsorientierten Umsetzung der\nentwickelten Konzepte auf Basis wissenschaftlicher Methoden.\n\nLiteratur:\n\n\nJe nach Dozent und Projektthema verschieden\n\nLearning outcomes,\ncompetences\n\n\nThe students are able to work successfully on a complex\napplication-oriented project in the field ofmedia informatics or,\nalternatively,media engineering, event technology or media\ndesign with a focus on informatics.They can achieve results in\nthe different project phases independently, analyse them\ncritically and present the results.\n\nContent\n\n\nThe students work alone or in teams on individual research\nquestions within the area of media informatics or related\ndisciplines with a focus on informatics. They discuss their\nprogress regularly with the supervisor and present first results.\nThe main focus is the research-oriented implementation of the\nconcepts developed based on scientific methodology.\n\nHochschule Düsseldorf\nModulhandbuch M.Sc. Medieninformatik\nVersion 1.0\nPO 2025\n19", "metadata": {"moduleNumber": "MMI 07", "moduleName": "Masterproject 3", "creditPoints": "10.0", "suggestedSemester": 3, "offeredInSeason": "winter_semester", "examType": "project", "heldInLanguage": "en_on_demand", "reviserName": "Prof. Dr. Thomas Franz", "reviserEmail": "thomas.franz@hs-duesseldorf.de", "studyProgramId": 11, "source_type": "json", "moduleNameDe": "Masterprojekt 3", "source_file": "MMI_MHB_PO2025_V1.0.pdf", "pdf_page_start": 17, "pdf_page_end": 18, "studyProgramAbbrev": "MMI", "studyProgram_Url": "https://medien.hs-duesseldorf.de/mmi", "pdf_url": "https://medien.hs-duesseldorf.de/studium/studiengaenge/Documents/Modulhandb%C3%BCcher/MMI_MHB_PO2025_V1.0.pdf"}}
{"id": "MMI08", "text": "Title: Individual Project\nModule Number: MMI 08\nCredits: 10.0 CP\nSemester: 3\nOffered In: winter_semester\nLanguage: en_on_demand\nExam Type: project\nInstructor: Prof. Dr. Thomas Franz (thomas.franz@hs-duesseldorf.de)\n--- Goals (EN) ---\nThe students are able to work successfully on a complex application-oriented project in the field ofmedia informatics or, alternatively,media engineering, event technology or media design with a focus on informatics.They can achieve results in the different project phases independently, analyse them critically and present the results.\n--- Goals (DE) ---\nTeilnehmer sind in der Lage, eine komplexe anwendungsorientierte Aufgabenstellung aus dem Bereiche Medieninformatik bzw. Medientechnik / Veranstaltungstechnik / Mediengestaltung mit signifikanten Informatikanteilen erfolgreich zu bearbeiten und in den verschiedenen Projektphasen eigenständig Ergebnisse erzielen, diese kritisch zu analysieren und Resultate zu präsentieren.\n--- Contents (EN) ---\nThe students work alone or in teams on individual research questions within the area of media informatics or related disciplines with a focus on informatics. They discuss their progress regularly with the supervisor and present first results. The focus is on research-orientation or practical implementation of the developed concepts in media production based on scientific methods.\n--- Contents (DE) ---\nStudierende arbeiten alleine oder im Team an einer eigenständigen wissenschaftlichen Fragestellung der Medieninformatik bzw. verwandter Medienbereiche mit Informatikanteil. Der Fortschritt wird regelmäßig mit dem Betreuer besprochen und (Teil-) Ergebnisse entsprechend präsentiert. Der Schwerpunkt liegt auf der forschungsorientierten oder medienpraktischen Umsetzung der entwickelten Konzepte auf Basis wissenschaftlicher Methoden.\n--- Literature (EN) ---\n--- Literature (DE) ---\nJe nach Dozent und Projektthema verschieden\n\nMMI 08 - Individuelles Projekt\nIndividual Project\nModulbeauftragte*r\nResponsible\nThomas Franz\nDozent*in\nTeaching staff\nLehrende*r der Hochschule Düsseldorf\nStudiengang\nM.Sc. Medieninformatik 2025\nVerwendung in anderen\nStudiengängen: / Used in other\nstudy programmes\nM.Sc. Medieninformatik, PO 2018 /\nM.Sc. Media Informatics, PO 2018\n\n\nLehrformen (alle Angaben in SWS zu je 45 Minuten / all values in SWS of 45 minutes each)\n\nCredits/\nCredits\nWorkload /\nWorkload\nKontaktzeit/\nContact time\nSelbststudium/\nSelf study\nDauer/\nLength\nSemester/\nSemester\nSprache/\nLanguage\n10\n300 h\n\n120 h\n180 h\n1 Sem.\n\nEnglish on\ndemand\nVorlesung/\nLecture\nÜbung/\nPractice\nSeminar/\nSeminar\nPraktiku\nm/ Lab\nwork\nProjekt/\nProject\nTutorium/\nTutorial\nSeminarist.\nUnterricht/\nSeminaristic\nlesson\nStudien\narbeit/\nResearch\nproject\nBegleitetes\nSelbstlernen/\nAccompan‘d\nself study\n\n\n2\n\n6\n\n\n\n\nModulkategorie / category\n\nWahlpflichtmodul / Elective module\nWahlkatalog(e) /\n\n/\nelective catalogue(s)\n\n\nVoraussetzungen zur Teilnahme /\nrequirements for participation\n\n\nFormal /\nFormal\n\nKeine /\nnone\n\nInhaltlich /\ncontentwise\n\nKeine /\nnone\nVoraussetzungen zur Prüfung /\nprerequisites for the\nexamination\n\nErfolgreiche Teilnahme am Seminar und Projekt / Successful\nparticipation in seminar and project\nPrüfungsform /\nform of examination\n\nProjektprüfung /\nProject examination\nBenotet, Stellenwert der Note\nfür die Endnote /\ngraded, value of the grade for\nthe final grade\n\nBenotet: Ja / Is graded: Yes\n\n10/90 bzw. 10/120 / 10/90 resp. 10/120\nVoraussetzungen zur\nCreditvergabe/ requirements for\nawarding credit:\n\nBestandene Modulprüfung / Passed module examination\n\nLernergebnisse, Kompetenzen:\n\n\nTeilnehmer sind in der Lage, eine komplexe\nanwendungsorientierte Aufgabenstellung aus dem Bereiche\nMedieninformatik bzw. Medientechnik / Veranstaltungstechnik /\nMediengestaltung mit signifikanten Informatikanteilen erfolgreich\nzu bearbeiten und in den verschiedenen Projektphasen\neigenständig Ergebnisse erzielen, diese kritisch zu analysieren\nund Resultate zu präsentieren.\n\n\n\n\nHochschule Düsseldorf\nModulhandbuch M.Sc. Medieninformatik\nVersion 1.0\nPO 2025\n20\n\n\nEnglish descriptions\n\nLehrinhalte:\nStudierende arbeiten alleine oder im Team an einer\neigenständigen wissenschaftlichen Fragestellung der\nMedieninformatik bzw. verwandter Medienbereiche mit\nInformatikanteil. Der Fortschritt wird regelmäßig mit dem Betreuer\nbesprochen und (Teil-) Ergebnisse entsprechend präsentiert. Der\nSchwerpunkt liegt auf der forschungsorientierten oder\nmedienpraktischen Umsetzung der entwickelten Konzepte auf\nBasis wissenschaftlicher Methoden.\n\nLiteratur:\n\n\nJe nach Dozent und Projektthema verschieden\n\nLearning outcomes,\ncompetences\n\n\nThe students are able to work successfully on a complex\napplication-oriented project in the field ofmedia informatics or,\nalternatively,media engineering, event technology or media\ndesign with a focus on informatics.They can achieve results in\nthe different project phases independently, analyse them\ncritically and present the results.\n\nContent\n\n\nThe students work alone or in teams on individual research\nquestions within the area of media informatics or related\ndisciplines with a focus on informatics. They discuss their\nprogress regularly with the supervisor and present first results.\nThe focus is on research-orientation or practical implementation\nof the developed concepts in media production based on\nscientific methods.\n\nHochschule Düsseldorf\nModulhandbuch M.Sc. Medieninformatik\nVersion 1.0\nPO 2025\n21", "metadata": {"moduleNumber": "MMI 08", "moduleName": "Individual Project", "creditPoints": "10.0", "suggestedSemester": 3, "offeredInSeason": "winter_semester", "examType": "project", "heldInLanguage": "en_on_demand", "reviserName": "Prof. Dr. Thomas Franz", "reviserEmail": "thomas.franz@hs-duesseldorf.de", "studyProgramId": 11, "source_type": "json", "moduleNameDe": "Individuelles Projekt", "source_file": "MMI_MHB_PO2025_V1.0.pdf", "pdf_page_start": 19, "pdf_page_end": 20, "studyProgramAbbrev": "MMI", "studyProgram_Url": "https://medien.hs-duesseldorf.de/mmi", "pdf_url": "https://medien.hs-duesseldorf.de/studium/studiengaenge/Documents/Modulhandb%C3%BCcher/MMI_MHB_PO2025_V1.0.pdf"}}
{"id": "MMI09", "text": "Title: Master Thesis and Colloquium\nModule Number: MMI 09\nCredits: 30.0 CP\nSemester: None\nOffered In: every_semester\nLanguage: de\nExam Type: master_thesis_and_colloquium\nInstructor: Prof. Dr. Thomas Franz (thomas.franz@hs-duesseldorf.de)\n--- Goals (EN) ---\nIndependent work on a scientific question from the field of media informatics. The students have applied the acquired competences in scientific methodology to complex research questions within a challenging topic in a targeted manner.\n--- Goals (DE) ---\nEigenständige Bearbeitung einer wissenschaftlichen Fragestellung aus dem Bereich der Medieninformatik. Dabei sollen die erlernten Kompetenzen einer methodischen wissenschaftlichen Vorgehensweise bei komplexen Fragestellungen zielgerichtet in einer anspruchsvollen Thematik eingesetzt werden.\n--- Contents (EN) ---\nThe students work on current topics from the field of media informatics – ideally developing ideas from compulsory elective courses or projects within the master’s programme Media Informatics further into advanced research questions. They discuss relevant scientific projects and relations to their own work in the context of an accompanying seminar.\n--- Contents (DE) ---\nBearbeitet werden aktuelle Themen aus dem Bereich Medieninformatik, idealerweise als weiterführende Fragestellung aus den Wahlpflichtveranstaltungen des Masters Medieninformatik oder aus den Projekten. Parallel werden im Rahmen eines Seminars relevanten wissenschaftliche Projekte diskutiert und ihr Bezug zur Arbeit der Studierenden aufgezeigt.\n--- Literature (EN) ---\nDepends on lecturer and topic\n--- Literature (DE) ---\nJe nach Dozent und Thema verschieden\n\nMMI 09 - Masterarbeit und Kolloquium\nMaster Thesis and Colloquium\nModulbeauftragte*r\nResponsible\nThomas Franz\nDozent*in\nTeaching staff\nLehrende*r der Hochschule Düsseldorf\nStudiengang\nM.Sc. Medieninformatik 2025\nVerwendung in anderen\nStudiengängen: / Used in other\nstudy programmes\nM.Sc. Medieninformatik, PO 2018 /\nM.Sc. Media Informatics, PO 2018\n\n\nLehrformen (alle Angaben in SWS zu je 45 Minuten / all values in SWS of 45 minutes each)\n\nCredits/\nCredits\nWorkload /\nWorkload\nKontaktzeit/\nContact time\nSelbststudium/\nSelf study\nDauer/\nLength\nSemester/\nSemester\nSprache/\nLanguage\n30\n900 h\n\n0 h\n900 h\n1 Sem.\n\nDeutsch\nVorlesung/\nLecture\nÜbung/\nPractice\nSeminar/\nSeminar\nPraktiku\nm/ Lab\nwork\nProjekt/\nProject\nTutorium/\nTutorial\nSeminarist.\nUnterricht/\nSeminaristic\nlesson\nStudien\narbeit/\nResearch\nproject\nBegleitetes\nSelbstlernen/\nAccompan‘d\nself study\n\n\n\n\n\n\n\n\n\nModulkategorie / category\n\nPflichtmodul / Compulsory module\nWahlkatalog(e) /\n\n/\nelective catalogue(s)\n\n\nVoraussetzungen zur Teilnahme /\nrequirements for participation\n\n\nFormal /\nFormal\n\nKeine /\nnone\n\nInhaltlich /\ncontentwise\n\nKeine /\nnone\nVoraussetzungen zur Prüfung /\nprerequisites for the\nexamination\n\nSiehe in den Modulen Masterarbeit und Kolloquium / See modules\nmaster thesis and colloquium\nPrüfungsform /\nform of examination\n\nMasterarbeit und Kolloquium /\nMaster thesis and colloquium\nBenotet, Stellenwert der Note\nfür die Endnote /\ngraded, value of the grade for\nthe final grade\n\nBenotet: Ja / Is graded: Yes\n\n30/90 bzw. 30/120 / 30/90 resp. 30/120\nVoraussetzungen zur\nCreditvergabe/ requirements for\nawarding credit:\n\nBestandene Modulprüfung / Passed module examination\n\nLernergebnisse, Kompetenzen:\n\n\nEigenständige Bearbeitung einer wissenschaftlichen\nFragestellung aus dem Bereich der Medieninformatik. Dabei\nsollen die erlernten Kompetenzen einer methodischen\nwissenschaftlichen Vorgehensweise bei komplexen\nFragestellungen zielgerichtet in einer anspruchsvollen Thematik\neingesetzt werden.\n\nLehrinhalte:\n\n\n\nHochschule Düsseldorf\nModulhandbuch M.Sc. Medieninformatik\nVersion 1.0\nPO 2025\n22\n\n\nEnglish descriptions\n\nBearbeitet werden aktuelle Themen aus dem Bereich\nMedieninformatik, idealerweise als weiterführende Fragestellung\naus den Wahlpflichtveranstaltungen des Masters\nMedieninformatik oder aus den Projekten. Parallel werden im\nRahmen eines Seminars relevanten wissenschaftliche Projekte\ndiskutiert und ihr Bezug zur Arbeit der Studierenden aufgezeigt.\n\nLiteratur:\n\n\nJe nach Dozent und Thema verschieden\n\nLearning outcomes,\ncompetences\n\n\nIndependent work on a scientific question from the field of media\ninformatics. The students have applied the acquired\ncompetences in scientific methodology to complex research\nquestions within a challenging topic in a targeted manner.\n\nContent\n\n\nThe students work on current topics from the field of media\ninformatics – ideally developing ideas from compulsory elective\ncourses or projects within the master’s programme Media\nInformatics further into advanced research questions. They\ndiscuss relevant scientific projects and relations to their own\nwork in the context of an accompanying seminar.\n\nHochschule Düsseldorf\nModulhandbuch M.Sc. Medieninformatik\nVersion 1.0\nPO 2025\n23", "metadata": {"moduleNumber": "MMI 09", "moduleName": "Master Thesis and Colloquium", "creditPoints": "30.0", "suggestedSemester": null, "offeredInSeason": "every_semester", "examType": "master_thesis_and_colloquium", "heldInLanguage": "de", "reviserName": "Prof. Dr. Thomas Franz", "reviserEmail": "thomas.franz@hs-duesseldorf.de", "studyProgramId": 11, "source_type": "json", "moduleNameDe": "Masterarbeit und Kolloquium", "source_file": "MMI_MHB_PO2025_V1.0.pdf", "pdf_page_start": 21, "pdf_page_end": 22, "studyProgramAbbrev": "MMI", "studyProgram_Url": "https://medien.hs-duesseldorf.de/mmi", "pdf_url": "https://medien.hs-duesseldorf.de/studium/studiengaenge/Documents/Modulhandb%C3%BCcher/MMI_MHB_PO2025_V1.0.pdf"}}
{"id": "MMI11", "text": "Title: Selection Module 1\nModule Number: MMI 11\nCredits: 5.0 CP\nSemester: 1\nOffered In: every_semester\nLanguage: de\nExam Type: see_elective\nInstructor: Prof. Dr. Thomas Franz (thomas.franz@hs-duesseldorf.de)\n--- Goals (EN) ---\nsee MMI 05.01 to MMI 05.33\n--- Goals (DE) ---\nsiehe MMI 05.01 bis MMI 05.33\n--- Contents (EN) ---\nsee MMI 05.01 to MMI 05.33\n--- Contents (DE) ---\nsiehe MMI 05.01 bis MMI 05.33\n--- Literature (EN) ---\n--- Literature (DE) ---\nsiehe MMI 05.01 bis MMI 05.33\n\nMMI 11 - Wahlpflichtmodul 1\nSelection Module 1\nModulbeauftragte*r\nResponsible\nThomas Franz\nDozent*in\nTeaching staff\nLehrende*r der Hochschule Düsseldorf\nStudiengang\nM.Sc. Medieninformatik 2025\nVerwendung in anderen\nStudiengängen: / Used in other\nstudy programmes\nM.Sc. Medieninformatik, PO 2018 /\nM.Sc. Media Informatics, PO 2018\n\n\nLehrformen (alle Angaben in SWS zu je 45 Minuten / all values in SWS of 45 minutes each)\n\n\nEnglish descriptions\nCredits/\nCredits\nWorkload /\nWorkload\nKontaktzeit/\nContact time\nSelbststudium/\nSelf study\nDauer/\nLength\nSemester/\nSemester\nSprache/\nLanguage\n5\n150 h\n\n60 h\n90 h\n1 Sem.\n1\nDeutsch\nVorlesung/\nLecture\nÜbung/\nPractice\nSeminar/\nSeminar\nPraktiku\nm/ Lab\nwork\nProjekt/\nProject\nTutorium/\nTutorial\nSeminarist.\nUnterricht/\nSeminaristic\nlesson\nStudien\narbeit/\nResearch\nproject\nBegleitetes\nSelbstlernen/\nAccompan‘d\nself study\n\n\n\n\n\n\n\n\n\nModulkategorie / category\n\nWahlpflichtmodul / Elective module\nWahlkatalog(e) /\n\n/\nelective catalogue(s)\n\n\nVoraussetzungen zur Teilnahme /\nrequirements for participation\n\n\nFormal /\nFormal\n\nKeine /\nnone\n\nInhaltlich /\ncontentwise\n\nKeine /\nnone\nVoraussetzungen zur Prüfung /\nprerequisites for the\nexamination\n\nDurch das gewählte Modul vorgegeben / Given by the chosen\nmodule\nPrüfungsform /\nform of examination\n\nAbhängig vom belegten Wahlfach /\nDepends on selected elective\nBenotet, Stellenwert der Note\nfür die Endnote /\ngraded, value of the grade for\nthe final grade\n\nBenotet: Ja / Is graded: Yes\n\n5/90 bzw. 5/120 / 5/90 resp. 5/120\nVoraussetzungen zur\nCreditvergabe/ requirements for\nawarding credit:\n\nBestandene Modulprüfung / Passed module examination\n\nLernergebnisse, Kompetenzen:\n\n\nsiehe MMI 05.01 bis MMI 05.33\n\nLehrinhalte:\n\n\nsiehe MMI 05.01 bis MMI 05.33\n\nLiteratur:\n\n\nsiehe MMI 05.01 bis MMI 05.33\n\nHochschule Düsseldorf\nModulhandbuch M.Sc. Medieninformatik\nVersion 1.0\nPO 2025\n24\n\n\n\nLearning outcomes,\ncompetences\n\n\nsee MMI 05.01 to MMI 05.33\n\nContent\n\n\nsee MMI 05.01 to MMI 05.33\n\nHochschule Düsseldorf\nModulhandbuch M.Sc. Medieninformatik\nVersion 1.0\nPO 2025\n25", "metadata": {"moduleNumber": "MMI 11", "moduleName": "Selection Module 1", "creditPoints": "5.0", "suggestedSemester": 1, "offeredInSeason": "every_semester", "examType": "see_elective", "heldInLanguage": "de", "reviserName": "Prof. Dr. Thomas Franz", "reviserEmail": "thomas.franz@hs-duesseldorf.de", "studyProgramId": 11, "source_type": "json", "moduleNameDe": "Wahlpflichtmodul 1", "source_file": "MMI_MHB_PO2025_V1.0.pdf", "pdf_page_start": 23, "pdf_page_end": 24, "studyProgramAbbrev": "MMI", "studyProgram_Url": "https://medien.hs-duesseldorf.de/mmi", "pdf_url": "https://medien.hs-duesseldorf.de/studium/studiengaenge/Documents/Modulhandb%C3%BCcher/MMI_MHB_PO2025_V1.0.pdf"}}
{"id": "MMI12", "text": "Title: Selection Module 2\nModule Number: MMI 12\nCredits: 5.0 CP\nSemester: 1\nOffered In: every_semester\nLanguage: de\nExam Type: see_elective\nInstructor: Prof. Dr. Thomas Franz (thomas.franz@hs-duesseldorf.de)\n--- Goals (EN) ---\nsee MMI 05.01 to MMI 05.33\n--- Goals (DE) ---\nsiehe MMI 05.01 bis MMI 05.33\n--- Contents (EN) ---\nsee MMI 05.01 to MMI 05.33\n--- Contents (DE) ---\nsiehe MMI 05.01 bis MMI 05.33\n--- Literature (EN) ---\n--- Literature (DE) ---\nsiehe MMI 05.01 bis MMI 05.33\n\nMMI 12 - Wahlpflichtmodul 2\nSelection Module 2\nModulbeauftragte*r\nResponsible\nThomas Franz\nDozent*in\nTeaching staff\nLehrende*r der Hochschule Düsseldorf\nStudiengang\nM.Sc. Medieninformatik 2025\nVerwendung in anderen\nStudiengängen: / Used in other\nstudy programmes\nM.Sc. Medieninformatik, PO 2018 /\nM.Sc. Media Informatics, PO 2018\n\n\nLehrformen (alle Angaben in SWS zu je 45 Minuten / all values in SWS of 45 minutes each)\n\n\nEnglish descriptions\nCredits/\nCredits\nWorkload /\nWorkload\nKontaktzeit/\nContact time\nSelbststudium/\nSelf study\nDauer/\nLength\nSemester/\nSemester\nSprache/\nLanguage\n5\n150 h\n\n60 h\n90 h\n1 Sem.\n1\nDeutsch\nVorlesung/\nLecture\nÜbung/\nPractice\nSeminar/\nSeminar\nPraktiku\nm/ Lab\nwork\nProjekt/\nProject\nTutorium/\nTutorial\nSeminarist.\nUnterricht/\nSeminaristic\nlesson\nStudien\narbeit/\nResearch\nproject\nBegleitetes\nSelbstlernen/\nAccompan‘d\nself study\n\n\n\n\n\n\n\n\n\nModulkategorie / category\n\nWahlpflichtmodul / Elective module\nWahlkatalog(e) /\n\n/\nelective catalogue(s)\n\n\nVoraussetzungen zur Teilnahme /\nrequirements for participation\n\n\nFormal /\nFormal\n\nKeine /\nnone\n\nInhaltlich /\ncontentwise\n\nKeine /\nnone\nVoraussetzungen zur Prüfung /\nprerequisites for the\nexamination\n\nDurch das gewählte Modul vorgegeben / Given by the chosen\nmodule\nPrüfungsform /\nform of examination\n\nAbhängig vom belegten Wahlfach /\nDepends on selected elective\nBenotet, Stellenwert der Note\nfür die Endnote /\ngraded, value of the grade for\nthe final grade\n\nBenotet: Ja / Is graded: Yes\n\n5/90 bzw. 5/120 / 5/90 resp. 5/120\nVoraussetzungen zur\nCreditvergabe/ requirements for\nawarding credit:\n\nBestandene Modulprüfung / Passed module examination\n\nLernergebnisse, Kompetenzen:\n\n\nsiehe MMI 05.01 bis MMI 05.33\n\nLehrinhalte:\n\n\nsiehe MMI 05.01 bis MMI 05.33\n\nLiteratur:\n\n\nsiehe MMI 05.01 bis MMI 05.33\n\nHochschule Düsseldorf\nModulhandbuch M.Sc. Medieninformatik\nVersion 1.0\nPO 2025\n26\n\n\n\nLearning outcomes,\ncompetences\n\n\nsee MMI 05.01 to MMI 05.33\n\nContent\n\n\nsee MMI 05.01 to MMI 05.33\n\nHochschule Düsseldorf\nModulhandbuch M.Sc. Medieninformatik\nVersion 1.0\nPO 2025\n27", "metadata": {"moduleNumber": "MMI 12", "moduleName": "Selection Module 2", "creditPoints": "5.0", "suggestedSemester": 1, "offeredInSeason": "every_semester", "examType": "see_elective", "heldInLanguage": "de", "reviserName": "Prof. Dr. Thomas Franz", "reviserEmail": "thomas.franz@hs-duesseldorf.de", "studyProgramId": 11, "source_type": "json", "moduleNameDe": "Wahlpflichtmodul 2", "source_file": "MMI_MHB_PO2025_V1.0.pdf", "pdf_page_start": 25, "pdf_page_end": 26, "studyProgramAbbrev": "MMI", "studyProgram_Url": "https://medien.hs-duesseldorf.de/mmi", "pdf_url": "https://medien.hs-duesseldorf.de/studium/studiengaenge/Documents/Modulhandb%C3%BCcher/MMI_MHB_PO2025_V1.0.pdf"}}
{"id": "MMI13", "text": "Title: Selection Module 3\nModule Number: MMI 13\nCredits: 5.0 CP\nSemester: 1\nOffered In: every_semester\nLanguage: de\nExam Type: see_elective\nInstructor: Prof. Dr. Thomas Franz (thomas.franz@hs-duesseldorf.de)\n--- Goals (EN) ---\nsee MMI 05.01 to MMI 05.33\n--- Goals (DE) ---\nsiehe MMI 05.01 bis MMI 05.33\n--- Contents (EN) ---\nsee MMI 05.01 to MMI 05.33\n--- Contents (DE) ---\nsiehe MMI 05.01 bis MMI 05.33\n--- Literature (EN) ---\n--- Literature (DE) ---\nsiehe MMI 05.01 bis MMI 05.33\n\nMMI 13 - Wahlpflichtmodul 3\nSelection Module 3\nModulbeauftragte*r\nResponsible\nThomas Franz\nDozent*in\nTeaching staff\nLehrende*r der Hochschule Düsseldorf\nStudiengang\nM.Sc. Medieninformatik 2025\nVerwendung in anderen\nStudiengängen: / Used in other\nstudy programmes\nM.Sc. Medieninformatik, PO 2018 /\nM.Sc. Media Informatics, PO 2018\n\n\nLehrformen (alle Angaben in SWS zu je 45 Minuten / all values in SWS of 45 minutes each)\n\n\nEnglish descriptions\nCredits/\nCredits\nWorkload /\nWorkload\nKontaktzeit/\nContact time\nSelbststudium/\nSelf study\nDauer/\nLength\nSemester/\nSemester\nSprache/\nLanguage\n5\n150 h\n\n60 h\n90 h\n1 Sem.\n1\nDeutsch\nVorlesung/\nLecture\nÜbung/\nPractice\nSeminar/\nSeminar\nPraktiku\nm/ Lab\nwork\nProjekt/\nProject\nTutorium/\nTutorial\nSeminarist.\nUnterricht/\nSeminaristic\nlesson\nStudien\narbeit/\nResearch\nproject\nBegleitetes\nSelbstlernen/\nAccompan‘d\nself study\n\n\n\n\n\n\n\n\n\nModulkategorie / category\n\nWahlpflichtmodul / Elective module\nWahlkatalog(e) /\n\n/\nelective catalogue(s)\n\n\nVoraussetzungen zur Teilnahme /\nrequirements for participation\n\n\nFormal /\nFormal\n\nKeine /\nnone\n\nInhaltlich /\ncontentwise\n\nKeine /\nnone\nVoraussetzungen zur Prüfung /\nprerequisites for the\nexamination\n\nDurch das gewählte Modul vorgegeben / Given by the chosen\nmodule\nPrüfungsform /\nform of examination\n\nAbhängig vom belegten Wahlfach /\nDepends on selected elective\nBenotet, Stellenwert der Note\nfür die Endnote /\ngraded, value of the grade for\nthe final grade\n\nBenotet: Ja / Is graded: Yes\n\n5/90 bzw. 5/120 / 5/90 resp. 5/120\nVoraussetzungen zur\nCreditvergabe/ requirements for\nawarding credit:\n\nBestandene Modulprüfung / Passed module examination\n\nLernergebnisse, Kompetenzen:\n\n\nsiehe MMI 05.01 bis MMI 05.33\n\nLehrinhalte:\n\n\nsiehe MMI 05.01 bis MMI 05.33\n\nLiteratur:\n\n\nsiehe MMI 05.01 bis MMI 05.33\n\nHochschule Düsseldorf\nModulhandbuch M.Sc. Medieninformatik\nVersion 1.0\nPO 2025\n28\n\n\n\nLearning outcomes,\ncompetences\n\n\nsee MMI 05.01 to MMI 05.33\n\nContent\n\n\nsee MMI 05.01 to MMI 05.33\n\nHochschule Düsseldorf\nModulhandbuch M.Sc. Medieninformatik\nVersion 1.0\nPO 2025\n29", "metadata": {"moduleNumber": "MMI 13", "moduleName": "Selection Module 3", "creditPoints": "5.0", "suggestedSemester": 1, "offeredInSeason": "every_semester", "examType": "see_elective", "heldInLanguage": "de", "reviserName": "Prof. Dr. Thomas Franz", "reviserEmail": "thomas.franz@hs-duesseldorf.de", "studyProgramId": 11, "source_type": "json", "moduleNameDe": "Wahlpflichtmodul 3", "source_file": "MMI_MHB_PO2025_V1.0.pdf", "pdf_page_start": 27, "pdf_page_end": 28, "studyProgramAbbrev": "MMI", "studyProgram_Url": "https://medien.hs-duesseldorf.de/mmi", "pdf_url": "https://medien.hs-duesseldorf.de/studium/studiengaenge/Documents/Modulhandb%C3%BCcher/MMI_MHB_PO2025_V1.0.pdf"}}
{"id": "MMI14", "text": "Title: Selection Module 4\nModule Number: MMI 14\nCredits: 5.0 CP\nSemester: 2\nOffered In: every_semester\nLanguage: de\nExam Type: see_elective\nInstructor: Prof. Dr. Thomas Franz (thomas.franz@hs-duesseldorf.de)\n--- Goals (EN) ---\nsee MMI 05.01 to MMI 05.33\n--- Goals (DE) ---\nsiehe MMI 05.01 bis MMI 05.33\n--- Contents (EN) ---\nsee MMI 05.01 to MMI 05.33\n--- Contents (DE) ---\nsiehe MMI 05.01 bis MMI 05.33\n--- Literature (EN) ---\n--- Literature (DE) ---\nsiehe MMI 05.01 bis MMI 05.33\n\nMMI 14 - Wahlpflichtmodul 4\nSelection Module 4\nModulbeauftragte*r\nResponsible\nThomas Franz\nDozent*in\nTeaching staff\nLehrende*r der Hochschule Düsseldorf\nStudiengang\nM.Sc. Medieninformatik 2025\nVerwendung in anderen\nStudiengängen: / Used in other\nstudy programmes\nM.Sc. Medieninformatik, PO 2018 /\nM.Sc. Media Informatics, PO 2018\n\n\nLehrformen (alle Angaben in SWS zu je 45 Minuten / all values in SWS of 45 minutes each)\n\n\nEnglish descriptions\nCredits/\nCredits\nWorkload /\nWorkload\nKontaktzeit/\nContact time\nSelbststudium/\nSelf study\nDauer/\nLength\nSemester/\nSemester\nSprache/\nLanguage\n5\n150 h\n\n60 h\n90 h\n1 Sem.\n2\nDeutsch\nVorlesung/\nLecture\nÜbung/\nPractice\nSeminar/\nSeminar\nPraktiku\nm/ Lab\nwork\nProjekt/\nProject\nTutorium/\nTutorial\nSeminarist.\nUnterricht/\nSeminaristic\nlesson\nStudien\narbeit/\nResearch\nproject\nBegleitetes\nSelbstlernen/\nAccompan‘d\nself study\n\n\n\n\n\n\n\n\n\nModulkategorie / category\n\nWahlpflichtmodul / Elective module\nWahlkatalog(e) /\n\n/\nelective catalogue(s)\n\n\nVoraussetzungen zur Teilnahme /\nrequirements for participation\n\n\nFormal /\nFormal\n\nKeine /\nnone\n\nInhaltlich /\ncontentwise\n\nKeine /\nnone\nVoraussetzungen zur Prüfung /\nprerequisites for the\nexamination\n\nDurch das gewählte Modul vorgegeben / Given by the chosen\nmodule\nPrüfungsform /\nform of examination\n\nAbhängig vom belegten Wahlfach /\nDepends on selected elective\nBenotet, Stellenwert der Note\nfür die Endnote /\ngraded, value of the grade for\nthe final grade\n\nBenotet: Ja / Is graded: Yes\n\n5/90 bzw. 5/120 / 5/90 resp. 5/120\nVoraussetzungen zur\nCreditvergabe/ requirements for\nawarding credit:\n\nBestandene Modulprüfung / Passed module examination\n\nLernergebnisse, Kompetenzen:\n\n\nsiehe MMI 05.01 bis MMI 05.33\n\nLehrinhalte:\n\n\nsiehe MMI 05.01 bis MMI 05.33\n\nLiteratur:\n\n\nsiehe MMI 05.01 bis MMI 05.33\n\nHochschule Düsseldorf\nModulhandbuch M.Sc. Medieninformatik\nVersion 1.0\nPO 2025\n30\n\n\n\nLearning outcomes,\ncompetences\n\n\nsee MMI 05.01 to MMI 05.33\n\nContent\n\n\nsee MMI 05.01 to MMI 05.33\n\nHochschule Düsseldorf\nModulhandbuch M.Sc. Medieninformatik\nVersion 1.0\nPO 2025\n31", "metadata": {"moduleNumber": "MMI 14", "moduleName": "Selection Module 4", "creditPoints": "5.0", "suggestedSemester": 2, "offeredInSeason": "every_semester", "examType": "see_elective", "heldInLanguage": "de", "reviserName": "Prof. Dr. Thomas Franz", "reviserEmail": "thomas.franz@hs-duesseldorf.de", "studyProgramId": 11, "source_type": "json", "moduleNameDe": "Wahlpflichtmodul 4", "source_file": "MMI_MHB_PO2025_V1.0.pdf", "pdf_page_start": 29, "pdf_page_end": 30, "studyProgramAbbrev": "MMI", "studyProgram_Url": "https://medien.hs-duesseldorf.de/mmi", "pdf_url": "https://medien.hs-duesseldorf.de/studium/studiengaenge/Documents/Modulhandb%C3%BCcher/MMI_MHB_PO2025_V1.0.pdf"}}
{"id": "MMI15", "text": "Title: Selection Module 4\nModule Number: MMI 15\nCredits: 5.0 CP\nSemester: 2\nOffered In: every_semester\nLanguage: de\nExam Type: see_elective\nInstructor: Prof. Dr. Thomas Franz (thomas.franz@hs-duesseldorf.de)\n--- Goals (EN) ---\nsee MMI 05.01 to MMI 05.33\n--- Goals (DE) ---\nsiehe MMI 05.01 bis MMI 05.33\n--- Contents (EN) ---\nsee MMI 05.01 to MMI 05.33\n--- Contents (DE) ---\nsiehe MMI 05.01 bis MMI 05.33\n--- Literature (EN) ---\n--- Literature (DE) ---\nsiehe MMI 05.01 bis MMI 05.33\n\nMMI 15 - Wahlpflichtmodul 5\nSelection Module 4\nModulbeauftragte*r\nResponsible\nThomas Franz\nDozent*in\nTeaching staff\nLehrende*r der Hochschule Düsseldorf\nStudiengang\nM.Sc. Medieninformatik 2025\nVerwendung in anderen\nStudiengängen: / Used in other\nstudy programmes\nM.Sc. Medieninformatik, PO 2018 /\nM.Sc. Media Informatics, PO 2018\n\n\nLehrformen (alle Angaben in SWS zu je 45 Minuten / all values in SWS of 45 minutes each)\n\n\nEnglish descriptions\nCredits/\nCredits\nWorkload /\nWorkload\nKontaktzeit/\nContact time\nSelbststudium/\nSelf study\nDauer/\nLength\nSemester/\nSemester\nSprache/\nLanguage\n5\n150 h\n\n60 h\n90 h\n1 Sem.\n2\nDeutsch\nVorlesung/\nLecture\nÜbung/\nPractice\nSeminar/\nSeminar\nPraktiku\nm/ Lab\nwork\nProjekt/\nProject\nTutorium/\nTutorial\nSeminarist.\nUnterricht/\nSeminaristic\nlesson\nStudien\narbeit/\nResearch\nproject\nBegleitetes\nSelbstlernen/\nAccompan‘d\nself study\n\n\n\n\n\n\n\n\n\nModulkategorie / category\n\nWahlpflichtmodul / Elective module\nWahlkatalog(e) /\n\n/\nelective catalogue(s)\n\n\nVoraussetzungen zur Teilnahme /\nrequirements for participation\n\n\nFormal /\nFormal\n\nKeine /\nnone\n\nInhaltlich /\ncontentwise\n\nKeine /\nnone\nVoraussetzungen zur Prüfung /\nprerequisites for the\nexamination\n\nDurch das gewählte Modul vorgegeben / Given by the chosen\nmodule\nPrüfungsform /\nform of examination\n\nAbhängig vom belegten Wahlfach /\nDepends on selected elective\nBenotet, Stellenwert der Note\nfür die Endnote /\ngraded, value of the grade for\nthe final grade\n\nBenotet: Ja / Is graded: Yes\n\n5/90 bzw. 5/120 / 5/90 resp. 5/120\nVoraussetzungen zur\nCreditvergabe/ requirements for\nawarding credit:\n\nBestandene Modulprüfung / Passed module examination\n\nLernergebnisse, Kompetenzen:\n\n\nsiehe MMI 05.01 bis MMI 05.33\n\nLehrinhalte:\n\n\nsiehe MMI 05.01 bis MMI 05.33\n\nLiteratur:\n\n\nsiehe MMI 05.01 bis MMI 05.33\n\nHochschule Düsseldorf\nModulhandbuch M.Sc. Medieninformatik\nVersion 1.0\nPO 2025\n32\n\n\n\nLearning outcomes,\ncompetences\n\n\nsee MMI 05.01 to MMI 05.33\n\nContent\n\n\nsee MMI 05.01 to MMI 05.33\n\nHochschule Düsseldorf\nModulhandbuch M.Sc. Medieninformatik\nVersion 1.0\nPO 2025\n33", "metadata": {"moduleNumber": "MMI 15", "moduleName": "Selection Module 4", "creditPoints": "5.0", "suggestedSemester": 2, "offeredInSeason": "every_semester", "examType": "see_elective", "heldInLanguage": "de", "reviserName": "Prof. Dr. Thomas Franz", "reviserEmail": "thomas.franz@hs-duesseldorf.de", "studyProgramId": 11, "source_type": "json", "moduleNameDe": "Wahlpflichtmodul 5", "source_file": "MMI_MHB_PO2025_V1.0.pdf", "pdf_page_start": 31, "pdf_page_end": 32, "studyProgramAbbrev": "MMI", "studyProgram_Url": "https://medien.hs-duesseldorf.de/mmi", "pdf_url": "https://medien.hs-duesseldorf.de/studium/studiengaenge/Documents/Modulhandb%C3%BCcher/MMI_MHB_PO2025_V1.0.pdf"}}
{"id": "MMI16", "text": "Title: Selection Module 6\nModule Number: MMI 16\nCredits: 5.0 CP\nSemester: 2\nOffered In: every_semester\nLanguage: de\nExam Type: see_elective\nInstructor: Prof. Dr. Thomas Franz (thomas.franz@hs-duesseldorf.de)\n--- Goals (EN) ---\nsee MMI 05.01 to MMI 05.33\n--- Goals (DE) ---\nsiehe MMI 05.01 bis MMI 05.33\n--- Contents (EN) ---\nsee MMI 05.01 to MMI 05.33\n--- Contents (DE) ---\nsiehe MMI 05.01 bis MMI 05.33\n--- Literature (EN) ---\n--- Literature (DE) ---\nsiehe MMI 05.01 bis MMI 05.33\n\nMMI 16 - Wahlpflichtmodul 6\nSelection Module 6\nModulbeauftragte*r\nResponsible\nThomas Franz\nDozent*in\nTeaching staff\nLehrende*r der Hochschule Düsseldorf\nStudiengang\nM.Sc. Medieninformatik 2025\nVerwendung in anderen\nStudiengängen: / Used in other\nstudy programmes\nM.Sc. Medieninformatik, PO 2018 /\nM.Sc. Media Informatics, PO 2018\n\n\nLehrformen (alle Angaben in SWS zu je 45 Minuten / all values in SWS of 45 minutes each)\n\n\nEnglish descriptions\nCredits/\nCredits\nWorkload /\nWorkload\nKontaktzeit/\nContact time\nSelbststudium/\nSelf study\nDauer/\nLength\nSemester/\nSemester\nSprache/\nLanguage\n5\n150 h\n\n60 h\n90 h\n1 Sem.\n2\nDeutsch\nVorlesung/\nLecture\nÜbung/\nPractice\nSeminar/\nSeminar\nPraktiku\nm/ Lab\nwork\nProjekt/\nProject\nTutorium/\nTutorial\nSeminarist.\nUnterricht/\nSeminaristic\nlesson\nStudien\narbeit/\nResearch\nproject\nBegleitetes\nSelbstlernen/\nAccompan‘d\nself study\n\n\n\n\n\n\n\n\n\nModulkategorie / category\n\nWahlpflichtmodul / Elective module\nWahlkatalog(e) /\n\n/\nelective catalogue(s)\n\n\nVoraussetzungen zur Teilnahme /\nrequirements for participation\n\n\nFormal /\nFormal\n\nKeine /\nnone\n\nInhaltlich /\ncontentwise\n\nKeine /\nnone\nVoraussetzungen zur Prüfung /\nprerequisites for the\nexamination\n\nDurch das gewählte Modul vorgegeben / Given by the chosen\nmodule\nPrüfungsform /\nform of examination\n\nAbhängig vom belegten Wahlfach /\nDepends on selected elective\nBenotet, Stellenwert der Note\nfür die Endnote /\ngraded, value of the grade for\nthe final grade\n\nBenotet: Ja / Is graded: Yes\n\n5/90 bzw. 5/120 / 5/90 resp. 5/120\nVoraussetzungen zur\nCreditvergabe/ requirements for\nawarding credit:\n\nBestandene Modulprüfung / Passed module examination\n\nLernergebnisse, Kompetenzen:\n\n\nsiehe MMI 05.01 bis MMI 05.33\n\nLehrinhalte:\n\n\nsiehe MMI 05.01 bis MMI 05.33\n\nLiteratur:\n\n\nsiehe MMI 05.01 bis MMI 05.33\n\nHochschule Düsseldorf\nModulhandbuch M.Sc. Medieninformatik\nVersion 1.0\nPO 2025\n34\n\n\n\nLearning outcomes,\ncompetences\n\n\nsee MMI 05.01 to MMI 05.33\n\nContent\n\n\nsee MMI 05.01 to MMI 05.33\n\nHochschule Düsseldorf\nModulhandbuch M.Sc. Medieninformatik\nVersion 1.0\nPO 2025\n35", "metadata": {"moduleNumber": "MMI 16", "moduleName": "Selection Module 6", "creditPoints": "5.0", "suggestedSemester": 2, "offeredInSeason": "every_semester", "examType": "see_elective", "heldInLanguage": "de", "reviserName": "Prof. Dr. Thomas Franz", "reviserEmail": "thomas.franz@hs-duesseldorf.de", "studyProgramId": 11, "source_type": "json", "moduleNameDe": "Wahlpflichtmodul 6", "source_file": "MMI_MHB_PO2025_V1.0.pdf", "pdf_page_start": 33, "pdf_page_end": 34, "studyProgramAbbrev": "MMI", "studyProgram_Url": "https://medien.hs-duesseldorf.de/mmi", "pdf_url": "https://medien.hs-duesseldorf.de/studium/studiengaenge/Documents/Modulhandb%C3%BCcher/MMI_MHB_PO2025_V1.0.pdf"}}
{"id": "MMI17", "text": "Title: Selection Module 7\nModule Number: MMI 17\nCredits: 5.0 CP\nSemester: 3\nOffered In: every_semester\nLanguage: de\nExam Type: see_elective\nInstructor: Prof. Dr. Thomas Franz (thomas.franz@hs-duesseldorf.de)\n--- Goals (EN) ---\nsee MMI 05.01 to MMI 05.33\n--- Goals (DE) ---\nsiehe MMI 05.01 bis MMI 05.33\n--- Contents (EN) ---\nsee MMI 05.01 to MMI 05.33\n--- Contents (DE) ---\nsiehe MMI 05.01 bis MMI 05.33\n--- Literature (EN) ---\n--- Literature (DE) ---\nsiehe MMI 05.01 bis MMI 05.33\n\nMMI 17 - Wahlpflichtmodul 7\nSelection Module 7\nModulbeauftragte*r\nResponsible\nThomas Franz\nDozent*in\nTeaching staff\nLehrende*r der Hochschule Düsseldorf\nStudiengang\nM.Sc. Medieninformatik 2025\nVerwendung in anderen\nStudiengängen: / Used in other\nstudy programmes\nM.Sc. Medieninformatik, PO 2018 /\nM.Sc. Media Informatics, PO 2018\n\n\nLehrformen (alle Angaben in SWS zu je 45 Minuten / all values in SWS of 45 minutes each)\n\n\nEnglish descriptions\nCredits/\nCredits\nWorkload /\nWorkload\nKontaktzeit/\nContact time\nSelbststudium/\nSelf study\nDauer/\nLength\nSemester/\nSemester\nSprache/\nLanguage\n5\n150 h\n\n60 h\n90 h\n1 Sem.\n3\nDeutsch\nVorlesung/\nLecture\nÜbung/\nPractice\nSeminar/\nSeminar\nPraktiku\nm/ Lab\nwork\nProjekt/\nProject\nTutorium/\nTutorial\nSeminarist.\nUnterricht/\nSeminaristic\nlesson\nStudien\narbeit/\nResearch\nproject\nBegleitetes\nSelbstlernen/\nAccompan‘d\nself study\n\n\n\n\n\n\n\n\n\nModulkategorie / category\n\nWahlpflichtmodul / Elective module\nWahlkatalog(e) /\n\n/\nelective catalogue(s)\n\n\nVoraussetzungen zur Teilnahme /\nrequirements for participation\n\n\nFormal /\nFormal\n\nKeine /\nnone\n\nInhaltlich /\ncontentwise\n\nKeine /\nnone\nVoraussetzungen zur Prüfung /\nprerequisites for the\nexamination\n\nDurch das gewählte Modul vorgegeben / Given by the chosen\nmodule\nPrüfungsform /\nform of examination\n\nAbhängig vom belegten Wahlfach /\nDepends on selected elective\nBenotet, Stellenwert der Note\nfür die Endnote /\ngraded, value of the grade for\nthe final grade\n\nBenotet: Ja / Is graded: Yes\n\n5/90 bzw. 5/120 / 5/90 resp. 5/120\nVoraussetzungen zur\nCreditvergabe/ requirements for\nawarding credit:\n\nBestandene Modulprüfung / Passed module examination\n\nLernergebnisse, Kompetenzen:\n\n\nsiehe MMI 05.01 bis MMI 05.33\n\nLehrinhalte:\n\n\nsiehe MMI 05.01 bis MMI 05.33\n\nLiteratur:\n\n\nsiehe MMI 05.01 bis MMI 05.33\n\nHochschule Düsseldorf\nModulhandbuch M.Sc. Medieninformatik\nVersion 1.0\nPO 2025\n36\n\n\n\nLearning outcomes,\ncompetences\n\n\nsee MMI 05.01 to MMI 05.33\n\nContent\n\n\nsee MMI 05.01 to MMI 05.33\n\nHochschule Düsseldorf\nModulhandbuch M.Sc. Medieninformatik\nVersion 1.0\nPO 2025\n37", "metadata": {"moduleNumber": "MMI 17", "moduleName": "Selection Module 7", "creditPoints": "5.0", "suggestedSemester": 3, "offeredInSeason": "every_semester", "examType": "see_elective", "heldInLanguage": "de", "reviserName": "Prof. Dr. Thomas Franz", "reviserEmail": "thomas.franz@hs-duesseldorf.de", "studyProgramId": 11, "source_type": "json", "moduleNameDe": "Wahlpflichtmodul 7", "source_file": "MMI_MHB_PO2025_V1.0.pdf", "pdf_page_start": 35, "pdf_page_end": 36, "studyProgramAbbrev": "MMI", "studyProgram_Url": "https://medien.hs-duesseldorf.de/mmi", "pdf_url": "https://medien.hs-duesseldorf.de/studium/studiengaenge/Documents/Modulhandb%C3%BCcher/MMI_MHB_PO2025_V1.0.pdf"}}
{"id": "MMI18", "text": "Title: Selection Module 8\nModule Number: MMI 18\nCredits: 5.0 CP\nSemester: 3\nOffered In: every_semester\nLanguage: de\nExam Type: see_elective\nInstructor: Prof. Dr. Thomas Franz (thomas.franz@hs-duesseldorf.de)\n--- Goals (EN) ---\nsee MMI 05.01 to MMI 05.33\n--- Goals (DE) ---\nsiehe MMI 05.01 bis MMI 05.33\n--- Contents (EN) ---\nsee MMI 05.01 to MMI 05.33\n--- Contents (DE) ---\nsiehe MMI 05.01 bis MMI 05.33\n--- Literature (EN) ---\n--- Literature (DE) ---\nsiehe MMI 05.01 bis MMI 05.33\n\nMMI 18 - Wahlpflichtmodul 8\nSelection Module 8\nModulbeauftragte*r\nResponsible\nThomas Franz\nDozent*in\nTeaching staff\nLehrende*r der Hochschule Düsseldorf\nStudiengang\nM.Sc. Medieninformatik 2025\nVerwendung in anderen\nStudiengängen: / Used in other\nstudy programmes\nM.Sc. Medieninformatik, PO 2018 /\nM.Sc. Media Informatics, PO 2018\n\n\nLehrformen (alle Angaben in SWS zu je 45 Minuten / all values in SWS of 45 minutes each)\n\n\nEnglish descriptions\nCredits/\nCredits\nWorkload /\nWorkload\nKontaktzeit/\nContact time\nSelbststudium/\nSelf study\nDauer/\nLength\nSemester/\nSemester\nSprache/\nLanguage\n5\n150 h\n\n60 h\n90 h\n1 Sem.\n3\nDeutsch\nVorlesung/\nLecture\nÜbung/\nPractice\nSeminar/\nSeminar\nPraktiku\nm/ Lab\nwork\nProjekt/\nProject\nTutorium/\nTutorial\nSeminarist.\nUnterricht/\nSeminaristic\nlesson\nStudien\narbeit/\nResearch\nproject\nBegleitetes\nSelbstlernen/\nAccompan‘d\nself study\n\n\n\n\n\n\n\n\n\nModulkategorie / category\n\nWahlpflichtmodul / Elective module\nWahlkatalog(e) /\n\n/\nelective catalogue(s)\n\n\nVoraussetzungen zur Teilnahme /\nrequirements for participation\n\n\nFormal /\nFormal\n\nKeine /\nnone\n\nInhaltlich /\ncontentwise\n\nKeine /\nnone\nVoraussetzungen zur Prüfung /\nprerequisites for the\nexamination\n\nDurch das gewählte Modul vorgegeben / Given by the chosen\nmodule\nPrüfungsform /\nform of examination\n\nAbhängig vom belegten Wahlfach /\nDepends on selected elective\nBenotet, Stellenwert der Note\nfür die Endnote /\ngraded, value of the grade for\nthe final grade\n\nBenotet: Ja / Is graded: Yes\n\n5/90 bzw. 5/120 / 5/90 resp. 5/120\nVoraussetzungen zur\nCreditvergabe/ requirements for\nawarding credit:\n\nBestandene Modulprüfung / Passed module examination\n\nLernergebnisse, Kompetenzen:\n\n\nsiehe MMI 05.01 bis MMI 05.33\n\nLehrinhalte:\n\n\nsiehe MMI 05.01 bis MMI 05.33\n\nLiteratur:\n\n\nsiehe MMI 05.01 bis MMI 05.33\n\nHochschule Düsseldorf\nModulhandbuch M.Sc. Medieninformatik\nVersion 1.0\nPO 2025\n38\n\n\nLearning outcomes,\ncompetences\n\n\nsee MMI 05.01 to MMI 05.33\n\nContent\n\n\nsee MMI 05.01 to MMI 05.33\n\nHochschule Düsseldorf\nModulhandbuch M.Sc. Medieninformatik\nVersion 1.0\nPO 2025\n39", "metadata": {"moduleNumber": "MMI 18", "moduleName": "Selection Module 8", "creditPoints": "5.0", "suggestedSemester": 3, "offeredInSeason": "every_semester", "examType": "see_elective", "heldInLanguage": "de", "reviserName": "Prof. Dr. Thomas Franz", "reviserEmail": "thomas.franz@hs-duesseldorf.de", "studyProgramId": 11, "source_type": "json", "moduleNameDe": "Wahlpflichtmodul 8", "source_file": "MMI_MHB_PO2025_V1.0.pdf", "pdf_page_start": 37, "pdf_page_end": 38, "studyProgramAbbrev": "MMI", "studyProgram_Url": "https://medien.hs-duesseldorf.de/mmi", "pdf_url": "https://medien.hs-duesseldorf.de/studium/studiengaenge/Documents/Modulhandb%C3%BCcher/MMI_MHB_PO2025_V1.0.pdf"}}
