{"id": "BCSIM_10", "text": "Title: Creative Coding\nModule Number: BCSIM 10\nCredits: 5.0 CP\nSemester: 1\nOffered In: winter_semester\nLanguage: de\nExam Type: written_exam\nInstructor: Prof. Dr. rer. nat. Christian Geiger\n\n--- Goals (EN) ---\n\n\n--- Goals (DE) ---\n\n\n--- Contents (EN) ---\n\n\n--- Contents (DE) ---\n\n\n--- Literature (EN) ---\n\n\n--- Literature (DE) ---", "metadata": {"moduleNumber": "BCSIM 10", "moduleName": "Creative Coding", "creditPoints": "5.0", "suggestedSemester": 1, "offeredInSeason": "winter_semester", "examType": "written_exam", "heldInLanguage": "de", "reviserName": "Prof. Dr. rer. nat. Christian Geiger", "reviserEmail": "geiger@hs-duesseldorf.de", "studyProgramId": 12, "source_type": "json"}}
{"id": "BCSIM_11", "text": "Title: Basics of Generative AI & Synthetic Media\nModule Number: BCSIM 11\nCredits: 5.0 CP\nSemester: 1\nOffered In: winter_semester\nLanguage: de\nExam Type: written_exam\nInstructor: Prof. Dr. rer. nat. Michael Marmann\n\n--- Goals (EN) ---\nThe students \n- understand the basic principles of generative AI systems/AI frameworks and can differentiate them from other AI technologies.\n- can understand basic algorithms and models of generative AI and analyze them in terms of their functionality and areas of application.\n- are able to create simple generative AI applications that are able to generate new content such as text, images or music.\n- know the role of synthetic media in the context of generative AI and can evaluate its potential for various media formats.\n- can reflect on ethical considerations and the social impact of the creation and use of synthetic media.\n- develop a critical understanding of the challenges of dealing with authenticity and copyright in relation to AI-generated content.\n- are able to design scenarios in which generative AI and synthetic media can be used sensibly for innovative applications.\n\n--- Goals (DE) ---\nDie Studierenden \n- verstehen die Grundprinzipien generativer KI-Systeme/KI-Frameworks und können diese von anderen KI-Technologien abgrenzen.\n- können grundlegende Algorithmen und Modelle der generativen KI nachvollziehen und in Bezug auf ihre Funktionsweise und Anwendungsgebiete analysieren.\n- sind in der Lage, einfache generative KI-Anwendungen zu erstellen, die in der Lage sind, neue Inhalte wie Texte, Bilder oder Musik zu generieren.\n- kennen die Rolle von Synthetic Media im Kontext der generativen KI und können dessen Potenzial für verschiedene Medienformate bewerten.\n- können ethische Überlegungen und gesellschaftliche Auswirkungen der Erstellung und Nutzung von Synthetic Media reflektieren.\n- entwickeln ein kritisches Verständnis für die Herausforderungen im Umgang mit Authentizität und Urheberrecht in Bezug auf durch KI generierte Inhalte.\n- sind befähigt, Szenarien zu konzipieren, in denen generative KI und Synthetic Media sinnvoll für innovative Anwendungen eingesetzt werden können.\n\n--- Contents (EN) ---\nThe lecture offers an introduction to the basics of generative artificial intelligence and synthetic media. The focus is on the practical application of generative technologies to create innovative and interactive media content. Students will learn how generative models such as GANs and VAEs can be used to generate personalized learning materials, interactive media applications and user-centric digital content. \n\nHands-on work with synthetic media development tools and platforms is an essential part of the course. Students will have the opportunity to develop their own projects to learn how generative AI technologies can be used to improve user experience and engagement. \n\nIn addition, the lecture deals with ethical and legal issues related to the use of synthetic media and generative AI, including data protection and copyright issues. The aim is to provide students with a comprehensive understanding of the opportunities and challenges of generative AI and synthetic media.\n\n--- Contents (DE) ---\nDie Vorlesung bietet eine Einführung in die Grundlagen der generativen Künstlichen Intelligenz und Synthetic Media. Der Fokus liegt auf der praktischen Anwendung generativer Technologien zur Erstellung innovativer und interaktiver Medieninhalte. Die Studierenden lernen, wie generative Modelle wie GANs und VAEs genutzt werden können, um personalisierte Lernmaterialien, interaktive Medienanwendungen und nutzerorientierte digitale Inhalte zu generieren. \n\nDie praktische Arbeit mit den Tools und Plattformen für die Entwicklung von Synthetic Media ist ein wesentlicher Bestandteil des Kurses. Die Studierenden erhalten die Möglichkeit, eigene Projekte zu entwickeln, um zu lernen, wie generative KI-Technologien zur Verbesserung von Benutzererfahrung und Engagement eingesetzt werden können. \n\nDarüber hinaus behandelt die Vorlesung ethische und rechtliche Fragen im Zusammenhang mit der Nutzung von Synthetic Media und generativer KI, einschließlich Datenschutz und Urheberrechtsfragen. Ziel ist es, den Studierenden ein umfassendes Verständnis der Möglichkeiten und Herausforderungen von generativer KI und Synthetic Media zu vermitteln.\n\n--- Literature (EN) ---\nCurrent literature references and sources of information are provided at the beginning of the module or directly from the course context. In addition, digital media are increasingly used as a source of knowledge.\n\n--- Literature (DE) ---\nAktuelle Literaturhinweise und Informationsquellen werden zu Beginn des Moduls oder unmittelbar aus dem Veranstaltungskontext herausgegeben. Zusätzlich werden verstärkt digitale Medien als Wissensquelle eingesetzt.", "metadata": {"moduleNumber": "BCSIM 11", "moduleName": "Basics of Generative AI & Synthetic Media", "creditPoints": "5.0", "suggestedSemester": 1, "offeredInSeason": "winter_semester", "examType": "written_exam", "heldInLanguage": "de", "reviserName": "Prof. Dr. rer. nat. Michael Marmann", "reviserEmail": "marmann@hs-duesseldorf.de", "studyProgramId": 12, "source_type": "json"}}
{"id": "BCSIM_12", "text": "Title: Design Basics 1: Visual Communication\nModule Number: BCSIM 12\nCredits: 5.0 CP\nSemester: 1\nOffered In: winter_semester\nLanguage: de\nExam Type: portfolio\nInstructor: Prof. Gabriele Schwab-Trapp\n\n--- Goals (EN) ---\nStudents understand the essential criteria of design and can apply basic theoretical and practical vocabulary for tasks in the field of visual design. They are able to independently develop and visualise design tasks using analogue and digital design tools and apply basic design and creative techniques.\n\n--- Goals (DE) ---\nDie Studierenden verstehen wesentliche Kriterien der Gestaltung und können theoretisches und praktisches Grundlagenvokabular für Aufgaben im Bereich der visuellen Gestaltung anwenden. Sie sind in der Lage eigenständig gestalterische Aufgabenstellungen mit analogen und digitalen Entwurfswerkzeugen zu entwickeln und zu visualisieren, sowie grundlegende Entwurfs- und Kreativtechniken anzuwenden.\n\n--- Contents (EN) ---\nIntroduction to visual communication and promotion of artistic representation skills through practical and artistic basic exercises, as well as the development of creative awareness through the systematic, theoretical and sensual examination of design.  \n\n- Design basics: colour, form, composition\n- Basic design and creativity techniques\n- Research, analysis, presentation, documentation\n- Introduction to various visual techniques of representation and presentation\n\n--- Contents (DE) ---\nEinführung in die visuelle Kommunikation und Förderung der bildnerischen Darstellungsfähigkeit durch praktisch-bildnerische Grundlagenübungen, sowie die Entwicklung eines gestalterischen Bewusstseins durch die systematische, theoretische und sinnliche Auseinandersetzung mit Gestaltung.  \n\n- Gestaltungsgrundlagen Farbe, Form, Komposition\n- Grundlegende Entwurfs- und Kreativitätstechniken\n- Recherche, Analyse, Präsentation, Dokumentation\n- Einführung in verschiedene bildnerische Darstellungs- und Präsentationstechniken\n\n--- Literature (EN) ---\nMaterial and literature references are provided for the respective topic in the seminar. Information in the form of text extracts, literature, image examples and research suggestions are provided to support the respective learning, realisation and design steps.\n\n--- Literature (DE) ---\nMaterial- und Literaturangaben werden zu dem jeweiligen Thema im Seminar ausgegeben. Zur Unterstützung der jeweiligen Lern-, Erkenntnis- und Gestaltungsschritte werden Hinweise in Form von Textauszügen, Literatur, Bildbeispielen und Recherchevorschlägen gegeben.", "metadata": {"moduleNumber": "BCSIM 12", "moduleName": "Design Basics 1: Visual Communication", "creditPoints": "5.0", "suggestedSemester": 1, "offeredInSeason": "winter_semester", "examType": "portfolio", "heldInLanguage": "de", "reviserName": "Prof. Gabriele Schwab-Trapp", "reviserEmail": "gabi.schwab-trapp@hs-duesseldorf.de", "studyProgramId": 12, "source_type": "json"}}
{"id": "BCSIM_13", "text": "Title: Basics Filmdesign audiovisual\nModule Number: BCSIM 13\nCredits: 5.0 CP\nSemester: 1\nOffered In: winter_semester\nLanguage: de\nExam Type: portfolio\nInstructor: Prof. Isolde Asal\n\n--- Goals (EN) ---\nStudents learn the basics of audiovisual perception.\n\n--- Goals (DE) ---\nDie Studierenden erlernen die Grundlagen audiovisueller Wahrnehmung.\n\n--- Contents (EN) ---\nStudents learn the basics of visual perception and image composition in order to create aesthetically pleasing and meaningful images. They deepen their understanding of film design, sound design and motion design in order to translate creative ideas convincingly into audiovisual concepts.\n\n- Basics of visual perception\n- Basics of image composition\n- Basics of film design / film conception\n- Implementation of creative ideas in audiovisual concepts\n- Basics of sound design\n- Basics of motion design\n\n--- Contents (DE) ---\nDie Studierenden lernen die Grundlagen visueller Wahrnehmung und Bildaufbau, um ästhetisch ansprechende und aussagekräftige Bilder zu schaffen. Sie vertiefen ihr Verständnis von Filmgestaltung, Sounddesign und Motion Design, um kreative Ideen überzeugend in audiovisuelle Konzepte umzusetzen.\n\n- Grundlagen visuelle Wahrnehmung\n- Grundlagen Bildaufbau/Bildkomposition\n- Grundlagen Filmgestaltung / Filmkonzeption\n- Umsetzung von kreativen Ideen in audiovisuelle Konzepte\n- Grundlagen Sounddesign\n- Grundlagen Motion Design\n\n--- Literature (EN) ---\n- P. Kandorfer: Lehrbuch der Filmgestaltung, Schiele und Schön, 2010\n- W. Faulstich: Grundkurs Filmanalyse, UTB Verlag, 2008\n- J. Monaco: Film verstehen, Rowohlt-Taschenbuch-Verlag, 2001\n- S. D. Katz: Die richtige Einstellung - Shot by shot, Zweitausendeins, 1999\n- S. Rene Meyer: Interactive Storytelling for the Screen, Routledge, 2021\n- D. Fissoun: Color Correction with DaVinci Resolve, Blackmagicdesign, 2020\n- H. Kapp: Motion Picture Design, Carl Hanser Verlag, 2021\n\n--- Literature (DE) ---\n- P. Kandorfer: Lehrbuch der Filmgestaltung, Schiele und Schön, 2010\n- W. Faulstich: Grundkurs Filmanalyse, UTB Verlag, 2008\n- J. Monaco: Film verstehen, Rowohlt-Taschenbuch-Verlag, 2001\n- S. D. Katz: Die richtige Einstellung - Shot by shot, Zweitausendeins, 1999\n- S. Rene Meyer: Interactive Storytelling for the Screen, Routledge, 2021\n- D. Fissoun: Color Correction with DaVinci Resolve, Blackmagicdesign, 2020\n- H. Kapp: Motion Picture Design, Carl Hanser Verlag, 2021", "metadata": {"moduleNumber": "BCSIM 13", "moduleName": "Basics Filmdesign audiovisual", "creditPoints": "5.0", "suggestedSemester": 1, "offeredInSeason": "winter_semester", "examType": "portfolio", "heldInLanguage": "de", "reviserName": "Prof. Isolde Asal", "reviserEmail": "isolde.asal@hs-duesseldorf.de", "studyProgramId": 12, "source_type": "json"}}
{"id": "BCSIM_14.01", "text": "Title: Design & Innovation Methods\nModule Number: BCSIM 14.01\nCredits: 5.0 CP\nSemester: 1\nOffered In: winter_semester\nLanguage: en_on_demand\nExam Type: portfolio\nInstructor: Prof. Dr. Alina Huldtgren\n\n--- Goals (EN) ---\nStudents understand the basics of iterative, user-centered design processes and the nuances of different empathic and participatory approaches.   \nStudents are able to select a suitable design approach depending on the project objective and implement a project iteratively. \nDepending on the project phase, students can select and implement suitable methods from a pool of methods.\n\n--- Goals (DE) ---\nDie Studierenden verstehen die Grundlagen iterativer, nutzer*innenzentrieter Designprozesse und die Nuancen verschiedener empathischer und partizipativer Ansätze.   \nDie Studierenden sind fähig je nach Projektziel einen passenden Designansatz auszuwählen und ein Projekt iterativ umzusetzen. \nJe nach Projektphase können die Studierenden aus einem Methodenpool passende Methoden wählen und durchführen.\n\n--- Contents (EN) ---\nFundamentals of design methodology and differentiation of user-centered and participative design approaches, including user-centered design, design thinking, experience design, co-design \n\nTheories in the human-centered development of media\n\nParadigms of human-technology interaction\n\nIntroduction to qualitative and quantitative methods for (UX) research, idea generation / conception, evaluation (ethnographic field studies, interviews, observations, cultural probes, creative methods, lab user studies)\n\nMethods of value-oriented design, e.g. value-sensitive design\n\nTranslated with DeepL.com (free version)\n\n--- Contents (DE) ---\nGrundlagen Designmethodik und Abgrenzung nutzer*innenzentrierter und partizipativer Designansätze, u.A. User-centered design, Design Thinking, Experience Design, Co-Design \n\nTheorien in der menschzentrierten Entwicklung von Medien\n\nParadigmen der Mensch-Technik Interaktion\n\nEinführung in qualitative und quantitative Methoden zur (UX-)Recherche, Ideenfindung / Konzeption, Evaluation (Ethnografische Feldstudien, Interviews, Beobachtungen, Cultural Probes, Kreativmethoden, Lab User Studies)\n\nMethoden des werteorientierten Designs, z.B. Value Sensitive Design\n\n--- Literature (EN) ---\n- Wright, P., & McCarthy, J. (2022). Experience-centered design: designers, users, and communities in dialogue. Springer Nature.\n- Uebernickel, F., Brenner, W., Pukall, B., Naef, T., & Schindlholzer, B. (2015). Design Thinking: Das Handbuch.\n- Kuniavsky, M. (2003). Observing the user experience: a practitioner's guide to user research. Elsevier. \n- Hassenzahl, M. (2010). Experience design: Technology for all the right reasons. Synthesis lectures on human-centered informatics, 3(1), 1-95. \n- McKercher, K. A. (2020). Beyond sticky notes. Doing co-design for Real: Mindsets, Methods, and Movements, 1st Edn. Sydney, NSW: Beyond Sticky Notes.\n- Friedman, B., Kahn, P. H., Borning, A., & Huldtgren, A. (2013). Value sensitive design and information systems. Early engagement and new technologies: Opening up the laboratory, 55-95.\n\n--- Literature (DE) ---\n- Wright, P., & McCarthy, J. (2022). Experience-centered design: designers, users, and communities in dialogue. Springer Nature.\n- Uebernickel, F., Brenner, W., Pukall, B., Naef, T., & Schindlholzer, B. (2015). Design Thinking: Das Handbuch.\n- Kuniavsky, M. (2003). Observing the user experience: a practitioner's guide to user research. Elsevier. \n- Hassenzahl, M. (2010). Experience design: Technology for all the right reasons. Synthesis lectures on human-centered informatics, 3(1), 1-95. \n- McKercher, K. A. (2020). Beyond sticky notes. Doing co-design for Real: Mindsets, Methods, and Movements, 1st Edn. Sydney, NSW: Beyond Sticky Notes.\n- Friedman, B., Kahn, P. H., Borning, A., & Huldtgren, A. (2013). Value sensitive design and information systems. Early engagement and new technologies: Opening up the laboratory, 55-95.", "metadata": {"moduleNumber": "BCSIM 14.01", "moduleName": "Design & Innovation Methods", "creditPoints": "5.0", "suggestedSemester": 1, "offeredInSeason": "winter_semester", "examType": "portfolio", "heldInLanguage": "en_on_demand", "reviserName": "Prof. Dr. Alina Huldtgren", "reviserEmail": "alina.huldtgren@hs-duesseldorf.de", "studyProgramId": 12, "source_type": "json"}}
{"id": "BCSIM_15", "text": "Title: Creative Project 1\nModule Number: BCSIM 15\nCredits: 5.0 CP\nSemester: 1\nOffered In: winter_semester\nLanguage: de\nExam Type: project\nInstructor: Prof. Isolde Asal\n\n--- Goals (EN) ---\nDepending on the project orientation.\n\n(a) Students are able to design, plan and realize projects. Students acquire key social and personal skills as well as in-depth specialist skills in various areas.\n\n(b) Students can work their way into subject areas in a relatively short time and develop and realize appropriate solutions.\n\n(c) Students develop the ability to critically analyze, problem-solving skills and a deeper understanding of the application of theoretical knowledge in practice.\n\n--- Goals (DE) ---\nJe nach Projektausrichtung verschieden.\n\n(a) Die Studierenden können Projekte konzipieren, planen und umsetzen. Die Studierenden erhalten soziale und persönliche Schlüsselkompetenzen sowie vertiefende Fachkompetenzen in unterschiedlichen Bereichen.\n\n(b) Die Studierenden können sich in relativ kurzer Zeit in Themenbereiche einarbeiten und entsprechende Lösungsansätze entwickeln und umsetzen.\n\n(c) Die Studierenden entwickeln die Fähigkeit zur kritischen Analyse, Problemlösungsfähigkeiten und ein tieferes Verständnis für die Anwendung theoretischer Kenntnisse in der Praxis.\n\n--- Contents (EN) ---\nDepending on the project orientation.\n\n(a) Project: The students work in a team to find a solution to a complex task. They go through all the steps of a typical project, from the initial idea to conception and implementation.\n\n(b) Compact week: During a compact week, students complete a practice-oriented project in line with the project focus.\n\n(c) Excursion: Students research and understand complex concepts through direct experience on site and then put them into practice.\n\n--- Contents (DE) ---\nJe nach Projektausrichtung verschieden.\n\n(a) Projekt: Die Studierenden arbeiten im Team an der Lösung einer komplexen Aufgabenstellung. Von der ersten Idee über die Konzeption bis hin zur Umsetzung werden alle Schritte eines typischen Projektes durchlaufen.\n\n(b) Kompaktwoche: Die Studierenden durchlaufen in einer Kompaktwoche ein praxisorientiertes Projekt entsprechend der Projektausrichtung.\n\n(c) Exkursion: Die Studierenden erforschen und verstehen durch direkte Erfahrungen vor Ort komplexe Konzepte und setzen diese anschließend praktisch um.\n\n--- Literature (EN) ---\nLiterature references will be issued for the respective topic at the beginning of the project.\n\n--- Literature (DE) ---\nLiteraturangaben werden zu dem jeweiligen Thema zu Beginn des Projektes ausgegeben.", "metadata": {"moduleNumber": "BCSIM 15", "moduleName": "Creative Project 1", "creditPoints": "5.0", "suggestedSemester": 1, "offeredInSeason": "winter_semester", "examType": "project", "heldInLanguage": "de", "reviserName": "Prof. Isolde Asal", "reviserEmail": "isolde.asal@hs-duesseldorf.de", "studyProgramId": 12, "source_type": "json"}}
{"id": "BCSIM_21", "text": "Title: Basics of prompt engineering\nModule Number: BCSIM 21\nCredits: 5.0 CP\nSemester: 2\nOffered In: summer_semester\nLanguage: de\nExam Type: written_exam\nInstructor: Prof. Dr. rer. nat. Michael Marmann\n\n--- Goals (EN) ---\nThe students\n\n- understand the role and importance of prompt engineering in the context of generative AI systems.\n- can develop effective prompts to achieve desired results from AI systems.\n- are able to optimize the interaction between users and AI systems through targeted prompt design.\n- know programming languages such as Python and frameworks such as PyTorch and can confidently classify their possible applications.\n- know methods for analyzing and evaluating the effectiveness of prompts in various application scenarios.\n- can take ethical and practical considerations into account when designing prompts.\n- are able to develop creative and innovative approaches in prompt engineering for specific applications.\n\n--- Goals (DE) ---\nDie Studierenden\n\n- verstehen die Rolle und Bedeutung von Prompt-Engineering im Kontext generativer KI-Systeme.\n- können effektive Prompts entwickeln, um gewünschte Ergebnisse von KI-Systemen zu erzielen.\n- sind in der Lage, die Interaktion zwischen Nutzern und KI-Systemen durch gezieltes Prompt-Design zu optimieren.\n- kennen Programmiersprachen wie Python und Frameworks wie PyTorch und können deren Einsatzmöglichkeiten sicher einordnen.\n- kennen Methoden zur Analyse und Bewertung der Effektivität von Prompts in verschiedenen Anwendungsszenarien.\n- können ethische und praktische Überlegungen bei der Gestaltung von Prompts berücksichtigen.\n- sind befähigt, kreative und innovative Ansätze im Prompt-Engineering für spezifische Anwendungsfälle zu entwickeln.\n\n--- Contents (EN) ---\nThe lecture Fundamentals of Prompt Engineering provides an in-depth introduction to the field of prompt engineering, a key element in dealing with generative AI systems, and complements the content of the module 'Fundamentals of Generative AI & Synthetic Media'. Students will learn how to construct effective prompts to drive the responses of AI systems such as chatbots, text generators and image synthesis tools.\n\nThe focus is on understanding how AI models respond to different types of prompts and how these can be used to control AI outcomes. The lecture covers topics such as structuring prompts, using keywords and customizing prompts to specific requirements.\n\nStudents also deal with the analysis and evaluation of prompt results. They learn how to measure the effectiveness of prompts in different application areas and how to use this information to refine the prompts.\n\nEthics and practical considerations in prompt engineering are also covered. Students will discuss how to design prompts so that they do not lead to misleading, inaccurate or unethical AI responses.\n\nFinally, students apply their knowledge in practical projects in which they develop innovative prompts for specific use cases in order to improve the interaction between users and AI systems.\n\n--- Contents (DE) ---\nDie Vorlesung Grundlagen des Prompt-Engineering bietet eine tiefgehende Einführung in das Gebiet des Prompt-Engineerings, einem Schlüsselelement im Umgang mit generativen KI-Systemen, und ergänzt die Inhalte des Moduls \"Grundlagen der Generativen KI & Synthetic Media\". Die Studierenden lernen, wie man effektive Prompts konstruiert, um die Antworten von KI-Systemen wie Chatbots, Textgeneratoren und Bildsynthesewerkzeugen zu steuern.\n\nIm Mittelpunkt steht das Verständnis dafür, wie KI-Modelle auf verschiedene Arten von Prompts reagieren und wie diese zur Steuerung der KI-Ergebnisse eingesetzt werden können. Die Vorlesung deckt Themen wie die Strukturierung von Prompts, die Verwendung von Schlüsselwörtern und die Anpassung der Prompts an spezifische Anforderungen ab.\n\nDie Studierenden befassen sich auch mit der Analyse und Bewertung von Prompt-Ergebnissen. Sie lernen, wie man die Effektivität von Prompts in unterschiedlichen Anwendungsbereichen misst und wie man diese Informationen nutzt, um die Prompts zu verfeinern.\n\nEthik und praktische Überlegungen im Prompt-Engineering werden ebenfalls behandelt. Die Studierenden diskutieren, wie man Prompts so gestaltet, dass sie nicht zu irreführenden, ungenauen oder unethischen KI-Antworten führen.\n\nAbschließend wenden die Studierenden ihr Wissen in praktischen Projekten an, in denen sie innovative Prompts für konkrete Anwendungsfälle entwickeln, um die Interaktion zwischen Nutzern und KI-Systemen zu verbessern.\n\n--- Literature (EN) ---\nCurrent literature references and sources of information are provided at the beginning of the module or directly from the course context. In addition, digital media are increasingly used as a source of knowledge.\n\n--- Literature (DE) ---\nAktuelle Literaturhinweise und Informationsquellen werden zu Beginn des Moduls oder unmittelbar aus dem Veranstaltungskontext herausgegeben. Zusätzlich werden verstärkt digitale Medien als Wissensquelle eingesetzt.", "metadata": {"moduleNumber": "BCSIM 21", "moduleName": "Basics of prompt engineering", "creditPoints": "5.0", "suggestedSemester": 2, "offeredInSeason": "summer_semester", "examType": "written_exam", "heldInLanguage": "de", "reviserName": "Prof. Dr. rer. nat. Michael Marmann", "reviserEmail": "marmann@hs-duesseldorf.de", "studyProgramId": 12, "source_type": "json"}}
{"id": "BCSIM_22", "text": "Title: Design Basics 2: Web & Interaction\nModule Number: BCSIM 22\nCredits: 5.0 CP\nSemester: 2\nOffered In: summer_semester\nLanguage: de\nExam Type: portfolio\nInstructor: Prof. Gabriele Schwab-Trapp\n\n--- Goals (EN) ---\nStudents understand essential criteria and the basics of interactive media. They can apply basic design and creativity techniques and independently develop prototypes using analogue and digital design tools. They can apply methods to independently develop and design solutions for interactive media in terms of concept and content. In addition to the basics of usability and user experience, students will be familiar with different methods and processes for developing meaningful interaction offers.\n\n--- Goals (DE) ---\nDie Studierenden verstehen wesentliche Kriterien und die Grundlagen interaktiver Medien. Sie können grundlegende Entwurfs- und Kreativitätstechniken anwenden und eigenständig mit analogen und digitalen Entwurfswerkzeugen Prototypen entwickeln. Sie können Methoden anwenden, um eigenständig Lösungen für interaktive Medien konzeptionell und inhaltsbezogen zu entwickeln und zu gestalten. Neben den Grundlagen Usability und User Experience kennen die Studierenden unterschiedliche Methoden und Prozesse zur Entwicklung sinnvoller Interaktionsangebote.\n\n--- Contents (EN) ---\nIntroduction to the basics of interactive design of information architecture via structuring of content, conception and design, creation of prototypes and the application of simple evaluations.\n\n- Information design and data visualisation \n- Fundamentals of conception and design of interaction and interface design\n- Basics of usability and human-centred design\n\n--- Contents (DE) ---\nEinführung in die Grundlagen interaktiver Gestaltung von Informationsarchitektur über Strukturierung der Inhalte, Konzeption und Entwurf, Erstellung von Prototypen und der Anwendung einfacher Evaluationen.\n\n- Informationsgestaltung und Datenvisualisierung \n- Grundlagen in Konzeption und Entwurf der Interaktions- und Interfacegestaltung\n- Grundlagen Usability und Human-Centered Design\n\n--- Literature (EN) ---\nMaterial and literature references are provided for the respective topic in the seminar. Information in the form of text extracts, literature, image examples and research suggestions are provided to support the respective learning, realisation and design steps.\n\n--- Literature (DE) ---\nMaterial- und Literaturangaben werden zu dem jeweiligen Thema im Seminar ausgegeben. Zur Unterstützung der jeweiligen Lern-, Erkenntnis- und Gestaltungsschritte werden Hinweise in Form von Textauszügen, Literatur, Bildbeispielen und Recherchevorschlägen gegeben.", "metadata": {"moduleNumber": "BCSIM 22", "moduleName": "Design Basics 2: Web & Interaction", "creditPoints": "5.0", "suggestedSemester": 2, "offeredInSeason": "summer_semester", "examType": "portfolio", "heldInLanguage": "de", "reviserName": "Prof. Gabriele Schwab-Trapp", "reviserEmail": "gabi.schwab-trapp@hs-duesseldorf.de", "studyProgramId": 12, "source_type": "json"}}
{"id": "BCSIM_23", "text": "Title: Advanced Film Design\nModule Number: BCSIM 23\nCredits: 5.0 CP\nSemester: 2\nOffered In: summer_semester\nLanguage: de\nExam Type: portfolio\nInstructor: Prof. Isolde Asal\n\n--- Goals (EN) ---\nStudents will learn advanced concepts of filmmaking, including advanced narrative and cinematic techniques, storytelling and sound design, with a focus on practical application and insights into industry practice.\n\n--- Goals (DE) ---\nDie Studierenden erlernen fortgeschrittene Konzepte der Filmgestaltung, darunter erweiterte Erzähl- und Filmtechniken, Storytelling und Sounddesign, wobei der Fokus auf praktischer Anwendung und Einblicken in die Industriepraxis liegt.\n\n--- Contents (EN) ---\nStudents learn in-depth cinematic narrative techniques and storytelling, including interactive techniques, as well as visual design and aesthetics in screen design, the conception of sound design and film music, advanced post-production techniques and their practical application and portfolio assignment.\n\n- In-depth study of cinematic narrative techniques and storytelling, also interactive \n- Visual design and aesthetics / screen design\n- Conception of sound design & film music\n- Advanced post-production techniques \n- Practical application and portfolio assignment\n\n--- Contents (DE) ---\nDie Studierenden erlernen die Vertiefung filmischer Erzähltechniken und Storytelling, auch interaktiv, sowie visuelles Design und Ästhetik im Screendesign, die Konzeption von Sounddesign und Filmmusik, fortgeschrittene Techniken der Postproduktion sowie deren praktische Anwendung und Portfolioaufgabe.\n\n- Vertiefung filmischer Erzähltechniken und Storytelling, auch interactive \n- Visuelles Design und Ästhetik / Screendesign\n- Konzeption Sounddesign & Filmmusik\n- Fortgeschrittene Techniken der Postproduktion \n- Praktische Anwendung und Portfolioaufgabe\n\n--- Literature (EN) ---\n- P. Kandorfer: Lehrbuch der Filmgestaltung, Schiele und Schön, 2010\n- W. Faulstich: Grundkurs Filmanalyse, UTB Verlag, 2008\n- J. Monaco: Film verstehen, Rowohlt-Taschenbuch-Verlag, 2001\n- S. D. Katz: Die richtige Einstellung - Shot by shot, Zweitausendeins, 1999\n- S. Rene Meyer: Interactive Storytelling for the Screen, Routledge, 2021\n- D. Fissoun: Color Correction with DaVinci Resolve, Blackmagicdesign, 2020\n- H. Kapp: Motion Picture Design, Carl Hanser Verlag, 2021\n\n--- Literature (DE) ---\n- P. Kandorfer: Lehrbuch der Filmgestaltung, Schiele und Schön, 2010\n- W. Faulstich: Grundkurs Filmanalyse, UTB Verlag, 2008\n- J. Monaco: Film verstehen, Rowohlt-Taschenbuch-Verlag, 2001\n- S. D. Katz: Die richtige Einstellung - Shot by shot, Zweitausendeins, 1999\n- S. Rene Meyer: Interactive Storytelling for the Screen, Routledge, 2021\n- D. Fissoun: Color Correction with DaVinci Resolve, Blackmagicdesign, 2020\n- H. Kapp: Motion Picture Design, Carl Hanser Verlag, 2021", "metadata": {"moduleNumber": "BCSIM 23", "moduleName": "Advanced Film Design", "creditPoints": "5.0", "suggestedSemester": 2, "offeredInSeason": "summer_semester", "examType": "portfolio", "heldInLanguage": "de", "reviserName": "Prof. Isolde Asal", "reviserEmail": "isolde.asal@hs-duesseldorf.de", "studyProgramId": 12, "source_type": "json"}}
{"id": "BCSIM_24.01", "text": "Title: Agile Work\nModule Number: BCSIM 24.01\nCredits: 5.0 CP\nSemester: 2\nOffered In: summer_semester\nLanguage: de\nExam Type: written_exam\nInstructor: Prof. Dr. rer. nat. Michael Marmann\n\n--- Goals (EN) ---\nThe students\n\n- know the basic principles and values of agile working and can differentiate between classic methods.\n- understand various agile methods such as Scrum, Kanban and Design Thinking.\n- can practically apply agile processes in creative and interactive media environments.\n- can analyze and evaluate the effectiveness of agile methods in different project scenarios.\n- develop skills to promote teamwork and effective communication in agile teams.\n- can reflect on and implement the importance of feedback and continuous improvement in agile processes.\n\n--- Goals (DE) ---\nDie Studierenden\n\n- kennen die Grundprinzipien und Werte des Agilen Arbeitens und können klassische Methoden davon abgrenzen.\n- verstehen verschiedene agile Methoden wie Scrum, Kanban und Design Thinking.\n- können agile Prozesse in kreativen und interaktiven Medienumgebungen praktisch anwenden.\n- können die Effektivität agiler Methoden in unterschiedlichen Projektszenarien analysieren und bewerten.\n- entwickeln Fähigkeiten zur Förderung von Teamarbeit und effektiver Kommunikation in agilen Teams.\n- können die Bedeutung von Feedback und kontinuierlicher Verbesserung in agilen Prozessen reflektieren und umsetzen.\n\n--- Contents (EN) ---\nIn this module, students receive a comprehensive introduction to the basic principles and core values of agile working. A special focus is placed on agile methods such as Scrum, Kanban, Design Thinking and Lean, whose specific characteristics, areas of application and differences are highlighted. These methods are discussed in the context of media production and design to show students how they can make projects more efficient and flexible.\n\nThe practical application of agile methods is illustrated through case studies and real projects, among other things. Students familiarize themselves with important tools and techniques of agile project management, which are essential for the dynamic working environment of today's media projects.\n\nAnother focus of the module is on promoting teamwork and communication in agile teams. Students learn how crucial open communication and regular feedback are for the success of agile projects. They acquire skills in teamwork and conflict resolution and learn how to promote a continuous improvement process within their teams.\n\nAt the end of the module, the challenges of introducing agile methods into existing work structures are addressed. Students develop an understanding of how to overcome these challenges and successfully apply agile methods in different organizational contexts.\n\n--- Contents (DE) ---\nIn diesem Modul erhalten die Studierenden eine umfassende Einführung in die Grundprinzipien und Kernwerte des Agilen Arbeitens. Es wird ein besonderer Fokus auf agile Methoden wie Scrum, Kanban, Design Thinking und Lean gelegt, deren spezifische Merkmale, Anwendungsbereiche und Unterschiede beleuchtet werden. Diese Methoden werden im Kontext der Medienproduktion und -gestaltung erörtert, um den Studierenden zu zeigen, wie sie Projekte effizienter und flexibler gestalten können.\n\nDie praktische Anwendung agiler Methoden wird u.a. durch Fallstudien und reale Projekte veranschaulicht. Die Studierenden machen sich mit wichtigen Werkzeugen und Techniken des agilen Projektmanagements vertraut, die für das dynamische Arbeitsumfeld heutiger Medienprojekte unerlässlich sind.\n\nEin weiterer Schwerpunkt des Moduls liegt auf der Förderung von Teamarbeit und Kommunikation in agilen Teams. Die Studierenden erfahren, wie entscheidend offene Kommunikation und regelmäßiges Feedback für den Erfolg agiler Projekte sind. Sie erwerben Fähigkeiten in Teamarbeit und Konfliktlösung und lernen, wie sie einen kontinuierlichen Verbesserungsprozess innerhalb ihrer Teams fördern können.\n\nZum Abschluss des Moduls werden die Herausforderungen bei der Einführung agiler Methoden in bestehende Arbeitsstrukturen behandelt. Die Studierenden entwickeln ein Verständnis dafür, wie man diese Herausforderungen überwindet und agile Methoden erfolgreich in verschiedenen Organisationskontexten anwendet.\n\n--- Literature (EN) ---\n- Uwe Weinreich (2016): Lean Digitization - Digital transformation through agile management. Heidelberg: Springer Gabler.\n- Siegfried Kaltenecker (2017): Selbstorganisierte Unternehmen - Management und Coaching in der agilen Welt. Heidelberg: dpunkt.verlag.\n- Holger Timinger (2017): Modern project management: Achieving success with traditional, agile and hybrid approaches. Weinheim: Wiley.\n- Nele Graf, Denise Gramß, Frank Edelkraut (2017): Agile learning. Freiburg, Munich, Stuttgart: Haufe Group.\n- Jörg Preußig (2018): Agile project management - agility and Scrum in the classic\n- Project environment. Freiburg: Haufe Lexware.\n- Peter Hohberger (2018): SCRUM - The 'new' way of project management. In: Sven Grote and Rüdiger Goyk (eds.): Management tools from Silicon Valley. Berlin, Heidelberg: Springer. S. 115-128.\n- Boris Gloger et al (2018): The Scrum Principle: Building and Shaping Agile Organizations. Stuttgart: Schäffer-Poeschel.\n\nFurther up-to-date literature references and sources of information are provided at the beginning of the module or directly from the course context. In addition, digital media are increasingly used as a source of knowledge.\n\n--- Literature (DE) ---\n- Uwe Weinreich (2016): Lean Digitization - Digitale Transformation durch agiles Management. Heidelberg: Springer Gabler.\n- Siegfried Kaltenecker (2017): Selbstorganisierte Unternehmen - Management und Coaching in der agilen Welt. Heidelberg: dpunkt.verlag.\n- Holger Timinger (2017): Modernes Projektmanagement: Mit traditionellem, agilem und hybridem Vorgehen zum Erfolg. Weinheim: Wiley.\n- Nele Graf, Denise Gramß, Frank Edelkraut (2017): Agiles Lernen. Freiburg, München, Stuttgart: Haufe Group.\n- Jörg Preußig (2018): Agiles Projektmanagement - Agilität und Scrum im klassischen Projektumfeld. Freiburg: Haufe Lexware.\n- Peter Hohberger (2018): SCRUM - Die \"neue\" Art des Projektmanagements. In: Sven Grote und Rüdiger Goyk (Hg.): Führungsinstrumente aus dem Silicon Valley. Berlin, Heidelberg: Springer. S. 115-128.\n- Boris Gloger et al. (2018): Das Scrum-Prinzip: Agile Organisationen aufbauen und gestalten. Stuttgart: Schäffer-Poeschel.\n\nWeitere aktuelle Literaturhinweise und Informationsquellen werden zu Beginn des Moduls oder unmittelbar aus dem Veranstaltungskontext herausgegeben. Zusätzlich werden verstärkt digitale Medien als Wissensquelle eingesetzt.", "metadata": {"moduleNumber": "BCSIM 24.01", "moduleName": "Agile Work", "creditPoints": "5.0", "suggestedSemester": 2, "offeredInSeason": "summer_semester", "examType": "written_exam", "heldInLanguage": "de", "reviserName": "Prof. Dr. rer. nat. Michael Marmann", "reviserEmail": "marmann@hs-duesseldorf.de", "studyProgramId": 12, "source_type": "json"}}
{"id": "BCSIM_25", "text": "Title: Creative Project 2\nModule Number: BCSIM 25\nCredits: 5.0 CP\nSemester: 2\nOffered In: summer_semester\nLanguage: de\nExam Type: project\nInstructor: Prof. Isolde Asal\n\n--- Goals (EN) ---\nDepending on the project orientation.\n\n(a) Students are able to design, plan and realize projects. Students acquire key social and personal skills as well as in-depth specialist skills in various areas.\n\n(b) Students can work their way into subject areas in a relatively short time and develop and realize appropriate solutions.\n\n(c) Students develop the ability to critically analyze, problem-solving skills and a deeper understanding of the application of theoretical knowledge in practice.\n\n--- Goals (DE) ---\nJe nach Projektausrichtung verschieden.\n\n(a) Die Studierenden können Projekte konzipieren, planen und umsetzen. Die Studierenden erhalten soziale und persönliche Schlüsselkompetenzen sowie vertiefende Fachkompetenzen in unterschiedlichen Bereichen.\n\n(b) Die Studierenden können sich in relativ kurzer Zeit in Themenbereiche einarbeiten und entsprechende Lösungsansätze entwickeln und umsetzen.\n\n(c) Die Studierenden entwickeln die Fähigkeit zur kritischen Analyse, Problemlösungsfähigkeiten und ein tieferes Verständnis für die Anwendung theoretischer Kenntnisse in der Praxis.\n\n--- Contents (EN) ---\nDepending on the project orientation.\n\n(a) Project: The students work in a team to find a solution to a complex task. They go through all the steps of a typical project, from the initial idea to conception and implementation.\n\n(b) Compact week: During a compact week, students complete a practice-oriented project in line with the project focus.\n\n(c) Excursion: Students research and understand complex concepts through direct experience on site and then put them into practice.\n\n--- Contents (DE) ---\nJe nach Projektausrichtung verschieden.\n\n(a) Projekt: Die Studierenden arbeiten im Team an der Lösung einer komplexen Aufgabenstellung. Von der ersten Idee über die Konzeption bis hin zur Umsetzung werden alle Schritte eines typischen Projektes durchlaufen.\n\n(b) Kompaktwoche: Die Studierenden durchlaufen in einer Kompaktwoche ein praxisorientiertes Projekt entsprechend der Projektausrichtung.\n\n(c) Exkursion: Die Studierenden erforschen und verstehen durch direkte Erfahrungen vor Ort komplexe Konzepte und setzen diese anschließend praktisch um.\n\n--- Literature (EN) ---\nLiterature references will be issued for the respective topic at the beginning of the project.\n\n--- Literature (DE) ---\nLiteraturangaben werden zu dem jeweiligen Thema zu Beginn des Projektes ausgegeben.", "metadata": {"moduleNumber": "BCSIM 25", "moduleName": "Creative Project 2", "creditPoints": "5.0", "suggestedSemester": 2, "offeredInSeason": "summer_semester", "examType": "project", "heldInLanguage": "de", "reviserName": "Prof. Isolde Asal", "reviserEmail": "isolde.asal@hs-duesseldorf.de", "studyProgramId": 12, "source_type": "json"}}
{"id": "BCSIM_35", "text": "Title: Creative Project 3\nModule Number: BCSIM 35\nCredits: 5.0 CP\nSemester: 3\nOffered In: winter_semester\nLanguage: de\nExam Type: project\nInstructor: Prof. Isolde Asal\n\n--- Goals (EN) ---\nDepending on the project orientation.\n\n(a) Students are able to design, plan and realize projects. Students acquire key social and personal skills as well as in-depth specialist skills in various areas.\n\n(b) Students can work their way into subject areas in a relatively short time and develop and realize appropriate solutions.\n\n(c) Students develop the ability to critically analyze, problem-solving skills and a deeper understanding of the application of theoretical knowledge in practice.\n\n--- Goals (DE) ---\nJe nach Projektausrichtung verschieden.\n\n(a) Die Studierenden können Projekte konzipieren, planen und umsetzen. Die Studierenden erhalten soziale und persönliche Schlüsselkompetenzen sowie vertiefende Fachkompetenzen in unterschiedlichen Bereichen.\n\n(b) Die Studierenden können sich in relativ kurzer Zeit in Themenbereiche einarbeiten und entsprechende Lösungsansätze entwickeln und umsetzen.\n\n(c) Die Studierenden entwickeln die Fähigkeit zur kritischen Analyse, Problemlösungsfähigkeiten und ein tieferes Verständnis für die Anwendung theoretischer Kenntnisse in der Praxis.\n\n--- Contents (EN) ---\nDepending on the project orientation.\n\n(a) Project: The students work in a team to find a solution to a complex task. They go through all the steps of a typical project, from the initial idea to conception and implementation.\n\n(b) Compact week: During a compact week, students complete a practice-oriented project in line with the project focus.\n\n(c) Excursion: Students research and understand complex concepts through direct experience on site and then put them into practice.\n\n--- Contents (DE) ---\nJe nach Projektausrichtung verschieden.\n\n(a) Projekt: Die Studierenden arbeiten im Team an der Lösung einer komplexen Aufgabenstellung. Von der ersten Idee über die Konzeption bis hin zur Umsetzung werden alle Schritte eines typischen Projektes durchlaufen.\n\n(b) Kompaktwoche: Die Studierenden durchlaufen in einer Kompaktwoche ein praxisorientiertes Projekt entsprechend der Projektausrichtung.\n\n(c) Exkursion: Die Studierenden erforschen und verstehen durch direkte Erfahrungen vor Ort komplexe Konzepte und setzen diese anschließend praktisch um.\n\n--- Literature (EN) ---\nLiterature references will be issued for the respective topic at the beginning of the project.\n\n--- Literature (DE) ---\nLiteraturangaben werden zu dem jeweiligen Thema zu Beginn des Projektes ausgegeben.", "metadata": {"moduleNumber": "BCSIM 35", "moduleName": "Creative Project 3", "creditPoints": "5.0", "suggestedSemester": 3, "offeredInSeason": "winter_semester", "examType": "project", "heldInLanguage": "de", "reviserName": "Prof. Isolde Asal", "reviserEmail": "isolde.asal@hs-duesseldorf.de", "studyProgramId": 12, "source_type": "json"}}
{"id": "BCSIM_45", "text": "Title: Creative Project 4\nModule Number: BCSIM 45\nCredits: 5.0 CP\nSemester: 4\nOffered In: summer_semester\nLanguage: de\nExam Type: project\nInstructor: Prof. Isolde Asal\n\n--- Goals (EN) ---\nDepending on the project orientation.\n\n(a) Students are able to design, plan and realize projects. Students acquire key social and personal skills as well as in-depth specialist skills in various areas.\n\n(b) Students can work their way into subject areas in a relatively short time and develop and realize appropriate solutions.\n\n(c) Students develop the ability to critically analyze, problem-solving skills and a deeper understanding of the application of theoretical knowledge in practice.\n\n--- Goals (DE) ---\nJe nach Projektausrichtung verschieden.\n\n(a) Die Studierenden können Projekte konzipieren, planen und umsetzen. Die Studierenden erhalten soziale und persönliche Schlüsselkompetenzen sowie vertiefende Fachkompetenzen in unterschiedlichen Bereichen.\n\n(b) Die Studierenden können sich in relativ kurzer Zeit in Themenbereiche einarbeiten und entsprechende Lösungsansätze entwickeln und umsetzen.\n\n(c) Die Studierenden entwickeln die Fähigkeit zur kritischen Analyse, Problemlösungsfähigkeiten und ein tieferes Verständnis für die Anwendung theoretischer Kenntnisse in der Praxis.\n\n--- Contents (EN) ---\nDepending on the project orientation.\n\n(a) Project: The students work in a team to find a solution to a complex task. They go through all the steps of a typical project, from the initial idea to conception and implementation.\n\n(b) Compact week: During a compact week, students complete a practice-oriented project in line with the project focus.\n\n(c) Excursion: Students research and understand complex concepts through direct experience on site and then put them into practice.\n\n--- Contents (DE) ---\nJe nach Projektausrichtung verschieden.\n\n(a) Projekt: Die Studierenden arbeiten im Team an der Lösung einer komplexen Aufgabenstellung. Von der ersten Idee über die Konzeption bis hin zur Umsetzung werden alle Schritte eines typischen Projektes durchlaufen.\n\n(b) Kompaktwoche: Die Studierenden durchlaufen in einer Kompaktwoche ein praxisorientiertes Projekt entsprechend der Projektausrichtung.\n\n(c) Exkursion: Die Studierenden erforschen und verstehen durch direkte Erfahrungen vor Ort komplexe Konzepte und setzen diese anschließend praktisch um.\n\n--- Literature (EN) ---\nLiterature references will be issued for the respective topic at the beginning of the project.\n\n--- Literature (DE) ---\nLiteraturangaben werden zu dem jeweiligen Thema zu Beginn des Projektes ausgegeben.", "metadata": {"moduleNumber": "BCSIM 45", "moduleName": "Creative Project 4", "creditPoints": "5.0", "suggestedSemester": 4, "offeredInSeason": "summer_semester", "examType": "project", "heldInLanguage": "de", "reviserName": "Prof. Isolde Asal", "reviserEmail": "isolde.asal@hs-duesseldorf.de", "studyProgramId": 12, "source_type": "json"}}
{"id": "BCSIM_50.01", "text": "Title: Interdisciplinary Project 15CP\nModule Number: BCSIM 50.01\nCredits: 15.0 CP\nSemester: 5\nOffered In: winter_semester\nLanguage: de\nExam Type: project\nInstructor: Prof. Isolde Asal\n\n--- Goals (EN) ---\nDepending on the project orientation.\n\n--- Goals (DE) ---\nJe nach Projektausrichtung verschieden.\n\n--- Contents (EN) ---\nDepending on the project orientation.\n\n--- Contents (DE) ---\nJe nach Projektausrichtung verschieden.\n\n--- Literature (EN) ---\nLiterature references will be issued for the respective topic at the beginning of the project.\n\n--- Literature (DE) ---\nLiteraturangaben werden zu dem jeweiligen Thema zu Beginn des Projektes ausgegeben.", "metadata": {"moduleNumber": "BCSIM 50.01", "moduleName": "Interdisciplinary Project 15CP", "creditPoints": "15.0", "suggestedSemester": 5, "offeredInSeason": "winter_semester", "examType": "project", "heldInLanguage": "de", "reviserName": "Prof. Isolde Asal", "reviserEmail": "isolde.asal@hs-duesseldorf.de", "studyProgramId": 12, "source_type": "json"}}
{"id": "BCSIM_51.01", "text": "Title: Learning agency\nModule Number: BCSIM 51.01\nCredits: 10.0 CP\nSemester: 5\nOffered In: winter_semester\nLanguage: de\nExam Type: portfolio\nInstructor: Prof. Dr. rer. nat. Michael Marmann\n\n--- Goals (EN) ---\nThe students \n\n- know the typical work processes of a digital agency and apply them under largely real conditions \n- take on a role within the project that corresponds to their competencies and a typical job profile in an agency \n- learn to organize themselves, act independently and participate in team development processes \n- know the tools required for the different project phases and can apply them in a phase-specific manner\n- are familiar with agile process models and supporting tools and apply these in the context of teamwork \n- design and develop a digital media product or a digitally supported service in a team on the basis of a specific project assignment \n- can present the results of individual project phases and the overall result to internal or external clients\n\n--- Goals (DE) ---\nDie Studierenden \n\n- kennen die typischen Arbeitsprozesse einer Digitalagentur und wenden diese unter weitgehend realen Bedingungen an \n- nehmen innerhalb des Projektes eine ihren Kompetenzen entsprechende Rolle ein, die einem typischen Tätigkeitsprofil in einer Agentur entspricht \n- lernen, sich selbst zu organisieren, eigenverantwortlich zu handeln und an Teamentwicklungsprozessen teilzunehmen \n- kennen die für die unterschiedlichen Projektphasen notwendigen Werkzeuge und können diese phasenspezifisch anwenden\n- kennen agile Vorgehensmodelle sowie unterstützende Tools und wenden diese im Rahmen der Teamarbeit an \n- konzipieren und entwickeln im Team auf der Basis eines konkreten Projektauftrages ein digitales Medienprodukt oder eine digital gestützte Dienstleistung \n- können Ergebnisse einzelner Projektphasen und das Gesamtergebnis vor internen oder externen Auftraggebern präsentieren\n\n--- Contents (EN) ---\nThe learning agency module is a special type of project that is highly relevant for later professional life. The special feature is that students work in a team on concrete and practical customer solutions, just like in a real digital agency, from the initial idea through to implementation. \n\nThe client can be internal or external. To this end, students take on specific roles that correspond to real job profiles in agencies. For example, there will be sales-oriented students as well as project managers, concept developers, developers or designers. If several teams are formed, they will be in competition with each other. The solution to be developed will go through all phases of digital product development or an online communication project. Special emphasis is placed on agile project management methods.\n\n--- Contents (DE) ---\nBeim Modul Lernagentur handelt es sich um eine spezielle Projektform mit hoher Relevanz für das spätere Berufsleben. Die Besonderheit besteht darin, dass Studierende wie in einer realen Digitalagentur im Team an konkreten und praxisnahen Kundenlösungen arbeiten, und zwar von der ersten Idee bis zur Umsetzung. \n\nDabei kann der Auftraggeber intern oder extern sein. Hierzu nehmen die Studierenden bestimmte Rollen ein, die realen Tätigkeitsprofilen in Agenturen entsprechen. So wird es vertrieblich orientierte Studierende genauso geben, wie z.B. Projektmanager, Konzepter, Entwickler oder Designer. Sollten sich mehrere Teams formieren, dann stehen sie im Wettbewerb zueinander. Die zu erarbeitende Lösung durchläuft alle Phasen einer digitalen Produktentwicklung oder eines Online-Kommunikations-Projektes. Dabei wird besonderer Wert auf agile Projektmanagementmethoden gelegt.\n\n--- Literature (EN) ---\nCurrent literature references and sources of information are provided at the beginning of the module or directly from the course context, if necessary. In addition, digital media are increasingly used as a source of knowledge.\n\n--- Literature (DE) ---\nAktuelle Literaturhinweise und Informationsquellen werden, so-fern notwendig, zu Beginn des Moduls oder unmittelbar aus dem Veranstaltungskontext herausgegeben. Zusätzlich werden verstärkt digitale Medien als Wissensquelle eingesetzt.", "metadata": {"moduleNumber": "BCSIM 51.01", "moduleName": "Learning agency", "creditPoints": "10.0", "suggestedSemester": 5, "offeredInSeason": "winter_semester", "examType": "portfolio", "heldInLanguage": "de", "reviserName": "Prof. Dr. rer. nat. Michael Marmann", "reviserEmail": "marmann@hs-duesseldorf.de", "studyProgramId": 12, "source_type": "json"}}
{"id": "BCSIM_51.02", "text": "Title: Sustainable Entrepreneurship\nModule Number: BCSIM 51.02\nCredits: 5.0 CP\nSemester: 5\nOffered In: winter_semester\nLanguage: de\nExam Type: portfolio\nInstructor: Prof. Dr. rer. nat. Michael Marmann\n\n--- Goals (EN) ---\nAfter successfully completing the module, students will be able to work out the issues involved in a start-up project and explain the process of setting up a company. They will be able to differentiate between the individual process steps and classify them in the start-up process and identify and analyze problem areas of a start-up project and implement them in a solution-oriented manner. Furthermore, they can structure a start-up project, develop their own business ideas, critically reflect on them and implement them in a concrete business plan including comprehensive financial planning, as well as recognize, present and analyze internal and external influencing factors on the start-up process. You will be able to recognize and evaluate the opportunities and risks of setting up a business and develop, compare and evaluate financing solutions for start-up projects.\n\n--- Goals (DE) ---\nNach erfolgreicher Teilnahme an dem Modul sind die Studierenden in der Lage Fragestellungen eines Gründungsvorhabens zu erarbeiten und den Prozess der Unternehmensgründung zu erklären. Sie können die einzelnen Prozessschritte unterscheiden und in den Gründungsprozess einordnen und Problemfelder eines Gründungsvorhabens identifizieren, analysieren und lösungsorientiert umsetzen. Des Weiteren können sie ein Gründungsvorhaben strukturieren, eigene Geschäftsideen entwickeln, kritisch reflektieren und in eine konkrete Businessplanung inklusiv einer umfassenden Finanzplanung umsetzen, sowie interne und externe Einflussfaktoren auf den Gründungsprozess erkennen, darstellen und analysieren. Chancen und Risiken einer Existenzgründung können Sie erkennen und bewerten, Finanzierungslösungen für Gründungsvorhaben erarbeiten, vergleichen und werten.\n\n--- Contents (EN) ---\n- Process of a livelihood foundation,\n- Networks in the context of start-ups,\n- Potential investors for start-ups,\n- Financing of start-up projects via bank loans, leasing and venture capital, Public funding of start-ups,\n-Structure of business plans, annual planning (personnel planning; investment and depreciation planning; profit and loss plan; budgeted balance sheets; financial planning; liquidity planning),\n- Preparation of a comprehensive business plan,\n- current developments in the field of entrepreneurship\n\n--- Contents (DE) ---\n- Prozess einer Existenzgründung,\n- Netzwerke im Rahmen von Existenzgründungen,\n- Potentielle Kapitalgeber von Start-ups,\n- Finanzierung von Gründungsvorhaben über Bankkredite, Leasing und Venture Capital, Öffentliche Förderung von Start-Ups,\n- Struktur von Businessplänen, Fünf-Jahres-Planung (Personalplanung; Investitions- und Abschreibungsplanung; Plan Gewinn-und Verlustrechnung; Planbilanzen; Finanzierungsplanung; Liquiditätsplanung),\n- Erstellung eines umfassenden Businessplans,\n- aktuelle Entwicklungen im Bereich Entrepreneurship\n\n--- Literature (EN) ---\nWill be announced in course.\n\n--- Literature (DE) ---\nWird in der Veranstaltung bekannt gegeben.", "metadata": {"moduleNumber": "BCSIM 51.02", "moduleName": "Sustainable Entrepreneurship", "creditPoints": "5.0", "suggestedSemester": 5, "offeredInSeason": "winter_semester", "examType": "portfolio", "heldInLanguage": "de", "reviserName": "Prof. Dr. rer. nat. Michael Marmann", "reviserEmail": "marmann@hs-duesseldorf.de", "studyProgramId": 12, "source_type": "json"}}
{"id": "BCSIM_51.03", "text": "Title: Medien & IT-Recht\nModule Number: BCSIM 51.03\nCredits: 5.0 CP\nSemester: 5\nOffered In: winter_semester\nLanguage: de\nExam Type: written_exam\nInstructor: Prof. Dr. Alina Huldtgren\n\n--- Goals (EN) ---\nStudents know the tasks, objectives and key methods of organizing, managing and controlling IT projects. They will be able to analyze existing projects and plan simple projects. They know the essential legal framework conditions for the use of IT systems in business practice and can analyze and classify corresponding application examples.\n\n--- Goals (DE) ---\nDie Studierenden kennen die Aufgaben, Ziele und wesentliche Methoden der Organisation, Steuerung und Kontrolle von informatischen Projekten. Sie können bestehende Projekte analysieren und einfache Projekte planen. Sie kennen die wesentlichen rechtlichen Rahmenbedingungen beim Einsatz von Informatiksystemen in der wirtschaftlichen Praxis und können entsprechende Anwendungsbeispiele analysieren und einordnen.\n\n--- Contents (EN) ---\n- Special features of the conduct of proceedings and litigation in media and IT law\n- Basic features of contract law; basic features Law of electronic business transactions (online/mobile business)\n- Fundamentals of intellectual property law in the area of media and IT law\n- References to trademark law, in particular domain law, Copyright law and labor law\n- Photo/image law\n- Basic principles of data protection law\n- Competition law and advertising law aspects of media and media and IT law\n- Right of expression; liability of forum and rating rating platforms\n- Liability issues in media and IT law, in particular for Internet platforms and social networks\n\n--- Contents (DE) ---\n- Besonderheiten der Verfahrens- und Prozessführung im Medien- und IT-Recht\n-  Grundzüge Vertragsrecht; Grundzüge Recht des elektronischen Geschäftsverkehrs (Online-/Mobile Business)\n- Grundzuge des Immaterialgüterrechts im Bereich Medien und IT-Recht\n- Bezuge zum Kennzeichenrecht, insbesondere Domainrecht, Urheberrecht und Arbeitsrecht\n- Foto-/ Bild-Recht\n- Grundzuge im Recht des Datenschutzes\n- wettbewerbsrechtliche und werberechtliche Bezuge des Medien- und des IT-Rechts\n- Äußerungsrecht; Haftung von Foren- und Bewertungsplattformen\n- Haftungsfragen im Medien- und IT-Recht, insbesondere bei Internetplattformen sowie Sozialen Netzwerken\n\n--- Literature (EN) ---\n- K. Gennen, A. Völkel: Recht der IT-Verträge: Start ins Rechtsgebiet, C. F. Muller Verlag 2009\n- H.-J. Homann: Praxishandbuch Filmrecht: Ein Leitfaden für Film-, Fernseh- und Medienschaffende, Springer Verlag 2008\n- J. Schneider: IT- und Computerrecht, dtv 2016\n- Helmut Redeker, IT-Recht, CH Beck 2017\n\n--- Literature (DE) ---\n- K. Gennen, A. Völkel: Recht der IT-Verträge: Start ins Rechtsgebiet, C. F. Muller Verlag 2009\n- H.-J. Homann: Praxishandbuch Filmrecht: Ein Leitfaden für Film-, Fernseh- und Medienschaffende, Springer Verlag 2008\n- J. Schneider: IT- und Computerrecht, dtv 2016\n- Helmut Redeker, IT-Recht, CH Beck 2017", "metadata": {"moduleNumber": "BCSIM 51.03", "moduleName": "Medien & IT-Recht", "creditPoints": "5.0", "suggestedSemester": 5, "offeredInSeason": "winter_semester", "examType": "written_exam", "heldInLanguage": "de", "reviserName": "Prof. Dr. Alina Huldtgren", "reviserEmail": "alina.huldtgren@hs-duesseldorf.de", "studyProgramId": 12, "source_type": "json"}}
{"id": "BCSIM_60", "text": "Title: External Work\nModule Number: BCSIM 60\nCredits: 30.0 CP\nSemester: 6\nOffered In: summer_semester\nLanguage: de\nExam Type: oral_exam\nInstructor: Prof. Dr. Eng. Univ. of Tsukuba Jens Herder\n\n--- Goals (EN) ---\nThe students acquire the skills to find their way in a previously unknown environment and to be able to work constructively there. You can choose between a practical semester, a study semester abroad and a research semester.(a) A practical semester is based on the later occupational field for media technicians. The students are aware of operational processes and can handle the tasks of media technology according to their level of knowledge. In particular, they are aware of the importance of teamwork in connection with complex business operations.(b) Studying abroad conveys the competencies in the chosen courses in the fields of media technology, media computer science and cross-sectional qualifications, supplemented by the increased demands for independence through the stay abroad as well as the learning competence in a foreign language.(c) A research semester imparts scientific work and the competence to develop new solutions and evaluate them. In particular, they are aware of the importance of teamwork in connection with a complex research enterprise.\n\n--- Goals (DE) ---\nDie Studierenden erwerben die Fähigkeiten, sich in einer vorher unbekannten Umgebung zurecht zu finden und dort konstruktiv mitarbeiten zu können. Hierfür stehen zur Wahl ein Praxissemester, ein Auslandsstudiensemester und ein Forschungssemester. \n\n(a) Ein Praxissemester orientiert sich am späteren Berufsfeld für Medientechniker. Die Studierenden kennen betriebliche Prozesse und können ihnen gestellte Aufgaben der Medientechnik gemäß ihrem Kenntnisstand bearbeiten. Sie kennen insbesondere die Bedeutung von Teamarbeit im Zusammenhang mit einem komplexen Betriebsgeschehen.\n\n(b) Ein Auslandsstudium vermittelt die Kompetenzen in den gewählten Kursen aus den Bereichen Medientechnik, Medieninformatik und Querschnittsqualifikationen, ergänzt um die erhöhten Anforderungen an Selbständigkeit durch den Auslandsaufenthalt sowie die Lernkompetenz in einer Fremdsprache. \n\n(c) Ein Forschungssemester vermittelt wissenschaftliches Arbeiten und die Kompetenz zur Entwicklung von neuen Lösungen und Bewertung von diesen. Sie kennen insbesondere die Bedeutung von Teamarbeit im Zusammenhang mit einem komplexen Forschungsbetrieb.\n\n--- Contents (EN) ---\n(a) practical semester:The students orientate themselves later in their profession for media technicians, get to know operational processes and work on tasks they have set. To do this you conclude a contract with the practice office regarding the duration, tasks and support. Regular reports to be confirmed by the practice office inform and advise the supervising professor or supervisor.(b) study abroad semester:Students can organize and use international educational offers. In the global context, you can develop, formulate and present concepts for problems in media technology and media informatics.(c) Research semester:Students work in a research institute on theoretical and practical problems of media technology and media computer science. They learn the scientific work and are supervised by a professor or professor.\n\n--- Contents (DE) ---\n(a) Praxissemester: Die Studierenden orientieren sich im späteren Berufsfeld für Medientechniker, lernen betriebliche Prozesse kennen und bearbeiten ihnen gestellte Aufgaben. Sie schließen dazu mit der Praxisstelle einen Vertrag über die Zeitdauer, Aufgaben und Betreuung ab. Durch regelmäßige, von der Praxisstelle zu bestätigenden Berichten, wird der betreuende Professor oder die betreuende Professorin informiert und berät den Studierenden oder die Studierende. \n\n(b) Auslandsstudiensemester: Studierende können für sich internationale Bildungsangebote organisieren und nutzen. Im globalen Kontext können Sie für Problemstellungen der Medientechnik und Medieninformatik Konzepte entwickeln, formulieren und präsentieren. \n\n(c) Forschungssemester: Studierende arbeiten in einem Forschungsinstitut an theoretischen und praktischen Problemstellungen der Medientechnik und Medieninformatik. Sie lernen das wissenschaftliche Arbeiten und werden durch einen Professor oder Professorin betreut.\n\n--- Literature (EN) ---\nLiterature / sources vary depending on the practice location and the tasks set there and will be announced there.\n\n--- Literature (DE) ---\nLiteratur / Quellen sind je nach Praxisstelle und dortiger Aufgabenstellung verschieden und werden jeweils dort bekanntgegeben.", "metadata": {"moduleNumber": "BCSIM 60", "moduleName": "External Work", "creditPoints": "30.0", "suggestedSemester": 6, "offeredInSeason": "summer_semester", "examType": "oral_exam", "heldInLanguage": "de", "reviserName": "Prof. Dr. Eng. Univ. of Tsukuba Jens Herder", "reviserEmail": "jens.herder@hs-duesseldorf.de", "studyProgramId": 12, "source_type": "json"}}
{"id": "BCSIM_72.01", "text": "Title: Blue Science\nModule Number: BCSIM 72.01\nCredits: 5.0 CP\nSemester: 7\nOffered In: winter_semester\nLanguage: de\nExam Type: portfolio\nInstructor: Prof. Dr. Alina Huldtgren\n\n--- Goals (EN) ---\nAfter successfully completing the module, students are able to critically assess technology. They will be able to reflect on the interrelationship between technology, nature, the individual and society. They can cooperate with others for democratic decision-making with regard to process, result and implementation. They can cope with the decision-making dilemma arising from individual and social responsibility and anticipate the effects and risks of technology on nature and society.\n\n--- Goals (DE) ---\nNach erfolgreichem Abschluss des Moduls sind die\nStudierenden in der Lage, Technik kritisch zu beurteilen. Sie\nkönnen das Wechselverhältnis von Technik, Natur, Individuum\nund Gesellschaft reflektieren. Sie können mit anderen fur eine\ndemokratische Entscheidungsfindung im Hinblick auf Prozess,\nErgebnis und Umsetzung kooperieren. Das Entscheidungsdilemma,\ndas sich aus individueller und gesellschaftlicher\nVerantwortung ergibt, können sie bewältigen.\nAuswirkungen und Risiken von Technik auf Natur und\nGesellschaft können antizipiert werden.\n\n--- Contents (EN) ---\nTechnology as a problem solver? Critical theory and its application to technology\n- Plastic and its local and global effects\n- Social and ecological dimensions of technology\n- Ambivalences of technological developments  Concepts of alternative economic enterprises, such as e.g. cooperatives\n- Career and career entry, working conditions and trade unions\n- Company organization\n- Social significance of computer science\n- Responsible action in the development of technology\n\n--- Contents (DE) ---\nTechnik als Problemlöser!? Kritische Theorie und ihre Anwendung auf Technik\n- Plastik und seine lokalen und globalen Auswirkungen\n- Soziale und Ökologische Dimension von Technik\n- Ambivalenzen technologischer Entwicklungen \n- Konzepte alternativer wirtschaftender Unternehmen, wie z.B. Genossenschaften\n- Beruf und Berufseinstieg, Arbeitsbedingungen und Gewerkschaften\n- Betriebliche Organisation\n- Gesellschaftliche Bedeutung der Informatik\n- Verantwortungsvolles Handeln in der Technikentwicklung\n\n--- Literature (EN) ---\n- DEMIROVI, Alex. Demokratie in der Wirtschaft: Positionen-Probleme-Perspektiven. Westfälisches Dampfboot, 2007.\n- HÄNGGI, Marcel. Fortschrittsgeschichten: für einen guten Umgang mit Technik. S. Fischer Verlag, 2015.\n- KORNWACHS, Klaus: Philosophie für Ingenieure. Hanser, 2018.\n- NOBLE, David F. Forces of production: A social history of industrial automation. Alfred A. Knopf, 1984.\n- SCHEIDLER, Fabian. Das Ende der Megamaschine: Geschichte einer scheiternden Zivilisation. Promedia, 2015.\n-  ULLRICH, Otto. Technik und Herrschaft: vom Handwerk zur verdinglichten Blockstruktur industrieller Produktion. Suhrkamp, 1979.\n\n--- Literature (DE) ---\n- DEMIROVI, Alex. Demokratie in der Wirtschaft: Positionen-Probleme-Perspektiven. Westfälisches Dampfboot, 2007.\n- HÄNGGI, Marcel. Fortschrittsgeschichten: für einen guten Umgang mit Technik. S. Fischer Verlag, 2015.\n- KORNWACHS, Klaus: Philosophie für Ingenieure. Hanser, 2018.\n- NOBLE, David F. Forces of production: A social history of industrial automation. Alfred A. Knopf, 1984.\n- SCHEIDLER, Fabian. Das Ende der Megamaschine: Geschichte einer scheiternden Zivilisation. Promedia, 2015.\n-  ULLRICH, Otto. Technik und Herrschaft: vom Handwerk zur verdinglichten Blockstruktur industrieller Produktion. Suhrkamp, 1979.", "metadata": {"moduleNumber": "BCSIM 72.01", "moduleName": "Blue Science", "creditPoints": "5.0", "suggestedSemester": 7, "offeredInSeason": "winter_semester", "examType": "portfolio", "heldInLanguage": "de", "reviserName": "Prof. Dr. Alina Huldtgren", "reviserEmail": "alina.huldtgren@hs-duesseldorf.de", "studyProgramId": 12, "source_type": "json"}}
{"id": "BCSIM_70", "text": "Title: Bachelor Research / Bachelor Project\nModule Number: BCSIM 70\nCredits: 10.0 CP\nSemester: 7\nOffered In: winter_semester\nLanguage: en_on_demand\nExam Type: portfolio\nInstructor: Prof. Dr. Alina Huldtgren\n\n--- Goals (EN) ---\n\n\n--- Goals (DE) ---\nzu a)\nDie Studierenden kennen die Grundlagen des wissenschaftlichen Arbeitens inklusive Plagiatsvermeidung. Sie können eine wissenschaftliche Recherche auf Basis von Datenbanken durchführen und adäquate Treffer auswählen sowie diese in einer schriftlichen Ausarbeitung verwalten und anwenden. Somit beherrschen Sie den Umgang mit wissenschaftlichen Informationsquellen (sowohl deutsch- als auch englischsprachig), können diese korrekt zitieren und sie dazu nutzen, den Stand der Forschung und Technik zu ermitteln sowie eigene Aufgabenstellungen zu analysieren und zu planen. Die Studierenden sind in der Lage eigene Arbeiten im Kontext des fachlichen Umfeldes zu sehen und in angemessener Form schriftlich und mündlich darüber zu kommunizieren.  \n\nzu b)\nStudierenden sollen eine umfassende Aufgabe der Untersuchung, Entwicklung und Gestaltung digitaler Medien und ihres Gebrauchs angehen können. Dabei wird die systematische, ingenieurmäßige bzw. künstlerisch-gestalterische Entwicklung von Kreativen, Synthetischen und/oder Interaktiven Medien angewendet, wie auch die Grundprinzipien des Agilen Projektmanagements. Die Lernform ist die eines Projektes, das von den Studierenden selbst organisiert werden kann und vom jeweiligen Lehrenden des Moduls inhaltlich und betreuend begleitet wird. Die fachlichen Ziele sind projektspezifisch und können daher nicht allgemein beschrieben werden.\n\n--- Contents (EN) ---\n\n\n--- Contents (DE) ---\nDie Studierenden bearbeiten unter Anleitung für ein spezielles Thema aus dem Bereich Creative, Synthetic und/oder Interactive Media als Vorbereitung auf die Abschlussarbeit entweder eine \n\"a) Wissenschaftliche Vertiefung (Bachelor Research)\" \noder eine \n\"b) Projektaufgabe (Bachelor Project)\".\n\nzu a) \nfolgende Aufgaben gehören u.a. zu einer Wissenschaftlichen Vertiefung:\n- Einarbeitung in die Aufgabenstellung  \n- Aspekte für eine effiziente wissenschaftliche Recherche (wissenschaftliche Veröffentlichungen, Fachbücher, Standards, etc.) \n- Inhaltliche Analyse der Informationsquellen\n- Einhaltung der guten wissenschaftlichen Praxis\n- Zitierweise und Zitationsstile-\n- Plagiatsvermeidungsstrategie\n- Zusammenstellung der Ergebnisse in einer Hausarbeit inkl. qualitative und formal entsprechende Literaturlisten\n- Präsentation des Themas in einem Referat \n\nzu b) \nAn einem gesellschaftlich, wissenschaftlich oder künstlerisch-gestalterisch bedeutsamen Thema werden erlernt und geübt: \n- Problemanalyse \n- Zielfindung \n- theoretische Überlegungen \n- Lösungskonzept bzw. Spezifikation \n- praktische Ausarbeitung \n- kritische Reflexion bzw. Evaluation von Ergebnissen \nDie fachlichen Inhalte sind projektspezifisch und können daher nicht allgemein beschrieben werden.\n\n--- Literature (EN) ---\n\n\n--- Literature (DE) ---\nzu a) und b)\nDie Literatur ist abhängig von der Aufgabenstellung und wird zu Beginn der Lehrveranstaltung bekannt gegeben bzw. sich selbst erarbeitet.", "metadata": {"moduleNumber": "BCSIM 70", "moduleName": "Bachelor Research / Bachelor Project", "creditPoints": "10.0", "suggestedSemester": 7, "offeredInSeason": "winter_semester", "examType": "portfolio", "heldInLanguage": "en_on_demand", "reviserName": "Prof. Dr. Alina Huldtgren", "reviserEmail": "alina.huldtgren@hs-duesseldorf.de", "studyProgramId": 12, "source_type": "json"}}
{"id": "BCSIM_71", "text": "Title: Bachelor Thesis & Colloquium\nModule Number: BCSIM 71\nCredits: 15.0 CP\nSemester: 7\nOffered In: winter_semester\nLanguage: en_on_demand\nExam Type: bachelor_thesis_and_colloquium\nInstructor: Prof. Dr. Alina Huldtgren\n\n--- Goals (EN) ---\n\n\n--- Goals (DE) ---\nDie Studierenden können selbstständig eine Aufgabenstellung aus einem der drei Skill-Cluster mit wissenschaftlichen und/oder gestalterischen Mitteln mit Zeitbeschränkung unter Anleitung des/ der Dozenten/ in bearbeiten. \n\nDas Kolloquium dient der Feststellung, ob die Kandidatin / der Kandidat befähigt ist, die Ergebnisse der Bachelor-Thesis, ihre fachlichen Grundlagen, ihre fächerübergreifenden Zusammenhänge und ihre außerfachlichen Bezüge mündlich darzustellen und selbstständig zu begründen und ihre Bedeutung für die Praxis einzuschätzen.\n\n--- Contents (EN) ---\n\n\n--- Contents (DE) ---\nDie Bachelor-Thesis ist der Abschluss des Bachelorstudiums. In ihr werden die erworbenen Kompetenzen des Studium in einer eigenständigen, theoretischen und/oder gestalterischen Arbeit zusammengeführt und dokumentiert. Die Ergebnisse werden präsentiert und in einem prüfenden Kolloquium diskutiert und verteidigt. \n\nDie Studierenden dokumentieren mit der Bachelor-Thesis ihre Kompetenzen zur Entwicklung, Analyse und Formulierung einer eigenständigen komplexen Fragestellung und Thematik. Sie können diese mit wissenschaftlichen und/oder gestalterischen Methoden durchdringen und sie zu einer eigenständigen Lösung bringen. \n\nSie dokumentieren und vermitteln ihre erworbenen gestalterischen und wissenschaftlich Kompetenzen und methodischen Fertigkeiten, die sie im Rahmen eines Kolloquiums verteidigen. Sie können ihre fachlichen Entscheidungen vor einem wissenschaftlichen und/oder gestaltungsmethodischen Hintergrund kritisch reflektieren, in gesellschaftliche und wissenschaftliche Diskurse einbetten.\n\n--- Literature (EN) ---\n\n\n--- Literature (DE) ---\nLiteratur / Quellen sind je nach Aufgabenstellung verschieden und werden durch den jeweiligen Betreuer / die jeweilige Betreuerin bekannt gegeben.", "metadata": {"moduleNumber": "BCSIM 71", "moduleName": "Bachelor Thesis & Colloquium", "creditPoints": "15.0", "suggestedSemester": 7, "offeredInSeason": "winter_semester", "examType": "bachelor_thesis_and_colloquium", "heldInLanguage": "en_on_demand", "reviserName": "Prof. Dr. Alina Huldtgren", "reviserEmail": "alina.huldtgren@hs-duesseldorf.de", "studyProgramId": 12, "source_type": "json"}}
{"id": "BCSIM_304", "text": "Title: Design Basics 3: Objects\nModule Number: BCSIM 304\nCredits: 5.0 CP\nSemester: 3\nOffered In: winter_semester\nLanguage: de\nExam Type: portfolio\nInstructor: Prof. Gabriele Schwab-Trapp\n\n--- Goals (EN) ---\nStudents learn the conception and prototyping of simple handcrafted, two- and three-dimensional objects through to realisation with the help of rapid prototyping and various technical production options such as 3D printing and laser cutting.\nThey develop skills in spatial-object-related design thinking and learn methods and processes to independently solve spatial-object-related tasks.\n\n--- Goals (DE) ---\nStudierende lernen Konzeption und Prototyping von einfachen handwerklichen, zwei-und dreidimensionalen Objekten bis zu Umsetzung mit Hilfe von Rapid Prototyping und verschiedenen technischen Fertigungsmöglichkeiten wie z.B. 3D-Druck und Lasercut.\nSie entwickeln Fähigkeiten in räumlich-objektbezogenem Entwurfsdenken und lernen Methoden und Prozesse, um eigenständig räumlich-objektbezogene Aufgabenstellungen zu lösen.\n\n--- Contents (EN) ---\nIn terms of content, basic knowledge and skills in the field of three-dimensional and spatial-sculptural design are taught. These include theoretical, aesthetic and design fundamentals as well as experimental material experience and 3D design methods. In addition to theoretical questions, everyday objects, spatial models or spatial installations can be the subject of investigation.\n\n--- Contents (DE) ---\nInhaltlich werden grundlegende Kenntnisse und Fähigkeiten im Bereich der dreidimensionalen und räumlich-plastischen Formgestaltung vermittelt. Diese umfasen theoretische, ästhetische und gestalterische Grundlagen sowie experimentelle Materialerfahrung und 3D-Gestaltungsmethoden. Untersuchende Auseinandersetzung können neben theoretischen Fragen, Alltagsobjekte, räumliche Modelle oder Rauminstallationen thematisieren.\n\n--- Literature (EN) ---\nMaterial and literature references are provided for the respective topic in the seminar. Information in the form of text extracts, literature, image examples and research suggestions are provided to support the respective learning, realisation and design steps.\n\n--- Literature (DE) ---\nMaterial- und Literaturangaben werden zu dem jeweiligen Thema im Seminar ausgegeben. Zur Unterstützung der jeweiligen Lern-, Erkenntnis- und Gestaltungsschritte werden Hinweise in Form von Textauszügen, Literatur, Bildbeispielen und Recherchevorschlägen gegeben.", "metadata": {"moduleNumber": "BCSIM 304", "moduleName": "Design Basics 3: Objects", "creditPoints": "5.0", "suggestedSemester": 3, "offeredInSeason": "winter_semester", "examType": "portfolio", "heldInLanguage": "de", "reviserName": "Prof. Gabriele Schwab-Trapp", "reviserEmail": "gabi.schwab-trapp@hs-duesseldorf.de", "studyProgramId": 12, "source_type": "json"}}
{"id": "BCSIM_103", "text": "Title: Metathematisches Storytelling\nModule Number: BCSIM 103\nCredits: 5.0 CP\nSemester: 3\nOffered In: winter_semester\nLanguage: de\nExam Type: portfolio\nInstructor: Prof. Gabriele Schwab-Trapp\n\n--- Goals (EN) ---\nStudents acquire skills in the conceptual handling of free or applied topics and the ability to independently develop context-related content. The development and practical realisation of their own ideas is made possible with the help of design processes. Experience in interdisciplinary, creative and constructive collaboration is gained within the seminar and possible project groups as well as in dealing with various forms of presentation.\n\n--- Goals (DE) ---\nDie Studierenden erwerben Fähigkeiten im konzeptionellen Umgang mit freien oder angewandten Themen und die Befähigung zur selbstständigen Erarbeitung von kontextbezogenen Inhalten. Mithilfe von Gestaltungsprozessen werden die Entwicklung und die praktische Umsetzung eigener Ideen ermöglicht. Erfahrungen in interdisziplinärer, kreativer und konstruktiver Zusammenarbeit werden innerhalb der Seminar- und möglicher Projektgruppen sowie im Umgang mit verschiedenen Präsentationsformen gesammelt.\n\n--- Contents (EN) ---\nFree or applied topics are dealt with, which are presented at the beginning of the semester. The joint deepening, development and unfolding of the topic takes place in seminar form. This also includes philosophical, knowledge-orientated and opinion-forming discussions. The aim is the independent development and realisation of context-related, visual concepts in various media. Various forms of presentation are practised according to the topics and results. Excursions may take place to support the topics, which will be announced at the beginning of the semester.\nThe module is regularly offered on an open, collaborative and interdisciplinary basis with students from other subject areas.\n\nSuitable advanced tasks are assigned for Master's students.\n\n--- Contents (DE) ---\nInhaltlich werden freie oder angewandte Themen behandelt, die zu Beginn des Semesters vorgestellt werden. Die gemeinsame Vertiefung, Entwicklung und Entfaltung des Themas findet in Seminarform statt. Dazu gehört auch die philosophische, erkenntnisorientierte und meinungsbildende Auseinandersetzung. Ziel ist die selbstständige Entwicklung und Umsetzung von kontextbezogenen, visuellen Konzepten in unterschiedlichen Medien. Den Themen und Ergebnissen entsprechend werden verschiedene Präsentationsformen eingeübt. Themenunterstützend können Exkursionen stattfinden, die zu Beginn des Semesters bekannt gegeben werden.\nDas Modul wird regelmäßig offen, kollaborativ und interdisziplinär mit Studierenden aus anderen Fachbereichen angeboten.\n\nFür Master-Studierende werden geeignete, fortgeschrittene Aufgaben vergeben.\n\n--- Literature (EN) ---\nMaterial and literature references are provided for the respective topic in the seminar. Information in the form of text extracts, literature, image examples and research suggestions are provided to support the respective learning, realisation and design steps.\n\n--- Literature (DE) ---\nMaterial- und Literaturangaben werden zu dem jeweiligen Thema im Seminar ausgegeben. Zur Unterstützung der jeweiligen Lern-, Erkenntnis- und Gestaltungsschritte werden Hinweise in Form von Textauszügen, Literatur, Bildbeispielen und Recherchevorschlägen gegeben.", "metadata": {"moduleNumber": "BCSIM 103", "moduleName": "Metathematisches Storytelling", "creditPoints": "5.0", "suggestedSemester": 3, "offeredInSeason": "winter_semester", "examType": "portfolio", "heldInLanguage": "de", "reviserName": "Prof. Gabriele Schwab-Trapp", "reviserEmail": "gabi.schwab-trapp@hs-duesseldorf.de", "studyProgramId": 12, "source_type": "json"}}
{"id": "BCSIM_100", "text": "Title: Crossmedia Production & Campaigns 1\nModule Number: BCSIM 100\nCredits: 5.0 CP\nSemester: 3\nOffered In: winter_semester\nLanguage: de\nExam Type: project\nInstructor: Prof. Isolde Asal\n\n--- Goals (EN) ---\nStudents have the knowledge and skills to integrate different media assets into interactive cross-media applications in terms of content, dramaturgy and with the help of new technologies. \nThey know the specific creative and associative design levels and design elements of the various individual media and apply these in a target-oriented manner when implementing cross-media projects. This also includes competence in usability and consistent user guidance. In addition to a high level of design competence, students master the practical and technical handling of cross-media composition. They can also investigate new forms of digital, cross-media productions and test them with contemporary video and online-based technologies.\n\n--- Goals (DE) ---\nDie Studierenden besitzen Kenntnisse und beherrschen Fertigkeiten, mit deren Hilfe sie unterschiedliche Medienassets inhaltlich, dramaturgisch und mit Hilfe neuer Technologien in interaktive Crossmedia-Applikationen integrieren können. \nSie kennen die spezifischen kreativen und assoziativen Gestaltungsebenen und Gestaltungselemente der verschiedenen Einzelmedien und wenden diese zielorientiert bei der Umsetzung in Crossmediaprojekten an. Dies beinhaltet auch die Kompetenz in Usability und konsistenter Benutzerführung. Die Studierenden beherrschen neben einer hohen Gestaltungskompetenz die praktische und technische Handhabung der crossmedialen Komposition. Sie können darüber weiterhin neue Formen digitaler, crossmedialer Produktionen untersuchen und auch mit den zeitgenössischen Video- und onlinebasierten Technologien erproben.\n\n--- Contents (EN) ---\nStudents learn the theory and practice of interactive cross-media productions, including planning, design and distribution of cross-media content, as well as the workflow of film and media production, asset planning, web-based distribution and user guidance.\n\n- Theory and practice of interactive cross-media productions\n- Planning & design of cross-media content\n- Film & media production workflow (creation and conception, production, camera, editing/post-production)\n- Asset planning and asset creation\n- Conception of web-based distribution and consistent user guidance/usability\n- Distribution of digital online content\n\n--- Contents (DE) ---\nDie Studierenden erlernen die Theorie und Praxis interaktiver Crossmediaproduktionen, inklusive Planung, Gestaltung und Distribution von crossmedialem Content, sowie den Workflow der Film- und Medienproduktion, Assetplanung, webbasierte Verbreitung und Benutzerführung.\n\n- Theorie und Praxis interaktiver Crossmediaproduktionen\n- Planung & Gestaltung von crossmedialem Content\n- Workflow Film- & Medienproduktion (Kreation und Konzeption, Produktion, Kamera, Montage/ Postproduktion)\n- Assetplanung und Asseterstellung\n- Konzeption von webbasierter Verbreitung und konsistenter Benutzerführung/Usability\n- Distribution von digitalem Online-Content\n\n--- Literature (EN) ---\n- N. Mahrdt: Crossmedia - Werbekampagnen erfolgreich planen und umsetzen, Springer Gabler, 2009\n- N. Schulz-Bruhdoel: Medienarbeit 2.0, Cross-MediaLösungen, Das Praxisbuch für PR und Journalismus von morgen, Frankfurter Allgemeine Buch, 2009\n- G. Schweiger: Praxishandbuch Werbung, UVK-Verlagsgesellschaft, 2013\n- Steven D. Katz: Die richtige Einstellung - Shot by shot, Zweitausendeins, 1999\n- P. Kandorfer: Lehrbuch der Filmgestaltung, Schiele und Schön, 2010\n- J. Monaco: Film verstehen, Rowohlt-Taschenbuch-Verl., 2001\n- S. Drate, D. Robbins, J. Salavetz: Motion by Design, Laurence King Publishing, 2006\n- M. Wäger: Grafik und Gestaltung, Galileo Press, 2010\n- M. Diefenbach: Workbook visuelles Denken: Ideen, Generieren, Kundenskizzen Anfertigen, Scribbles schnell gestalten, Books on Demand, 2013\n- G. Christiano: Storyboard Design, Stiebner Verlag, 2008\n- W. Faulstich: Grundkurs Filmanalyse, UTB Verlag, 2008\n- F. Hartmann: Globale Medienkultur: Technik, Geschichte, Theorien, UTB Verlag, 2006\n- D. Liebsch: Philosophie des Films, Mentis Verlag, 2005\n- W. Kamp: AV-Mediengestaltung Grundwissen, Europa-Lehrmittel Verlag, 2010\n- W. Murch: Ein Lidschlag, Ein Schnitt, Alexander Verlag, 2009\n- B. Ottersbach, T. Schadt: Filmschnitt-Bekenntnisse, UVK Verlag, 2009\n- M. A. Herzog: Generische Transformation von Multimedia-Content: Prozessautomatisierung am Beispiel von interaktivem Fernsehen und E-Learning-Anwendungen, Wissenschaftsverlag, 2010\n- K. Beck: Kommunikationswissenschaft, UTB Verlag, 2007\n- A. Grabs, K. Bannour, E. Vogl: Follow me!: Erfolgreiches Social Media Marketing, Rheinwerk Verlag, 2021\n- C. Beyer: Kongruenz in der Crossmedia-Kommunikation: Eine Untersuchung der Determinanten und Wirkungen, Springer, 2020\n- C. Pahrmann, K. Kupka, T. Schwenke: Social Media Marketing: Praxishandbuch für Facebook, Instagram, TikTok & Co, OReilly, 2022\n- M. Löffler, I. Michl: Think Content!: Erfolgreiches Content-Marketing, Rheinwerk Verlag, 2024\n\n--- Literature (DE) ---\n- N. Mahrdt: Crossmedia - Werbekampagnen erfolgreich planen und umsetzen, Springer Gabler, 2009\n- N. Schulz-Bruhdoel: Medienarbeit 2.0, Cross-MediaLösungen, Das Praxisbuch für PR und Journalismus von morgen, Frankfurter Allgemeine Buch, 2009\n- G. Schweiger: Praxishandbuch Werbung, UVK-Verlagsgesellschaft, 2013\n- Steven D. Katz: Die richtige Einstellung - Shot by shot, Zweitausendeins, 1999\n- P. Kandorfer: Lehrbuch der Filmgestaltung, Schiele und Schön, 2010\n- J. Monaco: Film verstehen, Rowohlt-Taschenbuch-Verl., 2001\n- S. Drate, D. Robbins, J. Salavetz: Motion by Design, Laurence King Publishing, 2006\n- M. Wäger: Grafik und Gestaltung, Galileo Press, 2010\n- M. Diefenbach: Workbook visuelles Denken: Ideen, Generieren, Kundenskizzen Anfertigen, Scribbles schnell gestalten, Books on Demand, 2013\n- G. Christiano: Storyboard Design, Stiebner Verlag, 2008\n- W. Faulstich: Grundkurs Filmanalyse, UTB Verlag, 2008\n- F. Hartmann: Globale Medienkultur: Technik, Geschichte, Theorien, UTB Verlag, 2006\n- D. Liebsch: Philosophie des Films, Mentis Verlag, 2005\n- W. Kamp: AV-Mediengestaltung Grundwissen, Europa-Lehrmittel Verlag, 2010\n- W. Murch: Ein Lidschlag, Ein Schnitt, Alexander Verlag, 2009\n- B. Ottersbach, T. Schadt: Filmschnitt-Bekenntnisse, UVK Verlag, 2009\n- M. A. Herzog: Generische Transformation von Multimedia-Content: Prozessautomatisierung am Beispiel von interaktivem Fernsehen und E-Learning-Anwendungen, Wissenschaftsverlag, 2010\n- K. Beck: Kommunikationswissenschaft, UTB Verlag, 2007\n- A. Grabs, K. Bannour, E. Vogl: Follow me!: Erfolgreiches Social Media Marketing, Rheinwerk Verlag, 2021\n- C. Beyer: Kongruenz in der Crossmedia-Kommunikation: Eine Untersuchung der Determinanten und Wirkungen, Springer, 2020\n- C. Pahrmann, K. Kupka, T. Schwenke: Social Media Marketing: Praxishandbuch für Facebook, Instagram, TikTok & Co, OReilly, 2022\n- M. Löffler, I. Michl: Think Content!: Erfolgreiches Content-Marketing, Rheinwerk Verlag, 2024", "metadata": {"moduleNumber": "BCSIM 100", "moduleName": "Crossmedia Production & Campaigns 1", "creditPoints": "5.0", "suggestedSemester": 3, "offeredInSeason": "winter_semester", "examType": "project", "heldInLanguage": "de", "reviserName": "Prof. Isolde Asal", "reviserEmail": "isolde.asal@hs-duesseldorf.de", "studyProgramId": 12, "source_type": "json"}}
{"id": "BCSIM_311", "text": "Title: Discursive Design and Future Visions\nModule Number: BCSIM 311\nCredits: 5.0 CP\nSemester: 4\nOffered In: winter_semester\nLanguage: de\nExam Type: portfolio\nInstructor: Prof. Gabriele Schwab-Trapp\n\n--- Goals (EN) ---\nStudents recognise the connection between design, technology, science and shaping the future. They are able to critically reflect on design concepts and their effects and can utilise speculative design strategies as a method for generating creative and sustainable ideas. They are able to apply and categorise the research potential of design.\n\n--- Goals (DE) ---\nDie Studierenden erkennen den Zusammenhang zwischen Design, Technik, Wissenschaft und Zukunftsgestaltung. Sie sind in der Lage Gestaltungskonzepte und deren Auswirkungen kritisch zu reflektieren und können den Einsatz spekulativer Designstrategien als Methode zur Erzeugung kreativer und nachhaltiger Ideen nutzen. Sie sind in der Lage das Forschungspotenzial durch Gestaltung anzuwenden und einzuordnen.\n\n--- Contents (EN) ---\nStudents are encouraged to engage analytically, theoretically and practically with concepts such as \"Design Fiction\", \"Critical Design\" and \"Speculative Design\". The focus is on the critical examination of current developments in science, technology, design and communication and their potential impact on society.\nOn this basis, possible future scenarios are to be developed and told in free narratives. Through the creative fusion of scientific knowledge and narrative elements, combined with practical applications, alternative realities can be explored and discussions stimulated that promote critical thinking. This integrative approach allows research through design to be trialled, using design as a tool to explore and deepen understanding of current issues and potential future scenarios. The aim is to identify the opportunities and challenges that designers and product developers face when dealing with increasingly complex and urgent social, political and environmental issues.\nThe theoretical discussion includes design and media history, design and media theory, as well as categorisation in the context of social developments.\n\nTranslated with DeepL.com (free version)\n\n--- Contents (DE) ---\nDie Studierenden werden dazu angeleitet, sich analytisch, theoretisch und praktisch mit Konzepten wie \"Design Fiction\", \"Critical Design\" und \"Speculative Design\" auseinanderzusetzen. Der Schwerpunkt liegt auf der kritischen Untersuchung aktueller Entwicklungen in Wissenschaft, Technik, Design und Kommunikation sowie deren potenziellen Auswirkungen auf die Gesellschaft. \n\nAuf dieser Basis sollen mögliche Zukunftsszenarien entwickelt werden, die in freien Narrativen erzählt werden. Durch die kreative Verschmelzung von wissenschaftlichem Wissen und erzählerischen Elementen, verknüpft mit praktischen Anwendungen, können alternative Realitäten erforscht und Diskussionen angeregt werden, die kritische Denkweisen fördern. Dieser integrative Ansatz ermöglicht es, Forschung durch Gestaltung zu erproben, bei dem Design als Instrument zur Erforschung und Vertiefung des Verständnisses aktueller Themen und potenzieller Zukunftsszenarien dient. Dabei sollen Möglichkeiten und Herausforderungen aufzeigt werden, denen sich GestalterInnen und ProduktentwicklerInnen stellen müssen, wenn sie sich mit immer komplexeren und dringlicheren sozialen, politischen und ökologischen Themen auseinandersetzen.\n\nZu der theoretischen Auseinandersetzung gehören Design- und Mediengeschichte, Design- und Medientheorie, sowie die Einordnung in gesellschaftliche Entwicklungen.\n\n--- Literature (EN) ---\nMaterial and literature references are provided for the respective topic in the seminar. Information in the form of text extracts, literature, image examples and research suggestions are provided to support the respective learning, realisation and design steps.\n\n--- Literature (DE) ---\nMaterial- und Literaturangaben werden zu dem jeweiligen Thema im Seminar ausgegeben. Zur Unterstützung der jeweiligen Lern-, Erkenntnis- und Gestaltungsschritte werden Hinweise in Form von Textauszügen, Literatur, Bildbeispielen und Recherchevorschlägen gegeben.", "metadata": {"moduleNumber": "BCSIM 311", "moduleName": "Discursive Design and Future Visions", "creditPoints": "5.0", "suggestedSemester": 4, "offeredInSeason": "winter_semester", "examType": "portfolio", "heldInLanguage": "de", "reviserName": "Prof. Gabriele Schwab-Trapp", "reviserEmail": "gabi.schwab-trapp@hs-duesseldorf.de", "studyProgramId": 12, "source_type": "json"}}
{"id": "BCSIM_104", "text": "Title: Crossmedia Production & Campaigns 2\nModule Number: BCSIM 104\nCredits: 5.0 CP\nSemester: 4\nOffered In: summer_semester\nLanguage: de\nExam Type: project\nInstructor: Prof. Isolde Asal\n\n--- Goals (EN) ---\nDeepening and supplementing the basic knowledge from Crossmedia Production & Campaigns 1\n\nStudents deepen their knowledge and master skills with the help of which they can integrate different media assets in terms of content, dramaturgy and with the help of new technologies in interactive cross-media applications. They know the specific technical and associative design levels and design elements of the various\nmedia and apply these in a target-oriented manner when implementation in cross-media projects. This also includes competence in usability and consistent user guidance. In addition to a high level of design competence, students master the practical and technical handling of cross-media composition. They can also investigate new forms of digital, cross-media productions and test them with contemporary video and online-based technologies.\n\n--- Goals (DE) ---\nVertiefung und Ergänzung der Grundlagenkenntnisse aus Crossmedia Production & Campaigns 1\n\nDie Studierenden vertiefen die Kenntnisse und beherrschen Fertigkeiten, mit deren Hilfe sie unterschiedliche Medienassets inhaltlich, dramaturgisch und mit Hilfe neuer Technologien in interaktive Crossmedia-Applikationen integrieren können. Sie kennen die spezifischen technischen und assoziativen Gestaltungsebenen und Gestaltungselemente der verschiedenen Einzelmedien und wenden diese zielorientiert bei der Umsetzung in Crossmediaprojekten an. Dies beinhaltet auch die Kompetenz in Usability und konsistenter Benutzerführung. Die Studierenden beherrschen neben einer hohen Gestaltungskompetenz die praktische und technische Handhabung der crossmedialen Komposition. Sie können darüber weiterhin neue Formen digitaler, crossmedialer Produktionen untersuchen und auch mit den zeitgenössischen Video- und onlinebasierten Technologien erproben.\n\n--- Contents (EN) ---\nBuilding on and complementing the Crossmedia Production & Campaigns 1 module\n\n- Theory and practice of interactive cross-media productions\n- Film & media production workflow (conception, production, camera, editing/post-production)\n- Asset planning and asset creation\n- Technical realization of devices\n- Cross-media content development (print, online, AV)\n- Conception of web-based distribution and consistent user guidance/usability\n- Distribution of digital online content\n\n--- Contents (DE) ---\nAufbauend und ergänzend zum Modul Crossmedia Production & Campaigns 1\n\n- Theorie und Praxis interaktiver Crossmediaproduktionen\n- Workflow Film- & Medienproduktion (Konzeption, Produktion, Kamera, Montage/Postproduktion)\n- Assetplanung und Asseterstellung\n- Gerätetechnische Realisierungen\n- Crossmediale Contententwicklung (Print, Online, AV)\n- Konzeption von webbasierter Verbreitung und konsistenter Benutzerführung/Usability\n- Distribution von digitalem Online-Content\n\n--- Literature (EN) ---\n- N. Mahrdt: Crossmedia - Werbekampagnen erfolgreich planen und umsetzen, Springer Gabler, 2009\n- N. Schulz-Bruhdoel: Medienarbeit 2.0, Cross-MediaLösungen, Das Praxisbuch für PR und Journalismus von morgen, Frankfurter Allgemeine Buch, 2009\n- G. Schweiger: Praxishandbuch Werbung, UVK-Verlagsgesellschaft, 2013\n- Steven D. Katz: Die richtige Einstellung - Shot by shot, Zweitausendeins, 1999\n- P. Kandorfer: Lehrbuch der Filmgestaltung, Schiele und Schön, 2010\n- J. Monaco: Film verstehen, Rowohlt-Taschenbuch-Verl., 2001\n- S. Drate, D. Robbins, J. Salavetz: Motion by Design, Laurence King Publishing, 2006\n- M. Wäger: Grafik und Gestaltung, Galileo Press, 2010\n- M. Diefenbach: Workbook visuelles Denken: Ideen, Generieren, Kundenskizzen Anfertigen, Scribbles schnell gestalten, Books on Demand, 2013\n- G. Christiano: Storyboard Design, Stiebner Verlag, 2008\n- W. Faulstich: Grundkurs Filmanalyse, UTB Verlag, 2008\n- F. Hartmann: Globale Medienkultur: Technik, Geschichte, Theorien, UTB Verlag, 2006\n- D. Liebsch: Philosophie des Films, Mentis Verlag, 2005\n- W. Kamp: AV-Mediengestaltung Grundwissen, Europa-Lehrmittel Verlag, 2010\n- W. Murch: Ein Lidschlag, Ein Schnitt, Alexander Verlag, 2009\n- B. Ottersbach, T. Schadt: Filmschnitt-Bekenntnisse, UVK Verlag, 2009\n- M. A. Herzog: Generische Transformation von Multimedia-Content: Prozessautomatisierung am Beispiel von interaktivem Fernsehen und E-Learning-Anwendungen, Wissenschaftsverlag, 2010\n- K. Beck: Kommunikationswissenschaft, UTB Verlag, 2007\n- A. Grabs, K. Bannour, E. Vogl: Follow me!: Erfolgreiches Social Media Marketing, Rheinwerk Verlag, 2021\n- C. Beyer: Kongruenz in der Crossmedia-Kommunikation: Eine Untersuchung der Determinanten und Wirkungen, Springer, 2020\n- C. Pahrmann, K. Kupka, T. Schwenke: Social Media Marketing: Praxishandbuch für Facebook, Instagram, TikTok & Co, OReilly, 2022\n- M. Löffler, I. Michl: Think Content!: Erfolgreiches Content-Marketing, Rheinwerk Verlag, 2024\n\n--- Literature (DE) ---\n- N. Mahrdt: Crossmedia - Werbekampagnen erfolgreich planen und umsetzen, Springer Gabler, 2009\n- N. Schulz-Bruhdoel: Medienarbeit 2.0, Cross-MediaLösungen, Das Praxisbuch für PR und Journalismus von morgen, Frankfurter Allgemeine Buch, 2009\n- G. Schweiger: Praxishandbuch Werbung, UVK-Verlagsgesellschaft, 2013\n- Steven D. Katz: Die richtige Einstellung - Shot by shot, Zweitausendeins, 1999\n- P. Kandorfer: Lehrbuch der Filmgestaltung, Schiele und Schön, 2010\n- J. Monaco: Film verstehen, Rowohlt-Taschenbuch-Verl., 2001\n- S. Drate, D. Robbins, J. Salavetz: Motion by Design, Laurence King Publishing, 2006\n- M. Wäger: Grafik und Gestaltung, Galileo Press, 2010\n- M. Diefenbach: Workbook visuelles Denken: Ideen, Generieren, Kundenskizzen Anfertigen, Scribbles schnell gestalten, Books on Demand, 2013\n- G. Christiano: Storyboard Design, Stiebner Verlag, 2008\n- W. Faulstich: Grundkurs Filmanalyse, UTB Verlag, 2008\n- F. Hartmann: Globale Medienkultur: Technik, Geschichte, Theorien, UTB Verlag, 2006\n- D. Liebsch: Philosophie des Films, Mentis Verlag, 2005\n- W. Kamp: AV-Mediengestaltung Grundwissen, Europa-Lehrmittel Verlag, 2010\n- W. Murch: Ein Lidschlag, Ein Schnitt, Alexander Verlag, 2009\n- B. Ottersbach, T. Schadt: Filmschnitt-Bekenntnisse, UVK Verlag, 2009\n- M. A. Herzog: Generische Transformation von Multimedia-Content: Prozessautomatisierung am Beispiel von interaktivem Fernsehen und E-Learning-Anwendungen, Wissenschaftsverlag, 2010\n- K. Beck: Kommunikationswissenschaft, UTB Verlag, 2007\n- A. Grabs, K. Bannour, E. Vogl: Follow me!: Erfolgreiches Social Media Marketing, Rheinwerk Verlag, 2021\n- C. Beyer: Kongruenz in der Crossmedia-Kommunikation: Eine Untersuchung der Determinanten und Wirkungen, Springer, 2020\n- C. Pahrmann, K. Kupka, T. Schwenke: Social Media Marketing: Praxishandbuch für Facebook, Instagram, TikTok & Co, OReilly, 2022\n- M. Löffler, I. Michl: Think Content!: Erfolgreiches Content-Marketing, Rheinwerk Verlag, 2024", "metadata": {"moduleNumber": "BCSIM 104", "moduleName": "Crossmedia Production & Campaigns 2", "creditPoints": "5.0", "suggestedSemester": 4, "offeredInSeason": "summer_semester", "examType": "project", "heldInLanguage": "de", "reviserName": "Prof. Isolde Asal", "reviserEmail": "isolde.asal@hs-duesseldorf.de", "studyProgramId": 12, "source_type": "json"}}
{"id": "BCSIM_102", "text": "Title: Contemporary Animation & Motion Design\nModule Number: BCSIM 102\nCredits: 5.0 CP\nSemester: 3\nOffered In: winter_semester\nLanguage: de\nExam Type: portfolio\nInstructor: Prof. Isolde Asal\n\n--- Goals (EN) ---\nStudents acquire creative animation techniques, develop interactive motion design concepts, integrate advanced 3D animation and visual effects, and understand the application of artificial intelligence in animation. In addition, they gain skills in color theory, user-centered design, teamwork, ethics in animation design, and project and time management to plan, execute, and present innovative and compelling animated projects.\n\n--- Goals (DE) ---\nStudierende erwerben kreative Animationstechniken, entwickeln interaktive Motion Design-Konzepte, integrieren fortgeschrittene 3D-Animationen und Visual Effects, und verstehen die Anwendung von künstlicher Intelligenz in der Animation. Zusätzlich erlangen sie Fähigkeiten in Farbtheorie, benutzerzentriertem Design, Teamarbeit, Ethik im Animationsdesign sowie Projekt- und Zeitmanagement, um innovative und überzeugende animierte Projekte zu planen, umzusetzen und zu präsentieren.\n\n--- Contents (EN) ---\nStudents learn the basics of motion design, modern animation principles, typography and layout in the context of motion design, as well as the basics of 3D animation, storytelling in animation, practical applications of artificial intelligence in animation and motion design, and the realization of their own animated projects with a focus on contemporary design principles and AI integration.\n\n- Basics of motion design\n- Modern animation principles\n- Typography & layout in the context of motion design\n- Basics of 3D animation\n- Storytelling in animation\n- Practical applications of artificial intelligence in animation & motion design\n- Implementation of own animated projects with a focus on contemporary design principles and AI integration\n\n--- Contents (DE) ---\nDie Studierenden erlernen die Grundlagen von Motion Design, moderne Animationsprinzipien, Typografie und Layout im Kontext von Motion Design, sowie die Grundlagen der 3D-Animation, Storytelling in der Animation, praktische Anwendungen von künstlicher Intelligenz in der Animation und Motion Design, und die Umsetzung eigener animierter Projekte mit Schwerpunkt auf zeitgenössischen Designprinzipien und KI-Integration.\n\n- Grundlagen von Motion Design\n- Moderne Animationsprinzipien\n- Typografie & Layout im Kontext von Motion Design\n- Grundlagen der 3D-Animation\n- Storytelling in der Animation\n- Praktische Anwendungen von künstlicher Intelligenz in der Animation & Motion Design\n- Umsetzung eigener animierter Projekte mit Schwerpunkt auf zeitgenössischen Designprinzipien und KI-Integration\n\n--- Literature (EN) ---\n- S. Drate, D. Robbins, J. Salavetz: Motion by Design, Laurence King Publishing, 2006\n- M. Betancourt: The History of Motion Graphics: from Avant-Garde to Industry in The United States, Wildside Press, 2013\n- R. E. Williams: The Animator's Survival Kit, Faber and Faber, 2009\n- M. Wäger: Grafik und Gestaltung, Galileo Press, 2010\n- C. Jackson: Motion Design: Moving Graphics for Television, Music, Video, and Film, Routledge, 2017\n- B. Mitchell: Independent Animation: Developing, Producing and Distributing Your Animated Films, CRC Press, 2023\n- H. Rall: Animation from Concepts and Production, CRC Press, 2017\n- T. White: Animation from Pencils to Pixels: Classical Techniques for the Digital Animator, Routledge, 2017\n- P. Fontaine, B. Vogel: Adobe After Effects: Das umfassende Handbuch, Rheinwerk Verlag, 2023\n\n--- Literature (DE) ---\n- S. Drate, D. Robbins, J. Salavetz: Motion by Design, Laurence King Publishing, 2006\n- M. Betancourt: The History of Motion Graphics: from Avant-Garde to Industry in The United States, Wildside Press, 2013\n- R. E. Williams: The Animator's Survival Kit, Faber and Faber, 2009\n- M. Wäger: Grafik und Gestaltung, Galileo Press, 2010\n- C. Jackson: Motion Design: Moving Graphics for Television, Music, Video, and Film, Routledge, 2017\n- B. Mitchell: Independent Animation: Developing, Producing and Distributing Your Animated Films, CRC Press, 2023\n- H. Rall: Animation from Concepts and Production, CRC Press, 2017\n- T. White: Animation from Pencils to Pixels: Classical Techniques for the Digital Animator, Routledge, 2017\n- P. Fontaine, B. Vogel: Adobe After Effects: Das umfassende Handbuch, Rheinwerk Verlag, 2023", "metadata": {"moduleNumber": "BCSIM 102", "moduleName": "Contemporary Animation & Motion Design", "creditPoints": "5.0", "suggestedSemester": 3, "offeredInSeason": "winter_semester", "examType": "portfolio", "heldInLanguage": "de", "reviserName": "Prof. Isolde Asal", "reviserEmail": "isolde.asal@hs-duesseldorf.de", "studyProgramId": 12, "source_type": "json"}}
{"id": "BCSIM_101", "text": "Title: Creative Technical Film Producing 1\nModule Number: BCSIM 101\nCredits: 5.0 CP\nSemester: 3\nOffered In: winter_semester\nLanguage: de\nExam Type: project\nInstructor: Prof. Isolde Asal\n\n--- Goals (EN) ---\nStudents acquire comprehensive skills in film and media production, including technical and creative knowledge in camera work, sound engineering, post-production and virtual effects. They integrate innovative technologies such as motion design, compositing and artificial intelligence into the production process.\n\n--- Goals (DE) ---\nStudierende erwerben umfassende Kompetenzen in der Film- und Medienproduktion, darunter technische und gestalterische Kenntnisse in Kameraführung, Tontechnik, Postproduktion und virtuellen Effekten. Sie integrieren innovative Technologien wie Motion Design, Compositing und künstliche Intelligenz in den Produktionsprozess.\n\n--- Contents (EN) ---\nStudents learn creative and technical aspects of film production, post-production processes such as film editing and sound design, visual effects, compositing techniques, basics of AI integration, case study analysis and practical implementation of film projects.\n\n- Creative and technical aspects of film production and the various phases of film production\n- Post-production processes (film editing, color correction, sound design and visual effects integration in post-production)\n- Introduction to visual effects techniques, green screen technology and digital effects integration in the production process\n- Compositing techniques for the integration of graphics in film shots\n- Fundamentals of integrating AI into various aspects of film production, such as automated scripting, image recognition and post-production processes\n- Analysis of case studies from the industry\n- Implementation of film projects to apply the acquired skills in practice\n\n--- Contents (DE) ---\nDie Studierenden erlernen gestalterische und technische Aspekte der Filmproduktion, Postproduktionsprozesse wie Filmschnitt und Sounddesign, Visual Effects, Compositing-Techniken, Grundlagen der KI-Integration, Fallstudienanalyse und praktische Umsetzung von Filmprojekten.\n\n- Gestalterische und technische Aspekte der Filmproduktion und der verschiedenen Phasen der Filmproduktion\n- Postproduktionsprozesse (Filmschnitt, Farbkorrektur, Sounddesign und visuelle Effektintegration in der Postproduktion)\n- Einführung in Techniken der Visual Effects, Green Screen-Technologie und digitale Effektintegration in den Produktionsprozess\n- Compositing-Techniken für die Integration von Grafiken in Filmaufnahmen\n- Grundlagen der Integration von KI in verschiedene Aspekte der Filmproduktion, wie automatisierte Skripterstellung, Bilderkennung und Postproduktionsprozesse\n- Analyse von Fallstudien aus der Branche\n- Umsetzung von Filmprojekten, um die erworbenen Fähigkeiten praktisch anzuwenden\n\n--- Literature (EN) ---\n- S. Holmes: Visual Effects for Indie Filmmakers: A Guide to VFX Integration and Artist Collaboration, Routledge, 2023\n- E. Dinur: The Filmmaker's Guide to Visual Effects: The Art and Techniques of VFX for Directors, Producers, Editors and Cinematographers, Routledge, 2023\n- B. Flueckiger: Visual Effects: Filmbilder aus dem Computer, Schüren Verlag, 2023\n- V. Perez: The Color Management Handbook for Visual Effects Artists, CRC Press, 2023\n\n--- Literature (DE) ---\n- S. Holmes: Visual Effects for Indie Filmmakers: A Guide to VFX Integration and Artist Collaboration, Routledge, 2023\n- E. Dinur: The Filmmaker's Guide to Visual Effects: The Art and Techniques of VFX for Directors, Producers, Editors and Cinematographers, Routledge, 2023\n- B. Flueckiger: Visual Effects: Filmbilder aus dem Computer, Schüren Verlag, 2023\n- V. Perez: The Color Management Handbook for Visual Effects Artists, CRC Press, 2023", "metadata": {"moduleNumber": "BCSIM 101", "moduleName": "Creative Technical Film Producing 1", "creditPoints": "5.0", "suggestedSemester": 3, "offeredInSeason": "winter_semester", "examType": "project", "heldInLanguage": "de", "reviserName": "Prof. Isolde Asal", "reviserEmail": "isolde.asal@hs-duesseldorf.de", "studyProgramId": 12, "source_type": "json"}}
{"id": "BCSIM_105", "text": "Title: Creative Technical Film Producing 2\nModule Number: BCSIM 105\nCredits: 5.0 CP\nSemester: 4\nOffered In: summer_semester\nLanguage: de\nExam Type: project\nInstructor: Prof. Isolde Asal\n\n--- Goals (EN) ---\nStudents acquire advanced technical skills in film production, including sophisticated camera and sound techniques as well as advanced visual effects, motion design and compositing applications. They master interdisciplinary collaboration and advanced project management for complex projects. In addition, they develop comprehensive knowledge of immersive media production, in-depth insights into the integration of artificial intelligence into post-production processes and advanced skills in legal, financial and sustainability aspects of film production.\n\n--- Goals (DE) ---\nStudierende erlangen fortgeschrittene technische Fertigkeiten in der Filmproduktion, einschließlich anspruchsvoller Kamera- und Tontechniken sowie fortgeschrittener Visual Effects-, Motion Design- und Compositing-Anwendungen. Sie beherrschen interdisziplinäre Zusammenarbeit und fortgeschrittenes Projektmanagement für komplexe Projekte. Darüber hinaus entwickeln sie umfassende Kenntnisse über immersive Medienproduktion, vertiefte Einblicke in die Integration von künstlicher Intelligenz in Postproduktionsprozesse und fortgeschrittene Fähigkeiten in rechtlichen, finanziellen sowie nachhaltigen Aspekten der Filmproduktion.\n\n--- Contents (EN) ---\nStudents learn advanced film production techniques, specialized visual effects and motion design applications, advanced compositing and CGI, as well as the integration of artificial intelligence in post-production, in order to subsequently apply these skills practically in film projects.\n\n- Advanced film production techniques\n- Specialized visual effects and motion design applications\n- Advanced compositing, Unreal Engine and CGI\n- Artificial intelligence in post-production\n- Implementation of film projects to apply the acquired skills in practice\n\n--- Contents (DE) ---\nDie Studierenden erlernen fortgeschrittene Techniken der Filmproduktion, spezialisierte Visual Effects und Motion Design-Anwendungen, Advanced Compositing und CGI, sowie die Integration künstlicher Intelligenz in der Postproduktion, um diese Fähigkeiten anschließend praktisch in Filmprojekten umzusetzen.\n\n- Fortgeschrittene Techniken der Filmproduktion\n- Spezialisierte Visual Effects und Motion Design-Anwendungen\n- Advanced Compositing, Unreal Engine und CGI\n- Künstliche Intelligenz in der Postproduktion\n- Umsetzung von Filmprojekten, um die erworbenen Fähigkeiten praktisch anzuwenden\n\n--- Literature (EN) ---\n- S. Holmes: Visual Effects for Indie Filmmakers: A Guide to VFX Integration and Artist Collaboration, Routledge, 2023\n- E. Dinur: The Filmmaker's Guide to Visual Effects: The Art and Techniques of VFX for Directors, Producers, Editors and Cinematographers, Routledge, 2023\n- B. Flueckiger: Visual Effects: Filmbilder aus dem Computer, Schüren Verlag, 2023\n- V. Perez: The Color Management Handbook for Visual Effects Artists, CRC Press, 2023\n\n--- Literature (DE) ---\n- S. Holmes: Visual Effects for Indie Filmmakers: A Guide to VFX Integration and Artist Collaboration, Routledge, 2023\n- E. Dinur: The Filmmaker's Guide to Visual Effects: The Art and Techniques of VFX for Directors, Producers, Editors and Cinematographers, Routledge, 2023\n- B. Flueckiger: Visual Effects: Filmbilder aus dem Computer, Schüren Verlag, 2023\n- V. Perez: The Color Management Handbook for Visual Effects Artists, CRC Press, 2023", "metadata": {"moduleNumber": "BCSIM 105", "moduleName": "Creative Technical Film Producing 2", "creditPoints": "5.0", "suggestedSemester": 4, "offeredInSeason": "summer_semester", "examType": "project", "heldInLanguage": "de", "reviserName": "Prof. Isolde Asal", "reviserEmail": "isolde.asal@hs-duesseldorf.de", "studyProgramId": 12, "source_type": "json"}}
{"id": "BCSIM_106", "text": "Title: Sound Design & Score\nModule Number: BCSIM 106\nCredits: 5.0 CP\nSemester: 4\nOffered In: summer_semester\nLanguage: de\nExam Type: portfolio\nInstructor: Prof. Isolde Asal\n\n--- Goals (EN) ---\nStudents acquire a sound knowledge of the basics of sound design, master the recording and editing of film sound and the integration of scores. They develop advanced skills in the creation of sound effects, understand technical aspects of sound design and can implement creative sound design for various genres. They also gain knowledge of post-production, legal skills in handling sound design materials and the ability to integrate contemporary AI models.\n\n--- Goals (DE) ---\nStudierende erwerben fundierte Kenntnisse in den Grundlagen des Sounddesigns, beherrschen die Aufnahme und Bearbeitung von Film-O-Ton sowie die Integration von Scores. Sie entwickeln fortgeschrittene Fähigkeiten in der Erstellung von Soundeffekten, verstehen technische Aspekte des Sounddesigns und können kreatives Sounddesign für verschiedene Genres umsetzen. Darüber hinaus erlangen sie Kenntnisse in der Postproduktion, rechtliche Kompetenzen im Umgang mit Sounddesign-Materialien sowie die Fähigkeit zur Integration von zeitgenössischen KI-Modellen.\n\n--- Contents (EN) ---\nStudents learn the basics of sound design, recording and editing of film sound, sound effect integration, spatial sound, technical aspects, creative sound design in film, integration into the production process, legal aspects and AI integration.\n\n- Basics of sound design\n- Recording and editing film sound\n- Creation and integration of sound effects\n- Spatial sound and immersive sound environments\n- Technical aspects of sound design\n- Creative sound design in film\n- Integration of sound design into the production process\n- Legal aspects and licensing\n- Integration of contemporary AI models into the production process\n\n--- Contents (DE) ---\nDie Studierenden erlernen die Grundlagen des Sounddesigns, Aufnahme und Bearbeitung von Film-O-Ton, Soundeffekt-Integration, Raumklang, technische Aspekte, kreatives Sounddesign im Film, Integration in den Produktionsprozess, rechtliche Aspekte und KI-Integration.\n\n- Grundlagen des Sounddesigns\n- Aufnahme und Bearbeitung von Film-O-Ton\n- Erstellung und Integration von Soundeffekten\n- Raumklang und immersive Klangumgebungen\n- Technische Aspekte des Sounddesigns\n- Kreatives Sounddesign im Film\n- Integration von Sounddesign in den Produktionsprozess\n- Rechtliche Aspekte und Lizensierung\n- Integration von zeitgenössischen KI-Modellen in den Produktionsprozess\n\n--- Literature (EN) ---\n- J. U. Lensing: Sound-Design, Sound-Montage, Soundtrack-Komposition: Über die Gestaltung von Filmton, Schiele und Schön, 2018\n- T. Görne: Sounddesign: Klang, Wahrnehmung, Emotion, Carl Hanser Verlag, 2017\n- A. Dunker: Filmtonaufnahme: kompakte Infos für Fotografen und Filmemacher, UVK Verlag, 2017\n- B. Flückiger: Sound design: die virtuelle Klangwelt des Films, Schüren, 2012\n- C. Johnson, N. Rodríguez-Fernández, S. M. Rebelo:  Artificial Intelligence in Music, Sound, Art and Design, Springer, 2023\n- P. Rea: A Filmmakers Guide to Sound Design, Routledge, 2023\n\n--- Literature (DE) ---\n- J. U. Lensing: Sound-Design, Sound-Montage, Soundtrack-Komposition: Über die Gestaltung von Filmton, Schiele und Schön, 2018\n- T. Görne: Sounddesign: Klang, Wahrnehmung, Emotion, Carl Hanser Verlag, 2017\n- A. Dunker: Filmtonaufnahme: kompakte Infos für Fotografen und Filmemacher, UVK Verlag, 2017\n- B. Flückiger: Sound design: die virtuelle Klangwelt des Films, Schüren, 2012\n- C. Johnson, N. Rodríguez-Fernández, S. M. Rebelo:  Artificial Intelligence in Music, Sound, Art and Design, Springer, 2023\n- P. Rea: A Filmmakers Guide to Sound Design, Routledge, 2023", "metadata": {"moduleNumber": "BCSIM 106", "moduleName": "Sound Design & Score", "creditPoints": "5.0", "suggestedSemester": 4, "offeredInSeason": "summer_semester", "examType": "portfolio", "heldInLanguage": "de", "reviserName": "Prof. Isolde Asal", "reviserEmail": "isolde.asal@hs-duesseldorf.de", "studyProgramId": 12, "source_type": "json"}}
{"id": "BCSIM_200", "text": "Title: Generative AI in media production and agency management\nModule Number: BCSIM 200\nCredits: 5.0 CP\nSemester: 3\nOffered In: winter_semester\nLanguage: de\nExam Type: portfolio\nInstructor: Prof. Dr. rer. nat. Michael Marmann\n\n--- Goals (EN) ---\nThis course concentrates on the specific application of generative AI technologies in media production and agency operations. It builds on the fundamentals of generative AI and prompt engineering and focuses on the practical implementation in these areas. Students learn how generative AI systems can be used to create content such as texts, images, videos and interactive media.\n\nAn important part of the course is the project work, in which students have the opportunity to develop and implement their own concepts for the use of generative AI in media projects. In doing so, they are familiarized with the challenges and limitations of these technologies, especially in terms of creativity, originality and authenticity.\n\nFurthermore, the effects of these technologies on the media landscape and the way agencies work are discussed. The students deal with the question of how generative AI can change the role of media professionals and agencies.\n\nFinally, ethical and legal issues associated with the use of generative AI systems in media production, such as copyrights, data protection and responsibility for generated content, will be addressed.\n\n--- Goals (DE) ---\nDiese Vorlesung konzentriert sich auf die spezifische Anwendung generativer KI-Technologien in der Medienproduktion und im Agenturbetrieb. Sie baut auf den Grundlagen der generativen KI und des Prompt-Engineerings auf und fokussiert sich auf die praktische Umsetzung in diesen Bereichen. Die Studierenden lernen, wie generative KI-Systeme zur Erstellung von Inhalten wie Texten, Bildern, Videos und interaktiven Medien genutzt werden können.\n\nEin wichtiger Bestandteil des Kurses ist die Projektarbeit, in der die Studierenden die Möglichkeit haben, eigene Konzepte für die Nutzung generativer KI in Medienprojekten zu entwickeln und umzusetzen. Dabei werden sie mit den Herausforderungen und Grenzen dieser Technologien vertraut gemacht, insbesondere in Bezug auf Kreativität, Originalität und Authentizität.\n\nDes Weiteren werden die Auswirkungen dieser Technologien auf die Medienlandschaft und die Arbeitsweise in Agenturen diskutiert. Die Studierenden setzen sich mit der Frage auseinander, wie generative KI die Rolle von Medienschaffenden und Agenturen verändern kann.\n\nAbschließend werden ethische und rechtliche Fragen thematisiert, die mit der Verwendung generativer KI-Systeme in der Medienproduktion verbunden sind, wie Urheberrechte, Datenschutz und die Verantwortung für generierte Inhalte.\n\n--- Contents (EN) ---\nThe students\n\n- understand the possible applications of generative AI technologies in media production and agency operations.\n- can use generative AI systems to create and optimize media content.\n- are able to plan and implement projects in the field of media production using generative AI.\n- know the challenges and limitations of using generative AI in creative professions.\n- can analyze and evaluate the effects of generative AI on the media landscape and agency work.\n- develop an understanding of the ethical and legal aspects of using generative AI in the media industry.\n\n--- Contents (DE) ---\nDie Studierenden\n\n- verstehen die Anwendungsmöglichkeiten generativer KI-Technologien in der Medienproduktion und im Agenturbetrieb.\n-  können generative KI-Systeme zur Erstellung und Optimierung von Medieninhalten einsetzen.\n- sind in der Lage, Projekte im Bereich Medienproduktion unter Einsatz generativer KI zu planen und durchzuführen.\n- kennen die Herausforderungen und Grenzen des Einsatzes generativer KI in kreativen Berufen.\n- können die Auswirkungen generativer KI auf die Medienlandschaft und die Agenturarbeit analysieren und bewerten.\n- entwickeln ein Verständnis für die ethischen und rechtlichen Aspekte beim Einsatz von generativer KI in der Medienbranche.\n\n--- Literature (EN) ---\nCurrent literature references and sources of information are provided at the beginning of the module or directly from the course context. In addition, digital media are increasingly used as a source of knowledge\n\n--- Literature (DE) ---\nAktuelle Literaturhinweise und Informationsquellen werden zu Beginn des Moduls oder unmittelbar aus dem Veranstaltungskontext herausgegeben. Zusätzlich werden verstärkt digitale Medien als Wissensquelle eingesetzt.", "metadata": {"moduleNumber": "BCSIM 200", "moduleName": "Generative AI in media production and agency management", "creditPoints": "5.0", "suggestedSemester": 3, "offeredInSeason": "winter_semester", "examType": "portfolio", "heldInLanguage": "de", "reviserName": "Prof. Dr. rer. nat. Michael Marmann", "reviserEmail": "marmann@hs-duesseldorf.de", "studyProgramId": 12, "source_type": "json"}}
{"id": "BCSIM_201", "text": "Title: Interactive & Synthetic Educational Media\nModule Number: BCSIM 201\nCredits: 5.0 CP\nSemester: 3\nOffered In: winter_semester\nLanguage: de\nExam Type: portfolio\nInstructor: Prof. Dr. rer. nat. Michael Marmann\n\n--- Goals (EN) ---\nThe students \n\n- know the main types of interactive learning and knowledge media and can compare and evaluate them using predefined or self-defined criteria.\n- know the meaning, differences and important functions of authoring systems and AI-supported media tools,\n- Learning Management Systems (LMS), Learning Experience Platforms (LXPs) and can describe them.\n- are familiar with stakeholders and agile process models in the development of digital learning and knowledge media and can independently design and produce initial digital media with the help of classic and AI-supported tools. \n- know competence profiles for creating interactive and synthetic media and can evaluate them.\n- can apply classic and agile process models and project management techniques for the development of digital learning and knowledge media.\n- can create and adapt AI-generated content such as storyboards, scripts or voice-over texts for interactive e-learning applications.\n- know current and future trends in the field of synthetic media or can research them.\n\n--- Goals (DE) ---\nDie Studierenden \n\n- kennen wesentliche Typen interaktiver Lern- und Wissensmedien und können diese anhand vorgegebener oder selbst definierter Kriterien gegenüberstellen und bewerten.\n- kennen die Bedeutung, Unterschiede und wichtige Funktionen von Autorensystemen, KI-gestützten Medientools,\n- Learning Management Systemen (LMS), Learning Experience Plattformen (LXPs) und können diese beschreiben.\n- kennen Beteiligte und agile Vorgehensmodelle bei der Entwicklung digitaler Lern- und Wissensmedien und können erste Digitalmedien mit Hilfe von klassischen und KI-gestützten Werkzeugen selbstständig konzipieren und produzieren. \n- kennen Kompetenzprofile zur Erstellung interaktiver und synthetischer Medien und können diese bewerten.\n- können klassische und agile Vorgehensmodelle und Projektmanagementtechniken für die Entwicklung digitaler Lern- und Wissensmedien anwenden.\n- können KI-generierte Inhalte wie z.B. Storyboards, Drehbücher oder Sprechertexte für interaktive E-Learning-Anwendungen erstellen und anpassen.\n- kennen aktuelle und zukünftige Trends im Bereich der synthetischen Medien oder können diese recherchieren.\n\n--- Contents (EN) ---\nThe module teaches the basics of designing and developing interactive learning and knowledge media. Different types of interactive and synthetic media are presented, followed by an introduction to relevant methods, tools and technologies, such as authoring systems, AI-supported tools and learning management systems. Special attention is paid to the presentation of competence profiles that will be needed in the future to develop these media, as well as to process models and project management required for the successful design and implementation of digital learning and knowledge media.\n\nIn the further course of the module, the focus is on the use and development of synthetic media as an innovative component of digital educational products. Students learn, for example, how to design and create AI-generated scripts and synthetic media for e-learning applications.\n\nThe module concludes with an outlook on future trends and current developments in the field of interactive and synthetic media. This will enable students to critically reflect on developments in this dynamic field and design innovative solutions for the education sector.\n\n--- Contents (DE) ---\nDas Modul vermittelt die Grundlagen der Konzeption und Entwicklung interaktiver Lern- und Wissensmedien. Es werden verschiedene Typen interaktiver und synthetischer Medien vorgestellt, gefolgt von einer Einführung in relevante Methoden, Tools und Technologien, wie z.B. Autorensysteme, KI-gestützte Werkzeuge und Learning Management Systeme. Ein besonderes Augenmerk liegt auf der Vorstellung von Kompetenzprofilen, die zur Entwicklung dieser Medien künftig benötigt werden, sowie auf Vorgehensmodellen und dem Projektmanagement, das für die erfolgreiche Konzeption und Umsetzung digitaler Lern- und Wissensmedien erforderlich ist.\n\nIm weiteren Verlauf des Moduls liegt der Fokus auf dem Einsatz und der Entwicklung von synthetischen Medien als innovative Komponente digitaler Bildungsprodukte. Die Studierenden lernen, wie z.B. KI-generierte Drehbücher und synthetische Medien für E-Learning-Anwendungen konzipiert und erstellt werden.\n\nDas Modul schließt mit einem Ausblick auf die Zukunftstrends und die aktuellen Entwicklungen im Bereich der interaktiven und synthetischen Medien. Dadurch werden die Studierenden in die Lage versetzt, Entwicklungen in diesem dynamischen Feld kritisch zu reflektieren und innovative Lösungen für die Bildungsbranche zu konzipieren.\n\n--- Literature (EN) ---\nCurrent literature references and sources of information are provided at the beginning of the module or directly from the course context. In addition, digital media are increasingly used as a source of knowledge.\n\n--- Literature (DE) ---\nAktuelle Literaturhinweise und Informationsquellen werden zu Beginn des Moduls oder unmittelbar aus dem Veranstaltungskontext herausgegeben. Zusätzlich werden verstärkt digitale Medien als Wissensquelle eingesetzt.", "metadata": {"moduleNumber": "BCSIM 201", "moduleName": "Interactive & Synthetic Educational Media", "creditPoints": "5.0", "suggestedSemester": 3, "offeredInSeason": "winter_semester", "examType": "portfolio", "heldInLanguage": "de", "reviserName": "Prof. Dr. rer. nat. Michael Marmann", "reviserEmail": "marmann@hs-duesseldorf.de", "studyProgramId": 12, "source_type": "json"}}
{"id": "BCSIM_205", "text": "Title: New Work & New Learning\nModule Number: BCSIM 205\nCredits: 5.0 CP\nSemester: 4\nOffered In: summer_semester\nLanguage: de\nExam Type: portfolio\nInstructor: Prof. Dr. rer. nat. Michael Marmann\n\n--- Goals (EN) ---\nThe students\n\n- understand the concepts and driving forces behind the New Work movement.\n- can identify the principles of New Learning and apply them to educational contexts.\n- are able to design modern working and learning environments that promote creativity and innovation.\n- can critically analyze the effects of new technologies on work and education.\n- develop skills to act as change agents in their organizations.\n- can implement interdisciplinary approaches for lifelong learning and agile work processes.\n- can research and structure a current topic and present it at several levels of abstraction.\n- can argue a topic in the seminar group.\n- can prepare a current topic digitally and with interactive elements.\n\n--- Goals (DE) ---\nDie Studierenden\n- verstehen die Konzepte und treibenden Kräfte hinter der New Work-Bewegung.\n- können die Prinzipien des New Learning identifizieren und auf Bildungskontexte anwenden.\n- sind in der Lage, moderne Arbeits- und Lernumgebungen zu gestalten, die Kreativität und Innovation fördern.\n- können kritisch die Auswirkungen neuer Technologien auf Arbeit und Bildung analysieren.\n- entwickeln Fähigkeiten, um als Change Agents in ihren Organisationen zu fungieren.\n- können interdisziplinäre Ansätze für lebenslanges Lernen und agile Arbeitsprozesse implementieren.\n- können ein aktuelles Thema recherchieren, strukturieren und auf mehreren Abstraktionslevels präsentieren.\n- können ein bearbeitetes Thema in der Seminargruppe argumentativ vertreten.\n- können ein aktuelles Thema digital und mit interaktiven Elementen aufbereiten.\n\n--- Contents (EN) ---\nThis seminar deals with the current changes in the world of work and their influence on learning processes. The basics of the New Work movement, which focuses on autonomy, flexibility and participation in the workplace, as well as the principles of New Learning, which emphasizes self-directed learning and the use of new technologies, are covered. Students learn about innovative approaches to the design of working and learning environments that take into account both the individual needs of learners and the requirements of modern organizations.\n\nAn essential part of the seminar is the examination of the challenges and opportunities that digital technologies bring for the world of work and education. Concepts such as lifelong learning, knowledge management and skills development in the context of New Work and New Learning will be discussed.\n\nThe seminar promotes the development of skills that enable participants to act as change agents and implement interdisciplinary approaches in their own professional contexts. This includes critical reflection on existing structures and the ability to design and manage agile and flexible learning and work processes.\n\n--- Contents (DE) ---\nDieses Seminar beschäftigt sich mit den aktuellen Veränderungen in der Arbeitswelt und deren Einfluss auf Lernprozesse. Es werden die Grundlagen der New Work-Bewegung, die auf Autonomie, Flexibilität und Partizipation am Arbeitsplatz abzielt, sowie die Prinzipien des New Learning, welches Selbstgesteuertes Lernen und den Einsatz neuer Technologien in den Vordergrund stellt, behandelt. Die Studierenden lernen innovative Ansätze zur Gestaltung von Arbeits- und Lernumgebungen kennen, die sowohl die individuellen Bedürfnisse der Lernenden als auch die Anforderungen moderner Organisationen berücksichtigen.\n\nEin wesentlicher Bestandteil des Seminars ist die Auseinandersetzung mit den Herausforderungen und Chancen, die digitale Technologien für die Arbeitswelt und das Bildungswesen mit sich bringen. Es werden Konzepte wie das lebenslange Lernen, Wissensmanagement und die Kompetenzentwicklung im Kontext von New Work und New Learning diskutiert.\n\nDas Seminar fördert die Entwicklung von Kompetenzen, die es den Teilnehmenden ermöglichen, als Change Agents zu agieren und interdisziplinäre Ansätze in ihren eigenen beruflichen Kontexten umzusetzen. Dies beinhaltet die kritische Reflexion über bestehende Strukturen und die Fähigkeit, agile und flexible Lern- und Arbeitsprozesse zu gestalten und zu steuern.\n\n--- Literature (EN) ---\nCurrent literature references and sources of information are provided at the beginning of the module or directly from the course context. In addition, digital media are increasingly used as a source of knowledge.\n\n--- Literature (DE) ---\nAktuelle Literaturhinweise und Informationsquellen werden zu Beginn des Moduls oder unmittelbar aus dem Veranstaltungskontext herausgegeben. Zusätzlich werden verstärkt digitale Medien als Wissensquelle eingesetzt.", "metadata": {"moduleNumber": "BCSIM 205", "moduleName": "New Work & New Learning", "creditPoints": "5.0", "suggestedSemester": 4, "offeredInSeason": "summer_semester", "examType": "portfolio", "heldInLanguage": "de", "reviserName": "Prof. Dr. rer. nat. Michael Marmann", "reviserEmail": "marmann@hs-duesseldorf.de", "studyProgramId": 12, "source_type": "json"}}
{"id": "BCSIM_202", "text": "Title: Educational & Synthetic Media I\nModule Number: BCSIM 202\nCredits: 10.0 CP\nSemester: 3\nOffered In: winter_semester\nLanguage: de\nExam Type: project\nInstructor: Prof. Dr. rer. nat. Michael Marmann\n\n--- Goals (EN) ---\nThe students\n\n- can understand the concepts and technologies behind synthetic media and identify their areas of application in education.\n- are able to independently create synthetic media products that can be used for educational purposes.\n- develop the ability to expand and improve existing educational content with the help of synthetic media.\n- can critically evaluate the effects of synthetic media on learning and knowledge transfer.\n- are able to consider ethical and legal aspects when dealing with synthetic media in education.\n- can design, plan, implement and present a project in the field of Educational & Synthetic Media.\n\n--- Goals (DE) ---\nDie Studierenden\n\n- können die Konzepte und Technologien hinter Synthetic Media verstehen und deren Anwendungsgebiete im Bildungsbereich identifizieren.\n- sind in der Lage, selbstständig synthetische Medienprodukte zu erstellen, die für Bildungszwecke eingesetzt werden können.\n- entwickeln die Fähigkeit, bestehende Bildungsinhalte mit Hilfe von Synthetic Media zu erweitern und zu verbessern.\n- können die Auswirkungen von Synthetic Media auf das Lernen und die Wissensvermittlung kritisch bewerten.\n- sind befähigt, ethische und rechtliche Aspekte im Umgang mit Synthetic Media im Bildungsbereich zu berücksichtigen.\n- können ein Projekt im Bereich Educational & Synthetic Media konzipieren, planen, durchführen und präsentieren.\n\n--- Contents (EN) ---\nIn this project module, students explore the interface between synthetic media and educational technologies. They will learn how artificial intelligence and machine learning can be used to create authentic and interactive learning experiences. The project includes the creation of content such as digital avatars, animated tutorials and AI-driven simulations that can be applied in different educational contexts.\n\nThe students deal intensively with the tools and frameworks required for the development of synthetic media and apply them in practice. They analyze best-practice examples and evaluate the effectiveness of synthetic media in existing learning environments.\n\nA key element of the project is addressing the ethical dimensions of using synthetic media, including issues of authenticity, privacy and information integrity. Students will learn how to create educational offerings that are both pedagogically valuable and technologically advanced.\n\nThe project concludes with the conception and realization of their own Educational & Synthetic Media product by the students. They present their projects and reflect on the development process and the learning outcomes achieved.\n\n--- Contents (DE) ---\nIn diesem Projektmodul erforschen die Studierenden die Schnittstelle zwischen synthetischen Medien und Bildungstechnologien. Sie lernen, wie künstliche Intelligenz und maschinelles Lernen eingesetzt werden können, um authentische und interaktive Lernerfahrungen zu schaffen. Das Projekt umfasst die Erstellung von Inhalten wie digitale Avatare, animierte Tutorials und KI-gesteuerte Simulationen, die in verschiedenen Bildungskontexten angewendet werden können.\n\nDie Studierenden setzen sich intensiv mit den Tools und Frameworks auseinander, die für die Entwicklung von Synthetic Media erforderlich sind, und wenden diese praktisch an. Sie analysieren Best-Practice-Beispiele und evaluieren die Effektivität von Synthetic Media in bestehenden Lernumgebungen.\n\nEin wesentliches Element des Projekts ist die Auseinandersetzung mit den ethischen Dimensionen der Verwendung von Synthetic Media, einschließlich Fragen der Authentizität, des Datenschutzes und der Informationsintegrität. Die Studierenden lernen, wie man Bildungsangebote schafft, die sowohl pädagogisch wertvoll als auch technologisch fortschrittlich sind.\n\nDas Projekt schließt mit der Konzeption und Realisierung eines eigenen Educational & Synthetic Media-Produkts durch die Studierenden ab. Sie präsentieren ihre Projekte und reflektieren den Entwicklungsprozess sowie die erzielten Lernerfolge.\n\n--- Literature (EN) ---\nCurrent literature references and sources of information are provided at the beginning of the module or directly from the course context. In addition, digital media are increasingly used as a source of knowledge.\n\n--- Literature (DE) ---\nAktuelle Literaturhinweise und Informationsquellen werden zu Beginn des Moduls oder unmittelbar aus dem Veranstaltungskontext herausgegeben. Zusätzlich werden verstärkt digitale Medien als Wissensquelle eingesetzt.", "metadata": {"moduleNumber": "BCSIM 202", "moduleName": "Educational & Synthetic Media I", "creditPoints": "10.0", "suggestedSemester": 3, "offeredInSeason": "winter_semester", "examType": "project", "heldInLanguage": "de", "reviserName": "Prof. Dr. rer. nat. Michael Marmann", "reviserEmail": "marmann@hs-duesseldorf.de", "studyProgramId": 12, "source_type": "json"}}
{"id": "BCSIM_203", "text": "Title: Digital Literacy & AI Literacy\nModule Number: BCSIM 203\nCredits: 5.0 CP\nSemester: 3\nOffered In: winter_semester\nLanguage: de\nExam Type: portfolio\nInstructor: Prof. Dr. rer. nat. Michael Marmann\n\n--- Goals (EN) ---\nThe students\n\n- recognize the importance of digital literacy in today's information society.\n- understand the basic concepts and applications of artificial intelligence.\n- can critically evaluate digital tools and use them effectively for different purposes.\n- are able to identify and discuss the ethical and social implications of AI use.\n- develop the ability to analyze AI technologies in terms of data protection and data security.\n- can design and implement their own projects using AI elements.\n- can research and structure a current topic and present it at several levels of abstraction \n- are able to argue a topic in the seminar group \n- can prepare a current topic digitally and with interactive elements\n\n--- Goals (DE) ---\nDie Studierenden\n\n- erkennen die Bedeutung von Digital Literacy in der heutigen Informationsgesellschaft.\n- verstehen die grundlegenden Konzepte und Anwendungen künstlicher Intelligenz.\n- können digitale Werkzeuge kritisch bewerten und effektiv für verschiedene Zwecke einsetzen.\n- sind in der Lage, ethische und soziale Implikationen der KI-Nutzung zu identifizieren und zu diskutieren.\n- entwickeln die Fähigkeit, KI-Technologien in Bezug auf Datenschutz und Datensicherheit zu analysieren.\n- können eigene Projekte unter Einbeziehung von AI-Elementen konzipieren und umsetzen.\n- können ein aktuelles Thema recherchieren, strukturieren und auf mehreren Abstraktionslevels präsentieren \n- können ein bearbeitetes Thema in der Seminargruppe argumentativ vertreten \n- können ein aktuelles Thema digital und mit interaktiven Elementen aufbereiten\n\n--- Contents (EN) ---\nThe 'Digital Literacy & AI Literacy' seminar provides students with an in-depth understanding of the digital literacies necessary to navigate effectively in the modern world. It covers the skills needed to search, evaluate and create information digitally. The focus is on critically examining the reliability and credibility of digital content.\n\nIn parallel, there is a focus on AI Literacy, which covers the understanding and application of artificial intelligence in different areas of life and work. Students will learn the basic principles of AI systems, including machine learning and data processing. They deal with the latest developments in the field of AI and reflect on their impact on society and the individual.\n\nThe seminar also examines the ethical aspects of digital and AI technologies, such as data protection, algorithmic bias and the effects of automation on the labor market. Methods are developed to deal with these challenges and students are enabled to plan and implement their own digital and AI-related projects.\n\n--- Contents (DE) ---\nDas Seminar \"Digital Literacy & AI Literacy\" bietet den Studierenden ein tiefgreifendes Verständnis der digitalen Kompetenzen, die notwendig sind, um in der modernen Welt effektiv zu navigieren. Es behandelt die Fähigkeiten, die benötigt werden, um Informationen digital zu suchen, zu bewerten und zu erstellen. Im Zentrum steht die kritische Auseinandersetzung mit der Verlässlichkeit und Glaubwürdigkeit von digitalen Inhalten.\n\nParallel dazu wird ein Schwerpunkt auf AI Literacy gelegt, der das Verständnis und die Anwendung von künstlicher Intelligenz in verschiedenen Lebens- und Arbeitsbereichen umfasst. Die Studierenden lernen die Grundprinzipien von KI-Systemen kennen, einschließlich maschinellem Lernen und Datenverarbeitung. Sie setzen sich mit den neuesten Entwicklungen im Bereich der KI auseinander und reflektieren deren Auswirkungen auf Gesellschaft und Individuum.\n\nDas Seminar beleuchtet zudem die ethischen Aspekte der digitalen und KI-Technologien, wie Datenschutz, Bias in Algorithmen (algorithmic bias) und die Auswirkungen der Automatisierung auf den Arbeitsmarkt. Es werden Methoden erarbeitet, um mit diesen Herausforderungen umzugehen und die Studierenden dazu befähigt, eigene digitale und KI-bezogene Projekte zu planen und zu realisieren.\n\n--- Literature (EN) ---\nCurrent literature references and sources of information are provided at the beginning of the module or directly from the course context. In addition, digital media are increasingly used as a source of knowledge.\n\n--- Literature (DE) ---\nAktuelle Literaturhinweise und Informationsquellen werden zu Beginn des Moduls oder unmittelbar aus dem Veranstaltungskontext herausgegeben. Zusätzlich werden verstärkt digitale Medien als Wissensquelle eingesetzt.", "metadata": {"moduleNumber": "BCSIM 203", "moduleName": "Digital Literacy & AI Literacy", "creditPoints": "5.0", "suggestedSemester": 3, "offeredInSeason": "winter_semester", "examType": "portfolio", "heldInLanguage": "de", "reviserName": "Prof. Dr. rer. nat. Michael Marmann", "reviserEmail": "marmann@hs-duesseldorf.de", "studyProgramId": 12, "source_type": "json"}}
{"id": "BCSIM_204", "text": "Title: Educational & Synthetic Media II\nModule Number: BCSIM 204\nCredits: 10.0 CP\nSemester: 4\nOffered In: summer_semester\nLanguage: de\nExam Type: project\nInstructor: Prof. Dr. rer. nat. Michael Marmann\n\n--- Goals (EN) ---\nThe students\n\n- can understand the concepts and technologies behind synthetic media and identify their areas of application in education.\n- are able to independently create synthetic media products that can be used for educational purposes.\n- develop the ability to expand and improve existing educational content with the help of synthetic media.\n- can critically evaluate the effects of synthetic media on learning and knowledge transfer.\n- are able to consider ethical and legal aspects when dealing with synthetic media in education.\n- can design, plan, implement and present a project in the field of Educational & Synthetic Media.\n\n--- Goals (DE) ---\nDie Studierenden\n\n- können die Konzepte und Technologien hinter Synthetic Media verstehen und deren Anwendungsgebiete im Bildungsbereich identifizieren.\n- sind in der Lage, selbstständig synthetische Medienprodukte zu erstellen, die für Bildungszwecke eingesetzt werden können.\n- entwickeln die Fähigkeit, bestehende Bildungsinhalte mit Hilfe von Synthetic Media zu erweitern und zu verbessern.\n- können die Auswirkungen von Synthetic Media auf das Lernen und die Wissensvermittlung kritisch bewerten.\n- sind befähigt, ethische und rechtliche Aspekte im Umgang mit Synthetic Media im Bildungsbereich zu berücksichtigen.\n- können ein Projekt im Bereich Educational & Synthetic Media konzipieren, planen, durchführen und präsentieren.\n\n--- Contents (EN) ---\nIn this project module, students explore the interface between synthetic media and educational technologies. They will learn how artificial intelligence and machine learning can be used to create authentic and interactive learning experiences. The project includes the creation of content such as digital avatars, animated tutorials and AI-driven simulations that can be applied in different educational contexts.\n\nThe students deal intensively with the tools and frameworks required for the development of synthetic media and apply them in practice. They analyze best-practice examples and evaluate the effectiveness of synthetic media in existing learning environments.\n\nA key element of the project is addressing the ethical dimensions of using synthetic media, including issues of authenticity, privacy and information integrity. Students will learn how to create educational offerings that are both pedagogically valuable and technologically advanced.\n\nThe project concludes with the conception and realization of their own Educational & Synthetic Media product by the students. They present their projects and reflect on the development process and the learning outcomes achieved.\n\n--- Contents (DE) ---\nIn diesem Projektmodul erforschen die Studierenden die Schnittstelle zwischen synthetischen Medien und Bildungstechnologien. Sie lernen, wie künstliche Intelligenz und maschinelles Lernen eingesetzt werden können, um authentische und interaktive Lernerfahrungen zu schaffen. Das Projekt umfasst die Erstellung von Inhalten wie digitale Avatare, animierte Tutorials und KI-gesteuerte Simulationen, die in verschiedenen Bildungskontexten angewendet werden können.\n\nDie Studierenden setzen sich intensiv mit den Tools und Frameworks auseinander, die für die Entwicklung von Synthetic Media erforderlich sind, und wenden diese praktisch an. Sie analysieren Best-Practice-Beispiele und evaluieren die Effektivität von Synthetic Media in bestehenden Lernumgebungen.\n\nEin wesentliches Element des Projekts ist die Auseinandersetzung mit den ethischen Dimensionen der Verwendung von Synthetic Media, einschließlich Fragen der Authentizität, des Datenschutzes und der Informationsintegrität. Die Studierenden lernen, wie man Bildungsangebote schafft, die sowohl pädagogisch wertvoll als auch technologisch fortschrittlich sind.\n\nDas Projekt schließt mit der Konzeption und Realisierung eines eigenen Educational & Synthetic Media-Produkts durch die Studierenden ab. Sie präsentieren ihre Projekte und reflektieren den Entwicklungsprozess sowie die erzielten Lernerfolge.\n\n--- Literature (EN) ---\nCurrent literature references and sources of information are provided at the beginning of the module or directly from the course context. In addition, digital media are increasingly used as a source of knowledge.\n\n--- Literature (DE) ---\nAktuelle Literaturhinweise und Informationsquellen werden zu Beginn des Moduls oder unmittelbar aus dem Veranstaltungskontext herausgegeben. Zusätzlich werden verstärkt digitale Medien als Wissensquelle eingesetzt.", "metadata": {"moduleNumber": "BCSIM 204", "moduleName": "Educational & Synthetic Media II", "creditPoints": "10.0", "suggestedSemester": 4, "offeredInSeason": "summer_semester", "examType": "project", "heldInLanguage": "de", "reviserName": "Prof. Dr. rer. nat. Michael Marmann", "reviserEmail": "marmann@hs-duesseldorf.de", "studyProgramId": 12, "source_type": "json"}}
{"id": "BCSIM_400", "text": "Title: ELSA & Media Theory\nModule Number: BCSIM 400\nCredits: 5.0 CP\nSemester: 3\nOffered In: winter_semester\nLanguage: de\nExam Type: written_exam\nInstructor: Prof. Dr. Alina Huldtgren\n\n--- Goals (EN) ---\nThe aims of the module are to teach the social and socio-scientific as well as philosophical and ethical foundations of technologization, in particular digitization processes, to impart relevant analytical skills in this field and to reflect on the role of technology developers. \nThe module contributes to understanding the digital transformation and its consequences as a social process, evaluating it using ethical approaches and reflecting on one's own position within it. Students acquire a basic understanding of the social implications of increasing digitalization, can theoretically analyse societal and social consequences of digitalization and digitality, have basic skills for analysing ethical conflicts, are given the opportunity to examine specific ethical dilemmas as examples and develop approaches for dealing with the negative consequences of digitalization.\n\n--- Goals (DE) ---\nDie Ziele des Moduls bestehen in der Vermittlung sozial- und gesellschaftswissenschaftlicher sowie philosophischer und ethischer Grundlagen von Technisierungs-, insb. Digitalisierungsprozessen, der Vermittlung relevanter Analysekompetenzen in diesem Feld sowie der Reflexion der Rolle als Technikentwickler/in. \nDas Modul leistet einen Beitrag dazu, die digitale Transformation und ihre Folgen als sozialen Prozess zu verstehen, diesen anhand ethischer Ansätze zu bewerten und die eigene Position darin zu reflektieren. Studierende erwerben ein grundlegendes Verständnis sozialer Implikationen zunehmender Digitalisierung, können gesellschaftliche und soziale Folgen von Digitalisierung und Digitalität theoretisch analysieren, verfügen über grundlegende Kompetenzen zur Analyse ethischer Konflikte, erhalten die Möglichkeit, konkrete ethische Dilemmata beispielhaft zu untersuchen sowie Ansätze zum Umgang mit negativen Folgen von Digitalisierung zu entwickeln.\n\n--- Contents (EN) ---\nThe aims of the module are to teach the social and socio-scientific as well as philosophical and ethical foundations of technologization, in particular digitization processes, to impart relevant analytical skills in this field and to reflect on the role of technology developers. The module contributes to understanding the digital transformation and its consequences as a social process, evaluating it using ethical approaches and reflecting on one's own position within it. Students acquire a basic understanding of the social implications of increasing digitalization, can theoretically analyse societal and social consequences of digitalization and digitality, have basic skills for analysing ethical conflicts, are given the opportunity to examine specific ethical dilemmas as examples and develop approaches for dealing with the negative consequences of digitalization.\n\n- Central concepts in the relationship between the individual and society as well as in the context of digitalization and digitality\n- Theoretical approaches to describing and analyzing the relationship between (digital) technologies and society, including technology theory, philosophy of technology and technology and digital ethics\n- Selected examples of digital transformation, in particular with the application of data science and AI in selected fields of action or areas of society, including their societal and social consequences - Objectives of ethical analyses and central concepts of philosophy and ethics, including selected ethical justification approaches (e.g. ethics of responsibility)\n- Ethical analyses using the example of selected fields of application of digital technologies- Selected concepts for ethical evaluation in the development and implementation of digital technologies\n- Dealing with ethical dilemmas using concrete examples from practice\n\n--- Contents (DE) ---\nDie Ziele des Moduls bestehen in der Vermittlung sozial- und gesellschaftswissenschaftlicher sowie philosophischer und ethischer Grundlagen von Technisierungs-, insb. Digitalisierungsprozessen, der Vermittlung relevanter Analysekompetenzen in diesem Feld sowie der Reflexion der Rolle als Technikentwickler/in. Das Modul leistet einen Beitrag dazu, die digitale Transformation und ihre Folgen als sozialen Prozess zu verstehen, diesen anhand ethischer Ansätze zu bewerten und die eigene Position darin zu reflektieren. \nStudierende erwerben ein grundlegendes Verständnis sozialer Implikationen zunehmender Digitalisierung, können gesellschaftliche und soziale Folgen von Digitalisierung und Digitalität theoretisch analysieren, verfugen über grundlegende Kompetenzen zur Analyse ethischer Konflikte, erhalten die Möglichkeit, konkrete ethische Dilemmata beispielhaft zu untersuchen sowie Ansätze zum Umgang mit negativen Folgen von Digitalisierung zu entwickeln.\n- Zentrale Begriffe im Verhältnis von Individuum und Gesellschaft sowie im Kontext von Digitalisierung und Digitalität\n- Theoretische Ansätze zur Beschreibung und Analyse des Verhältnisses von (digitalen) Technologien und Gesellschaft, inkl. Techniktheorie, Technikphilosophie sowie Technik- und Digitalen Ethik\n- Ausgewählte Beispiele für digitale Transformation, insbesondere unter der Anwendung von Data Science und KI in ausgewählten Handlungsfeldern bzw. gesellschaftlichen Bereichen inkl. ihrer gesellschaftlichen und sozialen Folgen\n-  Ziele ethischer Analysen sowie zentraler Begriffe der Philosophie und Ethik inkl. ausgewählter ethischer Begründungsansätze (z. B. Verantwortungsethik)\n-  Ethische Analysen am Beispiel ausgewählter Anwendungsfelder digitaler Technologien\n-  Ausgewählte Konzepte zur ethischen Evaluation bei der Entwicklung und Implementierung digitaler Technologien\n-  Beschäftigung mit ethischen Dilemmata anhand konkreter Beispiele aus der Praxis\n\n--- Literature (EN) ---\n- Capurro, R. (2017). Homo Digitalis. Beiträge zur Ontologie, Anthropologie und Ethik der digitalen Tech-nik. Wiesbaden: Springer VS\n- Daniels, J., Gregory, K. & McMillan Cottom, T. (Hrsg.) (2017). Digital Sociologies. Bristol: Policy Press\n- Dolata, U. (2011). Wandel durch Technik: Eine Theorie soziotechnischer Transformation. Frankfurt am Main\n- Felt, U., R. Fouché, C.A. Miller & Smith-Doerr, L. (Hrsg.) (2017). The Handbook of Science and Technology Studies, 4. Auflage. Cambridge, MA: MIT Press\n- Marres, N. (2017). Digital Sociology. The Reinvention of Social Research. Cambridge u. a.: Polity Misselhorn, C. (2018). Grundfragen der Maschinenethik. Ditzingen: Reclam\n- Nida-Rumelin, J. & Weidenfeld, N. (2018). Digitaler Humanismus. Eine Ethik für das Zeitalter der Künstlichen Intelligenz. Piper\n- Scharff, R. C. & Dusek, V. (Hrsg.) (2014). Philosophy of Technology: The Technological Condition: An An-thology. 2. Auflage. Oxford: Wiley\n\n--- Literature (DE) ---\n- Capurro, R. (2017). Homo Digitalis. Beiträge zur Ontologie, Anthropologie und Ethik der digitalen Technik. Wiesbaden: Springer VS\n- Daniels, J., Gregory, K. & McMillan Cottom, T. (Hrsg.) (2017). Digital Sociologies. Bristol: Policy Press\n- Dolata, U. (2011). Wandel durch Technik: Eine Theorie soziotechnischer Transformation. Frankfurt am Main\n- Felt, U., R. Fouché, C.A. Miller & Smith-Doerr, L. (Hrsg.) (2017). The Handbook of Science and Technology Studies, 4. Auflage. Cambridge, MA: MIT Press\n- Marres, N. (2017). Digital Sociology. The Reinvention of Social Research. Cambridge u. a.: Polity Misselhorn, C. (2018). Grundfragen der Maschinenethik. Ditzingen: Reclam\n- Nida-Rumelin, J. & Weidenfeld, N. (2018). Digitaler Humanismus. Eine Ethik für das Zeitalter der Künstlichen Intelligenz. Piper\n- Scharff, R. C. & Dusek, V. (Hrsg.) (2014). Philosophy of Technology: The Technological Condition: An Anthology. 2. Auflage. Oxford: Wiley", "metadata": {"moduleNumber": "BCSIM 400", "moduleName": "ELSA & Media Theory", "creditPoints": "5.0", "suggestedSemester": 3, "offeredInSeason": "winter_semester", "examType": "written_exam", "heldInLanguage": "de", "reviserName": "Prof. Dr. Alina Huldtgren", "reviserEmail": "alina.huldtgren@hs-duesseldorf.de", "studyProgramId": 12, "source_type": "json"}}
{"id": "BCSIM_302", "text": "Title: Virtual Reality and Augmented Reality\nModule Number: BCSIM 302\nCredits: 5.0 CP\nSemester: 3\nOffered In: winter_semester\nLanguage: de\nExam Type: written_exam\nInstructor: Prof. Dr. rer. nat. Christian Geiger\n\n--- Goals (EN) ---\n\n\n--- Goals (DE) ---\n\n\n--- Contents (EN) ---\n\n\n--- Contents (DE) ---\n\n\n--- Literature (EN) ---\n\n\n--- Literature (DE) ---", "metadata": {"moduleNumber": "BCSIM 302", "moduleName": "Virtual Reality and Augmented Reality", "creditPoints": "5.0", "suggestedSemester": 3, "offeredInSeason": "winter_semester", "examType": "written_exam", "heldInLanguage": "de", "reviserName": "Prof. Dr. rer. nat. Christian Geiger", "reviserEmail": "geiger@hs-duesseldorf.de", "studyProgramId": 12, "source_type": "json"}}
{"id": "BCSIM_301", "text": "Title: Human AI-Interaction\nModule Number: BCSIM 301\nCredits: 5.0 CP\nSemester: 3\nOffered In: winter_semester\nLanguage: de\nExam Type: written_exam\nInstructor: Prof. Dr. rer. nat. Christian Geiger\n\n--- Goals (EN) ---\n\n\n--- Goals (DE) ---\n\n\n--- Contents (EN) ---\n\n\n--- Contents (DE) ---\n\n\n--- Literature (EN) ---\n\n\n--- Literature (DE) ---", "metadata": {"moduleNumber": "BCSIM 301", "moduleName": "Human AI-Interaction", "creditPoints": "5.0", "suggestedSemester": 3, "offeredInSeason": "winter_semester", "examType": "written_exam", "heldInLanguage": "de", "reviserName": "Prof. Dr. rer. nat. Christian Geiger", "reviserEmail": "geiger@hs-duesseldorf.de", "studyProgramId": 12, "source_type": "json"}}
{"id": "BCSIM_303", "text": "Title: Mediale Inszenierung\nModule Number: BCSIM 303\nCredits: 5.0 CP\nSemester: 3\nOffered In: winter_semester\nLanguage: de\nExam Type: project\nInstructor: Prof. Dr. rer. nat. Christian Geiger\n\n--- Goals (EN) ---\nParticipants learn the procedures for the conception, design, development, construction and operation of operation of media productions and selected examples in the field of entertainment (e.g. serious games, playful interaction).\ngames, playful interaction). Conceptual, creative, technical and economic aspects are considered in equal measure. By critically discussing current and historically significant examples, participants will be able to assess media productions and installations and evaluate their use from different perspectives. They critically reflect on their use from different perspectives. The participants have practical experience in the pre-visualization, prototyping and final implementation of manageable tasks for projects on the basis of selected marketable or freely available tools.\n\n--- Goals (DE) ---\nDie Teilnehmer lernen die Vorgehensweisen bei der Konzeption, Gestaltung, Entwicklung, Aufbau und Betrieb medialer Inszenierungen bzw. ausgewählter Beispiele im Bereich Entertainment (z. B. Serious Games, Playful Interaction). Dabei werden konzeptionelle, gestalterische, technische und wirtschaftliche Aspekte zu gleichen Teilen betrachtet. Durch die kritische Diskussion aktueller bzw. historisch bedeutsamer Beispiele können die Teilnehmer mediale Inszenierungen und Installationen beurteilen und den Einsatz aus verschiedenen Blickwinkeln kritisch reflektieren. Die Teilnehmer besitzen praktische Erfahrung in der Prävisualisierung, Prototyping und finalen Umsetzung überschaubarer Aufgabenstelllungen für Projekte auf Basis ausgewählter marktgängiger bzw. frei verfügbarer Werkzeuge.\n\n--- Contents (EN) ---\nKnowledge and skills in the field of media productions are taught. The teaching takes place with an interdisciplinary perspective and is strongly project-oriented.\n- Theoretical foundations of media production (perception, artistic expression, media architectures)\n- Entertainment computing, transmedia spaces, video art and performances\n- Selected technical aspects of digital and physical game, object and spatial design (projection mapping, multi-displays, VR/AR)\n- Workflow and tools for media productions and entertainment computing\n- Planning and operation of large-scale projects\n- Player / audience development and user feedback\n- Critical reflection and impact from multiple perspectives (artistic, technical, economic, social)\n\n--- Contents (DE) ---\nEs werden Kenntnisse und Fähigkeiten im Bereich mediale Inszenierungen vermittelt. Die Vermittlung erfolgt mit interdisziplinärer Perspektive und ist stark projektorientiert ausgerichtet.\n- Theoretische Grundlagen medialer Inszenierung  (Wahrnehmung, künstlerischer Ausdruck, mediale Architekturen)\n- Entertainment Computing, Transmediale Räume, Videokunst und Performances\n- Ausgewählte technische Aspekte des digitale und physischen Spiel-, Objekt- und Raumdesigns (Projection Mapping, Multi-Displays, VR/AR)\n- Workflow und Werkzeuge für mediale Inszenierungen und Entertainment Computing\n- Planung und Betrieb umfangreicher Projekte\n- Player / Audience Development und Nutzerfeedback\n- Kritische Reflektion und Impact aus multiplen Perspektiven (künstlerisch, technisch, wirtschaftlich, sozial)\n\n--- Literature (EN) ---\n\n\n--- Literature (DE) ---\n- Paul Divjak: Integrative Inszenierungen: zur Szenografie von partizipativen Räumen. Band 5. transcript Verlag, 2014.\n- Vladimir Geroimenko. Augmented Reality Art - From an Emerging Technology to a novel Creative Medium, Springer 3rd ed, 2022", "metadata": {"moduleNumber": "BCSIM 303", "moduleName": "Mediale Inszenierung", "creditPoints": "5.0", "suggestedSemester": 3, "offeredInSeason": "winter_semester", "examType": "project", "heldInLanguage": "de", "reviserName": "Prof. Dr. rer. nat. Christian Geiger", "reviserEmail": "geiger@hs-duesseldorf.de", "studyProgramId": 12, "source_type": "json"}}
{"id": "BCSIM_300", "text": "Title: Co-Creation Lab\nModule Number: BCSIM 300\nCredits: 5.0 CP\nSemester: 3\nOffered In: winter_semester\nLanguage: en_on_demand\nExam Type: project\nInstructor: Prof. Dr. Alina Huldtgren\n\n--- Goals (EN) ---\nStudents are able to plan, implement and critically evaluate a participatory design process with external stakeholders. \nThey are able to carry out a stakeholder analysis at the beginning and, based on this, select and apply suitable methods for participation. \nThey can deal with the dynamics in participatory processes and analyze ethical and social aspects during the design process. \nThey independently reflect on their role as researchers and design experts as well as the decisions and experiences of the participants in the project.\n\n--- Goals (DE) ---\nDie Studierenden sind in der Lage, einen partizipativen Designprozess mit externen Stakeholdern zu planen, durchzuführen und kritisch zu evaluieren. \nSie sind fähig, eine Stakeholderanalyse zu Beginn durchzuführen und darauf basierend, geeignete Methoden zur Partizipation auszuwählen und anzuwenden. \nSie können mit den Dynamiken in partizipativen Prozessen umgehen und analysieren ethische und soziale Aspekte während des Gestaltungsprozesses. \nSie reflektieren eigenständig, ihre Rolle als Forschende bzw. Designexperten sowie die Entscheidungen und Erfahrungen der Teilnehmenden im Projekt.\n\n--- Contents (EN) ---\nIn the Co-Creation Lab, one real design case is worked on per semester, which is provided by an external stakeholder (e.g. charity, theater/museum, start-up, etc.). The case is to be carried out co-creatively with stakeholders and users. Building on the design methodology basics from the \"Design & Innovation\" Methods module, in-depth methods of co-creation (e.g. co-design workshops, Lego Serious Play) and interdisciplinary collaboration are taught at the beginning of the module.\n\n--- Contents (DE) ---\nIm Co-Creation Lab wird pro Semester ein echter Design Case bearbeitet, der von einem externen Stakeholder (z.B. Wohlfahrt, Theater / Museum, Start-up etc.) bereitgestellt wird. Der Case soll co-kreativ mit Stakeholdern und Nutzer*innen durchgeführt werden. Aufbauend auf den Designmethodik-Grundlagen aus dem Modul Design & Innovation Methods werden zu Beginn des Moduls vertiefende Methoden der Co-Creation (u.a. Co-Design Workshops, Lego Serious Play) und interdisziplinären Zusammenarbeit gelehrt.\n\n--- Literature (EN) ---\n- Bødker, S., Dindler, C., Iversen, O. S., & Smith, R. C. (2022). What Is Participatory Design?. In Participatory Design (pp. 5-13). Cham: Springer International Publishing.\n- McKercher, K. A. (2020). Beyond sticky notes. Doing co-design for Real: Mindsets, Methods, and Movements, 1st Edn. Sydney, NSW: Beyond Sticky Notes.\n- Sanders, E. B. N., & Stappers, P. J. (2008). Co-creation and the new landscapes of design. Co-design, 4(1), 5-18.\n- Hillmer, D. (2021). PLAY! Der unverzichtbare LEGO® Serious Play® Praxis-Guide für Trainer, Coaches und Moderatoren: Inklusive Online-Guide!. Carl Hanser Verlag GmbH Co KG.\n- Aktuelle wissenschaftliche Veröffentlichungen\n\n--- Literature (DE) ---\n- Bødker, S., Dindler, C., Iversen, O. S., & Smith, R. C. (2022). What Is Participatory Design?. In Participatory Design (pp. 5-13). Cham: Springer International Publishing.\n- McKercher, K. A. (2020). Beyond sticky notes. Doing co-design for Real: Mindsets, Methods, and Movements, 1st Edn. Sydney, NSW: Beyond Sticky Notes.\n- Sanders, E. B. N., & Stappers, P. J. (2008). Co-creation and the new landscapes of design. Co-design, 4(1), 5-18.\n- Hillmer, D. (2021). PLAY! Der unverzichtbare LEGO® Serious Play® Praxis-Guide für Trainer, Coaches und Moderatoren: Inklusive Online-Guide!. Carl Hanser Verlag GmbH Co KG.\n- Aktuelle wissenschaftliche Veröffentlichungen", "metadata": {"moduleNumber": "BCSIM 300", "moduleName": "Co-Creation Lab", "creditPoints": "5.0", "suggestedSemester": 3, "offeredInSeason": "winter_semester", "examType": "project", "heldInLanguage": "en_on_demand", "reviserName": "Prof. Dr. Alina Huldtgren", "reviserEmail": "alina.huldtgren@hs-duesseldorf.de", "studyProgramId": 12, "source_type": "json"}}
{"id": "BCSIM_305", "text": "Title: Advanced & Smart User Interfaces\nModule Number: BCSIM 305\nCredits: 5.0 CP\nSemester: 4\nOffered In: summer_semester\nLanguage: de\nExam Type: written_exam\nInstructor: Prof. Dr. rer. nat. Christian Geiger\n\n--- Goals (EN) ---\n\n\n--- Goals (DE) ---\n\n\n--- Contents (EN) ---\n\n\n--- Contents (DE) ---\n\n\n--- Literature (EN) ---\n\n\n--- Literature (DE) ---", "metadata": {"moduleNumber": "BCSIM 305", "moduleName": "Advanced & Smart User Interfaces", "creditPoints": "5.0", "suggestedSemester": 4, "offeredInSeason": "summer_semester", "examType": "written_exam", "heldInLanguage": "de", "reviserName": "Prof. Dr. rer. nat. Christian Geiger", "reviserEmail": "geiger@hs-duesseldorf.de", "studyProgramId": 12, "source_type": "json"}}
{"id": "BCSIM_308", "text": "Title: Experience Design and Embodied Interaction\nModule Number: BCSIM 308\nCredits: 5.0 CP\nSemester: 4\nOffered In: summer_semester\nLanguage: de\nExam Type: written_exam\nInstructor: Prof. Dr. rer. nat. Christian Geiger\n\n--- Goals (EN) ---\n\n\n--- Goals (DE) ---\n\n\n--- Contents (EN) ---\n\n\n--- Contents (DE) ---\n\n\n--- Literature (EN) ---\n\n\n--- Literature (DE) ---", "metadata": {"moduleNumber": "BCSIM 308", "moduleName": "Experience Design and Embodied Interaction", "creditPoints": "5.0", "suggestedSemester": 4, "offeredInSeason": "summer_semester", "examType": "written_exam", "heldInLanguage": "de", "reviserName": "Prof. Dr. rer. nat. Christian Geiger", "reviserEmail": "geiger@hs-duesseldorf.de", "studyProgramId": 12, "source_type": "json"}}
{"id": "BCSIM_309", "text": "Title: Immersive Visualisierung\nModule Number: BCSIM 309\nCredits: 5.0 CP\nSemester: 4\nOffered In: summer_semester\nLanguage: de\nExam Type: project\nInstructor: Prof. Dr. rer. nat. Christian Geiger\n\n--- Goals (EN) ---\nStudents can combine basic immersive technologies with typical interactive visualization tasks in a targeted manner. They can adapt suitable VR/AR/MR techniques for questions relating to high-dimensional data sets and realize them conceptually, creatively and technically.\nStudents are familiar with the most important visualization technologies and are able to design, build and evaluate suitable visualizations in application. They are able to transfer basic concepts of visualization to relevant scenarios in everyday life or in specific fields of application (e.g. data science). Here, students develop basic solution ideas for the topics mentioned together with others in a team and present them in an appropriate manner. They give appreciative and constructive feedback to fellow students during the presentations.\n\n--- Goals (DE) ---\nStudierende können grundlegende immersive Technologien mit typischen Aufgaben interaktiven Visualisierung zielgerichtet verknüpfen. Sie können für Fragestellungen zu hochdimensionalen Datensätzen geeignete VR/AR/MR-Techniken adaptieren und konzeptionell, gestalterisch und technisch realisieren. Die Studierenden kennen die wichtigsten Visualisierungstechnologien und sind in der Lage, geeignete Visualisierungen zu konzipieren, aufzubauen und in der Anwendung zu bewerten. Sie sind in der Lage grundlegende Konzepte der Visualisierung auf relevante Szenarien im täglichen Leben bzw. in spezifischen Anwendungsfeldern (z. B. Data Science) zu übertragen. \nHier entwickeln die Studierenden grundlegende Lösungsideen zu den genannten Themen gemeinsam mit anderen im Team und präsentieren diese auf geeignete Weise. Sie geben Kommilitonen im Rahmen der Präsentationen ein wertschätzendes und konstruktives Feedback.\n\n--- Contents (EN) ---\nThe complexity of media application areas and digital products requires a contextual and narrative form of\nnarrative form of conveying content. Product developers, designers and interaction designers develop immersive narratives and complex narratives and implement them in user journey models. To make this possible, content, dramaturgies and narrative paths for linear and non-linear storytelling in transmedia digital media are researched and developed.\n- Immersive workflow and pipeline for data generation, processing, presentation and analysis of multidimensional data.\n-analysis of multidimensional data\n- 3D scanning and related methods\n Fundamentals of immersive analysis methods and relevant related fields\n- Selected techniques for immersive data analysis\n- Current R&D results, tools and projects for immersive visualization\n\n--- Contents (DE) ---\nDie Komplexität medialer Anwendungsgebiete und digitaler Produkte erfordert eine kontextuelle und\nerzählerische Form der Vermittlung von Inhalten. Produktentwickler, Designer und Interaktionsgestalter entwickeln immersive Erzählungen und komplexe Narrative und setzen diese in User-Journey-Modelle um. Um dies zu ermöglichen werden Inhalte, Dramaturgien und narrative Parcours für lineares und nonlineares Erzählen in transmedialen digitalen Medien erforscht und entwickelt.\n- Immersiver Workflow und Pipeline für die Datengenerierung, -verarbeitung, -präsentation und -analyse multidimensionaler Daten\n- 3D Scanverfahren und verwandte Methoden\n Grundlagen immersiver Analyseverfahren und relevanter angrenzender Gebiete\n- Ausgewählte Techniken für immersive Datenanalyse\n- Aktuelle F&E-Ergebnisse, Werkzeuge und Projekte für immersive Visualisierung\n\n--- Literature (EN) ---\n- R. Dörner, W. Broll, P. Grimm, B. Jung (eds.), Virtual and Augmented Reality (VR/AR), 2nd edition. Fundamentals and Methods of Virtual and Augmented Reality, Springer, 2019, DOI 10.1007/978-3-642-28903-3\n- Jason Jerald. 2015. The VR Book: Human-Centered Design for Virtual Reality. Association for Computing Machinery and Morgan & Claypool, New York, NY, USA.\n- Kim Marriott et al. Immersive Analytics. Springer 2018\n- J. Dill et al. Expanding the Frontiers of Visual Analytics and Visualization, Springer , 2012\n- Further literature will be announced at the beginning of the lecture- R. Dörner, W. Broll, P. Grimm, B. Jung (eds.), Virtual and Augmented Reality (VR/AR), 2nd edition. Fundamentals and Methods of Virtual and Augmented Reality, Springer, 2019, DOI 10.1007/978-3-642-28903-3\n- Jason Jerald. 2015. The VR Book: Human-Centered Design for Virtual Reality. Association for Computing Machinery and Morgan & Claypool, New York, NY, USA.\n- Kim Marriott et al. Immersive Analytics. Springer 2018\n- J. Dill et al. Expanding the Frontiers of Visual Analytics and Visualization, Springer , 2012\n- Further literature will be announced at the beginning of the lecture\n\n--- Literature (DE) ---\n- R. Dörner, W. Broll, P. Grimm, B. Jung (Hrsg.), Virtual und Augmented Reality (VR/AR), 2. Auflage. Grundlagen und Methoden der Virtuellen und Augmentierten Realität, Springer, 2019, DOI 10.1007/978-3-642-28903-3\n- Jason Jerald. 2015. The VR Book: Human-Centered Design for Virtual Reality. Association for Computing Machinery and Morgan & Claypool, New York, NY, USA.\n- Kim Marriott et al. Immersive Analytics. Springer 2018\n- J. Dill et al. Expanding the Frontiers of Visual Analytics and Visualization, Springer , 2012\n- Weitere Literatur wird bei Vorlesungsbeginn bekannt gegeben", "metadata": {"moduleNumber": "BCSIM 309", "moduleName": "Immersive Visualisierung", "creditPoints": "5.0", "suggestedSemester": 4, "offeredInSeason": "summer_semester", "examType": "project", "heldInLanguage": "de", "reviserName": "Prof. Dr. rer. nat. Christian Geiger", "reviserEmail": "geiger@hs-duesseldorf.de", "studyProgramId": 12, "source_type": "json"}}
{"id": "BCSIM_310", "text": "Title: Mixed Reality Design & Digital Art\nModule Number: BCSIM 310\nCredits: 5.0 CP\nSemester: 4\nOffered In: summer_semester\nLanguage: de\nExam Type: project\nInstructor: Prof. Dr. rer. nat. Christian Geiger\n\n--- Goals (EN) ---\nParticipants will learn how basic aesthetic experiences can be conceived, designed and realised using mixed reality technologies.\n- Research on existing work in the field\n- Critical discussion of current works and discourses\n- brainstorming, conceptualisation and presentation of ideas\n- Prototyping and realisation of mixed reality content\n- Reflection and critical scrutiny of own and other people's work\n\n--- Goals (DE) ---\nDie Teilnehmer:innen lernen wie grundlegende ästhetische Erfahrungen mittels Mixed Reality Technologien konzipiert, gestaltet und realisiert werden können.\n- Recherche zu existierenden Arbeiten im Fachgebiet\n- kritische Diskussion zu aktuellen Arbeiten und Diskursen\n- Ideenfindung, Konzeption, Präsentation von Ideen\n- Prototyping und Realisierung von Mixed Reality Inhalten\n- Reflektion und kritische Hinterfragung eigener und fremder Arbeiten\n\n--- Contents (EN) ---\nThe lecture provides an overview of the design of mixed reality experiences with a focus on digital art. In addition to reflecting on existing works, participants will also develop and realise their own approaches.\n- Basics of mixed reality design and technology\n- Basics of digital art\n- Examples of current work in the field of mixed reality design and digital art\n- Conception of own ideas on a defined topic\n- Excursion and participation in external lectures / showings, if applicable\n- Project work \n- Presentation of the results as part of an event / exhibition\n\n--- Contents (DE) ---\nDie Veranstaltung gibt einen Überblick zur Gestaltung von Mixed Reality Experiences mit einem Fokus auf digitale Kunst. Neben der Reflektion existierender Arbeiten sollen die Teilnehmer:innen auch eigene Ansätze entwickeln und umsetzen.\n- Grundlagen Mixed Reality Design und Technologie\n- Grundlagen digitaler Kunst\n- Beispiele aktueller Arbeiten im Bereich Mixed Reality Design und Digital Art\n- Konzeption eigener Ideen zu einem definierten Thema\n- ggf. Exkursion und Teilnahme an externen Vorträgen / Showings\n- Projektarbeit \n- Präsentation der Ergebnisse im Rahmen einer Veranstaltung / Ausstellung\n\n--- Literature (EN) ---\n-Vladimir Geroimenko, Augmented Reality Art, 3rd ed, 2022, Springer\n\n--- Literature (DE) ---\n-Vladimir Geroimenko, Augmented Reality Art, 3rd ed, 2022, Springer", "metadata": {"moduleNumber": "BCSIM 310", "moduleName": "Mixed Reality Design & Digital Art", "creditPoints": "5.0", "suggestedSemester": 4, "offeredInSeason": "summer_semester", "examType": "project", "heldInLanguage": "de", "reviserName": "Prof. Dr. rer. nat. Christian Geiger", "reviserEmail": "geiger@hs-duesseldorf.de", "studyProgramId": 12, "source_type": "json"}}
{"id": "BCSIM_306", "text": "Title: Design for Wellbeing\nModule Number: BCSIM 306\nCredits: 5.0 CP\nSemester: 4\nOffered In: summer_semester\nLanguage: de\nExam Type: portfolio\nInstructor: Prof. Dr. Alina Huldtgren\n\n--- Goals (EN) ---\nStudents gain a comprehensive understanding of the interactions between different psychological and sociological models of subjective well-being. They are able to explain and differentiate between these models.\n\nFurthermore, students recognize that socio-sociological and psychological aspects in conjunction with designed technology can influence subjective well-being both positively and negatively.\n\nThe strategies and methods required to analyze these relationships are understood by the students and can be effectively applied in the process of technology development.\n\nBased on this knowledge and foundation, students are able to design technology and digital artifacts with regard to well-being, taking a sensitive approach.\n\n--- Goals (DE) ---\nDie Studierenden erlangen ein umfassendes Verständnis für die Wechselwirkungen zwischen verschiedenen psychologischen und soziologischen Modellen des subjektiven Wohlbefindens. Sie sind in der Lage, diese Modelle zu erläutern und voneinander abzugrenzen.\n\nDes Weiteren erkennen die Studierenden, dass gesellschaftlich-soziologische und psychologische Aspekte in Verbindung mit gestalteter Technologie das subjektive Wohlbefinden sowohl positiv als auch negativ beeinflussen können.\n\nDie erforderlichen Strategien und Methoden zur Analyse dieser Zusammenhänge werden von den Studierenden verstanden und können im Prozess der Technikentwicklung effektiv angewendet werden.\n\nAuf Grundlage dieser Erkenntnisse und Grundlagen sind die Studierenden in der Lage, Technologie und digitale Artefakte im Hinblick auf das Wohlbefinden zu gestalten, wobei sie einen sensiblen Ansatz verfolgen.\n\n--- Contents (EN) ---\nIntroduction to the theoretical foundations of sociology for analyzing social practices and in-depth study of psychological theories for researching positive experiences and memories.\n\nImparting knowledge of measuring and interpreting subjective well-being in the context of everyday life. Differentiation between bottom-up and top-down approaches in connection with qualitative and quantitative measurement methods.\n\nPresentation of design methods for well-being-oriented design, e.g. the Positive Practice Canvas. In addition, strategies for the sensitive design of technologies, e.g. positive computing, are presented.\n\n--- Contents (DE) ---\nEinführung in die theoretischen Grundlagen der Soziologie zur Analyse sozialer Praktiken sowie Vertiefung in psychologische Theorien zur Erforschung positiven Erlebens und Erinnerns.\n\nVermittlung von Kenntnissen im Messen und Interpretieren des subjektiven Wohlbefindens im Kontext des Alltags. Differenzierung von bottom-up- und top-down-Ansätzen im Zusammenhang mit qualitativen und quantitativen Messmethoden.\n\nPräsentation von Gestaltungsmethoden für wohlbefindens-orientiertes Design, z.B. des Positive Practice Canvas. Darüber hinaus werden Strategien zur sensiblen Gestaltung von Technologien, z.B. Positive Computing, vorgestellt.\n\n--- Literature (EN) ---\nBrey, Philip. \"Design for the value of human well-being.\" Handbook of ethics, values, and technological design: Sources, theory, values and application domains (2015): 365-382.\n\tCalvo, Rafael A., and Dorian Peters. Positive computing: technology for wellbeing and human potential. MIT press, 2014.\n\tDesmet, Pieter MA, and Anna E. Pohlmeyer. \"Positive design: An introduction to design for subjective well-being.\" International journal of design 7.3 (2013)\n\tHassenzahl, M., Eckoldt, K., Diefenbach, S., Laschke, M., Lenz, E., & Kim, J. (2013). Designing moments of meaning and pleasure. Experience design and happiness. International Journal of Design, 7(3), 21-31.\n\tLyubomirsky, S. (2013). The myths of happiness: What should make you happy, but doesnt, what shouldnt make you happy, but does. New York, NY: Penguin Books. \n\tRyan, R. M., & Deci, E. L. (2001). On happiness and human potentials: A review of research on hedonic and eudaimonic well-being. Annual Review of Psychology, 52(1), 141-166. \n\tReckwitz, A. (2002). Toward a theory of social practices: A development in culturalist theorizing. European Journal of Social Theory, 5(2), 243-263. \n\tPetermans, Ann, and Rebecca Cain, eds. Design for wellbeing: An applied approach. Routledge, 2019.\n\tShove, Elizabeth. The design of everyday life. Berg, 2007.\n\n--- Literature (DE) ---\nBrey, Philip. \"Design for the value of human well-being.\" Handbook of ethics, values, and technological design: Sources, theory, values and application domains (2015): 365-382.\n\tCalvo, Rafael A., and Dorian Peters. Positive computing: technology for wellbeing and human potential. MIT press, 2014.\n\tDesmet, Pieter MA, and Anna E. Pohlmeyer. \"Positive design: An introduction to design for subjective well-being.\" International journal of design 7.3 (2013)\n\tHassenzahl, M., Eckoldt, K., Diefenbach, S., Laschke, M., Lenz, E., & Kim, J. (2013). Designing moments of meaning and pleasure. Experience design and happiness. International Journal of Design, 7(3), 21-31.\n\tLyubomirsky, S. (2013). The myths of happiness: What should make you happy, but doesnt, what shouldnt make you happy, but does. New York, NY: Penguin Books. \n\tRyan, R. M., & Deci, E. L. (2001). On happiness and human potentials: A review of research on hedonic and eudaimonic well-being. Annual Review of Psychology, 52(1), 141-166. \n\tReckwitz, A. (2002). Toward a theory of social practices: A development in culturalist theorizing. European Journal of Social Theory, 5(2), 243-263. \n\tPetermans, Ann, and Rebecca Cain, eds. Design for wellbeing: An applied approach. Routledge, 2019.\n\tShove, Elizabeth. The design of everyday life. Berg, 2007.", "metadata": {"moduleNumber": "BCSIM 306", "moduleName": "Design for Wellbeing", "creditPoints": "5.0", "suggestedSemester": 4, "offeredInSeason": "summer_semester", "examType": "portfolio", "heldInLanguage": "de", "reviserName": "Prof. Dr. Alina Huldtgren", "reviserEmail": "alina.huldtgren@hs-duesseldorf.de", "studyProgramId": 12, "source_type": "json"}}
{"id": "BCSIM_307", "text": "Title: Designing digital health UX\nModule Number: BCSIM 307\nCredits: 5.0 CP\nSemester: 4\nOffered In: summer_semester\nLanguage: en_on_demand\nExam Type: project\nInstructor: Prof. Dr. Alina Huldtgren\n\n--- Goals (EN) ---\nStudents are able to explain the necessary non-technical principles for the conception and design of digital health solutions and demonstrate them using specific user requirements. They can carry out all phases of a user-centered approach for a given problem independently and in a team.\nStudents are able to present the important psychological models that are relevant for digital applications in the health sector and can compare models depending on a given question and select suitable ones for application development.\nThey can design applications based on the selected models and design their UIs in a user-friendly way and adapt them to user needs.\nYou will be able to develop suitable technical approaches for visualizing the resulting user experience and to develop prototypes quickly. Regardless of the type of application, students can assess the drivers and barriers of digital health technology and use selected design methodology to increase the acceptance of their design.\n\n--- Goals (DE) ---\nDie Studierenden sind in der Lage, notwendige nicht-technischen Grundlagen zur Konzeption und Gestaltung von Digital Health Lösungen zu erklären und anhand konkreter Nutzeranforderungen zu demonstrieren. Sie können für eine gegebene Fragestellung alle Phasen eines nutzerzentrierten Vorgehens eigenständig und im Team durchführen.\nDie Studierenden sind in der Lage die wichtigen psychologischen Modelle, die für digitale Anwendungen im Gesundheitsbereich relevant sind, darzustellen und können abhängig von einer gegebenen Fragestellung Modelle vergleichen und für die Anwendungsentwicklung passend selektieren.\nSie können auf Basis der gewählten Modelle, Anwendungen konzipieren und deren UIs nutzerfreundlich gestalten und an Nutzerbedürfnisse anpassen.\nSie sind fähig, geeignete technische Ansätze zur Visualisierung der resultierenden Nutzererfahrung und\nzur schnellen Prototypentwicklung selbst zu entwickeln. Unabhängig von der Art der Anwendung können die Studierenden die Treiber und Barrieren der digitalen Gesundheitstechnik beurteilen und mithilfe ausgewählter Designmethodik die Akzeptanz ihres Designs erhöhen\n\n--- Contents (EN) ---\nTeaching the necessary basics of the design, psychology and production of user-centered systems in the field of digital health. This includes the basics of HCI, UI/UX design and accessibility as well as the underlying psychological mechanisms and constructs in the health sector (including the Behavior Change Model and Self-Determination Theory for digital solutions, e.g. in the areas of prevention, rehabilitation or therapy). Strategies in the design of patient- and human-centered digital solutions such as gamification and nudging (persuasive design) are presented and applied. Students test the knowledge they have acquired on smaller design tasks or a project. Students learn the concept of user acceptance and how this can be increased through suitable design processes.\n- Fundamentals of human-technology interaction and design principles for digital health solutions \n- Psychological foundations for digital health, including self-determination theory, behavior change model, stage-based model of personal informatics\n- User-centered processes (UCD, PD, design thinking) and user experience in the healthcare sector\n- Acceptance models (e.g. TAM, UTAUT)\n- Mobile and ubiquitous health solutions\n- Wellbeing and prevention as behavioral patterns\n- Digital health literacy (eHealth literacy)\n- gamification\n- accessibility\n- Concepts of persuasive design (including nudging)\n\n--- Contents (DE) ---\nVermittlung notwendiger Grundlagen der Gestaltung, Psychologie und Produktion nutzerzentrierter Systeme im Bereich Digital Health. Dies beinhaltet einerseits Grundlagen im Bereich HCI, UI/UX Design und Accessibility sowie andererseits die im Gesundheitsbereich zugrundeliegenden psychologischen Mechanismen und Konstrukte (u. a. Behavior Change Model und Self-Determination Theorie für digitale Lösungen z. B. im Bereich Prävention, Rehabilitation oder Therapie). Strategien in der Gestaltung von patienten- und menschzentrierten digitalen Lösungen wie Gamification und Nudging (Persuasive Design) werden vorgestellt und angewandt. Studierende erproben ihr erlerntes Wissen an kleineren Designaufgaben bzw. einem Projekt. Studierenden erlernen das Konzept der Nutzer-Akzeptanz und wie diese aufgrund geeigneter Designprozesse erhöht werden kann.\n- Grundlagen der Mensch-Technik-Interaktion und Gestaltungsprinzipien für Digital Health-Lösungen\n- Psychologische Grundlagen für digitale Gesundheit, u. a. Self-Determination Theorie, Behavior Change Modell, Stage-based model of Personal Informatics\n- Nutzerzentrierte Prozesse (UCD, PD, Design Thinking) und User Experience im Gesundheitsbereich\n- Akzeptanzmodelle (u. a. TAM, UTAUT)\n- Mobile und allgegenwärtige Gesundheitslösungen\n- Wellbeing und Prävention als Verhaltensmuster\n- Digitale Gesundheitskompetenz (eHealth literacy)\n- Gamification\n- Accessibility\n- Konzepte des Persuasive Design (u. a. Nudging)\n\n--- Literature (EN) ---\n1.\tKu, B., Lupton, E. (2020).  Health Design Thinking Creating Products and Services for Better Health. MIT Press\n2.\tKuniavsky, M. (2003). Observing the user experience: a practitioner's guide to user research. Morgan Kaufmann\n3.\tHassenzahl, M. (2010). Experience design: Technology for all the right reasons. Synthesis Lectures on Human-Centered Informatics, 3(1), 1-95\n4.\tBJ Fogg. 2009. A behavior model for persuasive design. In Proceedings of the 4th International Conference on Persuasive Technology (Persuasive '09). Association for Computing Machinery, New York, NY, USA, Article 40, 17\n5.\tDeci, E. L., & Ryan, R. M. (2012). Self-determination theory\n\n--- Literature (DE) ---\n1.\tKu, B., Lupton, E. (2020).  Health Design Thinking Creating Products and Services for Better Health. MIT Press\n2.\tKuniavsky, M. (2003). Observing the user experience: a practitioner's guide to user research. Morgan Kaufmann\n3.\tHassenzahl, M. (2010). Experience design: Technology for all the right reasons. Synthesis Lectures on Human-Centered Informatics, 3(1), 1-95\n4.\tBJ Fogg. 2009. A behavior model for persuasive design. In Proceedings of the 4th International Conference on Persuasive Technology (Persuasive '09). Association for Computing Machinery, New York, NY, USA, Article 40, 17\n5.\tDeci, E. L., & Ryan, R. M. (2012). Self-determination theory", "metadata": {"moduleNumber": "BCSIM 307", "moduleName": "Designing digital health UX", "creditPoints": "5.0", "suggestedSemester": 4, "offeredInSeason": "summer_semester", "examType": "project", "heldInLanguage": "en_on_demand", "reviserName": "Prof. Dr. Alina Huldtgren", "reviserEmail": "alina.huldtgren@hs-duesseldorf.de", "studyProgramId": 12, "source_type": "json"}}
{"id": "BCSIM_20", "text": "Title: Digital Solutions\nModule Number: BCSIM 20\nCredits: 5.0 CP\nSemester: 2\nOffered In: summer_semester\nLanguage: de\nExam Type: written_exam\nInstructor: Prof. Dr. rer. nat. Michael Marmann\n\n--- Goals (EN) ---\nThe students\n\n- understand the basic concepts and architectures of web-based applications.\n- can design web pages using HTML, including structure, elements, attributes and forms.\n- are able to create appealing website layouts with CSS, using style sheets, selectors, the box model and responsive design.\n- can implement basic JavaScript programming for functions and event handling in order to integrate interactivity into websites.\n- understand the basics of relational databases and can perform simple SQL queries for data operations.\n- have an overview of content management systems, understand how they work and can handle common CMS such as WordPress.\n\n--- Goals (DE) ---\nDie Studierenden\n- verstehen die grundlegenden Konzepte und Architekturen webbasierter Anwendungen.\n- können Webseiten mit der Verwendung von HTML, einschließlich Struktur, Elemente, Attribute und Formulare, gestalten.\n- sind in der Lage, mit CSS ansprechende Webseiten-Layouts zu erstellen, unter Anwendung von Stilvorlagen, Selektoren, dem Box-Modell und Responsive Design.\n- können grundlegende JavaScript-Programmierung für Funktionen und Event Handling umsetzen, um Interaktivität in Webseiten zu integrieren.\n- verstehen die Grundlagen relationaler Datenbanken und können einfache SQL-Abfragen für Datenoperationen durchführen.\n- haben einen Überblick über Content-Management-Systeme, verstehen deren Funktionsweise und können mit gängigen CMS wie WordPress umgehen.\n\n--- Contents (EN) ---\nThis course focuses on practical skills in HTML, CSS and JavaScript for the design and implementation of interactive websites. HTML forms the foundation for structuring web content, complemented by CSS for visual design and responsive web design. JavaScript makes it possible to add dynamic elements and interactions to web-based applications.\n\nThe unit on relational databases and SQL prepares students to use data effectively in their applications. In addition, participants gain insights into the use and customization of content management systems, especially WordPress, and learn the basics of Drupal to understand the range of possibilities with CMS.\n\n--- Contents (DE) ---\nDiese Vorlesung konzentriert sich auf praktische Fähigkeiten in HTML, CSS und JavaScript für die Gestaltung und Implementierung interaktiver Webseiten. HTML bildet das Fundament für die Strukturierung von Webinhalten, ergänzt durch CSS für das visuelle Design und Responsive Webdesign. JavaScript ermöglicht es, dynamische Elemente und Interaktionen zu webbasierten Anwendungen hinzuzufügen.\n\nDie Einheit zu relationalen Datenbanken und SQL bereitet die Studierenden darauf vor, Daten effektiv in ihren Anwendungen zu nutzen. Zudem erhalten die Teilnehmenden Einblicke in die Verwendung und Anpassung von Content-Management-Systemen, speziell WordPress, und lernen die Grundlagen von Drupal kennen, um die Bandbreite der Möglichkeiten mit CMS zu verstehen.\n\n--- Literature (EN) ---\nCurrent literature references and sources of information are provided at the beginning of the module or directly from the course context. In addition, digital media are increasingly used as a source of knowledge.\n\n--- Literature (DE) ---\nAktuelle Literaturhinweise und Informationsquellen werden zu Beginn des Moduls oder unmittelbar aus dem Veranstaltungskontext herausgegeben. Zusätzlich werden verstärkt digitale Medien als Wissensquelle eingesetzt.", "metadata": {"moduleNumber": "BCSIM 20", "moduleName": "Digital Solutions", "creditPoints": "5.0", "suggestedSemester": 2, "offeredInSeason": "summer_semester", "examType": "written_exam", "heldInLanguage": "de", "reviserName": "Prof. Dr. rer. nat. Michael Marmann", "reviserEmail": "marmann@hs-duesseldorf.de", "studyProgramId": 12, "source_type": "json"}}
{"id": "BCSIM_50.02", "text": "Title: Interdisciplinary Project 20CP\nModule Number: BCSIM 50.02\nCredits: 20.0 CP\nSemester: 5\nOffered In: winter_semester\nLanguage: de\nExam Type: project\nInstructor: Prof. Isolde Asal\n\n--- Goals (EN) ---\nDepending on the project orientation.\n\n--- Goals (DE) ---\nJe nach Projektausrichtung verschieden.\n\n--- Contents (EN) ---\nDepending on the project orientation.\n\n--- Contents (DE) ---\nJe nach Projektausrichtung verschieden.\n\n--- Literature (EN) ---\nLiterature references will be issued for the respective topic at the beginning of the project.\n\n--- Literature (DE) ---\nLiteraturangaben werden zu dem jeweiligen Thema zu Beginn des Projektes ausgegeben.", "metadata": {"moduleNumber": "BCSIM 50.02", "moduleName": "Interdisciplinary Project 20CP", "creditPoints": "20.0", "suggestedSemester": 5, "offeredInSeason": "winter_semester", "examType": "project", "heldInLanguage": "de", "reviserName": "Prof. Isolde Asal", "reviserEmail": "isolde.asal@hs-duesseldorf.de", "studyProgramId": 12, "source_type": "json"}}
{"id": "BCSIM_206", "text": "Title: Data-Visualization\nModule Number: BCSIM 206\nCredits: 5.0 CP\nSemester: 4\nOffered In: summer_semester\nLanguage: de\nExam Type: project\nInstructor Moritz Fleischmann-Bergstein\n\n--- Goals (EN) ---\n\n\n--- Goals (DE) ---\nDie Studierenden kennen die wesentlichen Begriffe der Visualisierung und typische Vorgehensweise beim Entwurf. Sie kennen darüber hinaus typische Beispiele erfolgreicher Visualisierungsprojekte und können diese erläutern und bewerten. Sie sind in der Lage typische Probleme der Informationsvisualisierung zu erkennen und auf Basis etablierter Vorgehensweisen (Workflow, InfoVis Pipeline) für multivariate Daten expressive und effektive visuelle Darstellungskonzepte zu entwickeln, mittels geeigneter Technologien (Visualisierungssysteme, Grafikbibliotheken, etc) zu realisieren und zu bewerten. Sie sind in der Lage geeignete Probleme visuell zu beschreiben und für Lösungsansätze geeignete Visualisierungen zu entwickeln. \nÜbergeordnetes Ziel ist auch, existierende Visualisierungen zu bewerten und Vor- und Nachteile spezifischer Visualisierungstechniken zu identifizieren. Die Studierenden können Visualisierungen ausgewählter Probleme gemeinsam mit anderen im Team entwickeln und auf geeignete Weise prototypisch entwickeln und präsentieren. Sie geben Kommilitonen im Rahmen der Präsentationen ein wertschätzendes und konstruktives Feedback bzgl. der entwickelten Ansätze.\n\n--- Contents (EN) ---\n\n\n--- Contents (DE) ---\nVisualisierung als essentielle Aktivität im Bereich Data Science wird theoretisch, technisch und praktisch betrachtet. Kernthemen der Veranstaltung sind die menschliche visuelle Wahrnehmung, Visualisierung multivariater Daten, und Interaktionskonzepte für Visualisierungssysteme. Auf dieser Basis werden Visualisierungsstrategien speziell im Anwendungsbereich Data Science besprochen. Darüber hinaus \nwerden Visualisierungsprobleme mit gängigen Werkzeugen und Frameworks wie Tableau, D3 und Python/ matplotlib praktisch gelöst.  Aspekte der menschlichen visuelle Wahrnehmung und Modell der Visualisierung  Visualisierung multivariater Daten Workflow und Vorgehensmodelle im Visualisierungsprozess (Visualisierungspipeline)  Interaktionskonzepte, Gestaltungsgrundlagen und Storytelling von Informationsvisualisierungen  Überblick typischer Visualsierungssysteme (Tableau, D3, Jupyter Notebook/Python/matplotlib.  Auf dieser Basis werden Visualisierungsstrategien für Graphen, Netzwerke, Baumstrukturen, Text und Zeitbasierte Daten besprochen. Darüber hinaus werden Techniken zur effizienten Nutzung begrenzter Bildschirmfläche eingeführt und fortgeschrittene Darstellungstechnologien sowie webbasierte Visualisierungsansätze berücksichtigt.\n\n--- Literature (EN) ---\n\n\n--- Literature (DE) ---\n-K. Healy: Data Visualization  A Practical Introduction. Princeton University Press, 2018\n- Chaomei Chen: Information Visualization. Beyond the Horizon. 2. Auflage, Springer London, 2004\n- Colin Ware: Information Visualization : Perception for Design Morgan Kaufmann Series in Interactive Technologies, San Francisco, 2000\n- Natha Yau: Visualize This: The Flowing Data Guide to Design, Visualization and Statistics, Wiley, 2011\n- Cole Nussbaumer Knaflic: Storytelling with Data: A Data Visualization Guide for Business Professionals, Wiley, 2015 \n- J. Steele, N. Iliinsky: Beautiful Visualization. OReilly Media, 2010 C. Rossant: Learning IPython for interactive Computing and Data Visualization (2nd ed). Pact, 2018", "metadata": {"moduleNumber": "BCSIM 206", "moduleName": "Data-Visualization", "creditPoints": "5.0", "suggestedSemester": 4, "offeredInSeason": "summer_semester", "examType": "project", "heldInLanguage": "de", "reviserName": " Moritz Fleischmann-Bergstein", "reviserEmail": "moritz.fleischmann@hs-duesseldorf.de", "studyProgramId": 12, "source_type": "json"}}
{"id": "BCSIM_107", "text": "Title: Advanced Motion Design\nModule Number: BCSIM 107\nCredits: 5.0 CP\nSemester: 4\nOffered In: summer_semester\nLanguage: de\nExam Type: portfolio\nInstructor: Prof. Isolde Asal\n\n--- Goals (EN) ---\nStudents gain advanced skills in motion design techniques, including the use of 3D animation, visual effects and innovative approaches. They deepen their knowledge in the integration of artificial intelligence and experimental motion design. Advanced teamwork and efficient project management enable the realization of complex projects. Students develop an individual creative style, understand the ethical implications of motion design and present their work at a professional level, supported by a comprehensive portfolio.\n\n--- Goals (DE) ---\nStudierende erlangen fortgeschrittene Fähigkeiten in Motion Design-Techniken, einschließlich der Anwendung von 3D-Animation, Visual Effects und innovativen Ansätzen. Sie vertiefen ihre Kenntnisse in der Integration von künstlicher Intelligenz und experimentellem Motion Design. Fortgeschrittene Teamarbeit und effizientes Projektmanagement ermöglichen die Umsetzung komplexer Projekte. Studierende entwickeln einen individuellen kreativen Stil, verstehen die ethischen Implikationen im Motion Design und präsentieren ihre Arbeiten auf professionellem Niveau, gestützt durch ein umfassendes Portfolio.\n\n--- Contents (EN) ---\n- In-depth application of advanced motion design techniques\n- Advanced integration of interactivity in motion design\n- Advanced 3D animation software and complex visual effects\n- Integration of visual effects into higher level motion design projects\n- Advanced application of AI in motion design and visual effects processes\n- Advanced knowledge in the development of narrative structures in motion design\n- Responsible design of animated content and in-depth exploration of ethical considerations in motion design\n- Building a professional portfolio for career development\n\n--- Contents (DE) ---\n- Vertiefte Anwendung fortschrittlicher Motion Design-Techniken\n- Fortgeschrittene Integration von Interaktivität in Motion Design\n- Fortgeschrittene 3D-Animationssoftware und komplexe Visual Effects\n- Integration von Visual Effects in Motion Design-Projekte auf höherem Niveau\n- Vertiefte Anwendung von KI in Motion Design- und Visual Effects-Prozessen\n- Fortgeschrittene Kenntnisse in der Entwicklung narrativer Strukturen im Motion Design\n- Verantwortungsbewusste Gestaltung von animierten Inhalten und vertiefte Auseinandersetzung mit ethischen Überlegungen im Motion Design\n- Aufbau eines professionellen Portfolios für die berufliche Entwicklung\n\n--- Literature (EN) ---\n- S. Drate, D. Robbins, J. Salavetz: Motion by Design, Laurence King Publishing, 2006\n- M. Betancourt: The History of Motion Graphics: from Avant-Garde to Industry in The United States, Wildside Press, 2013\n- R. E. Williams: The Animator's Survival Kit, Faber and Faber, 2009\n- M. Wäger: Grafik und Gestaltung, Galileo Press, 2010\n- C. Jackson: Motion Design: Moving Graphics for Television, Music, Video, and Film, Routledge, 2017\n- B. Mitchell: Independent Animation: Developing, Producing and Distributing Your Animated Films, CRC Press, 2023\n- H. Rall: Animation from Concepts and Production, CRC Press, 2017\n- T. White: Animation from Pencils to Pixels: Classical Techniques for the Digital Animator, Routledge, 2017\n- P. Fontaine, B. Vogel: Adobe After Effects: Das umfassende Handbuch, Rheinwerk Verlag, 2023\n\n--- Literature (DE) ---\n- S. Drate, D. Robbins, J. Salavetz: Motion by Design, Laurence King Publishing, 2006\n- M. Betancourt: The History of Motion Graphics: from Avant-Garde to Industry in The United States, Wildside Press, 2013\n- R. E. Williams: The Animator's Survival Kit, Faber and Faber, 2009\n- M. Wäger: Grafik und Gestaltung, Galileo Press, 2010\n- C. Jackson: Motion Design: Moving Graphics for Television, Music, Video, and Film, Routledge, 2017\n- B. Mitchell: Independent Animation: Developing, Producing and Distributing Your Animated Films, CRC Press, 2023\n- H. Rall: Animation from Concepts and Production, CRC Press, 2017\n- T. White: Animation from Pencils to Pixels: Classical Techniques for the Digital Animator, Routledge, 2017\n- P. Fontaine, B. Vogel: Adobe After Effects: Das umfassende Handbuch, Rheinwerk Verlag, 2023", "metadata": {"moduleNumber": "BCSIM 107", "moduleName": "Advanced Motion Design", "creditPoints": "5.0", "suggestedSemester": 4, "offeredInSeason": "summer_semester", "examType": "portfolio", "heldInLanguage": "de", "reviserName": "Prof. Isolde Asal", "reviserEmail": "isolde.asal@hs-duesseldorf.de", "studyProgramId": 12, "source_type": "json"}}
{"id": "BCSIM_401", "text": "Title: Pencils and Polygons\nModule Number: BCSIM 401\nCredits: 5.0 CP\nSemester: 4\nOffered In: summer_semester\nLanguage: de\nExam Type: project\nInstructor: Prof. Dr.-Ing. Sina Mostafawy\n\n--- Goals (EN) ---\nThe students know the basics of drawing (picture composition, techniques, shading, perspective). They can transfer their knowledge from 2D to 3D modeling and rendering.\n\n--- Goals (DE) ---\nDie Studierenden erlernen die Grundlagen des Zeichnens. Sie können das Wissen aus dem 2D Zeichnen in die Erstellung von 3D Modelle übertragen (insbesondere Beleuchtung). Sie wissen, in welcher Form der Begriff des Formens sowie Licht und Schatten die Arbeit in der 3D Welt prägen.\n\n--- Contents (EN) ---\n- Basics of drawing\n- Dynamic and linear lines\n- Hatching techniques\n- Light and shadow\n- Image composition, image division and -perspective\n- Storyboard drawings\n\n--- Contents (DE) ---\n- Grundlagen des Zeichnens\n- Dynamische und lineare Linie\n- Schraffur Techniken\n- Licht und Schatten\n- Bildkomposition, Bildeinteilung und -perspektive\n- Storyboard Zeichnungen\n\n--- Literature (EN) ---\n\n\n--- Literature (DE) ---\n- F. A. Cerver: Zeichnen für Einsteiger, Konemann Verlag Koln 2002G. Bammes: Studien zur Gestalt des Menschen, 3. Aufl. Urania Verlag 2001", "metadata": {"moduleNumber": "BCSIM 401", "moduleName": "Pencils and Polygons", "creditPoints": "5.0", "suggestedSemester": 4, "offeredInSeason": "summer_semester", "examType": "project", "heldInLanguage": "de", "reviserName": "Prof. Dr.-Ing. Sina Mostafawy", "reviserEmail": "sina.mostafawy@hs-duesseldorf.de", "studyProgramId": 12, "source_type": "json"}}
{"id": "BCSIM_402", "text": "Title: Computer Animation\nModule Number: BCSIM 402\nCredits: 5.0 CP\nSemester: 3\nOffered In: winter_semester\nLanguage: de\nExam Type: oral_exam\nInstructor: Prof. Dr.-Ing. Sina Mostafawy\n\n--- Goals (EN) ---\nThe students master general and special procedures in the field of computer animation.Theoretical and mathematical basics of 3D animation.Various methods of data acquisition and data generation for animations.Real-time rendering vs. classic rendering methods. Additionally they will learn to prepare and give a presentation about a scientific topic of computeranimation.\n\n--- Goals (DE) ---\nDie Student:innen beherrschen allgemeine und spezielle Verfahren aus dem Bereich der Computeranimation. Theoretisch-mathematische Grundlagen der 3D-Animation, verschiedene Verfahren der Datenerzeugung für Animationen und Echtzeitrendering. Zusätzlich wird ein dem Kurs gelernt wie ein Vortrag recherchiert, vorbereitet und vor Publikum gehlaten wird.\n\n--- Contents (EN) ---\n- 12 Basic Principles of Animation \n- Rotation with Quaternions\n- Forward and Inverse Kinematics\n- Partikelanimation and Swarm Simulation\n- Deformation & Morphing Algorithms\n- Rigid- und Soft Bodies\n- Planing und Production of Animations\n\n--- Contents (DE) ---\n- 12 Basic Principles of Animation \n- Rotation with Quaternions\n- Forward and Inverse Kinematics\n- Partikelanimation and Swarm Simulation\n- Deformation & Morphing Algorithms\n- Rigid- und Soft Bodies\n- Planing und Production of Animations\n\n--- Literature (EN) ---\n- Computer Animation: Algorithms and Techniques, Rick Parent, 3rd 2012 \n- Advanced Animation and Renderning Techniques: Alan Watt, Mark Watt, Addision Wesley\n- Real-Time Rendering, Eric Haines, 4th 2020Computer Graphics with Open GL, Pearson Prentice Hall, 4th 2013\n\n--- Literature (DE) ---\n- Computer Animation: Algorithms and Techniques, Rick Parent, 3rd 2012 \n- Advanced Animation and Renderning Techniques: Alan Watt, Mark Watt, Addision Wesley\n- Real-Time Rendering, Eric Haines, 4th 2020Computer Graphics with Open GL, Pearson Prentice Hall, 4th 2013", "metadata": {"moduleNumber": "BCSIM 402", "moduleName": "Computer Animation", "creditPoints": "5.0", "suggestedSemester": 3, "offeredInSeason": "winter_semester", "examType": "oral_exam", "heldInLanguage": "de", "reviserName": "Prof. Dr.-Ing. Sina Mostafawy", "reviserEmail": "sina.mostafawy@hs-duesseldorf.de", "studyProgramId": 12, "source_type": "json"}}
{"id": "BCSIM_403", "text": "Title: Virtual Studio\nModule Number: BCSIM 403\nCredits: 5.0 CP\nSemester: 4\nOffered In: summer_semester\nLanguage: de\nExam Type: oral_exam\nInstructor: Prof. Dr. Eng. Univ. of Tsukuba Jens Herder\n\n--- Goals (EN) ---\nSuccessful participants will have a profound knowledge in building and developing virtual set environments for broadcasting applications and will be able to evaluate virtual studio (TV) technology. Composition of video and computer graphics under live conditions for media productions is an essential part.\n\n--- Goals (DE) ---\nStudierende können Video und Computergrafik unter Live-Bedingungen in Produktionen verbinden. Hierzu gehört die Erstellung fiktiver Umgebungen, in die Menschen und Gegenstände versetzt werden. Sie können Virtuelle Studios entwickeln, aufbauen und einsetzen.\n\n--- Contents (EN) ---\nTopics include virtual set design for artificial or real scenes, hard- and software for digital (TV) studio productions, light and light setting for TV studios, camera and actor tracking systems, motion capture, real-time computer graphics and effects, separation of image elements (e.g., chroma keying), inserting of animations and virtual characters, as well as studio production planning.\n\n--- Contents (DE) ---\nZu den Themen gehört die Wirkung künstlich erstellter Realitätsebenen, irrealer Szenenbilder und virtueller Kulissen. Bestandteile sind Hard- und Software für digitale Studioproduktionstechnik, Licht und Beleuchtung im Virtuellen Studio, Kameraverfolgungssysteme (Tracking), Bewegungsaufzeichnung, Echtzeitgenerierung dreidimensionaler Computergrafik, Herauslösen von Bildelementen (Chromakeying), Einbindung von Animationen und virtuellen Charakteren und Produktionsplanung.\n\n--- Literature (EN) ---\n- S. Gibbs. 1998. Virtual Studios. IEEE MultiMedia 5, 1 (January 1998, 17-17. DOI=10.1109/MMUL.1998.664739\n- A. R. Smith and J. F. Blinn. 1996. Blue screen matting. In Proceedings of the 23rd annual conference on Computer graphics and interactive techniques (SIGGRAPH '96). ACM, New York, NY, USA, 259-268. DOI=10.1145/237170.237263\n- R. Brinkmann: The Art and Science of Digital Compositing, Morgan Kaufman Verlag 2008\n- M. Moshkovitz: The Virtual Studio Technology & Techniques, Focal Press 2000\n- P. Tucker: Secrets of Screen Acting, Routlege Chapman & Hall 2003\n- D. Arijon: Grammar of the Film Language, Silman-James Press 1991\n- U. Schmidt: Professionelle Videotechnik: Analoge und Digitale Grundlagen, Filmtechnik, Fernsehtechnik, HDTV, Kameras, Displays, Videorecorder, Produktion und Studiotechnik, Springer Verlag 2009\n\nFurther current literature will be announced at the beginning of the course.\n\n--- Literature (DE) ---\n- S. Gibbs. 1998. Virtual Studios. IEEE MultiMedia 5, 1 (January 1998, 17-17. DOI=10.1109/MMUL.1998.664739\n- A. R. Smith and J. F. Blinn. 1996. Blue screen matting. In Proceedings of the 23rd annual conference on Computer graphics and interactive techniques (SIGGRAPH '96). ACM, New York, NY, USA, 259-268. DOI=10.1145/237170.237263\n-R. Brinkmann: The Art and Science of Digital Compositing, Morgan Kaufman Verlag 2008\n- M. Moshkovitz: The Virtual Studio Technology & Techniques, Focal Press 2000\n- P. Tucker: Secrets of Screen Acting, Routlege Chapman & Hall 2003\n- D. Arijon: Grammar of the Film Language, Silman-James Press 1991\n- U. Schmidt: Professionelle Videotechnik: Analoge und Digitale Grundlagen, Filmtechnik, Fernsehtechnik, HDTV, Kameras, Displays, Videorecorder, Produktion und Studiotechnik, Springer Verlag 2009\n\nWeitere aktuelle Literatur wird zu Beginn der LV bekannt gegeben.", "metadata": {"moduleNumber": "BCSIM 403", "moduleName": "Virtual Studio", "creditPoints": "5.0", "suggestedSemester": 4, "offeredInSeason": "summer_semester", "examType": "oral_exam", "heldInLanguage": "de", "reviserName": "Prof. Dr. Eng. Univ. of Tsukuba Jens Herder", "reviserEmail": "jens.herder@hs-duesseldorf.de", "studyProgramId": 12, "source_type": "json"}}
{"id": "BCSIM_72.02", "text": "Title: Evaluation of digital technologies\nModule Number: BCSIM 72.02\nCredits: 5.0 CP\nSemester: 7\nOffered In: winter_semester\nLanguage: de\nExam Type: research_paper\nInstructor: Prof. Dr. Alina Huldtgren\n\n--- Goals (EN) ---\n\n\n--- Goals (DE) ---\nStudierende erwerben Grundkenntnisse zentraler Begriffe im Feld technischer, sozialer und soziotechnischer Innovationen, sind mit zentralen theoretischen Ansätzen im Feld der Innovationsforschung inkl. verschiedener theoretischer Modelle von Innovationen betraut, verstehen Zusammenhänge zwischen technischer und sozialer Innovation (z. B. im Hinblick auf Durchsetzungsprozesse) und können Innovationsprozesse in ihrem systematischen Zusammenhang mit gesellschaftlichen Prozessen beschreiben und analysieren. Sie entwickeln ein Verständnis für Steuerungsmöglichkeiten von Innovationsentwicklung, können Ansätze und Konzepte zur Gestaltung von Innovationsprozessen anwenden und sie mit werteorientierten Ansätzen verbinden. Sie verfügen über die Kompetenz zur Einnahme kritischer Perspektiven auf Innovationsentwicklung und -förderung und sind in der Lage, ihren Beitrag zur Innovationsentwicklung, insbesondere im Kontext von Data Science und KI (u. a. Data-Driven-Innovation) inkl. der daraus erwachsenden Verantwortung zu reflektieren.\n\n--- Contents (EN) ---\n\n\n--- Contents (DE) ---\nDie Ziele des Moduls bestehen in der Vermittlung grundlegender Kenntnisse der Mensch-Technik-Interaktion im Kontext aktueller Forschung und Entwicklung. Studierende sollen befähigt werden, in Abhängigkeit von den Zielen ihres Studiums geeignete Fragen für die Konzeption und Realisierung von Schnittstellen zwischen Mensch und Technik unter besonderer Berücksichtigung der Merkmale künftiger Nutzergruppen, spezifischer Handlungskontexte und der zur Verfügung stehenden Ressourcen  zu formulieren. Eine wichtige Frage bildet dabei die Beteiligung potenzieller Nutzer*innen an der Schnittstellenentwicklung und der begleitenden Evaluierung im Rahmen eines iterativen Entwicklungsprozesses. Im Fokus des Moduls stehen verschiedene Methoden für Konzeption, Design, Prototyping und Evaluation deren beispielhafte Anwendung auf konkrete Felder im Kontext von Data Science und KI.  Zentraler Begriffe im Feld technischer, sozialer und soziotechnischer InnovationenGrundlagen, Methoden, Modelle und Konzepte zur Gestaltung von Benutzungsschnittstellen für interaktive AnwendungenPhysiologische und Psychologische Grundlagen der menschlichen Wahrnehmung, von Gedächtnis, Wissen, Erfahrung sowie der Handlungsregulation sowie Ihre Anwendung in der MCI Konsequenzen der Gestaltung von Hardware und Software für Nutzer Modelle der Kommunikation und Anwendung auf die MCIGestaltung von interaktiven Systemen, insbesondere webbasierte und mobile Systeme: Dialoggestaltung, Informationsdarstellung, Navigation, Orientierung, InteraktionsformenIntegration von Software-Ergonomie in Software-EngineeringNormen, gesetzliche Grundlagen und RichtlinienGrundlagen der Programmierung von GUIs\n\n--- Literature (EN) ---\n\n\n--- Literature (DE) ---\nAndreas Butz, Antonio Krüger. Mensch-Technik Interaktion, De Gruyter Oldenbourg, 2014\nKevin Liggeri, Oliver Müller. Mensch-Maschine-Interaktion: Handbuch zu Geschichte - Kultur - Ethik, JB Metzler, 2019\nMarkus Dahm: Grundlagen der Mensch-Computer-Interaktion, Pearson (2006)\nJens Jacobsen: Praxisbuch Usability und UX, Rheinwerk (2017)\nSteve Krug: Don't make me think - revisited, New Riders (2013)\nBernhard Preim, Raimund Dachselt: Interaktive Systeme Band 1 und 2, eXamen.pressDon Norman: The Design of Everyday Things, Basic Books (2013)\nMichael Richter, Markus D. Flückiger: Usability und UX kompakt: Produkte für Menschen (IT kompakt), Springer Vieweg (2016)\nWeitere Literatur wird bei Vorlesungsbeginn bekannt gegeben.", "metadata": {"moduleNumber": "BCSIM 72.02", "moduleName": "Evaluation of digital technologies", "creditPoints": "5.0", "suggestedSemester": 7, "offeredInSeason": "winter_semester", "examType": "research_paper", "heldInLanguage": "de", "reviserName": "Prof. Dr. Alina Huldtgren", "reviserEmail": "alina.huldtgren@hs-duesseldorf.de", "studyProgramId": 12, "source_type": "json"}}
{"id": "BCSIM_14", "text": "Title: Future Skills 1: Design\nModule Number: BCSIM 14\nCredits: 5.0 CP\nSemester: 1\nOffered In: winter_semester\nLanguage: de\nExam Type: see_elective\nInstructor: Prof. Dr. Alina Huldtgren\n\n--- Goals (EN) ---\nDepending on the elected course\n\n--- Goals (DE) ---\nAbhängig vom belegten Wahlmodul\n\n--- Contents (EN) ---\nThis is a subject module (compulsory elective module) for which modules from the \"Future Skills 1\" catalog of subject modules can be taken. The semester (winter semester, summer semester) in which this subject module is taken is not specified.\n\n--- Contents (DE) ---\nDas ist ein Wahlmodul (Wahlpflichtmodul), für das Module aus dem Wahlkatalog \"Future Skills 1\" belegt werden können. In welchem Semester (WiSe, SoSe) dieses Wahlmodul belegt wird, ist nicht festgelegt.\n\n--- Literature (EN) ---\nDepending on the elected course\n\n--- Literature (DE) ---\nAbhängig vom belegten Wahlmodul", "metadata": {"moduleNumber": "BCSIM 14", "moduleName": "Future Skills 1: Design", "creditPoints": "5.0", "suggestedSemester": 1, "offeredInSeason": "winter_semester", "examType": "see_elective", "heldInLanguage": "de", "reviserName": "Prof. Dr. Alina Huldtgren", "reviserEmail": "alina.huldtgren@hs-duesseldorf.de", "studyProgramId": 12, "source_type": "json"}}
{"id": "BCSIM_24", "text": "Title: Future Skills 2: Preperation for Project Work\nModule Number: BCSIM 24\nCredits: 5.0 CP\nSemester: 2\nOffered In: summer_semester\nLanguage: de\nExam Type: see_elective\nInstructor: Prof. Dr. rer. nat. Michael Marmann\n\n--- Goals (EN) ---\nDepending on the elected course\n\n--- Goals (DE) ---\nAbhängig vom belegten Wahlmodul\n\n--- Contents (EN) ---\nThis is a subject module (compulsory elective module) for which modules from the \"Future Skills 2\" catalog of subject modules can be taken. The semester (winter semester, summer semester) in which this subject module is taken is not specified.\n\n--- Contents (DE) ---\nDas ist ein Wahlmodul (Wahlpflichtmodul), für das Module aus dem Wahlkatalog \"Future Skills 2\" belegt werden können. In welchem Semester (WiSe, SoSe) dieses Wahlmodul belegt wird, ist nicht festgelegt.\n\n--- Literature (EN) ---\nDepending on the elected course\n\n--- Literature (DE) ---\nAbhängig vom belegten Wahlmodul", "metadata": {"moduleNumber": "BCSIM 24", "moduleName": "Future Skills 2: Preperation for Project Work", "creditPoints": "5.0", "suggestedSemester": 2, "offeredInSeason": "summer_semester", "examType": "see_elective", "heldInLanguage": "de", "reviserName": "Prof. Dr. rer. nat. Michael Marmann", "reviserEmail": "marmann@hs-duesseldorf.de", "studyProgramId": 12, "source_type": "json"}}
{"id": "BCSIM_51", "text": "Title: Future Skills 3: Preperation for Job\nModule Number: BCSIM 51\nCredits: 15.0 CP\nSemester: 5\nOffered In: winter_semester\nLanguage: de\nExam Type: see_elective\nInstructor: Prof. Dr. rer. nat. Michael Marmann\n\n--- Goals (EN) ---\nDepending on the elected course\n\n--- Goals (DE) ---\nAbhängig vom belegten Wahlmodul\n\n--- Contents (EN) ---\nThis is a subject module (compulsory elective module) for which modules from the \"Future Skills 3\" catalog of subject modules can be taken. The semester (winter semester, summer semester) in which this subject module is taken is not specified.\n\n--- Contents (DE) ---\nDas ist ein Wahlmodul (Wahlpflichtmodul), für das Module aus dem Wahlkatalog \"Future Skills 3\" belegt werden können. In welchem Semester (WiSe, SoSe) dieses Wahlmodul belegt wird, ist nicht festgelegt.\n\n--- Literature (EN) ---\nDepending on the elected course\n\n--- Literature (DE) ---\nAbhängig vom belegten Wahlmodul", "metadata": {"moduleNumber": "BCSIM 51", "moduleName": "Future Skills 3: Preperation for Job", "creditPoints": "15.0", "suggestedSemester": 5, "offeredInSeason": "winter_semester", "examType": "see_elective", "heldInLanguage": "de", "reviserName": "Prof. Dr. rer. nat. Michael Marmann", "reviserEmail": "marmann@hs-duesseldorf.de", "studyProgramId": 12, "source_type": "json"}}
{"id": "BCSIM_72", "text": "Title: Future Skills 4: Ethic and social responsibility\nModule Number: BCSIM 72\nCredits: 5.0 CP\nSemester: 7\nOffered In: winter_semester\nLanguage: de\nExam Type: see_elective\nInstructor: Prof. Dr. Alina Huldtgren\n\n--- Goals (EN) ---\nDepending on the elected course\n\n--- Goals (DE) ---\nAbhängig vom belegten Wahlmodul\n\n--- Contents (EN) ---\nThis is a subject module (compulsory elective module) for which modules from the \"Future Skills 4\" catalog of subject modules can be taken. The semester (winter semester, summer semester) in which this subject module is taken is not specified.\n\n--- Contents (DE) ---\nDas ist ein Wahlmodul (Wahlpflichtmodul), für das Module aus dem Wahlkatalog \"Future Skills 4\" belegt werden können. In welchem Semester (WiSe, SoSe) dieses Wahlmodul belegt wird, ist nicht festgelegt.\n\n--- Literature (EN) ---\nDepending on the elected course\n\n--- Literature (DE) ---\nAbhängig vom belegten Wahlmodul", "metadata": {"moduleNumber": "BCSIM 72", "moduleName": "Future Skills 4: Ethic and social responsibility", "creditPoints": "5.0", "suggestedSemester": 7, "offeredInSeason": "winter_semester", "examType": "see_elective", "heldInLanguage": "de", "reviserName": "Prof. Dr. Alina Huldtgren", "reviserEmail": "alina.huldtgren@hs-duesseldorf.de", "studyProgramId": 12, "source_type": "json"}}
{"id": "BCSIM_30", "text": "Title: Compulsory Elective Module 1\nModule Number: BCSIM 30\nCredits: 5.0 CP\nSemester: 3\nOffered In: winter_semester\nLanguage: de\nExam Type: see_elective\nInstructor: \n\n--- Goals (EN) ---\nDepending on the elected course\n\n--- Goals (DE) ---\nAbhängig vom belegten Wahlmodul\n\n--- Contents (EN) ---\nThis is a subject module (compulsory elective module) for which modules from the elective catalog 100, 200, 300 o 400 can be taken. The semester (winter semester, summer semester) in which this subject module is taken is not specified.\n\n--- Contents (DE) ---\nDas ist ein Wahlmodul (Wahlpflichtmodul), für das Module aus den Wahlkatalogen 100, 200, 300 oder 400 belegt werden können. In welchem Semester (WiSe, SoSe) dieses Wahlmodul belegt wird, ist nicht festgelegt.\n\n--- Literature (EN) ---\nDepending on the elected course\n\n--- Literature (DE) ---\nAbhängig vom belegten Wahlmodul", "metadata": {"moduleNumber": "BCSIM 30", "moduleName": "Compulsory Elective Module 1", "creditPoints": "5.0", "suggestedSemester": 3, "offeredInSeason": "winter_semester", "examType": "see_elective", "heldInLanguage": "de", "reviserName": "", "reviserEmail": null, "studyProgramId": 12, "source_type": "json"}}
{"id": "BCSIM_31", "text": "Title: Compulsory Elective Module 2\nModule Number: BCSIM 31\nCredits: 5.0 CP\nSemester: 3\nOffered In: winter_semester\nLanguage: de\nExam Type: see_elective\nInstructor: \n\n--- Goals (EN) ---\nDepending on the elected course\n\n--- Goals (DE) ---\nAbhängig vom belegten Wahlmodul\n\n--- Contents (EN) ---\nThis is a subject module (compulsory elective module) for which modules from the elective catalog 100, 200, 300 o 400 can be taken. The semester (winter semester, summer semester) in which this subject module is taken is not specified.\n\n--- Contents (DE) ---\nDas ist ein Wahlmodul (Wahlpflichtmodul), für das Module aus den Wahlkatalogen 100, 200, 300 oder 400 belegt werden können. In welchem Semester (WiSe, SoSe) dieses Wahlmodul belegt wird, ist nicht festgelegt.\n\n--- Literature (EN) ---\nDepending on the elected course\n\n--- Literature (DE) ---\nAbhängig vom belegten Wahlmodul", "metadata": {"moduleNumber": "BCSIM 31", "moduleName": "Compulsory Elective Module 2", "creditPoints": "5.0", "suggestedSemester": 3, "offeredInSeason": "winter_semester", "examType": "see_elective", "heldInLanguage": "de", "reviserName": "", "reviserEmail": null, "studyProgramId": 12, "source_type": "json"}}
{"id": "BCSIM_32", "text": "Title: Compulsory Elective Module 3\nModule Number: BCSIM 32\nCredits: 5.0 CP\nSemester: 3\nOffered In: winter_semester\nLanguage: de\nExam Type: see_elective\nInstructor: \n\n--- Goals (EN) ---\nDepending on the elected course\n\n--- Goals (DE) ---\nAbhängig vom belegten Wahlmodul\n\n--- Contents (EN) ---\nThis is a subject module (compulsory elective module) for which modules from the elective catalog 100, 200, 300 o 400 can be taken. The semester (winter semester, summer semester) in which this subject module is taken is not specified.\n\n--- Contents (DE) ---\nDas ist ein Wahlmodul (Wahlpflichtmodul), für das Module aus den Wahlkatalogen 100, 200, 300 oder 400 belegt werden können. In welchem Semester (WiSe, SoSe) dieses Wahlmodul belegt wird, ist nicht festgelegt.\n\n--- Literature (EN) ---\nDepending on the elected course\n\n--- Literature (DE) ---\nAbhängig vom belegten Wahlmodul", "metadata": {"moduleNumber": "BCSIM 32", "moduleName": "Compulsory Elective Module 3", "creditPoints": "5.0", "suggestedSemester": 3, "offeredInSeason": "winter_semester", "examType": "see_elective", "heldInLanguage": "de", "reviserName": "", "reviserEmail": null, "studyProgramId": 12, "source_type": "json"}}
{"id": "BCSIM_33", "text": "Title: Compulsory Elective Module 4\nModule Number: BCSIM 33\nCredits: 5.0 CP\nSemester: 3\nOffered In: winter_semester\nLanguage: de\nExam Type: see_elective\nInstructor: \n\n--- Goals (EN) ---\nDepending on the elected course\n\n--- Goals (DE) ---\nAbhängig vom belegten Wahlmodul\n\n--- Contents (EN) ---\nThis is a subject module (compulsory elective module) for which modules from the elective catalog 100, 200, 300 o 400 can be taken. The semester (winter semester, summer semester) in which this subject module is taken is not specified.\n\n--- Contents (DE) ---\nDas ist ein Wahlmodul (Wahlpflichtmodul), für das Module aus den Wahlkatalogen 100, 200, 300 oder 400 belegt werden können. In welchem Semester (WiSe, SoSe) dieses Wahlmodul belegt wird, ist nicht festgelegt.\n\n--- Literature (EN) ---\nDepending on the elected course\n\n--- Literature (DE) ---\nAbhängig vom belegten Wahlmodul", "metadata": {"moduleNumber": "BCSIM 33", "moduleName": "Compulsory Elective Module 4", "creditPoints": "5.0", "suggestedSemester": 3, "offeredInSeason": "winter_semester", "examType": "see_elective", "heldInLanguage": "de", "reviserName": "", "reviserEmail": null, "studyProgramId": 12, "source_type": "json"}}
{"id": "BCSIM_34", "text": "Title: Compulsory Elective Module 5\nModule Number: BCSIM 34\nCredits: 5.0 CP\nSemester: 3\nOffered In: winter_semester\nLanguage: de\nExam Type: see_elective\nInstructor: \n\n--- Goals (EN) ---\nDepending on the elected course\n\n--- Goals (DE) ---\nAbhängig vom belegten Wahlmodul\n\n--- Contents (EN) ---\nThis is a subject module (compulsory elective module) for which modules from the elective catalog 100, 200, 300 o 400 can be taken. The semester (winter semester, summer semester) in which this subject module is taken is not specified.\n\n--- Contents (DE) ---\nDas ist ein Wahlmodul (Wahlpflichtmodul), für das Module aus den Wahlkatalogen 100, 200, 300 oder 400 belegt werden können. In welchem Semester (WiSe, SoSe) dieses Wahlmodul belegt wird, ist nicht festgelegt.\n\n--- Literature (EN) ---\nDepending on the elected course\n\n--- Literature (DE) ---\nAbhängig vom belegten Wahlmodul", "metadata": {"moduleNumber": "BCSIM 34", "moduleName": "Compulsory Elective Module 5", "creditPoints": "5.0", "suggestedSemester": 3, "offeredInSeason": "winter_semester", "examType": "see_elective", "heldInLanguage": "de", "reviserName": "", "reviserEmail": null, "studyProgramId": 12, "source_type": "json"}}
{"id": "BCSIM_40", "text": "Title: Compulsory Elective Module 6\nModule Number: BCSIM 40\nCredits: 5.0 CP\nSemester: 4\nOffered In: summer_semester\nLanguage: de\nExam Type: see_elective\nInstructor: \n\n--- Goals (EN) ---\nDepending on the elected course\n\n--- Goals (DE) ---\nAbhängig vom belegten Wahlmodul\n\n--- Contents (EN) ---\nThis is a subject module (compulsory elective module) for which modules from the elective catalog 100, 200, 300 o 400 can be taken. The semester (winter semester, summer semester) in which this subject module is taken is not specified.\n\n--- Contents (DE) ---\nDas ist ein Wahlmodul (Wahlpflichtmodul), für das Module aus den Wahlkatalogen 100, 200, 300 oder 400 belegt werden können. In welchem Semester (WiSe, SoSe) dieses Wahlmodul belegt wird, ist nicht festgelegt.\n\n--- Literature (EN) ---\nDepending on the elected course\n\n--- Literature (DE) ---\nAbhängig vom belegten Wahlmodul", "metadata": {"moduleNumber": "BCSIM 40", "moduleName": "Compulsory Elective Module 6", "creditPoints": "5.0", "suggestedSemester": 4, "offeredInSeason": "summer_semester", "examType": "see_elective", "heldInLanguage": "de", "reviserName": "", "reviserEmail": null, "studyProgramId": 12, "source_type": "json"}}
{"id": "BCSIM_41", "text": "Title: Compulsory Elective Module 7\nModule Number: BCSIM 41\nCredits: 5.0 CP\nSemester: 4\nOffered In: summer_semester\nLanguage: de\nExam Type: see_elective\nInstructor: \n\n--- Goals (EN) ---\nDepending on the elected course\n\n--- Goals (DE) ---\nAbhängig vom belegten Wahlmodul\n\n--- Contents (EN) ---\nThis is a subject module (compulsory elective module) for which modules from the elective catalog 100, 200, 300 o 400 can be taken. The semester (winter semester, summer semester) in which this subject module is taken is not specified.\n\n--- Contents (DE) ---\nDas ist ein Wahlmodul (Wahlpflichtmodul), für das Module aus den Wahlkatalogen 100, 200, 300 oder 400 belegt werden können. In welchem Semester (WiSe, SoSe) dieses Wahlmodul belegt wird, ist nicht festgelegt.\n\n--- Literature (EN) ---\nDepending on the elected course\n\n--- Literature (DE) ---\nAbhängig vom belegten Wahlmodul", "metadata": {"moduleNumber": "BCSIM 41", "moduleName": "Compulsory Elective Module 7", "creditPoints": "5.0", "suggestedSemester": 4, "offeredInSeason": "summer_semester", "examType": "see_elective", "heldInLanguage": "de", "reviserName": "", "reviserEmail": null, "studyProgramId": 12, "source_type": "json"}}
{"id": "BCSIM_42", "text": "Title: Compulsory Elective Module 8\nModule Number: BCSIM 42\nCredits: 5.0 CP\nSemester: 4\nOffered In: summer_semester\nLanguage: de\nExam Type: see_elective\nInstructor: \n\n--- Goals (EN) ---\nDepending on the elected course\n\n--- Goals (DE) ---\nAbhängig vom belegten Wahlmodul\n\n--- Contents (EN) ---\nThis is a subject module (compulsory elective module) for which modules from the elective catalog 100, 200, 300 o 400 can be taken. The semester (winter semester, summer semester) in which this subject module is taken is not specified.\n\n--- Contents (DE) ---\nDas ist ein Wahlmodul (Wahlpflichtmodul), für das Module aus den Wahlkatalogen 100, 200, 300 oder 400 belegt werden können. In welchem Semester (WiSe, SoSe) dieses Wahlmodul belegt wird, ist nicht festgelegt.\n\n--- Literature (EN) ---\nDepending on the elected course\n\n--- Literature (DE) ---\nAbhängig vom belegten Wahlmodul", "metadata": {"moduleNumber": "BCSIM 42", "moduleName": "Compulsory Elective Module 8", "creditPoints": "5.0", "suggestedSemester": 4, "offeredInSeason": "summer_semester", "examType": "see_elective", "heldInLanguage": "de", "reviserName": "", "reviserEmail": null, "studyProgramId": 12, "source_type": "json"}}
{"id": "BCSIM_43", "text": "Title: Compulsory Elective Module 9\nModule Number: BCSIM 43\nCredits: 5.0 CP\nSemester: 4\nOffered In: summer_semester\nLanguage: de\nExam Type: see_elective\nInstructor: \n\n--- Goals (EN) ---\nDepending on the elected course\n\n--- Goals (DE) ---\nAbhängig vom belegten Wahlmodul\n\n--- Contents (EN) ---\nThis is a subject module (compulsory elective module) for which modules from the elective catalog 100, 200, 300 o 400 can be taken. The semester (winter semester, summer semester) in which this subject module is taken is not specified.\n\n--- Contents (DE) ---\nDas ist ein Wahlmodul (Wahlpflichtmodul), für das Module aus den Wahlkatalogen 100, 200, 300 oder 400 belegt werden können. In welchem Semester (WiSe, SoSe) dieses Wahlmodul belegt wird, ist nicht festgelegt.\n\n--- Literature (EN) ---\nDepending on the elected course\n\n--- Literature (DE) ---\nAbhängig vom belegten Wahlmodul", "metadata": {"moduleNumber": "BCSIM 43", "moduleName": "Compulsory Elective Module 9", "creditPoints": "5.0", "suggestedSemester": 4, "offeredInSeason": "summer_semester", "examType": "see_elective", "heldInLanguage": "de", "reviserName": "", "reviserEmail": null, "studyProgramId": 12, "source_type": "json"}}
{"id": "BCSIM_44", "text": "Title: Compulsory Elective Module 10\nModule Number: BCSIM 44\nCredits: 5.0 CP\nSemester: 4\nOffered In: summer_semester\nLanguage: de\nExam Type: see_elective\nInstructor: \n\n--- Goals (EN) ---\nDepending on the elected course\n\n--- Goals (DE) ---\nAbhängig vom belegten Wahlmodul\n\n--- Contents (EN) ---\nThis is a subject module (compulsory elective module) for which modules from the elective catalog 100, 200, 300 o 400 can be taken. The semester (winter semester, summer semester) in which this subject module is taken is not specified.\n\n--- Contents (DE) ---\nDas ist ein Wahlmodul (Wahlpflichtmodul), für das Module aus den Wahlkatalogen 100, 200, 300 oder 400 belegt werden können. In welchem Semester (WiSe, SoSe) dieses Wahlmodul belegt wird, ist nicht festgelegt.\n\n--- Literature (EN) ---\nDepending on the elected course\n\n--- Literature (DE) ---\nAbhängig vom belegten Wahlmodul", "metadata": {"moduleNumber": "BCSIM 44", "moduleName": "Compulsory Elective Module 10", "creditPoints": "5.0", "suggestedSemester": 4, "offeredInSeason": "summer_semester", "examType": "see_elective", "heldInLanguage": "de", "reviserName": "", "reviserEmail": null, "studyProgramId": 12, "source_type": "json"}}
{"id": "BCSIM_50", "text": "Title: Interdisciplinary Project\nModule Number: BCSIM 50\nCredits: 15.0 CP\nSemester: 5\nOffered In: winter_semester\nLanguage: de\nExam Type: see_elective\nInstructor: \n\n--- Goals (EN) ---\n\n\n--- Goals (DE) ---\nAbhängig vom gewählten Modul.\n\n--- Contents (EN) ---\n\n\n--- Contents (DE) ---\nDas ist ein Projektwahlmodul (Wahlpflichtmodul). Wählen Sie ein \"Interdisciplinary Project\" mit 15 oder 20 CP. Dies entscheidet darüber, wie viele CP in \"Future Skills 3\" gewählt werden müssen.\n\n--- Literature (EN) ---\n\n\n--- Literature (DE) ---\nAbhängig vom gewählten Modul.", "metadata": {"moduleNumber": "BCSIM 50", "moduleName": "Interdisciplinary Project", "creditPoints": "15.0", "suggestedSemester": 5, "offeredInSeason": "winter_semester", "examType": "see_elective", "heldInLanguage": "de", "reviserName": "", "reviserEmail": null, "studyProgramId": 12, "source_type": "json"}}
