{"id": "BDAISY__D_1.3", "text": "Title: EDIT\nModule Number: D 1.3\nCredits: 7.0 CP\nSemester: 1\nOffered In: winter_semester\nLanguage: de\nExam Type: oral_exam\nInstructor: None André Stuhlsatz\n\n--- Goals (EN) ---\nStudents have an overview of the central areas of computer science and are able to explain the relevant concepts of practical computer science and data science and apply them in practice to a limited extent. practical application, especially in combination with the other subjects of the first semester. They are able to transfer aspects of applied computer science through self-reflection and self-observation to their own life context. They are able to digitally process a current topic. If necessary, they are able to delve deeper into the areas of practical computer science presented and have a good introduction to further courses in the degree program. They can research and structure a current topic and present it at several levels of abstraction. You will be able to present a prepared topic in a tutorial group and explain it in technical terms. You can give appreciative and constructive feedback to fellow students during exercises and project presentations.\n\n--- Goals (DE) ---\nDie Studierenden kennen überblicksartig zentrale Bereiche der Informatik und können die entsprechenden Begrifflichkeiten der praktischen Informatik und Data Science erläutern und in begrenztem \nUmfang praktisch anwenden, insbesondere in Kombination mit den anderen Fächern des ersten Semesters. Sie sind in der Lage Aspekte der angewandten Informatik durch Selbstreflexion und -beobachtung auf \nihren eigenen Lebenskontext zu übertragen. Sie können ein aktuelles Thema digital aufbereiten.\nSie sind in der Lage bei Bedarf selbständig tiefer in die vorgestellten Gebiete der praktischen Informatik \neinzutauchen und besitzen einen guten Einstieg für im Studiengang weiterführenden Veranstaltungen. \nSie können ein aktuelles Thema recherchieren, strukturieren und auf mehreren Abstraktionslevels präsentieren. Sie können ein vorbereitetes Thema in einer Übungsgruppe präsentieren und grundsätzlich fachlich erläutern. Sie geben Kommilitonen im Rahmen von Übungen und Projektpräsentationen ein wertschätzendes und konstruktives Feedback.\n\n--- Contents (EN) ---\nIntroduction to practical computer science with an overview of basic computer science technologies and methods. The presentation focuses on an overview of selected fundamentals that are important for the field of data science, e.g. Information representation, modeling of knowledge, computer architecture, operating systems - Basic concepts of practical computer science, structure and history of computer science, programming paradigms (imperative, object-oriented, functional, logical, aspect-oriented) - Software engineering, modeling and processes - Operating systems and computer architecture, data science - Workflow in data analysis and visualization (data science stack) - Data science tools, development environments and libraries and their use. Implementation, presentation and communication of data science projects - Practical implementation of the concepts in a mini-project\n\n--- Contents (DE) ---\nEinführung in die praktische Informatik mit einer Übersicht grundlegender Technologien und Methoden der Informatik. Dabei konzentriert sich die Darstellung auf eine Übersicht ausgewählter Grundlagen, die für den Bereich Data Science wichtig sind, z. B. Informationsdarstellung, Modellierung von Wissen, Rechnerarchitektur, Betriebssysteme - Grundlegende Begriffe der praktischen Informatik, Struktur und Geschichte der Informatik, Programmierparadigmen (imperativ, objektorientiert, funktional, logisch, aspektorientiert) - Software Engineering, Modellierung und Prozesse - Betriebssysteme und Rechnerarchitektur, Data Science  - Workflow bei der Datenanalyse und -visualisierung (Data Science Stack) - Data Science Werkzeuge, Entwicklungsumgebungen und Bibliotheken und ihre Nutzung. Durchführung, Präsentation und Kommunikation von Data Science Projekten - Praktische Umsetzung der Konzepte in einem Mini-Projekt\n\n--- Literature (EN) ---\nH. Herold, B. Lurz, J. Wohlrab, M. Hopf. Grundlagen der Informatik (3. Auflage), Pearson. 2017 J. Grus. Data Science from Scratch, 2nd ed, OReilly. 2019 J. Plas. Python Data Science Handbook  Essential Tools for Working with Data, OReilly I. Witten, E. Frank., M. A. Hall, C. J. Pal. Data Mining  Practical Machine Learning Tools and Techniques, \nElsevier Verlag, 2016\n\n--- Literature (DE) ---\nH. Herold, B. Lurz, J. Wohlrab, M. Hopf. Grundlagen der Informatik (3. Auflage), Pearson. 2017 J. Grus. Data Science from Scratch, 2nd ed, O’Reilly. 2019 J. Plas. Python Data Science Handbook – Essential Tools for Working with Data, O’Reilly I. Witten, E. Frank., M. A. Hall, C. J. Pal. Data Mining – Practical Machine Learning Tools and Techniques, \nElsevier Verlag, 2016", "metadata": {"moduleNumber": "D 1.3", "moduleName": "EDIT", "creditPoints": "7.0", "suggestedSemester": 1, "offeredInSeason": "winter_semester", "examType": "oral_exam", "heldInLanguage": "de", "reviserName": "None André Stuhlsatz", "reviserEmail": "andre.stuhlsatz@hs-duesseldorf.de", "studyProgramId": 14, "source_type": "json"}}
{"id": "BDAISY__D_3.2", "text": "Title: Ubiquitous Computing\nModule Number: D 3.2\nCredits: 5.0 CP\nSemester: 3\nOffered In: winter_semester\nLanguage: de\nExam Type: written_exam\nInstructor: None Dorothea Schwung\n\n--- Goals (EN) ---\nStudents are able to understand the technical fundamentals of IoT applications and place them within the context of digitalization. They are familiar with key technologies and aspects relevant to the implementation of IoT solutions. Students understand security-related aspects and communication methods in the IoT. They are familiar with platforms for integrating sensors and actuators and for developing simple applications. They are capable of transferring aspects of applied computer science in the context of ubiquitous computing to their own life context through self-reflection and observation.\nStudents can digitally prepare and conceptually as well as practically develop a current topic in the field of the Internet of Things. They are able to independently delve deeper into the presented topics if needed and have a solid foundation for advanced courses in the study program. They can research, structure, and present a current topic on multiple levels of abstraction. Students can present a prepared topic in a project group and explain it in technical terms. They provide respectful and constructive feedback to their peers during exercises and project presentations.\n\n--- Goals (DE) ---\nDie Studierenden sind in der Lage die technischen Grundlagen von IoT-Anwendungen zu verstehen und \ndiese in der Anwendung in der Digitalisierung einzuordnen. Sie kennen wesentliche Technologien und \nAspekte zur Umsetzung von IoT-Lösungen. Die Studierenden kennen sicherheitsrelevante Aspekte und \nMethoden der Kommunikation im IoT. Die Studierenden kennen Plattformen zur Integration von Sensoren und Aktoren und zur Umsetzung einfacher Anwendungen. Sie sind in der Lage Aspekte der angewandten Informatik im Kontext Ubiquitous Computing durch \nSelbstreflexion und -beobachtung auf ihren eigenen Lebenskontext zu übertragen. Sie können ein aktuelles Thema im Bereich Internet of Things digital aufbereiten und konzeptionell wie auch praktisch weiterentwickeln. Sie sind in der Lage bei Bedarf selbständig tiefer in die vorgestellten Gebiete einzutauchen und besitzen \neinen guten Einstieg für im Studiengang weiterführenden Veranstaltungen. Sie können ein aktuelles \nThema recherchieren, strukturieren und auf mehreren Abstraktionsleveln präsentieren.\nSie können ein vorbereitetes Thema in einer Projektgruppe präsentieren und grundsätzlich fachlich erläutern. Sie geben Kommilitonen im Rahmen von Übungen und Projektpräsentationen ein wertschätzendes und konstruktives Feedback.\n\n--- Contents (EN) ---\n- Introduction to Ubiquitous Computing, including an overview of fundamental technologies and relevant methods from computer science and the Internet of Things - Basics of Network Technology\n- Wireless Network Protocols in the IoT - Communication Security - Arduino, Raspberry Pi, and Other Hardware Architectures - Wearable Computing: Fundamentals and Applications - Ubiquitous Computing: Fundamentals and Applications\n\n--- Contents (DE) ---\n- Einführung in Ubiquitous Computing mit einer Übersicht grundlegender Technologien und relevanter Methoden der Informatik und des Internet of Things - Grundlagen Netzwerktechnik - Funkbasierte Netzwerkprotokolle im IoT - Kommunikationssicherheit - Arduino, Raspberry PI und andere Hardwarearchitekturen - Wearable Computing Grundlagen und Anwendungen Ubiquitous Computing Grundlagen und Anwendungen\n\n--- Literature (EN) ---\nJ. Krum. Ubiquitous Computing Fundamentals. Chapman& Hall, 2009 S. Poslad. Ubiquitous Computing: Smart Devices, Environments and Interactions. Wiley, 2012 M. Mühlhäuser, I. Gurevych. Handbook of Research on Ubiquitous Computing Technology for Real \nTime Enterprises. IGI Global, ISBN 978-1-59904-832-1, 2007\n\n--- Literature (DE) ---\nJ. Krum. Ubiquitous Computing Fundamentals. Chapman& Hall, 2009 S. Poslad. Ubiquitous Computing: Smart Devices, Environments and Interactions. Wiley, 2012 M. Mühlhäuser, I. Gurevych. Handbook of Research on Ubiquitous Computing Technology for Real \nTime Enterprises. IGI Global, ISBN 978-1-59904-832-1, 2007", "metadata": {"moduleNumber": "D 3.2", "moduleName": "Ubiquitous Computing", "creditPoints": "5.0", "suggestedSemester": 3, "offeredInSeason": "winter_semester", "examType": "written_exam", "heldInLanguage": "de", "reviserName": "None Dorothea Schwung", "reviserEmail": "dorothea.schwung@hs-duesseldorf.de", "studyProgramId": 14, "source_type": "json"}}
{"id": "BDAISY__D_1.1", "text": "Title: Introduction to programming\nModule Number: D 1.1\nCredits: 8.0 CP\nSemester: 1\nOffered In: winter_semester\nLanguage: de\nExam Type: project\nInstructor: Prof. Dr. Florian Huber\n\n--- Goals (EN) ---\nBasic understanding of the structure and use of a programming language such as Python and its application in smaller projects. Students are familiar with basic terms, concepts, methods and procedures of a higher multi-paradigm programming language (Python) and can apply them in small projects. They should be able to convert simple practical tasks into a software solution by designing small programmes and completing them on computers with the help of suitable development environments and libraries. Students will master the use of central data types from Python and from some essential libraries. They will also be able to solve small to medium-sized development tasks cooperatively in a team and give their fellow students appreciative and constructive feedback during presentations.\n\n--- Goals (DE) ---\nGrundlegendes Verständnis des Aufbaus und der Verwendung einer Programmiersprache wie Python und dem Einsatz in kleineren Projekten. Die Studierenden kennen grundlegende Begriffe, Konzepte, Methoden und Verfahren einer höheren Multi-Paradigmen Programmiersprache (Python) kennen und können diese in kleinen Projekten anwenden. Sie sollen in die Lage versetzt werden, einfache Praxisaufgaben in eine softwaretechnische Lösung zu überführen, indem sie kleine Programme entwerfen und mit Hilfe von geeigneten Entwicklungsumgebungen und Bibliotheken auf Rechnern lauffähig fertigstellen. Die Studierenden beherrschen den Umgang mit zentrallen Datentypen aus Python sowie aus einigen essentiellen Bibliotheken. Sie sind weiterhin in der Lage im Team kleinere bis mittlere Entwicklungsaufgaben kooperativ zu lösen und geben Kommilitonen im Rahmen der Präsentationen ein wertschätzendes und konstruktives Feedback.\n\n--- Contents (EN) ---\nFundamental principles of higher-level programming languages are taught so that simple programmes can be understood, analysed, designed and implemented independently. The focus is on the Python programming language and the Python ecosystem. Central libraries in the context of data science/artificial intelligence are introduced and their practical use is practised.\n\n- Python basics: variables, simple data types (lists, tuples, strings, dictionaries)\n- Control structures\n- Functions, input and output\n- Exceptions & error handling\n- Object orientation in Python: classes, methods, objects, inheritance, polymorphism\n- Introduction to basic data science libraries (Numpy, Pandas)\n- Introduction to data visualisation with Python\n- Implementation of a small project in Python\n\n--- Contents (DE) ---\nGrundlegende Prinzipien höherer Programmiersprachen werden vermittelt, so dass einfache Programme verstanden, analysiert und selbst konzipiert und realisiert werden können. Der Schwerpunkt liegt dabei auf der Programmiersprache Python und dem Python-Ökosystem. Zentrale Bibliotheken im Kontext Data Science / Künstliche Intelligenz werden vorgestellt und ihr praktischer Einsatz wird geübt.\n\n- Grundlagen Python: Variablen, einfache Datentypen (Listen, Tupel, Strings, Dictionaries)\n- Kontrollstrukturen \n- Funktionen, Ein- und Ausgabe\n- Ausnahmen & Fehlerbehandlung\n- Objektorientierung in Python: Klassen, Methoden, Objekte, Vererbung, Polymorphie\n- Einführung grundlegender Data Science Bibliotheken (Numpy, Pandas)\n- Einführung Datenvisualisierung mit Python\n- Umsetzen eines kleinen Projekts in Python\n\n--- Literature (EN) ---\nJ. Zelle: Python Programming: An Introduction to Computer Science \nA. Downey: Think Python: How to Think Like a Computer Scientist, 2ed, O'Reilly Verlag \nB. Klein: Einführung in Python 3  Für Ein- und Umsteiger, Hanser Verlag\n\n--- Literature (DE) ---\nJ. Zelle: Python Programming: An Introduction to Computer Science \nA. Downey: Think Python: How to Think Like a Computer Scientist, 2ed, O'Reilly Verlag \nB. Klein: Einführung in Python 3  Für Ein- und Umsteiger, Hanser Verlag", "metadata": {"moduleNumber": "D 1.1", "moduleName": "Introduction to programming", "creditPoints": "8.0", "suggestedSemester": 1, "offeredInSeason": "winter_semester", "examType": "project", "heldInLanguage": "de", "reviserName": "Prof. Dr. Florian Huber", "reviserEmail": "florian.huber@hs-duesseldorf.de", "studyProgramId": 14, "source_type": "json"}}
{"id": "BDAISY__D_1.4", "text": "Title: Mathematics 1 for Data Science & AI\nModule Number: D 1.4\nCredits: 5.0 CP\nSemester: 1\nOffered In: winter_semester\nLanguage: de\nExam Type: written_exam\nInstructor: None Jörg Becker-Schweitzer\n\n--- Goals (EN) ---\nStudents who have completed the course are able to name and distinguish between number sets such as real, rational and natural numbers (Remember, Understand)\nThey can explain fundamental arithmetic laws such as commutativity, associativity, and distributivity and apply them correctly. (Understand, Apply)\nThey can use absolute values, exponents, and logarithms for scaling and normalization of mathematical expressions. (Apply)\nThey can interpret and apply summation and product notation in mathematical formulas. (Understand, Apply)\n\nStudents are able to formulate and solve linear systems of equations using both basic substitution and the Gaussian elimination method. (Apply)\nThey can analyze the solvability, uniqueness, and structure of possible solutions. (Analyze)\n\nThey can perform calculations with vectors and determine norms, dot products, and angles. (Apply)\nThey can execute matrix operations such as addition, multiplication, and transposition. (Apply)\nThey can compute inverses and determinants (up to 3×3 matrices) and explain their significance. (Apply, Understand)\nThey understand linear transformations, compute eigenvalues and eigenvectors, and evaluate matrix diagonalizability. (Understand, Apply, Evaluate)\n\nStudents can distinguish between linearly dependent and independent sets of vectors. (Understand)\nThey can identify bases, column spaces, and row spaces and derive the rank of a matrix. (Analyze)\nThey can explain the relationship between matrix rank and the solvability of systems of equations. (Understand, Analyze)\n\nOptional:\nThey can model lines and planes in R² / R³, calculate intersections, angles, and projections. (Apply)\nThey can determine distances between points and lines or planes and apply this knowledge as a foundation for further methods such as PCA or SVD. (Apply, Understand)\n\n--- Goals (DE) ---\nStudierende, die die Veranstaltung besucht haben, können verschiedene Zahlenbereiche wie N, Z, Q und R  benennen und unterscheiden. (Erinnern, Verstehen)\nSie erklären grundlegende Rechengesetze wie Kommutativität, Assoziativität und Distributivität und wenden diese sicher an. (Verstehen, Anwenden)\nSie nutzen Beträge, Potenzen und Logarithmen zur Skalierung und Normalisierung mathematischer Ausdrücke. (Anwenden)\nSie interpretieren und verwenden Summen- und Produktnotation in mathematischen Formeln. (Verstehen, Anwenden)\n\nStudierende können lineare Gleichungssysteme darstellen und lösen, sowohl mit einfachen Verfahren wie Substitution als auch mit dem Gauß-Algorithmus. (Anwenden)\nSie analysieren die Lösbarkeit, Eindeutigkeit und Struktur möglicher Lösungen. (Analysieren)\n\nSie rechnen mit Vektoren im R² / R³ und bestimmen Normen, Skalarprodukte und Winkel. (Anwenden)\nSie führen Matrixoperationen wie Addition, Multiplikation und Transposition korrekt aus. (Anwenden)\nSie berechnen Inverse und Determinanten (bis 3×3) und erklären deren Bedeutung. (Anwenden, Verstehen)\nSie verstehen lineare Abbildungen, berechnen Eigenwerte und Eigenvektoren und bewerten die Diagonalisierbarkeit von Matrizen. (Verstehen, Anwenden, Evaluieren)\n\nStudierende unterscheiden lineare Abhängigkeit und Unabhängigkeit von Vektoren. (Verstehen)\nSie bestimmen Basis, Spaltenraum, Zeilenraum und leiten daraus den Rang einer Matrix ab. (Analysieren)\nSie erklären den Zusammenhang zwischen Rang und Lösbarkeit von Gleichungssystemen. (Verstehen, Analysieren)\n\nOptional:\nSie modellieren Geraden und Ebenen im R² / R³, berechnen Schnittpunkte, Winkel und Projektionen. (Anwenden)\nSie ermitteln Abstände zwischen Punkten und Geraden/Ebenen und nutzen diese als Grundlage für weiterführende Methoden wie PCA oder SVD. (Anwenden, Verstehen)\n\n--- Contents (EN) ---\nThis course introduces the fundamental concepts of linear algebra, which play a central role in many applications in the natural sciences, engineering, and data science.\n\nNumber sets and algebraic foundations\n\n- Introduction to number sets: real numbers, rational numbers, natural numbers, and integers (excluding complex numbers)\n- Arithmetic rules and basic laws: commutativity, associativity, distributivity\n- Working with absolute values, powers, and logarithms (e.g., for scaling and normalization)\n- Introduction to summation and product notation\n\nLinear systems of equations\n- Representing problems as systems of linear equations\n- Solving small systems using substitution and elimination methods\n- Applying Gaussian elimination to larger systems\n- Investigating solvability, uniqueness, and the number of solutions\n\nMatrices and vectors\n- Calculations with vectors in n-dimensional space: addition, dot product, norms (L1, L2, Manhattan), angles\n- Basic matrix operations: addition, multiplication, transposition\n- Introduction to the inverse and determinant of matrices (limited to 3 by 3 matrices)\n- Linear transformations, eigenvalues, and eigenvectors\n- Diagonalizability and matrix factorization as structural tools\n\nLinear dependence and rank\n- Concept of linear dependence and independence of vectors\n- Column space, row space, and the definition of a basis\n- Importance of matrix rank for the solvability of linear systems\n\nGeometry in two- and three-dimensional space (optional)\n- Representing lines and planes in space\n- Calculating intersections, angles, and checking for orthogonality\n- Projections onto lines and planes (as a foundation for PCA and SVD)\n- Distance between a point and a line or plane\n\n--- Contents (DE) ---\nIn dieser Veranstaltung werden die grundlegenden Konzepte der linearen Algebra vermittelt, die eine zentrale Rolle für viele Anwendungen in den Natur-, Ingenieur- und Datenwissenschaften spielen:\n\nZahlenmengen & algebraische Grundlagen\n- Kennenlernen der Zahlbereiche N, Z, Q, R  (ohne komplexe Zahlen)\n- Rechenregeln und grundlegende Gesetze: Kommutativität, Assoziativität, Distributivität\n- Umgang mit Beträgen, Potenzen und Logarithmen (z.B. zur Skalierung und Normalisierung)\n- Einführung in Summen- und Produktnotation\n\nLineare Gleichungssysteme (LGS)\n- Darstellung von Problemstellungen als lineares Gleichungssystem\n- Lösung kleiner Systeme durch Substitution und Einsetzungsverfahren\n- Anwendung des Gauß-Algorithmus auf größere Systeme\n- Untersuchung von Lösbarkeit, Eindeutigkeit und Anzahl der Lösungen\n\nMatrizen & Vektoren\n- Rechnen mit Vektoren im : Addition, Skalarprodukt, Normen (L1, L2, Manhattan), Winkel\n- Grundrechenarten mit Matrizen: Addition, Multiplikation, Transposition\n- Einführung in die inverse Matrix und Determinante (beschränkt auf 3×3-Matrizen)\n- Lineare Abbildungen, Eigenwerte und Eigenvektoren\n- Diagonalisierbarkeit und Matrixfaktorisierung als Strukturwerkzeuge\n\nLineare Abhängigkeit & Rang\n- Begriff der linearen (Un-)Abhängigkeit von Vektoren\n- Spalten- und Zeilenraum, Basisdefinition\n- Bedeutung des Matrixrangs für die Lösbarkeit linearer Gleichungssysteme\n\nGeometrie im R² / R³ (optional)\n- Darstellung von Geraden und Ebenen im Raum\n- Berechnung von Schnittpunkten, Winkeln und Prüfung auf Orthogonalität\n- Projektionen auf Geraden und Ebenen (als Grundlage für PCA und SVD)\n- Abstand zwischen Punkt und Gerade bzw. Ebene\n\n--- Literature (EN) ---\n- J. Koch, M. Stämpfle: Mathematik für das Ingenieurstudium, 4. Auflage, Hanser Verlag  \n- L. Papula: Mathematik für Ingenieure und Naturwissenschaftler, Vieweg Verlag 2004  \n- T. Westermann: Mathematik für Ingenieure mit Maple, Springer Verlag 2004  \n- H. Tietze: Lineare Algebra: Eine Einführung für Studienanfänger, Springer Vieweg, 2019  \n\n- G. Strang: Introduction to Linear Algebra, 5th ed., Wellesley-Cambridge Press, 2016  \n- S. Axler: Linear Algebra Done Right, 3rd ed., Springer, 2015  \n- I. Savov: No Bullshit Guide to Linear Algebra, Minireference Co., 2018  \n- G. Strang: Video Lectures on Linear Algebra, MIT Boston, USA (Massachusetts Institute of Technology), Aufruf: 24.06.2025  \n  https://ocw.mit.edu/courses/18-06-linear-algebra-spring-2010/video_galleries/video-lectures/\n\n--- Literature (DE) ---\n- J. Koch, M. Stämpfle: Mathematik für das Ingenieurstudium, 4. Auflage, Hanser Verlag  \n- L. Papula: Mathematik für Ingenieure und Naturwissenschaftler, Vieweg Verlag 2004  \n- T. Westermann: Mathematik für Ingenieure mit Maple, Springer Verlag 2004  \n- H. Tietze: Lineare Algebra: Eine Einführung für Studienanfänger, Springer Vieweg, 2019  \n\n- G. Strang: Introduction to Linear Algebra, 5th ed., Wellesley-Cambridge Press, 2016  \n- S. Axler: Linear Algebra Done Right, 3rd ed., Springer, 2015  \n- I. Savov: No Bullshit Guide to Linear Algebra, Minireference Co., 2018  \n- G. Strang: Video Lectures on Linear Algebra, MIT Boston, USA (Massachusetts Institute of Technology), Aufruf: 24.06.2025  \n  https://ocw.mit.edu/courses/18-06-linear-algebra-spring-2010/video_galleries/video-lectures/", "metadata": {"moduleNumber": "D 1.4", "moduleName": "Mathematics 1 for Data Science & AI", "creditPoints": "5.0", "suggestedSemester": 1, "offeredInSeason": "winter_semester", "examType": "written_exam", "heldInLanguage": "de", "reviserName": "None Jörg Becker-Schweitzer", "reviserEmail": "jbs@hs-duesseldorf.de", "studyProgramId": 14, "source_type": "json"}}
{"id": "BDAISY__D_2.6", "text": "Title: Data-Visualization\nModule Number: D 2.6\nCredits: 5.0 CP\nSemester: 2\nOffered In: summer_semester\nLanguage: de\nExam Type: project\nInstructor: None Moritz Fleischmann-Bergstein\n\n--- Goals (EN) ---\n\n\n--- Goals (DE) ---\nDie Studierenden kennen die wesentlichen Begriffe der Visualisierung und typische Vorgehensweise beim Entwurf. Sie kennen darüber hinaus typische Beispiele erfolgreicher Visualisierungsprojekte und können diese erläutern und bewerten. Sie sind in der Lage typische Probleme der Informationsvisualisierung zu erkennen und auf Basis etablierter Vorgehensweisen (Workflow, InfoVis Pipeline) für multivariate Daten expressive und effektive visuelle Darstellungskonzepte zu entwickeln, mittels geeigneter Technologien (Visualisierungssysteme, Grafikbibliotheken, etc) zu realisieren und zu bewerten. Sie sind in der Lage geeignete Probleme visuell zu beschreiben und für Lösungsansätze geeignete Visualisierungen zu entwickeln. \nÜbergeordnetes Ziel ist auch, existierende Visualisierungen zu bewerten und Vor- und Nachteile spezifischer Visualisierungstechniken zu identifizieren. Die Studierenden können Visualisierungen ausgewählter Probleme gemeinsam mit anderen im Team entwickeln und auf geeignete Weise prototypisch entwickeln und präsentieren. Sie geben Kommilitonen im Rahmen der Präsentationen ein wertschätzendes und konstruktives Feedback bzgl. der entwickelten Ansätze.\n\n--- Contents (EN) ---\n\n\n--- Contents (DE) ---\nVisualisierung als essentielle Aktivität im Bereich Data Science wird theoretisch, technisch und praktisch betrachtet. Kernthemen der Veranstaltung sind die menschliche visuelle Wahrnehmung, Visualisierung multivariater Daten, und Interaktionskonzepte für Visualisierungssysteme. Auf dieser Basis werden Visualisierungsstrategien speziell im Anwendungsbereich Data Science besprochen. Darüber hinaus \nwerden Visualisierungsprobleme mit gängigen Werkzeugen und Frameworks wie Tableau, D3 und Python/ matplotlib praktisch gelöst.  Aspekte der menschlichen visuelle Wahrnehmung und Modell der Visualisierung  Visualisierung multivariater Daten Workflow und Vorgehensmodelle im Visualisierungsprozess (Visualisierungspipeline)  Interaktionskonzepte, Gestaltungsgrundlagen und Storytelling von Informationsvisualisierungen  Überblick typischer Visualsierungssysteme (Tableau, D3, Jupyter Notebook/Python/matplotlib.  Auf dieser Basis werden Visualisierungsstrategien für Graphen, Netzwerke, Baumstrukturen, Text und Zeitbasierte Daten besprochen. Darüber hinaus werden Techniken zur effizienten Nutzung begrenzter Bildschirmfläche eingeführt und fortgeschrittene Darstellungstechnologien sowie webbasierte Visualisierungsansätze berücksichtigt.\n\n--- Literature (EN) ---\n\n\n--- Literature (DE) ---\n-K. Healy: Data Visualization  A Practical Introduction. Princeton University Press, 2018\n- Chaomei Chen: Information Visualization. Beyond the Horizon. 2. Auflage, Springer London, 2004\n- Colin Ware: Information Visualization : Perception for Design Morgan Kaufmann Series in Interactive Technologies, San Francisco, 2000\n- Natha Yau: Visualize This: The Flowing Data Guide to Design, Visualization and Statistics, Wiley, 2011\n- Cole Nussbaumer Knaflic: Storytelling with Data: A Data Visualization Guide for Business Professionals, Wiley, 2015 \n- J. Steele, N. Iliinsky: Beautiful Visualization. OReilly Media, 2010 C. Rossant: Learning IPython for interactive Computing and Data Visualization (2nd ed). Pact, 2018", "metadata": {"moduleNumber": "D 2.6", "moduleName": "Data-Visualization", "creditPoints": "5.0", "suggestedSemester": 2, "offeredInSeason": "summer_semester", "examType": "project", "heldInLanguage": "de", "reviserName": "None Moritz Fleischmann-Bergstein", "reviserEmail": "moritz.fleischmann@hs-duesseldorf.de", "studyProgramId": 14, "source_type": "json"}}
{"id": "BDAISY__D_2.3", "text": "Title: Introduction to Data Science\nModule Number: D 2.3\nCredits: 5.0 CP\nSemester: 2\nOffered In: summer_semester\nLanguage: de\nExam Type: written_exam\nInstructor: Prof. Dr. Florian Huber\n\n--- Goals (EN) ---\nStudents can explain the main tasks of a data scientist. They know the main methods of a data science process and can use the right methods to analyse simple and medium-sized tasks in a focused way to get info. They can interpret the info they get and present it in a way that's easy to understand. They can develop the necessary programmes themselves using appropriate libraries or use available tools in a targeted manner. They are able to describe suitable problems from everyday life as data science problems and develop appropriate solutions.\n\n--- Goals (DE) ---\nDie Studierenden können die wesentlichen Aufgaben eines Data Scientists erläutern. Sie kennen die wesentlichen Methoden eines Data Science Prozesses und können einfache und mittlere Aufgabenstellungen zielgerichtet mit den geeigneten Methoden auswerten, um Informationen zu gewinnen. Sie können die gewonnenen Informationen interpretieren und verständlich darstellen und präsentieren. Die dazu benötigten Programme können sie unter Verwendung geeigneter Bibliotheken selbst entwickeln bzw. verfügbare Werkzeuge zielgerecht einsetzen. Sie sind in der Lage geeignete Probleme aus dem täglichen Leben als Data Science-Problem zu beschreiben und geeignete Lösungsansätze zu entwickeln.\n\n--- Contents (EN) ---\nThis course starts by defining what data science is, where it can be applied, and also examining its ethical and societal impacts. We then explore the nature of data, its various types, and the end-to-end workflow that turns raw inputs into actionable insights. From there, the course guides students through acquiring and preparing datasets, cleaning and pre-processing information, and conducting their first exploratory analyses to uncover patterns. A large part of this course will be introducing and applying key data science techniques such as correlation analysis, clustering, and dimensionality reduction to reveal deeper structure. Basic techniques from supervised machine learning are introduced and applied, followed by an introduction to modern handling of text data, before concluding with an introduction to graph representations.\n\n--- Contents (DE) ---\nDieser Kurs beginnt mit einer Definition des Begriffs \"Data Science\", seiner Anwendungsbereiche und möglicher ethischen und gesellschaftlichen Auswirkungen. Anschließend werden die Grundlege Eigenschaften im Umgang mit Daten erlernt und der Prozess von Rohdaten zu verwertbaren Erkenntnissen skizziert. Daraufhin werden die Studierenden in die Beschaffung, Aufbereitung und Bereinigung von Datensätzen, sowie die Durchführung erster explorativer Analysen zur Aufdeckung von Mustern eingeführt. Ein großer Teil dieses Kurses befasst sich mit der Einführung und Anwendung wichtiger Data-Science-Techniken wie der Korrelationsanalyse, Clustering und Dimensionsreduktion, um tiefere Strukturen aufzudecken. Es werden grundlegende Techniken aus dem überwachten maschinellen Lernen vorgestellt und angewendet, gefolgt von einer Einführung in den modernen Umgang mit Textdaten, bevor der Kurs mit einer Einführung in Graph-Darstellungen abgeschlossen wird.\n\n--- Literature (EN) ---\nFlorian Huber, \"Hands-on Introduction to Data Science with Python\", 2025, https://doi.org/10.5281/zenodo.10074474, online:\nhttps://florian-huber.github.io/data_science_course/\n\n--- Literature (DE) ---\nFlorian Huber, \"Hands-on Introduction to Data Science with Python\", 2025, https://doi.org/10.5281/zenodo.10074474, online:\nhttps://florian-huber.github.io/data_science_course/", "metadata": {"moduleNumber": "D 2.3", "moduleName": "Introduction to Data Science", "creditPoints": "5.0", "suggestedSemester": 2, "offeredInSeason": "summer_semester", "examType": "written_exam", "heldInLanguage": "de", "reviserName": "Prof. Dr. Florian Huber", "reviserEmail": "florian.huber@hs-duesseldorf.de", "studyProgramId": 14, "source_type": "json"}}
{"id": "BDAISY__D_2.2", "text": "Title: Databases\nModule Number: D 2.2\nCredits: 5.0 CP\nSemester: 2\nOffered In: summer_semester\nLanguage: de\nExam Type: written_exam\nInstructor: \n\n--- Goals (EN) ---\nStudents gain a solid understanding of the architectures and core principles of modern data and information systems and are able to contextualize and evaluate them appropriately. They understand key concepts such as layered architectures, distribution, and maturity models (e.g., Capability Maturity Model), and are capable of assessing their relevance for the development of scalable and reliable systems.\n\nThey analyze system requirements, model data structures using established methods such as the Entity-Relationship model or Unified Modeling Language (UML), and apply relational, object-oriented, and semantic data models in a targeted manner. They use various query languages and interfaces such as SQL, REST, or Java to integrate processes and design effective data flows.\n\nFurthermore, students are able to understand and apply modern database technologies such as document-based NoSQL databases (e.g., MongoDB) and vector databases (e.g., Annoy, pgVector), especially in the context of AI-powered search and the processing of unstructured data. They assess storage and access methods such as indexing, compression, and encryption, while also considering data protection and information security.\n\nIn practice-oriented projects, students plan, coordinate, and implement data-driven applications in team settings. They document their work, visualize results for specific audiences, and critically reflect on both the technical implementation and collaborative processes. Overall, they acquire the ability to not only develop complex information systems but also to evaluate and further refine them with regard to quality, scalability, and user orientation.\n\n--- Goals (DE) ---\nDie Studierenden verstehen grundlegende Architekturen und Prinzipien moderner Daten- und Informationssysteme und können diese kontextgerecht einordnen. Sie kennen Konzepte wie Schichtenmodelle, Verteilung und Reifegradmodelle (z.B. Capability Maturity Model) und sind in der Lage, deren Bedeutung für die Entwicklung skalierbarer und zuverlässiger Systeme zu beurteilen.\n\nSie analysieren Anforderungen an datenbasierte Systeme, modellieren Datenstrukturen mit etablierten Verfahren wie dem Entity-Relationship-Modell oder der Unified Modeling Language (UML) und wenden relationale, objektorientierte und semantische Datenmodelle zielgerichtet an. Dabei setzen sie verschiedene Abfragesprachen und Schnittstellen wie SQL, REST oder Java ein, um Prozesse zu integrieren und Datenströme effektiv zu gestalten.\n\nDarüber hinaus sind die Studierenden in der Lage, moderne Datenbanksysteme wie dokumentenbasierte NoSQL-Datenbanken (z.B. MongoDB) sowie Vektordatenbanken (z.B. Annoy, pgVector) zu verstehen und anzuwenden, insbesondere im Kontext KI-gestützter Suche und unstrukturierter Datenverarbeitung. Sie beurteilen Speicher- und Zugriffsmethoden wie Indexierung, Komprimierung und Verschlüsselung und berücksichtigen dabei auch Aspekte des Datenschutzes und der Datensicherheit.\n\nIn praxisnahen Projekten planen, koordinieren und realisieren sie gemeinsam im Team datengetriebene Anwendungen. Sie dokumentieren ihre Arbeit, visualisieren Ergebnisse zielgruppengerecht und reflektieren sowohl die technische Umsetzung als auch die Teamprozesse. Insgesamt erwerben sie die Fähigkeit, komplexe Informationssysteme nicht nur technisch umzusetzen, sondern auch im Hinblick auf Qualität, Skalierbarkeit und Nutzerorientierung zu bewerten und weiterzuentwickeln.\n\n--- Contents (EN) ---\nStudents are introduced to key concepts, technologies, and methods for designing, modeling, and implementing modern data and information systems. The module focuses on architectural principles, both structured and unstructured data models, as well as current storage and access technologies:\n\n- Layered models and architectures of distributed data and information systems\n- Core principles of scalability, distribution, redundancy, and maturity models (e.g., Capability Maturity Model)\n- Requirements analysis, data modeling, and quality assurance in information systems\n- Data modeling using relational, object-oriented, and semantic approaches (e.g., Entity-Relationship, UML, RDF)\n- Query languages and interfaces: SQL, REST, Java (integration of data-driven processes)\n- Fundamentals and application of NoSQL databases (e.g., MongoDB) for flexible, document-based structures\n- Introduction to vector databases (e.g., Annoy, pgVector) for efficient similarity search in AI-supported systems\n- Data storage techniques: indexing, compression, encryption, and data hierarchy\n- Metadata management and content-based search in large, heterogeneous data sets (e.g., tables, texts, images)\n- Fundamentals of data protection and information security in data-driven systems\n- Practical implementation in team projects, including project coordination, programming, visualization, presentation, and reflection\n\n--- Contents (DE) ---\nDie Studierenden lernen zentrale Konzepte, Technologien und Verfahren zur Konzeption, Modellierung und Umsetzung moderner Daten- und Informationssysteme kennen. Der Schwerpunkt liegt auf architekturellen Prinzipien, strukturierten und unstrukturierten Datenmodellen sowie aktuellen Speicher- und Zugriffstechnologien:\n\n- Schichtenmodelle und Architekturen verteilter Daten- und Informationssysteme\n- Grundprinzipien von Skalierung, Verteilung, Redundanz und Reifegradmodellen (z.B. Capability Maturity Model)\n- Anforderungsanalyse, Datenmodellierung und Qualitätssicherung von Informationssystemen\n- Datenmodellierung mit relationalen, objekt-orientierten und semantischen Ansätzen (z.B. Entity-Relationship, UML, RDF)\n- Abfragesprachen und Schnittstellen: SQL, REST, Java (Einbindung datengetriebener Prozesse)\n- Grundlagen und Anwendung von NoSQL-Datenbanken (z.B. MongoDB) für flexible, dokumentenbasierte Strukturen\n- Einführung in Vektordatenbanken (z.B. Annoy, pgVector) zur effizienten Ähnlichkeitssuche in KI-gestützten Systemen\n- Verfahren zur Datenspeicherung: Indexierung, Komprimierung, Verschlüsselung, Hierarchisierung\n- Metadatenmanagement und inhaltsbasierte Suche in großen, heterogenen Datenbeständen (z.B. Tabellen, Texte, Bilder)\n- Grundlagen zu Datenschutz und Datensicherheit in datengetriebenen Systemen\n- Praktische Umsetzung in Teamprojekten inkl. Projektkoordination, Programmierung, Visualisierung, Präsentation und Reflexion\n\n--- Literature (EN) ---\nWill be announced in the lecture\n\n--- Literature (DE) ---\nWird in der Veranstaltung bekannt gegeben", "metadata": {"moduleNumber": "D 2.2", "moduleName": "Databases", "creditPoints": "5.0", "suggestedSemester": 2, "offeredInSeason": "summer_semester", "examType": "written_exam", "heldInLanguage": "de", "reviserName": "", "reviserEmail": null, "studyProgramId": 14, "source_type": "json"}}
{"id": "BDAISY__D_2.1", "text": "Title: Fundamentals of the Internet\nModule Number: D 2.1\nCredits: 5.0 CP\nSemester: 2\nOffered In: summer_semester\nLanguage: de\nExam Type: portfolio\nInstructor: None Osmanbey Uzunkol\n\n--- Goals (EN) ---\nStudents are able to understand the technical fundamentals of internet technologies and apply and contextualize them within the broader framework of digitalization. They possess a solid theoretical foundation and familiarity with key models of computer networks, enabling them to classify and analyze network structures effectively. They are well-versed in the essential standards of network protocols and capable of applying various architectural models, protocols, and technologies relevant to implementing internet technologies.\n\nThanks to the practical components of the course, students are also equipped to configure and build computer networks, as well as to carry out error analyses based on the ISO/OSI reference model. They understand how the internet functions and can situate the technologies and protocols it uses within a broader conceptual and technical context. Building on this knowledge, students are capable of practically working with REST services and developing an understanding of distributed computing systems and cloud technologies.\n\nAn overarching objective of the course is to equip students with the methodological skills needed to approach problem-solving in the realm of internet-based AI and data science challenges. In advanced courses within the Professional Focus tracks, students are further empowered to independently tackle problems and explore web-based solutions. They learn to collaboratively develop fundamental solution ideas and to present their results in an appropriate and effective manner. As part of their presentations, they also learn to give their peers respectful and constructive feedback.\n\n--- Goals (DE) ---\nDie Studierenden sind in der Lage, die technischen Grundlagen von Internettechnologien zu verstehen und diese im Kontext der Digitalisierung anzuwenden und einzuordnen. Sie verfügen über theoretische Grundlagen und Modelle der Computernetzwerke, um diese zu klassifizieren und zu analysieren. Sie kennen die wesentlichen Standards von Protokollen in Computernetzen. Sie sind in der Lage, unterschiedliche Architekturformen, Protokolle und Technologien zur Umsetzung von Internettechnologien anzuwenden. Durch den praktischen Anteil der Vorlesung sind sie weiterhin in der Lage, Netzwerke zu konfigurieren und aufzubauen sowie Fehleranalysen nach dem ISO/OSI-Referenzmodell durchzuführen. Sie verstehen die Funktionsweise des Internets und können die darin verwendeten Technologien und Protokolle einordnen. Darauf aufbauend sind die Studierenden in der Lage, REST-Services praktisch zu nutzen und verteilte Computer- und Cloud-Systeme zu verstehen. Ein übergeordnetes Ziel ist es außerdem, die notwendige Vorgehensweise bei der Lösungsfindung für internetbasierte KI- und Data-Science-Probleme zu erlernen. In weiterführenden Veranstaltungen der Professional Fokusse (PF) werden die Studierenden dazu befähigt, sich bei Bedarf selbstständig mit Problemen und webbasierten Lösungen auseinanderzusetzen. Studierende können grundlegende Lösungsideen gemeinsam mit anderen entwickeln und auf geeignete Weise präsentieren. Sie geben ihren Kommilitoninnen und Kommilitonen im Rahmen von Präsentationen wertschätzendes und konstruktives Feedback.\n\n--- Contents (EN) ---\nThis module provides participants with an introduction to internet technologies that are essential in the context of digitalization. It enables students to understand and conceptually classify the use of these technologies, as well as to independently implement basic configurations of computer networks and internet-based applications. The foundational knowledge conveyed in this module prepares students for further in-depth study, either through self-guided learning or elective courses.\n\nKey topics include the fundamentals of computer networks, focusing on models such as the ISO/OSI reference model and the TCP/IP model. Various network protocols are introduced, including HTTP, SMTP, SSH, TLS, TCP/UDP, and IP. Students also explore different architectural models, such as client-server structures, service-oriented architectures (SOA), microservices, and layered architectures. An emphasis is placed on network security concepts, particularly the use of TLS, as well as on interface technologies like REST. The module concludes with the discussion of selected practical applications, providing a well-rounded perspective on how internet technologies are applied in real-world digital environments.\n\n--- Contents (DE) ---\nDieses Modul vermittelt dem Teilnehmer einen Einstieg in für die Digitalisierung relevante Internettechnologien, um den Einsatz dieser Technologien konzeptionell einordnen und einfache Konfigurationen der Computernetze und Internetanwendungen selbst umsetzen zu können. Die vermittelten Grundlagen befähigen den Studierenden zu einer eigenständigen oder in wahlfreien Veranstaltungen angebotenen Vertiefung. Grundlagen der Computernetze: ISO/OSI-Referenzmodell, TCP/IP-Referenzmodell+Protokolle: HTTP, SMTP, SSH, TLS, TCP/UDP, IP+Architekturformen: Client-/Server, SOA, Microservices, Schichtenarchitekturen+Netzwerksicherheit:TLS +Schnittstellentechnologien: REST+Ausgewählte Anwendungen.\n\n--- Literature (EN) ---\nJ. F. Kurose, K. Ross: Computernetzwerke: Der Top-Down-Ansatz, Pierson-Verlag, 2008. A. S. Tanenbaum, D. J. Wetherall: Computernetze, Pierson-Verlag, 2013.\n\n--- Literature (DE) ---\nJ. F. Kurose, K. Ross: Computernetzwerke: Der Top-Down-Ansatz, Pierson-Verlag, 2008. A. S. Tanenbaum, D. J. Wetherall: Computernetze, Pierson-Verlag, 2013.", "metadata": {"moduleNumber": "D 2.1", "moduleName": "Fundamentals of the Internet", "creditPoints": "5.0", "suggestedSemester": 2, "offeredInSeason": "summer_semester", "examType": "portfolio", "heldInLanguage": "de", "reviserName": "None Osmanbey Uzunkol", "reviserEmail": "osmanbey.uzunkol@hs-duesseldorf.de", "studyProgramId": 14, "source_type": "json"}}
{"id": "BDAISY__D_2.4", "text": "Title: Mathematics 2 for Data Science & AI\nModule Number: D 2.4\nCredits: 5.0 CP\nSemester: 2\nOffered In: summer_semester\nLanguage: de\nExam Type: written_exam\nInstructor: Prof. Dr. Dennis Müller\n\n--- Goals (EN) ---\nStudents who have completed the course are able to recall and explain the structure and properties of number sets, such as natural, integer, rational, and real numbers, and understand key concepts such as intervals, supremum, and infimum. They can interpret and represent functions in multiple formsexplicitly, graphically, and in tablesand distinguish between various types of functions including linear, quadratic, exponential, logarithmic, and typical machine learning activation functions like sigmoid, tanh, and ReLU. They are able to analyze and compose functions, identify inverse and piecewise-defined functions, and apply function concepts in different contexts. Students can understand and apply the concept of limits and continuity, compute limits using standard rules, and examine sequences and series as foundational tools. They are capable of deriving and interpreting derivatives both algebraically and geometrically, apply standard differentiation rules, and compute derivatives of elementary functions. They can also extend their knowledge to higher-order derivatives. In the application of derivatives, students can determine local extrema, investigate monotonicity and concavity, identify inflection points, and use Taylor approximations and Newtons method to analyze and solve problems. They are introduced to multivariable functions, can compute partial derivatives and basic gradients, and interpret these in higher-dimensional contexts such as level sets and slope direction. Finally, students are able to compute antiderivatives, apply standard rules of integration, and interpret definite integrals as areas under curves. These competencies span multiple cognitive levels including remembering, understanding, applying, analyzing, and evaluating.\n\n--- Goals (DE) ---\nStudierende, die die Veranstaltung abgeschlossen haben, können die Struktur und Eigenschaften von Zahlmengen wie natürlichen, ganzen, rationalen und reellen Zahlen wiedergeben und zentrale Konzepte wie Intervalle, Supremum und Infimum verständlich erklären. Sie sind in der Lage, Funktionen in verschiedenen Darstellungsformen  explizit, grafisch und tabellarisch  zu interpretieren und zwischen unterschiedlichen Funktionstypen zu unterscheiden, darunter lineare, quadratische, exponentielle, logarithmische sowie typische Aktivierungsfunktionen aus dem maschinellen Lernen wie Sigmoid, tanh und ReLU. Sie können Funktionen zusammensetzen, Umkehrfunktionen identifizieren und stückweise definierte Funktionen analysieren und anwenden. Darüber hinaus verstehen sie den Grenzwertbegriff, können Grenzwerte mit Rechenregeln berechnen und die Konzepte von Stetigkeit, Folgen und Reihen einordnen und nutzen. Studierende können Ableitungen sowohl algebraisch berechnen als auch geometrisch als Tangentensteigungen interpretieren. Sie wenden die Standardregeln der Differentiation an und leiten elementare Funktionen sicher ab, auch in höheren Ableitungen. In der Anwendung der Ableitung identifizieren sie Extremstellen, analysieren Monotonie und Krümmung, erkennen Wendepunkte und nutzen Taylor-Approximationen sowie das Newton-Verfahren zur Problemlösung. Sie werden in mehrdimensionale Funktionen eingeführt, berechnen partielle Ableitungen und einfache Gradienten und interpretieren diese in höheren Dimensionen, zum Beispiel anhand von Niveauflächen und Steigungsrichtungen. Schließlich berechnen sie Stammfunktionen und bestimmte Integrale, wenden Integrationsregeln an und deuten bestimmte Integrale als Flächeninhalte unter Kurven.\n\n--- Contents (EN) ---\nThis course introduces fundamental concepts of calculus, which are essential for mathematical modeling, scientific applications, and many aspects of machine learning:\n\nNumber Sets and Real Numbers / Review\n- Structure and properties of natural, integer, rational, and real numbers\n- Intervals, supremum and infimum (explained intuitively)\n- Absolute value, sign function, and inequalities involving absolute values\n\nFunctions: Fundamentals\n- Concept of a real-valued function of a real variable\n- Representations: explicit, graphical, and tabular\n- Common function types: linear, quadratic, exponential\n- Logarithmic functions with a focus on data scaling\n- Power functions as well as sigmoid, tanh, and ReLU as typical activation functions in machine learning\n- Composition and inverse functions (basic concepts)\n- Piecewise-defined functions\n\nLimits and Continuity\n- Introduction to the concept of limits (concrete, not overly formal)\n- Calculation rules for limits\n- Definition and examples of continuity\n- Sequences and series as foundational tools for limits\n\nDifferential Calculus in One Variable\n- Definition of the derivative and its geometric meaning as the slope of the tangent\n- Differentiation rules: product, quotient, and chain rule\n- Derivatives of elementary functions (exponential, logarithmic, polynomial, trigonometric)\n- Introduction to higher-order derivatives\n\nApplications of the Derivative\n- Determining local extrema (minima, maxima)\n- Analyzing monotonicity, concavity, and inflection points\n- Introduction to Taylor approximation\n- Newton's method for finding roots\n\nIntroduction to Multivariable Functions\n- Basics of functions with several variables\n- Partial derivatives\n- Gradient as directional derivative (fundamentals)\n- Interpretation in higher dimensions: level sets and slope direction\n\nIntegral Calculus (Basics)\n- Antiderivatives and indefinite integrals\n- Basic rules of integration\n- Definite integrals interpreted as area under a curve\n\n--- Contents (DE) ---\nIn dieser Veranstaltung werden grundlegende Konzepte der Analysis behandelt, die zentral für mathematische Modellierung, naturwissenschaftliche Anwendungen und viele Aspekte des maschinellen Lernens sind:\n\nZahlenmengen und reelle Zahlen / Wiederholung\n- Aufbau und Eigenschaften der natürlichen, ganzen, rationalen und reellen Zahlen\n- Intervalle sowie Supremum und Infimum (intuitiv erklärt)\n- Betrag, Vorzeichenfunktion und Betragsungleichungen\n\nFunktionen: Grundlagen\n- Begriff der Funktion von einer reellen Zahl in eine reelle Zahl\n- Darstellungsmöglichkeiten: explizit, graphisch und tabellarisch\n- Typische Funktionstypen: linear, quadratisch, exponentiell\n- Logarithmusfunktionen mit Fokus auf Datenskalierung\n- Potenzfunktionen sowie sigmoid, tanh und ReLU als ML-Aktivierungsfunktionen\n- Komposition und Umkehrfunktionen (grundlegende Konzepte)\n- Stückweise definierte Funktionen\n\nGrenzwerte und Stetigkeit\n- Einführung in das Grenzwertkonzept (konkret, nicht formalisiert)\n- Rechenregeln für Grenzwerte\n- Definition und Beispiele zur Stetigkeit von Funktionen\n- Folgen und Reihen als Grundlage des Grenzwertbegriffs\n\nDifferentialrechnung in einer Variablen\n- Definition der Ableitung und ihre geometrische Bedeutung als Tangentensteigung\n- Ableitungsregeln: Produkt-, Quotienten- und Kettenregel\n- Ableitungen elementarer Funktionen (Exponential-, Logarithmus-, Polynom-, trigonometrische Funktionen)\n- Einführung in höhere Ableitungen\n\nAnwendungen der Ableitung\n- Bestimmung lokaler Extremwerte (Minima, Maxima)\n- Analyse von Monotonie, Krümmung und Wendepunkten\n- Einführung in die Taylor-Approximation\n- Newton-Verfahren zur Nullstellenbestimmung\n\nEinführung in multivariate Funktionen\n- Grundlagen mehrerer Variablen: Funktionen mit mehreren Argumenten\n- Partielle Ableitungen\n- Gradient als Richtungsableitung (Grundlagen)\n- Interpretation in mehreren Dimensionen: Niveauflächen und Steigungsrichtung\n\nIntegralrechnung (Grundlagen)\n- Stammfunktion und unbestimmtes Integral\n- Grundlegende Rechenregeln für Integrale\n- Bestimmtes Integral als Flächeninhalt unter Funktionsgraphen\n\n--- Literature (EN) ---\nWill be announced during the lecture\n\n--- Literature (DE) ---\nWird in der Veranstaltung bekannt gegeben", "metadata": {"moduleNumber": "D 2.4", "moduleName": "Mathematics 2 for Data Science & AI", "creditPoints": "5.0", "suggestedSemester": 2, "offeredInSeason": "summer_semester", "examType": "written_exam", "heldInLanguage": "de", "reviserName": "Prof. Dr. Dennis Müller", "reviserEmail": "dennis.mueller@hs-duesseldorf.de", "studyProgramId": 14, "source_type": "json"}}
{"id": "BDAISY__D_2.5", "text": "Title: Digital Ethics\nModule Number: D 2.5\nCredits: 5.0 CP\nSemester: 2\nOffered In: summer_semester\nLanguage: de\nExam Type: written_exam\nInstructor: None Martin Doll\n\n--- Goals (EN) ---\nStudents are able to identify the social and ethical dimensions of digital technologies. They have a basic understanding of how to assess the opportunities and risks associated with digital technological developments. They are able to develop approaches to mitigate negative impacts or strengthen positive effects of digitalisation  particularly in the context of implementing artificial intelligence. They can evaluate these approaches using ethical frameworks and critically reflect on their own roles as technology developers within these processes.\n\n--- Goals (DE) ---\nDie Studierenden können die sozialen und ethischen Aspekte digitaler Technologien erkennen und haben ein grundlegendes Verständnis für die Abschätzung von Chancen und Risiken, die digitaltechnische Entwicklungen in sich tragen können. Sie sind in der Lage, Ansätze zur Vermeidung negativer Folgen bzw. der Verstärkung positiver Folgen von Digitalisierung (insbesondere dem Einsatz von Künstlicher Intelligenz) zu entwickeln, diese anhand ethischer Ansätze zu bewerten und ihre eigene Position als Technikentwickler*innen in diesen Prozessen zu reflektieren.\n\n--- Contents (EN) ---\nThe module aims to convey the social, ethical, and media studies foundations of technologisation, with a particular focus on digitalisation processes. It teaches relevant analytical skills and encourages critical reflection on the role of technology developers. The module contributes to an understanding of digital transformation as a socio-technical process and supports its ethical assessment.\n- Theoretical approaches to describing and analysing (digital) technologies in social contexts, including theories of technology and philosophy of technology\n- Foundations of ethics: utilitarianism, Kantian ethics, and virtue ethics\n- Technology assessment\n- Core principles of technology ethics and digital ethics\n- Value-sensitive design\n- Addressing value conflicts and moral dilemmas using real-world examples\n- Ethical analyses of selected application areas of digital technologies, including the examination of standard ethical frameworks (e.g. IEEE Std 7000-2021)\n\n--- Contents (DE) ---\nDie Ziele des Moduls bestehen in der Vermittlung sozialer und ethischer sowie medienwissenschaftlicher Grundlagen von Technisierungs-, insb. Digitalisierungsprozessen, der Vermittlung relevanter Analysekompetenzen in diesem Feld sowie der Reflexion der Rolle als Technikentwickler*in. Das Modul leistet einen Beitrag dazu, die digitale Transformation und ihre Folgen als soziotechnischen Prozess zu verstehen und ethisch einzuordnen. \n- Theoretische Ansätze zur Beschreibung und Analyse von (digitalen) Technologien im sozialen Kontext, inkl. Techniktheorie und Technikphilosophie\n- Grundlagen der Ethik: Utilitarismus, kantische Ethik und Tugendethik\n- Technikfolgenabschätzung\n- Prinzipien der Technikethik und Digitalen Ethik\n- Werte-basierte Ausgestaltung von Technologie bzw. Value Sensitive Design\n- Beschäftigung mit Wertekonflikten und ethischen Dilemmata anhand konkreter Beispiele aus der Praxis\n- Ethische Analysen am Beispiel ausgewählter Anwendungsfelder digitaler Technologien bis hin zur Auseinandersetzung mit Standardmodellen (z.B. IEEE Std 7000-2021)\n\n--- Literature (EN) ---\nFloridi, L. (2023). The Ethics of Artificial Intelligence: Principles, Challenges, and Opportunities. Oxford, UK: Oxford University Press\nGrunwald, A. u. Hillerbrand, R. (eds.) (2021). Handbuch Technikethik, 2. Aufl. Berlin: Springer / Metzler\nIEEE (2021). IEEE Std 7000-2021. IEEE Standard Model Process for Addressing Ethical Concerns during System Design. Piscataway: IEEE.\nLatour, B. (2010). Eine neue Soziologie für eine neue Gesellschaft. Einführung in die Akteur-Netzwerk-Theorie. Frankfurt a.M.: Suhrkamp\nMainzer, K. (ed.) (2021). Philosophisches Handbuch Künstliche Intelligenz, Wiesbaden: Springer Fachmedien\nMisselhorn, C. (2018). Grundfragen der Maschinenethik. Ditzingen: Reclam\nSimondon, G. (2012). Die Existenzweise technischer Objekte. Zürich u.a.: diaphanes\nSimonis, G. (eds.) (2012). Konzepte und Verfahren der Technikfolgenabschätzung. Wiesbaden: Springer VS\nSpiekermann, S. (2021). Digitale Ethik. Ein Wertesystem für das 21. Jahrhundert. München: Droemer\n\n--- Literature (DE) ---\nFloridi, L. (2023). The Ethics of Artificial Intelligence: Principles, Challenges, and Opportunities. Oxford, UK: Oxford University Press\nGrunwald, A. u. Hillerbrand, R. (Hrsg.) (2021). Handbuch Technikethik, 2. Aufl. Berlin: Springer / Metzler\nIEEE (2021). IEEE Std 7000-2021. IEEE Standard Model Process for Addressing Ethical Concerns during System Design. Piscataway: IEEE.\nLatour, B. (2010). Eine neue Soziologie für eine neue Gesellschaft. Einführung in die Akteur-Netzwerk-Theorie. Frankfurt a.M.: Suhrkamp\nMainzer, K. (Hrsg.) (2021). Philosophisches Handbuch Künstliche Intelligenz, Wiesbaden: Springer Fachmedien\nMisselhorn, C. (2018). Grundfragen der Maschinenethik. Ditzingen: Reclam\nSimondon, G. (2012). Die Existenzweise technischer Objekte. Zürich u.a.: diaphanes\nSimonis, G. (Hrsg.) (2012). Konzepte und Verfahren der Technikfolgenabschätzung. Wiesbaden: Springer VS\nSpiekermann, S. (2021). Digitale Ethik. Ein Wertesystem für das 21. Jahrhundert. München: Droemer", "metadata": {"moduleNumber": "D 2.5", "moduleName": "Digital Ethics", "creditPoints": "5.0", "suggestedSemester": 2, "offeredInSeason": "summer_semester", "examType": "written_exam", "heldInLanguage": "de", "reviserName": "None Martin Doll", "reviserEmail": "martin.doll@hs-duesseldorf.de", "studyProgramId": 14, "source_type": "json"}}
{"id": "BDAISY__D_3.3", "text": "Title: EDIT\nModule Number: D 3.3\nCredits: 5.0 CP\nSemester: 3\nOffered In: winter_semester\nLanguage: de\nExam Type: written_exam\nInstructor: Prof. Dr. Dennis Müller\n\n--- Goals (EN) ---\nUpon successful completion of the module, students are able to\n\nDetermine regression and classification models using linear and logistic methods,\n\nFind linear separating hyperplanes in high-dimensional spaces using a kernelized support vector machine,\n\nSelect different loss functions for optimizing regression problems purposefully and solve the resulting optimization problem,\n\nIdentify and interpret important metrics and measures (e.g., accuracy, precision, recall) of classification models,\n\nIndependently train perceptrons and multilayer neural networks using appropriate methods,\n\nImplement and train simple neural networks in PyTorch using training data.\n\n--- Goals (DE) ---\nMit dem erfolgreichen Absolvieren des Moduls sind Studierende in der Lage\n\nRegressions- und Klassifikationsmodelle mit Hilfe linearer sowie logistischer Methoden zu bestimmen,\n\nLineare Trennebenen in hochdimensionalen Räumen mit Hilfe einer kernelisierten Support-Vektor-Maschine zu finden,\n\nUnterschiedliche Loss-Funktionen zur Optimierung von Regressionsproblemen zielgerichtet auszuwählen und das sich daraus ergebende Optimierungsproblem zu lösen,\n\nWichtige Kenngrößen und Metriken (z.B. Accuracy, Precision, Recall) von Klassifikationsmodellen zu ermitteln und zu interpretieren,\n\nPerzeptronen- und mehrschichtige neuronale Netzwerke unter Einsatz geeigneter Verfahren selbstständig zu trainieren,\n\neinfache neuronale Netzwerke in PyTorch zu implementieren und anhand von Trainingsdaten zu trainieren.\n\n--- Contents (EN) ---\nHistory of artificial intelligence / knowledge-based systems\nLinear regression and linear classification\nKernel methods for regression and classification in high-dimensional spaces\nSupport vector machines\nLoss functions and metrics\nPerceptrons and neural networks\nBackpropagation and delta learning rule\nPractical application in Python and PyTorch\n\n--- Contents (DE) ---\nGeschichte der künstlichen Intelligenz / wissensbasierter Systeme\nLineare Regression und lineare Klassifikation\nKernelmethoden zur Regression und Klassifikation in hochdimensionalen Räumen\nSupport Vektor Maschinen\nLoss-Funktionen und Metriken\nPerzeptronen- und Neuronalenetzwerke\nBackpropagation und Delta-Lernregel\nPraktische Anwendung in Python und PyTorch\n\n--- Literature (EN) ---\nWill be announced in the lecture\n\n--- Literature (DE) ---\nWird in der Veranstaltung bekannt gegeben", "metadata": {"moduleNumber": "D 3.3", "moduleName": "EDIT", "creditPoints": "5.0", "suggestedSemester": 3, "offeredInSeason": "winter_semester", "examType": "written_exam", "heldInLanguage": "de", "reviserName": "Prof. Dr. Dennis Müller", "reviserEmail": "dennis.mueller@hs-duesseldorf.de", "studyProgramId": 14, "source_type": "json"}}
{"id": "BDAISY__D_3.1", "text": "Title: EDIT\nModule Number: D 3.1\nCredits: 5.0 CP\nSemester: 3\nOffered In: winter_semester\nLanguage: de\nExam Type: portfolio\nInstructor: None Osmanbey Uzunkol\n\n--- Goals (EN) ---\nStudents are familiar with and understand the importance of IT security for businesses and organizations, as well as the risks associated with the use of information technology. They possess a solid understanding of the technical foundations of IT security and data protection, along with the procedures outlined by international security standards.\n\nThey are well-versed in the core protection goals of IT security, including relevant security policies and mechanisms. Students are capable of analyzing, contextualizing, and effectively applying cryptographic tools within technical applications. They are also familiar with common IT security software tools and can use them proficiently in practical scenarios.\n\nIn collaborative settings, students are able to develop fundamental solution strategies for information security and present them appropriately. As part of their presentations, they offer their peers respectful and constructive feedback, contributing to a supportive and productive learning environment.\n\n--- Goals (DE) ---\nDie Studierenden kennen und verstehen die Bedeutung der IT-Sicherheit für Unternehmen und Organisationen sowie die mit dem IT-Einsatz verbundenen Risiken. Sie kennen und verstehen die technischen Grundlagen der IT-Sicherheit, des Datenschutzes sowie die Vorgehensweisen internationaler Sicherheitsstandards. Sie kennen und verstehen die Schutzziele der IT-Sicherheit einschließlich der Sicherheitsrichtlinien und -mechanismen. Die Studierenden sind in der Lage, kryptografische Werkzeuge zu analysieren, einzuordnen und in technischen Anwendungen sinnvoll umzusetzen. Sie kennen Softwaretools der IT-Sicherheit und können diese in der Praxis anwenden. Sie können grundlegende Lösungsideen der Informationssicherheit gemeinsam im Team entwickeln und auf geeignete Weise präsentieren. Ihren Kommilitoninnen und Kommilitonen geben sie im Rahmen von Präsentationen ein wertschätzendes und konstruktives Feedback.\n\n--- Contents (EN) ---\nThe course covers key objectives of IT security, focusing on the fundamental principles that guide the protection of information and systems. It introduces security policies and mechanisms that serve to uphold these goals, ensuring a structured and resilient approach to managing digital threats. Central to the module is the understanding of essential terminology, including concepts such as assets, threats, vulnerabilities, attacks, and risks.\n\nThe human factor in IT security is also explored, highlighting the role people play in both strengthening and compromising security systems. Beyond the classical security goals, the course also addresses extended protection objectives such as data privacy and anonymity.\n\nStudents gain foundational knowledge of cryptography, including symmetric encryption, hash functions, message authentication codes (MACs), asymmetric encryption, and digital signatures. These concepts are then applied in the study of key security protocols such as Public Key Infrastructure (PKI), SSL/TLS, and IPsec. The course concludes with advanced protocols that enhance security and privacy, such as the TOR network, providing students with a comprehensive understanding of modern tools and techniques in the field of cybersecurity.\n\n--- Contents (DE) ---\nSchutzziele der IT-Sicherheit+\nSicherheitsrichtlinien und Sicherheitsmechanismen+\nTerminologie (Werte, Bedrohungen, Schwachstellen /Verwundbarkeiten, Angriffe, Risiken)+Faktor Mensch in der IT-Sicherheit+Erweiterte Schutzziele: Datenschutz und Anonymität+\nKryptografische Grundlagen (Symmetrische Kryptografie, Hashfunktionen, MACs, Asymmetrische Kryptografie, Digitale Signaturen)+\nSicherheitsprotokolle (PKI, SSL/TLS, IPsec)+\nFortgeschrittene Protokolle für Sicherheit und Datenschutz (TOR-Netze)\n\n--- Literature (EN) ---\nC. Eckert: IT-Sicherheit, Konzepte  Verfahren  Protokolle, Oldenbourg Verlag 2014K. Schmeh: Kryptografie  Verfahren  Protokolle  Infrastrukturen, dpunkt.verlag 2013ISO/IEC 27000: Information technology  Security techniques  Information security management systems  Overview and vocabulary, 2014T. R. Peltier: Information Security Fundamentals, Taylor and Francis 2014\n\n--- Literature (DE) ---\nC. Eckert: IT-Sicherheit, Konzepte – Verfahren – Protokolle, Oldenbourg Verlag 2014K. Schmeh: Kryptografie – Verfahren – Protokolle – Infrastrukturen, dpunkt.verlag 2013ISO/IEC 27000: Information technology – Security techniques – Information security management systems – Overview and vocabulary, 2014T. R. Peltier: Information Security Fundamentals, Taylor and Francis 2014", "metadata": {"moduleNumber": "D 3.1", "moduleName": "EDIT", "creditPoints": "5.0", "suggestedSemester": 3, "offeredInSeason": "winter_semester", "examType": "portfolio", "heldInLanguage": "de", "reviserName": "None Osmanbey Uzunkol", "reviserEmail": "osmanbey.uzunkol@hs-duesseldorf.de", "studyProgramId": 14, "source_type": "json"}}
{"id": "BDAISY__D_1.2", "text": "Title: Software Engineering for Data Science\nModule Number: D 1.2\nCredits: 5.0 CP\nSemester: 1\nOffered In: winter_semester\nLanguage: de\nExam Type: project\nInstructor: Prof. Dr. Florian Huber\n\n--- Goals (EN) ---\nStudents will be able to write and maintain shell scripts to automate data ingestion and processing, collaborate seamlessly on codebases using Git branching and pull-request workflows, and apply clean-code principles to design readable, maintainable Python modules. They will confidently debug issues and author comprehensive unit tests, integrate those tests into CI pipelines, and use profiling reports to accelerate key computations. Students can conduct constructive code reviews and have learned to collaborate in teams using platforms such as GitHub.\n\n--- Goals (DE) ---\nDie Studierenden sind in der Lage, Shell-Skripte zu schreiben und zu pflegen, um die Datenerfassung und -verarbeitung zu automatisieren, mithilfe von Git-Branching und Pull-Request-Workflows nahtlos an Codebasen zusammenzuarbeiten und Clean-Code-Prinzipien anzuwenden, um lesbare, wartbare Python-Module zu entwerfen. Sie können Probleme sicher debuggen, umfassende Unit-Tests erstellen, diese Tests in CI-Pipelines integrieren und Profiling-Berichte verwenden, um wichtige Berechnungen zu beschleunigen. Die Studierenden können konstruktive Code Reviews durchführen und haben gelernt über Platformen wie GitHub im Team zusammenzuarbeiten.\n\n--- Contents (EN) ---\nThis course walks students through the key engineering practices that turn exploratory Python scripts into robust data science workflows. Starting with Shell scripting for automating common tasks, it then introduces version control with Git and GitHub alongside collaborative development strategies that mirror real-world team environments. From there, students learn to structure their code cleanly, applying design patterns and best practices, before diving into systematic debugging and writing unit tests to verify functionality. The course continues by setting up continuous integration pipelines that automatically run tests. Profiling tools are used to identify performance bottlenecks and various strategies for code optimisation are demonstrated. The outlook focuses on cloud computing platforms and possible ways to use them efficiently.\n\n--- Contents (DE) ---\nDieser Kurs führt durch die wichtigsten technischen Verfahren, mit denen explorative Python-Skripte in verlässliche Data Science Workflows umgewandelt werden. Ausgehend von Shell-Skripten zur Automatisierung gängiger Aufgaben werden zunächst die Versionskontrolle mit Git und GitHub sowie Strategien für die kollaborative Entwicklung vorgestellt, die reale Teamumgebungen widerspiegeln. Anschließend lernen die Teilnehmer, ihren Code sauber zu strukturieren und Designmuster und Best Practices anzuwenden, bevor sie sich mit systematischer Fehlersuche und dem Schreiben von Unit-Tests zur Überprüfung der Funktionalität befassen. Der Kurs wird mit der Einrichtung von Continuous-Integration-Pipelines fortgesetzt, die Tests automatisch ausführen. Mit Profiling-Tools werden Leistungsengpässen identifiziert und verschiedene Strategien zur Code-Optimierung gezeigt. Im Ausblick geht es um Cloud-Computing-Plattformen und mögliche Wege um diese effizient zu Nutzen.\n\n--- Literature (EN) ---\nWill be provided in the course.\n\n--- Literature (DE) ---\nWird in der Veranstaltung zu Beginn\nbekannt gegeben.", "metadata": {"moduleNumber": "D 1.2", "moduleName": "Software Engineering for Data Science", "creditPoints": "5.0", "suggestedSemester": 1, "offeredInSeason": "winter_semester", "examType": "project", "heldInLanguage": "de", "reviserName": "Prof. Dr. Florian Huber", "reviserEmail": "florian.huber@hs-duesseldorf.de", "studyProgramId": 14, "source_type": "json"}}
{"id": "BDAISY__D_3.5", "text": "Title: EDIT\nModule Number: D 3.5\nCredits: 5.0 CP\nSemester: 3\nOffered In: winter_semester\nLanguage: de\nExam Type: written_exam\nInstructor: None André Stuhlsatz\n\n--- Goals (EN) ---\n\n\n--- Goals (DE) ---\nDie Studierenden können Probleme der Stochastik analysieren und lösen.  Sie können Problemstellungen modellieren und sind in der Lage diese mathematisch zu beschreiben und Lösungen exakt zu formulieren. Übergeordnetes Ziel ist auch die notwendige mathematische Denkweise bei der Lösungsfindung zu erlernen. In weiterführenden Veranstaltungen werden die Studierenden in die Lage versetzt, sich bei Bedarf selbstständig mit den mathematischen Grundlagen auseinander zu setzen. Sie können grundlegende Lösungsideen gemeinsam mit anderen im Team entwickeln und auf geeignete Weise präsentieren.\n\n--- Contents (EN) ---\n\n\n--- Contents (DE) ---\nWeiterführende mathematische Konzepte für den Bereich Data Science und AI: Grundlagen der Maßtheorie, Verteilungsfunktionen, Wahrscheinlichkeitsdichten, Zufallsvariablen, Mehrdimensionale Zufallsvariablen, Wahrscheinlichkeitsrechnung, Kombinatorik, Punkt- und Intervallschätzungen.\n\n--- Literature (EN) ---\n\n\n--- Literature (DE) ---\nN. Henze: Stochastik für Einsteiger: Eine Einführung in die faszinierende Welt des Zufalls. Springer Spektrum; Auflage: 12., verb. u. erw. Aufl. 2018J. Lehn, H. Wegmann: Einführung in die Statistik. Vieweg+Teubner Verlag; Auflage: 5., durchges. Aufl. 2006L. Papula: Mathematik für Ingenieure und Naturwissenschaftler Band 3: Vektoranalysis, Wahrscheinlichkeitsrechnung, Mathematische Statistik, Fehler- und Ausgleichsrechnung. Springer Vieweg; Auflage: 7., überarb. u. erw. Aufl. 2016P.", "metadata": {"moduleNumber": "D 3.5", "moduleName": "EDIT", "creditPoints": "5.0", "suggestedSemester": 3, "offeredInSeason": "winter_semester", "examType": "written_exam", "heldInLanguage": "de", "reviserName": "None André Stuhlsatz", "reviserEmail": "andre.stuhlsatz@hs-duesseldorf.de", "studyProgramId": 14, "source_type": "json"}}
{"id": "BDAISY__D_1.5", "text": "Title: Business Planning\nModule Number: D 1.5\nCredits: 5.0 CP\nSemester: 1\nOffered In: winter_semester\nLanguage: de\nExam Type: project\nInstructor: None Dominik Austermann\n\n--- Goals (EN) ---\nThrough practical exercises, students are empowered to digitize and further develop existing business models. They gain hands-on experience with new forms of agile organizational structures and learn how to operate effectively within them. Students are able to apply entrepreneurial thinking and action in a variety of contexts. They develop an awareness of entrepreneurial opportunities and gain insights into the prerequisites and possibilities of starting a business. Additionally, students learn to structure and articulate the core concepts of innovation management.\n\n--- Goals (DE) ---\nStudierende werden befähigt mittels praktischer Übungen bestehende Geschäftsmodelle zu digitalisieren und weiterzuentwickeln. Sie lernen neue Formen der agilen Unternehmensorganisation praxisorientiert kennen und lernen sich in diesen zu organisieren. Studierende können unternehmerisches Denken und Handeln in verschiedenen Kontexten einsetzen. Studierende entwickeln ein Bewusstsein für unternehmerische Gelegenheiten und lernen Voraussetzungen und Möglichkeiten der Unternehmensgründung kennen. Studierende können die Inhalte des Innovationsmanagements gliedern und beschreiben.\n\n--- Contents (EN) ---\nThis course focuses on the (further) development of innovative business models in the context of digital transformation. Key topics covered include:\n\n- Presentation of business models (e.g., pitch formats)\n- Fundamentals of innovation management\n- Digitalization of business models\n- Intrapreneurship vs. entrepreneurship\n\n--- Contents (DE) ---\nDie (Weiter-)Entwicklung innovativer Geschäftsmodelle vor dem Hintergrund der Digitalisierung steht im Fokus dieser Veranstaltung. Die Veranstaltung behandelt\n- Präsentation von Geschäftsmodellen (z. B. Pitch)\n- Grundlagen des Innovationsmanagements\n- Digitalisierung von Geschäftsmodellen\n- Intrapreneurship vs. Entrepreneurship\n\n--- Literature (EN) ---\nWill be announced during the lecture\n\n--- Literature (DE) ---\nWird in Verantstaltung bekannt gegeben.", "metadata": {"moduleNumber": "D 1.5", "moduleName": "Business Planning", "creditPoints": "5.0", "suggestedSemester": 1, "offeredInSeason": "winter_semester", "examType": "project", "heldInLanguage": "de", "reviserName": "None Dominik Austermann", "reviserEmail": "dominik.austermann@hs-duesseldorf.de", "studyProgramId": 14, "source_type": "json"}}
{"id": "BDAISY__xxD_4.1_/_D_5.1", "text": "Title: EDIT\nModule Number: xxD 4.1 / D 5.1\nCredits: 20.0 CP\nSemester: 4\nOffered In: summer_semester\nLanguage: de\nExam Type: none\nInstructor: \n\n--- Goals (EN) ---\n\n\n--- Goals (DE) ---\n\n\n--- Contents (EN) ---\n\n\n--- Contents (DE) ---\n\n\n--- Literature (EN) ---\n\n\n--- Literature (DE) ---", "metadata": {"moduleNumber": "xxD 4.1 / D 5.1", "moduleName": "EDIT", "creditPoints": "20.0", "suggestedSemester": 4, "offeredInSeason": "summer_semester", "examType": "none", "heldInLanguage": "de", "reviserName": "", "reviserEmail": null, "studyProgramId": 14, "source_type": "json"}}
{"id": "BDAISY__WPM_PF_2", "text": "Title: Professional Focus Module 1\nModule Number: WPM PF 2\nCredits: 5.0 CP\nSemester: 4\nOffered In: summer_semester\nLanguage: de\nExam Type: see_elective\nInstructor: Prof. Dr. Dennis Müller\n\n--- Goals (EN) ---\nLearning outcomes according to the selected module\n\n--- Goals (DE) ---\nLernergebnisse gemäß des gewählten Moduls\n\n--- Contents (EN) ---\nLearning content according to the selected module\n\n--- Contents (DE) ---\nLerninhalte gemäß des gewählten Moduls\n\n--- Literature (EN) ---\nWill be announced in the module\n\n--- Literature (DE) ---\nWird in der Veranstaltung bekannt gegeben.", "metadata": {"moduleNumber": "WPM PF 2", "moduleName": "Professional Focus Module 1", "creditPoints": "5.0", "suggestedSemester": 4, "offeredInSeason": "summer_semester", "examType": "see_elective", "heldInLanguage": "de", "reviserName": "Prof. Dr. Dennis Müller", "reviserEmail": "dennis.mueller@hs-duesseldorf.de", "studyProgramId": 14, "source_type": "json"}}
{"id": "BDAISY__WPM_PF_3", "text": "Title: Professional Focus Module 3\nModule Number: WPM PF 3\nCredits: 5.0 CP\nSemester: 4\nOffered In: summer_semester\nLanguage: de\nExam Type: see_elective\nInstructor: Prof. Dr. Dennis Müller\n\n--- Goals (EN) ---\nLearning outcomes according to the selected module\n\n--- Goals (DE) ---\nLernergebnisse gemäß des gewählten Moduls\n\n--- Contents (EN) ---\nLearning content according to the selected module\n\n--- Contents (DE) ---\nLerninhalte gemäß des gewählten Moduls\n\n--- Literature (EN) ---\nWill be announced in the module\n\n--- Literature (DE) ---\nWird in der Veranstaltung bekannt gegeben.", "metadata": {"moduleNumber": "WPM PF 3", "moduleName": "Professional Focus Module 3", "creditPoints": "5.0", "suggestedSemester": 4, "offeredInSeason": "summer_semester", "examType": "see_elective", "heldInLanguage": "de", "reviserName": "Prof. Dr. Dennis Müller", "reviserEmail": "dennis.mueller@hs-duesseldorf.de", "studyProgramId": 14, "source_type": "json"}}
{"id": "BDAISY__WPM_PF_5", "text": "Title: Professional Focus Module 5\nModule Number: WPM PF 5\nCredits: 5.0 CP\nSemester: 5\nOffered In: winter_semester\nLanguage: de\nExam Type: see_elective\nInstructor: Prof. Dr. Dennis Müller\n\n--- Goals (EN) ---\nLearning outcomes according to the selected module\n\n--- Goals (DE) ---\nLernergebnisse gemäß des gewählten Moduls\n\n--- Contents (EN) ---\nLearning content according to the selected module\n\n--- Contents (DE) ---\nLerninhalte gemäß des gewählten Moduls\n\n--- Literature (EN) ---\nWill be announced in the module\n\n--- Literature (DE) ---\nWird in der Veranstaltung bekannt gegeben.", "metadata": {"moduleNumber": "WPM PF 5", "moduleName": "Professional Focus Module 5", "creditPoints": "5.0", "suggestedSemester": 5, "offeredInSeason": "winter_semester", "examType": "see_elective", "heldInLanguage": "de", "reviserName": "Prof. Dr. Dennis Müller", "reviserEmail": "dennis.mueller@hs-duesseldorf.de", "studyProgramId": 14, "source_type": "json"}}
{"id": "BDAISY__D_4.1.1", "text": "Title: Machine Perception und Tracking\nModule Number: D 4.1.1\nCredits: 5.0 CP\nSemester: 4\nOffered In: summer_semester\nLanguage: de\nExam Type: portfolio\nInstructor: Prof. Dr. Dennis Müller\n\n--- Goals (EN) ---\nStudents who have completed the course are able to describe and apply edge and corner detection methods. They can explain, compute, and evaluate feature extraction techniques such as Haar wavelets, AdaBoost, and HOG. They are capable of explaining the YOLO object detection method, applying it, and evaluating results using appropriate metrics. They can describe, model, and analyze stochastic and Markov processes. They explain the principle of minimal variance fusion and combine sensor data to reduce variance. They can explain the functionality of Kalman and Extended Kalman filters, implement them for state estimation, and compare their performance. Finally, they are able to describe the structure of particle filters, apply them for object tracking, and develop simple tracking systems independently.\n\n--- Goals (DE) ---\nStudierende, die die Veranstaltung besucht haben, können Verfahren zur Kanten- und Eckendetektion beschreiben und anwenden. Sie können Feature-Extraktionsmethoden wie Haar-Wavelets, AdaBoost und HOG erklären, berechnen und hinsichtlich ihrer Eignung bewerten. Sie sind in der Lage, das YOLO-Verfahren zur Objektdetektion zu erläutern, anzuwenden und mit geeigneten Metriken zu bewerten. Sie können stochastische und Markov-Prozesse beschreiben, modellieren und analysieren. Sie erklären das Prinzip der Minimal-Varianz-Fusion und kombinieren Sensordaten zur Varianzreduktion. Sie erläutern die Funktionsweise von Kalman- und Extended Kalman-Filtern, implementieren diese zur Zustandsschätzung und vergleichen deren Leistungsfähigkeit. Schließlich können sie die Struktur von Partikelfiltern darstellen, zur Objektverfolgung anwenden und einfache Tracking-Systeme selbst entwickeln.\n\n--- Contents (EN) ---\nBasic and Advanced Methods of Machine Vision and Object Tracking\n\n- Edge and corner detection\n- Feature extraction (Haar wavelets, AdaBoost, HOG)\n- Object detection using YOLO, object detection metrics\n- Stochastic processes, Markov processes\n- Minimal variance fusion\n- Kalman filter, extended Kalman filter\n- Particle filter\n\n--- Contents (DE) ---\nGrundlegende und fortschrittliche Methoden des maschinellen Sehens und der Objektverfolgung \n- Kanten- und Eckendetektion\n- Featureberechnung (Haar-Wavelets, AdaBoost, HOG)\n- Objektdetektion mit YOLO, Metriken zur Objektdetektion\n- Stochastische Prozeße, Markov-Prozeße\n- Minimal Variance Fusion\n- Kalmanfilter, Extended Kalmanfilter\n- Partikelfilter\n\n--- Literature (EN) ---\n\n\n--- Literature (DE) ---\nLiteratur\nwird bei Vorlesungsbeginn bekannt gegeben.", "metadata": {"moduleNumber": "D 4.1.1", "moduleName": "Machine Perception und Tracking", "creditPoints": "5.0", "suggestedSemester": 4, "offeredInSeason": "summer_semester", "examType": "portfolio", "heldInLanguage": "de", "reviserName": "Prof. Dr. Dennis Müller", "reviserEmail": "dennis.mueller@hs-duesseldorf.de", "studyProgramId": 14, "source_type": "json"}}
{"id": "BDAISY__D_4.1.3", "text": "Title: Big Data Analysis\nModule Number: D 4.1.3\nCredits: 5.0 CP\nSemester: 4\nOffered In: summer_semester\nLanguage: de\nExam Type: project\nInstructor: Prof. Dr. Florian Huber\n\n--- Goals (EN) ---\nStudents are familiar with essential techniques for processing and evaluating large, heterogeneous or inconsistent data sets and can independently address manageable questions. They have appropriate problem-solving skills for formulating solutions and have acquired practical knowledge in working on project-oriented tasks. The use of smart devices, social networks or cloud computing has been discussed and, where appropriate, taken into account in the practical implementation. Students can develop basic solution ideas on the above-mentioned topics together with others in a team and present them in an appropriate manner. They provide their fellow students with appreciative and constructive feedback during the presentations.\n\n--- Goals (DE) ---\nStudierende kennen wesentliche Techniken zur Verarbeitung und Auswertung großer, heterogener oder inkonsistenter Datenmengen und können überschaubare Fragestellungen selbständig adressieren. Sie verfügen über geeignete Problemlösungsfähigkeiten zur Lösungsformulierung und haben praktische Kenntnisse bei der Bearbeitung einer projektorientierten Aufgabenstellung erworben. Der Einsatz im Kontext Smart Devices, Social Networks oder Cloud Computing wurde diskutiert und ggf. in der praktischen Umsetzung berücksichtigt.Die Studierenden können grundlegende Lösungsideen zu den genannten Themen gemeinsam mit anderen im Team entwickeln und auf geeignete Weise präsentieren. Sie geben Kommilitonen im Rahmen der Präsentationen ein wertschätzendes und konstruktives Feedback.\n\n--- Contents (EN) ---\nThis module introduces and expands on basic techniques required for analysing and handling large, complex and heterogeneous data sources (big data). Techniques such as generators, databases (SQL and noSQL) and sparse data provide a foundation for handling even extensive data sets. Core techniques for handling unstructured data are explained in depth and applied, including distance and similarity measures, graph representations, dimension reduction and vector embeddings. Efficient search algorithms are discussed and applied for both structured and unstructured data. In addition, tools and strategies for cloud-based big data services and analyses are introduced. Many of the techniques presented are used in a semester-long project.\n\n--- Contents (DE) ---\nIn diesem Modul werden grundlegende Techniken eingeführt oder vertieft die nötig sind für die Analyse und den Umgang mit großen, komplexen bzw. heterogener Datenquellen (Big Data). Techniken wie Generatoren, Datenbanken (SQL und noSQL), Sparse Data liefern ein Fundament um auch mit umfangreichen Datensätzen umzugehen. Kerntechniken im umgang mit unstrukturierten Daten werden vertiefend erklärt und eingestetzt, u.a. Distanz- und Ähnlichkeitsmaße, Graphen-Darstellungen, Dimensionsreduzierungen und Vektor-Embeddings. Es werden effiziente Suchalgorithmen besprochen und angewendet, sowohl für strukturierte als auch unstrukturierte Daten. Darüber hinaus werden Werkzeuge und Strategien für Cloud-basierte Big Data Services und Analysen eingeführt.\n\nViele der vorgestellten Techniken werden in einem semesterbegleitenden Projekt eingesetzt.\n\n--- Literature (EN) ---\nWill be provided during the course.\n\n--- Literature (DE) ---\nLiteratur wird bei Vorlesungsbeginn bekannt gegeben.", "metadata": {"moduleNumber": "D 4.1.3", "moduleName": "Big Data Analysis", "creditPoints": "5.0", "suggestedSemester": 4, "offeredInSeason": "summer_semester", "examType": "project", "heldInLanguage": "de", "reviserName": "Prof. Dr. Florian Huber", "reviserEmail": "florian.huber@hs-duesseldorf.de", "studyProgramId": 14, "source_type": "json"}}
{"id": "BDAISY__PF_1.8", "text": "Title: Design Process\nModule Number: PF 1.8\nCredits: 5.0 CP\nSemester: 4\nOffered In: summer_semester\nLanguage: de\nExam Type: project\nInstructor: None Kay Schröder\n\n--- Goals (EN) ---\nStudents learn systematic approaches to design tasks and can apply various design methods appropriately to different situations. They acquire subject matter competence in design methods and systematic design processes, methodological competence in the application of design methodologies and idea generation techniques, social competence in teamwork and communication of design decisions, and self-competence in reflection and critical questioning of the design process.\n\n--- Goals (DE) ---\nDie Studierenden erlernen systematische Herangehensweisen an Designaufgaben und können verschiedene Designmethoden situationsgerecht anwenden. Sie erwerben:   \n\nFachkompetenz: Designmethoden und systematische Designprozesse \nMethodenkompetenz: Anwendung von Design Methodiken und Ideenfindungstechniken \nSozialkompetenz: Teamarbeit und Kommunikation von Designentscheidungen \nSelbstkompetenz: Reflexion und kritisches Hinterfragen des Designprozesses.\n\n--- Contents (EN) ---\nInstruction in systematic design methods and processes with a focus on iterative and user-centered approaches. Students learn structured approaches from user research through idea generation and evaluation to prototyping and testing. Key areas include concrete processes such as Human-Centered Design, Service Design, various research and analysis methods, as well as idea generation techniques and professional documentation and presentation of design processes in interdisciplinary teams.\n\n--- Contents (DE) ---\nVermittlung systematischer Designmethoden und -prozesse mit Fokus auf iterative und nutzerzentrierte Ansätze. Die Studierenden erlernen strukturierte Herangehensweisen von der Nutzerforschung über Ideenfindung und Bewertung bis hin zu Prototyping und Testing. Schwerpunkte liegen auf konkreten Prozessen wie z.B. Human-Centered Design, Service Design, verschiedenen Recherche- und Analysemethoden sowie Ideenfindungstechniken und professioneller Dokumentation und Präsentation von Designprozessen in interdisziplinären Teams.\n\n--- Literature (EN) ---\nThe literature will be announced at the beginning of the course.\n\n--- Literature (DE) ---\nWird bei Veranstaltungsbeginn bekannt gegeben.", "metadata": {"moduleNumber": "PF 1.8", "moduleName": "Design Process", "creditPoints": "5.0", "suggestedSemester": 4, "offeredInSeason": "summer_semester", "examType": "project", "heldInLanguage": "de", "reviserName": "None Kay Schröder", "reviserEmail": "kay.schroeder@hs-duesseldorf.de", "studyProgramId": 14, "source_type": "json"}}
{"id": "BDAISY__D_5.1.1", "text": "Title: Advances in Intelligent Systems\nModule Number: D 5.1.1\nCredits: 5.0 CP\nSemester: 5\nOffered In: winter_semester\nLanguage: de\nExam Type: project\nInstructor: Prof. Dr. Dennis Müller\n\n--- Goals (EN) ---\nStudents who have completed the course are able to describe and apply key components of modern neural network architectures such as convolution, pooling, batch and layer normalization, and dropout. They can explain and use advanced optimization methods including AdaGrad, AdaDelta, and Adam. They are capable of applying and assessing techniques for object detection, semantic segmentation, and style transfer. Furthermore, they can understand and implement generative models such as Variational Autoencoders, Generative Adversarial Networks, and diffusion models. They can explain the foundations of machine language processing and apply models such as RNNs, LSTMs, and Transformers. Finally, they are able to describe the principles of reinforcement learning and apply basic algorithms like Deep Q-Learning in practice.\n\n--- Goals (DE) ---\nStudierende, die die Veranstaltung besucht haben, können zentrale Bausteine moderner Netzwerkarchitekturen wie Faltung, Pooling, Batch- und Layer-Normalisierung sowie Dropout beschreiben und anwenden. Sie können fortgeschrittene Optimierungsverfahren wie AdaGrad, AdaDelta und Adam erklären und einsetzen. Sie sind in der Lage, Verfahren zur Objekterkennung, semantischen Segmentierung und zum Style-Transfer anzuwenden und zu bewerten. Darüber hinaus verstehen und implementieren sie generative Modelle wie Variational Autoencoder, Generative Adversarial Networks und Diffusionsmodelle. Sie können die Grundlagen der maschinellen Sprachverarbeitung erläutern und Modelle wie RNNs, LSTMs und Transformer anwenden. Schließlich sind sie in der Lage, die Prinzipien des Reinforcement Learnings zu beschreiben und grundlegende Algorithmen wie Deep-Q-Learning praktisch umzusetzen.\n\n--- Contents (EN) ---\nWe examine modern state-of-the-art methods in the field of Artificial Intelligence and Machine Learning (with a focus on Deep Learning):\n\n- Components of modern network architectures (convolution, pooling, batch and layer normalization, dropout)\n- Advanced optimization methods (AdaGrad, AdaDelta, Adam)\n- Object detection and semantic segmentation, style transfer\n- Variational Autoencoders, Generative Adversarial Networks, diffusion models\n- Fundamentals of machine language processing (RNNs, LSTMs, Transformers)\n- Fundamentals of reinforcement learning (Deep Q-Learning)\n\n--- Contents (DE) ---\nWir betrachten moderne State-of-the-Art Verfahren aus dem Bereich \"Artificial Intelligence\" und \"Machine Learning\" (insbesondere Deep-Learning)\n- Bausteiner moderner Netzwerkarchitekturen (Faltung, Pooling, Batch- und Layer Normalization, DropOut)\n- Moderne Optimierungsverfahren (AdaGrad, AdaDelta, Adam)\n- Objektdetektion und Semantische Segmentierung, Style-Transfer\n- Variational Auto-Encoder, Generative Adversarial Networks, Diffusionsmodelle\n- Grundlagen maschineller Sprachverarbeitung, (RNNs, LSTMS, Transformer)\n- Grundlagen des Reinforcement-Learnings (Deep-Q-Learning)\n\n--- Literature (EN) ---\nWill be announced during the lecture\n\n--- Literature (DE) ---\nWird in der Veranstaltung bekannt gegeben", "metadata": {"moduleNumber": "D 5.1.1", "moduleName": "Advances in Intelligent Systems", "creditPoints": "5.0", "suggestedSemester": 5, "offeredInSeason": "winter_semester", "examType": "project", "heldInLanguage": "de", "reviserName": "Prof. Dr. Dennis Müller", "reviserEmail": "dennis.mueller@hs-duesseldorf.de", "studyProgramId": 14, "source_type": "json"}}
{"id": "BDAISY__D_4.1.2", "text": "Title: EDIT\nModule Number: D 4.1.2\nCredits: 5.0 CP\nSemester: 4\nOffered In: summer_semester\nLanguage: de\nExam Type: project\nInstructor: \n\n--- Goals (EN) ---\n\n\n--- Goals (DE) ---\nStudierende\nkönnen grundlegende Technologien der maschinellen Wahrnehmung mit typischen\nAufgaben der Erkennung zielgerichtet verknüpfen. Sie besitzen einen Überblick\nrelevanter Arbeiten und kennen wesentliche Vor- und Nachteile existierender\nSysteme. Sie können für Fragestellungen zu der Entwicklung geeigneter\nmaschineller Systeme entsprechende Lösungsverfahren adaptieren und\nkonzeptionell, gestalterisch und technisch realisieren. Der Effekt dieser\nLösungen lässt sich durch geeignete Methoden angemessen evaluieren, bewerten\nund interpretieren.\n\n--- Contents (EN) ---\n\n\n--- Contents (DE) ---\nRecherche, Analyse und Bewertung von Produkten, Dienstleistungen und interaktiven Anwendungen aus den Bereichen medialer Kommunikation, Online- und Informationstechnologie, allgemeine Medien und Elektronik. Analyse diverser Szenarien der digitalen Anwendungsbereiche. Konzeption und Erstellung von Simulations- und Interaktionsprototypen. Entwicklung qualitativer und quantitativer Erhebungsmethoden und Analysetools für digitale Anwendungen. V.isuelle Darstellung der Evaluationen und Einsatz von Design als methodisches, integratives Tool. Die Veranstaltung fokussiert auf die Analyse visueller und thematischer Kontexte. Methodisch nutzt man vorallem bildliche und darstellende Vergleichmodelle, systematische visuelle Ordnung und Einordnung der Daten und Themen.MedienanalysenStakeholder AnalysenFokusgruppenanalysenProduktanalysenDefinitionen von MarkenpersönlichkeitMarkenarchitekturanalysenUser Insights durch visuelle VergleichePersonamodelle und MoodboardsUse Cases und NutzerszenarienVisuelle ZielmatrixVisuelle User StoriesDie Inhalte werden in Form von Simulations- und Interaktionsprototypen dargestellt und analysiert. Qualitative und quantitative Erhebungsmethoden und Analysetools für digitale Anwendungen werden strukturell aufbereitet. Visuelle Darstellung der Evaluationen und Einsatz von Design als methodisches, integratives Tool.\n\n--- Literature (EN) ---\n\n\n--- Literature (DE) ---\nMarco Spies: Branded Interactions – Digitale Markenerlebnisse planen und gestalten, 2018Colin Ware: Information Visualization : Perception for Design Morgan Kaufmann Series in Interactive Technologies, San Francisco, 2000Axel Puhlmann: Alle Berührungspunkte mit der Marke zählen! In: planung & analyse, Nr. 3/2013Frank Reese: Web Analytics – Damit aus Traffic Umsatz wird. Business Village GmbH, Göttingen 2008Weitere Literatur wird bei Vorlesungsbeginn bekannt gegeben.", "metadata": {"moduleNumber": "D 4.1.2", "moduleName": "EDIT", "creditPoints": "5.0", "suggestedSemester": 4, "offeredInSeason": "summer_semester", "examType": "project", "heldInLanguage": "de", "reviserName": "", "reviserEmail": null, "studyProgramId": 14, "source_type": "json"}}
{"id": "BDAISY__D_5.1.2", "text": "Title: EDIT\nModule Number: D 5.1.2\nCredits: 5.0 CP\nSemester: 5\nOffered In: winter_semester\nLanguage: de\nExam Type: project\nInstructor: Prof. Dr. rer. nat. Christian Geiger\n\n--- Goals (EN) ---\n\n\n--- Goals (DE) ---\nStudierende können grundlegende immersive Technologien mit typischen Aufgaben der Datenanalyse und interaktiven Visualisierung zielgerichtet verknüpfen. Sie können für Fragestellungen zu hochdimensionalen Datensätzen geeignete VR/AR/MR-Techniken adaptieren und konzeptionell, gestalterisch und technisch realisieren. Der Effekt dieser immersiven analytischen Nutzererfahrungen lässt sich durch geeignete Methoden angemessen evaluieren, bewerten und interpretieren.Die Studierenden kennen die wichtigsten Visualisierungstechnologien und sind in der Lage, geeignete Visualisierugssysteme zu konzipieren, aufzubauen und in der Anwendung zu bewerten. Sie sind in der Lage grundlegende Konzepte der Visualisierung auf relevante Szenarien im täglichen Leben bzw. in spezifischen Anwendungsfeldern (z. B. Data Science) zu übertragen. Hier entwickeln die Studierenden grundlegende Lösungsideen zu den genannten Themen gemeinsam mit anderen im Team und präsentieren diese auf geeignete Weise. Sie geben Kommilitonen im Rahmen der Präsentationen ein wertschätzendes und konstruktives Feedback.\n\n--- Contents (EN) ---\n\n\n--- Contents (DE) ---\nDie Komplexität medialer Anwendungsgebiete und digitaler Produkte erfordert eine kontextuelle und erzählerische Form der Vermittlung von Inhalten. Produktentwickler, Designer und Interaktionsgestalter entwickeln immersive Erzählungen und komplexe Narrative und setzen diese in User-Journey-Modelle um. Um dies zu ermöglichen werden Inhalte, Dramaturgien und narrative Parcours für lineares und nonlineares Erzählen in transmedialen digitalen Medien erforscht und entwickelt.Immersiver Workflow und Pipeline für die Datengenerierung, -verarbeitung, -präsentation und analyse multidimensionaler Daten3D Scanverfahren und verwandte MethodenGrundlagen immersiver Analyseverfahren und relevanter angrenzender GebieteAusgewählte Techniken für immersive DatenanalyseAktuelle F&E-Ergebnisse, Werkzeuge und Projekte für immersive VisualisierungIA im Bereich Produktion und FertigungIA im Bereich geografische InformationssystemeIA im Bereich Medizin, Gesundheit, Wohlbefinden und Life Science\n\n--- Literature (EN) ---\n\n\n--- Literature (DE) ---\nR. Dörner, W. Broll, P. Grimm, B. Jung (Hrsg.), Virtual und Augmented Reality (VR/AR), 2. Auflage. Grundlagen und Methoden der Virtuellen und Augmentierten Realität, Springer, 2019, DOI 10.1007/978-3-642-28903-3 Jason Jerald. 2015. The VR Book: Human-Centered Design for Virtual Reality. Association for Computing Machinery and Morgan & Claypool, New York, NY, USA.Kim Marriott et al. Immersive Analytics. Springer 2018J. Dill et al. Expanding the Frontiers of Visual Analytics and Visualization, Springer , 2012Weitere Literatur wird bei Vorlesungsbeginn bekannt gegeben.", "metadata": {"moduleNumber": "D 5.1.2", "moduleName": "EDIT", "creditPoints": "5.0", "suggestedSemester": 5, "offeredInSeason": "winter_semester", "examType": "project", "heldInLanguage": "de", "reviserName": "Prof. Dr. rer. nat. Christian Geiger", "reviserEmail": "geiger@hs-duesseldorf.de", "studyProgramId": 14, "source_type": "json"}}
{"id": "BDAISY__D_4.2.2", "text": "Title: EDIT\nModule Number: D 4.2.2\nCredits: 5.0 CP\nSemester: 4\nOffered In: summer_semester\nLanguage: de\nExam Type: project\nInstructor: Prof. Dr. rer. nat. Christian Geiger\n\n--- Goals (EN) ---\n\n\n--- Goals (DE) ---\nStudierende können grundlegende immersive Technologien (VR / AR /MR) mit typischen Aufgaben Entwicklung digitaler und realer Nutzererlebnisse zielgerichtet verknüpfen. Sie besitzen einen Überblick relevanter Arbeiten und kennen wesentliche Vor- und Nachteile existierender Mixed Reality - Systeme. Sie können für Fragestellungen zu der Entwicklung geeigneter immersiver Systeme entsprechende Lösungsverfahren adaptieren und konzeptionell, gestalterisch und technisch realisieren. Der Effekt dieser Lösungen lässt sich durch geeignete Evaluierungsmethoden angemessen evaluieren, bewerten und interpretieren.Die Studierenden kennen die wichtigsten VR-Technologien und sind in der Lage, virtuelle Umgebungen zu konzipieren, aufzubauen und in der Anwendung zu bewerten. Sie sind in der Lage grundlegende Konzepte immersiver Technologien auf relevante Szenarien im täglichen Leben bzw. in spezifischen Anwendungsfeldern zu übertragen. Hier entwickeln die Studierenden grundlegende Lösungsideen zu den genannten Themen gemeinsam mit anderen im Team und präsentieren diese auf geeignete Weise. Sie geben Kommilitonen im Rahmen der Präsentationen ein wertschätzendes und konstruktives Feedback.\n\n--- Contents (EN) ---\n\n\n--- Contents (DE) ---\nDie Ziele des Moduls bestehen in der Vermittlung grundlegender Kenntnisse immersiver Umgebungen wie Virtual Reality und Augmented Reality. Im Fokus des Moduls stehen verschiedene Technologien für Ein/Ausgabe, Rendering, Tracking sowie grundlegende Gebiete von VR/AR-Umgebungen. Neben rein technischen Aspekten werden auch Bereiche der Mensch-Technik-Interaktion und ethische und gesellschaftliche Implikationen adressiert. Sensortechnologie für eine Taxonomie von Sensorsystemen (u. a. visuelle und 3D-Sensoren), Modellierung von SensorenTheorie und Praxis digitaler Signalverarbeitung, Maschinensehen, Multisensorintegration und MultisensordatenfusionLokalisierung und Erkennung von Gesichtern, Mimik (facial expressions)Lokalisation und Tracking von Personen und PersonengruppenMotion Capturing, Tracking und Modellierung von Körpermodellen ('articulated body tracking')GestenerkennungAudio-visuelle SpracherkennungMulti-Kamera UmgebungenTools und Bibliotheken\n\n--- Literature (EN) ---\n\n\n--- Literature (DE) ---\nR. Dörner, W. Broll, P. Grimm, B. Jung (Hrsg.), Virtual und Augmented Reality (VR/AR), 2. Auflage. Grundlagen und Methoden der Virtuellen und Augmentierten Realität, Springer, 2019, DOI 10.1007/978-3-642-28903-3 Jason Jerald. 2015. The VR Book: Human-Centered Design for Virtual Reality. Association for Computing Machinery and Morgan & Claypool, New York, NY, USAWeitere Literatur wird bei Vorlesungsbeginn bekannt gegeben.", "metadata": {"moduleNumber": "D 4.2.2", "moduleName": "EDIT", "creditPoints": "5.0", "suggestedSemester": 4, "offeredInSeason": "summer_semester", "examType": "project", "heldInLanguage": "de", "reviserName": "Prof. Dr. rer. nat. Christian Geiger", "reviserEmail": "geiger@hs-duesseldorf.de", "studyProgramId": 14, "source_type": "json"}}
{"id": "BDAISY__D_5.2.1", "text": "Title: EDIT\nModule Number: D 5.2.1\nCredits: 5.0 CP\nSemester: 5\nOffered In: winter_semester\nLanguage: de\nExam Type: project\nInstructor: \n\n--- Goals (EN) ---\n\n\n--- Goals (DE) ---\nStudierende können grundlegende immersive Technologien mit typischen Aufgaben der Datenanalyse und interaktiven Visualisierung zielgerichtet verknüpfen. Sie können für Fragestellungen zu hochdimensionalen Datensätzen geeignete VR/AR/MR-Techniken adaptieren und konzeptionell, gestalterisch und technisch realisieren. Der Effekt dieser immersiven analytischen Nutzererfahrungen lässt sich durch geeignete Methoden angemessen evaluieren, bewerten und interpretieren.Die Studierenden kennen die wichtigsten Visualisierungstechnologien und sind in der Lage, geeignete Visualisierugssysteme zu konzipieren, aufzubauen und in der Anwendung zu bewerten. Sie sind in der Lage grundlegende Konzepte der Visualisierung auf relevante Szenarien im täglichen Leben bzw. in spezifischen Anwendungsfeldern (z. B. Data Science) zu übertragen. Hier entwickeln die Studierenden grundlegende Lösungsideen zu den genannten Themen gemeinsam mit anderen im Team und präsentieren diese auf geeignete Weise. Sie geben Kommilitonen im Rahmen der Präsentationen ein wertschätzendes und konstruktives Feedback.\n\n--- Contents (EN) ---\n\n\n--- Contents (DE) ---\nDie Komplexität medialer Anwendungsgebiete und digitaler Produkte erfordert eine kontextuelle und erzählerische Form der Vermittlung von Inhalten. Produktentwickler, Designer und Interaktionsgestalter entwickeln immersive Erzählungen und komplexe Narrative und setzen diese in User-Journey-Modelle um. Um dies zu ermöglichen werden Inhalte, Dramaturgien und narrative Parcours für lineares und nonlineares Erzählen in transmedialen digitalen Medien erforscht und entwickelt. Die Veranstaltung Interactive Storytelling befasst sich mit Inhalten, Dramaturgien und narrative Parcours für lineares und nonlineares Erzählen in digitalen Medien. Wesentliche Inhalte sind:NarratologieImmersion und Worldbuilding Seriality – die Aufteilung des Storyversums und der Handlung in spannende TeileSubjectivity – die verschiedenen Blickwinkel auf die Story Partizipation –  die Motivation des Users zum eigenen HandelnAuf dieser Basis werden der Aufbau von interaktiven Stories und deren Umsetzung in verschieden Medien besprochen. Darüber hinaus werden Techniken zur Verwebung von verschieden Ebenen einer Geschichte und Verknüpfung mit Events in der Realität eingeführt.\n\n--- Literature (EN) ---\n\n\n--- Literature (DE) ---\nAlbrecht Koschorke, Wahrheit und Erfindung. Grundzüge einer Allgemeinen Erzähltheorie (Frankfurt/M, 2012)Henry Jenkins: Transmedia 202. Further refelections (2011). URL: http://henryjenkins.or/2011/08/defining_transmedia_further_re.html (Stand 25.07.2013)Kelly McErlean: Interactive Narratives and Transmedia Storytelling. Creating Immersive Stories Across New Media Platforms New York: CRC Press, 2018Joachim Friedmann, Transmediales Erzählen. Narrative Gestaltung in Literatur, Film, Graphic Novel und Game Köln: Halem, 2017Weitere Literatur wird bei Vorlesungsbeginn bekannt gegeben.", "metadata": {"moduleNumber": "D 5.2.1", "moduleName": "EDIT", "creditPoints": "5.0", "suggestedSemester": 5, "offeredInSeason": "winter_semester", "examType": "project", "heldInLanguage": "de", "reviserName": "", "reviserEmail": null, "studyProgramId": 14, "source_type": "json"}}
{"id": "BDAISY__D_4.2.1", "text": "Title: EDIT\nModule Number: D 4.2.1\nCredits: 5.0 CP\nSemester: 4\nOffered In: summer_semester\nLanguage: de\nExam Type: research_paper\nInstructor: None Christian Voigt\n\n--- Goals (EN) ---\n\n\n--- Goals (DE) ---\nStudierende erwerben Grundkenntnisse zentraler Begriffe im Feld technischer, sozialer und soziotechnischer Innovationen, sind mit zentralen theoretischen Ansätzen im Feld der Innovationsforschung inkl. verschiedener theoretischer Modelle von Innovationen betraut, verstehen Zusammenhänge zwischen technischer und sozialer Innovation (z. B. im Hinblick auf Durchsetzungsprozesse) und können Innovationsprozesse in ihrem systematischen Zusammenhang mit gesellschaftlichen Prozessen beschreiben und analysieren. Sie entwickeln ein Verständnis für Steuerungsmöglichkeiten von Innovationsentwicklung, können Ansätze und Konzepte zur Gestaltung von Innovationsprozessen anwenden und sie mit werteorientierten Ansätzen verbinden. Sie verfügen über die  Kompetenz zur Einnahme kritischer Perspektiven auf Innovationsentwicklung und -förderung und sind in der Lage, ihren Beitrag zur Innovationsentwicklung, insbesondere im Kontext von Data Science und KI (u. a. Data-Driven-Innovation) inkl. der daraus erwachsenden Verantwortung zu reflektieren.\n\n--- Contents (EN) ---\n\n\n--- Contents (DE) ---\nDas Modul befasst sich mit sozio-technischen Innovationen im Kontext der Entwicklung, Anwendung und Evaluation digitaler Technologien. Vermittelt werden theoretische Grundlagen sozio-technischer Innovationen in Zeiten eines beschleunigten digitalen Wandels. Studierende erwerben Wissen über verschiedene Arten von Innovationen sowie Kompetenzen, unterschiedliche Innovationsentwicklungsprozesse zu initiieren, zu begleiten und – auch im Hinblick auf ihre Folgen – im Kontext gesellschaftlicher Werte, wie Nachhaltigkeit, Integrierbarkeit oder Verantwortung zu bewerten. Das Modul zeigt, dass Entwicklung und Diffusion von Innovationen verschiedenen Bedingungen unterliegen und im Zusammenhang mit ökonomischer und politischer Entwicklung betrachtet werden müssen.Zentraler Begriffe im Feld technischer, sozialer und soziotechnischer Innovationen Ausgewählte Innovationsansätze und -theorien (z. B. aus dem Kontext der Innovation Studies)Grundlagen der Innovationsentwicklung inkl. Innovationspolitik Innovationen in gesellschaftlicher Verantwortung (z. B. Responsible Science & Innovation, Innovation & Sustainability, Innovation & Social Justice) Zusammenhänge zwischen Innovationen und sozialem Wandel, Beziehungen zu anderen gesellschaftlichen Bereichen, z. B. ökonomischer Entwicklungen sowie Innovations- und Technikpolitik (Political Economy of Technology Innovation, Science Policy of Technology Innovation)Zentrale Akteure und Institutionen im Kontext strategischer Innovationsentwicklung Ansätze und Konzepte zur Gestaltung von Innovationsprozessen (z. B. Open Innovation, nutzerzentrierte Modelle, neue Formen der Wissensgenerierung, Bürgerorientierung) Soziale Bedeutung von Innovationen, z. B. Innovationen als Ursache und Folge sozialer Konflikte bzw. Probleme Potenziale und Grenzen zur (institutionalisierten) Lösung (bzw. Gestaltung) gesellschaftlicher Probleme durch sozio-technische Innovationen\n\n--- Literature (EN) ---\n\n\n--- Literature (DE) ---\nWeiterführende Literatur:Blättel-Mink B., Schulz-Schaeffer I., Windeler A. (2019) (Hrsg.). Handbuch Innovationsforschung. Wiesbaden: Springer VS.Cockburn, I., Henderson, R., Stern, S. (2018). The impact of artificial intelligence on innovation. National Bureau of Economic Research, NBER Working Paper 24449 (www.nber.org/papers/w24449) Dolata, U. (2013). The Transformative Capacity of New Technologies. A Theory of Sociotechnical Change. London: RoutledgeMai, M. (Hrsg.) (2014). Handbuch Innovationen. Interdisziplinäre Grundlagen und Anwendungsfelder. Wiesbaden: Springer VSVan der Have, R.P. & Rubalcaba, L. (2016).  Social innovation research: An emerging area of innovation studies? Research Policy, 45 (9), 1923-1935.Stilgoe, J., Owen, R. & MacNaghten, P. (2013). Developing a Framework for Responsible Innovation. Research Policy, 42 (9), 1568-1580Weitere Literatur wird bei Vorlesungsbeginn bekannt gegeben", "metadata": {"moduleNumber": "D 4.2.1", "moduleName": "EDIT", "creditPoints": "5.0", "suggestedSemester": 4, "offeredInSeason": "summer_semester", "examType": "research_paper", "heldInLanguage": "de", "reviserName": "None Christian Voigt", "reviserEmail": "christian.voigt@hs-duesseldorf.de", "studyProgramId": 14, "source_type": "json"}}
{"id": "BDAISY__D_5.1.3", "text": "Title: Technology utilisation and technology appropriation\nModule Number: D 5.1.3\nCredits: 5.0 CP\nSemester: 5\nOffered In: winter_semester\nLanguage: de\nExam Type: research_paper\nInstructor: None Martin Doll\n\n--- Goals (EN) ---\nStudents have skills in the application of central concepts of media studies, media psychology and media sociology. They are familiar with the theoretical foundations of media usage research and can apply them to specific contexts of their studies and future professional activities. They can analyse the effects of different media and technology usage patterns in a theoretically sound manner and are able to understand their complex conditionality. They recognise the significance of heterogeneity and diversity in patterns of use and appropriation processes of new technologies, are aware of the importance of specific technical skills and have the skills to reflect on their own role, especially from the perspective of new developments in the context of data science and artificial intelligence. In addition to theoretical approaches, e.g. from the fields of media studies, sociology and psychology, students should be able to recognise various aspects of dealing with media and technology (e.g. aspects of activity and passivity, communitisation and isolation, addiction, emotionalisation and cognition) and be able to reflect on them contextually. They should be able to assess the relevance of specific media skills and reflect on their role as developers of digital technologies.\n\n--- Goals (DE) ---\nStudierende verfügen über Kompetenzen in der Anwendung zentraler Begriffe der Medienwissenschaft, der Medienpsychologie und der Mediensoziologie. Sie kennen theoretische Grundlagen der Mediennutzungsforschung und können sie auf konkrete Kontexte ihres Studiums und künftiger beruflicher Tätigkeit übertragen. Sie können die Auswirkungen verschiedener Medien- und Techniknutzungsmuster theoretisch fundiert analysieren und sind in der Lage, deren komplexe Bedingtheit zu verstehen. Sie erkennen die Bedeutsamkeit von Heterogenität und Diversität in Nutzungsmustern und Aneignungsprozessen neuer Technologien, sind sich der Bedeutung spezifischer Technikkompetenzen bewusst und verfügen über Fähigkeiten zur Reflexion der eigenen Rolle, insbesondere aus der Perspektive neuer Entwicklungen im Kontext von Data Science und künstlicher Intelligenz.Neben theoretischen Ansätzen, z. B. aus dem Feld der Medienwissenschaft, der Soziologie und der Psychologie sollen Studierende in der Lage sein, verschiedene Aspekte des Umgangs mit Medien bzw. Technik (z. B. Aspekte von Aktivität- und Passivität, Vergemeinschaftung und Isolation, Sucht, Emotionalisierung und Kognition) zu erkennen und sie kontextuell reflektieren können. Sie sollen die Relevanz spezifischer Medienkompetenzen beurteilen und ihre Rolle als Entwickler*innen digitaler Technologien reflektieren können.\n\n--- Contents (EN) ---\nThe module focuses on the human use and appropriation of technology, its conditions and consequences, with a particular focus on accelerated digital change. Students should become familiar with patterns of technology use and appropriation, acquire skills for the theoretically sound analysis of media and technology use, develop awareness of problematic and pathological media use and recognise social functions, e.g. of internet use Central concepts of media science, media psychology and media sociology Central principles of media use research, in particular theoretical approaches from the functional (e.g. uses and gratifications approach), procedural and structural perspectives Societal and social framework conditions and accompanying processes (e.g. basics of media socialisation) of media and technology use and appropriation. Fundamentals of media socialisation) of media and technology use and appropriation Fundamentals of the mediatisation of everyday life and society, mediatisation of social relationships, media and generations, media and cultural change Mediatisation and heterogeneity / diversity, e.g. from the perspective of gender media studies and cultural media studies Models, techniques and practices of data processing Fundamentals of media psychology for analysing the prerequisites and consequences of media use, including the possibilities of shaping mediaTheoretical and practical fundamentals of acquiring, teaching and applying media skills.\n\n--- Contents (DE) ---\nDer Fokus des Moduls liegt auf der menschlichen Techniknutzung und Technikaneignung, ihren Bedingungen und Folgen unter besonderer Betrachtung eines beschleunigten digitalen Wandels. Studierende sollen Muster der Techniknutzung und -aneignung kennenlernen, Kompetenzen zur theoretisch fundierten Analyse von Medien- und Techniknutzung erwerben, Bewusstsein für problematischen und pathologischen Mediengebrauch entwickeln sowie soziale Funktionen, z. B. des Internetgebrauchs, erkennen.Zentraler Begriffe der Medienwissenschaft, der Medienpsychologie und Mediensoziologie Zentrale Grundlagen der Mediennutzungsforschung, insbesondere theoretische Ansätze aus der funktionalen (z. B. Uses-and-Gratifications-Ansatz), prozessualen und strukturellen Perspektive Gesellschaftliche und soziale Rahmenbedingungen und Begleitprozesse (z. B. Grundlagen der Mediensozialisation) von Medien- bzw. Techniknutzung und -aneignung Grundlagen der Mediatisierung von Alltag und Gesellschaft, Mediatisierung sozialer Beziehungen, Medien und Generationen, Medien und kultureller Wandel Mediatisierung und Heterogenität / Diversität, z. B. aus Sicht der Gender Media Studies und Cultural Media Studies Modelle, Techniken und Praktiken der Verdatung Medienpsychologische Grundlagen zur Analyse der Voraussetzungen sowie der Folgen von Mediennutzung inkl. der Möglichkeiten der Gestaltung von MedienTheoretische und praktische Grundlagen des Erwerbs, der Vermittlung und Anwendung von Medienkompetenzen\n\n--- Literature (EN) ---\nBonfadelli, H. & Friemel, T.N. (2011). Medienwirkungsforschung. Konstanz, München: UVK; UTB\nKnoblauch, H. (2016). Die kommunikative Konstruktion der Wirklichkeit. Wiesbaden: Springer VS\nKrotz, F., Despotovic, C. & Kruse, M.-M. (Hrsg.) (2017). Mediatisierung als Metaprozess. Transformationen, Formen der Entwicklung und die Generierung von Neuem. Wiesbaden: Springer VS\nMämecke, T., Passoth, J.-H. & Wehner, J. (Hrsg.) (2018). Bedeutende Daten. Modelle, Verfahren und Praxis der Vermessung und Verdatung im Netz. Wiesbaden: Springer VS\nSchweiger, W. (2007). Theorien der Mediennutzung. Eine Einführung. Wiesbaden: Springer VS\nPfadenhauer, M. & Grenz, T. (Hrsg.) (2017). De-Mediatisierung. Diskontinuitäten, Non-Linearitäten und Ambivalenzen im Mediatisierungsprozess. Wiesbaden: Springer VS\nTrepte, S. & Reinecke, K. (2013). Medienpsychologie. Stuttgart: KohlhammerWeitere Literatur wird bei Vorlesungsbeginn bekannt gegeben.\n\n--- Literature (DE) ---\nBonfadelli, H. & Friemel, T.N. (2011). Medienwirkungsforschung. Konstanz, München: UVK; UTB\nKnoblauch, H. (2016). Die kommunikative Konstruktion der Wirklichkeit. Wiesbaden: Springer VS\nKrotz, F., Despotovic, C. & Kruse, M.-M. (Hrsg.) (2017). Mediatisierung als Metaprozess. Transformationen, Formen der Entwicklung und die Generierung von Neuem. Wiesbaden: Springer VS\nMämecke, T., Passoth, J.-H. & Wehner, J. (Hrsg.) (2018). Bedeutende Daten. Modelle, Verfahren und Praxis der Vermessung und Verdatung im Netz. Wiesbaden: Springer VS\nSchweiger, W. (2007). Theorien der Mediennutzung. Eine Einführung. Wiesbaden: Springer VS\nPfadenhauer, M. & Grenz, T. (Hrsg.) (2017). De-Mediatisierung. Diskontinuitäten, Non-Linearitäten und Ambivalenzen im Mediatisierungsprozess. Wiesbaden: Springer VS\nTrepte, S. & Reinecke, K. (2013). Medienpsychologie. Stuttgart: KohlhammerWeitere Literatur wird bei Vorlesungsbeginn bekannt gegeben.", "metadata": {"moduleNumber": "D 5.1.3", "moduleName": "Technology utilisation and technology appropriation", "creditPoints": "5.0", "suggestedSemester": 5, "offeredInSeason": "winter_semester", "examType": "research_paper", "heldInLanguage": "de", "reviserName": "None Martin Doll", "reviserEmail": "martin.doll@hs-duesseldorf.de", "studyProgramId": 14, "source_type": "json"}}
{"id": "BDAISY__D_4.2.3", "text": "Title: Evaluation of digital technologies\nModule Number: D 4.2.3\nCredits: 5.0 CP\nSemester: 4\nOffered In: summer_semester\nLanguage: de\nExam Type: research_paper\nInstructor: Prof. Dr. Alina Huldtgren\n\n--- Goals (EN) ---\n\n\n--- Goals (DE) ---\nStudierende erwerben Grundkenntnisse zentraler Begriffe im Feld technischer, sozialer und soziotechnischer Innovationen, sind mit zentralen theoretischen Ansätzen im Feld der Innovationsforschung inkl. verschiedener theoretischer Modelle von Innovationen betraut, verstehen Zusammenhänge zwischen technischer und sozialer Innovation (z. B. im Hinblick auf Durchsetzungsprozesse) und können Innovationsprozesse in ihrem systematischen Zusammenhang mit gesellschaftlichen Prozessen beschreiben und analysieren. Sie entwickeln ein Verständnis für Steuerungsmöglichkeiten von Innovationsentwicklung, können Ansätze und Konzepte zur Gestaltung von Innovationsprozessen anwenden und sie mit werteorientierten Ansätzen verbinden. Sie verfügen über die Kompetenz zur Einnahme kritischer Perspektiven auf Innovationsentwicklung und -förderung und sind in der Lage, ihren Beitrag zur Innovationsentwicklung, insbesondere im Kontext von Data Science und KI (u. a. Data-Driven-Innovation) inkl. der daraus erwachsenden Verantwortung zu reflektieren.\n\n--- Contents (EN) ---\n\n\n--- Contents (DE) ---\nDie Ziele des Moduls bestehen in der Vermittlung grundlegender Kenntnisse der Mensch-Technik-Interaktion im Kontext aktueller Forschung und Entwicklung. Studierende sollen befähigt werden, in Abhängigkeit von den Zielen ihres Studiums geeignete Fragen für die Konzeption und Realisierung von Schnittstellen zwischen Mensch und Technik unter besonderer Berücksichtigung der Merkmale künftiger Nutzergruppen, spezifischer Handlungskontexte und der zur Verfügung stehenden Ressourcen  zu formulieren. Eine wichtige Frage bildet dabei die Beteiligung potenzieller Nutzer*innen an der Schnittstellenentwicklung und der begleitenden Evaluierung im Rahmen eines iterativen Entwicklungsprozesses. Im Fokus des Moduls stehen verschiedene Methoden für Konzeption, Design, Prototyping und Evaluation deren beispielhafte Anwendung auf konkrete Felder im Kontext von Data Science und KI.  Zentraler Begriffe im Feld technischer, sozialer und soziotechnischer InnovationenGrundlagen, Methoden, Modelle und Konzepte zur Gestaltung von Benutzungsschnittstellen für interaktive AnwendungenPhysiologische und Psychologische Grundlagen der menschlichen Wahrnehmung, von Gedächtnis, Wissen, Erfahrung sowie der Handlungsregulation sowie Ihre Anwendung in der MCI Konsequenzen der Gestaltung von Hardware und Software für Nutzer Modelle der Kommunikation und Anwendung auf die MCIGestaltung von interaktiven Systemen, insbesondere webbasierte und mobile Systeme: Dialoggestaltung, Informationsdarstellung, Navigation, Orientierung, InteraktionsformenIntegration von Software-Ergonomie in Software-EngineeringNormen, gesetzliche Grundlagen und RichtlinienGrundlagen der Programmierung von GUIs\n\n--- Literature (EN) ---\n\n\n--- Literature (DE) ---\nAndreas Butz, Antonio Krüger. Mensch-Technik Interaktion, De Gruyter Oldenbourg, 2014\nKevin Liggeri, Oliver Müller. Mensch-Maschine-Interaktion: Handbuch zu Geschichte - Kultur - Ethik, JB Metzler, 2019\nMarkus Dahm: Grundlagen der Mensch-Computer-Interaktion, Pearson (2006)\nJens Jacobsen: Praxisbuch Usability und UX, Rheinwerk (2017)\nSteve Krug: Don't make me think - revisited, New Riders (2013)\nBernhard Preim, Raimund Dachselt: Interaktive Systeme Band 1 und 2, eXamen.pressDon Norman: The Design of Everyday Things, Basic Books (2013)\nMichael Richter, Markus D. Flückiger: Usability und UX kompakt: Produkte für Menschen (IT kompakt), Springer Vieweg (2016)\nWeitere Literatur wird bei Vorlesungsbeginn bekannt gegeben.", "metadata": {"moduleNumber": "D 4.2.3", "moduleName": "Evaluation of digital technologies", "creditPoints": "5.0", "suggestedSemester": 4, "offeredInSeason": "summer_semester", "examType": "research_paper", "heldInLanguage": "de", "reviserName": "Prof. Dr. Alina Huldtgren", "reviserEmail": "alina.huldtgren@hs-duesseldorf.de", "studyProgramId": 14, "source_type": "json"}}
{"id": "BDAISY__xxD_4.3_PF", "text": "Title: EDIT\nModule Number: xxD 4.3 PF\nCredits: 15.0 CP\nSemester: 4\nOffered In: summer_semester\nLanguage: de\nExam Type: none\nInstructor: \n\n--- Goals (EN) ---\n\n\n--- Goals (DE) ---\n\n\n--- Contents (EN) ---\n\n\n--- Contents (DE) ---\n\n\n--- Literature (EN) ---\n\n\n--- Literature (DE) ---", "metadata": {"moduleNumber": "xxD 4.3 PF", "moduleName": "EDIT", "creditPoints": "15.0", "suggestedSemester": 4, "offeredInSeason": "summer_semester", "examType": "none", "heldInLanguage": "de", "reviserName": "", "reviserEmail": null, "studyProgramId": 14, "source_type": "json"}}
{"id": "BDAISY__xxD_5.PF", "text": "Title: EDIT\nModule Number: xxD 5.PF\nCredits: 15.0 CP\nSemester: 5\nOffered In: winter_semester\nLanguage: de\nExam Type: none\nInstructor: \n\n--- Goals (EN) ---\n\n\n--- Goals (DE) ---\n\n\n--- Contents (EN) ---\n\n\n--- Contents (DE) ---\n\n\n--- Literature (EN) ---\n\n\n--- Literature (DE) ---", "metadata": {"moduleNumber": "xxD 5.PF", "moduleName": "EDIT", "creditPoints": "15.0", "suggestedSemester": 5, "offeredInSeason": "winter_semester", "examType": "none", "heldInLanguage": "de", "reviserName": "", "reviserEmail": null, "studyProgramId": 14, "source_type": "json"}}
{"id": "BDAISY__PF_2.1", "text": "Title: EDIT\nModule Number: PF 2.1\nCredits: 5.0 CP\nSemester: 4\nOffered In: summer_semester\nLanguage: de\nExam Type: project\nInstructor: Prof. Dr. Alina Huldtgren\n\n--- Goals (EN) ---\n\n\n--- Goals (DE) ---\nDie Studierenden sind in der Lage die verschiedenen\nEinsatzmöglichkeiten digitaler Technologien im Gesundheitswesen zu erklären.\nSie sind fähig, Hilfsmittel und Dienstleistungen, bei denen Informations- und\nKommunikationstechnologien eingesetzt werden und die der Vorbeugung, Diagnose,\nBehandlung, Überwachung und Verwaltung im Gesundheitswesen dienen, zu\nanalysieren und zu beurteilen. Die Studierenden haben grundlegende Kompetenzen\nim Bereich Gesundheit und Wohlbefinden erlangt, um erste Ideen für\nentsprechende Digitalisierungsstrategien zu entwickeln.\n\n--- Contents (EN) ---\n\n\n--- Contents (DE) ---\nDas Modul gibt einen umfassenden Überblick über ausgewählte Bereiche des Digital Health im nationalen und internationalen Kontext. Prozesse, Akteure und Versorgungsziele des Digital Health werden ebenso näher beleuchtet wie aktuelle Standards der Gesundheitsversorgung, Forschung und patientenzentrierter Behandlung. Im Vordergrund stehen dabei die Einführung, Integration und Überwachung von digitalen Lösungen. Die Veranstaltung gibt einen breiten Überblick und vereinbart die wichtigsten begrifflichen Grundlagen für das gemeinsame Verständnis in anderen Veranstaltungen des Professional Fokus „Digital Health“.Einführung und Motivation mit Fokus auf Digitalisierung und Digitalität im GesundheitswesenStatus Quo Digital Health in Deutschland, Europa und der WeltDigitalisierung und digitale Transformation im Kontext Gesundheit (Begriffsklärung, Herausforderungen, Ansatzpunkte)Übersicht der verschiedenen Bereiche digitaler Gesundheit (Medizintechnik, eHealth, mHealth/ QS, AAL, Web & Social Media, AUIs wie VR, AR  etc.).Ausgewählte Best Practice-Lösungen der Digitalisierung im GesundheitswesenIT Einsatz im Gesundheitswesen: E-Health, Mobile Health, Ambient HealthData Science und KI im GesundheitswesenTransfer von Digital Health in den VersorgungsalltagGestaltung der Mensch-Maschine-Schnittstelle als Grundlage des AnwendungserfolgsErfolgsfaktoren in der DigitalisierungGesellschaftliche und ethische Folgen der digitalen Transformation\n\n--- Literature (EN) ---\n\n\n--- Literature (DE) ---\nWeiterführende Literatur:1. Margo Edmunds, Christopher Hass, Erin Holve: Consumer Informatics and Digital Health- Solutions for Health and Health Care, Springer, 20192. Arthur André. Digital Medicine. Springer, 20193. Lotfi Chaari. Digital Health Approach for Predictive, Preventive, Personalised and Participatory Medicine, Springer 20194. Robin Haring. Gesundheit Digital - Perspektiven zur Digitalisierung im Gesundheitswesen, Springer, 20195. Weitere Literatur wird bei Vorlesungsbeginn bekannt gegeben.", "metadata": {"moduleNumber": "PF 2.1", "moduleName": "EDIT", "creditPoints": "5.0", "suggestedSemester": 4, "offeredInSeason": "summer_semester", "examType": "project", "heldInLanguage": "de", "reviserName": "Prof. Dr. Alina Huldtgren", "reviserEmail": "alina.huldtgren@hs-duesseldorf.de", "studyProgramId": 14, "source_type": "json"}}
{"id": "BDAISY__PF_2.2", "text": "Title: EDIT\nModule Number: PF 2.2\nCredits: 5.0 CP\nSemester: 4\nOffered In: summer_semester\nLanguage: en_on_demand\nExam Type: project\nInstructor: Prof. Dr. Alina Huldtgren\n\n--- Goals (EN) ---\n\n\n--- Goals (DE) ---\nDie Studierenden sind in der Lage, notwendige nicht-technischen Grundlagen zur Konzeption und Gestaltung von Digital Health Lösungen zu erklären und anhand konkreter Nutzeranforderungen zu demonstrieren. Sie können für eine gegebene Fragestellung alle Phasen eines nutzerzentrierten Vorgehens eigenständig und im Team durchführen.Die Studierenden sind in der Lage die wichtigen psychologischen Modelle, die für digitale Anwendungen im Gesundheitsbereich relevant sind, darzustellen und können abhängig von einer gegebenen Fragestellung Modelle vergleichen und für die Anwendungsentwicklung passend selektieren. Sie können auf Basis der gewählten Modelle, Anwendungen konzipieren und deren UIs nutzerfreundlich gestalten und an Nutzerbedürfnisse anpassen. Sie sind fähig, geeignete technische Ansätze zur Visualisierung der resultierenden Nutzererfahrung und zur schnellen Prototypentwicklung selbst zu entwickeln. Unabhängig von der Art der Anwendung können die Studierenden die Treiber und Barrieren der digitalen Gesundheitstechnik beurteilen und mithilfe ausgewählter Designmethodik die Akzeptanz ihres Designs erhöhen.\n\n--- Contents (EN) ---\n\n\n--- Contents (DE) ---\nVermittlung notwendiger Grundlagen der Gestaltung, Psychologie und Produktion nutzerzentrierter Systeme im Bereich Digital Health. Dies beinhaltet einerseits Grundlagen im Bereich HCI, UI/UX Design und Accessibility sowie andererseits die im Gesundheitsbereich zugrundeliegenden psychologischen Mechanismen und Konstrukte (u. a. Behavior Change Model und Self-Determination Theorie für digitale Lösungen z. B. im Bereich Prävention, Rehabilitation oder Therapie). Strategien in der Gestaltung von patienten- und menschzentrierten digitalen Lösungen wie Gamification und Nudging (Persuasive Design) werden vorgestellt und angewandt. Studierende erproben ihr erlerntes Wissen an kleineren Designaufgaben bzw. einem Projekt. Studierenden erlernen das Konzept der Nutzer-Akzeptanz und wie diese aufgrund geeigneter Designprozesse erhöht werden kann.Grundlagen der Mensch-Technik-Interaktion und Gestaltungsprinzipien für Digital Health-LösungenPsychologische Grundlagen für digitale Gesundheit, u. a. Self-Determination Theorie, Behavior Change Modell, Stage-based model of Personal InformaticsNutzerzentrierte Prozesse (UCD, PD, Design Thinking) und User Experience im GesundheitsbereichAkzeptanzmodelle (u. a. TAM, UTAUT)Mobile und allgegenwärtige GesundheitslösungenWellbeing und Prävention als VerhaltensmusterDigitale Gesundheitskompetenz (eHealth literacy)GamificationAccessibilityKonzepte des Persuasive Design (u. a. Nudging)\n\n--- Literature (EN) ---\n\n\n--- Literature (DE) ---\nKu, B., Lupton, E. (2020).  Health Design Thinking Creating Products and Services for Better Health. MIT PressKuniavsky, M. (2003). Observing the user experience: a practitioner's guide to user research. Morgan KaufmannHassenzahl, M. (2010). Experience design: Technology for all the right reasons. Synthesis Lectures on Human-Centered Informatics, 3(1), 1-95BJ Fogg. 2009. A behavior model for persuasive design. In Proceedings of the 4th International Conference on Persuasive Technology (Persuasive '09). Association for Computing Machinery, New York, NY, USA, Article 40, 1–7Deci, E. L., & Ryan, R. M. (2012). Self-determination theory", "metadata": {"moduleNumber": "PF 2.2", "moduleName": "EDIT", "creditPoints": "5.0", "suggestedSemester": 4, "offeredInSeason": "summer_semester", "examType": "project", "heldInLanguage": "en_on_demand", "reviserName": "Prof. Dr. Alina Huldtgren", "reviserEmail": "alina.huldtgren@hs-duesseldorf.de", "studyProgramId": 14, "source_type": "json"}}
{"id": "BDAISY__PF_2.3", "text": "Title: EDIT\nModule Number: PF 2.3\nCredits: 5.0 CP\nSemester: 4\nOffered In: summer_semester\nLanguage: de\nExam Type: research_paper\nInstructor: Prof. Dr. Alina Huldtgren\n\n--- Goals (EN) ---\n\n\n--- Goals (DE) ---\nDie\nStudierenden können die relevanten Akteure in digitalen Gesundheitslösungen\nidentifizieren und sind in der Lage, profilspezifische Informationen von diesen\nzu extrahieren. Durch eine geeignete Modellbildung ist die Erstellung von\nNutzerprofilen möglich und es können unterschiedliche Perspektiven auf die\njeweilige Lösung entwickelt und abgewogen (value trade-offs) werden.\nInkonsistente, unvollständige oder kontroverse Sichtweisen können\nidentifiziert, analysiert und bewertet werden. Die Studierenden können bei\nBedarf neue Perspektiven ableiten und verschiedene Positionen anderer\nBeteiligter sachgerecht wiedergeben. Neben der Reflektionsfähigkeit über eigene\nund andere Perspektiven zu diskutieren, besitzen die Studierenden die\nFähigkeit, unter Nutzung werteorientierter Methodik verantwortungsvolle\nInnovationen (responsible innovation) im Gesundheitsbereich zu antizipieren, zu\ndokumentieren und zu kommunizieren.\n\n--- Contents (EN) ---\n\n\n--- Contents (DE) ---\nDas Fach betrachtet vor allem nicht-technische Aspekte digitaler Gesundheitslösungen aus unterschiedlichen Perspektiven der beteiligten Teilnehmer (Stakeholder). Dabei sollen insbesondere Sichtweisen erlebt werden, die neuartig, kritisch, kontrovers und ggf. inkonsistent sind. Die verschiedenen Rollen der Akteure werden identifiziert, spezifiziert und bewertet werden. Zukünftige Rollen verschiedener Akteure (z. B. selbstverantwortliche Patienten) lassen sich in diesem Modul spekulativ antizipieren, exakt definieren und geeignet dokumentieren. Aspekte wie Datensicherheit, Werteorientierung und freudvolles Erleben digitaler Gesundheitslösungen werden zielgerichtet unterstützt.Identifikation und Klassifikation von Akteuren im Gesundheitswesen, StakeholderanalyseBeschreibungsverfahren der Nutzerprofile und Entwicklung konkreter Ausprägung der StakeholderDarstellung unterschiedlicher Perspektiven und Vergleich bzw. Analyse unterschiedlicher PositionenEthische Grundlagen, verantwortungsvolle Innovation, Anwendung ethischer Modelle, z. B. MEESTAR, für Digital HealthRechtliche Aspekte digitaler GesundheitslösungenSoziale und gesellschaftliche Implikationen von Digital Health LösungenValue-Sensitive Design als Gestaltungsgrundlage von Digital Health LösungenDatensicherheit und Privatheit bei digitalen GesundheitslösungenFallstudienpraxis\n\n--- Literature (EN) ---\n\n\n--- Literature (DE) ---\nLupton, D. (2017). Digital health: critical and cross-disciplinary perspectives. RoutledgeWeber, K. (2015). MEESTAR: Ein Modell zur ethischen Evaluierung sozio-technischer Arrangements in der Pflege-und Gesundheitsversorgung. Technisierung des Alltags. Beitrag für ein gutes Leben, 247-262Friedman, B., Kahn, P. H., Borning, A., & Huldtgren, A. (2013). Value sensitive design and information systems. In Early engagement and new technologies: Opening up the laboratory (pp. 55-95). Springer, DordrechtVan Wynsberghe, A. (2013). Designing robots for care: Care centered value-sensitive design. Science and engineering ethics, 19(2), 407-433Nissenbaum, H. (2009). Privacy in context: Technology, policy, and the integrity of social life. Stanford University Press", "metadata": {"moduleNumber": "PF 2.3", "moduleName": "EDIT", "creditPoints": "5.0", "suggestedSemester": 4, "offeredInSeason": "summer_semester", "examType": "research_paper", "heldInLanguage": "de", "reviserName": "Prof. Dr. Alina Huldtgren", "reviserEmail": "alina.huldtgren@hs-duesseldorf.de", "studyProgramId": 14, "source_type": "json"}}
{"id": "BDAISY__PF_2.4", "text": "Title: Machine-Learning for Digital Health & Social Services\nModule Number: PF 2.4\nCredits: 5.0 CP\nSemester: 4\nOffered In: summer_semester\nLanguage: en_on_demand\nExam Type: portfolio\nInstructor: Prof. Dr. Florian Huber\n\n--- Goals (EN) ---\nStudents are able to weigh up and apply the use of previously considered methods for data science and artificial intelligence for the application area of digital health and social services.\n\n--- Goals (DE) ---\nDie Studierenden sind in der Lage, den Einsatz zuvor betrachteter Methoden für Data Science und Künstliche Intelligenz für den Anwendungsbereich Digitale Gesundheit und Soziale Dienste abzuwägen und anzuwenden.\n\n--- Contents (EN) ---\nTechniques from the field of artificial intelligence, especially machine learning, offer numerous promising applications in digital health and social services. This is particularly true for the analysis and use of very large and complex data sets. Examples include medical diagnostics and prognostics, or the large-scale evaluation and linking of text and process data with the aim of optimising or improving processes in healthcare or social services. This event provides an overview of current and future developments in the field. Key machine learning methods will be implemented with real data from the healthcare and social services sectors in live coding sessions.\n- Overview of application areas and common methods in the field of digital health and social services\n- Handling of key data types in the above-mentioned areas: tabular data, image data, time series, text data\n- Conventional linear models in medicine\n- Prediction models of classical machine learning (including linear models, random forest)\n- Evaluation of models and explainable AI\n- Deep learning models (e.g. CNNs) for the classification and segmentation of image data.\n- Deep learning models for the classification of time series (e.g. CNNs, LSTMs).\n- Consideration of related ethical issues regarding the use of AI for critical applications (e.g. biases, interpretability, or privacy).\n\n--- Contents (DE) ---\nTechniken aus dem Bereich Künstliche Intelligenz, insbesondere Machine-Learning, bieten zahlreiche vielversprechende Einsatzmöglichkeiten im Bereich Digital Health und Social Services. Das gilt besonders für die Analyse und Nutzung von sehr großen und komplexer Datensätzen. Beispiele dafür sind die medizinische Diagnostik oder Prognose, oder der großflächigen Auswertung und Verknüpfung von Text- und Prozessdaten mit dem Ziel Abläufe im Gesundheitsbereich oder bei sozialen Diensten zu optimieren oder zu verbessern. Dieser Veranstaltung gibt einen Überblick über aktuelle und zukünftige Entwicklungen in dem Gebiet, Zentrale Machine-Learning Verfahren werden dabei mit realen Daten aus dem Bereich Gesundheit oder Social Services in Live Coding Sessions umgesetzt.\n- Überblick über Einsatzgebiete und gängige Verfahren im Bereich Digital Health und Social Services\n- Behandlung zentraler Datentypen in den genannten Bereichen: Tabellarische Daten, Bilddaten, Zeitserien, Textdaten\n- Konventionelle linear Modelle in der Medizin\n- Vorhersagemodelle des klassischen Machine Learnings (u.a. lineare Modelle, Random Forest).\n- Evaluation von Modellen und Explainable AI\n- Deep Learning Modelle (z.B. CNNs) zur Klassifizierung und Segmentierung von Bilddaten.\n- Deep Learning Modele zur Klassifizierung von Zeitserien (z.B. CNNs, LSTMs).\n- Betrachtung angrenzender ethischer Fragen zum Einsatz von KI für kritische Anwendungen (z.B. Biases, Interpretierbarkeit, oder Privatshäre).\n\n--- Literature (EN) ---\nScientific articles are shared and discussed as part of a journal club. Further literature will be announced at the beginning of the lecture.\n\n--- Literature (DE) ---\nIm Rahmen eines Journal-Clubs werden wissenschaftliche Fachartikel geteilt und besprochen. Weitere Literatur wird bei Vorlesungsbeginn bekannt gegeben.", "metadata": {"moduleNumber": "PF 2.4", "moduleName": "Machine-Learning for Digital Health & Social Services", "creditPoints": "5.0", "suggestedSemester": 4, "offeredInSeason": "summer_semester", "examType": "portfolio", "heldInLanguage": "en_on_demand", "reviserName": "Prof. Dr. Florian Huber", "reviserEmail": "florian.huber@hs-duesseldorf.de", "studyProgramId": 14, "source_type": "json"}}
{"id": "BDAISY__PF_2.5", "text": "Title: EDIT\nModule Number: PF 2.5\nCredits: 10.0 CP\nSemester: 5\nOffered In: summer_semester\nLanguage: en_on_demand\nExam Type: project\nInstructor: Prof. Dr. Alina Huldtgren\n\n--- Goals (EN) ---\n\n\n--- Goals (DE) ---\nDie Studierenden\nlernen die praktische Gestaltung und Konzeption für eine neue Fragestellung\nkennen. Studierende können zuvor gelernte Designmethodik anwenden, u. a.\nBedürfnisse der Zielgruppe erheben, erhobene Daten zu Designanforderungen\nsynthetisieren sowie Prototypen entwickeln und zu evaluieren. Zudem können\nStudierende ihre Designkonzepte an (möglichst reale oder auch fiktive)\nAuftraggeber kommunizieren.\n\n--- Contents (EN) ---\n\n\n--- Contents (DE) ---\nUmsetzung eines größeren praktischen Vorhabens im Professional Fokus „Digital Health“ als interdisziplinäres Projekt mit gestalterisch-konzeptionellem Fokus. Die Zusammenarbeit mit Akteuren aus dem Gesundheitswesen wird dabei gesucht.Durchführung eines gestalterischen Projekts anhand eines iterativen Entwicklungsvorhabens, z. B. auf Basis von Design Thinking, Design Fiction oder andere Methoden.Projektdurchführung mit allen notwendigen Phasen (Anforderungsermittlung, Konzeption, Design, Prototyping, Evaluation, Dokumentation)Kommunikation mit potentiellen Projektpartnern bzw. AufgabenerstellernProjektmanagement auf Basis von agilen Methoden\n\n--- Literature (EN) ---\n\n\n--- Literature (DE) ---\nBrown, T., (2009). Change by Design. HarperCollinsDark Horse Innovation (2016). Digital Innovation Playbook. Das unverzichtbare Arbeitsbuch für Gründer*innen, Macher*innen und Manager*innen. MurmannDunne, A., & Raby, F. (2013). Speculative everything: design, fiction, and social dreaming. MIT pressTiemeyer, E. (Ed.). (2014). Handbuch IT-Projektmanagement: Vorgehensmodelle, Managementinstrumente, Good Practices. Carl Hanser Verlag GmbH Co KG.", "metadata": {"moduleNumber": "PF 2.5", "moduleName": "EDIT", "creditPoints": "10.0", "suggestedSemester": 5, "offeredInSeason": "summer_semester", "examType": "project", "heldInLanguage": "en_on_demand", "reviserName": "Prof. Dr. Alina Huldtgren", "reviserEmail": "alina.huldtgren@hs-duesseldorf.de", "studyProgramId": 14, "source_type": "json"}}
{"id": "BDAISY__PF_2.6", "text": "Title: EDIT\nModule Number: PF 2.6\nCredits: 10.0 CP\nSemester: 5\nOffered In: summer_semester\nLanguage: en_on_demand\nExam Type: project\nInstructor: Prof. Dr. Alina Huldtgren\n\n--- Goals (EN) ---\n\n\n--- Goals (DE) ---\nDie\nStudierenden erlernen die praktische Anwendung bisher erlernter\nITK-Technologien für den Bereich Digitale Gesundheit in allen Phasen der\nanspruchsvollen Projektdurchführung. Ein Schwerpunkt ist dabei die technische\nKonzeption und Entwicklung von Lösungen für praktisch relevante Fragestellungen\naus dem Kontext Digital Health. Dabei wird eng und kontinuierlich mit Anwendern\nund Praxispartnern kooperiert.\n\n--- Contents (EN) ---\n\n\n--- Contents (DE) ---\nUmsetzung eines größeren praktischen Vorhabens im Professional Fokus „Digital Health“ als interdisziplinäres Projekt mit technischem Fokus.Durchführung eines praktischen Projekts anhand eines iterativen Entwicklungsvorhabens, z. B. auf Basis von Design Thinking, Partizipativem Design oder User-Centered DesignProjektdurchführung mit allen notwendigen Phasen (Anforderungsermittlung, Konzeption, Design, Prototyping/Implementierung, Evaluation, Dokumentation)Kommunikation mit potentiellen Projektpartnern bzw. AufgabenerstellernProjektmanagement basierend auf agilen Methoden\n\n--- Literature (EN) ---\n\n\n--- Literature (DE) ---\nWeiterführende Literatur:Brown, T., (2009). Change by Design. HarperCollinsDark Horse Innovation (2016). Digital Innovation Playbook. Das unverzichtbare Arbeitsbuch für Gründer*innen, Macher*innen und Manager*innen. MurmannTiemeyer, E. (Ed.). (2014). Handbuch IT-Projektmanagement: Vorgehensmodelle, Managementinstrumente, Good Practices. Carl Hanser Verlag GmbH Co KG.", "metadata": {"moduleNumber": "PF 2.6", "moduleName": "EDIT", "creditPoints": "10.0", "suggestedSemester": 5, "offeredInSeason": "summer_semester", "examType": "project", "heldInLanguage": "en_on_demand", "reviserName": "Prof. Dr. Alina Huldtgren", "reviserEmail": "alina.huldtgren@hs-duesseldorf.de", "studyProgramId": 14, "source_type": "json"}}
{"id": "BDAISY__PF_3.1", "text": "Title: IT in Automation Technology\nModule Number: PF 3.1\nCredits: 5.0 CP\nSemester: 4\nOffered In: summer_semester\nLanguage: de\nExam Type: written_exam\nInstructor: None Michael Protogerakis\n\n--- Goals (EN) ---\nAfter successfully completing the module, students will be able to:\n\t1.\tDescribe and Classify (Remember / Understand)\nDescribe the fundamental concepts of embedded systems as well as typical computer architectures and classify them in terms of their use in automation technology.\n\t2.\tExplain and Compare (Understand / Analyze)\nExplain the structure and functioning of microcontrollers and programmable logic controllers (PLCs), and compare their possible applications.\n\t3.\tImplement (Apply)\nImplement simple programs for controlling automation tasks in MicroPython as well as in a PLC according to IEC 61131-3.\n\t4.\tAnalyze (Analyze)\nAnalyze scheduling strategies and their impact on the real-time capability of embedded systems.\n\t5.\tEvaluate (Evaluate)\nEvaluate different embedded solutions (e.g., based on PLCs or microcontrollers) with respect to specific requirements in automation technology.\n\t6.\tDevelop (Create)\nDevelop and document simple yet functional control solutions based on microcontrollers or PLCs.\n\n--- Goals (DE) ---\nNach erfolgreichem Abschluss des Moduls können die Studierenden:\n1.\tBeschreiben und Einordnen (Remember / Understand)\ndie grundlegenden Konzepte eingebetteter Systeme sowie typische Rechnerarchitekturen beschreiben und hinsichtlich ihres Einsatzes in der Automatisierungstechnik einordnen.\n2.\tErklären und Vergleichen (Understand / Analyze)\nden Aufbau und die Funktionsweise von Mikrocontrollern und speicherprogrammierbaren Steuerungen (SPS) erklären und deren Einsatzmöglichkeiten vergleichen.\n3.\tImplementieren (Apply)\neinfache Programme zur Steuerung von Automatisierungsaufgaben in MicroPython sowie in einer SPS gemäß IEC 61131-3 implementieren.\n4.\tAnalysieren (Analyze)\nScheduling-Strategien und deren Auswirkungen auf die Echtzeitfähigkeit eingebetteter Systeme analysieren.\n5.\tBewerten (Evaluate)\nunterschiedliche Embedded-Lösungen (z.B. auf Basis von SPS oder Mikrocontroller) im Hinblick auf spezifische Anforderungen in der Automatisierungstechnik bewerten.\n6.\tEntwickeln (Create)\neinfache, aber funktionale Steuerungslösungen auf Mikrocontroller- oder SPS-Basis entwickeln und dokumentieren.\n\n--- Contents (EN) ---\n- Fundamentals of Embedded Systems and Computer Architectures\n- Introduction to Real-Time Systems and Scheduling Strategies\n- Interfacing and Communication of Microcontrollers\n- Programming Microcontrollers with MicroPython\n- Fundamentals of PLCs according to IEC 61131-3\n- Programming PLCs in ST, FBD, and LD\n\n--- Contents (DE) ---\n- Grundlagen eingebetteter Systeme und Rechnerarchitekturen\n- Einführung in Echtzeitsysteme und Scheduling-Strategien\n- Interfacing und Kommunikation von Mikrocontrollern\n- Programmierung von Mikrocontrollern mit MicroPython\n- Grundlagen der SPS nach IEC 61131-3\n- Programmierung von SPS in ST, FBS und AS\n- Vergleich und Auswahl eingebetteter Lösungen für Automatisierungsaufgaben\n\n--- Literature (EN) ---\n- Bernstein: Mikrocontroller: Grundlagen der Hard- und Software der Mikrocontroller\nATtiny2313, ATtiny26 und ATmega32, Springer-Fachmedien;\nhttps://doi.org/10.1007/978-3-658-02813-8_5\n- Grundlagen für Echtzeitsysteme in der Automatisierung; in: Echtzeitsysteme, 1130.\neXamen.press. Springer; https://doi.org/10.1007/3-540-27416-2_1.\n- Wellenreuther, Zastrow: Automatisieren mit SPS - Theorie und Praxis: IEC 61131-3;\n- STEP 7; Bibliotheksbausteine; AS-i-Bus; PROFIBUS; Ethernet-TCP/IP; OPC;\nSteuerungssicherheit, Vieweg+Teubner; https://doi.org/10.1007/978-3-663-05705-\n5_2\n- Adam, Adam: SPS-Programmierung in Anweisungsliste nach IEC 61131-3: Eine\nsystematische und handlungsorientierte Einführung in die strukturierte\nProgrammierung, Springer; https://doi.org/10.1007/978-3-662-46716-9_1\n\n--- Literature (DE) ---\n- Bernstein: Mikrocontroller: Grundlagen der Hard- und Software der Mikrocontroller\nATtiny2313, ATtiny26 und ATmega32, Springer-Fachmedien;\nhttps://doi.org/10.1007/978-3-658-02813-8_5\n- Grundlagen für Echtzeitsysteme in der Automatisierung; in: Echtzeitsysteme, 1130.\neXamen.press. Springer; https://doi.org/10.1007/3-540-27416-2_1.\n- Wellenreuther, Zastrow: Automatisieren mit SPS - Theorie und Praxis: IEC 61131-3;\n- STEP 7; Bibliotheksbausteine; AS-i-Bus; PROFIBUS; Ethernet-TCP/IP; OPC;\nSteuerungssicherheit, Vieweg+Teubner; https://doi.org/10.1007/978-3-663-05705-\n5_2\n- Adam, Adam: SPS-Programmierung in Anweisungsliste nach IEC 61131-3: Eine\nsystematische und handlungsorientierte Einführung in die strukturierte\nProgrammierung, Springer; https://doi.org/10.1007/978-3-662-46716-9_1", "metadata": {"moduleNumber": "PF 3.1", "moduleName": "IT in Automation Technology", "creditPoints": "5.0", "suggestedSemester": 4, "offeredInSeason": "summer_semester", "examType": "written_exam", "heldInLanguage": "de", "reviserName": "None Michael Protogerakis", "reviserEmail": "michael.protogerakis@hs-duesseldorf.de", "studyProgramId": 14, "source_type": "json"}}
{"id": "BDAISY__PF_3.2", "text": "Title: EDIT\nModule Number: PF 3.2\nCredits: 5.0 CP\nSemester: 5\nOffered In: winter_semester\nLanguage: de\nExam Type: written_exam\nInstructor: None Moritz Fleischmann-Bergstein\n\n--- Goals (EN) ---\n\n\n--- Goals (DE) ---\nDie Studierenden sind in der Lage, notwendige fertigungstechnischen Grundlagen im Kontext Industrie40 zu erklären und zu demonstrieren. Sie können für eine gegebene Aufgabenstellung eine geeignete Methode und Technologie auswählen und anwenden und somit eine Lösung eigenständig entwickeln und präsentieren. Nach Abschluss des Moduls sind die Studierenden in der Lage:die gemäß DIN 8580 wichtigsten Fertigungsverfahren aus der Hauptgruppe „Trennen“ zu benennen und zu erklären. die wichtigsten Fertigungsverfahren bezüglich ihrer Verfahrensmerkmale und -grenzen sowie ihrer Vor- und Nachteile zu erklären.anhand von gegebenen fertigungstechnischen Randbedingungen ein Fertigungsverfahren auszuwählen und die jeweiligen Fertigungsprozesse zu beschreiben.auf das jeweilige Fertigungsverfahren bezogen fertigungsgerecht zu konstruierenverfügen die Studierenden über Verständnis für den Prozess der trennenden Fertigungsverfahrensind die Studierenden sensibilisiert für die komplexen Wechselwirkungen zwischen Konstruktion, Fertigungstechnologie und Fertigungsmitteln -auch unter wirtschaftlichen Gesichtspunkten; haben die Studierenden Verständnis für die speziellen Anforderungen an die Informationstechnologie bei den trennenden Fertigungsverfahrenkönnen die Studierenden:Standardmessverfahren in Zerspantechnik und Werkzeugmaschinenbau anwenden sowie Messergebnisse auswerten und deutenGeräte bedienen zur Vermessung von Werkzeugen für trennende Fertigungsverfahren, z. B. Radius- und Längenmessgerät für spanende Werkzeuge und AuswuchtgerätNC-Programme erstellen für CNC Werkzeugmaschinen\n\n--- Contents (EN) ---\n\n\n--- Contents (DE) ---\nTrennende Fertigungsverfahren:Spanen mit geometrisch bestimmter SchneideSpanen mit geometrisch unbestimmter SchneideAbtragende BearbeitungsverfahrenTechnologische Grundlagen des TrennvorgangsSchneidstoffe und WerkzeugeZeit-und KostenoptimierungAnwendungsgebiete und VerfahrensauswahlAnforderungen an WerkzeugmaschinenBauarten und Aufbau spanender WerkzeugmaschinenNC-Programmierverfahren; QualitätssicherungMessung üblicher technologischer Kenngrößen vom Zerspanvorgang und WerkzeugmaschinenFunktionsanalyse von Maschinenbaugruppen\n\n--- Literature (EN) ---\n\n\n--- Literature (DE) ---\nW. König, F. Klocke: Fertigungsverfahren 1: Zerspanung mit geometrisch bestimmter Schneide. Springer VerlagW. König, F. Klocke: Fertigungsverfahren 2: Zerspanung mit geometrisch unbestimmter Schneide. Springer VerlagEinführung in die Fertigungstechnik, E. Westkämper und H.-J. Warnecke, Springer VerlagSpanen, Grundlagen, H.K. Tönshoff und B. Denkena. Springer VerlagPraxis der Zerspantechnik, H. Tschätsch. Springer Verlag", "metadata": {"moduleNumber": "PF 3.2", "moduleName": "EDIT", "creditPoints": "5.0", "suggestedSemester": 5, "offeredInSeason": "winter_semester", "examType": "written_exam", "heldInLanguage": "de", "reviserName": "None Moritz Fleischmann-Bergstein", "reviserEmail": "moritz.fleischmann@hs-duesseldorf.de", "studyProgramId": 14, "source_type": "json"}}
{"id": "BDAISY__PF_3.3", "text": "Title: EDIT\nModule Number: PF 3.3\nCredits: 5.0 CP\nSemester: 4\nOffered In: summer_semester\nLanguage: de\nExam Type: written_exam\nInstructor: None Moritz Fleischmann-Bergstein\n\n--- Goals (EN) ---\n\n\n--- Goals (DE) ---\nDie Studierenden sind in der Lage, notwendige additiven fertigungstechnischen Grundlagen im Kontext Industrie40 zu erklären und zu demonstrieren. Sie können für eine gegebene Aufgabenstellung der additiven Fertigung geeignete Technologie auswählen und anwenden und somit eine Lösung eigenständig entwickeln und präsentieren. Nach erfolgreich angeschlossenem Modul sind die Studierenden in der Lage:die wichtigsten additiven bzw.  generativen Fertigungsverfahren zu beschreiben, spezifische Verfahren bezogen auf eine konkrete Anwendung richtig auszuwählen,die technischen Voraussetzungen hierfür zu erläutern,die Verfahrensgrenzen darzustellen,Bauteile entsprechend der verfahrensspezifischen Besonderheiten zu konstruieren,Unterschiede der additiven Fertigungsverfahren gegenüber anderen Fertigungsverfahren zu identifizieren und optimale Fertigungslösungen auszuwählen,grundlegende Fertigungsvorschriften für die Konstruktion von additiv gefertigten Bauteile anzuwenden.\n\n--- Contents (EN) ---\n\n\n--- Contents (DE) ---\nGrundlagen der additiven Fertigungstechnik:3D DruckersystemeLasersintern und -schmelzen von Metall und Kunststoffen (SLS, SLM)Fused Deposition Modeling (FDM)Stereolithographie (SLA) und andere Photopolymer basierende generative Fertigungs-verfahrenKonstruktion für generative Fertigungsverfahren).\n\n--- Literature (EN) ---\n\n\n--- Literature (DE) ---", "metadata": {"moduleNumber": "PF 3.3", "moduleName": "EDIT", "creditPoints": "5.0", "suggestedSemester": 4, "offeredInSeason": "summer_semester", "examType": "written_exam", "heldInLanguage": "de", "reviserName": "None Moritz Fleischmann-Bergstein", "reviserEmail": "moritz.fleischmann@hs-duesseldorf.de", "studyProgramId": 14, "source_type": "json"}}
{"id": "BDAISY__PF_3.4", "text": "Title: Industrial Communication Systems\nModule Number: PF 3.4\nCredits: 5.0 CP\nSemester: 5\nOffered In: winter_semester\nLanguage: de\nExam Type: written_exam\nInstructor: None Michael Protogerakis\n\n--- Goals (EN) ---\nStudents acquire essential knowledge and skills for both centralized and decentralized communication using fieldbus and real-time Ethernet systems. Upon successful completion of the module, they are able to analyze, understand, and modify existing process-oriented communication systems and structures, as well as develop simple applications and prepare corresponding requirement specifications (functional specifications).\nThey are capable of selecting, applying, and configuring suitable real-time communication systems for operation in automation environments, based on an analysis of the communication task.\n\nAfter successfully completing the laboratory component, students are able to design, configure, and commission simple applications using representative communication systems (fieldbus systems and systems based on Industrial Ethernet), taking into account the specific requirements of each application. They understand the structures of decentralized automation for computer-integrated manufacturing and are able to adapt and design associated organizational solutions independently.\nThe course enables students to recall the fundamental principles of process-oriented communication via standard fieldbus and Industrial Ethernet systems, to explain and visualize them for different target groups, and to apply them appropriately in practice.\n\n--- Goals (DE) ---\nEs werden Fähigkeiten und wesentliche Grundlagen zur zentralen und dezentralen Kommunikation mit Feldbussystemen und Echtzeit-Ethernet-Systemen erworben. Die Studierenden sind nach erfolgreichem Abschluss des Moduls in der Lage, vorhandene prozessnahe Kommunikationssysteme und -strukturen zu analysieren, zu verstehen und zu modifizieren sowie einfache Anwendungen zu entwickeln und entsprechende Lastenhefte zu verfassen. Sie sind befähigt, basierend auf einer\nAnalyse der Kommunikationsaufgabe, geeignete Echtzeit-Kommunikationssysteme für den Betrieb in Automatisierungsanlagen anzuwenden und zu parametrieren.\nNach erfolgreichem Abschluss des Praktikums können die Studierenden einfache Anwendungen mit beispielhaften Kommunikationssystemen (Feldbussysteme und Systeme auf der Basis von Industrial Ethernet) unter Beachtung der Anwendungseigenschaften konzipieren, konfigurieren und in Betrieb nehmen. Die Studierenden sind in der Lage, Strukturen der dezentralen Automatisierung zur rechnergestützten Produktion und darauf basierende betriebsorganisatorische Lösungen zu verstehen, diese selbst anzupassen und auszulegen. Die Veranstaltung versetzt die Studierenden in die Lage, das in der Vorlesung erlernte Wissen wesentlicher Grundlagen der prozessnahen Kommunikation über Standardfeldbusse und Industrial Ethernet zu reproduzieren, zielgruppenorientiert zu erläutern und zu visualisieren sowie anzuwenden.\n\n--- Contents (EN) ---\nTerminology and concepts of process-oriented communication using fieldbus systems; structure, functionality, and technology of fieldbus systems; programming and applications; real-time Ethernet systems for industrial automation (e.g., PROFINET).\nThe focus lies on various bus access methods, bus topologies, communication protocols, communication models, and transmission media, as well as their interrelations, advantages, and disadvantages in industrial applications.\n\nIn the laboratory sessions, students learn to apply the lecture content in a practical and purposeful manner. The focus is particularly on application-oriented work with fieldbus systems and Industrial Ethernet technologies.\n\n--- Contents (DE) ---\nBegriffe und Benennungen der prozessnahen Kommunikation mit Feldbussystemen; Aufbau, Funktionsweise und Technologie von Feldbussystemen, Programmierung und Anwendungen, Echtzeit-Ethernet-Systeme für die Industrieautomation (z.B. PROFINET). Im Fokus stehen hierbei verschiedene Buszugriffsverfahren, Bustopologien, Kommunikationsprotokolle, Kommunikationsmodelle und Übertragungsmedien, Zusammenhänge sowie deren Vor- und Nachteile im industriellen Einsatz.\nIm Praktikum lernen die Studierenden, die Inhalte der Vorlesung zweckmäßig anzuwenden. Insbesondere werden anwendungsorientiert die Themengebiete Feldbussysteme und Industrial Ethernet behandelt.\n\n--- Literature (EN) ---\n- Reißenweber: Feldbussysteme zur industriellen Kommunikation, Oldenburg\n- Langmann, Haehnel: Taschenbuch der Automatisierungstechnik, Abschnitt\nKommunikation, Hanser\n- Scherff, Haese, Wenzek, Hagen: Feldbussysteme in der Praxis, Springer\nBadach u.a.: Technik der IP-Netze, Hanser\n- Gollub: Messen, Steuern und Regeln mit TCP/IP, Franzis\n- Walter: Embedded Internet in der Industrieautomation, Hüthig\n\n--- Literature (DE) ---\n- Reißenweber: Feldbussysteme zur industriellen Kommunikation, Oldenburg\n- Langmann, Haehnel: Taschenbuch der Automatisierungstechnik, Abschnitt\nKommunikation, Hanser\n- Scherff, Haese, Wenzek, Hagen: Feldbussysteme in der Praxis, Springer\nBadach u.a.: Technik der IP-Netze, Hanser\n- Gollub: Messen, Steuern und Regeln mit TCP/IP, Franzis\n- Walter: Embedded Internet in der Industrieautomation, Hüthig", "metadata": {"moduleNumber": "PF 3.4", "moduleName": "Industrial Communication Systems", "creditPoints": "5.0", "suggestedSemester": 5, "offeredInSeason": "winter_semester", "examType": "written_exam", "heldInLanguage": "de", "reviserName": "None Michael Protogerakis", "reviserEmail": "michael.protogerakis@hs-duesseldorf.de", "studyProgramId": 14, "source_type": "json"}}
{"id": "BDAISY__PF_3.5", "text": "Title: EDIT\nModule Number: PF 3.5\nCredits: 5.0 CP\nSemester: 4\nOffered In: summer_semester\nLanguage: de\nExam Type: written_exam\nInstructor: None André Stuhlsatz\n\n--- Goals (EN) ---\n\n\n--- Goals (DE) ---\nDie\nStudierenden haben Wissen bezüglich ausgewählter Methoden der Künstlichen\nIntelligenz, die im Engineering angewandt werden, erworben. Sie können die\nerlernten Methoden an typischen Praxisproblemen der Industrie anwenden. Die\nStudierenden sind in der Lage, notwendige KI-Technologien im Kontext\nIndustrie40 zu erklären, zu adaptieren und zu demonstrieren. Sie können für\neine gegebene Aufgabenstellung geeignete Technologie auswählen und anwenden und\nsomit eine Lösung eigenständig entwickeln und präsentieren. Die Studierenden besitzen ein vertieftes Verständnis\nbezüglich der Funktion und dem Training einiger KI-Methoden und sind sich der\nGrenzen der Anwendbarkeit und Probleme dieser Methoden bewusst.\n\n--- Contents (EN) ---\n\n\n--- Contents (DE) ---\nDie Veranstaltung vermittelt ausgewählte Verfahren der Künstlichen Intelligenz für die Anwendungen in der Industrie 4.0 und der Energietechnik.Einführung in die Künstliche Intelligenz in den Anwendungsfeldern Industrie 4.0 und EnergietechnikEmpirisch-induktive und analytisch-deduktive Modellierung technischer Systeme, Datensätze für die Modellierung und Signifikanz von DatenKünstliche Neuronale Netze (NN): Biologische und künstliche Neuronen, Struktur, Eingang, Aktivierung, Ausgang, mathematische Grundlagen von NN.Arten und Strukturen von NN mit Fokus auf Multi-Layer Perceptrons (“Deep Learning\") und Rekurrenten NN (dynamische Systeme)Trainingsmethoden: Online-, Offline-, Reinforced LearningWissensbasierte Systeme: Fuzzy Logic, ExpertensystemeAnwendung der Methoden auf Probleme und Datensätze im Engineering in Coputerpraktika mit Matlab® / Simulink®, z. B.: Training und Validierung eines NN zur Schätzung des Ladezustands und der Reichweite eines E-FahrzeugsBilderkennung von Verpackungsfehlern zur Qualitätssicherung in der MassenproduktionEntwicklung von Softsensoren zum Ersetzen teurer oder nicht erhältlicher SensorikFuzzy-basierte Regelung eines Roboter-ArmsVorausschauende Wartung („Predictive Maintenance“) für eine Windturbine\n\n--- Literature (EN) ---\n\n\n--- Literature (DE) ---\nR. Kruse et al.: Computational Intelligence, Springer, 2015 (in German)C. C. Aggarwal: Neural Networks and Deep Learning: A Textbook, Springer, 2018S. Ablameyko (ed.): Neural Networks for Instrumentation, Measurement and Related Industrial Applications, IOS Press, 2003", "metadata": {"moduleNumber": "PF 3.5", "moduleName": "EDIT", "creditPoints": "5.0", "suggestedSemester": 4, "offeredInSeason": "summer_semester", "examType": "written_exam", "heldInLanguage": "de", "reviserName": "None André Stuhlsatz", "reviserEmail": "andre.stuhlsatz@hs-duesseldorf.de", "studyProgramId": 14, "source_type": "json"}}
{"id": "BDAISY__xPF_2.6", "text": "Title: EDIT\nModule Number: xPF 2.6\nCredits: 3.0 CP\nSemester: 4\nOffered In: summer_semester\nLanguage: de\nExam Type: none\nInstructor: \n\n--- Goals (EN) ---\n\n\n--- Goals (DE) ---\nDie Studierenden sind in der Lage, notwendige Grundlagen der Elektrotechnik im Kontext Industrie40 zu erklären und zu demonstrieren. Sie können für eine gegebene Aufgabenstellung geeignete Technologie auswählen und anwenden und somit eine Lösung eigenständig entwickeln und präsentieren.Sie könnensicher mit den elementarten Begriffen der Elektrotechnik umgehen,Gleichstromkreise analysieren,komplexe Widerstände berechnen,den Effektivwert periodischer Signale bestimmen,Betriebspunkte von Gleichstrommaschinen auslegen,mit Ersatzmodellen (elektro-)technischer Komponenten umgehen.\n\n--- Contents (EN) ---\n\n\n--- Contents (DE) ---\nDie Veranstaltung vermittelt die elementaren Grundlagen der Elektrotechnik für den Fokus Industrie 4.0: Gleichstrom- und Wechselstromkreise, Bauelemente, elektrische Antriebe.Grundbegriffe des Stromkreises: Strom, Ladung, Spannung und PotentialAnalyse von Gleichstromkreisen / NetzwerkanalyseElektrische und magnetische FelderElementare Bauteile: Widerstand, Induktivität, Kapazität, Diode, TransformatorSinusförmige Größen, Berechnung von WechselstromkreisenEffektivwertberechnungGleichstrommaschineErsatzschaltbilder\n\n--- Literature (EN) ---\n\n\n--- Literature (DE) ---\npdf-Dateien der Vorlesungsfolien für das Fachpdf-Dateien der Übungsaufgabenpdf-Dateien zur KlausurvorbereitungBusch, Rudolf: Elektrotechnik und Elektronik für Maschinenbauer und Verfahrenstechniker, Springer, 2015", "metadata": {"moduleNumber": "xPF 2.6", "moduleName": "EDIT", "creditPoints": "3.0", "suggestedSemester": 4, "offeredInSeason": "summer_semester", "examType": "none", "heldInLanguage": "de", "reviserName": "", "reviserEmail": null, "studyProgramId": 14, "source_type": "json"}}
{"id": "BDAISY__xPF_2.7", "text": "Title: EDIT\nModule Number: xPF 2.7\nCredits: 5.0 CP\nSemester: 5\nOffered In: summer_semester\nLanguage: de\nExam Type: written_exam\nInstructor: \n\n--- Goals (EN) ---\n\n\n--- Goals (DE) ---\nDie Studierenden sind in der Lage, notwendige Grundlagen vernetzter Automatisierungssysteme und vernetzter Produkte im Kontext Industrie40 zu erklären und zu demonstrieren. Sie können für eine gegebene Aufgabenstellung geeignete Technologie auswählen und anwenden und somit eine Lösung eigenständig entwickeln und präsentieren. Die Studierenden können exemplarisch den Aufbau und die Entwicklung von vernetzten Automatisierungssystemen für verschiedene Bereich beschreiben. Dabei können Sie ausgewählte Security-Aspekte diskutieren. Sie können die steigende Komplexität vernetzter Produkte reflektieren.Die Studierenden können ausgewählte Implikationen der Ablösung durch vernetzte Automatisierungssysteme und Produkte beschreiben.Sie können unterschiedliche Architekturtypen vernetzter Automatisierungssysteme und vernetzte Produkte unterscheiden und deren Grundelemente benennen.Sie können die wesentlichen Entwicklungsprozesse vernetzter Automatisierungssysteme und vernetzter Produkte beschreiben und typische Stolperfallen in der Entwicklung benennen.\n\n--- Contents (EN) ---\n\n\n--- Contents (DE) ---\nAufbau und Entwicklung von vernetzten Automatisierungssystemen und deren Anwendungen in den BereichenSmart Production (Industrie 4.0), Smart Home, Smart Environment, Connected Mobility unter besonderer Berücksichtigung von Security-Aspekten und steigender Komplexität der Produkte. Ablösung von Systemen die auf zentralen Entscheidungen basieren durch intelligente, selbststeuernde, sensorgestützte und miteinander vernetzte Automatisierungssysteme.Architekturen vernetzter Automatisierungssysteme und vernetzter ProdukteEntwicklungsprozesse vernetzter Automatisierungssysteme und vernetzter Produkte\n\n--- Literature (EN) ---\n\n\n--- Literature (DE) ---\nWird bei\nBeginn der Veranstaltung bekannt gegeben.", "metadata": {"moduleNumber": "xPF 2.7", "moduleName": "EDIT", "creditPoints": "5.0", "suggestedSemester": 5, "offeredInSeason": "summer_semester", "examType": "written_exam", "heldInLanguage": "de", "reviserName": "", "reviserEmail": null, "studyProgramId": 14, "source_type": "json"}}
{"id": "BDAISY__xPF_2.8", "text": "Title: EDIT\nModule Number: xPF 2.8\nCredits: 5.0 CP\nSemester: 4\nOffered In: summer_semester\nLanguage: de\nExam Type: written_exam\nInstructor: \n\n--- Goals (EN) ---\n\n\n--- Goals (DE) ---\nDie Studierenden sind in der Lage, notwendige\nGrundlagen IT-basierter Automatisierungstechnik im Kontext Industrie40 zu\nerklären und zu demonstrieren. Sie können für eine gegebene Aufgabenstellung\ngeeignete Technologie auswählen und anwenden und somit eine Lösung eigenständig\nentwickeln und präsentieren. Die\nStudierenden sind nach erfolgreichem Abschluss des Moduls befähigt,\nMikrocontroller für dezidierte Anwendungen (Embedded Systems) nach\nunterschiedlichen Kriterien auszuwählen und zu programmieren. Die Studierenden\nsind in der Lage anhand in praktischen Versuchen an Evaluationsboards mit\naktuellen Mikrocontrollern und Schaltungen, Programme zu erstellen, zu\nkompilieren und in die Mikrocontroller runterzuladen. Nach erfolgreichem\nAbschluss des Moduls sind die Studierenden in der Lage, produktionstechnische\nSysteme und Anlagen der Prozessindustrie wie auch der Fertigungsindustrie zu\nanalysieren, einfache Steuerungen zu entwerfen und diese in\nSpeicherprogrammierbaren Steuerungen (SPS) umzusetzen.\n\n--- Contents (EN) ---\n\n\n--- Contents (DE) ---\nGrundlagenveranstaltung zu Automatisierungstechnik, um die notwendige Basis für diese Vertiefung zu schaffen. Architektur von Mikroprozessorsystemen, Unterschiede Mikroprozessor / Mikrocontroller, minimales Mikroprozessor-System, Von-Neumann-Architektur, Harvard Architektur, CISC, RISC, Speicher, Ein-/Ausgabe, Busse, Befehlsstrukturen, Befehlssatz, Datenstrukturen, Adressiermodi, Programmierung, AnwendungAnschluss von externen Geräten wie z. B. Hydraulik, Pneumatik, Elektromotoren usw. an einen Mikrocontroller.Speicherprogrammierbare Steuerungen und Gerätekonfiguration; SPS-Programmierung nach IEC 61131-3 mit Schwerpunkt Funktionsbausteinsprache (FBS), Strukturierter Text (ST) und Ablaufsprache (AS)\n\n--- Literature (EN) ---\n\n\n--- Literature (DE) ---\nWird bei\nVorlesungsstart bekannt gegeben.", "metadata": {"moduleNumber": "xPF 2.8", "moduleName": "EDIT", "creditPoints": "5.0", "suggestedSemester": 4, "offeredInSeason": "summer_semester", "examType": "written_exam", "heldInLanguage": "de", "reviserName": "", "reviserEmail": null, "studyProgramId": 14, "source_type": "json"}}
{"id": "BDAISY__PF_3.10", "text": "Title: Introduction to Automation Technology\nModule Number: PF 3.10\nCredits: 5.0 CP\nSemester: 5\nOffered In: winter_semester\nLanguage: de\nExam Type: written_exam\nInstructor: None Dorothea Schwung\n\n--- Goals (EN) ---\nUpon successful completion of the module, students are able to understand and modify existing automation systems and structures.\nThey are also capable of solving basic control and automation tasks and testing them in a digital environment.\n\n--- Goals (DE) ---\nDie Studierenden sind nach erfolgreichem Abschluss des Moduls in der Lage, vorhandene Automatisierungssysteme und -strukturen zu verstehen, zu modifizieren, sowie einfache regelungs- und steuerungstechnische Aufgaben zu lösen und in einem digitalen Umfeld zu testen.\n\n--- Contents (EN) ---\nThis module provides students with the fundamentals of automation technology solutions. To this end, the course first introduces the objectives, tasks, structures, and different forms of automation technology. It then covers typical representation methods used in automation engineering, such as P&ID flow diagrams and block diagrams.\nBuilding on this, sensors and actuators for detecting and influencing typical process variables are discussed in an overview, including how they are connected to process-oriented automation components.\nThe structure of programmable logic controllers (PLCs) and their programming in accordance with IEC 61131-3 are also covered, with a focus on the languages Function Block Diagram (FBD) and Structured Text (ST), limited to basic constructs and functionalities.\nFollowing that, students are introduced to essential concepts of control and automation system modeling and the design of corresponding solutions. They learn methods for the description and analysis of continuous LTI (Linear Time-Invariant) systems in both the time and frequency domains.\nFurthermore, controller design using tuning rules is taught.\nFor the automation of discrete-event processes, methods for modeling and analysis are introduced, along with systematic approaches for designing control logic for discrete-event systems.\nFinally, the course introduces students to the fundamentals of industrial communication and robotics.\nIn the accompanying laboratory sessions, the knowledge gained is reinforced through simple automation experiments. In addition, students implement basic automation solutions using programmable logic controllers.\n\n--- Contents (DE) ---\nDieses Modul vermittelt Studierenden die Grundlagen automatisierungstechnischer Lösungen. Hierzu werden zunächst Ziele, Aufgaben, Strukturen und Ausprägungen der Automatisierungstechnik eingeführt. Im Folgenden werden typische Beschreibungsformen der Automatisierungstechnik\nwie R&I-Fließbilder und Blockschaltbilder vermittelt. Darauf aufbauend werden Sensoren und Aktoren zur Erfassung und Beeinflussung typischer Prozessgrößen überblicksmäßig besprochen und deren Anbindung an die prozessnahen Automatisierungskomponenten erläutert. Des Weiteren werden der Aufbau Speicherprogrammierbarer Steuerungen sowie deren Programmierung gemäß IEC 61131-3 vermittelt; es wird sich hier auf die Sprachen FBS und ST und einfache Sprachkonstrukte und Funktionalitäten beschränkt. Im Folgenden werden die Studierenden mit grundlegenden Konzepten der regelungs- und steuerungstechnischen Systembeschreibung und dem darauf aufbauenden Entwurf von Automatisierungen vertraut gemacht. Hierzu erlernen die Studierenden Methoden zur Beschreibung und Analyse kontinuierlicher LTI-Systeme im Zeit- und Bildbereich. Darüber hinaus wird der Regelungsentwurf mit Hilfe von Einstellregeln vermittelt. Für die Automatisierung ereignisdiskreter Prozesse werden ebenfalls Methoden zur Beschreibung und Analyse sowie Verfahren zum\nsystematischen Steuerungsentwurf für ereignisdiskrete Systeme eingeführt. Zum Abschluss der Veranstaltung werden die Studierenden mit den Grundlagen der industriellen Kommunikation sowie der Robotik vertraut gemacht. Im begleitenden Praktikum wird das vermittelte Wissen anhand einfacher automatisierungstechnischer Laborversuche vertieft. Außerdem werden einfache\nAutomatisierungslösungen mit Hilfe von Speicherprogrammierbaren Steuerungen umgesetzt.\n\n--- Literature (EN) ---\n- Langmann: Taschenbuch der Automatisierungstechnik, Carl Hanser, 2004\n- Litz: Grundlagen der Automatisierungstechnik. Oldenbourg, 2005\n- Lunze: Automatisierungstechnik  Methoden für die Überwachung und Steuerung kontinuierlicher und ereignisdiskreter Systeme. De Gruyter Oldenbourg, 2016\n- Walter: Grundkurs Regelungstechnik: Grundlagen für Bachelorstudiengänge aller technischen Fachrichtungen und Wirtschaftsingenieure. Springer Vieweg, 2013\n- Wellenreuther, Zastrow: Automatisieren mit SPS  Theorie und Praxis. Springer Vieweg, 2014\n\n--- Literature (DE) ---\n- Langmann: Taschenbuch der Automatisierungstechnik, Carl Hanser, 2004\n- Litz: Grundlagen der Automatisierungstechnik. Oldenbourg, 2005\n- Lunze: Automatisierungstechnik  Methoden für die Überwachung und Steuerung kontinuierlicher und ereignisdiskreter Systeme. De Gruyter Oldenbourg, 2016\n- Walter: Grundkurs Regelungstechnik: Grundlagen für Bachelorstudiengänge aller technischen Fachrichtungen und Wirtschaftsingenieure. Springer Vieweg, 2013\n- Wellenreuther, Zastrow: Automatisieren mit SPS  Theorie und Praxis. Springer Vieweg, 2014", "metadata": {"moduleNumber": "PF 3.10", "moduleName": "Introduction to Automation Technology", "creditPoints": "5.0", "suggestedSemester": 5, "offeredInSeason": "winter_semester", "examType": "written_exam", "heldInLanguage": "de", "reviserName": "None Dorothea Schwung", "reviserEmail": "dorothea.schwung@hs-duesseldorf.de", "studyProgramId": 14, "source_type": "json"}}
{"id": "BDAISY__D_6.1", "text": "Title: External Semester\nModule Number: D 6.1\nCredits: 30.0 CP\nSemester: 6\nOffered In: summer_semester\nLanguage: de\nExam Type: oral_exam\nInstructor: \n\n--- Goals (EN) ---\nStudents have deepened and/or broadened their knowledge and skills with regard to the concepts taught in the DAISY program so far. They are capable of planning an alternative study experience over an extended period and organizing it in such a way that it is fully realizable within the intended timeframe of one semester. Students acquire the ability to navigate unfamiliar environments and to contribute constructively within them. To this end, they can choose between a professional practical experience (Practical Semester), a Study Abroad semester, or a Research & Development semester.\n\nSubmodule: Practical Semester\nA professional practical experience is oriented toward the future career field of DAISY students. Students are familiar with operational processes and are capable of working on tasks assigned to them in accordance with their level of knowledge.\n\nSubmodule: Study Abroad Semester\nA study abroad experience conveys competencies in selected courses from the fields of Media Informatics and interdisciplinary qualifications. These are supplemented by increased demands for autonomy due to the international setting and by the development of learning competence in a foreign language.\n\nSubmodule: R&D Semester\nAn R&D semester provides foundational knowledge and skills in scientific research and/or practical development, as well as insight into the operations of a research institute or a comparable organization in the application areas addressed by the DAISY degree program.\n\n--- Goals (DE) ---\nSie haben dabei ihre Kenntnisse und Fähigkeiten in Bezug auf die in DAISY bisher vermittelten Konzepte vertieft bzw. verbreitert. Sie sind in der Lage über einen längeren Zeitraum eine alternative Studienerfahrung zu planen und derart organisieren, dass dies in der geplanten Zeit eines Semesters vollständig durchführbar ist. Die Studierenden erwerben die Fähigkeiten, sich in einer vorher unbekannten Umgebung zurecht zu finden und dort konstruktiv mitarbeiten zu können. Hierfür stehen zur Wahl eine berufspraktische Tätigkeit im Praxissemester, ein Auslandsstudium oder ein Projektsemester.\n\nTeilmodul Praxissemester: Eine berufspraktische Tätigkeit orientiert sich am späteren Berufsfeld für DAISY-Studierende. Die Studierenden kennen betriebliche Prozesse und können ihnen gestellte Aufgaben gemäß ihrem Kenntnisstand bearbeiten.\n\nTeilmodul Auslandsstudium: Ein Auslandsstudium vermittelt die Kompetenzen in den gewählten Kursen aus den Bereichen Medieninformatik und Querschnittsqualifikationen, ergänzt um die erhöhten Anforderungen an Selbständigkeit durch den Auslandsaufenthalt sowie die Lernkompetenz in einer Fremdsprache.\n\nTeilmodul F&E-Semester: Ein F&E-Semester vermittelt Grundlagen und Kenntnisse der wissenschaftlichen Forschung und / oder praktischen Entwicklung und der Abläufe an einem Forschungsinstitut oder einer vergleichbaren Organisation auf dem Gebiet der im Studiengang DASIY adressierten Anwendungsbereiche.\n\n--- Contents (EN) ---\nDepending on the chosen experience, the content varies.\n\nSubmodule: Practical Semester\nStudents gain orientation in their future professional field as computer scientists with a focus on Data Science, AI, and Intelligent Systems. They become familiar with operational processes and work on tasks assigned to them. To this end, they conclude a contract with the internship provider detailing the duration, tasks, and supervision. Through regular reports, the supervising professor is kept informed and provides guidance to the student.\n\nSubmodule: Study Abroad Semester\nStudents can independently organize and take advantage of international educational opportunities. In a global context, they are able to develop, formulate, and present suitable solution concepts for challenges in Data Science, AI, and Intelligent Systems.\n\nSubmodule: Research Semester\nStudents are familiar with working methods in scientific research and advanced development, particularly in the fields of Data Science, AI, and Intelligent Systems.\n\n--- Contents (DE) ---\nJe nach Wahl der Erfahrung unterschiedlich.\n\nTeilmodul Praxissemester: Die Studierenden orientieren sich im späteren Berufsfeld für Informatiker mit Schwerpunkt Data Science, AI und intelligente Systeme.  Sie lernen betriebliche Prozesse kennen und bearbeiten ihnen gestellte Aufgaben. Sie schließen dazu mit der Praxisstelle einen Vertrag über die Zeitdauer, Aufgaben und Betreuung ab. Durch regelmäßige Berichte wird der betreuende Professor oder die betreuende Professorin informiert und berät den Studierenden oder die Studierende.\n\nTeilmodul Auslandsstudium: Studierende können für sich internationale Bildungsangebote organisieren und nutzen. Im globalen Kontext können Sie für Problemstellungen der Data Science, KI und Intelligente Systeme geeignete Lösungskonzepte entwickeln, formulieren und präsentieren.\n\nTeilmodul Forschungssemester: Die Studierenden kennen die Arbeitsweisen in der wissenschaftlichen Forschung und anspruchsvollen Entwicklung, speziell im Bereich Data Science, KI und Intelligente Systeme.\n\n--- Literature (EN) ---\nAdditional literature will be provided at the start of the supervision, if applicable.\n\n--- Literature (DE) ---\nWeitere Literatur wird ggf. bei Start der Betreuung bereitgestellt.", "metadata": {"moduleNumber": "D 6.1", "moduleName": "External Semester", "creditPoints": "30.0", "suggestedSemester": 6, "offeredInSeason": "summer_semester", "examType": "oral_exam", "heldInLanguage": "de", "reviserName": "", "reviserEmail": null, "studyProgramId": 14, "source_type": "json"}}
{"id": "BDAISY__D_7.1", "text": "Title: EDIT\nModule Number: D 7.1\nCredits: 5.0 CP\nSemester: 7\nOffered In: winter_semester\nLanguage: de\nExam Type: see_elective\nInstructor: \n\n--- Goals (EN) ---\n\n\n--- Goals (DE) ---\nDie Studierenden können sich ein beliebiges Fach aus dem Fächerkatalog der HSD wählen. Es gibt keinerlei Einschränkungen bei der Wahl des Faches außer, dass das betreffende Fach noch nicht im bisherigen Studienverlauf belegt wurde und der Umfang 5CP entspricht. Die Lernergebnisse sind im Modulhandbuch des betreffenden Faches zu entnehmen.Die Studierenden haben verfügen über Erfahrung in der Wahl eines Faches aus einem selbstgewählten Bereich. Sie haben gelernt sich für einen begrenzten Zeitraum in eine andere Fachdisziplin oder zumindest in ein neues Fachgebiet einzuarbeiten und effektiv zu integrieren.\n\n--- Contents (EN) ---\n\n\n--- Contents (DE) ---\nDie\nVorlesungsinhalte variieren je nach Wahl der Vertiefung und sind im jeweiligen\nModulhandbuch der gewählten Veranstaltung zu finden.\n\n--- Literature (EN) ---\n\n\n--- Literature (DE) ---\nWeitere\nLiteratur wird bei Vorlesungsbeginn bekannt gegeben oder steht in der\nModulbeschreibung des gewählten Faches.", "metadata": {"moduleNumber": "D 7.1", "moduleName": "EDIT", "creditPoints": "5.0", "suggestedSemester": 7, "offeredInSeason": "winter_semester", "examType": "see_elective", "heldInLanguage": "de", "reviserName": "", "reviserEmail": null, "studyProgramId": 14, "source_type": "json"}}
{"id": "BDAISY__D_7.2", "text": "Title: EDIT\nModule Number: D 7.2\nCredits: 10.0 CP\nSemester: 7\nOffered In: winter_semester\nLanguage: de\nExam Type: research_paper\nInstructor: \n\n--- Goals (EN) ---\n\n\n--- Goals (DE) ---\nDie Studierenden beherrschen den Umgang mit\nwissenschaftlichen Informationsquellen (sowohl deutsch- als auch\nenglischsprachig), können diese korrekt zitieren und sie dazu nutzen, den Stand\nder Forschung und Technik zu ermitteln sowie eigene Aufgabenstellungen zu\nanalysieren und zu planen. Die Studierenden sind in der Lage, eigene Arbeiten\nim Kontext des fachlichen Umfeldes zu sehen und in angemessener Form\nschriftlich und mündlich zu kommunizieren.\n\n--- Contents (EN) ---\n\n\n--- Contents (DE) ---\nDie\nStudierenden bearbeiten individuell eine wissenschaftliche Fragestellung mit\nallen Facetten einer wissenschaftlichen Projektdurchführung.\n\n--- Literature (EN) ---\n\n\n--- Literature (DE) ---\nWeitere\nLiteratur wird bei Vorlesungsbeginn bekannt gegeben oder steht in der\nModulbeschreibung des gewählten Faches.", "metadata": {"moduleNumber": "D 7.2", "moduleName": "EDIT", "creditPoints": "10.0", "suggestedSemester": 7, "offeredInSeason": "winter_semester", "examType": "research_paper", "heldInLanguage": "de", "reviserName": "", "reviserEmail": null, "studyProgramId": 14, "source_type": "json"}}
{"id": "BDAISY__D_7.3", "text": "Title: EDIT\nModule Number: D 7.3\nCredits: 15.0 CP\nSemester: 7\nOffered In: winter_semester\nLanguage: de\nExam Type: bachelor_thesis_and_colloquium\nInstructor: \n\n--- Goals (EN) ---\n\n\n--- Goals (DE) ---\nDie Studierenden beherrschen den Umgang mit\nwissenschaftlichen Informationsquellen (sowohl deutsch- als auch\nenglischsprachig), können diese korrekt zitieren und sie dazu nutzen, den Stand\nder Forschung und Technik zu ermitteln sowie eigene Aufgabenstellungen zu\nanalysieren und zu planen. Die Studierenden sind in der Lage, eine eigene\nArbeit im Kontext des fachlichen Umfeldes zu konzipieren und praktisch zu\nrealisieren. Sie sind in der Lage die Arbeitsergebnisse angemessen zu\ndokumentieren, zu kommunizieren und kritisch zu diskutieren.\n\n--- Contents (EN) ---\n\n\n--- Contents (DE) ---\nDie Studierenden können selbstständig eine Aufgabenstellung aus fachlich relevanten Bereichen mit wissenschaftlichen, gestalterischen und ingenieurgemäßen Mitteln mit Zeitbeschränkung unter Anleitung des/ der Dozenten/ in bearbeiten. Sie können die Bearbeitung einer Aufgabenstellung unter fachlicher und wissenschaftlicher Einordnung präsentieren und vertreten. Die Studierenden bearbeiten unter Anleitung für ein spezielles DSY-relevantes Thema mit folgenden Aufgaben:Planung der BearbeitungBearbeitung der AufgabenstellungDokumentationPräsentation in einem Kolloquium\n\n--- Literature (EN) ---\n\n\n--- Literature (DE) ---\nKolloquium und Thesis siehe §15,§16 der PO", "metadata": {"moduleNumber": "D 7.3", "moduleName": "EDIT", "creditPoints": "15.0", "suggestedSemester": 7, "offeredInSeason": "winter_semester", "examType": "bachelor_thesis_and_colloquium", "heldInLanguage": "de", "reviserName": "", "reviserEmail": null, "studyProgramId": 14, "source_type": "json"}}
{"id": "BDAISY__PF_3.6", "text": "Title: EDIT\nModule Number: PF 3.6\nCredits: 5.0 CP\nSemester: 4\nOffered In: winter_semester\nLanguage: de\nExam Type: written_exam\nInstructor: None Moritz Fleischmann-Bergstein\n\n--- Goals (EN) ---\n\n\n--- Goals (DE) ---\nDie Studierenden sind in der Lage, notwendige Grundlagen ierneuerbarer Energien und Energieeffizienz im Kontext Smart Energy zu erklären und zu demonstrieren. Sie können für eine gegebene Aufgabenstellung geeignete Technologie auswählen und anwenden und somit eine Lösung eigenständig entwickeln und präsentieren. Nach erfolgreichem Abschluss des Moduls können die StudierendenMotivationen zur Energieeinsparung und zum Einsatz erneuerbarer Energien sowie vorhandene Hemmnisse dazu benennen und bewertend einordnen.die wichtigsten Techniken zur Nutzung erneuerbarer Energien und zur Energieeinsparung im Hinblick auf Komponenten, Anlagenaufbau und Funktionsweise beschreiben und charakteristische ökologische und ökonomische Eigenschaften nennen und bewerten.Aussagen zu sinnvollen Einsatzbereichen und Anlagendimensionierungen für die einzelnen Technologien treffen bzw. aus den Randbedingungen eines Einsatzfalles ableiten.ökologische und ökonomische Kenngrößen (gelieferte Energiemenge, Wirkungsgrad, Nutzungsgrad, Deckungsgrad, Amortisationszeit, Gestehungskosten, etc.) für die einzelnen Technologien berechnen.den Beitrag und die Leistungsfähigkeit der erneuerbaren Energien und der Energieeinsparung im Hinblick auf eine zukünftige Energieversorgung Deutschlands realistisch einschätzen.\n\n--- Contents (EN) ---\n\n\n--- Contents (DE) ---\nDas Modul gibt einen Überblick über die Techniken zur Nutzung erneuerbarer Energien sowie ausgewählte Technologien mit hoher Energieeffizienz gemäß den unten angegebenen Lerninhalten und Lernergebnissen.Energiewirtschaftliche Daten (weltweit und für Deutschland), Klimawandel und Klimaschutz, Ressourcenschonung, Hemmnisse für den Einsatz erneuerbarer EnergienErneuerbare Energien und Effizienztechnologien zur Strom-, Wärme- und Kälteerzeugung: Solarthermie, Geothermie, Biomasse, Photovoltaik, Wind- und Wasserkraft, effiziente konventionelle Heiztechniken, Wärmepumpen, Blockheizkraftwerke, Sorptions-Wärmepumpen/Kältemaschinen, Solares Kühlen, Kraft-Wärme-Kälte-Kopplung, etc.Erneuerbares EnergieangebotSystemkomponenten, Anlagenaufbau, Technik der EnergieumwandlungSinnvolle Einsatzbereiche und AnlagendimensionierungÖkologische Bewertung: Wirkungsgrade, ÖkobilanzierungWirtschaftliche Bewertung:  Amortisationszeit, Gestehungskosten, Energieeinsparkosten, Jahresgesamtkosten, etc.aktuelle MarktsituationBeispielhafte Techniken zur Wärme- und StromeinsparungPotenziale erneuerbarer Energien zur zukünftigen Energieversorgung Deutschlands\n\n--- Literature (EN) ---\n\n\n--- Literature (DE) ---", "metadata": {"moduleNumber": "PF 3.6", "moduleName": "EDIT", "creditPoints": "5.0", "suggestedSemester": 4, "offeredInSeason": "winter_semester", "examType": "written_exam", "heldInLanguage": "de", "reviserName": "None Moritz Fleischmann-Bergstein", "reviserEmail": "moritz.fleischmann@hs-duesseldorf.de", "studyProgramId": 14, "source_type": "json"}}
{"id": "BDAISY__PF_3.7", "text": "Title: EDIT\nModule Number: PF 3.7\nCredits: 5.0 CP\nSemester: 4\nOffered In: winter_semester\nLanguage: de\nExam Type: written_exam\nInstructor: None André Stuhlsatz\n\n--- Goals (EN) ---\n\n\n--- Goals (DE) ---\nDie Studierenden sind in der Lage, notwendige Grundlagen der Elektrotechnik im Kontext Industrie40 zu erklären und zu demonstrieren. Sie können für eine gegebene Aufgabenstellung geeignete Technologie auswählen und anwenden und somit eine Lösung eigenständig entwickeln und präsentieren. Die Studierenden besitzen fundiertes Grundwissen bezüglich elektrischer Gleich- und Wechselstromkreise. Sie könnensicher mit den elementaren Begriffen der Elektrotechnik umgehen,Gleichstromkreise analysieren,komplexe Widerstände berechnen,den Effektivwert periodischer Signale bestimmen,Betriebspunkte von Gleichstrommaschinen auslegen,mit Ersatzmodellen (elektro-)technischer Komponenten umgehen.\n\n--- Contents (EN) ---\n\n\n--- Contents (DE) ---\nDie Veranstaltung vermittelt die elementaren Grundlagen der Elektrotechnik für den Fokus Industrie 4.0: Gleichstrom- und Wechselstromkreise, Bauelemente, elektrische Antriebe.Grundbegriffe des Stromkreises: Strom, Ladung, Spannung und PotentialAnalyse von Gleichstromkreisen/NetzwerkanalyseElektrische und magnetische FelderElementare Bauteile: Widerstand, Induktivität, Kapazität, Diode, TransformatorSinusförmige Größen, Berechnung von WechselstromkreisenEffektivwertberechnungGleichstrommaschineErsatzschaltbilder\n\n--- Literature (EN) ---\n\n\n--- Literature (DE) ---\nSonstige Informationen: Entspricht PF 2.6 Industrie4.0Weiterführende Literatur:pdf-Dateien der Vorlesungsfolien für das Fachpdf-Dateien der Übungsaufgabenpdf-Dateien zur KlausurvorbereitunBusch, Rudolf: Elektrotechnik und Elektronik für Maschinenbauer und Verfahrenstechniker, Springer, 2015", "metadata": {"moduleNumber": "PF 3.7", "moduleName": "EDIT", "creditPoints": "5.0", "suggestedSemester": 4, "offeredInSeason": "winter_semester", "examType": "written_exam", "heldInLanguage": "de", "reviserName": "None André Stuhlsatz", "reviserEmail": "andre.stuhlsatz@hs-duesseldorf.de", "studyProgramId": 14, "source_type": "json"}}
{"id": "BDAISY__xPF_3.3", "text": "Title: EDIT\nModule Number: xPF 3.3\nCredits: 3.0 CP\nSemester: 4\nOffered In: summer_semester\nLanguage: de\nExam Type: written_exam\nInstructor: \n\n--- Goals (EN) ---\n\n\n--- Goals (DE) ---\nDie Studierenden sind in der Lage, notwendige Grundlagen der Thermodynamik im Kontext Smart Energy zu erklären und zu demonstrieren. Sie können für eine gegebene Aufgabenstellung geeignete Technologie auswählen und anwenden und somit eine Lösung eigenständig entwickeln und präsentieren. Nach erfolgreichem Abschluss des Moduls sind die Studierenden in der Lageden relevanten Massen- und Energieaustausch von einfachen thermodynamischen Systemen mit ihrer Umgebung zu erkennen und selbst zu bilanzieren.die fehlenden Stoffeigenschaften und Zustandsgrößen eines Systems aus bekannten Größen zu berechnen.Energieumwandlung und -übertragung, insbesondere für Wärme und Arbeit, zu quantifizieren.die Zustandsänderungen von idealen Gasen darzustellen und zu berechnen.\n\n--- Contents (EN) ---\n\n\n--- Contents (DE) ---\nDas Modul behandelt die Grundlagen der Thermodynamik gemäß den unten angegebenen Lerninhalten und Lernergebnissen.Einführung in die Thermodynamik (Wärmelehre)Grundbegriffe: System und Zustand, Zustandsgrößen, Zustandsänderungen, Bilanzierungreversible und irrreversible ProzesseFormen der Energie: Arbeit, Wärme, Innere Energie, EnthalpieZustandsgleichungen: kalorische Zustandsgleichungen, Zustandsänderungen idealer GaseErster Hauptsatz der Thermodynamik: geschlossene Systeme, offene SystemeAnwendung auf Otto-Prozess\n\n--- Literature (EN) ---\n\n\n--- Literature (DE) ---\nLABUHN, ROMBERG: Keine Panik vor Thermodynamik, Vieweg+Teubner (Einführung)HERWIG; KAUTZ: Technische Thermodynamik, Pearson Studium (Vertiefung)", "metadata": {"moduleNumber": "xPF 3.3", "moduleName": "EDIT", "creditPoints": "3.0", "suggestedSemester": 4, "offeredInSeason": "summer_semester", "examType": "written_exam", "heldInLanguage": "de", "reviserName": "", "reviserEmail": null, "studyProgramId": 14, "source_type": "json"}}
{"id": "BDAISY__PF_3.8", "text": "Title: Connected automation systems and connected products\nModule Number: PF 3.8\nCredits: 5.0 CP\nSemester: 5\nOffered In: winter_semester\nLanguage: de\nExam Type: project\nInstructor: None Michael Protogerakis\n\n--- Goals (EN) ---\n1.\tKnowledge (Remember / Understand)\n\t\tExplain and compare maturity models of smart systems\n\t\tDescribe architectures and technologies of smart systems\n\t2.\tApplication (Apply)\n\t\tApply suitable IoT technologies and development models to given use cases\n\t\tUse project management tools and agile methods in team contexts\n\t3.\tAnalysis and Evaluation (Analyze / Evaluate)\n\t\tCritically evaluate smart system architectures with regard to efficiency, scalability, and business model potential\n\t\tAnalyze and manage team roles and group processes in the context of projects\n\t4.\tCreation (Create)\n\t\tDesign, document, and develop an innovative smart system in a team and implement it as a prototype\n\n--- Goals (DE) ---\nNach erfolgreichem Abschluss sind die Studierenden in der Lage:\n1.\tWissen (Remember/Understand)\no\tReifegradmodelle smarter Systeme zu erklären und zu vergleichen\no\tArchitekturen und Technologien smarter Systeme zu beschreiben\n2.\tAnwendung (Apply)\no\tgeeignete IOT-Technologien und Entwicklungsmodelle auf gegebene Use Cases anzuwenden\no\tProjektmanagementtools und agile Methoden in Teamkontexten einzusetzen\n3.\tAnalyse und Bewertung (Analyze/Evaluate)\no\tsmarte Systemarchitekturen kritisch hinsichtlich Effizienz, Skalierbarkeit und Geschäftsmodellpotenzial zu bewerten\no\tTeamrollen und Gruppenprozesse projektbezogen zu analysieren und steuern\n4.\tKreation (Create)\no\tein eigenes, innovatives smartes System im Team zu konzipieren, dokumentieren und prototypisch umzusetzen\n\n--- Contents (EN) ---\n- Introduction to technology patterns of smart systems based on typical use cases (Smart Production, Smart Home, Smart Grid, Connected Mobility)\n- Introduction to architectures of smart systems\n- Development processes for smart systems (agile / hybrid development models)\n- Introduction to IoT technologies (Narrowband IoT, 5G, Edge Computing)\n- Introduction to novel business models driven by smart systems\n\n--- Contents (DE) ---\n- Analyse typischer Anwendungsfälle (Use Cases) smarter Systeme: Smart Production, Smart Home, Smart Grid, Connected Mobility\n- Architekturkonzepte smarter Systeme (Edge/Cloud, CPS, IOT-Plattformen)\n- Reifegradmodelle und Systematiken (u.a. acatech Industrie 4.0 Maturity Index & Smart Services Index)\n- Einführung in IOT-Technologien (Narrowband IoT, 5G, Edge Computing)\n- Smarte Geschäftsmodelle & servitization-getriebene Wertschöpfung\n- Projektmanagement-Methoden (agil/hybrid) und Gruppendynamiken (z.B. Tuckman, Belbin)\n- Praktische Projektarbeit: Konzeption und Realisierung eines eigenen Smart Systems\n\n--- Literature (EN) ---\nWill be announced during the course.\n\n--- Literature (DE) ---\nWird im Rahmen der Lehrveranstaltung bekannt gegeben.", "metadata": {"moduleNumber": "PF 3.8", "moduleName": "Connected automation systems and connected products", "creditPoints": "5.0", "suggestedSemester": 5, "offeredInSeason": "winter_semester", "examType": "project", "heldInLanguage": "de", "reviserName": "None Michael Protogerakis", "reviserEmail": "michael.protogerakis@hs-duesseldorf.de", "studyProgramId": 14, "source_type": "json"}}
{"id": "BDAISY__xPF_3.5", "text": "Title: EDIT\nModule Number: xPF 3.5\nCredits: 3.0 CP\nSemester: 5\nOffered In: winter_semester\nLanguage: de\nExam Type: written_exam\nInstructor: \n\n--- Goals (EN) ---\n\n\n--- Goals (DE) ---\nDie Studierenden sind in der Lage, notwendige Grundlagen der angewandten Thermodynamik im Kontext Smart Energy zu erklären und zu demonstrieren. Sie können für eine gegebene Aufgabenstellung geeignete Technologie auswählen und anwenden und somit eine Lösung eigenständig entwickeln und präsentieren. Nach erfolgreichem Abschluss des Moduls sind die Studierenden in der Lagedie Einschränkungen, die sich aus dem 2. Hauptsatz der Thermodynamik für Energieumwandlungen ergeben, auf technische Prozesse anzuwenden.über Bewertungsgrößen wie Wirkungsgrad und Leistungszahl die Prozessgüte von Energieumwandlungsprozessen zu ermittelnverschiedene Formen von Kreisprozessen zu beschreiben und zu unterscheidenZustandsänderungen und Energieumwandlungen in thermodynamischen Kreisprozessen (z. B. Wärmekraftmaschinen) zu berechnendas erlangte thermodynamische Grundverständnis auf technische Prozesse und Anlagen z. B. bei Bilanzierungen und Auslegungen zielgerichtet anzuwenden.mit der Darstellung und zur quantitativen Beschreibung der Zusammensetzung von feuchter Luft (h*,x-Diagramm) zu arbeiten, um Zustandsänderungen feuchter Luft zu beschreiben\n\n--- Contents (EN) ---\n\n\n--- Contents (DE) ---\nDas Modul behandelt Aspekte der angewandten der Thermodynamik gemäß den unten angegebenen Lerninhalten und Lernergebnissen.Zweiter Hauptsatz der Thermodynamik, linksläufige und rechtsläufige Kreisprozesse und deren BewertungPhasendiagrammeBerechnung der Zustandsänderungen in Wärmekraftmaschine und KältemaschineBerechnung der Stoffeigenschaften von Gemischen idealer GaseBeschreibung thermodynamischer Eigenschaften von feuchter Luft und ZustandsänderungenBilanzierung und Bewertung von thermodynamischen Systemen\n\n--- Literature (EN) ---\n\n\n--- Literature (DE) ---\nWird im Rahmen der Lehrveranstaltung bekannt\ngegeben.", "metadata": {"moduleNumber": "xPF 3.5", "moduleName": "EDIT", "creditPoints": "3.0", "suggestedSemester": 5, "offeredInSeason": "winter_semester", "examType": "written_exam", "heldInLanguage": "de", "reviserName": "", "reviserEmail": null, "studyProgramId": 14, "source_type": "json"}}
{"id": "BDAISY__PF_3.9", "text": "Title: EDIT\nModule Number: PF 3.9\nCredits: 5.0 CP\nSemester: 5\nOffered In: winter_semester\nLanguage: de\nExam Type: written_exam\nInstructor: None André Stuhlsatz\n\n--- Goals (EN) ---\n\n\n--- Goals (DE) ---\nDie Studierenden sind in der Lage, notwendige\nGrundlagen der elektrischen Energietechnik im Kontext Smart Energy zu erklären\nund zu demonstrieren. Sie können für eine gegebene Aufgabenstellung geeignete\nTechnologie auswählen und anwenden und somit eine Lösung eigenständig entwickeln\nund präsentieren. Nach erfolgreichem Abschluss des Moduls haben die\nStudierenden grundlegende Kenntnisse auf dem Gebiet der Energiewirtschaft,\nEnergiewandlung, Übertragung und der Verteilung elektrischer Energie.\n\n--- Contents (EN) ---\n\n\n--- Contents (DE) ---\nDas Modul behandelt die Grundlagen der elektrischen Energietechnik gemäß den unten angegebenen Lerninhalten und Lernergebnissen.Energiewirtschaft, rechtliche Grundlagen, EnergiewendeElektrische Kraftwerke, elektrische MaschinenAufbau elektrischer Netze, Übertragungsmittel (Freileitungen, Kabel, Transformatoren, Kondensatoren, Kompensationsanlagen, Schaltgeräte), Netzberechnung, Kurzschussstromberechnung nach VDE 0102\n\n--- Literature (EN) ---\n\n\n--- Literature (DE) ---\nHeuck, Dettmann: Elektrische Energieversorgung, ViewegOeding, Oswald: Elektrische Kraftwerke und Netze, Springer", "metadata": {"moduleNumber": "PF 3.9", "moduleName": "EDIT", "creditPoints": "5.0", "suggestedSemester": 5, "offeredInSeason": "winter_semester", "examType": "written_exam", "heldInLanguage": "de", "reviserName": "None André Stuhlsatz", "reviserEmail": "andre.stuhlsatz@hs-duesseldorf.de", "studyProgramId": 14, "source_type": "json"}}
{"id": "BDAISY__xPF_3.7", "text": "Title: EDIT\nModule Number: xPF 3.7\nCredits: 8.0 CP\nSemester: 5\nOffered In: winter_semester\nLanguage: de\nExam Type: project\nInstructor: \n\n--- Goals (EN) ---\n\n\n--- Goals (DE) ---\nDie Studierenden sind in der Lage, notwendige\nAnsätze für Smart Systems in der Energietechnik im Kontext Smart Energy zu\nerklären und zu demonstrieren. Sie können für eine gegebene Aufgabenstellung\ngeeignete Technologie auswählen und anwenden und somit eine Lösung eigenständig\nentwickeln und präsentieren. Nach erfolgreichem Abschluss des Moduls können die\nStudierenden wissensbasierte Methoden aus den Bereichen Künstliche\nIntelligenz, Machine Learning, Deep Learning, Data Science etc. auf ausgewählte\nProblemstellungen aus dem Bereich der Energietechnik praktisch anwenden.\n\n--- Contents (EN) ---\n\n\n--- Contents (DE) ---\nDas Modul dient der Vertiefung und projektorientierten Anwendung ausgewählter Aspekte aus dem Bereich Smart Energy Systems gemäß den unten angegebenen Lerninhalten und Lernergebnissen.problem- und projektorientierte Bearbeitung ausgewählter Fragestellungen aus dem Bereich der Energietechnik mit Hilfe wissensbasierter MethodenDigitaler Zwilling\n\n--- Literature (EN) ---\n\n\n--- Literature (DE) ---", "metadata": {"moduleNumber": "xPF 3.7", "moduleName": "EDIT", "creditPoints": "8.0", "suggestedSemester": 5, "offeredInSeason": "winter_semester", "examType": "project", "heldInLanguage": "de", "reviserName": "", "reviserEmail": null, "studyProgramId": 14, "source_type": "json"}}
{"id": "BDAISY__xPF_3.8", "text": "Title: EDIT\nModule Number: xPF 3.8\nCredits: 5.0 CP\nSemester: 5\nOffered In: winter_semester\nLanguage: de\nExam Type: project\nInstructor: \n\n--- Goals (EN) ---\n\n\n--- Goals (DE) ---\nDie Studierenden sind in der Lage, fortgeschrittene Ansätze für Smart Systems in der Energietechnik im Kontext Smart Energy zu erklären und zu demonstrieren. Sie können für eine gegebene Aufgabenstellung geeignete Technologie auswählen und anwenden und somit eine Lösung eigenständig entwickeln und präsentieren. Nach erfolgreichem Abschluss des Moduls können die Studierendensinnvolle Anwendungen wissensbasierter Methoden aus den Bereichen Künstliche Intelligenz, Machine Learning, Deep Learning, Data Science etc. auf konkrete Problemstellungen aus den Bereichen Energietechnik und Energiewirtschaft, insbesondere aus den Bereichen Smart Grid, Smart Building und Smart Citybenennen und beschreibenanhand ihrer Eigenschaften und Vor-/Nachteile bewertend einordnen undan Beispielen praktisch umsetzen\n\n--- Contents (EN) ---\n\n\n--- Contents (DE) ---\nDas Modul behandelt Teilaspekte aus dem Bereich Smart Energy Systems, insbesondere den Bereichen Smart Grid, Smart Building und Smart City, gemäß den unten angegebenen Lerninhalten und Lernergebnissen.Anwendungen wissensbasierter Methoden in der Energietechnik und Energiewirtschaft, insbesondere in den Bereichen Smart Grid und Smart Building (lokale, regionale und überregionale Strom- und Wärmenetze, Schwarmstromkonzepte, intelligente Nah-/Fernwärmenetze etc.) undSmart City (intelligente Sektorkopplungen der Verbrauchsbereiche Strom, Wärme/Kälte und Verkehr etc.)Methoden zur Metamodellierung der Systemeigenschaften und für Zukunftsprognosen der Randbedingungen energietechnischer Systeme, sowohl bei deren Auslegung als auch im Betrieb (z. B. Black box Modelle mit KNN, GPR)Methoden zur multikriteriellen Optimierung energietechnischer Systeme bzgl. Ökologie, Ökonomie und Versorgungssicherheit, sowohl bei deren Auslegung als auch im Betrieb\n\n--- Literature (EN) ---\n\n\n--- Literature (DE) ---\nWird im\nRahmen der Lehrveranstaltung bekannt gegeben.", "metadata": {"moduleNumber": "xPF 3.8", "moduleName": "EDIT", "creditPoints": "5.0", "suggestedSemester": 5, "offeredInSeason": "winter_semester", "examType": "project", "heldInLanguage": "de", "reviserName": "", "reviserEmail": null, "studyProgramId": 14, "source_type": "json"}}
{"id": "BDAISY__xPF_3.9", "text": "Title: EDIT\nModule Number: xPF 3.9\nCredits: 5.0 CP\nSemester: 4\nOffered In: summer_semester\nLanguage: de\nExam Type: project\nInstructor: \n\n--- Goals (EN) ---\n\n\n--- Goals (DE) ---\nDie Studierenden sind in der Lage, notwendige Ansätze der KI im Engineering im Kontext Smart Energy zu erklären und zu demonstrieren. Sie können für eine gegebene Aufgabenstellung geeignete KI-Technologie auswählen und anwenden und somit eine Lösung eigenständig entwickeln und präsentieren.Die Studierenden haben Wissen bezüglich ausgewählter Methoden der Künstlichen Intelligenz, die im Engineering angewandt werden.Sie können die erlernten Methoden an typischen Praxisproblemen der Industrie anwenden.Die Studierenden besitzen ein Verständnis bezüglich der Funktion und dem Training einiger KI-Methoden und sind sich der Grenzen der Anwendbarkeit und Probleme dieser Methoden bewusst.\n\n--- Contents (EN) ---\n\n\n--- Contents (DE) ---\nDie Veranstaltung vermittelt ausgewählte Verfahren der Künstlichen Intelligenz für die Anwendungen in der Industrie 4.0 und der Energietechnik.Einführung in die Künstliche Intelligenz in den Anwendungsfeldern Industrie 4.0 und EnergietechnikEmpirisch-induktive und analytisch-deduktive Modellierung technischer Systeme, Datensätze für die Modellierung und Signifikanz von DatenKünstliche Neuronale Netze (NN): Biologische und künstliche Neuronen, Struktur, Eingang, Aktivierung, Ausgang, mathematische Grundlagen von NN.Arten und Strukturen von NN mit Fokus auf Multi-Layer Perceptrons (“Deep Learning\") und Rekurrenten NN (dynamische Systeme)Trainingsmethoden: Online-, Offline-, Reinforced LearningWissensbasierte Systeme: Fuzzy Logic, ExpertensystemeAnwendung der Methoden auf Probleme und Datensätze im Engineering in Computerpraktika mit Matlab® / Simulink®, z. B.: Training und Validierung eines NN zur Schätzung des Ladezustands und der Reichweite eines E-FahrzeugsBilderkennung von Verpackungsfehlern zur Qualitätssicherung in der MassenproduktionEntwicklung von Softsensoren zum Ersetzen teurer oder nicht erhältlicher SensorikFuzzy-basierte Regelung eines Roboter-ArmsVorausschauende Wartung („Predictive Maintenance“) für eine Windturbine\n\n--- Literature (EN) ---\n\n\n--- Literature (DE) ---\nR. Kruse et al.: Computational Intelligence, Springer, 2015 (in German)C. C. Aggarwal: Neural Networks and Deep Learning: A Textbook, Springer, 2018S. Ablameyko (ed.): Neural Networks for Instrumentation, Measurement and Related Industrial Applications, IOS Press, 2003", "metadata": {"moduleNumber": "xPF 3.9", "moduleName": "EDIT", "creditPoints": "5.0", "suggestedSemester": 4, "offeredInSeason": "summer_semester", "examType": "project", "heldInLanguage": "de", "reviserName": "", "reviserEmail": null, "studyProgramId": 14, "source_type": "json"}}
{"id": "BDAISY__D_3.6", "text": "Title: Professional Fokus Kick-Off\nModule Number: D 3.6\nCredits: 5.0 CP\nSemester: 3\nOffered In: winter_semester\nLanguage: de\nExam Type: portfolio\nInstructor: Prof. Dr. Dennis Müller\n\n--- Goals (EN) ---\nLearning outcomes and competencies are announced through the respective selected module.\n\n--- Goals (DE) ---\nLernergebnisse und Kompetenzen werden über das jeweils gewählt Modul bekannt gegeben.\n\n--- Contents (EN) ---\nYou choose one of the three offered kick-off events for your desired professional focus area.\n\n--- Contents (DE) ---\nSie wählen eine der drei angebotenen Kick-Off Veranstaltungen für ihren gewünschten Professional Fokus Bereich.\n\n--- Literature (EN) ---\nProvided in the selected module.\n\n--- Literature (DE) ---\nWird im gewählten Modul bekannt gegeben.", "metadata": {"moduleNumber": "D 3.6", "moduleName": "Professional Fokus Kick-Off", "creditPoints": "5.0", "suggestedSemester": 3, "offeredInSeason": "winter_semester", "examType": "portfolio", "heldInLanguage": "de", "reviserName": "Prof. Dr. Dennis Müller", "reviserEmail": "dennis.mueller@hs-duesseldorf.de", "studyProgramId": 14, "source_type": "json"}}
{"id": "BDAISY__WPM_PF_1", "text": "Title: Professional Focus Module 1\nModule Number: WPM PF 1\nCredits: 5.0 CP\nSemester: 4\nOffered In: summer_semester\nLanguage: de\nExam Type: see_elective\nInstructor: Prof. Dr. Dennis Müller\n\n--- Goals (EN) ---\nLearning outcomes according to the selected module\n\n--- Goals (DE) ---\nLernergebnisse gemäß des gewählten Moduls\n\n--- Contents (EN) ---\nLearning content according to the selected module\n\n--- Contents (DE) ---\nLerninhalte gemäß des gewählten Moduls\n\n--- Literature (EN) ---\nWill be announced in the module\n\n--- Literature (DE) ---\nWird in der Veranstaltung bekannt gegeben.", "metadata": {"moduleNumber": "WPM PF 1", "moduleName": "Professional Focus Module 1", "creditPoints": "5.0", "suggestedSemester": 4, "offeredInSeason": "summer_semester", "examType": "see_elective", "heldInLanguage": "de", "reviserName": "Prof. Dr. Dennis Müller", "reviserEmail": "dennis.mueller@hs-duesseldorf.de", "studyProgramId": 14, "source_type": "json"}}
{"id": "BDAISY__WPM_Kern_1", "text": "Title: Core Module 1\nModule Number: WPM Kern 1\nCredits: 5.0 CP\nSemester: 4\nOffered In: summer_semester\nLanguage: de\nExam Type: see_elective\nInstructor: Prof. Dr. Dennis Müller\n\n--- Goals (EN) ---\nAccording to the selected module\n\n--- Goals (DE) ---\nGemöß des gewählten Moduls\n\n--- Contents (EN) ---\nAccording to the selected module\n\n--- Contents (DE) ---\nGemäß des gewählten Moduls\n\n--- Literature (EN) ---\nWill be announced in the lecture\n\n--- Literature (DE) ---\nWird in der Veranstaltung bekannt gegeben.", "metadata": {"moduleNumber": "WPM Kern 1", "moduleName": "Core Module 1", "creditPoints": "5.0", "suggestedSemester": 4, "offeredInSeason": "summer_semester", "examType": "see_elective", "heldInLanguage": "de", "reviserName": "Prof. Dr. Dennis Müller", "reviserEmail": "dennis.mueller@hs-duesseldorf.de", "studyProgramId": 14, "source_type": "json"}}
{"id": "BDAISY__WPM_Kern_2", "text": "Title: Core Module 2\nModule Number: WPM Kern 2\nCredits: 5.0 CP\nSemester: 4\nOffered In: summer_semester\nLanguage: de\nExam Type: see_elective\nInstructor: Prof. Dr. Dennis Müller\n\n--- Goals (EN) ---\nAccording to the selected module\n\n--- Goals (DE) ---\nGemäß gewählten Modul\n\n--- Contents (EN) ---\nAccording to the selected module\n\n--- Contents (DE) ---\nGemäß gewählten Modul\n\n--- Literature (EN) ---\nAccording to the selected module\n\n--- Literature (DE) ---\nGemäß gewähltem Modul", "metadata": {"moduleNumber": "WPM Kern 2", "moduleName": "Core Module 2", "creditPoints": "5.0", "suggestedSemester": 4, "offeredInSeason": "summer_semester", "examType": "see_elective", "heldInLanguage": "de", "reviserName": "Prof. Dr. Dennis Müller", "reviserEmail": "dennis.mueller@hs-duesseldorf.de", "studyProgramId": 14, "source_type": "json"}}
{"id": "BDAISY__WPM_PF_4", "text": "Title: Professional Focus Module 4\nModule Number: WPM PF 4\nCredits: 5.0 CP\nSemester: 5\nOffered In: winter_semester\nLanguage: de\nExam Type: see_elective\nInstructor: Prof. Dr. Dennis Müller\n\n--- Goals (EN) ---\nLearning outcomes according to the selected module\n\n--- Goals (DE) ---\nLernergebnisse gemäß des gewählten Moduls\n\n--- Contents (EN) ---\nLearning content according to the selected module\n\n--- Contents (DE) ---\nLerninhalte gemäß des gewählten Moduls\n\n--- Literature (EN) ---\nWill be announced in the module\n\n--- Literature (DE) ---\nWird in der Veranstaltung bekannt gegeben.", "metadata": {"moduleNumber": "WPM PF 4", "moduleName": "Professional Focus Module 4", "creditPoints": "5.0", "suggestedSemester": 5, "offeredInSeason": "winter_semester", "examType": "see_elective", "heldInLanguage": "de", "reviserName": "Prof. Dr. Dennis Müller", "reviserEmail": "dennis.mueller@hs-duesseldorf.de", "studyProgramId": 14, "source_type": "json"}}
{"id": "BDAISY__WPM_Kern_3", "text": "Title: Core Module 3\nModule Number: WPM Kern 3\nCredits: 5.0 CP\nSemester: 5\nOffered In: winter_semester\nLanguage: de\nExam Type: see_elective\nInstructor: Prof. Dr. Dennis Müller\n\n--- Goals (EN) ---\nLearning outcomes according to the selected module\n\n--- Goals (DE) ---\nLernergebnisse gemäß des gewählten Moduls\n\n--- Contents (EN) ---\nLearning content according to the selected module\n\n--- Contents (DE) ---\nLerninhalte gemäß des gewählten Moduls\n\n--- Literature (EN) ---\nWill be announced in the module\n\n--- Literature (DE) ---\nWird in der Veranstaltung bekannt gegeben.", "metadata": {"moduleNumber": "WPM Kern 3", "moduleName": "Core Module 3", "creditPoints": "5.0", "suggestedSemester": 5, "offeredInSeason": "winter_semester", "examType": "see_elective", "heldInLanguage": "de", "reviserName": "Prof. Dr. Dennis Müller", "reviserEmail": "dennis.mueller@hs-duesseldorf.de", "studyProgramId": 14, "source_type": "json"}}
{"id": "BDAISY__PF_1.3", "text": "Title: EDIT\nModule Number: PF 1.3\nCredits: 5.0 CP\nSemester: 5\nOffered In: winter_semester\nLanguage: de\nExam Type: portfolio\nInstructor: None Peter Scheideler\n\n--- Goals (EN) ---\n\n\n--- Goals (DE) ---\nNach erfolgreichem Abschluss des Moduls sind die Studierenden in der Lage, Supply Chain Netzwerke zu gestalten, Planungsmodelle zu entwickeln und anzuwenden sowie die Supply Chain basierend auf Daten zu optimieren. Ein wesentlicher Schwerpunkt liegt hierbei auf den Kollaborationskonzepten (vernetztes Denken, Kooperationen) und der Supply Chain Teilnehmer (Zulieferer, Original Equipment Manufacturers (OEMs), Logistikdienstleister, Handler etc.). Die Studierenden verstehen unterschiedliche Kollaborationskonzepte wie Collaborative Planning, Forecasting and Replenishment (CPFR), Efficient Consumer Response (ECR), Just-in-Time (JIT)\noder Vendor Managed Inventory und können diese anwenden.\n\n--- Contents (EN) ---\n\n\n--- Contents (DE) ---\nDie Studierenden lernen Supply Chain Management als Integrationskonzept verschiedener intra- und interinstitutioneller Bereiche kennen. Sie erhalten einen Überblick über Supply Chain Management als prozessorientierten Ansatz und als Koordinationsfunktion. Hierbei werden sowohl qualitative als auch quantitative Übungen durchgeführt. Zur Unterstützung des Lernerfolgs wird eine interaktive Simulationssoftware eingesetzt, mittels derer strategische und operative Aspekte im Team erlernt werden.\n\n--- Literature (EN) ---\n\n\n--- Literature (DE) ---\nArndt (2021): Supply Chain Management, Optimierung logistischer Prozesse\nChopra/Meindl (2019): Supply Chain Management  Strategy, Planning, and Operation, 7. Aufl.\nRobertson (2020):  Supply Chain Analytics: Using Data to Optimise Supply Chain Processes (Mastering Business Analytics)\nWerner (2020): Supply Chain Management: Grundlagen, Strategien, Instrumente und Controlling", "metadata": {"moduleNumber": "PF 1.3", "moduleName": "EDIT", "creditPoints": "5.0", "suggestedSemester": 5, "offeredInSeason": "winter_semester", "examType": "portfolio", "heldInLanguage": "de", "reviserName": "None Peter Scheideler", "reviserEmail": "peter.scheideler@hs-duesseldorf.de", "studyProgramId": 14, "source_type": "json"}}
{"id": "BDAISY__PF_1.2", "text": "Title: Marketing Analytics (FB W)\nModule Number: PF 1.2\nCredits: 5.0 CP\nSemester: 4\nOffered In: summer_semester\nLanguage: de\nExam Type: written_exam\nInstructor: None Bastian Martschink\n\n--- Goals (EN) ---\nAs part of the module, students will be enabled to address specific questions of data-driven marketing through application examples and case studies using data analytics methods. They will also learn to assess the described problem areas with regard to their strategic and operational implications.\n\n--- Goals (DE) ---\nIm Rahmen\ndes Moduls werden die Studierenden befähigt, konkrete Fragestellungen des\nData Driven Marketing im Rahmen von Anwendungsbeispielen und Fallstudien mittels\nData Analytics Methoden zu bearbeiten und die beschriebenen Problemfelder in\nBezug auf strategische und operative Implikationen zu bewerten.\n\n--- Contents (EN) ---\na) Data-Driven Marketing\nFundamentals of Data-Driven Marketing / Marketing Analytics (terminology, concepts, and distinctions)\nSelected use cases and analytical scenarios in specific marketing-related challenges (e.g., brand positioning)\n\nb) Methods, Metrics, and Tools\nFundamentals of Marketing Analytics (methods, concepts, tools)\nHands-on exercises using common data analysis tools such as R and Python\nSelected application areas:\ni. Customer Analytics (profiling, segmentation, targeting, and scoring)\nii. Market Segmentation\niii. Recommender Systems\niv. Digital Marketing (e.g., web analytics, A/B testing, social media analytics)\nv. Dynamic Pricing\n\nc) Marketing Controlling\nFundamentals of Marketing Controlling (academic and practical foundations)\nKey figures and data structures in marketing controlling (information basis, goal and KPI systems / scorecards and dashboards)\nStrategic Marketing Controlling (selected instruments for managing the product portfolio, brand value, and customer equity)\nOperational Marketing Controlling (selected instruments for evaluating campaign and segment performance, market-oriented variance analyses)\n\n--- Contents (DE) ---\na) Data Analytics im Marketing\n\tGrundlagen Data Driven Marketing / Marketing Analytics (Begrifflichkeiten, Konzepte und Abgrenzungen)\n\tAusgewählte Anwendungsfälle und Analyseszenarien in konkreten Marketing-bezogenen Problemstellungen, z.B. Markenpositionierung\nb) Methoden, Metriken und Tools\n\tGrundlagen Data Analytics (Methoden, Konzepte, Tools)\n\tÜbungen mit gängigen Tools der Datenauswertung, z.B. R, Python\n\tAusgewählte Anwendungen:\ni. Kundenanalytik (Profiling, Segmentierung, Targeting und Scoring)\nii. Marktsegmentierung\niii. Empfehlungssysteme\niv. Digitales Marketing (z.B. Web Analytics, A/B-Testing, Social Media Analytics)\nv. Dynamic Pricing\nc) Marketingcontrolling\n\tGrundlagen des Marketingcontrollings (wissenschaftliche und praktische Grundlagen)\n\tZahlenwerk des Marketingcontrollings (Informationsbasis, Ziel- und Kennzahlensysteme / Scorecards und Cockpits)\n\tStrategisches Marketingcontrolling (ausgewählte Instrumente zur Steuerung des Produktprogramms, des Marken- und Kundenwertes)\n\tOperatives Marketingcontrolling (ausgewählte Instrumente zur Steuerung von Maßnahmenerfolg und Segmenterfolg, marktorientierte Abweichungsanalysen)\n\n--- Literature (EN) ---\nBoßow-Thies et. al.; Data-driven Marketing  Insights aus Wissenschaft und Praxis, Wiesbaden 2020.\n\tFader/Toms: The Customer Centricity Playbook  Implement a Winning Stratey driven by Customer Lifetime Value, Philadelphia 2018.\n\tHalfmann/ Schüller: Marketing Analytics  Perspektiven, Technologien, Anwendungsfelder, Wiesbaden 2022.\n\tHassler: Von Data-driven zu People-based Marketing: Erfolgreiche Digital Marketing Strategien in einer Privacy First Ära, Frechen 2021.\n\tKreutzer: Toolbox für Marketing und Management  Kreativkonzepte  Analysewerkzeuge  Prognoseinstrumente, Wiesbaden 2018.\n\tStürze/Hoyer et al.: Agiles Marketing Performance Management, Wiesbaden 2021.\n\tProvost/ Fawcett: Data science for business. What you need to know about data mining and data-analytic thinking, Sebastopol, CA 2013.\n\tWickham/ Grolemund: R für Data Science. Daten importieren, bereinigen, umformen, modellieren und visualisieren, Heidelberg 2018.\n\tWeber/Stein: Online-Controlling, Vallendar 2019.\n\tWiltinger/Heupel/Deimel: Controlling, 2. Aufl., München 2022.\n\tZerres: Handbuch Marketing-Controlling, 5. Aufl., Berlin/Heidelberg 2021.\n\n--- Literature (DE) ---\nBoßow-Thies et. al.; Data-driven Marketing  Insights aus Wissenschaft und Praxis, Wiesbaden 2020.\n\tFader/Toms: The Customer Centricity Playbook  Implement a Winning Stratey driven by Customer Lifetime Value, Philadelphia 2018.\n\tHalfmann/ Schüller: Marketing Analytics  Perspektiven, Technologien, Anwendungsfelder, Wiesbaden 2022.\n\tHassler: Von Data-driven zu People-based Marketing: Erfolgreiche Digital Marketing Strategien in einer Privacy First Ära, Frechen 2021.\n\tKreutzer: Toolbox für Marketing und Management  Kreativkonzepte  Analysewerkzeuge  Prognoseinstrumente, Wiesbaden 2018.\n\tStürze/Hoyer et al.: Agiles Marketing Performance Management, Wiesbaden 2021.\n\tProvost/ Fawcett: Data science for business. What you need to know about data mining and data-analytic thinking, Sebastopol, CA 2013.\n\tWickham/ Grolemund: R für Data Science. Daten importieren, bereinigen, umformen, modellieren und visualisieren, Heidelberg 2018.\n\tWeber/Stein: Online-Controlling, Vallendar 2019.\n\tWiltinger/Heupel/Deimel: Controlling, 2. Aufl., München 2022.\n\tZerres: Handbuch Marketing-Controlling, 5. Aufl., Berlin/Heidelberg 2021.", "metadata": {"moduleNumber": "PF 1.2", "moduleName": "Marketing Analytics (FB W)", "creditPoints": "5.0", "suggestedSemester": 4, "offeredInSeason": "summer_semester", "examType": "written_exam", "heldInLanguage": "de", "reviserName": "None Bastian Martschink", "reviserEmail": "bastian.martschink@hs-duesseldorf.de", "studyProgramId": 14, "source_type": "json"}}
{"id": "BDAISY__PF_1.1", "text": "Title: Entrepreneurship (FB M & W)\nModule Number: PF 1.1\nCredits: 5.0 CP\nSemester: 4\nOffered In: summer_semester\nLanguage: de\nExam Type: portfolio\nInstructor: None Dominik Austermann\n\n--- Goals (EN) ---\nUpon successful completion of the module, students are able to formulate key questions related to startup or innovation projects and explain the overall process of business formation or innovation development. They can distinguish between individual process steps and place them within the broader entrepreneurial or innovation context. Students are capable of identifying, analyzing, and addressing the challenges associated with startup or innovation initiatives in a solution-oriented manner. Furthermore, they can structure an innovation or startup project, develop their own business ideas, critically reflect on them, and translate them into a concrete business plan. They are able to recognize, describe, and analyze both internal and external factors influencing the innovation or startup process. Additionally, they can identify and assess the opportunities and risks associated with launching a new venture or implementing an innovation.\n\n--- Goals (DE) ---\nNach erfolgreicher Teilnahme an dem Modul sind die Studierenden in der Lage Fragestellungen eines Gründungs- bzw. Innovationsvorhabens zu erarbeiten und den Prozess der Unternehmensgründung bzw. Innovationsentwicklung zu erklären. Sie können die einzelnen Prozessschritte unterscheiden und in den Gründungs-/Innovationsprozess einordnen. Die Studierenden können die Problemfelder eines Gründungs-/Innovationsvorhabens identifizieren, analysieren und lösungsorientiert umsetzen. Des Weiteren können sie ein Innovations-/Gründungsvorhaben strukturieren, eigene Geschäftsideen entwickeln, kritisch reflektieren und in eine konkrete Businessplanung umsetzen. Sie können interne und externe Einflussfaktoren auf den Innovations-/Gründungsprozess erkennen, darstellen und analysieren. Chancen und Risiken einer Innovation bzw. Gründung können Sie erkennen und bewerten.\n\n--- Contents (EN) ---\n- The emergence of new business ventures in startups or established companies\n- Securing financing or budgeting resources for project implementation\n- Building and leveraging networks within the startup and innovation ecosystem\n- The process of applying for public funding and grants\n- Structure and components of pitches and business plans\n- Current trends and developments in the field of entrepreneurship\n\n--- Contents (DE) ---\n- Entstehung neuen Geschäfts in Startups oder etablierten Unternehmen\n- Finanzierung bzw. Budgetbeschaffung für Umsetzung von Vorhaben\n- Netzwerkaufbau und Nutzung in der Startup- und Innovationsszene\n- Prozess der Einwerbung öffentlicher Fördermittel\n- Struktur von Pitches und Businessplänen\n- Aktuelle Entwicklungen im Bereich Entrepreneurship\n\n--- Literature (EN) ---\nWill be announced during the lecture\n\n--- Literature (DE) ---\nWird in der Veranstaltung bekanntgegeben", "metadata": {"moduleNumber": "PF 1.1", "moduleName": "Entrepreneurship (FB M & W)", "creditPoints": "5.0", "suggestedSemester": 4, "offeredInSeason": "summer_semester", "examType": "portfolio", "heldInLanguage": "de", "reviserName": "None Dominik Austermann", "reviserEmail": "dominik.austermann@hs-duesseldorf.de", "studyProgramId": 14, "source_type": "json"}}
{"id": "BDAISY__PF_1.4", "text": "Title: Business Model and Marketing Project (FB M & W)\nModule Number: PF 1.4\nCredits: 10.0 CP\nSemester: 4\nOffered In: summer_semester\nLanguage: de\nExam Type: project\nInstructor: None Dominik Austermann\n\n--- Goals (EN) ---\nWithin this module, students develop the ability to independently and responsibly carry out a complex, practice-oriented project in collaboration with external industry partners. They learn to analyze real-world problems, identify project-specific requirements together with their partners, and develop appropriate solution strategies.\n\nStudents plan and structure the course of the project (apply/analyze) and implement it in close coordination with their external collaborators. Through this process, they gain a deeper understanding of professional practice requirements and learn to purposefully integrate theoretical knowledge into concrete, real-world contexts (understand/apply).\n\nA particular emphasis is placed on audience-appropriate communication with external partners, team members, and other stakeholders. Students learn to convincingly present project progress and results both orally and in writing, to process feedback constructively, and to document their work in a professional manner (evaluate/create).\n\nIn addition, they reflect on their roles within the project team, develop problem-solving skills, strengthen their self-organization, and practice collaborative work on equal footing with external partners (analyze/evaluate). By the end of the module, students are capable of independently and solution-orientedly addressing complex professional challenges while adhering to professional communication standards (create).\n\n--- Goals (DE) ---\nIm Rahmen dieses Moduls erwerben die Studierenden die Fähigkeit, ein komplexes, praxisnahes Projekt in Zusammenarbeit mit externen Praxispartnern eigenständig und verantwortungsvoll durchzuführen. Sie lernen, reale Problemstellungen zu analysieren, projektbezogene Anforderungen gemeinsam mit den Praxispartnern zu identifizieren und geeignete Lösungsstrategien zu entwickeln.\nDie Studierenden planen und strukturieren Projektabläufe (Anwenden/Analysieren) und setzen diese in enger Abstimmung mit Praxispartnern um. Dabei entwickeln sie ein tieferes Verständnis für die Anforderungen aus der beruflichen Praxis und integrieren theoretisches Wissen zielgerichtet in konkrete Handlungszusammenhänge (Verstehen/Anwenden).\nEin besonderer Schwerpunkt liegt auf der adressatengerechten Kommunikation mit Praxispartnern, Teammitgliedern und weiteren Stakeholdern. Die Studierenden lernen, Projektfortschritte und -ergebnisse mündlich und schriftlich überzeugend zu präsentieren, konstruktiv Feedback zu verarbeiten sowie ihre Ergebnisse in professioneller Weise zu dokumentieren (Bewerten/Erschaffen).\nDarüber hinaus reflektieren sie ihre Rolle im Projektteam, entwickeln Problemlösekompetenz, stärken ihre Selbstorganisation und üben sich in kooperativem Arbeiten auf Augenhöhe mit externen Partnern (Analysieren/Bewerten). Am Ende des Moduls sind die Studierenden in der Lage, komplexe berufliche Aufgabenstellungen eigenverantwortlich und lösungsorientiert zu bewältigen und dabei professionelle Kommunikationsstandards einzuhalten (Erschaffen).\n\n--- Contents (EN) ---\nStudents work on a business-relevant challenge in the field of marketing or business model development, actively engaging with company representatives as part of the process.\n\n- Execution of a larger practical project in the area of marketing or business model development (e.g., market entry strategies)\n- Project implementation covering all essential phases, including aspects of innovation management\n- Communication and collaboration with company stakeholders\n\n--- Contents (DE) ---\nDie Studierenden bearbeiten eine unternehmensrelevante Fragestellung aus dem Bereich Marketing bzw. Geschäftsmodellentwicklung. Die Zusammenarbeit mit Akteuren aus Unternehmen wird dabei gesucht.\n\n- Durchführung eines größeren praktischen Projekts im Bereich Marketing bzw. Geschäftsmodellentwicklung (z. B. Markteintrittsstrategien)\n- Projektdurchführung mit allen notwendigen Phasen (inkl. Innovationsmanagement)\n- Kommunikation mit Unternehmensvertretern\n\n--- Literature (EN) ---\nWill be announced during the lecture\n\n--- Literature (DE) ---\nWird in der Veranstaltung bekannt gegeben.", "metadata": {"moduleNumber": "PF 1.4", "moduleName": "Business Model and Marketing Project (FB M & W)", "creditPoints": "10.0", "suggestedSemester": 4, "offeredInSeason": "summer_semester", "examType": "project", "heldInLanguage": "de", "reviserName": "None Dominik Austermann", "reviserEmail": "dominik.austermann@hs-duesseldorf.de", "studyProgramId": 14, "source_type": "json"}}
{"id": "BDAISY__PF_1.7", "text": "Title: Media Project\nModule Number: PF 1.7\nCredits: 5.0 CP\nSemester: 4\nOffered In: summer_semester\nLanguage: de\nExam Type: project\nInstructor: Prof. Dr. Dennis Müller\n\n--- Goals (EN) ---\nSubject to the chosen offering.\n\n--- Goals (DE) ---\nAbhängig vom gewählten Angebot.\n\n--- Contents (EN) ---\nYou will choose one of the offered projects together with students from other degree programs within the Faculty of Media. The list of available courses will be announced at the beginning of each semester. Some elective courses may be cancelled, while additional courses may expand the offerings.\n\n--- Contents (DE) ---\nSie wählen zusammen mit Studierenden aus anderen Studiengängen des FB Medien eines der angebotenen Projekte. Das Angebot der wählbaren Kurse wird zu Beginn jeden Semesters bekanntgegeben. Einzelne Wahlkurse können entfallen, weitere Kurse können das Angebot erweitern.\n\n--- Literature (EN) ---\nWill be announced in the course.\n\n--- Literature (DE) ---\nWird im Kurs bekannt gegebenen", "metadata": {"moduleNumber": "PF 1.7", "moduleName": "Media Project", "creditPoints": "5.0", "suggestedSemester": 4, "offeredInSeason": "summer_semester", "examType": "project", "heldInLanguage": "de", "reviserName": "Prof. Dr. Dennis Müller", "reviserEmail": "dennis.mueller@hs-duesseldorf.de", "studyProgramId": 14, "source_type": "json"}}
{"id": "BDAISY__WPM_PF_6", "text": "Title: Professional Focus Module 6\nModule Number: WPM PF 6\nCredits: 5.0 CP\nSemester: 5\nOffered In: winter_semester\nLanguage: de\nExam Type: see_elective\nInstructor: Prof. Dr. Dennis Müller\n\n--- Goals (EN) ---\nLearning outcomes according to the selected module\n\n--- Goals (DE) ---\nLernergebnisse gemäß des gewählten Moduls\n\n--- Contents (EN) ---\nLearning content according to the selected module\n\n--- Contents (DE) ---\nLerninhalte gemäß des gewählten Moduls\n\n--- Literature (EN) ---\nWill be announced in the module\n\n--- Literature (DE) ---\nWird in der Veranstaltung bekannt gegeben.", "metadata": {"moduleNumber": "WPM PF 6", "moduleName": "Professional Focus Module 6", "creditPoints": "5.0", "suggestedSemester": 5, "offeredInSeason": "winter_semester", "examType": "see_elective", "heldInLanguage": "de", "reviserName": "Prof. Dr. Dennis Müller", "reviserEmail": "dennis.mueller@hs-duesseldorf.de", "studyProgramId": 14, "source_type": "json"}}
{"id": "BDAISY__WPM_Kern_4", "text": "Title: Core Module 4\nModule Number: WPM Kern 4\nCredits: 5.0 CP\nSemester: 5\nOffered In: winter_semester\nLanguage: de\nExam Type: see_elective\nInstructor: Prof. Dr. Dennis Müller\n\n--- Goals (EN) ---\nLearning outcomes according to the selected module\n\n--- Goals (DE) ---\nLernergebnisse gemäß des gewählten Moduls\n\n--- Contents (EN) ---\nLearning content according to the selected module\n\n--- Contents (DE) ---\nLerninhalte gemäß des gewählten Moduls\n\n--- Literature (EN) ---\nWill be announced in the module\n\n--- Literature (DE) ---\nWird in der Veranstaltung bekannt gegeben.", "metadata": {"moduleNumber": "WPM Kern 4", "moduleName": "Core Module 4", "creditPoints": "5.0", "suggestedSemester": 5, "offeredInSeason": "winter_semester", "examType": "see_elective", "heldInLanguage": "de", "reviserName": "Prof. Dr. Dennis Müller", "reviserEmail": "dennis.mueller@hs-duesseldorf.de", "studyProgramId": 14, "source_type": "json"}}
{"id": "BDAISY__WPM_KWEG_2", "text": "Title: Culture, Economy, Ethics, and Society - 2\nModule Number: WPM KWEG 2\nCredits: 5.0 CP\nSemester: 5\nOffered In: winter_semester\nLanguage: de\nExam Type: see_elective\nInstructor: Prof. Dr. Dennis Müller\n\n--- Goals (EN) ---\nLearning outcomes according to the selected module\n\n--- Goals (DE) ---\nLernergebnisse gemäß des gewählten Moduls\n\n--- Contents (EN) ---\nLearning content according to the selected module\n\n--- Contents (DE) ---\nLerninhalte gemäß des gewählten Moduls\n\n--- Literature (EN) ---\nWill be announced in the module\n\n--- Literature (DE) ---\nWird in der Veranstaltung bekannt gegeben.", "metadata": {"moduleNumber": "WPM KWEG 2", "moduleName": "Culture, Economy, Ethics, and Society - 2", "creditPoints": "5.0", "suggestedSemester": 5, "offeredInSeason": "winter_semester", "examType": "see_elective", "heldInLanguage": "de", "reviserName": "Prof. Dr. Dennis Müller", "reviserEmail": "dennis.mueller@hs-duesseldorf.de", "studyProgramId": 14, "source_type": "json"}}
{"id": "BDAISY__PF_2.8", "text": "Title: EDIT\nModule Number: PF 2.8\nCredits: 5.0 CP\nSemester: 5\nOffered In: summer_semester\nLanguage: de\nExam Type: portfolio\nInstructor: Prof. Dr. Alina Huldtgren\n\n--- Goals (EN) ---\n\n\n--- Goals (DE) ---\nDie Studenten haben systemische Überblicks-Kompetenz für Transmedia Storytelling Prozesse, in denen sich wesentliche Bestandteile einer Geschichte systematisch über mehrere Medien entfalten. Sie können kollaboratives, partizipatives, ortsbasiertes oder nichtlineares Erzählen und narratives Design planen und die dafür notwendigen Prozesse, Bestandteile und Player identifizieren.In der Reflektion über erfolgreiche transmediale Produkte entwickeln sie einen kritischen und akademischen Standpunkt über die Potentiale und Herausforderungen von transmedialen Design in Branding und Entertainment.\n\n--- Contents (EN) ---\n\n\n--- Contents (DE) ---\nIn der Lehrveranstaltung werdenstrategische Anwendungs-kontexte und Verfahren genutzt, um transmediale Erzählungen in kulturellen und wirtschaftlichen Kontexten zu erproben, zu analysieren und strukturell aufzubereiten.Dazu werden Analysetools vorgestellt und Gestaltungstools im Graphik- und Web Design, Film- und Schnitttechniken vermittelt. Es werden Szenarios geschrieben und Storyboards entwickelt.\n\n--- Literature (EN) ---\n\n\n--- Literature (DE) ---\nHenry Jenkins: Transmedia 202. Further refelections (2011). URL: http://henryjenkins.or/2011/08/defining_transmedia_further_re.html (Stand 25.07.2013)Kelly McErlean: Interactive Narratives and Transmedia Storytelling. Creating Immersive Stories Across New Media Platforms New York: CRC Press, 2018Joachim Friedmann, Transmediales Erzählen. Narrative Gestaltung in Literatur, Film, Graphic Novel und Game Köln: Halem, 2017", "metadata": {"moduleNumber": "PF 2.8", "moduleName": "EDIT", "creditPoints": "5.0", "suggestedSemester": 5, "offeredInSeason": "summer_semester", "examType": "portfolio", "heldInLanguage": "de", "reviserName": "Prof. Dr. Alina Huldtgren", "reviserEmail": "alina.huldtgren@hs-duesseldorf.de", "studyProgramId": 14, "source_type": "json"}}
{"id": "BDAISY__PF_2.7", "text": "Title: EDIT\nModule Number: PF 2.7\nCredits: 5.0 CP\nSemester: 5\nOffered In: summer_semester\nLanguage: de\nExam Type: project\nInstructor: Prof. Dr. Alina Huldtgren\n\n--- Goals (EN) ---\n\n\n--- Goals (DE) ---\n\n\n--- Contents (EN) ---\n\n\n--- Contents (DE) ---\n\n\n--- Literature (EN) ---\n\n\n--- Literature (DE) ---", "metadata": {"moduleNumber": "PF 2.7", "moduleName": "EDIT", "creditPoints": "5.0", "suggestedSemester": 5, "offeredInSeason": "summer_semester", "examType": "project", "heldInLanguage": "de", "reviserName": "Prof. Dr. Alina Huldtgren", "reviserEmail": "alina.huldtgren@hs-duesseldorf.de", "studyProgramId": 14, "source_type": "json"}}
{"id": "BDAISY__PF_2.10", "text": "Title: EDIT\nModule Number: PF 2.10\nCredits: 5.0 CP\nSemester: 5\nOffered In: winter_semester\nLanguage: de\nExam Type: project\nInstructor: Prof. Dr. Alina Huldtgren\n\n--- Goals (EN) ---\n\n\n--- Goals (DE) ---\n\n\n--- Contents (EN) ---\n\n\n--- Contents (DE) ---\n\n\n--- Literature (EN) ---\n\n\n--- Literature (DE) ---", "metadata": {"moduleNumber": "PF 2.10", "moduleName": "EDIT", "creditPoints": "5.0", "suggestedSemester": 5, "offeredInSeason": "winter_semester", "examType": "project", "heldInLanguage": "de", "reviserName": "Prof. Dr. Alina Huldtgren", "reviserEmail": "alina.huldtgren@hs-duesseldorf.de", "studyProgramId": 14, "source_type": "json"}}
{"id": "BDAISY__PF_1.5", "text": "Title: EDIT\nModule Number: PF 1.5\nCredits: 5.0 CP\nSemester: 5\nOffered In: winter_semester\nLanguage: de\nExam Type: project\nInstructor: None Kay Schröder\n\n--- Goals (EN) ---\nIn this practice-oriented project, students apply fundamental design principles and further develop their creative skills. Throughout the module, they acquire the following competencies:\n\n- Subject-specific competence: The ability to apply basic design methods to solve a concrete design task\n- Methodological competence: A structured approach to the design process and basic project organization\n- Social competence: Giving and receiving feedback, and presenting one's own work effectively\n- Personal competence: Working independently and managing time responsibly\n\n--- Goals (DE) ---\nDie Studierenden wenden grundlegende Designprinzipien in einem praxisorientierten Projekt an und entwickeln ihre gestalterischen Fähigkeiten weiter. Sie erwerben:\n\n- Fachkompetenz: Anwendung grundlegender Designmethoden zur Lösung einer konkreten Gestaltungsaufgabe\n- Methodenkompetenz: Strukturiertes Vorgehen im Designprozess und grundlegende Projektorganisation\n- Sozialkompetenz: Feedback geben und annehmen, Präsentation eigener Arbeit\n- Selbstkompetenz: Selbstständiges Arbeiten und Zeitmanagement\n\n--- Contents (EN) ---\nExecution of a larger practical, conceptual, or theoretical project within the professional focus area Business and Human Data Interaction (HDI), approached as an interdisciplinary project with a strong design and conceptual orientation. The project follows an iterative workflow that fosters creative idea generation and systematic concept development across multiple design cycles, accompanied by continuous evaluation, professional documentation, and presentation of results.\n\nProject implementation includes all essential phases: requirements analysis, conceptual development, design, prototyping, evaluation, and documentation. Communication with potential project partners or task originators is also an integral part of the process.\n\n--- Contents (DE) ---\nUmsetzung eines größeren praktischen, konzeptionellen oder theoretischen Projekts im Professional Fokus Business und Human Data Interaction (HDI)\" als interdisziplinäres Projekt mit gestalterisch-konzeptionellem Fokus. Durch iterative Arbeitsweise erfolgen kreative Ideenfindung und systematische Konzeptentwicklung in mehreren Gestaltungszyklen mit kontinuierlicher Evaluation und professioneller Projektdokumentation sowie -präsentation. Projektdurchführung mit allen notwendigen Phasen (Anforderungsermittlung, Konzeption, Design, Prototyping, Evaluation, Dokumentation). Kommunikation mit potenziellen Projektpartnern bzw. Aufgabenerstellern.\n\n--- Literature (EN) ---\nWill be announced during the lecture\n\n--- Literature (DE) ---\nWird bei Veranstaltungsbeginn bekannt gegeben.", "metadata": {"moduleNumber": "PF 1.5", "moduleName": "EDIT", "creditPoints": "5.0", "suggestedSemester": 5, "offeredInSeason": "winter_semester", "examType": "project", "heldInLanguage": "de", "reviserName": "None Kay Schröder", "reviserEmail": "kay.schroeder@hs-duesseldorf.de", "studyProgramId": 14, "source_type": "json"}}
{"id": "BDAISY__xPF_6.8", "text": "Title: EDIT\nModule Number: xPF 6.8\nCredits: 5.0 CP\nSemester: 4\nOffered In: summer_semester\nLanguage: de\nExam Type: research_paper\nInstructor: \n\n--- Goals (EN) ---\n\n\n--- Goals (DE) ---\nDie Studierenden können Daten auf verschiedenen digitalen Wegen Weg austauschen, lernen durch diese untereinander und voneinander, nutzen (gemeinschaftlich) bestehende Daten und verändern sie kreativ, um sie damit zu \"neuen\" Daten zu \"remixen\" oder zu \"mashen\" oder auf deren Basis selbst eigene Werke zu erstellen.Die Studierenden arbeiten selbständig und eigeninitiativ mit dem E-Learning-Portal Moodle.Die Studierenden erlangen Kenntnisse über das kontinentaleuropäische Urheberrecht, Leistungsschutzrecht und das angloamerikanische Copyright-System. Sie kennen alternative Lizenzmodelle wie \"CreativeCommons\" und Bewegungen wie GNU und die Free Software Foundation von Richard Stallman.\n\n--- Contents (EN) ---\n\n\n--- Contents (DE) ---\nGrundsätze von freier Software (Free Software) und quelloffener Software (Open Source) werden kennengelernt. Die Studierenden setzen sich theoretisch und praktisch mit entsprechender Software auseinander und erörtern Beispiele für den Einsatz in mehreren Handlungsfeldern.- Grundsätze von freier Software (Free Software) und quelloffener Software (Open Source), kontinentaleuropäisches Urheberrecht, Leistungsschutzrecht,  angloamerikanische Copyright-System, alternative Lizenzmodelle wie \"CreativeCommons\"\n\n--- Literature (EN) ---\n\n\n--- Literature (DE) ---\nDjordjevic, Valie; Gehring, Robert A.; Grassmuck, Volker; Kreutzer, Till; Spielkamp, Matthias (Hrsg ). (2008): Urheberrecht im Alltag. Kopieren, bearbeiten, selber machen ; iRights.INFO. 2. Aufl. Bonn: Bundeszentrale für Polit. BildungGrassmuck, Volker (2004): Freie Software. Zwischen Privat- und Gemeineigentum. [Online-Ausg.], 2., korr. Aufl. Bonn: Bundeszentrale für Politische BildungHofmann, Jeanette (2006): Wissen und Eigentum. Geschichte, Recht und Ökonomie stoffloser Güter. Bonn: Bundeszentrale für Politische BildungImhorst, Christian (2005): Die Anarchie der Hacker. Richard Stallman und die Freie-Software-Bewegung. Marburg: TectumLessig, Lawrence (2006): Freie Kultur. Wesen und Zukunft der Kreativität. München, Open Source PressRakebrand, Thomas (2014): \"Gehört das dann der Welt oder Youtube?\" - Junge Erwachsene und ihr Verständnis vom Urheberrecht im Web 2.0. München, kopaed verlagsgmbhThemelidis, Markos (2004): Open Source. Die Freiheitsvision der Hacker. Norderstedt: Books on Demand", "metadata": {"moduleNumber": "xPF 6.8", "moduleName": "EDIT", "creditPoints": "5.0", "suggestedSemester": 4, "offeredInSeason": "summer_semester", "examType": "research_paper", "heldInLanguage": "de", "reviserName": "", "reviserEmail": null, "studyProgramId": 14, "source_type": "json"}}
{"id": "BDAISY__PF_2.9", "text": "Title: EDIT\nModule Number: PF 2.9\nCredits: 5.0 CP\nSemester: 5\nOffered In: winter_semester\nLanguage: de\nExam Type: research_paper\nInstructor: Prof. Dr. Alina Huldtgren\n\n--- Goals (EN) ---\n\n\n--- Goals (DE) ---\n\n\n--- Contents (EN) ---\n\n\n--- Contents (DE) ---\n\n\n--- Literature (EN) ---\n\n\n--- Literature (DE) ---", "metadata": {"moduleNumber": "PF 2.9", "moduleName": "EDIT", "creditPoints": "5.0", "suggestedSemester": 5, "offeredInSeason": "winter_semester", "examType": "research_paper", "heldInLanguage": "de", "reviserName": "Prof. Dr. Alina Huldtgren", "reviserEmail": "alina.huldtgren@hs-duesseldorf.de", "studyProgramId": 14, "source_type": "json"}}
{"id": "BDAISY__D_3.6.3", "text": "Title: PF Kick-Off (Automation & Construction)\nModule Number: D 3.6.3\nCredits: 5.0 CP\nSemester: 3\nOffered In: winter_semester\nLanguage: de\nExam Type: project\nInstructor: None Moritz Fleischmann-Bergstein\n\n--- Goals (EN) ---\nUpon successful completion of the module, students will be able to:\n- understand basic concepts in automation technology and energy systems,\n- analyze and design basic building automation systems,\n- integrate energy and building technology aspects into the planning process,\n- recognize and apply interdisciplinary connections between technology and architecture,\n- interpret and create technical drawings, construction plans, and basic CAD models,\n- conceptualize and implement a basic interdisciplinary project involving multiple technical domains.\n\n--- Goals (DE) ---\nNach erfolgreichem Abschluss des Moduls sind die Studierenden in der Lage:\n- grundlegende Konzepte der Automatisierungstechnik und Energietechnik zu verstehen,\n- einfache Systeme zur Gebäudeautomation zu analysieren und zu gestalten,\n- energie- und gebäudetechnische Aspekte in den Planungsprozess zu integrieren,\n- interdisziplinäre Zusammenhänge zwischen Technik und Architektur zu erkennen und in Projekten anzuwenden,\n- technische Zeichnungen, Konstruktionspläne und einfache CAD-Modelle zu interpretieren und zu erstellen,\n- ein einfaches Projekt unter Einbeziehung aller beteiligten Fachdisziplinen zu konzipieren und im Team zu realisieren.\n\n--- Contents (EN) ---\nThe module covers fundamental topics from automation technology, energy engineering, mechanical engineering, and architecture, as well as their intersections.\n- Introduction to automation technology - Sensors and actuators in technical systems - Basics of control and regulation systems - Fundamentals of energy technology and renewable energies\n- Smart buildings and building automation - Sustainability and energy efficiency in construction\n- Basics of mechanical engineering and construction - Introduction to architectural thinking and design\n- Technical drawings and CAD fundamentals - Safety aspects and relevant technical standards\n- Simulation of basic automated systems - Project work: Designing an automated system in a construction context\n\n--- Contents (DE) ---\nDas Modul beinhaltet grundlegende Themen aus der Automatisierungstechnik, der Energietechnik, des Maschinenbaus und der Architektur sowie deren Schnittmengen.\n- Einführung in die Automatisierungstechnik - Sensorik und Aktorik in technischen Systemen - Steuerungs- und Regelungstechnik (Grundlagen) - Grundlagen der Energietechnik und erneuerbare Energien - Smart Buildings und Gebäudeautomation - Nachhaltigkeit und Energieeffizienz im Bauwesen - Grundlagen des Maschinenbaus und der Konstruktion - Einführung in architektonisches Denken und Entwerfen - Technische Zeichnungen und CAD-Grundlagen - Sicherheitsaspekte und Normen in Technik und Bau - Simulation einfacher automatisierter Systeme - Projektarbeit: Konzeption eines automatisierten Systems im Baukontext\n\n--- Literature (EN) ---\n- Petermann, K. (2020): Automatisierungstechnik: Grundlagen für Studium und Praxis, Springer Vieweg, 5. Auflage, ISBN: 978-3-658-29356-6\n- Sickert, U. (2021): Energietechnik: Grundlagen elektrischer Energieversorgung, VDE Verlag, 2. Auflage, ISBN: 978-3-8007-4746-6\n- Mutschler, E. et al. (2022): Grundlagen Maschinenbau: Technische Mechanik, Werkstoffe, Konstruktion, Springer Vieweg, 4. Auflage, ISBN: 978-3-662-64293-3\n- Schittkowski, K. (2019): Grundlagen der Gebäudetechnik, Beuth Verlag, 3. Auflage, ISBN: 978-3-410-29046-1\n- Bauer, M.; Mösle, P.; Schwarz, M. (2022): Green Building: Nachhaltiges Bauen in der Praxis, Springer Vieweg, 4. Auflage, ISBN: 978-3-658-36278-1\n- Wittwer, C.; Heinemann, M. (2021): Gebäudeautomation: Systeme, Anwendungen, Projektierung, VDE Verlag, 3. Auflage, ISBN: 978-3-8007-5189-0\n\n--- Literature (DE) ---\n- Petermann, K. (2020): Automatisierungstechnik: Grundlagen für Studium und Praxis, Springer Vieweg, 5. Auflage, ISBN: 978-3-658-29356-6\n- Sickert, U. (2021): Energietechnik: Grundlagen elektrischer Energieversorgung, VDE Verlag, 2. Auflage, ISBN: 978-3-8007-4746-6\n- Mutschler, E. et al. (2022): Grundlagen Maschinenbau: Technische Mechanik, Werkstoffe, Konstruktion, Springer Vieweg, 4. Auflage, ISBN: 978-3-662-64293-3\n- Schittkowski, K. (2019): Grundlagen der Gebäudetechnik, Beuth Verlag, 3. Auflage, ISBN: 978-3-410-29046-1\n- Bauer, M.; Mösle, P.; Schwarz, M. (2022): Green Building: Nachhaltiges Bauen in der Praxis, Springer Vieweg, 4. Auflage, ISBN: 978-3-658-36278-1\n- Wittwer, C.; Heinemann, M. (2021): Gebäudeautomation: Systeme, Anwendungen, Projektierung, VDE Verlag, 3. Auflage, ISBN: 978-3-8007-5189-0", "metadata": {"moduleNumber": "D 3.6.3", "moduleName": "PF Kick-Off (Automation & Construction)", "creditPoints": "5.0", "suggestedSemester": 3, "offeredInSeason": "winter_semester", "examType": "project", "heldInLanguage": "de", "reviserName": "None Moritz Fleischmann-Bergstein", "reviserEmail": "moritz.fleischmann@hs-duesseldorf.de", "studyProgramId": 14, "source_type": "json"}}
{"id": "BDAISY__D_3.6.2", "text": "Title: EDIT\nModule Number: D 3.6.2\nCredits: 5.0 CP\nSemester: 3\nOffered In: winter_semester\nLanguage: de\nExam Type: project\nInstructor: Prof. Dr. Alina Huldtgren\n\n--- Goals (EN) ---\n\n\n--- Goals (DE) ---\n\n\n--- Contents (EN) ---\n\n\n--- Contents (DE) ---\n\n\n--- Literature (EN) ---\n\n\n--- Literature (DE) ---", "metadata": {"moduleNumber": "D 3.6.2", "moduleName": "EDIT", "creditPoints": "5.0", "suggestedSemester": 3, "offeredInSeason": "winter_semester", "examType": "project", "heldInLanguage": "de", "reviserName": "Prof. Dr. Alina Huldtgren", "reviserEmail": "alina.huldtgren@hs-duesseldorf.de", "studyProgramId": 14, "source_type": "json"}}
{"id": "BDAISY__WPM_KWEG_1", "text": "Title: Culture, Economy, Ethics, and Society 1\nModule Number: WPM KWEG 1\nCredits: 5.0 CP\nSemester: 4\nOffered In: summer_semester\nLanguage: de\nExam Type: see_elective\nInstructor: Prof. Dr. Dennis Müller\n\n--- Goals (EN) ---\nAccording to the selected module\n\n--- Goals (DE) ---\nGemäß gewählter Veranstaltung\n\n--- Contents (EN) ---\nAccording to the selected module\n\n--- Contents (DE) ---\nGemäß gewählter Veranstaltung\n\n--- Literature (EN) ---\nAccording to the selected module\n\n--- Literature (DE) ---\nGemäß gewählter Veranstaltung", "metadata": {"moduleNumber": "WPM KWEG 1", "moduleName": "Culture, Economy, Ethics, and Society 1", "creditPoints": "5.0", "suggestedSemester": 4, "offeredInSeason": "summer_semester", "examType": "see_elective", "heldInLanguage": "de", "reviserName": "Prof. Dr. Dennis Müller", "reviserEmail": "dennis.mueller@hs-duesseldorf.de", "studyProgramId": 14, "source_type": "json"}}
{"id": "BDAISY__D_3.6.1", "text": "Title: PF Kick-Off (Business & HDI)\nModule Number: D 3.6.1\nCredits: 5.0 CP\nSemester: 3\nOffered In: winter_semester\nLanguage: de\nExam Type: portfolio\nInstructor: Prof. Dr. Dennis Müller\n\n--- Goals (EN) ---\nAs part of this module, students acquire essential professional, methodological, and social competencies for working across disciplines at the intersection of economics, media, and design. They gain an understanding of the fundamental principles of innovation management and develop the ability to conduct basic economic analyses. Students learn to develop and communicate their own ideas using media-based tools and current technological capabilitiesparticularly within the context of artificial intelligencethrough the creation of prototypes. In addition, they build an understanding of design principles for communication and presentation, with a particular focus on interface design and the visual representation of complex content. Throughout the module, students enhance their skills in interdisciplinary collaboration, audience-appropriate communication of ideas, and thoughtful engagement with a variety of disciplinary perspectives.\n\n--- Goals (DE) ---\nDie Studierenden erwerben im Rahmen des Moduls grundlegende fachliche, methodische sowie soziale Kompetenzen im interdisziplinären Arbeiten an der Schnittstelle von Wirtschaftswissenschaften, Medien und Design. Sie verstehen grundlegende Prinzipien des Innovationsmanagements und sind in der Lage, einfache wirtschaftswissenschaftliche Analysen durchzuführen. Sie können eigene Ideen mediengestützt und unter Berücksichtigung aktueller technologischer Möglichkeiten  insbesondere im Kontext künstlicher Intelligenz  prototypisch umsetzen. Darüber hinaus entwickeln sie ein Verständnis für gestalterische Prinzipien der Kommunikation und Präsentation, insbesondere im Hinblick auf Interface-Design und visuelle Darstellung komplexer Inhalte. Im Verlauf des Moduls stärken die Studierenden ihre Fähigkeit zur Zusammenarbeit in interdisziplinären Teams, zur adressatengerechten Aufbereitung von Ideen sowie zur reflektierten Auseinandersetzung mit unterschiedlichen fachlichen Perspektiven.\n\n--- Contents (EN) ---\nIn this module, students are introduced to key foundational concepts and practice-oriented methods from the three participating disciplines, which they apply in a project-based setting. The module includes:\n\nAn introduction to interdisciplinary collaboration across business, media, and design\n\n- Fundamentals of innovation management\n- Conducting basic economic analyses\n- Introduction to media technology prototyping methods\n- Exploration of AI applications in early-stage innovation processes\n- Development and implementation of a self-initiated project idea in team-based work\n- Design methods and visual communication: fundamentals of concept development and design (e.g., interface design, storyboarding, visual language)\n- Presentation and communication of project outcomes in interdisciplinary contexts\n- Reflection on cross-disciplinary collaboration\n\n--- Contents (DE) ---\nDie Studierenden lernen im Rahmen dieses Moduls zentrale Grundlagen und praxisnahe Methoden aus den drei beteiligten Fachbereichen kennen und wenden diese projektbasiert an:\n\n\n- Einführung in interdisziplinäres Arbeiten zwischen Wirtschaftswissenschaften, Medien und Design\n- Grundlagen des Innovationsmanagements\n- Durchführung einfacher wirtschaftswissenschaftlicher Analysen\n- Einführung in medientechnische Prototyping-Verfahren\n- Auseinandersetzung mit KI-Anwendungen in frühen Innovationsprozessen\n- Entwicklung und Umsetzung einer eigenen Projektidee in Teamarbeit\n- Designmethoden und visuelle Kommunikation: Grundlagen der Konzeption und Gestaltung (z.B. Interface, Storyboard, visuelle Sprache)\n- Präsentation und Kommunikation von Projektergebnissen in interdisziplinären Kontexten\n- Reflexion der Zusammenarbeit über Fachbereichsgrenzen hinweg\n\n--- Literature (EN) ---\nWill be announced during the lectures\n\n--- Literature (DE) ---\nWird in der Veranstaltung bekannt gegeben", "metadata": {"moduleNumber": "D 3.6.1", "moduleName": "PF Kick-Off (Business & HDI)", "creditPoints": "5.0", "suggestedSemester": 3, "offeredInSeason": "winter_semester", "examType": "portfolio", "heldInLanguage": "de", "reviserName": "Prof. Dr. Dennis Müller", "reviserEmail": "dennis.mueller@hs-duesseldorf.de", "studyProgramId": 14, "source_type": "json"}}
{"id": "BDAISY__D_3.4", "text": "Title: Discrete Mathematics\nModule Number: D 3.4\nCredits: 5.0 CP\nSemester: 3\nOffered In: winter_semester\nLanguage: de\nExam Type: written_exam\nInstructor: \n\n--- Goals (EN) ---\nStudents who have completed the course are able to identify and use standard logical connectives and construct truth tables to evaluate logical expressions. They can distinguish between tautologies, contradictions, and logically equivalent statements and analyze the use of universal and existential quantifiers. In set theory, students are able to define and manipulate sets, subsets, unions, intersections, and differences, construct power sets and Cartesian products, and describe relationships between set operations. They can classify relations based on reflexivity, symmetry, transitivity, and antisymmetry, and distinguish between equivalence and order relations. Furthermore, they can determine whether functions are injective, surjective, or bijective. In the area of number theory, students are able to apply divisibility rules, compute greatest common divisors and least common multiples efficeiently, learn the Euclidean algorithm, decide the primality of numbers, and use the Chinese Remainder Theorem. With respect to algebraic structures, students can perform modular arithmetic, describe the structure of finite fields, and apply exponentiation in modular systems. Additionally, they are capable of constructing direct proofs, developing indirect proofs by contraposition or contradiction, and applying mathematical induction to verify statements involving natural numbers. These outcomes reflect learning objectives on various cognitive levels including remembering, understanding, applying, analyzing, evaluating, and creating.\n\n--- Goals (DE) ---\nStudierende, die die Veranstaltung abgeschlossen haben, können logische Aussagen und Junktoren erkennen und anwenden sowie Wahrheitstabellen zur Bewertung logischer Ausdrücke erstellen. Sie sind in der Lage, Tautologien, Kontradiktionen und logisch äquivalente Aussagen zu unterscheiden und den Einsatz von All- und Existenzquantoren zu analysieren. Im Bereich der Mengenlehre können sie Mengen, Teilmengen, Vereinigungs-, Schnitt- und Differenzmengen definieren und manipulieren, Potenzmengen und kartesische Produkte konstruieren und Zusammenhänge zwischen Mengenoperationen beschreiben. Sie können Relationen hinsichtlich Reflexivität, Symmetrie, Transitivität und Antisymmetrie klassifizieren und Äquivalenz- sowie Ordnungsrelationen unterscheiden. Darüber hinaus sind sie in der Lage zu beurteilen, ob Funktionen injektiv, surjektiv oder bijektiv sind. In der Zahlentheorie wenden sie Teilbarkeitsregeln an, berechnen den größten gemeinsamen Teiler und das kleinste gemeinsame Vielfache effizient, lernen den Euklidischen Algorithmus kennen, entscheiden die Primzahligkeit von Zahlen und verwenden den chinesischen Restsatz. Im Bereich der algebraischen Strukturen führen sie Berechnungen mit der Modulo-Rechnung durch, beschreiben die Struktur endlicher Körper und wenden Exponentiation in modularen Systemen an. Zusätzlich sind sie in der Lage, direkte Beweise zu formulieren, indirekte Beweise über Kontraposition oder Widerspruch zu entwickeln und vollständige Induktion anzuwenden, um Aussagen über natürliche Zahlen zu verifizieren.\n\n--- Contents (EN) ---\nThis course covers key concepts of discrete mathematics, providing foundational tools for both theoretical and applied computer science:\n\nLogic and Propositional Logic\n\n- Propositional logic with logical connectives (not, and, or, implication, equivalence)\n- Truth tables for evaluating logical expressions\n- Equivalence, tautologies, and contradictions\n- Types of statements and quantifiers (universal and existential quantifiers)\n\nSet Theory\n\n- Sets and subsets, union, intersection, and set difference\n- Power sets and Cartesian products\nRelations and Functions\n- Properties of relations: reflexive, symmetric, transitive, antisymmetric\n- Equivalence relations and order relations\n- Properties of functions: injective, surjective, bijective\n\nNumber Theory (Fundamentals)\n- Divisibility, greatest common divisor (gcd), least common multiple (lcm)\n- Prime numbers and the Euclidean algorithm\n- Primality tests and the Chinese Remainder Theorem\n\nGroups and Fields\n- Modular arithmetic and operations on residue classes\n- Finite fields and their structure\n- Exponentiation in residue classes\n\nProof Techniques (optional)\n\n- Direct proof\n- Indirect proof by contraposition and contradiction\n- Mathematical induction as a structural proof method\n\n--- Contents (DE) ---\nIn dieser Veranstaltung werden zentrale Konzepte der diskreten Mathematik behandelt, die grundlegende Werkzeuge für theoretische und angewandte Informatik bereitstellen:\n\nLogik und Aussagenlogik\n- Aussagenlogik mit Junktoren (nicht, und, oder, Implikation, Äquivalenz)\n- Wahrheitstabellen zur Auswertung logischer Aussagen\n- Äquivalenz, Tautologien und Kontradiktionen\n- Aussagenformen und Quantoren (Allquantor, Existenzquantor)\n\nMengenlehre\n\n- Mengen und Teilmengen, Vereinigungs-, Schnitt- und Differenzmengen\n- Potenzmengen und kartesisches Produkt\n\nRelationen und Funktionen\n- Eigenschaften von Relationen: reflexiv, symmetrisch, transitiv, antisymmetrisch\n- Äquivalenzrelationen und Ordnungsrelationen\n- Eigenschaften von Funktionen: injektiv, surjektiv, bijektiv\n\nZahlentheorie (Grundlagen)\n\n- Teilbarkeit, größter gemeinsamer Teiler (ggT), kleinstes gemeinsames Vielfaches (kgV)\n- Primzahlen und der Euklidische Algorithmus\n- Primzahltests und der chinesische Restsatz\n\nGruppen und Körper\n- Modulo-Rechnung und Rechnen mit Restklassen\n- Endliche Körper und deren Struktur\n- Exponentiation in Restklassen\n\nBeweismethoden (optional)\n\n- Direkter Beweis\n- Indirekter Beweis durch Kontraposition und Widerspruch\n- Vollständige Induktion als strukturelles Beweisverfahren\n\n--- Literature (EN) ---\nWill be announced in the lecture\n\n--- Literature (DE) ---\nWird in der Veranstaltung bekannt gegeben", "metadata": {"moduleNumber": "D 3.4", "moduleName": "Discrete Mathematics", "creditPoints": "5.0", "suggestedSemester": 3, "offeredInSeason": "winter_semester", "examType": "written_exam", "heldInLanguage": "de", "reviserName": "", "reviserEmail": null, "studyProgramId": 14, "source_type": "json"}}
{"id": "BDAISY__D_5.2.2.", "text": "Title: Human-Computer Interaction\nModule Number: D 5.2.2.\nCredits: 5.0 CP\nSemester: 5\nOffered In: winter_semester\nLanguage: de\nExam Type: written_exam\nInstructor: Prof. Dr.-Ing. M.Sc. Markus Dahm\n\n--- Goals (EN) ---\nStudents can explain basic models and guidelines of HCI and their applicability. They can base technical and programatical properties on human physiology and psychology and can design interactive systems accordingly. Given tasks can be analysed, human computer actions can be appropriately designed for optimal usability comforming to HCI norms and models. Students can describe a user centered process for designing and implelmentation of interaktive applications. They can evaluate and optimize the usability of given interactive system, i.e. they can explain and assess their properties as well as give well founded advice for improvement.\n\n--- Goals (DE) ---\nStudierende können grundlegende Modelle und Richtlinien der MCI erklären und ihre Anwendbarkeit einordnen. Sie können technische und programmatische Eigenschaften von interaktiven Systemen auf physiologische und psychologische Merkmale des Menschen zurückführen und daraufhin optimieren. GegebeneAufgabenstellungen können analysiert, Mensch-ComputerInteraktionen entworfen und ihre Gestaltung anhand von MCINormen und Modellen begründet werden. Studierende können einenEntwicklungsprozess beschreiben, mit dem nutzerzentriert MCI-en entworfen werden. Sie können Interaktive Systeme bezüglich ihrer Usability anhand geeigneter Normen, Modelle und Richtlinien evaluieren und optimieren, d.h. sie können ihre Eigenschaften erklären und bewerten sowie fundierte Verbesserungsvorschläge machen.\n\n--- Contents (EN) ---\n- Basics, methods, models and concepts of the design of user interfaces for interactive applications\n- Physiological and psychological basics of human perception, memory, knowledge, experience plus action control; their application in HCI\n- Consequences of the design of hardware and software for the user\n- Models of communication and their application in HCI\n- Design of interactive systems, especially webbased and mobile systems: dialog, information architecture, navigation, orientation, interaction methods\n- Integration of usability engineering in software engineering, user centered design\n- Norms, legal requirements and guidelines\n- Basic concepts of UI programming\n\n--- Contents (DE) ---\n- Grundlagen, Methoden, Modelle und Konzepte zur Gestaltung von Benutzungsschnittstellen für interaktive Anwendungen.\n- Physiologische und Psychologische Grundlagen der Wahrnehmung, von Gedächtnis, Wissen, Erfahrung sowie der Handlungsregulation sowie Ihre Anwendung in der MCI\n- Konsequenzen der Gestaltung von Hardware und Software für Nutzer.\n- Modelle der Kommunikation und Anwendung auf die MCI\n- Gestaltung von interaktiven Systemen, insbesondere webbasierte Systeme: Dialoggestaltung, Informationsdarstellung, Navigation, Orientierung, Interaktionsformen\n- Integration von Software-Ergonomie in Software Engineering\n- Normen, gesetzliche Grundlagen und Richtlinien\n- Grundlagen der Programmierung von GUIs\n\n--- Literature (EN) ---\n- Markus Dahm: Grundlagen der Mensch-Computer-Interaktion, Pearson (2006)\n- Jens Jacobsen: Praxisbuch Usability und UX, Rheinwerk (2017)\n- Steve Krug: Don't make me think - revisited, New Riders (2013)\n- Bernhard Preim, Raimund Dachselt: Interaktive Systeme Band 1 und 2, eXamen.press\n- Don Norman: The Design of Everyday Things, Basic Books (2013)\n- Michael Richter, Markus D. Flückiger: Usability und UX kompakt: Produkte für Menschen (IT kompakt), Springer Vieweg (2016)\n\n--- Literature (DE) ---\n- Markus Dahm: Grundlagen der Mensch-Computer-Interaktion, Pearson (2006)\n- Jens Jacobsen: Praxisbuch Usability und UX, Rheinwerk (2017)\n- Steve Krug: Don't make me think - revisited, New Riders (2013)\n- Bernhard Preim, Raimund Dachselt: Interaktive Systeme Band 1 und 2, eXamen.press\n- Don Norman: The Design of Everyday Things, Basic Books (2013)\n- Michael Richter, Markus D. Flückiger: Usability und UX kompakt: Produkte für Menschen (IT kompakt), Springer Vieweg (2016)", "metadata": {"moduleNumber": "D 5.2.2.", "moduleName": "Human-Computer Interaction", "creditPoints": "5.0", "suggestedSemester": 5, "offeredInSeason": "winter_semester", "examType": "written_exam", "heldInLanguage": "de", "reviserName": "Prof. Dr.-Ing. M.Sc. Markus Dahm", "reviserEmail": "markus.dahm@hs-duesseldorf.de", "studyProgramId": 14, "source_type": "json"}}
{"id": "BDAISY__PF_1.6", "text": "Title: Fundamentals of Computer Graphics\nModule Number: PF 1.6\nCredits: 5.0 CP\nSemester: None\nOffered In: winter_semester\nLanguage: de\nExam Type: written_exam\nInstructor: Prof. Dr.-Ing. Sina Mostafawy\n\n--- Goals (EN) ---\nThe students know the basics of 3D computer graphics, the functionality of the graphics pipeline, local illumoination algorithms and shading techniques and can apply them.\n\n--- Goals (DE) ---\nDie Student:innen kennen die Grundlagen der 3D Computergrafik, die Funktionsweise der Grafikpipeline, lokale Beleuchtungsmodelle und Shading-Verfahren und können diese anwenden.\n\n--- Contents (EN) ---\nFixed Graphics Pipeline\nRasterization techniques\nClipping and Culling Algorithms\nMatrix Transformations  (2D/ 3D)\nOrthogonal and Perspective Projektion\nIllumination and Shading Algorithms \nBasics of Beziér interpolation\n\n--- Contents (DE) ---\nFixed Graphics Pipeline\nRasterization techniques\nClipping and Culling Algorithms\nMatrix Transformations  (2D/ 3D)\nOrthogonal and Perspective Projektion\nIllumination and Shading Algorithms \nBasics of Beziér interpolation\n\n--- Literature (EN) ---\n\n\n--- Literature (DE) ---\nComputer Graphics with OpenGL, D. Hearn, M.P. Baker, Pearson Education I\nAdvanced Animation and Rendering Techniques, Watt, M. Watt, Addison Wesley\nComputergrafik,Xiang, Zhigang; Plastock, Roy mitp/bhv\nFundamentals of Computer Graphics, Shirley P. \nAdvanced Global Illumination, P. Dutré, AK Peters", "metadata": {"moduleNumber": "PF 1.6", "moduleName": "Fundamentals of Computer Graphics", "creditPoints": "5.0", "suggestedSemester": null, "offeredInSeason": "winter_semester", "examType": "written_exam", "heldInLanguage": "de", "reviserName": "Prof. Dr.-Ing. Sina Mostafawy", "reviserEmail": "sina.mostafawy@hs-duesseldorf.de", "studyProgramId": 14, "source_type": "json"}}
