{"id": "BMI10", "text": "Title: Object-Oriented Programming 1\nModule Number: BMI 10\nCredits: 5.0 CP\nSemester: 1\nOffered In: winter_semester\nLanguage: de\nExam Type: written_exam\nInstructor: Prof. Dr.-Ing. M.Sc. Markus Dahm (markus.dahm@hs-duesseldorf.de)\n--- Goals (EN) ---\nStudents can analyse simple problems in a top-down and object-oriented manner. \nThey can derive a simple class model for the solution and develop object-orientated solution code.\nSolution concepts can be implemented in Java. \nThey can use the basics of an integrated development environment (IDE).\n--- Goals (DE) ---\nDie Studierenden können einfache Probleme Top-Down und objektorientiert analysieren. \nSie können zur Lösung ein einfaches Klassenmodell ableiten und objektorientierten Lösungscode entwickeln.\nLösungskonzepte können in Java implementiert werden. \nEine integrierte Entwicklungsumgebung (IDE) kann in Grundzügen angewendet werden.\n--- Contents (EN) ---\n-Basics of technology: Processor, Memory\n- Workflow Edit  Compile  RunVariables, primitive und reference-data types, strings, arrays\n- Controll structures: sequence, conditionals, loopsFunktions, prozedures, parameter\n- Basic concepts of objektorientierted programming (OOP): object, encapsulation, class, inheritance, polymorphismTechnical aspects of OOP: virtual maschine, message passing, constructors\n- Methodology: basics of object oriented analysis, top down method, divide and conquer\n--- Contents (DE) ---\n- Einfache technische Grundlagen: Prozessor, Arbeitsspeicher\n- Workflow Edit  Compile  Run  \n- Variable, Primitive und Referenz-Datentypen, Strings, Arrays\n- Kontrollstrukturen: Sequenz, Verzweigung, SchleifenFunktionen, Prozeduren, Parameter\n- Grundbegriffe der Objektorientierten Programmierung (OOP): Klasse, Objekt, Kapselung, Vererbung, Polymorphismus\n- Technische Aspekte der OOP: Virtuelle Maschine, Polymorphie, Message Passing, Konstruktoren\n- Vorgehensweise: Einfache Objektoriente Analyse, Top Down Vorgehensweise, Teile und Herrsche\n--- Literature (EN) ---\n- Java von Kopf bis Fuß, K. Sierra, B. Bates, O'Reilly\n- Handbuch der Java-Programmierung, G. Krüger, Addison-Wesley \n- www.javabuch.de\n- Sprechen Sie Java?, H Mössenböck, dpunkt\n- Programmieren mit Java, R. Schiedermeier, Pearson\n- https://docs.oracle.com/javase/tutorial/\n--- Literature (DE) ---\n- Java von Kopf bis Fuß, K. Sierra, B. Bates, O'Reilly\n- Handbuch der Java-Programmierung, G. Krüger, Addison-Wesley \n- www.javabuch.de\n- Sprechen Sie Java?, H Mössenböck, dpunkt\n- Programmieren mit Java, R. Schiedermeier, Pearson\n- https://docs.oracle.com/javase/tutorial/", "metadata": {"moduleNumber": "BMI 10", "moduleName": "Object-Oriented Programming 1", "creditPoints": "5.0", "suggestedSemester": 1, "offeredInSeason": "winter_semester", "examType": "written_exam", "heldInLanguage": "de", "reviserName": "Prof. Dr.-Ing. M.Sc. Markus Dahm", "reviserEmail": "markus.dahm@hs-duesseldorf.de", "studyProgramId": 8, "source_type": "json"}}
{"id": "BMI22", "text": "Title: Database Systems 1\nModule Number: BMI 22\nCredits: 5.0 CP\nSemester: 2\nOffered In: summer_semester\nLanguage: de\nExam Type: written_exam\nInstructor: Prof. Dr.-Ing. Thomas Rakow (thomas.rakow@hs-duesseldorf.de)\n--- Goals (EN) ---\nThe students know the properties of database systems and their application in media information technology. You will master the design of databases in the entity-relationship data model and their implementation in the relational Structured Query Language (SQL), taking into account data security, multi-user access and error recovery for applications of simple complexity. You understand the tasks of administering database management systems. The knowledge acquired can be applied in the following module Database Systems 2 as well as in a database-oriented module for IT project 2.\n--- Goals (DE) ---\nDie Studierenden kennen die Eigenschaften von Datenbanksystemen und deren Anwendung in der Medieninformatik. Sie beherrschen den Entwurf von Datenbanken im Entity-Relationship-Datenmodell und deren Implementierung in der relationalen Structured Query Language (SQL) unter Berücksichtigung von Datensicherheit, Mehrbenutzerzugriff und Fehlererholung (Recovery) für Anwendungen einfacher Komplexität. Sie verstehen die Aufgaben der Administration von Datenbankmanagementsystemen. Die erworbenen Kenntnisse können in dem nachfolgendem Modul Datenbanksysteme 2 sowie in einem datenbankorientierten Wahmodul für Informatikprojekt 2 angewendet werden.\n--- Contents (EN) ---\nProperties and application of database systems\nThe relational data model and the relation algebra\nProgramming databases in SQL: queries, updates and schema definition\nDatabase design with the entity-relationship model: modeling, mapping to relational schema, normalization\nTransaction concept in SQL with data privacy and access control\nResponsibilities of the database administrator\n--- Contents (DE) ---\nEigenschaften und Anwendung von Datenbanksystemen\nDas relationale Datenmodell und die Relationenalgebra\nProgrammierung von Datenbanken in SQL: Anfragen, Änderungen, Schemadefinition\nDatenbankentwurf mit dem Entity-Relationship-Modell: Modellierung, Abbildung auf Relationenschema, Normalisierung \nDas Transaktionskonzept in SQL mit Datenschutz sowie Zugriffskontrolle\nAufgaben des Datenbank-Administrators\n--- Literature (EN) ---\nLemahieu, W., Broucke, S.V., Baesens, B.: Principles of Database Management: The Practical Guide to Storing, Managing and Analyzing Big and Small Data. Cambridge University Press 2018\n--- Literature (DE) ---\nFaeskorn-Woyke, H. et al.: Datenbanksysteme  Theorie und Praxis mit SQL2003, Oracle und MySQL. Pearson Studium 2007.\nKemper, A, Eickler, A.: Datenbanksysteme, Eine Einführung, 10. Aufl. Oldenbourg München 2015.\nKline, K.: SQL in a Nutshell, 3rd Edition. O'Reilly 2009.\nKnolle, H. et al.: Datenbanksysteme - Eine praktische Einführung. Hanser 2024.\nKudraß, T.: Taschenbuch Datenbanken, 2. Auflage. Fachbuchverlag Leipzig 2015.\nLemahieu, W., Broucke, S.V., Baesens, B.: Principles of Database Management: The Practical Guide to Storing, Managing and Analyzing Big and Small Data. Cambridge University Press 2018\nOracle Corp.: Oracle Database SQL Reference.", "metadata": {"moduleNumber": "BMI 22", "moduleName": "Database Systems 1", "creditPoints": "5.0", "suggestedSemester": 2, "offeredInSeason": "summer_semester", "examType": "written_exam", "heldInLanguage": "de", "reviserName": "Prof. Dr.-Ing. Thomas Rakow", "reviserEmail": "thomas.rakow@hs-duesseldorf.de", "studyProgramId": 8, "source_type": "json"}}
{"id": "BMI13", "text": "Title: Web Programming 1\nModule Number: BMI 13\nCredits: 5.0 CP\nSemester: 1\nOffered In: winter_semester\nLanguage: de\nExam Type: written_exam\nInstructor: Prof. Dr. Manfred Wojciechowski (manfred.wojciechowski@hs-duesseldorf.de)\n--- Goals (EN) ---\nThe student understands the technical foundations of web applications and the separation between structure, design and behavior of web sites. They can apply those technologies for the implementation of static websites. They can also apply advanced technologies for the clientside adaption of websites regarding the diverse presentation constraints of different end devices. They are able the evaluate existing static websites regarding the quality of implementation.\n--- Goals (DE) ---\nDie Studierenden verstehen die technischen Grundlagen von Webanwendungen und die Trennung zwischen Struktur, Design und Verhalten von Webseiten. Sie können Technologien zur Realisierung statischer Webseiten sowie fortgeschrittene Techniken für die clientseitige Anpassung von Webseiten in Hinblick auf unterschiedliche Darstellungsanforderungen anwenden. Sie sind in. der Lage bestehende statische Webseiten bezüglich einer sauberen Realisierung zu bewerten.\n--- Contents (EN) ---\nweb application fundamentals (www, client-server-architecture, http); technologies for the realization of static web sites: structure and content (XML, HTML5); design (CSS3); scripting (ECMAScript 6+, DOM); advanced technologies for the adaption of representation requirements, e.g. responsive webdesign\n--- Contents (DE) ---\nGrundlagen von Webanwendungen (WWW, Client-Server, httpProtokoll)\nTechniken für die Realisierung von statischen Webseiten: Struktur und Inhalte (XML, HTML5)\nDesign (CSS3)\nVerhalten (ECMAScript 6, DOM)\nFortgeschrittene Techniken zur Adaption an Darstellungsanforderungen, z.B. Responsive Webdesign\n--- Literature (EN) ---\n- M. Wojciechowski: Vorlesungsskript zu Webprogrammierung\n- E. Robson, E. Freeman: HTML und CSS von Kopf bis Fuß, O'Reilly, 2013\n- E. Robson, E. Freeman: HTML5-Programmierung von Kopf bis Fuß: \n- Webanwendungen mit HTML5 und JavaScript, 2012\n- C. Zillgens: Responsive Webdesign, Hanser-Verlag, 2013\n- S. Münz, C. Gull: HTML5 Handbuch, Franzis Verlag, 2013\n--- Literature (DE) ---\n- M. Wojciechowski: Vorlesungsskript zu Webprogrammierung\n- E. Robson, E. Freeman: HTML und CSS von Kopf bis Fuß, O'Reilly, 2013\n- E. Robson, E. Freeman: HTML5-Programmierung von Kopf bis Fuß: \n- Webanwendungen mit HTML5 und JavaScript, 2012\n- C. Zillgens: Responsive Webdesign, Hanser-Verlag, 2013\n- S. Münz, C. Gull: HTML5 Handbuch, Franzis Verlag, 2013", "metadata": {"moduleNumber": "BMI 13", "moduleName": "Web Programming 1", "creditPoints": "5.0", "suggestedSemester": 1, "offeredInSeason": "winter_semester", "examType": "written_exam", "heldInLanguage": "de", "reviserName": "Prof. Dr. Manfred Wojciechowski", "reviserEmail": "manfred.wojciechowski@hs-duesseldorf.de", "studyProgramId": 8, "source_type": "json"}}
{"id": "BMI15", "text": "Title: Media Design 1\nModule Number: BMI 15\nCredits: 5.0 CP\nSemester: 1\nOffered In: winter_semester\nLanguage: de\nExam Type: portfolio\nInstructor: Prof. Gabriele Schwab-Trapp (gabi.schwab-trapp@hs-duesseldorf.de)\n--- Goals (EN) ---\nStudents understand the essential criteria of design and can apply basic theoretical and practical vocabulary for tasks in the field of visual design. They are able to independently develop and visualise design tasks using analogue and digital design tools and apply basic design and creative techniques.\n--- Goals (DE) ---\nDie Studierenden verstehen wesentliche Kriterien der Gestaltung und können theoretisches und praktisches Grundlagenvokabular für Aufgaben im Bereich der visuellen Gestaltung anwenden. Sie sind in der Lage eigenständig gestalterische Aufgabenstellungen mit analogen und digitalen Entwurfswerkzeugen zu entwickeln und zu visualisieren, sowie grundlegende Entwurfs- und Kreativtechniken anzuwenden.\n--- Contents (EN) ---\nIntroduction to visual communication and promotion of artistic representation skills through practical and artistic basic exercises, as well as the development of creative awareness through the systematic, theoretical and sensual examination of design.  \n\n- Design basics: colour, form, composition\n- Basic design and creativity techniques\n- Research, analysis, presentation, documentation\n- Introduction to various visual techniques of representation and presentation\n--- Contents (DE) ---\nEinführung in die visuelle Kommunikation und Förderung der bildnerischen Darstellungsfähigkeit durch praktisch-bildnerische Grundlagenübungen, sowie die Entwicklung eines gestalterischen Bewusstseins durch die systematische, theoretische und sinnliche Auseinandersetzung mit Gestaltung.  \n\n- Gestaltungsgrundlagen Farbe, Form, Komposition\n- Grundlegende Entwurfs- und Kreativitätstechniken\n- Recherche, Analyse, Präsentation, Dokumentation\n- Einführung in verschiedene bildnerische Darstellungs- und Präsentationstechniken\n--- Literature (EN) ---\nLists of materials and literature are issued each semester in the seminar. The respective learning, realisation and design steps are supported by references in the form of text excerpts, literature, image examples and research suggestions. There is also a detailed oral introduction.\n--- Literature (DE) ---\nMaterial- und Literaturlisten werden jedes Semester aktuell im Seminar ausgegeben. Die jeweiligen Lern-, Erkenntnis- und Gestaltungsschritte werden unterstützt durch Hinweise in Form von Textauszügen, Literatur, Bildbeispielen und Recherchevorschlägen. Zudem erfolgt eine ausführliche mündliche Einführung.", "metadata": {"moduleNumber": "BMI 15", "moduleName": "Media Design 1", "creditPoints": "5.0", "suggestedSemester": 1, "offeredInSeason": "winter_semester", "examType": "portfolio", "heldInLanguage": "de", "reviserName": "Prof. Gabriele Schwab-Trapp", "reviserEmail": "gabi.schwab-trapp@hs-duesseldorf.de", "studyProgramId": 8, "source_type": "json"}}
{"id": "BMI11", "text": "Title: Mathematics Basics\nModule Number: BMI 11\nCredits: 5.0 CP\nSemester: 1\nOffered In: winter_semester\nLanguage: de\nExam Type: written_exam\nInstructor: None Jörg Becker-Schweitzer (jbs@hs-duesseldorf.de)\n--- Goals (EN) ---\nStudents gain a comprehensive understanding of mathematical concepts and their application. They refresh their knowledge of basic mathematics and deepen their understanding of mathematical concepts such as propositional logic, set theory, relations and functions. In addition, they are introduced to predicate logic and develop a deep understanding of modular arithmetic. The course also covers important topics such as vector calculus, analytic geometry and linear algebra. Finally, students are introduced to differential and integral calculus and learn their basic techniques and applications.\n--- Goals (DE) ---\nDie Studierenden erlangen ein umfassendes Verständnis mathematischer Konzepte und deren Anwendung. Sie frischen ihre Kenntnisse im mathematischen Grundwissen auf und vertiefen ihr Verständnis in mathematischen Konzepten wie der Aussagenlogik, Mengenlehre, Relationen und Funktionen. Darüber hinaus werden sie in die Prädikatenlogik eingeführt und entwickeln ein tiefes Verständnis für modulare Arithmetik. Der Kurs umfasst auch wichtige Themen wie Vektorrechnung, analytische Geometrie und lineare Algebra. Schließlich werden die Studierenden in die Differential- und Integralrechnung eingeführt und lernen deren grundlegende Techniken und Anwendungen kennen.\n--- Contents (EN) ---\n- Repetition of basic mathematical knowledge\n- External logic and set theory\n- Relations and functions\n- Predicate logic\n- Mathematical proof\n- Modular arithmetic\n- Vector calculus\n- Analytical geometry\n- Linear algebra\n- Differential and integral calculus\n--- Contents (DE) ---\n- Wiederholung mathematischen Grundwissens\n- Aussageenlogik und Mengenlehre\n- Relationen und Funktionen\n- Prädikatenlogik\n- Beweisführung\n- Modulare Arithmetik\n- Vektorrechnung\n- Analytische Geometrie\n- Lineare Algebra\n- Differenzial- und Integralrechnung\n--- Literature (EN) ---\n- J. Koch, M. Stämpfle: Mathematik für das Ingenieurstudium, 3. Auflage, Hanser Verlag, 2015\n- R. Socher: Mathematik für Informatiker, Hanser Verlag, 2011\n- M. Brill: Mathematik für Informatiker, Hanser Verlag 2005\n- K. Kiyek, F. Schwarz: Mathematik für Informatiker, 2 Bände, Teubner Verlag 1999\n- P. Stingl: Mathematik für Fachhochschulen, Technik und Informatik, Hanser Verlag 1998\n- L. Papula: Mathematik für Ingenieure und Naturwissenschaftler, 3 Bände, Vieweg Verlag 2004\n- T. Westermann: Mathematik für Ingenieure mit Maple, 2 Bände, Springer Verlag 2004\n- Maple 9.5 Programming Guide 2005\n--- Literature (DE) ---\n- J. Koch, M. Stämpfle: Mathematik für das Ingenieurstudium, 3. Auflage, Hanser Verlag, 2015\n- R. Socher: Mathematik für Informatiker, Hanser Verlag, 2011\n- M. Brill: Mathematik für Informatiker, Hanser Verlag 2005\n- K. Kiyek, F. Schwarz: Mathematik für Informatiker, 2 Bände, Teubner Verlag 1999\n- P. Stingl: Mathematik für Fachhochschulen, Technik und Informatik, Hanser Verlag 1998\n- L. Papula: Mathematik für Ingenieure und Naturwissenschaftler, 3 Bände, Vieweg Verlag 2004\n- T. Westermann: Mathematik für Ingenieure mit Maple, 2 Bände, Springer Verlag 2004\n- Maple 9.5 Programming Guide 2005", "metadata": {"moduleNumber": "BMI 11", "moduleName": "Mathematics Basics", "creditPoints": "5.0", "suggestedSemester": 1, "offeredInSeason": "winter_semester", "examType": "written_exam", "heldInLanguage": "de", "reviserName": "None Jörg Becker-Schweitzer", "reviserEmail": "jbs@hs-duesseldorf.de", "studyProgramId": 8, "source_type": "json"}}
{"id": "BMI20", "text": "Title: Object Oriented Programming 2\nModule Number: BMI 20\nCredits: 5.0 CP\nSemester: 2\nOffered In: winter_semester\nLanguage: de\nExam Type: written_exam\nInstructor: Prof. Dr.-Ing. M.Sc. Markus Dahm (markus.dahm@hs-duesseldorf.de)\n--- Goals (EN) ---\nStudents are able to identify, plan, implement and use generic data structures and collections to solve given tasks. They master the basics of input/output concepts and exception handling, can identify requirements in this regard and plan, implement and use fitting solutions. The know the basics of concurrency. The know important classes of the Java API for all these areas and know how to use them. To build basic and intermediate OO models they can use basic UML and software design patterns.\n--- Goals (DE) ---\nDie Studierenden können zusammengesetzte und generische Datenstrukturen zur Lösung von Aufgaben einsetzen. Sie beherrschen die Grundlagen des I/O und der Ausnahmebehandlung. Sie kennen die Grundkonzepte nebenläufiger Programmierung. Sie kennen die wichtigsten dazugehörigen Klassen des Java-APIs und können sie einsetzen. Zur Modellierung können sie UML und Entwurfsmuster einsetzen.\n--- Contents (EN) ---\n- Collections, data structures: list, tree and operations thereof, iterators, implementation in Java\n- Selected classes of the Java collection API\n- Generic data types and their usage in Java\n- Exeption handling, concepts and implementarion in Java\n- Stream concept for input/output\n- Selected classes of the Java I/O API\n- Concepts of concurrency and implementartion in Java\n- Basics of UML, selected diagrams\n- Introduction to software design pattens\n- Introduction to a debugging tool\n--- Contents (DE) ---\n- Zusammengesetzte Datenstrukturen: Listen, Bäume und ihre Operationen, Iteratoren\n- Ausgewählte Klassen des Java-Collection-APIs\n- Generische Datentypen und ihre Anwendung in Java\n- Ausnahmebehandlung mit Exceptions und Anwendung in Java\n- Das Stream-Konzept für Input/Output\n- Ausgewählte Klassen des Java-IO-APIs\n- Konzepte der Nebenläufigkeit und Umsetzung mit Java-Threads\n- Grundlagen von UML, die wichtigsten Diagramme\n- Software Entwurfsmuster\n- Einführung in einen Debugger\n--- Literature (EN) ---\n- K. Sierra, B. Bates: Java von Kopf bis Fuß, O'Reilly\n- G. Krüger: Handbuch der Java-Programmierung, Addison Wesley \n- www.javabuch.de\n- H Mössenböck: Sprechen Sie Java?, dpunkt\n- R. Schiedermeier: Programmieren mit Java, Pearson\n- https://docs.oracle.com/javase/tutorial/\n--- Literature (DE) ---\n- K. Sierra, B. Bates: Java von Kopf bis Fuß, O'Reilly\n- G. Krüger: Handbuch der Java-Programmierung, Addison Wesley \n- www.javabuch.de\n- H Mössenböck: Sprechen Sie Java?, dpunkt\n- R. Schiedermeier: Programmieren mit Java, Pearson\n- https://docs.oracle.com/javase/tutorial/", "metadata": {"moduleNumber": "BMI 20", "moduleName": "Object Oriented Programming 2", "creditPoints": "5.0", "suggestedSemester": 2, "offeredInSeason": "winter_semester", "examType": "written_exam", "heldInLanguage": "de", "reviserName": "Prof. Dr.-Ing. M.Sc. Markus Dahm", "reviserEmail": "markus.dahm@hs-duesseldorf.de", "studyProgramId": 8, "source_type": "json"}}
{"id": "BMI32", "text": "Title: Database Systems 2\nModule Number: BMI 32\nCredits: 5.0 CP\nSemester: 3\nOffered In: winter_semester\nLanguage: de\nExam Type: written_exam\nInstructor: Prof. Dr.-Ing. Thomas Rakow (thomas.rakow@hs-duesseldorf.de)\n--- Goals (EN) ---\nStudents can develop database systems for applications in media information technology with simple to medium complexity. You will master the design of databases in the Unified Modeling Language (UML) using class diagrams and their implementation in the Structured Query Language (SQL) using stored procedures. The architecture of database management systems in the 5-layer model of Interfaces and structures as well as query processing and persistent storage can be classified and evaluated. Database applications in the elective subjects Media Project A/B, the specializations A/B/C/D Catalog A as well as Individual, the scientific specialization and the bachelor's thesis can be analyzed and developed.\n--- Goals (DE) ---\nDie Studierenden können Datenbanksysteme für Anwendungen in der Medieninformatik mit einfacher bis mittlerer Komplexität entwickeln. Sie beherrschen dabei den Entwurf von Datenbanken in der Unified Modeling Language (UML) mittels Klassendiagramm und deren Implementierung in der Structured Query Language (SQL) auch mit Stored Procedures. Die Architektur von Datenbankmanagementsystemen im 5-Schichten-Modell mit Schnittstellen und Strukturen sowie die Anfrageverarbeitung und die persistente Speicherung können eingeordnet und bewertet werden. Datenbank-Anwendungen in den Wahlpflichtfächern Medienprojekt A/B, den Vertiefungen A/B/C/D Katalog A sowie Individuell,  der wissenschaftlichen Vertiefung und der Bachelorarbeit können analysiert und entwickelt werden.\n--- Contents (EN) ---\nDatabase design using UML class diagram and mapping to relational database management systems (DBMS)\nApplication programming of DBMS\n- Procedural concepts in SQL using Oracle (PL/SQL) as a model\n- Object-relational concepts of SQL using Oracle as a model\n- Procedural interfaces (Java) and OR mappers\n- optional: script interfaces (PHP)\n- Web databases\n- NoSQL databases\nLayered architecture of database systems\n- Buffer and secondary storage management (RAID)\n- Storage structures and indexes in SQL\n- Query processing and optimization\n- Transaction management\n--- Contents (DE) ---\nDatenbankentwurf mittels UML-Klassendiagramm und Abbildung auf relationale Datenbankmanagementsysteme (DBMS)\nAnwendungsprogrammierung von DBMS\n- Prozedurale Konzepte in SQL am Beispiel Oracle (PL/SQL)\n- Objektrelationale Konzepte von SQL am Beispiel Oracle\n- Prozedurale Schnittstellen (Java) und OR-Mapper\n- optional: Skript-Schnittstellen (PHP)\n- Web-Datenbanken\n- NoSQL-Datenbanken\nSchichtenarchitektur von Datenbanksystemen\n- Puffer- und Sekundärspeicherverwaltung (RAID)\n- Speicherungsstrukturen und Indexe in SQL\n- Queryverarbeitung und -optimierung\n- Transaktionsverwaltung\n--- Literature (EN) ---\nLemahieu, W., Broucke, S.V., Baesens, B.: Principles of Database Management: The Practical Guide to Storing, Managing and Analyzing Big and Small Data. Cambridge University Press 2018\n--- Literature (DE) ---\nLiteratur aus  Datenbanksysteme 1 plus\nHärder, T., Rahm, E.: Datenbanksysteme  Konzepte und Techniken der Implementierung. Springer 2001. \nRakow, T.: Datenbanken im Web. In: Kudraß, T.: Taschenbuch Datenbanken, Hanser 2015\nStörl, U.: NoSQL-Datenbanksysteme. In: Kudraß, T.: Taschenbuch Datenbanken, Hanser 2015\nOestereich, B.: Analyse und Design mit der UML 2.5. Oldenbourg 2012", "metadata": {"moduleNumber": "BMI 32", "moduleName": "Database Systems 2", "creditPoints": "5.0", "suggestedSemester": 3, "offeredInSeason": "winter_semester", "examType": "written_exam", "heldInLanguage": "de", "reviserName": "Prof. Dr.-Ing. Thomas Rakow", "reviserEmail": "thomas.rakow@hs-duesseldorf.de", "studyProgramId": 8, "source_type": "json"}}
{"id": "BMI24", "text": "Title: Informatics Project 1\nModule Number: BMI 24\nCredits: 5.0 CP\nSemester: 2\nOffered In: summer_semester\nLanguage: en_on_demand\nExam Type: project\nInstructor: Prof. Dr.-Ing. Thomas Rakow (thomas.rakow@hs-duesseldorf.de)\n--- Goals (EN) ---\nStudents are familiar with the exemplified software development process in a team. They can coordinate their part of the project in the team with the support of the project manager (lecturer) using software development procedures.\n--- Goals (DE) ---\nDie Studierenden kennen exemplarisch den Ablauf der Softwareentwicklung in einem Team. Sie können ihren Anteil an dem Projekt im Team mit Unterstützung des Projektleiters (Dozentin oder Dozent) unter Verwendung eines Softwareentwicklungsvorgehens koordinieren.\n--- Contents (EN) ---\nPractical work in:\n\tCoordination in the project team\n\tUtilisation of a software development environment\n\tprogramming\n\tPresentation and review\nThe task of the project is to develop a programme, for example from the following range:\n\tComputer game\n\tDatabases\n\tE-learning\n\tWebsite\n--- Contents (DE) ---\nPraktische Arbeiten in:\n\tKoordination im Projektteam\n\tNutzung einer Softwareentwicklungsumgebung\n\tProgrammierung\n\tPräsentation und Rückblick\nDie Aufgabenstellung des Projektes ist die Entwicklung eines Programms, beispielsweise jeweils aus folgendem Angebot:\n\tComputer-Spiel\n\tDatenbanken\n\tE-Learning\n\tWebseite\n--- Literature (EN) ---\n--- Literature (DE) ---\nHelmut Herold, Bruno Lutz, Martin Lutz, Jürgen Wohlrab: Grundlagen der Informatik, 4. Aufl. Pearson 2023 \nJim Benson, Tonianne DeMaria Barry: Personal Kanban, Dpunkt 2013. \nBernd Oestereich: Analyse und Design mit der UML 2.5. Oldenbourg 2013. \nPeter Farbig: Objektorientierte Softwareentwicklung mit UML, 4. Aufl. Hanser 2024. \nWeitere Literatur zur Aufgabenstellung des gewählten Projekts", "metadata": {"moduleNumber": "BMI 24", "moduleName": "Informatics Project 1", "creditPoints": "5.0", "suggestedSemester": 2, "offeredInSeason": "summer_semester", "examType": "project", "heldInLanguage": "en_on_demand", "reviserName": "Prof. Dr.-Ing. Thomas Rakow", "reviserEmail": "thomas.rakow@hs-duesseldorf.de", "studyProgramId": 8, "source_type": "json"}}
{"id": "BMI25", "text": "Title: Media Design Basics 2\nModule Number: BMI 25\nCredits: 5.0 CP\nSemester: 2\nOffered In: summer_semester\nLanguage: de\nExam Type: portfolio\nInstructor: Prof. Gabriele Schwab-Trapp (gabi.schwab-trapp@hs-duesseldorf.de)\n--- Goals (EN) ---\nStudents are enabled to independently solve design tasks with a conceptual approach. They are practised in dealing with different design methods and in the application of design processes: \n\n- Research and conception\n- Design and realisation\n- Presentation and documentation\n--- Goals (DE) ---\nDie Studierenden werden befähigt, Gestaltungsaufgaben mit konzeptionellem Ansatz selbstständig zu lösen. Sie sind geübt im Umgang mit unterschiedliche Entwurfsmethoden und in der Anwendung von Gestaltungsprozessen: \n\n- Recherche und Konzeption\n- Entwurf und Umsetzung\n- Präsentation und Dokumentation\n--- Contents (EN) ---\nConsolidation of the content of the Media Design 1 module, extended by the introduction to conceptual and creative work. Students are introduced to the realisation and independent development of context-related, visual concepts in print and online media:\n\n- Consolidation of the content of the Media Design 1 module\n- Fundamentals of visual communication in theory and practice\n- Development and realisation of visual concepts\n--- Contents (DE) ---\nVertiefung der Inhalte des Moduls Mediengestaltung 1, erweitert durch die Einführung in konzeptionell-gestalterisches Arbeiten. Die Studierenden werden an die Umsetzung und die selbständige Entwicklung von kontextbezogenen, visuellen Konzepten in Print- und Onlinemedien herangeführt:\n\n- Vertiefung der Inhalte des Moduls Mediengestaltung 1\n- Grundlagen der visuellen Kommunikation in Theorie und Praxis\n- Entwicklung und Umsetzung visueller Konzepte\n--- Literature (EN) ---\nLists of materials and literature are issued each semester in the seminar. The respective learning, realisation and design steps are supported by references in the form of text excerpts, literature, image examples and research suggestions. There is also a detailed oral introduction.\n--- Literature (DE) ---\nMaterial- und Literaturlisten werden jedes Semester aktuell im Seminar ausgegeben. Die jeweiligen Lern-, Erkenntnis- und Gestaltungsschritte werden unterstützt durch Hinweise in Form von Textauszügen, Literatur, Bildbeispielen und Recherchevorschlägen. Zudem erfolgt eine ausführliche mündliche Einführung.", "metadata": {"moduleNumber": "BMI 25", "moduleName": "Media Design Basics 2", "creditPoints": "5.0", "suggestedSemester": 2, "offeredInSeason": "summer_semester", "examType": "portfolio", "heldInLanguage": "de", "reviserName": "Prof. Gabriele Schwab-Trapp", "reviserEmail": "gabi.schwab-trapp@hs-duesseldorf.de", "studyProgramId": 8, "source_type": "json"}}
{"id": "BMI30", "text": "Title: Software Engineering\nModule Number: BMI 30\nCredits: 5.0 CP\nSemester: 3\nOffered In: winter_semester\nLanguage: de\nExam Type: written_exam\nInstructor: Prof. Dr. Thomas Franz (thomas.franz@hs-duesseldorf.de)\n--- Goals (EN) ---\nStudents know selected concepts, methods, practices and tools applied in professional software engineering. They can utilize and apply these to solve small software engineering tasks, e.g. documenting requirements, applying automated build management, develop continuous integration pipelines, create clean code, create different architectural views, create, share, and execute software containers.\n--- Goals (DE) ---\nDie Studierenden kennen Konzepte, Methoden, Praktiken und Werkzeuge zur professionellen Entwicklung von Software im Team und deren Betrieb. Die Studierenden können diese in Software-Entwicklungsprojekten mit gängigen Werkzeugen umsetzen und anwenden (u.a. Dokumentation von Anforderungen, Realisierung eines automatischen Build-Managements, Entwicklung von CI-Pipelines, Erzeugung von \"Clean Code\", Erstellung, Verteilung und Ausführung von Software-Containern.\n--- Contents (EN) ---\nCore-Disciplines of Software Engineering:\n- Requirements Engineering\n- Software Architecture\n- Clean Code Principles\n- Software-Testing, Test-Coverage\n- Operation, Deployment, and Maintenance, specificially Software Containers\n\nCross-sectional topics: \n- Configuration management\n- Continuous Integration\n- Automated Build-Management\n- Software Engineering process models (specifically agile approaches, e.g. SCRUM)\n--- Contents (DE) ---\nKern-Disziplinen des Software Engineerings:\n- Requirements Engineering\n- Software Architektur, insbesondere Kontextabgrenzung, Bausteinsicht, Laufzeitsicht, Verteilungs-Sicht\n- Implementierung nach Clean Code Prinzipien\n- Qualitätssicherung, insbesondere Software-Tests, Überdeckungsmetriken\n- Betrieb und Wartung, insbesondere Software-Container\n\nQuerschnittsthemen: \n- Konfigurationsmanagement\n- Continuous Integration\n- Automatisches Build-Management\n- Vorgehensmodelle des Software Engineering (klassische\nund insbesondere agile Vorgehensmodelle)\n--- Literature (EN) ---\n--- Literature (DE) ---\nHOFFMANN, Dirk W., 2008. Software-Qualität [online]. Berlin, Heidelberg: Springer-Verlag Berlin Heidelberg. ISBN 9783540763239. Verfügbar unter: https://doi.org/10.1007/978-3-540-76323-9\n\nSTARKE, Gernot und Peter HRUSCHKA, 2011. Software-Architektur kompakt:  angemessen und zielorientiert [online]. 2. Heidelberg: Spektrum Akademischer Verlag. ISBN 9783827428356. Verfügbar unter: https://doi.org/10.1007/978-3-8274-2835-6\n\nMATTHIAS, Karl, Sean KANE und Thomas DEMMIG, 2023. Praxiswissen Docker: Grundlagen und Best Practices für das Deployen von Software mit Containern. (Übersetzung der 3. Auflage). Heidelberg: OReilly Verlag. ISBN 9783960108320\n\nSchwaber, K. and Sutherland, J. (2020) The Scrum Guide - The Definitive Guide to Scrum: The Rules of the Game. www.scrum.org", "metadata": {"moduleNumber": "BMI 30", "moduleName": "Software Engineering", "creditPoints": "5.0", "suggestedSemester": 3, "offeredInSeason": "winter_semester", "examType": "written_exam", "heldInLanguage": "de", "reviserName": "Prof. Dr. Thomas Franz", "reviserEmail": "thomas.franz@hs-duesseldorf.de", "studyProgramId": 8, "source_type": "json"}}
{"id": "BMI21", "text": "Title: Formal Models and Algorithms\nModule Number: BMI 21\nCredits: 5.0 CP\nSemester: 2\nOffered In: summer_semester\nLanguage: de\nExam Type: written_exam\nInstructor: Prof. Dr. rer. nat. Christian Geiger (geiger@hs-duesseldorf.de)\n--- Goals (EN) ---\nThe students can formulate typical problems in computer science (searching, sorting, etc.) and provide solution strategies. They are familiar with the most important algorithms and procedures in the design of algorithms and can analyze the developed solutions. At the same time, the participants are familiar with typical data structures of computer science and can specify and use them when formulating algorithms. Participants can understand typical problems of (media) computer science and develop solutions that they implement in a suitable programming language (eg Java, Processing).\n--- Goals (DE) ---\nDie Teilnehmer können typische Probleme in der Informatik (Suchen, Sortieren, etc.) formulieren und Lösungsstrategien dafür angeben. Sie kennen die in der Informatik wichtigsten Algorithmen und Vorgehensweisen beim Entwurf von Algorithmen und können die entwickelten Lösungen analysieren. Gleichzeitig kennen die Teilnehmer typische Datenstrukturen der Informatik und können diese bei der Formulierung von Algorithmen spezifizieren und einsetzen. Die Teilnehmer können typische Probleme der (Medien-)Informatik verstehen und dafür Lösungen entwickeln, die sie in einer geeigneten Programmiersprache (z. B. Python) realisieren.\n--- Contents (EN) ---\nBasic terms / definitions of algorithms, specification and effort estimationIteration and recursionSearch & SortAbstract data structures and formal models (snake, cellar, set, tree, graph)Algorithms for graphs and treesSelected Computer Problems and Typical Solutions (Divide & Conquer, Backtracking, Greedy, Branch & Bound, Dynamic Programming)\n--- Contents (DE) ---\nGrundlegende Begriffe / Definitionen zu Algorithmen, Spezifikation und Aufwandsabschätzung, \n-Iteration und Rekursion, Suchen & Sortieren, Abstrakte Datenstrukturen (Schlange, Keller, Set, Baum, Graph), \n- Algorithmen für Graphen und Bäumen, \n- Ausgewählte Probleme der Informatik und typische Lösungsprinzipien (Divide & Conquer, Backtracking, Greedy, Branch & Bound, Dynamisches Programmieren)\n--- Literature (EN) ---\n--- Literature (DE) ---\nPrimärliteratur: \n- D. Logofâtu. Grundlegende Algorithmen mit Java, 2. Auflage, Springer Vieweg, 2014B. \n- Vöcking et al: Taschenbuch der Algorithmen, Springer Verlag, 1. Auflage, 2008\n- Hans Werner Lang, Algorithmen in Java, 2. Auflage, Vieweg, \n\nSekundärliteratur: \n- G. Pomberger, H Dobler. Algorithmen und Datenstrukturen, Pearson Studium, 2008\n- A. Beutelspacher. Diskrete Mathematik für Einsteiger, 4. Auflage, Vieweg Studium, 2011\n- S. Skiena. The Algorithm Design Manual. Springer VerlagR. Sedgewick: Algorithms in Java, Part 1-4, Addison Wesley", "metadata": {"moduleNumber": "BMI 21", "moduleName": "Formal Models and Algorithms", "creditPoints": "5.0", "suggestedSemester": 2, "offeredInSeason": "summer_semester", "examType": "written_exam", "heldInLanguage": "de", "reviserName": "Prof. Dr. rer. nat. Christian Geiger", "reviserEmail": "geiger@hs-duesseldorf.de", "studyProgramId": 8, "source_type": "json"}}
{"id": "BMI34", "text": "Title: Informatics Project 2\nModule Number: BMI 34\nCredits: 5.0 CP\nSemester: 3\nOffered In: winter_semester\nLanguage: en_on_demand\nExam Type: project\nInstructor: Prof. Dr.-Ing. Thomas Rakow (thomas.rakow@hs-duesseldorf.de)\n--- Goals (EN) ---\nOn a second informatics project the students know the course of program development in a team. They can plan and independently coordinate their share of team development with the support of the project leader (lecturer).\n--- Goals (DE) ---\nDie Studierenden kennen exemplarisch den Ablauf der Softwareentwicklung in einem Team. Sie können ihren Anteil an dem Projekt im Team mit Unterstützung des Projektleiters (Dozentin oder Dozent) unter Verwendung eines Softwareentwicklungsvorgehens koordinieren.  Die Studierenden können Ziele des Projekts und Anforderungen an die Software diskutieren, dokumentieren und Entwicklungsaufgaben daraus ableiten, planen und umsetzen.\n--- Contents (EN) ---\nConsolidation of the contents of the module Informatics Project 1, extended by the determination of requirements and tasks. Practical work in:\n\tCoordination in the project team\n\tUse of a software development environment\n\tDetermining requirements and development tasks\n\tProgramming\n\tPresentation and review\nThe task of the project is to develop a programme, for example from the following range:\n\tComputer game\n\tDatabase for media\n\tE-learning \nWebsite\nThe task can be based on programme developments from Informatics Project 1.\n--- Contents (DE) ---\nVertiefung der Inhalte des Moduls Informatikprojekt 1, erweitert durch die Anforderungs- und Aufgabenermittlung. Praktische Arbeiten in:\n\tKoordination im Projektteam\n\tNutzung einer Softwareentwicklungsumgebung\n\tErmitteln von Anforderungen und Entwicklungsaufgaben\n\tProgrammierung\n\tPräsentation und Rückblick\nDie Aufgabenstellung des Projektes ist die Entwicklung eines Programms, beispielsweise jeweils aus folgendem Angebot:\n\tComputer-Spiel\n\tDatenbank für Medien\n\tE-Learning \n\tWebseite\nDie Aufgabenstellung kann auf Programmentwicklungen aus dem Informatikprojekt 1 aufbauen.\n--- Literature (EN) ---\n--- Literature (DE) ---\nHelmut Herold, Bruno Lutz, Martin Lutz, Jürgen Wohlrab: Grundlagen der Informatik, 4. Aufl. Pearson 2023 \nJim Benson, Tonianne DeMaria Barry: Personal Kanban, Dpunkt 2013. \nBernd Oestereich: Analyse und Design mit der UML 2.5. Oldenbourg 2013. \nPeter Farbig: Objektorientierte Softwareentwicklung mit UML, 4. Aufl. Hanser 2024. \nWeitere Literatur zur Aufgabenstellung des gewählten Projekts", "metadata": {"moduleNumber": "BMI 34", "moduleName": "Informatics Project 2", "creditPoints": "5.0", "suggestedSemester": 3, "offeredInSeason": "winter_semester", "examType": "project", "heldInLanguage": "en_on_demand", "reviserName": "Prof. Dr.-Ing. Thomas Rakow", "reviserEmail": "thomas.rakow@hs-duesseldorf.de", "studyProgramId": 8, "source_type": "json"}}
{"id": "BMI35", "text": "Title: Human-Computer Interaction\nModule Number: BMI 35\nCredits: 5.0 CP\nSemester: 3\nOffered In: winter_semester\nLanguage: de\nExam Type: written_exam\nInstructor: Prof. Dr.-Ing. M.Sc. Markus Dahm (markus.dahm@hs-duesseldorf.de)\n--- Goals (EN) ---\nStudents can explain basic models and guidelines of HCI and their applicability. They can base technical and programatical properties on human physiology and psychology and can design interactive systems accordingly. Given tasks can be analysed, human computer actions can be appropriately designed for optimal usability comforming to HCI norms and models. Students can describe a user centered process for designing and implelmentation of interaktive applications. They can evaluate and optimize the usability of given interactive system, i.e. they can explain and assess their properties as well as give well founded advice for improvement.\n--- Goals (DE) ---\nStudierende können grundlegende Modelle und Richtlinien der MCI erklären und ihre Anwendbarkeit einordnen. Sie können technische und programmatische Eigenschaften von interaktiven Systemen auf physiologische und psychologische Merkmale des Menschen zurückführen und daraufhin optimieren. GegebeneAufgabenstellungen können analysiert, Mensch-ComputerInteraktionen entworfen und ihre Gestaltung anhand von MCINormen und Modellen begründet werden. Studierende können einenEntwicklungsprozess beschreiben, mit dem nutzerzentriert MCI-en entworfen werden. Sie können Interaktive Systeme bezüglich ihrer Usability anhand geeigneter Normen, Modelle und Richtlinien evaluieren und optimieren, d.h. sie können ihre Eigenschaften erklären und bewerten sowie fundierte Verbesserungsvorschläge machen.\n--- Contents (EN) ---\n- Basics, methods, models and concepts of the design of user interfaces for interactive applications\n- Physiological and psychological basics of human perception, memory, knowledge, experience plus action control; their application in HCI\n- Consequences of the design of hardware and software for the user\n- Models of communication and their application in HCI\n- Design of interactive systems, especially webbased and mobile systems: dialog, information architecture, navigation, orientation, interaction methods\n- Integration of usability engineering in software engineering, user centered design\n- Norms, legal requirements and guidelines\n- Basic concepts of UI programming\n--- Contents (DE) ---\n- Grundlagen, Methoden, Modelle und Konzepte zur Gestaltung von Benutzungsschnittstellen für interaktive Anwendungen.\n- Physiologische und Psychologische Grundlagen der Wahrnehmung, von Gedächtnis, Wissen, Erfahrung sowie der Handlungsregulation sowie Ihre Anwendung in der MCI\n- Konsequenzen der Gestaltung von Hardware und Software für Nutzer.\n- Modelle der Kommunikation und Anwendung auf die MCI\n- Gestaltung von interaktiven Systemen, insbesondere webbasierte Systeme: Dialoggestaltung, Informationsdarstellung, Navigation, Orientierung, Interaktionsformen\n- Integration von Software-Ergonomie in Software Engineering\n- Normen, gesetzliche Grundlagen und Richtlinien\n- Grundlagen der Programmierung von GUIs\n--- Literature (EN) ---\n- Markus Dahm: Grundlagen der Mensch-Computer-Interaktion, Pearson (2006)\n- Jens Jacobsen: Praxisbuch Usability und UX, Rheinwerk (2017)\n- Steve Krug: Don't make me think - revisited, New Riders (2013)\n- Bernhard Preim, Raimund Dachselt: Interaktive Systeme Band 1 und 2, eXamen.press\n- Don Norman: The Design of Everyday Things, Basic Books (2013)\n- Michael Richter, Markus D. Flückiger: Usability und UX kompakt: Produkte für Menschen (IT kompakt), Springer Vieweg (2016)\n--- Literature (DE) ---\n- Markus Dahm: Grundlagen der Mensch-Computer-Interaktion, Pearson (2006)\n- Jens Jacobsen: Praxisbuch Usability und UX, Rheinwerk (2017)\n- Steve Krug: Don't make me think - revisited, New Riders (2013)\n- Bernhard Preim, Raimund Dachselt: Interaktive Systeme Band 1 und 2, eXamen.press\n- Don Norman: The Design of Everyday Things, Basic Books (2013)\n- Michael Richter, Markus D. Flückiger: Usability und UX kompakt: Produkte für Menschen (IT kompakt), Springer Vieweg (2016)", "metadata": {"moduleNumber": "BMI 35", "moduleName": "Human-Computer Interaction", "creditPoints": "5.0", "suggestedSemester": 3, "offeredInSeason": "winter_semester", "examType": "written_exam", "heldInLanguage": "de", "reviserName": "Prof. Dr.-Ing. M.Sc. Markus Dahm", "reviserEmail": "markus.dahm@hs-duesseldorf.de", "studyProgramId": 8, "source_type": "json"}}
{"id": "BMI31", "text": "Title: Discrete Mathematics\nModule Number: BMI 31\nCredits: 5.0 CP\nSemester: 3\nOffered In: winter_semester\nLanguage: de\nExam Type: written_exam\nInstructor: Prof. Dr. rer. nat. Christian Geiger (geiger@hs-duesseldorf.de)\n--- Goals (EN) ---\nThe participants know the most important formal description methods of computer science and selected areas of discrete mathematics as far as they are relevant for applications of media informatics. You can formally model typical problems in computer science and use the most important techniques in principle. They have an overview of basic approaches to (descriptive) statistics, combinatorics and probability calculus and are familiar with the importance of these formal foundations for the practical solution of problems in media informatics.You know application scenarios of the o.g. Areas of Media Informatics (eg computer graphics, human-computer interaction or cryptology) are able to solve typical problems with the help of the learned techniques.\n--- Goals (DE) ---\nDie Teilnehmer kennen die wichtigsten formalen Beschreibungsverfahren der Informatik und ausgewählte Bereiche der diskreten Mathematik, soweit diese für Anwendungsgebiete der Medieninformatik relevant sind. Sie können typische Probleme in der Informatik formal modellieren und die wichtigsten Techniken prinzipiell einsetzen. Sie besitzen einen Überblick grundlegender Ansätze der (beschreibenden) Statistik, Kombinatorik und Wahrscheinlichkeitsrechnung und kennen die Bedeutung dieser formalen Grundlagen für die praktische Lösung von Problemen der Medieninformatik.Sie kennen Anwendungsszenarien der o.g. Bereiche in der Medieninformatik (z. B. in der Computergrafik, Mensch-ComputerInteraktion oder Kryptologie) und sind in der Lage, typische Problemstellungen mit Hilfe der erlernten Techniken zu lösen.\n--- Contents (EN) ---\nFormal specification (eg predicates, graphs, algebras)Basics of automaton theoryFormal grammarsBasics of Statistics (descriptive)Combinatoricsprobability calculationSelected problems and solution concepts of discrete mathematics and theoretical computer science\n--- Contents (DE) ---\nFormale Spezifikation (z. B. Prädikate, Graphen, Algebren)Grundlagen der AutomatentheorieFormale GrammatikenGrundlagen der Statistik (deskriptiv)KombinatorikWahrscheinlichkeitsrechnungAusgewählte Probleme und Lösungskonzepte der diskreten Mathematik und theoretischen Informatik\n--- Literature (EN) ---\n--- Literature (DE) ---\nPrimärliteraturJ. Matoušek, J. Nešetril. Diskrete Mathematik, 2. Auflage, Springer, 2007Steger. Diskrete Strukturen, Band 1 Kombinatorik, Graphentheorie, Algebra, 2. Auflage, Springer, 2007D. W. Hoffmann. Theoretische Informatik, 3. Auflage, Hanser Verlag, 2015U. Kuckartz, S. Rädiker, T. Ebert, J. Schehl. Statistik – eine verständliche Einführung, 2. Auflage, Springer SekundärliteraturHopcroft, Motwani, Ullman. Einführung in die Automatentheorie, Formale Sprachen und KomplexitätstheorieA. Beutelspacher. Diskrete Mathematik für Einsteiger, 4. Auflage, Vieweg studium, 2011", "metadata": {"moduleNumber": "BMI 31", "moduleName": "Discrete Mathematics", "creditPoints": "5.0", "suggestedSemester": 3, "offeredInSeason": "winter_semester", "examType": "written_exam", "heldInLanguage": "de", "reviserName": "Prof. Dr. rer. nat. Christian Geiger", "reviserEmail": "geiger@hs-duesseldorf.de", "studyProgramId": 8, "source_type": "json"}}
{"id": "BMI12", "text": "Title: Computer and network architectures\nModule Number: BMI 12\nCredits: 5.0 CP\nSemester: 1\nOffered In: winter_semester\nLanguage: de\nExam Type: written_exam\nInstructor: Prof. Dr.-Ing. Thomas Rakow (thomas.rakow@hs-duesseldorf.de)\n--- Goals (EN) ---\n--- Goals (DE) ---\nDie Studierenden kennen und verstehen die Struktur eines Rechners und die Funktion und Leistungsparameter seiner einzelnen Bestandteile. Sie sind in der Lage, Rechensysteme hinsichtlich ihrer Eignung für dedizierte Anwendungen zu beurteilen bzw. zu vergleichen. Sie wissen, wie Daten und Medien dargestellt werden. Die Studierenden kennen die wichtigsten Protokolle und Komponenten eines Rechnernetzes und verstehen, welche Aufgaben diese übernehmen und in welchem Zusammenhang sie zueinander stehen. Sie verstehen die Struktur und die Funktionsweise des Internets. Die Studierenden kennen Werkzeuge zur Analyse von Verbindungs- und Performanceproblemen und wissen, wie diese systematisch zur Problemlösung eingesetzt werden können.\n--- Contents (EN) ---\n--- Contents (DE) ---\nVon-Neumann-Architektur, Steuerwerk,\nRechenwerk, Arbeitsspeicher, Sekundärspeicher\nBoolesche Algebra und Schaltungen\nBinärcodierung, Zahlensysteme, Gleitpunktzahlen, Zeichencodes\nVirtualisierung\nInternet-Protokolle (z.B. IP, TCP, UDP, DNS)\nWegewahl im Internet: Algorithmen und Protokolle, Flusskontrolle und Lastverteilung,\n--- Literature (EN) ---\n--- Literature (DE) ---\nJ. L. Hennessy, D. A. Patterson: Computer Architecture  A Quantitative Approach (5th Ed.), Morgan Kaufmann 2012\nA. S. Tanenbaum, T. Austin: Rechnerarchitektur - Von der digitalen Logik zum Parallelrechner (6. Aufl.), Pearson 2014\nS. Tanenbaum: Computernetzwerke, Pearson Studium, 4. Auflage, 2012.\nR. Schreiner: Computernetzwerke: Von den Grundlagen zur Funktion und Anwendung, Carl Hanser Verlag 2014.", "metadata": {"moduleNumber": "BMI 12", "moduleName": "Computer and network architectures", "creditPoints": "5.0", "suggestedSemester": 1, "offeredInSeason": "winter_semester", "examType": "written_exam", "heldInLanguage": "de", "reviserName": "Prof. Dr.-Ing. Thomas Rakow", "reviserEmail": "thomas.rakow@hs-duesseldorf.de", "studyProgramId": 8, "source_type": "json"}}
{"id": "BMI44", "text": "Title: Media Project A\nModule Number: BMI 44\nCredits: 5.0 CP\nSemester: 4\nOffered In: summer_semester\nLanguage: en_on_demand\nExam Type: project\nInstructor: Prof. Dr.-Ing. M.Sc. Markus Dahm (markus.dahm@hs-duesseldorf.de)\n--- Goals (EN) ---\nStudents can collaborate on a given task in a project in a given time. In doing so, they will apply and deepen their knowledge, in particular of software engineering, other areas of computer science from previous semesters as well as media design.\n--- Goals (DE) ---\nStudierende können in einer bestimmten Zeit eine vorgegebene Aufgabe in einem Projekt gemeinsam bearbeiten. Dabei wenden Sie ihre Kenntnisse insbesondere des Software Engineering, weiterer Gebiete der Informatik aus den vorhergehenden Semestern sowie der Mediengestaltung an und vertiefen sie so.\n--- Contents (EN) ---\nExisting modules of the core area according to examination regulations §17 (7) are passed\n--- Contents (DE) ---\nDer Inhalt entspricht den für jedes Semester neu angebotenen Themen.\n--- Literature (EN) ---\nThe recommended literature corresponds to the new topics offered each semester and is specified by the lecturers.\n--- Literature (DE) ---\nDie empfohlene Literatur entspricht den für jedes Semester neu angebotenen Themen und wird von den Anbietenden angegeben.", "metadata": {"moduleNumber": "BMI 44", "moduleName": "Media Project A", "creditPoints": "5.0", "suggestedSemester": 4, "offeredInSeason": "summer_semester", "examType": "project", "heldInLanguage": "en_on_demand", "reviserName": "Prof. Dr.-Ing. M.Sc. Markus Dahm", "reviserEmail": "markus.dahm@hs-duesseldorf.de", "studyProgramId": 8, "source_type": "json"}}
{"id": "BMI43", "text": "Title: IT Security\nModule Number: BMI 43\nCredits: 5.0 CP\nSemester: 4\nOffered In: winter_semester\nLanguage: en_on_demand\nExam Type: written_exam\nInstructor: Prof. Dr.-Ing. M.Sc. Markus Dahm (markus.dahm@hs-duesseldorf.de)\n--- Goals (EN) ---\nThe students know and understand the importance of IT security for companies and organizations and the risks associated with IT deployment. They know and understand the legal framework of IT security, data protection and procedures of international security standards. They know and understand the protection goals of IT security as well as typical threats, vulnerabilities and risks. Students are able to analyze and assess threats and vulnerabilities and apply technical and non-technical measures as part of risk management. They know software tools of IT security and can apply them in practice.\n--- Goals (DE) ---\nDie Studierenden kennen und verstehen die Bedeutung der IT-Sicherheit für Unternehmen und Organisationen und die mit dem IT-Einsatz verbundenen Risiken. Sie kennen und verstehen rechtliche Rahmenbedingungen der IT-Sicherheit, des Datenschutzes und Vorgehensweisen internationaler Sicherheitsstandards. Sie kennen und verstehen die Schutzziele der IT-Sicherheit sowie typische Bedrohungen, Schwachstellen und Risiken. Die Studierenden sind in der Lage Bedrohungen und Schwachstellen zu analysieren und zu bewerten und im Rahmen der Risikobehandlung technische sowie nicht-technische Maßnahmen anzuwenden. Sie kennen SoftwareTools der IT-Sicherheit und können diese in der Praxis anwenden.\n--- Contents (EN) ---\nProtection goals of IT security\nTerminology (Assets, Threats, Weaknesses / Vulnerabilities, Attacks, Risks)\nRisk analysis and treatment\nThreat and vulnerability analysis\nOrganizational guidelines\nLegal framework (IT law and data protection law)\nSecurity standards (ISO / IEC 27000 series and Common Criteria)\nCryptology (Classical Techniques, Cryptanalysis, Cipher Design, DES, AES, DH, RSA, SHA-2 Family, SHA-3 / Keccak)\nAuthentication (password-based and biometric methods)\nOther technical security measures (digital signature procedures, security protocols)\nHuman factors in IT security\n--- Contents (DE) ---\nTerminologie (Werte, Bedrohungen, Schwachstellen / Verwundbarkeiten, Angriffe, Risiken)\nRisikoanalyse und behandlung\nBedrohungs- und Schwachstellenanalyse\nOrganisatorische Richtlinien\nRechtliche Rahmenbedingungen (IT-Recht und Datenschutzrecht)\nSicherheitsstandards (ISO/IEC 27000-Reihe und Common Criteria)\nKryptologie (Klassische Verfahren, Kryptoanalyse, Chiffren\nDesign, DES, AES, DH, RSA, SHA-1, SHA-2 Familie, SHA3/Keccak\n)\nAuthentifikation (Passwort-basierte, verteilte und in Rechnernetzen realisierte Verfahren)\nWeitere technische Sicherheitsmaßnahmen (Digitale Signaturverfahren, Sicherheitsprotokolle)\nFaktor Mensch in der IT-Sicherheit\n--- Literature (EN) ---\nC. Eckert: IT-Sicherheit, Konzepte  Verfahren  Protokolle (9. Aufl.), Oldenbourg Verlag 2014\nK. Schmeh: Kryptografie  Verfahren  Protokolle  Infrastrukturen (6. Aufl.), dpunkt.verlag 2016\nISO/IEC 27000: Information technology  Security techniques  Information security management systems  Overview and vocabulary, 2018\nT. R. Peltier: Information Security Fundamentals, Taylor and Francis 2014\n--- Literature (DE) ---\nC. Eckert: IT-Sicherheit, Konzepte  Verfahren  Protokolle (9. Aufl.), Oldenbourg Verlag 2014\nK. Schmeh: Kryptografie  Verfahren  Protokolle  Infrastrukturen (6. Aufl.), dpunkt.verlag 2016\nISO/IEC 27000: Information technology  Security techniques  Information security management systems  Overview and vocabulary, 2018\nT. R. Peltier: Information Security Fundamentals, Taylor and Francis 2014", "metadata": {"moduleNumber": "BMI 43", "moduleName": "IT Security", "creditPoints": "5.0", "suggestedSemester": 4, "offeredInSeason": "winter_semester", "examType": "written_exam", "heldInLanguage": "en_on_demand", "reviserName": "Prof. Dr.-Ing. M.Sc. Markus Dahm", "reviserEmail": "markus.dahm@hs-duesseldorf.de", "studyProgramId": 8, "source_type": "json"}}
{"id": "BMI54", "text": "Title: Media Project B\nModule Number: BMI 54\nCredits: 5.0 CP\nSemester: 5\nOffered In: winter_semester\nLanguage: en_on_demand\nExam Type: project\nInstructor: Prof. Dr.-Ing. M.Sc. Markus Dahm (markus.dahm@hs-duesseldorf.de)\n--- Goals (EN) ---\nStudents can collaborate on a given task in a project in a given time. In doing so, they will apply and deepen their knowledge, in particular of software engineering, other areas of computer science from previous semesters as well as media design.\n--- Goals (DE) ---\nStudierende können in einer bestimmten Zeit eine vorgegebene Aufgabe in einem Projekt gemeinsam bearbeiten. Dabei wenden Sie ihre Kenntnisse insbesondere des Software Engineering, weiterer Gebiete der Informatik aus den vorhergehenden Semestern sowie der Mediengestaltung an und vertiefen sie so.\n--- Contents (EN) ---\nThe content corresponds to the topics newly offered for each semester.\n--- Contents (DE) ---\nDer Inhalt entspricht den für jedes Semester neu angebotenen Themen.\n--- Literature (EN) ---\nThe recommended literature corresponds to the new topics offered each semester and is specified by the lecturers.\n--- Literature (DE) ---\nDie empfohlene Literatur entspricht den für jedes Semester neu angebotenen Themen und wird von den Anbietenden angegeben.", "metadata": {"moduleNumber": "BMI 54", "moduleName": "Media Project B", "creditPoints": "5.0", "suggestedSemester": 5, "offeredInSeason": "winter_semester", "examType": "project", "heldInLanguage": "en_on_demand", "reviserName": "Prof. Dr.-Ing. M.Sc. Markus Dahm", "reviserEmail": "markus.dahm@hs-duesseldorf.de", "studyProgramId": 8, "source_type": "json"}}
{"id": "BMI60", "text": "Title: External Semester\nModule Number: BMI 60\nCredits: 30.0 CP\nSemester: 6\nOffered In: summer_semester\nLanguage: en_on_demand\nExam Type: oral_exam\nInstructor: Prof. Dr.-Ing. Thomas Rakow (thomas.rakow@hs-duesseldorf.de)\n--- Goals (EN) ---\nStudents acquire the skills to find their way in a previously unfamiliar environment and to be able to work constructively there. To this end, students can choose between a practical work placement semester, studying abroad or a research semester.\n\nOptional module practical semester: \nPractical work experience is orientated towards the future professional field for media IT specialists. Students are familiarised with operational processes and can work on tasks in media informatics according to their level of knowledge.\n\nStudy abroad elective module: \nA study abroad programme imparts the skills in the selected courses from the areas of media informatics and cross-sectional qualifications, supplemented by the increased requirements for independence due to the stay abroad as well as learning skills in a foreign language.\n\nResearch semester elective module: \nA research semester imparts the basics and knowledge of scientific research and the processes at a research institute in the field of media informatics.\n--- Goals (DE) ---\nDie Studierenden erwerben die Fähigkeiten, sich in einer vorher unbekannten Umgebung zurecht zu finden und dort konstruktiv mitarbeiten zu können. Hierfür stehen zur Wahl eine berufspraktische Tätigkeit im Praxissemester, ein Auslandsstudium oder ein Forschungssemester.\n\nWahlmodul Praxissemester: \nEine berufspraktische Tätigkeit orientiert sich am späteren Berufsfeld für Medieninformatiker. Die Studierenden kennen betriebliche Prozesse und können ihnen gestellte Aufgaben der Medieninformatik gemäß ihrem Kenntnisstand bearbeiten.\n\nWahlmodul Auslandsstudium: \nEin Auslandsstudium vermittelt die Kompetenzen in den gewählten Kursen aus den Bereichen Medieninformatik und Querschnittsqualifikationen, ergänzt um die erhöhten Anforderungen an Selbständigkeit durch den Auslandsaufenthalt sowie die Lernkompetenz in einer Fremdsprache.\n\nWahlmodul Forschungssemester: \nEin Forschungssemester vermittelt Grundlagen und Kenntnisse der wissenschaftlichen Forschung und der Abläufe an einem Forschungsinstitut auf dem Gebiet der Medieninformatik.\n--- Contents (EN) ---\nElective module practical semester: \nStudents orientate themselves in the future professional field for media IT specialists, familiarise themselves with operational processes and work on tasks assigned to them. To this end, they conclude a contract with the placement centre regarding the duration, tasks and supervision. The supervising professor is informed and advises the student through regular reports to be confirmed by the practice centre.\n\nElective module study abroad: \nStudents can organise and use international educational opportunities for themselves. They can develop, formulate and present IT models and concepts in a global context. The students experience a foreign study programme and the culture of the host country.\n\nElective module research semester: \nStudents are familiar with working methods in scientific research, specifically in media informatics.\n--- Contents (DE) ---\nWahlmodul Praxissemester: \nDie Studierenden orientieren sich im späteren Berufsfeld für Medieninformatiker und Medieninformatikerinnen, lernen betriebliche Prozesse kennen und bearbeiten ihnen gestellte Aufgaben. Sie schließen dazu mit der Praxisstelle einen Vertrag über die Zeitdauer, Aufgaben und Betreuung ab. Durch regelmäßige, von der Praxisstelle zu bestätigende Berichte wird der betreuende Professor oder die betreuende Professorin informiert und berät den Studierenden oder die Studierende.\n\nWahlmodul Auslandsstudium: \nStudierende können für sich internationale Bildungsangebote organisieren und nutzen. Im globalen Kontext können Sie IT-Modelle und -Konzepte entwickeln, formulieren und präsentieren. Die Studierenden erleben eine fremden Studienalltags und die Kultur des aufnehmenden Landes.\n\nWahlmodul Forschungssemester: \nDie Studierenden kennen die Arbeitsweisen in der wissenschaftlichen Forschung speziell der Medieninformatik.\n--- Literature (EN) ---\nDepending on the elective module an the tasks at hand\n--- Literature (DE) ---\nJe nach Aufgabenstellung", "metadata": {"moduleNumber": "BMI 60", "moduleName": "External Semester", "creditPoints": "30.0", "suggestedSemester": 6, "offeredInSeason": "summer_semester", "examType": "oral_exam", "heldInLanguage": "en_on_demand", "reviserName": "Prof. Dr.-Ing. Thomas Rakow", "reviserEmail": "thomas.rakow@hs-duesseldorf.de", "studyProgramId": 8, "source_type": "json"}}
{"id": "BMI70", "text": "Title: Individual Compulsive Elective\nModule Number: BMI 70\nCredits: 5.0 CP\nSemester: 7\nOffered In: winter_semester\nLanguage: de\nExam Type: see_elective\nInstructor: Prof. Dr.-Ing. M.Sc. Markus Dahm (markus.dahm@hs-duesseldorf.de)\n--- Goals (EN) ---\nThe students extend their knowledge in a self-selected subject area\n--- Goals (DE) ---\nDie Studierenden erweitern ihre Kenntnisse in einem selbst gewählten Themengebiet.\n--- Contents (EN) ---\nFor the elective module current topics of the university are offered. The tasks are based on typical occupational activities of the graduates.\n--- Contents (DE) ---\nFür das Wahlmodul werden aktuelle Themen der Hochschule angeboten. Die Aufgabenstellungen orientieren sich an typischen beruflichen Tätigkeiten der Absolventinnen und Absolventen.\n--- Literature (EN) ---\nDefined by elective module\n--- Literature (DE) ---\nDurch Wahlmodul vorgegeben", "metadata": {"moduleNumber": "BMI 70", "moduleName": "Individual Compulsive Elective", "creditPoints": "5.0", "suggestedSemester": 7, "offeredInSeason": "winter_semester", "examType": "see_elective", "heldInLanguage": "de", "reviserName": "Prof. Dr.-Ing. M.Sc. Markus Dahm", "reviserEmail": "markus.dahm@hs-duesseldorf.de", "studyProgramId": 8, "source_type": "json"}}
{"id": "BMI101", "text": "Title: Interactive Systems\nModule Number: BMI 101\nCredits: 5.0 CP\nSemester: 4\nOffered In: summer_semester\nLanguage: de\nExam Type: written_exam\nInstructor: Prof. Dr.-Ing. M.Sc. Markus Dahm (markus.dahm@hs-duesseldorf.de)\n--- Goals (EN) ---\nStudents know fundamentals of programming interactive systems and can make use of them. They know the technological principles of displays and interaktion devices and can identify the best fitting ones. They know advanced concepts of usabilty and user experience and can apply them. They know criteria for successful usability, can describe them and apply them in concepts and in inmplementations. They know UI patterns and can apply them to the design of interactive system.\n--- Goals (DE) ---\nDie Studierenden kennen die Grundlagen der Programmierung Interaktiver Systeme und können sie anwenden. Sie kennen die Wirkungsweise und Eigenschaften von Display- und Interaktionstechnologien und können die jeweils geeigneten auswählen. Sie kennen die Definition von Usablity und User Experience und können sie gegeneinander abgrenzen. Sie kennen Anforderungen an die Usability von aktuellen Interaktiven Systemen und können sie mit Kriterien der entsprechenden Normen und Richtlinien beschreiben. Sie kennen Entwurfsmuster für die Gestaltung von Interaktiven Systemen und können sie anwenden.\n--- Contents (EN) ---\n- Output: display tree, 2.5D organisation, coordinates, collision detection\n- Input: polling and event-driven systems, gameloop\n- GUI-libraries such as JavaFX\n- Introduction to Kotlin and advanced programming concepts\n- Interaction technologies, e.g. touchscreens, motion detection, speech recognition\n- Advanced aspects of usability and usability engineering, e.g. for mobile applications and touch interactions\n- UI design patterns\n- Usability and UX\n--- Contents (DE) ---\n- Darstellung: Display Tree, 2,5D-Organisation, Kollisionsermittlung\n- Input: Polling und Event-Driven Systems, gameloop\n- GUI-Libraries z.B. Java FX\n- Einführung in Kotlin und fortgeschrittene Programmierkonzepte\n- Display-Technologien: z.B. LCD, eInk\n- Interaktions-Technologien, z.B. TouchScreens, Kinect\n- Vertiefung von Aspekten der Usability und des Usability-Engineering, z.B. für mobile und Touch-Interaktion\n- UI-Entwurfsmuster\n- UX und Usability\n--- Literature (EN) ---\n- Markus Dahm: Grundlagen der Mensch-Computer-Interaktion, Pearson (2006)\n- Jens Jacobsen: Praxisbuch Usability und UX, Rheinwerk (2017)\n- Steve Krug: Don't make me think - revisited, New Riders (2013)\n- Bernhard Preim, Raimund Dachselt: Interaktive Systeme Band 1 und 2, eXamen.press\n- Don Norman: The Design of Everyday Things, Basic Books (2013)\n- Michael Richter, Markus D. Flückiger: Usability und UX kompakt: Produkte für Menschen (IT kompakt), Springer Vieweg (2016)\n- David Griffiths and Dawn Griffiths: Head First Kotlin: A Brain-Friendly Guide, O'Reilly (2019)\n--- Literature (DE) ---\n- Markus Dahm: Grundlagen der Mensch-Computer-Interaktion, Pearson (2006)\n- Jens Jacobsen: Praxisbuch Usability und UX, Rheinwerk (2017)\n- Steve Krug: Don't make me think - revisited, New Riders (2013)\n- Bernhard Preim, Raimund Dachselt: Interaktive Systeme Band 1 und 2, eXamen.press\n- Don Norman: The Design of Everyday Things, Basic Books (2013)\n- Michael Richter, Markus D. Flückiger: Usability und UX kompakt: Produkte für Menschen (IT kompakt), Springer Vieweg (2016)\n- David Griffiths and Dawn Griffiths: Head First Kotlin: A Brain-Friendly Guide, O'Reilly (2019)", "metadata": {"moduleNumber": "BMI 101", "moduleName": "Interactive Systems", "creditPoints": "5.0", "suggestedSemester": 4, "offeredInSeason": "summer_semester", "examType": "written_exam", "heldInLanguage": "de", "reviserName": "Prof. Dr.-Ing. M.Sc. Markus Dahm", "reviserEmail": "markus.dahm@hs-duesseldorf.de", "studyProgramId": 8, "source_type": "json"}}
{"id": "BMI104", "text": "Title: Development of secure software\nModule Number: BMI 104\nCredits: 5.0 CP\nSemester: 5\nOffered In: winter_semester\nLanguage: de\nExam Type: oral_exam\nInstructor: Prof. Dr.-Ing. Thomas Rakow (thomas.rakow@hs-duesseldorf.de)\n--- Goals (EN) ---\nThe students know and understand the basics of cryptography and the development of secure software based on a software library for cryptographic techniques. They can analyze threats and vulnerabilities and select and apply adequate cryptographic security measures. Students can apply basic measures to develop secure software such as secure software design principles, secure coding policies, and unit testing when using cryptography. They know software tools of IT security and can apply them in practice.\n--- Goals (DE) ---\nDie Studierenden kennen und verstehen die Grundlagen der Kryptographie und der Entwicklung sicherer Software auf Basis einer Software-Bibliothek für kryptographische Verfahren. Sie können Bedrohungen und Schwachstellen analysieren und adäquate kryptographische Sicherheitsmaßnahmen auswählen und diese anwenden. Die Studierenden können grundlegende Maßnahmen zur Entwicklung sicherer Software wie Entwurfsprinzipien für sichere Software, Secure-Coding-Richtlinien und Unit-Testen beim Einsatz von Kryptographie anwenden. Sie kennen Software-Tools der IT-Sicherheit und können diese in der Praxis anwenden.\n--- Contents (EN) ---\nSelection of adequate cryptographic techniques based on threat and vulnerability analyzes     Java Cryptography Architecture and API     Legion of the Bouncy Castle Java cryptography APIs     Block ciphers: DES, AES, padding, block modes, use as stream ciphers     Power ciphers: RC4, generation of key streams     Password-based encryption / decryption     Key management     Message Digests, MACs and HMACs     Asymmetric cryptography: DH, RSA, El-Gamal, digital signatures     Actions for the development of secure software: design principles for secure software, secure coding policies, unit testing when using cryptography\n--- Contents (DE) ---\n- Auswahl geeigneter kryptographischer Verfahren auf Basis von \n- Bedrohungs- und Schwachstellenanalysen\n- Java Cryptography Architecture und API\n- Legion of the Bouncy Castle Java Cryptography APIs\n- Block-Chiffren: DES, AES, Padding, Block-Modi, Verwendung als Strom-Chiffren\n- Strom-Chiffren: RC4, Generierung von Schlüsselströmen\n- Passwort-basierte Ver-/ EntschlüsselungSchlüsselmanagement\n- Message Digests, MACs und HMACs\n- Asymmetrische Kryptographie: DH, RSA, El-Gamal, digitale Signaturen\n- Maßnahmen für die Entwicklung sicherer Software: Entwurfsprinzipien für sichere Software, Secure Coding Richtlinien, Unit-Testen beim Einsatz von Kryptographie\n--- Literature (EN) ---\n--- Literature (DE) ---\n- D. Hook und J. Eaves: Java Cryptography: Tools and Techniques, Leanpub, 2020\n- D. Hook: Beginning Cryptography with Java, John Wiley & Sons, 2005\n- F. Long, D. Mohindra, R. C. Seacord, D. F. Sutherland und D. Svoboda,  Java Coding Guidelines: 75 Recommendations for Reliable and Secure Programs, Addison-Wesley Professional, 2013\n- S. Oaks: Java Security, O'Reilly, 2010\n- K. Schmeh: Kryptografie  Verfahren  Protokolle  Infrastrukturen (6. Aufl.), dpunkt.verlag, 2016\n- R. E. Smith, A Contemporary Look at Saltzer and Schroeder's 1975 Design Principles, IEEE Security & Privacy, 10(6), 20-25, 2012", "metadata": {"moduleNumber": "BMI 104", "moduleName": "Development of secure software", "creditPoints": "5.0", "suggestedSemester": 5, "offeredInSeason": "winter_semester", "examType": "oral_exam", "heldInLanguage": "de", "reviserName": "Prof. Dr.-Ing. Thomas Rakow", "reviserEmail": "thomas.rakow@hs-duesseldorf.de", "studyProgramId": 8, "source_type": "json"}}
{"id": "BMI105", "text": "Title: Web Apps\nModule Number: BMI 105\nCredits: 5.0 CP\nSemester: 4\nOffered In: summer_semester\nLanguage: en_on_demand\nExam Type: written_exam\nInstructor: Prof. Dr. Manfred Wojciechowski (manfred.wojciechowski@hs-duesseldorf.de)\n--- Goals (EN) ---\nThe students understand and are able to apply the basics for the implementation of complex client side web applications including web apps. They know the fundamental language concepts of ECMAScript 6+ and can apply them in complex programs. Those concepts include the functions and the prototype based object oriented programming. They know important concepts for the realization of big and maintainable CSS code and can apply those. They know suitable tools for supporting the development process and can apply those. These include a package manager, build systems, precompiler and transpiler, documentation and test frameworks. They can implement browser based applications using the HTML5 Web API or suitable frameworks.\n--- Goals (DE) ---\nNach der Teilnahme an der Modulveranstaltung sind die Studierenden in der Lage die Grundlagen der Realisierung komplexer clientseitiger Webanwendungen bis hin zu Web-Apps zu verstehen und umzusetzen. Sie kennen die grundlegenden Sprachkonzepte von ECMAScript 6 und können diese in komplexen Programmen umsetzen. Dazu gehören die funktionale, sowie die prototypbasierte objektorientierte Programmierung. Zudem kennen sie wichtige Konzepte zur Erstellung großer und wartbarer CSS-Programme und können diese anwenden. Sie kennen geeignete Werkzeuge zur Unterstützung des Entwicklungsprozesses und können diese anwenden. Dazu gehören Paketmanager, Build-Systeme, Precompiler und Transpiler, Dokumentationssysteme, sowie Testframeworks. Sie können browserbasierte Applikationen mit Hilfe der HTML5 Web-API oder einem geeigneten Framework umsetzen.\n--- Contents (EN) ---\nLecture:\n- Advanced concepts of ECMAScript 6+: functional programming, object oriented programming, asynchron programming\n- advanced CSS concepts: styleguides, methodologies, pre-compiler\n- processing tools, e.g. packet manager, build system, documentation, testing, linter, ...\n- implementation of web apps with access to hardware and operating system near functions using the HTML5 Web API or a suitable framework\n\nPractice:\nPractical implementation of the learning content using given exercises in a development environment, e.g. brackets\n--- Contents (DE) ---\nVorlesung:\n- Fortgeschrittene Konzepte von ECMAScript 6: Funktionale Programmierung,  Objektorientierte Programmierung, Asynchrone Programmierung\n- Fortgeschrittene Konzepte zur Erstellung von CSS: Styleguides, Methodologie, Precompiler\n- Werkzeuge zur Prozessunterstützung, z.B. Paketmanager, Build-System, Dokumentation, Test, Linter\n- Erstellung einer Web-App mit Zugriff auf Hardware- und Betriebssystemnahe Funktionen mit Hilfe der HTML5 Web-API bzw. eines geeigneten Frameworks\n\nÜbung:\nPraktische Umsetzung der Lerninhalte anhand vorgegebener Übungsaufgaben in einer Entwicklungsumgebung, z.B. Brackets\n--- Literature (EN) ---\nM. Wojciechowski: Lecture slides and video for Web-Apps\n--- Literature (DE) ---\nM. Wojciechowski: Vorlesungsfolien und Videos zu Web-Apps", "metadata": {"moduleNumber": "BMI 105", "moduleName": "Web Apps", "creditPoints": "5.0", "suggestedSemester": 4, "offeredInSeason": "summer_semester", "examType": "written_exam", "heldInLanguage": "en_on_demand", "reviserName": "Prof. Dr. Manfred Wojciechowski", "reviserEmail": "manfred.wojciechowski@hs-duesseldorf.de", "studyProgramId": 8, "source_type": "json"}}
{"id": "BMI202", "text": "Title: Multimedia Storytelling\nModule Number: BMI 202\nCredits: 5.0 CP\nSemester: 5\nOffered In: winter_semester\nLanguage: de\nExam Type: portfolio\nInstructor: Prof. Gabriele Schwab-Trapp (gabi.schwab-trapp@hs-duesseldorf.de)\n--- Goals (EN) ---\nStudents acquire skills in the conceptual handling of free or applied topics and the ability to independently develop context-related content. The development and practical realisation of their own ideas is made possible with the help of design processes. Experience in interdisciplinary, creative and constructive collaboration is gained within the seminar and possible project groups as well as in dealing with various forms of presentation.\n--- Goals (DE) ---\nDie Studierenden erwerben Fähigkeiten im konzeptionellen Umgang mit freien oder angewandten Themen und die Befähigung zur selbstständigen Erarbeitung von kontextbezogenen Inhalten. Mithilfe von Gestaltungsprozessen werden die Entwicklung und die praktische Umsetzung eigener Ideen ermöglicht. Erfahrungen in interdisziplinärer, kreativer und konstruktiver Zusammenarbeit werden innerhalb der Seminar- und möglicher Projektgruppen sowie im Umgang mit verschiedenen Präsentationsformen gesammelt.\n--- Contents (EN) ---\nFree or applied topics are dealt with, which are presented at the beginning of the semester. The joint deepening, development and unfolding of the topic takes place in seminar form. This also includes philosophical, knowledge-orientated and opinion-forming discussions. The aim is the independent development and realisation of context-related, visual concepts in various media. Various forms of presentation are practised according to the topics and results. Excursions may be organised to support the topics, which will be announced at the beginning of the semester. Material and literature references will be provided for the respective topic in the seminar. Information in the form of text extracts, literature, image examples and research suggestions will be provided to support the respective learning, realisation and design steps. \nMultimedia storytelling is regularly offered as an open, collaborative and interdisciplinary module with students from other subject areas.\n--- Contents (DE) ---\nInhaltlich werden freie oder angewandte Themen behandelt, die zu Beginn des Semesters vorgestellt werden. Die gemeinsame Vertiefung, Entwicklung und Entfaltung des Themas findet in Seminarform statt. Dazu gehört auch die philosophische, erkenntnisorientierte und meinungsbildende Auseinandersetzung. Ziel ist die selbstständige Entwicklung und Umsetzung von kontextbezogenen, visuellen Konzepten in unterschiedlichen Medien. Den Themen und Ergebnissen entsprechend werden verschiedene Präsentationsformen eingeübt. Themenunterstützend können Exkursionen stattfinden, die zu Beginn des Semesters bekannt gegeben werden. Material- und Literaturangaben werden zu dem jeweiligen Thema im Seminar ausgegeben. Zur Unterstützung der jeweiligen Lern-, Erkenntnis- und Gestaltungsschritte werden Hinweise in Form von Textauszügen, Literatur, Bildbeispielen und Recherchevorschlägen gegeben. \nMultimediales Erzählen wird regelmäßig als offenes, kollaboratives und interdisziplinäres Modul mit Studierenden aus anderen Fachbereichen angeboten.\n--- Literature (EN) ---\nLists of materials and literature are issued each semester in the seminar. The respective learning, realisation and design steps are supported by references in the form of text excerpts, literature, image examples and research suggestions. There is also a detailed oral introduction.\n--- Literature (DE) ---\nMaterial- und Literaturlisten werden jedes Semester aktuell im Seminar ausgegeben. Die jeweiligen Lern-, Erkenntnis- und Gestaltungsschritte werden unterstützt durch Hinweise in Form von Textauszügen, Literatur, Bildbeispielen und Recherchevorschlägen. Zudem erfolgt eine ausführliche mündliche Einführung.", "metadata": {"moduleNumber": "BMI 202", "moduleName": "Multimedia Storytelling", "creditPoints": "5.0", "suggestedSemester": 5, "offeredInSeason": "winter_semester", "examType": "portfolio", "heldInLanguage": "de", "reviserName": "Prof. Gabriele Schwab-Trapp", "reviserEmail": "gabi.schwab-trapp@hs-duesseldorf.de", "studyProgramId": 8, "source_type": "json"}}
{"id": "BMI204", "text": "Title: Communication Design\nModule Number: BMI 204\nCredits: 5.0 CP\nSemester: 5\nOffered In: winter_semester\nLanguage: de\nExam Type: portfolio\nInstructor: Prof. Gabriele Schwab-Trapp (gabi.schwab-trapp@hs-duesseldorf.de)\n--- Goals (EN) ---\nOn the basis of practical and theoretical skills acquired in the design fundamentals, students can develop simple visual communication measures.\n--- Goals (DE) ---\nAuf Basis der in den Gestaltungsgrundlagen praktisch und theoretisch erworbenen Fähigkeiten können die Studierenden einfache visuelle Kommunikationsmaßnahmen entwickeln.\n--- Contents (EN) ---\nDevelopment of appearances, concepts and visualizations for different types of public communication. Various means of presentation can be used: typography, photography, illustration, film, animation, etc.\n--- Contents (DE) ---\nEntwicklung von Erscheinungsbildern, Konzepten und Visualisierungen für verschiedene Arten der öffentlichen Kommunikation. Hierbei können vielfältige Darstellungsmittel eingesetzt werden: Typografie, Fotografie, Illustration, Film, Animation, etc.\n--- Literature (EN) ---\nLists of materials and literature are issued each semester in the seminar. The respective learning, realisation and design steps are supported by references in the form of text excerpts, literature, image examples and research suggestions. There is also a detailed oral introduction.\n--- Literature (DE) ---\nMaterial- und Literaturlisten werden jedes Semester aktuell im Seminar ausgegeben. Die jeweiligen Lern-, Erkenntnis- und Gestaltungsschritte werden unterstützt durch Hinweise in Form von Textauszügen, Literatur, Bildbeispielen und Recherchevorschlägen. Zudem erfolgt eine ausführliche mündliche Einführung.", "metadata": {"moduleNumber": "BMI 204", "moduleName": "Communication Design", "creditPoints": "5.0", "suggestedSemester": 5, "offeredInSeason": "winter_semester", "examType": "portfolio", "heldInLanguage": "de", "reviserName": "Prof. Gabriele Schwab-Trapp", "reviserEmail": "gabi.schwab-trapp@hs-duesseldorf.de", "studyProgramId": 8, "source_type": "json"}}
{"id": "BMI207", "text": "Title: Introduction to 3D Modeling\nModule Number: BMI 207\nCredits: 5.0 CP\nSemester: 5\nOffered In: winter_semester\nLanguage: de\nExam Type: oral_exam\nInstructor: Prof. Dr.-Ing. Sina Mostafawy (sina.mostafawy@hs-duesseldorf.de)\n--- Goals (EN) ---\nThe participants will be able to construct complex objects in a 3D program after the course. They are still able to texture and illuminate them in order to represent them realistically. You are able to transfer from a given storyboard graphically implemented scenes in 3D and animate it there. You have a basic knowledge of different rendering methods and techniques. They have basic knowledge of what parts have to be rendered and what areas need to be created in post-production. Also, they can decide if a scene should be filmed in real or digitally generated.\n--- Goals (DE) ---\nDie Teilnehmer sind nach dem Kurs in der Lage komplexe Objekte in einem 3D Programm zu konstruieren. Sie sind weiterhin in der Lage diese zu texturieren und zu beleuchten, um sie realistisch abbilden zu können. Sie sind in der Lage aus einem vorgegebenen Storyboard zeichnerisch umgesetzte Sezen in 3D zu übertragen und diese dort nachzubilden. Sie haben ein grundsätzliches Wissen über verschieden Renderingmethoden und -techniken. Sie verfügen über grundsätzliches Wissen welche Bereiche gerendert und welche Bereiche in der Postproduktion entstehen müssen. Auch können sie entscheiden, ob eine Szene real gefilmt, oder beser digital erzeugt werden sollte.\n--- Contents (EN) ---\nIntroduction to 3D modeling\nIntroduction to 3D design with curves and freeform surfaces\nTexturing and mapping\n3D illumination and lighting\nCreation of simple path animations, rendering of individual images and animations.\nBasics of post-production with 3D and 2D elements.es\n--- Contents (DE) ---\nEinführung in 3D-Modellierung\nEinführung in 3D-Konstruktion mit Kurven und Freiformfläche\nTexturierung und Mapping\n3D Illumination und Beleuchtung\nErstellung einfacher Pfadanimationen, Rendering von Einzelbildern und Animationen.\nGrundlagen der Postproduktion mit 3D und 2D Elementen.\n--- Literature (EN) ---\n--- Literature (DE) ---\nWird in der Vorlesung bekannt gegeben", "metadata": {"moduleNumber": "BMI 207", "moduleName": "Introduction to 3D Modeling", "creditPoints": "5.0", "suggestedSemester": 5, "offeredInSeason": "winter_semester", "examType": "oral_exam", "heldInLanguage": "de", "reviserName": "Prof. Dr.-Ing. Sina Mostafawy", "reviserEmail": "sina.mostafawy@hs-duesseldorf.de", "studyProgramId": 8, "source_type": "json"}}
{"id": "BMI108", "text": "Title: Immersive Visualisation\nModule Number: BMI 108\nCredits: 5.0 CP\nSemester: 5\nOffered In: winter_semester\nLanguage: de\nExam Type: project\nInstructor: Prof. Dr. rer. nat. Christian Geiger (geiger@hs-duesseldorf.de)\n--- Goals (EN) ---\nStudents will be familiar with the key concepts of visualization and typical design procedures. They also know typical examples of successful visualization projects and can explain and evaluate them. They are able to recognize typical problems in the design and development of immersive visualizations and to develop expressive and effective visual representation concepts based on established procedures for multivariate data and to implement and evaluate them using suitable immersive technologies (visualization systems, 3D game engines, frameworks).\n--- Goals (DE) ---\nDie Studierenden kennen die wesentlichen Begriffe der Visualisierung und typische Vorgehensweise beim Entwurf. Sie kennen darüber hinaus typische Beispiele erfolgreicher Visualisierungsprojekte und können diese erläutern und bewerten. Sie sind in der Lage typische Probleme der bei der Gestaltung und Entwicklung immersiver Visualisierungen zu erkennen und auf Basis etablierter Vorgehensweisen  für multivariate Daten expressive und effektive visuelle Darstellungskonzepte zu entwickeln, mittels geeigneter immersiver Technologien (Visualisierungssysteme, 3D gameEngines, Frameworks) zu realisieren und zu bewerten.\n--- Contents (EN) ---\nThe course Immersive Visualization deals with computer-aided methods for the graphical representation of information and data, which are given an immersive character through design and technology. This can be achieved through extensive interaction, XR technologies, projections or large-scale displays. This special visual representation is intended to help evaluate, present and inform data or gain new insights from it. The main contents are \n- Aspects of human visual perception and visualization models:\n- Visualization of multivariate data\n- Workflow and procedure models in the visualization process (visualization pipeline)\n- multimodal interaction concepts, design principles and storytelling \n- Overview of typical visualization systems for real-time applications \n\nThe course will choose a specific topic in each semester offered, which will then be worked on with the participants. External lectures and excursions round off the program.\n--- Contents (DE) ---\nDie Veranstaltung Immersive Visualisierung befasst sich mit computerunterstützten Methoden zur grafischen Repräsentation von Informationen und Daten, die durch Gestaltung und Technologie einen immersiven Charakter erhalten. Das kann durch umfangreiche Interaktion, XR -Technologien, Projektionen oder großflächige Displays erfolgen. Diese besondere bildliche Darstellung soll dabei helfen, Daten auszuwerten, zu präsentieren und informieren bzw. neue Erkenntnisse daraus zu gewinnen. Wesentliche Inhalte sind \n- Aspekte der menschlichen visuellen Wahrnehmung und Modell der Visualisierung:\n- Visualisierung multivariater Daten\n- Workflow und Vorgehensmodelle im Visualisierungsprozess (Visualisierungspipeline)\n- multimodale Interaktionskonzepte, Gestaltungsgrundlagen und Storytelling \n- Überblick typischer Visualisierungssysteme für Echtzeitanwendungen \n\nDie Veranstaltung wird sich in jedem angebotenen Semester ein spezielles Thema wählen, das mit den Teilnehmer:innen dann bearbeitet wird. Externe Vorträge und Exkursionen runden das Angebot ab.\n--- Literature (EN) ---\n--- Literature (DE) ---\n-Chaomei Chen: Information Visualization. Beyond the Horizon. 2. Auflage, Springer London, (2004)\n-Colin Ware: Information Visualization : Perception for Design Morgan Kaufmann Series in Interactive Technologies, San Francisco, (2000)\n-Natha Yau: Visualize This: The Flowing Data Guide to Design, Visualization and Statistics, Wiley, (2011)\n- Cole Nussbaumer Knaflic: Storytelling with Data: A Data Visualization Guide for Business Professionals, Wiley, (2015)", "metadata": {"moduleNumber": "BMI 108", "moduleName": "Immersive Visualisation", "creditPoints": "5.0", "suggestedSemester": 5, "offeredInSeason": "winter_semester", "examType": "project", "heldInLanguage": "de", "reviserName": "Prof. Dr. rer. nat. Christian Geiger", "reviserEmail": "geiger@hs-duesseldorf.de", "studyProgramId": 8, "source_type": "json"}}
{"id": "BMI33", "text": "Title: Fundamentals of Computer Graphics\nModule Number: BMI 33\nCredits: 5.0 CP\nSemester: 3\nOffered In: winter_semester\nLanguage: de\nExam Type: written_exam\nInstructor: Prof. Dr.-Ing. Sina Mostafawy (sina.mostafawy@hs-duesseldorf.de)\n--- Goals (EN) ---\nThe students know the basics of 3D computer graphics, the functionality of the graphics pipeline, local illumoination algorithms and shading techniques and can apply them.\n--- Goals (DE) ---\nDie Student:innen kennen die Grundlagen der 3D Computergrafik, die Funktionsweise der Grafikpipeline, lokale Beleuchtungsmodelle und Shading-Verfahren und können diese anwenden.\n--- Contents (EN) ---\nFixed Graphics Pipeline\nRasterization techniques\nClipping and Culling Algorithms\nMatrix Transformations  (2D/ 3D)\nOrthogonal and Perspective Projektion\nIllumination and Shading Algorithms \nBasics of Beziér interpolation\n--- Contents (DE) ---\nFixed Graphics Pipeline\nRasterization techniques\nClipping and Culling Algorithms\nMatrix Transformations  (2D/ 3D)\nOrthogonal and Perspective Projektion\nIllumination and Shading Algorithms \nBasics of Beziér interpolation\n--- Literature (EN) ---\n--- Literature (DE) ---\nComputer Graphics with OpenGL, D. Hearn, M.P. Baker, Pearson Education I\nAdvanced Animation and Rendering Techniques, Watt, M. Watt, Addison Wesley\nComputergrafik,Xiang, Zhigang; Plastock, Roy mitp/bhv\nFundamentals of Computer Graphics, Shirley P. \nAdvanced Global Illumination, P. Dutré, AK Peters", "metadata": {"moduleNumber": "BMI 33", "moduleName": "Fundamentals of Computer Graphics", "creditPoints": "5.0", "suggestedSemester": 3, "offeredInSeason": "winter_semester", "examType": "written_exam", "heldInLanguage": "de", "reviserName": "Prof. Dr.-Ing. Sina Mostafawy", "reviserEmail": "sina.mostafawy@hs-duesseldorf.de", "studyProgramId": 8, "source_type": "json"}}
{"id": "BMI102", "text": "Title: Advanced Computer Graphics\nModule Number: BMI 102\nCredits: 5.0 CP\nSemester: 4\nOffered In: summer_semester\nLanguage: de\nExam Type: written_exam\nInstructor: Prof. Dr.-Ing. Sina Mostafawy (sina.mostafawy@hs-duesseldorf.de)\n--- Goals (EN) ---\nStudents are familiar with advanced topics in computer graphics, especially in the area of realistic rendering. They will also be able to use sampling methods for rendering processes. They will be able to decide which method is best to use for customer requests. They will also learn how to produce software in a team on the basics of a Raytracer.\n--- Goals (DE) ---\nDie Studenrt:innen kennen weiterführende Themen der Computergrafik, speziell im Bereich des Renderings und realistischen 3D Darstellung. Hinzu kommen der Einsatz von Samplingmethoden für Renderingverfahren. Sie können beurteilen welche Methode für welchen Einsatz am besten einzusetzen ist. Hinzu werden sie lernen ein großes Softwarepacket - einen Raytraycer - gemeinsam mit anderen in der Gruppe zu programmieren.\n--- Contents (EN) ---\n- Theorie und Programming of Raytracing\n- Monte Carlo Principles for Rendering\n- Beziér interpolation, Splines and B-Splines \n- Sampling Methods and Principles for Raytracing \n- Photon Mapping Rendering\n--- Contents (DE) ---\n- Theorie und Programming of Raytracing\n- Monte Carlo Principles for Rendering\n- Beziér interpolation, Splines and B-Splines \n- Sampling Methods and Principles for Raytracing \n- Photon Mapping Rendering\n--- Literature (EN) ---\n- J. D. Foley, A. van Dam: Computer Graphics -Principles und Practice, Addison-Wesley, 1997\n- T. Akenine-Möller, E. Haines: Real Time Rendering, AK Peters, 2002\n- D. Hearn, M.P. Baker: Computer Graphics with OpenGL, Verlag Pearson Education International, 2004\n--- Literature (DE) ---\n- J. D. Foley, A. van Dam: Computer Graphics -Principles und Practice, Addison-Wesley, 1997\n- T. Akenine-Möller, E. Haines: Real Time Rendering, AK Peters, 2002\n- D. Hearn, M.P. Baker: Computer Graphics with OpenGL, Verlag Pearson Education International, 2004", "metadata": {"moduleNumber": "BMI 102", "moduleName": "Advanced Computer Graphics", "creditPoints": "5.0", "suggestedSemester": 4, "offeredInSeason": "summer_semester", "examType": "written_exam", "heldInLanguage": "de", "reviserName": "Prof. Dr.-Ing. Sina Mostafawy", "reviserEmail": "sina.mostafawy@hs-duesseldorf.de", "studyProgramId": 8, "source_type": "json"}}
{"id": "BMI203", "text": "Title: Pencils and Polygons\nModule Number: BMI 203\nCredits: 5.0 CP\nSemester: 4\nOffered In: summer_semester\nLanguage: de\nExam Type: project\nInstructor: Prof. Dr.-Ing. Sina Mostafawy (sina.mostafawy@hs-duesseldorf.de)\n--- Goals (EN) ---\nThe students know the basics of drawing (picture composition, techniques, shading, perspective). They can transfer their knowledge from 2D to 3D modeling and rendering.\n--- Goals (DE) ---\nDie Studierenden erlernen die Grundlagen des Zeichnens. Sie können das Wissen aus dem 2D Zeichnen in die Erstellung von 3D Modelle übertragen (insbesondere Beleuchtung). Sie wissen, in welcher Form der Begriff des Formens sowie Licht und Schatten die Arbeit in der 3D Welt prägen.\n--- Contents (EN) ---\n- Basics of drawing\n- Dynamic and linear lines\n- Hatching techniques\n- Light and shadow\n- Image composition, image division and -perspective\n- Storyboard drawings\n--- Contents (DE) ---\n- Grundlagen des Zeichnens\n- Dynamische und lineare Linie\n- Schraffur Techniken\n- Licht und Schatten\n- Bildkomposition, Bildeinteilung und -perspektive\n- Storyboard Zeichnungen\n--- Literature (EN) ---\n--- Literature (DE) ---\n- F. A. Cerver: Zeichnen für Einsteiger, Konemann Verlag Koln 2002G. Bammes: Studien zur Gestalt des Menschen, 3. Aufl. Urania Verlag 2001", "metadata": {"moduleNumber": "BMI 203", "moduleName": "Pencils and Polygons", "creditPoints": "5.0", "suggestedSemester": 4, "offeredInSeason": "summer_semester", "examType": "project", "heldInLanguage": "de", "reviserName": "Prof. Dr.-Ing. Sina Mostafawy", "reviserEmail": "sina.mostafawy@hs-duesseldorf.de", "studyProgramId": 8, "source_type": "json"}}
{"id": "BMI103", "text": "Title: Virtual Reality and Augmented Reality\nModule Number: BMI 103\nCredits: 5.0 CP\nSemester: 4\nOffered In: winter_semester\nLanguage: en_on_demand\nExam Type: portfolio\nInstructor: Prof. Dr. Eng. Univ. of Tsukuba Jens Herder (jens.herder@hs-duesseldorf.de)\n--- Goals (EN) ---\nSuccessful participants will have a profound knowledge in building and developing virtual environments and will be able to evaluate application based on vr technology.\n--- Goals (DE) ---\nDie Studierenden kennen die wichtigsten VR-Technologien und sind in der Lage, virtuelle Umgebungen zu konzipieren, aufzubauen und in der Anwendung zu bewerten.\n--- Contents (EN) ---\n- Motivation, definitions, Layout and design of virtual environment\n- Application fields\n- Human factors in virtual environments\n- Augmented Reality\n- Display systems (e.g., stereo projection)\n- Input and output devices\n- Scene modeling (scene graph based)\n- Data structures and algorithms\n- Simulation\n- Programming of virtual environments\n- Tracking for user interaction\n- Navigation and Interaction in VR\n- Real-time rendering and special effects\n- Haptics\n- Virtual acoustics\n--- Contents (DE) ---\n- Motivation / Begriffsdefinition / Aufbau virtueller Umgebungen\n- Aktuelle Anwendungsgebiet\n- Wahrnehmungsfaktoren für virtuellen Umgebungen\n- Augmented Reality\n- Darstellungstechniken (u.a. stereographische Projektion)\n- Ein- und Ausgabegeräte\n- 3D-Szenenmodellierung\n- Datenstrukturen und Algorithmen für Virtuelle Umgebungen\n- Simulation in virtuellen Umgebungen\n- Entwurf und Programmierung virtueller Umgebungen\n- Tracking von Benutzern und Objekten in VR-Umgebungen\n- Navigation und Interaktion in VR\n- Visuelle Effekte in Echtzeit (u.a. Schatten)\n- Haptik\n- Virtuelle Akustik\n- Nicht-visuelle Repräsentation in Virtuellen Umgebungen\n--- Literature (EN) ---\n- Ralf Dörner, Wolfgang Broll, Paul Grimm, Bernhard Jung, Virtual and Augmented Reality (VR/AR), Foundations and Methods of Extended Realities (XR), Springer, 2022, DOI 10.1007/978-3-030-79062-2\n- Jason Jerald. The VR Book: Human-Centered Design for Virtual Reality. Association for Computing Machinery and Morgan & Claypool, New York, NY, USA, 2015, DOI 10.1145/2792790\n- G. C. Burdea, P. Coiffet: Virtual Reality Technology, John Wiley & Sons, 3. Edition, 2024, ISBN 978-1-118-01480-6\n- M. Guiterrez, F. Vexo, D. Thalman: Stepping into Virtual Reality, Springer Nature Publisher, 2. Edition, 2023, DOI 10.1007/978-3-031-36487-7\n- W. Sherman, A. Craig: Understanding Virtual Reality - Interface, Application, and Design, Morgan Kaufman, 2. Edition 2018, DOI 10.1016/C2013-0-18583-2\n- J. Vince: Introduction to Virtual Reality, Springer 2004, DOI 10.1007/978-0-85729-386-2\n- J. Blauert: Spatial Hearing - The Psychophysics of Human Sound Localization, The MIT Press, Revised Edition, ISBN 0-262-02413-6, 1996\n\nFurther recent literature will be announced at the beginning of the course.\n--- Literature (DE) ---\n- R. Dörner, W. Broll, P. Grimm, B. Jung (Hrsg.), Virtual und Augmented Reality (VR/AR), Grundlagen und Methoden der Virtuellen und Augmentierten Realität, Springer, 2014, DOI 10.1007/978-3-642-28903-3\n- Jason Jerald. The VR Book: Human-Centered Design for Virtual Reality. Association for Computing Machinery and Morgan & Claypool, New York, NY, USA. 2015, DOI 10.1145/2792790\n- G. C. Burdea, P. Coiffet: Virtual Reality Technology, John Wiley & Sons, 3. Auflage, 2024, ISBN 978-1-118-01480-6\n- M. Guiterrez, F. Vexo, D. Thalman: Stepping into Virtual Reality, Springer Nature Verlag, 2. Ausgabe, 2023, DOI 10.1007/978-3-031-36487-7\n- W. Sherman, A. Craig: Understanding Virtual Reality - Interface, Application, and Design, Morgan Kaufman, 2. Auflage, 2018, DOI 10.1016/C2013-0-18583-2\n- J. Vince: Introduction to Virtual Reality, Springer 2004, DOI 10.1007/978-0-85729-386-2\n- J. Blauert: Spatial Hearing - The Psychophysics of Human Sound Localization, The MIT Press, Revised Edition, ISBN 0-262-02413-6, 1996\n\nWeitere aktuelle Literatur wird zu Beginn der LV bekannt gegeben.", "metadata": {"moduleNumber": "BMI 103", "moduleName": "Virtual Reality and Augmented Reality", "creditPoints": "5.0", "suggestedSemester": 4, "offeredInSeason": "winter_semester", "examType": "portfolio", "heldInLanguage": "en_on_demand", "reviserName": "Prof. Dr. Eng. Univ. of Tsukuba Jens Herder", "reviserEmail": "jens.herder@hs-duesseldorf.de", "studyProgramId": 8, "source_type": "json"}}
{"id": "BMI72", "text": "Title: Bachelor's Thesis and Colloquium\nModule Number: BMI 72\nCredits: 15.0 CP\nSemester: 7\nOffered In: winter_semester\nLanguage: en_on_demand\nExam Type: bachelor_thesis_and_colloquium\nInstructor: Prof. Dr.-Ing. Thomas Rakow (thomas.rakow@hs-duesseldorf.de)\n--- Goals (EN) ---\nStudents can work independently on a media informatics task using scientific and engineering methods with a time limit under the guidance of the lecturer. They will be able to present their work in a colloquium and present it in a demonstration in the case of development tasks.\n--- Goals (DE) ---\nDie Studierenden können selbstständig eine Aufgabenstellung der Medieninformatik mit wissenschaftlichen und ingenieurgemäßen Mitteln mit Zeitbeschränkung unter Anleitung des/ der Dozenten/ in bearbeiten. Sie können ihre Bearbeitung der Aufgabenstellung unter fachlicher und wissenschaftlicher Einordnung präsentieren in einem Kolloquium verteidigen sowie bei Entwicklungsaufgaben in einer Demonstration vorstellen.\n--- Contents (EN) ---\nThe following tasks are covered:\nPlanning the processing\nProcessing the task\ndocumentation\nPresentation and, if necessary, demonstration in a colloquium\n--- Contents (DE) ---\nFolgende Aufgaben werden behandelt:\nPlanung der Bearbeitung\nBearbeitung der Aufgabenstellung\nDokumentation\nPräsentation und ggf. Demonstration in einem Kolloquium\n--- Literature (EN) ---\n--- Literature (DE) ---\nje nach gewählter Aufgabenstellung", "metadata": {"moduleNumber": "BMI 72", "moduleName": "Bachelor's Thesis and Colloquium", "creditPoints": "15.0", "suggestedSemester": 7, "offeredInSeason": "winter_semester", "examType": "bachelor_thesis_and_colloquium", "heldInLanguage": "en_on_demand", "reviserName": "Prof. Dr.-Ing. Thomas Rakow", "reviserEmail": "thomas.rakow@hs-duesseldorf.de", "studyProgramId": 8, "source_type": "json"}}
{"id": "BMI71", "text": "Title: Scientific Specialisation\nModule Number: BMI 71\nCredits: 10.0 CP\nSemester: 7\nOffered In: winter_semester\nLanguage: en_on_demand\nExam Type: research_paper\nInstructor: Prof. Dr.-Ing. Thomas Rakow (thomas.rakow@hs-duesseldorf.de)\n--- Goals (EN) ---\nStudents are proficient in dealing with scientific information sources (both in German and English), can cite them correctly and use them to determine the state of the art in research and technology as well as to analyse and plan their own tasks. Students are able to see their own work in the context of the subject area and to communicate appropriately in written and oral form.\n--- Goals (DE) ---\nDie Studierenden beherrschen den Umgang mit wissenschaftlichen Informationsquellen (sowohl deutsch- als auch englischsprachig), können diese korrekt zitieren und sie dazu nutzen, den Stand der Forschung und Technik zu ermitteln sowie eigene Aufgabenstellungen zu analysieren und zu planen. Die Studierenden sind in der Lage, eigene Arbeiten im Kontext des fachlichen Umfeldes zu sehen und in angemessener Form schriftlich und mündlich zu kommunizieren.\n--- Contents (EN) ---\nStudents work on the following tasks under supervision for a special topic from media informatics:familiarisation with the question,research for relevant sources of information (scientific publications, specialist books, standards, etc.),content analysis of the sources of information,compilation of the results in a paper,presentation of the topic.\n--- Contents (DE) ---\nDie Studierenden bearbeiten unter Anleitung für ein spezielles Thema aus der Medieninformatik folgende Aufgaben:Einarbeitung in die Fragestellung,Recherche nach relevanten Informationsquellen (wissenschaftliche Veröffentlichungen, Fachbücher, Standards, etc.),Inhaltliche Analyse der Informationsquellen,Zusammenstellung der Ergebnisse in einer Ausarbeitung,Präsentation des Themas.\n--- Literature (EN) ---\n--- Literature (DE) ---\nH. Balzert, M. Schröder, C. Schäfer,: Wissenschaftliches Arbeiten, 2. Aufl. W3L, 2011 \nD. Veit: Die wissenschaftliche Arbeit. Hanser 2022. \nA. Hänsch, D. Alewell: Wissenschaftliches Arbeiten, De Gruyter Oldenbourg, 2020. \nU. Bucher, K. Holzweißig, M. Schwarzer: Künstliche Intelligenz und wissenschaftliches Arbeiten. Vahlen 2023.", "metadata": {"moduleNumber": "BMI 71", "moduleName": "Scientific Specialisation", "creditPoints": "10.0", "suggestedSemester": 7, "offeredInSeason": "winter_semester", "examType": "research_paper", "heldInLanguage": "en_on_demand", "reviserName": "Prof. Dr.-Ing. Thomas Rakow", "reviserEmail": "thomas.rakow@hs-duesseldorf.de", "studyProgramId": 8, "source_type": "json"}}
{"id": "BMI100", "text": "Title: E-Business\nModule Number: BMI 100\nCredits: 5.0 CP\nSemester: 5\nOffered In: winter_semester\nLanguage: de\nExam Type: portfolio\nInstructor: Prof. Dr.-Ing. Thomas Rakow (thomas.rakow@hs-duesseldorf.de)\n--- Goals (EN) ---\nThe students know the participants and processes of e-business and can apply their knowledge to their tasks. You can analyze, develop and present e-business tasks in a team.\n--- Goals (DE) ---\nDie Studierenden kennen die Beteiligten und Prozesse des E-Business und können ihre Kenntnisse in dessen Aufgabenstellungen anwenden. Sie können im Team Aufgabenstellungen des E-Business analysieren, entwickeln und präsentieren.\n--- Contents (EN) ---\nDevelopment of e-business and the Web\nData privacy and security\nProducts and services on the Web: business models, e-shops, e-marketplaces, online publications\nMarketplaces on the Web: e-marketplaces, procurement on the Web, Web services, REST/SOAP\nOnline marketing: development model for online customers, methods, key figures, cooperations, web analytics & control\nDigital supply chain: distribution, value chain, rights protection, online payment, mobile devices\nCustomer relationship: customer relationship management, customer evaluation, data management, data analysis, customer communication\n--- Contents (DE) ---\nEntwicklung des E-Business und des Web \nDatenschutz und -sicherheit\nProdukte und Dienstleistungen im Web: Geschäftsmodelle, E-Shops, E-Marktplätze, Online-Publikationen\nMarktplätze im Web: E-Marktplätze, Beschaffung im Web, Web-Services, REST/ SOAP \nOnline-Marketing: Entwicklungsmodell für Online-Kunden, Methoden, Kennzahlen, Kooperationen, Web Analytics & Control\nDigitale Lieferkette: Distribution, Wertekette, Rechteschutz, Online-Bezahlung, mobile Geräte\nKundenbeziehung: Customer-Relationship-Management, Kundenbewertung, Datenverwaltung, Datenanalyse, Kundenkommunikation\n--- Literature (EN) ---\n--- Literature (DE) ---\nKollmann, Tobias: E-Business - Grundlagen elektronischer Geschäftsprozesse in der Net Economy, 6. Auflage, Gabler, Wiesbaden 2016.\nMeier, Andreas, Stormer, Henrik: eBusiness & eCommerce - Management der digitalen Wertschöpfungskette, 3. Aufl., Springer, 2012.\nWirtz, Bernd: Electronic Business - Wertschöpfung im Online-Geschäft, 5. Auflage, Gabler, Wiesbaden, 2016", "metadata": {"moduleNumber": "BMI 100", "moduleName": "E-Business", "creditPoints": "5.0", "suggestedSemester": 5, "offeredInSeason": "winter_semester", "examType": "portfolio", "heldInLanguage": "de", "reviserName": "Prof. Dr.-Ing. Thomas Rakow", "reviserEmail": "thomas.rakow@hs-duesseldorf.de", "studyProgramId": 8, "source_type": "json"}}
{"id": "BMI107", "text": "Title: Computer Animation\nModule Number: BMI 107\nCredits: 5.0 CP\nSemester: 5\nOffered In: winter_semester\nLanguage: de\nExam Type: oral_exam\nInstructor: Prof. Dr.-Ing. Sina Mostafawy (sina.mostafawy@hs-duesseldorf.de)\n--- Goals (EN) ---\nThe students master general and special procedures in the field of computer animation.Theoretical and mathematical basics of 3D animation.Various methods of data acquisition and data generation for animations.Real-time rendering vs. classic rendering methods. Additionally they will learn to prepare and give a presentation about a scientific topic of computeranimation.\n--- Goals (DE) ---\nDie Student:innen beherrschen allgemeine und spezielle Verfahren aus dem Bereich der Computeranimation. Theoretisch-mathematische Grundlagen der 3D-Animation, verschiedene Verfahren der Datenerzeugung für Animationen und Echtzeitrendering. Zusätzlich wird ein dem Kurs gelernt wie ein Vortrag recherchiert, vorbereitet und vor Publikum gehlaten wird.\n--- Contents (EN) ---\n- 12 Basic Principles of Animation \n- Rotation with Quaternions\n- Forward and Inverse Kinematics\n- Partikelanimation and Swarm Simulation\n- Deformation & Morphing Algorithms\n- Rigid- und Soft Bodies\n- Planing und Production of Animations\n--- Contents (DE) ---\n- 12 Basic Principles of Animation \n- Rotation with Quaternions\n- Forward and Inverse Kinematics\n- Partikelanimation and Swarm Simulation\n- Deformation & Morphing Algorithms\n- Rigid- und Soft Bodies\n- Planing und Production of Animations\n--- Literature (EN) ---\n- Computer Animation: Algorithms and Techniques, Rick Parent, 3rd 2012 \n- Advanced Animation and Renderning Techniques: Alan Watt, Mark Watt, Addision Wesley\n- Real-Time Rendering, Eric Haines, 4th 2020Computer Graphics with Open GL, Pearson Prentice Hall, 4th 2013\n--- Literature (DE) ---\n- Computer Animation: Algorithms and Techniques, Rick Parent, 3rd 2012 \n- Advanced Animation and Renderning Techniques: Alan Watt, Mark Watt, Addision Wesley\n- Real-Time Rendering, Eric Haines, 4th 2020Computer Graphics with Open GL, Pearson Prentice Hall, 4th 2013", "metadata": {"moduleNumber": "BMI 107", "moduleName": "Computer Animation", "creditPoints": "5.0", "suggestedSemester": 5, "offeredInSeason": "winter_semester", "examType": "oral_exam", "heldInLanguage": "de", "reviserName": "Prof. Dr.-Ing. Sina Mostafawy", "reviserEmail": "sina.mostafawy@hs-duesseldorf.de", "studyProgramId": 8, "source_type": "json"}}
{"id": "BMI201", "text": "Title: Company Formation\nModule Number: BMI 201\nCredits: 5.0 CP\nSemester: 5\nOffered In: winter_semester\nLanguage: de\nExam Type: research_paper\nInstructor: Prof. Dr.-Ing. M.Sc. Markus Dahm (markus.dahm@hs-duesseldorf.de)\n--- Goals (EN) ---\nAfter successfully completing the module, students know and understand basic business terms and approaches that enable them to develop a business idea in the form of a business plan. They are able to analyse and evaluate the strengths and weaknesses of a business model in order to develop a target-oriented competitive strategy on this basis\n--- Goals (DE) ---\nNach erfolgreicher Teilnahme am Modul kennen und verstehen die Studierenden grundlegende betriebswirtschaftliche Begriffe und Ansätze, die sie dazu befähigen, eine Geschäftsidee in Form eines Business Plans zu entwickeln. Sie sind in der Lage Stärken und Schwächen eines Geschäftsmodells zu analysieren und zu bewerten, um auf dieser Grundlage eine zielführende Wettbewerbsstrategie entwickeln zu können\n--- Contents (EN) ---\n- Descriptive parameters of a business model\n- Competition analysis\n- Target group analysis\n- SWOT analysis\n- Turnover/sales planning\n- P&L planning\n- Calculation of cost of goods sold\n- Financial planning\n- Determination of capital requirements (balance sheet) and financing\n- Choice of legal form\n--- Contents (DE) ---\n- Deskriptive Parameter eines Geschäftsmodells\n- Wettbewerbsanalyse\n- Zielgruppenanalyse\n- SWOT-Analyse\n- Umsatz-/Absatzplanung\n- GuV-Planung\n- Kalkulation der Selbstkosten\n- Finanzplanung\n- Kapitalbedarfsermittlung (bilanziell) und Finanzierung\n- Rechtsformwahl\n--- Literature (EN) ---\n- Kollmann, T.: E-Entrepreneurship. Grundlagen der Unternehmensgründung in der digitalen Wirtschaft. München, 2016\n- neuesunternehmertum.de (Materialien zur Erstellung eines Business Plans)\n- Osterwalder, L. et al.: Value Proposition Design: Entwickeln Sie Produkte und Services, die Ihre Kunden wirklich wollen. Frankfurt a.M., 2015\n- Ries, E.: Lean-Startup. Schnell, risikolos und erfolgreich Unternehmengründen. München, 2014\n--- Literature (DE) ---\n- Kollmann, T.: E-Entrepreneurship. Grundlagen der Unternehmensgründung in der digitalen Wirtschaft. München, 2016\n- neuesunternehmertum.de (Materialien zur Erstellung eines Business Plans)\n- Osterwalder, L. et al.: Value Proposition Design: Entwickeln Sie Produkte und Services, die Ihre Kunden wirklich wollen. Frankfurt a.M., 2015\n- Ries, E.: Lean-Startup. Schnell, risikolos und erfolgreich Unternehmengründen. München, 2014", "metadata": {"moduleNumber": "BMI 201", "moduleName": "Company Formation", "creditPoints": "5.0", "suggestedSemester": 5, "offeredInSeason": "winter_semester", "examType": "research_paper", "heldInLanguage": "de", "reviserName": "Prof. Dr.-Ing. M.Sc. Markus Dahm", "reviserEmail": "markus.dahm@hs-duesseldorf.de", "studyProgramId": 8, "source_type": "json"}}
{"id": "BMI106", "text": "Title: Software Architecture\nModule Number: BMI 106\nCredits: 5.0 CP\nSemester: 4\nOffered In: summer_semester\nLanguage: de\nExam Type: research_paper\nInstructor: Prof. Dr. Thomas Franz (thomas.franz@hs-duesseldorf.de)\n--- Goals (EN) ---\n--- Goals (DE) ---\nDie Studierenden haben Kenntnisse über die Zielsetzung, den Einsatzweck und die Teildisziplinen der Software Architektur. Sie kennen Architekturstile, Architektursichten und Kriterien für die Bewertung von Software-Architekturen.\nSie können Architekturen für verschiedene Arten von IT-Systemen unter Verwendung ausgewählter Architekturmuster entwerfen, visualisieren und dokumentieren sowie Architekturentscheidungen präsentieren und verteidigen.\n--- Contents (EN) ---\n--- Contents (DE) ---\n- Software-Architektur in Abgrenzung zu Enterprise-Architektur und OO-Modellierung.\n- Rollenbild Software-Architekt:in\n- Architektur-Sichten\t\n- Agile Software Architekturarbeit\n- Architekturstile\n- Architektur-Dokumentation\n- Architektur-Bewertung\n- Architekturentscheidungen\n- Architektur-Template arc42\n--- Literature (EN) ---\n--- Literature (DE) ---\n- Starke, Gernot, Arne Koschel, Andreas Rausch, und Mahbouba Gharbi. 2023. Basiswissen für Softwarearchitekten: Aus- und Weiterbildung nach iSAQB-Standard zum Certified Professional for Software Architecture  Foundation Level. Überarbeitete und aktualisierte Auflage. Heidelberg: dpunkt.verlag.\n- Starke, Gernot, und Peter Hruschka. 2011. Software-Architektur kompakt:  angemessen und zielorientiert. 2. Aufl. Heidelberg: Spektrum Akademischer Verlag. https://doi.org/10.1007/978-3-8274-2835-6.\n- Khononov, Vlad, und Thomas Demmig. 2022. Einführung in Domain-Driven Design: Von der Buisness-Strategie zum technischen Design. Auflage. Heidelberg: OReilly Verlag.\n- Richards, Mark, und Neal Ford. 2020. Handbuch moderner Softwarearchitektur: Architekturstile, Patterns und Best Practices. Heidelberg: OReilly Verlag.\n- Vernon, V., Henning Schwentner, & Schwentne, H. (2017). Domain-Driven Design kompakt: Aus dem Englischen übersetzt von Carola Lilienthal und Henning Schwentner. dpunkt.verlag.", "metadata": {"moduleNumber": "BMI 106", "moduleName": "Software Architecture", "creditPoints": "5.0", "suggestedSemester": 4, "offeredInSeason": "summer_semester", "examType": "research_paper", "heldInLanguage": "de", "reviserName": "Prof. Dr. Thomas Franz", "reviserEmail": "thomas.franz@hs-duesseldorf.de", "studyProgramId": 8, "source_type": "json"}}
{"id": "BMI208", "text": "Title: Blue Science\nModule Number: BMI 208\nCredits: 5.0 CP\nSemester: 5\nOffered In: winter_semester\nLanguage: de\nExam Type: portfolio\nInstructor: Prof. Dr. Alina Huldtgren (alina.huldtgren@hs-duesseldorf.de)\n--- Goals (EN) ---\n--- Goals (DE) ---\nNach erfolgreichem Abschluss des Moduls sind die\nStudierenden in der Lage, Technik kritisch zu beurteilen. Sie\nkönnen das Wechselverhältnis von Technik, Natur, Individuum\nund Gesellschaft reflektieren. Sie können mit anderen für eine\ndemokratische Entscheidungsfindung im Hinblick auf Prozess,\nErgebnis und Umsetzung kooperieren. Das Entscheidungs-\ndilemma, das sich aus individueller und gesellschaftlicher\nVerantwortung ergibt, können sie bewältigen.\nAuswirkungen und Risiken von Technik auf Natur und\nGesellschaft können antizipiert werden.\n--- Contents (EN) ---\n--- Contents (DE) ---\nTechnik als Problemlöser!? Kritische Theorie und ihre\nAnwendung auf Technik\n- Plastik und seine lokalen und globalen Auswirkungen\n- Soziale und Ökologische Dimension von Technik\n- Ambivalenzen technologischer Entwicklungen\n- Konzepte alternativer wirtschaftender Unternehmen, wie\nz.B. Genossenschaften\n- Beruf und Berufseinstieg, Arbeitsbedingungen und\nGewerkschaften\n- Betriebliche Organisation\n- Gesellschaftliche Bedeutung der Informatik\n- Verantwortungsvolles Handeln in der Technikentwicklung\n--- Literature (EN) ---\n--- Literature (DE) ---\n- Demirovi, Alex. Demokratie in der Wirtschaft:\nPositionen-Probleme-Perspektiven. Westfälisches\nDampfboot, 2007.\n- Hänggi, Marcel. Fortschrittsgeschichten: für einen guten\nUmgang mit Technik. S. Fischer Verlag, 2015.\n Kornwachs, Klaus: Philosophie für Ingenieure. Hanser,\n2018.\n- Noble, David F. Forces of production: A social history of\nindustrial automation. Alfred A. Knopf, 1984.\n- Scheidler, Fabian. Das Ende der Megamaschine:\nGeschichte einer scheiternden Zivilisation. Promedia, 2015.\n- Ullrich, Otto. Technik und Herrschaft: vom Handwerk\nzur verdinglichten Blockstruktur industrieller Produktion.\nSuhrkamp, 1979.", "metadata": {"moduleNumber": "BMI 208", "moduleName": "Blue Science", "creditPoints": "5.0", "suggestedSemester": 5, "offeredInSeason": "winter_semester", "examType": "portfolio", "heldInLanguage": "de", "reviserName": "Prof. Dr. Alina Huldtgren", "reviserEmail": "alina.huldtgren@hs-duesseldorf.de", "studyProgramId": 8, "source_type": "json"}}
{"id": "BMI14", "text": "Title: Work techniques\nModule Number: BMI 14\nCredits: 5.0 CP\nSemester: 1\nOffered In: winter_semester\nLanguage: de\nExam Type: written_exam\nInstructor: Prof. Dr. Thomas Franz (thomas.franz@hs-duesseldorf.de)\n--- Goals (EN) ---\n--- Goals (DE) ---\nDie Studierenden können ihr Studium organisieren und die eigene Arbeitseffizienz steigern. Sie erlernen die Grundlagen des professionellen Arbeitens anhand verschiedener Medien. Sie können Verfahren und Werkzeuge zur Planung und Durchführung von Projekten im IT-Bereich anwenden.\n\n- Grundlegende Fähigkeit zu selbständigem Arbeiten (Orientierung in unbekannten inhaltlichen Kontexten, Einordnung von Inhalten, Strukturierung eigener Ergebnisse und Gedanken)\n- Grundlegende Kenntniss und Anwendungskompetenz für die Nutzung verteilter Versionsverwaltungskonzepte (insbesondere GIT)\n- Grundlegende Kenntnis und Anwendungskompetenz für die Nutzung elementarer Funktionen von Entwicklungsplattformen (z.B. Github, Gitlab o.ä.), beispielsweise die Nutzung von Issues, Wikis\n--- Contents (EN) ---\n--- Contents (DE) ---\n- Motivation, Ziele, Eigenmanagement: Eigenmotivation, Eigenmanagement und Eigeninitiative im Studium, Orientierung und persönliche Zielsetzung, Selbstorganisation im Studium\n- Lernen und behalten: Gedächtnis, Gedächtnistraining, Wiederholung von Lerninhalten, intrinsische und extrinsische Motivation, Visualisierung von Lerninhalten, Lesetechniken\n- Recherchieren und präsentieren: Literaturrecherche, Identifikation vertrauenswürdiger Quellen, Benutzung von Literaturdatenbanken, Aufbau und Struktur von Präsentationen, Zielsetzung bei der Erstellung von Präsentationen, Präsentationstypen und persönliche Einordnung, Umgang mit Präsentationsblockaden, Nervosität, usw., Tipps für souveräne Präsentationen\n- Lernprozess und Selbstdisziplin: Schaffen eines geeigneten Lernklimas, Identifikation von Lernblockaden, Verbesserung von Lernphasen, Lerntypentest / Identifikation von Arbeitspartnern\n- Grundlegendes Projektmanagement\n- Grundlegende Konzepte der verteilten Versionsverwaltung von Programmcode\n- Grundlegende Konzepte von Software-Entwicklungsplattformen für verteilte Teams\n--- Literature (EN) ---\n--- Literature (DE) ---", "metadata": {"moduleNumber": "BMI 14", "moduleName": "Work techniques", "creditPoints": "5.0", "suggestedSemester": 1, "offeredInSeason": "winter_semester", "examType": "written_exam", "heldInLanguage": "de", "reviserName": "Prof. Dr. Thomas Franz", "reviserEmail": "thomas.franz@hs-duesseldorf.de", "studyProgramId": 8, "source_type": "json"}}
{"id": "BMI23", "text": "Title: Web Programming 2\nModule Number: BMI 23\nCredits: 5.0 CP\nSemester: 2\nOffered In: summer_semester\nLanguage: de\nExam Type: written_exam\nInstructor: Prof. Dr. Manfred Wojciechowski (manfred.wojciechowski@hs-duesseldorf.de)\n--- Goals (EN) ---\nThe student is able to develop a simple full-stack web application based on the technology stack presented. The student understands the architecture and the essential components and technologies of such an application. The student can name and describe essential concepts, e.g. layer architecture, UI component model, state management, routing, ...\n--- Goals (DE) ---\nDer Studierende ist in der Lage eine einfache Fullstack-Webanwendung auf Basis des vorgestellten Technologiestacks zu entwickeln. Der Studierende versteht die Architektur und die wesentlichen Komponenten und Technologien einer solcher Anwendung. Der Studierende kann wesentliche Konzepte darin benennen und beschreiben, z.B. Schichtenarchitektur, UI-Komponentenmodell, Zustandsverwaltung, Routing,\n--- Contents (EN) ---\nLecture:\n- Introduction to full stack web development\n- Introduction to TypeScript\n- Introduction to a web framework\n- Structure of a server backend architecture\n- Development of a frontend\n- Communication between front and backend\n- Integration of additional tools and libraries\n- Deployment and provisioning\n\nLab work\nDevelopment of a simple full-stack web application using the given technologystack\nInternship:\nDevelopment of a simple full-stack web application based on the presented technology stack.\n--- Contents (DE) ---\nVorlesung\n- Einführung in die Fullstack-Webentwicklung\n- Einführung in TypeScript\n- Einführung in ein Web-Frameworks\n- Aufbau einer Server-Backend-Architektur\n- Entwicklung eines Frontends\n- Kommunikation zwischen Front- und Backend\n- Integration von zusätzlichen Tools und Bibliotheken\n- Deployment und Bereitstellung\n\nPraktikum:\nEntwicklung einer einfachen Fullstack-Webanwendung auf Basis des vorgestellten Technologiestacks.\n--- Literature (EN) ---\nWill be given in the lecture\n--- Literature (DE) ---\nWird in der Vorlesung gegeben", "metadata": {"moduleNumber": "BMI 23", "moduleName": "Web Programming 2", "creditPoints": "5.0", "suggestedSemester": 2, "offeredInSeason": "summer_semester", "examType": "written_exam", "heldInLanguage": "de", "reviserName": "Prof. Dr. Manfred Wojciechowski", "reviserEmail": "manfred.wojciechowski@hs-duesseldorf.de", "studyProgramId": 8, "source_type": "json"}}
{"id": "BMI40", "text": "Title: Artificial Intelligence and Data Science\nModule Number: BMI 40\nCredits: 5.0 CP\nSemester: 4\nOffered In: summer_semester\nLanguage: de\nExam Type: written_exam\nInstructor: Prof. Dr. Dennis Müller (dennis.mueller@hs-duesseldorf.de)\n--- Goals (EN) ---\nUpon successful completion of the module, students are able to\n\nDetermine regression and classification models using linear and logistic methods,\n\nFind linear separating hyperplanes in high-dimensional spaces using a kernelized support vector machine,\n\nSelect different loss functions for optimizing regression problems purposefully and solve the resulting optimization problem,\n\nIdentify and interpret important metrics and measures (e.g., accuracy, precision, recall) of classification models,\n\nIndependently train perceptrons and multilayer neural networks using appropriate methods,\n\nImplement and train simple neural networks in PyTorch using training data.\n--- Goals (DE) ---\nMit dem erfolgreichen Absolvieren des Moduls sind Studierende in der Lage\n\nRegressions- und Klassifikationsmodelle mit Hilfe linearer sowie logistischer Methoden zu bestimmen,\n\nLineare Trennebenen in hochdimensionalen Räumen mit Hilfe einer kernelisierten Support-Vektor-Maschine zu finden,\n\nUnterschiedliche Loss-Funktionen zur Optimierung von Regressionsproblemen zielgerichtet auszuwählen und das sich daraus ergebende Optimierungsproblem zu lösen,\n\nWichtige Kenngrößen und Metriken (z.B. Accuracy, Precision, Recall) von Klassifikationsmodellen zu ermitteln und zu interpretieren,\n\nPerzeptronen- und mehrschichtige neuronale Netzwerke unter Einsatz geeigneter Verfahren selbstständig zu trainieren,\n\neinfache neuronale Netzwerke in PyTorch zu implementieren und anhand von Trainingsdaten zu trainieren.\n--- Contents (EN) ---\nHistory of artificial intelligence / knowledge-based systems\nLinear regression and linear classification\nKernel methods for regression and classification in high-dimensional spaces\nSupport vector machines\nLoss functions and metrics\nPerceptrons and neural networks\nBackpropagation and delta learning rule\nPractical application in Python and PyTorch\n--- Contents (DE) ---\nGeschichte der künstlichen Intelligenz / wissensbasierter Systeme\nLineare Regression und lineare Klassifikation\nKernelmethoden zur Regression und Klassifikation in hochdimensionalen Räumen\nSupport Vektor Maschinen\nLoss-Funktionen und Metriken\nPerzeptronen- und Neuronalenetzwerke\nBackpropagation und Delta-Lernregel\nPraktische Anwendung in Python und PyTorch\n--- Literature (EN) ---\nRussell, S. J., & Norvig, P. (2020). Artificial Intelligence: A Modern Approach (4th ed.). Pearson.\nDomingos, P. (2015). The Master Algorithm: How the Quest for the Ultimate Learning Machine Will Remake Our World. Basic Books.\nMitchell, T. M. (1997). Machine Learning. McGraw-Hill.\nGoodfellow, I., Bengio, Y., & Courville, A. (2016). Deep Learning. MIT Press.\nTegmark, M. (2017). Life 3.0: Being Human in the Age of Artificial Intelligence. Knopf.\n--- Literature (DE) ---\nRussell, S. J., & Norvig, P. (2020). Artificial Intelligence: A Modern Approach (4th ed.). Pearson.\nDomingos, P. (2015). The Master Algorithm: How the Quest for the Ultimate Learning Machine Will Remake Our World. Basic Books.\nMitchell, T. M. (1997). Machine Learning. McGraw-Hill.\nGoodfellow, I., Bengio, Y., & Courville, A. (2016). Deep Learning. MIT Press.\nTegmark, M. (2017). Life 3.0: Being Human in the Age of Artificial Intelligence. Knopf.", "metadata": {"moduleNumber": "BMI 40", "moduleName": "Artificial Intelligence and Data Science", "creditPoints": "5.0", "suggestedSemester": 4, "offeredInSeason": "summer_semester", "examType": "written_exam", "heldInLanguage": "de", "reviserName": "Prof. Dr. Dennis Müller", "reviserEmail": "dennis.mueller@hs-duesseldorf.de", "studyProgramId": 8, "source_type": "json"}}
{"id": "BMI45", "text": "Title: Mobile Applications\nModule Number: BMI 45\nCredits: 5.0 CP\nSemester: 4\nOffered In: summer_semester\nLanguage: de\nExam Type: written_exam\nInstructor: None Philipp Krieter (philipp.krieter@hs-duesseldorf.de)\n--- Goals (EN) ---\n- Forms of mobility (device, service, user)\n- Mobile radio technologies (radio technology)\n- Mobile radio systems and protocols (e.g. GSM, UMTS, LTE, 5G)\n- Mobile devices (mobile phone, tablet, smartphone, VR/AR)\n- Mobile services (e.g. SMS, LBS, added value)\n- Mobile applications (e.g. Android, WebApps)\n- Mobile business (mCommerce, mPayment)\n- Mobile content (e.g. information, games)\n- Mobile usability / UX\n- Mobile social impact (technology assessment)\n--- Goals (DE) ---\n- Mobilitätsformen (Gerät, Dienst, Benutzer)\n- Mobilfunk-Technologien (Funktechnik)\n- Mobilfunk-Systeme und Protokolle (z.B. GSM, UMTS, LTE, 5G)\n- Mobile Geräte (Handy, Tablet, Smartphone, VR/AR)\n- Mobile Dienste (z.B. SMS, LBS, Mehrwert)\n- Mobile Anwendungen (z.B. Android, WebApps)\n- Mobile Business (mCommerce, mPayment)\n- Mobile Content (z.B. Information, Spiele)\n- Mobile Usability / UX\n- Mobile Soziale Auswirkungen (Technikfolgenabschätzung)\n--- Contents (EN) ---\nStudents understand the technical fundamentals of mobile systems - both mobile devices and the infrastructure - and their impact on the use and development of mobile applications. \nThey are familiar with various mobile services and know how they can be linked to business models. \nStudents will be familiar with typical mobile devices and some of the options for developing customised applications for them, taking into account the special characteristics of the mobile usage context.\n--- Contents (DE) ---\nStudierende verstehen die technischen Grundlagen mobiler Systeme - sowohl der mobilen Geräte als auch der Infrastruktor - und ihre Auswirkungen auf die Nutzung und die Entwicklung mobiler Anwendungen. \nSie kennen verschiedene mobile Dienste und wissen, wie sie mit Geschäftsmodellen verknüpft werden können. \nDie Studierenden kennen typische mobile Geräte sowie einige Möglichkeiten, darauf angepasste Anwendungen zu entwickeln, wobei sie die besonderen Eigenschaften des mobilen Nutzungskontextes berücksichtigen können.\n--- Literature (EN) ---\n- Schiller: Mobilkommunikation, Pearson (2003)\n- Tanenbaum, van Steen: Verteilte Systeme, Pearson (2007)\n- http://www.wi-mobile.de/\n- http://www.eco.de/arbeitskreise/mobile.htm\n- http://www.heise.de/mobil/\n- http://developer.android.com\n--- Literature (DE) ---\n- Schiller: Mobilkommunikation, Pearson (2003)\n- Tanenbaum, van Steen: Verteilte Systeme, Pearson (2007)\n- http://www.wi-mobile.de/\n- http://www.eco.de/arbeitskreise/mobile.htm\n- http://www.heise.de/mobil/\n- http://developer.android.com", "metadata": {"moduleNumber": "BMI 45", "moduleName": "Mobile Applications", "creditPoints": "5.0", "suggestedSemester": 4, "offeredInSeason": "summer_semester", "examType": "written_exam", "heldInLanguage": "de", "reviserName": "None Philipp Krieter", "reviserEmail": "philipp.krieter@hs-duesseldorf.de", "studyProgramId": 8, "source_type": "json"}}
{"id": "BMI53", "text": "Title: Informatics and Economy\nModule Number: BMI 53\nCredits: 5.0 CP\nSemester: 5\nOffered In: winter_semester\nLanguage: de\nExam Type: written_exam\nInstructor: Prof. Dr.-Ing. M.Sc. Markus Dahm (markus.dahm@hs-duesseldorf.de)\n--- Goals (EN) ---\n- Economic order/economic framework\n- Business ethics (added value of economic activity)\n- Corporate constitution\n- Corporate strategies\n- Current management models\n- Fundamentals of accounting (external/internal)\n- Fundamentals of sales management\n--- Goals (DE) ---\n- Wirtschaftsordnung/Volkswirtschaftlicher Rahmen\n- Wirtschaftsethik (Mehrwertigkeit des Wirtschaftens)\n- Unternehmungsverfassung\n- Unternehmensstrategien\n- Aktuelle Managementmodelle\n- Grundlagen des Rechnungswesens (extern/intern)\n- Grundlagen der Absatzwirtschaft\n--- Contents (EN) ---\nStudents gain a basic understanding of business management systems as the basis for entrepreneurial thinking and action and business decision-making skills. They also learn to critically and reflectively analyse and evaluate microeconomic and macroeconomic problems. This promotes students' economic maturity and development opportunities both as future employees and as freelancers/self-employed persons.\n--- Contents (DE) ---\nDie Studierenden erlangen ein Grundverständnis betriebswirtschaftlicher Systeme als Grundlage unternehmerischen Denkens und Handelns und betriebswirtschaftlicher Entscheidungskompetenz. Geschult wird auch die kritisch-reflexive Analyse und Bewertung einzel- und gesamtwirtschaftlicher Problemstellungen. Hierdurch werden wirtschaftliche Mündigkeit und Entwicklungsmöglichkeiten der Studierenden sowohl als künftig angestellte Mitarbeiterinnen bzw. Mitarbeiter als auch als freiberuflich/ selbständig Tätige gefördert.\n--- Literature (EN) ---\n- Eisenführ, F., Theuvsen, L.: Einführung in die Betriebswirtschaftslehre. Stuttgart, 2011.\n- Klinkenberg, U.: Wertewirtschaft. Gedanken zu einer vernünftigeren Marktwirtschaft. München, 2016.\n- G. Schreyögg, J. Koch: Grundlagen des Managements, Wiesbaden, 2010\n- Ulrich, P.: Zivilisierte Marktwirtschaft. Bern, 2010.\n- B. W. Wirtz: Medien- und Internetmanagement, Wiesbaden, 2010\n- R. Wörlen/A. Kokemoor: Handelsrecht mit Gesellschaftsrecht, München, 12. Aufl. 2015.\n--- Literature (DE) ---\n- Eisenführ, F., Theuvsen, L.: Einführung in die Betriebswirtschaftslehre. Stuttgart, 2011.\n- Klinkenberg, U.: Wertewirtschaft. Gedanken zu einer vernünftigeren Marktwirtschaft. München, 2016.\n- G. Schreyögg, J. Koch: Grundlagen des Managements, Wiesbaden, 2010\n- Ulrich, P.: Zivilisierte Marktwirtschaft. Bern, 2010.\n- B. W. Wirtz: Medien- und Internetmanagement, Wiesbaden, 2010\n- R. Wörlen/A. Kokemoor: Handelsrecht mit Gesellschaftsrecht, München, 12. Aufl. 2015.", "metadata": {"moduleNumber": "BMI 53", "moduleName": "Informatics and Economy", "creditPoints": "5.0", "suggestedSemester": 5, "offeredInSeason": "winter_semester", "examType": "written_exam", "heldInLanguage": "de", "reviserName": "Prof. Dr.-Ing. M.Sc. Markus Dahm", "reviserEmail": "markus.dahm@hs-duesseldorf.de", "studyProgramId": 8, "source_type": "json"}}
{"id": "BMI55", "text": "Title: Informatics and Society\nModule Number: BMI 55\nCredits: 5.0 CP\nSemester: 5\nOffered In: winter_semester\nLanguage: de\nExam Type: written_exam\nInstructor: Prof. Dr.-Ing. M.Sc. Markus Dahm (markus.dahm@hs-duesseldorf.de)\n--- Goals (EN) ---\nSub-module \"Technology assessment and innovative development\"\n- Key terms in the field of technical, social and socio-technical innovations\n- Selected innovation approaches and theories (e.g. from the context of innovation studies)\n- Fundamentals of innovation development incl. innovation policy\n- Innovations in social responsibility (e.g. Responsible Science & Innovation, Innovation & Sustainability, Innovation & Social Justice)\n- Connections between innovations and social change, relationships to other areas of society, e.g. economic developments as well as innovation and technology policy (Political Economy of Technology Innovation, Science Policy of Technology Innovation)\n- Key players and institutions in the context of strategic innovation development\n\nMedia and IT law sub-module\n- Special features of proceedings and litigation in media and IT law\n- Basics of contract law; basics of electronic business law (online/mobile business)\n/mobile business)\n- Basics of intellectual property law in the area of media and IT law\n- References to trademark law, in particular domain law, copyright law and labour law\n- Photo/image law\n- Basics of data protection law\n- References to competition law and advertising law in media and IT law\n- Right of expression; liability of forum and rating platforms\n- Liability issues in media and IT law, in particular for internet platforms and social networks\n--- Goals (DE) ---\nTeilmodul \"Technikbewertung und innovative Entwicklung\"\n- Zentrale Begriffe im Feld technischer, sozialer und soziotechnischer Innovationen\n- Ausgewählte Innovationsansätze und -theorien (z. B. aus dem Kontext der Innovation Studies)\n- Grundlagen der Innovationsentwicklung inkl. Innovationspolitik\n- Innovationen in gesellschaftlicher Verantwortung (z. B. Responsible Science & Innovation, Innovation & Sustainability, Innovation & Social Justice)\n- Zusammenhänge zwischen Innovationen und sozialem Wandel, Beziehungen zu anderen gesellschaftlichen Bereichen, z. B. ökonomischer Entwicklungen sowie Innovations- und Technikpolitik (Political Economy of Technology Innovation, Science Policy of Technology Innovation)\n- Zentrale Akteure und Institutionen im Kontext strategischer Innovationsentwicklung\n\nTeilmodul Medien- und IT-Recht\n- Besonderheiten der Verfahrens- und Prozessführung im Medien- und IT-Recht\n- Grundzüge Vertragsrecht; Grundzüge Recht des elektronischen Geschäftsverkehrs (Online-\n/Mobile Business)\n- Grundzüge des Immaterialgüterrechts im Bereich Medien- und IT-Recht\n- Bezüge zum Kennzeichenrecht, insbesondere Domainrecht, Urheberrecht und Arbeitsrecht\n- Foto-/ Bild-Recht\n- Grundzüge im Recht des Datenschutzes\n- wettbewerbsrechtliche und werberechtliche Bezüge des Medien- und des IT-Rechts\n- Äußerungsrecht; Haftung von Foren- und Bewertungsplattformen\n- Haftungsfragen im Medien- und IT-Recht, insbesondere bei Internetplattformen sowie Sozialen Netzwerken\n--- Contents (EN) ---\nSub-module \"Technology assessment and innovative development\"\nStudents acquire basic knowledge of key terms in the field of technical, social and socio-technical developments. They understand the connections between technical and social development (e.g. with regard to implementation processes) and can describe and analyse innovation processes in their systematic connection with social processes.\nand analyse them. They develop an understanding of the possibilities for controlling innovation development, can apply approaches and concepts for shaping innovation processes and combine them with value-orientated approaches. \n\nMedia and IT law sub-module\nStudents are familiar with the tasks, objectives and key methods of organising, managing and controlling IT projects. They will be able to analyse existing projects and plan simple projects. They know the essential legal framework conditions for the use of IT systems in business practice and can analyse and classify corresponding application examples.\n--- Contents (DE) ---\nTeilmodul \"Technikbewertung und innovative Entwicklung\"\nStudierende erwerben Grundkenntnisse zentraler Begriffe im Feld technischer, sozialer und soziotechnischer Entwicklungen. Sie verstehen Zusammenhänge zwischen technischer und sozialer Entwicklung (z. B. im Hinblick auf Durchsetzungsprozesse) und können Innovationsprozesse in ihrem systematischen Zusammenhang mit gesellschaftlichen Prozessen beschreiben\nund analysieren. Sie entwickeln ein Verständnis für Steuerungsmöglichkeiten von Innovationsentwicklung, können Ansätze und Konzepte zur Gestaltung von Innovationsprozessen anwenden und sie mit werteorientierten Ansätzen verbinden. \n\nTeilmodul Medien- und IT-Recht\nDie Studierenden kennen die Aufgaben, Ziele und wesentliche Methoden der Organisation, Steuerung und Kontrolle von informatischen Projekten. Sie können bestehende Projekte analysieren und einfache Projekte planen. Sie kennen die wesentlichen rechtlichen Rahmenbedingungen beim Einsatz von Informatiksystemen in der wirtschaftlichen Praxis und können entsprechende Anwendungsbeispiele analysieren und einordnen.\n--- Literature (EN) ---\n- Blättel-Mink B., Schulz-Schaeffer I., Windeler A. (2019) (Hrsg.). Handbuch Innovationsforschung. Wiesbaden: Springer VS.\n- Cockburn, I., Henderson, R., Stern, S. (2018). The impact of artificial intelligence on innovation. National Bureau of Economic Research, NBER Working Paper 24449 (www.nber.org/pa-\npers/w24449)\n-  Dolata, U. (2013). The Transformative Capacity of New Technologies. A Theory of Sociotechnical Change. London: Routledge\n- Mai, M. (Hrsg.) (2014). Handbuch Innovationen. Interdisziplinäre Grundlagen und Anwendungsfelder. Wiesbaden: Springer VS\n\n- Gennen, A. Völkel: Recht der IT-Verträge: Start ins Rechtsgebiet, C. F. Müller Verlag 2009\n- H.-J. Homann: Praxishandbuch Filmrecht: Ein Leitfaden für Film-, Fernseh- und Medienschaffende, Springer Verlag, 2008\n- J. Schneider: IT- und Computerrecht, dtv 2016\n- Helmut Redeker, IT-Recht, CH Beck 2017\n--- Literature (DE) ---\n- Blättel-Mink B., Schulz-Schaeffer I., Windeler A. (2019) (Hrsg.). Handbuch Innovationsforschung. Wiesbaden: Springer VS.\n- Cockburn, I., Henderson, R., Stern, S. (2018). The impact of artificial intelligence on innovation. National Bureau of Economic Research, NBER Working Paper 24449 (www.nber.org/pa-\npers/w24449)\n-  Dolata, U. (2013). The Transformative Capacity of New Technologies. A Theory of Sociotechnical Change. London: Routledge\n- Mai, M. (Hrsg.) (2014). Handbuch Innovationen. Interdisziplinäre Grundlagen und Anwendungsfelder. Wiesbaden: Springer VS\n\n- Gennen, A. Völkel: Recht der IT-Verträge: Start ins Rechtsgebiet, C. F. Müller Verlag 2009\n- H.-J. Homann: Praxishandbuch Filmrecht: Ein Leitfaden für Film-, Fernseh- und Medienschaffende, Springer Verlag, 2008\n- J. Schneider: IT- und Computerrecht, dtv 2016\n- Helmut Redeker, IT-Recht, CH Beck 2017", "metadata": {"moduleNumber": "BMI 55", "moduleName": "Informatics and Society", "creditPoints": "5.0", "suggestedSemester": 5, "offeredInSeason": "winter_semester", "examType": "written_exam", "heldInLanguage": "de", "reviserName": "Prof. Dr.-Ing. M.Sc. Markus Dahm", "reviserEmail": "markus.dahm@hs-duesseldorf.de", "studyProgramId": 8, "source_type": "json"}}
{"id": "BMI205", "text": "Title: Digital Literacy & AI Literacy\nModule Number: BMI 205\nCredits: 5.0 CP\nSemester: 5\nOffered In: winter_semester\nLanguage: de\nExam Type: portfolio\nInstructor: Prof. Dr. rer. nat. Michael Marmann (marmann@hs-duesseldorf.de)\n--- Goals (EN) ---\nThe students\n\n- recognize the importance of digital literacy in today's information society.\n- understand the basic concepts and applications of artificial intelligence.\n- can critically evaluate digital tools and use them effectively for different purposes.\n- are able to identify and discuss the ethical and social implications of AI use.\n- develop the ability to analyze AI technologies in terms of data protection and data security.\n- can design and implement their own projects using AI elements.\n- can research and structure a current topic and present it at several levels of abstraction \n- are able to argue a topic in the seminar group \n- can prepare a current topic digitally and with interactive elements\n--- Goals (DE) ---\nDie Studierenden\n\n- erkennen die Bedeutung von Digital Literacy in der heutigen Informationsgesellschaft.\n- verstehen die grundlegenden Konzepte und Anwendungen künstlicher Intelligenz.\n- können digitale Werkzeuge kritisch bewerten und effektiv für verschiedene Zwecke einsetzen.\n- sind in der Lage, ethische und soziale Implikationen der KI-Nutzung zu identifizieren und zu diskutieren.\n- entwickeln die Fähigkeit, KI-Technologien in Bezug auf Datenschutz und Datensicherheit zu analysieren.\n- können eigene Projekte unter Einbeziehung von AI-Elementen konzipieren und umsetzen.\n- können ein aktuelles Thema recherchieren, strukturieren und auf mehreren Abstraktionslevels präsentieren \n- können ein bearbeitetes Thema in der Seminargruppe argumentativ vertreten \n- können ein aktuelles Thema digital und mit interaktiven Elementen aufbereiten\n--- Contents (EN) ---\nThe 'Digital Literacy & AI Literacy' seminar provides students with an in-depth understanding of the digital literacies necessary to navigate effectively in the modern world. It covers the skills needed to search, evaluate and create information digitally. The focus is on critically examining the reliability and credibility of digital content.\n\nIn parallel, there is a focus on AI Literacy, which covers the understanding and application of artificial intelligence in different areas of life and work. Students will learn the basic principles of AI systems, including machine learning and data processing. They deal with the latest developments in the field of AI and reflect on their impact on society and the individual.\n\nThe seminar also examines the ethical aspects of digital and AI technologies, such as data protection, algorithmic bias and the effects of automation on the labor market. Methods are developed to deal with these challenges and students are enabled to plan and implement their own digital and AI-related projects.\n--- Contents (DE) ---\nDas Seminar \"Digital Literacy & AI Literacy\" bietet den Studierenden ein tiefgreifendes Verständnis der digitalen Kompetenzen, die notwendig sind, um in der modernen Welt effektiv zu navigieren. Es behandelt die Fähigkeiten, die benötigt werden, um Informationen digital zu suchen, zu bewerten und zu erstellen. Im Zentrum steht die kritische Auseinandersetzung mit der Verlässlichkeit und Glaubwürdigkeit von digitalen Inhalten.\n\nParallel dazu wird ein Schwerpunkt auf AI Literacy gelegt, der das Verständnis und die Anwendung von künstlicher Intelligenz in verschiedenen Lebens- und Arbeitsbereichen umfasst. Die Studierenden lernen die Grundprinzipien von KI-Systemen kennen, einschließlich maschinellem Lernen und Datenverarbeitung. Sie setzen sich mit den neuesten Entwicklungen im Bereich der KI auseinander und reflektieren deren Auswirkungen auf Gesellschaft und Individuum.\n\nDas Seminar beleuchtet zudem die ethischen Aspekte der digitalen und KI-Technologien, wie Datenschutz, Bias in Algorithmen (algorithmic bias) und die Auswirkungen der Automatisierung auf den Arbeitsmarkt. Es werden Methoden erarbeitet, um mit diesen Herausforderungen umzugehen und die Studierenden dazu befähigt, eigene digitale und KI-bezogene Projekte zu planen und zu realisieren.\n--- Literature (EN) ---\nCurrent literature references and sources of information are provided at the beginning of the module or directly from the course context. In addition, digital media are increasingly used as a source of knowledge.\n--- Literature (DE) ---\nAktuelle Literaturhinweise und Informationsquellen werden zu Beginn des Moduls oder unmittelbar aus dem Veranstaltungskontext herausgegeben. Zusätzlich werden verstärkt digitale Medien als Wissensquelle eingesetzt.", "metadata": {"moduleNumber": "BMI 205", "moduleName": "Digital Literacy & AI Literacy", "creditPoints": "5.0", "suggestedSemester": 5, "offeredInSeason": "winter_semester", "examType": "portfolio", "heldInLanguage": "de", "reviserName": "Prof. Dr. rer. nat. Michael Marmann", "reviserEmail": "marmann@hs-duesseldorf.de", "studyProgramId": 8, "source_type": "json"}}
{"id": "BMI206", "text": "Title: New Work & New Learning\nModule Number: BMI 206\nCredits: 5.0 CP\nSemester: 4\nOffered In: summer_semester\nLanguage: de\nExam Type: portfolio\nInstructor: Prof. Dr. rer. nat. Michael Marmann (marmann@hs-duesseldorf.de)\n--- Goals (EN) ---\nThe students\n\n- understand the concepts and driving forces behind the New Work movement.\n- can identify the principles of New Learning and apply them to educational contexts.\n- are able to design modern working and learning environments that promote creativity and innovation.\n- can critically analyze the effects of new technologies on work and education.\n- develop skills to act as change agents in their organizations.\n- can implement interdisciplinary approaches for lifelong learning and agile work processes.\n- can research and structure a current topic and present it at several levels of abstraction.\n- can argue a topic in the seminar group.\n- can prepare a current topic digitally and with interactive elements.\n--- Goals (DE) ---\nDie Studierenden\n- verstehen die Konzepte und treibenden Kräfte hinter der New Work-Bewegung.\n- können die Prinzipien des New Learning identifizieren und auf Bildungskontexte anwenden.\n- sind in der Lage, moderne Arbeits- und Lernumgebungen zu gestalten, die Kreativität und Innovation fördern.\n- können kritisch die Auswirkungen neuer Technologien auf Arbeit und Bildung analysieren.\n- entwickeln Fähigkeiten, um als Change Agents in ihren Organisationen zu fungieren.\n- können interdisziplinäre Ansätze für lebenslanges Lernen und agile Arbeitsprozesse implementieren.\n- können ein aktuelles Thema recherchieren, strukturieren und auf mehreren Abstraktionslevels präsentieren.\n- können ein bearbeitetes Thema in der Seminargruppe argumentativ vertreten.\n- können ein aktuelles Thema digital und mit interaktiven Elementen aufbereiten.\n--- Contents (EN) ---\nThis seminar deals with the current changes in the world of work and their influence on learning processes. The basics of the New Work movement, which focuses on autonomy, flexibility and participation in the workplace, as well as the principles of New Learning, which emphasizes self-directed learning and the use of new technologies, are covered. Students learn about innovative approaches to the design of working and learning environments that take into account both the individual needs of learners and the requirements of modern organizations.\n\nAn essential part of the seminar is the examination of the challenges and opportunities that digital technologies bring for the world of work and education. Concepts such as lifelong learning, knowledge management and skills development in the context of New Work and New Learning will be discussed.\n\nThe seminar promotes the development of skills that enable participants to act as change agents and implement interdisciplinary approaches in their own professional contexts. This includes critical reflection on existing structures and the ability to design and manage agile and flexible learning and work processes.\n--- Contents (DE) ---\nDieses Seminar beschäftigt sich mit den aktuellen Veränderungen in der Arbeitswelt und deren Einfluss auf Lernprozesse. Es werden die Grundlagen der New Work-Bewegung, die auf Autonomie, Flexibilität und Partizipation am Arbeitsplatz abzielt, sowie die Prinzipien des New Learning, welches Selbstgesteuertes Lernen und den Einsatz neuer Technologien in den Vordergrund stellt, behandelt. Die Studierenden lernen innovative Ansätze zur Gestaltung von Arbeits- und Lernumgebungen kennen, die sowohl die individuellen Bedürfnisse der Lernenden als auch die Anforderungen moderner Organisationen berücksichtigen.\n\nEin wesentlicher Bestandteil des Seminars ist die Auseinandersetzung mit den Herausforderungen und Chancen, die digitale Technologien für die Arbeitswelt und das Bildungswesen mit sich bringen. Es werden Konzepte wie das lebenslange Lernen, Wissensmanagement und die Kompetenzentwicklung im Kontext von New Work und New Learning diskutiert.\n\nDas Seminar fördert die Entwicklung von Kompetenzen, die es den Teilnehmenden ermöglichen, als Change Agents zu agieren und interdisziplinäre Ansätze in ihren eigenen beruflichen Kontexten umzusetzen. Dies beinhaltet die kritische Reflexion über bestehende Strukturen und die Fähigkeit, agile und flexible Lern- und Arbeitsprozesse zu gestalten und zu steuern.\n--- Literature (EN) ---\nCurrent literature references and sources of information are provided at the beginning of the module or directly from the course context. In addition, digital media are increasingly used as a source of knowledge.\n--- Literature (DE) ---\nAktuelle Literaturhinweise und Informationsquellen werden zu Beginn des Moduls oder unmittelbar aus dem Veranstaltungskontext herausgegeben. Zusätzlich werden verstärkt digitale Medien als Wissensquelle eingesetzt.", "metadata": {"moduleNumber": "BMI 206", "moduleName": "New Work & New Learning", "creditPoints": "5.0", "suggestedSemester": 4, "offeredInSeason": "summer_semester", "examType": "portfolio", "heldInLanguage": "de", "reviserName": "Prof. Dr. rer. nat. Michael Marmann", "reviserEmail": "marmann@hs-duesseldorf.de", "studyProgramId": 8, "source_type": "json"}}
{"id": "BMI50", "text": "Title: Web Engineering\nModule Number: BMI 50\nCredits: 5.0 CP\nSemester: 5\nOffered In: winter_semester\nLanguage: de\nExam Type: written_exam\nInstructor: None Patrick Pogscheba (patrick.pogscheba@hs-duesseldorf.de)\n--- Goals (EN) ---\nThe student has a deeper understanding of the HTT protocol and can use this for advanced tasks, e.g. for caching. The student knows other architectural alternatives via the full stack architecture in the \"Web Programming 2\" module, e.g. server-side generation. The student can classify their respective advantages and disadvantages. The student identifies the relevant properties of different web frameworks, infrastructures or applications and uses them to make selection decisions in specific projects.\n--- Goals (DE) ---\nDer Studierende hat ein tiefergehendes Verständnis des HTT-Protokolls und kann dieses für fortgeschrittene Aufgabenstellungen nutzen, z.B. für das Cachen. Der Studierende kennt über die im Modul \"Webprogrammierung 2\" Fullstack-Architektur weitere Architekturalternativen, z.B. die serverseitige Generierung. Der Studierende kann deren jeweiligen Vor- und Nachteile einordnen. Der Studierende die relevanten Eigenschaften unterschiedlicher Webframeworks, Infrastrukturen oder Anwendungen identifizieren und für die Auswahlentscheidung in spezifischen Projekten nutzen.\n--- Contents (EN) ---\nLecture:\n- Deepening into the HTT protocol\n- Architecture alternatives for web applications\n- Properties, patterns and basic concepts of server-side and client-side web frameworks and infrastructures.\n- Content management systems\n\nPractice:\nDifferent tasks regarding the usage of the HTT protocol, as well as building simple applications using the frameworks and other technologies\n--- Contents (DE) ---\nVorlesung:\n- Vertiefung in das HTT-Protokoll\n- Architekturalternativen für Webanwendungen\n- Eigenschaften, Patterns und grundlegende Konzepte von serverseitigen und clientseitigen Webframeworks, sowie Infrastrukturen. \n- Content Management Systeme\n\nÜbung:\nEs werden Übungsaufgaben bearbeitet, mit denen die Nutzung des HTT-Protokolls, sowie der jeweiligen Frameworks und weiteren Technologien erprobt werden.\n--- Literature (EN) ---\nWill be given in the lecture\n--- Literature (DE) ---\nWird in der Vorlesung angegeben", "metadata": {"moduleNumber": "BMI 50", "moduleName": "Web Engineering", "creditPoints": "5.0", "suggestedSemester": 5, "offeredInSeason": "winter_semester", "examType": "written_exam", "heldInLanguage": "de", "reviserName": "None Patrick Pogscheba", "reviserEmail": "patrick.pogscheba@hs-duesseldorf.de", "studyProgramId": 8, "source_type": "json"}}
{"id": "BMI209", "text": "Title: Learning agency\nModule Number: BMI 209\nCredits: 5.0 CP\nSemester: 5\nOffered In: winter_semester\nLanguage: de\nExam Type: portfolio\nInstructor: Prof. Dr. rer. nat. Michael Marmann (marmann@hs-duesseldorf.de)\n--- Goals (EN) ---\nThe students \n\n- know the typical work processes of a digital agency and apply them under largely real conditions \n- take on a role within the project that corresponds to their competencies and a typical job profile in an agency \n- learn to organize themselves, act independently and participate in team development processes \n- know the tools required for the different project phases and can apply them in a phase-specific manner\n- are familiar with agile process models and supporting tools and apply these in the context of teamwork \n- design and develop a digital media product or a digitally supported service in a team on the basis of a specific project assignment \n- can present the results of individual project phases and the overall result to internal or external clients\n--- Goals (DE) ---\nDie Studierenden \n\n- kennen die typischen Arbeitsprozesse einer Digitalagentur und wenden diese unter weitgehend realen Bedingungen an \n- nehmen innerhalb des Projektes eine ihren Kompetenzen entsprechende Rolle ein, die einem typischen Tätigkeitsprofil in einer Agentur entspricht \n- lernen, sich selbst zu organisieren, eigenverantwortlich zu handeln und an Teamentwicklungsprozessen teilzunehmen \n- kennen die für die unterschiedlichen Projektphasen notwendigen Werkzeuge und können diese phasenspezifisch anwenden\n- kennen agile Vorgehensmodelle sowie unterstützende Tools und wenden diese im Rahmen der Teamarbeit an \n- konzipieren und entwickeln im Team auf der Basis eines konkreten Projektauftrages ein digitales Medienprodukt oder eine digital gestützte Dienstleistung \n- können Ergebnisse einzelner Projektphasen und das Gesamtergebnis vor internen oder externen Auftraggebern präsentieren\n--- Contents (EN) ---\nThe learning agency module is a special type of project that is highly relevant for later professional life. The special feature is that students work in a team on concrete and practical customer solutions, just like in a real digital agency, from the initial idea through to implementation. \n\nThe client can be internal or external. To this end, students take on specific roles that correspond to real job profiles in agencies. For example, there will be sales-oriented students as well as project managers, concept developers, developers or designers. If several teams are formed, they will be in competition with each other. The solution to be developed will go through all phases of digital product development or an online communication project. Special emphasis is placed on agile project management methods.\n--- Contents (DE) ---\nBeim Modul Lernagentur handelt es sich um eine spezielle Projektform mit hoher Relevanz für das spätere Berufsleben. Die Besonderheit besteht darin, dass Studierende wie in einer realen Digitalagentur im Team an konkreten und praxisnahen Kundenlösungen arbeiten, und zwar von der ersten Idee bis zur Umsetzung. \n\nDabei kann der Auftraggeber intern oder extern sein. Hierzu nehmen die Studierenden bestimmte Rollen ein, die realen Tätigkeitsprofilen in Agenturen entsprechen. So wird es vertrieblich orientierte Studierende genauso geben, wie z.B. Projektmanager, Konzepter, Entwickler oder Designer. Sollten sich mehrere Teams formieren, dann stehen sie im Wettbewerb zueinander. Die zu erarbeitende Lösung durchläuft alle Phasen einer digitalen Produktentwicklung oder eines Online-Kommunikations-Projektes. Dabei wird besonderer Wert auf agile Projektmanagementmethoden gelegt.\n--- Literature (EN) ---\nCurrent literature references and sources of information are provided at the beginning of the module or directly from the course context, if necessary. In addition, digital media are increasingly used as a source of knowledge.\n--- Literature (DE) ---\nAktuelle Literaturhinweise und Informationsquellen werden, so-fern notwendig, zu Beginn des Moduls oder unmittelbar aus dem Veranstaltungskontext herausgegeben. Zusätzlich werden verstärkt digitale Medien als Wissensquelle eingesetzt.", "metadata": {"moduleNumber": "BMI 209", "moduleName": "Learning agency", "creditPoints": "5.0", "suggestedSemester": 5, "offeredInSeason": "winter_semester", "examType": "portfolio", "heldInLanguage": "de", "reviserName": "Prof. Dr. rer. nat. Michael Marmann", "reviserEmail": "marmann@hs-duesseldorf.de", "studyProgramId": 8, "source_type": "json"}}
{"id": "BMI41", "text": "Title: Compulsory Elective Informatics A\nModule Number: BMI 41\nCredits: 5.0 CP\nSemester: 4\nOffered In: summer_semester\nLanguage: de\nExam Type: written_exam\nInstructor: Prof. Dr.-Ing. M.Sc. Markus Dahm (markus.dahm@hs-duesseldorf.de)\n--- Goals (EN) ---\nStudents deepen and/or broaden their knowledge in the chosen subject area and apply it.\n--- Goals (DE) ---\nDie Studierenden vertiefen und/oder erweitern ihre Kenntnisse in dem gewählten Themengebiet und wenden diese an.\n--- Contents (EN) ---\nFor this compulsory elective module, current topics in media informatics that deal with the design and/or realisation of complex IT systems are offered as electives. The tasks are orientated towards typical professional activities of graduates.\n--- Contents (DE) ---\nFür dieses Wahlpflichtmodul werden als Wahlangebote aktuelle Themen der Medieninformatik angeboten, die sich mit der Konzipierung und/oder Realisierung komplexer IT-Systeme beschäftigen. Die Aufgabenstellungen orientieren sich an typischen beruflichen Tätigkeiten der Absolventinnen und Absolventen.\n--- Literature (EN) ---\nGiven by elective module\n--- Literature (DE) ---\nDurch Wahlmodul vorgegeben", "metadata": {"moduleNumber": "BMI 41", "moduleName": "Compulsory Elective Informatics A", "creditPoints": "5.0", "suggestedSemester": 4, "offeredInSeason": "summer_semester", "examType": "written_exam", "heldInLanguage": "de", "reviserName": "Prof. Dr.-Ing. M.Sc. Markus Dahm", "reviserEmail": "markus.dahm@hs-duesseldorf.de", "studyProgramId": 8, "source_type": "json"}}
{"id": "BMI51", "text": "Title: Compulsory Elective Informatics A\nModule Number: BMI 51\nCredits: 5.0 CP\nSemester: 5\nOffered In: winter_semester\nLanguage: de\nExam Type: written_exam\nInstructor: Prof. Dr.-Ing. M.Sc. Markus Dahm (markus.dahm@hs-duesseldorf.de)\n--- Goals (EN) ---\nStudents deepen and/or broaden their knowledge in the chosen subject area and apply it.\n--- Goals (DE) ---\nDie Studierenden vertiefen und/oder erweitern ihre Kenntnisse in dem gewählten Themengebiet und wenden diese an.\n--- Contents (EN) ---\nFor this compulsory elective module, current topics in media informatics that deal with the design and/or realisation of complex IT systems are offered as electives. The tasks are orientated towards typical professional activities of graduates.\n--- Contents (DE) ---\nFür dieses Wahlpflichtmodul werden als Wahlangebote aktuelle Themen der Medieninformatik angeboten, die sich mit der Konzipierung und/oder Realisierung komplexer IT-Systeme beschäftigen. Die Aufgabenstellungen orientieren sich an typischen beruflichen Tätigkeiten der Absolventinnen und Absolventen.\n--- Literature (EN) ---\nGiven by elective module\n--- Literature (DE) ---\nDurch Wahlmodul vorgegeben", "metadata": {"moduleNumber": "BMI 51", "moduleName": "Compulsory Elective Informatics A", "creditPoints": "5.0", "suggestedSemester": 5, "offeredInSeason": "winter_semester", "examType": "written_exam", "heldInLanguage": "de", "reviserName": "Prof. Dr.-Ing. M.Sc. Markus Dahm", "reviserEmail": "markus.dahm@hs-duesseldorf.de", "studyProgramId": 8, "source_type": "json"}}
{"id": "BMI42", "text": "Title: Compulsory Elective Media A\nModule Number: BMI 42\nCredits: 5.0 CP\nSemester: 4\nOffered In: summer_semester\nLanguage: de\nExam Type: written_exam\nInstructor: Prof. Dr.-Ing. M.Sc. Markus Dahm (markus.dahm@hs-duesseldorf.de)\n--- Goals (EN) ---\nStudents deepen and/or broaden their knowledge in the chosen subject area and apply it.\n--- Goals (DE) ---\nDie Studierenden vertiefen und/oder erweitern ihre Kenntnisse in dem gewählten Themengebiet und wenden diese an.\n--- Contents (EN) ---\nFor this compulsory  elective module, current topics in media informatics are offered that deal with the design and/or realisation of complex media applications. The tasks are orientated towards typical professional activities of graduates.\n--- Contents (DE) ---\nFür dieses Wahlpflichtmodul werden aktuelle Themen der Medieninformatik angeboten, die sich mit der Konzeptionierung und/oder Realisierung komplexer Medienanwendungen beschäftigen. Die Aufgabenstellungen orientieren sich an typischen beruflichen Tätigkeiten der Absolventinnen und Absolventen.\n--- Literature (EN) ---\nGiven by elective module\n--- Literature (DE) ---\nDurch Wahlmodul vorgegeben", "metadata": {"moduleNumber": "BMI 42", "moduleName": "Compulsory Elective Media A", "creditPoints": "5.0", "suggestedSemester": 4, "offeredInSeason": "summer_semester", "examType": "written_exam", "heldInLanguage": "de", "reviserName": "Prof. Dr.-Ing. M.Sc. Markus Dahm", "reviserEmail": "markus.dahm@hs-duesseldorf.de", "studyProgramId": 8, "source_type": "json"}}
{"id": "BMI52", "text": "Title: Compulsory Elective Media B\nModule Number: BMI 52\nCredits: 5.0 CP\nSemester: 5\nOffered In: winter_semester\nLanguage: de\nExam Type: written_exam\nInstructor: Prof. Dr.-Ing. M.Sc. Markus Dahm (markus.dahm@hs-duesseldorf.de)\n--- Goals (EN) ---\nStudents deepen and/or broaden their knowledge in the chosen subject area and apply it.\n--- Goals (DE) ---\nDie Studierenden vertiefen und/oder erweitern ihre Kenntnisse in dem gewählten Themengebiet und wenden diese an.\n--- Contents (EN) ---\nFor this compulsory  elective module, current topics in media informatics are offered that deal with the design and/or realisation of complex media applications. The tasks are orientated towards typical professional activities of graduates.\n--- Contents (DE) ---\nFür dieses Wahlpflichtmodul werden aktuelle Themen der Medieninformatik angeboten, die sich mit der Konzeptionierung und/oder Realisierung komplexer Medienanwendungen beschäftigen. Die Aufgabenstellungen orientieren sich an typischen beruflichen Tätigkeiten der Absolventinnen und Absolventen.\n--- Literature (EN) ---\nGiven by elective module\n--- Literature (DE) ---\nDurch Wahlmodul vorgegeben", "metadata": {"moduleNumber": "BMI 52", "moduleName": "Compulsory Elective Media B", "creditPoints": "5.0", "suggestedSemester": 5, "offeredInSeason": "winter_semester", "examType": "written_exam", "heldInLanguage": "de", "reviserName": "Prof. Dr.-Ing. M.Sc. Markus Dahm", "reviserEmail": "markus.dahm@hs-duesseldorf.de", "studyProgramId": 8, "source_type": "json"}}
{"id": "BMI210", "text": "Title: Metathematisches Storytelling\nModule Number: BMI 210\nCredits: 5.0 CP\nSemester: 5\nOffered In: winter_semester\nLanguage: de\nExam Type: portfolio\nInstructor: Prof. Gabriele Schwab-Trapp (gabi.schwab-trapp@hs-duesseldorf.de)\n--- Goals (EN) ---\nStudents acquire skills in the conceptual handling of free or applied topics and the ability to independently develop context-related content. The development and practical realisation of their own ideas is made possible with the help of design processes. Experience in interdisciplinary, creative and constructive collaboration is gained within the seminar and possible project groups as well as in dealing with various forms of presentation.\n--- Goals (DE) ---\nDie Studierenden erwerben Fähigkeiten im konzeptionellen Umgang mit freien oder angewandten Themen und die Befähigung zur selbstständigen Erarbeitung von kontextbezogenen Inhalten. Mithilfe von Gestaltungsprozessen werden die Entwicklung und die praktische Umsetzung eigener Ideen ermöglicht. Erfahrungen in interdisziplinärer, kreativer und konstruktiver Zusammenarbeit werden innerhalb der Seminar- und möglicher Projektgruppen sowie im Umgang mit verschiedenen Präsentationsformen gesammelt.\n--- Contents (EN) ---\nFree or applied topics are dealt with, which are presented at the beginning of the semester. The joint deepening, development and unfolding of the topic takes place in seminar form. This also includes philosophical, knowledge-orientated and opinion-forming discussions. The aim is the independent development and realisation of context-related, visual concepts in various media. Various forms of presentation are practised according to the topics and results. Excursions may take place to support the topics, which will be announced at the beginning of the semester.\nThe module is regularly offered on an open, collaborative and interdisciplinary basis with students from other subject areas.\n\nSuitable advanced tasks are assigned for Master's students.\n--- Contents (DE) ---\nInhaltlich werden freie oder angewandte Themen behandelt, die zu Beginn des Semesters vorgestellt werden. Die gemeinsame Vertiefung, Entwicklung und Entfaltung des Themas findet in Seminarform statt. Dazu gehört auch die philosophische, erkenntnisorientierte und meinungsbildende Auseinandersetzung. Ziel ist die selbstständige Entwicklung und Umsetzung von kontextbezogenen, visuellen Konzepten in unterschiedlichen Medien. Den Themen und Ergebnissen entsprechend werden verschiedene Präsentationsformen eingeübt. Themenunterstützend können Exkursionen stattfinden, die zu Beginn des Semesters bekannt gegeben werden.\nDas Modul wird regelmäßig offen, kollaborativ und interdisziplinär mit Studierenden aus anderen Fachbereichen angeboten.\n\nFür Master-Studierende werden geeignete, fortgeschrittene Aufgaben vergeben.\n--- Literature (EN) ---\nMaterial and literature references are provided for the respective topic in the seminar. Information in the form of text extracts, literature, image examples and research suggestions are provided to support the respective learning, realisation and design steps.\n--- Literature (DE) ---\nMaterial- und Literaturangaben werden zu dem jeweiligen Thema im Seminar ausgegeben. Zur Unterstützung der jeweiligen Lern-, Erkenntnis- und Gestaltungsschritte werden Hinweise in Form von Textauszügen, Literatur, Bildbeispielen und Recherchevorschlägen gegeben.", "metadata": {"moduleNumber": "BMI 210", "moduleName": "Metathematisches Storytelling", "creditPoints": "5.0", "suggestedSemester": 5, "offeredInSeason": "winter_semester", "examType": "portfolio", "heldInLanguage": "de", "reviserName": "Prof. Gabriele Schwab-Trapp", "reviserEmail": "gabi.schwab-trapp@hs-duesseldorf.de", "studyProgramId": 8, "source_type": "json"}}
{"id": "BMI211", "text": "Title: Discursive Design and Future Visions\nModule Number: BMI 211\nCredits: 5.0 CP\nSemester: 5\nOffered In: winter_semester\nLanguage: de\nExam Type: portfolio\nInstructor: Prof. Gabriele Schwab-Trapp (gabi.schwab-trapp@hs-duesseldorf.de)\n--- Goals (EN) ---\nStudents recognise the connection between design, technology, science and shaping the future. They are able to critically reflect on design concepts and their effects and can utilise speculative design strategies as a method for generating creative and sustainable ideas. They are able to apply and categorise the research potential of design.\n--- Goals (DE) ---\nDie Studierenden erkennen den Zusammenhang zwischen Design, Technik, Wissenschaft und Zukunftsgestaltung. Sie sind in der Lage Gestaltungskonzepte und deren Auswirkungen kritisch zu reflektieren und können den Einsatz spekulativer Designstrategien als Methode zur Erzeugung kreativer und nachhaltiger Ideen nutzen. Sie sind in der Lage das Forschungspotenzial durch Gestaltung anzuwenden und einzuordnen.\n--- Contents (EN) ---\nStudents are encouraged to engage analytically, theoretically and practically with concepts such as \"Design Fiction\", \"Critical Design\" and \"Speculative Design\". The focus is on the critical examination of current developments in science, technology, design and communication and their potential impact on society.\nOn this basis, possible future scenarios are to be developed and told in free narratives. Through the creative fusion of scientific knowledge and narrative elements, combined with practical applications, alternative realities can be explored and discussions stimulated that promote critical thinking. This integrative approach allows research through design to be trialled, using design as a tool to explore and deepen understanding of current issues and potential future scenarios. The aim is to identify the opportunities and challenges that designers and product developers face when dealing with increasingly complex and urgent social, political and environmental issues.\nThe theoretical discussion includes design and media history, design and media theory, as well as categorisation in the context of social developments.\n\nTranslated with DeepL.com (free version)\n--- Contents (DE) ---\nDie Studierenden werden dazu angeleitet, sich analytisch, theoretisch und praktisch mit Konzepten wie \"Design Fiction\", \"Critical Design\" und \"Speculative Design\" auseinanderzusetzen. Der Schwerpunkt liegt auf der kritischen Untersuchung aktueller Entwicklungen in Wissenschaft, Technik, Design und Kommunikation sowie deren potenziellen Auswirkungen auf die Gesellschaft. \n\nAuf dieser Basis sollen mögliche Zukunftsszenarien entwickelt werden, die in freien Narrativen erzählt werden. Durch die kreative Verschmelzung von wissenschaftlichem Wissen und erzählerischen Elementen, verknüpft mit praktischen Anwendungen, können alternative Realitäten erforscht und Diskussionen angeregt werden, die kritische Denkweisen fördern. Dieser integrative Ansatz ermöglicht es, Forschung durch Gestaltung zu erproben, bei dem Design als Instrument zur Erforschung und Vertiefung des Verständnisses aktueller Themen und potenzieller Zukunftsszenarien dient. Dabei sollen Möglichkeiten und Herausforderungen aufzeigt werden, denen sich GestalterInnen und ProduktentwicklerInnen stellen müssen, wenn sie sich mit immer komplexeren und dringlicheren sozialen, politischen und ökologischen Themen auseinandersetzen.\n\nZu der theoretischen Auseinandersetzung gehören Design- und Mediengeschichte, Design- und Medientheorie, sowie die Einordnung in gesellschaftliche Entwicklungen.\n--- Literature (EN) ---\nMaterial and literature references are provided for the respective topic in the seminar. Information in the form of text extracts, literature, image examples and research suggestions are provided to support the respective learning, realisation and design steps.\n--- Literature (DE) ---\nMaterial- und Literaturangaben werden zu dem jeweiligen Thema im Seminar ausgegeben. Zur Unterstützung der jeweiligen Lern-, Erkenntnis- und Gestaltungsschritte werden Hinweise in Form von Textauszügen, Literatur, Bildbeispielen und Recherchevorschlägen gegeben.", "metadata": {"moduleNumber": "BMI 211", "moduleName": "Discursive Design and Future Visions", "creditPoints": "5.0", "suggestedSemester": 5, "offeredInSeason": "winter_semester", "examType": "portfolio", "heldInLanguage": "de", "reviserName": "Prof. Gabriele Schwab-Trapp", "reviserEmail": "gabi.schwab-trapp@hs-duesseldorf.de", "studyProgramId": 8, "source_type": "json"}}
