{"id": "BMT10", "text": "Title: Mathematics 1\nModule Number: BMT 10\nCredits: 6.0 CP\nSemester: 1\nOffered In: winter_semester\nLanguage: de\nExam Type: written_exam\nInstructor: None J\u00f6rg Becker-Schweitzer\n\n--- Goals (EN) ---\nStudents are able to apply mathematical methods to a wide range of problems. They have a solid understanding of basic concepts in the areas of propositional logic, set theory, relations and functions. In addition, they are proficient in dealing with elementary functions and complex numbers. Students are able to analyze problems in the field of differential and integral calculus and develop appropriate solutions.\n\n--- Goals (DE) ---\nDie Studierenden k\u00f6nnen die mathematische Arbeitsweise gezielt auf vielf\u00e4ltige Fragestellungen anwenden. Sie verf\u00fcgen \u00fcber ein solides Verst\u00e4ndnis der Grundkonzepte in den Bereichen Aussagenlogik, Mengenlehre, sowie Relationen und Funktionen. Dar\u00fcber hinaus beherrschen sie den Umgang mit elementaren Funktionen und komplexen Zahlen. Die Studierenden sind in der Lage, Problemstellungen im Bereich der Differential- und Integralrechnung zu analysieren und angemessene L\u00f6sungsans\u00e4tze zu entwickeln.\n\n--- Contents (EN) ---\n- Repetition of basic mathematical knowledge\n- Propositional logic, sets and number spaces\n- Relations and functions\n- Elementary functions\n- Complex numbers\n- Differential calculus\n- Integral calculus\n\n--- Contents (DE) ---\n- Wiederholung mathematischen Grundwissens\n- Aussagenlogik, Mengen und Zahlenr\u00e4ume\n- Relationen und Funktionen\n- Elementare Funktionen\n- Komplexe Zahlen\n- Differenzialrechnung\n- Integralrechnung\n\n--- Literature (EN) ---\n- J. Koch, M. St\u00e4mpfle: Mathematik f\u00fcr das Ingenieurstudium,3. Auflage, Hanser Verlag, 2015\n- L. Papula: Mathematik f\u00fcr Ingenieure und Naturwissenschaftler, Vieweg Verlag 2004\n- M. Brill: Mathematik f\u00fcr Informatiker, Hanser Verlag 2005\n- K. Kiyek, F. Schwarz: Mathematik f\u00fcr Informatiker, Teubner Verlag 1999\n- P. Stingl: Mathematik f\u00fcr Fachhochschulen, Technik und Informatik, Hanser Verlag 1998\n- L. Papula: Mathematik f\u00fcr Ingenieure und Naturwissenschaftler, Vieweg Verlag 2004\n- T. Westermann: Mathematik f\u00fcr Ingenieure mit Maple, Springer Verlag 2004\n- Maple 9.5 Programming Guide 2005\n- G. Strang: Video-Lectures on Linear Algebra, MIT Boston, USA (Massachusetts Institute of Technology), Weblink: https://ocw.mit.edu/courses/18-06-linear-algebra-spring-2010/video_galleries/video-lectures/\n\n--- Literature (DE) ---\n- J. Koch, M. St\u00e4mpfle: Mathematik f\u00fcr das Ingenieurstudium,3. Auflage, Hanser Verlag, 2015\n- L. Papula: Mathematik f\u00fcr Ingenieure und Naturwissenschaftler, Vieweg Verlag 2004\n- M. Brill: Mathematik f\u00fcr Informatiker, Hanser Verlag 2005\n- K. Kiyek, F. Schwarz: Mathematik f\u00fcr Informatiker, Teubner Verlag 1999\n- P. Stingl: Mathematik f\u00fcr Fachhochschulen, Technik und Informatik, Hanser Verlag 1998\n- L. Papula: Mathematik f\u00fcr Ingenieure und Naturwissenschaftler, Vieweg Verlag 2004\n- T. Westermann: Mathematik f\u00fcr Ingenieure mit Maple, Springer Verlag 2004\n- Maple 9.5 Programming Guide 2005\n- G. Strang: Video-Lectures on Linear Algebra, MIT Boston, USA (Massachusetts Institute of Technology), Weblink: https://ocw.mit.edu/courses/18-06-linear-algebra-spring-2010/video_galleries/video-lectures/", "metadata": {"moduleNumber": "BMT 10", "moduleName": "Mathematics 1", "creditPoints": "6.0", "suggestedSemester": 1, "offeredInSeason": "winter_semester", "examType": "written_exam", "heldInLanguage": "de", "reviserName": "None J\u00f6rg Becker-Schweitzer", "reviserEmail": "jbs@hs-duesseldorf.de", "studyProgramId": 9, "source_type": "json"}}
{"id": "BMT11", "text": "Title: Fundamentals of Electrical Engineering and Physics\nModule Number: BMT 11\nCredits: 5.0 CP\nSemester: 1\nOffered In: winter_semester\nLanguage: de\nExam Type: written_exam\nInstructor: None J\u00f6rg Becker-Schweitzer\n\n--- Goals (EN) ---\nStudents know and understand basic mathematical concepts that enable them to solve application-oriented problems \nsolve application-oriented problems from the natural sciences, electrical engineering and computer science. Students have knowledge of basic \nphysics. They are familiar with laws, the understanding of \nphysical or electrical engineering contexts, the independent \napply basic physical principles independently up to and including \nmathematical equations and the application of procedures up to the solution of differential equation systems.\n\n--- Goals (DE) ---\nDie Studierenden kennen und verstehen grundlegende mathematische Begriffe, die dazu bef\u00e4higen, anwendungsorientierte Problemstellungen aus Naturwissenschaft, Elektrotechnik und Informatik zu l\u00f6sen. Die Studierenden besitzen Kenntnis grundlegender Physik. Sie beherrschen Gesetzm\u00e4\u00dfigkeiten, das Erfassen von \nphysikalischen oder elektrotechnischen Zusammenhangen, das selbstst\u00e4ndige Anwenden grundlegender physikalischer bis hin zur Umsetzung in mathematische Gleichungen und die Anwendung von Verfahren bis hin zur L\u00f6sung von Differentialgleichungssystemen.\n\n--- Contents (EN) ---\n- Fundamentals of physics (Physical Quantities, Measured Value, \nMeasurement Error, SI-Units, Derived Units\n Linear motion, Momentum, Force, Work, Energy\nPower)\n- Electrostatics (Electric Field in empty Space, Charge, Potential, Field Strength, Fields of several point Charges, \nCapacitance, Dielectrics, Polarisation)\nElectric current (Resistance, Ohm's law, \nSwitching processes at capacitances)\nTheory of common Current Networks (Node-mesh analysis, Substitute Sources, Superposition theorem)\nMagnetism (Magnetic Field in empty Space, \nLorenz force, Magnetic Flux, Matter in a Magnetic Field,\nInduction, Switching processes on Coils)\n\n--- Contents (DE) ---\n- Grundlagen der Physik (Physikalische Gr\u00f6\u00dfen, Messwert, Messfehler, SI-Einheiten, Abgeleitete Einheiten\n Lineare Bewegung, Impuls, Kraft, Arbeit, Energie, Leistung)\n- Elektrostatik (Elektrisches Feld im leeren Raum, Ladung, Potential, Feldst\u00e4rke, Felder mehrerer Punktladungen, Kapazit\u00e4ten, Dielektrika, Polarisation)\n- Elektrischer Strom (Widerstand, Ohm'sches Gesetz, Schaltvorg\u00e4nge an Kapazit\u00e4ten)\n- Theorie der Gleichtstromnetze (Knoten- Maschenanalyse, Ersatzquellen, \u00dcberlagerungssatz)\n- Magnetismus (Magnetisches Feld im leeren Raum, Lorenzkraft, magnetischer Fluss, Materie im Magnetfeld, Induktion, Schaltvorg\u00e4nge an Spulen)\n\n--- Literature (EN) ---\n\n\n--- Literature (DE) ---\n- R. Pregla: Grundlagen der Elektrotechnik, 9.Auflage. VDE-Verlag 2016\n- W. Nerreter: Grundlagen der Elektrotechnik, Hanser Verlag 2011", "metadata": {"moduleNumber": "BMT 11", "moduleName": "Fundamentals of Electrical Engineering and Physics", "creditPoints": "5.0", "suggestedSemester": 1, "offeredInSeason": "winter_semester", "examType": "written_exam", "heldInLanguage": "de", "reviserName": "None J\u00f6rg Becker-Schweitzer", "reviserEmail": "jbs@hs-duesseldorf.de", "studyProgramId": 9, "source_type": "json"}}
{"id": "BMT12", "text": "Title: Network Engineering\nModule Number: BMT 12\nCredits: 5.0 CP\nSemester: 1\nOffered In: winter_semester\nLanguage: de\nExam Type: written_exam\nInstructor: Prof. Dr.-Ing. Stefanie Dederichs\n\n--- Goals (EN) ---\nStudents will be familiar with the most important protocols and components in computer networks and building, lighting and event technology networks. They know what tasks they perform and how they relate to each other. Students will be able to plan, set up and configure a local network with all the necessary components. They will be able to systematically analyse and solve connection and performance problems.\n\n--- Goals (DE) ---\nDie Studierenden kennen die wichtigsten Protokolle und Komponenten in Rechnernetzwerken und Netzwerken der Haus- , Beleuchtungs- und Veranstaltungstechnik. Sie wissen, welche Aufgaben diese \u00fcbernehmen und in welchem Zusammenhang sie zueinanderstehen. Die Studierenden sind in der Lage, ein lokales Netz mit allen notwendigen Komponenten zu planen, aufzubauen und zu konfigurieren. Sie k\u00f6nnen Verbindungs- und Performanceprobleme systematisch analysieren und l\u00f6sen.\n\n--- Contents (EN) ---\n- Basic concepts of computer networks\n- Basic concepts of networks in building, lighting and event technology\n- Transmission methods and media\n- Concepts and technologies for local networks\n- Network protocols\n\n--- Contents (DE) ---\n- Grundbegriffe zu Rechnernetzen\n- Grundbegriffe der Netzwerke der Haus-, Beleuchtungs- und Veranstaltungstechnik\n- \u00dcbertragungsverfahren und medien\n- Konzepte und Technologien f\u00fcr lokale Netze\n- Netzwerkprotokolle\n\n--- Literature (EN) ---\n- F. Kauffels: Lokale Netze Band 1 und 2, mitp- Verlag, 2003\n- Cisco CCNA Kursunterlagen (lokale Akademie HSD)\n- D. Comor: Computernetzwerke und Internets, Prentice Hall, 1998\n\nFurther various scripts of the RRZN Hannover on the mentioned topics are offered by the CampusIT of the HSD.\n\n--- Literature (DE) ---\n- F. Kauffels: Lokale Netze Band 1 und 2, mitp- Verlag, 2003\n- Cisco CCNA Kursunterlagen (lokale Akademie HSD)\n- D. Comor: Computernetzwerke und Internets, Prentice Hall, 1998\n\nWeitere diverse Skripte des RRZN Hannover zu den angef\u00fchrten Themenbereichen werden im Vertrieb durch die CampusIT der HSD angeboten.", "metadata": {"moduleNumber": "BMT 12", "moduleName": "Network Engineering", "creditPoints": "5.0", "suggestedSemester": 1, "offeredInSeason": "winter_semester", "examType": "written_exam", "heldInLanguage": "de", "reviserName": "Prof. Dr.-Ing. Stefanie Dederichs", "reviserEmail": "stefanie.dederichs@hs-duesseldorf.de", "studyProgramId": 9, "source_type": "json"}}
{"id": "BMT13", "text": "Title: Computer Science for Engineers\nModule Number: BMT 13\nCredits: 5.0 CP\nSemester: 1\nOffered In: winter_semester\nLanguage: de\nExam Type: written_exam\nInstructor: None Helmut Hiller\n\n--- Goals (EN) ---\nAfter successfully completing the module, students will be able to:\n- explain the basic structure of a computer and the principles of data processing\n- classify different programming paradigms and languages and apply the fundamentals of programming in C\n- design, write, and test simple programs in C independently\n- understand basic algorithms and data structures\n- formulate simple database queries and understand fundamental database concepts\n- understand and explain the typical phases and processes of software development\n- use common software development tools such as compilers and IDEs\n- explain fundamental aspects of IT security and data protection and their relevance to computer science\n\n--- Goals (DE) ---\nNach erfolgreichem Abschluss des Moduls k\u00f6nnen die Studierenden:\n- den grundlegenden Aufbau eines Computers sowie Prinzipien der Datenverarbeitung erkl\u00e4ren\n- verschiedene Programmierparadigmen und -sprachen einordnen und die Grundz\u00fcge der Programmierung in C praktisch anwenden\n- einfache Programme in C eigenst\u00e4ndig entwerfen, schreiben und testen \n- einfache Algorithmen und Datenstrukturen verstehen\n- einfache Datenbankabfragen formulieren und grundlegende Datenbankkonzepte kennen\n- die typischen Phasen und Prozesse der Softwareentwicklung verstehen und erkl\u00e4ren\n- g\u00e4ngige Softwareentwicklungswerkzeuge wie Compiler und IDEs verwenden\n- grundlegende Aspekte der IT-Sicherheit und des Datenschutzes und deren Relevanz f\u00fcr die Informatik erkl\u00e4ren\n\n--- Contents (EN) ---\nThis module provides fundamental knowledge in computer science and software development. It covers the structure and functionality of computers, offers an overview of programming languages, and introduces core programming concepts using the C language. Key topics include data types, control structures, functions, and basic algorithms and data structures. In addition, students are introduced to typical software development cycles and to tools such as operating systems, development environments, and compilers. Further topics include essential software engineering processes, an introduction to working with databases, and an overview of IT security and data protection.\n\n--- Contents (DE) ---\nDas Modul vermittelt grundlegende Kenntnisse der Informatik und Softwareentwicklung. Behandelt werden der Aufbau und die Funktionsweise von Computern, ein \u00dcberblick zu Programmiersprachen sowie zentrale Konzepte der Programmierung am Beispiel der Sprache C. Wichtige Themen sind dabei Datentypen, Kontrollstrukturen, Funktionen und einfache Algorithmen und Datenstrukturen. Erg\u00e4nzend erfolgt eine Einf\u00fchrung in typische Entwicklungszyklen sowie in Werkzeuge wie Betriebssystem, Entwicklungsumgebung und Compiler. Weitere Themen sind grundlegende Prozesse im Softwareengineering, der Einstieg in die Arbeit mit Datenbanken sowie ein \u00dcberblick zu den Themen IT-Sicherheit und Datenschutz.\n\n--- Literature (EN) ---\n- Ernst, Hartmut, Jochen Schmidt, und Gerd Hinrich Beneken. 2023. Grundkurs Informatik: Grundlagen und Konzepte f\u00fcr die erfolgreiche IT-Praxis - eine umfassende Einf\u00fchrung. 8. Auflage. Wiesbaden: Springer Vieweg.\n- Goll, Joachim, und Tobias Stamm. 2024. C als erste Programmiersprache: Nach den Standards C11 und C23. Wiesbaden: Springer Fachmedien.\n- Knolle, Harm, Andreas Behrend, Birgit Bertelsmeier, Heide Faeskorn-Woyke, Thomas Rakow, Inga Saatz, und Johann Schaible. 2024. Datenbanksysteme: Eine praktische Einf\u00fchrung. 1. Auflage. M\u00fcnchen: Hanser, Carl.\n- Eckert, Claudia. 2023. IT-Sicherheit: Konzepte, Verfahren, Protokolle. 11. Auflage. De Gruyter Studium. M\u00fcnchen Boston: De Gruyter Oldenbourg.\n\n--- Literature (DE) ---\n- Ernst, Hartmut, Jochen Schmidt, und Gerd Hinrich Beneken. 2023. Grundkurs Informatik: Grundlagen und Konzepte f\u00fcr die erfolgreiche IT-Praxis - eine umfassende Einf\u00fchrung. 8. Auflage. Wiesbaden: Springer Vieweg.\n- Goll, Joachim, und Tobias Stamm. 2024. C als erste Programmiersprache: Nach den Standards C11 und C23. Wiesbaden: Springer Fachmedien.\n- Knolle, Harm, Andreas Behrend, Birgit Bertelsmeier, Heide Faeskorn-Woyke, Thomas Rakow, Inga Saatz, und Johann Schaible. 2024. Datenbanksysteme: Eine praktische Einf\u00fchrung. 1. Auflage. M\u00fcnchen: Hanser, Carl.\n- Eckert, Claudia. 2023. IT-Sicherheit: Konzepte, Verfahren, Protokolle. 11. Auflage. De Gruyter Studium. M\u00fcnchen Boston: De Gruyter Oldenbourg.", "metadata": {"moduleNumber": "BMT 13", "moduleName": "Computer Science for Engineers", "creditPoints": "5.0", "suggestedSemester": 1, "offeredInSeason": "winter_semester", "examType": "written_exam", "heldInLanguage": "de", "reviserName": "None Helmut Hiller", "reviserEmail": "helmut.hiller@hs-duesseldorf.de", "studyProgramId": 9, "source_type": "json"}}
{"id": "BMT14", "text": "Title: MediaDesign Basics\nModule Number: BMT 14\nCredits: 5.0 CP\nSemester: 1\nOffered In: winter_semester\nLanguage: de\nExam Type: portfolio\nInstructor: Prof. Isolde Asal\n\n--- Goals (EN) ---\nStudents learn and understand the essential criteria of designing medial products. They know the procedure for the development of professionally designed media products and have gained first experience in the implementation. They basically understand the interdisciplinary cultural synergy between media, design and media technology and develop a constructive and critical attitude to media design.\n\n--- Goals (DE) ---\nDie Studierenden erlernen und verstehen die wesentlichen Kriterien der Gestaltung medialer Produkte. Sie kennen das Vorgehen zur Entwicklung professionell gestalteter medialer Produkte und haben erste Erfahrung in der Umsetzung gewonnen. Sie verstehen im Grundsatz die interdisziplin\u00e4re kulturelle Synergie zwischen Medien, Design und Medientechnik und entwickeln eine konstruktive und kritische Haltung zur Mediengestaltung.\n\n--- Contents (EN) ---\n- Basics perception\n- Basics graphic design\n- Basics typography, icons, logo development\n- Basics poster design\n- Basics photography\n- Basics Webdesign\n\n--- Contents (DE) ---\n- Grundlagen Wahrnehmung\n- Grundlagen Grafik-Design\n- Grundlagen Typografie, Icons, Logoentwicklung\n- Grundlagen Plakatgestaltung\n- Grundlagen Fotografie\n- Grundlagen Webdesign\n\n--- Literature (EN) ---\n- T. Porsch, S. Pieschl Hrsg.: Mediennutzung, Medienwirkung und Medienkompetenz, Hogrefe 2014\n- P. Schlaich, P. B\u00fchler, J. Bohringer: Kompendium der Mediengestaltung, Springer Verlag 2011\n- M. Wager: Grafik und Gestaltung, Galileo Press 2010B. Reiter, E. Ruhland: Gute Gestaltung, Addison Wesley Verlag 2011\n- F. Koschembar: Grafik f\u00fcr Nicht-Grafiker, Westend Verlag 2008\n- M. Diefenbach: Workbook visuelles Denken: Ideen, Generieren, Kundenskizzen Anfertigen, Scribbles schnell gestalten, Books on Demand, 2013\n- H. Schmid: 'gestaltung ist haltung/design is attitude', Birkh\u00e4user GmbH 2006P. Renner: Die Kunst der Typographie, Maro 2003\n- G. Schweiger: Praxishandbuch Werbung, UVK Verlagsgesellschaft, 2013M. Hahn: Webdesign, Galileo Press, 2015\n- J. Marchesi: Theorie und Grundlagen der digitalen Foto-grafie, Verlag Photographie, 2011H. Kraus: Digitale Highend-Fotografie: Grundlagen und Werkzeuge der professionellen Digitalfotografie, 2005\n- O. Rausch: Gestalten mit Licht und Schatten: Licht sehen und verstehen, dpunkt.verlag, 2016\n- J. J. Marchesi: Handbuch der Fotografie, Band 1-3, Verlag Photographie, 2006\n\n--- Literature (DE) ---\n- T. Porsch, S. Pieschl Hrsg.: Mediennutzung, Medienwirkung und Medienkompetenz, Hogrefe 2014\n- P. Schlaich, P. B\u00fchler, J. Bohringer: Kompendium der Mediengestaltung, Springer Verlag 2011\n- M. Wager: Grafik und Gestaltung, Galileo Press 2010B. Reiter, E. Ruhland: Gute Gestaltung, Addison Wesley Verlag 2011\n- F. Koschembar: Grafik f\u00fcr Nicht-Grafiker, Westend Verlag 2008\n- M. Diefenbach: Workbook visuelles Denken: Ideen, Generieren, Kundenskizzen Anfertigen, Scribbles schnell gestalten, Books on Demand, 2013\n- H. Schmid: 'gestaltung ist haltung/design is attitude', Birkh\u00e4user GmbH 2006P. Renner: Die Kunst der Typographie, Maro 2003\n- G. Schweiger: Praxishandbuch Werbung, UVK Verlagsgesellschaft, 2013M. Hahn: Webdesign, Galileo Press, 2015\n- J. Marchesi: Theorie und Grundlagen der digitalen Foto-grafie, Verlag Photographie, 2011H. Kraus: Digitale Highend-Fotografie: Grundlagen und Werkzeuge der professionellen Digitalfotografie, 2005\n- O. Rausch: Gestalten mit Licht und Schatten: Licht sehen und verstehen, dpunkt.verlag, 2016\n- J. J. Marchesi: Handbuch der Fotografie, Band 1-3, Verlag Photographie, 2006", "metadata": {"moduleNumber": "BMT 14", "moduleName": "MediaDesign Basics", "creditPoints": "5.0", "suggestedSemester": 1, "offeredInSeason": "winter_semester", "examType": "portfolio", "heldInLanguage": "de", "reviserName": "Prof. Isolde Asal", "reviserEmail": "isolde.asal@hs-duesseldorf.de", "studyProgramId": 9, "source_type": "json"}}
{"id": "BMT15", "text": "Title: Basic project / Learn-Coaching\nModule Number: BMT 15\nCredits: 6.0 CP\nSemester: 1\nOffered In: winter_semester\nLanguage: de\nExam Type: project\nInstructor: Prof. Dr.-Ing. Thomas Bonse\n\n--- Goals (EN) ---\nStudents can take responsibility for themselves and their team as they have experienced socialization in a learning group.\nStudents can realize projects with abstract objectives and a project scope to be managed in a team. To this end, they can structure tasks, define sub-goals and interfaces, develop, implement, test, optimize and document solution concepts based on a division of labour, integrate partial solutions, jointly evaluate and optimize product prototypes, communicate in a goal-oriented and respectful manner, make and adhere to binding agreements.\nStudents can correctly assess their own level of performance through self-reflection\nand reduce and close skills gaps through independent, targeted learning.\nStudents have become familiar with the faculty's facilities and have settled into their studies.\nThey can now develop, evaluate and apply learning and working strategies.\nThey can work under laboratory conditions and can recognize when work is carried out in an engineering manner, i.e. in a planned way, and when it is unstructured and inefficient.\nBy understanding and applying the instructions they receive from the project leaders, the Master's students from the coupled PLET module. By expanding their knowledge, skills and competencies through independent research. By self-reflecting on their own existing competencies, skills and competences.\n\n--- Goals (DE) ---\nDie Studierenden k\u00f6nnen Verantwortung f\u00fcr sich und ihr Team \u00fcbernehmen, da sie die Sozialisierung in einer Lerngruppe durchlebt haben.\nDie Studierenden k\u00f6nnen Projekte mit abstrakten Zielvorgaben und Arbeitsteilig zu bew\u00e4ltigendem Projektumfang im Team realisieren. Dazu k\u00f6nnen sie Aufgabe strukturieren, Teilziele und Schnittstellen definieren, L\u00f6sungskonzepte arbeitsteilig entwickeln, umsetzen, pr\u00fcfen, optimieren und dokumentieren, Teill\u00f6sungen integrieren, Produktprototypen gemeinsam bewerten und optimieren, zielorientiert und respektvoll kommunizieren verbindliche Absprachen treffen und einhalten.\nDie Studierenden k\u00f6nnen durch Selbstreflexion ihren eigenen Leistungsstand korrekt einsch\u00e4tzen\nund durch Selbst\u00e4ndiges, zielgerichtetes Lernen Kompetenzl\u00fccken verkleinern und schlie\u00dfen.\nDie Studierenden haben die Einrichtungen der Fakult\u00e4t kennengelernt und sind im Studium angekommen.\nSie k\u00f6nnen nun Lern- und Arbeitsstrategien entwickeln, bewerten und anwenden.\nSie k\u00f6nnen unter Laborbedingungen arbeiten und k\u00f6nnen erkennen, wann Ingenieurm\u00e4ssig, d.h. in geplante Arbeitsweise, vorgegangen wird und wann unstrukturiert, ineffizient gearbeitet wird.\nWomit: indem sie die Anleitungen, die Sie \u00fcber die Projektleiter*innen, den Masterstudenten*innen aus dem gekoppelten Modul PLET, bekommen, verstehen und anwenden. Indem sie durch eigenst\u00e4ndige Recherchen ihre Kenntnisse, Fertigkeiten und Kompetenzen erweitern. Indem sie durch Selbstreflexion der eigenen, bereits vorhandenen Kompetenzen, St\u00e4rken und Schw\u00e4chen erkennen, bewerten und die Schw\u00e4chen abbauen. Indem sie von den Projektleiter*innen unterst\u00fctzt ein funktionsf\u00e4higes Team bilden, mit dem sie innerhalb der 2 w\u00f6chigen Projektphase ein herausforderndes Kreativ-Projekt realisieren.\nWozu: um sp\u00e4ter ihre eigenen Kompetenzen besser einsch\u00e4tzen zu k\u00f6nnen. Um festzustellen, wie man durch Recherche, Einarbeitung und iteratives Verbessern ein zu Beginn unl\u00f6sbar erscheinendes Projekt in begrenzter Zeit realisieren kann. Um diese Erkenntnisse und gewonnen Kompetenzen auf ihr eigenes Projekt, das Bachelorstudium, erfolgreich anzuwenden. Um direkt zu Beginn eine teamf\u00e4hige Lerngruppe zu finden oder zu bilden, damit sie erfolgreich ihr Studium absolvieren.\n\n--- Contents (EN) ---\nTwo-part module:\n1st project week: in the project team across degree programs and semesters.\n2nd Ring lecture: planning the course of studies, organization during the semester, examination planning, academic work and writing, rights and obligations as a student, opportunities and options during studies: e.g. abroad and industry. Development of technical-mathematical texts and content and implementation of initial simple project results\n\n--- Contents (DE) ---\nZweigeteiltes Modul:\n1. Projektwoche: im Projektteam Studiengangs- und Semester\u00fcbergreifend.\n2. Ringvorlesung: Planung des Studienverlaufs, Organisation im Semester, Pr\u00fcfungsplanung, wissenschaftliches Arbeiten und Schreiben, Rechte und Pflichten als Studierender, M\u00f6glichkeiten und Optionen im Studium: z.B. Ausland und Industrie. Erarbeiten technische-mathematischer Texte und Inhalte und Umsetzung erster einfacher Projektergebnisse\n\n--- Literature (EN) ---\nDepending on content\n\n--- Literature (DE) ---\nAbh\u00e4ngig von den Projektinhalten", "metadata": {"moduleNumber": "BMT 15", "moduleName": "Basic project / Learn-Coaching", "creditPoints": "6.0", "suggestedSemester": 1, "offeredInSeason": "winter_semester", "examType": "project", "heldInLanguage": "de", "reviserName": "Prof. Dr.-Ing. Thomas Bonse", "reviserEmail": "thomas.bonse@hs-duesseldorf.de", "studyProgramId": 9, "source_type": "json"}}
{"id": "BMT20", "text": "Title: Mathematics 2\nModule Number: BMT 20\nCredits: 5.0 CP\nSemester: 2\nOffered In: summer_semester\nLanguage: de\nExam Type: written_exam\nInstructor: None J\u00f6rg Becker-Schweitzer\n\n--- Goals (EN) ---\nStudents are able to apply mathematical methods to a variety of problems. They have a solid understanding of the basic concepts in the areas of linear systems of equations, vector calculus, analytical geometry and linear algebra. In addition, they are proficient in dealing with sequences and power series. Students are able to understand the concept and application of the Fourier transformation and how to carry it out.\n\n--- Goals (DE) ---\nDie Studierenden k\u00f6nnen mathematische Methoden gezielt auf eine Vielzahl von Fragestellungen anwenden. Sie verf\u00fcgen \u00fcber ein solides Verst\u00e4ndnis der Grundkonzepte in den Bereichen lineare Gleichungssysteme, Vektorrechnung, Analytische Geometrie und lineare Algebra. Dar\u00fcber hinaus beherrschen sie den Umgang mit Folgen, sowie Potenzreihen. Die Studierenden sind in der Lage, das Konzept und die Anwendung der Fourier-Transformation zu verstehen und durchzuf\u00fchren.\n\n--- Contents (EN) ---\n- Solving linear systems of equations\n- Vector calculus\n- Analytic geometry\n- Linear algebra\n- Sequences, limits and continuity\n- Power series\n- Generalized functions\n- Fourier transform\n- Laplace transformation\n\n--- Contents (DE) ---\n- L\u00f6sen linearer Gleichungssysteme\n- Vektorrechnung\n- Analytische Geometrie\n- Lineare Algebra\n- Folgen, Grenzwerte und Stetigkeit\n- Potenzreihen\n- Verallgemeinerte Funktionen\n- Fourier-Transformation\n- Laplace-Transformation\n\n--- Literature (EN) ---\n- J. Koch, M. St\u00e4mpfle: Mathematik f\u00fcr das Ingenieurstudium, 3. Auflage, Hanser Verlag, 2015\n- M. Brill: Mathematik f\u00fcr Informatiker, Hanser Verlag 2005\n- K. Kiyek, F. Schwarz: Mathematik f\u00fcr Informatiker, 2 B\u00e4nde, Teubner Verlag 1999\n- P. Stingl: Mathematik f\u00fcr Fachhochschulen, Technik und Informatik, Hanser Verlag 1998\n- L. Papula: Mathematik f\u00fcr Ingenieure und Naturwissenschaftler, 3 B\u00e4nde, Vieweg Verlag 2004\n- T. Westermann: Mathematik f\u00fcr Ingenieure mit Maple, 2 B\u00e4nde, Springer Verlag 2004\n- Maple 9.5 Programming Guide 2005\n\n--- Literature (DE) ---\n- J. Koch, M. St\u00e4mpfle: Mathematik f\u00fcr das Ingenieurstudium, 3. Auflage, Hanser Verlag, 2015\n- M. Brill: Mathematik f\u00fcr Informatiker, Hanser Verlag 2005\n- K. Kiyek, F. Schwarz: Mathematik f\u00fcr Informatiker, 2 B\u00e4nde, Teubner Verlag 1999\n- P. Stingl: Mathematik f\u00fcr Fachhochschulen, Technik und Informatik, Hanser Verlag 1998\n- L. Papula: Mathematik f\u00fcr Ingenieure und Naturwissenschaftler, 3 B\u00e4nde, Vieweg Verlag 2004\n- T. Westermann: Mathematik f\u00fcr Ingenieure mit Maple, 2 B\u00e4nde, Springer Verlag 2004\n- Maple 9.5 Programming Guide 2005", "metadata": {"moduleNumber": "BMT 20", "moduleName": "Mathematics 2", "creditPoints": "5.0", "suggestedSemester": 2, "offeredInSeason": "summer_semester", "examType": "written_exam", "heldInLanguage": "de", "reviserName": "None J\u00f6rg Becker-Schweitzer", "reviserEmail": "jbs@hs-duesseldorf.de", "studyProgramId": 9, "source_type": "json"}}
{"id": "BMT21", "text": "Title: Fundamentals of Electrical Engineering\nModule Number: BMT 21\nCredits: 6.0 CP\nSemester: 2\nOffered In: summer_semester\nLanguage: de\nExam Type: portfolio\nInstructor: None J\u00f6rg Becker-Schweitzer\n\n--- Goals (EN) ---\nStudents have knowledge of physics. They master \nlaws, the understanding of physical relationships, the independent application of basic physical principles, through to the implementation in mathematical equations, the application of methods for solving systems of equations. \nequations, application of methods for solving systems of equations.\nThey learn how to deal with the basic mathematical concepts of analysis, i.e. differential and integral calculus. In particular, students acquire the skills to implement and solve application-oriented problems in electrical engineering. They will be able to calculate and design simple basic electrical engineering circuits in direct and alternating current networks. They can design simple active and passive filters and simple amplifier circuits\n\n--- Goals (DE) ---\nDie Studierenden besitzen Kenntnis der Physik. Sie beherrschen Gesetzm\u00e4\u00dfigkeiten, das Erfassen von physikalischen Zusammenh\u00e4ngen, das selbst\u00e4ndige Anwenden grundlegender physikalische Prinzipien, bis hin zur Umsetzung in mathematische Gleichungen, Anwendung von Verfahren zur L\u00f6sung der Gleichungssysteme.\nSie erwerben den Umgang mit den grundlegenden mathematischen Begriffen der Analysis, d.h. der Differenzial- und Integralrechnung. Insbesondere erhalten die Studierenden die Kompetenzen, anwendungsorientierte Probleme aus Elektrotechnik umzusetzen und zu l\u00f6sen. Sie k\u00f6nnen einfache Grundschaltungen der Elektrotechnik im Gleich- und Wechselstromnetz berechnen und auslegen. Sie k\u00f6nnen einfache aktive und passive Filter sowie einfache Verst\u00e4rkerschaltungen entwerfen\n\n--- Contents (EN) ---\nDirect current networks\nAlternating current networks\nThree-phase networks\nTransformer, resonant circuits, Maxwell's equations, \nElectromagnetic waves, waveguides\nComponents: Semiconductor physics, PN junction, diode, transistor, \noperational amplifier\n\n--- Contents (DE) ---\n- Gleichstromnetzwerke\n- Wechselstromnetzwerke\n- Drehstromnetzwerke\n- Transformator,  Schwingkreise, Maxwell'sche Gleichungen, Elektromagnetische Wellen, Wellenleiter\n- Bauteile: Halbleiterphysik, PN-\u00dcbergang, Diode, Transistor, Operationsverst\u00e4rker\n\n--- Literature (EN) ---\n\n\n--- Literature (DE) ---\n- R. Pregla: Grundlagen der Elektrotechnik, 9.Auflage. VDE-Verlag 2016\n- W. Nerreter: Grundlagen der Elektrotechnik, Hanser Verlag 2011", "metadata": {"moduleNumber": "BMT 21", "moduleName": "Fundamentals of Electrical Engineering", "creditPoints": "6.0", "suggestedSemester": 2, "offeredInSeason": "summer_semester", "examType": "portfolio", "heldInLanguage": "de", "reviserName": "None J\u00f6rg Becker-Schweitzer", "reviserEmail": "jbs@hs-duesseldorf.de", "studyProgramId": 9, "source_type": "json"}}
{"id": "BMT22", "text": "Title: Signal Processing\nModule Number: BMT 22\nCredits: 6.0 CP\nSemester: 2\nOffered In: summer_semester\nLanguage: de\nExam Type: written_exam\nInstructor: Prof. Dr.-Ing. Stefanie Dederichs\n\n--- Goals (EN) ---\nStudents are able to apply appropriate transformations on signals and have basic knowledge of analysing signals in the frequency domain.\n\n--- Goals (DE) ---\nStudierende wenden geeignete Transformationen auf kontinuierliche und diskrete Zeitsignale an und erkennen wesentliche Merkmale im Frequenzbereich. Das Abtasttheorem wird in jedem Zusammenhang sicher beherrscht.\n\n--- Contents (EN) ---\nThe modul focuses on continuous and discrete time signals and thus on digital signal processing. The basics include sampling with respect to the Nyquist-Shannon-Theorem and properties of signals and systems, in particular linear and time-invariant systems, so-called LTI systems. The transformation to the frequency domain contains the continuous and discrete Fourier-Transformation, the Laplace-Transformationand the Z-Transformation.\n\n--- Contents (DE) ---\nElementare Grundlagen zeitdiskreter und zeitkontinuierlicher Signale sowie die Abtastung unter Ber\u00fccksichtigung des Nyquist-Shannon-Theorem sind Gegenstand der Lehre. Die Grundlagen beinhalten Eigenschaften von Signalen und Systemen, insbesondere lineare und zeitinvariante Systeme, sogenannte LTI-Systeme, Fourier-Transformation zeitdiskreter und zeitkontinuierlicher Signale, Laplace-Transformation, Z-Transformation.\n\n--- Literature (EN) ---\nOppenheim, Willsky: Signals and Systems; \nMartin Werner: Nachrichtentechnik;\nMartin Meyer: Signalverarbeitung - Analoge und digitale Signale, Systeme und Filter;\nB. Boulet: Fundamentals of Signals and Systems;\nK. Kammeyer, K. Kroschel: Digitale Signalverarbeitung; etc.\n\n--- Literature (DE) ---\nOppenheim, Willsky: Signals and Systems; \nMartin Werner: Nachrichtentechnik;\nMartin Meyer: Signalverarbeitung - Analoge und digitale Signale, Systeme und Filter;\nB. Boulet: Fundamentals of Signals and Systems;\nK. Kammeyer, K. Kroschel: Digitale Signalverarbeitung; u.v.m.", "metadata": {"moduleNumber": "BMT 22", "moduleName": "Signal Processing", "creditPoints": "6.0", "suggestedSemester": 2, "offeredInSeason": "summer_semester", "examType": "written_exam", "heldInLanguage": "de", "reviserName": "Prof. Dr.-Ing. Stefanie Dederichs", "reviserEmail": "stefanie.dederichs@hs-duesseldorf.de", "studyProgramId": 9, "source_type": "json"}}
{"id": "BMT23", "text": "Title: Informatics for Engineers 2\nModule Number: BMT 23\nCredits: 5.0 CP\nSemester: 2\nOffered In: summer_semester\nLanguage: de\nExam Type: written_exam\nInstructor: None Helmut Hiller\n\n--- Goals (EN) ---\nAfter successfully completing the module, students will be able to:\n- confidently apply object-oriented concepts such as classes, objects, inheritance, and interfaces\n- design, implement, and test simple applications in Java\n- implement state-based logic\n- design and develop graphical user interfaces (GUIs)\n- understand, select, and implement fundamental algorithms and data structures at an advanced level\n- demonstrate an overview of using version control tools (e.g., Git) in both team and individual projects\n- plan, structure, and organize small software projects in a team environment\n- integrate software testing into the development process to ensure software quality\n\n--- Goals (DE) ---\nNach erfolgreichem Abschluss des Moduls sind die Studierenden in der Lage:\n-\tobjektorientierte Konzepte wie Klassen, Objekte, Vererbung und Interfaces sicher anzuwenden\n-\teinfache Anwendungen in Java zu entwerfen, zu implementieren und zu testen\n-\tzustandsbasierte Logik umzusetzen\n-\tgrafische Benutzeroberfl\u00e4chen (GUIs) zu gestalten und umzusetzen\n-\tgrundlegende Algorithmen und Datenstrukturen vertiefend zu verstehen, auszuw\u00e4hlen und zu implementieren\n-\t\u00dcberblick zur Nutzung von Werkzeugen zur Versionskontrolle (Git) in Team- und Einzelprojekten\n-\teinfache Softwareprojekte zu planen, zu strukturieren und im Team zu organisieren\n-\tSoftwaretests in den Entwicklungsprozess zu integrieren (Qualit\u00e4t von Software sichern)\n\n--- Contents (EN) ---\nThis module builds on the foundations of software development, with a focus on object-oriented programming and software development processes. It covers the principles of object-oriented and state-based programming using the Java programming language, including classes, objects, methods, inheritance, and interfaces. Additional topics include the development of graphical user interfaces (GUIs), software testing, and the design and implementation of small applications. Furthermore, important algorithms and data structures are explored in greater depth and applied. The module also introduces students to the organization and management of software projects, including the practical use of version control systems with Git.\n\n--- Contents (DE) ---\nDas Modul vertieft die Grundlagen der Softwareentwicklung mit Fokus auf objektorientierte Programmierung und Softwareentwicklungsprozessen. Behandelt werden Konzepte der objektorientierten und zustandsbasierten Programmierung anhand der Programmiersprache Java: Klassen, Objekte, Methoden, Vererbung und Interfaces. Weitere Inhalte sind die Entwicklung grafischer Benutzeroberfl\u00e4chen (GUIs), Testen von Software sowie der Entwurf und die Umsetzung kleiner Anwendungen. Dar\u00fcber hinaus werden wichtige Algorithmen und Datenstrukturen weiterf\u00fchrend betrachtet und angewendet.  Erg\u00e4nzend wird in die Organisation und das Management von Softwareprojekten eingef\u00fchrt unter praktischer Nutzung der Versionsverwaltung mit Git.\n\n--- Literature (EN) ---\n- Sommerville, Ian. 2020. Modernes Software-Engineering: Entwurf und Entwicklung von Softwareprodukten. Studium IT. M\u00fcnchen: Pearson Deutschland.\n- Abts, Dietmar. 2024. Grundkurs JAVA: Von den Grundlagen bis zu Datenbank- und Netzanwendungen. Wiesbaden: Springer Fachmedien.\n- Kopec, David. 2021. Algorithmen in Java: 32 Klassiker vom Rucksackproblem bis zu Neuronalen Netzen. 1. Auflage. Bonn: Rheinwerk Verlag.\n- Ullenboom, Christian. 2024. Java ist auch eine Insel: Einf\u00fchrung, Ausbildung, Praxis. 17., aktualisierte und \u00fcberarbeitete Auflage. Bonn: Rheinwerk Computing.\n\n--- Literature (DE) ---\n- Sommerville, Ian. 2020. Modernes Software-Engineering: Entwurf und Entwicklung von Softwareprodukten. Studium IT. M\u00fcnchen: Pearson Deutschland.\n- Abts, Dietmar. 2024. Grundkurs JAVA: Von den Grundlagen bis zu Datenbank- und Netzanwendungen. Wiesbaden: Springer Fachmedien.\n- Kopec, David. 2021. Algorithmen in Java: 32 Klassiker vom Rucksackproblem bis zu Neuronalen Netzen. 1. Auflage. Bonn: Rheinwerk Verlag.\n- Ullenboom, Christian. 2024. Java ist auch eine Insel: Einf\u00fchrung, Ausbildung, Praxis. 17., aktualisierte und \u00fcberarbeitete Auflage. Bonn: Rheinwerk Computing.", "metadata": {"moduleNumber": "BMT 23", "moduleName": "Informatics for Engineers 2", "creditPoints": "5.0", "suggestedSemester": 2, "offeredInSeason": "summer_semester", "examType": "written_exam", "heldInLanguage": "de", "reviserName": "None Helmut Hiller", "reviserEmail": "helmut.hiller@hs-duesseldorf.de", "studyProgramId": 9, "source_type": "json"}}
{"id": "BMT24", "text": "Title: Fundamentals of Digital Engineering\nModule Number: BMT 24\nCredits: 5.0 CP\nSemester: 2\nOffered In: summer_semester\nLanguage: de\nExam Type: written_exam\nInstructor: None J\u00f6rg Becker-Schweitzer\n\n--- Goals (EN) ---\nStudents understand the principles of converting analog to digital signals. They can perform simple digital processing, encoding and storage. They can convert the digital signals back to analog signals. They are able to simulate the processes.\n\n--- Goals (DE) ---\nDie Studierenden verstehen die Prinzipien der Umwandlung von analogen zu digitalen Signalen. Sie k\u00f6nnen einfache digitale Verarbeitung, Codierung und Speicherung durchf\u00fchren und die digitalen Signale wieder in analoge Signale umwandeln. Sie sind in der Lage, die Vorg\u00e4nge mittels Softwareunterst\u00fctzung zu simulieren.\n\n--- Contents (EN) ---\nAnalog to digital conversion, Coding and numerical systems, Boolean algebrabasic logic modules, programmable logic building blocks, basic digital circuitsdigital to analog conversion, simulation of circuits\n\n--- Contents (DE) ---\nAnalog-Digitalwandlung, Kodierung und Zahlensysteme, boolesche Algebra, einfache Logikbausteine, programmierbare Logikbausteine, digitale Grundschaltungen, Digital-Analogwandlung, Simulation von Schaltungen\n\n--- Literature (EN) ---\n- K. Fricke: Digitaltechnik, Verlag Vieweg+Teubner 2009\n- C. Siemers, A. Sikora: Taschenbuch Digitaltechnik, HanserVerlag 2007\n\nFurther literature will be announced at the beginning of the course.\n\n--- Literature (DE) ---\n- K. Fricke: Digitaltechnik, Verlag Vieweg+Teubner 2009\n- C. Siemers, A. Sikora: Taschenbuch Digitaltechnik, HanserVerlag 2007\n\nWeitere Literatur wird zu Beginn der LV bekannt gegeben.", "metadata": {"moduleNumber": "BMT 24", "moduleName": "Fundamentals of Digital Engineering", "creditPoints": "5.0", "suggestedSemester": 2, "offeredInSeason": "summer_semester", "examType": "written_exam", "heldInLanguage": "de", "reviserName": "None J\u00f6rg Becker-Schweitzer", "reviserEmail": "jbs@hs-duesseldorf.de", "studyProgramId": 9, "source_type": "json"}}
{"id": "BMT30", "text": "Title: Technical Acoustics\nModule Number: BMT 30\nCredits: 5.0 CP\nSemester: 3\nOffered In: winter_semester\nLanguage: de\nExam Type: written_exam\nInstructor: Prof. Dr.-Ing. Jochen Steffens\n\n--- Goals (EN) ---\nThe students are able to apply fundamentials of physics and engineering to calculate sound propagation.  They have basic knowledge on the determination of sound field quantities, acoustic properties of different materials an they can judge different spacial sound source configurations acoordung to their functions\n\n--- Goals (DE) ---\nDie Studierenden k\u00f6nnen die wesentlichen physikalischen, technischen Grundlagen zur akustischer Schallausbreitung anwenden. Sie beherrschen grundlegende Methoden zur Bestimmung von Schallfeldgr\u00f6\u00dfen, akustische Materialgr\u00f6\u00dfen und k\u00f6nnen r\u00e4umliche Anordnung von Schallquellen in der Funktionsweise beurteilen.\n\n--- Contents (EN) ---\n- Definition and meaning of acoustics\n- Sound and vibrations (sound field quantities)\n- Perception of sound (Weber-Fechner law, loudness perception and decibels, hearing range)\n- Basic concepts of wave propagation (general gas equation, adiabatic equation of state, basic equations of acoustics, wave equation)\n- Propagating and standing waves (solutions of the wave equation, propagating waves, standing waves and resonance phenomena, total fields, three-dimensional wave equation)\n- Energy and power transport and intensity measurement methods\n- Wave propagation in a moving medium (Doppler effect)\n- Sound radiation (omnidirectional radiation from point and line sources, volume sources, sound field of two sources, dipole)\n- Loudspeaker arrays (one-dimensional piston cone, shaping of main and side lobes, electronic panning)\n- Sound absorption I / measurements in Kundt's tube (2dim. Sound propagation in the tube, Mini-Max method, wave separation, sound absorption quantities, in-situ measurement method)\n- Sound absorption II (wall impedance, porous absorbers, matching law, acoustic equations in a porous medium, special absorbing arrangements)\n- Room acoustics (sound propagation in a room, mirror sound sources, wave theory, diffuse sound field, Sabine's reverberation formula)\n- Electroacoustic transducers for airborne sound (general operating principles, condenser microphones, directional dependencies of microphones, electrodynamic microphones and loudspeakers)\n\n--- Contents (DE) ---\n- Definition und Bedeutung von Akustik\n- Schall und Schwingungen (Schallfeldgr\u00f6\u00dfen)\n- Wahrnehmung von Schall (Weber-Fechner-Gesetz, Lautst\u00e4rkeempfindung und Dezibel, H\u00f6rbereich)\n- Grundbegriffe der Wellenausbreitung (Allgemeine Gasgleichung, adiabatische Zustandsgleichung, Grundgleichungen der Akustik, Wellengleichung)\n- Fortschreitende und stehende Wellen (L\u00f6sungen der Wellengleichung, fortschreitende Wellen, stehende Wellen und Resonanzph\u00e4nomen, Gesamtfelder, dreidimensionale Wellengleichung)\n- Energie- und Leistungstransport und Intensit\u00e4tsmessverfahren\n- Wellenausbreitung im bewegten Medium (Dopplereffekt)\n- Schallabstrahlung (Ungerichtete Abstrahlung von Punkt- und Linienquellen, Volumenquellen, Schallfeld zweier Quellen, Dipol)\n- Lautsprecherzeilen (eindimensionale Kolbenmembran, Formung von Haupt- und Nebenkeulen, elektronisches Schwenken\n- Schallabsorption I / Messungen im Kundtschen Rohr (2dim. Schallausbreitung im Rohr, Mini-Max-Verfahren, Wellentrennung, Gr\u00f6\u00dfen der Schallabsorption, In-Situ-Messverfahren)\n- Schallabsorption II (Wandimpedanz, por\u00f6se Absorber, Anpassungsgesetz, akustische Gleichungen im por\u00f6sen Medium, spezielle absorbierende Anordnungen)\n- Raumakustik (Schallausbreitung im Raum, Spiegelschallquellen, wellentheoretische Betrachtung, diffuses Schallfeld, Sabinesche Nachhallformel)\n- Elektroakustische Wandler f\u00fcr Luftschall (Allgemeine Funktionsprinzipien, Kondensatormikrofone, Richtungsabh\u00e4ngigkeiten von Mikrofonen, Elektrodynamische Mikrofone und Lautsprecher)\n\n--- Literature (EN) ---\nM\u00f6ser, M.: Technische Akustik 10.Aufl. Springer, 2015\nKuttruff, H.: Akustik - Eine Einf\u00fchrung, Hirzel, 2004\nCremer, L. & M\u00fcller, H. A.: Die wissenschaftlichen Grundlagen der Raumakustik, Bd. 1, Hirzel, 1978\nLerch, R.: Technische Akustik: Grundlagen und Anwendungen, Springer, 2009\n\n--- Literature (DE) ---\nM\u00f6ser, M.: Technische Akustik 10.Aufl. Springer, 2015\nKuttruff, H.: Akustik - Eine Einf\u00fchrung, Hirzel, 2004\nCremer, L. & M\u00fcller, H. A.: Die wissenschaftlichen Grundlagen der Raumakustik, Bd. 1, Hirzel, 1978\nLerch, R.: Technische Akustik: Grundlagen und Anwendungen, Springer, 2009", "metadata": {"moduleNumber": "BMT 30", "moduleName": "Technical Acoustics", "creditPoints": "5.0", "suggestedSemester": 3, "offeredInSeason": "winter_semester", "examType": "written_exam", "heldInLanguage": "de", "reviserName": "Prof. Dr.-Ing. Jochen Steffens", "reviserEmail": "jochen.steffens@hs-duesseldorf.de", "studyProgramId": 9, "source_type": "json"}}
{"id": "BMT31", "text": "Title: Audio Engineering\nModule Number: BMT 31\nCredits: 5.0 CP\nSemester: 3\nOffered In: winter_semester\nLanguage: de\nExam Type: written_exam\nInstructor: Prof. Dr.-Ing. Dieter Leckschat\n\n--- Goals (EN) ---\nAfter completing the course, students will be able to use audio technology equipment and relevant software in a professional manner and with the necessary background knowledge. From the practical exercises, students will have learned the basic methods of sound and music production. They can apply these in such a way that technically flawless and sonically appealing productions are created.\n\n--- Goals (DE) ---\nDie Studierenden sind nach Abschluss der Lehrveranstaltung in der Lage, mit Ger\u00e4ten der Audiotechnik und einschl\u00e4giger Software in professioneller Weise und mit dem n\u00f6tigen Hintergrundwissen umzugehen. Aus den praktischen \u00dcbungen haben die Studierenden grundlegende Arbeitsweisen der Ton- und Musikproduktion erlernt. Sie k\u00f6nnen diese so anwenden, dass technisch einwandfreie und klanglich ansprechende Produktionen entstehen.\n\n--- Contents (EN) ---\nThe focus is on the basics and conventional sound technology: basics of audio technology, professional recording, processing, storage, transmission and analysis of analogue and digital sound signals and the technical implementation of equipment.\n\n--- Contents (DE) ---\nDer Schwerpunkt liegt auf den Grundlagen und der konventionellen Tontechnik: Grundlagen der Audiotechnik, Professionelle Aufnahme, Bearbeitung, Speicherung, \u00dcbertragung und Analyse von analogen und digitalen Tonsignalen und die ger\u00e4tetechnische Realisierung.\n\n--- Literature (EN) ---\n- Th. Gorne: Tontechnik, Hanser Fachbuchverlag 2011S. \n- Weinzierl (Hrgb.): Handbuch der Audiotechnik, Springer Verlag 2008\n- J. Webers: Das Handbuch der Tonstudiotechnik, Franzis\u00b4 Verlag 7. Auflage 1999\n- M.Zollner, E. Zwicker: Elektroakustik, Springer Verlag 1998\n- Journal of the Audio Engineering Society (AES)\n\n--- Literature (DE) ---\n- Th. Gorne: Tontechnik, Hanser Fachbuchverlag 2011S. \n- Weinzierl (Hrgb.): Handbuch der Audiotechnik, Springer Verlag 2008\n- J. Webers: Das Handbuch der Tonstudiotechnik, Franzis\u00b4 Verlag 7. Auflage 1999\n- M.Zollner, E. Zwicker: Elektroakustik, Springer Verlag 1998\n- Journal of the Audio Engineering Society (AES)", "metadata": {"moduleNumber": "BMT 31", "moduleName": "Audio Engineering", "creditPoints": "5.0", "suggestedSemester": 3, "offeredInSeason": "winter_semester", "examType": "written_exam", "heldInLanguage": "de", "reviserName": "Prof. Dr.-Ing. Dieter Leckschat", "reviserEmail": "dieter.leckschat@hs-duesseldorf.de", "studyProgramId": 9, "source_type": "json"}}
{"id": "BMT32", "text": "Title: Fundamentals of Image Engineering\nModule Number: BMT 32\nCredits: 5.0 CP\nSemester: 3\nOffered In: winter_semester\nLanguage: de\nExam Type: written_exam\nInstructor: Prof. Dr.-Ing. Thomas Bonse\n\n--- Goals (EN) ---\nStudents understand the physical principles of light and lighting and can describe them formally. They know the most important properties of the human visual system. They will be able to describe how technical systems for image acquisition and reproduction work in image transmission systems (studio cameras, EB cameras, displays). They will be able to describe the necessary fundamentals of signal processing for digital video signals (image field decomposition, scanning, transmission). They are able to give examples of important interfaces between the system components of image engineering. They are able to interpret the coding transformation for still images (DCT) and calculate this themself in practical examples.\n\n--- Goals (DE) ---\nDie Studierenden verstehen die physikalischen Grundlagen von Licht und Beleuchtung und k\u00f6nnen diese formal beschreiben. Sie kennen die wichtigsten Eigenschaften des menschlichen visuellen Systems. Sie k\u00f6nnen in Bild\u00fcbertragungssystemen beschreiben, wie technische Systeme zur Bildaufnahme und Bildwiedergabe funktionieren (Studiokameras, EB-Kameras, Displays). Dabei k\u00f6nnen sie die erforderlichen Grundlagen der Signaltheorie f\u00fcr digitale Bildsignale (Bildfeldzerlegung, Abtastung, \u00dcbertragung) darstellen. F\u00fcr wichtige Schnittstellen zwischen den Systemkomponenten der Bildtechnik k\u00f6nnen Sie Beispiele angeben. Sie k\u00f6nnen die Transformationscodierung f\u00fcr Stillbilder (DCT) interpretieren und diese in praktischen Beispielen selbst errechnen.\n\n--- Contents (EN) ---\nThe module provides an introduction to image and video engineering:\n- Physical and psychophysical fundamentals of image engineering\n- Colourimetry, lighting technology\n- Fundamentals of signal processing in video technology\n- camera and display technologies\n- Fundamentals of digital image and video technology\n- Source coding for images\n\n--- Contents (DE) ---\nDas Modul f\u00fchrt in Bild- und Videotechnik ein:\n- Physikalische und psychophysische Grundlagen der Bildtechnik\n- Farbmetrik, Beleuchtungstechnik\n- Grundlagen der Signalverarbeitung in der Videotechnik\n- Bildaufnahme- und Bildwiedergabetechnik\n- Grundlagen der digitalen Bild- und Videotechnik\n- Quellencodierung f\u00fcr Stillbilder\nAnschlussmodul: Vertiefung Bildtechnik\n\n--- Literature (EN) ---\n\n\n--- Literature (DE) ---\n- U. Schmidt: Professionelle Videotechnik, Springer Verlag 2021\n- C. Poynton: Digital Video and HD, 2nd Edition, Algorithms and Interfaces, Morgan Kaufmann Publishers 2012\n- Th, Bonse, F. Kaderali: Digitale Bildcodierung - Grundlagen der Bildcodierung, Hagen, 2007", "metadata": {"moduleNumber": "BMT 32", "moduleName": "Fundamentals of Image Engineering", "creditPoints": "5.0", "suggestedSemester": 3, "offeredInSeason": "winter_semester", "examType": "written_exam", "heldInLanguage": "de", "reviserName": "Prof. Dr.-Ing. Thomas Bonse", "reviserEmail": "thomas.bonse@hs-duesseldorf.de", "studyProgramId": 9, "source_type": "json"}}
{"id": "BMT33", "text": "Title: Fundamentals of Computer Graphics\nModule Number: BMT 33\nCredits: 5.0 CP\nSemester: 3\nOffered In: winter_semester\nLanguage: de\nExam Type: written_exam\nInstructor: Prof. Dr.-Ing. Sina Mostafawy\n\n--- Goals (EN) ---\nThe students know the basics of 3D computer graphics, the functionality of the graphics pipeline, local illumoination algorithms and shading techniques and can apply them.\n\n--- Goals (DE) ---\nDie Student:innen kennen die Grundlagen der 3D Computergrafik, die Funktionsweise der Grafikpipeline, lokale Beleuchtungsmodelle und Shading-Verfahren und k\u00f6nnen diese anwenden.\n\n--- Contents (EN) ---\nFixed Graphics Pipeline\nRasterization techniques\nClipping and Culling Algorithms\nMatrix Transformations  (2D/ 3D)\nOrthogonal and Perspective Projektion\nIllumination and Shading Algorithms \nBasics of Bezi\u00e9r interpolation\n\n--- Contents (DE) ---\nFixed Graphics Pipeline\nRasterization techniques\nClipping and Culling Algorithms\nMatrix Transformations  (2D/ 3D)\nOrthogonal and Perspective Projektion\nIllumination and Shading Algorithms \nBasics of Bezi\u00e9r interpolation\n\n--- Literature (EN) ---\n\n\n--- Literature (DE) ---\nComputer Graphics with OpenGL, D. Hearn, M.P. Baker, Pearson Education I\nAdvanced Animation and Rendering Techniques, Watt, M. Watt, Addison Wesley\nComputergrafik,Xiang, Zhigang; Plastock, Roy mitp/bhv\nFundamentals of Computer Graphics, Shirley P. \nAdvanced Global Illumination, P. Dutr\u00e9, AK Peters", "metadata": {"moduleNumber": "BMT 33", "moduleName": "Fundamentals of Computer Graphics", "creditPoints": "5.0", "suggestedSemester": 3, "offeredInSeason": "winter_semester", "examType": "written_exam", "heldInLanguage": "de", "reviserName": "Prof. Dr.-Ing. Sina Mostafawy", "reviserEmail": "sina.mostafawy@hs-duesseldorf.de", "studyProgramId": 9, "source_type": "json"}}
{"id": "BMT34", "text": "Title: Embedded Systems\nModule Number: BMT 34\nCredits: 5.0 CP\nSemester: 3\nOffered In: winter_semester\nLanguage: de\nExam Type: written_exam\nInstructor: Dipl.-Ing. M.Sc. Christian Epe\n\n--- Goals (EN) ---\nStudents can understand digital media technology devices in terms of their hardware function and assess the specifications. They can recognize the requirements for a microcontroller/microprocessor-based system including sensors and actuators and design, develop and program them accordingly.\n\n--- Goals (DE) ---\nStudierende k\u00f6nnen digitale Ger\u00e4te der Medientechnik in ihrer Hardwarefunktion verstehen und die Spezifikationen beurteilen. Sie k\u00f6nnen die Anforderungen an ein mikrocontroller- /mikoprozessorbasiertes System inkl. Sensoren und Aktoren erkennen und entsprechend konzipieren, entwickeln und programmieren.\n\n--- Contents (EN) ---\n- Programming of common microcontroller systems\n- Introduction to semiconductor manufacturing and integrated circuit design (ASIC, FPGA, logic synthesis)\n- Processor types and their tasks in the media technology context\n- Parallel/serial interfaces and bus systems in media technology\n- Storage technologies (volatile & non-volatile memories)\n- Finite state machines\n- SoC\n- Sensor technology\n- Power-saving \u00b5C design\n- Real-time systems\n- Introduction to feedback control system technology\n- Wireless transmission in the area of IoT and smart home\n\n--- Contents (DE) ---\n- Programmierung g\u00e4ngiger Mikrocontroller-Systeme\n- Einf\u00fchrung in die Halbleiterherstellung und den Entwurf integrierter Schaltungen (ASIC, FPGA, Logic-Synthese)\n- Prozessortypen und ihre Aufgaben im medientechnologischen Kontext\n- Parallele/Serielle Schnittstellen und Bus-Systeme in der Medientechnik\n- Speichertechnologien (fl\u00fcchtige & nicht fl\u00fcchtige Speicher)\n- Finite-State-Machines\n- SoC \n- Sensorik\n- Stromsparendes \u00b5C-Design \n- Echtzeitsysteme\n- Einf\u00fchrung in die Regelungstechnik\n- Drahtlose \u00dcbertragung im Bereich IoT und Smarthome\n\n--- Literature (EN) ---\n- D. W. Hoffmann : Grundlagen der Technischen Informatik, Carl Hanser Verlag\n- H.G\u00f6bel: Einf\u00fchrung in die Halbleiter-Schaltungstechnik, Springer \n- Frank Kesel: FPGA Hardware-Entwurf, De Gruyter Oldenbourg\n- Jens Lienig: Layoutsynthese elektronischer Schaltungen, Springer\n- Klaus W\u00fcst: Mikroprozessortechnik, Vieweg & Teubner\n- W.Pla\u00dfmann, D.Schulz : Handbuch Elektrotechnik - Grundlagen und Anwendungen f\u00fcr Elektrotechniker , Springer\n- L.Stiny: Grundwissen Elektrotechnik und Elektronik, Springer\n\n--- Literature (DE) ---\n- D. W. Hoffmann : Grundlagen der Technischen Informatik, Carl Hanser Verlag\n- H.G\u00f6bel: Einf\u00fchrung in die Halbleiter-Schaltungstechnik, Springer \n- Frank Kesel: FPGA Hardware-Entwurf, De Gruyter Oldenbourg\n- Jens Lienig: Layoutsynthese elektronischer Schaltungen, Springer\n- Klaus W\u00fcst: Mikroprozessortechnik, Vieweg & Teubner\n- W.Pla\u00dfmann, D.Schulz : Handbuch Elektrotechnik - Grundlagen und Anwendungen f\u00fcr Elektrotechniker , Springer\n- L.Stiny: Grundwissen Elektrotechnik und Elektronik, Springer", "metadata": {"moduleNumber": "BMT 34", "moduleName": "Embedded Systems", "creditPoints": "5.0", "suggestedSemester": 3, "offeredInSeason": "winter_semester", "examType": "written_exam", "heldInLanguage": "de", "reviserName": "Dipl.-Ing. M.Sc. Christian Epe", "reviserEmail": "christian.epe@hs-duesseldorf.de", "studyProgramId": 9, "source_type": "json"}}
{"id": "BMT35", "text": "Title: Media production processes\nModule Number: BMT 35\nCredits: 5.0 CP\nSemester: 3\nOffered In: winter_semester\nLanguage: de\nExam Type: written_exam\nInstructor: \n\n--- Goals (EN) ---\n1. Understanding of the business fundamentals of media production, including budgeting, cost calculation and project management.\n2. Ability to creatively design and implement media content, taking into account aesthetic and design principles.\n3. Development of skills for efficient planning and implementation of media projects, taking into account time and resource constraints.\n4. Use of technological tools and methods to optimize media production and ensure product quality.\n\n--- Goals (DE) ---\n1. Verst\u00e4ndnis f\u00fcr die betriebswirtschaftlichen Grundlagen der Medienproduktion, einschlie\u00dflich Budgetierung, Kostenkalkulation und Projektmanagement.\n2. F\u00e4higkeit zur kreativen Gestaltung und Umsetzung von Medieninhalten unter Ber\u00fccksichtigung \u00e4sthetischer und gestalterischer Prinzipien.\n3. Entwicklung von Fertigkeiten zur effizienten Planung und Durchf\u00fchrung von Medienprojekten unter Ber\u00fccksichtigung von Zeit- und Ressourcenbeschr\u00e4nkungen.\n4. Anwendung von technologischen Werkzeugen und Methoden zur Optimierung der Medienproduktion und Sicherstellung der Produktqualit\u00e4t.\n\n--- Contents (EN) ---\nThe module \"Media Production Processes\" offers students a holistic insight into the planning, implementation and optimization of media production projects from a business, technical and design perspective. Students will become familiar with basic concepts of media production and gain practical experience in the effective planning, design and implementation of media projects.\n. **Basics of media production:**\n   - Introduction to the different formats and genres of audiovisual media production.\n   - Overview of the phases of the production process: preparation, production and post-production.\n\n2 **Business aspects of media production:**\n   - Budgeting and costing for media production projects.\n   - Project management techniques and tools for the effective planning and coordination of media projects.\n\n3 **Media design basics:**\n   - Aesthetic principles and design techniques for audiovisual media production.\n   - Use of color, composition and design in media production.\n\n4 **Technologies in media production:**\n   - Overview of the main technological instruments and tools used in media production, including cameras, sound and lighting equipment and editing software.\n\n5 **Workflow optimization and efficiency improvement:**\n   - Analysis of production workflows and identification of bottlenecks or inefficient processes.\n   - Implementation of methods to optimize the workflow and increase productivity.\n\n6 **Quality assurance and control:**\n   - Develop strategies to ensure the quality of media products throughout the production process.\n   - Use of quality control tools and procedures.\n\n7 **Risk management in media production:**\n   - Identify potential risks and problems during the production phases.\n   - Development of risk mitigation and management strategies.\n\n--- Contents (DE) ---\nDas Modul \"Medienproduktions-Prozesse\" bietet den Studierenden einen ganzheitlichen Einblick in die Planung, Durchf\u00fchrung und Optimierung von Medienproduktionsprojekten aus betriebswirtschaftlicher, technischer und gestalterischer Perspektive. Die Studierenden werden grundlegende Konzepte der Medienproduktion kennenlernen und praktische Erfahrung in der effektiven Planung, Gestaltung und Umsetzung von Medienprojekten sammeln.\n. **Grundlagen der Medienproduktion:**\n   - Einf\u00fchrung in die verschiedenen Formate und Genres der audiovisuellen Medienproduktion.\n   - \u00dcberblick \u00fcber die Phasen des Produktionsprozesses: Vorbereitung, Produktion und Postproduktion.\n\n2. **Betriebswirtschaftliche Aspekte der Medienproduktion:**\n   - Budgetierung und Kostenkalkulation f\u00fcr Medienproduktionsprojekte.\n   - Projektmanagementtechniken und -tools f\u00fcr die effektive Planung und Koordination von Medienprojekten.\n\n3. **Mediengestalterische Grundlagen:**\n   - \u00c4sthetische Prinzipien und Gestaltungstechniken f\u00fcr die audiovisuelle Medienproduktion.\n   - Nutzung von Farbe, Komposition und Design in der Medienproduktion.\n\n4. **Technologien in der Medienproduktion:**\n   - \u00dcberblick \u00fcber die wichtigsten technologischen Instrumente und Werkzeuge in der Medienproduktion, einschlie\u00dflich Kameras, Ton- und Lichtausr\u00fcstung sowie Editing-Software.\n\n5. **Workflow-Optimierung und Effizienzsteigerung:**\n   - Analyse von Produktionsabl\u00e4ufen und Identifizierung von Engp\u00e4ssen oder ineffizienten Prozessen.\n   - Implementierung von Methoden zur Optimierung des Workflows und zur Steigerung der Produktivit\u00e4t.\n\n6. **Qualit\u00e4tssicherung und -kontrolle:**\n   - Entwicklung von Strategien zur Sicherstellung der Qualit\u00e4t von Medienprodukten w\u00e4hrend des gesamten Produktionsprozesses.\n   - Einsatz von Qualit\u00e4tskontrollwerkzeugen und -verfahren.\n\n7. **Risikomanagement in der Medienproduktion:**\n   - Identifizierung potenzieller Risiken und Probleme w\u00e4hrend der Produktionsphasen.\n   - Entwicklung von Strategien zur Risikominderung und -bew\u00e4ltigung.\n\n--- Literature (EN) ---\n\n\n--- Literature (DE) ---\n- \"The Filmmaker's Handbook\" von Steven Ascher und Edward Pincus\n- \"Digital Video Production Cookbook\" von Chris Kenworthy\n- \"Project Management for Engineering and Technology\" von David L. Goetsch und Stanley Davis\n- \"Mediengestaltung: Kreative Grundlagen, Techniken, Werkzeuge\" von Michael Kr\u00fcger", "metadata": {"moduleNumber": "BMT 35", "moduleName": "Media production processes", "creditPoints": "5.0", "suggestedSemester": 3, "offeredInSeason": "winter_semester", "examType": "written_exam", "heldInLanguage": "de", "reviserName": "", "reviserEmail": null, "studyProgramId": 9, "source_type": "json"}}
{"id": "BMT40", "text": "Title: Advanced module 1\nModule Number: BMT 40\nCredits: 5.0 CP\nSemester: 4\nOffered In: summer_semester\nLanguage: de\nExam Type: see_elective\nInstructor: \n\n--- Goals (EN) ---\nDepending on the elected course\n\n--- Goals (DE) ---\nAbh\u00e4ngig vom belegten Fachmodul\n\n--- Contents (EN) ---\nThis is a subject module (compulsory elective module) for which modules from the elective catalog of subject modules can be taken.\nThe semester (winter semester, summer semester) in which this subject module is taken is not specified.\n\n--- Contents (DE) ---\nDas ist ein Fachmodul (Wahlpflichtmodul), f\u00fcr das Module aus dem Wahlkatalog Fachmodule belegt werden k\u00f6nnen.\nIn welchem Semester (WiSe, SoSe) dieses Fachmodul belegt wird, ist nicht festgelegt.\n\n--- Literature (EN) ---\nDepending on the elected course\n\n--- Literature (DE) ---\nAbh\u00e4ngig vom belegten Fachmodul", "metadata": {"moduleNumber": "BMT 40", "moduleName": "Advanced module 1", "creditPoints": "5.0", "suggestedSemester": 4, "offeredInSeason": "summer_semester", "examType": "see_elective", "heldInLanguage": "de", "reviserName": "", "reviserEmail": null, "studyProgramId": 9, "source_type": "json"}}
{"id": "BMT41", "text": "Title: Advanced module 2\nModule Number: BMT 41\nCredits: 5.0 CP\nSemester: 4\nOffered In: summer_semester\nLanguage: de\nExam Type: see_elective\nInstructor: \n\n--- Goals (EN) ---\nDepending on the elected course\n\n--- Goals (DE) ---\nAbh\u00e4ngig vom belegten Fachmodul\n\n--- Contents (EN) ---\nThis is a subject module (compulsory elective module) for which modules from the elective catalog of subject modules can be taken.\nThe semester (winter semester, summer semester) in which this subject module is taken is not specified.\n\n--- Contents (DE) ---\nDas ist ein Fachmodul (Wahlpflichtmodul), f\u00fcr das Module aus dem Wahlkatalog Fachmodule belegt werden k\u00f6nnen.\nIn welchem Semester (WiSe, SoSe) dieses Fachmodul belegt wird, ist nicht festgelegt.\n\n--- Literature (EN) ---\nDepending on the elected course\n\n--- Literature (DE) ---\nAbh\u00e4ngig vom belegten Fachmodul", "metadata": {"moduleNumber": "BMT 41", "moduleName": "Advanced module 2", "creditPoints": "5.0", "suggestedSemester": 4, "offeredInSeason": "summer_semester", "examType": "see_elective", "heldInLanguage": "de", "reviserName": "", "reviserEmail": null, "studyProgramId": 9, "source_type": "json"}}
{"id": "BMT42", "text": "Title: Compulsory Elective Module 1\nModule Number: BMT 42\nCredits: 5.0 CP\nSemester: 4\nOffered In: summer_semester\nLanguage: de\nExam Type: see_elective\nInstructor: \n\n--- Goals (EN) ---\nDepending on the elected course\n\n--- Goals (DE) ---\nAbh\u00e4ngig vom belegten Wahlmodul\n\n--- Contents (EN) ---\nThis is a subject module (compulsory elective module) for which modules from the elective catalog of subject modules can be taken. The semester (winter semester, summer semester) in which this subject module is taken is not specified.\n\n--- Contents (DE) ---\nDas ist ein Wahlmodul (Wahlpflichtmodul), f\u00fcr das Module aus den Wahlkatalogen Wahlmodule oder Fachmodule  belegt werden k\u00f6nnen. In welchem Semester (WiSe, SoSe) dieses Wahlmodul belegt wird, ist nicht festgelegt.\n\n--- Literature (EN) ---\nDepending on the elected course\n\n--- Literature (DE) ---\nAbh\u00e4ngig vom belegten Wahlmodul", "metadata": {"moduleNumber": "BMT 42", "moduleName": "Compulsory Elective Module 1", "creditPoints": "5.0", "suggestedSemester": 4, "offeredInSeason": "summer_semester", "examType": "see_elective", "heldInLanguage": "de", "reviserName": "", "reviserEmail": null, "studyProgramId": 9, "source_type": "json"}}
{"id": "BMT43", "text": "Title: Virtual Studio\nModule Number: BMT 43\nCredits: 5.0 CP\nSemester: 4\nOffered In: summer_semester\nLanguage: de\nExam Type: oral_exam\nInstructor: Prof. Dr. Eng. Univ. of Tsukuba Jens Herder\n\n--- Goals (EN) ---\nSuccessful participants will have a profound knowledge in building and developing virtual set environments for broadcasting applications and will be able to evaluate virtual studio (TV) technology. Composition of video and computer graphics under live conditions for media productions is an essential part.\n\n--- Goals (DE) ---\nStudierende k\u00f6nnen Video und Computergrafik unter Live-Bedingungen in Produktionen verbinden. Hierzu geh\u00f6rt die Erstellung fiktiver Umgebungen, in die Menschen und Gegenst\u00e4nde versetzt werden. Sie k\u00f6nnen Virtuelle Studios entwickeln, aufbauen und einsetzen.\n\n--- Contents (EN) ---\nTopics include virtual set design for artificial or real scenes, hard- and software for digital (TV) studio productions, light and light setting for TV studios, camera and actor tracking systems, motion capture, real-time computer graphics and effects, separation of image elements (e.g., chroma keying), inserting of animations and virtual characters, as well as studio production planning.\n\n--- Contents (DE) ---\nZu den Themen geh\u00f6rt die Wirkung k\u00fcnstlich erstellter Realit\u00e4tsebenen, irrealer Szenenbilder und virtueller Kulissen. Bestandteile sind Hard- und Software f\u00fcr digitale Studioproduktionstechnik, Licht und Beleuchtung im Virtuellen Studio, Kameraverfolgungssysteme (Tracking), Bewegungsaufzeichnung, Echtzeitgenerierung dreidimensionaler Computergrafik, Herausl\u00f6sen von Bildelementen (Chromakeying), Einbindung von Animationen und virtuellen Charakteren und Produktionsplanung.\n\n--- Literature (EN) ---\n- S. Gibbs. 1998. Virtual Studios. IEEE MultiMedia 5, 1 (January 1998, 17-17. DOI=10.1109/MMUL.1998.664739\n- A. R. Smith and J. F. Blinn. 1996. Blue screen matting. In Proceedings of the 23rd annual conference on Computer graphics and interactive techniques (SIGGRAPH '96). ACM, New York, NY, USA, 259-268. DOI=10.1145/237170.237263\n- R. Brinkmann: The Art and Science of Digital Compositing, Morgan Kaufman Verlag 2008\n- M. Moshkovitz: The Virtual Studio Technology & Techniques, Focal Press 2000\n- P. Tucker: Secrets of Screen Acting, Routlege Chapman & Hall 2003\n- D. Arijon: Grammar of the Film Language, Silman-James Press 1991\n- U. Schmidt: Professionelle Videotechnik: Analoge und Digitale Grundlagen, Filmtechnik, Fernsehtechnik, HDTV, Kameras, Displays, Videorecorder, Produktion und Studiotechnik, Springer Verlag 2009\n\nFurther current literature will be announced at the beginning of the course.\n\n--- Literature (DE) ---\n- S. Gibbs. 1998. Virtual Studios. IEEE MultiMedia 5, 1 (January 1998, 17-17. DOI=10.1109/MMUL.1998.664739\n- A. R. Smith and J. F. Blinn. 1996. Blue screen matting. In Proceedings of the 23rd annual conference on Computer graphics and interactive techniques (SIGGRAPH '96). ACM, New York, NY, USA, 259-268. DOI=10.1145/237170.237263\n-R. Brinkmann: The Art and Science of Digital Compositing, Morgan Kaufman Verlag 2008\n- M. Moshkovitz: The Virtual Studio Technology & Techniques, Focal Press 2000\n- P. Tucker: Secrets of Screen Acting, Routlege Chapman & Hall 2003\n- D. Arijon: Grammar of the Film Language, Silman-James Press 1991\n- U. Schmidt: Professionelle Videotechnik: Analoge und Digitale Grundlagen, Filmtechnik, Fernsehtechnik, HDTV, Kameras, Displays, Videorecorder, Produktion und Studiotechnik, Springer Verlag 2009\n\nWeitere aktuelle Literatur wird zu Beginn der LV bekannt gegeben.", "metadata": {"moduleNumber": "BMT 43", "moduleName": "Virtual Studio", "creditPoints": "5.0", "suggestedSemester": 4, "offeredInSeason": "summer_semester", "examType": "oral_exam", "heldInLanguage": "de", "reviserName": "Prof. Dr. Eng. Univ. of Tsukuba Jens Herder", "reviserEmail": "jens.herder@hs-duesseldorf.de", "studyProgramId": 9, "source_type": "json"}}
{"id": "BMT44", "text": "Title: Compulsory Elective Module 2\nModule Number: BMT 44\nCredits: 5.0 CP\nSemester: 4\nOffered In: summer_semester\nLanguage: de\nExam Type: see_elective\nInstructor: \n\n--- Goals (EN) ---\nDepending on the elected course\n\n--- Goals (DE) ---\nAbh\u00e4ngig vom belegten Wahlmodul\n\n--- Contents (EN) ---\nThis is a subject module (compulsory elective module) for which modules from the elective catalog of subject modules can be taken. The semester (winter semester, summer semester) in which this subject module is taken is not specified.\n\n--- Contents (DE) ---\nDas ist ein Wahlmodul (Wahlpflichtmodul), f\u00fcr das Module aus den Wahlkatalogen Wahlmodule oder Fachmodule belegt werden k\u00f6nnen. In welchem Semester (WiSe, SoSe) dieses Wahlmodul belegt wird, ist nicht festgelegt.\n\n--- Literature (EN) ---\nDepending on the elected course\n\n--- Literature (DE) ---\nAbh\u00e4ngig vom belegten Wahlmodul", "metadata": {"moduleNumber": "BMT 44", "moduleName": "Compulsory Elective Module 2", "creditPoints": "5.0", "suggestedSemester": 4, "offeredInSeason": "summer_semester", "examType": "see_elective", "heldInLanguage": "de", "reviserName": "", "reviserEmail": null, "studyProgramId": 9, "source_type": "json"}}
{"id": "BMT45", "text": "Title: Focus module A\nModule Number: BMT 45\nCredits: 5.0 CP\nSemester: 4\nOffered In: summer_semester\nLanguage: en_on_demand\nExam Type: project\nInstructor: Prof. Dr.-Ing. Thomas Bonse\n\n--- Goals (EN) ---\nThe central aim is to enable students to act successfully even in variable, complex, unpredictable situations. \nThis requires a comprehensive ability to act, which means, for example, that someone is able to recognize a problem in a team and solve it in a reflected \nand solve it in a reflected and criteria-led manner and within a reasonable time with the aid of method x and y.\nStudents master complex requirements independently, as is the case in problem-oriented, project-based and research-based learning. Depending on the example, concrete examples of :\n\na) Interactive media: Students master the conception, planning and implementation of an interactive media application using VR technologies and are able to evaluate these critically. The ability to communicate effectively in an interdisciplinary team is one of the skills acquired. \n\nb) AV media production: Students are able to design, plan and implement media production projects. The project provides students with in-depth social and personal key skills as well as in-depth specialist skills in various areas of media technology and prepares them specifically for professional practice.\n\nc) Rapid system prototyping: Students understand the concepts and importance of rapid system prototyping in hardware and software development. They will master the techniques for creating functional prototypes of hardware/software and information systems. The students have the ability to use various prototyping tools and methods, including prototyping software, mockups and wireframes.\n\n--- Goals (DE) ---\nZentrales Ziel ist es Studierende zu bef\u00e4higen auch in variablen, komplexen, nicht vorhersehbaren Situationen erfolgreich zu handeln. \nDaf\u00fcr ist eine umfassende Handlungskompetenz notwen\u0002dig, die zum Beispiel beinhaltet, dass jemand in der Lage ist, im Team ein Problem zu erkennen und es reflektiert \nund kriteriengeleitet und in einer angemessenen Zeit unter Zuhilfenahme von Methode x und y zu l\u00f6sen.\nStudierende meistern eigent\u00e4tig komplexe Anforderungen wie es im Problemorientierten, Projektbasierten und im Forschenden Lernen angelegt ist. Je nach Beispiel  k\u00f6nnen sein  konkret beispielhaft f\u00fcr :\n\na)Interaktive Medien: Studierende beherrschen die Konzeption, Planung und Umsetzung einer interaktiven Medienanwendung unter Verwendung von VR-Technologien und sind in der Lage diese kritisch zu bewerten. Die F\u00e4higkeit zur zielf\u00fchrenden Kommunikation in einem interdisziplin\u00e4ren Team geh\u00f6rt zu den erworbenen Kompetenzen. \n\nb)  AV-Medienproduktion: Studierende konnen Projekte zur Medienproduktion konzipieren, planen und umsetzen. Durch das Projekt erhalten die Studierenden vertieft soziale und pers\u00f6nliche Schl\u00fcsselkompetenzen sowie vertiefende Fachkompetenzen in unterschiedlichen Bereichen der Medientechnik und werden gezielt auf die berufliche Praxis vorbereitet.\n\nc) Rapid System Prototyping: Studierende habe Verst\u00e4ndnis der Konzepte und Bedeutung des Rapid System Prototyping in der Hard- und Softwareentwicklung. Sie beherrschen die Techniken zur Erstellung funktionsf\u00e4higer Prototypen von Hard-/Software- und Informationssystemen. Sie besitzen F\u00e4higkeit zur Anwendung verschiedener Prototyping-Tools und -Methoden, einschlie\u00dflich Prototyping-Software, Mockups und Wireframes.\n\n--- Contents (EN) ---\nThe content is based on current topics in media technology, where the students can either implement and test their own ideas in interdisciplinary or subject-specific maker spaces and laboratories or develop project solutions as part of projects in a team with preliminary sketches, design and implementation of prototype work in the field of media technology.\n\na) Functionality and application examples of interactive media, concepts for their implementation using VR/AR technologies in video and/or audio and other areas of modern media concepts.\n\nb) Planning, implementation and optimization of media production projects of the various formats and genres of audiovisual media production in preparation, production and post-production. Application of project management techniques and tools for the effective planning and coordination of media projects. Selection according to aesthetic principles and design techniques for audiovisual media production. Application of the most important technological instruments and tools in media production, including cameras, sound and lighting equipment and editing software.\n\nc) Rapid System Prototyping: Concepts, objectives and applications as well as a presentation of the different prototyping tools and methods: Available tools and selection of suitable methods for different use cases e.g. 3D modeling, implementation using CAM processes (3D printing, CNC milling, lasering), development of circuit diagrams and design of printed circuit boards; Creation of prototypes: Practical exercises for creating prototypes using prototyping software, mockups and wireframes; Iteration and validation: Methods for rapid iteration of prototypes based on feedback and validation of design ideas and requirements.\n\nDuring the focus modules, there is the opportunity to work intensively on just one topic for a week during the focus weeks.\n\n--- Contents (DE) ---\nDie Inhalte richten sich nach aktuellen Themen der Medientechnik die einerseits in interdisziplin\u00e4ren oder fachbezogenen Makerspaces  und Laboren eigene Ideen umsetzen und erproben k\u00f6nnen oder im Rahmen von Projekten im Team mit vorskizzieren Projekt L\u00f6sungen entwickeln, Konzeption und Umsetzung von prototypischen Arbeiten aus dem Bereich der Medientechnik.\n\na) Funktionsweise und Anwendungsbeispiele interaktiver Medien, Konzepte zu deren Implementierung mittels VR/AR-Technologien in Video und/oder Audio und anderen Bereichen moderner Medienkonzepte.\n\nb) Planung, Durchf\u00fchrung und Optimierung von Medienproduktionsprojekten der verschiedenen Formate und Genres der audiovisuellen Medienproduktion in Vorbereitung,und Produktion und Postproduktion. Anwendung von Projektmanagementtechniken und -tools f\u00fcr die effektive Planung und Koordination von Medienprojekten.  Auswahl nach \u00e4sthetische Prinzipien und Gestaltungstechniken f\u00fcr die audiovisuelle Medienproduktion.\nAnwendung der wichtigsten technologischen Instrumente und Werkzeuge in der Medienproduktion, einschlie\u00dflich Kameras, Ton- und Lichtausr\u00fcstung sowie Editing-Software.\n\nc) Rapid System Prototyping: Konzepte, Ziele und Anwendungen sowie eine Darstellung der verschiedenen Prototyping-Tools und -Methoden; Verf\u00fcgbare Tools und Auswahl geeigneter Methoden f\u00fcr verschiedene Anwendungsf\u00e4lle z.B. 3D-Modellierung, Umsetzung mittels CAM-Verfahren (3D-Druck, CNC Fr\u00e4sen, Lasern) , Entwicklung von Schaltpl\u00e4nen und Design von Leiterplatten; Erstellung von Prototypen: Praktische \u00dcbungen zur Erstellung von Prototypen unter Verwendung von Prototyping-Software, Mockups und Wireframes; Iteration und Validierung: Methoden zur schnellen Iteration von Prototypen basierend auf Feedback und Validierung von Designideen und Anforderungen. \n\nIn den Focusmodulen besteht die M\u00f6glichkeit in den Focuswochen eine Woche intensiv nur an einem Thema zu arbeiten\n\n--- Literature (EN) ---\nReinmann, G. (2014): Pr\u00fcfungen und forschendes Lernen. Preprint. http://gabi-reinmann.de/wp-cont\u0002ent/uploads/2014/12/Artikel_Pruefung\nHuber, L. (2009): Warum Forschendes Lernen n\u00f6tig und m\u00f6glich ist. In: Huber, L. / Hellmer, J. / Schneider, F. (Hrsg.): Forschendes Lernen im Studium. Aktuelle Konzepte und Erfahrungen. Bielefeld, S. 9-35\nAlexander Pusch, Nils Haverkamp: \"3D-Druck f\u00fcr Schule und Hochschule\", Springer Spektrum\nJens Lienig, Juergen Scheible: \"Fundamentals of Layout Design for Electronic Circuits\", Springer Engineering\nUlrich Tietze, Christoph Schenk, Eberhard Gamm: \"Halbleiter-Schaltungstechnik\", Springer Vieweg\n\n--- Literature (DE) ---\nReinmann, G. (2014): Pr\u00fcfungen und forschendes Lernen. Preprint. http://gabi-reinmann.de/wp-cont\u0002ent/uploads/2014/12/Artikel_Pruefung\nHuber, L. (2009): Warum Forschendes Lernen n\u00f6tig und m\u00f6glich ist. In: Huber, L. / Hellmer, J. / Schneider, F. (Hrsg.): Forschendes Lernen im Studium. Aktuelle Konzepte und Erfahrungen. Bielefeld, S. 9-35\nAlexander Pusch, Nils Haverkamp: \"3D-Druck f\u00fcr Schule und Hochschule\", Springer Spektrum\nJens Lienig, Juergen Scheible: \"Fundamentals of Layout Design for Electronic Circuits\", Springer Engineering\nUlrich Tietze, Christoph Schenk, Eberhard Gamm: \"Halbleiter-Schaltungstechnik\", Springer Vieweg", "metadata": {"moduleNumber": "BMT 45", "moduleName": "Focus module A", "creditPoints": "5.0", "suggestedSemester": 4, "offeredInSeason": "summer_semester", "examType": "project", "heldInLanguage": "en_on_demand", "reviserName": "Prof. Dr.-Ing. Thomas Bonse", "reviserEmail": "thomas.bonse@hs-duesseldorf.de", "studyProgramId": 9, "source_type": "json"}}
{"id": "BMT50", "text": "Title: Advanced module 3\nModule Number: BMT 50\nCredits: 5.0 CP\nSemester: 5\nOffered In: winter_semester\nLanguage: de\nExam Type: see_elective\nInstructor: \n\n--- Goals (EN) ---\nDepending on the elected course\n\n--- Goals (DE) ---\nAbh\u00e4ngig vom belegten Fachmodul\n\n--- Contents (EN) ---\nThis is a subject module (compulsory elective module) for which modules from the elective catalog of subject modules can be taken.\nThe semester (winter semester, summer semester) in which this subject module is taken is not specified.\n\n--- Contents (DE) ---\nDas ist ein Fachmodul (Wahlpflichtmodul), f\u00fcr das Module aus dem Wahlkatalog Fachmodule belegt werden k\u00f6nnen.\nIn welchem Semester (WiSe, SoSe) dieses Fachmodul belegt wird, ist nicht festgelegt.\n\n--- Literature (EN) ---\nDepending on the elected course\n\n--- Literature (DE) ---\nAbh\u00e4ngig vom belegten Fachmodul", "metadata": {"moduleNumber": "BMT 50", "moduleName": "Advanced module 3", "creditPoints": "5.0", "suggestedSemester": 5, "offeredInSeason": "winter_semester", "examType": "see_elective", "heldInLanguage": "de", "reviserName": "", "reviserEmail": null, "studyProgramId": 9, "source_type": "json"}}
{"id": "BMT51", "text": "Title: Compulsory Elective Module 3\nModule Number: BMT 51\nCredits: 5.0 CP\nSemester: 5\nOffered In: winter_semester\nLanguage: de\nExam Type: see_elective\nInstructor: \n\n--- Goals (EN) ---\nDepending on the elected course\n\n--- Goals (DE) ---\nAbh\u00e4ngig vom belegten Wahlmodul\n\n--- Contents (EN) ---\nThis is a subject module (compulsory elective module) for which modules from the elective catalog of subject modules can be taken. The semester (winter semester, summer semester) in which this subject module is taken is not specified.\n\n--- Contents (DE) ---\nDas ist ein Wahlmodul (Wahlpflichtmodul), f\u00fcr das Module aus den Wahlkatalogen Wahlmodule oder Fachmodule belegt werden k\u00f6nnen. In welchem Semester (WiSe, SoSe) dieses Wahlmodul belegt wird, ist nicht festgelegt.\n\n--- Literature (EN) ---\nDepending on the elected course\n\n--- Literature (DE) ---\nAbh\u00e4ngig vom belegten Wahlmodul", "metadata": {"moduleNumber": "BMT 51", "moduleName": "Compulsory Elective Module 3", "creditPoints": "5.0", "suggestedSemester": 5, "offeredInSeason": "winter_semester", "examType": "see_elective", "heldInLanguage": "de", "reviserName": "", "reviserEmail": null, "studyProgramId": 9, "source_type": "json"}}
{"id": "BMT52", "text": "Title: Compulsory Elective Module 4\nModule Number: BMT 52\nCredits: 5.0 CP\nSemester: 5\nOffered In: winter_semester\nLanguage: de\nExam Type: see_elective\nInstructor: \n\n--- Goals (EN) ---\nDepending on the elected course\n\n--- Goals (DE) ---\nAbh\u00e4ngig vom belegten Wahlmodul\n\n--- Contents (EN) ---\nThis is a subject module (compulsory elective module) for which modules from the elective catalog of subject modules can be taken. The semester (winter semester, summer semester) in which this subject module is taken is not specified.\n\n--- Contents (DE) ---\nDas ist ein Wahlmodul (Wahlpflichtmodul), f\u00fcr das Module aus den Wahlkatalogen Wahlmodule oder Fachmodule belegt werden k\u00f6nnen. In welchem Semester (WiSe, SoSe) dieses Wahlmodul belegt wird, ist nicht festgelegt.\n\n--- Literature (EN) ---\nDepending on the elected course\n\n--- Literature (DE) ---\nAbh\u00e4ngig vom belegten Wahlmodul", "metadata": {"moduleNumber": "BMT 52", "moduleName": "Compulsory Elective Module 4", "creditPoints": "5.0", "suggestedSemester": 5, "offeredInSeason": "winter_semester", "examType": "see_elective", "heldInLanguage": "de", "reviserName": "", "reviserEmail": null, "studyProgramId": 9, "source_type": "json"}}
{"id": "BMT53", "text": "Title: IT-networked AV Media Production\nModule Number: BMT 53\nCredits: 5.0 CP\nSemester: 5\nOffered In: winter_semester\nLanguage: de\nExam Type: written_exam\nInstructor: Prof. Dr.-Ing. Thomas Bonse\n\n--- Goals (EN) ---\nStudents achieve an understanding of the fundamentals of audiovisual media production in the context of IP networks.\nStudents will be able to demonstrate the integration of IP network technology into the entire production cycle.\nThey will be able to develop solutions to the challenges of audiovisual media production using IP networks.\nThey will be able to transfer their practical experience in the configuration and management of IP networks for media production to new scenarios.\n\n--- Goals (DE) ---\nStudierende erlangen Verst\u00e4ndnis f\u00fcr die Grundlagen der audiovisuellen Medienproduktion im Kontext von IP-Netzwerken.\nStudierende erhalten die F\u00e4higkeit, die Integration von IP-Netzwerktechnik in den gesamten Produktionszyklus aufzuzeigen.\nSie k\u00f6nnen L\u00f6sungen f\u00fcr die Herausforderungen der audiovisuellen Medienproduktion unter Verwendung von IP-Netzwerken entwickeln.\nSie k\u00f6nnen ihre praktische Erfahrung in der Konfiguration und Verwaltung von IP-Netzwerken f\u00fcr Medienproduktion auf neue Szenarien \u00fcbertragen.\n\n--- Contents (EN) ---\nThis module covers the integration of IP network technology into the audiovisual media production process. It focuses on the design, implementation and optimisation of networked media production systems using IT infrastructures.\n1. information technology in media production: overview of IT infrastructures for media production, data management and storage, cloud-based media production tools\n2. media storage and transmission in IP networks: storage of media content in IP networks, streaming technologies and protocols\n3. networked media production: collaborative tools and platforms for collaboration, real-time communication and remote editing and production technologies\n4. IT infrastructure for audiovisual media production: design and implementation of networked production environments, virtualisation and cloud resources for media production\n5. interactive media production with IP technology: IP networks for the development of interactive media content, application of IP technology in virtual reality (VR) and augmented reality (AR)\n\n--- Contents (DE) ---\nDieses Modul vermittelt die Integration von IP-Netzwerktechnik in den Produktionsprozess audiovisueller Medien. Es konzentriert sich auf die Konzeption, Implementierung und Optimierung von vernetzten Medienproduktionssystemen unter Verwendung von IT-Infrastrukturen.\n1. Informationstechnologie in der Medienproduktion: \u00dcberblick \u00fcber IT-Infrastrukturen f\u00fcr Medienproduktion, Datenmanagement und -speicherung, Cloud-basierte Medienproduktionswerkzeuge\n2. Medienspeicherung und -\u00fcbertragung in IP-Netzwerken: Speicherung von Medieninhalten in IP-Netzwerken, Streaming-Technologien und -Protokolle\n3. Vernetzte Medienproduktion: Kollaborative Tools und Plattformen f\u00fcr die Zusammenarbeit, Echtzeit-Kommunikation und Remote-Editing- und Produktionstechnologien\n4. IT-Infrastruktur f\u00fcr audiovisuelle Medienproduktion: Konzeption und Implementierung von vernetzten Produktionsumgebungen, Virtualisierung und Cloud-Ressourcen f\u00fcr Medienproduktion\n5. Interaktive Medienproduktion mit IP-Technologie: IP-Netzwerke f\u00fcr die Entwicklung von interaktiven Medieninhalten, Anwendung von IP-Technologie in Virtual Reality (VR) und Augmented Reality (AR)\n\n--- Literature (EN) ---\nAppropriate teaching materials will be provided in the course.\n\n--- Literature (DE) ---\nGeeignete Lehrmaterialien werden in der Lehrveranstaltung bekannt gegeben.", "metadata": {"moduleNumber": "BMT 53", "moduleName": "IT-networked AV Media Production", "creditPoints": "5.0", "suggestedSemester": 5, "offeredInSeason": "winter_semester", "examType": "written_exam", "heldInLanguage": "de", "reviserName": "Prof. Dr.-Ing. Thomas Bonse", "reviserEmail": "thomas.bonse@hs-duesseldorf.de", "studyProgramId": 9, "source_type": "json"}}
{"id": "BMT54", "text": "Title: Compulsory Elective Module 5\nModule Number: BMT 54\nCredits: 5.0 CP\nSemester: 5\nOffered In: winter_semester\nLanguage: de\nExam Type: see_elective\nInstructor: \n\n--- Goals (EN) ---\nDepending on the elected course\n\n--- Goals (DE) ---\nAbh\u00e4ngig vom belegten Wahlmodul\n\n--- Contents (EN) ---\nThis is a subject module (compulsory elective module) for which modules from the elective catalog of subject modules can be taken. The semester (winter semester, summer semester) in which this subject module is taken is not specified.\n\n--- Contents (DE) ---\nDas ist ein Wahlmodul (Wahlpflichtmodul), f\u00fcr das Module aus den Wahlkatalogen Wahlmodule oder Fachmodule belegt werden k\u00f6nnen. In welchem Semester (WiSe, SoSe) dieses Wahlmodul belegt wird, ist nicht festgelegt.\n\n--- Literature (EN) ---\nDepending on the elected course\n\n--- Literature (DE) ---\nAbh\u00e4ngig vom belegten Wahlmodul", "metadata": {"moduleNumber": "BMT 54", "moduleName": "Compulsory Elective Module 5", "creditPoints": "5.0", "suggestedSemester": 5, "offeredInSeason": "winter_semester", "examType": "see_elective", "heldInLanguage": "de", "reviserName": "", "reviserEmail": null, "studyProgramId": 9, "source_type": "json"}}
{"id": "BMT55", "text": "Title: Focus module B\nModule Number: BMT 55\nCredits: 5.0 CP\nSemester: 5\nOffered In: winter_semester\nLanguage: en_on_demand\nExam Type: project\nInstructor: Prof. Dr.-Ing. Thomas Bonse\n\n--- Goals (EN) ---\nThe central aim is to enable students to act successfully even in variable, complex, unpredictable situations. \nThis requires a comprehensive ability to act, which means, for example, that someone is able to recognize a problem in a team and solve it in a reflected \nand solve it in a reflected and criteria-led manner and within a reasonable time with the aid of method x and y.\nStudents master complex requirements independently, as is the case in problem-oriented, project-based and research-based learning. Depending on the example, concrete examples of :\n\na) Interactive media: Students master the conception, planning and implementation of an interactive media application using VR technologies and are able to evaluate these critically. The ability to communicate effectively in an interdisciplinary team is one of the skills acquired. \n\nb) AV media production: Students are able to design, plan and implement media production projects. The project provides students with in-depth social and personal key skills as well as in-depth specialist skills in various areas of media technology and prepares them specifically for professional practice.\n\nc) Rapid system prototyping: Students understand the concepts and importance of rapid system prototyping in hardware and software development. They will master the techniques for creating functional prototypes of hardware/software and information systems. The students have the ability to use various prototyping tools and methods, including prototyping software, mockups and wireframes.\n\n--- Goals (DE) ---\nZentrales Ziel ist es Studierende zu bef\u00e4higen auch in variablen, komplexen, nicht vorhersehbaren Situationen erfolgreich zu handeln. \nDaf\u00fcr ist eine umfassende Handlungskompetenz notwen\u0002dig, die zum Beispiel beinhaltet, dass jemand in der Lage ist, im Team ein Problem zu erkennen und es reflektiert \nund kriteriengeleitet und in einer angemessenen Zeit unter Zuhilfenahme von Methode x und y zu l\u00f6sen.\nStudierende meistern eigent\u00e4tig komplexe Anforderungen wie es im Problemorientierten, Projektbasierten und im Forschenden Lernen angelegt ist. Je nach Beispiel  k\u00f6nnen sein  konkret beispielhaft f\u00fcr :\n\na)Interaktive Medien: Studierende beherrschen die Konzeption, Planung und Umsetzung einer interaktiven Medienanwendung unter Verwendung von VR-Technologien und sind in der Lage diese kritisch zu bewerten. Die F\u00e4higkeit zur zielf\u00fchrenden Kommunikation in einem interdisziplin\u00e4ren Team geh\u00f6rt zu den erworbenen Kompetenzen. \n\nb)  AV-Medienproduktion: Studierende konnen Projekte zur Medienproduktion konzipieren, planen und umsetzen. Durch das Projekt erhalten die Studierenden vertieft soziale und pers\u00f6nliche Schl\u00fcsselkompetenzen sowie vertiefende Fachkompetenzen in unterschiedlichen Bereichen der Medientechnik und werden gezielt auf die berufliche Praxis vorbereitet.\n\nc) Rapid System Prototyping: Studierende habe Verst\u00e4ndnis der Konzepte und Bedeutung des Rapid System Prototyping in der Hard- und Softwareentwicklung. Sie beherrschen die Techniken zur Erstellung funktionsf\u00e4higer Prototypen von Hard-/Software- und Informationssystemen. Sie besitzen F\u00e4higkeit zur Anwendung verschiedener Prototyping-Tools und -Methoden, einschlie\u00dflich Prototyping-Software, Mockups und Wireframes.\n\n--- Contents (EN) ---\nThe content is based on current topics in media technology, where the students can either implement and test their own ideas in interdisciplinary or subject-specific maker spaces and laboratories or develop project solutions as part of projects in a team with preliminary sketches, design and implementation of prototype work in the field of media technology.\n\na) Functionality and application examples of interactive media, concepts for their implementation using VR/AR technologies in video and/or audio and other areas of modern media concepts.\n\nb) Planning, implementation and optimization of media production projects of the various formats and genres of audiovisual media production in preparation, production and post-production. Application of project management techniques and tools for the effective planning and coordination of media projects. Selection according to aesthetic principles and design techniques for audiovisual media production. Application of the most important technological instruments and tools in media production, including cameras, sound and lighting equipment and editing software.\n\nc) Rapid System Prototyping: Concepts, objectives and applications as well as a presentation of the different prototyping tools and methods: Available tools and selection of suitable methods for different use cases e.g. 3D modeling, implementation using CAM processes (3D printing, CNC milling, lasering), development of circuit diagrams and design of printed circuit boards; Creation of prototypes: Practical exercises for creating prototypes using prototyping software, mockups and wireframes; Iteration and validation: Methods for rapid iteration of prototypes based on feedback and validation of design ideas and requirements.\n\nDuring the focus modules, there is the opportunity to work intensively on just one topic for a week during the focus weeks.\n\n--- Contents (DE) ---\nDie Inhalte richten sich nach aktuellen Themen der Medientechnik die einerseits in interdisziplin\u00e4ren oder fachbezogenen Makerspaces  und Laboren eigene Ideen umsetzen und erproben k\u00f6nnen oder im Rahmen von Projekten im Team mit vorskizzieren Projekt L\u00f6sungen entwickeln, Konzeption und Umsetzung von prototypischen Arbeiten aus dem Bereich der Medientechnik.\n\na) Funktionsweise und Anwendungsbeispiele interaktiver Medien, Konzepte zu deren Implementierung mittels VR/AR-Technologien in Video und/oder Audio und anderen Bereichen moderner Medienkonzepte.\n\nb) Planung, Durchf\u00fchrung und Optimierung von Medienproduktionsprojekten der verschiedenen Formate und Genres der audiovisuellen Medienproduktion in Vorbereitung,und Produktion und Postproduktion. Anwendung von Projektmanagementtechniken und -tools f\u00fcr die effektive Planung und Koordination von Medienprojekten.  Auswahl nach \u00e4sthetische Prinzipien und Gestaltungstechniken f\u00fcr die audiovisuelle Medienproduktion.\nAnwendung der wichtigsten technologischen Instrumente und Werkzeuge in der Medienproduktion, einschlie\u00dflich Kameras, Ton- und Lichtausr\u00fcstung sowie Editing-Software.\n\nc) Rapid System Prototyping: Konzepte, Ziele und Anwendungen sowie eine Darstellung der verschiedenen Prototyping-Tools und -Methoden; Verf\u00fcgbare Tools und Auswahl geeigneter Methoden f\u00fcr verschiedene Anwendungsf\u00e4lle z.B. 3D-Modellierung, Umsetzung mittels CAM-Verfahren (3D-Druck, CNC Fr\u00e4sen, Lasern) , Entwicklung von Schaltpl\u00e4nen und Design von Leiterplatten; Erstellung von Prototypen: Praktische \u00dcbungen zur Erstellung von Prototypen unter Verwendung von Prototyping-Software, Mockups und Wireframes; Iteration und Validierung: Methoden zur schnellen Iteration von Prototypen basierend auf Feedback und Validierung von Designideen und Anforderungen. \n\nIn den Focusmodulen besteht die M\u00f6glichkeit in den Focuswochen eine Woche intensiv nur an einem Thema zu arbeiten\n\n--- Literature (EN) ---\nReinmann, G. (2014): Pr\u00fcfungen und forschendes Lernen. Preprint. http://gabi-reinmann.de/wp-cont\u0002ent/uploads/2014/12/Artikel_Pruefung\nHuber, L. (2009): Warum Forschendes Lernen n\u00f6tig und m\u00f6glich ist. In: Huber, L. / Hellmer, J. / Schneider, F. (Hrsg.): Forschendes Lernen im Studium. Aktuelle Konzepte und Erfahrungen. Bielefeld, S. 9-35\nAlexander Pusch, Nils Haverkamp: \"3D-Druck f\u00fcr Schule und Hochschule\", Springer Spektrum\nJens Lienig, Juergen Scheible: \"Fundamentals of Layout Design for Electronic Circuits\", Springer Engineering\nUlrich Tietze, Christoph Schenk, Eberhard Gamm: \"Halbleiter-Schaltungstechnik\", Springer Vieweg\n\n--- Literature (DE) ---\nReinmann, G. (2014): Pr\u00fcfungen und forschendes Lernen. Preprint. http://gabi-reinmann.de/wp-cont\u0002ent/uploads/2014/12/Artikel_Pruefung\nHuber, L. (2009): Warum Forschendes Lernen n\u00f6tig und m\u00f6glich ist. In: Huber, L. / Hellmer, J. / Schneider, F. (Hrsg.): Forschendes Lernen im Studium. Aktuelle Konzepte und Erfahrungen. Bielefeld, S. 9-35\nAlexander Pusch, Nils Haverkamp: \"3D-Druck f\u00fcr Schule und Hochschule\", Springer Spektrum\nJens Lienig, Juergen Scheible: \"Fundamentals of Layout Design for Electronic Circuits\", Springer Engineering\nUlrich Tietze, Christoph Schenk, Eberhard Gamm: \"Halbleiter-Schaltungstechnik\", Springer Vieweg", "metadata": {"moduleNumber": "BMT 55", "moduleName": "Focus module B", "creditPoints": "5.0", "suggestedSemester": 5, "offeredInSeason": "winter_semester", "examType": "project", "heldInLanguage": "en_on_demand", "reviserName": "Prof. Dr.-Ing. Thomas Bonse", "reviserEmail": "thomas.bonse@hs-duesseldorf.de", "studyProgramId": 9, "source_type": "json"}}
{"id": "BMT60", "text": "Title: External semester\nModule Number: BMT 60\nCredits: 30.0 CP\nSemester: 6\nOffered In: summer_semester\nLanguage: de\nExam Type: oral_exam\nInstructor: Prof. Dr. Eng. Univ. of Tsukuba Jens Herder\n\n--- Goals (EN) ---\nThe students acquire the skills to find their way in a previously unknown environment and to be able to work constructively there. You can choose between a practical semester, a study semester abroad and a research semester.\n(a) A practical semester is based on the later occupational field for media technicians. The students are aware of operational processes and can handle the tasks of media technology according to their level of knowledge. In particular, they are aware of the importance of teamwork in connection with complex business operations.\n(b) Studying abroad conveys the competencies in the chosen courses in the fields of media technology, media computer science and cross-sectional qualifications, supplemented by the increased demands for independence through the stay abroad as well as the learning competence in a foreign language.\n(c) A research semester imparts scientific work and the competence to develop new solutions and evaluate them. In particular, they are aware of the importance of teamwork in connection with a complex research enterprise.\n\n--- Goals (DE) ---\nDie Studierenden erwerben die F\u00e4higkeiten, sich in einer vorher unbekannten Umgebung zurecht zu finden und dort konstruktiv mitarbeiten zu k\u00f6nnen. Hierf\u00fcr stehen zur Wahl ein Praxissemester, ein Auslandsstudiensemester und ein Forschungssemester.\n(a) Ein Praxissemester orientiert sich am sp\u00e4teren Berufsfeld f\u00fcr Medientechniker. Die Studierenden kennen betriebliche Prozesse und k\u00f6nnen ihnen gestellte Aufgaben der Medientechnik gem\u00e4\u00df ihrem Kenntnisstand bearbeiten. Sie kennen insbesondere die Bedeutung von Teamarbeit im Zusammenhang mit einem komplexen Betriebsgeschehen.\n(b) Ein Auslandsstudium vermittelt die Kompetenzen in den gew\u00e4hlten Kursen aus den Bereichen Medientechnik, Medieninformatik und Querschnittsqualifikationen, erg\u00e4nzt um die erh\u00f6hten Anforderungen an Selbst\u00e4ndigkeit durch den Auslandsaufenthalt sowie die Lernkompetenz in einer Fremdsprache.\n(c) Ein Forschungssemester vermittelt wissenschaftliches Arbeiten und die Kompetenz zur Entwicklung von neuen L\u00f6sungen und Bewertung von diesen. Sie kennen insbesondere die Bedeutung von Teamarbeit im Zusammenhang mit einem komplexen Forschungsbetrieb.\n\n--- Contents (EN) ---\n(a) practical semester:\nThe students orientate themselves later in their profession for media technicians, get to know operational processes and work on tasks they have set. To do this you conclude a contract with the practice office regarding the duration, tasks and support. Regular reports to be confirmed by the practice office inform and advise the supervising professor or supervisor.\n(b) study abroad semester:\nStudents can organize and use international educational offers. In the global context, you can develop, formulate and present concepts for problems in media technology and media informatics.\n(c) Research semester:\nStudents work in a research institute on theoretical and practical problems of media technology and media computer science. They learn the scientific work and are supervised by a professor or professor.\n\n--- Contents (DE) ---\n(a) Praxissemester:\nDie Studierenden orientieren sich im sp\u00e4teren Berufsfeld f\u00fcr Medientechniker, lernen betriebliche Prozesse kennen und bearbeiten ihnen gestellte Aufgaben. Sie schlie\u00dfen dazu mit der Praxisstelle einen Vertrag \u00fcber die Zeitdauer, Aufgaben und Betreuung ab. Durch regelm\u00e4\u00dfige, von der Praxisstelle zu best\u00e4tigenden Berichten, wird der betreuende Professor oder die betreuende Professorin informiert und ber\u00e4t den Studierenden oder die Studierende.\n(b) Auslandsstudiensemester:\nStudierende k\u00f6nnen f\u00fcr sich internationale Bildungsangebote organisieren und nutzen. Im globalen Kontext k\u00f6nnen Sie f\u00fcr Problemstellungen der Medientechnik und Medieninformatik Konzepte entwickeln, formulieren und pr\u00e4sentieren.\n(c) Forschungssemester:\nStudierende arbeiten in einem Forschungsinstitut an theoretischen und praktischen Problemstellungen der Medientechnik und Medieninformatik. Sie lernen das wissenschaftliche Arbeiten und werden durch einen Professor oder Professorin betreut.\n\n--- Literature (EN) ---\nLiterature/sources vary depending on the internship location or university or institute and the tasks assigned there, and will be announced at the respective location.\n\n--- Literature (DE) ---\nLiteratur / Quellen sind je nach Praxisstelle bzw. Hochschule oder Institut und dortiger Aufgabenstellung verschieden und werden jeweils dort bekanntgegeben.", "metadata": {"moduleNumber": "BMT 60", "moduleName": "External semester", "creditPoints": "30.0", "suggestedSemester": 6, "offeredInSeason": "summer_semester", "examType": "oral_exam", "heldInLanguage": "de", "reviserName": "Prof. Dr. Eng. Univ. of Tsukuba Jens Herder", "reviserEmail": "jens.herder@hs-duesseldorf.de", "studyProgramId": 9, "source_type": "json"}}
{"id": "BMT70", "text": "Title: Individual compulsory elective module\nModule Number: BMT 70\nCredits: 5.0 CP\nSemester: 7\nOffered In: winter_semester\nLanguage: de\nExam Type: see_elective\nInstructor: \n\n--- Goals (EN) ---\nSee module description of the elekted modul\n\n--- Goals (DE) ---\nSiehe Modulbeschreibung des belegten Moduls\n\n--- Contents (EN) ---\nThe content of the individual elective subject depends on the content of the selected modules. You can choose from the following:\n\nAny external module from a degree program at a German or international university - including your own university and department - which is not offered in this degree program. \n\nAny module from the catalog of elective modules or elective modules of this degree program that has not yet been taken.\n\n--- Contents (DE) ---\nDas Inhalte des individuellen Wahlfach richten sich nach den Inhalt der gew\u00e4hlten Module . Zur Auswahl stehen dabei:\n\nEin beliebiges externes Modul eines Studiengangs einer deutschen oder internationalen Hochschule  -auch der eigenen Hochschule und  des eigene Fachbereichs - welches nicht in diesem Studiengang angeboten wird. \n\nBeliebiges Modul aus Wahlkatalog Fachmodule oder Wahlmodule dieses Studiengangs das noch nicht belegt wurde.\n\n--- Literature (EN) ---\nSee module description of the elekted modul\n\n--- Literature (DE) ---\nSiehe Modulbeschreibung des belegten Moduls", "metadata": {"moduleNumber": "BMT 70", "moduleName": "Individual compulsory elective module", "creditPoints": "5.0", "suggestedSemester": 7, "offeredInSeason": "winter_semester", "examType": "see_elective", "heldInLanguage": "de", "reviserName": "", "reviserEmail": null, "studyProgramId": 9, "source_type": "json"}}
{"id": "BMT71", "text": "Title: Scientific specialisation\nModule Number: BMT 71\nCredits: 10.0 CP\nSemester: 7\nOffered In: winter_semester\nLanguage: en_on_demand\nExam Type: see_elective\nInstructor: \n\n--- Goals (EN) ---\nStudents can carry out scientific research on the basis of databases and select appropriate results as well as manage and apply these in a written paper. They are thus proficient in dealing with scientific information sources (both in German and English), can cite them correctly and use them to determine the state of the art in research and technology as well as to analyze, plan and implement their own tasks. Students are able to see their own work in the context of the specialist environment and communicate about it in an appropriate written and oral form.\n\n--- Goals (DE) ---\nDie Studierenden k\u00f6nnen eine wissenschaftliche Recherche auf Basis von Datenbanken durchf\u00fchren und ad\u00e4quate Treffer ausw\u00e4hlen sowie diese in einer schriftlichen Ausarbeitung verwalten und anwenden. Somit beherrschen Sie den Umgang mit wissenschaftlichen Informationsquellen (sowohl deutsch- als auch englischsprachig), k\u00f6nnen diese korrekt zitieren und sie dazu nutzen, den Stand der Forschung und Technik zu ermitteln sowie eigene Aufgabenstellungen zu analysieren und zu planen und umzusetzen. Die Studierenden sind in der Lage eigene Arbeiten im Kontext des fachlichen Umfeldes zu sehen und in angemessener Form schriftlich und m\u00fcndlich dar\u00fcber zu kommunizieren.\n\n--- Contents (EN) ---\nStudents work on the following tasks under supervision for a specific topic from media technology: (scientific publications, specialist books, standards, etc.) Content analysis of the information sources Compliance with good scientific practice Citation methods and citation styles Plagiarism avoidance strategy Compilation of the results in a term paper including qualitative and formally appropriate literature lists. \n\nAlternatively, in addition to the theoretical scientific elaboration, practical work and experimental set-ups can be created, which can then be used for further investigations \nPresentation of the topic or explanation of the practical work in a presentation.\n\n--- Contents (DE) ---\nDie Studierenden bearbeiten unter Anleitung f\u00fcr ein spezielles Thema aus der Medientechnik folgende Aufgaben:(wissenschaftliche Ver\u00f6ffentlichungen, Fachb\u00fccher, Standards, etc.)Inhaltliche Analyse der Informationsquellen Einhaltung der guten wissenschaftlichen Praxis Zitierweise und Zitationsstile Plagiatsvermeidungsstrategie Zusammenstellung der Ergebnisse in einer Hausarbeit inkl. qualitative und formal entsprechende Literaturlisten. \n\nAlternativ k\u00f6nnen neben der theoretischen wissenschaftlichen Ausarbeitungen praktischen Arbeiten und Versuchsaufbauten erstellt werden, die dann f\u00fcr weitere Untersuchungen genutzt werden k\u00f6nnen \nPr\u00e4sentation des Themas oder Erl\u00e4uterung der praktischen Arbeit in einem Referat.\n\n--- Literature (EN) ---\n\n\n--- Literature (DE) ---\nDie Literatur ist abh\u00e4ngig von der Aufgabenstellung und wird zu Beginn der Lehrveranstaltung bekannt gegeben bzw. sich selbst erarbeitet.\nLiteratur zum Seminar:\n- Prexl, L. (2019). Mit digitalen Quellen arbeiten. Richtig zitieren aus Datenbanken, E-Books, YouTube & Co (utb Schl\u00fcsselkompetenzen, 3., aktual. u. \u00fcberarb. Aufl.). Stuttgart: Sch\u00f6ningh.\n- Kreutzer, Till; Rack, Stefanie; Fileccia, Marco (2018): Nicht alles, was geht, ist auch erlaubt: Downloaden, tauschen, online stellen  Urheberrecht im Alltag Zusatzmodul zu Knowhow f\u00fcr junge User. Materialien f\u00fcr den Unterricht. 5., aktual. Aufl. Ludwigshafen: klicksafe", "metadata": {"moduleNumber": "BMT 71", "moduleName": "Scientific specialisation", "creditPoints": "10.0", "suggestedSemester": 7, "offeredInSeason": "winter_semester", "examType": "see_elective", "heldInLanguage": "en_on_demand", "reviserName": "", "reviserEmail": null, "studyProgramId": 9, "source_type": "json"}}
{"id": "BMT72", "text": "Title: Bachelor's Thesis and Colloquium\nModule Number: BMT 72\nCredits: 15.0 CP\nSemester: 7\nOffered In: winter_semester\nLanguage: en_on_demand\nExam Type: bachelor_thesis_and_colloquium\nInstructor: Prof. Dr.-Ing. Thomas Bonse\n\n--- Goals (EN) ---\nCompetence for the independent solution of complex tasks from the subject area of the study program\n\n--- Goals (DE) ---\nsiehe BMT 25.01 und BMT 25.02\n\n--- Contents (EN) ---\nThe bachelor thesis should show that the candidate is capable of solving a theoretical or practical task in the subject area of the study program independently within a specified period of time and writing it down.\n\n--- Contents (DE) ---\nsiehe BMT 25.01 und BMT 25.02\n\n--- Literature (EN) ---\n\n\n--- Literature (DE) ---\nsiehe BMT 25.01 und BMT 25.02", "metadata": {"moduleNumber": "BMT 72", "moduleName": "Bachelor's Thesis and Colloquium", "creditPoints": "15.0", "suggestedSemester": 7, "offeredInSeason": "winter_semester", "examType": "bachelor_thesis_and_colloquium", "heldInLanguage": "en_on_demand", "reviserName": "Prof. Dr.-Ing. Thomas Bonse", "reviserEmail": "thomas.bonse@hs-duesseldorf.de", "studyProgramId": 9, "source_type": "json"}}
{"id": "BMT72_1", "text": "Title: Colloquium\nModule Number: BMT 72_1\nCredits: 3.0 CP\nSemester: None\nOffered In: every_semester\nLanguage: en_on_demand\nExam Type: none\nInstructor: Prof. Dr.-Ing. Thomas Bonse\n\n--- Goals (EN) ---\nThe purpose of the colloquium is to determine whether the candidate is able to present and explain the results of the Bachelor Thesis, their subject matter, their interdisciplinary contexts and their extra-curricular interests, and to assess their significance for the practice.\n\n--- Goals (DE) ---\nDas Kolloquium dient der Feststellung, ob die Kandidatin / der Kandidat bef\u00e4higt ist, die Ergebnisse der Bachelor-Abschlussarbeit, ihre fachlichen Grundlagen, ihre f\u00e4cher\u00fcbergreifenden Zusammenh\u00e4nge und ihre au\u00dferfachlichen Bez\u00fcge m\u00fcndlich darzustellen und selbstst\u00e4ndig zu begr\u00fcnden und ihre Bedeutung f\u00fcr die Praxis einzusch\u00e4tzen.\n\n--- Contents (EN) ---\nThe colloquium consists of a presentation as a summary of the completed bachelor thesis and a related expert discussion.\n\n--- Contents (DE) ---\nDas Kolloquium besteht aus einer Pr\u00e4sentation als Zusammenfassung der bestandenen Bachelorarbeit und einem dazugeh\u00f6rigen Fachgespr\u00e4ch.\n\n--- Literature (EN) ---\n\n\n--- Literature (DE) ---\nLiteratur / Quellen sind je nach Aufgabenstellung verschieden und werden durch den jeweiligen Betreuer / die jeweilige Betreuerin bekannt gegeben.", "metadata": {"moduleNumber": "BMT 72_1", "moduleName": "Colloquium", "creditPoints": "3.0", "suggestedSemester": null, "offeredInSeason": "every_semester", "examType": "none", "heldInLanguage": "en_on_demand", "reviserName": "Prof. Dr.-Ing. Thomas Bonse", "reviserEmail": "thomas.bonse@hs-duesseldorf.de", "studyProgramId": 9, "source_type": "json"}}
{"id": "BMT72_2", "text": "Title: Bachelor's Thesis\nModule Number: BMT 72_2\nCredits: 12.0 CP\nSemester: None\nOffered In: every_semester\nLanguage: en_on_demand\nExam Type: none\nInstructor: Prof. Dr. Eng. Univ. of Tsukuba Jens Herder\n\n--- Goals (EN) ---\nCompetence for the independent solution of complex tasks from the subject area of the study program\n\n--- Goals (DE) ---\nKompetenz zur selbst\u00e4ndigen Lo\u0308sung komplexer Aufgaben aus dem fachlichen Gebiet des Studiengangs\n\n--- Contents (EN) ---\nThe bachelor thesis should show that the candidate is capable of solving a theoretical or practical task in the subject area of the study program independently within a specified period of time and writing it down.\n\n--- Contents (DE) ---\nDie Bachelorarbeit soll zeigen, dass die Kandidatin / der Kandidat in der Lage ist, innerhalb einer vorgegebenen Frist eine theoretische oder praktische Aufgabe aus dem Fachgebiet des Studiengangs selbst\u00e4ndig zu lo\u0308sen und schriftlich niederzulegen.\n\n--- Literature (EN) ---\n\n\n--- Literature (DE) ---\nLiteratur / Quellen sind je nach Aufgabenstellung verschieden und werden durch den jeweiligen Betreuer / die jeweilige Betreuerin bekannt gegeben.", "metadata": {"moduleNumber": "BMT 72_2", "moduleName": "Bachelor's Thesis", "creditPoints": "12.0", "suggestedSemester": null, "offeredInSeason": "every_semester", "examType": "none", "heldInLanguage": "en_on_demand", "reviserName": "Prof. Dr. Eng. Univ. of Tsukuba Jens Herder", "reviserEmail": "jens.herder@hs-duesseldorf.de", "studyProgramId": 9, "source_type": "json"}}
{"id": "BMTF01", "text": "Title: Advanced Acoustics (Psychoacoustics)\nModule Number: BMT F01\nCredits: 5.0 CP\nSemester: 4\nOffered In: summer_semester\nLanguage: de\nExam Type: oral_exam\nInstructor: Prof. Dr.-Ing. Jochen Steffens\n\n--- Goals (EN) ---\nThe students are able to transfer the contents conveyed in the module Technical Acoustics (Acoustics 1) to the concrete application areas of psychoacoustics and to answer some of the central questions of psychoacoustics (including how our hearing works and what it processes, where its limits lie, how it can be fooled and what that means for the perception of music, language and our acoustic environment). In addition, they are able to correctly classify and explain perceptual phenomena by means of central concepts of psychoacoustics.\n\n--- Goals (DE) ---\nDie Studierenden sind in der Lage, die im Modul Technische Akustik (Akustik 1) vermittelten Inhalte auf die konkreten Anwendungsgebiete der Psychoakustik zu \u00fcbertragen und einige zentrale Fragen der Psychoakustik zu beantworten (u. a wie unser Geh\u00f6r arbeitet und was es verarbeitet, wo seine Grenzen liegen, wie es sich t\u00e4uschen l\u00e4sst und was dies f\u00fcr die Wahrnehmung von Musik, Sprache und unserer akustischen Umwelt bedeutet). Sie sind dar\u00fcber hinaus in der Lage, Wahrnehmungsph\u00e4nomene mittels zentraler Konzepte der Psychoakustik richtig einzuordnen und zu erkl\u00e4ren.\n\n--- Contents (EN) ---\n- Anatomy of the auditory system (outer, middle and inner ear, afferent and efferent auditory pathway, auditory cortex)\n- Functions of the auditory system (tonotopy, signal transmission of neurons, tuning curves, coding of frequency and intensity, otoacoustic emissions)\n- Sound analysis of the auditory system I (pitch perception and periodicity recognition, frequency groups, masking)\n- Sound analysis of the auditory system II (temporal resolution, Weber-Fechner law, loudness perception, psychoacoustic metrics)\n- Pathology of the auditory system (sound conduction and perception disorders and their diagnosis)\n- Spatial hearing (HRTF, spatial hearing with one and more sound sources) Hearing with one and several sound sources, distance perception, binaural signal processing)\n- Auditory attention (bottom-up and top-down processes, theories of selective attention, Gestalt perception, auditory scene analysis)\n- Methods of psychoacoustics I (classical psychophysical methods, adaptive forced choice (AFC) methods, methods for evaluating audio quality)\n- Methods of psychoacoustics II - listening tests (variables, hypotheses, measurement theory, empirical methods and their quality criteria, questionnaire construction)\n- Statistical evaluation methods (descriptive and inferential statistics, correlation, regression, variance analysis, general and mixed linear models)\n- Noise - causes and effects (noise effects, noise measurement, noise protection)\n- Ecological psychoacoustics & soundscapes (perception of acoustic events in everyday life, soundscape approach, effects of sounds and noise)\n\n--- Contents (DE) ---\n- Aufbau des Geh\u00f6rs (Au\u00dfen, Mittel- und Innenohr, afferente und efferente H\u00f6rbahn, auditorischer Kortex)\n- Funktionen des Geh\u00f6rs (Tonotopie, Signal\u00fcbertragung von Neuronen, Tuning Curves, Kodierung von Frequenz und Intensit\u00e4t, otoakustische Emissionen\n- Schallanalyse des Geh\u00f6rs I (Tonh\u00f6henempfindung und Periodizit\u00e4tserkennung, Frequenzgruppen, Maskierung)\n- Schallanalyse des Geh\u00f6rs II (Zeitliches Aufl\u00f6sungsverm\u00f6gen, Weber-Fechner-Gesetz, Lautheitswahrnehmung, psychoakustische Gr\u00f6\u00dfen)\n- Pathologie des Geh\u00f6rs (Schallleitungs- und empfindungsst\u00f6rungen und deren Diagnostik)\n- R\u00e4umliches H\u00f6ren (HRTF, r\u00e4uml. H\u00f6ren bei einer und mehreren Schallquellen, Entfernungsh\u00f6ren, binaurale Signalverarbeitung)\n- Auditive Aufmerksamkeit (Bottom-up und Top-down-Prozesse, Theorien der selekt. Aufmerksamkeit, Gestaltwahrnehmung, auditive Szenenanalyse)\n- Methoden der Psychoakustik I (klass. psychophysische Methoden, Adaptive Forced-Choice (AFC)-Methoden, Verfahren zur Bewertung von Audioqualit\u00e4t)\n- Methoden der Psychoakustik II - H\u00f6rversuche (Variablen, Hypothesen, Messtheorie, empirische Methoden und deren G\u00fctekriterien, Fragebogenkonstruktion)\n- Statistische Auswertungsmethoden (Deskriptive und Inferenzstatistik, Korrelation, Regression, Varianzanalyse, allgemeine und gemischte lineare Modelle)\n- L\u00e4rm - Ursachen und Wirkungen (L\u00e4rmwirkungen, L\u00e4rmmessung, L\u00e4rmschutz)\n- \u00d6kologische Psychoakustik & Soundscapes (Wahrnehmung akustischer Ereignisse im Alltag, Soundscape-Ansatz, Effekte von Ger\u00e4uschen und Musik)\n- Praktische Psychoakustik (Audio Branding und Produkt-Sound-Design)\n\n--- Literature (EN) ---\nH. Fastl, E. Zwicker: Psychoacoustics: Facts and models, Springer Science & Business Media., 2007. \nA. Gelfand: Hearing: An introduction to psychological and physiological acoustics, CRC Press, 2009.\nJ. Hellbr\u00fcck, W. Ellermeier: Horen: Physiologie, Psychologie und Pathologie, Hogrefe Verlag, 2004.\n\n--- Literature (DE) ---\nH. Fastl, E. Zwicker: Psychoacoustics: Facts and models, Springer Science & Business Media., 2007. \nA. Gelfand: Hearing: An introduction to psychological and physiological acoustics, CRC Press, 2009.\nJ. Hellbr\u00fcck, W. Ellermeier: Horen: Physiologie, Psychologie und Pathologie, Hogrefe Verlag, 2004.", "metadata": {"moduleNumber": "BMT F01", "moduleName": "Advanced Acoustics (Psychoacoustics)", "creditPoints": "5.0", "suggestedSemester": 4, "offeredInSeason": "summer_semester", "examType": "oral_exam", "heldInLanguage": "de", "reviserName": "Prof. Dr.-Ing. Jochen Steffens", "reviserEmail": "jochen.steffens@hs-duesseldorf.de", "studyProgramId": 9, "source_type": "json"}}
{"id": "BMTF02", "text": "Title: Advanced Image Engineering\nModule Number: BMT F02\nCredits: 5.0 CP\nSemester: 4\nOffered In: summer_semester\nLanguage: de\nExam Type: written_exam\nInstructor: Prof. Dr.-Ing. Thomas Bonse\n\n--- Goals (EN) ---\nStudents will be able to name the most important algorithms and concepts of video coding and apply them in practical examples. They also understand the basics of the Digital Video Broadcast Standard (DVB) and can name and apply the most important basics in the field of video streaming.\n\n--- Goals (DE) ---\nDie Studierenden k\u00f6nnen die wichtigsten Algorithmen und Konzepte der Videocodierung benennen und diese in praktischen Beispielen anwenden. Sie verstehen \u00fcberdies auch die Grundlagen des Digital Video Broadcast Standards (DVB) und k\u00f6nnen im Bereich des Videostreamings die wichtigsten Grundlagen benennen und anwenden.\n\n--- Contents (EN) ---\nThe module deepens and extends the image and video engineering from the module Image Engineering Basics (BMT 114):\n- Intra-frame video coding and predictive image coding with motion estimation\n- Hybrid DCT, MPEG video standards\n- Improved video coding\n- Digital video distribution for broadcast and streaming applications\n- Fundamentals of digital image processing\n- Digital formats for recording media and the AV archive\n\n--- Contents (DE) ---\nDas Modul vertieft und erweitert die Bild- und Videotechnik aus Modul Bildtechnik Grundlagen (BMT 114):\n- Intra-Frame Bewegtbildcodierungen und pr\u00e4diktive Bildcodierung mit Bewegungssch\u00e4tzung\n- Hybride DCT, MPEG-VideostandardsV\n- Verbesserte Bewegtbildcodierung\n- Digitale Video\u00fcbertragung f\u00fcr Broadcast- und Streaming-Anwendungen\n- Grundlagen der digitalen Bildverarbeitung\n- Digitale Formate f\u00fcr Aufzeichnungsmedien und das AV-Archiv\n\n--- Literature (EN) ---\n\n\n--- Literature (DE) ---\n-Th. Bonse, F. Kaderali: Digitale Bildcodierung - Grundlagen der digitalen Bildtechnik, Hagen, 2007\n- U. Schmidt: Professionelle Videotechnik, Springer Verlag 2021\n- W. Fischer: Digitale Fernseh- und H\u00f6rfunktechnik in Theorie und Praxis, Springer 2016\n- I. E. G. Richardson: The H.264 Advanced Compression Standard, 2nd Ed., Wiley 2010\n- U. Reimers: DVB  digitale Fernsehtechnik: Datenkompression und \u00dcbertragung, Springer 2008\n- Akramullah, S.: Digital Video Concepts, Methods, and Metrics: Quality, Compression, Performance, and Power Trade-off Analysis, ApressOpen 2014", "metadata": {"moduleNumber": "BMT F02", "moduleName": "Advanced Image Engineering", "creditPoints": "5.0", "suggestedSemester": 4, "offeredInSeason": "summer_semester", "examType": "written_exam", "heldInLanguage": "de", "reviserName": "Prof. Dr.-Ing. Thomas Bonse", "reviserEmail": "thomas.bonse@hs-duesseldorf.de", "studyProgramId": 9, "source_type": "json"}}
{"id": "BMTF03", "text": "Title: Advanced Computer Graphics\nModule Number: BMT F03\nCredits: 5.0 CP\nSemester: 4\nOffered In: summer_semester\nLanguage: de\nExam Type: written_exam\nInstructor: Prof. Dr.-Ing. Sina Mostafawy\n\n--- Goals (EN) ---\nStudents are familiar with advanced topics in computer graphics, especially in the area of realistic rendering. They will also be able to use sampling methods for rendering processes. They will be able to decide which method is best to use for customer requests. They will also learn how to produce software in a team on the basics of a Raytracer.\n\n--- Goals (DE) ---\nDie Studenrt:innen kennen weiterf\u00fchrende Themen der Computergrafik, speziell im Bereich des Renderings und realistischen 3D Darstellung. Hinzu kommen der Einsatz von Samplingmethoden f\u00fcr Renderingverfahren. Sie k\u00f6nnen beurteilen welche Methode f\u00fcr welchen Einsatz am besten einzusetzen ist. Hinzu werden sie lernen ein gro\u00dfes Softwarepacket - einen Raytraycer - gemeinsam mit anderen in der Gruppe zu programmieren.\n\n--- Contents (EN) ---\n- Theorie und Programming of Raytracing\n- Monte Carlo Principles for Rendering\n- Bezi\u00e9r interpolation, Splines and B-Splines \n- Sampling Methods and Principles for Raytracing \n- Photon Mapping Rendering\n\n--- Contents (DE) ---\n- Theorie und Programming of Raytracing\n- Monte Carlo Principles for Rendering\n- Bezi\u00e9r interpolation, Splines and B-Splines \n- Sampling Methods and Principles for Raytracing \n- Photon Mapping Rendering\n\n--- Literature (EN) ---\n- J. D. Foley, A. van Dam: Computer Graphics -Principles und Practice, Addison-Wesley, 1997\n- T. Akenine-M\u00f6ller, E. Haines: Real Time Rendering, AK Peters, 2002\n- D. Hearn, M.P. Baker: Computer Graphics with OpenGL, Verlag Pearson Education International, 2004\n\n--- Literature (DE) ---\n- J. D. Foley, A. van Dam: Computer Graphics -Principles und Practice, Addison-Wesley, 1997\n- T. Akenine-M\u00f6ller, E. Haines: Real Time Rendering, AK Peters, 2002\n- D. Hearn, M.P. Baker: Computer Graphics with OpenGL, Verlag Pearson Education International, 2004", "metadata": {"moduleNumber": "BMT F03", "moduleName": "Advanced Computer Graphics", "creditPoints": "5.0", "suggestedSemester": 4, "offeredInSeason": "summer_semester", "examType": "written_exam", "heldInLanguage": "de", "reviserName": "Prof. Dr.-Ing. Sina Mostafawy", "reviserEmail": "sina.mostafawy@hs-duesseldorf.de", "studyProgramId": 9, "source_type": "json"}}
{"id": "BMTF04", "text": "Title: Advanced Signal Processing\nModule Number: BMT F04\nCredits: 5.0 CP\nSemester: 4\nOffered In: summer_semester\nLanguage: de\nExam Type: portfolio\nInstructor: Prof. Dr.-Ing. Stefanie Dederichs\n\n--- Goals (EN) ---\n\n\n--- Goals (DE) ---\nStudierende haben Erfahrung mit der Auswahl geeigneter Signalanalytischer Verfahren und deren Auswahl f\u00fcr vorliegende Anwendungen.\n\n--- Contents (EN) ---\n\n\n--- Contents (DE) ---\nVerst\u00e4ndnis und Auswahl verschiedener Frequenz- und Zeitbereichs basierter Methoden zur Skalierung, Transformation, Analyse, Interpretation und Manipulation von Signalen. Anwendungen enthalten die Verbesserung der Qualit\u00e4t, Extraktion von n\u00fctzlicher Information und Generation neuer Signale.\n\n--- Literature (EN) ---\n\n\n--- Literature (DE) ---\n- Alan V. Oppenheim, Alan S. Willsky, Signals & Systems, Prentice Hall\n- Alan V. Oppenheim, Ronald W. Schafer: Zeitdiskrete Signalverarbeitung. R. Oldenbourg, \n- Steven W. Smith: The Scientist and Engineer's Guide to digital Signal Processing. California Technical Publishing", "metadata": {"moduleNumber": "BMT F04", "moduleName": "Advanced Signal Processing", "creditPoints": "5.0", "suggestedSemester": 4, "offeredInSeason": "summer_semester", "examType": "portfolio", "heldInLanguage": "de", "reviserName": "Prof. Dr.-Ing. Stefanie Dederichs", "reviserEmail": "stefanie.dederichs@hs-duesseldorf.de", "studyProgramId": 9, "source_type": "json"}}
{"id": "BMTF05", "text": "Title: Advanced Audio Engineering\nModule Number: BMT F05\nCredits: 5.0 CP\nSemester: 4\nOffered In: summer_semester\nLanguage: de\nExam Type: written_exam\nInstructor: Prof. Dr.-Ing. Dieter Leckschat\n\n--- Goals (EN) ---\nAfter completing the course, the students will be able to deal with sound equipment and relevant software in a professional manner and with well-founded background knowledge. From the practical exercises the students have learned ways of working with sound and music production. They can use them such that technically flawless and sonically pleasing productions arise.\n\n--- Goals (DE) ---\nDie Studierenden sind nach Abschluss der Lehrveranstaltung in der Lage, mit Ger\u00e4ten der Tontechnik und einschl\u00e4giger Software in professioneller Weise und mit einem fundierten Hintergrundwissen umzugehen. Aus den praktischen \u00dcbungen haben die Studierenden grundlegende Arbeitsweisen der Ton und Musikproduktion erlernt. Sie k\u00f6nnen diese so anwenden, dass technisch einwandfreie und klanglich ansprechende Produktionen entstehen.\n\n--- Contents (EN) ---\nA focus of this module is in digital audio technology: Professional recording, editing, storage, transmission and analysis of analog and digital audio signals and device implementationIntroduction to algorithms of digital audio signal processing and audio coding (data reduction).\n\n--- Contents (DE) ---\nDer Schwerpunkt dieses Moduls liegt in der Digitalen Audiotechnik: Professionelle Aufnahme, Bearbeitung, Speicherung, \u00dcbertragung und Analyse von analogen und digitalen Tonsignalen und die ger\u00e4tetechnische Realisierung. Einf\u00fchrung in Algorithmen der Digitalen Audiosignalverarbeitung und Datenreduktionsverfahren.\n\n--- Literature (EN) ---\n- Th. Gorne: Tontechnik, Hanser Fachbuchverlag 2011S. \n- Weinzierl (Hrgb.): Handbuch der Audiotechnik Springer Verlag 2008\n- J. - Webers: Das Handbuch der Tonstudiotechnik Franzis\u00b4 Verlag 7. Auflage 1999\n- U. - Zolzer, M. Bossert, N. Fliege: Digitale Audiosignalverarbeitung, Vieweg+Teubner Verlag 2005\n- M. Zollner, E. Zwicker: Elektroakustik, Springer Verlag 1998\n- M. - Kahrs, K.-H. Brandenburg (Ed.): Applications of Digital Signal Processing to Audio and Acoustics, Kluwer Academic Press 1998\n- A. - Spanias, T. Painter: Perceptual Coding of Digital Audio, Proc. IEEE, Vol.88 No.4, 2000 \n- Journal of the Audio Engineering Sociey (AES)\n\n--- Literature (DE) ---\n- Th. Gorne: Tontechnik, Hanser Fachbuchverlag 2011S. \n- Weinzierl (Hrgb.): Handbuch der Audiotechnik Springer Verlag 2008\n- J. - Webers: Das Handbuch der Tonstudiotechnik Franzis\u00b4 Verlag 7. Auflage 1999\n- U. - Zolzer, M. Bossert, N. Fliege: Digitale Audiosignalverarbeitung, Vieweg+Teubner Verlag 2005\n- M. Zollner, E. Zwicker: Elektroakustik, Springer Verlag 1998\n- M. - Kahrs, K.-H. Brandenburg (Ed.): Applications of Digital Signal Processing to Audio and Acoustics, Kluwer Academic Press 1998\n- A. - Spanias, T. Painter: Perceptual Coding of Digital Audio, Proc. IEEE, Vol.88 No.4, 2000 \n- Journal of the Audio Engineering Sociey (AES)", "metadata": {"moduleNumber": "BMT F05", "moduleName": "Advanced Audio Engineering", "creditPoints": "5.0", "suggestedSemester": 4, "offeredInSeason": "summer_semester", "examType": "written_exam", "heldInLanguage": "de", "reviserName": "Prof. Dr.-Ing. Dieter Leckschat", "reviserEmail": "dieter.leckschat@hs-duesseldorf.de", "studyProgramId": 9, "source_type": "json"}}
{"id": "BMTF06", "text": "Title: Musical Acoustics\nModule Number: BMT F06\nCredits: 5.0 CP\nSemester: 5\nOffered In: winter_semester\nLanguage: de\nExam Type: oral_exam\nInstructor: Prof. Dr.-Ing. Jochen Steffens\n\n--- Goals (EN) ---\nThe students are able to transfer the contents conveyed in the modules \"Technical Acoustics\" and \"Psychoacoustics\" to concrete applications of Musical Acoustics.In the field of musical instrument acoustics, they know the mode of operation of the individual instruments of different instrument groups and master their acoustic or sonic analysis. They are familiar with common analysis methods (e.g., vibration / modal analyzes, artificial lip / blower and stimulation devices) as well as the evaluation of quality features (e.g., intonation, response, style). This includes phenomena of the interaction between the musician and the instrument.They may explain the influence of instrumentation and performance parameters on perception and effect on the recipient (e.g., material or nature of mouthpiece, reed, valve and bow, as well as intonation or movement patterns of musicians). In addition, they are able to assess phenomena of musical acoustics from a perceptual-psychological or music-psychological perspective.\n\n--- Goals (DE) ---\nDie Studierenden sind in der Lage, die in den Modulen \"Technische Akustik\" und \"Psychoakustik\" vermittelten Inhalte auf konkrete Anwendungsgebiete der musikalischen Akustik zu \u00fcbertragen. Im Bereich der Musikinstrumentenakustik kennen sie die Funktionsweise der einzelnen Instrumente unterschiedlicher Instrumentengruppen und beherrschen deren akustische bzw. klangliche Analyse. Sie sind vertraut mit g\u00e4ngigen Analysemethoden (z.B. Schwingungs-/ Modalanalysen, k\u00fcnstliche Lippen / Anblas- und Anregungsvorrichtungen) sowie der Bewertung von Qualit\u00e4tsmerkmalen (z.B. Intonation, Ansprache, Spielart). Dazu geh\u00f6ren auch Ph\u00e4nomene der Interaktion zwischen Musiker und Instrument. Sie k\u00f6nnen den Einfluss von instrumentenakustischen und spieltechnischen Parametern hinsichtlich der Wahrnehmung und Wirkung auf den Rezipienten erkl\u00e4ren (z.B. Material oder Beschaffenheit von Mundst\u00fcck, Rohrblatt, Ventil und Bogen sowie Intonation oder Bewegungsmuster von Musikern).  Dar\u00fcber hinaus sind sie in der Lage, Ph\u00e4nomene der musikalischen Akustik aus einer wahrnehmungspsychologischen bzw. musikpsychologischen Perspektive zu beurteilen.\n\n--- Contents (EN) ---\n- Introduction to musical acoustics and related disciplines\n- Acoustics of musical sound sources (sound power and dynamics, transient and decay processes, excitation and spectrum, radiation)\n- Stringed instruments (types of excitation, string vibration, properties of wood, bridge admittance)\n- Brass instruments (how they work, mouthpiece, airlock model, resonance and response, natural tone formation, summation principle, valves)\n- Woodwind instruments (flutes, single and double reed instruments, edge and reed tone, resonance conditions)\n- Percussion instruments (idiophones and membranophones, modes of vibration, coupled vibration systems, modal structures, presentation of relevant instruments)\n- The acoustics of the voice (source-filter model, sound formation, formants, vocal genres, vocal registers, singing styles)\n- The acoustics of the (pipe) organ (mechanics, stops, lip and reed pipes)\n- Tone systems (interval perception, harmonic series, Pythagorean music theory, pure, meantone and equal temperament, non-Western and modern systems)\n- Interplay of musical instruments (auditory scene analysis, arrangement of timbres, dissonance and consonance)\n- Room acoustics of musical performance spaces (basics of room acoustics, historical development of concert halls, room shapes, physical and perceptual evaluation measures)\n- Sound synthesis (additive and subtractive synthesis, amplitude and frequency modulation, waveshaping, granular synthesis, physical modelling, sampling, direct synthesis)\n- Electronic instruments and musical interfaces (history, MIDI and OSC protocol, types of controllers)\n- Music Information Retrieval (areas of application, audio features, methods of pitch and chord recognition, novelty function, tempo and beat recognition, toolboxes)\n-\tMusic psychology I (music listening behaviour, functions of music listening, musical taste, musicality, personal and situational influences)\n-\tMusic Psychology II - Music and Emotion (definition and classification of emotions, perception and induction of musical emotions, emotion measurement)\n\n--- Contents (DE) ---\n- Einf\u00fchrung in die musikalische Akustik und verwandete Disziplinen\n- Akustik musikalischer Schallquellen (Schallleistung und Dynamik, Ein- und Ausschwingvorg\u00e4nge, Anregung und Spektrum, Abstrahlung)\n- Saiteninstrumente (Arten der Erregung, Saitenschwingung, Eigenschaften von Holz, Stegadmittanz)\n- Blechblasinstrumente (Funktionsweise, Mundst\u00fcck, Schleusenmodell, Resonanz und Ansprache, Naturtonbildung, Summenprinzip, Ventile)\n- Holzblasinstrumente (Fl\u00f6ten, Einfach- und Doppelrohrblattinstrumente, Kanten- und Zungenton, Resonanzbedingungen)\n- Schlaginstrumente (Idio- und Membranophone, Schwingungsformen, gekoppelte Schwingungssysteme, modale Strukturen, Vorstellung relevanter Instrumente)\n- Die Akustik der Stimme (Quelle-Filter-Modell, Klangformung, Formanten, Stimmgattungen, Stimmregister, Singstile)\n- Die Akustik der (Pfeifen-)Orgel (Mechanik, Register, Lippen- und Zungenpfeifen)\n- Tonsysteme (Intervallwahrnehmung, harmonische Reihe, pythagor\u00e4ische Musiklehre, reine, mittelt\u00f6nige und gleichstufige Stimmung, nichtwestliche und moderne Systeme)\n- Zusammenklang von Musikinstrumenten (Auditorische Szenenanalyse, Anordnung von Klangfarben, Dissonanz und Konsonanz)\n- Raumakustik musikalischer Auff\u00fchrungsr\u00e4ume (Grundlagen der Raumakustik, historische Entwicklung von Konzerts\u00e4len, Raumformen, physikalische und perzeptive Bewertungsma\u00dfe)\n- Klangsynthese (Additive und subtraktive S., Amplituden-  und Frequenzmodulation, Waveshaping, Granularsynthese, Physical Modeling, Sampling, Direkte Synthese)\n- Elektronische Instrumente und Musical Interfaces (Geschichte, MIDI- und OSC-Protokoll, Arten von Controllern)\n- Music Information Retrieval (Anwendungsgebiete, Audiodeskriptoren, Verfahren der Tonh\u00f6hen- und Akkorderkennung, Novelty-Function, Tempo- und Takterkennung, Toolboxen)\n- Musikpsychologie I (Musikh\u00f6rverhalten, Funktionen des Musikh\u00f6rens, Musikgeschmack, Musikalit\u00e4t, Einflussfaktoren von Person und Situation)\n- Musikpsychologie II - Musik und Emotion (Definition und Klassifikation von Emotionen, Wahrnehmung und Induktion musikalischer Emotionen, Emotionsmessung)\n\n--- Literature (EN) ---\nJ.W. Beauchamp: Analysis, synthesis, and perception of musical sounds: the sound of music. Springer, 2007\nN.H. Fletcher & T. D. Rossing: The Physics of Musical Instruments. Berlin: Springer, 1998\nD.E. Hall, Musikalische Akustik. Schott, 2008M.R. Jones; Music Perception. Springer, 2010\u00b7\nJ. Meyer: Akustik und musikalische Auff\u00fchrungspraxis, 6. erweiterte Auflage, Edition Bochinsky, 2015\nS. Weinzierl, Akustische Grundlagen der Musik. Laaber, 2014\n\n--- Literature (DE) ---\nJ.W. Beauchamp: Analysis, synthesis, and perception of musical sounds: the sound of music. Springer, 2007\nN.H. Fletcher & T. D. Rossing: The Physics of Musical Instruments. Berlin: Springer, 1998\nD.E. Hall, Musikalische Akustik. Schott, 2008M.R. Jones; Music Perception. Springer, 2010\u00b7\nJ. Meyer: Akustik und musikalische Auff\u00fchrungspraxis, 6. erweiterte Auflage, Edition Bochinsky, 2015\nS. Weinzierl, Akustische Grundlagen der Musik. Laaber, 2014", "metadata": {"moduleNumber": "BMT F06", "moduleName": "Musical Acoustics", "creditPoints": "5.0", "suggestedSemester": 5, "offeredInSeason": "winter_semester", "examType": "oral_exam", "heldInLanguage": "de", "reviserName": "Prof. Dr.-Ing. Jochen Steffens", "reviserEmail": "jochen.steffens@hs-duesseldorf.de", "studyProgramId": 9, "source_type": "json"}}
{"id": "BMTF07", "text": "Title: Selected Topics in Image Engineering\nModule Number: BMT F07\nCredits: 5.0 CP\nSemester: 5\nOffered In: winter_semester\nLanguage: de\nExam Type: portfolio\nInstructor: Prof. Dr.-Ing. Thomas Bonse\n\n--- Goals (EN) ---\nStudents can apply advanced technologies, algorithms and applications of image technology. Students can derive important content from professional topic research, prepare it didactically and present it in a differentiated manner in the seminar. They evaluate the central results of the seminar-based treatment of an image engineeering topic in a short scientific documentation.\n\n--- Goals (DE) ---\nDie Studierenden k\u00f6nnen fortgeschrittene Technologien, Algorithmen und Anwendungen der Bildtechnik anwenden. Die Studierenden k\u00f6nnen in einer professionellen Themenrecherche wichtige Inhalte ableiten, didaktisch aufbereiten und differenziert im Seminar pr\u00e4sentieren. Sie evaluieren die zentralen Ergebnisse der seminaristischen Behandlung eines bildtechnischen Themas in einer kurzen wissenschaftlichen Dokumentation.\n\n--- Contents (EN) ---\nThis module covers selected topics in image and video engineering. These may vary from semester to semester. Examples:\n- Algorithms and applications of digital image processing, e.g. image manipulation, filters, feature extraction (object recognition, image processing in the automotive sector, medical image processing), image processing with machine learning and KI\n- Special image recording and playback processes (multi-camera recordings for virtual camera movements and 360-degree productions)\n- Technologies and applications for VR HMDs\n- Specialised areas in video post-production Video distribution (media, broadcast, IP infrastructures, etc.)\n- Camera movement and image stabilisation (action cam and drone), camera-side stabilisation and image stabilisation in post-production\n- Studio networking, studio automation and remote production\n- Video communication/video distribution (broadcast and streaming)\n- Image presentation in the cinema, culture and event sector\n\n--- Contents (DE) ---\nIn diesem Modul werden ausgew\u00e4hlte Themengebiete der Bild- und Videotechnik behandelt. Diese k\u00f6nnen von Semester zu Semester variieren. Beispiele:\n- Algorithmen und Anwendungen der digitalen Bildverarbeitung, z.B. Bildmanipulation, Filter, Feature Extraktion (Object Recognition, BV im Automobilbereich, medizinische BV), BV mit Maschine Learning und KI\n- Besondere Bildaufnahme- und Wiedergabeverfahren (Multikameraaufnahmen f\u00fcr virtuelle Kamerabewegungen und 360-Grad Produktionen)\n- Technologien und Anwendungen f\u00fcr VR-HMDs\n- Spezialgebiete in der Video-Postproduktion Videodistribution (Medien, Broadcast, IP-Infrastrukturen etc.)\n- Kamerabewegung und Bildstabilisierung (Actioncam und Drohne), kameraseitige Stabilisierung und Bildstabilisierung in der Postproduktion\n- Studiovernetzung, Studioautomatisation und Remote Produktion\n- VideokommunikationVideodistribution (Broadcast und Streaming)\n- Bilddarstellung im Kino-, Kultur- und Eventbereich\n\n--- Literature (EN) ---\nCurrent sources will be announced at the beginning of the course according to the seminar topics.\n\n--- Literature (DE) ---\nAktuelle Quellen werden den Seminarthemen entsprechend zu Beginn der LV bekannt gegeben.", "metadata": {"moduleNumber": "BMT F07", "moduleName": "Selected Topics in Image Engineering", "creditPoints": "5.0", "suggestedSemester": 5, "offeredInSeason": "winter_semester", "examType": "portfolio", "heldInLanguage": "de", "reviserName": "Prof. Dr.-Ing. Thomas Bonse", "reviserEmail": "thomas.bonse@hs-duesseldorf.de", "studyProgramId": 9, "source_type": "json"}}
{"id": "BMTF08", "text": "Title: Selected Topics in Signal Processing\nModule Number: BMT F08\nCredits: 5.0 CP\nSemester: 5\nOffered In: winter_semester\nLanguage: de\nExam Type: portfolio\nInstructor: Prof. Dr.-Ing. Stefanie Dederichs\n\n--- Goals (EN) ---\nParticipants expand their knowledge of signal processing and recognise their systematic way of thinking. They evaluate methods according to applications. Participants also familiarise themselves with processes that are typical of teamwork and project work.\n\n--- Goals (DE) ---\nDie Teilnehmer erg\u00e4nzen ihre Kenntnisse in der Signalverarbeitung und erkennen ihre systematische Denkweise. Sie bewerten Methoden passend zu Anwendungen. Die Teilnehmer lernen au\u00dferdem Abl\u00e4ufe kennen, wie sie f\u00fcr die Teamarbeit und Projektarbeit typisch sind.\n\n--- Contents (EN) ---\nSome specialised areas of signal processing are listed below. Matlab programmes are available for sound and image processing, and students are also involved in their development. For this reason, knowledge of programming is an advantage. \nFurther contents are:\n- Implementation of the Discrete Fourier Transform (DFT) using the Fast Fourier Transform (FFT), for example in sound and image processing - Digital control technology\n- Filters for image and sound\n- Graphical representation and evaluation\n\n--- Contents (DE) ---\nIm Folgenden werden einige Spezialgebiete der Signalverarbeitung aufgef\u00fchrt. F\u00fcr die Ton -und Bildverarbeitung stehen Matlab-Programme zur Verf\u00fcgung, an deren Entwicklung Studierende auch beteiligt werden. Aus diesem Grund sind Programmier-Kenntnisse von Vorteil. \nWeitere Inhalte sind:\n- Implementierung der Diskreten Fourier-Transformation (DFT) durch die Fast Fourier Transformation (FFT), beispielsweise in der Ton- und Bildverarbeitung - Digitale Regelungstechnik\n- Filter f\u00fcr Bild und Ton\n- graphische Darstellung und Auswertung\n\n--- Literature (EN) ---\n- A. V. Oppenheim, R. W. Schafer: Digital Signal Processing, Prentice-Hall 1975 \n- K. Kammeyer, K. Kroschel: Digitale Signalverarbeitung, Teubner 2002\n- N. Fliege, M. Bossert, T. Frey: Signal  und Systemtheorie, Teubner 2008\n- B. Jahne: Digitale Bildverarbeitung, Springer 2005\n- K. D. Tonnies: Grundlagen der Bildverarbeitung, Pearson 2005\n- S. Weinzierl: Handbuch der Audiotechnik, Springer 2008M. \n- J. Tonge: The sampling of Television Images, Report 112/81, IBA 1981\n\n--- Literature (DE) ---\n- A. V. Oppenheim, R. W. Schafer: Digital Signal Processing, Prentice-Hall 1975 \n- K. Kammeyer, K. Kroschel: Digitale Signalverarbeitung, Teubner 2002\n- N. Fliege, M. Bossert, T. Frey: Signal  und Systemtheorie, Teubner 2008\n- B. Jahne: Digitale Bildverarbeitung, Springer 2005\n- K. D. Tonnies: Grundlagen der Bildverarbeitung, Pearson 2005\n- S. Weinzierl: Handbuch der Audiotechnik, Springer 2008M. \n- J. Tonge: The sampling of Television Images, Report 112/81, IBA 1981", "metadata": {"moduleNumber": "BMT F08", "moduleName": "Selected Topics in Signal Processing", "creditPoints": "5.0", "suggestedSemester": 5, "offeredInSeason": "winter_semester", "examType": "portfolio", "heldInLanguage": "de", "reviserName": "Prof. Dr.-Ing. Stefanie Dederichs", "reviserEmail": "stefanie.dederichs@hs-duesseldorf.de", "studyProgramId": 9, "source_type": "json"}}
{"id": "BMTF09", "text": "Title: Special fields of audio engineering\nModule Number: BMT F09\nCredits: 5.0 CP\nSemester: None\nOffered In: to_be_announced\nLanguage: de\nExam Type: oral_exam\nInstructor: Prof. Dr.-Ing. Dieter Leckschat\n\n--- Goals (EN) ---\nStudents master activities with selected, advanced techniques from the fields of recording studio technology, measurement technology, electroacoustics or digital audio signal processing. Skills to be acquired may include, for example, the ability to program audio algorithms. Learning objectives for other selected topics include technical understanding and the ability to analyze and synthesize sometimes complex sound engineering systems.\n\n--- Goals (DE) ---\nDie Studierenden beherrschen T\u00e4tigkeiten mit ausgew\u00e4hlten, fortgeschrittenen Techniken aus den Gebieten Tonstudiotechnik, Messtechnik, Elektroakustik oder Digitaler Audiosignalverarbeitung. Zu erwerbende Kompetenzen k\u00f6nnen beispielsweise die F\u00e4higkeit zur Programmierung von Audioalgorithmen sein. Lernziele bei weiteren Auswahlthemen umfassen das technische Verst\u00e4ndnis, die Analyse- und Synthesef\u00e4higkeit von teilweise komplexen Systemen des Sound Engineering.\n\n--- Contents (EN) ---\nFurther, selected topics from the field of recording studio technology: electroacoustics/electromechanical analogies, theory and practical aspects of sound transducers, binaural technology, electroacoustic measurement technology, sound reinforcement technology, spatial audio, digital audio signal processing, fast convolution, adaptive filters, filter banks, audio coding (data reduction), realization of digital audio effects, e.g: Room simulation, modulation effects, dynamic effects, signal processors: DSP technology.\n\n--- Contents (DE) ---\nWeiterf\u00fchrende, ausgew\u00e4hlte Themen aus dem Gebiet Tonstudiotechnik: Elektroakustik/Elektromechanische Analogien, Theorie und praktische Aspekte der Schallwandler, Binauraltechnik, Elektroakustische Messtechnik, Beschallungstechnik, Spatial Audio, Digitale Audiosignalverarbeitung, Schnelle Faltung, Adaptive Filter, Filterbanke, Audio Coding (Datenreduktion), Realisierung digitaler Audioeffekte, z.B.: Raumsimulation, Modulationseffekte, Dynamikeffekte, Signalprozessoren: DSP-Technik.\n\n--- Literature (EN) ---\n- M. Zollner, E. Zwicker: Elektroakustik, Springer Verlag 1998\n- I. Veit: Technische Akustik, Vogel Fachbuch Verlag 2005\n- S. Weinzierl (Hrsg.): Handbuch der Audiotechnik, Springer Verlag 2008\n- H. Kuttruff: Akustik  eine Einf\u00fchrung, Hirzel Verlag 2004\n- W. Ahnert, F. Steffen: Beschallungstechnik  Grundlagen und Praxis, Hirzel Verlag 1993\n- M. Gayford (Hrsg.): Microphone Engineering Handbook, Focal Press 1994\n- M. Colloms: High Performance Loudspeakers, John Wiley&Sons 1999\n- U. Zolzer: Digitale Audiosignalverarbeitung, Vieweg+Teubner Verlag 2005\n- J. Dattorro: Effect Design Part 1 - 3, AES Journal Vol. 45 Nr.9 ff\n- M. Kahrs, K.H. Brandenburg (Ed.): Applications of Digital Signal Processing to Audio and Acoustics, Kluwer Academic Press 1998\n\n--- Literature (DE) ---\n- M. Zollner, E. Zwicker: Elektroakustik, Springer Verlag 1998\n- I. Veit: Technische Akustik, Vogel Fachbuch Verlag 2005\n- S. Weinzierl (Hrsg.): Handbuch der Audiotechnik, Springer Verlag 2008\n- H. Kuttruff: Akustik  eine Einf\u00fchrung, Hirzel Verlag 2004\n- W. Ahnert, F. Steffen: Beschallungstechnik  Grundlagen und Praxis, Hirzel Verlag 1993\n- M. Gayford (Hrsg.): Microphone Engineering Handbook, Focal Press 1994\n- M. Colloms: High Performance Loudspeakers, John Wiley&Sons 1999\n- U. Zolzer: Digitale Audiosignalverarbeitung, Vieweg+Teubner Verlag 2005\n- J. Dattorro: Effect Design Part 1 - 3, AES Journal Vol. 45 Nr.9 ff\n- M. Kahrs, K.H. Brandenburg (Ed.): Applications of Digital Signal Processing to Audio and Acoustics, Kluwer Academic Press 1998", "metadata": {"moduleNumber": "BMT F09", "moduleName": "Special fields of audio engineering", "creditPoints": "5.0", "suggestedSemester": null, "offeredInSeason": "to_be_announced", "examType": "oral_exam", "heldInLanguage": "de", "reviserName": "Prof. Dr.-Ing. Dieter Leckschat", "reviserEmail": "dieter.leckschat@hs-duesseldorf.de", "studyProgramId": 9, "source_type": "json"}}
{"id": "BMTW01", "text": "Title: Computer Animation\nModule Number: BMT W01\nCredits: 5.0 CP\nSemester: None\nOffered In: to_be_announced\nLanguage: de\nExam Type: oral_exam\nInstructor: Prof. Dr.-Ing. Sina Mostafawy\n\n--- Goals (EN) ---\nThe students master general and special procedures in the field of computer animation.Theoretical and mathematical basics of 3D animation.Various methods of data acquisition and data generation for animations.Real-time rendering vs. classic rendering methods. Additionally they will learn to prepare and give a presentation about a scientific topic of computeranimation.\n\n--- Goals (DE) ---\nDie Student:innen beherrschen allgemeine und spezielle Verfahren aus dem Bereich der Computeranimation. Theoretisch-mathematische Grundlagen der 3D-Animation, verschiedene Verfahren der Datenerzeugung f\u00fcr Animationen und Echtzeitrendering. Zus\u00e4tzlich wird ein dem Kurs gelernt wie ein Vortrag recherchiert, vorbereitet und vor Publikum gehlaten wird.\n\n--- Contents (EN) ---\n- 12 Basic Principles of Animation \n- Rotation with Quaternions\n- Forward and Inverse Kinematics\n- Partikelanimation and Swarm Simulation\n- Deformation & Morphing Algorithms\n- Rigid- und Soft Bodies\n- Planing und Production of Animations\n\n--- Contents (DE) ---\n- 12 Basic Principles of Animation \n- Rotation with Quaternions\n- Forward and Inverse Kinematics\n- Partikelanimation and Swarm Simulation\n- Deformation & Morphing Algorithms\n- Rigid- und Soft Bodies\n- Planing und Production of Animations\n\n--- Literature (EN) ---\n- Computer Animation: Algorithms and Techniques, Rick Parent, 3rd 2012 \n- Advanced Animation and Renderning Techniques: Alan Watt, Mark Watt, Addision Wesley\n- Real-Time Rendering, Eric Haines, 4th 2020Computer Graphics with Open GL, Pearson Prentice Hall, 4th 2013\n\n--- Literature (DE) ---\n- Computer Animation: Algorithms and Techniques, Rick Parent, 3rd 2012 \n- Advanced Animation and Renderning Techniques: Alan Watt, Mark Watt, Addision Wesley\n- Real-Time Rendering, Eric Haines, 4th 2020Computer Graphics with Open GL, Pearson Prentice Hall, 4th 2013", "metadata": {"moduleNumber": "BMT W01", "moduleName": "Computer Animation", "creditPoints": "5.0", "suggestedSemester": null, "offeredInSeason": "to_be_announced", "examType": "oral_exam", "heldInLanguage": "de", "reviserName": "Prof. Dr.-Ing. Sina Mostafawy", "reviserEmail": "sina.mostafawy@hs-duesseldorf.de", "studyProgramId": 9, "source_type": "json"}}
{"id": "BMTW02", "text": "Title: Digital Literacy & AI Literacy\nModule Number: BMT W02\nCredits: 5.0 CP\nSemester: None\nOffered In: to_be_announced\nLanguage: de\nExam Type: portfolio\nInstructor: Prof. Dr. rer. nat. Michael Marmann\n\n--- Goals (EN) ---\nThe students\n\n- recognize the importance of digital literacy in today's information society.\n- understand the basic concepts and applications of artificial intelligence.\n- can critically evaluate digital tools and use them effectively for different purposes.\n- are able to identify and discuss the ethical and social implications of AI use.\n- develop the ability to analyze AI technologies in terms of data protection and data security.\n- can design and implement their own projects using AI elements.\n- can research and structure a current topic and present it at several levels of abstraction \n- are able to argue a topic in the seminar group \n- can prepare a current topic digitally and with interactive elements\n\n--- Goals (DE) ---\nDie Studierenden\n\n- erkennen die Bedeutung von Digital Literacy in der heutigen Informationsgesellschaft.\n- verstehen die grundlegenden Konzepte und Anwendungen k\u00fcnstlicher Intelligenz.\n- k\u00f6nnen digitale Werkzeuge kritisch bewerten und effektiv f\u00fcr verschiedene Zwecke einsetzen.\n- sind in der Lage, ethische und soziale Implikationen der KI-Nutzung zu identifizieren und zu diskutieren.\n- entwickeln die F\u00e4higkeit, KI-Technologien in Bezug auf Datenschutz und Datensicherheit zu analysieren.\n- k\u00f6nnen eigene Projekte unter Einbeziehung von AI-Elementen konzipieren und umsetzen.\n- k\u00f6nnen ein aktuelles Thema recherchieren, strukturieren und auf mehreren Abstraktionslevels pr\u00e4sentieren \n- k\u00f6nnen ein bearbeitetes Thema in der Seminargruppe argumentativ vertreten \n- k\u00f6nnen ein aktuelles Thema digital und mit interaktiven Elementen aufbereiten\n\n--- Contents (EN) ---\nThe 'Digital Literacy & AI Literacy' seminar provides students with an in-depth understanding of the digital literacies necessary to navigate effectively in the modern world. It covers the skills needed to search, evaluate and create information digitally. The focus is on critically examining the reliability and credibility of digital content.\n\nIn parallel, there is a focus on AI Literacy, which covers the understanding and application of artificial intelligence in different areas of life and work. Students will learn the basic principles of AI systems, including machine learning and data processing. They deal with the latest developments in the field of AI and reflect on their impact on society and the individual.\n\nThe seminar also examines the ethical aspects of digital and AI technologies, such as data protection, algorithmic bias and the effects of automation on the labor market. Methods are developed to deal with these challenges and students are enabled to plan and implement their own digital and AI-related projects.\n\n--- Contents (DE) ---\nDas Seminar \"Digital Literacy & AI Literacy\" bietet den Studierenden ein tiefgreifendes Verst\u00e4ndnis der digitalen Kompetenzen, die notwendig sind, um in der modernen Welt effektiv zu navigieren. Es behandelt die F\u00e4higkeiten, die ben\u00f6tigt werden, um Informationen digital zu suchen, zu bewerten und zu erstellen. Im Zentrum steht die kritische Auseinandersetzung mit der Verl\u00e4sslichkeit und Glaubw\u00fcrdigkeit von digitalen Inhalten.\n\nParallel dazu wird ein Schwerpunkt auf AI Literacy gelegt, der das Verst\u00e4ndnis und die Anwendung von k\u00fcnstlicher Intelligenz in verschiedenen Lebens- und Arbeitsbereichen umfasst. Die Studierenden lernen die Grundprinzipien von KI-Systemen kennen, einschlie\u00dflich maschinellem Lernen und Datenverarbeitung. Sie setzen sich mit den neuesten Entwicklungen im Bereich der KI auseinander und reflektieren deren Auswirkungen auf Gesellschaft und Individuum.\n\nDas Seminar beleuchtet zudem die ethischen Aspekte der digitalen und KI-Technologien, wie Datenschutz, Bias in Algorithmen (algorithmic bias) und die Auswirkungen der Automatisierung auf den Arbeitsmarkt. Es werden Methoden erarbeitet, um mit diesen Herausforderungen umzugehen und die Studierenden dazu bef\u00e4higt, eigene digitale und KI-bezogene Projekte zu planen und zu realisieren.\n\n--- Literature (EN) ---\nCurrent literature references and sources of information are provided at the beginning of the module or directly from the course context. In addition, digital media are increasingly used as a source of knowledge.\n\n--- Literature (DE) ---\nAktuelle Literaturhinweise und Informationsquellen werden zu Beginn des Moduls oder unmittelbar aus dem Veranstaltungskontext herausgegeben. Zus\u00e4tzlich werden verst\u00e4rkt digitale Medien als Wissensquelle eingesetzt.", "metadata": {"moduleNumber": "BMT W02", "moduleName": "Digital Literacy & AI Literacy", "creditPoints": "5.0", "suggestedSemester": null, "offeredInSeason": "to_be_announced", "examType": "portfolio", "heldInLanguage": "de", "reviserName": "Prof. Dr. rer. nat. Michael Marmann", "reviserEmail": "marmann@hs-duesseldorf.de", "studyProgramId": 9, "source_type": "json"}}
{"id": "BMTW03", "text": "Title: E-Business\nModule Number: BMT W03\nCredits: 5.0 CP\nSemester: None\nOffered In: to_be_announced\nLanguage: de\nExam Type: portfolio\nInstructor: Prof. Dr.-Ing. Thomas Rakow\n\n--- Goals (EN) ---\nThe students know the participants and processes of e-business and can apply their knowledge to their tasks. You can analyze, develop and present e-business tasks in a team.\n\n--- Goals (DE) ---\nDie Studierenden kennen die Beteiligten und Prozesse des E-Business und k\u00f6nnen ihre Kenntnisse in dessen Aufgabenstellungen anwenden. Sie k\u00f6nnen im Team Aufgabenstellungen des E-Business analysieren, entwickeln und pr\u00e4sentieren.\n\n--- Contents (EN) ---\nDevelopment of e-business and the Web\nData privacy and security\nProducts and services on the Web: business models, e-shops, e-marketplaces, online publications\nMarketplaces on the Web: e-marketplaces, procurement on the Web, Web services, REST/SOAP\nOnline marketing: development model for online customers, methods, key figures, cooperations, web analytics & control\nDigital supply chain: distribution, value chain, rights protection, online payment, mobile devices\nCustomer relationship: customer relationship management, customer evaluation, data management, data analysis, customer communication\n\n--- Contents (DE) ---\nEntwicklung des E-Business und des Web \nDatenschutz und -sicherheit\nProdukte und Dienstleistungen im Web: Gesch\u00e4ftsmodelle, E-Shops, E-Marktpl\u00e4tze, Online-Publikationen\nMarktpl\u00e4tze im Web: E-Marktpl\u00e4tze, Beschaffung im Web, Web-Services, REST/ SOAP \nOnline-Marketing: Entwicklungsmodell f\u00fcr Online-Kunden, Methoden, Kennzahlen, Kooperationen, Web Analytics & Control\nDigitale Lieferkette: Distribution, Wertekette, Rechteschutz, Online-Bezahlung, mobile Ger\u00e4te\nKundenbeziehung: Customer-Relationship-Management, Kundenbewertung, Datenverwaltung, Datenanalyse, Kundenkommunikation\n\n--- Literature (EN) ---\n\n\n--- Literature (DE) ---\nKollmann, Tobias: E-Business - Grundlagen elektronischer Gesch\u00e4ftsprozesse in der Net Economy, 6. Auflage, Gabler, Wiesbaden 2016.\nMeier, Andreas, Stormer, Henrik: eBusiness & eCommerce - Management der digitalen Wertsch\u00f6pfungskette, 3. Aufl., Springer, 2012.\nWirtz, Bernd: Electronic Business - Wertsch\u00f6pfung im Online-Gesch\u00e4ft, 5. Auflage, Gabler, Wiesbaden, 2016", "metadata": {"moduleNumber": "BMT W03", "moduleName": "E-Business", "creditPoints": "5.0", "suggestedSemester": null, "offeredInSeason": "to_be_announced", "examType": "portfolio", "heldInLanguage": "de", "reviserName": "Prof. Dr.-Ing. Thomas Rakow", "reviserEmail": "thomas.rakow@hs-duesseldorf.de", "studyProgramId": 9, "source_type": "json"}}
{"id": "BMTW04", "text": "Title: Introduction to 3D Modeling\nModule Number: BMT W04\nCredits: 5.0 CP\nSemester: None\nOffered In: to_be_announced\nLanguage: de\nExam Type: oral_exam\nInstructor: Prof. Dr.-Ing. Sina Mostafawy\n\n--- Goals (EN) ---\nThe participants will be able to construct complex objects in a 3D program after the course. They are still able to texture and illuminate them in order to represent them realistically. You are able to transfer from a given storyboard graphically implemented scenes in 3D and animate it there. You have a basic knowledge of different rendering methods and techniques. They have basic knowledge of what parts have to be rendered and what areas need to be created in post-production. Also, they can decide if a scene should be filmed in real or digitally generated.\n\n--- Goals (DE) ---\nDie Teilnehmer sind nach dem Kurs in der Lage komplexe Objekte in einem 3D Programm zu konstruieren. Sie sind weiterhin in der Lage diese zu texturieren und zu beleuchten, um sie realistisch abbilden zu k\u00f6nnen. Sie sind in der Lage aus einem vorgegebenen Storyboard zeichnerisch umgesetzte Sezen in 3D zu \u00fcbertragen und diese dort nachzubilden. Sie haben ein grunds\u00e4tzliches Wissen u\u0308ber verschieden Renderingmethoden und -techniken. Sie verf\u00fcgen u\u0308ber grunds\u00e4tzliches Wissen welche Bereiche gerendert und welche Bereiche in der Postproduktion entstehen mu\u0308ssen. Auch k\u00f6nnen sie entscheiden, ob eine Szene real gefilmt, oder beser digital erzeugt werden sollte.\n\n--- Contents (EN) ---\nIntroduction to 3D modeling\nIntroduction to 3D design with curves and freeform surfaces\nTexturing and mapping\n3D illumination and lighting\nCreation of simple path animations, rendering of individual images and animations.\nBasics of post-production with 3D and 2D elements.es\n\n--- Contents (DE) ---\nEinf\u00fchrung in 3D-Modellierung\nEinf\u00fchrung in 3D-Konstruktion mit Kurven und Freiformfl\u00e4che\nTexturierung und Mapping\n3D Illumination und Beleuchtung\nErstellung einfacher Pfadanimationen, Rendering von Einzelbildern und Animationen.\nGrundlagen der Postproduktion mit 3D und 2D Elementen.\n\n--- Literature (EN) ---\n\n\n--- Literature (DE) ---\nWird in der Vorlesung bekannt gegeben", "metadata": {"moduleNumber": "BMT W04", "moduleName": "Introduction to 3D Modeling", "creditPoints": "5.0", "suggestedSemester": null, "offeredInSeason": "to_be_announced", "examType": "oral_exam", "heldInLanguage": "de", "reviserName": "Prof. Dr.-Ing. Sina Mostafawy", "reviserEmail": "sina.mostafawy@hs-duesseldorf.de", "studyProgramId": 9, "source_type": "json"}}
{"id": "BMTW05", "text": "Title: Fundamentals of stochastics\nModule Number: BMT W05\nCredits: 5.0 CP\nSemester: None\nOffered In: to_be_announced\nLanguage: de\nExam Type: portfolio\nInstructor: None J\u00f6rg Becker-Schweitzer\n\n--- Goals (EN) ---\nStudents acquire a basic understanding of the relationships and methods in probability theory and statistics, with a particular focus on their application in engineering and the natural sciences. They are able to use stochastic methods for further scientific work and have the necessary skills to work out relationships in specialist texts/publications on data analysis and statistical modeling.\n\n--- Goals (DE) ---\nDie Studierenden erwerben ein grundlegendes Verst\u00e4ndnis der Zusammenh\u00e4nge und Methoden in Wahrscheinlichkeitstheorie und Statistik, mit besonderem Blick auf deren Anwendung in den Ingenieur- und Naturwissenschaften. Sie k\u00f6nnen stochastische Methoden f\u00fcr weiterf\u00fchrende wissenschaftliche Arbeiten nutzen und besitzen die notwendigen Kompetenzen, um sich Zusammenh\u00e4nge in Fachtexten/Ver\u00f6ffentlichungen zur Datenanalyse und statistischen Modellierung zu erarbeiten.\n\n--- Contents (EN) ---\n- Probability spaces and random variables\n- Probability distributions\n- Conditional probabilities and independence\n- Descriptive statistics\n- Estimation theory\n- Law of large numbers and central limit theorem\n- Confidence intervals and distributions\n- Regression and variance analysis\n- Hypothesis tests\n\n--- Contents (DE) ---\n- Wahrscheinlichkeitsr\u00e4ume und Zufallsvariablen\n- Wahrscheinlichkeitsverteilungen\n- Bedingte Wahrscheinlichkeiten und Unabh\u00e4ngigkeit\n- Deskriptive Statistik\n- Sch\u00e4tztheorie\n- Gesetz der gro\u00dfen Zahlen und zentraler Grenzwertsatz\n- Konfidenzintervalle und Verteilungen\n- Regressions- und Varianzanalyse\n- Hypothesen Tests\n\n--- Literature (EN) ---\n\n\n--- Literature (DE) ---\nL. Fahrmeir, C. Heumann, R. K\u00fcnstler, I. Pigeot, G. Tutz: Statistik - Der Weg zur Datenanalyse, Springer, 2016.\nL. Papula: Mathematik f\u00fcr Ingenieure und Naturwissenschaftler 3, Vieweg, 2009.\nE. Behrends: Elementare Stochastik, Vieweg, 2012.", "metadata": {"moduleNumber": "BMT W05", "moduleName": "Fundamentals of stochastics", "creditPoints": "5.0", "suggestedSemester": null, "offeredInSeason": "to_be_announced", "examType": "portfolio", "heldInLanguage": "de", "reviserName": "None J\u00f6rg Becker-Schweitzer", "reviserEmail": "jbs@hs-duesseldorf.de", "studyProgramId": 9, "source_type": "json"}}
{"id": "BMTW06", "text": "Title: Immersive Visualisation\nModule Number: BMT W06\nCredits: 5.0 CP\nSemester: None\nOffered In: to_be_announced\nLanguage: de\nExam Type: portfolio\nInstructor: Prof. Dr. rer. nat. Christian Geiger\n\n--- Goals (EN) ---\nStudents will be familiar with the key concepts of visualization and typical design procedures. They also know typical examples of successful visualization projects and can explain and evaluate them. They are able to recognize typical problems in the design and development of immersive visualizations and to develop expressive and effective visual representation concepts based on established procedures for multivariate data and to implement and evaluate them using suitable immersive technologies (visualization systems, 3D game engines, frameworks).\n\n--- Goals (DE) ---\nDie Studierenden kennen die wesentlichen Begriffe der Visualisierung und typische Vorgehensweise beim Entwurf. Sie kennen dar\u00fcber hinaus typische Beispiele erfolgreicher Visualisierungsprojekte und k\u00f6nnen diese erl\u00e4utern und bewerten. Sie sind in der Lage typische Probleme der bei der Gestaltung und Entwicklung immersiver Visualisierungen zu erkennen und auf Basis etablierter Vorgehensweisen  f\u00fcr multivariate Daten expressive und effektive visuelle Darstellungskonzepte zu entwickeln, mittels geeigneter immersiver Technologien (Visualisierungssysteme, 3D gameEngines, Frameworks) zu realisieren und zu bewerten.\n\n--- Contents (EN) ---\nThe course Immersive Visualization deals with computer-aided methods for the graphical representation of information and data, which are given an immersive character through design and technology. This can be achieved through extensive interaction, XR technologies, projections or large-scale displays. This special visual representation is intended to help evaluate, present and inform data or gain new insights from it. The main contents are \n- Aspects of human visual perception and visualization models:\n- Visualization of multivariate data\n- Workflow and procedure models in the visualization process (visualization pipeline)\n- multimodal interaction concepts, design principles and storytelling \n- Overview of typical visualization systems for real-time applications \nThe course will choose a specific topic in each semester offered, which will then be worked on with the participants. External lectures and excursions round off the program.\n\n--- Contents (DE) ---\nDie Veranstaltung Immersive Visualisierung befasst sich mit computerunterst\u00fctzten Methoden zur grafischen Repr\u00e4sentation von Informationen und Daten, die durch Gestaltung und Technologie einen immersiven Charakter erhalten. Das kann durch umfangreiche Interaktion, XR -Technologien, Projektionen oder gro\u00dffl\u00e4chige Displays erfolgen. Diese besondere bildliche Darstellung soll dabei helfen, Daten auszuwerten, zu pr\u00e4sentieren und informieren bzw. neue Erkenntnisse daraus zu gewinnen. Wesentliche Inhalte sind \n- Aspekte der menschlichen visuellen Wahrnehmung und Modell der Visualisierung:\n- Visualisierung multivariater Daten\n- Workflow und Vorgehensmodelle im Visualisierungsprozess (Visualisierungspipeline)\n- multimodale Interaktionskonzepte, Gestaltungsgrundlagen und Storytelling \n- \u00dcberblick typischer Visualisierungssysteme f\u00fcr Echtzeitanwendungen \nDie Veranstaltung wird sich in jedem angebotenen Semester ein spezielles Thema w\u00e4hlen, das mit den Teilnehmer:innen dann bearbeitet wird. Externe Vortr\u00e4ge und Exkursionen runden das Angebot ab.\n\n--- Literature (EN) ---\n\n\n--- Literature (DE) ---\n- Chaomei Chen: Information Visualization. Beyond the Horizon. 2. Auflage, Springer London, (2004)\n- Colin Ware: Information Visualization : Perception for Design Morgan Kaufmann Series in Interactive Technologies, San Francisco, (2000)\n- Natha Yau: Visualize This: The Flowing Data Guide to Design, Visualization and Statistics, Wiley, (2011)\n- Cole Nussbaumer Knaflic: Storytelling with Data: A Data Visualization Guide for Business Professionals, Wiley, (2015)", "metadata": {"moduleNumber": "BMT W06", "moduleName": "Immersive Visualisation", "creditPoints": "5.0", "suggestedSemester": null, "offeredInSeason": "to_be_announced", "examType": "portfolio", "heldInLanguage": "de", "reviserName": "Prof. Dr. rer. nat. Christian Geiger", "reviserEmail": "geiger@hs-duesseldorf.de", "studyProgramId": 9, "source_type": "json"}}
{"id": "BMTW07", "text": "Title: Learning agency\nModule Number: BMT W07\nCredits: 5.0 CP\nSemester: None\nOffered In: to_be_announced\nLanguage: de\nExam Type: portfolio\nInstructor: Prof. Dr. rer. nat. Michael Marmann\n\n--- Goals (EN) ---\nThe students \n\n- know the typical work processes of a digital agency and apply them under largely real conditions \n- take on a role within the project that corresponds to their competencies and a typical job profile in an agency \n- learn to organize themselves, act independently and participate in team development processes \n- know the tools required for the different project phases and can apply them in a phase-specific manner\n- are familiar with agile process models and supporting tools and apply these in the context of teamwork \n- design and develop a digital media product or a digitally supported service in a team on the basis of a specific project assignment \n- can present the results of individual project phases and the overall result to internal or external clients\n\n--- Goals (DE) ---\nDie Studierenden \n\n- kennen die typischen Arbeitsprozesse einer Digitalagentur und wenden diese unter weitgehend realen Bedingungen an \n- nehmen innerhalb des Projektes eine ihren Kompetenzen entsprechende Rolle ein, die einem typischen T\u00e4tigkeitsprofil in einer Agentur entspricht \n- lernen, sich selbst zu organisieren, eigenverantwortlich zu handeln und an Teamentwicklungsprozessen teilzunehmen \n- kennen die f\u00fcr die unterschiedlichen Projektphasen notwendigen Werkzeuge und k\u00f6nnen diese phasenspezifisch anwenden\n- kennen agile Vorgehensmodelle sowie unterst\u00fctzende Tools und wenden diese im Rahmen der Teamarbeit an \n- konzipieren und entwickeln im Team auf der Basis eines konkreten Projektauftrages ein digitales Medienprodukt oder eine digital gest\u00fctzte Dienstleistung \n- k\u00f6nnen Ergebnisse einzelner Projektphasen und das Gesamtergebnis vor internen oder externen Auftraggebern pr\u00e4sentieren\n\n--- Contents (EN) ---\nThe learning agency module is a special type of project that is highly relevant for later professional life. The special feature is that students work in a team on concrete and practical customer solutions, just like in a real digital agency, from the initial idea through to implementation. \n\nThe client can be internal or external. To this end, students take on specific roles that correspond to real job profiles in agencies. For example, there will be sales-oriented students as well as project managers, concept developers, developers or designers. If several teams are formed, they will be in competition with each other. The solution to be developed will go through all phases of digital product development or an online communication project. Special emphasis is placed on agile project management methods.\n\n--- Contents (DE) ---\nBeim Modul Lernagentur handelt es sich um eine spezielle Projektform mit hoher Relevanz f\u00fcr das sp\u00e4tere Berufsleben. Die Besonderheit besteht darin, dass Studierende wie in einer realen Digitalagentur im Team an konkreten und praxisnahen Kundenl\u00f6sungen arbeiten, und zwar von der ersten Idee bis zur Umsetzung. \n\nDabei kann der Auftraggeber intern oder extern sein. Hierzu nehmen die Studierenden bestimmte Rollen ein, die realen T\u00e4tigkeitsprofilen in Agenturen entsprechen. So wird es vertrieblich orientierte Studierende genauso geben, wie z.B. Projektmanager, Konzepter, Entwickler oder Designer. Sollten sich mehrere Teams formieren, dann stehen sie im Wettbewerb zueinander. Die zu erarbeitende L\u00f6sung durchl\u00e4uft alle Phasen einer digitalen Produktentwicklung oder eines Online-Kommunikations-Projektes. Dabei wird besonderer Wert auf agile Projektmanagementmethoden gelegt.\n\n--- Literature (EN) ---\nCurrent literature references and sources of information are provided at the beginning of the module or directly from the course context, if necessary. In addition, digital media are increasingly used as a source of knowledge.\n\n--- Literature (DE) ---\nAktuelle Literaturhinweise und Informationsquellen werden, so-fern notwendig, zu Beginn des Moduls oder unmittelbar aus dem Veranstaltungskontext herausgegeben. Zus\u00e4tzlich werden verst\u00e4rkt digitale Medien als Wissensquelle eingesetzt.", "metadata": {"moduleNumber": "BMT W07", "moduleName": "Learning agency", "creditPoints": "5.0", "suggestedSemester": null, "offeredInSeason": "to_be_announced", "examType": "portfolio", "heldInLanguage": "de", "reviserName": "Prof. Dr. rer. nat. Michael Marmann", "reviserEmail": "marmann@hs-duesseldorf.de", "studyProgramId": 9, "source_type": "json"}}
{"id": "BMTW08", "text": "Title: Lighting Engineering\nModule Number: BMT W08\nCredits: 5.0 CP\nSemester: None\nOffered In: to_be_announced\nLanguage: de\nExam Type: project\nInstructor: None J\u00f6rg Becker-Schweitzer\n\n--- Goals (EN) ---\nThe students have basic knowledge of the quality criteria and the most important physical parameters needed in lighting technology. On this basis, they are able to provide advice, design and planning with light and color as well as its effect on materials.They have knowledge of the devices of lighting technology and their use in event technology. They are able to dimension lighting systems, to position them and to estimate their effects on the interior.\n\n--- Goals (DE) ---\nDie Studierenden besitzen Grundkenntnisse \u00fcber die Qualit\u00e4tskriterien und die wichtigsten physikalischen Gr\u00f6\u00dfen, die in der Lichttechnik ben\u00f6tigt werden. Auf dieser Basis sind sie in der Lage, Beratung, Gestaltung und Planung mit Licht und Farbe sowie dessen Wirkung auf Materialien durchzuf\u00fchren. Sie besitzen Kenntnisse \u00fcber die Ger\u00e4te der Lichttechnik und deren Einsatz in der Veranstaltungstechnik. Sie sind in der Lage, Beleuchtungsanlagen zu dimensionieren, zu positionieren und deren Wirkungen auf den Innenraum abzusch\u00e4tzen.\n\n--- Contents (EN) ---\nFundamentals of light: biological effects, visual perception, spectraFundamentals of lighting technology: Basic parameters such as luminance, daylight quotient, illuminance, glare, light colorFundamentals of light physics: Types of light generation, emergency lighting, measuring instruments of lighting technologyLighting control and dimming technologyLighting arrangements, lighting design, lighting effectsColor events as artistic impulsesCreate simple lighting plans\n\n--- Contents (DE) ---\nGrundlagen Licht: biologische Wirkungen, optische Wahrnehmung, Spektren\nGrundlagen Lichttechnik: Grundgr\u00f6\u00dfen wie Leuchtdichte, Tageslichtquotient, Beleuchtungsst\u00e4rke, Blendung, Lichtfarbe\nGrundlagen Lichtphysik: Arten der Lichterzeugung, Sicherheitsbeleuchtung, Messger\u00e4te der Lichttechnik\nLichtsteuerung und Dimmertechnik\nLichtarrangements, Lichtplanung, Lichteffekte\nFarbereignisse als k\u00fcnstlerische Impulse\nErstellen einfacher Lichtplanungen\n\n--- Literature (EN) ---\n\n\n--- Literature (DE) ---\n- H. R. Ris: Beleuchtungstechnik f\u00fcr Praktiker, VDE Verlag 2008DIN EN 12464-1, z.B. in Leitfaden zur DIN EN 12464-1-Beleuchtung von Arbeitsstatten, Beuth Verlag 2006\n- C. Geissmar-Brandi: Lichtbuch. Die Praxis der Lichtplanung, Birkh\u00e4user Verlag 2001\n- H. J. Hentschel: Licht und Beleuchtung, H\u00fcthig Verlag 2001\n- N. Ackermann: Lichttechnik, Oldenbourg Wissenschaftsverlag 2006\n- J. M\u00fcller: Handbuch der Lichttechnik: Das Kompendium f\u00fcr den Praktiker. Know-How f\u00fcr Film. Fernsehen, Theater, Veranstaltungen und Events, PPV Medien Verlag 2008\n- M. Keller: Faszination Licht: Licht auf der B\u00fchne, Prestel Verlag 2010 \nWeitere aktuelle Literatur wird zu Beginn der LV bekannt gegeben.", "metadata": {"moduleNumber": "BMT W08", "moduleName": "Lighting Engineering", "creditPoints": "5.0", "suggestedSemester": null, "offeredInSeason": "to_be_announced", "examType": "project", "heldInLanguage": "de", "reviserName": "None J\u00f6rg Becker-Schweitzer", "reviserEmail": "jbs@hs-duesseldorf.de", "studyProgramId": 9, "source_type": "json"}}
{"id": "BMTW09", "text": "Title: Mathematics 3\nModule Number: BMT W09\nCredits: 5.0 CP\nSemester: None\nOffered In: to_be_announced\nLanguage: de\nExam Type: portfolio\nInstructor: None J\u00f6rg Becker-Schweitzer\n\n--- Goals (EN) ---\nThe students acquire a deeper understanding of mathematical relationships and methods, with a particular focus on their application in the engineering and natural sciences. They can use mathematical methods for advanced scientific work and have the necessary skills to work on mathematical relationships in advanced technical texts / publications on media technology.\n\n--- Goals (DE) ---\nDie Studierenden erwerben ein vertieftes Verst\u00e4ndnis mathematischer Zusammenh\u00e4nge und Methoden, mit besonderem Blick auf deren Anwendung in den Ingenieur- und Naturwissenschaften. Sie k\u00f6nnen mathematische Methoden f\u00fcr weiterf\u00fchrende wissenschaftliche Arbeiten nutzen und besitzen die notwendigen Kompetenzen, um sich mathematische Zusammenh\u00e4nge in fortgeschrittenen Fachtexten/Ver\u00f6ffentlichungen zur Medientechnik zu erarbeiten.\n\n--- Contents (EN) ---\n- Differential calculus in R^n (domain integral and volume integrals)\n- Vector Analysis\n- Partial differential equations\n- Numerical Methods in Mathematics\n\n--- Contents (DE) ---\n- Differentialrechnung im R^n (Gebietsintegrale und Volumenintegrale)\n- Vektoranalysis\n- Partielle Differentialgleichungen\n- Numerische Methoden in Mathematik\n\n--- Literature (EN) ---\n\n\n--- Literature (DE) ---\nL. Papula: Mathematik f\u00fcr Ingenieure und Naturwissenschaftler 3, Vieweg, 2009.O. Forster: Analysis 2, Vieweg, 2002.J. Stoer: Numerische Mathematik 1, Springer, 2004.J. Stoer, R. Bulirsch: Numerische Mathematik 2, Springer, 2000. A. Hoffmann, B. Max, W. Vogt: Mathematik f\u00fcr Ingenieure 1/2", "metadata": {"moduleNumber": "BMT W09", "moduleName": "Mathematics 3", "creditPoints": "5.0", "suggestedSemester": null, "offeredInSeason": "to_be_announced", "examType": "portfolio", "heldInLanguage": "de", "reviserName": "None J\u00f6rg Becker-Schweitzer", "reviserEmail": "jbs@hs-duesseldorf.de", "studyProgramId": 9, "source_type": "json"}}
{"id": "BMTW10", "text": "Title: Human-Computer Interaction\nModule Number: BMT W10\nCredits: 5.0 CP\nSemester: None\nOffered In: to_be_announced\nLanguage: de\nExam Type: written_exam\nInstructor: Prof. Dr.-Ing. M.Sc. Markus Dahm\n\n--- Goals (EN) ---\nStudents can explain basic models and guidelines of HCI and their applicability. They can base technical and programatical properties on human physiology and psychology and can design interactive systems accordingly. Given tasks can be analysed, human computer actions can be appropriately designed for optimal usability comforming to HCI norms and models. Students can describe a user centered process for designing and implelmentation of interaktive applications. They can evaluate and optimize the usability of given interactive system, i.e. they can explain and assess their properties as well as give well founded advice for improvement.\n\n--- Goals (DE) ---\nStudierende k\u00f6nnen grundlegende Modelle und Richtlinien der MCI erkl\u00e4ren und ihre Anwendbarkeit einordnen. Sie k\u00f6nnen technische und programmatische Eigenschaften von interaktiven Systemen auf physiologische und psychologische Merkmale des Menschen zur\u00fcckf\u00fchren und daraufhin optimieren. GegebeneAufgabenstellungen k\u00f6nnen analysiert, Mensch-ComputerInteraktionen entworfen und ihre Gestaltung anhand von MCINormen und Modellen begr\u00fcndet werden. Studierende k\u00f6nnen einenEntwicklungsprozess beschreiben, mit dem nutzerzentriert MCI-en entworfen werden. Sie k\u00f6nnen Interaktive Systeme bez\u00fcglich ihrer Usability anhand geeigneter Normen, Modelle und Richtlinien evaluieren und optimieren, d.h. sie k\u00f6nnen ihre Eigenschaften erkl\u00e4ren und bewerten sowie fundierte Verbesserungsvorschl\u00e4ge machen.\n\n--- Contents (EN) ---\n- Basics, methods, models and concepts of the design of user interfaces for interactive applications\n- Physiological and psychological basics of human perception, memory, knowledge, experience plus action control; their application in HCI\n- Consequences of the design of hardware and software for the user\n- Models of communication and their application in HCI\n- Design of interactive systems, especially webbased and mobile systems: dialog, information architecture, navigation, orientation, interaction methods\n- Integration of usability engineering in software engineering, user centered design\n- Norms, legal requirements and guidelines\n- Basic concepts of UI programming\n\n--- Contents (DE) ---\n- Grundlagen, Methoden, Modelle und Konzepte zur Gestaltung von Benutzungsschnittstellen f\u00fcr interaktive Anwendungen.\n- Physiologische und Psychologische Grundlagen der Wahrnehmung, von Ged\u00e4chtnis, Wissen, Erfahrung sowie der Handlungsregulation sowie Ihre Anwendung in der MCI\n- Konsequenzen der Gestaltung von Hardware und Software f\u00fcr Nutzer.\n- Modelle der Kommunikation und Anwendung auf die MCI\n- Gestaltung von interaktiven Systemen, insbesondere webbasierte Systeme: Dialoggestaltung, Informationsdarstellung, Navigation, Orientierung, Interaktionsformen\n- Integration von Software-Ergonomie in Software Engineering\n- Normen, gesetzliche Grundlagen und Richtlinien\n- Grundlagen der Programmierung von GUIs\n\n--- Literature (EN) ---\n- Markus Dahm: Grundlagen der Mensch-Computer-Interaktion, Pearson (2006)\n- Jens Jacobsen: Praxisbuch Usability und UX, Rheinwerk (2017)\n- Steve Krug: Don't make me think - revisited, New Riders (2013)\n- Bernhard Preim, Raimund Dachselt: Interaktive Systeme Band 1 und 2, eXamen.press\n- Don Norman: The Design of Everyday Things, Basic Books (2013)\n- Michael Richter, Markus D. Fl\u00fcckiger: Usability und UX kompakt: Produkte f\u00fcr Menschen (IT kompakt), Springer Vieweg (2016)\n\n--- Literature (DE) ---\n- Markus Dahm: Grundlagen der Mensch-Computer-Interaktion, Pearson (2006)\n- Jens Jacobsen: Praxisbuch Usability und UX, Rheinwerk (2017)\n- Steve Krug: Don't make me think - revisited, New Riders (2013)\n- Bernhard Preim, Raimund Dachselt: Interaktive Systeme Band 1 und 2, eXamen.press\n- Don Norman: The Design of Everyday Things, Basic Books (2013)\n- Michael Richter, Markus D. Fl\u00fcckiger: Usability und UX kompakt: Produkte f\u00fcr Menschen (IT kompakt), Springer Vieweg (2016)", "metadata": {"moduleNumber": "BMT W10", "moduleName": "Human-Computer Interaction", "creditPoints": "5.0", "suggestedSemester": null, "offeredInSeason": "to_be_announced", "examType": "written_exam", "heldInLanguage": "de", "reviserName": "Prof. Dr.-Ing. M.Sc. Markus Dahm", "reviserEmail": "markus.dahm@hs-duesseldorf.de", "studyProgramId": 9, "source_type": "json"}}
{"id": "BMTW11", "text": "Title: Multicopter Technology\nModule Number: BMT W11\nCredits: 5.0 CP\nSemester: None\nOffered In: to_be_announced\nLanguage: de\nExam Type: written_exam\nInstructor: None J\u00f6rg Becker-Schweitzer\n\n--- Goals (EN) ---\nThe students understand the technical structure and the components of a multicopter. They know the technical as well as the legal framework and can plan a multicopter flight on this basis. The students are able to put the aircraft into flight mode and operate it. They know the technical security systems of a multicopter and can react appropriately to dangerous situations. Students acquire the necessary flight experience and learn how to use a multicopter in professional film and video productions.\n\n--- Goals (DE) ---\nDie Studierenden verstehen den technischen Aufbau sowie die Komponenten eines Multikopters. Sie kennen technische als auch rechtliche Rahmenbedingungen und k\u00f6nnen auf dieser Grundlage einen Multikopterflug planen. Die Studierenden sind in der Lage, das Flugger\u00e4t in den Flugmodus zu bringen und zu bedienen. Sie kennen die technischen Sicherungssysteme eines Multikopters und k\u00f6nnen auf Gefahrensituationen geeignet reagieren. Die Studierenden erwerben die notwendige Flugpraxis und lernen den Einsatz eines Multikopters in professionellen Film- und Videoproduktionen kennen.\n\n--- Contents (EN) ---\nTechnical components of multicopters and comparable unmanned aerial vehicles, Basics of regulatory framework for usage in Germany, for example air traffic laws and media laws, Handling and controlling of multicopters / flight practice, Common safety systems and flight modes of multicopters, Usage of multicopters in video production environments\n\n--- Contents (DE) ---\nSchematischer Aufbau von Multikoptern sowie vergleichbaren Flugger\u00e4ten, Grundlagen rechtlicher Rahmenbedingungen in Deutschland, u. a. Luft-Verkehrsrecht und Medienrecht, Bedienung und Steuerung von Multikoptern / Flugpraxis, G\u00e4ngige Sicherheitssysteme und Flugmodi von Multikoptern, Einsatz von Multikoptern in Videoproduktionen\n\n--- Literature (EN) ---\n\n\n--- Literature (DE) ---\n- R. B\u00fcchi: Faszination Multicopter, vth 2015\n- C. Kornmeier: Der Einsatz von Drohnen zur Bildaufnahme (Eine luftverkehrs- und datenschutzrechliche Betrachtung), LIT 2012\n- D. A. Knight: \u00dcberirdisch Die Schonheit der Welt in Drohnenfotografie, teNeues 2016\n- E. Cheng: Mit Drohnen fotografieren und filmen: Das Praxisbuch f\u00fcr Einsteiger, dpunkt.Verlag GmbH 2016\n- I. Marloh / M. J. Sanderson: Filmen und Fotografieren mit Drohnen: Technik, Kaufratgeber, Pilotenschule, Vierfarben 2016", "metadata": {"moduleNumber": "BMT W11", "moduleName": "Multicopter Technology", "creditPoints": "5.0", "suggestedSemester": null, "offeredInSeason": "to_be_announced", "examType": "written_exam", "heldInLanguage": "de", "reviserName": "None J\u00f6rg Becker-Schweitzer", "reviserEmail": "jbs@hs-duesseldorf.de", "studyProgramId": 9, "source_type": "json"}}
{"id": "BMTW12", "text": "Title: Multimedia Storytelling\nModule Number: BMT W12\nCredits: 5.0 CP\nSemester: None\nOffered In: to_be_announced\nLanguage: de\nExam Type: portfolio\nInstructor: Prof. Gabriele Schwab-Trapp\n\n--- Goals (EN) ---\nStudents acquire skills in the conceptual handling of free or applied topics and the ability to independently develop context-related content. The development and practical realisation of their own ideas is made possible with the help of design processes. Experience in interdisciplinary, creative and constructive collaboration is gained within the seminar and possible project groups as well as in dealing with various forms of presentation.\n\n--- Goals (DE) ---\nDie Studierenden erwerben F\u00e4higkeiten im konzeptionellen Umgang mit freien oder angewandten Themen und die Bef\u00e4higung zur selbstst\u00e4ndigen Erarbeitung von kontextbezogenen Inhalten. Mithilfe von Gestaltungsprozessen werden die Entwicklung und die praktische Umsetzung eigener Ideen erm\u00f6glicht. Erfahrungen in interdisziplin\u00e4rer, kreativer und konstruktiver Zusammenarbeit werden innerhalb der Seminar- und m\u00f6glicher Projektgruppen sowie im Umgang mit verschiedenen Pr\u00e4sentationsformen gesammelt.\n\n--- Contents (EN) ---\nFree or applied topics are dealt with, which are presented at the beginning of the semester. The joint deepening, development and unfolding of the topic takes place in seminar form. This also includes philosophical, knowledge-orientated and opinion-forming discussions. The aim is the independent development and realisation of context-related, visual concepts in various media. Various forms of presentation are practised according to the topics and results. Excursions may be organised to support the topics, which will be announced at the beginning of the semester. Material and literature references will be provided for the respective topic in the seminar. Information in the form of text extracts, literature, image examples and research suggestions will be provided to support the respective learning, realisation and design steps. \nMultimedia storytelling is regularly offered as an open, collaborative and interdisciplinary module with students from other subject areas.\n\n--- Contents (DE) ---\nInhaltlich werden freie oder angewandte Themen behandelt, die zu Beginn des Semesters vorgestellt werden. Die gemeinsame Vertiefung, Entwicklung und Entfaltung des Themas findet in Seminarform statt. Dazu geh\u00f6rt auch die philosophische, erkenntnisorientierte und meinungsbildende Auseinandersetzung. Ziel ist die selbstst\u00e4ndige Entwicklung und Umsetzung von kontextbezogenen, visuellen Konzepten in unterschiedlichen Medien. Den Themen und Ergebnissen entsprechend werden verschiedene Pr\u00e4sentationsformen einge\u00fcbt. Themenunterst\u00fctzend k\u00f6nnen Exkursionen stattfinden, die zu Beginn des Semesters bekannt gegeben werden. Material- und Literaturangaben werden zu dem jeweiligen Thema im Seminar ausgegeben. Zur Unterst\u00fctzung der jeweiligen Lern-, Erkenntnis- und Gestaltungsschritte werden Hinweise in Form von Textausz\u00fcgen, Literatur, Bildbeispielen und Recherchevorschl\u00e4gen gegeben. \nMultimediales Erz\u00e4hlen wird regelm\u00e4\u00dfig als offenes, kollaboratives und interdisziplin\u00e4res Modul mit Studierenden aus anderen Fachbereichen angeboten.\n\n--- Literature (EN) ---\nLists of materials and literature are issued each semester in the seminar. The respective learning, realisation and design steps are supported by references in the form of text excerpts, literature, image examples and research suggestions. There is also a detailed oral introduction.\n\n--- Literature (DE) ---\nMaterial- und Literaturlisten werden jedes Semester aktuell im Seminar ausgegeben. Die jeweiligen Lern-, Erkenntnis- und Gestaltungsschritte werden unterst\u00fctzt durch Hinweise in Form von Textausz\u00fcgen, Literatur, Bildbeispielen und Recherchevorschl\u00e4gen. Zudem erfolgt eine ausf\u00fchrliche m\u00fcndliche Einf\u00fchrung.", "metadata": {"moduleNumber": "BMT W12", "moduleName": "Multimedia Storytelling", "creditPoints": "5.0", "suggestedSemester": null, "offeredInSeason": "to_be_announced", "examType": "portfolio", "heldInLanguage": "de", "reviserName": "Prof. Gabriele Schwab-Trapp", "reviserEmail": "gabi.schwab-trapp@hs-duesseldorf.de", "studyProgramId": 9, "source_type": "json"}}
{"id": "BMTW13", "text": "Title: New Work & New Learning\nModule Number: BMT W13\nCredits: 5.0 CP\nSemester: None\nOffered In: to_be_announced\nLanguage: de\nExam Type: portfolio\nInstructor: Prof. Dr. rer. nat. Michael Marmann\n\n--- Goals (EN) ---\nThe students\n\n- understand the concepts and driving forces behind the New Work movement.\n- can identify the principles of New Learning and apply them to educational contexts.\n- are able to design modern working and learning environments that promote creativity and innovation.\n- can critically analyze the effects of new technologies on work and education.\n- develop skills to act as change agents in their organizations.\n- can implement interdisciplinary approaches for lifelong learning and agile work processes.\n- can research and structure a current topic and present it at several levels of abstraction.\n- can argue a topic in the seminar group.\n- can prepare a current topic digitally and with interactive elements.\n\n--- Goals (DE) ---\nDie Studierenden\n- verstehen die Konzepte und treibenden Kr\u00e4fte hinter der New Work-Bewegung.\n- k\u00f6nnen die Prinzipien des New Learning identifizieren und auf Bildungskontexte anwenden.\n- sind in der Lage, moderne Arbeits- und Lernumgebungen zu gestalten, die Kreativit\u00e4t und Innovation f\u00f6rdern.\n- k\u00f6nnen kritisch die Auswirkungen neuer Technologien auf Arbeit und Bildung analysieren.\n- entwickeln F\u00e4higkeiten, um als Change Agents in ihren Organisationen zu fungieren.\n- k\u00f6nnen interdisziplin\u00e4re Ans\u00e4tze f\u00fcr lebenslanges Lernen und agile Arbeitsprozesse implementieren.\n- k\u00f6nnen ein aktuelles Thema recherchieren, strukturieren und auf mehreren Abstraktionslevels pr\u00e4sentieren.\n- k\u00f6nnen ein bearbeitetes Thema in der Seminargruppe argumentativ vertreten.\n- k\u00f6nnen ein aktuelles Thema digital und mit interaktiven Elementen aufbereiten.\n\n--- Contents (EN) ---\nThis seminar deals with the current changes in the world of work and their influence on learning processes. The basics of the New Work movement, which focuses on autonomy, flexibility and participation in the workplace, as well as the principles of New Learning, which emphasizes self-directed learning and the use of new technologies, are covered. Students learn about innovative approaches to the design of working and learning environments that take into account both the individual needs of learners and the requirements of modern organizations.\n\nAn essential part of the seminar is the examination of the challenges and opportunities that digital technologies bring for the world of work and education. Concepts such as lifelong learning, knowledge management and skills development in the context of New Work and New Learning will be discussed.\n\nThe seminar promotes the development of skills that enable participants to act as change agents and implement interdisciplinary approaches in their own professional contexts. This includes critical reflection on existing structures and the ability to design and manage agile and flexible learning and work processes.\n\n--- Contents (DE) ---\nDieses Seminar besch\u00e4ftigt sich mit den aktuellen Ver\u00e4nderungen in der Arbeitswelt und deren Einfluss auf Lernprozesse. Es werden die Grundlagen der New Work-Bewegung, die auf Autonomie, Flexibilit\u00e4t und Partizipation am Arbeitsplatz abzielt, sowie die Prinzipien des New Learning, welches Selbstgesteuertes Lernen und den Einsatz neuer Technologien in den Vordergrund stellt, behandelt. Die Studierenden lernen innovative Ans\u00e4tze zur Gestaltung von Arbeits- und Lernumgebungen kennen, die sowohl die individuellen Bed\u00fcrfnisse der Lernenden als auch die Anforderungen moderner Organisationen ber\u00fccksichtigen.\n\nEin wesentlicher Bestandteil des Seminars ist die Auseinandersetzung mit den Herausforderungen und Chancen, die digitale Technologien f\u00fcr die Arbeitswelt und das Bildungswesen mit sich bringen. Es werden Konzepte wie das lebenslange Lernen, Wissensmanagement und die Kompetenzentwicklung im Kontext von New Work und New Learning diskutiert.\n\nDas Seminar f\u00f6rdert die Entwicklung von Kompetenzen, die es den Teilnehmenden erm\u00f6glichen, als Change Agents zu agieren und interdisziplin\u00e4re Ans\u00e4tze in ihren eigenen beruflichen Kontexten umzusetzen. Dies beinhaltet die kritische Reflexion \u00fcber bestehende Strukturen und die F\u00e4higkeit, agile und flexible Lern- und Arbeitsprozesse zu gestalten und zu steuern.\n\n--- Literature (EN) ---\nCurrent literature references and sources of information are provided at the beginning of the module or directly from the course context. In addition, digital media are increasingly used as a source of knowledge.\n\n--- Literature (DE) ---\nAktuelle Literaturhinweise und Informationsquellen werden zu Beginn des Moduls oder unmittelbar aus dem Veranstaltungskontext herausgegeben. Zus\u00e4tzlich werden verst\u00e4rkt digitale Medien als Wissensquelle eingesetzt.", "metadata": {"moduleNumber": "BMT W13", "moduleName": "New Work & New Learning", "creditPoints": "5.0", "suggestedSemester": null, "offeredInSeason": "to_be_announced", "examType": "portfolio", "heldInLanguage": "de", "reviserName": "Prof. Dr. rer. nat. Michael Marmann", "reviserEmail": "marmann@hs-duesseldorf.de", "studyProgramId": 9, "source_type": "json"}}
{"id": "BMTW14", "text": "Title: Pencils and Polygons\nModule Number: BMT W14\nCredits: 5.0 CP\nSemester: None\nOffered In: to_be_announced\nLanguage: de\nExam Type: project\nInstructor: Prof. Dr.-Ing. Sina Mostafawy\n\n--- Goals (EN) ---\nThe students know the basics of drawing (picture composition, techniques, shading, perspective). They can transfer their knowledge from 2D to 3D modeling and rendering.\n\n--- Goals (DE) ---\nDie Studierenden erlernen die Grundlagen des Zeichnens. Sie k\u00f6nnen das Wissen aus dem 2D Zeichnen in die Erstellung von 3D Modelle \u00fcbertragen (insbesondere Beleuchtung). Sie wissen, in welcher Form der Begriff des Formens sowie Licht und Schatten die Arbeit in der 3D Welt pr\u00e4gen.\n\n--- Contents (EN) ---\n- Basics of drawing\n- Dynamic and linear lines\n- Hatching techniques\n- Light and shadow\n- Image composition, image division and -perspective\n- Storyboard drawings\n\n--- Contents (DE) ---\n- Grundlagen des Zeichnens\n- Dynamische und lineare Linie\n- Schraffur Techniken\n- Licht und Schatten\n- Bildkomposition, Bildeinteilung und -perspektive\n- Storyboard Zeichnungen\n\n--- Literature (EN) ---\n\n\n--- Literature (DE) ---\n- F. A. Cerver: Zeichnen f\u00fcr Einsteiger, Konemann Verlag Koln 2002G. Bammes: Studien zur Gestalt des Menschen, 3. Aufl. Urania Verlag 2001", "metadata": {"moduleNumber": "BMT W14", "moduleName": "Pencils and Polygons", "creditPoints": "5.0", "suggestedSemester": null, "offeredInSeason": "to_be_announced", "examType": "project", "heldInLanguage": "de", "reviserName": "Prof. Dr.-Ing. Sina Mostafawy", "reviserEmail": "sina.mostafawy@hs-duesseldorf.de", "studyProgramId": 9, "source_type": "json"}}
{"id": "BMTW15", "text": "Title: Project Media Engineering\nModule Number: BMT W15\nCredits: 5.0 CP\nSemester: None\nOffered In: to_be_announced\nLanguage: en_on_demand\nExam Type: project\nInstructor: \n\n--- Goals (EN) ---\nDifferent depending on the project orientation\nExample 1 - Interactive Media: Students master the conception, planning and implementation of an interactive media application using VR technologies and are able to critically evaluate them. The ability to communicate purposefully in an interdisciplinary team is one of the acquired competences.\nExample 2 - AV Media Production: Students can design, plan and implement media production projects. Through the project, students gain in-depth social and personal key competences as well as in-depth specialist skills in various areas of media technology and are specifically prepared for professional practice.\n\n--- Goals (DE) ---\nJe nach Projektausrichtung verschieden\nBeispiel 1  Interaktive Medien: Studierende beherrschen die Konzeption, Planung und Umsetzung einer interaktiven Medienanwendung unter Verwendung von VR-Technologien und sind in der Lage diese kritisch zu bewerten. Die F\u00e4higkeit zur zielf\u00fchrenden Kommunikation in einem interdisziplin\u00e4ren Team geh\u00f6rt zu den erworbenen Kompetenzen.\nBeispiel 2  AV-Medienproduktion: Studierende konnen Projekte zur Medienproduktion konzipieren, planen und umsetzen. Durch das Projekt erhalten die Studierenden vertieft soziale und pers\u00f6nliche Schl\u00fcsselkompetenzen sowie vertiefende Fachkompetenzen in unterschiedlichen Bereichen der Medientechnik und werden gezielt auf die berufliche Praxis vorbereitet.\n\n--- Contents (EN) ---\nExample 1 - Interactive Media: From an idea for an interactive application (e.g., for the web or as an installation), requirements and an application scenario are developed and various technical implementations discussed. This then leads to a specification and project plan. The development and creation of media content (models, images, video, sound, etc.) are carried out on a division of labor basis. Project schedule:Idea, requirements, application scenario, project planModeling and developmentTest cases and evaluationProject documentation and presentation\nExample 2 - \"AV Media Production\": Possible project sequence:Idea, concept development (storyboard, project plan)Audio- / Videoproduktion (casting, set planning, light / sound planning, camera technology, possibly tracking)3D modeling and possibly computer animationFusion of real and virtual objectsSound and music productionPost-production with nonlinear workflow and color grading / color correctionProject management and presentation\n\n--- Contents (DE) ---\nBeispiel 1  Interaktive Medien: Aus einer Idee f\u00fcr eine interaktive Anwendung (z.B. f\u00fcr das Web oder als Installation) werden Anforderungen und ein Anwendungsszenario entwickelt und verschiedene technische Realisierungsm\u00f6glichkeiten diskutiert. Dies f\u00fchrt dann zu einem Pflichtenheft und Projektplan. Die Entwicklung und die Erstellung der Medieninhalte (Modelle, Bilder, Video, Ton etc.) werden arbeitsteilig durchgef\u00fchrt. Projektablauf: Idee, Anforderungen, Anwendungsszenario, Projektplan, Modellierung und Entwicklung, Testf\u00e4lle und Evaluierung, Projektdokumentation und Pr\u00e4sentation\nBeispiel 2  AV-Medienproduktion: M\u00f6glicher Projektablauf: Idee, Konzeptentwicklung (Storyboard, Projektplan), Audio-/Videoproduktion (Casting, Setplanung, Licht/Tonplanung, Kameratechnik, ggf. Tracking), 3D-Modellierung und ggf. Computeranimation\nFusion realer und virtueller Objekte\nSound- und Musikproduktion\nPostproduktion mit nonlinearem Workflow und Color Grading/Farbkorrektur\nProjektmanagement und Pr\u00e4sentation\n\n--- Literature (EN) ---\nVaries depending on the project focus: Will be announced at the beginning of the course within the respective project.\n\n--- Literature (DE) ---\nJe nach Projektausrichtung verschieden: Wird zu Beginn der LV innerhalb des jeweiligen Projektes bekannt gegeben.", "metadata": {"moduleNumber": "BMT W15", "moduleName": "Project Media Engineering", "creditPoints": "5.0", "suggestedSemester": null, "offeredInSeason": "to_be_announced", "examType": "project", "heldInLanguage": "en_on_demand", "reviserName": "", "reviserEmail": null, "studyProgramId": 9, "source_type": "json"}}
{"id": "BMTW16", "text": "Title: Project Media Engineering Extension\nModule Number: BMT W16\nCredits: 5.0 CP\nSemester: None\nOffered In: to_be_announced\nLanguage: en_on_demand\nExam Type: project\nInstructor: \n\n--- Goals (EN) ---\nDifferent depending on the project orientation\nExample 1 - Interactive Media: Students master the conception, planning and implementation of an interactive media application using VR technologies and are able to critically evaluate them. The ability to communicate purposefully in an interdisciplinary team is one of the acquired competences.\nExample 2 - AV Media Production: Students can design, plan and implement media production projects. Through the project, students gain in-depth social and personal key competences as well as in-depth specialist skills in various areas of media technology and are specifically prepared for professional practice.\n\n--- Goals (DE) ---\nJe nach Projektausrichtung verschieden\nBeispiel 1  Interaktive Medien: Studierende beherrschen die Konzeption, Planung und Umsetzung einer interaktiven Medienanwendung unter Verwendung von VR-Technologien und sind in der Lage diese kritisch zu bewerten. Die F\u00e4higkeit zur zielf\u00fchrenden Kommunikation in einem interdisziplin\u00e4ren Team geh\u00f6rt zu den erworbenen Kompetenzen.\nBeispiel 2  AV-Medienproduktion: Studierende konnen Projekte zur Medienproduktion konzipieren, planen und umsetzen. Durch das Projekt erhalten die Studierenden vertieft soziale und pers\u00f6nliche Schl\u00fcsselkompetenzen sowie vertiefende Fachkompetenzen in unterschiedlichen Bereichen der Medientechnik und werden gezielt auf die berufliche Praxis vorbereitet.\n\n--- Contents (EN) ---\nExample 1 - Interactive Media: From an idea for an interactive application (e.g., for the web or as an installation), requirements and an application scenario are developed and various technical implementations discussed. This then leads to a specification and project plan. The development and creation of media content (models, images, video, sound, etc.) are carried out on a division of labor basis. Project schedule: Idea, requirements, application scenario, project plan, Modeling and development, Test cases and evaluation, Project documentation and presentation\nExample 2 - \"AV Media Production\": Possible project sequence: Idea, concept development (storyboard, project plan), Audio- / Videoproduktion (casting, set planning, light / sound planning, camera technology, possibly tracking), 3D modeling and possibly computer animation, Fusion of real and virtual objects, Sound and music production, Post-production with nonlinear workflow and color grading / color correction, Project management and presentation\n\n--- Contents (DE) ---\nBeispiel 1  Interaktive Medien: Aus einer Idee f\u00fcr eine interaktive Anwendung (z.B. f\u00fcr das Web oder als Installation) werden Anforderungen und ein Anwendungsszenario entwickelt und verschiedene technische Realisierungsm\u00f6glichkeiten diskutiert. Dies f\u00fchrt dann zu einem Pflichtenheft und Projektplan. Die Entwicklung und die Erstellung der Medieninhalte (Modelle, Bilder, Video, Ton etc.) werden arbeitsteilig durchgef\u00fchrt. Projektablauf: Idee, Anforderungen, Anwendungsszenario, Projektplan, Modellierung und Entwicklung, Testf\u00e4lle und Evaluierung, Projektdokumentation und Pr\u00e4sentation \nBeispiel 2  AV-Medienproduktion: M\u00f6glicher Projektablauf: Idee, Konzeptentwicklung (Storyboard, Projektplan), Audio-/Videoproduktion (Casting, Setplanung, Licht/Tonplanung, Kameratechnik, ggf. Tracking), 3D-Modellierung und ggf. Computeranimation, Fusion realer und virtueller Objekte, Sound- und Musikproduktion, Postproduktion mit nonlinearem Workflow und Color Grading/Farbkorrektur, Projektmanagement und Pr\u00e4sentation\n\n--- Literature (EN) ---\nVaries depending on the project focus: Will be announced at the beginning of the course within the respective project.\n\n--- Literature (DE) ---\nJe nach Projektausrichtung verschieden: Wird zu Beginn der LV innerhalb des jeweiligen Projektes bekannt gegeben.", "metadata": {"moduleNumber": "BMT W16", "moduleName": "Project Media Engineering Extension", "creditPoints": "5.0", "suggestedSemester": null, "offeredInSeason": "to_be_announced", "examType": "project", "heldInLanguage": "en_on_demand", "reviserName": "", "reviserEmail": null, "studyProgramId": 9, "source_type": "json"}}
{"id": "BMTW17", "text": "Title: Room and Building Acoustics\nModule Number: BMT W17\nCredits: 5.0 CP\nSemester: None\nOffered In: to_be_announced\nLanguage: de\nExam Type: written_exam\nInstructor: None J\u00f6rg Becker-Schweitzer\n\n--- Goals (EN) ---\nAfter completing this event, the students have applied and market-related basic knowledge in the field of room and building acoustics. They are able to judge given space situations technically and to be able to estimate technical innovations in the field of room and building acoustics\n\n--- Goals (DE) ---\nDie Studierenden verf\u00fcgen nach Abschluss dieser Veranstaltung \u00fcber anwendungs- und marktbezogene Grundkenntnisse im Bereich der Raum- und Bauakustik. Sie sind im Stande, gegebene Raumsituationen fachtechnisch zu beurteilen und technische Innovationen im Bereich der Raum- und Bauakustik einsch\u00e4tzen zu k\u00f6nnen\n\n--- Contents (EN) ---\nThe lecture deals with basic methods and procedures of room acoustics analysis and project planning. The focus is on teaching basic principles of room acoustics models: Geometric room acoustics, Statistical room acoustics, Wave theoretical room acoustics. Application-oriented methods, methods and estimations used in room acoustics consulting are presented. At the impedance model of interfaces basic equations of building acoustics are derived.\n\nSound propagation in rooms, reflection, transmission, absorption, direct field, diffuse sound field, Hall radius, sound level in space, absorbers and their application (porous absorbers, plate vibrators, Helmholtz resonators, alternative absorbers), noise reduction, reflection, sound insulation, definition of reverberation time according to planned use, design criteria for rooms, examples of different rooms, DIN standards, fundamentals of studio acoustics\n\n--- Contents (DE) ---\nDie Vorlesung behandelt grundlegende Methoden und Verfahren der raumakustischen Analyse und Projektierung. Der Schwerpunkt liegt auf der Vermittlung von grundlegenden Prinzipien der Raumakustik Modelle: Geometrische Raumakustik, Statistische Raumakustik, Wellentheoretische Raumakustik. Es werden anwendungsorientierte Verfahren, Methoden und Absch\u00e4tzungen, die in der raumakustischen Beratung zum Einsatz kommen, vorgestellt. Am Impedanzmodell von Grenzfl\u00e4chen werden grundlegende Gleichungen der Bauakustik abgeleitet.\n\nSchallausbreitung in R\u00e4umen, Reflexion, Transmission, Absorption, Direktfeld, Diffuses Schallfeld, Hallradius, Schallpegel im Raum, Absorber und ihre Anwendung (Por\u00f6se Absorber, Plattenschwinger, Helmholtz-Resonatoren, Alternative Absorber), Schallenkung, Reflexion, Schalld\u00e4mmung, Festlegung der Nachhallzeit je nach geplanter Nutzung, Auslegungskriterien f\u00fcr R\u00e4ume, Beispiele f\u00fcr verschiedene R\u00e4ume, DIN Normen, Grundlagen der Studioakustik\n\n--- Literature (EN) ---\n\n\n--- Literature (DE) ---\n- H. Kuttruff: Room Acoustics, Applied Science Publishers London. 4th Edition 2000\n- J. Cowan: Architectural Acoustics Design Guide, MCGraw-Hill 2000\n- L.K. Irvine, R.L. Richards: Acoustics and Noise Control Handbook for Architects an Builders, Krieger Publishing 1998\n- H. Bobran, I. Bobran: Handbuch der Bauphysik, Vieweg Braunschweig 1995\n- C. Romer: Schall und Raum - Eine kleine Einf\u00fchrung in die Raumakustik, vde verlag Berlin 1994\n- L. Cremer, H.A. M\u00fcller: Die wissenschaftlichen Grundlagen der Raumakustik, Bd. 1 u. 2 Hirzel Verlag Stuttgart 1978", "metadata": {"moduleNumber": "BMT W17", "moduleName": "Room and Building Acoustics", "creditPoints": "5.0", "suggestedSemester": null, "offeredInSeason": "to_be_announced", "examType": "written_exam", "heldInLanguage": "de", "reviserName": "None J\u00f6rg Becker-Schweitzer", "reviserEmail": "jbs@hs-duesseldorf.de", "studyProgramId": 9, "source_type": "json"}}
{"id": "BMTW18", "text": "Title: Technical Event Planning\nModule Number: BMT W18\nCredits: 5.0 CP\nSemester: None\nOffered In: to_be_announced\nLanguage: de\nExam Type: oral_exam\nInstructor: None J\u00f6rg Becker-Schweitzer\n\n--- Goals (EN) ---\nThe students have the ability to carry out technical planning tasks. They can plan a booth and display it with CAD. They can perform simple analysis of the static structures and construction parts as well as the electrical connection performance.\n\n--- Goals (DE) ---\nDie Studierenden besitzen die F\u00e4higkeit zur Durchf\u00fchrung von Aufgabenstellungen der technischen Messeplanung. Sie k\u00f6nnen einen Messestand planen, mit CAD darstellen und einfache statische Untersuchungen der Konstruktionen und Konstruktionsteile sowie der elektrischen Anschlussleistungen durchf\u00fchren.\n\n--- Contents (EN) ---\nStatic equilibrium conditions, application examplesDetermination of internal forces and moments (normal force, lateral force, bending moment, torsional moment) and the stressesDealing with computer aided (structural) design toolsExamples, tasks and exercises for all teaching contentsRegulations and guidelines of the exhibition and event area\n\n--- Contents (DE) ---\nGleichgewichtsbedingungen, AnwendungsbeispieleErmittlung der inneren Kr\u00e4fte und Momente (Normalkraft, Querkraft, Biegemoment, Torsionsmoment) und der Spannungen\nUmgang mit Computer Aided (Structural) Design-Werkzeugen\nBeispiele, Aufgaben und \u00dcbungen zu allen Lehrinhalten\nVorschriften und Richtlinien des Messe- und Veranstaltungsbereiches\n\n--- Literature (EN) ---\n\n\n--- Literature (DE) ---\n- J. Berger: Technische Mechanik f\u00fcr Ingenieure, Bande: Bd.1: Statik, Vieweg Verlag 1991 Bd.2: Festigkeitslehre, Vieweg Verlag 1994 Bd.3: Dynamik, Vieweg Verlag 1998\n- D. Gross, W. Hauger, J. Schroder, W. Wall: Technische Mechanik 1: Statik, Springer Verlag 2011\n- D. Gross, W. Hauger, J. Schroder, W. Wall: Technische Mechanik 2: Elastostatik, Springer Verlag 2011\n- D. Gross, W. Hauger, J. Schroder, W. Wall: Technische Mechanik 3: Kinetik, Springer Verlag 2010\n- D. Gross, W. Hauger, J. Schr\u00f6der, W. Wall: Technische Mechanik 4: Hydromechanik, Springer Verlag 2009\n- H. Dankert, J. Dankert: Technische Mechanik computerunterst\u00fctzt, Teubner B.G. Verlag 1995\n- G. Henning, A. Jahr, U. Mrowka: Technische Mechanik mit Mathcad, Matlab und Maple, Vieweg & Teubner Verlag 2004\nWeitere aktuelle Literatur wird zu Beginn der LV bekanntgegeben.", "metadata": {"moduleNumber": "BMT W18", "moduleName": "Technical Event Planning", "creditPoints": "5.0", "suggestedSemester": null, "offeredInSeason": "to_be_announced", "examType": "oral_exam", "heldInLanguage": "de", "reviserName": "None J\u00f6rg Becker-Schweitzer", "reviserEmail": "jbs@hs-duesseldorf.de", "studyProgramId": 9, "source_type": "json"}}
{"id": "BMTW19", "text": "Title: Company Formation\nModule Number: BMT W19\nCredits: 5.0 CP\nSemester: None\nOffered In: to_be_announced\nLanguage: de\nExam Type: research_paper\nInstructor: Prof. Dr.-Ing. M.Sc. Markus Dahm\n\n--- Goals (EN) ---\nAfter successfully completing the module, students know and understand basic business terms and approaches that enable them to develop a business idea in the form of a business plan. They are able to analyse and evaluate the strengths and weaknesses of a business model in order to develop a target-oriented competitive strategy on this basis\n\n--- Goals (DE) ---\nNach erfolgreicher Teilnahme am Modul kennen und verstehen die Studierenden grundlegende betriebswirtschaftliche Begriffe und Ans\u00e4tze, die sie dazu bef\u00e4higen, eine Gesch\u00e4ftsidee in Form eines Business Plans zu entwickeln. Sie sind in der Lage St\u00e4rken und Schw\u00e4chen eines Gesch\u00e4ftsmodells zu analysieren und zu bewerten, um auf dieser Grundlage eine zielf\u00fchrende Wettbewerbsstrategie entwickeln zu k\u00f6nnen\n\n--- Contents (EN) ---\n- Descriptive parameters of a business model\n- Competition analysis\n- Target group analysis\n- SWOT analysis\n- Turnover/sales planning\n- P&L planning\n- Calculation of cost of goods sold\n- Financial planning\n- Determination of capital requirements (balance sheet) and financing\n- Choice of legal form\n\n--- Contents (DE) ---\n- Deskriptive Parameter eines Gesch\u00e4ftsmodells\n- Wettbewerbsanalyse\n- Zielgruppenanalyse\n- SWOT-Analyse\n- Umsatz-/Absatzplanung\n- GuV-Planung\n- Kalkulation der Selbstkosten\n- Finanzplanung\n- Kapitalbedarfsermittlung (bilanziell) und Finanzierung\n- Rechtsformwahl\n\n--- Literature (EN) ---\n- Kollmann, T.: E-Entrepreneurship. Grundlagen der Unternehmensgr\u00fcndung in der digitalen Wirtschaft. M\u00fcnchen, 2016\n- neuesunternehmertum.de (Materialien zur Erstellung eines Business Plans)\n- Osterwalder, L. et al.: Value Proposition Design: Entwickeln Sie Produkte und Services, die Ihre Kunden wirklich wollen. Frankfurt a.M., 2015\n- Ries, E.: Lean-Startup. Schnell, risikolos und erfolgreich Unternehmengr\u00fcnden. M\u00fcnchen, 2014\n\n--- Literature (DE) ---\n- Kollmann, T.: E-Entrepreneurship. Grundlagen der Unternehmensgr\u00fcndung in der digitalen Wirtschaft. M\u00fcnchen, 2016\n- neuesunternehmertum.de (Materialien zur Erstellung eines Business Plans)\n- Osterwalder, L. et al.: Value Proposition Design: Entwickeln Sie Produkte und Services, die Ihre Kunden wirklich wollen. Frankfurt a.M., 2015\n- Ries, E.: Lean-Startup. Schnell, risikolos und erfolgreich Unternehmengr\u00fcnden. M\u00fcnchen, 2014", "metadata": {"moduleNumber": "BMT W19", "moduleName": "Company Formation", "creditPoints": "5.0", "suggestedSemester": null, "offeredInSeason": "to_be_announced", "examType": "research_paper", "heldInLanguage": "de", "reviserName": "Prof. Dr.-Ing. M.Sc. Markus Dahm", "reviserEmail": "markus.dahm@hs-duesseldorf.de", "studyProgramId": 9, "source_type": "json"}}
{"id": "BMTW20", "text": "Title: Advanced Room and Building Acoustics\nModule Number: BMT W20\nCredits: 5.0 CP\nSemester: None\nOffered In: to_be_announced\nLanguage: de\nExam Type: oral_exam\nInstructor: None J\u00f6rg Becker-Schweitzer\n\n--- Goals (EN) ---\nAfter completing this course, students have applied and market-related knowledge in the field of room and building acoustics, the contents and requirements of relevant standards and guidelines are familiar to them. They are able to carry out building acoustical measurements and to be able to evaluate rooms on the basis of characteristic values.\n\n--- Goals (DE) ---\nDie Studierenden verf\u00fcgen nach Abschluss dieser Veranstaltung \u00fcber anwendungs- und marktbezogene Kenntnisse im Bereich der Raum- und Bauakustik, die Inhalte und Anforderungen einschl\u00e4giger Normen und Richtlinien sind ihnen gel\u00e4ufig. Sie sind im Stande bau und raumakustische Messungen durchzuf\u00fchren und R\u00e4ume anhand von Kennwerten beurteilen zu k\u00f6nnen.\n\n--- Contents (EN) ---\nIn the event further contents and procedures of the measuring technique of the room acoustics and building acoustics as well as the noise measurement technology are presented. The focus is on communicating the content of relevant standards and guidelines. Different requirement profiles for music rooms, speech lecture, office use are explained. By way of example, measurements and calculations are carried out to determine the room and building acoustic characteristics. Detailed solutions for achieving the high acoustic requirements in studio areas are described.Keywords: metrology:FFT / RTA, LA, eq, airborne, impact and structure-borne sound insulation, derivation of single number characteristic, noise limits for sound reinforcement, room acoustics parameters in the concert hall and auditorium, acoustic requirements in studio zones, acoustics in office areas Components: absorber, reflector and diffuser\n\n--- Contents (DE) ---\nIn der Veranstaltung werden weiterf\u00fchrende Inhalte und Verfahren der Messtechnik der Raum- bzw. Bauakustik sowie der L\u00e4rmmesstechnik vorgestellt. Der Schwerpunkt liegt auf der Vermittlung der Inhalte einschl\u00e4giger Normen und Richtlinien. Unterschiedliche Anforderungsprofile f\u00fcr Musikr\u00e4ume, Sprachvortrag, B\u00fcronutzung werden erl\u00e4utert. Beispielhaft werden Messungen und Berechnungen zur Ermittlung der Raum- und Bauakustik-Kennwerte durchgef\u00fchrt. Detaill\u00f6sungen zur Erreichung der hohen Akustikanforderungen in Studiobereichen werden beschrieben. Schlagworte: Messtechnik:FFT / RTA, LA,eq , Luftschall-, Trittschall- undKorperschalldammung, Ableitung von Einzahl-Kennwerten,L\u00e4rmgrenzwerte bei Beschallung, Raumakustik-Parameter imKonzertsaal und H\u00f6rsaal, Akustikanforderungen in Studiozonen,Akustik in B\u00fcrobereichen Bauelemente: Absorber, Reflektor undDiffusor\n\n--- Literature (EN) ---\n\n\n--- Literature (DE) ---\n- H. Kuttruff: Room Acoustics, Applied Science Publishers 2000\n- R. F. Barron: Industrial Noise Control and Acoustics, CRC Press 2002\n- P. Newell: Recording Studio Design, Focal Press 3 rd Ed. 2011\n- Th. Rossing: Handbook of Acoustics, Springer Verlag 2007\n- J. Meyer: Acoustics and Performance of Music, Springer Verlag 2009\n- L. Cremer, H.A. M\u00fcller: Die wissenschaftlichen Grundlagen der Raumakustik, Bd. 1 u. 2 Hirzel Verlag Stuttgart 1978\n- T. E. Vigran: Building Acoustics, Taylor & Francis 2007\n- H. Fuchs: Schallabsorber und Schalldampfer_3-2010\n- F. A. Everest, K. C. Pohlmann: Master Handbook of Acoustics, 6th Ed McGraw-Hill 2014\n- T. Cox, P. D'Antonio: Acoustic Absorbers and Diffusers, CRC Press 2nd Ed. 2009\n- M. Long: Architectural Acoustics, Academic Press 2006\n- BBC-Engineering: Guide to Acoustic Practice 2nd Ed. 1990\n- Div. Normen und Richtlinien der Fachliteratur", "metadata": {"moduleNumber": "BMT W20", "moduleName": "Advanced Room and Building Acoustics", "creditPoints": "5.0", "suggestedSemester": null, "offeredInSeason": "to_be_announced", "examType": "oral_exam", "heldInLanguage": "de", "reviserName": "None J\u00f6rg Becker-Schweitzer", "reviserEmail": "jbs@hs-duesseldorf.de", "studyProgramId": 9, "source_type": "json"}}
{"id": "BMTW21", "text": "Title: Virtual Reality and Augmented Reality\nModule Number: BMT W21\nCredits: 5.0 CP\nSemester: None\nOffered In: to_be_announced\nLanguage: en_on_demand\nExam Type: portfolio\nInstructor: Prof. Dr. Eng. Univ. of Tsukuba Jens Herder\n\n--- Goals (EN) ---\nSuccessful participants will have a profound knowledge in building and developing virtual environments and will be able to evaluate application based on vr technology.\n\n--- Goals (DE) ---\nDie Studierenden kennen die wichtigsten VR-Technologien und sind in der Lage, virtuelle Umgebungen zu konzipieren, aufzubauen und in der Anwendung zu bewerten.\n\n--- Contents (EN) ---\n- Motivation, definitions, Layout and design of virtual environment\n- Application fields\n- Human factors in virtual environments\n- Augmented Reality\n- Display systems (e.g., stereo projection)\n- Input and output devices\n- Scene modeling (scene graph based)\n- Data structures and algorithms\n- Simulation\n- Programming of virtual environments\n- Tracking for user interaction\n- Navigation and Interaction in VR\n- Real-time rendering and special effects\n- Haptics\n- Virtual acoustics\n\n--- Contents (DE) ---\n- Motivation / Begriffsdefinition / Aufbau virtueller Umgebungen\n- Aktuelle Anwendungsgebiet\n- Wahrnehmungsfaktoren f\u00fcr virtuellen Umgebungen\n- Augmented Reality\n- Darstellungstechniken (u.a. stereographische Projektion)\n- Ein- und Ausgabeger\u00e4te\n- 3D-Szenenmodellierung\n- Datenstrukturen und Algorithmen f\u00fcr Virtuelle Umgebungen\n- Simulation in virtuellen Umgebungen\n- Entwurf und Programmierung virtueller Umgebungen\n- Tracking von Benutzern und Objekten in VR-Umgebungen\n- Navigation und Interaktion in VR\n- Visuelle Effekte in Echtzeit (u.a. Schatten)\n- Haptik\n- Virtuelle Akustik\n- Nicht-visuelle Repr\u00e4sentation in Virtuellen Umgebungen\n\n--- Literature (EN) ---\n- Ralf D\u00f6rner, Wolfgang Broll, Paul Grimm, Bernhard Jung, Virtual and Augmented Reality (VR/AR), Foundations and Methods of Extended Realities (XR), Springer, 2022, DOI 10.1007/978-3-030-79062-2\n- Jason Jerald. The VR Book: Human-Centered Design for Virtual Reality. Association for Computing Machinery and Morgan & Claypool, New York, NY, USA, 2015, DOI 10.1145/2792790\n- G. C. Burdea, P. Coiffet: Virtual Reality Technology, John Wiley & Sons, 3. Edition, 2024, ISBN 978-1-118-01480-6\n- M. Guiterrez, F. Vexo, D. Thalman: Stepping into Virtual Reality, Springer Nature Publisher, 2. Edition, 2023, DOI 10.1007/978-3-031-36487-7\n- W. Sherman, A. Craig: Understanding Virtual Reality - Interface, Application, and Design, Morgan Kaufman, 2. Edition 2018, DOI 10.1016/C2013-0-18583-2\n- J. Vince: Introduction to Virtual Reality, Springer 2004, DOI 10.1007/978-0-85729-386-2\n- J. Blauert: Spatial Hearing - The Psychophysics of Human Sound Localization, The MIT Press, Revised Edition, ISBN 0-262-02413-6, 1996\n\nFurther recent literature will be announced at the beginning of the course.\n\n--- Literature (DE) ---\n- R. D\u00f6rner, W. Broll, P. Grimm, B. Jung (Hrsg.), Virtual und Augmented Reality (VR/AR), Grundlagen und Methoden der Virtuellen und Augmentierten Realit\u00e4t, Springer, 2014, DOI 10.1007/978-3-642-28903-3\n- Jason Jerald. The VR Book: Human-Centered Design for Virtual Reality. Association for Computing Machinery and Morgan & Claypool, New York, NY, USA. 2015, DOI 10.1145/2792790\n- G. C. Burdea, P. Coiffet: Virtual Reality Technology, John Wiley & Sons, 3. Auflage, 2024, ISBN 978-1-118-01480-6\n- M. Guiterrez, F. Vexo, D. Thalman: Stepping into Virtual Reality, Springer Nature Verlag, 2. Ausgabe, 2023, DOI 10.1007/978-3-031-36487-7\n- W. Sherman, A. Craig: Understanding Virtual Reality - Interface, Application, and Design, Morgan Kaufman, 2. Auflage, 2018, DOI 10.1016/C2013-0-18583-2\n- J. Vince: Introduction to Virtual Reality, Springer 2004, DOI 10.1007/978-0-85729-386-2\n- J. Blauert: Spatial Hearing - The Psychophysics of Human Sound Localization, The MIT Press, Revised Edition, ISBN 0-262-02413-6, 1996\n\nWeitere aktuelle Literatur wird zu Beginn der LV bekannt gegeben.", "metadata": {"moduleNumber": "BMT W21", "moduleName": "Virtual Reality and Augmented Reality", "creditPoints": "5.0", "suggestedSemester": null, "offeredInSeason": "to_be_announced", "examType": "portfolio", "heldInLanguage": "en_on_demand", "reviserName": "Prof. Dr. Eng. Univ. of Tsukuba Jens Herder", "reviserEmail": "jens.herder@hs-duesseldorf.de", "studyProgramId": 9, "source_type": "json"}}
{"id": "BMTW22", "text": "Title: Web Programming\nModule Number: BMT W22\nCredits: 5.0 CP\nSemester: None\nOffered In: to_be_announced\nLanguage: de\nExam Type: written_exam\nInstructor: Prof. Dr. Manfred Wojciechowski\n\n--- Goals (EN) ---\nThe student understands the technical foundations of web applications and the separation between structure, design and behavior of web sites. They can apply those technologies for the implementation of static websites. They can also apply advanced technologies for the clientside adaption of websites regarding the diverse presentation constraints of different end devices. They are able the evaluate existing static websites regarding the quality of implementation.\n\n--- Goals (DE) ---\nDie Studierenden verstehen die technischen Grundlagen von Webanwendungen und die Trennung zwischen Struktur, Design und Verhalten von Webseiten. Sie k\u00f6nnen Technologien zur Realisierung statischer Webseiten sowie Fortgeschrittene Techniken f\u00fcr die clientseitige Anpassung von Webseiten in Hinblick auf unterschiedliche Darstellungsanforderungen anwenden. Sie sind in der Lagebestehende statische Webseiten bez\u00fcglich einer sauberen Realisierung zu bewerten.\n\n--- Contents (EN) ---\nweb application fundamentals (www, client-server-architecture, http)\ntechnologies for the realization of static web sites: structure and content (XML, HTML5); design (CSS3); scripting (ECMAScript 6+, DOM)\nadvanced technologies for the adaption of representation requirements, e.g. responsive webdesign\n\n--- Contents (DE) ---\nVorlesung:\nGrundlagen von Webanwendungen (WWW, Client-Server, http-Protokoll)\nTechniken f\u00fcr die Realisierung von statischen Webseiten: Struktur und Inhalte (XML, HTML5); Design (CSS3); Verhalten (ECMAScript 6, DOM)\nFortgeschrittene Techniken zur Adaption an Darstellungsanforderungen, z.B. responsive Webdesign\n\u00dcbung: \u00dcbungsaufgaben zur Anwendung der Lehrinhalte aus der Vorlesung\nUmsetzung einer eigenen Webseite auf Basis der gelernten Techniken.\n\n--- Literature (EN) ---\n\n\n--- Literature (DE) ---\n- M. Wojciechowski: Vorlesungsskript zur Webprogrammierung\n- E. Robson, E. Freeman: HTML und CSS von Kopf bis Fu\u00df, O'Reilly 2013\n-E. Robson, E. Freeman: HTML5-Programmierung von Kopf bis Fu\u00df: Webanwendungen mit HTML5 und JavaScript, 2012\n- C. Zillgens: Responsive Webdesign, Hanser-Verlag 2013\n- S. M\u00fcnz, C. Gull: HTML5 Handbuch, Franzis Verlag 2013", "metadata": {"moduleNumber": "BMT W22", "moduleName": "Web Programming", "creditPoints": "5.0", "suggestedSemester": null, "offeredInSeason": "to_be_announced", "examType": "written_exam", "heldInLanguage": "de", "reviserName": "Prof. Dr. Manfred Wojciechowski", "reviserEmail": "manfred.wojciechowski@hs-duesseldorf.de", "studyProgramId": 9, "source_type": "json"}}
{"id": "BMTW23", "text": "Title: Network Engineering 2\nModule Number: BMT W23\nCredits: 5.0 CP\nSemester: None\nOffered In: to_be_announced\nLanguage: de\nExam Type: portfolio\nInstructor: Prof. Dr.-Ing. Stefanie Dederichs\n\n--- Goals (EN) ---\nStudents are aware of the need for routing when submitting packets over subnets. They are able to classify the routing according to the ISO / OSI layer model. They now the use cases, the advantages and disadvantages of static and dynamic routing. They are able to apply those concepts in the configuration of small and medium sized networks. The students know the reasons for the usage of VLANs. They are able to create VLANs on routers and switches. They know selected use cases for access control lists. They are able to limit access to subnets by creating appropriate access control lists. They are aware of the need for dynamic allocation of IPv4 and IPv6 addresses. They know mechanisms for the dynamic allocation of IPv6 addresses. They are able to configure network participants and routers for the dynamic allocation of IP addresses. The students know some use cases for the temporary assignment of public addresses. They are able to configure NAT on a router.\n\n--- Goals (DE) ---\nDie Studierenden kennen die Notwendigkeit des Routings bei der \u00dcbermittlung von Paketen \u00fcber Subnetze und k\u00f6nnen dieses im ISO/OSI Kommunikationmodell einordnen. Sie kennen die Einsatzf\u00e4lle, sowie die Vor- und Nachteile des statischen bzw. des dynamischen Routings. Sie sind in der Lage statische und dynamische Routen zu erstellen. Die Studierenden kennen Gr\u00fcnde f\u00fcr den Einsatz von VLANs. Sie sind in der Lage ein VLAN auf Routern und Switchen anzulegen. Sie kennen einige Einsatzf\u00e4lle f\u00fcr Zugriffskontrolllisten. Sie sind in der Lage den Zugriff auf Subnetze durch das Anlegen von entsprechenden Zugriffskontrolllisten zu kontrollieren. Sie kennen die Notwendigkeit f\u00fcr die dynamische Zuordnung von IPv4 und IPv6-Adressen. Sie kennen Mechanismen zur dynamischen Zuordnung von IPv6-Adressen. Sie sind in der Lage Netzwerkteilnehmer und Router f\u00fcr die dynamische Vergabe von IP-Adressen zu konfigurieren. Die Studierenden kennen Einsatzfelder f\u00fcr die tempor\u00e4re Zuordnung \u00f6ffentlicher Adressen. Sie sind in der Lage auf einem Router das NAT zu konfigurieren.\n\n--- Contents (EN) ---\nStatic and dynamic routing, Flexible networks using VLAN, Access Control List, Dynamic assigment of IP adresses using DHCP, Temporary mapping of public addresses using NAT\n\n--- Contents (DE) ---\nStatisches und Dynamisches Routing, Flexible Netzwerke mit Hilfe von VLANs, Zugriffskontrolllisten, Dynamische Vergabe von IP-Adressen mittels DHCP, Temporare Zuordnung \u00f6ffentlicher Adressen mittels NAT\n\n--- Literature (EN) ---\n\n\n--- Literature (DE) ---\nWebbasiertes Curriculum CCNA 2Computer-Netzwerke: Grundlagen, Funktionsweisen, Anwendung. F\u00fcr Studium, Ausbildung und Beruf, Rheinwerk ComputingNetzwerktechnik, Band 2: Erweiterte Grundlagen, Airnet", "metadata": {"moduleNumber": "BMT W23", "moduleName": "Network Engineering 2", "creditPoints": "5.0", "suggestedSemester": null, "offeredInSeason": "to_be_announced", "examType": "portfolio", "heldInLanguage": "de", "reviserName": "Prof. Dr.-Ing. Stefanie Dederichs", "reviserEmail": "stefanie.dederichs@hs-duesseldorf.de", "studyProgramId": 9, "source_type": "json"}}
{"id": "BMTW24", "text": "Title: Network Engineering 3\nModule Number: BMT W24\nCredits: 5.0 CP\nSemester: None\nOffered In: to_be_announced\nLanguage: de\nExam Type: portfolio\nInstructor: Prof. Dr.-Ing. Stefanie Dederichs\n\n--- Goals (EN) ---\n\n\n--- Goals (DE) ---\nDie Studierenden erkl\u00e4ren sich die Arbeitsweise und die Vorteile des Spanning Tree Protokolls. Sie sind in der Lage ein solches Protokoll im Netzwerk zu konfigurieren und Fehler zu beseitigen. Sie kennen die Eigenschaften des Inter-VLAN Routing und sind in der Lage das Netzwerk entsprechend einzurichten. Sie kennen die M\u00f6glichkeiten, die Bandbreiten zwischen verschiedenen Knoten mittels der Aggregation mehrerer physikalischer Leitungen zu erh\u00f6hen. Sie kennen die entsprechenden Protokolle dazu und k\u00f6nnen das Netzwerk entsprechend konfigurieren. Sie kennen unterschiedliche dynamische Routingprotokolle und setzen diese entsprechend ein.\n\n--- Contents (EN) ---\n\n\n--- Contents (DE) ---\nAusgew\u00e4hlte Gebiete der Netzwerktechnik werden vertieft: Technologien f\u00fcr gro\u00dfe und komplexe Netzwerke, Spanning Tree Protocol, Inter-VLAN Routing, EtherChannel und HSRP, Routing Protokolle, z.B. OSPF und EIGRP\n\n--- Literature (EN) ---\n\n\n--- Literature (DE) ---\nTanenbaum: Computer Networks, Pearson;\nR. Schreiner: Computernetzwerke: Von den Grundlagen zur Funktion und Anwendung, Carl Hanser Verlag;\nWebbasiertes Curriculum;", "metadata": {"moduleNumber": "BMT W24", "moduleName": "Network Engineering 3", "creditPoints": "5.0", "suggestedSemester": null, "offeredInSeason": "to_be_announced", "examType": "portfolio", "heldInLanguage": "de", "reviserName": "Prof. Dr.-Ing. Stefanie Dederichs", "reviserEmail": "stefanie.dederichs@hs-duesseldorf.de", "studyProgramId": 9, "source_type": "json"}}
{"id": "BMTW25", "text": "Title: Rapid System Prototyping\nModule Number: BMT W25\nCredits: 5.0 CP\nSemester: 4\nOffered In: summer_semester\nLanguage: de\nExam Type: oral_exam\nInstructor: Dipl.-Ing. M.Sc. Christian Epe\n\n--- Goals (EN) ---\n- Understanding of the concepts and importance of rapid system prototyping in hardware and software development.\n- Mastering techniques for creating functional prototypes of hardware/software and information systems.\n- Ability to apply various prototyping tools and methods, including prototyping software, mockups and wireframes.\n\n--- Goals (DE) ---\n- Verst\u00e4ndnis der Konzepte und Bedeutung des Rapid System Prototyping in der Hard- und Softwareentwicklung. \n- Beherrschung von Techniken zur Erstellung funktionsf\u00e4higer Prototypen von Hard-/Software- und Informationssystemen. \n- F\u00e4higkeit zur Anwendung verschiedener Prototyping-Tools und -Methoden, einschlie\u00dflich Prototyping-Software, Mockups und Wireframes.\n\n--- Contents (EN) ---\n- Conception and implementation of prototypical works in the field of media technology\n- Introduction to Rapid System Prototyping: Concepts, Goals and Applications.\n- Prototyping tools and methods: Available tools and selection of suitable methods for various applications, e.g. 3D modeling, implementation using CAM processes (3D printing, CNC milling, lasering)\n- Development of circuit diagrams and design of circuit boards\n- Prototyping: Practical exercises in creating prototypes using prototyping software, mockups and wireframes.\n- Iteration and Validation: Methods for quickly iterating prototypes based on feedback and validation of design ideas and requirements.\n\n--- Contents (DE) ---\n- Konzeption und Umsetzung von prototypischen Arbeiten aus dem Bereich der Medientechnik \n- Einf\u00fchrung in das Rapid System Prototyping: Konzepte, Ziele und Anwendungen. \n- Prototyping-Tools und -Methoden: Verf\u00fcgbare Tools und Auswahl geeigneter Methoden f\u00fcr verschiedene Anwendungsf\u00e4lle z.B. 3D-Modellierung, Umsetzung mittels CAM-Verfahren (3D-Druck, CNC Fr\u00e4sen, Lasern) \n- Entwicklung von Schaltpl\u00e4nen und Design von Leiterplatten \n- Erstellung von Prototypen: Praktische \u00dcbungen zur Erstellung von Prototypen unter Verwendung von Prototyping-Software, Mockups und Wireframes. \n- Iteration und Validierung: Methoden zur schnellen Iteration von Prototypen basierend auf Feedback und Validierung von Designideen und Anforderungen.\n\n--- Literature (EN) ---\n- Alexander Pusch, Nils Haverkamp: \"3D-Druck f\u00fcr Schule und Hochschule\", Springer Spektrum\n- Jens Lienig, Juergen Scheible: \"Fundamentals of Layout Design for Electronic Circuits\", Springer Engineering\n- Ulrich Tietze, Christoph Schenk, Eberhard Gamm: \"Halbleiter-Schaltungstechnik\", Springer Vieweg\n\n--- Literature (DE) ---\n- Alexander Pusch, Nils Haverkamp: \"3D-Druck f\u00fcr Schule und Hochschule\", Springer Spektrum\n- Jens Lienig, Juergen Scheible: \"Fundamentals of Layout Design for Electronic Circuits\", Springer Engineering\n- Ulrich Tietze, Christoph Schenk, Eberhard Gamm: \"Halbleiter-Schaltungstechnik\", Springer Vieweg", "metadata": {"moduleNumber": "BMT W25", "moduleName": "Rapid System Prototyping", "creditPoints": "5.0", "suggestedSemester": 4, "offeredInSeason": "summer_semester", "examType": "oral_exam", "heldInLanguage": "de", "reviserName": "Dipl.-Ing. M.Sc. Christian Epe", "reviserEmail": "christian.epe@hs-duesseldorf.de", "studyProgramId": 9, "source_type": "json"}}
