{"id": "MAR_01", "text": "Title: Theoretical Basic Module 1\nModule Number: MAR 01\nCredits: 5.0 CP\nSemester: 1\nOffered In: winter_semester\nLanguage: de\nExam Type: none\nInstructor: None Margareta Urbaniak\n\n--- Goals (EN) ---\nSVE: Students deepen their understanding of theoretical sound field properties.\nThey can independently analyse and calculate complex acoustic problems.\nThey know methods for noise reduction and evaluate acoustic influencing factors.\nThey develop well-founded solutions for optimising technical systems with regard to sound quality.\n\nHTI: Students systematically identify user needs and apply design principles. They are able to analyse and design interactive systems and user interfaces. They select suitable evaluation methods and assess design solutions in terms of usability and user experience.\n\nApDS: Students analyse complex data sets. They apply methods for data cleansing and visualisation. They implement classic ML models and basic deep learning architectures.\n\n--- Goals (DE) ---\nSVE: Die Studierenden vertiefen ihr Verständnis der theoretischen Schallfeld-Eigenschaften. Sie können komplexe akustische Probleme selbstständig analysieren und berechnen. Sie kennen Verfahren zur Lärmminderung und bewerten akustische Einflussfaktoren. Sie entwickeln fundierte Lösungen zur Optimierung technischer Systeme im Hinblick auf Klangqualität.\n\nHTI: Die Studierenden erfassen Benutzerbedürfnisse systematisch und wenden Designprinzipien an. Sie sind in der Lage, interaktive Systeme und Benutzeroberflächen zu analysieren und zu gestalten. Sie wählen geeignete Evaluationsmethoden aus und bewerten Designlösungen hinsichtlich Usability und User Experience.\n\nApDS: Die Studierenden analysieren komplexe Datensätze. Sie wenden Verfahren zur Datenbereinigung und -visualisierung an. Sie setzen klassische ML-Modelle sowie grundlegende Deep-Learning-Architekturen um.\n\n--- Contents (EN) ---\nThe basic theory module provides theoretical foundations for the following three specialisations:\n\nSVE: Mathematical modelling of acoustic systems\nMethods for noise reduction and noise mitigation\n\nHTI: Usability principles and design heuristics\nMethods of analysing user requirements\n\nApDS: Graph-based and unstructured data analyses\nData cleansing and analysis\n\n--- Contents (DE) ---\nDas theoretische Basismodul bietet theoretische Grundlagen zu folgenden drei Vertiefungsrichtungen:\n\nSVE: Mathematische Modellierung akustischer Systeme\nVerfahren zur Schallreduktion und Lärmminderung\n\nHTI: Usability-Prinzipien und Designheuristiken\nMethoden der Benutzeranforderungsanalyse\n\nApDS: Graphbasierte und unstrukturierte Datenanalysen\nDatenbereinigung und -analyse\n\n--- Literature (EN) ---\n\n\n--- Literature (DE) ---", "metadata": {"moduleNumber": "MAR 01", "moduleName": "Theoretical Basic Module 1", "creditPoints": "5.0", "suggestedSemester": 1, "offeredInSeason": "winter_semester", "examType": "none", "heldInLanguage": "de", "reviserName": "None Margareta Urbaniak", "reviserEmail": "margareta.urbaniak@hs-duesseldorf.de", "studyProgramId": 13, "source_type": "json"}}
{"id": "MAR_02", "text": "Title: Theoretical Basic Module 2\nModule Number: MAR 02\nCredits: 5.0 CP\nSemester: 2\nOffered In: winter_semester\nLanguage: de\nExam Type: written_exam\nInstructor: None Margareta Urbaniak\n\n--- Goals (EN) ---\nSVE: Students apply advanced methods of digital audio signal processing and flow acoustics to complex acoustic scenarios. They are able to measure and analyse complex vibration and noise problems from an engineering perspective.\n\nApDS: You will develop intelligent systems using modern AI methods, e.g. for language processing, image classification or robotics. You will design scalable software solutions for data-driven problem solving and use interactive visualisation methods.\n\n--- Goals (DE) ---\nSVE: Die Studierenden wenden fortgeschrittene Methoden der digitalen Audiosignalverarbeitung und Strömungsakustik auf komplexe akustische Szenarien an. Sie sind in der Lage, komplexe Schwingungs- und Geräuschprobleme messtechnisch zu erfassen und ingenieurwissenschaftlich zu bewerten.\n\nHTI: Die Studierenden vertiefen nutzerzentrierte Methoden zur Gestaltung interaktiver Systeme und bewerten diese hinsichtlich User Experience und Funktionalität. Sie integrieren psychologische und technische Aspekte in kreative Designprozesse und reflektieren deren Wirkung auf Nutzer:innen.\n\nApDS: Sie entwickeln intelligente Systeme unter Einsatz moderner KI-Methoden, z.B. für Sprachverarbeitung, Bildklassifikation oder Robotik. Sie entwerfen skalierbare Softwarelösungen zur datengetriebenen Problemlösung und nutzen Methoden der interaktiven Visualisierung.\n\n--- Contents (EN) ---\nSVE: Digital audio signal processing and flow acoustics\nComputer-based measurement technology and vibration technology\n\nHTI: Advanced User Interfaces und Usability Engineering\nDesign Thinking und kreative Problemlösungsmethoden\n\nApDS: Advanced methods of pattern recognition and classification\nDevelopment of intelligent systems for data processing\n\n--- Contents (DE) ---\nSVE: Digitale Audiosignalverarbeitung und Strömungsakustik\nComputerbasierte Messtechnik und Schwingungstechnik\n\nHTI: Advanced User Interfaces und Usability Engineering\nDesign Thinking und kreative Problemlösungsmethoden\n\nApDS: Fortgeschrittene Verfahren der Mustererkennung und Klassifikation\nEntwicklung intelligenter Systeme zur Datenverarbeitung\n\n--- Literature (EN) ---\n\n\n--- Literature (DE) ---", "metadata": {"moduleNumber": "MAR 02", "moduleName": "Theoretical Basic Module 2", "creditPoints": "5.0", "suggestedSemester": 2, "offeredInSeason": "winter_semester", "examType": "written_exam", "heldInLanguage": "de", "reviserName": "None Margareta Urbaniak", "reviserEmail": "margareta.urbaniak@hs-duesseldorf.de", "studyProgramId": 13, "source_type": "json"}}
{"id": "MAR_03", "text": "Title: Scientific Methods\nModule Number: MAR 03\nCredits: 5.0 CP\nSemester: 1\nOffered In: winter_semester\nLanguage: de\nExam Type: research_paper\nInstructor: None Margareta Urbaniak\n\n--- Goals (EN) ---\nThe students are familiar with quality criteria, rules and standards of good scientific practice. They have the ability to independently organize and produce scientific publications as well as to present new research aspects and solutions in German and English. The students know the procedures for quality assurance in science and research and are sensitized to forms of scientific misconduct. They are able to evaluate political, social, and ethical responsibilities and implications of science and to integrate them in their work. For future executive activities in research and development, students are given an overview of the diverse ways in which research and work unfold in different disciplines. In the comparative study, students learn about and apply approaches from science and technology, design sciences as well as social and economic sciences. Students are knowledgeable about epistemological differences in these disciplines. They can name the differences, possibilities and requirements in both experimental and technical as well as literary analysis procedures. The students are in a position to go beyond the engineering-scientific point of view, to follow the path of the researcher gaining knowledge in different disciplines and to make a well-founded choice of methods for their own research projects, including interdisciplinary research.\n\n--- Goals (DE) ---\nDie Studierenden sind mit den Qualitätskriterien, Regeln und Standards guter wissenschaftlicher Praxis vertraut. Sie können wissenschaftliche Publikationen selbstständig organisieren und erstellen sowie neue Forschungsaspekte und Lösungen in deutscher und englischer Sprache präsentieren. Sie kennen die Verfahren zur Qualitätssicherung in Wissenschaft und Forschung und sind für Formen wissenschaftlichen Fehlverhaltens sensibilisiert. Sie können politische, gesellschaftliche und ethische Verantwortung und Implikationen der Wissenschaft bewerten und in ihre Arbeit integrieren. Für künftige leitende Tätigkeiten in Forschung und Entwicklung erhalten sie einen Überblick über die vielfältigen Forschungs- und Arbeitsweisen in unterschiedlichen Disziplinen. Im vergleichenden Studium lernen sie Ansätze aus den Natur- und Technikwissenschaften, den Designwissenschaften sowie den Sozial- und Wirtschaftswissenschaften kennen und anzuwenden. Sie kennen die erkenntnistheoretischen Unterschiede in diesen Disziplinen. Sie können die Unterschiede, Möglichkeiten und Erfordernisse sowohl bei experimentellen und technischen als auch bei literarischen Analyseverfahren benennen. Sie sind in der Lage, den Weg des Erkenntnisgewinns des Forschers in verschiedenen Disziplinen nachzuvollziehen und über die ingenieurwissenschaftliche Sichtweise hinaus eine fundierte Methodenwahl für eigene, auch interdisziplinäre Forschungsvorhaben zu treffen.\n\n--- Contents (EN) ---\nScientific practice \nScientific work\nInterdisciplinarity in research and research-orientated sciences\nMethodological expertise for interdisciplinary research projects\n\n--- Contents (DE) ---\nWissenschaftliche Praxis \nWissenschaftliches Arbeiten\nInterdisziplinarität in Forschung und forschugsorientierten Wissenschaften \nMethodenkompetenz für interdisziplinäre Forschungsvorhaben\n\n--- Literature (EN) ---\n\n\n--- Literature (DE) ---", "metadata": {"moduleNumber": "MAR 03", "moduleName": "Scientific Methods", "creditPoints": "5.0", "suggestedSemester": 1, "offeredInSeason": "winter_semester", "examType": "research_paper", "heldInLanguage": "de", "reviserName": "None Margareta Urbaniak", "reviserEmail": "margareta.urbaniak@hs-duesseldorf.de", "studyProgramId": 13, "source_type": "json"}}
{"id": "MAR_04", "text": "Title: Empirical Methods\nModule Number: MAR 04\nCredits: 5.0 CP\nSemester: 2\nOffered In: summer_semester\nLanguage: de\nExam Type: research_paper\nInstructor: None Jörg Becker-Schweitzer\n\n--- Goals (EN) ---\nStudents know the theoretical embedding of empirical research and recognize the importance, possibilities, and limitations of quantitative and qualitative empirical research. They are capable of choosing appropriate quantitative or qualitative methods based on their research questions. They understand that scientific knowledge gained in the empirical sciences is based on the systematic collection, preparation, and analysis of empirical data. By means of the profound knowledge of methods of investigation planning, sample tracking, data collection, data processing and data analysis, the students are enabled to develop create a research design that meets the prevailing quality criteria. The students are capable to analyze their data with the help of software; statistical data using one-dimensional and two-dimensional methods as well as multivariate methods and qualitative data using content analysis methods. The students are able to use and develop scientific theories on the research subject as well as on the research methodology during the course of the research process. Within the framework of a written documentation, the students are finally able to create a study set-up and choose a method, and compile finding appropriately to the scientific interests and the interests of the target group.\n\n--- Goals (DE) ---\nDie Studierenden kennen die theoretische Einbettung empirischer Forschung und sind sich der Bedeutung, Möglichkeiten und Grenzen quantitativer und qualitativer Forschung bewusst. Auf der Grundlage ihrer Forschungsfragen können sie geeignete quantitative oder qualitative Methoden auswählen. Ihnen ist bewusst, dass wissenschaftliche Erkenntnisse in den empirischen Wissenschaften auf der systematischen Erhebung, Aufbereitung und Analyse von empirischen Daten beruhen. Durch die vertiefte Kenntnis von Methoden der Untersuchungsplanung, der Stichprobenziehung, der Datenerhebung, der Datenaufbereitung und der Datenanalyse sind die Studierenden in der Lage, ein Forschungsdesign zu entwickeln, das den vorherrschenden Qualitätskriterien entspricht. Sie können ihre Daten mithilfe von Software analysieren: statistische Daten mit ein- und zweidimensionalen sowie multivariaten Methoden und qualitative Daten mit inhaltsanalytischen Methoden. Sie können wissenschaftliche Theorien zum Forschungsgegenstand sowie zur Forschungsmethodik im Verlauf des Forschungsprozesses anwenden und weiterentwickeln. Im Rahmen einer schriftlichen Dokumentation erstellen sie schließlich einen Studienaufbau, wählen eine Methode aus und stellen die Ergebnisse entsprechend den wissenschaftlichen Interessen und den Interessen der Zielgruppe zusammen.\n\n--- Contents (EN) ---\nScientific theories incl. quantitative and qualitative research\nClassification of empirical research into the theory of science\nQuality criteria in empirical research\nResearch planning and study design\nOperationalization in quantitative studies\nRecruitment and data collection procedures\nData processing and data analysis using either qualitative or quantitative methods\nDocumentation of the research results\n\n--- Contents (DE) ---\nWissenschaftstheorien inkl. quantitativer und qualitativer Forschung\nEinordnung empirischer Forschung in die Wissenschaftstheorie\nQualitätskriterien in der empirischen Forschung\nForschungsplanung und Studiendesign\nOperationalisierung in quantitativen Studien\nRekrutierungs- und Erhebungsverfahren\nDatenaufbereitung und Datenanalyse mit qualitativen oder quantitativen Methoden\nDokumentation der Forschungsergebnisse\n\n--- Literature (EN) ---\nSchreier, M. (2012). Qualitative content analysis in practice. Sage publications.\n\n--- Literature (DE) ---\nSchreier, M. (2012). Qualitative content analysis in practice. Sage publications", "metadata": {"moduleNumber": "MAR 04", "moduleName": "Empirical Methods", "creditPoints": "5.0", "suggestedSemester": 2, "offeredInSeason": "summer_semester", "examType": "research_paper", "heldInLanguage": "de", "reviserName": "None Jörg Becker-Schweitzer", "reviserEmail": "jbs@hs-duesseldorf.de", "studyProgramId": 13, "source_type": "json"}}
{"id": "MAR_05", "text": "Title: Basic Research Project\nModule Number: MAR 05\nCredits: 10.0 CP\nSemester: 1\nOffered In: every_semester\nLanguage: de\nExam Type: research_paper\nInstructor: \n\n--- Goals (EN) ---\nThe students are able to work on a scientific topic and independently derive further research objectives, develop time and work plans, and work independently. They are able to present their results in a scientific maner in word and in speech. They are able to compare their work and results to related work.\n\n--- Goals (DE) ---\nDie Studierenden können ein wissenschaftliches Thema bearbeiten, selbstständig weitere Forschungsziele ableiten, Zeit- und Arbeitspläne erstellen und eigenständig arbeiten. Sie können ihre Ergebnisse wissenschaftlich fundiert in Wort und Schrift präsentieren. Zudem können sie ihre Arbeit und Ergebnisse mit verwandten Arbeiten vergleichen.\n\n--- Contents (EN) ---\nResearch topics result from the individual research problem - ROS\n\n--- Contents (DE) ---\nForschungsthemen ergeben sich aus dem individuellen Forschungsproblem - ROS\n\n--- Literature (EN) ---\n\n\n--- Literature (DE) ---", "metadata": {"moduleNumber": "MAR 05", "moduleName": "Basic Research Project", "creditPoints": "10.0", "suggestedSemester": 1, "offeredInSeason": "every_semester", "examType": "research_paper", "heldInLanguage": "de", "reviserName": "", "reviserEmail": null, "studyProgramId": 13, "source_type": "json"}}
{"id": "MAR_06", "text": "Title: Interdisciplinary Research Project\nModule Number: MAR 06\nCredits: 10.0 CP\nSemester: 1\nOffered In: every_semester\nLanguage: de\nExam Type: research_paper\nInstructor: \n\n--- Goals (EN) ---\nThe students are able to work on a scientific topic of interdisciplinary relevance and independently derive further research objectives, develop time and work plans, and work independently. They are able to present their results in a scientific maner in word and in speech. They are able to compare their work and results to related work.\n\n--- Goals (DE) ---\nDie Studierenden sind in der Lage, ein wissenschaftliches Thema von interdisziplinärer Relevanz zu bearbeiten und selbständig weitere Forschungsziele abzuleiten, Zeit- und Arbeitspläne zu entwickeln und selbständig zu arbeiten. Sie sind in der Lage, ihre Ergebnisse wissenschaftlich fundiert in Wort und Schrift zu präsentieren. Sie sind in der Lage, ihre Arbeiten und Ergebnisse mit verwandten Arbeiten zu vergleichen.\n\n--- Contents (EN) ---\nResearch topics result from the individual research problem - ROS\n\n--- Contents (DE) ---\nForschungsthemen ergeben sich aus dem individuellen Forschungsproblem - ROS\n\n--- Literature (EN) ---\n\n\n--- Literature (DE) ---", "metadata": {"moduleNumber": "MAR 06", "moduleName": "Interdisciplinary Research Project", "creditPoints": "10.0", "suggestedSemester": 1, "offeredInSeason": "every_semester", "examType": "research_paper", "heldInLanguage": "de", "reviserName": "", "reviserEmail": null, "studyProgramId": 13, "source_type": "json"}}
{"id": "MAR_07", "text": "Title: Advanced Research Project\nModule Number: MAR 07\nCredits: 20.0 CP\nSemester: 2\nOffered In: every_semester\nLanguage: de\nExam Type: research_paper\nInstructor: \n\n--- Goals (EN) ---\nThe students are able to work on an advanced scientific topic and independently derive further research objectives, develop time and work plans, and work independently. They are able to present their results in a scientific manner in word and in speech. They are able to compare their work and results to related work.\n\n--- Goals (DE) ---\nDie Studierenden können ein fortgeschrittenes wissenschaftliches Thema bearbeiten, selbstständig weitere Forschungsziele ableiten und Zeit- und Arbeitspläne erstellen. Sie können ihre Ergebnisse wissenschaftlich fundiert in Wort und Schrift präsentieren. Zudem können sie ihre Arbeiten und Ergebnisse mit verwandten Arbeiten vergleichen.\n\n--- Contents (EN) ---\nResearch topics result from the individual research problem - ROS\n\n--- Contents (DE) ---\nDie Forschungsthemen ergeben sich aus dem individuellen Forschungsproblem - ROS\n\n--- Literature (EN) ---\n\n\n--- Literature (DE) ---", "metadata": {"moduleNumber": "MAR 07", "moduleName": "Advanced Research Project", "creditPoints": "20.0", "suggestedSemester": 2, "offeredInSeason": "every_semester", "examType": "research_paper", "heldInLanguage": "de", "reviserName": "", "reviserEmail": null, "studyProgramId": 13, "source_type": "json"}}
{"id": "MAR_08", "text": "Title: Master Thesis\nModule Number: MAR 08\nCredits: 30.0 CP\nSemester: 3\nOffered In: every_semester\nLanguage: de\nExam Type: master_thesis_and_colloquium\nInstructor: \n\n--- Goals (EN) ---\nThe students are able to work on a scientific topic and independently derive further research objectives, develop time and work plans, and work independently. They are able to present their results in a scientific manner in word and in speech. They are able to compare their work and results to related work.\n\n--- Goals (DE) ---\nDie Studierenden können ein wissenschaftliches Thema bearbeiten, selbstständig weitere Forschungsziele ableiten und Zeit- sowie Arbeitspläne erstellen. Sie können ihre Ergebnisse wissenschaftlich fundiert in Wort und Schrift präsentieren. Zudem können sie ihre Arbeiten und Ergebnisse mit verwandten Arbeiten vergleichen.\n\n--- Contents (EN) ---\nStudents select topics relevant to their research specialisation (SVE, HTI o. ADS). Ideally, they expand on the research questions posed in the scientific projects or the basic theory module.\n\n--- Contents (DE) ---\nDie Studierenden wählen relevante Themen zu ihrem Forschungsschwerpunkt (SVE, HTI o. ADS) aus. Idealerweise erweitern sie dabei die Forschungsfragen, die in den wissenschaftlichen Projekten oder dem theoretischen Basismodul gestellt wurden.\n\n--- Literature (EN) ---\n\n\n--- Literature (DE) ---", "metadata": {"moduleNumber": "MAR 08", "moduleName": "Master Thesis", "creditPoints": "30.0", "suggestedSemester": 3, "offeredInSeason": "every_semester", "examType": "master_thesis_and_colloquium", "heldInLanguage": "de", "reviserName": "", "reviserEmail": null, "studyProgramId": 13, "source_type": "json"}}
{"id": "MAR_01.TB001", "text": "Title: Theoretical Acoustics 1\nModule Number: MAR 01.TB001\nCredits: 5.0 CP\nSemester: 1\nOffered In: winter_semester\nLanguage: de\nExam Type: written_exam\nInstructor: None Jörg Becker-Schweitzer\n\n--- Goals (EN) ---\nThey gain a deeper understanding of the theoretical relationships of multi-dimensional sound field properties and the ability to methodically solve corresponding problems,\nThey can independently analyse and calculate complex tasks that go beyond practical engineering work, but are essential for a scientific examination of acoustic problems\n\n--- Goals (DE) ---\nSie erwerben ein vertieftes Verständnis für die theoretischen Zusammenhänge mehrdimensionaler Schallfeldeigenschaften und die Fähigkeit, entsprechende Probleme methodisch zu lösen,\nSie können komplexe Aufgabenstellungen, die über die praktische Ingenieurarbeit hinausgehen, aber für eine wissenschaftliche Auseinandersetzung mit akustischen Problemen unerlässlich sind, selbständig analysieren und berechnen\n\n--- Contents (EN) ---\nLecture series with theoretical teaching content from\nIndustrial Sound Design, Audio/Video Coding, Electroacoustics\nMusical Acoustics, Room and Building Acoustics.\n\n--- Contents (DE) ---\nVortragsreihe mit theoretischen Lehrinhalten aus\nIndustrial Sound Design, Audio/Video Coding, Elektroakustik\nMusikalische Akustik, Raum- und Bauakustik.\n\n--- Literature (EN) ---\n\n\n--- Literature (DE) ---", "metadata": {"moduleNumber": "MAR 01.TB001", "moduleName": "Theoretical Acoustics 1", "creditPoints": "5.0", "suggestedSemester": 1, "offeredInSeason": "winter_semester", "examType": "written_exam", "heldInLanguage": "de", "reviserName": "None Jörg Becker-Schweitzer", "reviserEmail": "jbs@hs-duesseldorf.de", "studyProgramId": 13, "source_type": "json"}}
{"id": "MAR_02.TB001", "text": "Title: Theoretical Acoustics 2\nModule Number: MAR 02.TB001\nCredits: 5.0 CP\nSemester: 2\nOffered In: summer_semester\nLanguage: de\nExam Type: written_exam\nInstructor: None Jörg Becker-Schweitzer\n\n--- Goals (EN) ---\nStudents apply advanced methods of digital audio signal processing and flow acoustics to complex acoustic scenarios. They are able to measure and analyse complex vibration and noise problems from an engineering point of view.\n\n--- Goals (DE) ---\nDie Studierenden wenden fortgeschrittene Methoden der digitalen Audiosignalverarbeitung und Strömungsakustik auf komplexe akustische Szenarien an. Sie sind in der Lage, komplexe Schwingungs- und Geräuschprobleme messtechnisch zu erfassen und ingenieurwissenschaftlich zu bewerten.\n\n--- Contents (EN) ---\nDigital audio signal processing and flow acoustics\nComputer-based measurement technology and vibration technology\n\n--- Contents (DE) ---\nDigitale Audiosignalverarbeitung und Strömungsakustik\nComputerbasierte Messtechnik und Schwingungstechnik\n\n--- Literature (EN) ---\n\n\n--- Literature (DE) ---", "metadata": {"moduleNumber": "MAR 02.TB001", "moduleName": "Theoretical Acoustics 2", "creditPoints": "5.0", "suggestedSemester": 2, "offeredInSeason": "summer_semester", "examType": "written_exam", "heldInLanguage": "de", "reviserName": "None Jörg Becker-Schweitzer", "reviserEmail": "jbs@hs-duesseldorf.de", "studyProgramId": 13, "source_type": "json"}}
{"id": "MAR_01.TB002", "text": "Title: Human Technology Interaction 1\nModule Number: MAR 01.TB002\nCredits: 5.0 CP\nSemester: 1\nOffered In: winter_semester\nLanguage: de\nExam Type: oral_exam\nInstructor: Prof. Dr. Alina Huldtgren\n\n--- Goals (EN) ---\nStudents know the fundamentals of Interaction Design, Human-Computer Interaction Models, Theories of Design, and Software Ergonomics / Usa-bility.\nThey acquire the competence to design interactive systems systematically, i.e. they will be able to research user contexts and needs, define re-quirements and apply core interaction design principles to real-world prob-lems following an iterative process and employing human-centered and interaction design methods. \nThey are capable of analyzing and evaluating user interfaces using ap-propriate methods as well as sketching own designs of user interfaces for various technologies, users, and use contexts. They will be able to choose either quantitative or qualitative evaluation methods (incl. experiments, survey, interviews, usability studies) based on the research question\n\n--- Goals (DE) ---\nDie Studierenden kennen die Grundlagen des Interaktionsdesigns, Modelle der Mensch-Computer-Interaktion, Theorien der Gestaltung und Software-Ergonomie / Usability.\nSie erwerben die Kompetenz, interaktive Systeme systematisch zu gestalten, d.h. sie sind in der Lage, Benutzerkontexte und -bedürfnisse zu erforschen, Anforderungen zu definieren und Kernprinzipien des Interaktionsdesigns in einem iterativen Prozess auf reale Problemstellungen anzuwenden und dabei Methoden des Human-Centered und Interaction Design einzusetzen. \nSie sind in der Lage, Benutzerschnittstellen mit geeigneten Methoden zu analysieren und zu evaluieren sowie eigene Entwürfe von Benutzerschnittstellen für verschiedene Technologien, Nutzer und Nutzungskontexte zu entwerfen. Sie sind in der Lage, je nach Fragestellung quantitative oder qualitative Evaluationsmethoden (u.a. Experimente, Befragungen, Interviews, Usability-Studien) zu wählen.\n\n--- Contents (EN) ---\nFundamentals in Human Information Processing: Perception, Cognition and Motorics and resulting Design Principles\nTheories, Models, and Paradigms in Human-Computer Interaction Re-search\nTheories of Designing in HTI, e.g. Distributed Cognition, Activity Theory\nOverview of Technologies (introduction to natural user interfaces, VR, AR) and Types of Interaction \nFundamentals of software ergonomics, usability, accessibility\nUser-Centered Design Processes incl. Methods for elicitating requirements and analyzing, testing and evaluating user interfaces (qualitative and quantitative)\n\n--- Contents (DE) ---\nGrundlagen der menschlichen Informationsverarbeitung: Wahrnehmung, Kognition und Motorik und daraus resultierende Gestaltungsprinzipien\nTheorien, Modelle und Paradigmen in der Mensch-Computer-Interaktion-Forschung\nTheorien der Gestaltung in HTI, z.B. Verteilte Kognition, Aktivitätstheorie\nÜberblick über Technologien (Einführung in natürliche Benutzerschnittstellen, VR, AR) und Interaktionstypen\nGrundlagen der Software-Ergonomie, Usability, Barrierefreiheit\nNutzerzentrierte Designprozesse inkl. Methoden zur Erhebung von Anforderungen und zur Analyse, Prüfung und Bewertung von Benutzerschnittstellen (qualitativ und quantitativ)\n\n--- Literature (EN) ---\nNorman, D. (2013). The design of everyday things: Revised and expand-ed edition. Basic books.\nJohnson, J. (2013). Designing with the mind in mind: simple guide to un-derstanding user interface design guidelines. Elsevier. \nLazar, J., Feng, J. H., & Hochheiser, H. (2017). Research methods in hu-man-computer interaction. Morgan Kaufmann. \nAndy Pratt, Jason Nunes. Interactive Design: An Introduction to the Theory and Application of User-centered Design. Rockport Publishers, 2012.  Guy Boy. Orchestrating Human-Centered Desig. Springer, 2013\n\n--- Literature (DE) ---\nNorman, D. (2013). The design of everyday things: Revised and expand-ed edition. Basic books.\nJohnson, J. (2013). Designing with the mind in mind: simple guide to un-derstanding user interface design guidelines. Elsevier. \nLazar, J., Feng, J. H., & Hochheiser, H. (2017). Research methods in hu-man-computer interaction. Morgan Kaufmann. \nAndy Pratt, Jason Nunes. Interactive Design: An Introduction to the Theory and Application of User-centered Design. Rockport Publishers, 2012.  Guy Boy. Orchestrating Human-Centered Desig. Springer, 2013", "metadata": {"moduleNumber": "MAR 01.TB002", "moduleName": "Human Technology Interaction 1", "creditPoints": "5.0", "suggestedSemester": 1, "offeredInSeason": "winter_semester", "examType": "oral_exam", "heldInLanguage": "de", "reviserName": "Prof. Dr. Alina Huldtgren", "reviserEmail": "alina.huldtgren@hs-duesseldorf.de", "studyProgramId": 13, "source_type": "json"}}
{"id": "MAR_02.TB002", "text": "Title: Human Technology Interaction 2\nModule Number: MAR 02.TB002\nCredits: 5.0 CP\nSemester: 2\nOffered In: winter_semester\nLanguage: de\nExam Type: research_paper\nInstructor: Prof. Dr. Alina Huldtgren\n\n--- Goals (EN) ---\nStudents know about the historic development and the various goals of specific design methods that go beyond UCD, e.g. Experience Design, Participatory Design, or Value Sensitive Design. They are able to pick relevant design methods for given design contexts. They know a range of advanced user interface technologies and specific application areas and users with special needs. They are capable of assessing design solutions in a specific context according to the usability and user experience and critically reflect on recent developments within HTI research with regards to its ethical and social implications.\n\n--- Goals (DE) ---\nDie Studierenden kennen die historische Entwicklung und die verschiedenen Ziele spezifischer Designmethoden, die über UCD hinausgehen, z.B. Experience Design, Participatory Design oder Value Sensitive Design. Sie sind in der Lage, relevante Designmethoden für gegebene Designkontexte auszuwählen. Sie kennen eine Reihe von fortschrittlichen User-Interface-Technologien sowie spezifische Anwendungsbereiche und Nutzer mit besonderen Bedürfnissen. Sie sind in der Lage, Designlösungen in einem bestimmten Kontext nach der Usability und User Experience zu beurteilen und aktuelle Entwicklungen in der HTI-Forschung hinsichtlich ihrer ethischen und sozialen Implikationen kritisch zu reflektieren.\n\n--- Contents (EN) ---\nAdvanced User-Centred Design Methods, e.g. UX and Experience Design, Participatory Design, Co-Design, Value-Sensitive Design\nIntroduction to advanced User Interfaces, e.g. VR, AR, Tangible UIs, Intelligent User Interfaces\nDesigning for specific human capabilities, e.g. design for people with psychological, cognitive or motorical handicaps, blind people etc. \nSpecific application areas, e.g. musical interfaces, exergames, computer-supported cooperative work / learning (cscw, cscl)  \nCritical Assessment of HTI, e.g. ethical, social implications, design noir, speculative design\n\n--- Contents (DE) ---\nFortgeschrittene nutzerzentrierte Designmethoden, z.B. UX und Experience Design, Participatory Design, Co-Design, Value-Sensitive Design\nEinführung in fortgeschrittene User Interfaces, z.B. VR, AR, Tangible UIs, Intelligent User Interfaces\nDesign für spezifische menschliche Fähigkeiten, z.B. Design für Menschen mit psychischen, kognitiven oder motorischen Behinderungen, Blinde etc. \nSpezifische Anwendungsbereiche, z. B. musikalische Schnittstellen, Exergames, computergestütztes kooperatives Arbeiten/Lernen (cscw, cscl) \nKritische Bewertung von HTI, z. B. ethische, soziale Auswirkungen, Design Noir, spekulatives Design\n\n--- Literature (EN) ---\nHassenzahl, M. (2010). Experience design: Technology for all the right reasons. Synthesis lectures on human-centered informatics, 3(1), 1-95. \nKuniavsky, M. (2003). Observing the user experience: a practitioner's guide to user research. Elsevier. \nWigdor, Dennis Wixon Daniel. Brave NUI World: Designing Natural User Interfaces for Touch and Gesture. Morgan Kaufmann, 2011. \nDunne, A. and Raby, R. (2002): Design Noir: The Secret Life of Electronic Objects. \nKortum, Philip. HCI Beyond the GUI: Design for Haptic, Speech, Olfactory, and Other Nontraditional Interfaces. Morgan Kaufmann, 2008. \nCapita selecta (recent conference publications)\n\n--- Literature (DE) ---\nHassenzahl, M. (2010). Experience design: Technology for all the right reasons. Synthesis lectures on human-centered informatics, 3(1), 1-95. \nKuniavsky, M. (2003). Observing the user experience: a practitioner's guide to user research. Elsevier. \nWigdor, Dennis Wixon Daniel. Brave NUI World: Designing Natural User Interfaces for Touch and Gesture. Morgan Kaufmann, 2011. \nDunne, A. and Raby, R. (2002): Design Noir: The Secret Life of Electronic Objects. \nKortum, Philip. HCI Beyond the GUI: Design for Haptic, Speech, Olfactory, and Other Nontraditional Interfaces. Morgan Kaufmann, 2008. \nCapita selecta (recent conference publications)", "metadata": {"moduleNumber": "MAR 02.TB002", "moduleName": "Human Technology Interaction 2", "creditPoints": "5.0", "suggestedSemester": 2, "offeredInSeason": "winter_semester", "examType": "research_paper", "heldInLanguage": "de", "reviserName": "Prof. Dr. Alina Huldtgren", "reviserEmail": "alina.huldtgren@hs-duesseldorf.de", "studyProgramId": 13, "source_type": "json"}}
{"id": "MAR_01.TB003", "text": "Title: Applied Data Science 1\nModule Number: MAR 01.TB003\nCredits: 5.0 CP\nSemester: 1\nOffered In: winter_semester\nLanguage: de\nExam Type: oral_exam\nInstructor: Prof. Dr.-Ing. M.Sc. Markus Dahm\n\n--- Goals (EN) ---\nStudents learn how to extract and interpret information from complex datasets using Data Science methods. This includes that students can explain a typical Data Science workflow. They are able to identify key steps based on a posed problem or question which includes identifying data requirements and suitable analysis tools and algorithms. Students can apply fundamental techniques in Python to clean and analyse datasets of various datatypes (including tabular data, time series, text). They will be able to interpret the generated results and are able to critically assess the data and its origin as well as the final conclusions. Students can build basic data visualizations to communicate the outcomes and have learned to present and discuss their results in front of a group. This includes giving constructive feedback and organizing projects in a team.\n\n--- Goals (DE) ---\nDie Studierenden lernen, wie sie mithilfe von Data-Science-Methoden Informationen aus komplexen Datensätzen extrahieren und interpretieren können. Dazu gehört, dass die Studierenden einen typischen Data-Science-Workflow erklären können. Sie sind in der Lage, ausgehend von einer Problem- oder Fragestellung die wichtigsten Schritte zu identifizieren, wozu auch die Ermittlung von Datenanforderungen und geeigneten Analysewerkzeugen und Algorithmen gehört. Die Studierenden können grundlegende Techniken in Python anwenden, um Datensätze verschiedener Datentypen (einschließlich Tabellendaten, Zeitreihen, Text) zu bereinigen und zu analysieren. Sie sind in der Lage, die generierten Ergebnisse zu interpretieren und können die Daten und ihre Herkunft sowie die endgültigen Schlussfolgerungen kritisch beurteilen. Die Schüler können grundlegende Datenvisualisierungen erstellen, um die Ergebnisse zu kommunizieren, und haben gelernt, ihre Ergebnisse vor einer Gruppe zu präsentieren und zu diskutieren. Dazu gehört auch, konstruktives Feedback zu geben und Projekte im Team zu organisieren.\n\n--- Contents (EN) ---\nPython crash course (or refresher, depending on prior experience)\nUsing Python and core libraries to build a Data Science workflow (importing, data cleaning, analysis tools, visualization)\nData Science (Datenimport, Datenerkundung, Analyse, Auswertung)\nHandling of frequently used data types and formats.\nBasics of knowledge generation process and applied examples to build an intuition for interpreting data (correlation, causation, logic, biases) \nStatistical and graphical data analysis\nCommon clustering algorithms (K-Means, DBSCAN)\nDimensionality reduction techniques (PCA, t-SNE)\nBasics of network analysis and graph theory\nUse of simpler machine-learning techniques for analysis and classification\nCritical assessment of possibilities and consequences of Data Science applications\n\n--- Contents (DE) ---\nPython-Crashkurs (oder Auffrischung, je nach Vorkenntnissen)\nVerwendung von Python und Kernbibliotheken zum Aufbau eines Data Science-Workflows (Import, Datenbereinigung, Analysetools, Visualisierung)\nData Science (Datenimport, Datenerkundung, Analyse, Auswertung)\nUmgang mit häufig verwendeten Datentypen und -formaten.\nGrundlagen der Wissensgenerierung und angewandte Beispiele zum Aufbau eines Gespürs für die Interpretation von Daten (Korrelation, Kausalität, Logik, Verzerrungen) \nStatistische und grafische Datenanalyse\nGängige Clustering-Algorithmen (K-Means, DBSCAN)\nTechniken zur Dimensionalitätsreduktion (PCA, t-SNE)\nGrundlagen der Netzwerkanalyse und Graphentheorie\nEinsatz von einfacheren Machine-Learning-Techniken zur Analyse und Klassifikation\nKritische Beurteilung von Möglichkeiten und Konsequenzen von Data Science-Anwendungen\n\n--- Literature (EN) ---\nJoel Grus, Data Science from Scratch: First Principles with Python, OReilly, 2nd edition, 2019.\nJake Vanderplas, Python Data Science Handbook, OReilly (2016). Free version:  https://jakevdp.github.io/PythonDataScienceHandbook/\nJohn D. Kelleher and Brendan Tierney, Data Science, MIT Press (2018)\nDavid Spiegelhalter, The Art of Statistics  Learning from Data, Pelican books (2019)\nAllen B. Downey, Think Stats: Exploratory Data Analysis in Python, Green Tea Press (2014). Free version:  https://greenteapress.com/wp/think-stats-2e/\n\n--- Literature (DE) ---\nJoel Grus, Data Science from Scratch: First Principles with Python, OReilly, 2nd edition, 2019.\nJake Vanderplas, Python Data Science Handbook, OReilly (2016). Free version:  https://jakevdp.github.io/PythonDataScienceHandbook/\nJohn D. Kelleher and Brendan Tierney, Data Science, MIT Press (2018)\nDavid Spiegelhalter, The Art of Statistics  Learning from Data, Pelican books (2019)\nAllen B. Downey, Think Stats: Exploratory Data Analysis in Python, Green Tea Press (2014). Free version:  https://greenteapress.com/wp/think-stats-2e/", "metadata": {"moduleNumber": "MAR 01.TB003", "moduleName": "Applied Data Science 1", "creditPoints": "5.0", "suggestedSemester": 1, "offeredInSeason": "winter_semester", "examType": "oral_exam", "heldInLanguage": "de", "reviserName": "Prof. Dr.-Ing. M.Sc. Markus Dahm", "reviserEmail": "markus.dahm@hs-duesseldorf.de", "studyProgramId": 13, "source_type": "json"}}
{"id": "MAR_02.TB003", "text": "Title: Applied Data Science 2\nModule Number: MAR 02.TB003\nCredits: 5.0 CP\nSemester: 2\nOffered In: winter_semester\nLanguage: de\nExam Type: oral_exam\nInstructor: Prof. Dr.-Ing. M.Sc. Markus Dahm\n\n--- Goals (EN) ---\nStudents will expand their knowledge and repertoire of modern Data Science approaches to handle large, complex datasets.\nThey will learn to implement classical machine-learning models to classify data or to make predictions. Students can explain the most common deep learning approaches and can name their strengths and limitations. They will be able to implement basic deep learning architectures in Python. Students can apply graph-based analysis methods and can handle and visualize large graph datasets. They are able to work with large unstructured datasets (e.g. audio, images, video) and can identify suitable approaches to represent those data (e.g. latent embeddings) or extract representative features\n\n--- Goals (DE) ---\nDie Studierenden erweitern ihre Kenntnisse und ihr Repertoire an modernen Data-Science-Ansätzen zum Umgang mit großen, komplexen Datensätzen.\nSie lernen, klassische Machine-Learning-Modelle zu implementieren, um Daten zu klassifizieren oder Vorhersagen zu treffen. Die Studierenden können die gängigsten Deep-Learning-Ansätze erklären und deren Stärken und Grenzen benennen. Sie sind in der Lage, grundlegende Deep-Learning-Architekturen in Python zu implementieren. Die Studierenden können graphenbasierte Analysemethoden anwenden und große Graphendatensätze verarbeiten und visualisieren. Sie sind in der Lage, mit großen unstrukturierten Datensätzen (z.B. Audio, Bilder, Video) zu arbeiten und können geeignete Ansätze identifizieren, um diese Daten zu repräsentieren (z.B. latente Einbettungen) oder repräsentative Merkmale zu extrahieren\n\n--- Contents (EN) ---\nMachine-learning and deep learning in data science\nIntroduction of latent space concept\nBasic introduction to NLP (topic modeling, transformer models)\nGraph theory and network analysis\nHandling of large scale, unstructured data (e.g. audio, images, video)\n\n--- Contents (DE) ---\nMaschinelles Lernen und Deep Learning in der Datenwissenschaft\nEinführung in das Konzept des latenten Raums\nGrundlegende Einführung in NLP (Themenmodellierung, Transformer-Modelle)\nGraphentheorie und Netzwerkanalyse\nUmgang mit großen, unstrukturierten Daten (z. B. Audio, Bilder, Video)\n\n--- Literature (EN) ---\n\n\n--- Literature (DE) ---", "metadata": {"moduleNumber": "MAR 02.TB003", "moduleName": "Applied Data Science 2", "creditPoints": "5.0", "suggestedSemester": 2, "offeredInSeason": "winter_semester", "examType": "oral_exam", "heldInLanguage": "de", "reviserName": "Prof. Dr.-Ing. M.Sc. Markus Dahm", "reviserEmail": "markus.dahm@hs-duesseldorf.de", "studyProgramId": 13, "source_type": "json"}}
