{"id": "MMI01", "text": "Title: Advanced Software Engineering\nModule Number: MMI 01\nCredits: 5.0 CP\nSemester: 2\nOffered In: summer_semester\nLanguage: de\nExam Type: written_exam\nInstructor: Prof. Dr. Thomas Franz (thomas.franz@hs-duesseldorf.de)\n--- Goals (EN) ---\nThe students know essential advanced methods, procedures and techniques of software engineering. They can distinguish, evaluate, select and apply them in a software development process.\n--- Goals (DE) ---\nDie Studierenden kennen wichtige fortgeschrittene Methoden, Vorgehensweisen und Techniken des Software Engineering. Sie k\u00f6nnen diese einordnen, bewerten und in einem Software-Entwicklungsprozess ausw\u00e4hlen und einsetzen.\n--- Contents (EN) ---\nSelected advanced methods, procedures and techniques of software engineering, e.g. Impact Mapping und Domain Storytelling for Requirements Engineering, Domain-Driven Design for Software Architectures, Clean Code for Software Development, scaled agile Methodologies, Cloud-Native Infrastructure.\n--- Contents (DE) ---\nAusgew\u00e4hlte fortgeschrittene Methoden, Vorgehensweisen und Techniken des Software Engineerings, z.B. Impact Mapping und Domain Storytelling f\u00fcr das Requirements Engineering, Domain-Driven Design f\u00fcr Software Architekturen, Clean Code Prinzipien der Softwareentwicklung, agile Vorgehensweisen und deren Skalierung, Cloud-Native Infrastrukturen.\n--- Literature (EN) ---\nS. Hofer, H. Schwentner: Domain Storytelling: Gemeinschaftlich, visuell und agil zu fachlich wertvoller Software, dpunkt.verlag, 2023\nE. Evans: Domain driven design: tackling complexity in the heart of software, Addison-Wesley, 2011\nR. C. Martin: Clean Code - Refactoring, Patterns, Testen und Techniken f\u00fcr sauberen Code, mitp (2009)\nC. Mathis: SAFe  Das Scaled Agile Framework: Lean und Agile in gro\u00dfen Unternehmen skalieren, dpunkt.verlag, 2017\nC. Surianarayanan, P. R. Chelliah: Essentials of Cloud Computing: A Holistic, Cloud-Native Perspective, Springer, 2023\n\nAdditionally, selected articles for specific topics.\n--- Literature (DE) ---\nS. Hofer, H. Schwentner: Domain Storytelling: Gemeinschaftlich, visuell und agil zu fachlich wertvoller Software, dpunkt.verlag, 2023\nE. Evans: Domain driven design: tackling complexity in the heart of software, Addison-Wesley, 2011\nR. C. Martin: Clean Code - Refactoring, Patterns, Testen und Techniken f\u00fcr sauberen Code, mitp (2009)\nC. Mathis: SAFe  Das Scaled Agile Framework: Lean und Agile in gro\u00dfen Unternehmen skalieren, dpunkt.verlag, 2017\nC. Surianarayanan, P. R. Chelliah: Essentials of Cloud Computing: A Holistic, Cloud-Native Perspective, Springer, 2023\n\nAusgew\u00e4hlte Artikel und Fachliteratur zu den jeweiligen Themen", "metadata": {"moduleNumber": "MMI 01", "moduleName": "Advanced Software Engineering", "creditPoints": "5.0", "suggestedSemester": 2, "offeredInSeason": "summer_semester", "examType": "written_exam", "heldInLanguage": "de", "reviserName": "Prof. Dr. Thomas Franz", "reviserEmail": "thomas.franz@hs-duesseldorf.de", "studyProgramId": 11, "source_type": "json"}}
{"id": "MMI02", "text": "Title: Computational Thinking\nModule Number: MMI 02\nCredits: 5.0 CP\nSemester: 1\nOffered In: winter_semester\nLanguage: de\nExam Type: written_exam\nInstructor: Prof. Dr. rer. nat. Christian Geiger (geiger@hs-duesseldorf.de)\n--- Goals (EN) ---\nStudents know and understand the various automata models and formal languages as well as the essential properties of formal systems. Students know and understand calculation models and complexity measures suitable for these models. They understand the problem of algorithmic solvability/non-solvability of problems. Students are able to independently analyze problems and estimate complexity and are familiar with the basic relationships between computability, decidability and complexity. They know the typical proof methods of mathematics and can apply these to simple problems in computer science. They have gained an insight into problem solving (puzzle-based problem solving) and can develop solutions for new problems using suitable strategies.\n--- Goals (DE) ---\nDie Studierenden kennen und verstehen die verschiedenen Automatenmodelle und formale Sprachen sowie wesentliche Eigenschaften formaler Systeme. Die Studierenden kennen und verstehen Berechnungsmodelle und zu diesen Modellen passende Komplexit\u00e4tsma\u00dfe. Sie verstehen die Problematik der algorithmischen L\u00f6sbarkeit/Nichtl\u00f6sbarkeit von Problemen. Die Studierenden sind in der Lage, eigenst\u00e4ndig Probleme zu analysieren und Komplexit\u00e4tsabsch\u00e4tzungen vorzunehmen und beherrschen die grundlegenden Zusammenh\u00e4nge zwichen Berechenbarkeit, Entscheidbarkeit und Komplexit\u00e4t. Sie kennen die typischen Beweisverfahren der Mathematik und k\u00f6nnen diese auf einfache Probleme der Informatik anwenden. Sie haben einen Einblick in das Probleml\u00f6sen erhalten (Puzzle Based Problem Solving) und k\u00f6nnen durch geeignete Strategien L\u00f6sungen f\u00fcr neue Probleme entwickeln.\n--- Contents (EN) ---\nPuzzle-Based Problem Solving (PBPS) and mathematical thinking: \nPBPS as an exploratory approach to strategic problem solving\nStrategies and rules of PBPS\nWorkshop on various techniques and strategies for problem solving\nProof methods in computer science (direct, indirect, induction)\n\nFinite automata: Selected properties from\n- Equivalence to regular expressions and regular languages\n- Pumping lemma\n- Algorithms on automata (minimization, transformation of non-deterministic automata)\n\nContext-free and context-sensitive languages: Selected properties from\n- Pumping lemma\n- Conclusion properties and operational models (PDA, LBA)\n- Normalization of CFG (Chomsky normal form)\n- Algorithms on CFG (CYK, etc)\n\nTuring machines: Selected properties from\n- Formal description of Turing machines\n- Examples of Turing programs\n- Variants: Single-band TM, multi-band TM, multi-head TM\n- Chomsky hierarchy\n\nComplexity, computability, decidability\n- Computability models and complexity classes\n- Non-computable or undecidable problems\n- NP-completeness, P =NP hypothesis and reduction of problems\n--- Contents (DE) ---\nPuzzle-Based Problem Solving (PBPS) und Mathematisches Denken: \nPBPS als explorativer Ansatz zum strategischen Probleml\u00f6sen\nStrategien und Regeln des PBPS\nWorkshop zu verschiedenen Techniken und Strategien der Probleml\u00f6sung\nBeweisverfahren der Informatik (dirket, indirekt, Induktion)\n\nEndliche Automaten: Ausgew\u00e4hlte Eigenschaften aus\n-\tAquivalenz zu regul\u00e4ren Ausdr\u00fccke und regul\u00e4ren Sprachen\n-\tPumping Lemma\n-\tAlgorithmen auf Automaten (Minimierung, Umwandlung Nichtdeterministische Automaten)\n\nKontextfreie und kontextsenstive Sprachen: Ausgew\u00e4hlte Eigenschaften aus\n-\tPumpingLemma\n-\tAbschlusseigenschaften und operationale Modelle (PDA, LBA)\n-\tNormalisierung von CFG (Chomsky Normalform)\n-\tAlgorithmen auf CFG (CYK, etc)\n\nTuringmaschinen: Ausgew\u00e4hlte Eigenschaften aus\n-\tFormale Beschreibung Turingmaschine\n-\tBeispiele zu Turingprogrammen\n-\tVarianten: Einband-TM, Mehrband-TM, Mehrkopf-TM\n-\tChomsky-Hierarchie\n\nKomplexit\u00e4t, Berechenbarkeit, Entscheidbarkeit\n-\tBerechenbarkeitsmodelle und Komplexit\u00e4tsklassen\n-\tNichtberechenbare bzw unentscheidbare Probleme\n-\tNP-Vollst\u00e4ndigkeit, P =NP Hypothese und Reduktion von Problemen\n--- Literature (EN) ---\n--- Literature (DE) ---\nJ.E. Hopcroft, R. Motwani, und J.D. Ullman: Einf\u00fchrung in die Automatentheorie, formale Sprachen und Komplexit\u00e4tstheorie, Pearson Studium (2011)\n\nU. Sch\u00f6ning: Theoretische Informatik  kurz gefasst, Spektrum Akademischer Verlag (2008)\n\nD. Hoffmann: Theoretische Informatik, Hanser Verlag, 2023\n\nZ. Michalewicz, M. Michalewicz: Puzzle-based Learning: Introduction to critical thinking, mathematics, and problem solving, Credibility CorporationPty Ltd, 2008\n\nE. F. F. Meyer, N. Falkner, R. Sooriamurthi, Z. Michalewicz. Guide to Puzzle-Based Learning, Springer 2014", "metadata": {"moduleNumber": "MMI 02", "moduleName": "Computational Thinking", "creditPoints": "5.0", "suggestedSemester": 1, "offeredInSeason": "winter_semester", "examType": "written_exam", "heldInLanguage": "de", "reviserName": "Prof. Dr. rer. nat. Christian Geiger", "reviserEmail": "geiger@hs-duesseldorf.de", "studyProgramId": 11, "source_type": "json"}}
{"id": "MMI03", "text": "Title: Master Project 1\nModule Number: MMI 03\nCredits: 10.0 CP\nSemester: 1\nOffered In: winter_semester\nLanguage: en_on_demand\nExam Type: project\nInstructor: Prof. Dr. Thomas Franz (thomas.franz@hs-duesseldorf.de)\n--- Goals (EN) ---\nThe students are able to work successfully on a complex application-oriented project in the field of- media informatics or, alternatively,- media engineering, event technology or media design with a focus on informatics.They can achieve results in the different project phases independently, analyse them critically and present the results.\n--- Goals (DE) ---\nTeilnehmer sind in der Lage, eine komplexe anwendungs-orientierte Aufgabenstellung aus dem Bereiche Medieninformatik bzw. Medientechnik / Veranstaltungstechnik / Mediengestaltung mit signifikanten Informatikanteilen erfolgreich zu bearbeiten und in den verschiedenen Projektphasen eigenst\u00e4ndig Ergebnisse erzielen, diese kritisch zu analysieren und Resultate zu pr\u00e4sentieren.\n--- Contents (EN) ---\nThe students work alone or in teams on individual research questions within the area of media informatics or related disciplines with a focus on informatics. They discuss their progress regularly with the supervisor and present first results. The main focus is the research-oriented implementation of the concepts developed based on scientific methodology.\n--- Contents (DE) ---\nStudierende arbeiten alleine oder im Team an einer eigenst\u00e4ndigen wissenschaftlichen Fragestellung der Medieninformatik bzw. verwandter Medienbereiche mit Informatikanteil. Der Fortschritt wird regelm\u00e4\u00dfig mit dem Betreuer besprochen und (Teil-) Ergebnisse entsprechend pr\u00e4sentiert. Der Schwerpunkt liegt auf der forschungsorientierten Umsetzung der entwickelten Konzepte auf Basis wissenschaftlicher Methoden.\n--- Literature (EN) ---\n--- Literature (DE) ---\nJe nach Dozent und Projektthema verschieden", "metadata": {"moduleNumber": "MMI 03", "moduleName": "Master Project 1", "creditPoints": "10.0", "suggestedSemester": 1, "offeredInSeason": "winter_semester", "examType": "project", "heldInLanguage": "en_on_demand", "reviserName": "Prof. Dr. Thomas Franz", "reviserEmail": "thomas.franz@hs-duesseldorf.de", "studyProgramId": 11, "source_type": "json"}}
{"id": "MMI04", "text": "Title: Master Project 2\nModule Number: MMI 04\nCredits: 10.0 CP\nSemester: 2\nOffered In: summer_semester\nLanguage: en_on_demand\nExam Type: project\nInstructor: Prof. Dr. Thomas Franz (thomas.franz@hs-duesseldorf.de)\n--- Goals (EN) ---\nThe students are able to work successfully on a complex application-oriented project in the field ofmedia informatics or, alternatively,media engineering, event technology or media design with a focus on informatics.They can achieve results in the different project phases independently, analyse them critically and present the results.\n--- Goals (DE) ---\nTeilnehmer sind in der Lage, eine komplexe, forschungs-orientierte Aufgabenstellung aus dem Bereiche Medieninformatik bzw. Medientechnik / Veranstaltungstechnik / Mediengestaltung mit signifikanten Informatikanteilen erfolgreich zu bearbeiten und in den verschiedenen Projektphasen eigenst\u00e4ndig Ergebnisse erzielen, diese kritisch zu analysieren und Resultate zu pr\u00e4sentieren.\n--- Contents (EN) ---\nThe students work alone or in teams on individual research questions within the area of media informatics or related disciplines with a focus on informatics. They discuss their progress regularly with the supervisor and present first results. The main focus is the research-oriented implementation of the concepts developed based on scientific methodology.\n--- Contents (DE) ---\nStudierende arbeiten alleine oder im Team an einer eigenst\u00e4ndigen wissenschaftlichen Fragestellung der Medieninformatik bzw. verwandter Medienbereiche mit Informatikanteil. Der Fortschritt wird regelm\u00e4\u00dfig mit dem Betreuer besprochen und (Teil-) Ergebnisse entsprechend pr\u00e4sentiert. Der Schwerpunkt liegt auf der forschungsorientierten Umsetzung der entwickelten Konzepte auf Basis wissenschaftlicher Methoden.\n--- Literature (EN) ---\n--- Literature (DE) ---\nJe nach Dozent und Projektthema verschieden", "metadata": {"moduleNumber": "MMI 04", "moduleName": "Master Project 2", "creditPoints": "10.0", "suggestedSemester": 2, "offeredInSeason": "summer_semester", "examType": "project", "heldInLanguage": "en_on_demand", "reviserName": "Prof. Dr. Thomas Franz", "reviserEmail": "thomas.franz@hs-duesseldorf.de", "studyProgramId": 11, "source_type": "json"}}
{"id": "MMI05.02", "text": "Title: Usability Engineering and User Experience\nModule Number: MMI 05.02\nCredits: 5.0 CP\nSemester: 2\nOffered In: summer_semester\nLanguage: en_on_demand\nExam Type: project\nInstructor: Prof. Dr. Alina Huldtgren (alina.huldtgren@hs-duesseldorf.de)\n--- Goals (EN) ---\nThe students understand how technology can influence human experience and how to develop digital products according to users' needs and habits. They know the basic characteristics of human experiences according to Hassenzahl. They can select and apply common methods for needs analysis, prototyping and evaluation. The students understand fundamental differences between usability and UX. They can determine and communicate requirements for the technical development of a product in the context of usability and UX.\n--- Goals (DE) ---\nDie Studierenden verstehen in welcher Weise Technik die menschliche Erfahrung beeinflussen kann und wie man digitale Produkte mit Hinblick auf die Bed\u00fcrfnisse und Erfahrungen der Nutzer hin entwickelt. Dabei kennen die Studierenden die grundlegenden Eigenschaften menschlicher Erfahrungen nach Hassenzahl und k\u00f6nnen g\u00e4ngige Methoden zur Bed\u00fcrfnisanalyse, Prototyping und Evaluation ausw\u00e4hlen und anwenden. Sie verstehen grundlegende Unterschiede zwischen Usability und UX und k\u00f6nnen Anforderungen f\u00fcr die technische Entwicklung eines Produktes im Hinblick auf Usability und UX formulieren und kommunizieren.\n--- Contents (EN) ---\nHistorical development of usability and UXBasic theoretical models on actions and human experiencesntroduction to design processes such as user-centred design, co-design and experience designPractical application of UX design methods (interviews, personas, scenarios, prototyping, evaluation) based on a design task\n--- Contents (DE) ---\nGeschichtliche Entwicklung der Usability und UXGrundlegende Theoretische Modelle zu Handlungen und menschlichen Erfahrungen/ErlebnissenEinf\u00fchrung in Designprozesse wie Nutzerzentrierter Gestaltung, Co-Design und Experience DesignPraktische Anwendung von UX Design Methoden (Interviews, Personas, Szenarien, Prototyping, Evaluation) anhand einer Designaufgabe\n--- Literature (EN) ---\n--- Literature (DE) ---\nMorgan Kaufmann: Observing the user experience: a practitioner's guide to user research, Goodman, Kuniavsky and Moed (2012)Hassenzahl, M: Experience design: Technology for all the right reasons. Synthesis Lectures on Human-Centered Informatics, 3(1), 1-95 (2010)Richter und Fl\u00fcckiger: Usability Engineering Kompakt, Spektrum Akademischer Verlag (2009)Aktuelle Publikationen aus der HCI-Forschung, z. B. von Konferenzen wie ACM CHI, ACM UIST, DIS, Mensch und Computer, etc.", "metadata": {"moduleNumber": "MMI 05.02", "moduleName": "Usability Engineering and User Experience", "creditPoints": "5.0", "suggestedSemester": 2, "offeredInSeason": "summer_semester", "examType": "project", "heldInLanguage": "en_on_demand", "reviserName": "Prof. Dr. Alina Huldtgren", "reviserEmail": "alina.huldtgren@hs-duesseldorf.de", "studyProgramId": 11, "source_type": "json"}}
{"id": "MMI05.03", "text": "Title: Advanced User Interfaces\nModule Number: MMI 05.03\nCredits: 5.0 CP\nSemester: None\nOffered In: to_be_announced\nLanguage: de\nExam Type: project\nInstructor: Prof. Dr. rer. nat. Christian Geiger (geiger@hs-duesseldorf.de)\n--- Goals (EN) ---\nThe students know selected advanced approaches to advanced user interfaces (post-WIMP interfaces, such as tangible and embedded interaction, 3D user interfaces, mixed reality interaction). They are able to understand new ideas based on scientific publications or peers\u2019 project results, critically reflect on them and implement or expand them in their own approaches. For specific selected problems, the students can develop new ideas and test their implementation. They can evaluate their results and present them (e.g. at trade fairs, workshops and conferences).\n--- Goals (DE) ---\nDie Studierenden kennen ausgew\u00e4hlte fortgeschrittene Ans\u00e4tze zu fortgeschrittenen Benutzungsschnittstellen (Post-WIMP Interfaces, z. B. tangible and embedded Interaction, 3D User Interfaces, Mixed Reality Interaktion) und sind in der Lage, sich auf Grundlage wissenschaftlicher Publikationen bzw. fremder Projektergebnisse in neue Ideen einzuarbeiten, diese kritisch zu reflektieren und in eigenen Ans\u00e4tzen umzusetzen bzw. zu erweitern. F\u00fcr spezifische ausgew\u00e4hlte Probleme k\u00f6nnen Sie neue Ideen entwickeln und prototypisch realisieren sowie ihre Ergebnisse bewerten und \u00f6ffentlich pr\u00e4sentieren (z. B. auf Messen, Workshops / Konferenzen).\n--- Contents (EN) ---\nIn this module, the students analyse current work from different fields depending on the focus chosen. They present results, critically discuss and apply them to an individual assignment or develop the results further into a new solution. Possible topics include:Tangible and embedded interactionMixed, augmented and virtual reality interfacesIntelligent user interfacesUbiquitous computingPhysical computing interfaces\n--- Contents (DE) ---\nJe nach gew\u00e4hltem Schwerpunkt werden aktuelle Arbeiten unterschiedlicher Gebiete ausgew\u00e4hlt. Diese werden pr\u00e4sentiert, kritisch diskutiert und im Rahmen einer eigenen Aufgabenstellung umgesetzt bzw. zu einer neuen L\u00f6sung weiterentwickelt. M\u00f6gliche Bereiche sind dabei:Tangible and Embedded InteractionMixed, Augmented and Virtual Reality InterfacesIntelligent User InterfacesUbiquitous ComputingPhysical Computing Interfaces\n--- Literature (EN) ---\n--- Literature (DE) ---\nSears, Jacko: The Human-Computer Interaction Handbook, 2nd Edition, CRC Press (2008)Bowman, Kruijff, LaViola, Poupyrev: 3D User Interfaces: Theory and Practice, Addison-Wesley (2004)Jason Jerald: The VR Book: Human-Centered Design for Virtual Reality, Association for Computing Machinery and Morgan & Claypool, New York, NY, USA (2015)D. Schmalstieg and T. H\u00f6llerer: Augmented Reality: Principles and Practice. Addison-Wesley Professional, First Edition (June 2016)M. Haller, M. Billinghurst, B. Thomas: Emerging Technologies of Augmented Reality: Interfaces and Design, Idea Group Publishing (2006)Aktuelle Publikationen aus ACM / IEEE Konferenzen wie z.B. TEI, ISMAR, CHI, UIST, VR, VRST, IST, soweit verf\u00fcgbar in den digitalen Bibliotheken www.acm.org, www.computer.org", "metadata": {"moduleNumber": "MMI 05.03", "moduleName": "Advanced User Interfaces", "creditPoints": "5.0", "suggestedSemester": null, "offeredInSeason": "to_be_announced", "examType": "project", "heldInLanguage": "de", "reviserName": "Prof. Dr. rer. nat. Christian Geiger", "reviserEmail": "geiger@hs-duesseldorf.de", "studyProgramId": 11, "source_type": "json"}}
{"id": "MMI05.04", "text": "Title: Web Data Analytics\nModule Number: MMI 05.04\nCredits: 5.0 CP\nSemester: 2\nOffered In: summer_semester\nLanguage: de\nExam Type: portfolio\nInstructor: Prof. Dr.-Ing. Thomas Rakow (thomas.rakow@hs-duesseldorf.de)\n--- Goals (EN) ---\nThe students can analyse data which are unstructured, heterogenous, large or gathered from media content. They master techniques to analyse applications of the Web such as search engines, social networks and user access data. They are enabled to apply the results in typical environments and to visualise them appropriately. They understand the economic impact of data analysis.In order to meet the scientific as well as the application-oriented demands of the topic of data analysis, the competences are tested in two examinations.1) Student thesis: Presentation of scientific papers with presentation and elaboration (seminar)2) Project appraisal: Demonstration of a software prototype and creation of a handout (project)\n--- Goals (DE) ---\nDie Studierenden k\u00f6nnen unstrukturierte, heterogene, gro\u00dfe und mediale Datenvolumina analysieren. Sie beherrschen die Techniken zur Analyse von Web-Anwendungen wie Suchmaschinen, Sozialen Netzwerken und Zugriffscontrolling. Sie k\u00f6nnen deren Ergebnisse praktisch anwenden und visualisieren. Die wirtschaftliche Bedeutung des Themas ist verstanden worden.\n--- Contents (EN) ---\nDesigning database systems for text, image, speech, music, video and animation content\nUnderstanding distributed systems for large data volumes in the context of the web\nVisualising large data volumes\nRetrieving content-based information\nDeveloping semantic networks based on heterogenous data sets\nAnalysing user access data \nGetting information from big data and open data\nSentiment Analysis\n--- Contents (DE) ---\nMediale Datenbanken, insbesondere f\u00fcr Text, Bild, Sprache, Musik, Video, Animation\nVerteilte Systeme zur Verarbeitung gro\u00dfer Datenvolumina aus dem Web\nVisualisierung gro\u00dfer Datenbest\u00e4nde\nInhaltsbasiertes Retrieval\nSemantische Netze aus heterogenen Datenbasen\nWeb-Analyse, insbesondere Zugriffsdaten\nBig Data und Open Data\nSentiment Analyse\n--- Literature (EN) ---\nSee the current notes in the course on the respective topic\n--- Literature (DE) ---\nSiehe die aktuellen Hinweise im Kurs zu dem jeweiligen Thema", "metadata": {"moduleNumber": "MMI 05.04", "moduleName": "Web Data Analytics", "creditPoints": "5.0", "suggestedSemester": 2, "offeredInSeason": "summer_semester", "examType": "portfolio", "heldInLanguage": "de", "reviserName": "Prof. Dr.-Ing. Thomas Rakow", "reviserEmail": "thomas.rakow@hs-duesseldorf.de", "studyProgramId": 11, "source_type": "json"}}
{"id": "MMI05.05", "text": "Title: Immersive Visualization\nModule Number: MMI 05.05\nCredits: 5.0 CP\nSemester: 2\nOffered In: summer_semester\nLanguage: de\nExam Type: none\nInstructor: Prof. Dr. rer. nat. Christian Geiger (geiger@hs-duesseldorf.de)\n--- Goals (EN) ---\nStudents will be familiar with the key concepts of visualization and typical design procedures. They also know typical examples of successful immersive visualization projects and can explain and evaluate them. They are able to recognize typical problems in the design and development of immersive visualizations and to develop expressive and effective visual representation concepts based on established procedures for multivariate data, to implement and evaluate them using suitable immersive technologies (visualization systems, 3D game engines, frameworks). They are able to design their own visualization projects and successfully implement them within a given time frame. They will be able to present and critically reflect on the scientific and artistic state of development.\n--- Goals (DE) ---\nDie Studierenden kennen die wesentlichen Begriffe der Visualisierung und typische Vorgehensweise beim Entwurf. Sie kennen dar\u00fcber hinaus typische Beispiele erfolgreicher immersiver Visualisierungsprojekte und k\u00f6nnen diese erl\u00e4utern und bewerten. Sie sind in der Lage, typische Probleme der bei der Gestaltung und Entwicklung immersiver Visualisierungen zu erkennen und auf Basis etablierter Vorgehensweisen  f\u00fcr multivariate Daten expressive und effektive visuelle Darstellungskonzepte zu entwickeln, mittels geeigneter immersiver Technologien (Visualisierungssysteme, 3D Game Engines, Frameworks) zu realisieren und zu bewerten. Sie sind in der Lage, eigene Visualisierungsprojekte zu konzipieren und in einem gegebenen Zeitrahmen erfolgreich umzusetzen. Sie k\u00f6nnen den wissenschaftlichen und k\u00fcnstlerischen Stand der Entwicklung darstellen und kritisch reflektieren.\n--- Contents (EN) ---\nThe course Immersive Visualization deals with computer-aided methods for the graphical representation of information and data, which are given an immersive character through design and technology. This can be achieved through extensive interaction, XR technologies, projections or large-scale displays. This special visual representation is intended to help evaluate, present and inform data or gain new insights from it. The main contents are \n- Aspects of human visual perception and visualization models:\n- Visualization of multivariate data\n- Workflow and procedure models in the visualization process (visualization pipeline)\n- multimodal interaction concepts, design principles and storytelling \n- Overview of typical visualization systems for real-time applications \n- VR/AR technologies for immersive visualization\n- scientific and artistic research in this field\n\nThe course will choose a specific topic in each semester offered, which will then be worked on with the participants. External lectures and excursions round off the program.\n--- Contents (DE) ---\nDie Veranstaltung Immersive Visualisierung befasst sich mit computerunterst\u00fctzten Methoden zur grafischen Repr\u00e4sentation von Informationen und Daten, die durch Gestaltung und Technologie einen immersiven Charakter erhalten. Das kann durch umfangreiche Interaktion, XR -Technologien, Projektionen oder gro\u00dffl\u00e4chige Displays erfolgen. Diese besondere bildliche Darstellung soll dabei helfen, Daten auszuwerten, zu pr\u00e4sentieren und informieren bzw. neue Erkenntnisse daraus zu gewinnen. Wesentliche Inhalte sind \n- Aspekte der menschlichen visuellen Wahrnehmung und Modell der Visualisierung:\n- Visualisierung multivariater Daten\n- Workflow und Vorgehensmodelle im Visualisierungsprozess (Visualisierungspipeline)\n- multimodale Interaktionskonzepte, Gestaltungsgrundlagen und Storytelling \n- \u00dcberblick typischer Visualisierungssysteme f\u00fcr Echtzeitanwendungen \n- VR/AR Technologien f\u00fcr immersive Visualisierung\n- wissenschaftliche und k\u00fcnstlerische Forschung in diesem Bereich\n\nDie Veranstaltung wird sich in jedem angebotenen Semester ein spezielles Thema w\u00e4hlen, das mit den Teilnehmer:innen dann bearbeitet wird. Externe Vortr\u00e4ge und Exkursionen runden das Angebot ab.\n--- Literature (EN) ---\n--- Literature (DE) ---\n-Chaomei Chen: Information Visualization. Beyond the Horizon. 2. Auflage, Springer London, (2004)\n-Colin Ware: Information Visualization : Perception for Design Morgan Kaufmann Series in Interactive Technologies, San Francisco, (2000)\n-Natha Yau: Visualize This: The Flowing Data Guide to Design, Visualization and Statistics, Wiley, (2011)\n- Cole Nussbaumer Knaflic: Storytelling with Data: A Data Visualization Guide for Business Professionals, Wiley, (2015)\n- Cornel Hillmann: UX for XR: User Experience Design and Strategies for Immersive Technologies (Design Thinking), Apress 2021.", "metadata": {"moduleNumber": "MMI 05.05", "moduleName": "Immersive Visualization", "creditPoints": "5.0", "suggestedSemester": 2, "offeredInSeason": "summer_semester", "examType": "none", "heldInLanguage": "de", "reviserName": "Prof. Dr. rer. nat. Christian Geiger", "reviserEmail": "geiger@hs-duesseldorf.de", "studyProgramId": 11, "source_type": "json"}}
{"id": "MMI05.07", "text": "Title: Intelligent Systems\nModule Number: MMI 05.07\nCredits: 5.0 CP\nSemester: 2\nOffered In: summer_semester\nLanguage: de\nExam Type: written_exam\nInstructor: Prof. Dr. Dennis M\u00fcller (dennis.mueller@hs-duesseldorf.de)\n--- Goals (EN) ---\nUpon successful completion of the module, students are able to\n\nDetermine regression and classification models using linear and logistic methods,\n\nFind linear separating hyperplanes in high-dimensional spaces using a kernelized support vector machine,\n\nSelect different loss functions for optimizing regression problems purposefully and solve the resulting optimization problem,\n\nIdentify and interpret important metrics and measures (e.g., accuracy, precision, recall) of classification models,\n\nIndependently train perceptrons and multilayer neural networks using appropriate methods,\n\nImplement and train simple neural networks in PyTorch using training data.\n\nMMI PO18 and MMI PO25 only:\nThe students independently work on a simple task from the field of \"Artificial Intelligence\" in consultation with the instructor and present the results in a short oral presentation during lecture or exercise time. The additional required work will be coordinated with the instructor at the beginning of the semester and independently developed during the semester.\n--- Goals (DE) ---\nMit dem erfolgreichen Absolvieren des Moduls sind Studierende in der Lage\n\nRegressions- und Klassifikationsmodelle mit Hilfe linearer sowie logistischer Methoden zu bestimmen,\n\nLineare Trennebenen in hochdimensionalen R\u00e4umen mit Hilfe einer kernelisierten Support-Vektor-Maschine zu finden,\n\nUnterschiedliche Loss-Funktionen zur Optimierung von Regressionsproblemen zielgerichtet auszuw\u00e4hlen und das sich daraus ergebende Optimierungsproblem zu l\u00f6sen,\n\nWichtige Kenngr\u00f6\u00dfen und Metriken (z.B. Accuracy, Precision, Recall) von Klassifikationsmodellen zu ermitteln und zu interpretieren,\n\nPerzeptronen- und mehrschichtige neuronale Netzwerke unter Einsatz geeigneter Verfahren selbstst\u00e4ndig zu trainieren,\n\neinfache neuronale Netzwerke in PyTorch zu implementieren und anhand von Trainingsdaten zu trainieren.\n\nF\u00fcr MMI PO18 und MMI PO25 zus\u00e4tzlich:\nDie Studierenden bearbeiten selbstst\u00e4ndig eine einfache Aufgabenstellung aus dem Bereich \"K\u00fcnstliche Intelligenz\" in Absprache mit dem Dozierenden und stellen die Ergebnisse in einem kurzen m\u00fcndlichen Vortrag w\u00e4hrend der Vorlesungs- oder \u00dcbungszeit vor. Die zu erbringende Zusatzleistung wird am Anfang des Semesters mit dem Dozenten abgestimmt und im laufenden Semester selbstst\u00e4ndig erarbeitet.\n--- Contents (EN) ---\nHistory of artificial intelligence / knowledge-based systems\nLinear regression and linear classification\nKernel methods for regression and classification in high-dimensional spaces\nSupport vector machines\nLoss functions and metrics\nPerceptrons and neural networks\nBackpropagation and delta learning rule\nPractical application in Python and PyTorch\n--- Contents (DE) ---\nGeschichte der k\u00fcnstlichen Intelligenz / wissensbasierter Systeme\nLineare Regression und lineare Klassifikation\nKernelmethoden zur Regression und Klassifikation in hochdimensionalen R\u00e4umen\nSupport Vektor Maschinen\nLoss-Funktionen und Metriken\nPerzeptronen- und Neuronalenetzwerke\nBackpropagation und Delta-Lernregel\nPraktische Anwendung in Python und PyTorch\n--- Literature (EN) ---\nRussell, S. J., & Norvig, P. (2020). Artificial Intelligence: A Modern Approach (4th ed.). Pearson.\nDomingos, P. (2015). The Master Algorithm: How the Quest for the Ultimate Learning Machine Will Remake Our World. Basic Books.\nMitchell, T. M. (1997). Machine Learning. McGraw-Hill.\nGoodfellow, I., Bengio, Y., & Courville, A. (2016). Deep Learning. MIT Press.\nTegmark, M. (2017). Life 3.0: Being Human in the Age of Artificial Intelligence. Knopf.\n--- Literature (DE) ---\nRussell, S. J., & Norvig, P. (2020). Artificial Intelligence: A Modern Approach (4th ed.). Pearson.\nDomingos, P. (2015). The Master Algorithm: How the Quest for the Ultimate Learning Machine Will Remake Our World. Basic Books.\nMitchell, T. M. (1997). Machine Learning. McGraw-Hill.\nGoodfellow, I., Bengio, Y., & Courville, A. (2016). Deep Learning. MIT Press.\nTegmark, M. (2017). Life 3.0: Being Human in the Age of Artificial Intelligence. Knopf.", "metadata": {"moduleNumber": "MMI 05.07", "moduleName": "Intelligent Systems", "creditPoints": "5.0", "suggestedSemester": 2, "offeredInSeason": "summer_semester", "examType": "written_exam", "heldInLanguage": "de", "reviserName": "Prof. Dr. Dennis M\u00fcller", "reviserEmail": "dennis.mueller@hs-duesseldorf.de", "studyProgramId": 11, "source_type": "json"}}
{"id": "MMI05.08", "text": "Title: Interactive Virtual Studio\nModule Number: MMI 05.08\nCredits: 5.0 CP\nSemester: 1\nOffered In: winter_semester\nLanguage: en_on_demand\nExam Type: project\nInstructor: Prof. Dr. Eng. Univ. of Tsukuba Jens Herder (jens.herder@hs-duesseldorf.de)\n--- Goals (EN) ---\nSuccessful participants will have a profound knowledge in building and developing virtual set environments for broadcasting applications and will be able to evaluate virtual studio (TV) technology. Tracking, composition of video and computer graphics under live conditions for media productions are essential part.\n--- Goals (DE) ---\nStudierende k\u00f6nnen Video und Computergrafik unter Live-Bedingungen in Produktionen verbinden. Hierzu geh\u00f6rt die Erstellung fiktiver Umgebungen, in die Menschen und Gegenstande versetzt werden. Sie k\u00f6nnen Virtuelle Studios entwickeln, aufbauen und einsetzen. Die grundlegenden Technologien wie z.B. Tracking, Computergrafik k\u00f6nnen angepasst und bewertet werden.\n--- Contents (EN) ---\nTopics include:\n- Application and use of virtual sets\n- Effect of artificially created levels of reality, unreal scenery and virtual backdrops\n- Hard- and software for digital (TV) studio productions\n- Light and light setting for TV studios\n- Camera and actor tracking systems\n- Virtual set design for artificial or real scenes\n- Motion capture\n- Real-time computer graphics and visual effects\n- Separation of image elements (e.g., chroma keying)\n- Integration of animations and virtual characters/avatars\n- Interaction within a virtual tv studio\n- Feedback methods for actors\n- Studio production planning and automation\n--- Contents (DE) ---\nZu den Themen geh\u00f6ren:\n- Anwendungen und Nutzung von virtuellen Sets\n- Wirkung k\u00fcnstlich erstellter Realit\u00e4tsebenen, irrealer Szenenbilder und virtueller Kulissen\n- Hard- und Software f\u00fcr digitale Studioproduktionstechnik\n- Licht und Beleuchtung im Virtuellen Studio, Lichtsch\u00e4tzung\n- Kamera- und Darstellerverfolgungssysteme (Tracking)\n- Set Design\n- Bewegungsaufzeichnung (auch markerlos)\n- Echtzeitgenerierung dreidimensionaler Computergraphik, visuelle Effekte\n- Herausl\u00f6sen von Bildelementen (z.B. Chromakeying)\n- Einbindung von Animationen und virtuellen Charakteren/Avataren\n- Interaktion im Virtuellen Studio\n- Feedbackmethoden f\u00fcr Darsteller\n- Produktionsplanung, Automatisierung und Produktionsdurchf\u00fchrung\n--- Literature (EN) ---\n- S. Gibbs: Virtual Studios, IEEE MultiMedia 5, 1 (January 1998), 17-17. DOI=http://dx.doi.org/10.1109/MMUL.1998.664739\n- A. R. Smith and J. F. Blinn: Blue screen matting. In Proceedings of the 23rd annual conference on Computer graphics and interactive techniques (SIGGRAPH '96), ACM, New York, NY, USA, 259-268. DOI=http://dx.doi.org/10.1145/237170.237263\n- R. Brinkmann: The Art and Science of Digital Compositing, Morgan Kaufman, lis Group (M\u00e4rz 2000)\n- M. Moshkovitz: The Virtual Studio Technology & Techniques, Focal Press (2000)\n- P. Tucker: Secrets of Screen Acting, Routlege (1994)\n- D. Arijon: Grammar of the Film Language, Silman-James Press (1976)\n- U. Schmidt: Professionelle Videotechnik: Analoge und Digitale Grundlagen, Filmtechnik, Fernsehtechnik, HDTV, Kameras, Displays, Videorecorder, Produktion und Studiotechnik, Springer (2005)\n- Journal of Virtual Reality and Broadcasting, www.jvrb.org\n--- Literature (DE) ---\n- S. Gibbs: Virtual Studios, IEEE MultiMedia 5, 1 (January 1998), 17-17. DOI=http://dx.doi.org/10.1109/MMUL.1998.664739\n- A. R. Smith and J. F. Blinn: Blue screen matting. In Proceedings of the 23rd annual conference on Computer graphics and interactive techniques (SIGGRAPH '96), ACM, New York, NY, USA, 259-268. DOI=http://dx.doi.org/10.1145/237170.237263\n- R. Brinkmann: The Art and Science of Digital Compositing, Morgan Kaufman, lis Group (M\u00e4rz 2000)\n- M. Moshkovitz: The Virtual Studio Technology & Techniques, Focal Press (2000)\n- P. Tucker: Secrets of Screen Acting, Routlege (1994)\n- D. Arijon: Grammar of the Film Language, Silman-James Press (1976)\n- U. Schmidt: Professionelle Videotechnik: Analoge und Digitale Grundlagen, Filmtechnik, Fernsehtechnik, HDTV, Kameras, Displays, Videorecorder, Produktion und Studiotechnik, Springer (2005)\n- Journal of Virtual Reality and Broadcasting, www.jvrb.org", "metadata": {"moduleNumber": "MMI 05.08", "moduleName": "Interactive Virtual Studio", "creditPoints": "5.0", "suggestedSemester": 1, "offeredInSeason": "winter_semester", "examType": "project", "heldInLanguage": "en_on_demand", "reviserName": "Prof. Dr. Eng. Univ. of Tsukuba Jens Herder", "reviserEmail": "jens.herder@hs-duesseldorf.de", "studyProgramId": 11, "source_type": "json"}}
{"id": "MMI05.09", "text": "Title: VR and AR Systems\nModule Number: MMI 05.09\nCredits: 5.0 CP\nSemester: 2\nOffered In: summer_semester\nLanguage: en_on_demand\nExam Type: oral_exam\nInstructor: Prof. Dr. Eng. Univ. of Tsukuba Jens Herder (jens.herder@hs-duesseldorf.de)\n--- Goals (EN) ---\nSuccessful participants will have a profound knowledge in building and developing VR and AR systems and will be able to evaluate application based on VR and AR technology. Specific base technology (e.g., tracking) can be further developed and new VR and AR concepts can be implemented.\n--- Goals (DE) ---\nStudierende beherrschen die wichtigsten VR / AR-Technologien (Virtual Reality / Augmented Reality) und sind in der Lage, virtuelle Umgebungen und Augmented Reality-Anwendungen zu konzipieren, aufzubauen und zu bewerten. Studierende k\u00f6nnen einzelne Basistechnologien (z.B. Tracking) weiterentwickeln und neue VR/AR-Konzepte umsetzten.\n--- Contents (EN) ---\n- Motivation, definitions, Layout and design of VR and AR systems\n- Applications in VR and AR\n- Multimodal cues\n- Augmented Reality\n- Advanced display technology for mixed reality\n- Advanded input and output devices\n- Hybrid tracking for users, objects and environments\n- Navigation and interaction in VR\n- Haptic\n- Virtual acoustics for realtime applications\n- Scene modeling (scene graph based ) and programming\n- Data structures and algorithmes f\u00fcr VR and AR\n- Rapid prototyping and tools for VR/AR systems\n--- Contents (DE) ---\n- Motivation / Begriffsdefinition / Aufbau von VR/AR-Systemen\n- Aktuelle Anwendungsgebiete\n- Multimodalen Wahrnehmungsfaktoren\n- Augmented Reality\n- Fortgeschrittenen Darstellungstechniken (u.a. Mixed Reality)\n- Fortgeschrittene Ein- und Ausgabeger\u00e4te f\u00fcr VR/AR\n- Hybrides Tracking von Benutzern, Objekten und Umgebungen\n- Navigation und Interaktionstechniken\n- Haptik\n- Virtuelle Akustik f\u00fcr Echtzeitanwendungen\n- VR/AR-Szenenmodellierung und Programmierung\n- Datenstrukturen und Algorithmen f\u00fcr VR/AR Umgebungen\n- Entwurf und Werkzeuge f\u00fcr VR/AR-Systemen\n--- Literature (EN) ---\n- R. D\u00f6rner, W. Broll, P. Grimm, B. Jung, Virtual and Augmented Reality (VR/AR), Foundations and Methods of Extended Realities (XR), Springer, 2022, DOI 10.1007/978-3-030-79062-2\n- Jason Jerald. The VR Book: Human-Centered Design for Virtual Reality. Association for Computing Machinery and Morgan & Claypool, New York, NY, USA. 2015, DOI 10.1145/2792790\n- G. C. Burdea, P. Coiffet: Virtual Reality Technology, John Wiley & Sons, 3. Auflage, 2024, ISBN 978-1-118-01480-6\n- M. Guiterrez, F. Vexo, D. Thalman: Stepping into Virtual Reality, Springer Nature Verlag, 2. Ausgabe, 2023, DOI 10.1007/978-3-031-36487-7\n- W. Sherman, A. Craig: Understanding Virtual Reality - Interface, Application, and Design, Morgan Kaufman, 2. Auflage, 2018, DOI 10.1016/C2013-0-18583-2\n- J. Vince: Introduction to Virtual Reality, Springer 2004, DOI 10.1007/978-0-85729-386-2\n- J. Blauert: Spatial Hearing - The Psychophysics of Human Sound Localization, The MIT Press, Revised Edition, 1996, ISBN 0-262-02413-6\n- T. Akenine-M\u00f6ller, E. Haines und N. Hoffman: Real- Time Rendering, A.K. Peters Ltd., 2008, ISBN 978-1-56881-424-7\n- O. Bimber and R. Raskar: Spatial Augmented Reality - Merging Real and Virtual Worlds, A K Peters LTD, 2005, DOI 10.1201/b10624\n- C. Ericson, Real-Time Collision Detection, Morgan Kaufmann Series in Interactive 3D Technology, 2005, ISBN 1-55860-732-3\n- Thorsten A. Kern, Christian Hatzfeld, Alireza Abbasimoshaei (Editors): Engineering Haptic Devices, Springer (2023), DOI: 10.1007/978-3-031-04536-3\n\n\nFurther literature will be announced at the beginning of the lecture.\n--- Literature (DE) ---\n- R. D\u00f6rner, W. Broll, P. Grimm, B. Jung (Hrsg.): Virtual und Augmented Reality (VR/AR), Grundlagen und Methoden der Virtuellen und Augmentierten Realit\u00e4t, Springer, 2019, DOI 10.1007/978-3-662-58861-1\n- Jason Jerald. The VR Book: Human-Centered Design for Virtual Reality. Association for Computing Machinery and Morgan & Claypool, New York, NY, USA. 2015, DOI 10.1145/2792790\n- G. C. Burdea, P. Coiffet: Virtual Reality Technology, John Wiley & Sons, 3. Auflage, 2024, ISBN 978-1-118-01480-6\n- M. Guiterrez, F. Vexo, D. Thalman: Stepping into Virtual Reality, Springer Nature Verlag, 2. Ausgabe, 2023, DOI 10.1007/978-3-031-36487-7\n- W. Sherman, A. Craig: Understanding Virtual Reality - Interface, Application, and Design, Morgan Kaufman, 2. Auflage, 2018, DOI 10.1016/C2013-0-18583-2\n- J. Vince: Introduction to Virtual Reality, Springer 2004, DOI 10.1007/978-0-85729-386-2\n- J. Blauert: Spatial Hearing - The Psychophysics of Human Sound Localization, The MIT Press, Revised Edition, 1996, ISBN 0-262-02413-6\n- T. Akenine-M\u00f6ller, E. Haines und N. Hoffman: Real- Time Rendering, A.K. Peters Ltd., 2008, ISBN 978-1-56881-424-7\n- O. Bimber und R. Raskar: Spatial Augmented Reality - Merging Real and Virtual Worlds, A K Peters LTD, 2005, DOI 10.1201/b10624\n- C. Ericson, Real-Time Collision Detection, Morgan Kaufmann Series in Interactive 3D Technology, 2005, ISBN 1-55860-732-3\n- T. A. Kern (Hrsg.): Entwicklung Haptischer Ger\u00e4te - Ein Einstieg f\u00fcr Ingenieure, Springer, 2009, ISBN: 978-3-540-87643-4\n\nWeitere Literatur zu speziellen Gebieten wird in der Vorlesung bekannt gegeben.", "metadata": {"moduleNumber": "MMI 05.09", "moduleName": "VR and AR Systems", "creditPoints": "5.0", "suggestedSemester": 2, "offeredInSeason": "summer_semester", "examType": "oral_exam", "heldInLanguage": "en_on_demand", "reviserName": "Prof. Dr. Eng. Univ. of Tsukuba Jens Herder", "reviserEmail": "jens.herder@hs-duesseldorf.de", "studyProgramId": 11, "source_type": "json"}}
{"id": "MMI05.10", "text": "Title: Real-Time Rendering\nModule Number: MMI 05.10\nCredits: 5.0 CP\nSemester: 2\nOffered In: summer_semester\nLanguage: en_on_demand\nExam Type: project\nInstructor: Prof. Dr. Eng. Univ. of Tsukuba Jens Herder (jens.herder@hs-duesseldorf.de)\n--- Goals (EN) ---\nSuccessful participants will have developed skills for literature research, documentation and presentation as well as the ability to compare objectively different approaches to scientific problems. Participants gain profound insides to realtime rendering for virtual environments.\n--- Goals (DE) ---\nSpezielle Algorithmen und Verfahren zur Echtzeit-Computergrafik kennen, Methodische Entwicklung eigener Verfahren, Einsatz in relevanten Anwendungsfeldern beurteilen und umsetzen k\u00f6nnen, Anforderungen an Computerhardware erstellen und beurteilen k\u00f6nnen.\n--- Contents (EN) ---\n- Architecture of graphic hardware\n- Rendering pipeline and optimization\n- Shader (Pixel, Vertex, ...)\n- Image operations using shader\n- Shadow algorithms\n- Real-time raytracing\n- Selected topics for realtime graphics like advance collision detection, continouse level of detail, image based rendering, non photorealistic renderig, efficient modelling procedures\n--- Contents (DE) ---\n- Architektur von Grafikhardware\n- Render Pipeline und Optimierung\n- Shader (Pixel, Vertex, ...)\n- Bildoperatoren per Shader\n- Schattenalgorithmen\n- Realtime Raytracing\n- Ausgew\u00e4hlte Algorithmen zur 3D-Echtzeitgrafik, z. B. Fortgeschrittene Kollisionserkennung, Kontinuierlicher Level of Detail, Image-based Rendering, Nicht photorealistisches Rendering, Effiziente Modellierungsverfahren\n--- Literature (EN) ---\n- T. Akenine-M\u00f6ller, E. Haines, N. Hoffman, A. Pesce, M. Iwanicki, und S. Hillaire: Real-Time Rendering, 4th Ed, A.K. Peters/CRC Press (2018).\n- E. Haines und T. Akenine-M\u00f6ller: Ray Tracing Gems, Apress (2019).\n- R. Fernando: GPU Gems I+II, Addison-Wesley Professional (2004/05)\n- S. St. Laurent: Shaders for Game Programmers and Artists, Premier Press (2004)\n- T. Strothotte, S. Schlechtweg: Non-Photorealistic Computer Graphics, Morgan Kaufmann Publisher (2002)\n--- Literature (DE) ---\n- T. Akenine-M\u00f6ller, E. Haines, N. Hoffman, A. Pesce, M. Iwanicki, und S. Hillaire: Real-Time Rendering, 4th Ed, A.K. Peters/CRC Press (2018).\n- E. Haines und T. Akenine-M\u00f6ller: Ray Tracing Gems, Apress (2019).\n- R. Fernando: GPU Gems I+II, Addison-Wesley Professional (2004/05)\n- S. St. Laurent: Shaders for Game Programmers and Artists, Premier Press (2004)\n- T. Strothotte, S. Schlechtweg: Non-Photorealistic Computer Graphics, Morgan Kaufmann Publisher (2002)", "metadata": {"moduleNumber": "MMI 05.10", "moduleName": "Real-Time Rendering", "creditPoints": "5.0", "suggestedSemester": 2, "offeredInSeason": "summer_semester", "examType": "project", "heldInLanguage": "en_on_demand", "reviserName": "Prof. Dr. Eng. Univ. of Tsukuba Jens Herder", "reviserEmail": "jens.herder@hs-duesseldorf.de", "studyProgramId": 11, "source_type": "json"}}
{"id": "MMI05.11", "text": "Title: Computer Animation\nModule Number: MMI 05.11\nCredits: 5.0 CP\nSemester: 1\nOffered In: to_be_announced\nLanguage: de\nExam Type: oral_exam\nInstructor: Prof. Dr.-Ing. Sina Mostafawy (sina.mostafawy@hs-duesseldorf.de)\n--- Goals (EN) ---\nThe students master general and special procedures in the field of computer animation.Theoretical and mathematical basics of 3D animation.Various methods of data acquisition and data generation for animations.Real-time rendering vs. classic rendering methods. Additionally they will learn to prepare and give a presentation about a scientific topic of computeranimation.\n--- Goals (DE) ---\nDie Student:innen beherrschen allgemeine und spezielle Verfahren aus dem Bereich der Computeranimation. Theoretisch-mathematische Grundlagen der 3D-Animation, verschiedene Verfahren der Datenerzeugung f\u00fcr Animationen und Echtzeitrendering. Zus\u00e4tzlich wird ein dem Kurs gelernt wie ein Vortrag recherchiert, vorbereitet und vor Publikum gehlaten wird.\n--- Contents (EN) ---\n- 12 Basic Principles of Animation \n- Rotation with Quaternions\n- Forward and Inverse Kinematics\n- Partikelanimation and Swarm Simulation\n- Deformation & Morphing Algorithms\n- Rigid- und Soft Bodies\n- Planing und Production of Animations\n--- Contents (DE) ---\n- 12 Basic Principles of Animation \n- Rotation with Quaternions\n- Forward and Inverse Kinematics\n- Partikelanimation and Swarm Simulation\n- Deformation & Morphing Algorithms\n- Rigid- und Soft Bodies\n- Planing und Production of Animations\n--- Literature (EN) ---\n- Computer Animation: Algorithms and Techniques, Rick Parent, 3rd 2012 \n- Advanced Animation and Renderning Techniques: Alan Watt, Mark Watt, Addision Wesley\n- Real-Time Rendering, Eric Haines, 4th 2020Computer Graphics with Open GL, Pearson Prentice Hall, 4th 2013\n--- Literature (DE) ---\n- Computer Animation: Algorithms and Techniques, Rick Parent, 3rd 2012 \n- Advanced Animation and Renderning Techniques: Alan Watt, Mark Watt, Addision Wesley\n- Real-Time Rendering, Eric Haines, 4th 2020Computer Graphics with Open GL, Pearson Prentice Hall, 4th 2013", "metadata": {"moduleNumber": "MMI 05.11", "moduleName": "Computer Animation", "creditPoints": "5.0", "suggestedSemester": 1, "offeredInSeason": "to_be_announced", "examType": "oral_exam", "heldInLanguage": "de", "reviserName": "Prof. Dr.-Ing. Sina Mostafawy", "reviserEmail": "sina.mostafawy@hs-duesseldorf.de", "studyProgramId": 11, "source_type": "json"}}
{"id": "MMI05.12", "text": "Title: Character Production\nModule Number: MMI 05.12\nCredits: 5.0 CP\nSemester: 2\nOffered In: to_be_announced\nLanguage: de\nExam Type: project\nInstructor: Prof. Dr. rer. nat. Christian Geiger (geiger@hs-duesseldorf.de)\n--- Goals (EN) ---\nThe students know the fields of application of character production and can list and assess prominent examples. They know all steps in the process to produce virtual characters as well as basic techniques for selected steps. They can apply these techniques independently using relevant tools. The students can design a character independently, step by step, based on a concept. They can define criteria for a successful character production and assess both characters produced by themselves and others.\n--- Goals (DE) ---\nDie Studierenden kennen die Einsatzgebiete der Charakterproduktion und k\u00f6nnen prominente Beispiele nennen und diese bewerten. Sie kennen alle Arbeitsschritte des Produktionsprozesses bei der Erstellung virtueller Charaktere und die grundlegenden Techniken ausgew\u00e4hlter Arbeitsschritte. Diese k\u00f6nnen sie in auch selbst\u00e4ndig mit relevanten Werkzeugen anwenden. Den Entwurf eines Charakters \u00fcber alle Entwicklungsschritte ausgehend von einem Konzept k\u00f6nnen die Studierenden selbst\u00e4ndig umsetzen und Kriterien einer gelungenen Charakterproduktion formulieren und existierende eigene und fremde Arbeiten bewerten.\n--- Contents (EN) ---\nHistory of character production and milestones of the genreOverview of current examplesProcess of and different steps in character production (workflow and pipeline)Tools and production environmentSelected techniques of character production (modelling, texturing, rigging, skinning, animation and simulation, rendering and output)Integration into larger projects (films, games, installations)Distribution formatsAnalysis and assessmentPrinciples of design and profitability analysis\n--- Contents (DE) ---\nHistorie der Charakterproduktion und Meilensteine des Genres\u00dcbersicht aktueller BeispieleProduktionsprozess und Arbeitsschritte der Charakterproduktion (Workflow und Pipeline)Werkzeuge und ProduktionsumgebungenAusgew\u00e4hlte Techniken der Charakterproduktion (Modellierung, Texturierung, Rigging, Skinning, Animation / Simulation, Rendering / Output)Integration in gr\u00f6\u00dfere Projekte (Film, Games, Installation)DistributionsformateAnalyse und BewertungGestaltungsprinzipien und Wirtschaftlichkeitsbetrachtungen\n--- Literature (EN) ---\n--- Literature (DE) ---\nRichard Willimas: The Animator's Survival Kit: A Manual of Methods, Principles and Formulas for Classical, Computer, Games, Stop Motion and Internet Animator, 4th ed, Farrar, Straus and Giroux (2012)Parag Chaudhuri, Prem Kalra, Subhashis Banerjee: View-Dependent Character Animation, Springer (2009)Eric Allen et al: Body Language: Advanced 3D Character Rigging, Sybex (2008)Jason Opira: Stop Staring - Facial Modeling and Animation Done Right, 3rd Edition, Sybex (2010)Chris Legaspi: Anatomy for 3D Artists: The Essential Guide for CG Professionals, 3DTotal Publishing (2015)", "metadata": {"moduleNumber": "MMI 05.12", "moduleName": "Character Production", "creditPoints": "5.0", "suggestedSemester": 2, "offeredInSeason": "to_be_announced", "examType": "project", "heldInLanguage": "de", "reviserName": "Prof. Dr. rer. nat. Christian Geiger", "reviserEmail": "geiger@hs-duesseldorf.de", "studyProgramId": 11, "source_type": "json"}}
{"id": "MMI05.13", "text": "Title: Ambient Assisted Living\nModule Number: MMI 05.13\nCredits: 5.0 CP\nSemester: None\nOffered In: to_be_announced\nLanguage: en_on_demand\nExam Type: written_exam\nInstructor: Prof. Dr. Manfred Wojciechowski (manfred.wojciechowski@hs-duesseldorf.de)\n--- Goals (EN) ---\nThe students know the basic concepts of ambient assisted living (AAL) solutions. They can describe the application domains, benefits and restrictions of AAL technology. They can develop sociotechnical concepts and implement prototypes. The students are able to read relevant scientific publications and put them into the right context of AAL.\n--- Goals (DE) ---\nThe student knows the basic concepts of AAL solutions. He/she can describe the application domains, benefits and restrictions of AAL technology. He/she can develop socio-technical concepts and implement prototypes. The student is able to read relevant scientific publications and place them into the right context of AAL.\n--- Contents (EN) ---\nLearning ObjectivesTheoryObjectives of AAL, demographic backgroundTechnology aspectsSmart EnvironmentsContext AwarenessKnowledge RepresentationInfrastructureInteroperabilityApplication domainsHome careRestrictionsPracticeDeveloping an AAL solution Scientific workReading and discussing scientific publicationsEnglishScientific community in AAL\n--- Contents (DE) ---\nLearning ObjectivesTheoryObjectives of AAL, demographic backgroundTechnology aspectsSmart EnvironmentsContext AwarenessKnowledge RepresentationInfrastructureInteroperabilityApplication domainsHome careRestrictionsPracticeDeveloping an AAL solution Scientific workReading and discussing scientific publicationsEnglishScientific community in AAL\n--- Literature (EN) ---\n--- Literature (DE) ---\nWill be given during the lectures", "metadata": {"moduleNumber": "MMI 05.13", "moduleName": "Ambient Assisted Living", "creditPoints": "5.0", "suggestedSemester": null, "offeredInSeason": "to_be_announced", "examType": "written_exam", "heldInLanguage": "en_on_demand", "reviserName": "Prof. Dr. Manfred Wojciechowski", "reviserEmail": "manfred.wojciechowski@hs-duesseldorf.de", "studyProgramId": 11, "source_type": "json"}}
{"id": "MMI05.14", "text": "Title: Music Informatics\nModule Number: MMI 05.14\nCredits: 5.0 CP\nSemester: 2\nOffered In: summer_semester\nLanguage: de\nExam Type: project\nInstructor: Prof. Dr.-Ing. Jochen Steffens (jochen.steffens@hs-duesseldorf.de)\n--- Goals (EN) ---\nThe students have an application-oriented overview of the field of music informatics. This includes particularly music information retrieval (MIR) as well as sound synthesis and musical interfaces. The students master basic concepts and methods of MIR. They know the fields of application and can apply standard tools (e.g. MIRtoolbox) to conduct analyses (e.g. feature extraction for audio signals, audio identification, audio matching).They also master the basic concepts of different kinds of sound synthesis and can apply these to environments for music and multimedia development (e.g. in MAX/MSP). A focus is on common technology to realise interactions between humans and (electrical) musical instruments using musical interfaces or sensors.\n--- Goals (DE) ---\nDie Studierenden erhalten einen anwendungsbezogenen \u00dcberblick \u00fcber das Feld der Musikinformatik. Dabei stehen die Gebiete des Music Information Retrieval (MIR) sowie der Klangsynthese und musikalischen Interfaces im Mittelpunkt. Die Studierenden beherrschen die Grundbegriffe und Methoden des MIR. Sie kennen die Anwendungsgebiete und k\u00f6nnen mit Hilfe von Standardwerkzeugen (z.B. MIRtoolbox) selbst verschiedene Analysen durchf\u00fchren (z.B. Merkmalsextraktion f\u00fcr Audiosignale, Audioidentifikation, Audio Matching). Des Weiteren beherrschen die Studierenden die grundlegenden Konzepte verschiedener Klangsynthesearten und k\u00f6nnen diese in Entwicklungsumgebungen f\u00fcr Musik und Multimedia anwenden (z.B. in Max/MSP). Ein Schwerpunkt liegt dabei auf den g\u00e4ngigen Technologien zur Realisierung der Interaktion zwischen Mensch und (elektronischem) Musikinstrument mittels musikalischer Interfaces bzw. Sensoren.\n--- Contents (EN) ---\nMusic information retrieval (MIR)Fundamentals of MIRStandard tools of MIR (e.g. MIRtoolbox, Auditory toolbox, SOM toolbox)Application of MIR (e.g. music recommendation systems, classification of sounds and music, automatic instrument and genre recognition, automatic transcription and notation systems)Computational auditory scene analysis (CASA), sound synthesis and musical interfacesElectrical and electronic musical instrumentsAnalogue and digital sound synthesisAudio programming (e.g. in Max/MSP, Csound, Pure Data, NI Reaktor), live electronicsMusical interfacesSensor and controller environmentsCommunication protocols for musical applications (e.g. Open Sound Control (OSC), MIDI, HD Protocol, mLAN)\n--- Contents (DE) ---\nMusic Information RetrievalGrundlagen des Music Information Retrieval (MIR)Standardwerkzeuge des MIR (z.B. MIRtoolbox, Auditory toolbox, SOM toolbox)Anwendungen des Music Information Retrieval (u.a. Musikalische Empfehlungsdienste, Klassifikation von Kl\u00e4ngen/Musik, automatische Instrumenten- und Genreerkennung, automatische Transkriptions- und Notationssysteme)CASA - Computational Auditory Scene Analysis, Klangsynthese und musikalische InterfacesElektrische und elektronische MusikinstrumenteAnaloge und digitale KlangsyntheseAudio-Programmierung (z.B. mit Max/MSP, Csound, Pure Data, NI Reaktor) / Live-ElektronikMusikalische InterfacesSensor- und Controllerumgebungen Kommunikationsprotokolle f\u00fcr musikalische Anwendungen (z.B. Open Sound Control (OSC), MIDI, HD Protocol, mLAN)\n--- Literature (EN) ---\n--- Literature (DE) ---\nBeauchamp, J. W.: Analysis, synthesis, and perception of musical sounds : the sound of music, New York Springer (2007)Boulanger, R.: The Csound Book: Perspectives in Software Synthesis, Sound Design, Signal Processing, and Programming. Cambridge MIT Press (2000)Mazzola, G. B.: Elemente der Musikinformatik. Basel Birkh\u00e4user (2006)Miranda, E. R.: Computer sound design: synthesis techniques and programming. Oxford Focal Press (2002)M\u00fcller, M.: Information Retrieval for Music and Motion. Berlin Springer (2007)Russ, M.: Sound Synthesis and Sampling. Oxford Focal Press (2009)Wang, D. L. Brown, G. J.: Computational auditory scene analysis: Principles, algorithms and applications. IEEE Press (2006)Aktuelle Publikationen aus folgenden Konferenzen: ICMC, ICMPC, IEEE, ISMIR, NIME", "metadata": {"moduleNumber": "MMI 05.14", "moduleName": "Music Informatics", "creditPoints": "5.0", "suggestedSemester": 2, "offeredInSeason": "summer_semester", "examType": "project", "heldInLanguage": "de", "reviserName": "Prof. Dr.-Ing. Jochen Steffens", "reviserEmail": "jochen.steffens@hs-duesseldorf.de", "studyProgramId": 11, "source_type": "json"}}
{"id": "MMI05.15", "text": "Title: Media Conception\nModule Number: MMI 05.15\nCredits: 5.0 CP\nSemester: 1\nOffered In: winter_semester\nLanguage: de\nExam Type: portfolio\nInstructor: Prof. Gabriele Schwab-Trapp (gabi.schwab-trapp@hs-duesseldorf.de)\n--- Goals (EN) ---\nThe students have acquired skills to apply a conceptual approach to individual or applied topics. They are able to independently develop contextual content. The students have learned to use design processes to develop and practically implement their own ideas. They have gained experience in creative and constructive cooperation within the seminar and potentially within project groups. They have also practised to deal with different presentation forms.\n--- Goals (DE) ---\nDie Studierenden erwerben F\u00e4higkeiten im konzeptionellen Umgang mit freien oder angewandten Themen und die Bef\u00e4higung zur selbstst\u00e4ndigen Erarbeitung von kontextbezogenen Inhalten. Mithilfe von Gestaltungsprozessen werden die Entwicklung und die praktische Umsetzung eigener Ideen erm\u00f6glicht. Erfahrungen in interdisziplin\u00e4rer, kreativer und konstruktiver Zusammenarbeit werden innerhalb der Seminar- und m\u00f6glicher Projektgruppen sowie im Umgang mit verschiedenen Pr\u00e4sentationsformen gesammelt.\n--- Contents (EN) ---\nThe module focuses on individual or applied topics which will be communicated at the beginning of the semester. A seminar serves to go deeper into the topic and to develop it further, together with the lecturer and the other students. This includes philosophical, insight-oriented and opinion-forming debates. The goal is to develop contextual, visual concepts independently and realise them using different media. The students practise different forms of presentation depending on the topics and results. If excursions relevant to the topics are planned, they will be announced at the beginning of the semester. Media conception is regularly offered as an open, collaborative and interdisciplinary module with students from other departments.\n--- Contents (DE) ---\nInhaltlich werden freie oder angewandte Themen behandelt, die zu Beginn des Semesters vorgestellt werden. Die gemeinsame Vertiefung, Entwicklung und Entfaltung des Themas findet in Seminarform statt. Dazu geh\u00f6rt auch die philosophische, erkenntnisorientierte und meinungsbildende Auseinandersetzung. Ziel ist die selbstst\u00e4ndige Entwicklung und Umsetzung von kontextbezogenen, visuellen Konzepten in unterschiedlichen Medien. Den Themen und Ergebnissen entsprechend werden verschiedene Pr\u00e4sentationsformen einge\u00fcbt. Themenunterst\u00fctzend k\u00f6nnen Exkursionen stattfinden, die zu Beginn des Semesters bekannt gegeben werden. Medienkonzeption wird regelm\u00e4\u00dfig als offenes, kollaboratives und interdisziplin\u00e4res Modul mit Studierenden aus anderen Fachbereichen angeboten.\n--- Literature (EN) ---\nMaterial and literature references are provided for the respective topic in the seminar. Information in the form of text extracts, literature, image examples and research suggestions are provided to support the respective learning, realisation and design steps.\n--- Literature (DE) ---\nMaterial- und Literaturangaben werden zu dem jeweiligen Thema im Seminar ausgegeben. Zur Unterst\u00fctzung der jeweiligen Lern-, Erkenntnis- und Gestaltungsschritte werden Hinweise in Form von Textausz\u00fcgen, Literatur, Bildbeispielen und Recherchevorschl\u00e4gen gegeben.", "metadata": {"moduleNumber": "MMI 05.15", "moduleName": "Media Conception", "creditPoints": "5.0", "suggestedSemester": 1, "offeredInSeason": "winter_semester", "examType": "portfolio", "heldInLanguage": "de", "reviserName": "Prof. Gabriele Schwab-Trapp", "reviserEmail": "gabi.schwab-trapp@hs-duesseldorf.de", "studyProgramId": 11, "source_type": "json"}}
{"id": "MMI05.16", "text": "Title: Machine-Learning for Digital Health & Social Services\nModule Number: MMI 05.16\nCredits: 5.0 CP\nSemester: 2\nOffered In: summer_semester\nLanguage: en_on_demand\nExam Type: portfolio\nInstructor: Prof. Dr. Florian Huber (florian.huber@hs-duesseldorf.de)\n--- Goals (EN) ---\nStudents are able to weigh up and apply the use of previously considered methods for data science and artificial intelligence for the application area of digital health and social services.\n--- Goals (DE) ---\nDie Studierenden sind in der Lage, den Einsatz zuvor betrachteter Methoden f\u00fcr Data Science und K\u00fcnstliche Intelligenz f\u00fcr den Anwendungsbereich Digitale Gesundheit und Soziale Dienste abzuw\u00e4gen und anzuwenden.\n--- Contents (EN) ---\nTechniques from the field of artificial intelligence, especially machine learning, offer numerous promising applications in digital health and social services. This is particularly true for the analysis and use of very large and complex data sets. Examples include medical diagnostics and prognostics, or the large-scale evaluation and linking of text and process data with the aim of optimising or improving processes in healthcare or social services. This event provides an overview of current and future developments in the field. Key machine learning methods will be implemented with real data from the healthcare and social services sectors in live coding sessions.\n- Overview of application areas and common methods in the field of digital health and social services\n- Handling of key data types in the above-mentioned areas: tabular data, image data, time series, text data\n- Conventional linear models in medicine\n- Prediction models of classical machine learning (including linear models, random forest)\n- Evaluation of models and explainable AI\n- Deep learning models (e.g. CNNs) for the classification and segmentation of image data.\n- Deep learning models for the classification of time series (e.g. CNNs, LSTMs).\n- Consideration of related ethical issues regarding the use of AI for critical applications (e.g. biases, interpretability, or privacy).\n--- Contents (DE) ---\nTechniken aus dem Bereich K\u00fcnstliche Intelligenz, insbesondere Machine-Learning, bieten zahlreiche vielversprechende Einsatzm\u00f6glichkeiten im Bereich Digital Health und Social Services. Das gilt besonders f\u00fcr die Analyse und Nutzung von sehr gro\u00dfen und komplexer Datens\u00e4tzen. Beispiele daf\u00fcr sind die medizinische Diagnostik oder Prognose, oder der gro\u00dffl\u00e4chigen Auswertung und Verkn\u00fcpfung von Text- und Prozessdaten mit dem Ziel Abl\u00e4ufe im Gesundheitsbereich oder bei sozialen Diensten zu optimieren oder zu verbessern. Dieser Veranstaltung gibt einen \u00dcberblick \u00fcber aktuelle und zuk\u00fcnftige Entwicklungen in dem Gebiet, Zentrale Machine-Learning Verfahren werden dabei mit realen Daten aus dem Bereich Gesundheit oder Social Services in Live Coding Sessions umgesetzt.\n- \u00dcberblick \u00fcber Einsatzgebiete und g\u00e4ngige Verfahren im Bereich Digital Health und Social Services\n- Behandlung zentraler Datentypen in den genannten Bereichen: Tabellarische Daten, Bilddaten, Zeitserien, Textdaten\n- Konventionelle linear Modelle in der Medizin\n- Vorhersagemodelle des klassischen Machine Learnings (u.a. lineare Modelle, Random Forest).\n- Evaluation von Modellen und Explainable AI\n- Deep Learning Modelle (z.B. CNNs) zur Klassifizierung und Segmentierung von Bilddaten.\n- Deep Learning Modele zur Klassifizierung von Zeitserien (z.B. CNNs, LSTMs).\n- Betrachtung angrenzender ethischer Fragen zum Einsatz von KI f\u00fcr kritische Anwendungen (z.B. Biases, Interpretierbarkeit, oder Privatsh\u00e4re).\n--- Literature (EN) ---\nScientific articles are shared and discussed as part of a journal club. Further literature will be announced at the beginning of the lecture.\n--- Literature (DE) ---\nIm Rahmen eines Journal-Clubs werden wissenschaftliche Fachartikel geteilt und besprochen. Weitere Literatur wird bei Vorlesungsbeginn bekannt gegeben.", "metadata": {"moduleNumber": "MMI 05.16", "moduleName": "Machine-Learning for Digital Health & Social Services", "creditPoints": "5.0", "suggestedSemester": 2, "offeredInSeason": "summer_semester", "examType": "portfolio", "heldInLanguage": "en_on_demand", "reviserName": "Prof. Dr. Florian Huber", "reviserEmail": "florian.huber@hs-duesseldorf.de", "studyProgramId": 11, "source_type": "json"}}
{"id": "MMI05.20", "text": "Title: Distributed Collaborative Systems\nModule Number: MMI 05.20\nCredits: 5.0 CP\nSemester: 1\nOffered In: winter_semester\nLanguage: de\nExam Type: portfolio\nInstructor: Prof. Dr.-Ing. Thomas Rakow (thomas.rakow@hs-duesseldorf.de)\n--- Goals (EN) ---\nThe students have acquired knowledge of distributed systems, their architecture, processes and applications. They are particularly familiar with the requirements of collaborative applications. They are able to evaluate distributed algorithms.\n--- Goals (DE) ---\nDie Teilnehmer erwerben Kenntnisse \u00fcber die Architektur und Funktionsweise verteilter Systeme und Anwendungen, unter besonderer Ber\u00fccksichtigung der Anforderungen kollaborativer Anwendungen. Verteilte Algorithmen k\u00f6nnen bewertet werden.\n--- Contents (EN) ---\nArchitecture of distributed systems\nProcesses and communication\nNaming systems\nSynchronisation in distributed systems\nConsistency and replication\nFault tolerance and security\nParadigms of distributed systems: file, object, coordination, streaming\nCooperation and collaboration\nComputer supported cooperative work\n--- Contents (DE) ---\nArchitekturen verteilter Systeme\nProzesse und Kommunikation\nBenennungs- und Namenssysteme\nSynchronisierung in verteilten Systemen\nKonsistenz und Replikation\nFehlertoleranz und Sicherheit\nParadigmen verteilter Systeme: Datei, Objekt, Koordination, Streaming\nKooperation und Kollaboration\n--- Literature (EN) ---\n--- Literature (DE) ---\nMaarten van Steen, Andrew S. Tanenbaum: Distributed Systems, 3rd Ed. Self-publishing 2017\nM. Tamer \u00d6zsu, Patrick Valduriez: Principles of Distributed Database Systems, 4th Ed., Springer 2020\nFranz Lehner: Wissensmanagement, 6. Aufl. Hanser (2019)", "metadata": {"moduleNumber": "MMI 05.20", "moduleName": "Distributed Collaborative Systems", "creditPoints": "5.0", "suggestedSemester": 1, "offeredInSeason": "winter_semester", "examType": "portfolio", "heldInLanguage": "de", "reviserName": "Prof. Dr.-Ing. Thomas Rakow", "reviserEmail": "thomas.rakow@hs-duesseldorf.de", "studyProgramId": 11, "source_type": "json"}}
{"id": "MMI05.21", "text": "Title: Scientific Work\nModule Number: MMI 05.21\nCredits: 5.0 CP\nSemester: 1\nOffered In: winter_semester\nLanguage: en_on_demand\nExam Type: academic_paper\nInstructor: Prof. Dr. Alina Huldtgren (alina.huldtgren@hs-duesseldorf.de)\n--- Goals (EN) ---\nThe students know and understand the basic aspects of scientific work with the essential methods and tools for the planning, production and documentation of scientific results. They acquire the skills to deal with scientific literature and comparable research documents and to be able to filter out the essentials. The clearly structured and formally correct production of scientific texts in the various variants (house and seminar papers, reports, scientific publications) as well as the presentation of the results, also in English, is known to the students.\n--- Goals (DE) ---\nDie Studierenden kennen und verstehen die grundlegenden Aspekte wissenschaftlichen Arbeitens mit den wesentlichen Methoden und Werkzeuge f\u00fcr die Planung, Produktion und Dokumentation wissenschaftlicher Ergebnisse. Sie erwerben die F\u00e4higkeiten mit wissenschaftlicher Literatur und vergleichbaren Forschungsdokumenten umgehen und das Wesentliche herausfiltern zu k\u00f6nnen. Die klar strukturierte und formal korrekte Produktion wissenschaftlicher Texte in den verschiedenen Varianten (Haus- und Seminararbeiten, Berichte, wiss. Publikationen) sowie die Pr\u00e4sentationen der Ergebnisse, auch in englischer Sprache, ist den Studierenden bekannt.\n--- Contents (EN) ---\nQuality criteria in scienceScientific methods in adjacent relevant scientific fieldsIdentify, rate and cite relevant literatureWrite, evaluate and evaluate scientific textsPrepare, present and document presentationsLead and moderate expert discussions\n--- Contents (DE) ---\nQualit\u00e4tskriterien in der WissenschaftWissenschaftliche Methoden in angrenzenden relevanten WissenschaftsfeldernEinschl\u00e4gige Literatur ermitteln, bewerten und richtig zitierenWissenschaftliche Texte schreiben, evaluieren und bewertenPr\u00e4sentationen vorbereiten, vortragen und dokumentierenFachdiskussionen f\u00fchren und moderieren\n--- Literature (EN) ---\n--- Literature (DE) ---\nH. Balzert, C.Sch\u00e4fer, M. Schr\u00f6der, U.Kern: Wissenschaftliches Arbeiten, W3L GmbH (2008)Norbert Franck: Handbuch Wissenschaftliches Arbeiten, 3. Aufl. Paderborn: Sch\u00f6ningh (2017)Berit Sandberg: Wissenschaftlich Arbeiten von Abbildung bis Zitat. Ein Lehr- und \u00dcbungsbuch f\u00fcr Bachelor, Master und Promotion., Oldenbourg, M\u00fcnchen (2012)", "metadata": {"moduleNumber": "MMI 05.21", "moduleName": "Scientific Work", "creditPoints": "5.0", "suggestedSemester": 1, "offeredInSeason": "winter_semester", "examType": "academic_paper", "heldInLanguage": "en_on_demand", "reviserName": "Prof. Dr. Alina Huldtgren", "reviserEmail": "alina.huldtgren@hs-duesseldorf.de", "studyProgramId": 11, "source_type": "json"}}
{"id": "MMI05.22", "text": "Title: Mobile Systemes\nModule Number: MMI 05.22\nCredits: 5.0 CP\nSemester: 1\nOffered In: winter_semester\nLanguage: de\nExam Type: oral_exam\nInstructor: Prof. Dr.-Ing. M.Sc. Markus Dahm (markus.dahm@hs-duesseldorf.de)\n--- Goals (EN) ---\n- Forms of mobility (device, service, user)\n- Mobile radio technologies (radio technology)\n- Mobile radio systems and protocols (e.g. GSM, UMTS, LTE, 5G)\n- Mobile devices (mobile phone, tablet, smartphone, VR/AR)\n- Mobile services (e.g. SMS, LBS, added value)\n- Mobile applications (e.g. Android, WebApps)\n- Mobile business (mCommerce, mPayment)\n- Mobile content (e.g. information, games)\n- Mobile usability / UX\n- Mobile social impact (technology assessment)\n--- Goals (DE) ---\n- Mobilit\u00e4tsformen (Ger\u00e4t, Dienst, Benutzer)\n- Mobilfunk-Technologien (Funktechnik)\n- Mobilfunk-Systeme und Protokolle (z.B. GSM, UMTS, LTE, 5G)\n- Mobile Ger\u00e4te (Handy, Tablet, Smartphone, VR/AR)\n- Mobile Dienste (z.B. SMS, LBS, Mehrwert)\n- Mobile Anwendungen (z.B. Android, WebApps)\n- Mobile Business (mCommerce, mPayment)\n- Mobile Content (z.B. Information, Spiele)\n- Mobile Usability / UX\n- Mobile Soziale Auswirkungen (Technikfolgenabsch\u00e4tzung)\n--- Contents (EN) ---\nStudents understand the technical fundamentals of mobile systems - both mobile devices and the infrastructure - and their impact on the use and development of mobile applications. They are familiar with various mobile services and know how they can be linked to business models. Students will be familiar with typical mobile devices and some of the options for developing customised applications for them, taking into account the special characteristics of the mobile usage context.\n--- Contents (DE) ---\nStudierende verstehen die technischen Grundlagen mobiler Systeme - sowohl der mobilen Ger\u00e4te als auch der Infrastruktur - und ihre Auswirkungen auf die Nutzung und die Entwicklung mobiler Anwendungen. Sie kennen verschiedene mobile Dienste und wissen, wie sie mit Gesch\u00e4ftsmodellen verkn\u00fcpft werden k\u00f6nnen. \nDie Studierenden kennen typische mobile Ger\u00e4te sowie einige M\u00f6glichkeiten, darauf angepasste Anwendungen zu entwickeln, wobei sie die besonderen Eigenschaften des mobilen Nutzungskontextes ber\u00fccksichtigen k\u00f6nnen.\n--- Literature (EN) ---\n- Schiller: Mobilkommunikation, Pearson (2003)\n- Tanenbaum, van Steen: Verteilte Systeme, Pearson (2007)\n- http://www.wi-mobile.de/\n- http://www.eco.de/arbeitskreise/mobile.htm\n- http://www.heise.de/mobil/\n- http://developer.android.com\n--- Literature (DE) ---\n- Schiller: Mobilkommunikation, Pearson (2003)\n- Tanenbaum, van Steen: Verteilte Systeme, Pearson (2007)\n- http://www.wi-mobile.de/\n- http://www.eco.de/arbeitskreise/mobile.htm\n- http://www.heise.de/mobil/\n- http://developer.android.com", "metadata": {"moduleNumber": "MMI 05.22", "moduleName": "Mobile Systemes", "creditPoints": "5.0", "suggestedSemester": 1, "offeredInSeason": "winter_semester", "examType": "oral_exam", "heldInLanguage": "de", "reviserName": "Prof. Dr.-Ing. M.Sc. Markus Dahm", "reviserEmail": "markus.dahm@hs-duesseldorf.de", "studyProgramId": 11, "source_type": "json"}}
{"id": "MMI05.23", "text": "Title: Medial Productions\nModule Number: MMI 05.23\nCredits: 5.0 CP\nSemester: 2\nOffered In: summer_semester\nLanguage: de\nExam Type: project\nInstructor: Prof. Dr. rer. nat. Christian Geiger (geiger@hs-duesseldorf.de)\n--- Goals (EN) ---\nThe participants learn the procedures in the conception, design, development, construction and operation of media staging. Conceptual, design, technical and economic aspects are considered in equal parts. By critically discussing current or historically significant examples, participants can assess media staging and reflect critically on their work from different perspectives. The participants have practical experience in the pre-visualization and final implementation of simple installation concepts based on selected marketable or freely available tools.\n--- Goals (DE) ---\nDie Teilnehmer lernen die Vorgehensweisen bei der Konzeption, Gestaltung, Entwicklung, Aufbau und Betrieb medialer Inszenierungen. Dabei werden konzeptionelle, gestalterische, technische und wirtschaftliche Aspekte zu gleichen Teilen betrachtet. Durch die kritische Diskussion aktueller bzw. historisch bedeutsamer Beispiele k\u00f6nnen die Teilnehmer mediale Inszenierungen beurteilen und den Einsatz aus verschiedenen Blickwinkeln kritisch reflektieren. Die Teilnehmer besitzen praktische Erfahrung in der Pr\u00e4visualisierung und finalen Umsetzung einfacher Installationskonzepte auf Basis ausgew\u00e4hlter marktg\u00e4ngiger bzw. frei verf\u00fcgbarer Werkzeuge.\n--- Contents (EN) ---\n- Theoretical foundations of media staging (perception, artistic expression, media architectures)\n- Analysis of historically relevant examplesTransmedia spaces, video art and performances\n- Selected forms of media staging, \n- Attempt at typification\n- Selected technical aspects of digital and physical object and space design (projection mapping, multi-displays, VR/AR)\n-Tools for media productions\n-Workflow planning and operation of extensive installations\n- Audience development and user feedback\n- Critical reflection and impact from multiple perspectives (artistic, technical, economic, social)\n--- Contents (DE) ---\nTheoretische Grundlagen medialer Inszenierung (Wahrnehmung, k\u00fcnstlerischer Ausdruck, mediale Architekturen)\n- Analyse historisch relevanter BeispieleTransmediale R\u00e4ume, Videokunst und Performances\n- Ausgew\u00e4hlte Formen medialer Inszenierung, \n- Versuch einer Typisierung\n- Ausgew\u00e4hlte technische Aspekte des digitale und physischen Objekt- und Raumdesigns (Projection Mapping, Multi-Displays, VR/AR)\n-Werkzeuge f\u00fcr mediale Inszenierungen\n-WorkflowPlanung und Betrieb umfangreicher Installationen\n- Audience Development und Nutzerfeedback\n- Kritische Reflektion und Impact aus multiplen Perspektiven (k\u00fcnstlerisch, technisch, wirtschaftlich, sozial)\n--- Literature (EN) ---\n--- Literature (DE) ---\n- Claire Bishop: Installation Art, Tate Publishing (2005)\n- New Installation Art, Ginko Press (2013)\n- The Complete Book of Mixed Media Art, Walter Foster Creative Team, 2018\n- Aktuelle Ausstellungskataloge erfolgreicher Inszenierungen", "metadata": {"moduleNumber": "MMI 05.23", "moduleName": "Medial Productions", "creditPoints": "5.0", "suggestedSemester": 2, "offeredInSeason": "summer_semester", "examType": "project", "heldInLanguage": "de", "reviserName": "Prof. Dr. rer. nat. Christian Geiger", "reviserEmail": "geiger@hs-duesseldorf.de", "studyProgramId": 11, "source_type": "json"}}
{"id": "MMI05.24", "text": "Title: Qualitative and Quantitative Methods\nModule Number: MMI 05.24\nCredits: 5.0 CP\nSemester: 1\nOffered In: winter_semester\nLanguage: de\nExam Type: none\nInstructor: Prof. Dr. Thomas Franz (thomas.franz@hs-duesseldorf.de)\n--- Goals (EN) ---\nThe students understand that there are fundamentally different ways to gather and analyse data to evaluate concepts and prototypes of digital media. They also know the epistemological background of these different approaches respectively. The students are able to determine the most suitable method to work on a given research question. They can apply both quantitative and qualitative methods in practice and analyse data accordingly. In terms of quantitative methods, the students can design and implement methods and technologies for experiments, form hypotheses, plan experiments and perform statistical evaluations. In terms of qualitative methods, the students can prepare a suitable interview guide, record observation results, code data in different ways and prepare a thematic map.\n--- Goals (DE) ---\nDie Studierenden verstehen, dass es grundlegend unterschiedliche Arten der Datensammlung und Analyse zur Evaluation von Konzepten und Prototypen digitaler Medien gibt und welchen erkenntnistheoretischen Hintergrund diese haben. Sie k\u00f6nnen anhand einer Forschungsfrage analysieren, welche Methodik sich am besten zur Beantwortung der Frage eignet. Sie k\u00f6nnen sowohl quantitative als auch qualitative Methoden in der Praxis anwenden und die Daten dementsprechend analysieren. Im Bereich der quantitativen Methoden, k\u00f6nnen Studierende Konstrukte zur Messung operationalisieren, Hypothesen aufstellen, Experimente planen, und statistische Auswertungen vornehmen. Im Bereich der qualitativen Methoden k\u00f6nnen Studierende einen Interviewleitfaden erstellen, ein Beobachtungsprotokoll erstellen, verschiedene Kodierungen der Daten vornehmen und eine Thematic Map erstellen.\n--- Contents (EN) ---\nIntroduction to the differences between quantitative and qualitative research from an epistemological perspectiveDeveloping research questions and determining suitable methods to work on themIntroduction to scientific experiments, formation of hypotheses, operationalisation, testing of hypothesis, statistical data analysisIntroduction to qualitative, empirical data acquisition by means of observation, interviews, focus groups and diaries\n--- Contents (DE) ---\nEinf\u00fchrung in die Unterschiede quantitativer und qualitativer Forschung aus erkenntnistheoretischer SichtEntwicklung von Forschungsfragen und Auswahl geeigneter Methoden zur BeantwortungEinf\u00fchrung in wiss. Experimente, Hypothesenbildung, Operationalisierung, Hypothesentesten, statistische DatenanalyseEinf\u00fchrung in die Erhebung qualitativer, empirischer Daten durch Beobachtungen, Interviews, Fokusgruppen und Tageb\u00fccher.\n--- Literature (EN) ---\n--- Literature (DE) ---\nD\u00f6ring, N. und Bortz, J.: Forschungsmethoden und Evaluation in den Sozial- und Humanwissenschaften, 3. Auflage Springer (2016)", "metadata": {"moduleNumber": "MMI 05.24", "moduleName": "Qualitative and Quantitative Methods", "creditPoints": "5.0", "suggestedSemester": 1, "offeredInSeason": "winter_semester", "examType": "none", "heldInLanguage": "de", "reviserName": "Prof. Dr. Thomas Franz", "reviserEmail": "thomas.franz@hs-duesseldorf.de", "studyProgramId": 11, "source_type": "json"}}
{"id": "MMI05.25", "text": "Title: Image Processing\nModule Number: MMI 05.25\nCredits: 5.0 CP\nSemester: 2\nOffered In: to_be_announced\nLanguage: de\nExam Type: portfolio\nInstructor: Prof. Dr.-Ing. Thomas Bonse (thomas.bonse@hs-duesseldorf.de)\n--- Goals (EN) ---\nStudents develop a profound understanding of the fundamental concepts of digital image processing. Students are familiar with advanced image processing algorithms and are able to apply them.\nStudents are able to apply theoretical concepts of image processing to real-world problems.\nStudents acquire practical experience in the implementation of image processing algorithms. They deepen their programming skills and strengthen their handling of relevant software tools in order to evaluate their results.\n--- Goals (DE) ---\nDie Studierenden entwickeln ein fundiertes Verst\u00e4ndnis der grundlegenden Konzepte in der digitalen Bildverarbeitung. Die Studierenden kennen fortgeschrittene Bildverarbeitungsalgorithmen und k\u00f6nnen diese anwenden.\nDie Studierenden sind in der Lage, theoretische Konzepte der Bildverarbeitung auf reale Probleme anzuwenden.\nDie Studierenden erwerben praktische Erfahrung in der Implementierung von Bildverarbeitungsalgorithmen. Sie vertiefen ihre F\u00e4higkeiten in der Programmierung und st\u00e4rken Ihren Umgang mit relevanten Softwaretools, um ihre Ergebnisse zu evaluieren.\n--- Contents (EN) ---\nThe module offers an in-depth examination of advanced concepts and techniques in the processing of digital images. The module focuses on theoretical foundations, algorithmic approaches and practical applications in order to provide students with a comprehensive understanding of digital image processing. Bachelor's and Master's students each receive customised subtasks. \n1. theoretical basics: image representation, colour models, image filtering and transformations.\n2. algorithms and techniques: Digital filters, image segmentation, pattern recognition, feature extraction and description, and algorithms from image coding\n3. applications in practice: feature extraction, image recognition and interpretation, machine vision. \n4. programming and implementation.\n--- Contents (DE) ---\nDas Modul bietet eine vertiefte Auseinandersetzung mit fortgeschrittenen Konzepten und Techniken in der Verarbeitung von digitalen Bildern. Das Modul legt den Fokus auf theoretische Grundlagen, algorithmische Ans\u00e4tze und praktische Anwendungen, um den Studierenden ein umfassendes Verst\u00e4ndnis f\u00fcr die digitale Bildverarbeitung zu vermitteln. Bachelor- und Masterstudierende erhalten jeweils angepasste Teilaufgaben. \n1. Theoretische Grundlagen: Bildrepr\u00e4sentation, Farbmodelle, Bildfilterung und Transformationen.\n2. Algorithmen und Techniken: Digitale Filter, Bildsegmentierung, Mustererkennung, Merkmalsextraktion und -beschreibung sowie Algorithmen aus der Bildcodierung.\n3. Anwendungen in der Praxis: Feature Extraction, Bilderkennung und Interpretation, maschinelles Sehen. \n4. Programmierung und Implementierung.\n--- Literature (EN) ---\n- Gonzalez, R.C., Woods, R.E.: Digital Image Processing, Pearson 2008\n- Burger,  W., Burge, M.J.: Digital Image Processing, Springer 2022\n- Burger, W., Burge, M.J.: Digitale Bildverarbeitung - Eine algorithmische Einf\u00fchrung mit Java, Springer 2015\n- Russ, J.C.: The Image Processing Handbook, CRC Press 2018\n- J\u00e4hne, B.: Digitale Bildverarbeitung und Bildgewinnung, Springer 2012\n--- Literature (DE) ---\n- Gonzalez, R.C., Woods, R.E.: Digital Image Processing, Pearson 2008\n- Burger,  W., Burge, M.J.: Digital Image Processing, Springer 2022\n- Burger, W., Burge, M.J.: Digitale Bildverarbeitung - Eine algorithmische Einf\u00fchrung mit Java, Springer 2015\n- Russ, J.C.: The Image Processing Handbook, CRC Press 2018\n- J\u00e4hne, B.: Digitale Bildverarbeitung und Bildgewinnung, Springer 2012", "metadata": {"moduleNumber": "MMI 05.25", "moduleName": "Image Processing", "creditPoints": "5.0", "suggestedSemester": 2, "offeredInSeason": "to_be_announced", "examType": "portfolio", "heldInLanguage": "de", "reviserName": "Prof. Dr.-Ing. Thomas Bonse", "reviserEmail": "thomas.bonse@hs-duesseldorf.de", "studyProgramId": 11, "source_type": "json"}}
{"id": "MMI05.26", "text": "Title: Digital Storytelling\nModule Number: MMI 05.26\nCredits: 5.0 CP\nSemester: 1\nOffered In: to_be_announced\nLanguage: de\nExam Type: project\nInstructor: Prof. Dr. rer. nat. Christian Geiger (geiger@hs-duesseldorf.de)\n--- Goals (EN) ---\nThe students know the concepts of digital storytelling and narrative structures. They can use the necessary practical fundamentals in various fields of application (e.g. games, marketing, social media). They can describe the design process of digital storytelling and apply basic principles for the development of narrative structures to various formats. In addition, they can outline other current issues as well as solutions in the field of digital and non-linear storytelling.\n--- Goals (DE) ---\nDie Studierenden kennen das Konzept des \u201eDigital Storytelling\u201c und narrativer Strukturen und beherrschen die notwendigen praktischen Grundlage in verschiedene Anwendungsbereiche (wie Games, Marketing, Social Media) transferieren. Sie k\u00f6nnen den Entwurfsprozess des Digital Storytellings beschreiben und grunds\u00e4tzliche Prinzipien der Entwicklung narrativer Strukturen f\u00fcr verschiedene Formate anwenden. Au\u00dferdem k\u00f6nnen sie weitere aktuelle Fragestellungen sowie deren L\u00f6sungen aus dem Bereich digitales und nicht-lineares Storytelling skizzieren.\n--- Contents (EN) ---\nTelling stories: history and narrative fundamentalsStorytelling in filmsStorytelling in gamesScripts and storyboardsStorytelling as a marketing toolForms of digital storytellingStorytelling in virtual realityInteractive storytelling (non-linear)Multimodal storytellingTransmedia storytellingWeb 2.0 storytellingSocial media storytellingNew forms of storytelling for new media\n--- Contents (DE) ---\nGeschichten erz\u00e4hlen: Historie und narrative GrundlagenStorytelling im FilmStorytelling in GamesScripts and StoryboardsStorytelling als Marketing InstrumentFormen von Digital StorytellingStorytelling in der Virtuellen Realit\u00e4tInteractive Storytelling (nonlinear)Multimodales StorytellingTransmedia Storytelling Web 2.0 StorytellingSocial Media StorytellingNeue Storytelling Formen f\u00fcr neue Medien\n--- Literature (EN) ---\n--- Literature (DE) ---\nBryan Alexander: The New Digital Storytelling: Creating Narratives with New Media, ABC-ClioDennis Eick: Digitales Erz\u00e4hlen. Die Dramaturgie der Neuen Medien, UVK VerlagsgesellschaftPia Kleine Wieskamp: Storytelling: Digital - Multimedial - Social: Formen und Praxis f\u00fcr PR, Marketing, TV, Game und Social Media, HanserMedienNetzwerk Bayern: Story Now: Ein Handbuch f\u00fcr digitales Erz\u00e4hlen, mixtvisionDavid Lochner: Storytelling in virtuellen Welten, UVK Verlagsgesellschaft", "metadata": {"moduleNumber": "MMI 05.26", "moduleName": "Digital Storytelling", "creditPoints": "5.0", "suggestedSemester": 1, "offeredInSeason": "to_be_announced", "examType": "project", "heldInLanguage": "de", "reviserName": "Prof. Dr. rer. nat. Christian Geiger", "reviserEmail": "geiger@hs-duesseldorf.de", "studyProgramId": 11, "source_type": "json"}}
{"id": "MMI05.27", "text": "Title: Design Thinking\nModule Number: MMI 05.27\nCredits: 5.0 CP\nSemester: None\nOffered In: to_be_announced\nLanguage: en_on_demand\nExam Type: project\nInstructor: Prof. Dr. Alina Huldtgren (alina.huldtgren@hs-duesseldorf.de)\n--- Goals (EN) ---\nThe students understand why it is important to keep a balance between user focus, economical considerations and technical feasibility for the development of new digital media. In this context, they have learned about the wicked problems, which designers often face today. The students know the process of design thinking and its five phases: understanding, observing, point-of-view, brainstorming, prototyping and refinement. They have applied methods of the Stanford d.school to a design task.\n--- Goals (DE) ---\nDie Studierenden verstehen, warum eine Balance zwischen Nutzerfokus, \u00f6konomischen Abw\u00e4gungen und technischer Machbarkeit zur Entwicklung neuer digitaler Medien wichtig ist. In diesem Zusammenhang lernen sie das Konzept des Wicked Problems kennen, mit denen Designer sich heutzutage oft konfrontiert sehen. Die Studierenden lernen den Prozess des Design Thinkings mit den 5 Schritten: Verstehen, Beobachten, Point-of-View, Ideenfindung, Prototyping, und Verfeinerung kennen und wenden Methoden der Standford d.school in einer Designaufgabe an.\n--- Contents (EN) ---\nTeam building exercise (e.g. the Marshmallow Challenge)Introduction to wicked problems and changing requirements for the design of digital media in the digital ageOverview of design thinking: five phases, T-shaped people, principles of design thinking (e.g. \u2018Show, don\u2019t tell!\u2019, radical collaboration etc.)Application of individual design thinking methods in the different phasesSelected approaches of iterative prototyping according to the topic of the courseProject work in groups on a previously selected problem area and a suitable research question\n--- Contents (DE) ---\nTeambuilding mittels Marshmallow Challenge oder vgl.Einf\u00fchrung Wicked Problems und Ver\u00e4nderungen der Anforderungen an das Design digitaler Medien im Zeitalter der Digitalisierung\u00dcbersicht Design Thinking: 5 Phasen, T-Shaped People, Prinzipien des Design Thinkings (z.B. Show don't tell, Radical Collaboration, etc)Anwendung einzelner Design Thinking Methoden in den PhasenAusgew\u00e4hlte Ans\u00e4tze des iterativen Prototypings je nach gew\u00e4hltem Themenkomplex der VeranstaltungProjektarbeit in Gruppen bzgl eines zuvor ausgew\u00e4hlten Problembereichs und einer geeigneten Fragestellung\n--- Literature (EN) ---\n--- Literature (DE) ---\nJ\u00fcrgen Erbeldinger, Thomas Ramge, Erik Spiekermann: Durch die Decke denken: Design Thinking in der Praxis, Redline (2013)Martin J. Eppler: Creability: Gemeinsam kreativ - innovative Methoden f\u00fcr die Ideenentwicklung in Teams, Sch\u00e4fer/Poeschel (2014)Sebastian Olma, Yulia Kryazheva: The Serendipity Machine, Verlag Stitching Society (2013)Thomas Brown: Change by design, Harper Business (2009)", "metadata": {"moduleNumber": "MMI 05.27", "moduleName": "Design Thinking", "creditPoints": "5.0", "suggestedSemester": null, "offeredInSeason": "to_be_announced", "examType": "project", "heldInLanguage": "en_on_demand", "reviserName": "Prof. Dr. Alina Huldtgren", "reviserEmail": "alina.huldtgren@hs-duesseldorf.de", "studyProgramId": 11, "source_type": "json"}}
{"id": "MMI05.28", "text": "Title: Selected Aspects of Multimedia Systems\nModule Number: MMI 05.28\nCredits: 5.0 CP\nSemester: None\nOffered In: every_semester\nLanguage: de\nExam Type: none\nInstructor: Prof. Dr. Thomas Franz (thomas.franz@hs-duesseldorf.de)\n--- Goals (EN) ---\nThe students know relevant concepts, systems, technologies and fields of application of a selected area of media informatics. Having familiarised themselves with the topic, they are able to critically evaluate existing work or independently develop new approaches.\n--- Goals (DE) ---\nDer Studierende kennt f\u00fcr einen ausgew\u00e4hlten Bereich der\nMedieninformatik die zugrunde liegenden Konzepte, Systeme & Technologien bzw.\nAnwendungsgebiete. Nach der Einarbeitung in die Thematik ist er in der Lage\nexistierende Arbeiten kritisch zu beurteilen bzw. neue Ans\u00e4tze eigenst\u00e4ndig zu\nentwickeln.\n--- Contents (EN) ---\nEach semester, the lecturer determines the contents for the semester and the study programme director confirms them. This module serves as a placeholder to be able to react flexibly to new developments in media informatics or to include relevant topics from other study programmes. The topics mustbe closely related to media informatics andhave an orientation which is comparable to the orientation of the compulsory elective modules from the professional specialisation Multimedia Systems and Applications.\n--- Contents (DE) ---\nDieses Modul dient als Platzhalter um flexibel auf neue Entwick-lungen in der Medieninformatik / Vertiefungsrichtung \u201eDigitalisie-rung in multimedialen Systemen\u201c zu reagieren bzw. auch um relevante F\u00e4cher aus anderen Studieng\u00e4ngen importieren zu k\u00f6nnen. Die F\u00e4cher m\u00fcssen einen starken Bezug zur Medienin-formatik auf Masterniveau besitzen und in der Ausrichtung ver-gleichbar sein mit WPF-Modulen aus der Vertiefungsrichtung \u201eDigitalisierung in multimedialen Systemen\u201c. Die Inhalte werden von dem jeweiligen Dozenten festgelegt und durch den Studien-gangskoordinator best\u00e4tigt. Bereits fr\u00fcher importierte, externe Module:\u2022\t\"E-Business\u201c aus BMI PO 2018 (Pr\u00fcfungsumfang mit Mas-terniveau nach Absprache)\u2022\t\u201eEntwicklung sicherer Software\u201c aus BMI PO 2018 (Pr\u00fc-fungsumfang mit Masterniveau nach Absprache)\u2022\t\u201eMusikalische Akustik\u201c aus BTB PO 2018 (Pr\u00fcfungsumfang mit Masterniveau nach Absprache)\n--- Literature (EN) ---\n--- Literature (DE) ---\nLiteratur wird vom jeweiligen Dozenten bekannt gegeben. Verst\u00e4rkt werden neben einschl\u00e4gigen Lehrb\u00fcchern auch Beitr\u00e4ge aus Fachzeitschriften und Konferenzen als Literatur eingesetzt.", "metadata": {"moduleNumber": "MMI 05.28", "moduleName": "Selected Aspects of Multimedia Systems", "creditPoints": "5.0", "suggestedSemester": null, "offeredInSeason": "every_semester", "examType": "none", "heldInLanguage": "de", "reviserName": "Prof. Dr. Thomas Franz", "reviserEmail": "thomas.franz@hs-duesseldorf.de", "studyProgramId": 11, "source_type": "json"}}
{"id": "MMI05.29", "text": "Title: Selected Aspects of Virtual Environments\nModule Number: MMI 05.29\nCredits: 5.0 CP\nSemester: None\nOffered In: every_semester\nLanguage: en_on_demand\nExam Type: none\nInstructor: Prof. Dr. Eng. Univ. of Tsukuba Jens Herder (jens.herder@hs-duesseldorf.de)\n--- Goals (EN) ---\nThe student knows the underlying concepts, systems & technologies and areas of application for a selected area of Virtual Environments / Media Informatics. After familiarising themselves with the topic, they will be able to critically assess existing work and independently develop new approaches.\n--- Goals (DE) ---\nDer Studierende kennt f\u00fcr einen ausgew\u00e4hlten Bereich der Richtung\nVirtueller Umgebungen / Medieninformatik die zugrunde liegenden Konzepte, Systeme\n& Technologien bzw. Anwendungsgebiete. Nach der Einarbeitung in die\nThematik ist er in der Lage, existierende Arbeiten kritisch zu beurteilen bzw.\nneue Ans\u00e4tze eigenst\u00e4ndig zu entwickeln.\n--- Contents (EN) ---\nEach semester, the lecturer determines the contents for the semester and the study programme director confirms them. This module serves as a placeholder to be able to react flexibly to new developments in virtual systems and media informatics or to include relevant topics from other study programmes. The topics mustbe closely related to media informatics andhave an orientation which is comparable to the orientation of the compulsory elective modules from the professional specialisation Virtual Environments.\n--- Contents (DE) ---\nDieses Modul dient als Platzhalter um flexibel auf neue Entwicklungen in der Medieninformatik / Vertiefungsrichtung \u201eVirtuelle Umgebungen\u201c zu reagieren bzw. auch relevante F\u00e4cher aus anderen Studieng\u00e4ngen importieren zu k\u00f6nnen. Die F\u00e4cher m\u00fcssen einen starken Bezug zur Medieninformatik auf Masterniveau besitzen und in der Ausrichtung vergleichbar sein mit WPF-Modulen aus der Vertiefungsrichtung \u201eVirtuelle Umgebungen\u201c. Die Inhalte werden von dem jeweiligen Dozenten festgelegt und durch den Studiengangskoordinator best\u00e4tigt. Bereits fr\u00fcher importierte, externe Module:\u201eEinf\u00fchrung in die 3D Modellierung\u201c aus BMI PO 2018 (Pr\u00fcfungsumfang mit Masterniveau nach Absprache)\u201ePencils and Polygons\u201c aus BMT PO 2018 (Pr\u00fcfungsumfang mit Masterniveau nach Absprache)\n--- Literature (EN) ---\nRecommended literature will be announced depending on the topic. In addition to relevant books, the recommendations may include articles from specialist journals and contributions from conferences.\n--- Literature (DE) ---\nWird vom jeweiligen Dozenten bekannt gegeben. Verst\u00e4rkt werden neben einschl\u00e4gigen Lehrb\u00fcchern auch Beitr\u00e4ge aus Fachzeitschriften und Konferenzen als Literatur eingesetzt.", "metadata": {"moduleNumber": "MMI 05.29", "moduleName": "Selected Aspects of Virtual Environments", "creditPoints": "5.0", "suggestedSemester": null, "offeredInSeason": "every_semester", "examType": "none", "heldInLanguage": "en_on_demand", "reviserName": "Prof. Dr. Eng. Univ. of Tsukuba Jens Herder", "reviserEmail": "jens.herder@hs-duesseldorf.de", "studyProgramId": 11, "source_type": "json"}}
{"id": "MMI05.30", "text": "Title: Digital Literacy & AI Literacy\nModule Number: MMI 05.30\nCredits: 5.0 CP\nSemester: 1\nOffered In: winter_semester\nLanguage: de\nExam Type: portfolio\nInstructor: Prof. Dr. rer. nat. Michael Marmann (marmann@hs-duesseldorf.de)\n--- Goals (EN) ---\nThe students\n\n- recognize the importance of digital literacy in today's information society.\n- understand the basic concepts and applications of artificial intelligence.\n- can critically evaluate digital tools and use them effectively for different purposes.\n- are able to identify and discuss the ethical and social implications of AI use.\n- develop the ability to analyze AI technologies in terms of data protection and data security.\n- can design and implement their own projects using AI elements.\n- can research and structure a current topic and present it at several levels of abstraction \n- are able to argue a topic in the seminar group \n- can prepare a current topic digitally and with interactive elements\n--- Goals (DE) ---\nDie Studierenden\n\n- erkennen die Bedeutung von Digital Literacy in der heutigen Informationsgesellschaft.\n- verstehen die grundlegenden Konzepte und Anwendungen k\u00fcnstlicher Intelligenz.\n- k\u00f6nnen digitale Werkzeuge kritisch bewerten und effektiv f\u00fcr verschiedene Zwecke einsetzen.\n- sind in der Lage, ethische und soziale Implikationen der KI-Nutzung zu identifizieren und zu diskutieren.\n- entwickeln die F\u00e4higkeit, KI-Technologien in Bezug auf Datenschutz und Datensicherheit zu analysieren.\n- k\u00f6nnen eigene Projekte unter Einbeziehung von AI-Elementen konzipieren und umsetzen.\n- k\u00f6nnen ein aktuelles Thema recherchieren, strukturieren und auf mehreren Abstraktionslevels pr\u00e4sentieren \n- k\u00f6nnen ein bearbeitetes Thema in der Seminargruppe argumentativ vertreten \n- k\u00f6nnen ein aktuelles Thema digital und mit interaktiven Elementen aufbereiten\n--- Contents (EN) ---\nThe 'Digital Literacy & AI Literacy' seminar provides students with an in-depth understanding of the digital literacies necessary to navigate effectively in the modern world. It covers the skills needed to search, evaluate and create information digitally. The focus is on critically examining the reliability and credibility of digital content.\n\nIn parallel, there is a focus on AI Literacy, which covers the understanding and application of artificial intelligence in different areas of life and work. Students will learn the basic principles of AI systems, including machine learning and data processing. They deal with the latest developments in the field of AI and reflect on their impact on society and the individual.\n\nThe seminar also examines the ethical aspects of digital and AI technologies, such as data protection, algorithmic bias and the effects of automation on the labor market. Methods are developed to deal with these challenges and students are enabled to plan and implement their own digital and AI-related projects.\n--- Contents (DE) ---\nDas Seminar \"Digital Literacy & AI Literacy\" bietet den Studierenden ein tiefgreifendes Verst\u00e4ndnis der digitalen Kompetenzen, die notwendig sind, um in der modernen Welt effektiv zu navigieren. Es behandelt die F\u00e4higkeiten, die ben\u00f6tigt werden, um Informationen digital zu suchen, zu bewerten und zu erstellen. Im Zentrum steht die kritische Auseinandersetzung mit der Verl\u00e4sslichkeit und Glaubw\u00fcrdigkeit von digitalen Inhalten.\n\nParallel dazu wird ein Schwerpunkt auf AI Literacy gelegt, der das Verst\u00e4ndnis und die Anwendung von k\u00fcnstlicher Intelligenz in verschiedenen Lebens- und Arbeitsbereichen umfasst. Die Studierenden lernen die Grundprinzipien von KI-Systemen kennen, einschlie\u00dflich maschinellem Lernen und Datenverarbeitung. Sie setzen sich mit den neuesten Entwicklungen im Bereich der KI auseinander und reflektieren deren Auswirkungen auf Gesellschaft und Individuum.\n\nDas Seminar beleuchtet zudem die ethischen Aspekte der digitalen und KI-Technologien, wie Datenschutz, Bias in Algorithmen (algorithmic bias) und die Auswirkungen der Automatisierung auf den Arbeitsmarkt. Es werden Methoden erarbeitet, um mit diesen Herausforderungen umzugehen und die Studierenden dazu bef\u00e4higt, eigene digitale und KI-bezogene Projekte zu planen und zu realisieren.\n--- Literature (EN) ---\nCurrent literature references and sources of information are provided at the beginning of the module or directly from the course context. In addition, digital media are increasingly used as a source of knowledge.\n--- Literature (DE) ---\nAktuelle Literaturhinweise und Informationsquellen werden zu Beginn des Moduls oder unmittelbar aus dem Veranstaltungskontext herausgegeben. Zus\u00e4tzlich werden verst\u00e4rkt digitale Medien als Wissensquelle eingesetzt.", "metadata": {"moduleNumber": "MMI 05.30", "moduleName": "Digital Literacy & AI Literacy", "creditPoints": "5.0", "suggestedSemester": 1, "offeredInSeason": "winter_semester", "examType": "portfolio", "heldInLanguage": "de", "reviserName": "Prof. Dr. rer. nat. Michael Marmann", "reviserEmail": "marmann@hs-duesseldorf.de", "studyProgramId": 11, "source_type": "json"}}
{"id": "MMI05.31", "text": "Title: New Work & New Learning\nModule Number: MMI 05.31\nCredits: 5.0 CP\nSemester: 2\nOffered In: summer_semester\nLanguage: de\nExam Type: portfolio\nInstructor: Prof. Dr. rer. nat. Michael Marmann (marmann@hs-duesseldorf.de)\n--- Goals (EN) ---\nThe students\n\n- understand the concepts and driving forces behind the New Work movement.\n- can identify the principles of New Learning and apply them to educational contexts.\n- are able to design modern working and learning environments that promote creativity and innovation.\n- can critically analyze the effects of new technologies on work and education.\n- develop skills to act as change agents in their organizations.\n- can implement interdisciplinary approaches for lifelong learning and agile work processes.\n- can research and structure a current topic and present it at several levels of abstraction.\n- can argue a topic in the seminar group.\n- can prepare a current topic digitally and with interactive elements.\n--- Goals (DE) ---\nDie Studierenden\n- verstehen die Konzepte und treibenden Kr\u00e4fte hinter der New Work-Bewegung.\n- k\u00f6nnen die Prinzipien des New Learning identifizieren und auf Bildungskontexte anwenden.\n- sind in der Lage, moderne Arbeits- und Lernumgebungen zu gestalten, die Kreativit\u00e4t und Innovation f\u00f6rdern.\n- k\u00f6nnen kritisch die Auswirkungen neuer Technologien auf Arbeit und Bildung analysieren.\n- entwickeln F\u00e4higkeiten, um als Change Agents in ihren Organisationen zu fungieren.\n- k\u00f6nnen interdisziplin\u00e4re Ans\u00e4tze f\u00fcr lebenslanges Lernen und agile Arbeitsprozesse implementieren.\n- k\u00f6nnen ein aktuelles Thema recherchieren, strukturieren und auf mehreren Abstraktionslevels pr\u00e4sentieren.\n- k\u00f6nnen ein bearbeitetes Thema in der Seminargruppe argumentativ vertreten.\n- k\u00f6nnen ein aktuelles Thema digital und mit interaktiven Elementen aufbereiten.\n--- Contents (EN) ---\nThis seminar deals with the current changes in the world of work and their influence on learning processes. The basics of the New Work movement, which focuses on autonomy, flexibility and participation in the workplace, as well as the principles of New Learning, which emphasizes self-directed learning and the use of new technologies, are covered. Students learn about innovative approaches to the design of working and learning environments that take into account both the individual needs of learners and the requirements of modern organizations.\n\nAn essential part of the seminar is the examination of the challenges and opportunities that digital technologies bring for the world of work and education. Concepts such as lifelong learning, knowledge management and skills development in the context of New Work and New Learning will be discussed.\n\nThe seminar promotes the development of skills that enable participants to act as change agents and implement interdisciplinary approaches in their own professional contexts. This includes critical reflection on existing structures and the ability to design and manage agile and flexible learning and work processes.\n--- Contents (DE) ---\nDieses Seminar besch\u00e4ftigt sich mit den aktuellen Ver\u00e4nderungen in der Arbeitswelt und deren Einfluss auf Lernprozesse. Es werden die Grundlagen der New Work-Bewegung, die auf Autonomie, Flexibilit\u00e4t und Partizipation am Arbeitsplatz abzielt, sowie die Prinzipien des New Learning, welches Selbstgesteuertes Lernen und den Einsatz neuer Technologien in den Vordergrund stellt, behandelt. Die Studierenden lernen innovative Ans\u00e4tze zur Gestaltung von Arbeits- und Lernumgebungen kennen, die sowohl die individuellen Bed\u00fcrfnisse der Lernenden als auch die Anforderungen moderner Organisationen ber\u00fccksichtigen.\n\nEin wesentlicher Bestandteil des Seminars ist die Auseinandersetzung mit den Herausforderungen und Chancen, die digitale Technologien f\u00fcr die Arbeitswelt und das Bildungswesen mit sich bringen. Es werden Konzepte wie das lebenslange Lernen, Wissensmanagement und die Kompetenzentwicklung im Kontext von New Work und New Learning diskutiert.\n\nDas Seminar f\u00f6rdert die Entwicklung von Kompetenzen, die es den Teilnehmenden erm\u00f6glichen, als Change Agents zu agieren und interdisziplin\u00e4re Ans\u00e4tze in ihren eigenen beruflichen Kontexten umzusetzen. Dies beinhaltet die kritische Reflexion \u00fcber bestehende Strukturen und die F\u00e4higkeit, agile und flexible Lern- und Arbeitsprozesse zu gestalten und zu steuern.\n--- Literature (EN) ---\nCurrent literature references and sources of information are provided at the beginning of the module or directly from the course context. In addition, digital media are increasingly used as a source of knowledge.\n--- Literature (DE) ---\nAktuelle Literaturhinweise und Informationsquellen werden zu Beginn des Moduls oder unmittelbar aus dem Veranstaltungskontext herausgegeben. Zus\u00e4tzlich werden verst\u00e4rkt digitale Medien als Wissensquelle eingesetzt.", "metadata": {"moduleNumber": "MMI 05.31", "moduleName": "New Work & New Learning", "creditPoints": "5.0", "suggestedSemester": 2, "offeredInSeason": "summer_semester", "examType": "portfolio", "heldInLanguage": "de", "reviserName": "Prof. Dr. rer. nat. Michael Marmann", "reviserEmail": "marmann@hs-duesseldorf.de", "studyProgramId": 11, "source_type": "json"}}
{"id": "MMI05.33", "text": "Title: 360deg Video\nModule Number: MMI 05.33\nCredits: 5.0 CP\nSemester: None\nOffered In: to_be_announced\nLanguage: de\nExam Type: project\nInstructor: Prof. Dr. rer. nat. Christian Geiger (geiger@hs-duesseldorf.de)\n--- Goals (EN) ---\nThe students have gained an overview of relevant technologies for immersive media productions. At the same time, they have experienced changed procedures in digital storytelling and media production as a holistic process. They have learned the essential steps in the process from conception to playout of immersive contents and applied the acquired knowledge to practical immersive media production. The students have also taken a closer look at relevant effects of this new media form on users and society.\n--- Goals (DE) ---\nDie Studierenden erhalten einen \u00dcberblick relevanter Technologien f\u00fcr die immersive Medienproduktion und betrachten gleichzeitig die ge\u00e4nderten Vorgehensweisen im Storytelling und der Medienproduktion als ganzheitlichen Prozess. Sie erlernen die wesentlichen Arbeitsschritte von der Konzeption bis zur Ausspielung immersiver Inhalte und wenden das erworbene Wissen praktisch in einer immersiven Medienproduktion an. Die Auswirkungen dieser neuen Vermittlungsform werden ebenfalls umfangreich betrachtet.\n--- Contents (EN) ---\nFundamentals of moving image production in the context of innovative technologiesHardware and software technologies for mixed reality storytellingNon-linear storytelling for mixed realityImmersive applications: theatre, performances, journalism, educationWorkflow of immersive media productionsReflection on immersive technologies and participatory approaches\n--- Contents (DE) ---\nDas Medium Video bzw. Bewegtbild wird in vielen Bereichen der Digitalisierung eingesetzt, insbesondere im Kontext Wissensvermittlung, Lehre und Ausbildung. Der Einsatz immersiver Technologien in der Medienproduktion erfordert neben der Beherrschung relevanter Technologien auch neue Ans\u00e4tze der Kameraf\u00fchrung und Aufbereitung der inhaltlichen Darstellung. Die Veranstaltung betrachtet daher sowohl technische, gestalterische, inhaltliche und prozessorientierte Ans\u00e4tze der Bewegtbildproduktion. Grundlagen Bewegtbildproduktion im Kontext innovativer Technologien Hardware / Softwaretechnologien f\u00fcr Mixed Reality Storytelling Nicht-lineares Storytelling f\u00fcr Mixed Reality Immersive Anwendungsgebiete: Theater, Performances, Journalismus, Ausbildung Workflow immersiver Medienproduktion Reflektion immersiver Technologien und partizipativer Ans\u00e4tze\n--- Literature (EN) ---\n--- Literature (DE) ---\nJ. Bucher. Storytelling for Virtual Reality: Methods and Principles for Crafting Immersive Narratives, Focal Press, 2017C. Tricart. Virtual Reality Filmmaking: Techniques & Best Practices for VR Filmmakers, Routledge, 2017J. Jerald. The VR Book: Human Centred Design of Virtual Reality, ACM Books, 2015M. Wohl. The 360\u00b0 Video Handbook: A step-by-step guide to creating video for virtual reality, WohlProductions, 2017K. Kulshreshth, J.J. LaViola Jr. Designing Immersive Video Games Using 3DUI Technologies, Springer, 2018", "metadata": {"moduleNumber": "MMI 05.33", "moduleName": "360deg Video", "creditPoints": "5.0", "suggestedSemester": null, "offeredInSeason": "to_be_announced", "examType": "project", "heldInLanguage": "de", "reviserName": "Prof. Dr. rer. nat. Christian Geiger", "reviserEmail": "geiger@hs-duesseldorf.de", "studyProgramId": 11, "source_type": "json"}}
{"id": "MMI05.35", "text": "Title: Data Science\nModule Number: MMI 05.35\nCredits: 5.0 CP\nSemester: 2\nOffered In: summer_semester\nLanguage: en_on_demand\nExam Type: portfolio\nInstructor: Prof. Dr. Florian Huber (florian.huber@hs-duesseldorf.de)\n--- Goals (EN) ---\nStudents can use basic data science methods to gain insights from complex data and communicate them. This includes getting to know typical data science workflows that are implemented in a practical way using Python. Central techniques for cleaning, analyzing, interpreting and visualizing data are discussed and applied. Another core aspect is the critical examination of data (or its origin) and interpretations based on it. Insights gained from data are presented and discussed using data visualization\n--- Goals (DE) ---\nDie Studierenden k\u00f6nnen mit Hilfe grundlegender Data Science Methoden aus komplexen Daten Erkenntnisse zu gewinnen und zu kommunizieren. Dies beinhaltet das Kennenlernen typischer Data Science Workflows die praxisnah mit Python umgesetzt werden. Dabei werden zentrale Techniken zum Aufreinigen, Analysieren, Interpretieren und Visualisieren von Daten besprochen und eingesetzt. Ein weiterer Kernaspekt ist die kritische Auseinandersetzung mit Daten (bzw. deren Ursprung) und darauf beruhenden Interpretationen. Aus Daten gewonnene Erkenntnisse werden \u00fcber Datenvisualisierungen dargestellt und diskutiert\n--- Contents (EN) ---\n- Use of Python in the field of data science (data import, data exploration, analysis, evaluation) \n- Dealing with common data types and formats. \n- Fundamentals of epistemology and scientific method (correlation, causality, logic, dealing with cognitive distortions)\n- Statistical and graphical analysis of data \n- Application of frequently used clustering algorithms (K-Means, DBSCAN)\n- Techniques for dimensionality reduction (PCA, t-SNE)\n- Fundamentals of network analysis, graph theory \n- Use of machine learning to analyze data as well as for prediction \n- Critical consideration of the possibilities and consequences / technology impact assessment\n--- Contents (DE) ---\n- Nutzung von Python im Bereich Data Science (Datenimport, Datenerkundung, Analyse, Auswertung)  \n- Umgang mit h\u00e4ufigen Datentypen und Formaten. \n- Grundlagen der Erkenntnistheorie und wissenschaftlichen Methode (Korrelation, Kausalit\u00e4t, Logik, Umgang mit kognitiven Verzerrungen)\n- Statistische und graphische Analyse der Daten  \n- Anwendung von h\u00e4ufig genutzten Clustering-Algorithmen (K-Means, DBSCAN)\n- Techniken zur Dimensionsreduktion (PCA, t-SNE)\n- Grundlagen der Netzwerkanalyse, Graphentheorie \n- Einsatz von Maschinellem Lernen zur Analyse von Daten sowie auch zur Vorhersage  \n- Kritische Betrachtung der M\u00f6glichkeiten und Konsequenzen / Technikfolgenabsch\u00e4tzung\n--- Literature (EN) ---\nFlorian Huber, \"Introduction to Data (for not-yet-scientists), https://florian-huber.github.io/data_science_course/\n--- Literature (DE) ---\nFlorian Huber, \"Introduction to Data (for not-yet-scientists), https://florian-huber.github.io/data_science_course/", "metadata": {"moduleNumber": "MMI 05.35", "moduleName": "Data Science", "creditPoints": "5.0", "suggestedSemester": 2, "offeredInSeason": "summer_semester", "examType": "portfolio", "heldInLanguage": "en_on_demand", "reviserName": "Prof. Dr. Florian Huber", "reviserEmail": "florian.huber@hs-duesseldorf.de", "studyProgramId": 11, "source_type": "json"}}
{"id": "MMI05.36", "text": "Title: Pencils and Polygons\nModule Number: MMI 05.36\nCredits: 5.0 CP\nSemester: 2\nOffered In: summer_semester\nLanguage: de\nExam Type: project\nInstructor: Prof. Dr.-Ing. Sina Mostafawy (sina.mostafawy@hs-duesseldorf.de)\n--- Goals (EN) ---\nThe students know the basics of drawing (picture composition, techniques, shading, perspective). They can transfer their knowledge from 2D to 3D modeling and rendering.\n--- Goals (DE) ---\nDie Studierenden erlernen die Grundlagen des Zeichnens. Sie k\u00f6nnen das Wissen aus dem 2D Zeichnen in die Erstellung von 3D Modelle \u00fcbertragen (insbesondere Beleuchtung). Sie wissen, in welcher Form der Begriff des Formens sowie Licht und Schatten die Arbeit in der 3D Welt pr\u00e4gen.\n--- Contents (EN) ---\n- Basics of drawing\n- Dynamic and linear lines\n- Hatching techniques\n- Light and shadow\n- Image composition, image division and -perspective\n- Storyboard drawings\n--- Contents (DE) ---\n- Grundlagen des Zeichnens\n- Dynamische und lineare Linie\n- Schraffur Techniken\n- Licht und Schatten\n- Bildkomposition, Bildeinteilung und -perspektive\n- Storyboard Zeichnungen\n--- Literature (EN) ---\n--- Literature (DE) ---\n- F. A. Cerver: Zeichnen f\u00fcr Einsteiger, Konemann Verlag Koln 2002G. Bammes: Studien zur Gestalt des Menschen, 3. Aufl. Urania Verlag 2001", "metadata": {"moduleNumber": "MMI 05.36", "moduleName": "Pencils and Polygons", "creditPoints": "5.0", "suggestedSemester": 2, "offeredInSeason": "summer_semester", "examType": "project", "heldInLanguage": "de", "reviserName": "Prof. Dr.-Ing. Sina Mostafawy", "reviserEmail": "sina.mostafawy@hs-duesseldorf.de", "studyProgramId": 11, "source_type": "json"}}
{"id": "MMI05.37", "text": "Title: Technology utilisation and technology appropriation\nModule Number: MMI 05.37\nCredits: 5.0 CP\nSemester: 1\nOffered In: to_be_announced\nLanguage: de\nExam Type: research_paper\nInstructor: None Martin Doll (martin.doll@hs-duesseldorf.de)\n--- Goals (EN) ---\nStudents have skills in the application of central concepts of media studies, media psychology and media sociology. They are familiar with the theoretical foundations of media usage research and can apply them to specific contexts of their studies and future professional activities. They can analyse the effects of different media and technology usage patterns in a theoretically sound manner and are able to understand their complex conditionality. They recognise the significance of heterogeneity and diversity in patterns of use and appropriation processes of new technologies, are aware of the importance of specific technical skills and have the skills to reflect on their own role, especially from the perspective of new developments in the context of data science and artificial intelligence. In addition to theoretical approaches, e.g. from the fields of media studies, sociology and psychology, students should be able to recognise various aspects of dealing with media and technology (e.g. aspects of activity and passivity, communitisation and isolation, addiction, emotionalisation and cognition) and be able to reflect on them contextually. They should be able to assess the relevance of specific media skills and reflect on their role as developers of digital technologies.\n--- Goals (DE) ---\nStudierende verf\u00fcgen \u00fcber Kompetenzen in der Anwendung zentraler Begriffe der Medienwissenschaft, der Medienpsychologie und der Mediensoziologie. Sie kennen theoretische Grundlagen der Mediennutzungsforschung und k\u00f6nnen sie auf konkrete Kontexte ihres Studiums und k\u00fcnftiger beruflicher T\u00e4tigkeit \u00fcbertragen. Sie k\u00f6nnen die Auswirkungen verschiedener Medien- und Techniknutzungsmuster theoretisch fundiert analysieren und sind in der Lage, deren komplexe Bedingtheit zu verstehen. Sie erkennen die Bedeutsamkeit von Heterogenit\u00e4t und Diversit\u00e4t in Nutzungsmustern und Aneignungsprozessen neuer Technologien, sind sich der Bedeutung spezifischer Technikkompetenzen bewusst und verf\u00fcgen \u00fcber F\u00e4higkeiten zur Reflexion der eigenen Rolle, insbesondere aus der Perspektive neuer Entwicklungen im Kontext von Data Science und k\u00fcnstlicher Intelligenz.Neben theoretischen Ans\u00e4tzen, z. B. aus dem Feld der Medienwissenschaft, der Soziologie und der Psychologie sollen Studierende in der Lage sein, verschiedene Aspekte des Umgangs mit Medien bzw. Technik (z. B. Aspekte von Aktivit\u00e4t- und Passivit\u00e4t, Vergemeinschaftung und Isolation, Sucht, Emotionalisierung und Kognition) zu erkennen und sie kontextuell reflektieren k\u00f6nnen. Sie sollen die Relevanz spezifischer Medienkompetenzen beurteilen und ihre Rolle als Entwickler*innen digitaler Technologien reflektieren k\u00f6nnen.\n--- Contents (EN) ---\nThe module focuses on the human use and appropriation of technology, its conditions and consequences, with a particular focus on accelerated digital change. Students should become familiar with patterns of technology use and appropriation, acquire skills for the theoretically sound analysis of media and technology use, develop awareness of problematic and pathological media use and recognise social functions, e.g. of internet use Central concepts of media science, media psychology and media sociology Central principles of media use research, in particular theoretical approaches from the functional (e.g. uses and gratifications approach), procedural and structural perspectives Societal and social framework conditions and accompanying processes (e.g. basics of media socialisation) of media and technology use and appropriation. Fundamentals of media socialisation) of media and technology use and appropriation Fundamentals of the mediatisation of everyday life and society, mediatisation of social relationships, media and generations, media and cultural change Mediatisation and heterogeneity / diversity, e.g. from the perspective of gender media studies and cultural media studies Models, techniques and practices of data processing Fundamentals of media psychology for analysing the prerequisites and consequences of media use, including the possibilities of shaping mediaTheoretical and practical fundamentals of acquiring, teaching and applying media skills.\n--- Contents (DE) ---\nDer Fokus des Moduls liegt auf der menschlichen Techniknutzung und Technikaneignung, ihren Bedingungen und Folgen unter besonderer Betrachtung eines beschleunigten digitalen Wandels. Studierende sollen Muster der Techniknutzung und -aneignung kennenlernen, Kompetenzen zur theoretisch fundierten Analyse von Medien- und Techniknutzung erwerben, Bewusstsein f\u00fcr problematischen und pathologischen Mediengebrauch entwickeln sowie soziale Funktionen, z. B. des Internetgebrauchs, erkennen.Zentraler Begriffe der Medienwissenschaft, der Medienpsychologie und Mediensoziologie Zentrale Grundlagen der Mediennutzungsforschung, insbesondere theoretische Ans\u00e4tze aus der funktionalen (z. B. Uses-and-Gratifications-Ansatz), prozessualen und strukturellen Perspektive Gesellschaftliche und soziale Rahmenbedingungen und Begleitprozesse (z. B. Grundlagen der Mediensozialisation) von Medien- bzw. Techniknutzung und -aneignung Grundlagen der Mediatisierung von Alltag und Gesellschaft, Mediatisierung sozialer Beziehungen, Medien und Generationen, Medien und kultureller Wandel Mediatisierung und Heterogenit\u00e4t / Diversit\u00e4t, z. B. aus Sicht der Gender Media Studies und Cultural Media Studies Modelle, Techniken und Praktiken der Verdatung Medienpsychologische Grundlagen zur Analyse der Voraussetzungen sowie der Folgen von Mediennutzung inkl. der M\u00f6glichkeiten der Gestaltung von MedienTheoretische und praktische Grundlagen des Erwerbs, der Vermittlung und Anwendung von Medienkompetenzen\n--- Literature (EN) ---\nBonfadelli, H. & Friemel, T.N. (2011). Medienwirkungsforschung. Konstanz, M\u00fcnchen: UVK; UTB\nKnoblauch, H. (2016). Die kommunikative Konstruktion der Wirklichkeit. Wiesbaden: Springer VS\nKrotz, F., Despotovic, C. & Kruse, M.-M. (Hrsg.) (2017). Mediatisierung als Metaprozess. Transformationen, Formen der Entwicklung und die Generierung von Neuem. Wiesbaden: Springer VS\nM\u00e4mecke, T., Passoth, J.-H. & Wehner, J. (Hrsg.) (2018). Bedeutende Daten. Modelle, Verfahren und Praxis der Vermessung und Verdatung im Netz. Wiesbaden: Springer VS\nSchweiger, W. (2007). Theorien der Mediennutzung. Eine Einf\u00fchrung. Wiesbaden: Springer VS\nPfadenhauer, M. & Grenz, T. (Hrsg.) (2017). De-Mediatisierung. Diskontinuit\u00e4ten, Non-Linearit\u00e4ten und Ambivalenzen im Mediatisierungsprozess. Wiesbaden: Springer VS\nTrepte, S. & Reinecke, K. (2013). Medienpsychologie. Stuttgart: KohlhammerWeitere Literatur wird bei Vorlesungsbeginn bekannt gegeben.\n--- Literature (DE) ---\nBonfadelli, H. & Friemel, T.N. (2011). Medienwirkungsforschung. Konstanz, M\u00fcnchen: UVK; UTB\nKnoblauch, H. (2016). Die kommunikative Konstruktion der Wirklichkeit. Wiesbaden: Springer VS\nKrotz, F., Despotovic, C. & Kruse, M.-M. (Hrsg.) (2017). Mediatisierung als Metaprozess. Transformationen, Formen der Entwicklung und die Generierung von Neuem. Wiesbaden: Springer VS\nM\u00e4mecke, T., Passoth, J.-H. & Wehner, J. (Hrsg.) (2018). Bedeutende Daten. Modelle, Verfahren und Praxis der Vermessung und Verdatung im Netz. Wiesbaden: Springer VS\nSchweiger, W. (2007). Theorien der Mediennutzung. Eine Einf\u00fchrung. Wiesbaden: Springer VS\nPfadenhauer, M. & Grenz, T. (Hrsg.) (2017). De-Mediatisierung. Diskontinuit\u00e4ten, Non-Linearit\u00e4ten und Ambivalenzen im Mediatisierungsprozess. Wiesbaden: Springer VS\nTrepte, S. & Reinecke, K. (2013). Medienpsychologie. Stuttgart: KohlhammerWeitere Literatur wird bei Vorlesungsbeginn bekannt gegeben.", "metadata": {"moduleNumber": "MMI 05.37", "moduleName": "Technology utilisation and technology appropriation", "creditPoints": "5.0", "suggestedSemester": 1, "offeredInSeason": "to_be_announced", "examType": "research_paper", "heldInLanguage": "de", "reviserName": "None Martin Doll", "reviserEmail": "martin.doll@hs-duesseldorf.de", "studyProgramId": 11, "source_type": "json"}}
{"id": "MMI05.38", "text": "Title: Product Owner Seminar\nModule Number: MMI 05.38\nCredits: 5.0 CP\nSemester: 2\nOffered In: summer_semester\nLanguage: de\nExam Type: project\nInstructor: Prof. Dr. Thomas Franz (thomas.franz@hs-duesseldorf.de)\n--- Goals (EN) ---\n--- Goals (DE) ---\nDie Studierenden kennen ausgew\u00e4hlte Konzepte, Methoden und Praktiken der agilen Software-Produkt-Entwicklung und k\u00f6nnen diese f\u00fcr Weiterentwicklung konkreter Softwareprodukte anwenden. Sie sind in der Lage, die Entwicklung von Software-Produkten wertorientiert zu planen und in Zusammenarbeit mit agilen Software-Entwicklungsteams zu steuern. Sie k\u00f6nnen Wert- und Verschwendung identifizieren und beschreiben, sowie Experimente f\u00fcr die Produktinnovation konzipieren und durchf\u00fchren.\n--- Contents (EN) ---\n--- Contents (DE) ---\nLehrinhalte sind Konzepte, Methoden und Praktiken der agilen Software-Produkt-Entwicklung, insbesondere die Rolle des Product Owners in der agilen Software-Produkt-Entwicklung, die Definition von Wert und Verschwendung, Innovation Accounting, Pivotierungsformen, Produkt-Experimente, agile Planung und Priorisierung.\n--- Literature (EN) ---\n--- Literature (DE) ---\nIn Abh\u00e4ngigkeit aktueller Entwicklungen: verschiedene wissenschaftliche Grundlagen-Artikel sowie (i.d.R. online verf\u00fcgbare Artikel und Blog-Posts aus der Praxis).\n- RIES, Eric, 2017. The lean startup: how todays entrepreneurs use continuous innovation to create radically successful businesses. Currency international edition, first international edition. New York: Currency. ISBN 9781524762407\n- PICHLER, Roman und Stefan ZUMBR\u00c4GEL, 2023. Strategisches Produktmanagement: Produktstrategien und Roadmaps f\u00fcr digitale Produkte und agile Teams. \u00dcbersetzung der 2. englischen Auflage von Stefan Zumbr\u00e4gel. Heidelberg: dpunkt.verlag. ISBN 9783988900807", "metadata": {"moduleNumber": "MMI 05.38", "moduleName": "Product Owner Seminar", "creditPoints": "5.0", "suggestedSemester": 2, "offeredInSeason": "summer_semester", "examType": "project", "heldInLanguage": "de", "reviserName": "Prof. Dr. Thomas Franz", "reviserEmail": "thomas.franz@hs-duesseldorf.de", "studyProgramId": 11, "source_type": "json"}}
{"id": "MMI05.39", "text": "Title: Entrepreneurship\nModule Number: MMI 05.39\nCredits: 5.0 CP\nSemester: 1\nOffered In: to_be_announced\nLanguage: de\nExam Type: portfolio\nInstructor: None Denise Heidenreich (denise.heidenreich@hs-duesseldorf.de)\n--- Goals (EN) ---\n--- Goals (DE) ---\nNach erfolgreicher Teilnahme an dem Modul sind die Studierenden in der Lage:\n- Entrepreneurship zu definieren \n- Grundungsideen im fachbereichsubergreifenden Zusammenspiel mit anderen Studierenden anhand erlernter Methoden zu entwickeln und fur eine Umsetzung weiter zu nutzen\n- Chancen und Risiken ihrer Gesch\u00e4ftsidee zu bewerten\n- die relevanten Schritte zur Gr\u00fcndung eines Startups/Unternehmens zu nennen, zu erkl\u00e4ren und auszu\u00fcben\n- ihre eigene Gr\u00fcndungsidee zielgerichtet zu kommunizieren und sich vor einem interdisziplin\u00e4ren Plenum zu positionieren\n- die Weiterentwicklungschancen fur ihre Idee zu erkennen und f\u00fcr die Praxis zu nutzen\n- ihr Wissen \u00fcber unternehmerisches Denken und Handeln in der Berufspraxis anzuwenden\n--- Contents (EN) ---\n--- Contents (DE) ---\nIn diesem Modul erhalten die Studierenden eine praxisorientierte Einfuhrung in das Thema Entrepreneurship und lernen grundlegende Kenntnisse des unternehmerischen Denkens und Handelns f\u00fcr eine Gr\u00fcndung und/oder ihre berufliche Entwicklung kennen. \n\nLerninhalte im Detail:\n\tEntrepreneurial Mindset und Gr\u00fcnder*innenpers\u00f6nlichkeit\n\tEntrepreneurship vs. Intrapreneurship\n\tEntwicklung Gesch\u00e4ftsmodelle\n\tWettbewerbsanalyse und Marktforschung \n\tMarketing- und Vertriebsstrategien \n\tSWOT-Analyse\n\tBusiness Model Canvas\n\tFinanzen und F\u00f6rderm\u00f6glichkeiten\n\tInterdisziplin\u00e4re Ideenwerkstatt: Wie entwickle ich eine tragf\u00e4hige Gr\u00fcndungsidee?\n\tDer Wert der Idee und Ideenkommunikation \n\tPitch Deck: Aufbau, Struktur, Ziele\n\nKriterien eines guten Pitches: Zielgruppe, Rhetorik, K\u00f6rpersprache\n\nArbeitsformen/Methodik\n\nDie Veranstaltung findet im 2-Wochen-Rhythmus statt, um in den einzelnen Einheiten die jeweiligen Bausteine theoretisch einzuf\u00fchren und im Anschluss direkt in der Praxis zu erproben. Die Studierenden werden nach einer generellen Einf\u00fchrung in Teams arbeiten, um gemeinsam eine reale oder fiktive Idee zu entwickeln und die Gr\u00fcndung durchzuspielen. \n\n- Die Vermittlung der Lehrinhalte erfolgt durch Impulsvortr\u00e4ge, Lehrgespr\u00e4che und Diskussionen im Rahmen der Lehrveranstaltung. Die einzelnen Aspekte der Lehrinhalte werden in moderierter und gezielt unterst\u00fctzter Gruppenarbeit erarbeitet. Kreativmethoden und Elemente des Design Thinking werden eingesetzt. Die erlernten Inhalte werden an der eigens entwickelten Idee angewandt. \n- Die Pr\u00e4sentation der eigenen, entwickelten Gesch\u00e4ftsidee erfolgt anhand eines Kurzpitches vor den Lehrenden und den Teilnehmer*innen. Aus den Ideenpitches werden die Ideen f\u00fcr den Praxisteil ausgew\u00e4hlt, an denen die Teilnehmer*innen dann in kleinen Teams weiterarbeiten und die finalen Ideen in einem Abschlussfinale pr\u00e4sentieren.\n\nWeiterer Bestandteil der Pr\u00fcfungsleistung ist zudem ein aussagekr\u00e4ftiger Kurzbericht f\u00fcr die Weiterentwicklung der Idee.\n--- Literature (EN) ---\n--- Literature (DE) ---", "metadata": {"moduleNumber": "MMI 05.39", "moduleName": "Entrepreneurship", "creditPoints": "5.0", "suggestedSemester": 1, "offeredInSeason": "to_be_announced", "examType": "portfolio", "heldInLanguage": "de", "reviserName": "None Denise Heidenreich", "reviserEmail": "denise.heidenreich@hs-duesseldorf.de", "studyProgramId": 11, "source_type": "json"}}
{"id": "MMI05.40", "text": "Title: Mixed Reality Art\nModule Number: MMI 05.40\nCredits: 5.0 CP\nSemester: 1\nOffered In: to_be_announced\nLanguage: de\nExam Type: project\nInstructor: Prof. Dr. rer. nat. Christian Geiger (geiger@hs-duesseldorf.de)\n--- Goals (EN) ---\nParticipants will be given an overview of current works on mixed reality art.\nBased on a discussion of the concept of art, they will learn the procedures for the conception, design, development, construction and operation of mixed reality art projects,\ndesign, development, construction and operation of mixed reality art projects. Conceptual, creative, technical and economic aspects are considered in equal measure. Through\nthe critical discussion of current and historically significant examples\nexamples, participants will be able to assess this art form from a technical and conceptual perspective and critically reflect on its use from different angles.The participants have practical experience in pre-visualization and final implementation of simple installation concepts on the basis of selected marketable or freely available tools.\n--- Goals (DE) ---\nDie Teilnehmer erhalten einen \u00dcberblick aktueller Arbeiten zu Mixed Reality Art.\nAusgehend von einer Diskussion des Kunstbegriffs lernen sie die Vorgehensweisen bei der Konzeption,\nGestaltung, Entwicklung, Aufbau und Betrieb von Mixed Reality Art Projekten. Dabei werden konzeptionelle, gestalterische, technische und wirtschaftliche Aspekte zu gleichen Teilen betrachtet. Durch\ndie kritische Diskussion aktueller bzw. historisch bedeutsamer\nBeispiele k\u00f6nnen die Teilnehmer diese Kunstform aus technisch-konzeptioneller Sicht beurteilen und den Einsatz aus verschiedenen Blickwinkeln kritisch\nreflektieren. Die Teilnehmer besitzen praktische Erfahrung in der\nPr\u00e4visualisierung und finalen Umsetzung einfacher Installationskonzepte auf Basis ausgew\u00e4hlter marktg\u00e4ngiger bzw. frei verf\u00fcgbarer Werkzeuge.\n--- Contents (EN) ---\nBasic concepts of mixed reality art (definition, artistic expression, XR technologies, experience)\n- Analysis of historically relevant examples and established artists\n- Critical reflection on selected examples\n- Selected technical aspects of digital and physical object and spatial design, (projection mapping,\n VR/AR, Generative AI)\n- Tools for mixed reality art\n- Workflow, planning and operation of extensive installations\n- Excursion and invited lectures by artists, curators and media experts\n- Seminar phase and project phase\n--- Contents (DE) ---\n- Grundlegende Begriffe Mixed Reality Art (Definition, k\u00fcnstlerischer Ausdruck,  XR-Technologien, Experience)\n- Analyse historisch relevanter Beispiele und etablierter K\u00fcnstler:innen\n- Kritische Reflektion ausgew\u00e4hlter Beispiele\n- Ausgew\u00e4hlte technische Aspekte des digitale und physischen Objekt- und Raumdesigns (Projection Mapping,\n VR/AR, Generative KI)\n- Werkzeuge f\u00fcr Mixed Reality Art\n- Workflow, Planung und Betrieb umfangreicher Installationen\n- Exkursion und eingeladene Vortr\u00e4ge von K\u00fcnstler:innen, Kurator:innen und Medienexperten\n- Seminarphase und Projektphase\n--- Literature (EN) ---\nVladimir Geroimenko: Augmented Reality Art: From an Emerging Technology to a Novel Creative Medium (3rd Ed), 2022\n--- Literature (DE) ---\nVladimir Geroimenko: Augmented Reality Art: From an Emerging Technology to a Novel Creative Medium (3rd Ed), 2022", "metadata": {"moduleNumber": "MMI 05.40", "moduleName": "Mixed Reality Art", "creditPoints": "5.0", "suggestedSemester": 1, "offeredInSeason": "to_be_announced", "examType": "project", "heldInLanguage": "de", "reviserName": "Prof. Dr. rer. nat. Christian Geiger", "reviserEmail": "geiger@hs-duesseldorf.de", "studyProgramId": 11, "source_type": "json"}}
{"id": "MMI05.41", "text": "Title: Metathematisches Storytelling\nModule Number: MMI 05.41\nCredits: 5.0 CP\nSemester: 1\nOffered In: winter_semester\nLanguage: de\nExam Type: portfolio\nInstructor: Prof. Gabriele Schwab-Trapp (gabi.schwab-trapp@hs-duesseldorf.de)\n--- Goals (EN) ---\nStudents acquire skills in the conceptual handling of free or applied topics and the ability to independently develop context-related content. The development and practical realisation of their own ideas is made possible with the help of design processes. Experience in interdisciplinary, creative and constructive collaboration is gained within the seminar and possible project groups as well as in dealing with various forms of presentation.\n--- Goals (DE) ---\nDie Studierenden erwerben F\u00e4higkeiten im konzeptionellen Umgang mit freien oder angewandten Themen und die Bef\u00e4higung zur selbstst\u00e4ndigen Erarbeitung von kontextbezogenen Inhalten. Mithilfe von Gestaltungsprozessen werden die Entwicklung und die praktische Umsetzung eigener Ideen erm\u00f6glicht. Erfahrungen in interdisziplin\u00e4rer, kreativer und konstruktiver Zusammenarbeit werden innerhalb der Seminar- und m\u00f6glicher Projektgruppen sowie im Umgang mit verschiedenen Pr\u00e4sentationsformen gesammelt.\n--- Contents (EN) ---\nFree or applied topics are dealt with, which are presented at the beginning of the semester. The joint deepening, development and unfolding of the topic takes place in seminar form. This also includes philosophical, knowledge-orientated and opinion-forming discussions. The aim is the independent development and realisation of context-related, visual concepts in various media. Various forms of presentation are practised according to the topics and results. Excursions may take place to support the topics, which will be announced at the beginning of the semester.\nThe module is regularly offered on an open, collaborative and interdisciplinary basis with students from other subject areas.\n\nSuitable advanced tasks are assigned for Master's students.\n--- Contents (DE) ---\nInhaltlich werden freie oder angewandte Themen behandelt, die zu Beginn des Semesters vorgestellt werden. Die gemeinsame Vertiefung, Entwicklung und Entfaltung des Themas findet in Seminarform statt. Dazu geh\u00f6rt auch die philosophische, erkenntnisorientierte und meinungsbildende Auseinandersetzung. Ziel ist die selbstst\u00e4ndige Entwicklung und Umsetzung von kontextbezogenen, visuellen Konzepten in unterschiedlichen Medien. Den Themen und Ergebnissen entsprechend werden verschiedene Pr\u00e4sentationsformen einge\u00fcbt. Themenunterst\u00fctzend k\u00f6nnen Exkursionen stattfinden, die zu Beginn des Semesters bekannt gegeben werden.\nDas Modul wird regelm\u00e4\u00dfig offen, kollaborativ und interdisziplin\u00e4r mit Studierenden aus anderen Fachbereichen angeboten.\n\nF\u00fcr Master-Studierende werden geeignete, fortgeschrittene Aufgaben vergeben.\n--- Literature (EN) ---\nMaterial and literature references are provided for the respective topic in the seminar. Information in the form of text extracts, literature, image examples and research suggestions are provided to support the respective learning, realisation and design steps.\n--- Literature (DE) ---\nMaterial- und Literaturangaben werden zu dem jeweiligen Thema im Seminar ausgegeben. Zur Unterst\u00fctzung der jeweiligen Lern-, Erkenntnis- und Gestaltungsschritte werden Hinweise in Form von Textausz\u00fcgen, Literatur, Bildbeispielen und Recherchevorschl\u00e4gen gegeben.", "metadata": {"moduleNumber": "MMI 05.41", "moduleName": "Metathematisches Storytelling", "creditPoints": "5.0", "suggestedSemester": 1, "offeredInSeason": "winter_semester", "examType": "portfolio", "heldInLanguage": "de", "reviserName": "Prof. Gabriele Schwab-Trapp", "reviserEmail": "gabi.schwab-trapp@hs-duesseldorf.de", "studyProgramId": 11, "source_type": "json"}}
{"id": "MMI05.42", "text": "Title: Discursive Design and Future Visions\nModule Number: MMI 05.42\nCredits: 5.0 CP\nSemester: 1\nOffered In: winter_semester\nLanguage: de\nExam Type: portfolio\nInstructor: Prof. Gabriele Schwab-Trapp (gabi.schwab-trapp@hs-duesseldorf.de)\n--- Goals (EN) ---\nStudents recognise the connection between design, technology, science and shaping the future. They are able to critically reflect on design concepts and their effects and can utilise speculative design strategies as a method for generating creative and sustainable ideas. They are able to apply and categorise the research potential of design.\n--- Goals (DE) ---\nDie Studierenden erkennen den Zusammenhang zwischen Design, Technik, Wissenschaft und Zukunftsgestaltung. Sie sind in der Lage Gestaltungskonzepte und deren Auswirkungen kritisch zu reflektieren und k\u00f6nnen den Einsatz spekulativer Designstrategien als Methode zur Erzeugung kreativer und nachhaltiger Ideen nutzen. Sie sind in der Lage das Forschungspotenzial durch Gestaltung anzuwenden und einzuordnen.\n--- Contents (EN) ---\nStudents are encouraged to engage analytically, theoretically and practically with concepts such as \"Design Fiction\", \"Critical Design\" and \"Speculative Design\". The focus is on the critical examination of current developments in science, technology, design and communication and their potential impact on society.\nOn this basis, possible future scenarios are to be developed and told in free narratives. Through the creative fusion of scientific knowledge and narrative elements, combined with practical applications, alternative realities can be explored and discussions stimulated that promote critical thinking. This integrative approach allows research through design to be trialled, using design as a tool to explore and deepen understanding of current issues and potential future scenarios. The aim is to identify the opportunities and challenges that designers and product developers face when dealing with increasingly complex and urgent social, political and environmental issues.\nThe theoretical discussion includes design and media history, design and media theory, as well as categorisation in the context of social developments.\n\nTranslated with DeepL.com (free version)\n--- Contents (DE) ---\nDie Studierenden werden dazu angeleitet, sich analytisch, theoretisch und praktisch mit Konzepten wie \"Design Fiction\", \"Critical Design\" und \"Speculative Design\" auseinanderzusetzen. Der Schwerpunkt liegt auf der kritischen Untersuchung aktueller Entwicklungen in Wissenschaft, Technik, Design und Kommunikation sowie deren potenziellen Auswirkungen auf die Gesellschaft. \n\nAuf dieser Basis sollen m\u00f6gliche Zukunftsszenarien entwickelt werden, die in freien Narrativen erz\u00e4hlt werden. Durch die kreative Verschmelzung von wissenschaftlichem Wissen und erz\u00e4hlerischen Elementen, verkn\u00fcpft mit praktischen Anwendungen, k\u00f6nnen alternative Realit\u00e4ten erforscht und Diskussionen angeregt werden, die kritische Denkweisen f\u00f6rdern. Dieser integrative Ansatz erm\u00f6glicht es, Forschung durch Gestaltung zu erproben, bei dem Design als Instrument zur Erforschung und Vertiefung des Verst\u00e4ndnisses aktueller Themen und potenzieller Zukunftsszenarien dient. Dabei sollen M\u00f6glichkeiten und Herausforderungen aufzeigt werden, denen sich GestalterInnen und ProduktentwicklerInnen stellen m\u00fcssen, wenn sie sich mit immer komplexeren und dringlicheren sozialen, politischen und \u00f6kologischen Themen auseinandersetzen.\n\nZu der theoretischen Auseinandersetzung geh\u00f6ren Design- und Mediengeschichte, Design- und Medientheorie, sowie die Einordnung in gesellschaftliche Entwicklungen.\n--- Literature (EN) ---\nMaterial and literature references are provided for the respective topic in the seminar. Information in the form of text extracts, literature, image examples and research suggestions are provided to support the respective learning, realisation and design steps.\n--- Literature (DE) ---\nMaterial- und Literaturangaben werden zu dem jeweiligen Thema im Seminar ausgegeben. Zur Unterst\u00fctzung der jeweiligen Lern-, Erkenntnis- und Gestaltungsschritte werden Hinweise in Form von Textausz\u00fcgen, Literatur, Bildbeispielen und Recherchevorschl\u00e4gen gegeben.", "metadata": {"moduleNumber": "MMI 05.42", "moduleName": "Discursive Design and Future Visions", "creditPoints": "5.0", "suggestedSemester": 1, "offeredInSeason": "winter_semester", "examType": "portfolio", "heldInLanguage": "de", "reviserName": "Prof. Gabriele Schwab-Trapp", "reviserEmail": "gabi.schwab-trapp@hs-duesseldorf.de", "studyProgramId": 11, "source_type": "json"}}
{"id": "MMI07", "text": "Title: Masterproject 3\nModule Number: MMI 07\nCredits: 10.0 CP\nSemester: 3\nOffered In: winter_semester\nLanguage: en_on_demand\nExam Type: project\nInstructor: Prof. Dr. Thomas Franz (thomas.franz@hs-duesseldorf.de)\n--- Goals (EN) ---\nThe students are able to work successfully on a complex application-oriented project in the field ofmedia informatics or, alternatively,media engineering, event technology or media design with a focus on informatics.They can achieve results in the different project phases independently, analyse them critically and present the results.\n--- Goals (DE) ---\nTeilnehmer sind in der Lage, eine komplexe anwendungsorientierte Aufgabenstellung aus dem Bereiche Medieninformatik bzw. Medientechnik / Veranstaltungstechnik / Mediengestaltung mit signifikanten Informatikanteilen erfolgreich zu bearbeiten und in den verschiedenen Projektphasen eigenst\u00e4ndig Ergebnisse erzielen, diese kritisch zu analysieren und Resultate zu pr\u00e4sentieren.\n--- Contents (EN) ---\nThe students work alone or in teams on individual research questions within the area of media informatics or related disciplines with a focus on informatics. They discuss their progress regularly with the supervisor and present first results. The main focus is the research-oriented implementation of the concepts developed based on scientific methodology.\n--- Contents (DE) ---\nStudierende arbeiten alleine oder im Team an einer eigenst\u00e4ndigen wissenschaftlichen Fragestellung der Medieninformatik bzw. verwandter Medienbereiche mit Informatikanteil. Der Fortschritt wird regelm\u00e4\u00dfig mit dem Betreuer besprochen und (Teil-) Ergebnisse entsprechend pr\u00e4sentiert. Der Schwerpunkt liegt auf der forschungsorientierten Umsetzung der entwickelten Konzepte auf Basis wissenschaftlicher Methoden.\n--- Literature (EN) ---\n--- Literature (DE) ---\nJe nach Dozent und Projektthema verschieden", "metadata": {"moduleNumber": "MMI 07", "moduleName": "Masterproject 3", "creditPoints": "10.0", "suggestedSemester": 3, "offeredInSeason": "winter_semester", "examType": "project", "heldInLanguage": "en_on_demand", "reviserName": "Prof. Dr. Thomas Franz", "reviserEmail": "thomas.franz@hs-duesseldorf.de", "studyProgramId": 11, "source_type": "json"}}
{"id": "MMI08", "text": "Title: Individual Project\nModule Number: MMI 08\nCredits: 10.0 CP\nSemester: 3\nOffered In: winter_semester\nLanguage: en_on_demand\nExam Type: project\nInstructor: Prof. Dr. Thomas Franz (thomas.franz@hs-duesseldorf.de)\n--- Goals (EN) ---\nThe students are able to work successfully on a complex application-oriented project in the field ofmedia informatics or, alternatively,media engineering, event technology or media design with a focus on informatics.They can achieve results in the different project phases independently, analyse them critically and present the results.\n--- Goals (DE) ---\nTeilnehmer sind in der Lage, eine komplexe anwendungsorientierte Aufgabenstellung aus dem Bereiche Medieninformatik bzw. Medientechnik / Veranstaltungstechnik / Mediengestaltung mit signifikanten Informatikanteilen erfolgreich zu bearbeiten und in den verschiedenen Projektphasen eigenst\u00e4ndig Ergebnisse erzielen, diese kritisch zu analysieren und Resultate zu pr\u00e4sentieren.\n--- Contents (EN) ---\nThe students work alone or in teams on individual research questions within the area of media informatics or related disciplines with a focus on informatics. They discuss their progress regularly with the supervisor and present first results. The focus is on research-orientation or practical implementation of the developed concepts in media production based on scientific methods.\n--- Contents (DE) ---\nStudierende arbeiten alleine oder im Team an einer eigenst\u00e4ndigen wissenschaftlichen Fragestellung der Medieninformatik bzw. verwandter Medienbereiche mit Informatikanteil. Der Fortschritt wird regelm\u00e4\u00dfig mit dem Betreuer besprochen und (Teil-) Ergebnisse entsprechend pr\u00e4sentiert. Der Schwerpunkt liegt auf der forschungsorientierten oder medienpraktischen Umsetzung der entwickelten Konzepte auf Basis wissenschaftlicher Methoden.\n--- Literature (EN) ---\n--- Literature (DE) ---\nJe nach Dozent und Projektthema verschieden", "metadata": {"moduleNumber": "MMI 08", "moduleName": "Individual Project", "creditPoints": "10.0", "suggestedSemester": 3, "offeredInSeason": "winter_semester", "examType": "project", "heldInLanguage": "en_on_demand", "reviserName": "Prof. Dr. Thomas Franz", "reviserEmail": "thomas.franz@hs-duesseldorf.de", "studyProgramId": 11, "source_type": "json"}}
{"id": "MMI09", "text": "Title: Master Thesis and Colloquium\nModule Number: MMI 09\nCredits: 30.0 CP\nSemester: None\nOffered In: every_semester\nLanguage: de\nExam Type: master_thesis_and_colloquium\nInstructor: Prof. Dr. Thomas Franz (thomas.franz@hs-duesseldorf.de)\n--- Goals (EN) ---\nIndependent work on a scientific question from the field of media informatics. The students have applied the acquired competences in scientific methodology to complex research questions within a challenging topic in a targeted manner.\n--- Goals (DE) ---\nEigenst\u00e4ndige Bearbeitung einer wissenschaftlichen Fragestellung aus dem Bereich der Medieninformatik. Dabei sollen die erlernten Kompetenzen einer methodischen wissenschaftlichen Vorgehensweise bei komplexen Fragestellungen zielgerichtet in einer anspruchsvollen Thematik eingesetzt werden.\n--- Contents (EN) ---\nThe students work on current topics from the field of media informatics \u2013 ideally developing ideas from compulsory elective courses or projects within the master\u2019s programme Media Informatics further into advanced research questions. They discuss relevant scientific projects and relations to their own work in the context of an accompanying seminar.\n--- Contents (DE) ---\nBearbeitet werden aktuelle Themen aus dem Bereich Medieninformatik, idealerweise als weiterf\u00fchrende Fragestellung aus den Wahlpflichtveranstaltungen des Masters Medieninformatik oder aus den Projekten. Parallel werden im Rahmen eines Seminars relevanten wissenschaftliche Projekte diskutiert und ihr Bezug zur Arbeit der Studierenden aufgezeigt.\n--- Literature (EN) ---\nDepends on lecturer and topic\n--- Literature (DE) ---\nJe nach Dozent und Thema verschieden", "metadata": {"moduleNumber": "MMI 09", "moduleName": "Master Thesis and Colloquium", "creditPoints": "30.0", "suggestedSemester": null, "offeredInSeason": "every_semester", "examType": "master_thesis_and_colloquium", "heldInLanguage": "de", "reviserName": "Prof. Dr. Thomas Franz", "reviserEmail": "thomas.franz@hs-duesseldorf.de", "studyProgramId": 11, "source_type": "json"}}
{"id": "MMI11", "text": "Title: Selection Module 1\nModule Number: MMI 11\nCredits: 5.0 CP\nSemester: 1\nOffered In: every_semester\nLanguage: de\nExam Type: see_elective\nInstructor: Prof. Dr. Thomas Franz (thomas.franz@hs-duesseldorf.de)\n--- Goals (EN) ---\nsee MMI 05.01 to MMI 05.33\n--- Goals (DE) ---\nsiehe MMI 05.01 bis MMI 05.33\n--- Contents (EN) ---\nsee MMI 05.01 to MMI 05.33\n--- Contents (DE) ---\nsiehe MMI 05.01 bis MMI 05.33\n--- Literature (EN) ---\n--- Literature (DE) ---\nsiehe MMI 05.01 bis MMI 05.33", "metadata": {"moduleNumber": "MMI 11", "moduleName": "Selection Module 1", "creditPoints": "5.0", "suggestedSemester": 1, "offeredInSeason": "every_semester", "examType": "see_elective", "heldInLanguage": "de", "reviserName": "Prof. Dr. Thomas Franz", "reviserEmail": "thomas.franz@hs-duesseldorf.de", "studyProgramId": 11, "source_type": "json"}}
{"id": "MMI12", "text": "Title: Selection Module 2\nModule Number: MMI 12\nCredits: 5.0 CP\nSemester: 1\nOffered In: every_semester\nLanguage: de\nExam Type: see_elective\nInstructor: Prof. Dr. Thomas Franz (thomas.franz@hs-duesseldorf.de)\n--- Goals (EN) ---\nsee MMI 05.01 to MMI 05.33\n--- Goals (DE) ---\nsiehe MMI 05.01 bis MMI 05.33\n--- Contents (EN) ---\nsee MMI 05.01 to MMI 05.33\n--- Contents (DE) ---\nsiehe MMI 05.01 bis MMI 05.33\n--- Literature (EN) ---\n--- Literature (DE) ---\nsiehe MMI 05.01 bis MMI 05.33", "metadata": {"moduleNumber": "MMI 12", "moduleName": "Selection Module 2", "creditPoints": "5.0", "suggestedSemester": 1, "offeredInSeason": "every_semester", "examType": "see_elective", "heldInLanguage": "de", "reviserName": "Prof. Dr. Thomas Franz", "reviserEmail": "thomas.franz@hs-duesseldorf.de", "studyProgramId": 11, "source_type": "json"}}
{"id": "MMI13", "text": "Title: Selection Module 3\nModule Number: MMI 13\nCredits: 5.0 CP\nSemester: 1\nOffered In: every_semester\nLanguage: de\nExam Type: see_elective\nInstructor: Prof. Dr. Thomas Franz (thomas.franz@hs-duesseldorf.de)\n--- Goals (EN) ---\nsee MMI 05.01 to MMI 05.33\n--- Goals (DE) ---\nsiehe MMI 05.01 bis MMI 05.33\n--- Contents (EN) ---\nsee MMI 05.01 to MMI 05.33\n--- Contents (DE) ---\nsiehe MMI 05.01 bis MMI 05.33\n--- Literature (EN) ---\n--- Literature (DE) ---\nsiehe MMI 05.01 bis MMI 05.33", "metadata": {"moduleNumber": "MMI 13", "moduleName": "Selection Module 3", "creditPoints": "5.0", "suggestedSemester": 1, "offeredInSeason": "every_semester", "examType": "see_elective", "heldInLanguage": "de", "reviserName": "Prof. Dr. Thomas Franz", "reviserEmail": "thomas.franz@hs-duesseldorf.de", "studyProgramId": 11, "source_type": "json"}}
{"id": "MMI14", "text": "Title: Selection Module 4\nModule Number: MMI 14\nCredits: 5.0 CP\nSemester: 2\nOffered In: every_semester\nLanguage: de\nExam Type: see_elective\nInstructor: Prof. Dr. Thomas Franz (thomas.franz@hs-duesseldorf.de)\n--- Goals (EN) ---\nsee MMI 05.01 to MMI 05.33\n--- Goals (DE) ---\nsiehe MMI 05.01 bis MMI 05.33\n--- Contents (EN) ---\nsee MMI 05.01 to MMI 05.33\n--- Contents (DE) ---\nsiehe MMI 05.01 bis MMI 05.33\n--- Literature (EN) ---\n--- Literature (DE) ---\nsiehe MMI 05.01 bis MMI 05.33", "metadata": {"moduleNumber": "MMI 14", "moduleName": "Selection Module 4", "creditPoints": "5.0", "suggestedSemester": 2, "offeredInSeason": "every_semester", "examType": "see_elective", "heldInLanguage": "de", "reviserName": "Prof. Dr. Thomas Franz", "reviserEmail": "thomas.franz@hs-duesseldorf.de", "studyProgramId": 11, "source_type": "json"}}
{"id": "MMI15", "text": "Title: Selection Module 4\nModule Number: MMI 15\nCredits: 5.0 CP\nSemester: 2\nOffered In: every_semester\nLanguage: de\nExam Type: see_elective\nInstructor: Prof. Dr. Thomas Franz (thomas.franz@hs-duesseldorf.de)\n--- Goals (EN) ---\nsee MMI 05.01 to MMI 05.33\n--- Goals (DE) ---\nsiehe MMI 05.01 bis MMI 05.33\n--- Contents (EN) ---\nsee MMI 05.01 to MMI 05.33\n--- Contents (DE) ---\nsiehe MMI 05.01 bis MMI 05.33\n--- Literature (EN) ---\n--- Literature (DE) ---\nsiehe MMI 05.01 bis MMI 05.33", "metadata": {"moduleNumber": "MMI 15", "moduleName": "Selection Module 4", "creditPoints": "5.0", "suggestedSemester": 2, "offeredInSeason": "every_semester", "examType": "see_elective", "heldInLanguage": "de", "reviserName": "Prof. Dr. Thomas Franz", "reviserEmail": "thomas.franz@hs-duesseldorf.de", "studyProgramId": 11, "source_type": "json"}}
{"id": "MMI16", "text": "Title: Selection Module 6\nModule Number: MMI 16\nCredits: 5.0 CP\nSemester: 2\nOffered In: every_semester\nLanguage: de\nExam Type: see_elective\nInstructor: Prof. Dr. Thomas Franz (thomas.franz@hs-duesseldorf.de)\n--- Goals (EN) ---\nsee MMI 05.01 to MMI 05.33\n--- Goals (DE) ---\nsiehe MMI 05.01 bis MMI 05.33\n--- Contents (EN) ---\nsee MMI 05.01 to MMI 05.33\n--- Contents (DE) ---\nsiehe MMI 05.01 bis MMI 05.33\n--- Literature (EN) ---\n--- Literature (DE) ---\nsiehe MMI 05.01 bis MMI 05.33", "metadata": {"moduleNumber": "MMI 16", "moduleName": "Selection Module 6", "creditPoints": "5.0", "suggestedSemester": 2, "offeredInSeason": "every_semester", "examType": "see_elective", "heldInLanguage": "de", "reviserName": "Prof. Dr. Thomas Franz", "reviserEmail": "thomas.franz@hs-duesseldorf.de", "studyProgramId": 11, "source_type": "json"}}
{"id": "MMI17", "text": "Title: Selection Module 7\nModule Number: MMI 17\nCredits: 5.0 CP\nSemester: 3\nOffered In: every_semester\nLanguage: de\nExam Type: see_elective\nInstructor: Prof. Dr. Thomas Franz (thomas.franz@hs-duesseldorf.de)\n--- Goals (EN) ---\nsee MMI 05.01 to MMI 05.33\n--- Goals (DE) ---\nsiehe MMI 05.01 bis MMI 05.33\n--- Contents (EN) ---\nsee MMI 05.01 to MMI 05.33\n--- Contents (DE) ---\nsiehe MMI 05.01 bis MMI 05.33\n--- Literature (EN) ---\n--- Literature (DE) ---\nsiehe MMI 05.01 bis MMI 05.33", "metadata": {"moduleNumber": "MMI 17", "moduleName": "Selection Module 7", "creditPoints": "5.0", "suggestedSemester": 3, "offeredInSeason": "every_semester", "examType": "see_elective", "heldInLanguage": "de", "reviserName": "Prof. Dr. Thomas Franz", "reviserEmail": "thomas.franz@hs-duesseldorf.de", "studyProgramId": 11, "source_type": "json"}}
{"id": "MMI18", "text": "Title: Selection Module 8\nModule Number: MMI 18\nCredits: 5.0 CP\nSemester: 3\nOffered In: every_semester\nLanguage: de\nExam Type: see_elective\nInstructor: Prof. Dr. Thomas Franz (thomas.franz@hs-duesseldorf.de)\n--- Goals (EN) ---\nsee MMI 05.01 to MMI 05.33\n--- Goals (DE) ---\nsiehe MMI 05.01 bis MMI 05.33\n--- Contents (EN) ---\nsee MMI 05.01 to MMI 05.33\n--- Contents (DE) ---\nsiehe MMI 05.01 bis MMI 05.33\n--- Literature (EN) ---\n--- Literature (DE) ---\nsiehe MMI 05.01 bis MMI 05.33", "metadata": {"moduleNumber": "MMI 18", "moduleName": "Selection Module 8", "creditPoints": "5.0", "suggestedSemester": 3, "offeredInSeason": "every_semester", "examType": "see_elective", "heldInLanguage": "de", "reviserName": "Prof. Dr. Thomas Franz", "reviserEmail": "thomas.franz@hs-duesseldorf.de", "studyProgramId": 11, "source_type": "json"}}
